Workbook
Name _Dates_Conc: [1]Dealers!$BF$37:$KA$63
Name _Dates_Conc: #REF!
Name _scen: '[1]Scen & Sens'!$E$26
Name _scen: #REF!
Name _scen1: '[1]Scen & Sens'!$E$27
Name _scen1: #REF!
Name _scen2: '[1]Scen & Sens'!$E$28
Name _scen2: #REF!
Name _SCenarios: '[1]Scen & Sens'!$J$26:$O$26
Name _SCenarios: #REF!
Name _Sens1: '[1]Scen & Sens'!$F$9
Name _Sens1: #REF!
Name _Sens2: '[1]Scen & Sens'!$F$10
Name _Sens2: #REF!
Name _sensRes1: '[1]Scen & Sens'!$E$15
Name _sensRes1: #REF!
Name _sensRes2: '[1]Scen & Sens'!$E$16
Name _sensRes2: #REF!
Name _sensRes3: '[1]Scen & Sens'!$E$17
Name _sensRes3: #REF!
Name _sensRes4: '[1]Scen & Sens'!$E$18
Name _sensRes4: #REF!
Name _sensRes5: '[1]Scen & Sens'!$E$19
Name _sensRes5: #REF!
Name _sensRes6: '[1]Scen & Sens'!$E$20
Name _sensRes6: #REF!
Name _sensRes7: '[1]Scen & Sens'!$E$21
Name _sensRes7: #REF!
Name Compco1: {"Page1",#N/A,FALSE,"CompCo";"Page2",#N/A,FALSE,"CompCo"}
Name Compco2: {"Page1",#N/A,FALSE,"CompCo";"Page2",#N/A,FALSE,"CompCo"}
Name DateRange: [1]Volkswagen!$BF$6:$DY$6
Name DateRange: #REF!
Name DateRangePr: OFFSET([2]!DateRangePriceMain,5,0,COUNTA([2]!DateRangePriceMain)-COUNTA(#REF!),1)
Name DateRangePrice: OFFSET([3]!DateRangePriceMain,5,0,COUNTA([3]!DateRangePriceMain)-COUNTA(#REF!),1)
Name DateRangePrice1: OFFSET([3]!DateRangePriceMain,5,0,COUNTA([3]!DateRangePriceMain)-COUNTA(#REF!),1)
Name DateRangePrice2: OFFSET([2]!DateRangePriceMain,5,0,COUNTA([2]!DateRangePriceMain)-COUNTA(#REF!),1)
Name ERT: {"execsum",#N/A,FALSE,"ExecSum";"finstatement",#N/A,FALSE,"Fin_St"}
Name hn.Delete015: '[4]CREDIT STATS'!$B$9:$K$14,'[4]CREDIT STATS'!$O$11:$X$18,'[4]CREDIT STATS'!$B$28:$K$37,'[4]CREDIT STATS'!$O$28:$X$32,'[4]CREDIT STATS'!$O$46:$X$46
Name kjjkghkhj: {"finana",#N/A,FALSE,"Fin"}
Name lkhkhj: {"sub1",#N/A,FALSE,"Subs";"pac1",#N/A,FALSE,"Packages";"rev1",#N/A,FALSE,"2. Revenues"}
Name Monetary_Unit: [1]Parameters!$B$15
Name Monetary_Unit: #REF!
Name Months: [1]Parameters!$E$9:$E$20
Name Months: #REF!
Name PriceRange: OFFSET([3]!PriceRangeMain,5,0,COUNTA([3]!PriceRangeMain)-COUNTA(#REF!),1)
Name PriceRange2: OFFSET([2]!PriceRangeMain,5,0,COUNTA([2]!PriceRangeMain)-COUNTA(#REF!),1)
Name Rng_Dealers_Names: [1]!Tbl_Dealers[Dealer Name]
Name Rng_Dealers_Names: #REF!
Name Rng_Dlr_Dates: [1]!Tbl_V_Dlr_Dates[Date]
Name Rng_Dlr_Dates: #REF!
Name test: {"execsum",#N/A,FALSE,"ExecSum";"finstatement",#N/A,FALSE,"Fin_St"}
Name test21: OFFSET([2]!DateRangePriceMain,5,0,COUNTA([2]!DateRangePriceMain)-COUNTA(#REF!),1)
Name Ticker: #REF!
Name Ticker: #REF!
Name Titre: [1]Front!$A$9
Name Titre: #REF!
Name value: OFFSET([3]!DateRangePriceMain,5,0,COUNTA([3]!DateRangePriceMain)-COUNTA(#REF!),1)
Name value2: OFFSET([2]!DateRangePriceMain,5,0,COUNTA([2]!DateRangePriceMain)-COUNTA(#REF!),1)
Name wrn.amendement.: {#N/A,#N/A,FALSE,"amendement"}
Name wrn.amendement..: {#N/A,#N/A,FALSE,"amendement"}

Sheet Parametres
A1: Compagnie | B1: BMW Sherbrooke
G2: 1-Mémo | M2: Mois | N2: YTD
A3: Mois Courant | B3: Avril | C3: =+VLOOKUP(B3,$K$3:$L$14,2,0) -> 4 | G3: 10-Compte compteur | K3: Janvier | L3: 1 | M3: =+IF($K3=$B$3,"X","") | N3: =+IF(K3=B3,"X",IF(L3<=$C$3,"X","")) -> X
A4: Année | B4: 2024 | K4: Février | L4: 2 | M4: =+IF($K4=$B$3,"X","") | N4: =+IF(K4=B4,"X",IF(L4<=$C$3,"X","")) -> X
K5: Mars | L5: 3 | M5: =+IF($K5=$B$3,"X","") | N5: =+IF(K5=B5,"X",IF(L5<=$C$3,"X","")) -> X
K6: Avril | L6: 4 | M6: =+IF($K6=$B$3,"X","") -> X | N6: =+IF(K6=B6,"X",IF(L6<=$C$3,"X","")) -> X
K7: Mai | L7: 5 | M7: =+IF($K7=$B$3,"X","") | N7: =+IF(K7=B7,"X",IF(L7<=$C$3,"X",""))
K8: Juin | L8: 6 | M8: =+IF($K8=$B$3,"X","") | N8: =+IF(K8=B8,"X",IF(L8<=$C$3,"X",""))
A9: Sélectionner le mois en B3 | K9: Juillet | L9: 7 | M9: =+IF($K9=$B$3,"X","") | N9: =+IF(K9=B9,"X",IF(L9<=$C$3,"X",""))
A10: Coller les balances de vérification respectives en cellule A1 dans les onglets BV_Data_An_Cour et BV_Data_An_Prec | K10: Août | L10: 8 | M10: =+IF($K10=$B$3,"X","") | N10: =+IF(K10=B10,"X",IF(L10<=$C$3,"X",""))
A11: Vérifier s'il y a des #N/A dans les colonnes T à X des onlgets de BV | K11: Septembre | L11: 9 | M11: =+IF($K11=$B$3,"X","") | N11: =+IF(K11=B11,"X",IF(L11<=$C$3,"X",""))
A12: Vérifier les chiffres avec l'état financier et les réalisés an passé pour les résultat net mois et aad | K12: Octobre | L12: 10 | M12: =+IF($K12=$B$3,"X","") | N12: =+IF(K12=B12,"X",IF(L12<=$C$3,"X",""))
K13: Novembre | L13: 11 | M13: =+IF($K13=$B$3,"X","") | N13: =+IF(K13=B13,"X",IF(L13<=$C$3,"X",""))
K14: Décembre | L14: 12 | M14: =+IF($K14=$B$3,"X","") | N14: =+IF(K14=B14,"X",IF(L14<=$C$3,"X",""))

Sheet Bilan
A1: BILAN
A2: =+Parametres!B1 -> BMW Sherbrooke
A3: =CONCATENATE("",,Parametres!B3," ",Parametres!B4) -> Avril 2024
A5: Encaisse | B5: =SUMIFS(BV_Data_An_Cour!$P:$P,BV_Data_An_Cour!$U:$U,$A$1,BV_Data_An_Cour!$V:$V,$A5) -> 1759141.7 | D5: Marge de crédit | E5: =-SUMIFS(BV_Data_An_Cour!$P:$P,BV_Data_An_Cour!$U:$U,$A$1,BV_Data_An_Cour!$V:$V,$D5) -> 0
A6: Total Trésorerie et équivalent de Trésorerie | B6: =SUM(B5) -> 1759141.7
D7: Portion Court Terme de la Dette Long Terme | E7: =-SUMIFS(BV_Data_An_Cour!$P:$P,BV_Data_An_Cour!$U:$U,$A$1,BV_Data_An_Cour!$V:$V,$D7) -> 0
A8: Recevables Contrats en Transit | B8: =SUMIFS(BV_Data_An_Cour!$P:$P,BV_Data_An_Cour!$U:$U,$A$1,BV_Data_An_Cour!$V:$V,$A8) -> 639296.47
A9: Recevables Véhicules | B9: =SUMIFS(BV_Data_An_Cour!$P:$P,BV_Data_An_Cour!$U:$U,$A$1,BV_Data_An_Cour!$V:$V,$A9) -> 241757.65 | D9: Avances à payer | E9: =-SUMIFS(BV_Data_An_Cour!$P:$P,BV_Data_An_Cour!$U:$U,$A$1,BV_Data_An_Cour!$V:$V,$D9) -> 0
A10: Recevables Manufacturier | B10: =SUMIFS(BV_Data_An_Cour!$P:$P,BV_Data_An_Cour!$U:$U,$A$1,BV_Data_An_Cour!$V:$V,$A10) -> 168068.73 | D10: Comptes à Payer Fournisseurs | E10: =-SUMIFS(BV_Data_An_Cour!$P:$P,BV_Data_An_Cour!$U:$U,$A$1,BV_Data_An_Cour!$V:$V,$D10) -> 138190.68
A11: Recevables Pièces et Service | B11: =SUMIFS(BV_Data_An_Cour!$P:$P,BV_Data_An_Cour!$U:$U,$A$1,BV_Data_An_Cour!$V:$V,$A11) -> 51022.5 | D11: Taxes de Vente à Payer | E11: =-SUMIFS(BV_Data_An_Cour!$P:$P,BV_Data_An_Cour!$U:$U,$A$1,BV_Data_An_Cour!$V:$V,$D11) -> 115064.41
A12: Recevables Garantie Manufacturier | B12: =SUMIFS(BV_Data_An_Cour!$P:$P,BV_Data_An_Cour!$U:$U,$A$1,BV_Data_An_Cour!$V:$V,$A12) -> 19244.17 | D12: Impôts à payer | E12: =-SUMIFS(BV_Data_An_Cour!$P:$P,BV_Data_An_Cour!$U:$U,$A$1,BV_Data_An_Cour!$V:$V,$D12) -> 661471.24
A13: Recevables Carrosserie | B13: =SUMIFS(BV_Data_An_Cour!$P:$P,BV_Data_An_Cour!$U:$U,$A$1,BV_Data_An_Cour!$V:$V,$A13) -> 0 | D13: Dépôts de Client | E13: =-SUMIFS(BV_Data_An_Cour!$P:$P,BV_Data_An_Cour!$U:$U,$A$1,BV_Data_An_Cour!$V:$V,$D13) -> 129495
A14: Recevables Intercos | B14: =SUMIFS(BV_Data_An_Cour!$P:$P,BV_Data_An_Cour!$U:$U,$A$1,BV_Data_An_Cour!$V:$V,$A14) -> 46543.41 | D14: Payables Intercos | E14: =-SUMIFS(BV_Data_An_Cour!$P:$P,BV_Data_An_Cour!$U:$U,$A$1,BV_Data_An_Cour!$V:$V,$D14) -> 216511.65
A15: Recevables Autres | B15: =SUMIFS(BV_Data_An_Cour!$P:$P,BV_Data_An_Cour!$U:$U,$A$1,BV_Data_An_Cour!$V:$V,$A15) -> 100935.53 | D15: Autres Comptes à Payer | E15: =-SUMIFS(BV_Data_An_Cour!$P:$P,BV_Data_An_Cour!$U:$U,$A$1,BV_Data_An_Cour!$V:$V,$D15) -> 238484.3
A16: Total Comptes à Recevoir | B16: =+SUM(B8:B15) -> 1266868.5 | D16: Total Comptes à Payer | E16: =+SUM(E10:E15) -> 1499217.3
A18: Inventaire Véhicules Neufs | B18: =SUMIFS(BV_Data_An_Cour!$P:$P,BV_Data_An_Cour!$U:$U,$A$1,BV_Data_An_Cour!$V:$V,$A18) -> 5978608 | D18: Effet à Payer Véhicules Neufs | E18: =-SUMIFS(BV_Data_An_Cour!$P:$P,BV_Data_An_Cour!$U:$U,$A$1,BV_Data_An_Cour!$V:$V,$D18) -> 6985235.9
A19: Inventaire Véhicules Usagés | B19: =SUMIFS(BV_Data_An_Cour!$P:$P,BV_Data_An_Cour!$U:$U,$A$1,BV_Data_An_Cour!$V:$V,$A19) -> 2055013.9 | D19: Effet à Payer Véhicules Usagés | E19: =-SUMIFS(BV_Data_An_Cour!$P:$P,BV_Data_An_Cour!$U:$U,$A$1,BV_Data_An_Cour!$V:$V,$D19) -> 1381777.2
A20: Inventaire Pièces, Pneus, Huile | B20: =SUMIFS(BV_Data_An_Cour!$P:$P,BV_Data_An_Cour!$U:$U,$A$1,BV_Data_An_Cour!$V:$V,$A20) -> 426727.86 | D20: Total Effets à Payer | E20: =+SUM(E18:E19) -> 8367013.1
A21: Total Inventaires | B21: =SUM(B18:B20) -> 8460349.7
D22: Salaires à Payer | E22: =-SUMIFS(BV_Data_An_Cour!$P:$P,BV_Data_An_Cour!$U:$U,$A$1,BV_Data_An_Cour!$V:$V,$D22) -> 272466.73
A23: Avances à recevoir | B23: =SUMIFS(BV_Data_An_Cour!$P:$P,BV_Data_An_Cour!$U:$U,$A$1,BV_Data_An_Cour!$V:$V,$A23) -> 0 | D23: DAS à Payer | E23: =-SUMIFS(BV_Data_An_Cour!$P:$P,BV_Data_An_Cour!$U:$U,$A$1,BV_Data_An_Cour!$V:$V,$D23) -> -7108.34
A24: Travaux en Cours | B24: =SUMIFS(BV_Data_An_Cour!$P:$P,BV_Data_An_Cour!$U:$U,$A$1,BV_Data_An_Cour!$V:$V,$A24) -> 4075.1 | D24: Autres Courus | E24: =-SUMIFS(BV_Data_An_Cour!$P:$P,BV_Data_An_Cour!$U:$U,$A$1,BV_Data_An_Cour!$V:$V,$D24) -> 184234.13
A25: Sous-Traitance | B25: =SUMIFS(BV_Data_An_Cour!$P:$P,BV_Data_An_Cour!$U:$U,$A$1,BV_Data_An_Cour!$V:$V,$A25) -> 2761.92 | D25: [...] | E25: =-SUMIFS(BV_Data_An_Cour!$P:$P,BV_Data_An_Cour!$U:$U,$A$1,BV_Data_An_Cour!$V:$V,$D25) -> 0
A26: Frais Payés d'Avance | B26: =SUMIFS(BV_Data_An_Cour!$P:$P,BV_Data_An_Cour!$U:$U,$A$1,BV_Data_An_Cour!$V:$V,$A26) -> -3785.82 | D26: [...] | E26: =-SUMIFS(BV_Data_An_Cour!$P:$P,BV_Data_An_Cour!$U:$U,$A$1,BV_Data_An_Cour!$V:$V,$D26) -> 0
A27: [...] | B27: =SUMIFS(BV_Data_An_Cour!$P:$P,BV_Data_An_Cour!$U:$U,$A$1,BV_Data_An_Cour!$V:$V,$A27) -> 0 | D27: [...] | E27: =-SUMIFS(BV_Data_An_Cour!$P:$P,BV_Data_An_Cour!$U:$U,$A$1,BV_Data_An_Cour!$V:$V,$D27) -> 0
A28: [...] | B28: =SUMIFS(BV_Data_An_Cour!$P:$P,BV_Data_An_Cour!$U:$U,$A$1,BV_Data_An_Cour!$V:$V,$A28) -> 0 | D28: Total Frais Courus | E28: =SUM(E22:E24) -> 449592.52
A29: [...] | B29: =SUMIFS(BV_Data_An_Cour!$P:$P,BV_Data_An_Cour!$U:$U,$A$1,BV_Data_An_Cour!$V:$V,$A29) -> 0
A30: Total Autres | B30: =SUM(B23:B29) -> 3051.2 | D30: Total Passif Court Terme | E30: =+E5+E7+E16+E20+E28 -> 10315823
A32: Total Actif Court Terme | B32: =+B6+B16+B21+B30 -> 11489411
D33: Impôts Futurs à payer | E33: =-SUMIFS(BV_Data_An_Cour!$P:$P,BV_Data_An_Cour!$U:$U,$A$1,BV_Data_An_Cour!$V:$V,$D33) -> 1101731
A35: Terrain | B35: =SUMIFS(BV_Data_An_Cour!$P:$P,BV_Data_An_Cour!$U:$U,$A$1,BV_Data_An_Cour!$V:$V,$A35) -> 0 | D35: Avances Long Terme à Payer | E35: =-SUMIFS(BV_Data_An_Cour!$P:$P,BV_Data_An_Cour!$U:$U,$A$1,BV_Data_An_Cour!$V:$V,$D35) -> 0
A36: Bâtisse | B36: =SUMIFS(BV_Data_An_Cour!$P:$P,BV_Data_An_Cour!$U:$U,$A$1,BV_Data_An_Cour!$V:$V,$A36) -> 0 | D36: Hypothèque à Payer | E36: =-SUMIFS(BV_Data_An_Cour!$P:$P,BV_Data_An_Cour!$U:$U,$A$1,BV_Data_An_Cour!$V:$V,$D36) -> 0
A37: Améliorations Locatives | B37: =SUMIFS(BV_Data_An_Cour!$P:$P,BV_Data_An_Cour!$U:$U,$A$1,BV_Data_An_Cour!$V:$V,$A37) -> 727525.41 | D37: Dette à Long Terme | E37: =-SUMIFS(BV_Data_An_Cour!$P:$P,BV_Data_An_Cour!$U:$U,$A$1,BV_Data_An_Cour!$V:$V,$D37) -> 0
A38: Améliorations Locatives Permanentes | B38: =SUMIFS(BV_Data_An_Cour!$P:$P,BV_Data_An_Cour!$U:$U,$A$1,BV_Data_An_Cour!$V:$V,$A38) -> 0 | D38: Autres Dettes à Long Terme | E38: =-SUMIFS(BV_Data_An_Cour!$P:$P,BV_Data_An_Cour!$U:$U,$A$1,BV_Data_An_Cour!$V:$V,$D38) -> 0
A39: Équipements Service | B39: =SUMIFS(BV_Data_An_Cour!$P:$P,BV_Data_An_Cour!$U:$U,$A$1,BV_Data_An_Cour!$V:$V,$A39) -> 249198.74 | D39: [...] | E39: =-SUMIFS(BV_Data_An_Cour!$P:$P,BV_Data_An_Cour!$U:$U,$A$1,BV_Data_An_Cour!$V:$V,$D39) -> 0
A40: Mobilier | B40: =SUMIFS(BV_Data_An_Cour!$P:$P,BV_Data_An_Cour!$U:$U,$A$1,BV_Data_An_Cour!$V:$V,$A40) -> 121568.58 | D40: [...] | E40: =-SUMIFS(BV_Data_An_Cour!$P:$P,BV_Data_An_Cour!$U:$U,$A$1,BV_Data_An_Cour!$V:$V,$D40) -> 0
A41: Équipements Informatique | B41: =SUMIFS(BV_Data_An_Cour!$P:$P,BV_Data_An_Cour!$U:$U,$A$1,BV_Data_An_Cour!$V:$V,$A41) -> 13180.56 | D41: [...] | E41: =-SUMIFS(BV_Data_An_Cour!$P:$P,BV_Data_An_Cour!$U:$U,$A$1,BV_Data_An_Cour!$V:$V,$D41) -> 0
A42: Équipements Téléphonique | B42: =SUMIFS(BV_Data_An_Cour!$P:$P,BV_Data_An_Cour!$U:$U,$A$1,BV_Data_An_Cour!$V:$V,$A42) -> 0 | D42: Total Passif long terme | E42: =+SUM(E33:E38) -> 1101731
A43: Enseigne | B43: =SUMIFS(BV_Data_An_Cour!$P:$P,BV_Data_An_Cour!$U:$U,$A$1,BV_Data_An_Cour!$V:$V,$A43) -> 20003.32
A44: Total Immobilisations Nettes | B44: =SUM(B35:B43) -> 1131476.6
D45: Total Passifs | E45: =+E42+E30 -> 11417554
A46: Avances à Recevoir Long Terme | B46: =SUMIFS(BV_Data_An_Cour!$P:$P,BV_Data_An_Cour!$U:$U,$A$1,BV_Data_An_Cour!$V:$V,$A46) -> 1750000
A48: Achalandage | B48: =SUMIFS(BV_Data_An_Cour!$P:$P,BV_Data_An_Cour!$U:$U,$A$1,BV_Data_An_Cour!$V:$V,$A48) -> 4854961.3 | D48: Capital Actions | E48: =-SUMIFS(BV_Data_An_Cour!$P:$P,BV_Data_An_Cour!$U:$U,$A$1,BV_Data_An_Cour!$V:$V,$D48) -> 4390685.6
D49: Apport | E49: =-SUMIFS(BV_Data_An_Cour!$P:$P,BV_Data_An_Cour!$U:$U,$A$1,BV_Data_An_Cour!$V:$V,$D49) -> 0
A50: [...] | B50: =SUMIFS(BV_Data_An_Cour!$P:$P,BV_Data_An_Cour!$U:$U,$A$1,BV_Data_An_Cour!$V:$V,$A50) -> 0 | D50: Bénéfices non répartis | E50: =-SUMIFS(BV_Data_An_Cour!$P:$P,BV_Data_An_Cour!$U:$U,$A$1,BV_Data_An_Cour!$V:$V,$D50)+Print_AAD!AF502 -> 3417609.6
A51: [...] | B51: =SUMIFS(BV_Data_An_Cour!$P:$P,BV_Data_An_Cour!$U:$U,$A$1,BV_Data_An_Cour!$V:$V,$A51) -> 0 | D51: Dividendes | E51: =-SUMIFS(BV_Data_An_Cour!$P:$P,BV_Data_An_Cour!$U:$U,$A$1,BV_Data_An_Cour!$V:$V,$D51) -> 0
A52: [...] | B52: =SUMIFS(BV_Data_An_Cour!$P:$P,BV_Data_An_Cour!$U:$U,$A$1,BV_Data_An_Cour!$V:$V,$A52) -> 0
A53: Total Actif Long Terme | B53: =+B44+B48+B46 -> 7736437.9 | D53: Total Capitaux Propres / Avoir | E53: =SUM(E48:E51) -> 7808295.2
A56: Total Actif | B56: =+B32+B53 -> 19225849 | D56: Total Passif et Capitaux Propres / Avoir | E56: =+E53+E45 -> 19225849
E65: =+B56-E56 -> 0

Sheet Budget original
B1: ="Budget 2023 Mensuel"&" "&Parametres!$B$1 -> Budget 2023 Mensuel BMW Sherbrooke
B2: Mois | F2: =+IF(Parametres!$B$3=F$6,"X","") | G2: =+IF(Parametres!$B$3=F$6,"O","") | H2: =+IF(Parametres!$B$3=F$6,"U","") | I2: =+IF(Parametres!$B$3=I$6,"X","") | J2: =+IF(Parametres!$B$3=I$6,"O","") | K2: =+IF(Parametres!$B$3=I$6,"U","") | L2: =+IF(Parametres!$B$3=L$6,"X","") | M2: =+IF(Parametres!$B$3=L$6,"O","") | N2: =+IF(Parametres!$B$3=L$6,"U","") | O2: =+IF(Parametres!$B$3=O$6,"X","") -> X | P2: =+IF(Parametres!$B$3=O$6,"O","") -> O | Q2: =+IF(Parametres!$B$3=O$6,"U","") -> U | R2: =+IF(Parametres!$B$3=R$6,"X","") | S2: =+IF(Parametres!$B$3=R$6,"O","") | T2: =+IF(Parametres!$B$3=R$6,"U","") | U2: =+IF(Parametres!$B$3=U$6,"X","") | V2: =+IF(Parametres!$B$3=U$6,"O","") | W2: =+IF(Parametres!$B$3=U$6,"U","") | X2: =+IF(Parametres!$B$3=X$6,"X","") | Y2: =+IF(Parametres!$B$3=X$6,"O","") | Z2: =+IF(Parametres!$B$3=X$6,"U","") | AA2: =+IF(Parametres!$B$3=AA$6,"X","") | AB2: =+IF(Parametres!$B$3=AA$6,"O","") | AC2: =+IF(Parametres!$B$3=AA$6,"U","") | AD2: =+IF(Parametres!$B$3=AD$6,"X","") | AE2: =+IF(Parametres!$B$3=AD$6,"O","") | AF2: =+IF(Parametres!$B$3=AD$6,"U","") | AG2: =+IF(Parametres!$B$3=AG$6,"X","") | AH2: =+IF(Parametres!$B$3=AG$6,"O","") | AI2: =+IF(Parametres!$B$3=AG$6,"U","") | AJ2: =+IF(Parametres!$B$3=AJ$6,"X","") | AK2: =+IF(Parametres!$B$3=AJ$6,"O","") | AL2: =+IF(Parametres!$B$3=AJ$6,"U","") | AM2: =+IF(Parametres!$B$3=AM$6,"X","") | AN2: =+IF(Parametres!$B$3=AM$6,"O","") | AO2: =+IF(Parametres!$B$3=AM$6,"U","")
B3: YTD | F3: =+IF(VLOOKUP(F$6,Parametres!$K$3:$N$14,4,0)="X","X","") -> X | G3: =+IF(VLOOKUP(F$6,Parametres!$K$3:$N$14,4,0)="X","O","") -> O | H3: =+IF(VLOOKUP(F$6,Parametres!$K$3:$N$14,4,0)="X","U","") -> U | I3: =+IF(VLOOKUP(I$6,Parametres!$K$3:$N$14,4,0)="X","X","") -> X | J3: =+IF(VLOOKUP(I$6,Parametres!$K$3:$N$14,4,0)="X","O","") -> O | K3: =+IF(VLOOKUP(I$6,Parametres!$K$3:$N$14,4,0)="X","U","") -> U | L3: =+IF(VLOOKUP(L$6,Parametres!$K$3:$N$14,4,0)="X","X","") -> X | M3: =+IF(VLOOKUP(L$6,Parametres!$K$3:$N$14,4,0)="X","O","") -> O | N3: =+IF(VLOOKUP(L$6,Parametres!$K$3:$N$14,4,0)="X","U","") -> U | O3: =+IF(VLOOKUP(O$6,Parametres!$K$3:$N$14,4,0)="X","X","") -> X | P3: =+IF(VLOOKUP(O$6,Parametres!$K$3:$N$14,4,0)="X","O","") -> O | Q3: =+IF(VLOOKUP(O$6,Parametres!$K$3:$N$14,4,0)="X","U","") -> U | R3: =+IF(VLOOKUP(R$6,Parametres!$K$3:$N$14,4,0)="X","X","") | S3: =+IF(VLOOKUP(R$6,Parametres!$K$3:$N$14,4,0)="X","O","") | T3: =+IF(VLOOKUP(R$6,Parametres!$K$3:$N$14,4,0)="X","U","") | U3: =+IF(VLOOKUP(U$6,Parametres!$K$3:$N$14,4,0)="X","X","") | V3: =+IF(VLOOKUP(U$6,Parametres!$K$3:$N$14,4,0)="X","O","") | W3: =+IF(VLOOKUP(U$6,Parametres!$K$3:$N$14,4,0)="X","U","") | X3: =+IF(VLOOKUP(X$6,Parametres!$K$3:$N$14,4,0)="X","X","") | Y3: =+IF(VLOOKUP(X$6,Parametres!$K$3:$N$14,4,0)="X","O","") | Z3: =+IF(VLOOKUP(X$6,Parametres!$K$3:$N$14,4,0)="X","U","") | AA3: =+IF(VLOOKUP(AA$6,Parametres!$K$3:$N$14,4,0)="X","X","") | AB3: =+IF(VLOOKUP(AA$6,Parametres!$K$3:$N$14,4,0)="X","O","") | AC3: =+IF(VLOOKUP(AA$6,Parametres!$K$3:$N$14,4,0)="X","U","") | AD3: =+IF(VLOOKUP(AD$6,Parametres!$K$3:$N$14,4,0)="X","X","") | AE3: =+IF(VLOOKUP(AD$6,Parametres!$K$3:$N$14,4,0)="X","O","") | AF3: =+IF(VLOOKUP(AD$6,Parametres!$K$3:$N$14,4,0)="X","U","") | AG3: =+IF(VLOOKUP(AG$6,Parametres!$K$3:$N$14,4,0)="X","X","") | AH3: =+IF(VLOOKUP(AG$6,Parametres!$K$3:$N$14,4,0)="X","O","") | AI3: =+IF(VLOOKUP(AG$6,Parametres!$K$3:$N$14,4,0)="X","U","") | AJ3: =+IF(VLOOKUP(AJ$6,Parametres!$K$3:$N$14,4,0)="X","X","") | AK3: =+IF(VLOOKUP(AJ$6,Parametres!$K$3:$N$14,4,0)="X","O","") | AL3: =+IF(VLOOKUP(AJ$6,Parametres!$K$3:$N$14,4,0)="X","U","") | AM3: =+IF(VLOOKUP(AM$6,Parametres!$K$3:$N$14,4,0)="X","X","") | AN3: =+IF(VLOOKUP(AM$6,Parametres!$K$3:$N$14,4,0)="X","O","") | AO3: =+IF(VLOOKUP(AM$6,Parametres!$K$3:$N$14,4,0)="X","U","")
B4: Budget 2024 | C4: Véhicules neufs
B6: Mois | C6: 2024 | F6: Janvier | I6: Février | L6: Mars | O6: Avril | R6: Mai | U6: Juin | X6: Juillet | AA6: Août | AD6: Septembre | AG6: Octobre | AJ6: Novembre | AM6: Décembre
C7: UNITE | D7: $P/UNITE | E7: $PROFITS | F7: UNITE | G7: $P/UNITE | H7: $PROFITS | I7: UNITE | J7: $P/UNITE | K7: $PROFITS | L7: UNITE | M7: $P/UNITE | N7: $PROFITS | O7: UNITE | P7: $P/UNITE | Q7: $PROFITS | R7: UNITE | S7: $P/UNITE | T7: $PROFITS | U7: UNITE | V7: $P/UNITE | W7: $PROFITS | X7: UNITE | Y7: $P/UNITE | Z7: $PROFITS | AA7: UNITE | AB7: $P/UNITE | AC7: $PROFITS | AD7: UNITE | AE7: $P/UNITE | AF7: $PROFITS | AG7: UNITE | AH7: $P/UNITE | AI7: $PROFITS | AJ7: UNITE | AK7: $P/UNITE | AL7: $PROFITS | AM7: UNITE | AN7: $P/UNITE | AO7: $PROFITS
A8: =+$C$4&B8 -> Véhicules neufsVentes nettes | B8: Ventes nettes | E8: 23738856 | H8: 908508.74 | K8: 1154769.3 | N8: 2794294.1 | Q8: 3032403.6 | T8: 2803316.5 | W8: 2000167.3 | Z8: 1608193.6 | AC8: 2002452.1 | AF8: 2407689.2 | AI8: 1708172.4 | AL8: 1856597 | AO8: 1462292.2
A9: =+$C$4&B9 -> Véhicules neufsAutos détail | B9: Autos détail | C9: 81 | D9: 5144.9383 | E9: 416740 | F9: 3 | G9: 5144.9383 | H9: 15434.815 | I9: 4 | J9: 5144.9383 | K9: 20579.753 | L9: 9 | M9: 5144.9383 | N9: 46304.444 | O9: 10 | P9: 5144.9383 | Q9: 51449.383 | R9: 9 | S9: 5144.9383 | T9: 46304.444 | U9: 7 | V9: 5144.9383 | W9: 36014.568 | X9: 6 | Y9: 5144.9383 | Z9: 30869.63 | AA9: 7 | AB9: 5144.9383 | AC9: 36014.568 | AD9: 9 | AE9: 5144.9383 | AF9: 46304.444 | AG9: 6 | AH9: 5144.9383 | AI9: 30869.63 | AJ9: 6 | AK9: 5144.9383 | AL9: 30869.63 | AM9: 5 | AN9: 5144.9383 | AO9: 25724.691
A10: =+$C$4&B10 -> Véhicules neufsCamions détail | B10: Camions détail | C10: 151 | D10: 5386.4238 | E10: 813350 | F10: 6 | G10: 5386.4238 | H10: 32318.543 | I10: 7 | J10: 5386.4238 | K10: 37704.967 | L10: 18 | M10: 5386.4238 | N10: 96955.629 | O10: 19 | P10: 5386.4238 | Q10: 102342.05 | R10: 17 | S10: 5386.4238 | T10: 91569.205 | U10: 13 | V10: 5386.4238 | W10: 70023.51 | X10: 10 | Y10: 5386.4238 | Z10: 53864.238 | AA10: 13 | AB10: 5386.4238 | AC10: 70023.51 | AD10: 15 | AE10: 5386.4238 | AF10: 80796.358 | AG10: 11 | AH10: 5386.4238 | AI10: 59250.662 | AJ10: 12 | AK10: 5386.4238 | AL10: 64637.086 | AM10: 10 | AN10: 5386.4238 | AO10: 53864.238
A11: =+$C$4&B11 -> Véhicules neufsSprinter | B11: Sprinter | C11: 0 | D11: 0 | E11: 0 | F11: 0 | G11: 0 | H11: 0 | I11: 0 | J11: 0 | K11: 0 | L11: 0 | M11: 0 | N11: 0 | O11: 0 | P11: 0 | Q11: 0 | R11: 0 | S11: 0 | T11: 0 | U11: 0 | V11: 0 | W11: 0 | X11: 0 | Y11: 0 | Z11: 0 | AA11: 0 | AB11: 0 | AC11: 0 | AD11: 0 | AE11: 0 | AF11: 0 | AG11: 0 | AH11: 0 | AI11: 0 | AJ11: 0 | AK11: 0 | AL11: 0 | AM11: 0 | AN11: 0 | AO11: 0
A12: =+$C$4&B12 -> Véhicules neufsMoto détail | B12: Moto détail | C12: 0 | D12: 0 | E12: 0 | F12: 0 | G12: 0 | H12: 0 | I12: 0 | J12: 0 | K12: 0 | L12: 0 | M12: 0 | N12: 0 | O12: 0 | P12: 0 | Q12: 0 | R12: 0 | S12: 0 | T12: 0 | U12: 0 | V12: 0 | W12: 0 | X12: 0 | Y12: 0 | Z12: 0 | AA12: 0 | AB12: 0 | AC12: 0 | AD12: 0 | AE12: 0 | AF12: 0 | AG12: 0 | AH12: 0 | AI12: 0 | AJ12: 0 | AK12: 0 | AL12: 0 | AM12: 0 | AN12: 0 | AO12: 0
A13: =+$C$4&B13 -> Véhicules neufs[...] | B13: [...] | C13: 0 | D13: 0 | E13: 0 | G13: 0 | J13: 0 | M13: 0 | P13: 0 | S13: 0 | V13: 0 | Y13: 0 | AB13: 0 | AE13: 0 | AH13: 0 | AK13: 0 | AN13: 0
A14: =+$C$4&B14 -> Véhicules neufs[...] | B14: [...] | C14: 0 | D14: 0 | E14: 0 | G14: 0 | J14: 0 | M14: 0 | P14: 0 | S14: 0 | V14: 0 | Y14: 0 | AB14: 0 | AE14: 0 | AH14: 0 | AK14: 0 | AN14: 0
A15: =+$C$4&B15 -> Véhicules neufs[...] | B15: [...] | C15: 0 | D15: 0 | E15: 0 | G15: 0 | J15: 0 | M15: 0 | P15: 0 | S15: 0 | V15: 0 | Y15: 0 | AB15: 0 | AE15: 0 | AH15: 0 | AK15: 0 | AN15: 0
A16: =+$C$4&B16 -> Véhicules neufsTotal Neufs | B16: Total Neufs | C16: 232 | D16: 5302.1121 | E16: 1230090 | F16: 9 | G16: 5305.9287 | H16: 47753.358 | I16: 11 | J16: 5298.6109 | K16: 58284.72 | L16: 27 | M16: 5305.9287 | N16: 143260.07 | O16: 29 | P16: 5303.153 | Q16: 153791.44 | R16: 26 | S16: 5302.8327 | T16: 137873.65 | U16: 20 | V16: 5301.9039 | W16: 106038.08 | X16: 16 | Y16: 5295.8668 | Z16: 84733.868 | AA16: 20 | AB16: 5301.9039 | AC16: 106038.08 | AD16: 24 | AE16: 5295.8668 | AF16: 127100.8 | AG16: 17 | AH16: 5301.1936 | AI16: 90120.292 | AJ16: 18 | AK16: 5305.9287 | AL16: 95506.716 | AM16: 15 | AN16: 5305.9287 | AO16: 79588.93
A17: =+$C$4&B17 -> Véhicules neufs
A18: =+$C$4&B18 -> Véhicules neufsEx-Démos et courtoisies | B18: Ex-Démos et courtoisies | C18: 24 | D18: 2500 | E18: 60000 | F18: 1 | G18: 2500 | H18: 2500 | I18: 1 | J18: 2500 | K18: 2500 | L18: 3 | M18: 2500 | N18: 7500 | O18: 3 | P18: 2500 | Q18: 7500 | R18: 3 | S18: 2500 | T18: 7500 | U18: 2 | V18: 2500 | W18: 5000 | X18: 2 | Y18: 2500 | Z18: 5000 | AA18: 2 | AB18: 2500 | AC18: 5000 | AD18: 2 | AE18: 2500 | AF18: 5000 | AG18: 2 | AH18: 2500 | AI18: 5000 | AJ18: 2 | AK18: 2500 | AL18: 5000 | AM18: 1 | AN18: 2500 | AO18: 2500
A19: =+$C$4&B19 -> Véhicules neufs
A20: =+$C$4&B20 -> Véhicules neufsFlottes | B20: Flottes | C20: 4 | D20: 2500 | E20: 10000 | F20: 0 | G20: 0 | H20: 0 | I20: 0 | J20: 0 | K20: 0 | L20: 1 | M20: 2500 | N20: 2500 | O20: 1 | P20: 2500 | Q20: 2500 | R20: 1 | S20: 2500 | T20: 2500 | U20: 0 | V20: 0 | W20: 0 | X20: 0 | Y20: 0 | Z20: 0 | AA20: 0 | AB20: 0 | AC20: 0 | AD20: 1 | AE20: 2500 | AF20: 2500 | AG20: 0 | AH20: 0 | AI20: 0 | AJ20: 0 | AK20: 0 | AL20: 0 | AM20: 0 | AN20: 0 | AO20: 0
A21: =+$C$4&B21 -> Véhicules neufs
A22: =+$C$4&B22 -> Véhicules neufsRachat bail | B22: Rachat bail | E22: 38961 | H22: 1386.4053 | K22: 3512.1376 | N22: 3667.8254 | Q22: 5546.8032 | T22: 6629.0564 | W22: 2988.0085 | Z22: 1827.3374 | AC22: 3057.1768 | AF22: 2093.133 | AI22: 2165.8719 | AL22: 3970.9903 | AO22: 2116.2542
A23: =+$C$4&B23 -> Véhicules neufs
A24: =+$C$4&B24 -> Véhicules neufsRev. Finances | B24: Rev. Finances | D24: 85 | E24: 21760 | G24: 85 | H24: 850 | J24: 85 | K24: 1020 | M24: 85 | N24: 2550 | P24: 85 | Q24: 2720 | S24: 85 | T24: 2465 | V24: 85 | W24: 1870 | Y24: 85 | Z24: 1530 | AB24: 85 | AC24: 1870 | AE24: 85 | AF24: 2210 | AH24: 85 | AI24: 1615 | AK24: 85 | AL24: 1700 | AN24: 85 | AO24: 1360
A25: =+$C$4&B25 -> Véhicules neufsRev. Protections | B25: Rev. Protections | D25: 1020 | E25: 261120 | G25: 1020 | H25: 10200 | J25: 1020 | K25: 12240 | M25: 1020 | N25: 30600 | P25: 1020 | Q25: 32640 | S25: 1020 | T25: 29580 | V25: 1020 | W25: 22440 | Y25: 1020 | Z25: 18360 | AB25: 1020 | AC25: 22440 | AE25: 1020 | AF25: 26520 | AH25: 1020 | AI25: 19380 | AK25: 1020 | AL25: 20400 | AN25: 1020 | AO25: 16320
A26: =+$C$4&B26 -> Véhicules neufsRev. Autres | B26: Rev. Autres | D26: 495 | E26: 126720 | G26: 495 | H26: 4950 | J26: 495 | K26: 5940 | M26: 495 | N26: 14850 | P26: 495 | Q26: 15840 | S26: 495 | T26: 14355 | V26: 495 | W26: 10890 | Y26: 495 | Z26: 8910 | AB26: 495 | AC26: 10890 | AE26: 495 | AF26: 12870 | AH26: 495 | AI26: 9405 | AK26: 495 | AL26: 9900 | AN26: 495 | AO26: 7920
A27: =+$C$4&B27 -> Véhicules neufsTotal F&I | B27: Total F&I | C27: 256 | D27: 1600 | E27: 409600 | F27: 10 | G27: 1600 | H27: 16000 | I27: 12 | J27: 1600 | K27: 19200 | L27: 30 | M27: 1600 | N27: 48000 | O27: 32 | P27: 1600 | Q27: 51200 | R27: 29 | S27: 1600 | T27: 46400 | U27: 22 | V27: 1600 | W27: 35200 | X27: 18 | Y27: 1600 | Z27: 28800 | AA27: 22 | AB27: 1600 | AC27: 35200 | AD27: 26 | AE27: 1600 | AF27: 41600 | AG27: 19 | AH27: 1600 | AI27: 30400 | AJ27: 20 | AK27: 1600 | AL27: 32000 | AM27: 16 | AN27: 1600 | AO27: 25600
A28: =+$C$4&B28 -> Véhicules neufs
A29: =+$C$4&B29 -> Véhicules neufs
A30: =+$C$4&B30 -> Véhicules neufsTotal Dépt. Neufs | B30: Total Dépt. Neufs | C30: 260 | D30: 6725.5808 | E30: 1748651 | F30: 10 | G30: 6763.9763 | H30: 67639.763 | I30: 12 | J30: 6958.0715 | K30: 83496.858 | L30: 31 | M30: 6610.5774 | N30: 204927.9 | O30: 33 | P30: 6682.9769 | Q30: 220538.24 | R30: 30 | S30: 6696.7569 | T30: 200902.71 | U30: 22 | V30: 6783.0039 | W30: 149226.09 | X30: 18 | Y30: 6686.7336 | Z30: 120361.21 | AA30: 22 | AB30: 6786.1479 | AC30: 149295.25 | AD30: 27 | AE30: 6603.4791 | AF30: 178293.94 | AG30: 19 | AH30: 6720.3244 | AI30: 127686.16 | AJ30: 20 | AK30: 6823.8853 | AL30: 136477.71 | AM30: 16 | AN30: 6862.824 | AO30: 109805.18
A31: =+$C$4&B31 -> Véhicules neufs
A32: =+$C$4&B32 -> Véhicules neufs
A33: =+$C$4&B33 -> Véhicules neufsDEPENSES | B33: DEPENSES
A34: =+$C$4&B34 -> Véhicules neufsComm. vendeurs | B34: Comm. vendeurs | C34: 0.29576514 | D34: 1490.483 | E34: 381563.65 | F34: 0.3259414 | G34: 1637.965 | H34: 16379.65 | I34: 0.31901474 | J34: 1615.9352 | K34: 19391.222 | L34: 0.28836372 | M34: 1449.1245 | N34: 43473.736 | O34: 0.29022398 | P34: 1462.8326 | Q34: 46810.642 | R34: 0.29628195 | S34: 1485.2272 | T34: 43071.589 | U34: 0.28996409 | V34: 1463.5025 | W34: 32197.055 | X34: 0.29815739 | Y34: 1486.3786 | Z34: 26754.816 | AA34: 0.29244348 | AB34: 1476.0165 | AC34: 32472.362 | AD34: 0.28939001 | AE34: 1470.3328 | AF34: 38228.652 | AG34: 0.29688638 | AH34: 1486.3115 | AI34: 28239.919 | AJ34: 0.29683244 | AK34: 1491.6827 | AL34: 29833.654 | AM34: 0.30101931 | AN34: 1544.3971 | AO34: 24710.353
A35: =+$C$4&B35 -> Véhicules neufsComm. F&I | B35: Comm. F&I | C35: 0.25 | D35: 400 | E35: 102400 | F35: 0.25 | G35: 400 | H35: 4000 | I35: 0.25 | J35: 400 | K35: 4800 | L35: 0.25 | M35: 400 | N35: 12000 | O35: 0.25 | P35: 400 | Q35: 12800 | R35: 0.25 | S35: 400 | T35: 11600 | U35: 0.25 | V35: 400 | W35: 8800 | X35: 0.25 | Y35: 400 | Z35: 7200 | AA35: 0.25 | AB35: 400 | AC35: 8800 | AD35: 0.25 | AE35: 400 | AF35: 10400 | AG35: 0.25 | AH35: 400 | AI35: 7600 | AJ35: 0.25 | AK35: 400 | AL35: 8000 | AM35: 0.25 | AN35: 400 | AO35: 6400
A36: =+$C$4&B36 -> Véhicules neufsFrais de livraison | B36: Frais de livraison | D36: 100 | E36: 25600 | G36: 100 | H36: 1000 | J36: 100 | K36: 1200 | M36: 100 | N36: 3000 | P36: 100 | Q36: 3200 | S36: 100 | T36: 2900 | V36: 100 | W36: 2200 | Y36: 100 | Z36: 1800 | AB36: 100 | AC36: 2200 | AE36: 100 | AF36: 2600 | AH36: 100 | AI36: 1900 | AK36: 100 | AL36: 2000 | AN36: 100 | AO36: 1600
A37: =+$C$4&B37 -> Véhicules neufsService gratuit 1 | B37: Service gratuit 1 | D37: 45 | E37: 11520 | G37: 45 | H37: 450 | J37: 45 | K37: 540 | M37: 45 | N37: 1350 | P37: 45 | Q37: 1440 | S37: 45 | T37: 1305 | V37: 45 | W37: 990 | Y37: 45 | Z37: 810 | AB37: 45 | AC37: 990 | AE37: 45 | AF37: 1170 | AH37: 45 | AI37: 855 | AK37: 45 | AL37: 900 | AN37: 45 | AO37: 720
A38: =+$C$4&B38 -> Véhicules neufsEntretien stock | B38: Entretien stock | D38: 47.03125 | E38: 12040 | G38: 55 | H38: 550 | J38: 52.5 | K38: 630 | M38: 45 | N38: 1350 | P38: 44.6875 | Q38: 1430 | S38: 45.172414 | T38: 1310 | V38: 46.818182 | W38: 1030 | Y38: 48.333333 | Z38: 870 | AB38: 46.818182 | AC38: 1030 | AE38: 45.769231 | AF38: 1190 | AH38: 47.894737 | AI38: 910 | AK38: 47.5 | AL38: 950 | AN38: 49.375 | AO38: 790
A39: =+$C$4&B39 -> Véhicules neufsPublicité 1 | B39: Publicité 1 | D39: 496.60938 | E39: 127132 | G39: 496.60938 | H39: 4966.0938 | J39: 496.60938 | K39: 5959.3125 | M39: 496.60938 | N39: 14898.281 | P39: 496.60938 | Q39: 15891.5 | S39: 496.60938 | T39: 14401.672 | V39: 496.60938 | W39: 10925.406 | Y39: 496.60938 | Z39: 8938.9688 | AB39: 496.60938 | AC39: 10925.406 | AE39: 496.60938 | AF39: 12911.844 | AH39: 496.60938 | AI39: 9435.5781 | AK39: 496.60938 | AL39: 9932.1875 | AN39: 496.60938 | AO39: 7945.75
A40: =+$C$4&B40 -> Véhicules neufsIntérêt de gros | B40: Intérêt de gros | D40: 1254.1719 | E40: 321068.01 | G40: 2225.557 | H40: 22255.57 | J40: 2114.5035 | K40: 25374.042 | M40: 1066.4127 | N40: 31992.382 | P40: 960.50061 | Q40: 30736.02 | S40: 1007.2564 | T40: 29210.436 | V40: 1162.5435 | W40: 25575.958 | Y40: 1468.2494 | Z40: 26428.49 | AB40: 1296.1341 | AC40: 28514.95 | AE40: 1035.4639 | AF40: 26922.061 | AH40: 1378.7716 | AI40: 26196.661 | AK40: 1233.9278 | AL40: 24678.556 | AN40: 1448.9304 | AO40: 23182.886
A41: =+$C$4&B41 -> Véhicules neufs[...] | B41: [...] | D41: 0 | E41: 0 | G41: 0 | J41: 0 | M41: 0 | P41: 0 | S41: 0 | V41: 0 | Y41: 0 | AB41: 0 | AE41: 0 | AH41: 0 | AK41: 0 | AN41: 0
A42: =+$C$4&B42 -> Véhicules neufs[...] | B42: [...] | D42: 0 | E42: 0 | G42: 0 | J42: 0 | M42: 0 | P42: 0 | S42: 0 | V42: 0 | Y42: 0 | AB42: 0 | AE42: 0 | AH42: 0 | AK42: 0 | AN42: 0
A43: =+$C$4&B43 -> Véhicules neufs[...] | B43: [...] | D43: 0 | E43: 0 | G43: 0 | J43: 0 | M43: 0 | P43: 0 | S43: 0 | V43: 0 | Y43: 0 | AB43: 0 | AE43: 0 | AH43: 0 | AK43: 0 | AN43: 0
A44: =+$C$4&B44 -> Véhicules neufsTOTAL VARIABLES | B44: TOTAL VARIABLES | C44: % brut | D44: 0.56118897 | E44: 981323.66 | F44: % brut | G44: 0.7333159 | H44: 49601.314 | I44: % brut | J44: 0.69337432 | K44: 57894.577 | L44: % brut | M44: 0.52732888 | N44: 108064.4 | O44: % brut | P44: 0.50924575 | Q44: 112308.16 | R44: % brut | S44: 0.51666152 | T44: 103798.7 | U44: % brut | V44: 0.54761484 | W44: 81718.419 | X44: % brut | Y44: 0.60486495 | Z44: 72802.274 | AA44: % brut | AB44: 0.56889094 | AC44: 84932.718 | AD44: % brut | AE44: 0.52398056 | AF44: 93422.557 | AG44: % brut | AH44: 0.58845184 | AI44: 75137.158 | AJ44: % brut | AK44: 0.55902462 | AL44: 76294.397 | AM44: % brut | AN44: 0.59513574 | AO44: 65348.989
A45: =+$C$4&B45 -> Véhicules neufsSalaires cadres | B45: Salaires cadres | E45: 150223.4 | H45: 12750.169 | K45: 12353.222 | N45: 12353.222 | Q45: 12551.696 | T45: 12750.169 | W45: 12154.749 | Z45: 12750.169 | AC45: 12551.696 | AF45: 12353.222 | AI45: 12750.169 | AL45: 12353.222 | AO45: 12551.696
A46: =+$C$4&B46 -> Véhicules neufsSalaires commis | B46: Salaires commis | E46: 104129.9 | H46: 9014.8378 | K46: 8436.5302 | N46: 8436.5302 | Q46: 8725.684 | T46: 9014.8378 | W46: 8147.3763 | Z46: 9014.8378 | AC46: 8725.684 | AF46: 8436.5302 | AI46: 9014.8378 | AL46: 8436.5302 | AO46: 8725.684
A47: =+$C$4&B47 -> Véhicules neufsSalaires autres | B47: Salaires autres | E47: 4104 | H47: 342 | K47: 342 | N47: 342 | Q47: 342 | T47: 342 | W47: 342 | Z47: 342 | AC47: 342 | AF47: 342 | AI47: 342 | AL47: 342 | AO47: 342
A48: =+$C$4&B48 -> Véhicules neufsSalaires spécialistes | B48: Salaires spécialistes | E48: 0 | H48: 0 | K48: 0 | N48: 0 | Q48: 0 | T48: 0 | W48: 0 | Z48: 0 | AC48: 0 | AF48: 0 | AI48: 0 | AL48: 0 | AO48: 0
A49: =+$C$4&B49 -> Véhicules neufs[...] | B49: [...] | E49: 0 | H49: 0 | K49: 0 | N49: 0 | Q49: 0 | T49: 0 | W49: 0 | Z49: 0 | AC49: 0 | AF49: 0 | AI49: 0 | AL49: 0 | AO49: 0
A50: =+$C$4&B50 -> Véhicules neufs[...] | B50: [...] | E50: 0 | H50: 0 | K50: 0 | N50: 0 | Q50: 0 | T50: 0 | W50: 0 | Z50: 0 | AC50: 0 | AF50: 0 | AI50: 0 | AL50: 0 | AO50: 0
A51: =+$C$4&B51 -> Véhicules neufs[...] | B51: [...] | E51: 0 | H51: 0 | K51: 0 | N51: 0 | Q51: 0 | T51: 0 | W51: 0 | Z51: 0 | AC51: 0 | AF51: 0 | AI51: 0 | AL51: 0 | AO51: 0
A52: =+$C$4&B52 -> Véhicules neufsSalaires en absences | B52: Salaires en absences | E52: 83157.726 | H52: 5313.2599 | K52: 4901.6184 | N52: 7856.5596 | Q52: 9076.1105 | T52: 8639.878 | W52: 7010.6436 | Z52: 6503.66 | AC52: 6582.0274 | AF52: 7870.6385 | AI52: 6698.0432 | AL52: 6190.2803 | AO52: 6515.007
A53: =+$C$4&B53 -> Véhicules neufsDéduction à la source | B53: Déduction à la source | E53: 110380.2 | H53: 6731.5252 | K53: 7057.18 | N53: 11311.602 | Q53: 11970.581 | T53: 11311.44 | W53: 9178.4255 | Z53: 8451.6044 | AC53: 9337.2132 | AF53: 10151.685 | AI53: 8556.633 | AL53: 8584.8835 | AO53: 7737.4293
A54: =+$C$4&B54 -> Véhicules neufsBénéfices marginaux | B54: Bénéfices marginaux | E54: 51053.689 | H54: 3068.7836 | K54: 3217.2438 | N54: 5156.7597 | Q54: 5457.1765 | T54: 5194.8838 | W54: 4215.2769 | Z54: 3910.4438 | AC54: 4320.2031 | AF54: 4732.3645 | AI54: 4027.3203 | AL54: 4063.0746 | AO54: 3690.1586
A55: =+$C$4&B55 -> Véhicules neufsCsst | B55: Csst | E55: 11528.252 | H55: 692.95113 | K55: 726.47442 | N55: 1164.4296 | Q55: 1232.2657 | T55: 1173.0383 | W55: 951.83672 | Z55: 883.00344 | AC55: 975.52974 | AF55: 1068.5984 | AI55: 909.3949 | AL55: 917.46847 | AO55: 833.26161
A56: =+$C$4&B56 -> Véhicules neufs[...] | B56: [...] | E56: 0
A57: =+$C$4&B57 -> Véhicules neufsTOTAL PERSONNEL | B57: TOTAL PERSONNEL | C57: % brut | D57: 0.29427094 | E57: 514577.17 | F57: % brut | G57: 0.56052128 | H57: 37913.526 | I57: % brut | J57: 0.44354087 | K57: 37034.269 | L57: % brut | M57: 0.22750003 | N57: 46621.103 | O57: % brut | P57: 0.22379571 | Q57: 49355.513 | R57: % brut | S57: 0.24104328 | T57: 48426.247 | U57: % brut | V57: 0.2814542 | W57: 42000.308 | X57: % brut | Y57: 0.34775091 | Z57: 41855.718 | AA57: % brut | AB57: 0.28691035 | AC57: 42834.353 | AD57: % brut | AE57: 0.25214004 | AF57: 44955.039 | AG57: % brut | AH57: 0.33126845 | AI57: 42298.398 | AJ57: % brut | AK57: 0.29959076 | AL57: 40887.459 | AM57: % brut | AN57: 0.36788096 | AO57: 40395.236
A58: =+$C$4&B58 -> Véhicules neufsPublicité 2 | B58: Publicité 2 | E58: 0 | H58: 0 | K58: 0 | N58: 0 | Q58: 0 | T58: 0 | W58: 0 | Z58: 0 | AC58: 0 | AF58: 0 | AI58: 0 | AL58: 0 | AO58: 0
A59: =+$C$4&B59 -> Véhicules neufsService gratuit 2 | B59: Service gratuit 2 | E59: 0 | H59: 0 | K59: 0 | N59: 0 | Q59: 0 | T59: 0 | W59: 0 | Z59: 0 | AC59: 0 | AF59: 0 | AI59: 0 | AL59: 0 | AO59: 0
A60: =+$C$4&B60 -> Véhicules neufsFrais véhicules de cie | B60: Frais véhicules de cie | E60: 60961 | H60: 5080.0833 | K60: 5080.0833 | N60: 5080.0833 | Q60: 5080.0833 | T60: 5080.0833 | W60: 5080.0833 | Z60: 5080.0833 | AC60: 5080.0833 | AF60: 5080.0833 | AI60: 5080.0833 | AL60: 5080.0833 | AO60: 5080.0833
A61: =+$C$4&B61 -> Véhicules neufsInformatique | B61: Informatique | E61: 59916.6 | H61: 4993.05 | K61: 4993.05 | N61: 4993.05 | Q61: 4993.05 | T61: 4993.05 | W61: 4993.05 | Z61: 4993.05 | AC61: 4993.05 | AF61: 4993.05 | AI61: 4993.05 | AL61: 4993.05 | AO61: 4993.05
A62: =+$C$4&B62 -> Véhicules neufsFrais de déplacement | B62: Frais de déplacement | E62: 9871.2 | H62: 822.6 | K62: 822.6 | N62: 822.6 | Q62: 822.6 | T62: 822.6 | W62: 822.6 | Z62: 822.6 | AC62: 822.6 | AF62: 822.6 | AI62: 822.6 | AL62: 822.6 | AO62: 822.6
A63: =+$C$4&B63 -> Véhicules neufsServices extérieurs | B63: Services extérieurs | E63: 33053.4 | H63: 2754.45 | K63: 2754.45 | N63: 2754.45 | Q63: 2754.45 | T63: 2754.45 | W63: 2754.45 | Z63: 2754.45 | AC63: 2754.45 | AF63: 2754.45 | AI63: 2754.45 | AL63: 2754.45 | AO63: 2754.45
A64: =+$C$4&B64 -> Véhicules neufsFournitures autres | B64: Fournitures autres | E64: 800 | H64: 31.25 | K64: 37.5 | N64: 93.75 | Q64: 100 | T64: 90.625 | W64: 68.75 | Z64: 56.25 | AC64: 68.75 | AF64: 81.25 | AI64: 59.375 | AL64: 62.5 | AO64: 50
A65: =+$C$4&B65 -> Véhicules neufsUniformes | B65: Uniformes | E65: 180 | H65: 15 | K65: 15 | N65: 15 | Q65: 15 | T65: 15 | W65: 15 | Z65: 15 | AC65: 15 | AF65: 15 | AI65: 15 | AL65: 15 | AO65: 15
A66: =+$C$4&B66 -> Véhicules neufsPapeterie | B66: Papeterie | E66: 9450 | H66: 787.5 | K66: 787.5 | N66: 787.5 | Q66: 787.5 | T66: 787.5 | W66: 787.5 | Z66: 787.5 | AC66: 787.5 | AF66: 787.5 | AI66: 787.5 | AL66: 787.5 | AO66: 787.5
A67: =+$C$4&B67 -> Véhicules neufsTéléphone | B67: Téléphone | E67: 2524.8 | H67: 210.4 | K67: 210.4 | N67: 210.4 | Q67: 210.4 | T67: 210.4 | W67: 210.4 | Z67: 210.4 | AC67: 210.4 | AF67: 210.4 | AI67: 210.4 | AL67: 210.4 | AO67: 210.4
A68: =+$C$4&B68 -> Véhicules neufsFrais postaux | B68: Frais postaux | E68: 2700 | H68: 225 | K68: 225 | N68: 225 | Q68: 225 | T68: 225 | W68: 225 | Z68: 225 | AC68: 225 | AF68: 225 | AI68: 225 | AL68: 225 | AO68: 225
A69: =+$C$4&B69 -> Véhicules neufsDivers | B69: Divers | E69: 10033.2 | H69: 836.1 | K69: 836.1 | N69: 836.1 | Q69: 836.1 | T69: 836.1 | W69: 836.1 | Z69: 836.1 | AC69: 836.1 | AF69: 836.1 | AI69: 836.1 | AL69: 836.1 | AO69: 836.1
... A71: =+$C$4&B71 -> Véhicules neufsFrais bancaires | B71: Frais bancaires | E71: 30702.743 | H71: 1297.6436 | K71: 1615.3007 | N71: 3073.998 | Q71: 3524.2641 | T71: 3588.6372 | W71: 2782.081 | Z71: 2461.5447 | AC71: 2783.4464 | AF71: 3014.984 | AI71: 2360.8114 | AL71: 2428.5129 | AO71: 1771.5186
A72: =+$C$4&B72 -> Véhicules neufs[...] | B72: [...] | E72: 0
A73: =+$C$4&B73 -> Véhicules neufs[...] | B73: [...] | E73: 0
A74: =+$C$4&B74 -> Véhicules neufs[...] | B74: [...] | E74: 0
A75: =+$C$4&B75 -> Véhicules neufsTOTAL SEMI-FIXES | B75: TOTAL SEMI-FIXES | C75: % brut | D75: 0.12923042 | E75: 225978.91 | F75: % brut | G75: 0.25924456 | H75: 17535.241 | I75: % brut | J75: 0.21389006 | K75: 17859.148 | L75: % brut | M75: 0.094541032 | N75: 19374.095 | O75: % brut | P75: 0.089919151 | Q75: 19830.611 | R75: % brut | S75: 0.098981291 | T75: 19885.609 | U75: % brut | V75: 0.12770675 | W75: 19057.178 | X75: % brut | Y75: 0.15556625 | Z75: 18724.142 | AA75: % brut | AB75: 0.12765673 | AC75: 19058.544 | AD75: % brut | AE75: 0.10826269 | AF75: 19302.581 | AG75: % brut | AH75: 0.14587746 | AI75: 18626.534 | AJ75: % brut | AK75: 0.13699937 | AL75: 18697.36 | AM75: % brut | AN75: 0.16418046 | AO75: 18027.866
A76: =+$C$4&B76 -> Véhicules neufs
A77: =+$C$4&B77 -> Véhicules neufsTOTAL DES DÉPENSES | B77: TOTAL DES DÉPENSES | C77: % brut | D77: 0.98469034 | E77: 1721879.7 | F77: % brut | G77: 1.5530817 | H77: 105050.08 | I77: % brut | J77: 1.3508053 | K77: 112787.99 | L77: % brut | M77: 0.84936994 | N77: 174059.6 | O77: % brut | P77: 0.82296062 | Q77: 181494.29 | R77: % brut | S77: 0.85668609 | T77: 172110.55 | U77: % brut | V77: 0.95677578 | W77: 142775.91 | X77: % brut | Y77: 1.1081821 | Z77: 133382.13 | AA77: % brut | AB77: 0.98345801 | AC77: 146825.61 | AD77: % brut | AE77: 0.88438329 | AF77: 157680.18 | AG77: % brut | AH77: 1.0655978 | AI77: 136062.09 | AJ77: % brut | AK77: 0.99561475 | AL77: 135879.22 | AM77: % brut | AN77: 1.1271972 | AO77: 123772.09
A78: =+$C$4&B78 -> Véhicules neufsRBSC neuf | B78: RBSC neuf | E78: 378571.48 | H78: 14560.442 | K78: 17472.53 | N78: 45137.369 | Q78: 48049.457 | T78: 43681.325 | W78: 32032.971 | Z78: 26208.795 | AC78: 32032.971 | AF78: 39313.192 | AI78: 27664.839 | AL78: 29120.883 | AO78: 23296.706
A79: =+$C$4&B79 -> Véhicules neufsProgramme neuf 2 | B79: Programme neuf 2 | E79: 0 | H79: 0 | K79: 0 | N79: 0 | Q79: 0 | T79: 0 | W79: 0 | Z79: 0 | AC79: 0 | AF79: 0 | AI79: 0 | AL79: 0 | AO79: 0
A80: =+$C$4&B80 -> Véhicules neufsProgramme neuf 3 | B80: Programme neuf 3 | E80: 0 | H80: 0 | K80: 0 | N80: 0 | Q80: 0 | T80: 0 | W80: 0 | Z80: 0 | AC80: 0 | AF80: 0 | AI80: 0 | AL80: 0 | AO80: 0
A81: =+$C$4&B81 -> Véhicules neufsHoldbacks | B81: Holdbacks | E81: 432653.12 | H81: 16640.505 | K81: 19968.606 | N81: 51585.564 | Q81: 54913.665 | T81: 49921.514 | W81: 36609.11 | Z81: 29952.908 | AC81: 36609.11 | AF81: 44929.362 | AI81: 31616.959 | AL81: 33281.009 | AO81: 26624.807
A82: =+$C$4&B82 -> Véhicules neufs[...] | B82: [...] | E82: 0 | H82: 0 | K82: 0 | N82: 0 | Q82: 0 | T82: 0 | W82: 0 | Z82: 0 | AC82: 0 | AF82: 0 | AI82: 0 | AL82: 0 | AO82: 0
A83: =+$C$4&B83 -> Véhicules neufs[...] | B83: [...] | E83: 0 | H83: 0 | K83: 0 | N83: 0 | Q83: 0 | T83: 0 | W83: 0 | Z83: 0 | AC83: 0 | AF83: 0 | AI83: 0 | AL83: 0 | AO83: 0
A84: =+$C$4&B84 -> Véhicules neufs[...] | B84: [...] | E84: 0 | H84: 0 | K84: 0 | N84: 0 | Q84: 0 | T84: 0 | W84: 0 | Z84: 0 | AC84: 0 | AF84: 0 | AI84: 0 | AL84: 0 | AO84: 0
A85: =+$C$4&B85 -> Véhicules neufsFrais administration | B85: Frais administration | E85: 150796.8 | H85: 5890.5 | K85: 7068.6 | N85: 17671.5 | Q85: 18849.6 | T85: 17082.45 | W85: 12959.1 | Z85: 10602.9 | AC85: 12959.1 | AF85: 15315.3 | AI85: 11191.95 | AL85: 11781 | AO85: 9424.8
A86: =+$C$4&B86 -> Véhicules neufsAUTRES REVENUS | B86: AUTRES REVENUS | E86: 962021.4 | H86: 37091.446 | K86: 44509.735 | N86: 114394.43 | Q86: 121812.72 | T86: 110685.29 | W86: 81601.182 | Z86: 66764.603 | AC86: 81601.182 | AF86: 99557.855 | AI86: 70473.748 | AL86: 74182.892 | AO86: 59346.314
A87: =+$C$4&B87 -> Véhicules neufs
A88: =+$C$4&B88 -> Véhicules neufsPROFIT DÉPARTEMENTAL | B88: PROFIT DÉPARTEMENTAL | E88: 988792.66 | H88: -318.87182 | K88: 15218.599 | N88: 145262.73 | Q88: 160856.68 | T88: 139477.44 | W88: 88051.362 | Z88: 53743.674 | AC88: 84070.821 | AF88: 120171.61 | AI88: 62097.821 | AL88: 74781.382 | AO88: 45379.407
B92: Budget 2024 | C92: Véhicules usagés
B94: Mois | C94: 2024 | F94: Janvier | I94: Février | L94: Mars | O94: Avril | R94: Mai | U94: Juin | X94: Juillet | AA94: Août | AD94: Septembre | AG94: Octobre | AJ94: Novembre | AM94: Décembre
C95: UNITE | D95: $P/UNITE | E95: $PROFITS | F95: UNITE | G95: $P/UNITE | H95: $PROFITS | I95: UNITE | J95: $P/UNITE | K95: $PROFITS | L95: UNITE | M95: $P/UNITE | N95: $PROFITS | O95: UNITE | P95: $P/UNITE | Q95: $PROFITS | R95: UNITE | S95: $P/UNITE | T95: $PROFITS | U95: UNITE | V95: $P/UNITE | W95: $PROFITS | X95: UNITE | Y95: $P/UNITE | Z95: $PROFITS | AA95: UNITE | AB95: $P/UNITE | AC95: $PROFITS | AD95: UNITE | AE95: $P/UNITE | AF95: $PROFITS | AG95: UNITE | AH95: $P/UNITE | AI95: $PROFITS | AJ95: UNITE | AK95: $P/UNITE | AL95: $PROFITS | AM95: UNITE | AN95: $P/UNITE | AO95: $PROFITS
A96: =+$C$92&B96 -> Véhicules usagésVentes nettes | B96: Ventes nettes | E96: 16032345 | H96: 716603.45 | K96: 912137.93 | N96: 1274517.2 | Q96: 1661741.4 | T96: 1890275.9 | W96: 1628741.4 | Z96: 1593896.6 | AC96: 1661741.4 | AF96: 1560896.6 | AI96: 1241517.2 | AL96: 1103827.6 | AO96: 786448.28
A97: =+$C$92&B97 -> Véhicules usagésCertifié | B97: Certifié | C97: 68 | D97: 3000 | E97: 204000 | F97: 3 | G97: 3000 | H97: 9000 | I97: 4 | J97: 3000 | K97: 12000 | L97: 5 | M97: 3000 | N97: 15000 | O97: 7 | P97: 3000 | Q97: 21000 | R97: 8 | S97: 3000 | T97: 24000 | U97: 7 | V97: 3000 | W97: 21000 | X97: 7 | Y97: 3000 | Z97: 21000 | AA97: 7 | AB97: 3000 | AC97: 21000 | AD97: 7 | AE97: 3000 | AF97: 21000 | AG97: 5 | AH97: 3000 | AI97: 15000 | AJ97: 5 | AK97: 3000 | AL97: 15000 | AM97: 3 | AN97: 3000 | AO97: 9000
A98: =+$C$92&B98 -> Véhicules usagésNon Certifié | B98: Non Certifié | C98: 50 | D98: 2200 | E98: 110000 | F98: 2 | G98: 2200 | H98: 4400 | I98: 3 | J98: 2200 | K98: 6600 | L98: 4 | M98: 2200 | N98: 8800 | O98: 5 | P98: 2200 | Q98: 11000 | R98: 6 | S98: 2200 | T98: 13200 | U98: 5 | V98: 2200 | W98: 11000 | X98: 5 | Y98: 2200 | Z98: 11000 | AA98: 5 | AB98: 2200 | AC98: 11000 | AD98: 5 | AE98: 2200 | AF98: 11000 | AG98: 4 | AH98: 2200 | AI98: 8800 | AJ98: 3 | AK98: 2200 | AL98: 6600 | AM98: 3 | AN98: 2200 | AO98: 6600
A99: =+$C$92&B99 -> Véhicules usagésAutres Marques | B99: Autres Marques | C99: 86 | D99: 1850 | E99: 159100 | F99: 4 | G99: 1850 | H99: 7400 | I99: 5 | J99: 1850 | K99: 9250 | L99: 7 | M99: 1850 | N99: 12950 | O99: 9 | P99: 1850 | Q99: 16650 | R99: 10 | S99: 1850 | T99: 18500 | U99: 9 | V99: 1850 | W99: 16650 | X99: 8 | Y99: 1850 | Z99: 14800 | AA99: 9 | AB99: 1850 | AC99: 16650 | AD99: 8 | AE99: 1850 | AF99: 14800 | AG99: 7 | AH99: 1850 | AI99: 12950 | AJ99: 6 | AK99: 1850 | AL99: 11100 | AM99: 4 | AN99: 1850 | AO99: 7400
A100: =+$C$92&B100 -> Véhicules usagésTotal Usagés | B100: Total Usagés | C100: 204 | D100: 2319.1176 | E100: 473100 | F100: 9 | G100: 2311.1111 | H100: 20800 | I100: 12 | J100: 2320.8333 | K100: 27850 | L100: 16 | M100: 2296.875 | N100: 36750 | O100: 21 | P100: 2316.6667 | Q100: 48650 | R100: 24 | S100: 2320.8333 | T100: 55700 | U100: 21 | V100: 2316.6667 | W100: 48650 | X100: 20 | Y100: 2340 | Z100: 46800 | AA100: 21 | AB100: 2316.6667 | AC100: 48650 | AD100: 20 | AE100: 2340 | AF100: 46800 | AG100: 16 | AH100: 2296.875 | AI100: 36750 | AJ100: 14 | AK100: 2335.7143 | AL100: 32700 | AM100: 10 | AN100: 2300 | AO100: 23000
A101: =+$C$92&B101 -> Véhicules usagés
A102: =+$C$92&B102 -> Véhicules usagés | F102: 0 | H102: 0
A103: =+$C$92&B103 -> Véhicules usagésVentes au Gros | B103: Ventes au Gros | C103: 220 | D103: 375 | E103: 82500 | F103: 10 | G103: 375 | H103: 3750 | I103: 12 | J103: 375 | K103: 4500 | L103: 18 | M103: 375 | N103: 6750 | O103: 23 | P103: 375 | Q103: 8625 | R103: 26 | S103: 375 | T103: 9750 | U103: 22 | V103: 375 | W103: 8250 | X103: 22 | Y103: 375 | Z103: 8250 | AA103: 23 | AB103: 375 | AC103: 8625 | AD103: 21 | AE103: 375 | AF103: 7875 | AG103: 17 | AH103: 375 | AI103: 6375 | AJ103: 15 | AK103: 375 | AL103: 5625 | AM103: 11 | AN103: 375 | AO103: 4125
A104: =+$C$92&B104 -> Véhicules usagés
A105: =+$C$92&B105 -> Véhicules usagésRev. Finances | B105: Rev. Finances | D105: 600 | E105: 122400 | G105: 600 | H105: 5400 | J105: 600 | K105: 7200 | M105: 600 | N105: 9600 | P105: 600 | Q105: 12600 | S105: 600 | T105: 14400 | V105: 600 | W105: 12600 | Y105: 600 | Z105: 12000 | AB105: 600 | AC105: 12600 | AE105: 600 | AF105: 12000 | AH105: 600 | AI105: 9600 | AK105: 600 | AL105: 8400 | AN105: 600 | AO105: 6000
A106: =+$C$92&B106 -> Véhicules usagésRev. Protections | B106: Rev. Protections | D106: 880 | E106: 179520 | G106: 880 | H106: 7920 | J106: 880 | K106: 10560 | M106: 880 | N106: 14080 | P106: 880 | Q106: 18480 | S106: 880 | T106: 21120 | V106: 880 | W106: 18480 | Y106: 880 | Z106: 17600 | AB106: 880 | AC106: 18480 | AE106: 880 | AF106: 17600 | AH106: 880 | AI106: 14080 | AK106: 880 | AL106: 12320 | AN106: 880 | AO106: 8800
...

Sheet Réel 2023
B1: ="Budget 2023 Mensuel"&" "&Parametres!$B$1 -> Budget 2023 Mensuel BMW Sherbrooke
B2: Mois | F2: =+IF(Parametres!$B$3=F$6,"X","") | G2: =+IF(Parametres!$B$3=F$6,"O","") | H2: =+IF(Parametres!$B$3=F$6,"U","") | I2: =+IF(Parametres!$B$3=I$6,"X","") | J2: =+IF(Parametres!$B$3=I$6,"O","") | K2: =+IF(Parametres!$B$3=I$6,"U","") | L2: =+IF(Parametres!$B$3=L$6,"X","") | M2: =+IF(Parametres!$B$3=L$6,"O","") | N2: =+IF(Parametres!$B$3=L$6,"U","") | O2: =+IF(Parametres!$B$3=O$6,"X","") -> X | P2: =+IF(Parametres!$B$3=O$6,"O","") -> O | Q2: =+IF(Parametres!$B$3=O$6,"U","") -> U | R2: =+IF(Parametres!$B$3=R$6,"X","") | S2: =+IF(Parametres!$B$3=R$6,"O","") | T2: =+IF(Parametres!$B$3=R$6,"U","") | U2: =+IF(Parametres!$B$3=U$6,"X","") | V2: =+IF(Parametres!$B$3=U$6,"O","") | W2: =+IF(Parametres!$B$3=U$6,"U","") | X2: =+IF(Parametres!$B$3=X$6,"X","") | Y2: =+IF(Parametres!$B$3=X$6,"O","") | Z2: =+IF(Parametres!$B$3=X$6,"U","") | AA2: =+IF(Parametres!$B$3=AA$6,"X","") | AB2: =+IF(Parametres!$B$3=AA$6,"O","") | AC2: =+IF(Parametres!$B$3=AA$6,"U","") | AD2: =+IF(Parametres!$B$3=AD$6,"X","") | AE2: =+IF(Parametres!$B$3=AD$6,"O","") | AF2: =+IF(Parametres!$B$3=AD$6,"U","") | AG2: =+IF(Parametres!$B$3=AG$6,"X","") | AH2: =+IF(Parametres!$B$3=AG$6,"O","") | AI2: =+IF(Parametres!$B$3=AG$6,"U","") | AJ2: =+IF(Parametres!$B$3=AJ$6,"X","") | AK2: =+IF(Parametres!$B$3=AJ$6,"O","") | AL2: =+IF(Parametres!$B$3=AJ$6,"U","") | AM2: =+IF(Parametres!$B$3=AM$6,"X","") | AN2: =+IF(Parametres!$B$3=AM$6,"O","") | AO2: =+IF(Parametres!$B$3=AM$6,"U","")
B3: YTD | F3: =+IF(VLOOKUP(F$6,Parametres!$K$3:$N$14,4,0)="X","X","") -> X | G3: =+IF(VLOOKUP(F$6,Parametres!$K$3:$N$14,4,0)="X","O","") -> O | H3: =+IF(VLOOKUP(F$6,Parametres!$K$3:$N$14,4,0)="X","U","") -> U | I3: =+IF(VLOOKUP(I$6,Parametres!$K$3:$N$14,4,0)="X","X","") -> X | J3: =+IF(VLOOKUP(I$6,Parametres!$K$3:$N$14,4,0)="X","O","") -> O | K3: =+IF(VLOOKUP(I$6,Parametres!$K$3:$N$14,4,0)="X","U","") -> U | L3: =+IF(VLOOKUP(L$6,Parametres!$K$3:$N$14,4,0)="X","X","") -> X | M3: =+IF(VLOOKUP(L$6,Parametres!$K$3:$N$14,4,0)="X","O","") -> O | N3: =+IF(VLOOKUP(L$6,Parametres!$K$3:$N$14,4,0)="X","U","") -> U | O3: =+IF(VLOOKUP(O$6,Parametres!$K$3:$N$14,4,0)="X","X","") -> X | P3: =+IF(VLOOKUP(O$6,Parametres!$K$3:$N$14,4,0)="X","O","") -> O | Q3: =+IF(VLOOKUP(O$6,Parametres!$K$3:$N$14,4,0)="X","U","") -> U | R3: =+IF(VLOOKUP(R$6,Parametres!$K$3:$N$14,4,0)="X","X","") | S3: =+IF(VLOOKUP(R$6,Parametres!$K$3:$N$14,4,0)="X","O","") | T3: =+IF(VLOOKUP(R$6,Parametres!$K$3:$N$14,4,0)="X","U","") | U3: =+IF(VLOOKUP(U$6,Parametres!$K$3:$N$14,4,0)="X","X","") | V3: =+IF(VLOOKUP(U$6,Parametres!$K$3:$N$14,4,0)="X","O","") | W3: =+IF(VLOOKUP(U$6,Parametres!$K$3:$N$14,4,0)="X","U","") | X3: =+IF(VLOOKUP(X$6,Parametres!$K$3:$N$14,4,0)="X","X","") | Y3: =+IF(VLOOKUP(X$6,Parametres!$K$3:$N$14,4,0)="X","O","") | Z3: =+IF(VLOOKUP(X$6,Parametres!$K$3:$N$14,4,0)="X","U","") | AA3: =+IF(VLOOKUP(AA$6,Parametres!$K$3:$N$14,4,0)="X","X","") | AB3: =+IF(VLOOKUP(AA$6,Parametres!$K$3:$N$14,4,0)="X","O","") | AC3: =+IF(VLOOKUP(AA$6,Parametres!$K$3:$N$14,4,0)="X","U","") | AD3: =+IF(VLOOKUP(AD$6,Parametres!$K$3:$N$14,4,0)="X","X","") | AE3: =+IF(VLOOKUP(AD$6,Parametres!$K$3:$N$14,4,0)="X","O","") | AF3: =+IF(VLOOKUP(AD$6,Parametres!$K$3:$N$14,4,0)="X","U","") | AG3: =+IF(VLOOKUP(AG$6,Parametres!$K$3:$N$14,4,0)="X","X","") | AH3: =+IF(VLOOKUP(AG$6,Parametres!$K$3:$N$14,4,0)="X","O","") | AI3: =+IF(VLOOKUP(AG$6,Parametres!$K$3:$N$14,4,0)="X","U","") | AJ3: =+IF(VLOOKUP(AJ$6,Parametres!$K$3:$N$14,4,0)="X","X","") | AK3: =+IF(VLOOKUP(AJ$6,Parametres!$K$3:$N$14,4,0)="X","O","") | AL3: =+IF(VLOOKUP(AJ$6,Parametres!$K$3:$N$14,4,0)="X","U","") | AM3: =+IF(VLOOKUP(AM$6,Parametres!$K$3:$N$14,4,0)="X","X","") | AN3: =+IF(VLOOKUP(AM$6,Parametres!$K$3:$N$14,4,0)="X","O","") | AO3: =+IF(VLOOKUP(AM$6,Parametres!$K$3:$N$14,4,0)="X","U","")
B4: Réel 2023 | C4: Véhicules neufs
B6: Mois | C6: 2023 | F6: Janvier | I6: Février | L6: Mars | O6: Avril | R6: Mai | U6: Juin | X6: Juillet | AA6: Août | AD6: Septembre | AG6: Octobre | AJ6: Novembre | AM6: Décembre
C7: UNITE | D7: $P/UNITE | E7: $PROFITS | F7: UNITE | G7: $P/UNITE | H7: $PROFITS | I7: UNITE | J7: $P/UNITE | K7: $PROFITS | L7: UNITE | M7: $P/UNITE | N7: $PROFITS | O7: UNITE | P7: $P/UNITE | Q7: $PROFITS | R7: UNITE | S7: $P/UNITE | T7: $PROFITS | U7: UNITE | V7: $P/UNITE | W7: $PROFITS | X7: UNITE | Y7: $P/UNITE | Z7: $PROFITS | AA7: UNITE | AB7: $P/UNITE | AC7: $PROFITS | AD7: UNITE | AE7: $P/UNITE | AF7: $PROFITS | AG7: UNITE | AH7: $P/UNITE | AI7: $PROFITS | AJ7: UNITE | AK7: $P/UNITE | AL7: $PROFITS | AM7: UNITE | AN7: $P/UNITE | AO7: $PROFITS
A8: =+$C$4&B8 -> Véhicules neufsVentes nettes | B8: Ventes nettes | E8: 44786734 | H8: 1359610 | K8: 788251.23 | N8: 2739760.8 | Q8: 2399882.7 | T8: 3061839.7 | W8: 1791786.6 | Z8: 1070672.8 | AC8: 2532428.1 | AF8: 2506516.8 | AI8: 8285274.9 | AL8: 10151414 | AO8: 8099296.2
A9: =+$C$4&B9 -> Véhicules neufsAutos détail | B9: Autos détail | C9: 86 | D9: 5345.9624 | E9: 459752.77 | F9: 4 | G9: 5270.98 | H9: 21083.92 | I9: 4 | J9: 3943.36 | K9: 15773.44 | L9: 9 | M9: 5970.7556 | N9: 53736.8 | O9: 9 | P9: 6333.3722 | Q9: 57000.35 | R9: 12 | S9: 4855.6392 | T9: 58267.67 | U9: 5 | V9: 5865.958 | W9: 29329.79 | X9: 2 | Y9: 4970.88 | Z9: 9941.76 | AA9: 9 | AB9: 5589.2289 | AC9: 50303.06 | AD9: 7 | AE9: 5593.4486 | AF9: 39154.14 | AG9: 5 | AH9: 4279.278 | AI9: 21396.39 | AJ9: 14 | AK9: 5054.9321 | AL9: 70769.05 | AM9: 6 | AN9: 5499.4 | AO9: 32996.4
A10: =+$C$4&B10 -> Véhicules neufsCamions détail | B10: Camions détail | C10: 136 | D10: 5686.1199 | E10: 773312.31 | F10: 6 | G10: 4340.0667 | H10: 26040.4 | I10: 4 | J10: 4483.6225 | K10: 17934.49 | L10: 15 | M10: 6103.068 | N10: 91546.02 | O10: 14 | P10: 6103.68 | Q10: 85451.52 | R10: 16 | S10: 5055.2144 | T10: 80883.43 | U10: 13 | V10: 5473.6615 | W10: 71157.6 | X10: 9 | Y10: 5731.4567 | Z10: 51583.11 | AA10: 14 | AB10: 5896.9686 | AC10: 82557.56 | AD10: 17 | AE10: 7536.4665 | AF10: 128119.93 | AG10: 13 | AH10: 4990.9962 | AI10: 64882.95 | AJ10: 8 | AK10: 4481.7612 | AL10: 35854.09 | AM10: 7 | AN10: 5328.7443 | AO10: 37301.21
A11: =+$C$4&B11 -> Véhicules neufsSprinter | B11: Sprinter | C11: 0 | D11: 0 | E11: 0 | F11: 0 | G11: 0 | H11: 0 | I11: 0 | J11: 0 | K11: 0 | L11: 0 | M11: 0 | N11: 0 | O11: 0 | P11: 0 | Q11: 0 | R11: 0 | S11: 0 | T11: 0 | U11: 0 | V11: 0 | W11: 0 | X11: 0 | Y11: 0 | Z11: 0 | AA11: 0 | AB11: 0 | AC11: 0 | AD11: 0 | AE11: 0 | AF11: 0 | AG11: 0 | AH11: 0 | AI11: 0 | AJ11: 0 | AK11: 0 | AL11: 0 | AM11: 0 | AN11: 0 | AO11: 0
A12: =+$C$4&B12 -> Véhicules neufsMoto détail | B12: Moto détail | C12: 0 | D12: 0 | E12: 0 | F12: 0 | G12: 0 | H12: 0 | I12: 0 | J12: 0 | K12: 0 | L12: 0 | M12: 0 | N12: 0 | O12: 0 | P12: 0 | Q12: 0 | R12: 0 | S12: 0 | T12: 0 | U12: 0 | V12: 0 | W12: 0 | X12: 0 | Y12: 0 | Z12: 0 | AA12: 0 | AB12: 0 | AC12: 0 | AD12: 0 | AE12: 0 | AF12: 0 | AG12: 0 | AH12: 0 | AI12: 0 | AJ12: 0 | AK12: 0 | AL12: 0 | AM12: 0 | AN12: 0 | AO12: 0
A13: =+$C$4&B13 -> Véhicules neufs[...] | B13: [...] | C13: 0 | D13: 0 | E13: 0 | G13: 0 | J13: 0 | M13: 0 | P13: 0 | S13: 0 | V13: 0 | Y13: 0 | AB13: 0 | AE13: 0 | AH13: 0 | AK13: 0 | AN13: 0
A14: =+$C$4&B14 -> Véhicules neufs[...] | B14: [...] | C14: 0 | D14: 0 | E14: 0 | G14: 0 | J14: 0 | M14: 0 | P14: 0 | S14: 0 | V14: 0 | Y14: 0 | AB14: 0 | AE14: 0 | AH14: 0 | AK14: 0 | AN14: 0
A15: =+$C$4&B15 -> Véhicules neufs[...] | B15: [...] | C15: 0 | D15: 0 | E15: 0 | G15: 0 | J15: 0 | M15: 0 | P15: 0 | S15: 0 | V15: 0 | Y15: 0 | AB15: 0 | AE15: 0 | AH15: 0 | AK15: 0 | AN15: 0
A16: =+$C$4&B16 -> Véhicules neufsTotal Neufs | B16: Total Neufs | C16: 222 | D16: 5554.3472 | E16: 1233065.1 | F16: 10 | G16: 4712.432 | H16: 47124.32 | I16: 8 | J16: 4213.4913 | K16: 33707.93 | L16: 24 | M16: 6053.4508 | N16: 145282.82 | O16: 23 | P16: 6193.5596 | Q16: 142451.87 | R16: 28 | S16: 4969.6821 | T16: 139151.1 | U16: 18 | V16: 5582.6328 | W16: 100487.39 | X16: 11 | Y16: 5593.17 | Z16: 61524.87 | AA16: 23 | AB16: 5776.5487 | AC16: 132860.62 | AD16: 24 | AE16: 6969.7529 | AF16: 167274.07 | AG16: 18 | AH16: 4793.2967 | AI16: 86279.34 | AJ16: 22 | AK16: 4846.5064 | AL16: 106623.14 | AM16: 13 | AN16: 5407.5085 | AO16: 70297.61
A17: =+$C$4&B17 -> Véhicules neufs
A18: =+$C$4&B18 -> Véhicules neufsEx-Démos et courtoisies | B18: Ex-Démos et courtoisies | C18: 21 | D18: 2993.8876 | E18: 62871.64 | F18: 2 | G18: 2750 | H18: 5500 | I18: 0 | J18: 0 | K18: 0 | L18: 1 | M18: 2500 | N18: 2500 | O18: 0 | P18: 0 | Q18: 0 | R18: 4 | S18: 5079.2875 | T18: 20317.15 | U18: 2 | V18: 5000 | W18: 10000 | X18: 2 | Y18: 7404.6 | Z18: 14809.2 | AA18: 3 | AB18: 2568.3867 | AC18: 7705.16 | AD18: 0 | AE18: 0 | AF18: -558.61 | AG18: 4 | AH18: 3882.6525 | AI18: 15530.61 | AJ18: 0 | AK18: 0 | AL18: -150 | AM18: 3 | AN18: -4260.6233 | AO18: -12781.87
A19: =+$C$4&B19 -> Véhicules neufs
A20: =+$C$4&B20 -> Véhicules neufsFlottes | B20: Flottes | C20: 4 | D20: 3136.3025 | E20: 12545.21 | F20: 1 | G20: 0 | H20: 0 | I20: 0 | J20: 0 | K20: 0 | L20: 2 | M20: 3453.48 | N20: 6906.96 | O20: 1 | P20: 5638.25 | Q20: 5638.25 | R20: 0 | S20: 0 | T20: 0 | U20: 0 | V20: 0 | W20: 0 | X20: 0 | Y20: 0 | Z20: 0 | AA20: 0 | AB20: 0 | AC20: 0 | AD20: 0 | AE20: 0 | AF20: 0 | AG20: 0 | AH20: 0 | AI20: 0 | AJ20: 0 | AK20: 0 | AL20: 0 | AM20: 0 | AN20: 0 | AO20: 0
A21: =+$C$4&B21 -> Véhicules neufs
A22: =+$C$4&B22 -> Véhicules neufsRachat bail | B22: Rachat bail | E22: 83269.17 | H22: 6793 | K22: 2996.96 | N22: 7991.96 | Q22: 8990.92 | T22: 8515.33 | W22: 9990 | Z22: 3486 | AC22: 9990 | AF22: 3996 | AI22: 4995 | AL22: 6029 | AO22: 9495
A23: =+$C$4&B23 -> Véhicules neufs
A24: =+$C$4&B24 -> Véhicules neufsRev. Finances | B24: Rev. Finances | D24: 65.425844 | E24: 15898.48 | G24: 117.1225 | H24: 1405.47 | J24: 0 | K24: 0 | M24: 16 | N24: 400 | P24: 47.826087 | Q24: 1100 | S24: 252.4375 | T24: 8078 | V24: 0 | W24: 0 | Y24: 17.089231 | Z24: 222.16 | AB24: 169.18077 | AC24: 4398.7 | AE24: -4.1666667 | AF24: -100 | AH24: 0 | AI24: 0 | AK24: 17.915909 | AL24: 394.15 | AN24: 0 | AO24: 0
A25: =+$C$4&B25 -> Véhicules neufsRev. Protections | B25: Rev. Protections | D25: 1042.7458 | E25: 253387.23 | G25: 1740 | H25: 20880 | J25: 504.29125 | K25: 4034.33 | M25: 798.16 | N25: 19954 | P25: 1404.4491 | Q25: 32302.33 | S25: 1132.4553 | T25: 36238.57 | V25: 993.7 | W25: 19874 | Y25: 1323.3077 | Z25: 17203 | AB25: 857.69231 | AC25: 22300 | AE25: 505.83333 | AF25: 12140 | AH25: 1077.7273 | AI25: 23710 | AK25: 1069.5 | AL25: 23529 | AN25: 1326.375 | AO25: 21222
A26: =+$C$4&B26 -> Véhicules neufsRev. Autres | B26: Rev. Autres | D26: 471.4023 | E26: 114550.76 | G26: 370.74167 | H26: 4448.9 | J26: 475.125 | K26: 3801 | M26: 603.5596 | N26: 15088.99 | P26: 452.38913 | Q26: 10404.95 | S26: 433.41875 | T26: 13869.4 | V26: 509 | W26: 10180 | Y26: 529.47615 | Z26: 6883.19 | AB26: 544.04769 | AC26: 14145.24 | AE26: 411.16667 | AF26: 9868 | AH26: 425.595 | AI26: 9363.09 | AK26: 411.54545 | AL26: 9054 | AN26: 465.25 | AO26: 7444
A27: =+$C$4&B27 -> Véhicules neufsTotal F&I | B27: Total F&I | C27: 243 | D27: 1579.574 | E27: 383836.47 | F27: 12 | G27: 2227.8642 | H27: 26734.37 | I27: 8 | J27: 979.41625 | K27: 7835.33 | L27: 25 | M27: 1417.7196 | N27: 35442.99 | O27: 23 | P27: 1904.6643 | Q27: 43807.28 | R27: 32 | S27: 1818.3116 | T27: 58185.97 | U27: 20 | V27: 1502.7 | W27: 30054 | X27: 13 | Y27: 1869.8731 | Z27: 24308.35 | AA27: 26 | AB27: 1570.9208 | AC27: 40843.94 | AD27: 24 | AE27: 912.83333 | AF27: 21908 | AG27: 22 | AH27: 1503.3223 | AI27: 33073.09 | AJ27: 22 | AK27: 1498.9614 | AL27: 32977.15 | AM27: 16 | AN27: 1791.625 | AO27: 28666
A28: =+$C$4&B28 -> Véhicules neufs
A29: =+$C$4&B29 -> Véhicules neufs
A30: =+$C$4&B30 -> Véhicules neufsTotal Dépt. Neufs | B30: Total Dépt. Neufs | C30: 247 | D30: 7188.6136 | E30: 1775587.6 | F30: 13 | G30: 6627.0531 | H30: 86151.69 | I30: 8 | J30: 5567.5275 | K30: 44540.22 | L30: 27 | M30: 7337.953 | N30: 198124.73 | O30: 24 | P30: 8370.3467 | Q30: 200888.32 | R30: 32 | S30: 7067.7984 | T30: 226169.55 | U30: 20 | V30: 7526.5695 | W30: 150531.39 | X30: 13 | Y30: 8009.8785 | Z30: 104128.42 | AA30: 26 | AB30: 7361.5277 | AC30: 191399.72 | AD30: 24 | AE30: 8025.8108 | AF30: 192619.46 | AG30: 22 | AH30: 6358.0927 | AI30: 139878.04 | AJ30: 22 | AK30: 6612.695 | AL30: 145479.29 | AM30: 16 | AN30: 5979.7963 | AO30: 95676.74
A31: =+$C$4&B31 -> Véhicules neufs
A32: =+$C$4&B32 -> Véhicules neufs
A33: =+$C$4&B33 -> Véhicules neufsDEPENSES | B33: DEPENSES
A34: =+$C$4&B34 -> Véhicules neufsComm. vendeurs | B34: Comm. vendeurs | C34: 0.29749071 | D34: 1586.5396 | E34: 385529.13 | F34: 0.34976528 | G34: 1533.8467 | H34: 18406.16 | I34: 0.29601996 | J34: 1247.2775 | K34: 9978.22 | L34: 0.27019853 | M34: 1597.228 | N34: 39930.7 | O34: 0.28986239 | P34: 1795.28 | Q34: 41291.44 | R34: 0.31640662 | S34: 1576.7753 | T34: 50456.81 | U34: 0.27667411 | V34: 1528.45 | W34: 30569 | X34: 0.26208271 | Y34: 1538.9108 | Z34: 20005.84 | AA34: 0.29395383 | AB34: 1589.225 | AC34: 41319.85 | AD34: 0.2302309 | AE34: 1599.2938 | AF34: 38383.05 | AG34: 0.39350525 | AH34: 1821.0341 | AI34: 40062.75 | AJ34: 0.30887114 | AK34: 1494.84 | AL34: 32886.48 | AM34: 0.38665642 | AN34: 1389.9269 | AO34: 22238.83
A35: =+$C$4&B35 -> Véhicules neufsComm. F&I | B35: Comm. F&I | C35: 0.24949122 | D35: 394.08984 | E35: 95763.83 | F35: 0.24999916 | G35: 556.96417 | H35: 6683.57 | I35: 0.24999968 | J35: 244.85375 | K35: 1958.83 | L35: 0.25000007 | M35: 354.43 | N35: 8860.75 | O35: 0.24755201 | P35: 471.50348 | Q35: 10844.58 | R35: 0.24986195 | S35: 454.32687 | T35: 14538.46 | U35: 0.24983363 | V35: 375.425 | W35: 7508.5 | X35: 0.25102856 | Y35: 469.39154 | Z35: 6102.09 | AA35: 0.25000012 | AB35: 392.73038 | AC35: 10210.99 | AD35: 0.25 | AE35: 228.20833 | AF35: 5477 | AG35: 0.24168501 | AH35: 363.33045 | AI35: 7993.27 | AJ35: 0.25379058 | AK35: 380.42227 | AL35: 8369.29 | AM35: 0.25174423 | AN35: 451.03125 | AO35: 7216.5
A36: =+$C$4&B36 -> Véhicules neufsFrais de livraison | B36: Frais de livraison | D36: 92.279918 | E36: 22424.02 | G36: 95.435833 | H36: 1145.23 | J36: 117.30375 | K36: 938.43 | M36: 64.8876 | N36: 1622.19 | P36: 88.415217 | Q36: 2033.55 | S36: 41.204375 | T36: 1318.54 | V36: 112.023 | W36: 2240.46 | Y36: 167.71846 | Z36: 2180.34 | AB36: 97.216538 | AC36: 2527.63 | AE36: 142.46208 | AF36: 3419.09 | AH36: 105.57727 | AI36: 2322.7 | AK36: 74.969545 | AL36: 1649.33 | AN36: 64.158125 | AO36: 1026.53
A37: =+$C$4&B37 -> Véhicules neufsService gratuit 1 | B37: Service gratuit 1 | D37: 44.81214 | E37: 10889.35 | G37: 66.046667 | H37: 792.56 | J37: 146 | K37: 1168 | M37: 13.0708 | N37: 326.77 | P37: 32.104783 | Q37: 738.41 | S37: 49.581562 | T37: 1586.61 | V37: 25.25 | W37: 505 | Y37: 67.839231 | Z37: 881.91 | AB37: 62.066538 | AC37: 1613.73 | AE37: 36.605 | AF37: 878.52 | AH37: 27.948182 | AI37: 614.86 | AK37: 53.87 | AL37: 1185.14 | AN37: 37.365 | AO37: 597.84
A38: =+$C$4&B38 -> Véhicules neufsEntretien stock | B38: Entretien stock | D38: 46.574733 | E38: 11317.66 | G38: 90.208333 | H38: 1082.5 | J38: 124.125 | K38: 993 | M38: 11.76 | N38: 294 | P38: 25.156522 | Q38: 578.6 | S38: 52.022188 | T38: 1664.71 | V38: 29.45 | W38: 589 | Y38: 37.923077 | Z38: 493 | AB38: 31.988462 | AC38: 831.7 | AE38: 52.96875 | AF38: 1271.25 | AH38: 55.568182 | AI38: 1222.5 | AK38: 55.704545 | AL38: 1225.5 | AN38: 66.99375 | AO38: 1071.9
A39: =+$C$4&B39 -> Véhicules neufsPublicité 1 | B39: Publicité 1 | D39: 588.02543 | E39: 142890.18 | G39: 705.6325 | H39: 8467.59 | J39: 1116.2625 | K39: 8930.1 | M39: 728.6512 | N39: 18216.28 | P39: 727.05478 | Q39: 16722.26 | S39: 436.2675 | T39: 13960.56 | V39: 542.347 | W39: 10846.94 | Y39: 730.09769 | Z39: 9491.27 | AB39: 353.25038 | AC39: 9184.51 | AE39: 444.47583 | AF39: 10667.42 | AH39: 466.17045 | AI39: 10255.75 | AK39: 667.48727 | AL39: 14684.72 | AN39: 716.42375 | AO39: 11462.78
A40: =+$C$4&B40 -> Véhicules neufsIntérêt de gros | B40: Intérêt de gros | D40: 476.63449 | E40: 115822.18 | G40: 441.83417 | H40: 5302.01 | J40: 750.3125 | K40: 6002.5 | M40: 128.7224 | N40: 3218.06 | P40: 227.60826 | Q40: 5234.99 | S40: 236.32094 | T40: 7562.27 | V40: 276.6485 | W40: 5532.97 | Y40: 532.72154 | Z40: 6925.38 | AB40: 563.735 | AC40: 14657.11 | AE40: 711.69708 | AF40: 17080.73 | AH40: 631.93545 | AI40: 13902.58 | AK40: 645.76591 | AL40: 14206.85 | AN40: 1012.2956 | AO40: 16196.73
A41: =+$C$4&B41 -> Véhicules neufs[...] | B41: [...] | D41: 0 | E41: 0 | G41: 0 | J41: 0 | M41: 0 | P41: 0 | S41: 0 | V41: 0 | Y41: 0 | AB41: 0 | AE41: 0 | AH41: 0 | AK41: 0 | AN41: 0
A42: =+$C$4&B42 -> Véhicules neufs[...] | B42: [...] | D42: 0 | E42: 0 | G42: 0 | J42: 0 | M42: 0 | P42: 0 | S42: 0 | V42: 0 | Y42: 0 | AB42: 0 | AE42: 0 | AH42: 0 | AK42: 0 | AN42: 0
A43: =+$C$4&B43 -> Véhicules neufs[...] | B43: [...] | D43: 0 | E43: 0 | G43: 0 | J43: 0 | M43: 0 | P43: 0 | S43: 0 | V43: 0 | Y43: 0 | AB43: 0 | AE43: 0 | AH43: 0 | AK43: 0 | AN43: 0
A44: =+$C$4&B44 -> Véhicules neufsTOTAL VARIABLES | B44: TOTAL VARIABLES | C44: % brut | D44: 0.44190237 | E44: 784636.35 | F44: % brut | G44: 0.4861149 | H44: 41879.62 | I44: % brut | J44: 0.67285433 | K44: 29969.08 | L44: % brut | M44: 0.36577337 | N44: 72468.75 | O44: % brut | P44: 0.38550688 | Q44: 77443.83 | R44: % brut | S44: 0.40274193 | T44: 91087.96 | U44: % brut | V44: 0.38391906 | W44: 57791.87 | X44: % brut | Y44: 0.44252885 | Z44: 46079.83 | AA44: % brut | AB44: 0.41977867 | AC44: 80345.52 | AD44: % brut | AE44: 0.40067115 | AF44: 77177.06 | AG44: % brut | AH44: 0.54600715 | AI44: 76374.41 | AJ44: % brut | AK44: 0.51008848 | AL44: 74207.31 | AM44: % brut | AN44: 0.62513742 | AO44: 59811.11
A45: =+$C$4&B45 -> Véhicules neufsSalaires cadres | B45: Salaires cadres | E45: 186404.95 | H45: 17915.84 | K45: 15135.03 | N45: 14431.24 | Q45: 13604.22 | T45: 15431.24 | W45: 14604.22 | Z45: 10496.39 | AC45: 18431.25 | AF45: 18400.43 | AI45: 17915.84 | AL45: 15588.82 | AO45: 14450.43
A46: =+$C$4&B46 -> Véhicules neufsSalaires commis | B46: Salaires commis | E46: 81679.18 | H46: 7006.44 | K46: 6781.09 | N46: 7221.4 | Q46: 6649.17 | T46: 8287.01 | W46: 6890.54 | Z46: 6302.71 | AC46: 7085.63 | AF46: 6065.73 | AI46: 7314.42 | AL46: 6694.98 | AO46: 5380.06
A47: =+$C$4&B47 -> Véhicules neufsSalaires autres | B47: Salaires autres | E47: 4104 | H47: 342 | K47: 342 | N47: 342 | Q47: 342 | T47: 342 | W47: 342 | Z47: 342 | AC47: 342 | AF47: 342 | AI47: 342 | AL47: 342 | AO47: 342
A48: =+$C$4&B48 -> Véhicules neufsSalaires spécialistes | B48: Salaires spécialistes | E48: 0 | H48: 0 | K48: 0 | N48: 0 | Q48: 0 | T48: 0 | W48: 0 | Z48: 0 | AC48: 0 | AF48: 0 | AI48: 0 | AL48: 0 | AO48: 0
A49: =+$C$4&B49 -> Véhicules neufs[...] | B49: [...] | E49: 0 | H49: 0 | K49: 0 | N49: 0 | Q49: 0 | T49: 0 | W49: 0 | Z49: 0 | AC49: 0 | AF49: 0 | AI49: 0 | AL49: 0 | AO49: 0
A50: =+$C$4&B50 -> Véhicules neufs[...] | B50: [...] | E50: 0 | H50: 0 | K50: 0 | N50: 0 | Q50: 0 | T50: 0 | W50: 0 | Z50: 0 | AC50: 0 | AF50: 0 | AI50: 0 | AL50: 0 | AO50: 0
A51: =+$C$4&B51 -> Véhicules neufs[...] | B51: [...] | E51: 0 | H51: 0 | K51: 0 | N51: 0 | Q51: 0 | T51: 0 | W51: 0 | Z51: 0 | AC51: 0 | AF51: 0 | AI51: 0 | AL51: 0 | AO51: 0
A52: =+$C$4&B52 -> Véhicules neufsSalaires en absences | B52: Salaires en absences | E52: 73886.69 | H52: 3903.18 | K52: 6938.82 | N52: 3234.63 | Q52: 5562.25 | T52: 7533.08 | W52: 7615.48 | Z52: 4841.25 | AC52: 5383.38 | AF52: 6752.15 | AI52: 6363.86 | AL52: 5043.63 | AO52: 10714.98
A53: =+$C$4&B53 -> Véhicules neufsDéduction à la source | B53: Déduction à la source | E53: 92813.14 | H53: 8593.87 | K53: 8155.65 | N53: 8526.27 | Q53: 10343.44 | T53: 11152.22 | W53: 7630.09 | Z53: 6444.83 | AC53: 6393.44 | AF53: 6336.97 | AI53: 5961.27 | AL53: 6230.97 | AO53: 7044.12
A54: =+$C$4&B54 -> Véhicules neufsBénéfices marginaux | B54: Bénéfices marginaux | E54: 41278.62 | H54: 2223.6 | K54: 3026.84 | N54: 3288.12 | Q54: 3409.51 | T54: 4253.3 | W54: 3798.41 | Z54: 3789.41 | AC54: 3306.05 | AF54: 3350.01 | AI54: 3452.34 | AL54: 3801.06 | AO54: 3579.97
A55: =+$C$4&B55 -> Véhicules neufsCsst | B55: Csst | E55: 7035.69 | H55: 716.66 | K55: 1186.79 | N55: 666.22 | Q55: 900.84 | T55: 1068.9 | W55: 878.72 | Z55: 707.76 | AC55: 303.64 | AF55: 100.85 | AI55: 87.56 | AL55: 80.34 | AO55: 337.41
A56: =+$C$4&B56 -> Véhicules neufs[...] | B56: [...] | E56: 0
A57: =+$C$4&B57 -> Véhicules neufsTOTAL PERSONNEL | B57: TOTAL PERSONNEL | C57: % brut | D57: 0.27438932 | E57: 487202.27 | F57: % brut | G57: 0.47244099 | H57: 40701.59 | I57: % brut | J57: 0.93322889 | K57: 41566.22 | L57: % brut | M57: 0.19033404 | N57: 37709.88 | O57: % brut | P57: 0.20315482 | Q57: 40811.43 | R57: % brut | S57: 0.21252971 | T57: 48067.75 | U57: % brut | V57: 0.27741363 | W57: 41759.46 | X57: % brut | Y57: 0.31618985 | Z57: 32924.35 | AA57: % brut | AB57: 0.21549347 | AC57: 41245.39 | AD57: % brut | AE57: 0.21466232 | AF57: 41348.14 | AG57: % brut | AH57: 0.29623871 | AI57: 41437.29 | AJ57: % brut | AK57: 0.25970569 | AL57: 37781.8 | AM57: % brut | AN57: 0.43739962 | AO57: 41848.97
A58: =+$C$4&B58 -> Véhicules neufsPublicité 2 | B58: Publicité 2 | E58: 0 | H58: 0 | K58: 0 | N58: 0 | Q58: 0 | T58: 0 | W58: 0 | Z58: 0 | AC58: 0 | AF58: 0 | AI58: 0 | AL58: 0 | AO58: 0
A59: =+$C$4&B59 -> Véhicules neufsService gratuit 2 | B59: Service gratuit 2 | E59: 0 | H59: 0 | K59: 0 | N59: 0 | Q59: 0 | T59: 0 | W59: 0 | Z59: 0 | AC59: 0 | AF59: 0 | AI59: 0 | AL59: 0 | AO59: 0
A60: =+$C$4&B60 -> Véhicules neufsFrais véhicules de cie | B60: Frais véhicules de cie | E60: 57977.58 | H60: 3900.35 | K60: 4453.62 | N60: 4220.64 | Q60: 3938.31 | T60: 4318.92 | W60: 6947.4 | Z60: 4507.11 | AC60: 4266.63 | AF60: 5975.59 | AI60: 5945.3 | AL60: 5151.59 | AO60: 4352.12
A61: =+$C$4&B61 -> Véhicules neufsInformatique | B61: Informatique | E61: 57517.16 | H61: 4417.22 | K61: 5158.28 | N61: 4417.22 | Q61: 4620.97 | T61: 5673.05 | W61: 4560.8 | Z61: 4923.88 | AC61: 4819.61 | AF61: 4534.64 | AI61: 4756.88 | AL61: 4757.24 | AO61: 4877.37
A62: =+$C$4&B62 -> Véhicules neufsFrais de déplacement | B62: Frais de déplacement | E62: 10822.28 | H62: 794.79 | K62: 575.76 | N62: 676.56 | Q62: 524.23 | T62: 555.96 | W62: 1724.36 | Z62: 681.65 | AC62: 428.8 | AF62: 342.17 | AI62: 544.8 | AL62: 2422.62 | AO62: 1550.58
A63: =+$C$4&B63 -> Véhicules neufsServices extérieurs | B63: Services extérieurs | E63: 32741.49 | H63: 2505.85 | K63: 2535.84 | N63: 2995.68 | Q63: 3346.33 | T63: 2080.72 | W63: 3162.47 | Z63: 2466.58 | AC63: 2359.25 | AF63: 3374.59 | AI63: 2150.34 | AL63: 3183.03 | AO63: 2580.81
A64: =+$C$4&B64 -> Véhicules neufsFournitures autres | B64: Fournitures autres | E64: 651.17 | H64: 191.66 | K64: 41.97 | N64: 0 | Q64: 20.69 | T64: 210.75 | W64: 36.35 | Z64: 0 | AC64: 0 | AF64: 119.55 | AI64: 0 | AL64: 30.2 | AO64: 0
A65: =+$C$4&B65 -> Véhicules neufsUniformes | B65: Uniformes | E65: 155.03 | H65: 0 | K65: 0 | N65: 71.89 | Q65: 83.14 | T65: 0 | W65: 0 | Z65: 0 | AC65: 0 | AF65: 0 | AI65: 0 | AL65: 0 | AO65: 0
A66: =+$C$4&B66 -> Véhicules neufsPapeterie | B66: Papeterie | E66: 7349.04 | H66: 569.07 | K66: 738.18 | N66: 276.01 | Q66: 578.44 | T66: 561.34 | W66: 1019.53 | Z66: 590.87 | AC66: 736.41 | AF66: 594.31 | AI66: 609.26 | AL66: 746.08 | AO66: 329.54
A67: =+$C$4&B67 -> Véhicules neufsTéléphone | B67: Téléphone | E67: 2939.91 | H67: 362.84 | K67: 219.4 | N67: 177.59 | Q67: 173.28 | T67: 340.2 | W67: 401.68 | Z67: 138.35 | AC67: 273.86 | AF67: 219.58 | AI67: 206.26 | AL67: 206.76 | AO67: 220.11
A68: =+$C$4&B68 -> Véhicules neufsFrais postaux | B68: Frais postaux | E68: 3545.45 | H68: 204.12 | K68: 376.47 | N68: 228.77 | Q68: 295.54 | T68: 165.25 | W68: 198.76 | Z68: 266.48 | AC68: 297.43 | AF68: 268.21 | AI68: 386.76 | AL68: 319.88 | AO68: 537.78
A69: =+$C$4&B69 -> Véhicules neufsDivers | B69: Divers | E69: 9654.35 | H69: 668.39 | K69: 762.73 | N69: 678.45 | Q69: 858.09 | T69: 972.45 | W69: 658.8 | Z69: 668.16 | AC69: 1037.93 | AF69: 715.19 | AI69: 928.58 | AL69: 751.95 | AO69: 953.63
... A71: =+$C$4&B71 -> Véhicules neufsFrais bancaires | B71: Frais bancaires | E71: 31444.38 | H71: 1889.61 | K71: 1938.39 | N71: 2199.58 | Q71: 3314.97 | T71: 3184.55 | W71: 3121.95 | Z71: 2428.92 | AC71: 2629.8 | AF71: 2576.45 | AI71: 3065.55 | AL71: 3509.48 | AO71: 1585.13
A72: =+$C$4&B72 -> Véhicules neufs[...] | B72: [...] | E72: 0
A73: =+$C$4&B73 -> Véhicules neufs[...] | B73: [...] | E73: 0
A74: =+$C$4&B74 -> Véhicules neufs[...] | B74: [...] | E74: 0
A75: =+$C$4&B75 -> Véhicules neufsTOTAL SEMI-FIXES | B75: TOTAL SEMI-FIXES | C75: % brut | D75: 0.1237048 | E75: 219648.7 | F75: % brut | G75: 0.18390562 | H75: 15843.78 | I75: % brut | J75: 0.37849544 | K75: 16858.27 | L75: % brut | M75: 0.081285158 | N75: 16104.6 | O75: % brut | P75: 0.089672162 | Q75: 18014.09 | R75: % brut | S75: 0.080923581 | T75: 18302.45 | U75: % brut | V75: 0.14882597 | W75: 22402.98 | X75: % brut | Y75: 0.16981569 | Z75: 17682.64 | AA75: % brut | AB75: 0.089967686 | AC75: 17219.79 | AD75: % brut | AE75: 0.095854386 | AF75: 18463.42 | AG75: % brut | AH75: 0.13642213 | AI75: 19082.46 | AJ75: % brut | AK75: 0.14998362 | AL75: 21819.51 | AM75: % brut | AN75: 0.18661495 | AO75: 17854.71
A76: =+$C$4&B76 -> Véhicules neufs
A77: =+$C$4&B77 -> Véhicules neufsTOTAL DES DÉPENSES | B77: TOTAL DES DÉPENSES | C77: % brut | D77: 0.83999649 | E77: 1491487.3 | F77: % brut | G77: 1.1424615 | H77: 98424.99 | I77: % brut | J77: 1.9845787 | K77: 88393.57 | L77: % brut | M77: 0.63739257 | N77: 126283.23 | O77: % brut | P77: 0.67833386 | Q77: 136269.35 | R77: % brut | S77: 0.69619522 | T77: 157458.16 | U77: % brut | V77: 0.81015867 | W77: 121954.31 | X77: % brut | Y77: 0.9285344 | Z77: 96686.82 | AA77: % brut | AB77: 0.72523983 | AC77: 138810.7 | AD77: % brut | AE77: 0.71118785 | AF77: 136988.62 | AG77: % brut | AH77: 0.97866799 | AI77: 136894.16 | AJ77: % brut | AK77: 0.91977779 | AL77: 133808.62 | AM77: % brut | AN77: 1.249152 | AO77: 119514.79
A78: =+$C$4&B78 -> Véhicules neufsRBSC neuf | B78: RBSC neuf | E78: 435844.24 | H78: 17143.9 | K78: 12729 | N78: 40832.3 | Q78: 44091.88 | T78: 38478.17 | W78: 28947.02 | Z78: 24477.93 | AC78: 44929.74 | AF78: 83436.11 | AI78: 36701.35 | AL78: 36663.84 | AO78: 27413
A79: =+$C$4&B79 -> Véhicules neufsProgramme neuf 2 | B79: Programme neuf 2 | E79: 0 | H79: 0 | K79: 0 | N79: 0 | Q79: 0 | T79: 0 | W79: 0 | Z79: 0 | AC79: 0 | AF79: 0 | AI79: 0 | AL79: 0 | AO79: 0
A80: =+$C$4&B80 -> Véhicules neufsProgramme neuf 3 | B80: Programme neuf 3 | E80: 0 | H80: 0 | K80: 0 | N80: 0 | Q80: 0 | T80: 0 | W80: 0 | Z80: 0 | AC80: 0 | AF80: 0 | AI80: 0 | AL80: 0 | AO80: 0
A81: =+$C$4&B81 -> Véhicules neufsHoldbacks | B81: Holdbacks | E81: 432057.7 | H81: 23124.6 | K81: 13235.2 | N81: 41421.5 | Q81: 48030.4 | T81: 57482.6 | W81: 32547.6 | Z81: 25316 | AC81: 43027.7 | AF81: 49858.9 | AI81: 33506.3 | AL81: 28951 | AO81: 35555.9
A82: =+$C$4&B82 -> Véhicules neufs[...] | B82: [...] | E82: 0 | H82: 0 | K82: 0 | N82: 0 | Q82: 0 | T82: 0 | W82: 0 | Z82: 0 | AC82: 0 | AF82: 0 | AI82: 0 | AL82: 0 | AO82: 0
A83: =+$C$4&B83 -> Véhicules neufs[...] | B83: [...] | E83: 0 | H83: 0 | K83: 0 | N83: 0 | Q83: 0 | T83: 0 | W83: 0 | Z83: 0 | AC83: 0 | AF83: 0 | AI83: 0 | AL83: 0 | AO83: 0
A84: =+$C$4&B84 -> Véhicules neufs[...] | B84: [...] | E84: 0 | H84: 0 | K84: 0 | N84: 0 | Q84: 0 | T84: 0 | W84: 0 | Z84: 0 | AC84: 0 | AF84: 0 | AI84: 0 | AL84: 0 | AO84: 0
A85: =+$C$4&B85 -> Véhicules neufsFrais administration | B85: Frais administration | E85: 143300 | H85: 6545 | K85: 4760 | N85: 14875 | Q85: 13685 | T85: 18945 | W85: 11900 | Z85: 7735 | AC85: 15470 | AF85: 14280 | AI85: 12495 | AL85: 13090 | AO85: 9520
A86: =+$C$4&B86 -> Véhicules neufsAUTRES REVENUS | B86: AUTRES REVENUS | E86: 1011201.9 | H86: 46813.5 | K86: 30724.2 | N86: 97128.8 | Q86: 105807.28 | T86: 114905.77 | W86: 73394.62 | Z86: 57528.93 | AC86: 103427.44 | AF86: 147575.01 | AI86: 82702.65 | AL86: 78704.84 | AO86: 72488.9
A87: =+$C$4&B87 -> Véhicules neufs
A88: =+$C$4&B88 -> Véhicules neufsPROFIT DÉPARTEMENTAL | B88: PROFIT DÉPARTEMENTAL | E88: 1295302.2 | H88: 34540.2 | K88: -13129.15 | N88: 168970.3 | Q88: 170426.25 | T88: 183617.16 | W88: 101971.7 | Z88: 64970.53 | AC88: 156016.46 | AF88: 203205.85 | AI88: 85686.53 | AL88: 90375.51 | AO88: 48650.85
B92: Budget 2024 | C92: Véhicules usagés
B94: Mois | C94: 2023 | F94: Janvier | I94: Février | L94: Mars | O94: Avril | R94: Mai | U94: Juin | X94: Juillet | AA94: Août | AD94: Septembre | AG94: Octobre | AJ94: Novembre | AM94: Décembre
C95: UNITE | D95: $P/UNITE | E95: $PROFITS | F95: UNITE | G95: $P/UNITE | H95: $PROFITS | I95: UNITE | J95: $P/UNITE | K95: $PROFITS | L95: UNITE | M95: $P/UNITE | N95: $PROFITS | O95: UNITE | P95: $P/UNITE | Q95: $PROFITS | R95: UNITE | S95: $P/UNITE | T95: $PROFITS | U95: UNITE | V95: $P/UNITE | W95: $PROFITS | X95: UNITE | Y95: $P/UNITE | Z95: $PROFITS | AA95: UNITE | AB95: $P/UNITE | AC95: $PROFITS | AD95: UNITE | AE95: $P/UNITE | AF95: $PROFITS | AG95: UNITE | AH95: $P/UNITE | AI95: $PROFITS | AJ95: UNITE | AK95: $P/UNITE | AL95: $PROFITS | AM95: UNITE | AN95: $P/UNITE | AO95: $PROFITS
A96: =+$C$92&B96 -> Véhicules usagésVentes nettes | B96: Ventes nettes | E96: 16009693 | H96: 1163648.2 | K96: 1094326.6 | N96: 1035414.6 | Q96: 1647548.1 | T96: 1602636.4 | W96: 1633050.9 | Z96: 1084525.5 | AC96: 2262127 | AF96: 1028845.2 | AI96: 1429684 | AL96: 1257294.7 | AO96: 770592.27
A97: =+$C$92&B97 -> Véhicules usagésCertifié | B97: Certifié | C97: 66 | D97: 2688.5633 | E97: 177445.18 | F97: 3 | G97: 1853.0667 | H97: 5559.2 | I97: 4 | J97: 3467.44 | K97: 13869.76 | L97: 4 | M97: 4328.685 | N97: 17314.74 | O97: 3 | P97: 2381.7333 | Q97: 7145.2 | R97: 5 | S97: 2240.688 | T97: 11203.44 | U97: 6 | V97: 3063.19 | W97: 18379.14 | X97: 8 | Y97: 3135.9625 | Z97: 25087.7 | AA97: 10 | AB97: 4122.351 | AC97: 41223.51 | AD97: 4 | AE97: 1977.9975 | AF97: 7911.99 | AG97: 8 | AH97: 2241.9812 | AI97: 17935.85 | AJ97: 4 | AK97: 2058.275 | AL97: 8233.1 | AM97: 7 | AN97: 511.65 | AO97: 3581.55
A98: =+$C$92&B98 -> Véhicules usagésNon Certifié | B98: Non Certifié | C98: 130 | D98: 2188.029 | E98: 284443.77 | F98: 13 | G98: 857.3 | H98: 11144.9 | I98: 7 | J98: 1944.9786 | K98: 13614.85 | L98: 10 | M98: 1808.465 | N98: 18084.65 | O98: 14 | P98: 2545.8421 | Q98: 35641.79 | R98: 15 | S98: 2698.6187 | T98: 40479.28 | U98: 16 | V98: 2929.0137 | W98: 46864.22 | X98: 10 | Y98: 1906.81 | Z98: 19068.1 | AA98: 9 | AB98: 3497.2778 | AC98: 31475.5 | AD98: 7 | AE98: 1875.0671 | AF98: 13125.47 | AG98: 11 | AH98: 2755.0964 | AI98: 30306.06 | AJ98: 12 | AK98: 1574.45 | AL98: 18893.4 | AM98: 6 | AN98: 957.59167 | AO98: 5745.55
A99: =+$C$92&B99 -> Véhicules usagésAutres Marques | B99: Autres Marques
A100: =+$C$92&B100 -> Véhicules usagésTotal Usagés | B100: Total Usagés | C100: 196 | D100: 2356.5763 | E100: 461888.95 | F100: 16 | G100: 1044.0062 | H100: 16704.1 | I100: 11 | J100: 2498.6009 | K100: 27484.61 | L100: 14 | M100: 2528.5279 | N100: 35399.39 | O100: 17 | P100: 2516.8818 | Q100: 42786.99 | R100: 20 | S100: 2584.136 | T100: 51682.72 | U100: 22 | V100: 2965.6073 | W100: 65243.36 | X100: 18 | Y100: 2453.1 | Z100: 44155.8 | AA100: 19 | AB100: 3826.2637 | AC100: 72699.01 | AD100: 11 | AE100: 1912.4964 | AF100: 21037.46 | AG100: 19 | AH100: 2539.0479 | AI100: 48241.91 | AJ100: 16 | AK100: 1695.4062 | AL100: 27126.5 | AM100: 13 | AN100: 717.46923 | AO100: 9327.1
A101: =+$C$92&B101 -> Véhicules usagés
A102: =+$C$92&B102 -> Véhicules usagés | F102: 0 | H102: 0 | I102: 0 | K102: 0 | L102: 0 | N102: 0 | O102: 0 | Q102: 0 | R102: 0 | T102: 0 | U102: 0 | W102: 0 | X102: 0 | Z102: 0 | AA102: 0 | AC102: 0 | AD102: 0 | AF102: 0 | AG102: 0 | AI102: 0 | AJ102: 0 | AL102: 0 | AM102: 0 | AO102: 0
A103: =+$C$92&B103 -> Véhicules usagésVentes au Gros | B103: Ventes au Gros | C103: 214 | D103: 375.70561 | E103: 80401 | F103: 17 | G103: -350.31471 | H103: -5955.35 | I103: 13 | J103: 228.82692 | K103: 2974.75 | L103: 14 | M103: 226.71071 | N103: 3173.95 | O103: 21 | P103: 470.61238 | Q103: 9882.86 | R103: 26 | S103: 11.195385 | T103: 291.08 | U103: 23 | V103: 1285.4087 | W103: 29564.4 | X103: 14 | Y103: 530.30786 | Z103: 7424.31 | AA103: 31 | AB103: 511.53452 | AC103: 15857.57 | AD103: 13 | AE103: 333.00462 | AF103: 4329.06 | AG103: 19 | AH103: 812.57684 | AI103: 15438.96 | AJ103: 17 | AK103: -234.15824 | AL103: -3980.69 | AM103: 6 | AN103: 233.35 | AO103: 1400.1
A104: =+$C$92&B104 -> Véhicules usagés
A105: =+$C$92&B105 -> Véhicules usagésRev. Finances | B105: Rev. Finances | D105: 576.11036 | E105: 112917.63 | G105: 351.69875 | H105: 5627.18 | J105: 1150.46 | K105: 12655.06 | M105: 521.32929 | N105: 7298.61 | P105: 799.83529 | Q105: 13597.2 | S105: 836.7175 | T105: 16734.35 | V105: 384.29182 | W105: 8454.42 | Y105: 356.19333 | Z105: 6411.48 | AB105: 813.99895 | AC105: 15465.98 | AE105: 544.42636 | AF105: 5988.69 | AH105: 417.16263 | AI105: 7926.09 | AK105: 418.41437 | AL105: 6694.63 | AN105: 466.45692 | AO105: 6063.94
A106: =+$C$92&B106 -> Véhicules usagésRev. Protections | B106: Rev. Protections | D106: 752.0952 | E106: 147410.66 | G106: 963.98125 | H106: 15423.7 | J106: 577 | K106: 6347 | M106: 511.87857 | N106: 7166.3 | P106: 750.93471 | Q106: 12765.89 | S106: 858.902 | T106: 17178.04 | V106: 665.34091 | W106: 14637.5 | Y106: 1413.7222 | Z106: 25447 | AB106: 994.57895 | AC106: 18897 | AE106: 463.74818 | AF106: 5101.23 | AH106: 463.26316 | AI106: 8802 | AK106: 451.25 | AL106: 7220 | AN106: 648.07692 | AO106: 8425
...

Sheet Capex
A1: CONCESSION
A2: Forecast Immobilisation 2024 | H2: 1 | I2: 2 | J2: 3 | K2: 4 | L2: 5 | M2: 6 | N2: 7 | O2: 8 | P2: 9 | Q2: 10 | R2: 11 | S2: 12
H3: =+IF(VLOOKUP(H2,Parametres!$L$3:$N$14,3,0)="X","REEL","FORECAST") -> REEL | I3: =+IF(VLOOKUP(I2,Parametres!$L$3:$N$14,3,0)="X","REEL","FORECAST") -> REEL | J3: =+IF(VLOOKUP(J2,Parametres!$L$3:$N$14,3,0)="X","REEL","FORECAST") -> REEL | K3: =+IF(VLOOKUP(K2,Parametres!$L$3:$N$14,3,0)="X","REEL","FORECAST") -> REEL | L3: =+IF(VLOOKUP(L2,Parametres!$L$3:$N$14,3,0)="X","REEL","FORECAST") -> FORECAST | M3: =+IF(VLOOKUP(M2,Parametres!$L$3:$N$14,3,0)="X","REEL","FORECAST") -> FORECAST | N3: =+IF(VLOOKUP(N2,Parametres!$L$3:$N$14,3,0)="X","REEL","FORECAST") -> FORECAST | O3: =+IF(VLOOKUP(O2,Parametres!$L$3:$N$14,3,0)="X","REEL","FORECAST") -> FORECAST | ... S3: =+IF(VLOOKUP(S2,Parametres!$L$3:$N$14,3,0)="X","REEL","FORECAST") -> FORECAST
A4: Concession | B4: Budgété / Non budgété | C4: Projet | D4: Catégorie Immo | E4: Total forecast | F4: Budget Annuel | G4: Écart vs budget | H4: January | I4: February | J4: March | K4: April | L4: May | M4: June | N4: July | O4: August | P4: September | Q4: October | R4: November | S4: December | T4: Raison / Description
C5: Total | E5: =+SUM(E6:E40) -> 244135 | F5: =+SUM(F6:F40) -> 240000 | G5: =+SUM(G6:G40) -> 4135 | H5: =+SUM(H6:H40) -> 1922 | I5: =+SUM(I6:I40) -> 5358 | J5: =+SUM(J6:J40) -> 4856 | K5: =+SUM(K6:K40) -> 3323 | L5: =+SUM(L6:L40) -> 38676 | ... S5: =+SUM(S6:S40) -> 0 | X5: Terrain
A6: =+Parametres!$B$1 -> BMW Sherbrooke | B6: oui | C6: Borne électrique | D6: Équipements Service | E6: =+SUM(H6:S6) -> 145000 | F6: 145000 | G6: =+E6-F6 -> 0 | M6: 145000 | X6: Bâtisse
A7: =+Parametres!$B$1 -> BMW Sherbrooke | B7: oui | C7: Mise à jour pour MSP | D7: Améliorations Locatives | E7: =+SUM(H7:S7) -> 40000 | F7: 40000 | G7: =+E7-F7 -> 0 | K7: 1324 | L7: 38676 | X7: Améliorations Locatives
A8: =+Parametres!$B$1 -> BMW Sherbrooke | B8: oui | C8: Pilon enseigne | D8: Améliorations Locatives | E8: =+SUM(H8:S8) -> 25000 | F8: 25000 | G8: =+E8-F8 -> 0 | M8: 25000 | X8: Améliorations Locatives Permanentes
A9: =+Parametres!$B$1 -> BMW Sherbrooke | B9: oui | C9: Mise à niveau entreposage | D9: Améliorations Locatives | E9: =+SUM(H9:S9) -> 20000 | F9: 20000 | G9: =+E9-F9 -> 0 | M9: 20000 | X9: Équipements Service
A10: =+Parametres!$B$1 -> BMW Sherbrooke | B10: non | C10: Outils obligatoire | D10: Équipements Service | E10: =+SUM(H10:S10) -> 10465 | F10: 10000 | G10: =+E10-F10 -> 465 | H10: 1922 | I10: 2688 | J10: 3856 | K10: 1999 | X10: Mobilier
A11: =+Parametres!$B$1 -> BMW Sherbrooke | B11: non | C11: Repeindre salle conférence | D11: Améliorations Locatives Permanentes | E11: =+SUM(H11:S11) -> 2670 | G11: =+E11-F11 -> 2670 | I11: 2670 | X11: Équipements Informatique
A12: =+Parametres!$B$1 -> BMW Sherbrooke | B12: non | C12: Chaises salle conférence | D12: Mobilier | E12: =+SUM(H12:S12) -> 1000 | G12: =+E12-F12 -> 1000 | J12: 1000 | X12: Équipements Téléphonique
A13: =+Parametres!$B$1 -> BMW Sherbrooke | B13: non | E13: =+SUM(H13:S13) -> 0 | G13: =+E13-F13 -> 0 | X13: Enseigne
A14: =+Parametres!$B$1 -> BMW Sherbrooke | B14: non | E14: =+SUM(H14:S14) -> 0 | G14: =+E14-F14 -> 0
A15: =+Parametres!$B$1 -> BMW Sherbrooke | B15: non | E15: =+SUM(H15:S15) -> 0 | G15: =+E15-F15 -> 0
A16: =+Parametres!$B$1 -> BMW Sherbrooke | B16: non | E16: =+SUM(H16:S16) -> 0 | G16: =+E16-F16 -> 0
A17: =+Parametres!$B$1 -> BMW Sherbrooke | B17: non | E17: =+SUM(H17:S17) -> 0 | G17: =+E17-F17 -> 0
A18: =+Parametres!$B$1 -> BMW Sherbrooke | B18: non | E18: =+SUM(H18:S18) -> 0 | G18: =+E18-F18 -> 0
A19: =+Parametres!$B$1 -> BMW Sherbrooke | B19: non | E19: =+SUM(H19:S19) -> 0 | G19: =+E19-F19 -> 0
A20: =+Parametres!$B$1 -> BMW Sherbrooke | B20: non | E20: =+SUM(H20:S20) -> 0 | G20: =+E20-F20 -> 0
A21: =+Parametres!$B$1 -> BMW Sherbrooke | B21: non | E21: =+SUM(H21:S21) -> 0 | G21: =+E21-F21 -> 0
A22: =+Parametres!$B$1 -> BMW Sherbrooke | B22: non | E22: =+SUM(H22:S22) -> 0 | G22: =+E22-F22 -> 0
A23: =+Parametres!$B$1 -> BMW Sherbrooke | B23: non | E23: =+SUM(H23:S23) -> 0 | G23: =+E23-F23 -> 0
A24: =+Parametres!$B$1 -> BMW Sherbrooke | B24: non | E24: =+SUM(H24:S24) -> 0 | G24: =+E24-F24 -> 0
A25: =+Parametres!$B$1 -> BMW Sherbrooke | B25: non | E25: =+SUM(H25:S25) -> 0 | G25: =+E25-F25 -> 0
... A35: =+Parametres!$B$1 -> BMW Sherbrooke | B35: non | E35: =+SUM(H35:S35) -> 0 | G35: =+E35-F35 -> 0
A36: =+Parametres!$B$1 -> BMW Sherbrooke | B36: non | E36: =+SUM(H36:S36) -> 0 | G36: =+E36-F36 -> 0 | X36: oui
A37: =+Parametres!$B$1 -> BMW Sherbrooke | B37: non | E37: =+SUM(H37:S37) -> 0 | G37: =+E37-F37 -> 0 | X37: non
A38: =+Parametres!$B$1 -> BMW Sherbrooke | B38: non | E38: =+SUM(H38:S38) -> 0 | G38: =+E38-F38 -> 0
A39: =+Parametres!$B$1 -> BMW Sherbrooke | B39: non | E39: =+SUM(H39:S39) -> 0 | G39: =+E39-F39 -> 0
A40: =+Parametres!$B$1 -> BMW Sherbrooke | B40: non | E40: =+SUM(H40:S40) -> 0 | G40: =+E40-F40 -> 0

Sheet Inventaire_Neuf
A1: #Contrôle | B1: Année | C1: Marque | D1: Modèle | E1: $ Inventaire | F1: $ Financé | G1: NIV | H1: Jours en stock | L1: $ Inventaire | M1: $ Financé
A2: 23019 | B2: 2023 | C2: BMW | D2: 430 | E2: 65121.87 | F2: -60905.25 | G2: WBA73AP05PCL27730 | H2: 478 | K2: CTRL | L2: =+SUM(E2:E10000) -> 3938633.3 | M2: =+SUM(F2:F10000) -> -3910068
A3: 23020 | B3: 2023 | C3: BMW | D3: 430 | E3: 63963.67 | G3: WBA73AP06PCL26036 | H3: 465 | L3: =+COUNT(E2:E10000) -> 45
A4: 23084 | B4: 2023 | C4: BMW | D4: 530xe | E4: 75509.5 | G4: WBA33AG06PCL42221 | H4: 411
A5: 23218 | B5: 2023 | C5: BMW SAV | D5: X3 | E5: 84833.61 | F5: -88452 | G5: 5UX83DP04P9T17873 | H5: 146
A6: 23221 | B6: 2023 | C6: BMW | D6: SERIE 2 | E6: 66617.36 | F6: -69326.25 | G6: 3MW53CM06P8D70441 | H6: 151
A7: 23228 | B7: 2023 | C7: BMW SAV | D7: X3 | E7: 73335.37 | F7: -69809.25 | G7: 5UX53DP06P9T28635 | H7: 143
A8: 23240 | B8: 2023 | C8: BMW SAV | D8: X1 | E8: 50471.49 | F8: -50473.5 | G8: WBX73EF02P5X85602 | H8: 67
A9: 23241 | B9: 2023 | C9: BMW SAV | D9: X1 | E9: 50262.11 | F9: -52143 | G9: WBX73EF00P5X86053 | H9: 58
A10: 24019 | B10: 2024 | C10: BMW SAV | D10: X5 | E10: 95266.49 | F10: -95303.25 | G10: 5UX23EU05R9T15522 | H10: 158
A11: 24023 | B11: 2024 | C11: BMW SAV | D11: X7 | E11: 126612.36 | F11: -131675.25 | G11: 5UX23EM04R9T23238 | H11: 149
A12: 24024 | B12: 2024 | C12: BMWI | D12: IX40 | E12: 97633.14 | F12: -97203.75 | G12: WB513CF03RCN76497 | H12: 152
A13: 24032 | B13: 2024 | C13: BMW SAV | D13: X6 | E13: 103328.55 | F13: -107651.25 | G13: 5UX33EX02R9T31595 | H13: 144
A14: 24034 | B14: 2024 | C14: BMW | D14: SERIE 4 | E14: 66533.61 | F14: -69237 | G14: WBA73AP07RCN92250 | H14: 144
A15: 24038 | B15: 2024 | C15: BMWI | D15: I7 | E15: 159476.47 | F15: -173664.75 | G15: WBY53EJ01RCN94634 | H15: 142
A16: 24051 | B16: 2024 | C16: BMW | D16: SERIE 3 | E16: 62907.21 | F16: -60149.52 | G16: 3MW89FF00R8D80878 | H16: 117
... A46: 24130 | B46: 2024 | C46: BMW SAV | D46: X3 | E46: 65370 | F46: -68638.5 | G46: 5UX53DP06R9U99484 | H46: 9

Sheet Inventaire_Used
A1: #Contrôle | B1: Année | C1: Marque | D1: Description | E1: Amount | F1: Financé | G1: NIV | H1: Jours en stock | L1: $ Inventaire | M1: $ Financé
A2: P0512 | B2: 2004 | C2: CHEVROLET TRUCK | D2: SILVERADO 2500 | E2: 3856.45 | G2: 1GCGK23U14F218132 | H2: 1482 | K2: CTRL | L2: =+SUM(E2:E9999) -> 1972155.4 | M2: =+SUM(F2:F9999) -> -1357394.6
A3: P2173 | B3: 2022 | C3: BMW | D3: 540i | E3: 75917.21 | F3: -50220 | G3: WBA73BJ07NWX54871 | H3: 490 | L3: =+COUNT(E2:E10000) -> 50
A4: P2259 | B4: 2021 | C4: BMW SAV | D4: X5 | E4: 75668.81 | F4: -55025 | G4: 5UXTA6C07M9G89398 | H4: 306
A5: P2282 | B5: 2019 | C5: BMW | D5: Z4 | E5: 61477.55 | F5: -55037.5 | G5: WBAHF3C57KWW21386 | H5: 235
A6: P2321 | B6: 2021 | C6: JEEP | D6: GLADIATOR 4X4 | E6: 57247.58 | F6: -48210.15 | G6: 1C6HJTAG8ML543623 | H6: 144
A7: P2327 | B7: 2023 | C7: BMW SAV | D7: X1 | E7: 51697.81 | F7: -49599.39 | G7: WBX73EF03P5W40276 | H7: 137
A8: 23231A | B8: 2020 | C8: MINI | D8: COUNTRYMAN | E8: 35295.85 | F8: -20589.76 | G8: WMZYZ9C04L3L18702 | H8: 125
A9: P2334 | B9: 2019 | C9: BMW | D9: 330i | E9: 31287.41 | F9: -23537.41 | G9: WBA5R7C54KFH22955 | H9: 111
A10: 23193A | B10: 2022 | C10: VOLVO | D10: XC60 | E10: 58424.95 | F10: -80500 | G10: LYV062RL8NB979235 | H10: 108
A11: P2335 | B11: 2020 | C11: BMW SAV | D11: X3 | E11: 30904.85 | F11: -21000 | G11: 5UXTY5C03L9D44647 | H11: 103
A12: 24082A | B12: 2023 | C12: MAZDA | D12: MX-5 | E12: 34707.45 | F12: -32060.23 | G12: JM1NDAD7XP0552574 | H12: 73
A13: 23225A | B13: 2023 | C13: BMW | D13: 330i | E13: 54482.17 | F13: -37837.25 | G13: WBA83FF0XPFN75280 | H13: 72
A14: P2342A | B14: 2023 | C14: BMW | D14: 530e | E14: 65103.95 | F14: -45150 | G14: WBA33AG00PCL72878 | H14: 72
A15: P2343 | B15: 2023 | C15: ACURA | D15: Integra | E15: 39059.95 | F15: -35100 | G15: 19UDE4G72PA800656 | H15: 67
... A28: P2356 | B28: 2021 | C28: ACURA | D28: TLX | E28: 39793.95 | F28: -35550 | G28: 19UUB6F51MA801958 | H28: 38
A29: 24098A | B29: 2015 | C29: MINI | D29: 5 DOOR | E29: 8000 | G29: WMWXS5C59FT837198 | H29: 38
A30: 23116B | B30: 2021 | C30: JEEP | D30: Wrangler Unlim | E30: 43899.95 | F30: -30450 | G30: 1C4HJXEN3MW680010 | H30: 37
A31: 24078A | B31: 2023 | C31: VOLKSWAGEN | D31: ID.4 | E31: 47899.95 | F31: -34300 | G31: 1V2JNPE8XPC021183 | H31: 31
A32: 23243A | B32: 2020 | C32: BMW | D32: 2 SERIES | E32: 29024.85 | F32: -19599.51 | G32: WBA73AK0XL7G01503 | H32: 26
A33: P2361 | B33: 2014 | C33: BMW | D33: 320i | E33: 11164.86 | G33: WBA3C3C57EK200069 | H33: 22
A34: P2362 | B34: 2023 | C34: BMW | D34: M240i xDrive | E34: 53250.2 | F34: -52796.25 | G34: 3MW53CM03P8C99750 | H34: 20
A35: P2363 | B35: 2023 | C35: BMW | D35: 230i | E35: 42103.5 | F35: -41658.65 | G35: 3MW33CM08P8C93109 | H35: 18
A36: P2364 | B36: 2017 | C36: BMW SAV | D36: X4 | E36: 27407.01 | F36: -24300 | G36: 5UXXW3C37H0T79741 | H36: 17
A37: 24040A | B37: 2023 | C37: BMW SAV | D37: X4 | E37: 58745 | F37: -45726.94 | G37: 5UX33DT01P9N56202 | H37: 13
A38: P2367 | B38: 2019 | C38: NISSAN | D38: Micra | E38: 11000 | F38: -9900 | G38: 3N1CK3CP5KL236170 | H38: 10
A39: 23244A | B39: 2019 | C39: BMW SAV | D39: X2 | E39: 26995 | F39: -16020.18 | G39: WBXYJ5C54K5N01549 | H39: 10
A40: 24103A | B40: 2021 | C40: BMW SAV | D40: X3 | E40: 42500 | F40: -30072.18 | G40: 5UXTS1C06M9H64396 | H40: 10
A41: P2223A | B41: 2023 | C41: BMW | D41: I4 | E41: 51776.06 | F41: -29211.39 | G41: WBY43AW09PFP45888 | H41: 10
A42: P2366 | B42: 2012 | C42: BMW | D42: M3 | E42: 37500 | G42: WBSKG9C53CE798848 | H42: 10
A43: P2365 | B43: 2021 | C43: DODGE TRUCK | D43: RAM 1500 Class | E43: 32547.15 | F43: -32547.15 | G43: 3C6RR7KG7MG709002 | H43: 9
A44: 23227A | B44: 2017 | C44: HONDA | D44: CIVIC HATCHBAC | E44: 14000 | G44: SHHFK7H26HU304092 | H44: 9
A45: 24097A | B45: 2018 | C45: AUDI | D45: A5 Sportback | E45: 18500 | G45: WAUANCF51JA004190 | H45: 3
A46: 24126A | B46: 2017 | C46: BMW | D46: 2 SERIES | E46: 28000 | G46: WBA2L3C32HV667851 | H46: 3
A47: 24091B | B47: 2013 | C47: VOLKSWAGEN | D47: JETTA | E47: 1500 | G47: 3VW1K7AJ9DM416983 | H47: 2
A48: 24125B | B48: 2017 | C48: BMW | D48: 650i | E48: 37000 | G48: WBA6F7C50HD930698 | H48: 2
A49: 23122A | B49: 2022 | C49: BMW | D49: 2 SERIES | E49: 37500 | G49: WBA13AL03N7K75967 | H49: 2
A50: 24125A | B50: 2021 | C50: BMW SAV | D50: X5 | E50: 60000 | G50: 5UXJU4C08M9E22693 | H50: 2
A51: 24104B | B51: 2019 | C51: BMW SAV | D51: X2 | E51: 31000 | G51: WBXYN1C56K5N23209 | H51: 0

Sheet Démo
B1: Suivi de Démo
B2: # Stock | C2: NIV | D2: Année | E2: Marque | F2: Modèle | G2: $ Valeur | H2: Nom | I2: Prénom | J2: Titre / Fonction
B3: 24081 | C3: 5UX23EM03R9T54626 | D3: 2024 | E3: BMW | F3: X7 | G3: 128665 | H3: Hébert | I3: Norman | J3: Président Exécutif du Conseil
B4: 24183 | C4: WBAHF3C09RWY32362 | D4: 2024 | E4: BMW | F4: Z4 | G4: 75415 | H4: Rosa | I4: Yvon | J4: Conseiller aux ventes
B5: 24101 | C5: 5UX33EX00R9U61472 | D5: 2024 | E5: BMW | F5: X6 | G5: 101460 | H5: Beaudoin | I5: Sébastien | J5: VPDG

Sheet Wholesale
C1: ="Analyse Wholesale "&Parametres!B1 -> Analyse Wholesale BMW Sherbrooke
D2: $ | F2: X | G2: U | L2: $ | N2: X | O2: U
E4: =CONCATENATE("Pièces Wholesale ",Parametres!B3," ",Parametres!B4) -> Pièces Wholesale Avril 2024 | J4: =CONCATENATE("Pièces Wholesale AAD ",Parametres!B4) -> Pièces Wholesale AAD 2024
E5: Réel | F5: Budget | G5: ▲ $ | H5: ▲ % | J5: Réel | K5: Budget | L5: ▲ $ | M5: ▲ %
C6: NB de livraisons | E6: =SUMIF(A37:A48,"X",E37:E48) -> 24 | F6: =SUMIF(A37:A48,"X",F37:F48) -> 30 | G6: =E6-F6 -> -6 | H6: =G6/F6 -> -0.2 | J6: =SUMIF($B$37:$B$48,"X",$E$37:$E$48) -> 83 | K6: =SUMIF($B$37:$B$48,"X",$F$37:$F$48) -> 120 | L6: =J6-K6 -> -37 | M6: =L6/K6 -> -0.30833333
A7: =B7&C7 -> piècesVentes de Gros | B7: pièces | C7: Ventes de Gros | E7: =-SUMIFS(BV_Data_An_Cour!$O:$O,BV_Data_An_Cour!$X:$X,"Oui",BV_Data_An_Cour!$U:$U,$B7,BV_Data_An_Cour!$V:$V,$C7) -> 50271.28 | F7: =+INDEX('Budget original'!$A$2:$AO$501,MATCH($A7,'Budget original'!$A$2:$A$501,0),MATCH(F$2,'Budget original'!$A$2:$AO$2,0)) -> 49868.28 | G7: =E7-F7 -> 403.00037 | H7: =G7/F7 -> 0.0080812968 | J7: =-SUMIFS(BV_Data_An_Cour!$P:$P,BV_Data_An_Cour!$X:$X,"Oui",BV_Data_An_Cour!$U:$U,$B7,BV_Data_An_Cour!$V:$V,$C7) -> 187847 | K7: {=+SUMPRODUCT(('Budget original'!$A$8:$A$501=$A7)*('Budget original'!$C$3:$AO$3=N$2),'Budget original'!$C$8:$AO$501)} -> 242326.34 | L7: =J7-K7 -> -54479.344 | M7: =L7/K7 -> -0.22481808
C8: Coûts | E8: =E7-E9 -> 39207.11 | F8: =F7-F9 -> 37052.136 | G8: =E8-F8 -> 2154.9739 | H8: =G8/F8 -> 0.058160586 | J8: =J7-J9 -> 144354.22 | K8: =K7-K9 -> 180048.48 | L8: =J8-K8 -> -35694.263 | M8: =L8/K8 -> -0.19824806
C9: Profit brut | E9: =E12+E11 -> 11064.17 | F9: =F12+F11 -> 12816.144 | G9: =E9-F9 -> -1751.9736 | H9: =G9/F9 -> -0.13670053 | J9: =J12+J11 -> 43492.78 | K9: =K12+K11 -> 62277.861 | L9: =J9-K9 -> -18785.081 | M9: =L9/K9 -> -0.30163337
C10: % avant redevances | E10: =E9/E7 -> 0.22008928 | F10: =F9/F7 -> 0.25699991 | G10: =E10-F10 -> -0.03691063 | J10: =J9/J7 -> 0.231533 | K10: =K9/K7 -> 0.25699996 | L10: =J10-K10 -> -0.025466959
C11: Coûts de redevance | E11: =SUMIFS(BV_Data_An_Cour!$O:$O,BV_Data_An_Cour!$W:$W,$D$2,BV_Data_An_Cour!L:L,C31) -> 981.18 | F11: =SUMIF($A$37:$A$48,"X",$G$37:$G$48) -> 2194.2 | G11: =E11-F11 -> -1213.02 | H11: =G11/F11 -> -0.55283019 | J11: =SUMIFS(BV_Data_An_Cour!$P:$P,BV_Data_An_Cour!$W:$W,$L$2,BV_Data_An_Cour!T:T,C31) -> 6680.53 | K11: =SUMIF($B$37:$B$48,"X",$G$37:$G$48) -> 10662.35 | L11: =J11-K11 -> -3981.82 | M11: =L11/K11 -> -0.37344675
A12: Ventes de Gros | B12: pièces | C12: Profit | E12: =-SUMIFS(BV_Data_An_Cour!$O:$O,BV_Data_An_Cour!$U:$U,$B12,BV_Data_An_Cour!$V:$V,$A12,BV_Data_An_Cour!$W:$W,$D$2) -> 10082.99 | F12: =+INDEX('Budget original'!$A$2:$AO$501,MATCH(B12&$A12,'Budget original'!$A$2:$A$501,0),MATCH(G$2,'Budget original'!$A$2:$AO$2,0)) -> 10621.944 | G12: =E12-F12 -> -538.95356 | H12: =G12/F12 -> -0.050739637 | J12: =-SUMIFS(BV_Data_An_Cour!$P:$P,BV_Data_An_Cour!$U:$U,$B12,BV_Data_An_Cour!$V:$V,$A12,BV_Data_An_Cour!$W:$W,$D$2) -> 36812.25 | K12: {=+SUMPRODUCT(('Budget original'!$A$8:$A$501=B12&$A12)*('Budget original'!$C$3:$AO$3=O$2),'Budget original'!$C$8:$AO$501)} -> 51615.511 | L12: =J12-K12 -> -14803.261 | M12: =L12/K12 -> -0.2867987
C13: % brut | E13: =(E12)/E7 -> 0.20057158 | F13: =(F12)/F7 -> 0.213 | G13: =E13-F13 -> -0.012428421 | J13: =(J12)/J7 -> 0.19596933 | K13: =(K12)/K7 -> 0.213 | L13: =J13-K13 -> -0.017030674
C14: Coûts de livraison | E14: =SUMIFS(BV_Data_An_Cour!$O:$O,BV_Data_An_Cour!$W:$W,$D$2,BV_Data_An_Cour!L:L,C33) -> 600 | F14: =SUMIF(A37:A48,"X",F37:F48)*$G$33 -> 750 | G14: =E14-F14 -> -150 | H14: =G14/F14 -> -0.2 | J14: =SUMIFS(BV_Data_An_Cour!$P:$P,BV_Data_An_Cour!$W:$W,$L$2,BV_Data_An_Cour!T:T,C33) -> 2075 | K14: =SUMIF(B37:B48,"X",F37:F48)*$G$33 -> 3000 | L14: =J14-K14 -> -925 | M14: =L14/K14 -> -0.30833333
C15: Profit net | E15: =E12-E14 -> 9482.99 | F15: =F12-F14 -> 9871.9436 | G15: =E15-F15 -> -388.95356 | H15: =G15/F15 -> -0.039399897 | J15: =J12-J14 -> 34737.25 | K15: =K12-K14 -> 48615.511 | L15: =J15-K15 -> -13878.261 | M15: =L15/K15 -> -0.28546982
C16: % net | E16: =E15/E7 -> 0.18863633 | F16: =F15/F7 -> 0.19796038 | G16: =E16-F16 -> -0.0093240448 | J16: =J15/J7 -> 0.1849231 | K16: =K15/K7 -> 0.20062 | L16: =J16-K16 -> -0.015696898
E18: =CONCATENATE("Pièces Wholesale $ / livraison ",Parametres!B3," ",Parametres!B4) -> Pièces Wholesale $ / livraison Avril 2024 | J18: =CONCATENATE("Pièces Wholesale AAD $ / livraison ",Parametres!B4) -> Pièces Wholesale AAD $ / livraison 2024
E19: Réel | F19: Budget | G19: ▲ $ | H19: ▲ % | J19: Réel | K19: Budget | L19: ▲ $ | M19: ▲ %
C20: Ventes de Gros | E20: =E7/E$6 -> 2094.6367 | F20: =F7/F$6 -> 1662.276 | G20: =E20-F20 -> 432.36068 | H20: =G20/F20 -> 0.26010162 | J20: =J7/J$6 -> 2263.2169 | K20: =K7/K$6 -> 2019.3862 | L20: =J20-K20 -> 243.83066 | M20: =L20/K20 -> 0.12074494
C21: Coûts | E21: =E8/E$6 -> 1633.6296 | F21: =F8/F$6 -> 1235.0712 | G21: =E21-F21 -> 398.55838 | H21: =G21/F21 -> 0.32270073 | J21: =J8/J$6 -> 1739.2075 | K21: =K8/K$6 -> 1500.404 | L21: =J21-K21 -> 238.80344 | M21: =L21/K21 -> 0.15915943
C22: Profit brut | E22: =E9/E$6 -> 461.00708 | F22: =F9/F$6 -> 427.20479 | G22: =E22-F22 -> 33.802298 | H22: =G22/F22 -> 0.079124343 | J22: =J9/J$6 -> 524.0094 | K22: =K9/K$6 -> 518.98218 | L22: =J22-K22 -> 5.0272196 | M22: =L22/K22 -> 0.0096866903
C23: Coûts de redevance | E23: =E11/E$6 -> 40.8825 | F23: =F11/F$6 -> 73.14 | G23: =E23-F23 -> -32.2575 | H23: =G23/F23 -> -0.44103774 | J23: =J11/J$6 -> 80.488313 | K23: =K11/K$6 -> 88.852917 | L23: =J23-K23 -> -8.3646034 | M23: =L23/K23 -> -0.094139886
C24: Profit | E24: =E12/E$6 -> 420.12458 | F24: =F12/F$6 -> 354.06479 | G24: =E24-F24 -> 66.059798 | H24: =G24/F24 -> 0.18657545 | J24: =J12/J$6 -> 443.52108 | K24: =K12/K$6 -> 430.12926 | L24: =J24-K24 -> 13.391823 | M24: =L24/K24 -> 0.031134415
C25: Coûts de livraison | E25: =E14/E$6 -> 25 | F25: =F14/F$6 -> 25 | G25: =E25-F25 -> 0 | H25: =G25/F25 -> 0 | J25: =J14/J$6 -> 25 | K25: =K14/K$6 -> 25 | L25: =J25-K25 -> 0 | M25: =L25/K25 -> 0
C26: Profit net | E26: =E15/E$6 -> 395.12458 | F26: =F15/F$6 -> 329.06479 | G26: =E26-F26 -> 66.059798 | H26: =G26/F26 -> 0.20075013 | J26: =J15/J$6 -> 418.52108 | K26: =K15/K$6 -> 405.12926 | L26: =J26-K26 -> 13.391823 | M26: =L26/K26 -> 0.03305568
C29: Inscrire les GL
C30: Couts de redevance | E30: Contrôle mois | G30: =SUMIF(A37:A48,"X",E37:E48)*$G$33-E14 -> 0 | H30: frais de livraison doit être de 25$ / livraison
C31: 675L | E31: Contrôle YTD | G31: =SUMIF(B37:B48,"X",E37:E48)*$G$33-J14 -> 0 | H31: frais de livraison doit être de 25$ / livraison
C32: GL livraison
C33: 70L | E33: Coût / livraison | G33: 25
E35: NB de livraison
A36: Mois | B36: YTD | C36: Mois | E36: Réel | F36: Budgeté | G36: Coûts de redevance budgeté | H36: =+IF(Parametres!$B$3=H$38,"X","") | I36: =+IF(Parametres!$B$3=I$38,"X","") | J36: =+IF(Parametres!$B$3=J$38,"X","") | K36: =+IF(Parametres!$B$3=K$38,"X","") | L36: =+IF(Parametres!$B$3=L$38,"X","") | M36: =+IF(Parametres!$B$3=M$38,"X","") | N36: =+IF(Parametres!$B$3=N$38,"X","") | O36: =+IF(Parametres!$B$3=O$38,"X","") | ... S36: =+IF(Parametres!$B$3=S$38,"X","") | U36: =+IF(Parametres!$B$3=N$7,"X","") | V36: =+IF(Parametres!$B$3=N$7,"O","") | W36: =+IF(Parametres!$B$3=N$7,"U","") | X36: =+IF(Parametres!$B$3=Q$7,"X","") | Y36: =+IF(Parametres!$B$3=Q$7,"O","") | Z36: =+IF(Parametres!$B$3=Q$7,"U","") | AA36: =+IF(Parametres!$B$3=T$7,"X","") | AB36: =+IF(Parametres!$B$3=T$7,"O","") | AC36: =+IF(Parametres!$B$3=T$7,"U","") | AD36: =+IF(Parametres!$B$3=W$7,"X","") | AE36: =+IF(Parametres!$B$3=W$7,"O","") | AF36: =+IF(Parametres!$B$3=W$7,"U","") | AG36: =+IF(Parametres!$B$3=Z$7,"X","") | AH36: =+IF(Parametres!$B$3=Z$7,"O","") | AI36: =+IF(Parametres!$B$3=Z$7,"U","") | AJ36: =+IF(Parametres!$B$3=AC$7,"X","") | AK36: =+IF(Parametres!$B$3=AC$7,"O","") | AL36: =+IF(Parametres!$B$3=AC$7,"U","") | AM36: =+IF(Parametres!$B$3=AF$7,"X","") | AN36: =+IF(Parametres!$B$3=AF$7,"O","") | AO36: =+IF(Parametres!$B$3=AF$7,"U","")
A37: =+IF(Parametres!$B$3=$C37,"X","") | B37: =+IF(VLOOKUP($C37,Parametres!$K$3:$N$14,4,0)="X","X","") -> X | C37: Janvier | E37: 23 | F37: 30 | G37: 2662.04
A38: =+IF(Parametres!$B$3=$C38,"X","") | B38: =+IF(VLOOKUP($C38,Parametres!$K$3:$N$14,4,0)="X","X","") -> X | C38: Février | E38: 23 | F38: 30 | G38: 2686.35
A39: =+IF(Parametres!$B$3=$C39,"X","") | B39: =+IF(VLOOKUP($C39,Parametres!$K$3:$N$14,4,0)="X","X","") -> X | C39: Mars | E39: 13 | F39: 30 | G39: 3119.76
A40: =+IF(Parametres!$B$3=$C40,"X","") -> X | B40: =+IF(VLOOKUP($C40,Parametres!$K$3:$N$14,4,0)="X","X","") -> X | C40: Avril | E40: 24 | F40: 30 | G40: 2194.2
A41: =+IF(Parametres!$B$3=$C41,"X","") | B41: =+IF(VLOOKUP($C41,Parametres!$K$3:$N$14,4,0)="X","X","") | C41: Mai | F41: 30 | G41: 3569.08
A42: =+IF(Parametres!$B$3=$C42,"X","") | B42: =+IF(VLOOKUP($C42,Parametres!$K$3:$N$14,4,0)="X","X","") | C42: Juin | F42: 30 | G42: 2969.14
A43: =+IF(Parametres!$B$3=$C43,"X","") | B43: =+IF(VLOOKUP($C43,Parametres!$K$3:$N$14,4,0)="X","X","") | C43: Juillet | F43: 30 | G43: 2322.39
A44: =+IF(Parametres!$B$3=$C44,"X","") | B44: =+IF(VLOOKUP($C44,Parametres!$K$3:$N$14,4,0)="X","X","") | C44: Août | F44: 30 | G44: 2796.57
A45: =+IF(Parametres!$B$3=$C45,"X","") | B45: =+IF(VLOOKUP($C45,Parametres!$K$3:$N$14,4,0)="X","X","") | C45: Septembre | F45: 30 | G45: 3451.22
A46: =+IF(Parametres!$B$3=$C46,"X","") | B46: =+IF(VLOOKUP($C46,Parametres!$K$3:$N$14,4,0)="X","X","") | C46: Octobre | F46: 30 | G46: 2901.53
A47: =+IF(Parametres!$B$3=$C47,"X","") | B47: =+IF(VLOOKUP($C47,Parametres!$K$3:$N$14,4,0)="X","X","") | C47: Novembre | F47: 30 | G47: 2924.65
A48: =+IF(Parametres!$B$3=$C48,"X","") | B48: =+IF(VLOOKUP($C48,Parametres!$K$3:$N$14,4,0)="X","X","") | C48: Décembre | F48: 30 | G48: 2943.06

Sheet Print_Mois
C1: =Parametres!B1 -> BMW Sherbrooke | K1: Véhicules neufs | S1: =CONCATENATE("Réalisé,"," ",Parametres!B3," ",Parametres!B4) -> Réalisé, Avril 2024
D2: X | E2: O | F2: U | J2: NB | L2: $ | O2: X | P2: O | Q2: U
D3: BUDGET ORIGINAL | J3: RÉALISATION | M3: ÉCART réel / Budget | O3: ANNÉE PRÉCÉDENTE | R3: ECART (réel/ Ann.Préc.)
D4: UNITE | E4: $P/UNITÉ | F4: $PROFITS | J4: UNITE | K4: $P/UNITE | L4: $PROFITS | M4: UNFTÉ | N4: $PROFITS | O4: UNITE | P4: $P/UNITÉ | Q4: $PROFITS | R4: UNITE | S4: $PROFITS
A5: =+B5&C5 -> Véhicules neufsVentes nettes | B5: =+$K$1 -> Véhicules neufs | C5: Ventes nettes | F5: =+INDEX('Budget original'!$A$2:$AO$501,MATCH($A5,'Budget original'!$A$2:$A$501,0),MATCH(F$2,'Budget original'!$A$2:$AO$2,0)) -> 3032403.6 | L5: =-SUMIFS(BV_Data_An_Cour!$O:$O,BV_Data_An_Cour!$X:$X,"Oui",BV_Data_An_Cour!$U:$U,$B5) -> 2814437.6 | Q5: {=+INDEX('Réel 2023'!$A$2:$AO$501,MATCH($A5,'Réel 2023'!$A$2:$A$501,0),MATCH(Q$2,'Réel 2023'!$A$2:$AO$2,0))} -> 2399882.7
A6: =+B6&C6 -> Véhicules neufsAutos détail | B6: =+$K$1 -> Véhicules neufs | C6: Autos détail | D6: =+INDEX('Budget original'!$A$2:$AO$501,MATCH($A6,'Budget original'!$A$2:$A$501,0),MATCH(D$2,'Budget original'!$A$2:$AO$2,0)) -> 10 | E6: =IF(D6=0,0,F6/D6) -> 5144.9383 | F6: =+INDEX('Budget original'!$A$2:$AO$501,MATCH($A6,'Budget original'!$A$2:$A$501,0),MATCH(F$2,'Budget original'!$A$2:$AO$2,0)) -> 51449.383 | J6: =-SUMIFS(BV_Data_An_Cour!$O:$O,BV_Data_An_Cour!$U:$U,$B6,BV_Data_An_Cour!$V:$V,$C6,BV_Data_An_Cour!$W:$W,J$2) -> 13 | K6: =IF(J6=0,0,L6/J6) -> 5336.7323 | L6: =-SUMIFS(BV_Data_An_Cour!$O:$O,BV_Data_An_Cour!$U:$U,$B6,BV_Data_An_Cour!$V:$V,$C6,BV_Data_An_Cour!$W:$W,L$2) -> 69377.52 | M6: =J6-D6 -> 3 | N6: =L6-F6 -> 17928.137 | O6: =+INDEX('Réel 2023'!$A$2:$AO$501,MATCH($A6,'Réel 2023'!$A$2:$A$501,0),MATCH(O$2,'Réel 2023'!$A$2:$AO$2,0)) -> 9 | P6: =IF(O6=0,0,Q6/O6) -> 6333.3722 | Q6: {=+INDEX('Réel 2023'!$A$2:$AO$501,MATCH($A6,'Réel 2023'!$A$2:$A$501,0),MATCH(Q$2,'Réel 2023'!$A$2:$AO$2,0))} -> 57000.35 | R6: =J6-O6 -> 4 | S6: =L6-Q6 -> 12377.17
A7: =+B7&C7 -> Véhicules neufsCamions détail | B7: =+$K$1 -> Véhicules neufs | C7: Camions détail | D7: =+INDEX('Budget original'!$A$2:$AO$501,MATCH($A7,'Budget original'!$A$2:$A$501,0),MATCH(D$2,'Budget original'!$A$2:$AO$2,0)) -> 19 | E7: =IF(D7=0,0,F7/D7) -> 5386.4238 | F7: =+INDEX('Budget original'!$A$2:$AO$501,MATCH($A7,'Budget original'!$A$2:$A$501,0),MATCH(F$2,'Budget original'!$A$2:$AO$2,0)) -> 102342.05 | J7: =-SUMIFS(BV_Data_An_Cour!$O:$O,BV_Data_An_Cour!$U:$U,$B7,BV_Data_An_Cour!$V:$V,$C7,BV_Data_An_Cour!$W:$W,J$2) -> 12 | K7: =IF(J7=0,0,L7/J7) -> 4634.92 | L7: =-SUMIFS(BV_Data_An_Cour!$O:$O,BV_Data_An_Cour!$U:$U,$B7,BV_Data_An_Cour!$V:$V,$C7,BV_Data_An_Cour!$W:$W,L$2) -> 55619.04 | M7: =J7-D7 -> -7 | N7: =L7-F7 -> -46723.013 | O7: {=+INDEX('Réel 2023'!$A$2:$AO$501,MATCH($A7,'Réel 2023'!$A$2:$A$501,0),MATCH(O$2,'Réel 2023'!$A$2:$AO$2,0))} -> 14 | P7: =IF(O7=0,0,Q7/O7) -> 6103.68 | Q7: {=+INDEX('Réel 2023'!$A$2:$AO$501,MATCH($A7,'Réel 2023'!$A$2:$A$501,0),MATCH(Q$2,'Réel 2023'!$A$2:$AO$2,0))} -> 85451.52 | R7: =J7-O7 -> -2 | S7: =L7-Q7 -> -29832.48
A8: =+B8&C8 -> Véhicules neufsSprinter | B8: =+$K$1 -> Véhicules neufs | C8: Sprinter | D8: =+INDEX('Budget original'!$A$2:$AO$501,MATCH($A8,'Budget original'!$A$2:$A$501,0),MATCH(D$2,'Budget original'!$A$2:$AO$2,0)) -> 0 | E8: =IF(D8=0,0,F8/D8) -> 0 | F8: =+INDEX('Budget original'!$A$2:$AO$501,MATCH($A8,'Budget original'!$A$2:$A$501,0),MATCH(F$2,'Budget original'!$A$2:$AO$2,0)) -> 0 | J8: =-SUMIFS(BV_Data_An_Cour!$O:$O,BV_Data_An_Cour!$U:$U,$B8,BV_Data_An_Cour!$V:$V,$C8,BV_Data_An_Cour!$W:$W,J$2) -> 0 | K8: =IF(J8=0,0,L8/J8) -> 0 | L8: =-SUMIFS(BV_Data_An_Cour!$O:$O,BV_Data_An_Cour!$U:$U,$B8,BV_Data_An_Cour!$V:$V,$C8,BV_Data_An_Cour!$W:$W,L$2) -> 0 | M8: =J8-D8 -> 0 | N8: =L8-F8 -> 0 | O8: {=+INDEX('Réel 2023'!$A$2:$AO$501,MATCH($A8,'Réel 2023'!$A$2:$A$501,0),MATCH(O$2,'Réel 2023'!$A$2:$AO$2,0))} -> 0 | P8: =IF(O8=0,0,Q8/O8) -> 0 | Q8: {=+INDEX('Réel 2023'!$A$2:$AO$501,MATCH($A8,'Réel 2023'!$A$2:$A$501,0),MATCH(Q$2,'Réel 2023'!$A$2:$AO$2,0))} -> 0 | R8: =J8-O8 -> 0 | S8: =L8-Q8 -> 0
A9: =+B9&C9 -> Véhicules neufsMoto détail | B9: =+$K$1 -> Véhicules neufs | C9: Moto détail | D9: =+INDEX('Budget original'!$A$2:$AO$501,MATCH($A9,'Budget original'!$A$2:$A$501,0),MATCH(D$2,'Budget original'!$A$2:$AO$2,0)) -> 0 | E9: =IF(D9=0,0,F9/D9) -> 0 | F9: =+INDEX('Budget original'!$A$2:$AO$501,MATCH($A9,'Budget original'!$A$2:$A$501,0),MATCH(F$2,'Budget original'!$A$2:$AO$2,0)) -> 0 | J9: =-SUMIFS(BV_Data_An_Cour!$O:$O,BV_Data_An_Cour!$U:$U,$B9,BV_Data_An_Cour!$V:$V,$C9,BV_Data_An_Cour!$W:$W,J$2) -> 0 | K9: =IF(J9=0,0,L9/J9) -> 0 | L9: =-SUMIFS(BV_Data_An_Cour!$O:$O,BV_Data_An_Cour!$U:$U,$B9,BV_Data_An_Cour!$V:$V,$C9,BV_Data_An_Cour!$W:$W,L$2) -> 0 | M9: =J9-D9 -> 0 | N9: =L9-F9 -> 0 | O9: {=+INDEX('Réel 2023'!$A$2:$AO$501,MATCH($A9,'Réel 2023'!$A$2:$A$501,0),MATCH(O$2,'Réel 2023'!$A$2:$AO$2,0))} -> 0 | P9: =IF(O9=0,0,Q9/O9) -> 0 | Q9: {=+INDEX('Réel 2023'!$A$2:$AO$501,MATCH($A9,'Réel 2023'!$A$2:$A$501,0),MATCH(Q$2,'Réel 2023'!$A$2:$AO$2,0))} -> 0 | R9: =J9-O9 -> 0 | S9: =L9-Q9 -> 0
A10: =+B10&C10 -> Véhicules neufs[...] | B10: =+$K$1 -> Véhicules neufs | C10: [...] | D10: =+INDEX('Budget original'!$A$2:$AO$501,MATCH($A10,'Budget original'!$A$2:$A$501,0),MATCH(D$2,'Budget original'!$A$2:$AO$2,0)) -> 0 | E10: =IF(D10=0,0,F10/D10) -> 0 | F10: =+INDEX('Budget original'!$A$2:$AO$501,MATCH($A10,'Budget original'!$A$2:$A$501,0),MATCH(F$2,'Budget original'!$A$2:$AO$2,0)) -> 0 | J10: =-SUMIFS(BV_Data_An_Cour!$O:$O,BV_Data_An_Cour!$U:$U,$B10,BV_Data_An_Cour!$V:$V,$C10,BV_Data_An_Cour!$W:$W,J$2) -> 0 | K10: =IF(J10=0,0,L10/J10) -> 0 | L10: =-SUMIFS(BV_Data_An_Cour!$O:$O,BV_Data_An_Cour!$U:$U,$B10,BV_Data_An_Cour!$V:$V,$C10,BV_Data_An_Cour!$W:$W,L$2) -> 0 | M10: =J10-D10 -> 0 | N10: =L10-F10 -> 0 | O10: {=+INDEX('Réel 2023'!$A$2:$AO$501,MATCH($A10,'Réel 2023'!$A$2:$A$501,0),MATCH(O$2,'Réel 2023'!$A$2:$AO$2,0))} -> 0 | P10: =IF(O10=0,0,Q10/O10) -> 0 | Q10: {=+INDEX('Réel 2023'!$A$2:$AO$501,MATCH($A10,'Réel 2023'!$A$2:$A$501,0),MATCH(Q$2,'Réel 2023'!$A$2:$AO$2,0))} -> 0 | R10: =J10-O10 -> 0 | S10: =L10-Q10 -> 0
A11: =+B11&C11 -> Véhicules neufs[...] | B11: =+$K$1 -> Véhicules neufs | C11: [...] | D11: =+INDEX('Budget original'!$A$2:$AO$501,MATCH($A11,'Budget original'!$A$2:$A$501,0),MATCH(D$2,'Budget original'!$A$2:$AO$2,0)) -> 0 | E11: =IF(D11=0,0,F11/D11) -> 0 | F11: =+INDEX('Budget original'!$A$2:$AO$501,MATCH($A11,'Budget original'!$A$2:$A$501,0),MATCH(F$2,'Budget original'!$A$2:$AO$2,0)) -> 0 | J11: =-SUMIFS(BV_Data_An_Cour!$O:$O,BV_Data_An_Cour!$U:$U,$B11,BV_Data_An_Cour!$V:$V,$C11,BV_Data_An_Cour!$W:$W,J$2) -> 0 | K11: =IF(J11=0,0,L11/J11) -> 0 | L11: =-SUMIFS(BV_Data_An_Cour!$O:$O,BV_Data_An_Cour!$U:$U,$B11,BV_Data_An_Cour!$V:$V,$C11,BV_Data_An_Cour!$W:$W,L$2) -> 0 | M11: =J11-D11 -> 0 | N11: =L11-F11 -> 0 | O11: {=+INDEX('Réel 2023'!$A$2:$AO$501,MATCH($A11,'Réel 2023'!$A$2:$A$501,0),MATCH(O$2,'Réel 2023'!$A$2:$AO$2,0))} -> 0 | P11: =IF(O11=0,0,Q11/O11) -> 0 | Q11: {=+INDEX('Réel 2023'!$A$2:$AO$501,MATCH($A11,'Réel 2023'!$A$2:$A$501,0),MATCH(Q$2,'Réel 2023'!$A$2:$AO$2,0))} -> 0 | R11: =J11-O11 -> 0 | S11: =L11-Q11 -> 0
A12: =+B12&C12 -> Véhicules neufs[...] | B12: =+$K$1 -> Véhicules neufs | C12: [...] | D12: =+INDEX('Budget original'!$A$2:$AO$501,MATCH($A12,'Budget original'!$A$2:$A$501,0),MATCH(D$2,'Budget original'!$A$2:$AO$2,0)) -> 0 | E12: =IF(D12=0,0,F12/D12) -> 0 | F12: =+INDEX('Budget original'!$A$2:$AO$501,MATCH($A12,'Budget original'!$A$2:$A$501,0),MATCH(F$2,'Budget original'!$A$2:$AO$2,0)) -> 0 | J12: =-SUMIFS(BV_Data_An_Cour!$O:$O,BV_Data_An_Cour!$U:$U,$B12,BV_Data_An_Cour!$V:$V,$C12,BV_Data_An_Cour!$W:$W,J$2) -> 0 | K12: =IF(J12=0,0,L12/J12) -> 0 | L12: =-SUMIFS(BV_Data_An_Cour!$O:$O,BV_Data_An_Cour!$U:$U,$B12,BV_Data_An_Cour!$V:$V,$C12,BV_Data_An_Cour!$W:$W,L$2) -> 0 | M12: =J12-D12 -> 0 | N12: =L12-F12 -> 0 | O12: {=+INDEX('Réel 2023'!$A$2:$AO$501,MATCH($A12,'Réel 2023'!$A$2:$A$501,0),MATCH(O$2,'Réel 2023'!$A$2:$AO$2,0))} -> 0 | P12: =IF(O12=0,0,Q12/O12) -> 0 | Q12: {=+INDEX('Réel 2023'!$A$2:$AO$501,MATCH($A12,'Réel 2023'!$A$2:$A$501,0),MATCH(Q$2,'Réel 2023'!$A$2:$AO$2,0))} -> 0 | R12: =J12-O12 -> 0 | S12: =L12-Q12 -> 0
A13: =+B13&C13 -> Véhicules neufsTotal Neufs | B13: =+$K$1 -> Véhicules neufs | C13: Total Neufs | D13: =+SUM(D6:D12) -> 29 | E13: =IF(D13<=0,0,F13/D13) -> 5303.153 | F13: =+SUM(F6:F12) -> 153791.44 | J13: =+SUM(J6:J12) -> 25 | K13: =IF(J13<=0,0,L13/J13) -> 4999.8624 | L13: =+SUM(L6:L12) -> 124996.56 | M13: =+SUM(M6:M12) -> -4 | N13: =+SUM(N6:N12) -> -28794.876 | O13: =+SUM(O6:O12) -> 23 | P13: =IF(O13<=0,0,Q13/O13) -> 6193.5596 | Q13: =+SUM(Q6:Q12) -> 142451.87 | R13: =+SUM(R6:R12) -> 2 | S13: =+SUM(S6:S12) -> -17455.31
A14: =+B14&C14 -> Véhicules neufs | B14: =+$K$1 -> Véhicules neufs | M14: =IF(D13=0,0,M13/D13) -> -0.13793103 | N14: =IF(F13=0,0,N13/F13) -> -0.18723328 | R14: =R13/O13 -> 0.086956522 | S14: =IF(Q13=0,0,(S13/Q13)) -> -0.12253479
A15: =+B15&C15 -> Véhicules neufsEx-Démos et courtoisies | B15: =+$K$1 -> Véhicules neufs | C15: Ex-Démos et courtoisies | D15: =+INDEX('Budget original'!$A$2:$AO$501,MATCH($A15,'Budget original'!$A$2:$A$501,0),MATCH(D$2,'Budget original'!$A$2:$AO$2,0)) -> 3 | E15: =IF(D15=0,0,F15/D15) -> 2500 | F15: =+INDEX('Budget original'!$A$2:$AO$501,MATCH($A15,'Budget original'!$A$2:$A$501,0),MATCH(F$2,'Budget original'!$A$2:$AO$2,0)) -> 7500 | J15: =-SUMIFS(BV_Data_An_Cour!$O:$O,BV_Data_An_Cour!$U:$U,$B15,BV_Data_An_Cour!$V:$V,$C15,BV_Data_An_Cour!$W:$W,J$2) -> 5 | K15: =IF(J15=0,0,L15/J15) -> 3098.878 | L15: =-SUMIFS(BV_Data_An_Cour!$O:$O,BV_Data_An_Cour!$U:$U,$B15,BV_Data_An_Cour!$V:$V,$C15,BV_Data_An_Cour!$W:$W,L$2) -> 15494.39 | M15: =J15-D15 -> 2 | N15: =L15-F15 -> 7994.39 | O15: {=+INDEX('Réel 2023'!$A$2:$AO$501,MATCH($A15,'Réel 2023'!$A$2:$A$501,0),MATCH(O$2,'Réel 2023'!$A$2:$AO$2,0))} -> 0 | P15: =IF(O15=0,0,Q15/O15) -> 0 | Q15: {=+INDEX('Réel 2023'!$A$2:$AO$501,MATCH($A15,'Réel 2023'!$A$2:$A$501,0),MATCH(Q$2,'Réel 2023'!$A$2:$AO$2,0))} -> 0 | R15: =J15-O15 -> 5 | S15: =L15-Q15 -> 15494.39
A16: =+B16&C16 -> Véhicules neufs | B16: =+$K$1 -> Véhicules neufs
A17: =+B17&C17 -> Véhicules neufsFlottes | B17: =+$K$1 -> Véhicules neufs | C17: Flottes | D17: =+INDEX('Budget original'!$A$2:$AO$501,MATCH($A17,'Budget original'!$A$2:$A$501,0),MATCH(D$2,'Budget original'!$A$2:$AO$2,0)) -> 1 | E17: =IF(D17=0,0,F17/D17) -> 2500 | F17: =+INDEX('Budget original'!$A$2:$AO$501,MATCH($A17,'Budget original'!$A$2:$A$501,0),MATCH(F$2,'Budget original'!$A$2:$AO$2,0)) -> 2500 | J17: =-SUMIFS(BV_Data_An_Cour!$O:$O,BV_Data_An_Cour!$U:$U,$B17,BV_Data_An_Cour!$V:$V,$C17,BV_Data_An_Cour!$W:$W,J$2) -> 0 | K17: =IF(J17=0,0,L17/J17) -> 0 | L17: =-SUMIFS(BV_Data_An_Cour!$O:$O,BV_Data_An_Cour!$U:$U,$B17,BV_Data_An_Cour!$V:$V,$C17,BV_Data_An_Cour!$W:$W,L$2) -> 0 | M17: =J17-D17 -> -1 | N17: =L17-F17 -> -2500 | O17: {=+INDEX('Réel 2023'!$A$2:$AO$501,MATCH($A17,'Réel 2023'!$A$2:$A$501,0),MATCH(O$2,'Réel 2023'!$A$2:$AO$2,0))} -> 1 | P17: =IF(O17=0,0,Q17/O17) -> 5638.25 | Q17: {=+INDEX('Réel 2023'!$A$2:$AO$501,MATCH($A17,'Réel 2023'!$A$2:$A$501,0),MATCH(Q$2,'Réel 2023'!$A$2:$AO$2,0))} -> 5638.25 | R17: =J17-O17 -> -1 | S17: =L17-Q17 -> -5638.25
A18: =+B18&C18 -> Véhicules neufs | B18: =+$K$1 -> Véhicules neufs
A19: =+B19&C19 -> Véhicules neufsRachat bail | B19: =+$K$1 -> Véhicules neufs | C19: Rachat bail | D19: =+INDEX('Budget original'!$A$2:$AO$501,MATCH($A19,'Budget original'!$A$2:$A$501,0),MATCH(D$2,'Budget original'!$A$2:$AO$2,0)) -> 0 | E19: =IF(D19=0,0,F19/D19) -> 0 | F19: =+INDEX('Budget original'!$A$2:$AO$501,MATCH($A19,'Budget original'!$A$2:$A$501,0),MATCH(F$2,'Budget original'!$A$2:$AO$2,0)) -> 5546.8032 | L19: =-SUMIFS(BV_Data_An_Cour!$O:$O,BV_Data_An_Cour!$U:$U,$B19,BV_Data_An_Cour!$V:$V,$C19,BV_Data_An_Cour!$W:$W,L$2) -> 3495.39 | N19: =L19-F19 -> -2051.4132 | Q19: {=+INDEX('Réel 2023'!$A$2:$AO$501,MATCH($A19,'Réel 2023'!$A$2:$A$501,0),MATCH(Q$2,'Réel 2023'!$A$2:$AO$2,0))} -> 8990.92 | R19: =O19-K19 -> 0 | S19: =L19-Q19 -> -5495.53
A20: =+B20&C20 -> Véhicules neufs | B20: =+$K$1 -> Véhicules neufs
A21: =+B21&C21 -> Véhicules neufsRev. Finances | B21: =+$K$1 -> Véhicules neufs | C21: Rev. Finances | D21: =+INDEX('Budget original'!$A$2:$AO$501,MATCH($A21,'Budget original'!$A$2:$A$501,0),MATCH(D$2,'Budget original'!$A$2:$AO$2,0)) -> 0 | E21: =IF(D21=0,0,F21/D21) -> 0 | F21: =+INDEX('Budget original'!$A$2:$AO$501,MATCH($A21,'Budget original'!$A$2:$A$501,0),MATCH(F$2,'Budget original'!$A$2:$AO$2,0)) -> 2720 | K21: =IF(J13=0,0,L21/(J13+J15)) -> 0 | L21: =-SUMIFS(BV_Data_An_Cour!$O:$O,BV_Data_An_Cour!$U:$U,$B21,BV_Data_An_Cour!$V:$V,$C21,BV_Data_An_Cour!$W:$W,L$2) -> 0 | N21: =L21-F21 -> -2720 | Q21: {=+INDEX('Réel 2023'!$A$2:$AO$501,MATCH($A21,'Réel 2023'!$A$2:$A$501,0),MATCH(Q$2,'Réel 2023'!$A$2:$AO$2,0))} -> 1100 | R21: =O21-K21 -> 0 | S21: =L21-Q21 -> -1100
A22: =+B22&C22 -> Véhicules neufsRev. Protections | B22: =+$K$1 -> Véhicules neufs | C22: Rev. Protections | D22: =+INDEX('Budget original'!$A$2:$AO$501,MATCH($A22,'Budget original'!$A$2:$A$501,0),MATCH(D$2,'Budget original'!$A$2:$AO$2,0)) -> 0 | E22: =IF(D22=0,0,F22/D22) -> 0 | F22: =+INDEX('Budget original'!$A$2:$AO$501,MATCH($A22,'Budget original'!$A$2:$A$501,0),MATCH(F$2,'Budget original'!$A$2:$AO$2,0)) -> 32640 | K22: =IF(J13=0,0,L22/(J13+J15)) -> 1293.3413 | L22: =-SUMIFS(BV_Data_An_Cour!$O:$O,BV_Data_An_Cour!$U:$U,$B22,BV_Data_An_Cour!$V:$V,$C22,BV_Data_An_Cour!$W:$W,L$2) -> 38800.24 | N22: =L22-F22 -> 6160.24 | Q22: {=+INDEX('Réel 2023'!$A$2:$AO$501,MATCH($A22,'Réel 2023'!$A$2:$A$501,0),MATCH(Q$2,'Réel 2023'!$A$2:$AO$2,0))} -> 32302.33 | R22: =O22-K22 -> -1293.3413 | S22: =L22-Q22 -> 6497.91
A23: =+B23&C23 -> Véhicules neufsRev. Autres | B23: =+$K$1 -> Véhicules neufs | C23: Rev. Autres | D23: =+INDEX('Budget original'!$A$2:$AO$501,MATCH($A23,'Budget original'!$A$2:$A$501,0),MATCH(D$2,'Budget original'!$A$2:$AO$2,0)) -> 0 | E23: =IF(D23=0,0,F23/D23) -> 0 | F23: =+INDEX('Budget original'!$A$2:$AO$501,MATCH($A23,'Budget original'!$A$2:$A$501,0),MATCH(F$2,'Budget original'!$A$2:$AO$2,0)) -> 15840 | K23: =IF(J13=0,0,L23/(J13+J15)) -> 448.63467 | L23: =-SUMIFS(BV_Data_An_Cour!$O:$O,BV_Data_An_Cour!$U:$U,$B23,BV_Data_An_Cour!$V:$V,$C23,BV_Data_An_Cour!$W:$W,L$2) -> 13459.04 | N23: =L23-F23 -> -2380.96 | Q23: {=+INDEX('Réel 2023'!$A$2:$AO$501,MATCH($A23,'Réel 2023'!$A$2:$A$501,0),MATCH(Q$2,'Réel 2023'!$A$2:$AO$2,0))} -> 10404.95 | R23: =O23-K23 -> -448.63467 | S23: =L23-Q23 -> 3054.09
A24: =+B24&C24 -> Véhicules neufsTotal F&I | B24: =+$K$1 -> Véhicules neufs | C24: Total F&I | D24: =+D15+D13 -> 32 | E24: =IF(D24<=0,0,F24/D24) -> 1600 | F24: =F21+F22+F23 -> 51200 | J24: =+J15+J13 -> 30 | K24: =IF(J24<=0,0,L24/J24) -> 1741.976 | L24: =L21+L22+L23 -> 52259.28 | M24: =J24-D24 -> -2 | N24: =L24-F24 -> 1059.28 | O24: =+O15+O13 -> 23 | P24: =IF(O24<=0,0,Q24/O24) -> 1904.6643 | Q24: =Q21+Q22+Q23 -> 43807.28 | S24: =L24-Q24 -> 8452
A25: =+B25&C25 -> Véhicules neufs | B25: =+$K$1 -> Véhicules neufs | N25: =IF(N24=0,0,N24/F24) -> 0.020689063 | S25: =IF(Q24=0,0,(S24/Q24)) -> 0.19293597
A26: =+B26&C26 -> Véhicules neufs | B26: =+$K$1 -> Véhicules neufs
A27: =+B27&C27 -> Véhicules neufsTotal Dépt. Neufs | B27: =+$K$1 -> Véhicules neufs | C27: Total Dépt. Neufs | D27: =+D13+D15+D17 -> 33 | E27: =IF(D27<=0,0,F27/D27) -> 6682.9769 | F27: =F13+F17+F24+F19+F15 -> 220538.24 | J27: =+J13+J15+J17 -> 30 | K27: =IF(J27<=0,0,L27/J27) -> 6541.5207 | L27: =L13+L17+L24+L19+L15 -> 196245.62 | M27: =J27-D27 -> -3 | N27: =L27-F27 -> -24292.619 | O27: =+O13+O15+O17 -> 24 | P27: =IF(O27<=0,0,Q27/O27) -> 8370.3467 | Q27: =Q13+Q17+Q24+Q19+Q15 -> 200888.32 | R27: =J27-O27 -> 6 | S27: =L27-Q27 -> -4642.7
A28: =+B28&C28 -> Véhicules neufs | B28: =+$K$1 -> Véhicules neufs | M28: =M27/D27 -> -0.090909091 | N28: =N27/F27 -> -0.1101515 | R28: =R27/O27 -> 0.25 | S28: =IF(Q27=0,0,S27/Q27) -> -0.023110851
A29: =+B29&C29 -> Véhicules neufs | B29: =+$K$1 -> Véhicules neufs
A30: =+B30&C30 -> Véhicules neufsDEPENSES | B30: =+$K$1 -> Véhicules neufs | C30: DEPENSES
A31: =+B31&C31 -> Véhicules neufsComm. vendeurs | B31: =+$K$1 -> Véhicules neufs | C31: Comm. vendeurs | D31: =F31/(F13+F15) -> 0.29022398 | E31: =F31/D$24 -> 1462.8326 | F31: =+INDEX('Budget original'!$A$2:$AO$501,MATCH($A31,'Budget original'!$A$2:$A$501,0),MATCH(F$2,'Budget original'!$A$2:$AO$2,0)) -> 46810.642 | J31: =L31/(L13+L15) -> 0.26502027 | K31: =IF(L31=0,0,L31/J$24) -> 1241.0983 | L31: =SUMIFS(BV_Data_An_Cour!$O:$O,BV_Data_An_Cour!$U:$U,$B31,BV_Data_An_Cour!$V:$V,$C31,BV_Data_An_Cour!$W:$W,L$2) -> 37232.95 | N31: =L31-F31 -> -9577.692 | O31: =Q31/(Q13+Q15+Q17) -> 0.27882643 | P31: =Q31/O$24 -> 1795.28 | Q31: {=+INDEX('Réel 2023'!$A$2:$AO$501,MATCH($A31,'Réel 2023'!$A$2:$A$501,0),MATCH(Q$2,'Réel 2023'!$A$2:$AO$2,0))} -> 41291.44 | S31: =L31-Q31 -> -4058.49 | V31: avec boni F&I vendeur 34%
A32: =+B32&C32 -> Véhicules neufsComm. F&I | B32: =+$K$1 -> Véhicules neufs | C32: Comm. F&I | D32: =F32/F24 -> 0.25 | E32: =F32/D$24 -> 400 | F32: =+INDEX('Budget original'!$A$2:$AO$501,MATCH($A32,'Budget original'!$A$2:$A$501,0),MATCH(F$2,'Budget original'!$A$2:$AO$2,0)) -> 12800 | J32: =L32/L24 -> 0.4073422 | K32: =IF(L32=0,0,L32/J$24) -> 709.58033 | L32: =SUMIFS(BV_Data_An_Cour!$O:$O,BV_Data_An_Cour!$U:$U,$B32,BV_Data_An_Cour!$V:$V,$C32,BV_Data_An_Cour!$W:$W,L$2) -> 21287.41 | N32: =L32-F32 -> 8487.41 | O32: =Q32/Q24 -> 0.24755201 | P32: =Q32/O$24 -> 471.50348 | Q32: {=+INDEX('Réel 2023'!$A$2:$AO$501,MATCH($A32,'Réel 2023'!$A$2:$A$501,0),MATCH(Q$2,'Réel 2023'!$A$2:$AO$2,0))} -> 10844.58 | S32: =L32-Q32 -> 10442.83 | V32: sans boni F&I vendeur 26%
A33: =+B33&C33 -> Véhicules neufsFrais de livraison | B33: =+$K$1 -> Véhicules neufs | C33: Frais de livraison | E33: =F33/D$24 -> 100 | F33: =+INDEX('Budget original'!$A$2:$AO$501,MATCH($A33,'Budget original'!$A$2:$A$501,0),MATCH(F$2,'Budget original'!$A$2:$AO$2,0)) -> 3200 | K33: =IF(L33=0,0,L33/J$24) -> 73.194667 | L33: =SUMIFS(BV_Data_An_Cour!$O:$O,BV_Data_An_Cour!$U:$U,$B33,BV_Data_An_Cour!$V:$V,$C33,BV_Data_An_Cour!$W:$W,L$2) -> 2195.84 | N33: =L33-F33 -> -1004.16 | P33: =Q33/O$24 -> 88.415217 | Q33: {=+INDEX('Réel 2023'!$A$2:$AO$501,MATCH($A33,'Réel 2023'!$A$2:$A$501,0),MATCH(Q$2,'Réel 2023'!$A$2:$AO$2,0))} -> 2033.55 | S33: =L33-Q33 -> 162.29
A34: =+B34&C34 -> Véhicules neufsService gratuit 1 | B34: =+$K$1 -> Véhicules neufs | C34: Service gratuit 1 | E34: =F34/D$24 -> 45 | F34: =+INDEX('Budget original'!$A$2:$AO$501,MATCH($A34,'Budget original'!$A$2:$A$501,0),MATCH(F$2,'Budget original'!$A$2:$AO$2,0)) -> 1440 | K34: =IF(L34=0,0,L34/J$24) -> 26.899 | L34: =SUMIFS(BV_Data_An_Cour!$O:$O,BV_Data_An_Cour!$U:$U,$B34,BV_Data_An_Cour!$V:$V,$C34,BV_Data_An_Cour!$W:$W,L$2) -> 806.97 | N34: =L34-F34 -> -633.03 | P34: =Q34/O$24 -> 32.104783 | Q34: {=+INDEX('Réel 2023'!$A$2:$AO$501,MATCH($A34,'Réel 2023'!$A$2:$A$501,0),MATCH(Q$2,'Réel 2023'!$A$2:$AO$2,0))} -> 738.41 | S34: =L34-Q34 -> 68.56
A35: =+B35&C35 -> Véhicules neufsEntretien stock | B35: =+$K$1 -> Véhicules neufs | C35: Entretien stock | E35: =F35/D$24 -> 44.6875 | F35: =+INDEX('Budget original'!$A$2:$AO$501,MATCH($A35,'Budget original'!$A$2:$A$501,0),MATCH(F$2,'Budget original'!$A$2:$AO$2,0)) -> 1430 | K35: =IF(L35=0,0,L35/J$24) -> 62.396 | L35: =SUMIFS(BV_Data_An_Cour!$O:$O,BV_Data_An_Cour!$U:$U,$B35,BV_Data_An_Cour!$V:$V,$C35,BV_Data_An_Cour!$W:$W,L$2) -> 1871.88 | N35: =L35-F35 -> 441.88 | P35: =Q35/O$24 -> 25.156522 | Q35: {=+INDEX('Réel 2023'!$A$2:$AO$501,MATCH($A35,'Réel 2023'!$A$2:$A$501,0),MATCH(Q$2,'Réel 2023'!$A$2:$AO$2,0))} -> 578.6 | S35: =L35-Q35 -> 1293.28
A36: =+B36&C36 -> Véhicules neufsPublicité 1 | B36: =+$K$1 -> Véhicules neufs | C36: Publicité 1 | E36: =F36/D$24 -> 496.60938 | F36: =+INDEX('Budget original'!$A$2:$AO$501,MATCH($A36,'Budget original'!$A$2:$A$501,0),MATCH(F$2,'Budget original'!$A$2:$AO$2,0)) -> 15891.5 | K36: =IF(L36=0,0,L36/J$24) -> 512.11267 | L36: =SUMIFS(BV_Data_An_Cour!$O:$O,BV_Data_An_Cour!$U:$U,$B36,BV_Data_An_Cour!$V:$V,$C36,BV_Data_An_Cour!$W:$W,L$2) -> 15363.38 | N36: =L36-F36 -> -528.12 | P36: =Q36/O$24 -> 727.05478 | Q36: {=+INDEX('Réel 2023'!$A$2:$AO$501,MATCH($A36,'Réel 2023'!$A$2:$A$501,0),MATCH(Q$2,'Réel 2023'!$A$2:$AO$2,0))} -> 16722.26 | S36: =L36-Q36 -> -1358.88 | V36: 15363
A37: =+B37&C37 -> Véhicules neufsIntérêt de gros | B37: =+$K$1 -> Véhicules neufs | C37: Intérêt de gros | E37: =F37/D$24 -> 960.50061 | F37: =+INDEX('Budget original'!$A$2:$AO$501,MATCH($A37,'Budget original'!$A$2:$A$501,0),MATCH(F$2,'Budget original'!$A$2:$AO$2,0)) -> 30736.02 | K37: =IF(L37=0,0,L37/J$24) -> 1210.5003 | L37: =SUMIFS(BV_Data_An_Cour!$O:$O,BV_Data_An_Cour!$U:$U,$B37,BV_Data_An_Cour!$V:$V,$C37,BV_Data_An_Cour!$W:$W,L$2) -> 36315.01 | N37: =L37-F37 -> 5578.9905 | P37: =Q37/O$24 -> 227.60826 | Q37: {=+INDEX('Réel 2023'!$A$2:$AO$501,MATCH($A37,'Réel 2023'!$A$2:$A$501,0),MATCH(Q$2,'Réel 2023'!$A$2:$AO$2,0))} -> 5234.99 | S37: =L37-Q37 -> 31080.02 | V37: 36315
A38: =+B38&C38 -> Véhicules neufs[...] | B38: =+$K$1 -> Véhicules neufs | C38: [...] | E38: =F38/D$24 -> 0 | F38: =+INDEX('Budget original'!$A$2:$AO$501,MATCH($A38,'Budget original'!$A$2:$A$501,0),MATCH(F$2,'Budget original'!$A$2:$AO$2,0)) -> 0 | K38: =IF(L38=0,0,L38/J$24) -> 0 | L38: =SUMIFS(BV_Data_An_Cour!$O:$O,BV_Data_An_Cour!$U:$U,$B38,BV_Data_An_Cour!$V:$V,$C38,BV_Data_An_Cour!$W:$W,L$2) -> 0 | N38: =L38-F38 -> 0 | P38: =Q38/O$24 -> 0 | Q38: {=+INDEX('Réel 2023'!$A$2:$AO$501,MATCH($A38,'Réel 2023'!$A$2:$A$501,0),MATCH(Q$2,'Réel 2023'!$A$2:$AO$2,0))} -> 0 | S38: =L38-Q38 -> 0
A39: =+B39&C39 -> Véhicules neufs[...] | B39: =+$K$1 -> Véhicules neufs | C39: [...] | E39: =F39/D$24 -> 0 | F39: =+INDEX('Budget original'!$A$2:$AO$501,MATCH($A39,'Budget original'!$A$2:$A$501,0),MATCH(F$2,'Budget original'!$A$2:$AO$2,0)) -> 0 | K39: =IF(L39=0,0,L39/J$24) -> 0 | L39: =SUMIFS(BV_Data_An_Cour!$O:$O,BV_Data_An_Cour!$U:$U,$B39,BV_Data_An_Cour!$V:$V,$C39,BV_Data_An_Cour!$W:$W,L$2) -> 0 | N39: =L39-F39 -> 0 | P39: =Q39/O$24 -> 0 | Q39: {=+INDEX('Réel 2023'!$A$2:$AO$501,MATCH($A39,'Réel 2023'!$A$2:$A$501,0),MATCH(Q$2,'Réel 2023'!$A$2:$AO$2,0))} -> 0 | S39: =L39-Q39 -> 0
A40: =+B40&C40 -> Véhicules neufs[...] | B40: =+$K$1 -> Véhicules neufs | C40: [...] | E40: =F40/D$24 -> 0 | F40: =+INDEX('Budget original'!$A$2:$AO$501,MATCH($A40,'Budget original'!$A$2:$A$501,0),MATCH(F$2,'Budget original'!$A$2:$AO$2,0)) -> 0 | K40: =IF(L40=0,0,L40/J$24) -> 0 | L40: =SUMIFS(BV_Data_An_Cour!$O:$O,BV_Data_An_Cour!$U:$U,$B40,BV_Data_An_Cour!$V:$V,$C40,BV_Data_An_Cour!$W:$W,L$2) -> 0 | N40: =L40-F40 -> 0 | P40: =Q40/O$24 -> 0 | Q40: {=+INDEX('Réel 2023'!$A$2:$AO$501,MATCH($A40,'Réel 2023'!$A$2:$A$501,0),MATCH(Q$2,'Réel 2023'!$A$2:$AO$2,0))} -> 0 | S40: =L40-Q40 -> 0
A41: =+B41&C41 -> Véhicules neufsTOTAL VARIABLES | B41: =+$K$1 -> Véhicules neufs | C41: TOTAL VARIABLES | D41: % brut | E41: =F41/F$27 -> 0.50924575 | F41: =SUM(F31:F40) -> 112308.16 | J41: % brut | K41: =L41/L$27 -> 0.58637456 | L41: =SUM(L31:L40) -> 115073.44 | N41: =L41-F41 -> 2765.2784 | O41: % brut | P41: =Q41/Q$27 -> 0.38550688 | Q41: =SUM(Q31:Q40) -> 77443.83 | S41: =L41-Q41 -> 37629.61
A42: =+B42&C42 -> Véhicules neufsSalaires cadres | B42: =+$K$1 -> Véhicules neufs | C42: Salaires cadres | F42: =+INDEX('Budget original'!$A$2:$AO$501,MATCH($A42,'Budget original'!$A$2:$A$501,0),MATCH(F$2,'Budget original'!$A$2:$AO$2,0)) -> 12551.696 | L42: =SUMIFS(BV_Data_An_Cour!$O:$O,BV_Data_An_Cour!$U:$U,$B42,BV_Data_An_Cour!$V:$V,$C42,BV_Data_An_Cour!$W:$W,L$2) -> 12302.2 | N42: =L42-F42 -> -249.49555 | Q42: {=+INDEX('Réel 2023'!$A$2:$AO$501,MATCH($A42,'Réel 2023'!$A$2:$A$501,0),MATCH(Q$2,'Réel 2023'!$A$2:$AO$2,0))} -> 13604.22 | S42: =L42-Q42 -> -1302.02
A43: =+B43&C43 -> Véhicules neufsSalaires commis | B43: =+$K$1 -> Véhicules neufs | C43: Salaires commis | F43: =+INDEX('Budget original'!$A$2:$AO$501,MATCH($A43,'Budget original'!$A$2:$A$501,0),MATCH(F$2,'Budget original'!$A$2:$AO$2,0)) -> 8725.684 | L43: =SUMIFS(BV_Data_An_Cour!$O:$O,BV_Data_An_Cour!$U:$U,$B43,BV_Data_An_Cour!$V:$V,$C43,BV_Data_An_Cour!$W:$W,L$2) -> 8037.27 | N43: =L43-F43 -> -688.41397 | Q43: {=+INDEX('Réel 2023'!$A$2:$AO$501,MATCH($A43,'Réel 2023'!$A$2:$A$501,0),MATCH(Q$2,'Réel 2023'!$A$2:$AO$2,0))} -> 6649.17 | S43: =L43-Q43 -> 1388.1
A44: =+B44&C44 -> Véhicules neufsSalaires autres | B44: =+$K$1 -> Véhicules neufs | C44: Salaires autres | F44: =+INDEX('Budget original'!$A$2:$AO$501,MATCH($A44,'Budget original'!$A$2:$A$501,0),MATCH(F$2,'Budget original'!$A$2:$AO$2,0)) -> 342 | L44: =SUMIFS(BV_Data_An_Cour!$O:$O,BV_Data_An_Cour!$U:$U,$B44,BV_Data_An_Cour!$V:$V,$C44,BV_Data_An_Cour!$W:$W,L$2) -> 342 | N44: =L44-F44 -> 0 | Q44: {=+INDEX('Réel 2023'!$A$2:$AO$501,MATCH($A44,'Réel 2023'!$A$2:$A$501,0),MATCH(Q$2,'Réel 2023'!$A$2:$AO$2,0))} -> 342 | S44: =L44-Q44 -> 0
A45: =+B45&C45 -> Véhicules neufsSalaires spécialistes | B45: =+$K$1 -> Véhicules neufs | C45: Salaires spécialistes | F45: =+INDEX('Budget original'!$A$2:$AO$501,MATCH($A45,'Budget original'!$A$2:$A$501,0),MATCH(F$2,'Budget original'!$A$2:$AO$2,0)) -> 0 | L45: =SUMIFS(BV_Data_An_Cour!$O:$O,BV_Data_An_Cour!$U:$U,$B45,BV_Data_An_Cour!$V:$V,$C45,BV_Data_An_Cour!$W:$W,L$2) -> 0 | N45: =L45-F45 -> 0 | Q45: {=+INDEX('Réel 2023'!$A$2:$AO$501,MATCH($A45,'Réel 2023'!$A$2:$A$501,0),MATCH(Q$2,'Réel 2023'!$A$2:$AO$2,0))} -> 0 | S45: =L45-Q45 -> 0
A46: =+B46&C46 -> Véhicules neufs[...] | B46: =+$K$1 -> Véhicules neufs | C46: [...] | F46: =+INDEX('Budget original'!$A$2:$AO$501,MATCH($A46,'Budget original'!$A$2:$A$501,0),MATCH(F$2,'Budget original'!$A$2:$AO$2,0)) -> 0 | L46: =SUMIFS(BV_Data_An_Cour!$O:$O,BV_Data_An_Cour!$U:$U,$B46,BV_Data_An_Cour!$V:$V,$C46,BV_Data_An_Cour!$W:$W,L$2) -> 0 | N46: =L46-F46 -> 0 | Q46: {=+INDEX('Réel 2023'!$A$2:$AO$501,MATCH($A46,'Réel 2023'!$A$2:$A$501,0),MATCH(Q$2,'Réel 2023'!$A$2:$AO$2,0))} -> 0 | S46: =L46-Q46 -> 0
A47: =+B47&C47 -> Véhicules neufs[...] | B47: =+$K$1 -> Véhicules neufs | C47: [...] | F47: =+INDEX('Budget original'!$A$2:$AO$501,MATCH($A47,'Budget original'!$A$2:$A$501,0),MATCH(F$2,'Budget original'!$A$2:$AO$2,0)) -> 0 | L47: =SUMIFS(BV_Data_An_Cour!$O:$O,BV_Data_An_Cour!$U:$U,$B47,BV_Data_An_Cour!$V:$V,$C47,BV_Data_An_Cour!$W:$W,L$2) -> 0 | N47: =L47-F47 -> 0 | Q47: {=+INDEX('Réel 2023'!$A$2:$AO$501,MATCH($A47,'Réel 2023'!$A$2:$A$501,0),MATCH(Q$2,'Réel 2023'!$A$2:$AO$2,0))} -> 0 | S47: =L47-Q47 -> 0
A48: =+B48&C48 -> Véhicules neufs[...] | B48: =+$K$1 -> Véhicules neufs | C48: [...] | F48: =+INDEX('Budget original'!$A$2:$AO$501,MATCH($A48,'Budget original'!$A$2:$A$501,0),MATCH(F$2,'Budget original'!$A$2:$AO$2,0)) -> 0 | L48: =SUMIFS(BV_Data_An_Cour!$O:$O,BV_Data_An_Cour!$U:$U,$B48,BV_Data_An_Cour!$V:$V,$C48,BV_Data_An_Cour!$W:$W,L$2) -> 0 | N48: =L48-F48 -> 0 | Q48: {=+INDEX('Réel 2023'!$A$2:$AO$501,MATCH($A48,'Réel 2023'!$A$2:$A$501,0),MATCH(Q$2,'Réel 2023'!$A$2:$AO$2,0))} -> 0 | S48: =L48-Q48 -> 0
A49: =+B49&C49 -> Véhicules neufsSalaires en absences | B49: =+$K$1 -> Véhicules neufs | C49: Salaires en absences | F49: =+INDEX('Budget original'!$A$2:$AO$501,MATCH($A49,'Budget original'!$A$2:$A$501,0),MATCH(F$2,'Budget original'!$A$2:$AO$2,0)) -> 9076.1105 | L49: =SUMIFS(BV_Data_An_Cour!$O:$O,BV_Data_An_Cour!$U:$U,$B49,BV_Data_An_Cour!$V:$V,$C49,BV_Data_An_Cour!$W:$W,L$2) -> 4466.22 | N49: =L49-F49 -> -4609.8905 | Q49: {=+INDEX('Réel 2023'!$A$2:$AO$501,MATCH($A49,'Réel 2023'!$A$2:$A$501,0),MATCH(Q$2,'Réel 2023'!$A$2:$AO$2,0))} -> 5562.25 | S49: =L49-Q49 -> -1096.03
A50: =+B50&C50 -> Véhicules neufsDéduction à la source | B50: =+$K$1 -> Véhicules neufs | C50: Déduction à la source | F50: =+INDEX('Budget original'!$A$2:$AO$501,MATCH($A50,'Budget original'!$A$2:$A$501,0),MATCH(F$2,'Budget original'!$A$2:$AO$2,0)) -> 11970.581 | L50: =SUMIFS(BV_Data_An_Cour!$O:$O,BV_Data_An_Cour!$U:$U,$B50,BV_Data_An_Cour!$V:$V,$C50,BV_Data_An_Cour!$W:$W,L$2) -> 10796.69 | N50: =L50-F50 -> -1173.8907 | Q50: {=+INDEX('Réel 2023'!$A$2:$AO$501,MATCH($A50,'Réel 2023'!$A$2:$A$501,0),MATCH(Q$2,'Réel 2023'!$A$2:$AO$2,0))} -> 10343.44 | S50: =L50-Q50 -> 453.25
A51: =+B51&C51 -> Véhicules neufsBénéfices marginaux | B51: =+$K$1 -> Véhicules neufs | C51: Bénéfices marginaux | F51: =+INDEX('Budget original'!$A$2:$AO$501,MATCH($A51,'Budget original'!$A$2:$A$501,0),MATCH(F$2,'Budget original'!$A$2:$AO$2,0)) -> 5457.1765 | L51: =SUMIFS(BV_Data_An_Cour!$O:$O,BV_Data_An_Cour!$U:$U,$B51,BV_Data_An_Cour!$V:$V,$C51,BV_Data_An_Cour!$W:$W,L$2) -> 4198.83 | N51: =L51-F51 -> -1258.3465 | Q51: {=+INDEX('Réel 2023'!$A$2:$AO$501,MATCH($A51,'Réel 2023'!$A$2:$A$501,0),MATCH(Q$2,'Réel 2023'!$A$2:$AO$2,0))} -> 3409.51 | S51: =L51-Q51 -> 789.32
A52: =+B52&C52 -> Véhicules neufsCsst | B52: =+$K$1 -> Véhicules neufs | C52: Csst | F52: =+INDEX('Budget original'!$A$2:$AO$501,MATCH($A52,'Budget original'!$A$2:$A$501,0),MATCH(F$2,'Budget original'!$A$2:$AO$2,0)) -> 1232.2657 | L52: =SUMIFS(BV_Data_An_Cour!$O:$O,BV_Data_An_Cour!$U:$U,$B52,BV_Data_An_Cour!$V:$V,$C52,BV_Data_An_Cour!$W:$W,L$2) -> 1249.8 | N52: =L52-F52 -> 17.534344 | Q52: {=+INDEX('Réel 2023'!$A$2:$AO$501,MATCH($A52,'Réel 2023'!$A$2:$A$501,0),MATCH(Q$2,'Réel 2023'!$A$2:$AO$2,0))} -> 900.84 | S52: =L52-Q52 -> 348.96
A53: =+B53&C53 -> Véhicules neufs[...] | B53: =+$K$1 -> Véhicules neufs | C53: [...] | D53: =VLOOKUP(C53,$B$2:$B$46,1,FALSE) -> #N/A | F53: =+INDEX('Budget original'!$A$2:$AO$501,MATCH($A53,'Budget original'!$A$2:$A$501,0),MATCH(F$2,'Budget original'!$A$2:$AO$2,0)) -> 0 | L53: =SUMIFS(BV_Data_An_Cour!$O:$O,BV_Data_An_Cour!$U:$U,$B53,BV_Data_An_Cour!$V:$V,$C53,BV_Data_An_Cour!$W:$W,L$2) -> 0 | N53: =L53-F53 -> 0 | Q53: {=+INDEX('Réel 2023'!$A$2:$AO$501,MATCH($A53,'Réel 2023'!$A$2:$A$501,0),MATCH(Q$2,'Réel 2023'!$A$2:$AO$2,0))} -> 0 | S53: =L53-Q53 -> 0
A54: =+B54&C54 -> Véhicules neufsTOTAL PERSONNEL | B54: =+$K$1 -> Véhicules neufs | C54: TOTAL PERSONNEL | D54: % brut | E54: =F54/F$27 -> 0.22379571 | F54: =+SUM(F42:F53) -> 49355.513 | J54: % brut | K54: =L54/L$27 -> 0.2109245 | L54: =+SUM(L42:L53) -> 41393.01 | N54: =+SUM(N42:N53) -> -7962.5028 | O54: % brut | P54: =Q54/Q$27 -> 0.20315482 | Q54: =+SUM(Q42:Q53) -> 40811.43 | S54: =+SUM(S42:S53) -> 581.58
A55: =+B55&C55 -> Véhicules neufsPublicité 2 | B55: =+$K$1 -> Véhicules neufs | C55: Publicité 2 | F55: =+INDEX('Budget original'!$A$2:$AO$501,MATCH($A55,'Budget original'!$A$2:$A$501,0),MATCH(F$2,'Budget original'!$A$2:$AO$2,0)) -> 0 | L55: =SUMIFS(BV_Data_An_Cour!$O:$O,BV_Data_An_Cour!$U:$U,$B55,BV_Data_An_Cour!$V:$V,$C55,BV_Data_An_Cour!$W:$W,L$2) -> 0 | N55: =L55-F55 -> 0 | Q55: {=+INDEX('Réel 2023'!$A$2:$AO$501,MATCH($A55,'Réel 2023'!$A$2:$A$501,0),MATCH(Q$2,'Réel 2023'!$A$2:$AO$2,0))} -> 0 | S55: =L55-Q55 -> 0
A56: =+B56&C56 -> Véhicules neufsService gratuit 2 | B56: =+$K$1 -> Véhicules neufs | C56: Service gratuit 2 | F56: =+INDEX('Budget original'!$A$2:$AO$501,MATCH($A56,'Budget original'!$A$2:$A$501,0),MATCH(F$2,'Budget original'!$A$2:$AO$2,0)) -> 0 | L56: =SUMIFS(BV_Data_An_Cour!$O:$O,BV_Data_An_Cour!$U:$U,$B56,BV_Data_An_Cour!$V:$V,$C56,BV_Data_An_Cour!$W:$W,L$2) -> 0 | N56: =L56-F56 -> 0 | Q56: {=+INDEX('Réel 2023'!$A$2:$AO$501,MATCH($A56,'Réel 2023'!$A$2:$A$501,0),MATCH(Q$2,'Réel 2023'!$A$2:$AO$2,0))} -> 0 | S56: =L56-Q56 -> 0
A57: =+B57&C57 -> Véhicules neufsFrais véhicules de cie | B57: =+$K$1 -> Véhicules neufs | C57: Frais véhicules de cie | F57: =+INDEX('Budget original'!$A$2:$AO$501,MATCH($A57,'Budget original'!$A$2:$A$501,0),MATCH(F$2,'Budget original'!$A$2:$AO$2,0)) -> 5080.0833 | L57: =SUMIFS(BV_Data_An_Cour!$O:$O,BV_Data_An_Cour!$U:$U,$B57,BV_Data_An_Cour!$V:$V,$C57,BV_Data_An_Cour!$W:$W,L$2) -> 4993.44 | N57: =L57-F57 -> -86.643333 | Q57: {=+INDEX('Réel 2023'!$A$2:$AO$501,MATCH($A57,'Réel 2023'!$A$2:$A$501,0),MATCH(Q$2,'Réel 2023'!$A$2:$AO$2,0))} -> 3938.31 | S57: =L57-Q57 -> 1055.13
A58: =+B58&C58 -> Véhicules neufsInformatique | B58: =+$K$1 -> Véhicules neufs | C58: Informatique | F58: =+INDEX('Budget original'!$A$2:$AO$501,MATCH($A58,'Budget original'!$A$2:$A$501,0),MATCH(F$2,'Budget original'!$A$2:$AO$2,0)) -> 4993.05 | L58: =SUMIFS(BV_Data_An_Cour!$O:$O,BV_Data_An_Cour!$U:$U,$B58,BV_Data_An_Cour!$V:$V,$C58,BV_Data_An_Cour!$W:$W,L$2) -> 4537.54 | N58: =L58-F58 -> -455.51 | Q58: {=+INDEX('Réel 2023'!$A$2:$AO$501,MATCH($A58,'Réel 2023'!$A$2:$A$501,0),MATCH(Q$2,'Réel 2023'!$A$2:$AO$2,0))} -> 4620.97 | S58: =L58-Q58 -> -83.43
A59: =+B59&C59 -> Véhicules neufsFrais de déplacement | B59: =+$K$1 -> Véhicules neufs | C59: Frais de déplacement | F59: =+INDEX('Budget original'!$A$2:$AO$501,MATCH($A59,'Budget original'!$A$2:$A$501,0),MATCH(F$2,'Budget original'!$A$2:$AO$2,0)) -> 822.6 | L59: =SUMIFS(BV_Data_An_Cour!$O:$O,BV_Data_An_Cour!$U:$U,$B59,BV_Data_An_Cour!$V:$V,$C59,BV_Data_An_Cour!$W:$W,L$2) -> 1481.23 | N59: =L59-F59 -> 658.63 | Q59: {=+INDEX('Réel 2023'!$A$2:$AO$501,MATCH($A59,'Réel 2023'!$A$2:$A$501,0),MATCH(Q$2,'Réel 2023'!$A$2:$AO$2,0))} -> 524.23 | S59: =L59-Q59 -> 957
A60: =+B60&C60 -> Véhicules neufsServices extérieurs | B60: =+$K$1 -> Véhicules neufs | C60: Services extérieurs | F60: =+INDEX('Budget original'!$A$2:$AO$501,MATCH($A60,'Budget original'!$A$2:$A$501,0),MATCH(F$2,'Budget original'!$A$2:$AO$2,0)) -> 2754.45 | L60: =SUMIFS(BV_Data_An_Cour!$O:$O,BV_Data_An_Cour!$U:$U,$B60,BV_Data_An_Cour!$V:$V,$C60,BV_Data_An_Cour!$W:$W,L$2) -> 3008.26 | N60: =L60-F60 -> 253.81 | Q60: {=+INDEX('Réel 2023'!$A$2:$AO$501,MATCH($A60,'Réel 2023'!$A$2:$A$501,0),MATCH(Q$2,'Réel 2023'!$A$2:$AO$2,0))} -> 3346.33 | S60: =L60-Q60 -> -338.07
A61: =+B61&C61 -> Véhicules neufsFournitures autres | B61: =+$K$1 -> Véhicules neufs | C61: Fournitures autres | F61: =+INDEX('Budget original'!$A$2:$AO$501,MATCH($A61,'Budget original'!$A$2:$A$501,0),MATCH(F$2,'Budget original'!$A$2:$AO$2,0)) -> 100 | L61: =SUMIFS(BV_Data_An_Cour!$O:$O,BV_Data_An_Cour!$U:$U,$B61,BV_Data_An_Cour!$V:$V,$C61,BV_Data_An_Cour!$W:$W,L$2) -> 2.49 | N61: =L61-F61 -> -97.51 | Q61: {=+INDEX('Réel 2023'!$A$2:$AO$501,MATCH($A61,'Réel 2023'!$A$2:$A$501,0),MATCH(Q$2,'Réel 2023'!$A$2:$AO$2,0))} -> 20.69 | S61: =L61-Q61 -> -18.2
A62: =+B62&C62 -> Véhicules neufsUniformes | B62: =+$K$1 -> Véhicules neufs | C62: Uniformes | F62: =+INDEX('Budget original'!$A$2:$AO$501,MATCH($A62,'Budget original'!$A$2:$A$501,0),MATCH(F$2,'Budget original'!$A$2:$AO$2,0)) -> 15 | L62: =SUMIFS(BV_Data_An_Cour!$O:$O,BV_Data_An_Cour!$U:$U,$B62,BV_Data_An_Cour!$V:$V,$C62,BV_Data_An_Cour!$W:$W,L$2) -> 0 | N62: =L62-F62 -> -15 | Q62: {=+INDEX('Réel 2023'!$A$2:$AO$501,MATCH($A62,'Réel 2023'!$A$2:$A$501,0),MATCH(Q$2,'Réel 2023'!$A$2:$AO$2,0))} -> 83.14 | S62: =L62-Q62 -> -83.14
A63: =+B63&C63 -> Véhicules neufsPapeterie | B63: =+$K$1 -> Véhicules neufs | C63: Papeterie | F63: =+INDEX('Budget original'!$A$2:$AO$501,MATCH($A63,'Budget original'!$A$2:$A$501,0),MATCH(F$2,'Budget original'!$A$2:$AO$2,0)) -> 787.5 | L63: =SUMIFS(BV_Data_An_Cour!$O:$O,BV_Data_An_Cour!$U:$U,$B63,BV_Data_An_Cour!$V:$V,$C63,BV_Data_An_Cour!$W:$W,L$2) -> 431.9 | N63: =L63-F63 -> -355.6 | Q63: {=+INDEX('Réel 2023'!$A$2:$AO$501,MATCH($A63,'Réel 2023'!$A$2:$A$501,0),MATCH(Q$2,'Réel 2023'!$A$2:$AO$2,0))} -> 578.44 | S63: =L63-Q63 -> -146.54
A64: =+B64&C64 -> Véhicules neufsTéléphone | B64: =+$K$1 -> Véhicules neufs | C64: Téléphone | F64: =+INDEX('Budget original'!$A$2:$AO$501,MATCH($A64,'Budget original'!$A$2:$A$501,0),MATCH(F$2,'Budget original'!$A$2:$AO$2,0)) -> 210.4 | L64: =SUMIFS(BV_Data_An_Cour!$O:$O,BV_Data_An_Cour!$U:$U,$B64,BV_Data_An_Cour!$V:$V,$C64,BV_Data_An_Cour!$W:$W,L$2) -> 235.92 | N64: =L64-F64 -> 25.52 | Q64: {=+INDEX('Réel 2023'!$A$2:$AO$501,MATCH($A64,'Réel 2023'!$A$2:$A$501,0),MATCH(Q$2,'Réel 2023'!$A$2:$AO$2,0))} -> 173.28 | S64: =L64-Q64 -> 62.64
A65: =+B65&C65 -> Véhicules neufsFrais postaux | B65: =+$K$1 -> Véhicules neufs | C65: Frais postaux | F65: =+INDEX('Budget original'!$A$2:$AO$501,MATCH($A65,'Budget original'!$A$2:$A$501,0),MATCH(F$2,'Budget original'!$A$2:$AO$2,0)) -> 225 | L65: =SUMIFS(BV_Data_An_Cour!$O:$O,BV_Data_An_Cour!$U:$U,$B65,BV_Data_An_Cour!$V:$V,$C65,BV_Data_An_Cour!$W:$W,L$2) -> 258.2 | N65: =L65-F65 -> 33.2 | Q65: {=+INDEX('Réel 2023'!$A$2:$AO$501,MATCH($A65,'Réel 2023'!$A$2:$A$501,0),MATCH(Q$2,'Réel 2023'!$A$2:$AO$2,0))} -> 295.54 | S65: =L65-Q65 -> -37.34
A66: =+B66&C66 -> Véhicules neufsDivers | B66: =+$K$1 -> Véhicules neufs | C66: Divers | F66: =+INDEX('Budget original'!$A$2:$AO$501,MATCH($A66,'Budget original'!$A$2:$A$501,0),MATCH(F$2,'Budget original'!$A$2:$AO$2,0)) -> 836.1 | L66: =SUMIFS(BV_Data_An_Cour!$O:$O,BV_Data_An_Cour!$U:$U,$B66,BV_Data_An_Cour!$V:$V,$C66,BV_Data_An_Cour!$W:$W,L$2) -> 832.95 | N66: =L66-F66 -> -3.15 | Q66: {=+INDEX('Réel 2023'!$A$2:$AO$501,MATCH($A66,'Réel 2023'!$A$2:$A$501,0),MATCH(Q$2,'Réel 2023'!$A$2:$AO$2,0))} -> 858.09 | S66: =L66-Q66 -> -25.14
... A68: =+B68&C68 -> Véhicules neufsFrais bancaires | B68: =+$K$1 -> Véhicules neufs | C68: Frais bancaires | F68: =+INDEX('Budget original'!$A$2:$AO$501,MATCH($A68,'Budget original'!$A$2:$A$501,0),MATCH(F$2,'Budget original'!$A$2:$AO$2,0)) -> 3524.2641 | L68: =SUMIFS(BV_Data_An_Cour!$O:$O,BV_Data_An_Cour!$U:$U,$B68,BV_Data_An_Cour!$V:$V,$C68,BV_Data_An_Cour!$W:$W,L$2) -> 4388.05 | N68: =L68-F68 -> 863.78587 | Q68: {=+INDEX('Réel 2023'!$A$2:$AO$501,MATCH($A68,'Réel 2023'!$A$2:$A$501,0),MATCH(Q$2,'Réel 2023'!$A$2:$AO$2,0))} -> 3314.97 | S68: =L68-Q68 -> 1073.08
A69: =+B69&C69 -> Véhicules neufs[...] | B69: =+$K$1 -> Véhicules neufs | C69: [...] | F69: =+INDEX('Budget original'!$A$2:$AO$501,MATCH($A69,'Budget original'!$A$2:$A$501,0),MATCH(F$2,'Budget original'!$A$2:$AO$2,0)) -> 0 | N69: =L69-F69 -> 0 | Q69: {=+INDEX('Réel 2023'!$A$2:$AO$501,MATCH($A69,'Réel 2023'!$A$2:$A$501,0),MATCH(Q$2,'Réel 2023'!$A$2:$AO$2,0))} -> 0 | S69: =L69-Q69 -> 0
A70: =+B70&C70 -> Véhicules neufs[...] | B70: =+$K$1 -> Véhicules neufs | C70: [...] | F70: =+INDEX('Budget original'!$A$2:$AO$501,MATCH($A70,'Budget original'!$A$2:$A$501,0),MATCH(F$2,'Budget original'!$A$2:$AO$2,0)) -> 0 | L70: =SUMIFS(BV_Data_An_Cour!$O:$O,BV_Data_An_Cour!$U:$U,$B70,BV_Data_An_Cour!$V:$V,$C70,BV_Data_An_Cour!$W:$W,L$2) -> 0 | N70: =L70-F70 -> 0 | Q70: {=+INDEX('Réel 2023'!$A$2:$AO$501,MATCH($A70,'Réel 2023'!$A$2:$A$501,0),MATCH(Q$2,'Réel 2023'!$A$2:$AO$2,0))} -> 0 | S70: =L70-Q70 -> 0
A71: =+B71&C71 -> Véhicules neufs[...] | B71: =+$K$1 -> Véhicules neufs | C71: [...] | F71: =+INDEX('Budget original'!$A$2:$AO$501,MATCH($A71,'Budget original'!$A$2:$A$501,0),MATCH(F$2,'Budget original'!$A$2:$AO$2,0)) -> 0 | L71: =SUMIFS(BV_Data_An_Cour!$O:$O,BV_Data_An_Cour!$U:$U,$B71,BV_Data_An_Cour!$V:$V,$C71,BV_Data_An_Cour!$W:$W,L$2)*0.32 -> 0 | N71: =L71-F71 -> 0 | Q71: {=+INDEX('Réel 2023'!$A$2:$AO$501,MATCH($A71,'Réel 2023'!$A$2:$A$501,0),MATCH(Q$2,'Réel 2023'!$A$2:$AO$2,0))} -> 0 | S71: =L71-Q71 -> 0
A72: =+B72&C72 -> Véhicules neufsTOTAL SEMI-FIXES | B72: =+$K$1 -> Véhicules neufs | C72: TOTAL SEMI-FIXES | D72: % brut | E72: =F72/F$27 -> 0.089919151 | F72: =+SUM(F55:F71) -> 19830.611 | J72: % brut | K72: =L72/L$27 -> 0.10541998 | L72: =+SUM(L55:L71) -> 20688.21 | N72: =+SUM(N55:N71) -> 857.59872 | O72: % brut | P72: =Q72/Q$27 -> 0.089672162 | Q72: =+SUM(Q55:Q71) -> 18014.09 | S72: =+SUM(S55:S71) -> 2674.12
A73: =+B73&C73 -> Véhicules neufs | B73: =+$K$1 -> Véhicules neufs
A74: =+B74&C74 -> Véhicules neufsTOTAL DES DÉPENSES | B74: =+$K$1 -> Véhicules neufs | C74: TOTAL DES DÉPENSES | D74: % brut | E74: =F74/F$27 -> 0.82296062 | F74: =F41+F54+F72 -> 181494.29 | J74: % brut | K74: =L74/L$27 -> 0.90271905 | L74: =L41+L54+L72 -> 177154.66 | N74: =L74-F74 -> -4339.6257 | O74: % brut | P74: =Q74/Q$27 -> 0.67833386 | Q74: =Q41+Q54+Q72 -> 136269.35 | S74: =L74-Q74 -> 40885.31
A75: =+B75&C75 -> Véhicules neufsRBSC neuf | B75: =+$K$1 -> Véhicules neufs | C75: RBSC neuf | F75: =+INDEX('Budget original'!$A$2:$AO$501,MATCH($A75,'Budget original'!$A$2:$A$501,0),MATCH(F$2,'Budget original'!$A$2:$AO$2,0)) -> 48049.457 | L75: =-SUMIFS(BV_Data_An_Cour!$O:$O,BV_Data_An_Cour!$U:$U,$B75,BV_Data_An_Cour!$V:$V,$C75,BV_Data_An_Cour!$W:$W,L$2) -> 56342.42 | N75: =L75-F75 -> 8292.9629 | Q75: =+INDEX('Réel 2023'!$A$2:$AO$501,MATCH($A75,'Réel 2023'!$A$2:$A$501,0),MATCH(Q$2,'Réel 2023'!$A$2:$AO$2,0)) -> 44091.88 | S75: =L75-Q75 -> 12250.54
A76: =+B76&C76 -> Véhicules neufsProgramme neuf 2 | B76: =+$K$1 -> Véhicules neufs | C76: Programme neuf 2 | F76: =+INDEX('Budget original'!$A$2:$AO$501,MATCH($A76,'Budget original'!$A$2:$A$501,0),MATCH(F$2,'Budget original'!$A$2:$AO$2,0)) -> 0 | L76: =-SUMIFS(BV_Data_An_Cour!$O:$O,BV_Data_An_Cour!$U:$U,$B76,BV_Data_An_Cour!$V:$V,$C76,BV_Data_An_Cour!$W:$W,L$2) -> 0 | N76: =L76-F76 -> 0 | Q76: {=+INDEX('Réel 2023'!$A$2:$AO$501,MATCH($A76,'Réel 2023'!$A$2:$A$501,0),MATCH(Q$2,'Réel 2023'!$A$2:$AO$2,0))} -> 0 | S76: =L76-Q76 -> 0
A77: =+B77&C77 -> Véhicules neufsProgramme neuf 3 | B77: =+$K$1 -> Véhicules neufs | C77: Programme neuf 3 | F77: =+INDEX('Budget original'!$A$2:$AO$501,MATCH($A77,'Budget original'!$A$2:$A$501,0),MATCH(F$2,'Budget original'!$A$2:$AO$2,0)) -> 0 | L77: =-SUMIFS(BV_Data_An_Cour!$O:$O,BV_Data_An_Cour!$U:$U,$B77,BV_Data_An_Cour!$V:$V,$C77,BV_Data_An_Cour!$W:$W,L$2) -> 0 | N77: =L77-F77 -> 0 | Q77: {=+INDEX('Réel 2023'!$A$2:$AO$501,MATCH($A77,'Réel 2023'!$A$2:$A$501,0),MATCH(Q$2,'Réel 2023'!$A$2:$AO$2,0))} -> 0 | S77: =L77-Q77 -> 0
A78: =+B78&C78 -> Véhicules neufsHoldbacks | B78: =+$K$1 -> Véhicules neufs | C78: Holdbacks | F78: =+INDEX('Budget original'!$A$2:$AO$501,MATCH($A78,'Budget original'!$A$2:$A$501,0),MATCH(F$2,'Budget original'!$A$2:$AO$2,0)) -> 54913.665 | L78: =-SUMIFS(BV_Data_An_Cour!$O:$O,BV_Data_An_Cour!$U:$U,$B78,BV_Data_An_Cour!$V:$V,$C78,BV_Data_An_Cour!$W:$W,L$2) -> 47079 | N78: =L78-F78 -> -7834.6652 | Q78: {=+INDEX('Réel 2023'!$A$2:$AO$501,MATCH($A78,'Réel 2023'!$A$2:$A$501,0),MATCH(Q$2,'Réel 2023'!$A$2:$AO$2,0))} -> 48030.4 | S78: =L78-Q78 -> -951.4
A79: =+B79&C79 -> Véhicules neufs[...] | B79: =+$K$1 -> Véhicules neufs | C79: [...] | F79: =+INDEX('Budget original'!$A$2:$AO$501,MATCH($A79,'Budget original'!$A$2:$A$501,0),MATCH(F$2,'Budget original'!$A$2:$AO$2,0)) -> 0 | L79: =-SUMIFS(BV_Data_An_Cour!$O:$O,BV_Data_An_Cour!$U:$U,$B79,BV_Data_An_Cour!$V:$V,$C79,BV_Data_An_Cour!$W:$W,L$2) -> 0 | N79: =L79-F79 -> 0 | Q79: {=+INDEX('Réel 2023'!$A$2:$AO$501,MATCH($A79,'Réel 2023'!$A$2:$A$501,0),MATCH(Q$2,'Réel 2023'!$A$2:$AO$2,0))} -> 0 | S79: =L79-Q79 -> 0
A80: =+B80&C80 -> Véhicules neufs[...] | B80: =+$K$1 -> Véhicules neufs | C80: [...] | F80: =+INDEX('Budget original'!$A$2:$AO$501,MATCH($A80,'Budget original'!$A$2:$A$501,0),MATCH(F$2,'Budget original'!$A$2:$AO$2,0)) -> 0 | L80: =-SUMIFS(BV_Data_An_Cour!$O:$O,BV_Data_An_Cour!$U:$U,$B80,BV_Data_An_Cour!$V:$V,$C80,BV_Data_An_Cour!$W:$W,L$2) -> 0 | N80: =L80-F80 -> 0 | Q80: {=+INDEX('Réel 2023'!$A$2:$AO$501,MATCH($A80,'Réel 2023'!$A$2:$A$501,0),MATCH(Q$2,'Réel 2023'!$A$2:$AO$2,0))} -> 0 | S80: =L80-Q80 -> 0
A81: =+B81&C81 -> Véhicules neufs[...] | B81: =+$K$1 -> Véhicules neufs | C81: [...] | F81: =+INDEX('Budget original'!$A$2:$AO$501,MATCH($A81,'Budget original'!$A$2:$A$501,0),MATCH(F$2,'Budget original'!$A$2:$AO$2,0)) -> 0 | L81: =-SUMIFS(BV_Data_An_Cour!$O:$O,BV_Data_An_Cour!$U:$U,$B81,BV_Data_An_Cour!$V:$V,$C81,BV_Data_An_Cour!$W:$W,L$2) -> 0 | N81: =L81-F81 -> 0 | Q81: {=+INDEX('Réel 2023'!$A$2:$AO$501,MATCH($A81,'Réel 2023'!$A$2:$A$501,0),MATCH(Q$2,'Réel 2023'!$A$2:$AO$2,0))} -> 0 | S81: =L81-Q81 -> 0
A82: =+B82&C82 -> Véhicules neufsFrais administration | B82: =+$K$1 -> Véhicules neufs | C82: Frais administration | F82: =+INDEX('Budget original'!$A$2:$AO$501,MATCH($A82,'Budget original'!$A$2:$A$501,0),MATCH(F$2,'Budget original'!$A$2:$AO$2,0)) -> 18849.6 | L82: =-SUMIFS(BV_Data_An_Cour!$O:$O,BV_Data_An_Cour!$U:$U,$B82,BV_Data_An_Cour!$V:$V,$C82,BV_Data_An_Cour!$W:$W,L$2) -> 17850 | N82: =L82-F82 -> -999.6 | Q82: {=+INDEX('Réel 2023'!$A$2:$AO$501,MATCH($A82,'Réel 2023'!$A$2:$A$501,0),MATCH(Q$2,'Réel 2023'!$A$2:$AO$2,0))} -> 13685 | S82: =L82-Q82 -> 4165
A83: =+B83&C83 -> Véhicules neufsAUTRES REVENUS | B83: =+$K$1 -> Véhicules neufs | C83: AUTRES REVENUS | F83: =+SUM(F75:F82) -> 121812.72 | L83: =+SUM(L75:L82) -> 121271.42 | N83: =+SUM(N75:N82) -> -541.30231 | Q83: =+SUM(Q75:Q82) -> 105807.28 | S83: =+SUM(S75:S82) -> 15464.14
A84: =+B84&C84 -> Véhicules neufs | B84: =+$K$1 -> Véhicules neufs
A85: =+B85&C85 -> Véhicules neufsPROFIT DÉPARTEMENTAL | B85: =+$K$1 -> Véhicules neufs | C85: PROFIT DÉPARTEMENTAL | F85: =F27-F74+F83 -> 160856.68 | L85: =L27-L74+L83 -> 140362.38 | N85: =N27-N41-N54-N72+N83 -> -20494.296 | Q85: =Q27-Q74+Q83 -> 170426.25 | S85: =S27-S41-S54-S72+S83 -> -30063.87
C89: =C1 -> BMW Sherbrooke | K89: Véhicules usagés | S89: =$S$1 -> Réalisé, Avril 2024
D91: BUDGET ORIGINAL | J91: RÉALISATION | M91: ÉCART réel / Budget | O91: ANNÉE PRÉCÉDENTE | R91: ECART (réel/ Ann.Préc.)
D92: UNITE | E92: $P/UNITÉ | F92: $PROFITS | J92: UNITE | K92: $P/UNITE | L92: $PROFITS | M92: UNFTÉ | N92: $PROFFTS | O92: UNITE | P92: $P/UNITÉ | Q92: $PROFITS | R92: UNITE | S92: $PROFITS
A93: =+B93&C93 -> Véhicules usagésVentes nettes | B93: Véhicules usagés | C93: Ventes nettes | F93: =+INDEX('Budget original'!$A$2:$AO$501,MATCH($A93,'Budget original'!$A$2:$A$501,0),MATCH(F$2,'Budget original'!$A$2:$AO$2,0)) -> 1661741.4 | L93: =-SUMIFS(BV_Data_An_Cour!$O:$O,BV_Data_An_Cour!$X:$X,"Oui",BV_Data_An_Cour!$U:$U,$B93) -> 1837134.2 | Q93: {=+INDEX('Réel 2023'!$A$2:$AO$501,MATCH($A93,'Réel 2023'!$A$2:$A$501,0),MATCH(Q$2,'Réel 2023'!$A$2:$AO$2,0))} -> 1647548.1
A94: =+B94&C94 -> Véhicules usagésCertifié | B94: Véhicules usagés | C94: Certifié | D94: =+INDEX('Budget original'!$A$2:$AO$501,MATCH($A94,'Budget original'!$A$2:$A$501,0),MATCH(D$2,'Budget original'!$A$2:$AO$2,0)) -> 7 | E94: =IF(D94=0,0,F94/D94) -> 3000 | F94: =+INDEX('Budget original'!$A$2:$AO$501,MATCH($A94,'Budget original'!$A$2:$A$501,0),MATCH(F$2,'Budget original'!$A$2:$AO$2,0)) -> 21000 | J94: =-SUMIFS(BV_Data_An_Cour!$O:$O,BV_Data_An_Cour!$U:$U,$B94,BV_Data_An_Cour!$V:$V,$C94,BV_Data_An_Cour!$W:$W,J$2) -> 7 | K94: =IF(J94=0,0,L94/J94) -> 1622.3443 | L94: =-SUMIFS(BV_Data_An_Cour!$O:$O,BV_Data_An_Cour!$U:$U,$B94,BV_Data_An_Cour!$V:$V,$C94,BV_Data_An_Cour!$W:$W,$L2) -> 11356.41 | M94: =J94-D94 -> 0 | N94: =L94-F94 -> -9643.59 | O94: {=+INDEX('Réel 2023'!$A$2:$AO$501,MATCH($A94,'Réel 2023'!$A$2:$A$501,0),MATCH(O$2,'Réel 2023'!$A$2:$AO$2,0))} -> 3 | P94: =IF(O94=0,0,Q94/O94) -> 2381.7333 | Q94: {=+INDEX('Réel 2023'!$A$2:$AO$501,MATCH($A94,'Réel 2023'!$A$2:$A$501,0),MATCH(Q$2,'Réel 2023'!$A$2:$AO$2,0))} -> 7145.2 | R94: =J94-O94 -> 4 | S94: =L94-Q94 -> 4211.21
A95: =+B95&C95 -> Véhicules usagésNon Certifié | B95: Véhicules usagés | C95: Non Certifié | D95: =+INDEX('Budget original'!$A$2:$AO$501,MATCH($A95,'Budget original'!$A$2:$A$501,0),MATCH(D$2,'Budget original'!$A$2:$AO$2,0)) -> 5 | E95: =IF(D95=0,0,F95/D95) -> 2200 | F95: =+INDEX('Budget original'!$A$2:$AO$501,MATCH($A95,'Budget original'!$A$2:$A$501,0),MATCH(F$2,'Budget original'!$A$2:$AO$2,0)) -> 11000 | J95: =-SUMIFS(BV_Data_An_Cour!$O:$O,BV_Data_An_Cour!$U:$U,$B95,BV_Data_An_Cour!$V:$V,$C95,BV_Data_An_Cour!$W:$W,J$2) -> 9 | K95: =IF(J95=0,0,L95/J95) -> 1875.23 | L95: =-SUMIFS(BV_Data_An_Cour!$O:$O,BV_Data_An_Cour!$U:$U,$B95,BV_Data_An_Cour!$V:$V,$C95,BV_Data_An_Cour!$W:$W,$L2) -> 16877.07 | M95: =J95-D95 -> 4 | N95: =L95-F95 -> 5877.07 | O95: {=+INDEX('Réel 2023'!$A$2:$AO$501,MATCH($A95,'Réel 2023'!$A$2:$A$501,0),MATCH(O$2,'Réel 2023'!$A$2:$AO$2,0))} -> 14 | P95: =IF(O95=0,0,Q95/O95) -> 2545.8421 | Q95: {=+INDEX('Réel 2023'!$A$2:$AO$501,MATCH($A95,'Réel 2023'!$A$2:$A$501,0),MATCH(Q$2,'Réel 2023'!$A$2:$AO$2,0))} -> 35641.79 | R95: =J95-O95 -> -5 | S95: =L95-Q95 -> -18764.72
A96: =+B96&C96 -> Véhicules usagésAutres marques | B96: Véhicules usagés | C96: Autres marques | D96: =+INDEX('Budget original'!$A$2:$AO$501,MATCH($A96,'Budget original'!$A$2:$A$501,0),MATCH(D$2,'Budget original'!$A$2:$AO$2,0)) -> 9 | E96: =IF(D96=0,0,F96/D96) -> 1850 | F96: =+INDEX('Budget original'!$A$2:$AO$501,MATCH($A96,'Budget original'!$A$2:$A$501,0),MATCH(F$2,'Budget original'!$A$2:$AO$2,0)) -> 16650 | J96: =-SUMIFS(BV_Data_An_Cour!$O:$O,BV_Data_An_Cour!$U:$U,$B96,BV_Data_An_Cour!$V:$V,$C96,BV_Data_An_Cour!$W:$W,J$2) -> 12 | K96: =IF(J96=0,0,L96/J96) -> 862.97167 | L96: =-SUMIFS(BV_Data_An_Cour!$O:$O,BV_Data_An_Cour!$U:$U,$B96,BV_Data_An_Cour!$V:$V,$C96,BV_Data_An_Cour!$W:$W,$L2) -> 10355.66 | M96: =J96-D96 -> 3 | N96: =L96-F96 -> -6294.34 | O96: =+INDEX('Réel 2023'!$A$2:$AO$501,MATCH($A96,'Réel 2023'!$A$2:$A$501,0),MATCH(O$2,'Réel 2023'!$A$2:$AO$2,0)) -> 0 | P96: =IF(O96=0,0,Q96/O96) -> 0 | Q96: =+INDEX('Réel 2023'!$A$2:$AO$501,MATCH($A96,'Réel 2023'!$A$2:$A$501,0),MATCH(Q$2,'Réel 2023'!$A$2:$AO$2,0)) -> 0 | R96: =J96-O96 -> 12 | S96: =L96-Q96 -> 10355.66
A97: =+B97&C97 -> Véhicules usagésTotal Usagés | B97: Véhicules usagés | C97: Total Usagés | D97: =+D95+D94+D96 -> 21 | E97: =IF(D97=0,0,F97/D97) -> 2316.6667 | F97: =+F94+F95+F96 -> 48650 | J97: =+J94+J95+J96 -> 28 | K97: =IF(J97<=0,0,L97/J97) -> 1378.1836 | L97: =+L94+L95+L96 -> 38589.14 | M97: =J97-D97 -> 7 | N97: =L97-F97 -> -10060.86 | O97: =+O95+O94+O96 -> 17 | P97: =IF(O97=0,0,Q97/O97) -> 2516.8818 | Q97: =+Q94+Q95+Q96 -> 42786.99 | R97: =R94+R95 -> -1 | S97: =S94+S95 -> -14553.51
A98: =+B98&C98 -> Véhicules usagés | B98: Véhicules usagés | M98: =M97/D97 -> 0.33333333 | N98: =N97/F97 -> -0.20680082 | R98: =R97/O97 -> -0.058823529 | S98: =IF(Q97=0,0,(S97/Q97)) -> -0.34013867
A99: =+B99&C99 -> Véhicules usagés | B99: Véhicules usagés
A100: =+B100&C100 -> Véhicules usagésVentes au Gros | B100: Véhicules usagés | C100: Ventes au Gros | D100: =+INDEX('Budget original'!$A$2:$AO$501,MATCH($A100,'Budget original'!$A$2:$A$501,0),MATCH(D$2,'Budget original'!$A$2:$AO$2,0)) -> 23 | E100: =IF(D100=0,0,F100/D100) -> 375 | F100: =+INDEX('Budget original'!$A$2:$AO$501,MATCH($A100,'Budget original'!$A$2:$A$501,0),MATCH(F$2,'Budget original'!$A$2:$AO$2,0)) -> 8625 | J100: =-SUMIFS(BV_Data_An_Cour!$O:$O,BV_Data_An_Cour!$U:$U,$B100,BV_Data_An_Cour!$V:$V,$C100,BV_Data_An_Cour!$W:$W,J$2) -> 16 | K100: =IF(J100=0,0,L100/J100) -> 462.19375 | L100: =-SUMIFS(BV_Data_An_Cour!$O:$O,BV_Data_An_Cour!$U:$U,$B100,BV_Data_An_Cour!$V:$V,$C100,BV_Data_An_Cour!$W:$W,L$2) -> 7395.1 | M100: =J100-D100 -> -7 | N100: =L100-F100 -> -1229.9 | O100: {=+INDEX('Réel 2023'!$A$2:$AO$501,MATCH($A100,'Réel 2023'!$A$2:$A$501,0),MATCH(O$2,'Réel 2023'!$A$2:$AO$2,0))} -> 21 | P100: =IF(O100=0,0,Q100/O100) -> 470.61238 | Q100: {=+INDEX('Réel 2023'!$A$2:$AO$501,MATCH($A100,'Réel 2023'!$A$2:$A$501,0),MATCH(Q$2,'Réel 2023'!$A$2:$AO$2,0))} -> 9882.86 | R100: =J100-O100 -> -5 | S100: =L100-Q100 -> -2487.76
A101: =+B101&C101 -> Véhicules usagés | B101: Véhicules usagés
A102: =+B102&C102 -> Véhicules usagésRev. Finances | B102: Véhicules usagés | C102: Rev. Finances | D102: =+INDEX('Budget original'!$A$2:$AO$501,MATCH($A102,'Budget original'!$A$2:$A$501,0),MATCH(D$2,'Budget original'!$A$2:$AO$2,0)) -> 0 | E102: =IF(D102=0,0,F102/D102) -> 0 | F102: =+INDEX('Budget original'!$A$2:$AO$501,MATCH($A102,'Budget original'!$A$2:$A$501,0),MATCH(F$2,'Budget original'!$A$2:$AO$2,0)) -> 12600 | K102: =IF(J97=0,0,L102/J97) -> 469.70679 | L102: =-SUMIFS(BV_Data_An_Cour!$O:$O,BV_Data_An_Cour!$U:$U,$B102,BV_Data_An_Cour!$V:$V,$C102,BV_Data_An_Cour!$W:$W,$L2) -> 13151.79 | N102: =L102-F102 -> 551.79 | Q102: {=+INDEX('Réel 2023'!$A$2:$AO$501,MATCH($A102,'Réel 2023'!$A$2:$A$501,0),MATCH(Q$2,'Réel 2023'!$A$2:$AO$2,0))} -> 13597.2 | R102: =O102-K102 -> -469.70679 | S102: =L102-Q102 -> -445.41
A103: =+B103&C103 -> Véhicules usagésRev. Protections | B103: Véhicules usagés | C103: Rev. Protections | D103: =+INDEX('Budget original'!$A$2:$AO$501,MATCH($A103,'Budget original'!$A$2:$A$501,0),MATCH(D$2,'Budget original'!$A$2:$AO$2,0)) -> 0 | E103: =IF(D103=0,0,F103/D103) -> 0 | F103: =+INDEX('Budget original'!$A$2:$AO$501,MATCH($A103,'Budget original'!$A$2:$A$501,0),MATCH(F$2,'Budget original'!$A$2:$AO$2,0)) -> 18480 | K103: =IF(J97=0,0,L103/J97) -> 654.39286 | L103: =-SUMIFS(BV_Data_An_Cour!$O:$O,BV_Data_An_Cour!$U:$U,$B103,BV_Data_An_Cour!$V:$V,$C103,BV_Data_An_Cour!$W:$W,$L2) -> 18323 | N103: =L103-F103 -> -157 | Q103: {=+INDEX('Réel 2023'!$A$2:$AO$501,MATCH($A103,'Réel 2023'!$A$2:$A$501,0),MATCH(Q$2,'Réel 2023'!$A$2:$AO$2,0))} -> 12765.89 | R103: =O103-K103 -> -654.39286 | S103: =L103-Q103 -> 5557.11
A104: =+B104&C104 -> Véhicules usagésRev. Autres | B104: Véhicules usagés | C104: Rev. Autres | D104: =+INDEX('Budget original'!$A$2:$AO$501,MATCH($A104,'Budget original'!$A$2:$A$501,0),MATCH(D$2,'Budget original'!$A$2:$AO$2,0)) -> 0 | E104: =IF(D104=0,0,F104/D104) -> 0 | F104: =+INDEX('Budget original'!$A$2:$AO$501,MATCH($A104,'Budget original'!$A$2:$A$501,0),MATCH(F$2,'Budget original'!$A$2:$AO$2,0)) -> 3570 | K104: =IF(J97=0,0,L104/J97) -> 152.21429 | L104: =-SUMIFS(BV_Data_An_Cour!$O:$O,BV_Data_An_Cour!$U:$U,$B104,BV_Data_An_Cour!$V:$V,$C104,BV_Data_An_Cour!$W:$W,$L$2) -> 4262 | N104: =L104-F104 -> 692 | Q104: {=+INDEX('Réel 2023'!$A$2:$AO$501,MATCH($A104,'Réel 2023'!$A$2:$A$501,0),MATCH(Q$2,'Réel 2023'!$A$2:$AO$2,0))} -> 2900.99 | R104: =O104-K104 -> -152.21429 | S104: =L104-Q104 -> 1361.01
A105: =+B105&C105 -> Véhicules usagésTotal F&I | B105: Véhicules usagés | C105: Total F&I | D105: =D97 -> 21 | E105: =IF(D105=0,0,F105/D105) -> 1650 | F105: =F102+F103+F104 -> 34650 | J105: =J97 -> 28 | K105: =IF(J105<=0,0,L105/J105) -> 1276.3139 | L105: =L102+L103+L104 -> 35736.79 | M105: =J105-D105 -> 7 | N105: =L105-F105 -> 1086.79 | O105: =O97 -> 17 | P105: =IF(O105=0,0,Q105/O105) -> 1721.4165 | Q105: =Q102+Q103+Q104 -> 29264.08 | S105: =L105-Q105 -> 6472.71
...

Sheet Print_AAD
C1: =Parametres!B1 -> BMW Sherbrooke | K1: Véhicules neufs | S1: =CONCATENATE("Réalisé,"," ",Parametres!B3," ",Parametres!B4," AAD") -> Réalisé, Avril 2024 AAD
D2: X | E2: O | F2: U | J2: NB | L2: $ | O2: X | P2: O | Q2: U | X2: X | Y2: O | Z2: U | AJ2: X | AK2: O | AL2: U
D3: BUDGET ORIGINAL | J3: RÉALISATION | M3: ÉCART réel / Budget | O3: ANNÉE PRÉCÉDENTE | R3: ECART (réel/ Ann.Préc.)
D4: UNITE | E4: $P/UNITÉ | F4: $PROFITS | J4: UNITE | K4: $P/UNITE | L4: $PROFITS | M4: UNFTÉ | N4: $PROFITS | O4: UNITE | P4: $P/UNITÉ | Q4: $PROFITS | R4: UNITE | S4: $PROFITS
A5: =+B5&C5 -> Véhicules neufsVentes nettes | B5: =+$K$1 -> Véhicules neufs | C5: Ventes nettes | F5: {=+SUMPRODUCT(('Budget original'!$A$8:$A$501=$A5)*('Budget original'!$C$3:$AO$3=F$2),'Budget original'!$C$8:$AO$501)} -> 7889975.7 | L5: =-SUMIFS(BV_Data_An_Cour!$P:$P,BV_Data_An_Cour!$X:$X,"Oui",BV_Data_An_Cour!$U:$U,$B5) -> 6459230.3 | Q5: {=+SUMPRODUCT(('Réel 2023'!$A$8:$A$501=$A5)*('Réel 2023'!$C$3:$AO$3=Q$2),'Réel 2023'!$C$8:$AO$501)} -> 7287504.7
A6: =+B6&C6 -> Véhicules neufsAutos détail | B6: =+$K$1 -> Véhicules neufs | C6: Autos détail | D6: {=+SUMPRODUCT(('Budget original'!$A$8:$A$501=$A6)*('Budget original'!$C$3:$AO$3=D$2),'Budget original'!$C$8:$AO$501)} -> 26 | E6: =IF(D6=0,0,F6/D6) -> 5144.9383 | F6: {=+SUMPRODUCT(('Budget original'!$A$8:$A$501=$A6)*('Budget original'!$C$3:$AO$3=F$2),'Budget original'!$C$8:$AO$501)} -> 133768.4 | J6: =-SUMIFS(BV_Data_An_Cour!$P:$P,BV_Data_An_Cour!$U:$U,$B6,BV_Data_An_Cour!$V:$V,$C6,BV_Data_An_Cour!$W:$W,J$2) -> 24 | K6: =IF(J6=0,0,L6/J6) -> 5389.0008 | L6: =-SUMIFS(BV_Data_An_Cour!$P:$P,BV_Data_An_Cour!$U:$U,$B6,BV_Data_An_Cour!$V:$V,$C6,BV_Data_An_Cour!$W:$W,L$2) -> 129336.02 | M6: =J6-D6 -> -2 | N6: =L6-F6 -> -4432.3751 | O6: {=+SUMPRODUCT(('Réel 2023'!$A$8:$A$501=$A6)*('Réel 2023'!$C$3:$AO$3=O$2),'Réel 2023'!$C$8:$AO$501)} -> 26 | P6: =IF(O6=0,0,Q6/O6) -> 5676.7119 | Q6: {=+SUMPRODUCT(('Réel 2023'!$A$8:$A$501=$A6)*('Réel 2023'!$C$3:$AO$3=Q$2),'Réel 2023'!$C$8:$AO$501)} -> 147594.51 | R6: =J6-O6 -> -2 | S6: =L6-Q6 -> -18258.49
A7: =+B7&C7 -> Véhicules neufsCamions détail | B7: =+$K$1 -> Véhicules neufs | C7: Camions détail | D7: {=+SUMPRODUCT(('Budget original'!$A$8:$A$501=$A7)*('Budget original'!$C$3:$AO$3=D$2),'Budget original'!$C$8:$AO$501)} -> 50 | E7: =IF(D7=0,0,F7/D7) -> 5386.4238 | F7: {=+SUMPRODUCT(('Budget original'!$A$8:$A$501=$A7)*('Budget original'!$C$3:$AO$3=F$2),'Budget original'!$C$8:$AO$501)} -> 269321.19 | J7: =-SUMIFS(BV_Data_An_Cour!$P:$P,BV_Data_An_Cour!$U:$U,$B7,BV_Data_An_Cour!$V:$V,$C7,BV_Data_An_Cour!$W:$W,J$2) -> 29 | K7: =IF(J7=0,0,L7/J7) -> 5047.0814 | L7: =-SUMIFS(BV_Data_An_Cour!$P:$P,BV_Data_An_Cour!$U:$U,$B7,BV_Data_An_Cour!$V:$V,$C7,BV_Data_An_Cour!$W:$W,L$2) -> 146365.36 | M7: =J7-D7 -> -21 | N7: =L7-F7 -> -122955.83 | O7: {=+SUMPRODUCT(('Réel 2023'!$A$8:$A$501=$A7)*('Réel 2023'!$C$3:$AO$3=O$2),'Réel 2023'!$C$8:$AO$501)} -> 39 | P7: =IF(O7=0,0,Q7/O7) -> 5665.9597 | Q7: {=+SUMPRODUCT(('Réel 2023'!$A$8:$A$501=$A7)*('Réel 2023'!$C$3:$AO$3=Q$2),'Réel 2023'!$C$8:$AO$501)} -> 220972.43 | R7: =J7-O7 -> -10 | S7: =L7-Q7 -> -74607.07
A8: =+B8&C8 -> Véhicules neufsSprinter | B8: =+$K$1 -> Véhicules neufs | C8: Sprinter | D8: {=+SUMPRODUCT(('Budget original'!$A$8:$A$501=$A8)*('Budget original'!$C$3:$AO$3=D$2),'Budget original'!$C$8:$AO$501)} -> 0 | E8: =IF(D8=0,0,F8/D8) -> 0 | F8: {=+SUMPRODUCT(('Budget original'!$A$8:$A$501=$A8)*('Budget original'!$C$3:$AO$3=F$2),'Budget original'!$C$8:$AO$501)} -> 0 | J8: =-SUMIFS(BV_Data_An_Cour!$P:$P,BV_Data_An_Cour!$U:$U,$B8,BV_Data_An_Cour!$V:$V,$C8,BV_Data_An_Cour!$W:$W,J$2) -> 0 | K8: =IF(J8=0,0,L8/J8) -> 0 | L8: =-SUMIFS(BV_Data_An_Cour!$P:$P,BV_Data_An_Cour!$U:$U,$B8,BV_Data_An_Cour!$V:$V,$C8,BV_Data_An_Cour!$W:$W,L$2) -> 0 | M8: =J8-D8 -> 0 | N8: =L8-F8 -> 0 | O8: {=+SUMPRODUCT(('Réel 2023'!$A$8:$A$501=$A8)*('Réel 2023'!$C$3:$AO$3=O$2),'Réel 2023'!$C$8:$AO$501)} -> 0 | P8: =IF(O8=0,0,Q8/O8) -> 0 | Q8: {=+SUMPRODUCT(('Réel 2023'!$A$8:$A$501=$A8)*('Réel 2023'!$C$3:$AO$3=Q$2),'Réel 2023'!$C$8:$AO$501)} -> 0 | R8: =J8-O8 -> 0 | S8: =L8-Q8 -> 0
A9: =+B9&C9 -> Véhicules neufsMoto détail | B9: =+$K$1 -> Véhicules neufs | C9: Moto détail | D9: {=+SUMPRODUCT(('Budget original'!$A$8:$A$501=$A9)*('Budget original'!$C$3:$AO$3=D$2),'Budget original'!$C$8:$AO$501)} -> 0 | E9: =IF(D9=0,0,F9/D9) -> 0 | F9: {=+SUMPRODUCT(('Budget original'!$A$8:$A$501=$A9)*('Budget original'!$C$3:$AO$3=F$2),'Budget original'!$C$8:$AO$501)} -> 0 | J9: =-SUMIFS(BV_Data_An_Cour!$P:$P,BV_Data_An_Cour!$U:$U,$B9,BV_Data_An_Cour!$V:$V,$C9,BV_Data_An_Cour!$W:$W,J$2) -> 0 | K9: =IF(J9=0,0,L9/J9) -> 0 | L9: =-SUMIFS(BV_Data_An_Cour!$P:$P,BV_Data_An_Cour!$U:$U,$B9,BV_Data_An_Cour!$V:$V,$C9,BV_Data_An_Cour!$W:$W,L$2) -> 0 | M9: =J9-D9 -> 0 | N9: =L9-F9 -> 0 | O9: {=+SUMPRODUCT(('Réel 2023'!$A$8:$A$501=$A9)*('Réel 2023'!$C$3:$AO$3=O$2),'Réel 2023'!$C$8:$AO$501)} -> 0 | P9: =IF(O9=0,0,Q9/O9) -> 0 | Q9: {=+SUMPRODUCT(('Réel 2023'!$A$8:$A$501=$A9)*('Réel 2023'!$C$3:$AO$3=Q$2),'Réel 2023'!$C$8:$AO$501)} -> 0 | R9: =J9-O9 -> 0 | S9: =L9-Q9 -> 0
A10: =+B10&C10 -> Véhicules neufs[...] | B10: =+$K$1 -> Véhicules neufs | C10: [...] | D10: {=+SUMPRODUCT(('Budget original'!$A$8:$A$501=$A10)*('Budget original'!$C$3:$AO$3=D$2),'Budget original'!$C$8:$AO$501)} -> 0 | E10: =IF(D10=0,0,F10/D10) -> 0 | F10: {=+SUMPRODUCT(('Budget original'!$A$8:$A$501=$A10)*('Budget original'!$C$3:$AO$3=F$2),'Budget original'!$C$8:$AO$501)} -> 0 | J10: =-SUMIFS(BV_Data_An_Cour!$P:$P,BV_Data_An_Cour!$U:$U,$B10,BV_Data_An_Cour!$V:$V,$C10,BV_Data_An_Cour!$W:$W,J$2) -> 0 | K10: =IF(J10=0,0,L10/J10) -> 0 | L10: =-SUMIFS(BV_Data_An_Cour!$P:$P,BV_Data_An_Cour!$U:$U,$B10,BV_Data_An_Cour!$V:$V,$C10,BV_Data_An_Cour!$W:$W,L$2) -> 0 | M10: =J10-D10 -> 0 | N10: =L10-F10 -> 0 | O10: {=+SUMPRODUCT(('Réel 2023'!$A$8:$A$501=$A10)*('Réel 2023'!$C$3:$AO$3=O$2),'Réel 2023'!$C$8:$AO$501)} -> 0 | P10: =IF(O10=0,0,Q10/O10) -> 0 | Q10: {=+SUMPRODUCT(('Réel 2023'!$A$8:$A$501=$A10)*('Réel 2023'!$C$3:$AO$3=Q$2),'Réel 2023'!$C$8:$AO$501)} -> 0 | R10: =J10-O10 -> 0 | S10: =L10-Q10 -> 0
A11: =+B11&C11 -> Véhicules neufs[...] | B11: =+$K$1 -> Véhicules neufs | C11: [...] | D11: {=+SUMPRODUCT(('Budget original'!$A$8:$A$501=$A11)*('Budget original'!$C$3:$AO$3=D$2),'Budget original'!$C$8:$AO$501)} -> 0 | E11: =IF(D11=0,0,F11/D11) -> 0 | F11: {=+SUMPRODUCT(('Budget original'!$A$8:$A$501=$A11)*('Budget original'!$C$3:$AO$3=F$2),'Budget original'!$C$8:$AO$501)} -> 0 | J11: =-SUMIFS(BV_Data_An_Cour!$P:$P,BV_Data_An_Cour!$U:$U,$B11,BV_Data_An_Cour!$V:$V,$C11,BV_Data_An_Cour!$W:$W,J$2) -> 0 | K11: =IF(J11=0,0,L11/J11) -> 0 | L11: =-SUMIFS(BV_Data_An_Cour!$P:$P,BV_Data_An_Cour!$U:$U,$B11,BV_Data_An_Cour!$V:$V,$C11,BV_Data_An_Cour!$W:$W,L$2) -> 0 | M11: =J11-D11 -> 0 | N11: =L11-F11 -> 0 | O11: {=+SUMPRODUCT(('Réel 2023'!$A$8:$A$501=$A11)*('Réel 2023'!$C$3:$AO$3=O$2),'Réel 2023'!$C$8:$AO$501)} -> 0 | P11: =IF(O11=0,0,Q11/O11) -> 0 | Q11: {=+SUMPRODUCT(('Réel 2023'!$A$8:$A$501=$A11)*('Réel 2023'!$C$3:$AO$3=Q$2),'Réel 2023'!$C$8:$AO$501)} -> 0 | R11: =J11-O11 -> 0 | S11: =L11-Q11 -> 0
A12: =+B12&C12 -> Véhicules neufs[...] | B12: =+$K$1 -> Véhicules neufs | C12: [...] | D12: {=+SUMPRODUCT(('Budget original'!$A$8:$A$501=$A12)*('Budget original'!$C$3:$AO$3=D$2),'Budget original'!$C$8:$AO$501)} -> 0 | E12: =IF(D12=0,0,F12/D12) -> 0 | F12: {=+SUMPRODUCT(('Budget original'!$A$8:$A$501=$A12)*('Budget original'!$C$3:$AO$3=F$2),'Budget original'!$C$8:$AO$501)} -> 0 | J12: =-SUMIFS(BV_Data_An_Cour!$P:$P,BV_Data_An_Cour!$U:$U,$B12,BV_Data_An_Cour!$V:$V,$C12,BV_Data_An_Cour!$W:$W,J$2) -> 0 | K12: =IF(J12=0,0,L12/J12) -> 0 | L12: =-SUMIFS(BV_Data_An_Cour!$P:$P,BV_Data_An_Cour!$U:$U,$B12,BV_Data_An_Cour!$V:$V,$C12,BV_Data_An_Cour!$W:$W,L$2) -> 0 | M12: =J12-D12 -> 0 | N12: =L12-F12 -> 0 | O12: {=+SUMPRODUCT(('Réel 2023'!$A$8:$A$501=$A12)*('Réel 2023'!$C$3:$AO$3=O$2),'Réel 2023'!$C$8:$AO$501)} -> 0 | P12: =IF(O12=0,0,Q12/O12) -> 0 | Q12: {=+SUMPRODUCT(('Réel 2023'!$A$8:$A$501=$A12)*('Réel 2023'!$C$3:$AO$3=Q$2),'Réel 2023'!$C$8:$AO$501)} -> 0 | R12: =J12-O12 -> 0 | S12: =L12-Q12 -> 0
A13: =+B13&C13 -> Véhicules neufsTotal Neufs | B13: =+$K$1 -> Véhicules neufs | C13: Total Neufs | D13: =+SUM(D6:D12) -> 76 | E13: =IF(D13<=0,0,F13/D13) -> 5303.8104 | F13: =+SUM(F6:F12) -> 403089.59 | J13: =+SUM(J6:J12) -> 53 | K13: =IF(J13<=0,0,L13/J13) -> 5201.9128 | L13: =+SUM(L6:L12) -> 275701.38 | M13: =+SUM(M6:M12) -> -23 | N13: =+SUM(N6:N12) -> -127388.21 | O13: =+SUM(O6:O12) -> 65 | P13: =IF(O13<=0,0,Q13/O13) -> 5670.2606 | Q13: =+SUM(Q6:Q12) -> 368566.94 | R13: =+SUM(R6:R12) -> -12 | S13: =+SUM(S6:S12) -> -92865.56
A14: =+B14&C14 -> Véhicules neufs | B14: =+$K$1 -> Véhicules neufs | M14: =IF(D13=0,0,M13/D13) -> -0.30263158 | N14: =IF(F13=0,0,N13/F13) -> -0.31602952 | R14: =R13/O13 -> -0.18461538 | S14: =IF(Q13=0,0,(S13/Q13)) -> -0.25196389
A15: =+B15&C15 -> Véhicules neufsEx-Démos et courtoisies | B15: =+$K$1 -> Véhicules neufs | C15: Ex-Démos et courtoisies | D15: {=+SUMPRODUCT(('Budget original'!$A$8:$A$501=$A15)*('Budget original'!$C$3:$AO$3=D$2),'Budget original'!$C$8:$AO$501)} -> 8 | E15: =IF(D15=0,0,F15/D15) -> 2500 | F15: {=+SUMPRODUCT(('Budget original'!$A$8:$A$501=$A15)*('Budget original'!$C$3:$AO$3=F$2),'Budget original'!$C$8:$AO$501)} -> 20000 | J15: =-SUMIFS(BV_Data_An_Cour!$P:$P,BV_Data_An_Cour!$U:$U,$B15,BV_Data_An_Cour!$V:$V,$C15,BV_Data_An_Cour!$W:$W,J$2) -> 15 | K15: =IF(J15=0,0,L15/J15) -> 2940.3067 | L15: =-SUMIFS(BV_Data_An_Cour!$P:$P,BV_Data_An_Cour!$U:$U,$B15,BV_Data_An_Cour!$V:$V,$C15,BV_Data_An_Cour!$W:$W,L$2) -> 44104.6 | M15: =J15-D15 -> 7 | N15: =L15-F15 -> 24104.6 | O15: {=+SUMPRODUCT(('Réel 2023'!$A$8:$A$501=$A15)*('Réel 2023'!$C$3:$AO$3=O$2),'Réel 2023'!$C$8:$AO$501)} -> 3 | P15: =IF(O15=0,0,Q15/O15) -> 2666.6667 | Q15: {=+SUMPRODUCT(('Réel 2023'!$A$8:$A$501=$A15)*('Réel 2023'!$C$3:$AO$3=Q$2),'Réel 2023'!$C$8:$AO$501)} -> 8000 | R15: =J15-O15 -> 12 | S15: =L15-Q15 -> 36104.6
A16: =+B16&C16 -> Véhicules neufs | B16: =+$K$1 -> Véhicules neufs
A17: =+B17&C17 -> Véhicules neufsFlottes | B17: =+$K$1 -> Véhicules neufs | C17: Flottes | D17: {=+SUMPRODUCT(('Budget original'!$A$8:$A$501=$A17)*('Budget original'!$C$3:$AO$3=D$2),'Budget original'!$C$8:$AO$501)} -> 2 | E17: =IF(D17=0,0,F17/D17) -> 2500 | F17: {=+SUMPRODUCT(('Budget original'!$A$8:$A$501=$A17)*('Budget original'!$C$3:$AO$3=F$2),'Budget original'!$C$8:$AO$501)} -> 5000 | J17: =-SUMIFS(BV_Data_An_Cour!$P:$P,BV_Data_An_Cour!$U:$U,$B17,BV_Data_An_Cour!$V:$V,$C17,BV_Data_An_Cour!$W:$W,J$2) -> 1 | K17: =IF(J17=0,0,L17/J17) -> 0 | L17: =-SUMIFS(BV_Data_An_Cour!$P:$P,BV_Data_An_Cour!$U:$U,$B17,BV_Data_An_Cour!$V:$V,$C17,BV_Data_An_Cour!$W:$W,L$2) -> 0 | M17: =J17-D17 -> -1 | N17: =L17-F17 -> -5000 | O17: {=+SUMPRODUCT(('Réel 2023'!$A$8:$A$501=$A17)*('Réel 2023'!$C$3:$AO$3=O$2),'Réel 2023'!$C$8:$AO$501)} -> 4 | P17: =IF(O17=0,0,Q17/O17) -> 3136.3025 | Q17: {=+SUMPRODUCT(('Réel 2023'!$A$8:$A$501=$A17)*('Réel 2023'!$C$3:$AO$3=Q$2),'Réel 2023'!$C$8:$AO$501)} -> 12545.21 | R17: =J17-O17 -> -3 | S17: =L17-Q17 -> -12545.21
A18: =+B18&C18 -> Véhicules neufs | B18: =+$K$1 -> Véhicules neufs
A19: =+B19&C19 -> Véhicules neufsRachat bail | B19: =+$K$1 -> Véhicules neufs | C19: Rachat bail | D19: {=+SUMPRODUCT(('Budget original'!$A$8:$A$501=$A19)*('Budget original'!$C$3:$AO$3=D$2),'Budget original'!$C$8:$AO$501)} -> 0 | E19: =IF(D19=0,0,F19/D19) -> 0 | F19: {=+SUMPRODUCT(('Budget original'!$A$8:$A$501=$A19)*('Budget original'!$C$3:$AO$3=F$2),'Budget original'!$C$8:$AO$501)} -> 14113.172 | L19: =-SUMIFS(BV_Data_An_Cour!$P:$P,BV_Data_An_Cour!$U:$U,$B19,BV_Data_An_Cour!$V:$V,$C19,BV_Data_An_Cour!$W:$W,L$2) -> 11435.16 | N19: =L19-F19 -> -2678.0116 | O19: {=+SUMPRODUCT(('Réel 2023'!$A$8:$A$501=$A19)*('Réel 2023'!$C$3:$AO$3=O$2),'Réel 2023'!$C$8:$AO$501)} -> 0 | P19: =IF(O19=0,0,Q19/O19) -> 0 | Q19: {=+SUMPRODUCT(('Réel 2023'!$A$8:$A$501=$A19)*('Réel 2023'!$C$3:$AO$3=Q$2),'Réel 2023'!$C$8:$AO$501)} -> 26772.84 | R19: =O19-K19 -> 0 | S19: =L19-Q19 -> -15337.68
A20: =+B20&C20 -> Véhicules neufs | B20: =+$K$1 -> Véhicules neufs
A21: =+B21&C21 -> Véhicules neufsRev. Finances | B21: =+$K$1 -> Véhicules neufs | C21: Rev. Finances | F21: {=+SUMPRODUCT(('Budget original'!$A$8:$A$501=$A21)*('Budget original'!$C$3:$AO$3=F$2),'Budget original'!$C$8:$AO$501)} -> 7140 | K21: =IF(J13=0,0,L21/(J13+J15)) -> 41.8925 | L21: =-SUMIFS(BV_Data_An_Cour!$P:$P,BV_Data_An_Cour!$U:$U,$B21,BV_Data_An_Cour!$V:$V,$C21,BV_Data_An_Cour!$W:$W,L$2) -> 2848.69 | N21: =L21-F21 -> -4291.31 | Q21: {=+SUMPRODUCT(('Réel 2023'!$A$8:$A$501=$A21)*('Réel 2023'!$C$3:$AO$3=Q$2),'Réel 2023'!$C$8:$AO$501)} -> 2905.47 | R21: =O21-K21 -> -41.8925 | S21: =L21-Q21 -> -56.78
A22: =+B22&C22 -> Véhicules neufsRev. Protections | B22: =+$K$1 -> Véhicules neufs | C22: Rev. Protections | F22: {=+SUMPRODUCT(('Budget original'!$A$8:$A$501=$A22)*('Budget original'!$C$3:$AO$3=F$2),'Budget original'!$C$8:$AO$501)} -> 85680 | K22: =IF(J13=0,0,L22/(J13+J15)) -> 1225.7256 | L22: =-SUMIFS(BV_Data_An_Cour!$P:$P,BV_Data_An_Cour!$U:$U,$B22,BV_Data_An_Cour!$V:$V,$C22,BV_Data_An_Cour!$W:$W,L$2) -> 83349.34 | N22: =L22-F22 -> -2330.66 | Q22: {=+SUMPRODUCT(('Réel 2023'!$A$8:$A$501=$A22)*('Réel 2023'!$C$3:$AO$3=Q$2),'Réel 2023'!$C$8:$AO$501)} -> 77170.66 | R22: =O22-K22 -> -1225.7256 | S22: =L22-Q22 -> 6178.68
A23: =+B23&C23 -> Véhicules neufsRev. Autres | B23: =+$K$1 -> Véhicules neufs | C23: Rev. Autres | F23: {=+SUMPRODUCT(('Budget original'!$A$8:$A$501=$A23)*('Budget original'!$C$3:$AO$3=F$2),'Budget original'!$C$8:$AO$501)} -> 41580 | K23: =IF(J13=0,0,L23/(J13+J15)) -> 479.70044 | L23: =-SUMIFS(BV_Data_An_Cour!$P:$P,BV_Data_An_Cour!$U:$U,$B23,BV_Data_An_Cour!$V:$V,$C23,BV_Data_An_Cour!$W:$W,L$2) -> 32619.63 | N23: =L23-F23 -> -8960.37 | Q23: {=+SUMPRODUCT(('Réel 2023'!$A$8:$A$501=$A23)*('Réel 2023'!$C$3:$AO$3=Q$2),'Réel 2023'!$C$8:$AO$501)} -> 33743.84 | R23: =O23-K23 -> -479.70044 | S23: =L23-Q23 -> -1124.21
A24: =+B24&C24 -> Véhicules neufsTotal F&I | B24: =+$K$1 -> Véhicules neufs | C24: Total F&I | D24: =+D15+D13 -> 84 | E24: =IF(D24<=0,0,F24/D24) -> 1600 | F24: =F21+F22+F23 -> 134400 | J24: =+J15+J13 -> 68 | K24: =IF(J24<=0,0,L24/J24) -> 1747.3185 | L24: =L21+L22+L23 -> 118817.66 | M24: =J24-D24 -> -16 | N24: =L24-F24 -> -15582.34 | O24: =+O15+O13 -> 68 | P24: =IF(O24<=0,0,Q24/O24) -> 1673.8231 | Q24: =Q21+Q22+Q23 -> 113819.97 | S24: =L24-Q24 -> 4997.69
A25: =+B25&C25 -> Véhicules neufs | B25: =+$K$1 -> Véhicules neufs | N25: =IF(N24=0,0,N24/F24) -> -0.11594003 | S25: =IF(Q24=0,0,(S24/Q24)) -> 0.043908727
A26: =+B26&C26 -> Véhicules neufs | B26: =+$K$1 -> Véhicules neufs
A27: =+B27&C27 -> Véhicules neufsTotal Dépt. Neufs | B27: =+$K$1 -> Véhicules neufs | C27: Total Dépt. Neufs | D27: =+D13+D15+D17 -> 86 | E27: =IF(D27<=0,0,F27/D27) -> 6704.6832 | F27: =F13+F17+F24+F19+F15 -> 576602.76 | J27: =+J13+J15+J17 -> 69 | K27: =IF(J27<=0,0,L27/J27) -> 6522.5913 | L27: =L13+L17+L24+L19+L15 -> 450058.8 | M27: =J27-D27 -> -17 | N27: =L27-F27 -> -126543.96 | O27: =+O13+O15+O17 -> 72 | P27: =IF(O27<=0,0,Q27/O27) -> 7357.0133 | Q27: =Q13+Q17+Q24+Q19+Q15 -> 529704.96 | R27: =J27-O27 -> -3 | S27: =L27-Q27 -> -79646.16
A28: =+B28&C28 -> Véhicules neufs | B28: =+$K$1 -> Véhicules neufs | M28: =M27/D27 -> -0.19767442 | N28: =N27/F27 -> -0.21946471 | R28: =R27/O27 -> -0.041666667 | S28: =IF(Q27=0,0,S27/Q27) -> -0.15035948
A29: =+B29&C29 -> Véhicules neufs | B29: =+$K$1 -> Véhicules neufs
A30: =+B30&C30 -> Véhicules neufsDEPENSES | B30: =+$K$1 -> Véhicules neufs | C30: DEPENSES
A31: =+B31&C31 -> Véhicules neufsComm. vendeurs | B31: =+$K$1 -> Véhicules neufs | C31: Comm. vendeurs | E31: =F31/D$24 -> 1500.6577 | F31: {=+SUMPRODUCT(('Budget original'!$A$8:$A$501=$A31)*('Budget original'!$C$3:$AO$3=F$2),'Budget original'!$C$8:$AO$501)} -> 126055.25 | J31: =L31/(L13+L15) -> 0.27818801 | K31: =IF(L31=0,0,L31/J$24) -> 1308.3263 | L31: =SUMIFS(BV_Data_An_Cour!$P:$P,BV_Data_An_Cour!$U:$U,$B31,BV_Data_An_Cour!$V:$V,$C31,BV_Data_An_Cour!$W:$W,L$2) -> 88966.19 | N31: =L31-F31 -> -37089.06 | P31: =Q31/O$24 -> 1611.8606 | Q31: {=+SUMPRODUCT(('Réel 2023'!$A$8:$A$501=$A31)*('Réel 2023'!$C$3:$AO$3=Q$2),'Réel 2023'!$C$8:$AO$501)} -> 109606.52 | S31: =L31-Q31 -> -20640.33
A32: =+B32&C32 -> Véhicules neufsComm. F&I | B32: =+$K$1 -> Véhicules neufs | C32: Comm. F&I | E32: =F32/D$24 -> 400 | F32: {=+SUMPRODUCT(('Budget original'!$A$8:$A$501=$A32)*('Budget original'!$C$3:$AO$3=F$2),'Budget original'!$C$8:$AO$501)} -> 33600 | J32: =L32/L24 -> 0.41124914 | K32: =IF(L32=0,0,L32/J$24) -> 718.58324 | L32: =SUMIFS(BV_Data_An_Cour!$P:$P,BV_Data_An_Cour!$U:$U,$B32,BV_Data_An_Cour!$V:$V,$C32,BV_Data_An_Cour!$W:$W,L$2) -> 48863.66 | N32: =L32-F32 -> 15263.66 | P32: =Q32/O$24 -> 416.87838 | Q32: {=+SUMPRODUCT(('Réel 2023'!$A$8:$A$501=$A32)*('Réel 2023'!$C$3:$AO$3=Q$2),'Réel 2023'!$C$8:$AO$501)} -> 28347.73 | S32: =L32-Q32 -> 20515.93
A33: =+B33&C33 -> Véhicules neufsFrais de livraison | B33: =+$K$1 -> Véhicules neufs | C33: Frais de livraison | E33: =F33/D$24 -> 100 | F33: {=+SUMPRODUCT(('Budget original'!$A$8:$A$501=$A33)*('Budget original'!$C$3:$AO$3=F$2),'Budget original'!$C$8:$AO$501)} -> 8400 | K33: =IF(L33=0,0,L33/J$24) -> 113.44382 | L33: =SUMIFS(BV_Data_An_Cour!$P:$P,BV_Data_An_Cour!$U:$U,$B33,BV_Data_An_Cour!$V:$V,$C33,BV_Data_An_Cour!$W:$W,L$2) -> 7714.18 | N33: =L33-F33 -> -685.82 | P33: =Q33/O$24 -> 84.402941 | Q33: {=+SUMPRODUCT(('Réel 2023'!$A$8:$A$501=$A33)*('Réel 2023'!$C$3:$AO$3=Q$2),'Réel 2023'!$C$8:$AO$501)} -> 5739.4 | S33: =L33-Q33 -> 1974.78
A34: =+B34&C34 -> Véhicules neufsService gratuit 1 | B34: =+$K$1 -> Véhicules neufs | C34: Service gratuit 1 | E34: =F34/D$24 -> 45 | F34: {=+SUMPRODUCT(('Budget original'!$A$8:$A$501=$A34)*('Budget original'!$C$3:$AO$3=F$2),'Budget original'!$C$8:$AO$501)} -> 3780 | K34: =IF(L34=0,0,L34/J$24) -> 39.178971 | L34: =SUMIFS(BV_Data_An_Cour!$P:$P,BV_Data_An_Cour!$U:$U,$B34,BV_Data_An_Cour!$V:$V,$C34,BV_Data_An_Cour!$W:$W,L$2) -> 2664.17 | N34: =L34-F34 -> -1115.83 | P34: =Q34/O$24 -> 44.496176 | Q34: {=+SUMPRODUCT(('Réel 2023'!$A$8:$A$501=$A34)*('Réel 2023'!$C$3:$AO$3=Q$2),'Réel 2023'!$C$8:$AO$501)} -> 3025.74 | S34: =L34-Q34 -> -361.57
A35: =+B35&C35 -> Véhicules neufsEntretien stock | B35: =+$K$1 -> Véhicules neufs | C35: Entretien stock | E35: =F35/D$24 -> 47.142857 | F35: {=+SUMPRODUCT(('Budget original'!$A$8:$A$501=$A35)*('Budget original'!$C$3:$AO$3=F$2),'Budget original'!$C$8:$AO$501)} -> 3960 | K35: =IF(L35=0,0,L35/J$24) -> 72.974706 | L35: =SUMIFS(BV_Data_An_Cour!$P:$P,BV_Data_An_Cour!$U:$U,$B35,BV_Data_An_Cour!$V:$V,$C35,BV_Data_An_Cour!$W:$W,L$2) -> 4962.28 | N35: =L35-F35 -> 1002.28 | P35: =Q35/O$24 -> 43.354412 | Q35: {=+SUMPRODUCT(('Réel 2023'!$A$8:$A$501=$A35)*('Réel 2023'!$C$3:$AO$3=Q$2),'Réel 2023'!$C$8:$AO$501)} -> 2948.1 | S35: =L35-Q35 -> 2014.18
A36: =+B36&C36 -> Véhicules neufsPublicité 1 | B36: =+$K$1 -> Véhicules neufs | C36: Publicité 1 | E36: =F36/D$24 -> 496.60938 | F36: {=+SUMPRODUCT(('Budget original'!$A$8:$A$501=$A36)*('Budget original'!$C$3:$AO$3=F$2),'Budget original'!$C$8:$AO$501)} -> 41715.188 | K36: =IF(L36=0,0,L36/J$24) -> 622.98779 | L36: =SUMIFS(BV_Data_An_Cour!$P:$P,BV_Data_An_Cour!$U:$U,$B36,BV_Data_An_Cour!$V:$V,$C36,BV_Data_An_Cour!$W:$W,L$2) -> 42363.17 | N36: =L36-F36 -> 647.9825 | P36: =Q36/O$24 -> 769.65044 | Q36: {=+SUMPRODUCT(('Réel 2023'!$A$8:$A$501=$A36)*('Réel 2023'!$C$3:$AO$3=Q$2),'Réel 2023'!$C$8:$AO$501)} -> 52336.23 | S36: =L36-Q36 -> -9973.06
A37: =+B37&C37 -> Véhicules neufsIntérêt de gros | B37: =+$K$1 -> Véhicules neufs | C37: Intérêt de gros | E37: =F37/D$24 -> 1313.7859 | F37: {=+SUMPRODUCT(('Budget original'!$A$8:$A$501=$A37)*('Budget original'!$C$3:$AO$3=F$2),'Budget original'!$C$8:$AO$501)} -> 110358.01 | K37: =IF(L37=0,0,L37/J$24) -> 1897.5865 | L37: =SUMIFS(BV_Data_An_Cour!$P:$P,BV_Data_An_Cour!$U:$U,$B37,BV_Data_An_Cour!$V:$V,$C37,BV_Data_An_Cour!$W:$W,L$2) -> 129035.88 | N37: =L37-F37 -> 18677.865 | P37: =Q37/O$24 -> 290.55235 | Q37: {=+SUMPRODUCT(('Réel 2023'!$A$8:$A$501=$A37)*('Réel 2023'!$C$3:$AO$3=Q$2),'Réel 2023'!$C$8:$AO$501)} -> 19757.56 | S37: =L37-Q37 -> 109278.32
A38: =+B38&C38 -> Véhicules neufs[...] | B38: =+$K$1 -> Véhicules neufs | C38: [...] | E38: =F38/D$24 -> 0 | F38: {=+SUMPRODUCT(('Budget original'!$A$8:$A$501=$A38)*('Budget original'!$C$3:$AO$3=F$2),'Budget original'!$C$8:$AO$501)} -> 0 | K38: =IF(L38=0,0,L38/J$24) -> 0 | L38: =SUMIFS(BV_Data_An_Cour!$P:$P,BV_Data_An_Cour!$U:$U,$B38,BV_Data_An_Cour!$V:$V,$C38,BV_Data_An_Cour!$W:$W,L$2) -> 0 | N38: =L38-F38 -> 0 | P38: =Q38/O$24 -> 0 | Q38: {=+SUMPRODUCT(('Réel 2023'!$A$8:$A$501=$A38)*('Réel 2023'!$C$3:$AO$3=Q$2),'Réel 2023'!$C$8:$AO$501)} -> 0 | S38: =L38-Q38 -> 0
A39: =+B39&C39 -> Véhicules neufs[...] | B39: =+$K$1 -> Véhicules neufs | C39: [...] | E39: =F39/D$24 -> 0 | F39: {=+SUMPRODUCT(('Budget original'!$A$8:$A$501=$A39)*('Budget original'!$C$3:$AO$3=F$2),'Budget original'!$C$8:$AO$501)} -> 0 | K39: =IF(L39=0,0,L39/J$24) -> 0 | L39: =SUMIFS(BV_Data_An_Cour!$P:$P,BV_Data_An_Cour!$U:$U,$B39,BV_Data_An_Cour!$V:$V,$C39,BV_Data_An_Cour!$W:$W,L$2) -> 0 | N39: =L39-F39 -> 0 | P39: =Q39/O$24 -> 0 | Q39: {=+SUMPRODUCT(('Réel 2023'!$A$8:$A$501=$A39)*('Réel 2023'!$C$3:$AO$3=Q$2),'Réel 2023'!$C$8:$AO$501)} -> 0 | S39: =L39-Q39 -> 0
A40: =+B40&C40 -> Véhicules neufs[...] | B40: =+$K$1 -> Véhicules neufs | C40: [...] | E40: =F40/D$24 -> 0 | F40: {=+SUMPRODUCT(('Budget original'!$A$8:$A$501=$A40)*('Budget original'!$C$3:$AO$3=F$2),'Budget original'!$C$8:$AO$501)} -> 0 | K40: =IF(L40=0,0,L40/J$24) -> 0 | L40: =SUMIFS(BV_Data_An_Cour!$P:$P,BV_Data_An_Cour!$U:$U,$B40,BV_Data_An_Cour!$V:$V,$C40,BV_Data_An_Cour!$W:$W,L$2) -> 0 | N40: =L40-F40 -> 0 | P40: =Q40/O$24 -> 0 | Q40: {=+SUMPRODUCT(('Réel 2023'!$A$8:$A$501=$A40)*('Réel 2023'!$C$3:$AO$3=Q$2),'Réel 2023'!$C$8:$AO$501)} -> 0 | S40: =L40-Q40 -> 0
A41: =+B41&C41 -> Véhicules neufsTOTAL VARIABLES | B41: =+$K$1 -> Véhicules neufs | C41: TOTAL VARIABLES | D41: % brut | E41: =F41/F$27 -> 0.56862103 | F41: =SUM(F31:F40) -> 327868.45 | J41: % brut | K41: =L41/L$27 -> 0.72117139 | L41: =SUM(L31:L40) -> 324569.53 | N41: =L41-F41 -> -3298.9218 | O41: % brut | P41: =Q41/Q$27 -> 0.41865056 | Q41: =SUM(Q31:Q40) -> 221761.28 | S41: =L41-Q41 -> 102808.25
A42: =+B42&C42 -> Véhicules neufsSalaires cadres | B42: =+$K$1 -> Véhicules neufs | C42: Salaires cadres | F42: {=+SUMPRODUCT(('Budget original'!$A$8:$A$501=$A42)*('Budget original'!$C$3:$AO$3=F$2),'Budget original'!$C$8:$AO$501)} -> 50008.309 | L42: =SUMIFS(BV_Data_An_Cour!$P:$P,BV_Data_An_Cour!$U:$U,$B42,BV_Data_An_Cour!$V:$V,$C42,BV_Data_An_Cour!$W:$W,L$2) -> 48542.42 | N42: =L42-F42 -> -1465.8889 | Q42: {=+SUMPRODUCT(('Réel 2023'!$A$8:$A$501=$A42)*('Réel 2023'!$C$3:$AO$3=Q$2),'Réel 2023'!$C$8:$AO$501)} -> 61086.33
A43: =+B43&C43 -> Véhicules neufsSalaires commis | B43: =+$K$1 -> Véhicules neufs | C43: Salaires commis | F43: {=+SUMPRODUCT(('Budget original'!$A$8:$A$501=$A43)*('Budget original'!$C$3:$AO$3=F$2),'Budget original'!$C$8:$AO$501)} -> 34613.582 | L43: =SUMIFS(BV_Data_An_Cour!$P:$P,BV_Data_An_Cour!$U:$U,$B43,BV_Data_An_Cour!$V:$V,$C43,BV_Data_An_Cour!$W:$W,L$2) -> 33263.99 | N43: =L43-F43 -> -1349.5921 | Q43: {=+SUMPRODUCT(('Réel 2023'!$A$8:$A$501=$A43)*('Réel 2023'!$C$3:$AO$3=Q$2),'Réel 2023'!$C$8:$AO$501)} -> 27658.1 | S43: =L43-Q43 -> 5605.89
A44: =+B44&C44 -> Véhicules neufsSalaires autres | B44: =+$K$1 -> Véhicules neufs | C44: Salaires autres | F44: {=+SUMPRODUCT(('Budget original'!$A$8:$A$501=$A44)*('Budget original'!$C$3:$AO$3=F$2),'Budget original'!$C$8:$AO$501)} -> 1368 | L44: =SUMIFS(BV_Data_An_Cour!$P:$P,BV_Data_An_Cour!$U:$U,$B44,BV_Data_An_Cour!$V:$V,$C44,BV_Data_An_Cour!$W:$W,L$2) -> 1368 | N44: =L44-F44 -> 0 | Q44: {=+SUMPRODUCT(('Réel 2023'!$A$8:$A$501=$A44)*('Réel 2023'!$C$3:$AO$3=Q$2),'Réel 2023'!$C$8:$AO$501)} -> 1368 | S44: =L44-Q44 -> 0
A45: =+B45&C45 -> Véhicules neufsSalaires spécialistes | B45: =+$K$1 -> Véhicules neufs | C45: Salaires spécialistes | F45: {=+SUMPRODUCT(('Budget original'!$A$8:$A$501=$A45)*('Budget original'!$C$3:$AO$3=F$2),'Budget original'!$C$8:$AO$501)} -> 0 | L45: =SUMIFS(BV_Data_An_Cour!$P:$P,BV_Data_An_Cour!$U:$U,$B45,BV_Data_An_Cour!$V:$V,$C45,BV_Data_An_Cour!$W:$W,L$2) -> 0 | N45: =L45-F45 -> 0 | Q45: {=+SUMPRODUCT(('Réel 2023'!$A$8:$A$501=$A45)*('Réel 2023'!$C$3:$AO$3=Q$2),'Réel 2023'!$C$8:$AO$501)} -> 0 | S45: =L45-Q45 -> 0
A46: =+B46&C46 -> Véhicules neufs[...] | B46: =+$K$1 -> Véhicules neufs | C46: [...] | F46: {=+SUMPRODUCT(('Budget original'!$A$8:$A$501=$A46)*('Budget original'!$C$3:$AO$3=F$2),'Budget original'!$C$8:$AO$501)} -> 0 | L46: =SUMIFS(BV_Data_An_Cour!$P:$P,BV_Data_An_Cour!$U:$U,$B46,BV_Data_An_Cour!$V:$V,$C46,BV_Data_An_Cour!$W:$W,L$2) -> 0 | N46: =L46-F46 -> 0 | Q46: {=+SUMPRODUCT(('Réel 2023'!$A$8:$A$501=$A46)*('Réel 2023'!$C$3:$AO$3=Q$2),'Réel 2023'!$C$8:$AO$501)} -> 0 | S46: =L46-Q46 -> 0
A47: =+B47&C47 -> Véhicules neufs[...] | B47: =+$K$1 -> Véhicules neufs | C47: [...] | F47: {=+SUMPRODUCT(('Budget original'!$A$8:$A$501=$A47)*('Budget original'!$C$3:$AO$3=F$2),'Budget original'!$C$8:$AO$501)} -> 0 | L47: =SUMIFS(BV_Data_An_Cour!$P:$P,BV_Data_An_Cour!$U:$U,$B47,BV_Data_An_Cour!$V:$V,$C47,BV_Data_An_Cour!$W:$W,L$2) -> 0 | N47: =L47-F47 -> 0 | Q47: {=+SUMPRODUCT(('Réel 2023'!$A$8:$A$501=$A47)*('Réel 2023'!$C$3:$AO$3=Q$2),'Réel 2023'!$C$8:$AO$501)} -> 0 | S47: =L47-Q47 -> 0
A48: =+B48&C48 -> Véhicules neufs[...] | B48: =+$K$1 -> Véhicules neufs | C48: [...] | F48: {=+SUMPRODUCT(('Budget original'!$A$8:$A$501=$A48)*('Budget original'!$C$3:$AO$3=F$2),'Budget original'!$C$8:$AO$501)} -> 0 | L48: =SUMIFS(BV_Data_An_Cour!$P:$P,BV_Data_An_Cour!$U:$U,$B48,BV_Data_An_Cour!$V:$V,$C48,BV_Data_An_Cour!$W:$W,L$2) -> 0 | N48: =L48-F48 -> 0 | Q48: {=+SUMPRODUCT(('Réel 2023'!$A$8:$A$501=$A48)*('Réel 2023'!$C$3:$AO$3=Q$2),'Réel 2023'!$C$8:$AO$501)} -> 0 | S48: =L48-Q48 -> 0
A49: =+B49&C49 -> Véhicules neufsSalaires en absences | B49: =+$K$1 -> Véhicules neufs | C49: Salaires en absences | F49: {=+SUMPRODUCT(('Budget original'!$A$8:$A$501=$A49)*('Budget original'!$C$3:$AO$3=F$2),'Budget original'!$C$8:$AO$501)} -> 27147.548 | L49: =SUMIFS(BV_Data_An_Cour!$P:$P,BV_Data_An_Cour!$U:$U,$B49,BV_Data_An_Cour!$V:$V,$C49,BV_Data_An_Cour!$W:$W,L$2) -> 31183.28 | N49: =L49-F49 -> 4035.7316 | Q49: {=+SUMPRODUCT(('Réel 2023'!$A$8:$A$501=$A49)*('Réel 2023'!$C$3:$AO$3=Q$2),'Réel 2023'!$C$8:$AO$501)} -> 19638.88 | S49: =L49-Q49 -> 11544.4
A50: =+B50&C50 -> Véhicules neufsDéduction à la source | B50: =+$K$1 -> Véhicules neufs | C50: Déduction à la source | F50: {=+SUMPRODUCT(('Budget original'!$A$8:$A$501=$A50)*('Budget original'!$C$3:$AO$3=F$2),'Budget original'!$C$8:$AO$501)} -> 37070.888 | L50: =SUMIFS(BV_Data_An_Cour!$P:$P,BV_Data_An_Cour!$U:$U,$B50,BV_Data_An_Cour!$V:$V,$C50,BV_Data_An_Cour!$W:$W,L$2) -> 39328.01 | N50: =L50-F50 -> 2257.1221 | Q50: {=+SUMPRODUCT(('Réel 2023'!$A$8:$A$501=$A50)*('Réel 2023'!$C$3:$AO$3=Q$2),'Réel 2023'!$C$8:$AO$501)} -> 35619.23 | S50: =L50-Q50 -> 3708.78
A51: =+B51&C51 -> Véhicules neufsBénéfices marginaux | B51: =+$K$1 -> Véhicules neufs | C51: Bénéfices marginaux | F51: {=+SUMPRODUCT(('Budget original'!$A$8:$A$501=$A51)*('Budget original'!$C$3:$AO$3=F$2),'Budget original'!$C$8:$AO$501)} -> 16899.964 | L51: =SUMIFS(BV_Data_An_Cour!$P:$P,BV_Data_An_Cour!$U:$U,$B51,BV_Data_An_Cour!$V:$V,$C51,BV_Data_An_Cour!$W:$W,L$2) -> 16432.44 | N51: =L51-F51 -> -467.52358 | Q51: {=+SUMPRODUCT(('Réel 2023'!$A$8:$A$501=$A51)*('Réel 2023'!$C$3:$AO$3=Q$2),'Réel 2023'!$C$8:$AO$501)} -> 11948.07 | S51: =L51-Q51 -> 4484.37
A52: =+B52&C52 -> Véhicules neufsCsst | B52: =+$K$1 -> Véhicules neufs | C52: Csst | F52: {=+SUMPRODUCT(('Budget original'!$A$8:$A$501=$A52)*('Budget original'!$C$3:$AO$3=F$2),'Budget original'!$C$8:$AO$501)} -> 3816.1208 | L52: =SUMIFS(BV_Data_An_Cour!$P:$P,BV_Data_An_Cour!$U:$U,$B52,BV_Data_An_Cour!$V:$V,$C52,BV_Data_An_Cour!$W:$W,L$2) -> 4727.58 | N52: =L52-F52 -> 911.45919 | Q52: {=+SUMPRODUCT(('Réel 2023'!$A$8:$A$501=$A52)*('Réel 2023'!$C$3:$AO$3=Q$2),'Réel 2023'!$C$8:$AO$501)} -> 3470.51 | S52: =L52-Q52 -> 1257.07
A53: =+B53&C53 -> Véhicules neufs[...] | B53: =+$K$1 -> Véhicules neufs | C53: [...] | F53: {=+SUMPRODUCT(('Budget original'!$A$8:$A$501=$A53)*('Budget original'!$C$3:$AO$3=F$2),'Budget original'!$C$8:$AO$501)} -> 0 | L53: =SUMIFS(BV_Data_An_Cour!$P:$P,BV_Data_An_Cour!$U:$U,$B53,BV_Data_An_Cour!$V:$V,$C53,BV_Data_An_Cour!$W:$W,L$2) -> 0 | N53: =L53-F53 -> 0 | Q53: {=+SUMPRODUCT(('Réel 2023'!$A$8:$A$501=$A53)*('Réel 2023'!$C$3:$AO$3=Q$2),'Réel 2023'!$C$8:$AO$501)} -> 0 | S53: =L53-Q53 -> 0
A54: =+B54&C54 -> Véhicules neufsTOTAL PERSONNEL | B54: =+$K$1 -> Véhicules neufs | C54: TOTAL PERSONNEL | D54: % brut | E54: =F54/F$27 -> 0.29643357 | F54: =+SUM(F42:F53) -> 170924.41 | J54: % brut | K54: =L54/L$27 -> 0.38849528 | L54: =+SUM(L42:L53) -> 174845.72 | N54: =+SUM(N42:N53) -> 3921.3084 | O54: % brut | P54: =Q54/Q$27 -> 0.30354468 | Q54: =+SUM(Q42:Q53) -> 160789.12 | S54: =+SUM(S42:S53) -> 26600.51
A55: =+B55&C55 -> Véhicules neufsPublicité 2 | B55: =+$K$1 -> Véhicules neufs | C55: Publicité 2 | F55: {=+SUMPRODUCT(('Budget original'!$A$8:$A$501=$A55)*('Budget original'!$C$3:$AO$3=F$2),'Budget original'!$C$8:$AO$501)} -> 0 | L55: =SUMIFS(BV_Data_An_Cour!$P:$P,BV_Data_An_Cour!$U:$U,$B55,BV_Data_An_Cour!$V:$V,$C55,BV_Data_An_Cour!$W:$W,L$2) -> 0 | N55: =L55-F55 -> 0 | Q55: {=+SUMPRODUCT(('Réel 2023'!$A$8:$A$501=$A55)*('Réel 2023'!$C$3:$AO$3=Q$2),'Réel 2023'!$C$8:$AO$501)} -> 0 | S55: =L55-Q55 -> 0
A56: =+B56&C56 -> Véhicules neufsService gratuit 2 | B56: =+$K$1 -> Véhicules neufs | C56: Service gratuit 2 | F56: {=+SUMPRODUCT(('Budget original'!$A$8:$A$501=$A56)*('Budget original'!$C$3:$AO$3=F$2),'Budget original'!$C$8:$AO$501)} -> 0 | L56: =SUMIFS(BV_Data_An_Cour!$P:$P,BV_Data_An_Cour!$U:$U,$B56,BV_Data_An_Cour!$V:$V,$C56,BV_Data_An_Cour!$W:$W,L$2) -> 0 | N56: =L56-F56 -> 0 | Q56: {=+SUMPRODUCT(('Réel 2023'!$A$8:$A$501=$A56)*('Réel 2023'!$C$3:$AO$3=Q$2),'Réel 2023'!$C$8:$AO$501)} -> 0 | S56: =L56-Q56 -> 0
A57: =+B57&C57 -> Véhicules neufsFrais véhicules de cie | B57: =+$K$1 -> Véhicules neufs | C57: Frais véhicules de cie | F57: {=+SUMPRODUCT(('Budget original'!$A$8:$A$501=$A57)*('Budget original'!$C$3:$AO$3=F$2),'Budget original'!$C$8:$AO$501)} -> 20320.333 | L57: =SUMIFS(BV_Data_An_Cour!$P:$P,BV_Data_An_Cour!$U:$U,$B57,BV_Data_An_Cour!$V:$V,$C57,BV_Data_An_Cour!$W:$W,L$2) -> 21142.27 | N57: 0 | Q57: {=+SUMPRODUCT(('Réel 2023'!$A$8:$A$501=$A57)*('Réel 2023'!$C$3:$AO$3=Q$2),'Réel 2023'!$C$8:$AO$501)} -> 16512.92 | S57: =L57-Q57 -> 4629.35
A58: =+B58&C58 -> Véhicules neufsInformatique | B58: =+$K$1 -> Véhicules neufs | C58: Informatique | F58: {=+SUMPRODUCT(('Budget original'!$A$8:$A$501=$A58)*('Budget original'!$C$3:$AO$3=F$2),'Budget original'!$C$8:$AO$501)} -> 19972.2 | L58: =SUMIFS(BV_Data_An_Cour!$P:$P,BV_Data_An_Cour!$U:$U,$B58,BV_Data_An_Cour!$V:$V,$C58,BV_Data_An_Cour!$W:$W,L$2) -> 18029.82 | N58: =L58-F58 -> -1942.38 | Q58: {=+SUMPRODUCT(('Réel 2023'!$A$8:$A$501=$A58)*('Réel 2023'!$C$3:$AO$3=Q$2),'Réel 2023'!$C$8:$AO$501)} -> 18613.69 | S58: =L58-Q58 -> -583.87
A59: =+B59&C59 -> Véhicules neufsFrais de déplacement | B59: =+$K$1 -> Véhicules neufs | C59: Frais de déplacement | F59: {=+SUMPRODUCT(('Budget original'!$A$8:$A$501=$A59)*('Budget original'!$C$3:$AO$3=F$2),'Budget original'!$C$8:$AO$501)} -> 3290.4 | L59: =SUMIFS(BV_Data_An_Cour!$P:$P,BV_Data_An_Cour!$U:$U,$B59,BV_Data_An_Cour!$V:$V,$C59,BV_Data_An_Cour!$W:$W,L$2) -> 3986.53 | N59: =L59-F59 -> 696.13 | Q59: {=+SUMPRODUCT(('Réel 2023'!$A$8:$A$501=$A59)*('Réel 2023'!$C$3:$AO$3=Q$2),'Réel 2023'!$C$8:$AO$501)} -> 2571.34 | S59: =L59-Q59 -> 1415.19
A60: =+B60&C60 -> Véhicules neufsServices extérieurs | B60: =+$K$1 -> Véhicules neufs | C60: Services extérieurs | F60: {=+SUMPRODUCT(('Budget original'!$A$8:$A$501=$A60)*('Budget original'!$C$3:$AO$3=F$2),'Budget original'!$C$8:$AO$501)} -> 11017.8 | L60: =SUMIFS(BV_Data_An_Cour!$P:$P,BV_Data_An_Cour!$U:$U,$B60,BV_Data_An_Cour!$V:$V,$C60,BV_Data_An_Cour!$W:$W,L$2) -> 12188.38 | N60: =L60-F60 -> 1170.58 | Q60: {=+SUMPRODUCT(('Réel 2023'!$A$8:$A$501=$A60)*('Réel 2023'!$C$3:$AO$3=Q$2),'Réel 2023'!$C$8:$AO$501)} -> 11383.7 | S60: =L60-Q60 -> 804.68
A61: =+B61&C61 -> Véhicules neufsFournitures autres | B61: =+$K$1 -> Véhicules neufs | C61: Fournitures autres | F61: {=+SUMPRODUCT(('Budget original'!$A$8:$A$501=$A61)*('Budget original'!$C$3:$AO$3=F$2),'Budget original'!$C$8:$AO$501)} -> 262.5 | L61: =SUMIFS(BV_Data_An_Cour!$P:$P,BV_Data_An_Cour!$U:$U,$B61,BV_Data_An_Cour!$V:$V,$C61,BV_Data_An_Cour!$W:$W,L$2) -> 9.99 | N61: =L61-F61 -> -252.51 | Q61: {=+SUMPRODUCT(('Réel 2023'!$A$8:$A$501=$A61)*('Réel 2023'!$C$3:$AO$3=Q$2),'Réel 2023'!$C$8:$AO$501)} -> 254.32 | S61: =L61-Q61 -> -244.33
A62: =+B62&C62 -> Véhicules neufsUniformes | B62: =+$K$1 -> Véhicules neufs | C62: Uniformes | F62: {=+SUMPRODUCT(('Budget original'!$A$8:$A$501=$A62)*('Budget original'!$C$3:$AO$3=F$2),'Budget original'!$C$8:$AO$501)} -> 60 | L62: =SUMIFS(BV_Data_An_Cour!$P:$P,BV_Data_An_Cour!$U:$U,$B62,BV_Data_An_Cour!$V:$V,$C62,BV_Data_An_Cour!$W:$W,L$2) -> 0 | N62: =L62-F62 -> -60 | Q62: {=+SUMPRODUCT(('Réel 2023'!$A$8:$A$501=$A62)*('Réel 2023'!$C$3:$AO$3=Q$2),'Réel 2023'!$C$8:$AO$501)} -> 155.03 | S62: =L62-Q62 -> -155.03
A63: =+B63&C63 -> Véhicules neufsPapeterie | B63: =+$K$1 -> Véhicules neufs | C63: Papeterie | F63: {=+SUMPRODUCT(('Budget original'!$A$8:$A$501=$A63)*('Budget original'!$C$3:$AO$3=F$2),'Budget original'!$C$8:$AO$501)} -> 3150 | L63: =SUMIFS(BV_Data_An_Cour!$P:$P,BV_Data_An_Cour!$U:$U,$B63,BV_Data_An_Cour!$V:$V,$C63,BV_Data_An_Cour!$W:$W,L$2) -> 1742.09 | N63: =L63-F63 -> -1407.91 | Q63: {=+SUMPRODUCT(('Réel 2023'!$A$8:$A$501=$A63)*('Réel 2023'!$C$3:$AO$3=Q$2),'Réel 2023'!$C$8:$AO$501)} -> 2161.7 | S63: =L63-Q63 -> -419.61
A64: =+B64&C64 -> Véhicules neufsTéléphone | B64: =+$K$1 -> Véhicules neufs | C64: Téléphone | F64: {=+SUMPRODUCT(('Budget original'!$A$8:$A$501=$A64)*('Budget original'!$C$3:$AO$3=F$2),'Budget original'!$C$8:$AO$501)} -> 841.6 | L64: =SUMIFS(BV_Data_An_Cour!$P:$P,BV_Data_An_Cour!$U:$U,$B64,BV_Data_An_Cour!$V:$V,$C64,BV_Data_An_Cour!$W:$W,L$2) -> 897.81 | N64: =L64-F64 -> 56.21 | Q64: {=+SUMPRODUCT(('Réel 2023'!$A$8:$A$501=$A64)*('Réel 2023'!$C$3:$AO$3=Q$2),'Réel 2023'!$C$8:$AO$501)} -> 933.11 | S64: =L64-Q64 -> -35.3
A65: =+B65&C65 -> Véhicules neufsFrais postaux | B65: =+$K$1 -> Véhicules neufs | C65: Frais postaux | F65: {=+SUMPRODUCT(('Budget original'!$A$8:$A$501=$A65)*('Budget original'!$C$3:$AO$3=F$2),'Budget original'!$C$8:$AO$501)} -> 900 | L65: =SUMIFS(BV_Data_An_Cour!$P:$P,BV_Data_An_Cour!$U:$U,$B65,BV_Data_An_Cour!$V:$V,$C65,BV_Data_An_Cour!$W:$W,L$2) -> 805.09 | N65: =L65-F65 -> -94.91 | Q65: {=+SUMPRODUCT(('Réel 2023'!$A$8:$A$501=$A65)*('Réel 2023'!$C$3:$AO$3=Q$2),'Réel 2023'!$C$8:$AO$501)} -> 1104.9 | S65: =L65-Q65 -> -299.81
A66: =+B66&C66 -> Véhicules neufsDivers | B66: =+$K$1 -> Véhicules neufs | C66: Divers | F66: {=+SUMPRODUCT(('Budget original'!$A$8:$A$501=$A66)*('Budget original'!$C$3:$AO$3=F$2),'Budget original'!$C$8:$AO$501)} -> 3344.4 | L66: =SUMIFS(BV_Data_An_Cour!$P:$P,BV_Data_An_Cour!$U:$U,$B66,BV_Data_An_Cour!$V:$V,$C66,BV_Data_An_Cour!$W:$W,L$2) -> 3174.22 | N66: =L66-F66 -> -170.18 | Q66: {=+SUMPRODUCT(('Réel 2023'!$A$8:$A$501=$A66)*('Réel 2023'!$C$3:$AO$3=Q$2),'Réel 2023'!$C$8:$AO$501)} -> 2967.66 | S66: =L66-Q66 -> 206.56
A67: =+B67&C67 -> Véhicules neufsFormation | B67: =+$K$1 -> Véhicules neufs | C67: Formation | F67: {=+SUMPRODUCT(('Budget original'!$A$8:$A$501=$A67)*('Budget original'!$C$3:$AO$3=F$2),'Budget original'!$C$8:$AO$501)} -> 1928.6553 | L67: =SUMIFS(BV_Data_An_Cour!$P:$P,BV_Data_An_Cour!$U:$U,$B67,BV_Data_An_Cour!$V:$V,$C67,BV_Data_An_Cour!$W:$W,L$2) -> 567.88 | N67: =L67-F67 -> -1360.7753 | Q67: {=+SUMPRODUCT(('Réel 2023'!$A$8:$A$501=$A67)*('Réel 2023'!$C$3:$AO$3=Q$2),'Réel 2023'!$C$8:$AO$501)} -> 819.82 | S67: =L67-Q67 -> -251.94
A68: =+B68&C68 -> Véhicules neufsFrais bancaires | B68: =+$K$1 -> Véhicules neufs | C68: Frais bancaires | F68: {=+SUMPRODUCT(('Budget original'!$A$8:$A$501=$A68)*('Budget original'!$C$3:$AO$3=F$2),'Budget original'!$C$8:$AO$501)} -> 9511.2064 | L68: =SUMIFS(BV_Data_An_Cour!$P:$P,BV_Data_An_Cour!$U:$U,$B68,BV_Data_An_Cour!$V:$V,$C68,BV_Data_An_Cour!$W:$W,L$2) -> 10362.06 | N68: =L68-F68 -> 850.85357 | Q68: {=+SUMPRODUCT(('Réel 2023'!$A$8:$A$501=$A68)*('Réel 2023'!$C$3:$AO$3=Q$2),'Réel 2023'!$C$8:$AO$501)} -> 9342.55 | S68: =L68-Q68 -> 1019.51
A69: =+B69&C69 -> Véhicules neufs[...] | B69: =+$K$1 -> Véhicules neufs | C69: [...] | F69: {=+SUMPRODUCT(('Budget original'!$A$8:$A$501=$A69)*('Budget original'!$C$3:$AO$3=F$2),'Budget original'!$C$8:$AO$501)} -> 0 | N69: =L69-F69 -> 0 | Q69: {=+SUMPRODUCT(('Réel 2023'!$A$8:$A$501=$A69)*('Réel 2023'!$C$3:$AO$3=Q$2),'Réel 2023'!$C$8:$AO$501)} -> 0 | S69: =L69-Q69 -> 0
A70: =+B70&C70 -> Véhicules neufs[...] | B70: =+$K$1 -> Véhicules neufs | C70: [...] | F70: {=+SUMPRODUCT(('Budget original'!$A$8:$A$501=$A70)*('Budget original'!$C$3:$AO$3=F$2),'Budget original'!$C$8:$AO$501)} -> 0 | L70: =SUMIFS(BV_Data_An_Cour!$P:$P,BV_Data_An_Cour!$U:$U,$B70,BV_Data_An_Cour!$V:$V,$C70,BV_Data_An_Cour!$W:$W,L$2) -> 0 | N70: =L70-F70 -> 0 | Q70: {=+SUMPRODUCT(('Réel 2023'!$A$8:$A$501=$A70)*('Réel 2023'!$C$3:$AO$3=Q$2),'Réel 2023'!$C$8:$AO$501)} -> 0 | S70: =L70-Q70 -> 0
A71: =+B71&C71 -> Véhicules neufs[...] | B71: =+$K$1 -> Véhicules neufs | C71: [...] | F71: {=+SUMPRODUCT(('Budget original'!$A$8:$A$501=$A71)*('Budget original'!$C$3:$AO$3=F$2),'Budget original'!$C$8:$AO$501)} -> 0 | L71: =SUMIFS(BV_Data_An_Cour!$P:$P,BV_Data_An_Cour!$U:$U,$B71,BV_Data_An_Cour!$V:$V,$C71,BV_Data_An_Cour!$W:$W,L$2)*0.32 -> 0 | N71: =L71-F71 -> 0 | Q71: {=+SUMPRODUCT(('Réel 2023'!$A$8:$A$501=$A71)*('Réel 2023'!$C$3:$AO$3=Q$2),'Réel 2023'!$C$8:$AO$501)} -> 0 | S71: =L71-Q71 -> 0
A72: =+B72&C72 -> Véhicules neufsTOTAL SEMI-FIXES | B72: =+$K$1 -> Véhicules neufs | C72: TOTAL SEMI-FIXES | D72: % brut | E72: =F72/F$27 -> 0.12937693 | F72: =+SUM(F55:F71) -> 74599.095 | J72: % brut | K72: =L72/L$27 -> 0.16199248 | L72: =+SUM(L55:L71) -> 72906.14 | N72: =+SUM(N55:N71) -> -2514.8917 | O72: % brut | P72: =Q72/Q$27 -> 0.12614709 | Q72: =+SUM(Q55:Q71) -> 66820.74 | S72: =+SUM(S55:S71) -> 6085.4
A73: =+B73&C73 -> Véhicules neufs | B73: =+$K$1 -> Véhicules neufs
A74: =+B74&C74 -> Véhicules neufsTOTAL DES DÉPENSES | B74: =+$K$1 -> Véhicules neufs | C74: TOTAL DES DÉPENSES | D74: % brut | E74: =F74/F$27 -> 0.99443152 | F74: =F41+F54+F72 -> 573391.96 | J74: % brut | K74: =L74/L$27 -> 1.2716591 | L74: =L41+L54+L72 -> 572321.39 | N74: =L74-F74 -> -1070.5684 | O74: % brut | P74: =Q74/Q$27 -> 0.84834233 | Q74: =Q41+Q54+Q72 -> 449371.14 | S74: =L74-Q74 -> 122950.25
A75: =+B75&C75 -> Véhicules neufsRBSC neuf | B75: =+$K$1 -> Véhicules neufs | C75: RBSC neuf | F75: {=+SUMPRODUCT(('Budget original'!$A$8:$A$501=$A75)*('Budget original'!$C$3:$AO$3=F$2),'Budget original'!$C$8:$AO$501)} -> 125219.8 | L75: =-SUMIFS(BV_Data_An_Cour!$P:$P,BV_Data_An_Cour!$U:$U,$B75,BV_Data_An_Cour!$V:$V,$C75,BV_Data_An_Cour!$W:$W,L$2) -> 110662.43 | N75: =L75-F75 -> -14557.367 | Q75: {=+SUMPRODUCT(('Réel 2023'!$A$8:$A$501=$A75)*('Réel 2023'!$C$3:$AO$3=Q$2),'Réel 2023'!$C$8:$AO$501)} -> 114797.08
A76: =+B76&C76 -> Véhicules neufsProgramme neuf 2 | B76: =+$K$1 -> Véhicules neufs | C76: Programme neuf 2 | F76: {=+SUMPRODUCT(('Budget original'!$A$8:$A$501=$A76)*('Budget original'!$C$3:$AO$3=F$2),'Budget original'!$C$8:$AO$501)} -> 0 | L76: =-SUMIFS(BV_Data_An_Cour!$P:$P,BV_Data_An_Cour!$U:$U,$B76,BV_Data_An_Cour!$V:$V,$C76,BV_Data_An_Cour!$W:$W,L$2) -> 0 | N76: =L76-F76 -> 0 | Q76: {=+SUMPRODUCT(('Réel 2023'!$A$8:$A$501=$A76)*('Réel 2023'!$C$3:$AO$3=Q$2),'Réel 2023'!$C$8:$AO$501)} -> 0 | S76: =L76-Q76 -> 0
A77: =+B77&C77 -> Véhicules neufsProgramme neuf 3 | B77: =+$K$1 -> Véhicules neufs | C77: Programme neuf 3 | F77: {=+SUMPRODUCT(('Budget original'!$A$8:$A$501=$A77)*('Budget original'!$C$3:$AO$3=F$2),'Budget original'!$C$8:$AO$501)} -> 0 | L77: =-SUMIFS(BV_Data_An_Cour!$P:$P,BV_Data_An_Cour!$U:$U,$B77,BV_Data_An_Cour!$V:$V,$C77,BV_Data_An_Cour!$W:$W,L$2) -> 0 | N77: =L77-F77 -> 0 | Q77: {=+SUMPRODUCT(('Réel 2023'!$A$8:$A$501=$A77)*('Réel 2023'!$C$3:$AO$3=Q$2),'Réel 2023'!$C$8:$AO$501)} -> 0 | S77: =L77-Q77 -> 0
A78: =+B78&C78 -> Véhicules neufsHoldbacks | B78: =+$K$1 -> Véhicules neufs | C78: Holdbacks | F78: {=+SUMPRODUCT(('Budget original'!$A$8:$A$501=$A78)*('Budget original'!$C$3:$AO$3=F$2),'Budget original'!$C$8:$AO$501)} -> 143108.34 | L78: =-SUMIFS(BV_Data_An_Cour!$P:$P,BV_Data_An_Cour!$U:$U,$B78,BV_Data_An_Cour!$V:$V,$C78,BV_Data_An_Cour!$W:$W,L$2) -> 121402.4 | N78: =L78-F78 -> -21705.94 | Q78: {=+SUMPRODUCT(('Réel 2023'!$A$8:$A$501=$A78)*('Réel 2023'!$C$3:$AO$3=Q$2),'Réel 2023'!$C$8:$AO$501)} -> 125811.7 | S78: =L78-Q78 -> -4409.3
A79: =+B79&C79 -> Véhicules neufs[...] | B79: =+$K$1 -> Véhicules neufs | C79: [...] | F79: {=+SUMPRODUCT(('Budget original'!$A$8:$A$501=$A79)*('Budget original'!$C$3:$AO$3=F$2),'Budget original'!$C$8:$AO$501)} -> 0 | L79: =-SUMIFS(BV_Data_An_Cour!$P:$P,BV_Data_An_Cour!$U:$U,$B79,BV_Data_An_Cour!$V:$V,$C79,BV_Data_An_Cour!$W:$W,L$2) -> 0 | N79: =L79-F79 -> 0 | Q79: {=+SUMPRODUCT(('Réel 2023'!$A$8:$A$501=$A79)*('Réel 2023'!$C$3:$AO$3=Q$2),'Réel 2023'!$C$8:$AO$501)} -> 0 | S79: =L79-Q79 -> 0
A80: =+B80&C80 -> Véhicules neufs[...] | B80: =+$K$1 -> Véhicules neufs | C80: [...] | F80: {=+SUMPRODUCT(('Budget original'!$A$8:$A$501=$A80)*('Budget original'!$C$3:$AO$3=F$2),'Budget original'!$C$8:$AO$501)} -> 0 | L80: =-SUMIFS(BV_Data_An_Cour!$P:$P,BV_Data_An_Cour!$U:$U,$B80,BV_Data_An_Cour!$V:$V,$C80,BV_Data_An_Cour!$W:$W,L$2) -> 0 | N80: =L80-F80 -> 0 | Q80: {=+SUMPRODUCT(('Réel 2023'!$A$8:$A$501=$A80)*('Réel 2023'!$C$3:$AO$3=Q$2),'Réel 2023'!$C$8:$AO$501)} -> 0 | S80: =L80-Q80 -> 0
A81: =+B81&C81 -> Véhicules neufs[...] | B81: =+$K$1 -> Véhicules neufs | C81: [...] | F81: {=+SUMPRODUCT(('Budget original'!$A$8:$A$501=$A81)*('Budget original'!$C$3:$AO$3=F$2),'Budget original'!$C$8:$AO$501)} -> 0 | L81: =-SUMIFS(BV_Data_An_Cour!$P:$P,BV_Data_An_Cour!$U:$U,$B81,BV_Data_An_Cour!$V:$V,$C81,BV_Data_An_Cour!$W:$W,L$2) -> 0 | N81: =L81-F81 -> 0 | Q81: {=+SUMPRODUCT(('Réel 2023'!$A$8:$A$501=$A81)*('Réel 2023'!$C$3:$AO$3=Q$2),'Réel 2023'!$C$8:$AO$501)} -> 0 | S81: =L81-Q81 -> 0
A82: =+B82&C82 -> Véhicules neufsFrais administration | B82: =+$K$1 -> Véhicules neufs | C82: Frais administration | F82: {=+SUMPRODUCT(('Budget original'!$A$8:$A$501=$A82)*('Budget original'!$C$3:$AO$3=F$2),'Budget original'!$C$8:$AO$501)} -> 49480.2 | L82: =-SUMIFS(BV_Data_An_Cour!$P:$P,BV_Data_An_Cour!$U:$U,$B82,BV_Data_An_Cour!$V:$V,$C82,BV_Data_An_Cour!$W:$W,L$2) -> 39270 | N82: =L82-F82 -> -10210.2 | Q82: {=+SUMPRODUCT(('Réel 2023'!$A$8:$A$501=$A82)*('Réel 2023'!$C$3:$AO$3=Q$2),'Réel 2023'!$C$8:$AO$501)} -> 39865 | S82: =L82-Q82 -> -595
A83: =+B83&C83 -> Véhicules neufsAUTRES REVENUS | B83: =+$K$1 -> Véhicules neufs | C83: AUTRES REVENUS | F83: =+SUM(F75:F82) -> 317808.34 | L83: =+SUM(L75:L82) -> 271334.83 | N83: =+SUM(N75:N82) -> -46473.507 | Q83: =+SUM(Q75:Q82) -> 280473.78 | S83: =+SUM(S75:S82) -> -5004.3
A84: =+B84&C84 -> Véhicules neufs | B84: =+$K$1 -> Véhicules neufs
A85: =+B85&C85 -> Véhicules neufsPROFIT DÉPARTEMENTAL | B85: =+$K$1 -> Véhicules neufs | C85: PROFIT DÉPARTEMENTAL | F85: =F27-F74+F83 -> 321019.14 | L85: =L27-L74+L83 -> 149072.24 | N85: =N27-N41-N54-N72+N83 -> -171124.96 | Q85: =Q27-Q74+Q83 -> 360807.6 | S85: =S27-S41-S54-S72+S83 -> -220144.62
C89: =C1 -> BMW Sherbrooke | K89: Véhicules usagés | S89: =$S$1 -> Réalisé, Avril 2024 AAD
D91: BUDGET ORIGINAL | J91: RÉALISATION | M91: ÉCART réel / Budget | O91: ANNÉE PRÉCÉDENTE | R91: ECART (réel/ Ann.Préc.)
D92: UNITE | E92: $P/UNITÉ | F92: $PROFITS | J92: UNITE | K92: $P/UNITE | L92: $PROFITS | M92: UNFTÉ | N92: $PROFFTS | O92: UNITE | P92: $P/UNITÉ | Q92: $PROFITS | R92: UNITE | S92: $PROFITS
A93: =+B93&C93 -> Véhicules usagésVentes nettes | B93: Véhicules usagés | C93: Ventes nettes | F93: {=+SUMPRODUCT(('Budget original'!$A$8:$A$501=$A93)*('Budget original'!$C$3:$AO$3=F$2),'Budget original'!$C$8:$AO$501)} -> 4565000 | L93: =-SUMIFS(BV_Data_An_Cour!$P:$P,BV_Data_An_Cour!$X:$X,"Oui",BV_Data_An_Cour!$U:$U,$B93) -> 4874227.9 | Q93: {=+SUMPRODUCT(('Réel 2023'!$A$8:$A$501=$A93)*('Réel 2023'!$C$3:$AO$3=Q$2),'Réel 2023'!$C$8:$AO$501)} -> 4940937.5
