Workbook
Name _Dates_Conc: #REF!
Name _scen: #REF!
Name _scen1: #REF!
Name _scen2: #REF!
Name _SCenarios: #REF!
Name _Sens1: #REF!
Name _Sens2: #REF!
Name _sensRes1: #REF!
Name _sensRes2: #REF!
Name _sensRes3: #REF!
Name _sensRes4: #REF!
Name _sensRes5: #REF!
Name _sensRes6: #REF!
Name _sensRes7: #REF!
Name DateRange: #REF!
Name Monetary_Unit: #REF!
Name Months: #REF!
Name Rng_Dealers_Names: #REF!
Name Rng_Dlr_Dates: #REF!
Name Titre: #REF!

Sheet Paramètre
B3: Quarter | C3: Q2 2026
B6: BUDGET | F6: BUDGET RÉVISÉ | J6: ACTUAL | N6: LAST YEAR
B7: Ventes | C7: Profits bruts | D7: BAIIA | E7: EBIT | F7: Ventes | G7: Profits bruts | H7: BAIIA | I7: EBIT | J7: Ventes | K7: Profits bruts | L7: BAIIA | M7: EBIT | N7: Ventes | O7: Profits bruts | P7: BAIIA | Q7: EBIT
A8: CTRL | B8: =+B9-B10 -> #VALUE! | C8: =+C9-C10 -> 0 | D8: =+D9-D10 -> 0 | E8: =+E9-E10 -> 0 | F8: =+F9-F10 -> #VALUE! | G8: =+G9-G10 -> 0 | H8: =+H9-H10 -> 0 | I8: =+I9-I10 -> 0 | ... Q8: =+Q9-Q10 -> 0
A9: CONSO | B9: =+Conso!$Z$406 -> $TOTAL | C9: =+Conso!$Z$407 -> 18042432 | D9: =+Conso!$Z$483 -> 0 | E9: =+Conso!$Z$498 -> 0 | F9: =+Conso!$AC$406 -> $TOTAL | G9: =+Conso!$AC$407 -> 0 | H9: =+Conso!$AC$483 -> 0 | I9: =+Conso!$AC$498 -> 0 | J9: =+Conso!$AF$406 -> $TOTAL | K9: =+Conso!$AF$407 -> 19326469 | L9: =+Conso!$AF$483 -> 0 | M9: =+Conso!$AF$498 -> 0 | N9: =+Conso!$AL$406 -> $TOTAL | O9: =+Conso!$AL$407 -> 14964562 | P9: =+Conso!$AL$483 -> 0 | Q9: =+Conso!$AL$498 -> 0
A10: TOTAL | B10: =+SUM(B11:B13) -> 0 | C10: =+SUM(C11:C13) -> 18042432 | D10: =+SUM(D11:D13) -> 0 | E10: =+SUM(E11:E13) -> 0 | F10: =+SUM(F11:F13) -> 0 | G10: =+SUM(G11:G13) -> 0 | H10: =+SUM(H11:H13) -> 0 | I10: =+SUM(I11:I13) -> 0 | ... Q10: =+SUM(Q11:Q13) -> 0
A11: Mois 1 | B11: =+'Mois 1'!$Z$406 -> $TOTAL | C11: =+'Mois 1'!$Z$407 -> 5932390.6 | D11: =+'Mois 1'!$Z$483 -> 0 | E11: =+'Mois 1'!$Z$498 -> 0 | F11: =+'Mois 1'!$AC$406 -> 0 | G11: =+'Mois 1'!$AC$407 -> 0 | H11: =+'Mois 1'!$AC$483 -> 0 | I11: =+'Mois 1'!$AC$498 -> 0 | J11: =+'Mois 1'!$AF$406 -> $TOTAL | K11: =+'Mois 1'!$AF$407 -> 6155759.5 | L11: =+'Mois 1'!$AF$483 -> 0 | M11: =+'Mois 1'!$AF$498 -> 0 | N11: =+'Mois 1'!$AL$406 -> $TOTAL | O11: =+'Mois 1'!$AL$407 -> 4784256.5 | P11: =+'Mois 1'!$AL$483 -> 0 | Q11: =+'Mois 1'!$AL$498 -> 0
A12: Mois 2 | B12: =+'Mois 2'!$Z$406 -> $TOTAL | C12: =+'Mois 2'!$Z$407 -> 6617137.8 | D12: =+'Mois 2'!$Z$483 -> 0 | E12: =+'Mois 2'!$Z$498 -> 0 | F12: =+'Mois 2'!$AC$406 -> 0 | G12: =+'Mois 2'!$AC$407 -> 0 | H12: =+'Mois 2'!$AC$483 -> 0 | I12: =+'Mois 2'!$AC$498 -> 0 | J12: =+'Mois 2'!$AF$406 -> $TOTAL | K12: =+'Mois 2'!$AF$407 -> 6778938.7 | L12: =+'Mois 2'!$AF$483 -> 0 | M12: =+'Mois 2'!$AF$498 -> 0 | N12: =+'Mois 2'!$AL$406 -> $TOTAL | O12: =+'Mois 2'!$AL$407 -> 6366734.3 | P12: =+'Mois 2'!$AL$483 -> 0 | Q12: =+'Mois 2'!$AL$498 -> 0
A13: Mois 3 | B13: =+'Mois 3'!$Z$406 -> $TOTAL | C13: =+'Mois 3'!$Z$407 -> 5492903.3 | D13: =+'Mois 3'!$Z$483 -> 0 | E13: =+'Mois 3'!$Z$498 -> 0 | F13: =+'Mois 3'!$AC$406 -> 0 | G13: =+'Mois 3'!$AC$407 -> 0 | H13: =+'Mois 3'!$AC$483 -> 0 | I13: =+'Mois 3'!$AC$498 -> 0 | J13: =+'Mois 3'!$AF$406 -> $TOTAL | K13: =+'Mois 3'!$AF$407 -> 6391770.9 | L13: =+'Mois 3'!$AF$483 -> 0 | M13: =+'Mois 3'!$AF$498 -> 0 | N13: =+'Mois 3'!$AL$406 -> $TOTAL | O13: =+'Mois 3'!$AL$407 -> 3813571.5 | P13: =+'Mois 3'!$AL$483 -> 0 | Q13: =+'Mois 3'!$AL$498 -> 0

Sheet Conso
C1: BMW Sherbrooke | K1: Véhicules neufs | S1: =CONCATENATE("Réalisé"," ",Paramètre!$C$2," ",Paramètre!$C$3) -> Réalisé Q2 2026
D2: X | E2: O | F2: U | G2: X | H2: O | I2: U
D3: BUDGET ORIGINAL | G3: BUDGET REVISE | J3: RÉALISATION | M3: ÉCART réel / Budget | O3: ANNÉE PRÉCÉDENTE | R3: ECART (réel/ Ann.Préc.)
D4: UNITE | E4: $P/UNITÉ | F4: $PROFITS | G4: UNITE | H4: $P/UNITÉ | I4: $PROFITS | J4: UNITE | K4: $P/UNITE | L4: $PROFITS | M4: UNFTÉ | N4: $PROFITS | O4: UNITE | P4: $P/UNITE | Q4: $PROFITS | R4: UNITE | S4: $PROFITS
A5: =+B5&C5 -> Véhicules neufsVentes nettes | B5: =+$K$1 -> Véhicules neufs | C5: Ventes nettes | F5: =+SUM(START:END!F5) -> 9500834.8 | I5: =+SUM(START:END!I5) -> 0 | L5: =+SUM(START:END!L5) -> 10082677 | Q5: =+SUM(START:END!Q5) -> 8603227.3
A6: =+B6&C6 -> Véhicules neufsAutos détail | B6: =+$K$1 -> Véhicules neufs | C6: Autos détail | D6: =+SUM(START:END!D6) -> 28 | E6: =IF(D6=0,0,F6/D6) -> 4701.1765 | F6: =+SUM(START:END!F6) -> 131632.94 | G6: =+SUM(START:END!G6) -> 0 | H6: =IF(G6=0,0,I6/G6) -> 0 | I6: =+SUM(START:END!I6) -> 0 | J6: =+SUM(START:END!J6) -> 37 | K6: =IF(J6=0,0,L6/J6) -> 5547.4197 | L6: =+SUM(START:END!L6) -> 205254.53 | M6: =J6-D6 -> 9 | N6: =L6-F6 -> 73621.589 | O6: =+SUM(START:END!O6) -> 27 | P6: =IF(O6=0,0,Q6/O6) -> 5997.1281 | Q6: =+SUM(START:END!Q6) -> 161922.46 | R6: =J6-O6 -> 10 | S6: =L6-Q6 -> 43332.07
A7: =+B7&C7 -> Véhicules neufsCamions détail | B7: =+$K$1 -> Véhicules neufs | C7: Camions détail | D7: =+SUM(START:END!D7) -> 65 | E7: =IF(D7=0,0,F7/D7) -> 3928.5 | F7: =+SUM(START:END!F7) -> 255352.5 | G7: =+SUM(START:END!G7) -> 0 | H7: =IF(G7=0,0,I7/G7) -> 0 | I7: =+SUM(START:END!I7) -> 0 | J7: =+SUM(START:END!J7) -> 45 | K7: =IF(J7=0,0,L7/J7) -> 3957.2978 | L7: =+SUM(START:END!L7) -> 178078.4 | M7: =J7-D7 -> -20 | N7: =L7-F7 -> -77274.1 | O7: =+SUM(START:END!O7) -> 45 | P7: =IF(O7=0,0,Q7/O7) -> 4008.3438 | Q7: =+SUM(START:END!Q7) -> 180375.47 | R7: =J7-O7 -> 0 | S7: =L7-Q7 -> -2297.07
A8: =+B8&C8 -> Véhicules neufsSprinter | B8: =+$K$1 -> Véhicules neufs | C8: Sprinter | D8: =+SUM(START:END!D8) -> 0 | E8: =IF(D8=0,0,F8/D8) -> 0 | F8: =+SUM(START:END!F8) -> 0 | G8: =+SUM(START:END!G8) -> 0 | H8: =IF(G8=0,0,I8/G8) -> 0 | I8: =+SUM(START:END!I8) -> 0 | J8: =+SUM(START:END!J8) -> 0 | K8: =IF(J8=0,0,L8/J8) -> 0 | L8: =+SUM(START:END!L8) -> 0 | M8: =J8-D8 -> 0 | N8: =L8-F8 -> 0 | O8: =+SUM(START:END!O8) -> 0 | P8: =IF(O8=0,0,Q8/O8) -> 0 | Q8: =+SUM(START:END!Q8) -> 0 | R8: =J8-O8 -> 0 | S8: =L8-Q8 -> 0
A9: =+B9&C9 -> Véhicules neufsMoto détail | B9: =+$K$1 -> Véhicules neufs | C9: Moto détail | D9: =+SUM(START:END!D9) -> 0 | E9: =IF(D9=0,0,F9/D9) -> 0 | F9: =+SUM(START:END!F9) -> 0 | G9: =+SUM(START:END!G9) -> 0 | H9: =IF(G9=0,0,I9/G9) -> 0 | I9: =+SUM(START:END!I9) -> 0 | J9: =+SUM(START:END!J9) -> 0 | K9: =IF(J9=0,0,L9/J9) -> 0 | L9: =+SUM(START:END!L9) -> 0 | M9: =J9-D9 -> 0 | N9: =L9-F9 -> 0 | O9: =+SUM(START:END!O9) -> 0 | P9: =IF(O9=0,0,Q9/O9) -> 0 | Q9: =+SUM(START:END!Q9) -> 0 | R9: =J9-O9 -> 0 | S9: =L9-Q9 -> 0
A10: =+B10&C10 -> Véhicules neufs[...] | B10: =+$K$1 -> Véhicules neufs | C10: [...] | D10: =+SUM(START:END!D10) -> 0 | E10: =IF(D10=0,0,F10/D10) -> 0 | F10: =+SUM(START:END!F10) -> 0 | G10: =+SUM(START:END!G10) -> 0 | H10: =IF(G10=0,0,I10/G10) -> 0 | I10: =+SUM(START:END!I10) -> 0 | J10: =+SUM(START:END!J10) -> 0 | K10: =IF(J10=0,0,L10/J10) -> 0 | L10: =+SUM(START:END!L10) -> 0 | M10: =J10-D10 -> 0 | N10: =L10-F10 -> 0 | O10: =+SUM(START:END!O10) -> 0 | P10: =IF(O10=0,0,Q10/O10) -> 0 | Q10: =+SUM(START:END!Q10) -> 0 | R10: =J10-O10 -> 0 | S10: =L10-Q10 -> 0
A11: =+B11&C11 -> Véhicules neufs[...] | B11: =+$K$1 -> Véhicules neufs | C11: [...] | D11: =+SUM(START:END!D11) -> 0 | E11: =IF(D11=0,0,F11/D11) -> 0 | F11: =+SUM(START:END!F11) -> 0 | G11: =+SUM(START:END!G11) -> 0 | H11: =IF(G11=0,0,I11/G11) -> 0 | I11: =+SUM(START:END!I11) -> 0 | J11: =+SUM(START:END!J11) -> 0 | K11: =IF(J11=0,0,L11/J11) -> 0 | L11: =+SUM(START:END!L11) -> 0 | M11: =J11-D11 -> 0 | N11: =L11-F11 -> 0 | O11: =+SUM(START:END!O11) -> 0 | P11: =IF(O11=0,0,Q11/O11) -> 0 | Q11: =+SUM(START:END!Q11) -> 0 | R11: =J11-O11 -> 0 | S11: =L11-Q11 -> 0
A12: =+B12&C12 -> Véhicules neufs[...] | B12: =+$K$1 -> Véhicules neufs | C12: [...] | D12: =+SUM(START:END!D12) -> 0 | E12: =IF(D12=0,0,F12/D12) -> 0 | F12: =+SUM(START:END!F12) -> 0 | G12: =+SUM(START:END!G12) -> 0 | H12: =IF(G12=0,0,I12/G12) -> 0 | I12: =+SUM(START:END!I12) -> 0 | J12: =+SUM(START:END!J12) -> 0 | K12: =IF(J12=0,0,L12/J12) -> 0 | L12: =+SUM(START:END!L12) -> 0 | M12: =J12-D12 -> 0 | N12: =L12-F12 -> 0 | O12: =+SUM(START:END!O12) -> 0 | P12: =IF(O12=0,0,Q12/O12) -> 0 | Q12: =+SUM(START:END!Q12) -> 0 | R12: =J12-O12 -> 0 | S12: =L12-Q12 -> 0
A13: =+B13&C13 -> Véhicules neufsTotal Neufs | B13: =+$K$1 -> Véhicules neufs | C13: Total Neufs | D13: =+SUM(D6:D12) -> 93 | E13: =IF(D13<=0,0,F13/D13) -> 4161.1338 | F13: =+SUM(F6:F12) -> 386985.44 | G13: =+SUM(G6:G12) -> 0 | H13: =IF(G13<=0,0,I13/G13) -> 0 | I13: =+SUM(I6:I12) -> 0 | J13: =+SUM(J6:J12) -> 82 | K13: =IF(J13<=0,0,L13/J13) -> 4674.7918 | L13: =+SUM(L6:L12) -> 383332.93 | M13: =+SUM(M6:M12) -> -11 | N13: =+SUM(N6:N12) -> -3652.5112 | O13: =+SUM(O6:O12) -> 72 | P13: =IF(O13<=0,0,Q13/O13) -> 4754.1379 | Q13: =+SUM(Q6:Q12) -> 342297.93 | R13: =+SUM(R6:R12) -> 10 | S13: =+SUM(S6:S12) -> 41035
A14: =+B14&C14 -> Véhicules neufs | B14: =+$K$1 -> Véhicules neufs | M14: =IF(D13=0,0,M13/D13) -> -0.11827957 | N14: =IF(F13=0,0,N13/F13) -> -0.0094383684 | R14: =R13/O13 -> 0.13888889 | S14: =IF(Q13=0,0,(S13/Q13)) -> 0.11988095
A15: =+B15&C15 -> Véhicules neufsEx-Démos et courtoisies | B15: =+$K$1 -> Véhicules neufs | C15: Ex-Démos et courtoisies | D15: =+SUM(START:END!D15) -> 10 | E15: =IF(D15=0,0,F15/D15) -> 1200 | F15: =+SUM(START:END!F15) -> 12000 | G15: =+SUM(START:END!G15) -> 0 | H15: =IF(G15=0,0,I15/G15) -> 0 | I15: =+SUM(START:END!I15) -> 0 | J15: =+SUM(START:END!J15) -> 11 | K15: =IF(J15=0,0,L15/J15) -> 398.09545 | L15: =+SUM(START:END!L15) -> 4379.05 | M15: =J15-D15 -> 1 | N15: =L15-F15 -> -7620.95 | O15: =+SUM(START:END!O15) -> 21 | P15: =IF(O15=0,0,Q15/O15) -> 2815.8662 | Q15: =+SUM(START:END!Q15) -> 59133.19 | R15: =J15-O15 -> -10 | S15: =L15-Q15 -> -54754.14
A16: =+B16&C16 -> Véhicules neufs | B16: =+$K$1 -> Véhicules neufs
A17: =+B17&C17 -> Véhicules neufsFlottes | B17: =+$K$1 -> Véhicules neufs | C17: Flottes | D17: =+SUM(START:END!D17) -> 6 | E17: =IF(D17=0,0,F17/D17) -> 750 | F17: =+SUM(START:END!F17) -> 4500 | G17: =+SUM(START:END!G17) -> 0 | H17: =IF(G17=0,0,I17/G17) -> 0 | I17: =+SUM(START:END!I17) -> 0 | J17: =+SUM(START:END!J17) -> 11 | K17: =IF(J17=0,0,L17/J17) -> 484.49727 | L17: =+SUM(START:END!L17) -> 5329.47 | M17: =J17-D17 -> 5 | N17: =L17-F17 -> 829.47 | O17: =+SUM(START:END!O17) -> 0 | P17: =IF(O17=0,0,Q17/O17) -> 0 | Q17: =+SUM(START:END!Q17) -> 0 | R17: =J17-O17 -> 11 | S17: =L17-Q17 -> 5329.47
A18: =+B18&C18 -> Véhicules neufs | B18: =+$K$1 -> Véhicules neufs
A19: =+B19&C19 -> Véhicules neufsRachat bail | B19: =+$K$1 -> Véhicules neufs | C19: Rachat bail | F19: =+SUM(START:END!F19) -> 0 | I19: =+SUM(START:END!I19) -> 0 | L19: =+SUM(START:END!L19) -> 0 | N19: =L19-F19 -> 0 | Q19: =+SUM(START:END!Q19) -> 0 | R19: =O19-K19 -> 0 | S19: =L19-Q19 -> 0
A20: =+B20&C20 -> Véhicules neufs | B20: =+$K$1 -> Véhicules neufs
A21: =+B21&C21 -> Véhicules neufsRev. Finances | B21: =+$K$1 -> Véhicules neufs | C21: Rev. Finances | D21: 0 | E21: =IF(D21=0,0,F21/D21) -> 0 | F21: =+SUM(START:END!F21) -> 721 | G21: 0 | H21: =IF(G21=0,0,I21/G21) -> 0 | I21: =+SUM(START:END!I21) -> 0 | K21: =IF(J13=0,0,L21/(J13+J15)) -> 14.300108 | L21: =+SUM(START:END!L21) -> 1329.91 | N21: =L21-F21 -> 608.91 | P21: =IF(O13=0,0,Q21/(O13+O15)) -> 5.2893548 | Q21: =+SUM(START:END!Q21) -> 491.91 | R21: =O21-K21 -> -14.300108 | S21: =L21-Q21 -> 838
A22: =+B22&C22 -> Véhicules neufsRev. Protections | B22: =+$K$1 -> Véhicules neufs | C22: Rev. Protections | D22: 0 | E22: =IF(D22=0,0,F22/D22) -> 0 | F22: =+SUM(START:END!F22) -> 118450 | G22: 0 | H22: =IF(G22=0,0,I22/G22) -> 0 | I22: =+SUM(START:END!I22) -> 0 | K22: =IF(J13=0,0,L22/(J13+J15)) -> 563.04624 | L22: =+SUM(START:END!L22) -> 52363.3 | N22: =L22-F22 -> -66086.7 | P22: =IF(O13=0,0,Q22/(O13+O15)) -> 1464.1901 | Q22: =+SUM(START:END!Q22) -> 136169.68 | R22: =O22-K22 -> -563.04624 | S22: =L22-Q22 -> -83806.38
A23: =+B23&C23 -> Véhicules neufsRev. Autres | B23: =+$K$1 -> Véhicules neufs | C23: Rev. Autres | D23: 0 | E23: =IF(D23=0,0,F23/D23) -> 0 | F23: =+SUM(START:END!F23) -> 45629 | G23: 0 | H23: =IF(G23=0,0,I23/G23) -> 0 | I23: =+SUM(START:END!I23) -> 0 | K23: =IF(J13=0,0,L23/(J13+J15)) -> 495.57247 | L23: =+SUM(START:END!L23) -> 46088.24 | N23: =L23-F23 -> 459.24 | P23: =IF(O13=0,0,Q23/(O13+O15)) -> 802.84452 | Q23: =+SUM(START:END!Q23) -> 74664.54 | R23: =O23-K23 -> -495.57247 | S23: =L23-Q23 -> -28576.3
A24: =+B24&C24 -> Véhicules neufsTotal F&I | B24: =+$K$1 -> Véhicules neufs | C24: Total F&I | D24: =+D15+D13 -> 103 | E24: =IF(D24<=0,0,F24/D24) -> 1600 | F24: =F21+F22+F23 -> 164800 | G24: =+G15+G13 -> 0 | H24: =IF(G24<=0,0,I24/G24) -> 0 | I24: =I21+I22+I23 -> 0 | J24: =+J15+J13 -> 93 | K24: =IF(J24<=0,0,L24/J24) -> 1072.9188 | L24: =L21+L22+L23 -> 99781.45 | M24: =J24-D24 -> -10 | N24: =L24-F24 -> -65018.55 | O24: =+O15+O13 -> 93 | P24: =IF(O24<=0,0,Q24/O24) -> 2272.324 | Q24: =Q21+Q22+Q23 -> 211326.13 | S24: =L24-Q24 -> -111544.68
A25: =+B25&C25 -> Véhicules neufs | B25: =+$K$1 -> Véhicules neufs | N25: =IF(N24=0,0,N24/F24) -> -0.39453004 | S25: =IF(Q24=0,0,(S24/Q24)) -> -0.52783193
A26: =+B26&C26 -> Véhicules neufs | B26: =+$K$1 -> Véhicules neufs
A27: =+B27&C27 -> Véhicules neufsTotal Dépt. Neufs | B27: =+$K$1 -> Véhicules neufs | C27: Total Dépt. Neufs | D27: =+D13+D15+D17 -> 109 | E27: =IF(D27<=0,0,F27/D27) -> 5213.6279 | F27: =F13+F17+F24+F19+F15 -> 568285.44 | G27: =+G13+G15+G17 -> 0 | H27: =IF(G27<=0,0,I27/G27) -> 0 | I27: =I13+I17+I24+I19+I15 -> 0 | J27: =+J13+J15+J17 -> 104 | K27: =IF(J27<=0,0,L27/J27) -> 4738.6817 | L27: =L13+L17+L24+L19+L15 -> 492822.9 | M27: =J27-D27 -> -5 | N27: =L27-F27 -> -75462.541 | O27: =+O13+O15+O17 -> 93 | P27: =IF(O27<=0,0,Q27/O27) -> 6588.7876 | Q27: =Q13+Q17+Q24+Q19+Q15 -> 612757.25 | R27: =J27-O27 -> 11 | S27: =L27-Q27 -> -119934.35
A28: =+B28&C28 -> Véhicules neufs | B28: =+$K$1 -> Véhicules neufs | M28: =M27/D27 -> -0.04587156 | N28: =N27/F27 -> -0.13278985 | R28: =R27/O27 -> 0.11827957 | S28: =IF(Q27=0,0,S27/Q27) -> -0.19572898
A29: =+B29&C29 -> Véhicules neufs | B29: =+$K$1 -> Véhicules neufs
A30: =+B30&C30 -> Véhicules neufsDEPENSES | B30: =+$K$1 -> Véhicules neufs | C30: DEPENSES
A31: =+B31&C31 -> Véhicules neufsComm. vendeurs | B31: =+$K$1 -> Véhicules neufs | C31: Comm. vendeurs | D31: =F31/(F13+F15) -> 0.27413523 | E31: =F31/D$24 -> 1061.9026 | F31: =+SUM(START:END!F31) -> 109375.96 | H31: =I31/G$24 -> #DIV/0! | I31: =+SUM(START:END!I31) -> 0 | J31: =L31/(L13+L15) -> 0.26539273 | K31: =IF(L31=0,0,L31/J$24) -> 1106.408 | L31: =+SUM(START:END!L31) -> 102895.94 | N31: =L31-F31 -> -6480.0237 | O31: =Q31/(Q13+Q15+Q17) -> 0.25727176 | P31: =IF(Q31=0,0,Q31/O$24) -> 1110.5042 | Q31: =+SUM(START:END!Q31) -> 103276.89 | S31: =L31-Q31 -> -380.95
A32: =+B32&C32 -> Véhicules neufsComm. F&I | B32: =+$K$1 -> Véhicules neufs | C32: Comm. F&I | D32: =F32/F24 -> 0.305 | E32: =F32/D$24 -> 488 | F32: =+SUM(START:END!F32) -> 50264 | H32: =I32/G$24 -> #DIV/0! | I32: =+SUM(START:END!I32) -> 0 | J32: =L32/L24 -> 0.23001189 | K32: =IF(L32=0,0,L32/J$24) -> 246.78409 | L32: =+SUM(START:END!L32) -> 22950.92 | N32: =L32-F32 -> -27313.08 | O32: =Q32/Q24 -> 0.3409876 | P32: =IF(Q32=0,0,Q32/O$24) -> 774.8343 | Q32: =+SUM(START:END!Q32) -> 72059.59 | S32: =L32-Q32 -> -49108.67
A33: =+B33&C33 -> Véhicules neufsFrais de livraison | B33: =+$K$1 -> Véhicules neufs | C33: Frais de livraison | E33: =F33/D$24 -> 120 | F33: =+SUM(START:END!F33) -> 12360 | H33: =I33/G$24 -> #DIV/0! | I33: =+SUM(START:END!I33) -> 0 | K33: =IF(L33=0,0,L33/J$24) -> 167.99355 | L33: =+SUM(START:END!L33) -> 15623.4 | N33: =L33-F33 -> 3263.4 | P33: =IF(Q33=0,0,Q33/O$24) -> 122.49 | Q33: =+SUM(START:END!Q33) -> 11391.57 | S33: =L33-Q33 -> 4231.83
A34: =+B34&C34 -> Véhicules neufsService gratuit 1 | B34: =+$K$1 -> Véhicules neufs | C34: Service gratuit 1 | E34: =F34/D$24 -> 35 | F34: =+SUM(START:END!F34) -> 3605 | H34: =I34/G$24 -> #DIV/0! | I34: =+SUM(START:END!I34) -> 0 | K34: =IF(L34=0,0,L34/J$24) -> 51.072366 | L34: =+SUM(START:END!L34) -> 4749.73 | N34: =L34-F34 -> 1144.73 | P34: =IF(Q34=0,0,Q34/O$24) -> 37.78129 | Q34: =+SUM(START:END!Q34) -> 3513.66 | S34: =L34-Q34 -> 1236.07
A35: =+B35&C35 -> Véhicules neufsEntretien stock | B35: =+$K$1 -> Véhicules neufs | C35: Entretien stock | E35: =F35/D$24 -> 95.718447 | F35: =+SUM(START:END!F35) -> 9859 | H35: =I35/G$24 -> #DIV/0! | I35: =+SUM(START:END!I35) -> 0 | K35: =IF(L35=0,0,L35/J$24) -> 96.994086 | L35: =+SUM(START:END!L35) -> 9020.45 | N35: =L35-F35 -> -838.55 | P35: =IF(Q35=0,0,Q35/O$24) -> 52.236774 | Q35: =+SUM(START:END!Q35) -> 4858.02 | S35: =L35-Q35 -> 4162.43
A36: =+B36&C36 -> Véhicules neufsPublicité 1 | B36: =+$K$1 -> Véhicules neufs | C36: Publicité 1 | E36: =F36/D$24 -> 234.88788 | F36: =+SUM(START:END!F36) -> 24193.452 | H36: =I36/G$24 -> #DIV/0! | I36: =+SUM(START:END!I36) -> 0 | K36: =IF(L36=0,0,L36/J$24) -> 180.01914 | L36: =+SUM(START:END!L36) -> 16741.78 | N36: =L36-F36 -> -7451.6715 | P36: =IF(Q36=0,0,Q36/O$24) -> 494.38527 | Q36: =+SUM(START:END!Q36) -> 45977.83 | S36: =L36-Q36 -> -29236.05
A37: =+B37&C37 -> Véhicules neufsIntérêt de gros | B37: =+$K$1 -> Véhicules neufs | C37: Intérêt de gros | E37: =F37/D$24 -> 686.46233 | F37: =+SUM(START:END!F37) -> 70705.62 | H37: =I37/G$24 -> #DIV/0! | I37: =+SUM(START:END!I37) -> 0 | K37: =IF(L37=0,0,L37/J$24) -> 689.2943 | L37: =+SUM(START:END!L37) -> 64104.37 | N37: =L37-F37 -> -6601.2505 | P37: =IF(Q37=0,0,Q37/O$24) -> 800.39151 | Q37: =+SUM(START:END!Q37) -> 74436.41 | S37: =L37-Q37 -> -10332.04
A38: =+B38&C38 -> Véhicules neufs[...] | B38: =+$K$1 -> Véhicules neufs | C38: [...] | E38: =F38/D$24 -> 0 | F38: =+SUM(START:END!F38) -> 0 | H38: =I38/G$24 -> #DIV/0! | I38: =+SUM(START:END!I38) -> 0 | K38: =IF(L38=0,0,L38/J$24) -> 0 | L38: =+SUM(START:END!L38) -> 0 | N38: =L38-F38 -> 0 | P38: =IF(Q38=0,0,Q38/O$24) -> 0 | Q38: =+SUM(START:END!Q38) -> 0 | S38: =L38-Q38 -> 0
A39: =+B39&C39 -> Véhicules neufs[...] | B39: =+$K$1 -> Véhicules neufs | C39: [...] | E39: =F39/D$24 -> 0 | F39: =+SUM(START:END!F39) -> 0 | H39: =I39/G$24 -> #DIV/0! | I39: =+SUM(START:END!I39) -> 0 | K39: =IF(L39=0,0,L39/J$24) -> 0 | L39: =+SUM(START:END!L39) -> 0 | N39: =L39-F39 -> 0 | P39: =IF(Q39=0,0,Q39/O$24) -> 0 | Q39: =+SUM(START:END!Q39) -> 0 | S39: =L39-Q39 -> 0
A40: =+B40&C40 -> Véhicules neufs[...] | B40: =+$K$1 -> Véhicules neufs | C40: [...] | E40: =F40/D$24 -> 0 | F40: =+SUM(START:END!F40) -> 0 | H40: =I40/G$24 -> #DIV/0! | I40: =+SUM(START:END!I40) -> 0 | K40: =IF(L40=0,0,L40/J$24) -> 0 | L40: =+SUM(START:END!L40) -> 0 | N40: =L40-F40 -> 0 | P40: =IF(Q40=0,0,Q40/O$24) -> 0 | Q40: =+SUM(START:END!Q40) -> 0 | S40: =L40-Q40 -> 0
A41: =+B41&C41 -> Véhicules neufsTOTAL VARIABLES | B41: =+$K$1 -> Véhicules neufs | C41: TOTAL VARIABLES | D41: % brut | E41: =F41/F$27 -> 0.49334897 | F41: =SUM(F31:F40) -> 280363.04 | G41: % brut | H41: =I41/I$27 -> #DIV/0! | I41: =SUM(I31:I40) -> 0 | J41: % brut | K41: =L41/L$27 -> 0.47904955 | L41: =SUM(L31:L40) -> 236086.59 | N41: =L41-F41 -> -44276.446 | O41: % brut | P41: =Q41/Q$27 -> 0.51490859 | Q41: =SUM(Q31:Q40) -> 315513.97 | S41: =L41-Q41 -> -79427.38
A42: =+B42&C42 -> Véhicules neufsSalaires cadres | B42: =+$K$1 -> Véhicules neufs | C42: Salaires cadres | F42: =+SUM(START:END!F42) -> 39460.48 | I42: =+SUM(START:END!I42) -> 0 | L42: =+SUM(START:END!L42) -> 28010.9 | N42: =L42-F42 -> -11449.58 | Q42: =+SUM(START:END!Q42) -> 41662.89 | S42: =L42-Q42 -> -13651.99
A43: =+B43&C43 -> Véhicules neufsSalaires commis | B43: =+$K$1 -> Véhicules neufs | C43: Salaires commis | F43: =+SUM(START:END!F43) -> 15160.025 | I43: =+SUM(START:END!I43) -> 0 | L43: =+SUM(START:END!L43) -> 12364.78 | N43: =L43-F43 -> -2795.2452 | Q43: =+SUM(START:END!Q43) -> 28011.77 | S43: =L43-Q43 -> -15646.99
A44: =+B44&C44 -> Véhicules neufsSalaires autres | B44: =+$K$1 -> Véhicules neufs | C44: Salaires autres | F44: =+SUM(START:END!F44) -> 0 | I44: =+SUM(START:END!I44) -> 0 | L44: =+SUM(START:END!L44) -> 520 | N44: =L44-F44 -> 520 | Q44: =+SUM(START:END!Q44) -> 1026 | S44: =L44-Q44 -> -506
A45: =+B45&C45 -> Véhicules neufsSalaires spécialistes | B45: =+$K$1 -> Véhicules neufs | C45: Salaires spécialistes | F45: =+SUM(START:END!F45) -> 0 | I45: =+SUM(START:END!I45) -> 0 | L45: =+SUM(START:END!L45) -> 0 | N45: =L45-F45 -> 0 | Q45: =+SUM(START:END!Q45) -> 0 | S45: =L45-Q45 -> 0
A46: =+B46&C46 -> Véhicules neufs[...] | B46: =+$K$1 -> Véhicules neufs | C46: [...] | F46: =+SUM(START:END!F46) -> 0 | I46: =+SUM(START:END!I46) -> 0 | L46: =+SUM(START:END!L46) -> 0 | N46: =L46-F46 -> 0 | Q46: =+SUM(START:END!Q46) -> 0 | S46: =L46-Q46 -> 0
A47: =+B47&C47 -> Véhicules neufs[...] | B47: =+$K$1 -> Véhicules neufs | C47: [...] | F47: =+SUM(START:END!F47) -> 0 | I47: =+SUM(START:END!I47) -> 0 | L47: =+SUM(START:END!L47) -> 0 | N47: =L47-F47 -> 0 | Q47: =+SUM(START:END!Q47) -> 0 | S47: =L47-Q47 -> 0
A48: =+B48&C48 -> Véhicules neufs[...] | B48: =+$K$1 -> Véhicules neufs | C48: [...] | F48: =+SUM(START:END!F48) -> 0 | I48: =+SUM(START:END!I48) -> 0 | L48: =+SUM(START:END!L48) -> 0 | N48: =L48-F48 -> 0 | Q48: =+SUM(START:END!Q48) -> 0 | S48: =L48-Q48 -> 0
A49: =+B49&C49 -> Véhicules neufsSalaires en absences | B49: =+$K$1 -> Véhicules neufs | C49: Salaires en absences | F49: =+SUM(START:END!F49) -> 29740.36 | I49: =+SUM(START:END!I49) -> 0 | L49: =+SUM(START:END!L49) -> 21525.49 | N49: =L49-F49 -> -8214.8704 | Q49: =+SUM(START:END!Q49) -> 28615.34 | S49: =L49-Q49 -> -7089.85
A50: =+B50&C50 -> Véhicules neufsDéduction à la source | B50: =+$K$1 -> Véhicules neufs | C50: Déduction à la source | F50: =+SUM(START:END!F50) -> 31629.612 | I50: =+SUM(START:END!I50) -> 0 | L50: =+SUM(START:END!L50) -> 26428.31 | N50: =L50-F50 -> -5201.3016 | Q50: =+SUM(START:END!Q50) -> 37522.08 | S50: =L50-Q50 -> -11093.77
A51: =+B51&C51 -> Véhicules neufsBénéfices marginaux | B51: =+$K$1 -> Véhicules neufs | C51: Bénéfices marginaux | F51: =+SUM(START:END!F51) -> 20500.674 | I51: =+SUM(START:END!I51) -> 0 | L51: =+SUM(START:END!L51) -> 11591.98 | N51: =L51-F51 -> -8908.6942 | Q51: =+SUM(START:END!Q51) -> 14434.63 | S51: =L51-Q51 -> -2842.65
A52: =+B52&C52 -> Véhicules neufsCsst | B52: =+$K$1 -> Véhicules neufs | C52: Csst | F52: =+SUM(START:END!F52) -> 5740.1888 | I52: =+SUM(START:END!I52) -> 0 | L52: =+SUM(START:END!L52) -> 3903.91 | N52: =L52-F52 -> -1836.2788 | Q52: =+SUM(START:END!Q52) -> 6957.45 | S52: =L52-Q52 -> -3053.54
A53: =+B53&C53 -> Véhicules neufs[...] | B53: =+$K$1 -> Véhicules neufs | C53: [...] | F53: =+SUM(START:END!F53) -> 0 | I53: =+SUM(START:END!I53) -> 0 | L53: =+SUM(START:END!L53) -> 0 | N53: =L53-F53 -> 0 | Q53: =+SUM(START:END!Q53) -> 0 | S53: =L53-Q53 -> 0
A54: =+B54&C54 -> Véhicules neufsTOTAL PERSONNEL | B54: =+$K$1 -> Véhicules neufs | C54: TOTAL PERSONNEL | D54: % brut | E54: =F54/F$27 -> 0.25028151 | F54: =+SUM(F42:F53) -> 142231.34 | G54: % brut | H54: =I54/I$27 -> #DIV/0! | I54: =+SUM(I42:I53) -> 0 | J54: % brut | K54: =L54/L$27 -> 0.21172995 | L54: =+SUM(L42:L53) -> 104345.37 | N54: =+SUM(N42:N53) -> -37885.97 | O54: % brut | P54: =Q54/Q$27 -> 0.2582265 | Q54: =+SUM(Q42:Q53) -> 158230.16 | S54: =+SUM(S42:S53) -> -53884.79
A55: =+B55&C55 -> Véhicules neufsPublicité 2 | B55: =+$K$1 -> Véhicules neufs | C55: Publicité 2 | F55: =+SUM(START:END!F55) -> 0 | I55: =+SUM(START:END!I55) -> 0 | L55: =+SUM(START:END!L55) -> 0 | N55: =L55-F55 -> 0 | Q55: =+SUM(START:END!Q55) -> 0 | S55: =L55-Q55 -> 0
A56: =+B56&C56 -> Véhicules neufsService gratuit 2 | B56: =+$K$1 -> Véhicules neufs | C56: Service gratuit 2 | F56: =+SUM(START:END!F56) -> 0 | I56: =+SUM(START:END!I56) -> 0 | L56: =+SUM(START:END!L56) -> 0 | N56: =L56-F56 -> 0 | Q56: =+SUM(START:END!Q56) -> 0 | S56: =L56-Q56 -> 0
A57: =+B57&C57 -> Véhicules neufsFrais véhicules de cie | B57: =+$K$1 -> Véhicules neufs | C57: Frais véhicules de cie | F57: =+SUM(START:END!F57) -> 6109.5 | I57: =+SUM(START:END!I57) -> 0 | L57: =+SUM(START:END!L57) -> 3406.89 | N57: =L57-F57 -> -2702.61 | Q57: =+SUM(START:END!Q57) -> 27833.32 | S57: =L57-Q57 -> -24426.43
A58: =+B58&C58 -> Véhicules neufsInformatique | B58: =+$K$1 -> Véhicules neufs | C58: Informatique | F58: =+SUM(START:END!F58) -> 27586.057 | I58: =+SUM(START:END!I58) -> 0 | L58: =+SUM(START:END!L58) -> 27910.2 | N58: =L58-F58 -> 324.1435 | Q58: =+SUM(START:END!Q58) -> 15279.84 | S58: =L58-Q58 -> 12630.36
A59: =+B59&C59 -> Véhicules neufsFrais de déplacement | B59: =+$K$1 -> Véhicules neufs | C59: Frais de déplacement | F59: =+SUM(START:END!F59) -> 3990 | I59: =+SUM(START:END!I59) -> 0 | L59: =+SUM(START:END!L59) -> 9212.53 | N59: =L59-F59 -> 5222.53 | Q59: =+SUM(START:END!Q59) -> 2750.86 | S59: =L59-Q59 -> 6461.67
A60: =+B60&C60 -> Véhicules neufsServices extérieurs | B60: =+$K$1 -> Véhicules neufs | C60: Services extérieurs | F60: =+SUM(START:END!F60) -> 8017.081 | I60: =+SUM(START:END!I60) -> 0 | L60: =+SUM(START:END!L60) -> 10749.63 | N60: =L60-F60 -> 2732.549 | Q60: =+SUM(START:END!Q60) -> 10516.29 | S60: =L60-Q60 -> 233.34
A61: =+B61&C61 -> Véhicules neufsFournitures autres | B61: =+$K$1 -> Véhicules neufs | C61: Fournitures autres | F61: =+SUM(START:END!F61) -> 225 | I61: =+SUM(START:END!I61) -> 0 | L61: =+SUM(START:END!L61) -> 543.57 | N61: =L61-F61 -> 318.57 | Q61: =+SUM(START:END!Q61) -> 138.66 | S61: =L61-Q61 -> 404.91
A62: =+B62&C62 -> Véhicules neufsUniformes | B62: =+$K$1 -> Véhicules neufs | C62: Uniformes | F62: =+SUM(START:END!F62) -> 90 | I62: =+SUM(START:END!I62) -> 0 | L62: =+SUM(START:END!L62) -> 74.1 | N62: =L62-F62 -> -15.9 | Q62: =+SUM(START:END!Q62) -> 297 | S62: =L62-Q62 -> -222.9
A63: =+B63&C63 -> Véhicules neufsPapeterie | B63: =+$K$1 -> Véhicules neufs | C63: Papeterie | F63: =+SUM(START:END!F63) -> 1740 | I63: =+SUM(START:END!I63) -> 0 | L63: =+SUM(START:END!L63) -> 2087.3 | N63: =L63-F63 -> 347.3 | Q63: =+SUM(START:END!Q63) -> 1630.62 | S63: =L63-Q63 -> 456.68
A64: =+B64&C64 -> Véhicules neufsTéléphone | B64: =+$K$1 -> Véhicules neufs | C64: Téléphone | F64: =+SUM(START:END!F64) -> 472.8 | I64: =+SUM(START:END!I64) -> 0 | L64: =+SUM(START:END!L64) -> 906.55 | N64: =L64-F64 -> 433.75 | Q64: =+SUM(START:END!Q64) -> 559.83 | S64: =L64-Q64 -> 346.72
A65: =+B65&C65 -> Véhicules neufsFrais postaux | B65: =+$K$1 -> Véhicules neufs | C65: Frais postaux | F65: =+SUM(START:END!F65) -> 680 | I65: =+SUM(START:END!I65) -> 0 | L65: =+SUM(START:END!L65) -> 403.06 | N65: =L65-F65 -> -276.94 | Q65: =+SUM(START:END!Q65) -> 731.84 | S65: =L65-Q65 -> -328.78
A66: =+B66&C66 -> Véhicules neufsDivers | B66: =+$K$1 -> Véhicules neufs | C66: Divers | F66: =+SUM(START:END!F66) -> 1887.25 | I66: =+SUM(START:END!I66) -> 0 | L66: =+SUM(START:END!L66) -> 2081.31 | N66: =L66-F66 -> 194.06 | Q66: =+SUM(START:END!Q66) -> 3376.37 | S66: =L66-Q66 -> -1295.06
... A71: =+B71&C71 -> Véhicules neufs[...] | B71: =+$K$1 -> Véhicules neufs | C71: [...] | F71: =+SUM(START:END!F71) -> 0 | I71: =+SUM(START:END!I71) -> 0 | L71: =+SUM(START:END!L71) -> 0 | N71: =L71-F71 -> 0 | Q71: =+SUM(START:END!Q71) -> 0 | S71: =L71-Q71 -> 0
A72: =+B72&C72 -> Véhicules neufsTOTAL SEMI-FIXES | B72: =+$K$1 -> Véhicules neufs | C72: TOTAL SEMI-FIXES | D72: % brut | E72: =F72/F$27 -> 0.11406772 | F72: =+SUM(F55:F71) -> 64823.022 | G72: % brut | H72: =I72/I$27 -> #DIV/0! | I72: =+SUM(I55:I71) -> 0 | J72: % brut | K72: =L72/L$27 -> 0.1362586 | L72: =+SUM(L55:L71) -> 67151.36 | N72: =+SUM(N55:N71) -> 2328.3377 | O72: % brut | P72: =Q72/Q$27 -> 0.12362522 | Q72: =+SUM(Q55:Q71) -> 75752.25 | S72: =+SUM(S55:S71) -> -8600.89
A73: =+B73&C73 -> Véhicules neufs | B73: =+$K$1 -> Véhicules neufs
A74: =+B74&C74 -> Véhicules neufsTOTAL DES DÉPENSES | B74: =+$K$1 -> Véhicules neufs | C74: TOTAL DES DÉPENSES | D74: % brut | E74: =F74/F$27 -> 0.8576982 | F74: =F41+F54+F72 -> 487417.4 | G74: % brut | H74: =I74/I$27 -> #DIV/0! | I74: =I41+I54+I72 -> 0 | J74: % brut | K74: =L74/L$27 -> 0.82703811 | L74: =L41+L54+L72 -> 407583.32 | N74: =L74-F74 -> -79834.078 | O74: % brut | P74: =Q74/Q$27 -> 0.89676031 | Q74: =Q41+Q54+Q72 -> 549496.38 | S74: =L74-Q74 -> -141913.06
A75: =+B75&C75 -> Véhicules neufsRBSC neuf | B75: =+$K$1 -> Véhicules neufs | C75: RBSC neuf | F75: =+SUM(START:END!F75) -> 150269.81 | I75: =+SUM(START:END!I75) -> 0 | L75: =+SUM(START:END!L75) -> 137796.24 | N75: =L75-F75 -> -12473.574 | Q75: =+SUM(START:END!Q75) -> 147274.36 | S75: =L75-Q75 -> -9478.12
A76: =+B76&C76 -> Véhicules neufsProgramme neuf 2 | B76: =+$K$1 -> Véhicules neufs | C76: Programme neuf 2 | F76: =+SUM(START:END!F76) -> 0 | I76: =+SUM(START:END!I76) -> 0 | L76: =+SUM(START:END!L76) -> 0 | N76: =L76-F76 -> 0 | Q76: =+SUM(START:END!Q76) -> 0 | S76: =L76-Q76 -> 0
A77: =+B77&C77 -> Véhicules neufsProgramme neuf 3 | B77: =+$K$1 -> Véhicules neufs | C77: Programme neuf 3 | F77: =+SUM(START:END!F77) -> 0 | I77: =+SUM(START:END!I77) -> 0 | L77: =+SUM(START:END!L77) -> 0 | N77: =L77-F77 -> 0 | Q77: =+SUM(START:END!Q77) -> 0 | S77: =L77-Q77 -> 0
A78: =+B78&C78 -> Véhicules neufsHoldbacks | B78: =+$K$1 -> Véhicules neufs | C78: Holdbacks | F78: =+SUM(START:END!F78) -> 182145.23 | I78: =+SUM(START:END!I78) -> 0 | L78: =+SUM(START:END!L78) -> 165196.8 | N78: =L78-F78 -> -16948.429 | Q78: =+SUM(START:END!Q78) -> 160254.8 | S78: =L78-Q78 -> 4942
A79: =+B79&C79 -> Véhicules neufs[...] | B79: =+$K$1 -> Véhicules neufs | C79: [...] | F79: =+SUM(START:END!F79) -> 0 | I79: =+SUM(START:END!I79) -> 0 | L79: =+SUM(START:END!L79) -> 0 | N79: =L79-F79 -> 0 | Q79: =+SUM(START:END!Q79) -> 0 | S79: =L79-Q79 -> 0
A80: =+B80&C80 -> Véhicules neufs[...] | B80: =+$K$1 -> Véhicules neufs | C80: [...] | F80: =+SUM(START:END!F80) -> 0 | I80: =+SUM(START:END!I80) -> 0 | L80: =+SUM(START:END!L80) -> 0 | N80: =L80-F80 -> 0 | Q80: =+SUM(START:END!Q80) -> 0 | S80: =L80-Q80 -> 0
A81: =+B81&C81 -> Véhicules neufs[...] | B81: =+$K$1 -> Véhicules neufs | C81: [...] | F81: =+SUM(START:END!F81) -> 0 | I81: =+SUM(START:END!I81) -> 0 | L81: =+SUM(START:END!L81) -> 0 | N81: =L81-F81 -> 0 | Q81: =+SUM(START:END!Q81) -> 0 | S81: =L81-Q81 -> 0
A82: =+B82&C82 -> Véhicules neufsFrais administration | B82: =+$K$1 -> Véhicules neufs | C82: Frais administration | F82: =+SUM(START:END!F82) -> 60059.3 | I82: =+SUM(START:END!I82) -> 0 | L82: =+SUM(START:END!L82) -> 53550 | N82: =L82-F82 -> -6509.3 | Q82: =+SUM(START:END!Q82) -> 55335 | S82: =L82-Q82 -> -1785
A83: =+B83&C83 -> Véhicules neufsAUTRES REVENUS | B83: =+$K$1 -> Véhicules neufs | C83: AUTRES REVENUS | F83: =+SUM(F75:F82) -> 392474.34 | I83: =+SUM(I75:I82) -> 0 | L83: =+SUM(L75:L82) -> 356543.04 | N83: =+SUM(N75:N82) -> -35931.302 | Q83: =+SUM(Q75:Q82) -> 362864.16 | S83: =+SUM(S75:S82) -> -6321.12
A84: =+B84&C84 -> Véhicules neufs | B84: =+$K$1 -> Véhicules neufs
A85: =+B85&C85 -> Véhicules neufsPROFIT DÉPARTEMENTAL | B85: =+$K$1 -> Véhicules neufs | C85: PROFIT DÉPARTEMENTAL | F85: =F27-F74+F83 -> 473342.39 | I85: =I27-I74+I83 -> 0 | L85: =L27-L74+L83 -> 441782.62 | N85: =N27-N41-N54-N72+N83 -> -31559.765 | Q85: =Q27-Q74+Q83 -> 426125.03 | S85: =S27-S41-S54-S72+S83 -> 15657.59
C89: =C1 -> BMW Sherbrooke | K89: Véhicules usagés | S89: =$S$1 -> Réalisé Q2 2026
D91: BUDGET ORIGINAL | G91: BUDGET RÉVISÉ | J91: RÉALISATION | M91: ÉCART réel / Budget | O91: ANNÉE PRÉCÉDENTE | R91: ECART (réel/ Ann.Préc.)
D92: UNITE | E92: $P/UNITÉ | F92: $PROFITS | G92: UNITE | H92: $P/UNITÉ | I92: $PROFITS | J92: UNITE | K92: $P/UNITE | L92: $PROFITS | M92: UNFTÉ | N92: $PROFFTS | O92: UNITE | P92: $P/UNITE | Q92: $PROFITS | R92: UNITE | S92: $PROFITS
A93: =+B93&C93 -> Véhicules usagésVentes nettes | B93: Véhicules usagés | C93: Ventes nettes | F93: =+SUM(START:END!F93) -> 6592888.3 | I93: =+SUM(START:END!I93) -> 0 | L93: =+SUM(START:END!L93) -> 7460702.5 | Q93: =+SUM(START:END!Q93) -> 4642482.4
A94: =+B94&C94 -> Véhicules usagésCertifié | B94: Véhicules usagés | C94: Certifié | D94: =+SUM(START:END!D94) -> 46 | E94: =IF(D94=0,0,F94/D94) -> 2400 | F94: =+SUM(START:END!F94) -> 110400 | G94: =+SUM(START:END!G94) -> 0 | H94: =IF(G94=0,0,I94/G94) -> 0 | I94: =+SUM(START:END!I94) -> 0 | J94: =+SUM(START:END!J94) -> 35 | K94: =IF(J94=0,0,L94/J94) -> 1828.6843 | L94: =+SUM(START:END!L94) -> 64003.95 | M94: =J94-D94 -> -11 | N94: =L94-F94 -> -46396.05 | O94: =+SUM(START:END!O94) -> 14 | P94: =IF(O94=0,0,Q94/O94) -> 2570.5036 | Q94: =+SUM(START:END!Q94) -> 35987.05 | R94: =J94-O94 -> 21 | S94: =L94-Q94 -> 28016.9
A95: =+B95&C95 -> Véhicules usagésNon Certifié | B95: Véhicules usagés | C95: Non Certifié | D95: =+SUM(START:END!D95) -> 12 | E95: =IF(D95=0,0,F95/D95) -> 1400 | F95: =+SUM(START:END!F95) -> 16800 | G95: =+SUM(START:END!G95) -> 0 | H95: =IF(G95=0,0,I95/G95) -> 0 | I95: =+SUM(START:END!I95) -> 0 | J95: =+SUM(START:END!J95) -> 9 | K95: =IF(J95=0,0,L95/J95) -> 3424.6667 | L95: =+SUM(START:END!L95) -> 30822 | M95: =J95-D95 -> -3 | N95: =L95-F95 -> 14022 | O95: =+SUM(START:END!O95) -> 29 | P95: =IF(O95=0,0,Q95/O95) -> 1877.6983 | Q95: =+SUM(START:END!Q95) -> 54453.25 | R95: =J95-O95 -> -20 | S95: =L95-Q95 -> -23631.25
A96: =+B96&C96 -> Véhicules usagésAutres marques | B96: Véhicules usagés | C96: Autres marques | D96: =+SUM(START:END!D96) -> 19 | E96: =IF(D96=0,0,F96/D96) -> 1500 | F96: =+SUM(START:END!F96) -> 28500 | G96: =+SUM(START:END!G96) -> 0 | H96: =IF(G96=0,0,I96/G96) -> 0 | I96: =+SUM(START:END!I96) -> 0 | J96: =+SUM(START:END!J96) -> 19 | K96: =IF(J96=0,0,L96/J96) -> 2094.4832 | L96: =+SUM(START:END!L96) -> 39795.18 | M96: =J96-D96 -> 0 | N96: =L96-F96 -> 11295.18 | O96: =+SUM(START:END!O96) -> 19 | P96: =IF(O96=0,0,Q96/O96) -> 1441.9768 | Q96: =+SUM(START:END!Q96) -> 27397.56 | R96: =J96-O96 -> 0 | S96: =L96-Q96 -> 12397.62
A97: =+B97&C97 -> Véhicules usagésTotal Usagés | B97: Véhicules usagés | C97: Total Usagés | D97: =+D95+D94+D96 -> 77 | E97: =IF(D97=0,0,F97/D97) -> 2022.0779 | F97: =+F94+F95+F96 -> 155700 | G97: =+G95+G94+G96 -> 0 | H97: =IF(G97=0,0,I97/G97) -> 0 | I97: =+I94+I95+I96 -> 0 | J97: =+J95+J94+J96 -> 63 | K97: =IF(J97=0,0,L97/J97) -> 2136.8433 | L97: =+L94+L95+L96 -> 134621.13 | M97: =J97-D97 -> -14 | N97: =L97-F97 -> -21078.87 | O97: =+O95+O94+O96 -> 62 | P97: =IF(O97<=0,0,Q97/O97) -> 1900.6106 | Q97: =+Q94+Q95+Q96 -> 117837.86 | R97: =J97-O97 -> 1 | S97: =L97-Q97 -> 16783.27
A98: =+B98&C98 -> Véhicules usagés | B98: Véhicules usagés | H98: =IF(G98=0,0,I98/G98) -> 0 | M98: =M97/D97 -> -0.18181818 | N98: =N97/F97 -> -0.13538131 | R98: =R97/O97 -> 0.016129032 | S98: =IF(Q97=0,0,(S97/Q97)) -> 0.14242681
A99: =+B99&C99 -> Véhicules usagésRachat bail | B99: Véhicules usagés | C99: Rachat bail | F99: =+SUM(START:END!F99) -> 6532.8942 | I99: =+SUM(START:END!I99) -> 0 | L99: =+SUM(START:END!L99) -> 9983.01 | N99: =L99-F99 -> 3450.1158 | Q99: =+SUM(START:END!Q99) -> 7056.64 | R99: =O99-K99 -> 0 | S99: =L99-Q99 -> 2926.37
A100: =+B100&C100 -> Véhicules usagés | B100: Véhicules usagés
A101: =+B101&C101 -> Véhicules usagésVentes au Gros | B101: Véhicules usagés | C101: Ventes au Gros | D101: =+SUM(START:END!D101) -> 81 | E101: =IF(D101=0,0,F101/D101) -> 500 | F101: =+SUM(START:END!F101) -> 40500 | G101: =+SUM(START:END!G101) -> 0 | H101: =IF(G101=0,0,I101/G101) -> 0 | I101: =+SUM(START:END!I101) -> 0 | J101: =+SUM(START:END!J101) -> 108 | K101: =IF(J101=0,0,L101/J101) -> 634.12583 | L101: =+SUM(START:END!L101) -> 68485.59 | M101: =J101-D101 -> 27 | N101: =L101-F101 -> 27985.59 | O101: =+SUM(START:END!O101) -> 60 | P101: =IF(O101=0,0,Q101/O101) -> 404.7835 | Q101: =+SUM(START:END!Q101) -> 24287.01 | R101: =J101-O101 -> 48 | S101: =L101-Q101 -> 44198.58
A102: =+B102&C102 -> Véhicules usagés | B102: Véhicules usagés
A103: =+B103&C103 -> Véhicules usagésRev. Finances | B103: Véhicules usagés | C103: Rev. Finances | D103: =+SUM(START:END!D103) -> 0 | E103: =IF(D103=0,0,F103/D103) -> 0 | F103: =+SUM(START:END!F103) -> 26950 | G103: =+SUM(START:END!G103) -> 0 | H103: =IF(G103=0,0,I103/G103) -> 0 | I103: =+SUM(START:END!I103) -> 0 | J103: =+SUM(START:END!J103) -> 0 | K103: =IF(J103=0,0,L103/J103) -> 0 | L103: =+SUM(START:END!L103) -> 23648.46 | N103: =L103-F103 -> -3301.54 | O103: =+SUM(START:END!O103) -> 0 | P103: =IF(O103=0,0,Q103/O103) -> 0 | Q103: =+SUM(START:END!Q103) -> 34930.13 | R103: =O103-K103 -> 0 | S103: =L103-Q103 -> -11281.67
A104: =+B104&C104 -> Véhicules usagésRev. Protections | B104: Véhicules usagés | C104: Rev. Protections | D104: =+SUM(START:END!D104) -> 0 | E104: =IF(D104=0,0,F104/D104) -> 0 | F104: =+SUM(START:END!F104) -> 73150 | G104: =+SUM(START:END!G104) -> 0 | H104: =IF(G104=0,0,I104/G104) -> 0 | I104: =+SUM(START:END!I104) -> 0 | J104: =+SUM(START:END!J104) -> 0 | K104: =IF(J104=0,0,L104/J104) -> 0 | L104: =+SUM(START:END!L104) -> 31423.86 | N104: =L104-F104 -> -41726.14 | O104: =+SUM(START:END!O104) -> 0 | P104: =IF(O104=0,0,Q104/O104) -> 0 | Q104: =+SUM(START:END!Q104) -> 86875.39 | R104: =O104-K104 -> 0 | S104: =L104-Q104 -> -55451.53
A105: =+B105&C105 -> Véhicules usagésRev. Autres | B105: Véhicules usagés | C105: Rev. Autres | D105: =+SUM(START:END!D105) -> 0 | E105: =IF(D105=0,0,F105/D105) -> 0 | F105: =+SUM(START:END!F105) -> 15400 | G105: =+SUM(START:END!G105) -> 0 | H105: =IF(G105=0,0,I105/G105) -> 0 | I105: =+SUM(START:END!I105) -> 0 | J105: =+SUM(START:END!J105) -> 0 | K105: =IF(J105=0,0,L105/J105) -> 0 | L105: =+SUM(START:END!L105) -> 5189.84 | N105: =L105-F105 -> -10210.16 | O105: =+SUM(START:END!O105) -> 0 | P105: =IF(O105=0,0,Q105/O105) -> 0 | Q105: =+SUM(START:END!Q105) -> 23749.93 | R105: =O105-K105 -> 0 | S105: =L105-Q105 -> -18560.09
A106: =+B106&C106 -> Véhicules usagésTotal F&I | B106: Véhicules usagés | C106: Total F&I | D106: =D98 -> 0 | E106: =IF(D106=0,0,F106/D106) -> 0 | F106: =F103+F104+F105 -> 115500 | G106: =G98 -> 0 | H106: =IF(G106=0,0,I106/G106) -> 0 | I106: =I103+I104+I105 -> 0 | J106: =J98 -> 0 | K106: =IF(J106<=0,0,L106/J106) -> 0 | L106: =L103+L104+L105 -> 60262.16 | M106: =J106-D106 -> 0 | N106: =L106-F106 -> -55237.84 | O106: =O98 -> 0 | P106: =IF(O106<=0,0,Q106/O106) -> 0 | Q106: =Q103+Q104+Q105 -> 145555.45 | S106: =L106-Q106 -> -85293.29
A107: =+B107&C107 -> Véhicules usagés | B107: Véhicules usagés | N107: =N106/F106 -> -0.4782497 | S107: =IF(Q106=0,0,(S106/Q106)) -> -0.58598486
A108: =+B108&C108 -> Véhicules usagés | B108: Véhicules usagés
...

Sheet START

Sheet Mois 1
C1: BMW Sherbrooke | K1: Véhicules neufs | S1: Réalisé, Avril 2026
D2: X | E2: O | F2: U | J2: NB | L2: $ | O2: X | P2: O | Q2: U
D3: BUDGET ORIGINAL | J3: RÉALISATION | M3: ÉCART réel / Budget | O3: ANNÉE PRÉCÉDENTE | R3: ECART (réel/ Ann.Préc.)
D4: UNITE | E4: $P/UNITÉ | F4: $PROFITS | J4: UNITE | K4: $P/UNITE | L4: $PROFITS | M4: UNFTÉ | N4: $PROFITS | O4: UNITE | P4: $P/UNITÉ | Q4: $PROFITS | R4: UNITE | S4: $PROFITS
A5: =+B5&C5 -> Véhicules neufsVentes nettes | B5: =+$K$1 -> Véhicules neufs | C5: Ventes nettes | F5: 3149139.2 | L5: 2930239.2 | Q5: 2822748.8
A6: =+B6&C6 -> Véhicules neufsAutos détail | B6: =+$K$1 -> Véhicules neufs | C6: Autos détail | D6: 10 | E6: =IF(D6=0,0,F6/D6) -> 4701.1765 | F6: 47011.765 | J6: 10 | K6: =IF(J6=0,0,L6/J6) -> 4249.874 | L6: 42498.74 | M6: =J6-D6 -> 0 | N6: =L6-F6 -> -4513.0247 | O6: 6 | P6: =IF(O6=0,0,Q6/O6) -> 6338.2117 | Q6: 38029.27 | R6: =J6-O6 -> 4 | S6: =L6-Q6 -> 4469.47
A7: =+B7&C7 -> Véhicules neufsCamions détail | B7: =+$K$1 -> Véhicules neufs | C7: Camions détail | D7: 20 | E7: =IF(D7=0,0,F7/D7) -> 3928.5 | F7: 78570 | J7: 15 | K7: =IF(J7=0,0,L7/J7) -> 3894.7053 | L7: 58420.58 | M7: =J7-D7 -> -5 | N7: =L7-F7 -> -20149.42 | O7: 15 | P7: =IF(O7=0,0,Q7/O7) -> 4719.5127 | Q7: 70792.69 | R7: =J7-O7 -> 0 | S7: =L7-Q7 -> -12372.11
A8: =+B8&C8 -> Véhicules neufsSprinter | B8: =+$K$1 -> Véhicules neufs | C8: Sprinter | D8: 0 | E8: =IF(D8=0,0,F8/D8) -> 0 | F8: 0 | J8: 0 | K8: =IF(J8=0,0,L8/J8) -> 0 | L8: 0 | M8: =J8-D8 -> 0 | N8: =L8-F8 -> 0 | O8: 0 | P8: =IF(O8=0,0,Q8/O8) -> 0 | Q8: 0 | R8: =J8-O8 -> 0 | S8: =L8-Q8 -> 0
A9: =+B9&C9 -> Véhicules neufsMoto détail | B9: =+$K$1 -> Véhicules neufs | C9: Moto détail | D9: 0 | E9: =IF(D9=0,0,F9/D9) -> 0 | F9: 0 | J9: 0 | K9: =IF(J9=0,0,L9/J9) -> 0 | L9: 0 | M9: =J9-D9 -> 0 | N9: =L9-F9 -> 0 | O9: 0 | P9: =IF(O9=0,0,Q9/O9) -> 0 | Q9: 0 | R9: =J9-O9 -> 0 | S9: =L9-Q9 -> 0
A10: =+B10&C10 -> Véhicules neufs[...] | B10: =+$K$1 -> Véhicules neufs | C10: [...] | D10: 0 | E10: =IF(D10=0,0,F10/D10) -> 0 | F10: 0 | J10: 0 | K10: =IF(J10=0,0,L10/J10) -> 0 | L10: 0 | M10: =J10-D10 -> 0 | N10: =L10-F10 -> 0 | O10: 0 | P10: =IF(O10=0,0,Q10/O10) -> 0 | Q10: 0 | R10: =J10-O10 -> 0 | S10: =L10-Q10 -> 0
A11: =+B11&C11 -> Véhicules neufs[...] | B11: =+$K$1 -> Véhicules neufs | C11: [...] | D11: 0 | E11: =IF(D11=0,0,F11/D11) -> 0 | F11: 0 | J11: 0 | K11: =IF(J11=0,0,L11/J11) -> 0 | L11: 0 | M11: =J11-D11 -> 0 | N11: =L11-F11 -> 0 | O11: 0 | P11: =IF(O11=0,0,Q11/O11) -> 0 | Q11: 0 | R11: =J11-O11 -> 0 | S11: =L11-Q11 -> 0
A12: =+B12&C12 -> Véhicules neufs[...] | B12: =+$K$1 -> Véhicules neufs | C12: [...] | D12: 0 | E12: =IF(D12=0,0,F12/D12) -> 0 | F12: 0 | J12: 0 | K12: =IF(J12=0,0,L12/J12) -> 0 | L12: 0 | M12: =J12-D12 -> 0 | N12: =L12-F12 -> 0 | O12: 0 | P12: =IF(O12=0,0,Q12/O12) -> 0 | Q12: 0 | R12: =J12-O12 -> 0 | S12: =L12-Q12 -> 0
A13: =+B13&C13 -> Véhicules neufsTotal Neufs | B13: =+$K$1 -> Véhicules neufs | C13: Total Neufs | D13: =+SUM(D6:D12) -> 30 | E13: =IF(D13<=0,0,F13/D13) -> 4186.0588 | F13: =+SUM(F6:F12) -> 125581.76 | J13: =+SUM(J6:J12) -> 25 | K13: =IF(J13<=0,0,L13/J13) -> 4036.7728 | L13: =+SUM(L6:L12) -> 100919.32 | M13: =+SUM(M6:M12) -> -5 | N13: =+SUM(N6:N12) -> -24662.445 | O13: =+SUM(O6:O12) -> 21 | P13: =IF(O13<=0,0,Q13/O13) -> 5181.9981 | Q13: =+SUM(Q6:Q12) -> 108821.96 | R13: =+SUM(R6:R12) -> 4 | S13: =+SUM(S6:S12) -> -7902.64
A14: =+B14&C14 -> Véhicules neufs | B14: =+$K$1 -> Véhicules neufs | M14: =IF(D13=0,0,M13/D13) -> -0.16666667 | N14: =IF(F13=0,0,N13/F13) -> -0.19638556 | R14: =R13/O13 -> 0.19047619 | S14: =IF(Q13=0,0,(S13/Q13)) -> -0.072619901
A15: =+B15&C15 -> Véhicules neufsEx-Démos et courtoisies | B15: =+$K$1 -> Véhicules neufs | C15: Ex-Démos et courtoisies | D15: 4 | E15: =IF(D15=0,0,F15/D15) -> 1200 | F15: 4800 | J15: 1 | K15: =IF(J15=0,0,L15/J15) -> 1824.91 | L15: 1824.91 | M15: =J15-D15 -> -3 | N15: =L15-F15 -> -2975.09 | O15: 8 | P15: =IF(O15=0,0,Q15/O15) -> 2225.18 | Q15: 17801.44 | R15: =J15-O15 -> -7 | S15: =L15-Q15 -> -15976.53
A16: =+B16&C16 -> Véhicules neufs | B16: =+$K$1 -> Véhicules neufs
A17: =+B17&C17 -> Véhicules neufsFlottes | B17: =+$K$1 -> Véhicules neufs | C17: Flottes | D17: 2 | E17: =IF(D17=0,0,F17/D17) -> 750 | F17: 1500 | J17: 5 | K17: =IF(J17=0,0,L17/J17) -> 1065.894 | L17: 5329.47 | M17: =J17-D17 -> 3 | N17: =L17-F17 -> 3829.47 | O17: 0 | P17: =IF(O17=0,0,Q17/O17) -> 0 | Q17: 0 | R17: =J17-O17 -> 5 | S17: =L17-Q17 -> 5329.47
A18: =+B18&C18 -> Véhicules neufs | B18: =+$K$1 -> Véhicules neufs
B19: =+$K$1 -> Véhicules neufs
A20: =+B20&C20 -> Véhicules neufs | B20: =+$K$1 -> Véhicules neufs
A21: =+B21&C21 -> Véhicules neufsRev. Finances | B21: =+$K$1 -> Véhicules neufs | C21: Rev. Finances | E21: =IF(D13=0,0,F21/(D13+D15)) -> 7 | F21: 238 | K21: =IF(J13=0,0,L21/(J13+J15)) -> 51.150385 | L21: 1329.91 | N21: =L21-F21 -> 1091.91 | P21: =IF(O13=0,0,Q21/(O13+O15)) -> 16.962414 | Q21: 491.91 | R21: =O21-K21 -> -51.150385 | S21: =L21-Q21 -> 838
A22: =+B22&C22 -> Véhicules neufsRev. Protections | B22: =+$K$1 -> Véhicules neufs | C22: Rev. Protections | E22: =IF(D13=0,0,F22/(D13+D15)) -> 1150 | F22: 39100 | K22: =IF(J13=0,0,L22/(J13+J15)) -> 685.80769 | L22: 17831 | N22: =L22-F22 -> -21269 | P22: =IF(O13=0,0,Q22/(O13+O15)) -> 1674.7852 | Q22: 48568.77 | R22: =O22-K22 -> -685.80769 | S22: =L22-Q22 -> -30737.77
A23: =+B23&C23 -> Véhicules neufsRev. Autres | B23: =+$K$1 -> Véhicules neufs | C23: Rev. Autres | E23: =IF(D13=0,0,F23/(D13+D15)) -> 443 | F23: 15062 | K23: =IF(J13=0,0,L23/(J13+J15)) -> 451.71308 | L23: 11744.54 | N23: =L23-F23 -> -3317.46 | P23: =IF(O13=0,0,Q23/(O13+O15)) -> 843.75828 | Q23: 24468.99 | R23: =O23-K23 -> -451.71308 | S23: =L23-Q23 -> -12724.45
A24: =+B24&C24 -> Véhicules neufsTotal F&I | B24: =+$K$1 -> Véhicules neufs | C24: Total F&I | D24: =+D15+D13 -> 34 | E24: =IF(D24<=0,0,F24/D24) -> 1600 | F24: =F21+F22+F23 -> 54400 | J24: =+J15+J13 -> 26 | K24: =IF(J24<=0,0,L24/J24) -> 1188.6712 | L24: =L21+L22+L23 -> 30905.45 | M24: =J24-D24 -> -8 | N24: =L24-F24 -> -23494.55 | O24: =+O15+O13 -> 29 | P24: =IF(O24<=0,0,Q24/O24) -> 2535.5059 | Q24: =Q21+Q22+Q23 -> 73529.67 | S24: =L24-Q24 -> -42624.22
A25: =+B25&C25 -> Véhicules neufs | B25: =+$K$1 -> Véhicules neufs | N25: =IF(N24=0,0,N24/F24) -> -0.43188511 | S25: =IF(Q24=0,0,(S24/Q24)) -> -0.57968736
A26: =+B26&C26 -> Véhicules neufs | B26: =+$K$1 -> Véhicules neufs
A27: =+B27&C27 -> Véhicules neufsTotal Dépt. Neufs | B27: =+$K$1 -> Véhicules neufs | C27: Total Dépt. Neufs | D27: =+D13+D15+D17 -> 36 | E27: =IF(D27<=0,0,F27/D27) -> 5174.4935 | F27: =F13+F17+F24+F15 -> 186281.76 | J27: =+J13+J15+J17 -> 31 | K27: =IF(J27<=0,0,L27/J27) -> 4483.1984 | L27: =L13+L17+L24+L15 -> 138979.15 | M27: =J27-D27 -> -5 | N27: =L27-F27 -> -47302.615 | O27: =+O13+O15+O17 -> 29 | P27: =IF(O27<=0,0,Q27/O27) -> 6901.83 | Q27: =Q13+Q17+Q24+Q15 -> 200153.07 | R27: =J27-O27 -> 2 | S27: =L27-Q27 -> -61173.92
A28: =+B28&C28 -> Véhicules neufs | B28: =+$K$1 -> Véhicules neufs | M28: =M27/D27 -> -0.13888889 | N28: =N27/F27 -> -0.25393046 | R28: =R27/O27 -> 0.068965517 | S28: =IF(Q27=0,0,S27/Q27) -> -0.30563568
A29: =+B29&C29 -> Véhicules neufs | B29: =+$K$1 -> Véhicules neufs
A30: =+B30&C30 -> Véhicules neufsDEPENSES | B30: =+$K$1 -> Véhicules neufs | C30: DEPENSES
A31: =+B31&C31 -> Véhicules neufsComm. vendeurs | B31: =+$K$1 -> Véhicules neufs | C31: Comm. vendeurs | D31: =F31/(F13+F15) -> 0.27513307 | E31: =F31/D$24 -> 1055.0687 | F31: 35872.335 | J31: =L31/(L13+L15) -> 0.21791316 | K31: =IF(L31=0,0,L31/J$24) -> 861.12769 | L31: 22389.32 | N31: =L31-F31 -> -13483.015 | O31: =Q31/(Q13+Q15+Q17) -> 0.24913105 | P31: =Q31/O$24 -> 1087.7869 | Q31: 31545.82 | S31: =L31-Q31 -> -9156.5
A32: =+B32&C32 -> Véhicules neufsComm. F&I | B32: =+$K$1 -> Véhicules neufs | C32: Comm. F&I | D32: =F32/F24 -> 0.305 | E32: =F32/D$24 -> 488 | F32: 16592 | J32: =L32/L24 -> 0.26398936 | K32: =IF(L32=0,0,L32/J$24) -> 313.79654 | L32: 8158.71 | N32: =L32-F32 -> -8433.29 | O32: =Q32/Q24 -> 0.34564999 | P32: =Q32/O$24 -> 876.39759 | Q32: 25415.53 | S32: =L32-Q32 -> -17256.82
A33: =+B33&C33 -> Véhicules neufsFrais de livraison | B33: =+$K$1 -> Véhicules neufs | C33: Frais de livraison | E33: =F33/D$24 -> 120 | F33: 4080 | K33: =IF(L33=0,0,L33/J$24) -> 188.28269 | L33: 4895.35 | N33: =L33-F33 -> 815.35 | P33: =Q33/O$24 -> 132.36483 | Q33: 3838.58 | S33: =L33-Q33 -> 1056.77 | V33: Transport
A34: =+B34&C34 -> Véhicules neufsService gratuit 1 | B34: =+$K$1 -> Véhicules neufs | C34: Service gratuit 1 | E34: =F34/D$24 -> 35 | F34: 1190 | K34: =IF(L34=0,0,L34/J$24) -> 40.125 | L34: 1043.25 | N34: =L34-F34 -> -146.75 | P34: =Q34/O$24 -> 62.720345 | Q34: 1818.89 | S34: =L34-Q34 -> -775.64
A35: =+B35&C35 -> Véhicules neufsEntretien stock | B35: =+$K$1 -> Véhicules neufs | C35: Entretien stock | E35: =F35/D$24 -> 95.794118 | F35: 3257 | K35: =IF(L35=0,0,L35/J$24) -> 64.176923 | L35: 1668.6 | N35: =L35-F35 -> -1588.4 | P35: =Q35/O$24 -> 37.223793 | Q35: 1079.49 | S35: =L35-Q35 -> 589.11
A36: =+B36&C36 -> Véhicules neufsPublicité 1 | B36: =+$K$1 -> Véhicules neufs | C36: Publicité 1 | E36: =F36/D$24 -> 234.88788 | F36: 7986.1879 | K36: =IF(L36=0,0,L36/J$24) -> 187.42346 | L36: 4873.01 | N36: =L36-F36 -> -3113.1779 | P36: =Q36/O$24 -> 595.14138 | Q36: 17259.1 | S36: =L36-Q36 -> -12386.09
A37: =+B37&C37 -> Véhicules neufsIntérêt de gros | B37: =+$K$1 -> Véhicules neufs | C37: Intérêt de gros | E37: =F37/D$24 -> 733.27477 | F37: 24931.342 | K37: =IF(L37=0,0,L37/J$24) -> 774.34885 | L37: 20133.07 | N37: =L37-F37 -> -4798.2722 | P37: =Q37/O$24 -> 853.67172 | Q37: 24756.48 | S37: =L37-Q37 -> -4623.41 | V37: 20133
A38: =+B38&C38 -> Véhicules neufs[...] | B38: =+$K$1 -> Véhicules neufs | C38: [...] | E38: =F38/D$24 -> 0 | F38: 0 | K38: =IF(L38=0,0,L38/J$24) -> 0 | L38: 0 | N38: =L38-F38 -> 0 | P38: =Q38/O$24 -> 0 | Q38: 0 | S38: =L38-Q38 -> 0
A39: =+B39&C39 -> Véhicules neufs[...] | B39: =+$K$1 -> Véhicules neufs | C39: [...] | E39: =F39/D$24 -> 0 | F39: 0 | K39: =IF(L39=0,0,L39/J$24) -> 0 | L39: 0 | N39: =L39-F39 -> 0 | P39: =Q39/O$24 -> 0 | Q39: 0 | S39: =L39-Q39 -> 0
A40: =+B40&C40 -> Véhicules neufs[...] | B40: =+$K$1 -> Véhicules neufs | C40: [...] | E40: =F40/D$24 -> 0 | F40: 0 | K40: =IF(L40=0,0,L40/J$24) -> 0 | L40: 0 | N40: =L40-F40 -> 0 | P40: =Q40/O$24 -> 0 | Q40: 0 | S40: =L40-Q40 -> 0
A41: =+B41&C41 -> Véhicules neufsTOTAL VARIABLES | B41: =+$K$1 -> Véhicules neufs | C41: TOTAL VARIABLES | D41: % brut | E41: =F41/F$27 -> 0.50412269 | F41: =SUM(F31:F40) -> 93908.865 | J41: % brut | K41: =L41/L$27 -> 0.45446608 | L41: =SUM(L31:L40) -> 63161.31 | N41: =L41-F41 -> -30747.555 | O41: % brut | P41: =Q41/Q$27 -> 0.52816522 | Q41: =SUM(Q31:Q40) -> 105713.89 | S41: =L41-Q41 -> -42552.58
A42: =+B42&C42 -> Véhicules neufsSalaires cadres | B42: =+$K$1 -> Véhicules neufs | C42: Salaires cadres | F42: 13260.139 | L42: 7262.3 | N42: =L42-F42 -> -5997.8393 | Q42: 13325.86 | S42: =L42-Q42 -> -6063.56
A43: =+B43&C43 -> Véhicules neufsSalaires commis | B43: =+$K$1 -> Véhicules neufs | C43: Salaires commis | F43: 5131.0855 | L43: 3761.82 | N43: =L43-F43 -> -1369.2655 | Q43: 8772.33 | S43: =L43-Q43 -> -5010.51
A44: =+B44&C44 -> Véhicules neufsSalaires autres | B44: =+$K$1 -> Véhicules neufs | C44: Salaires autres | F44: 0 | L44: 0 | N44: =L44-F44 -> 0 | Q44: 342 | S44: =L44-Q44 -> -342
A45: =+B45&C45 -> Véhicules neufsSalaires spécialistes | B45: =+$K$1 -> Véhicules neufs | C45: Salaires spécialistes | F45: 0 | L45: 0 | N45: =L45-F45 -> 0 | Q45: 0 | S45: =L45-Q45 -> 0
A46: =+B46&C46 -> Véhicules neufs[...] | B46: =+$K$1 -> Véhicules neufs | C46: [...] | F46: 0 | L46: 0 | N46: =L46-F46 -> 0 | Q46: 0 | S46: =L46-Q46 -> 0
A47: =+B47&C47 -> Véhicules neufs[...] | B47: =+$K$1 -> Véhicules neufs | C47: [...] | F47: 0 | L47: 0 | N47: =L47-F47 -> 0 | Q47: 0 | S47: =L47-Q47 -> 0
A48: =+B48&C48 -> Véhicules neufs[...] | B48: =+$K$1 -> Véhicules neufs | C48: [...] | F48: 0 | L48: 0 | N48: =L48-F48 -> 0 | Q48: 0 | S48: =L48-Q48 -> 0
A49: =+B49&C49 -> Véhicules neufsSalaires en absences | B49: =+$K$1 -> Véhicules neufs | C49: Salaires en absences | F49: 9867.3594 | L49: 6551.83 | N49: =L49-F49 -> -3315.5294 | Q49: 9449.46 | S49: =L49-Q49 -> -2897.63
A50: =+B50&C50 -> Véhicules neufsDéduction à la source | B50: =+$K$1 -> Véhicules neufs | C50: Déduction à la source | F50: 10479.052 | L50: 8051.55 | N50: =L50-F50 -> -2427.5023 | Q50: 11008.13 | S50: =L50-Q50 -> -2956.58
A51: =+B51&C51 -> Véhicules neufsBénéfices marginaux | B51: =+$K$1 -> Véhicules neufs | C51: Bénéfices marginaux | F51: 6791.9783 | L51: 3512.4 | N51: =L51-F51 -> -3279.5783 | Q51: 4701.09 | S51: =L51-Q51 -> -1188.69
A52: =+B52&C52 -> Véhicules neufsCsst | B52: =+$K$1 -> Véhicules neufs | C52: Csst | F52: 1901.7539 | L52: 1021.61 | N52: =L52-F52 -> -880.14393 | Q52: 1835.54 | S52: =L52-Q52 -> -813.93
A53: =+B53&C53 -> Véhicules neufs[...] | B53: =+$K$1 -> Véhicules neufs | C53: [...] | D53: =VLOOKUP(C53,$B$2:$B$46,1,FALSE) -> #N/A | F53: 0 | L53: 0 | N53: =L53-F53 -> 0 | Q53: 0 | S53: =L53-Q53 -> 0
A54: =+B54&C54 -> Véhicules neufsTOTAL PERSONNEL | B54: =+$K$1 -> Véhicules neufs | C54: TOTAL PERSONNEL | D54: % brut | E54: =F54/F$27 -> 0.25462164 | F54: =+SUM(F42:F53) -> 47431.369 | J54: % brut | K54: =L54/L$27 -> 0.21702183 | L54: =+SUM(L42:L53) -> 30161.51 | N54: =+SUM(N42:N53) -> -17269.859 | O54: % brut | P54: =Q54/Q$27 -> 0.24698302 | Q54: =+SUM(Q42:Q53) -> 49434.41 | S54: =+SUM(S42:S53) -> -19272.9
A55: =+B55&C55 -> Véhicules neufsPublicité 2 | B55: =+$K$1 -> Véhicules neufs | C55: Publicité 2 | F55: 0 | L55: 0 | N55: =L55-F55 -> 0 | Q55: 0 | S55: =L55-Q55 -> 0
A56: =+B56&C56 -> Véhicules neufsService gratuit 2 | B56: =+$K$1 -> Véhicules neufs | C56: Service gratuit 2 | F56: 0 | L56: 0 | N56: =L56-F56 -> 0 | Q56: 0 | S56: =L56-Q56 -> 0
A57: =+B57&C57 -> Véhicules neufsFrais véhicules de cie | B57: =+$K$1 -> Véhicules neufs | C57: Frais véhicules de cie | F57: 2036.5 | L57: 1002.45 | N57: =L57-F57 -> -1034.05 | Q57: 8435.32 | S57: =L57-Q57 -> -7432.87
A58: =+B58&C58 -> Véhicules neufsInformatique | B58: =+$K$1 -> Véhicules neufs | C58: Informatique | F58: 9195.3522 | L58: 9336.17 | N58: =L58-F58 -> 140.81783 | Q58: 4823.25 | S58: =L58-Q58 -> 4512.92
A59: =+B59&C59 -> Véhicules neufsFrais de déplacement | B59: =+$K$1 -> Véhicules neufs | C59: Frais de déplacement | F59: 1330 | L59: 1863.28 | N59: =L59-F59 -> 533.28 | Q59: 1180.26 | S59: =L59-Q59 -> 683.02
A60: =+B60&C60 -> Véhicules neufsServices extérieurs | B60: =+$K$1 -> Véhicules neufs | C60: Services extérieurs | F60: 2672.3603 | L60: 3191.92 | N60: =L60-F60 -> 519.55967 | Q60: 4615.6 | S60: =L60-Q60 -> -1423.68
A61: =+B61&C61 -> Véhicules neufsFournitures autres | B61: =+$K$1 -> Véhicules neufs | C61: Fournitures autres | F61: 75 | L61: 387.51 | N61: =L61-F61 -> 312.51 | Q61: 0 | S61: =L61-Q61 -> 387.51
A62: =+B62&C62 -> Véhicules neufsUniformes | B62: =+$K$1 -> Véhicules neufs | C62: Uniformes | F62: 30 | L62: 0 | N62: =L62-F62 -> -30 | Q62: 297 | S62: =L62-Q62 -> -297
A63: =+B63&C63 -> Véhicules neufsPapeterie | B63: =+$K$1 -> Véhicules neufs | C63: Papeterie | F63: 580 | L63: 912.46 | N63: =L63-F63 -> 332.46 | Q63: 527.44 | S63: =L63-Q63 -> 385.02
A64: =+B64&C64 -> Véhicules neufsTéléphone | B64: =+$K$1 -> Véhicules neufs | C64: Téléphone | F64: 157.6 | L64: 532.41 | N64: =L64-F64 -> 374.81 | Q64: 183.22 | S64: =L64-Q64 -> 349.19
A65: =+B65&C65 -> Véhicules neufsFrais postaux | B65: =+$K$1 -> Véhicules neufs | C65: Frais postaux | F65: 226.66667 | L65: 310.02 | N65: =L65-F65 -> 83.353333 | Q65: 222.71 | S65: =L65-Q65 -> 87.31
A66: =+B66&C66 -> Véhicules neufsDivers | B66: =+$K$1 -> Véhicules neufs | C66: Divers | F66: 629.08333 | L66: 845.12 | N66: =L66-F66 -> 216.03667 | Q66: 682.2 | S66: =L66-Q66 -> 162.92
... A68: =+B68&C68 -> Véhicules neufsFrais bancaires | B68: =+$K$1 -> Véhicules neufs | C68: Frais bancaires | F68: 4294.6546 | L68: 3700.4 | N68: =L68-F68 -> -594.25458 | Q68: 4475.89 | S68: =L68-Q68 -> -775.49
A69: =+B69&C69 -> Véhicules neufs[...] | B69: =+$K$1 -> Véhicules neufs | C69: [...] | F69: 0 | N69: =L69-F69 -> 0 | Q69: 0 | S69: =L69-Q69 -> 0
A70: =+B70&C70 -> Véhicules neufs[...] | B70: =+$K$1 -> Véhicules neufs | C70: [...] | F70: 0 | L70: 0 | N70: =L70-F70 -> 0 | Q70: 0 | S70: =L70-Q70 -> 0
A71: =+B71&C71 -> Véhicules neufs[...] | B71: =+$K$1 -> Véhicules neufs | C71: [...] | F71: 0 | L71: 0 | N71: =L71-F71 -> 0 | Q71: 0 | S71: =L71-Q71 -> 0
A72: =+B72&C72 -> Véhicules neufsTOTAL SEMI-FIXES | B72: =+$K$1 -> Véhicules neufs | C72: TOTAL SEMI-FIXES | D72: % brut | E72: =F72/F$27 -> 0.11567859 | F72: =+SUM(F55:F71) -> 21548.812 | J72: % brut | K72: =L72/L$27 -> 0.15823532 | L72: =+SUM(L55:L71) -> 21991.41 | N72: =+SUM(N55:N71) -> 442.59826 | O72: % brut | P72: =Q72/Q$27 -> 0.12985631 | Q72: =+SUM(Q55:Q71) -> 25991.14 | S72: =+SUM(S55:S71) -> -3999.73
A73: =+B73&C73 -> Véhicules neufs | B73: =+$K$1 -> Véhicules neufs
A74: =+B74&C74 -> Véhicules neufsTOTAL DES DÉPENSES | B74: =+$K$1 -> Véhicules neufs | C74: TOTAL DES DÉPENSES | D74: % brut | E74: =F74/F$27 -> 0.87442292 | F74: =F41+F54+F72 -> 162889.05 | J74: % brut | K74: =L74/L$27 -> 0.82972324 | L74: =L41+L54+L72 -> 115314.23 | N74: =L74-F74 -> -47574.816 | O74: % brut | P74: =Q74/Q$27 -> 0.90500455 | Q74: =Q41+Q54+Q72 -> 181139.44 | S74: =L74-Q74 -> -65825.21
A75: =+B75&C75 -> Véhicules neufsRBSC neuf | B75: =+$K$1 -> Véhicules neufs | C75: RBSC neuf | F75: 49630.397 | L75: 41431.62 | N75: =L75-F75 -> -8198.7771 | Q75: 43701.85 | S75: =L75-Q75 -> -2270.23
A76: =+B76&C76 -> Véhicules neufsProgramme neuf 2 | B76: =+$K$1 -> Véhicules neufs | C76: Programme neuf 2 | F76: 0 | L76: 0 | N76: =L76-F76 -> 0 | Q76: 0 | S76: =L76-Q76 -> 0
A77: =+B77&C77 -> Véhicules neufsProgramme neuf 3 | B77: =+$K$1 -> Véhicules neufs | C77: Programme neuf 3 | F77: 0 | L77: 0 | N77: =L77-F77 -> 0 | Q77: 0 | S77: =L77-Q77 -> 0
A78: =+B78&C78 -> Véhicules neufsHoldbacks | B78: =+$K$1 -> Véhicules neufs | C78: Holdbacks | F78: 60158.057 | L78: 53782 | N78: =L78-F78 -> -6376.0571 | Q78: 52973 | S78: =L78-Q78 -> 809
A79: =+B79&C79 -> Véhicules neufs[...] | B79: =+$K$1 -> Véhicules neufs | C79: [...] | F79: 0 | L79: 0 | N79: =L79-F79 -> 0 | Q79: 0 | S79: =L79-Q79 -> 0
A80: =+B80&C80 -> Véhicules neufs[...] | B80: =+$K$1 -> Véhicules neufs | C80: [...] | F80: 0 | L80: 0 | N80: =L80-F80 -> 0 | Q80: 0 | S80: =L80-Q80 -> 0
A81: =+B81&C81 -> Véhicules neufs[...] | B81: =+$K$1 -> Véhicules neufs | C81: [...] | F81: 0 | L81: 0 | N81: =L81-F81 -> 0 | Q81: 0 | S81: =L81-Q81 -> 0
A82: =+B82&C82 -> Véhicules neufsFrais administration | B82: =+$K$1 -> Véhicules neufs | C82: Frais administration | F82: 19825.4 | L82: 14280 | N82: =L82-F82 -> -5545.4 | Q82: 17255 | S82: =L82-Q82 -> -2975 | V82: =L82/595 -> 24 | W82: =V82/J27 -> 0.77419355
A83: =+B83&C83 -> Véhicules neufsAUTRES REVENUS | B83: =+$K$1 -> Véhicules neufs | C83: AUTRES REVENUS | F83: =+SUM(F75:F82) -> 129613.85 | L83: =+SUM(L75:L82) -> 109493.62 | N83: =+SUM(N75:N82) -> -20120.234 | Q83: =+SUM(Q75:Q82) -> 113929.85 | S83: =+SUM(S75:S82) -> -4436.23
A84: =+B84&C84 -> Véhicules neufs | B84: =+$K$1 -> Véhicules neufs
A85: =+B85&C85 -> Véhicules neufsPROFIT DÉPARTEMENTAL | B85: =+$K$1 -> Véhicules neufs | C85: PROFIT DÉPARTEMENTAL | F85: =F27-F74+F83 -> 153006.57 | L85: =L27-L74+L83 -> 133158.54 | N85: =N27-N41-N54-N72+N83 -> -19848.033 | Q85: =Q27-Q74+Q83 -> 132943.48 | S85: =S27-S41-S54-S72+S83 -> 215.06
C89: =C1 -> BMW Sherbrooke | K89: Véhicules usagés | S89: =$S$1 -> Réalisé, Avril 2026
D91: BUDGET ORIGINAL | J91: RÉALISATION | M91: ÉCART réel / Budget | O91: ANNÉE PRÉCÉDENTE | R91: ECART (réel/ Ann.Préc.)
D92: UNITE | E92: $P/UNITÉ | F92: $PROFITS | J92: UNITE | K92: $P/UNITE | L92: $PROFITS | M92: UNFTÉ | N92: $PROFFTS | O92: UNITE | P92: $P/UNITÉ | Q92: $PROFITS | R92: UNITE | S92: $PROFITS
A93: =+B93&C93 -> Véhicules usagésVentes nettes | B93: Véhicules usagés | C93: Ventes nettes | F93: 2102808.7 | L93: 2562554.5 | Q93: 1384484.5
A94: =+B94&C94 -> Véhicules usagésCertifié | B94: Véhicules usagés | C94: Certifié | D94: 15 | E94: =IF(D94=0,0,F94/D94) -> 2400 | F94: 36000 | J94: 7 | K94: =IF(J94=0,0,L94/J94) -> 2530.8914 | L94: 17716.24 | M94: =J94-D94 -> -8 | N94: =L94-F94 -> -18283.76 | O94: 5 | P94: =IF(O94=0,0,Q94/O94) -> 3241.292 | Q94: 16206.46 | R94: =J94-O94 -> 2 | S94: =L94-Q94 -> 1509.78
A95: =+B95&C95 -> Véhicules usagésNon Certifié | B95: Véhicules usagés | C95: Non Certifié | D95: 4 | E95: =IF(D95=0,0,F95/D95) -> 1400 | F95: 5600 | J95: 0 | K95: =IF(J95=0,0,L95/J95) -> 0 | L95: 0 | M95: =J95-D95 -> -4 | N95: =L95-F95 -> -5600 | O95: 12 | P95: =IF(O95=0,0,Q95/O95) -> 1852.42 | Q95: 22229.04 | R95: =J95-O95 -> -12 | S95: =L95-Q95 -> -22229.04
A96: =+B96&C96 -> Véhicules usagésAutres marques | B96: Véhicules usagés | C96: Autres marques | D96: 6 | E96: =IF(D96=0,0,F96/D96) -> 1500 | F96: 9000 | J96: 3 | K96: =IF(J96=0,0,L96/J96) -> 2969.6433 | L96: 8908.93 | M96: =J96-D96 -> -3 | N96: =L96-F96 -> -91.07 | O96: 5 | P96: =IF(O96=0,0,Q96/O96) -> 1888.092 | Q96: 9440.46 | R96: =J96-O96 -> -2 | S96: =L96-Q96 -> -531.53
A97: =+B97&C97 -> Véhicules usagésTotal Usagés | B97: Véhicules usagés | C97: Total Usagés | D97: =+D95+D94+D96 -> 25 | E97: =IF(D97=0,0,F97/D97) -> 2024 | F97: =+F94+F95+F96 -> 50600 | J97: =+J94+J95+J96 -> 10 | K97: =IF(J97<=0,0,L97/J97) -> 2662.517 | L97: =+L94+L95+L96 -> 26625.17 | M97: =J97-D97 -> -15 | N97: =L97-F97 -> -23974.83 | O97: =+O95+O94+O96 -> 22 | P97: =IF(O97=0,0,Q97/O97) -> 2176.18 | Q97: =+Q94+Q95+Q96 -> 47875.96 | R97: =J97-O97 -> -12 | S97: =L97-Q97 -> -21250.79
A98: =+B98&C98 -> Véhicules usagés | B98: Véhicules usagés | M98: =M97/D97 -> -0.6 | N98: =N97/F97 -> -0.47381087 | R98: =R97/O97 -> -0.54545455 | S98: =IF(Q97=0,0,(S97/Q97)) -> -0.44387183
A99: =+B99&C99 -> Véhicules neufsRachat bail | B99: =+$K$1 -> Véhicules neufs | C99: Rachat bail | D99: 0 | E99: =IF(D99=0,0,F99/D99) -> 0 | F99: 2188.3232 | L99: 999 | N99: =L99-F99 -> -1189.3232 | Q99: 3995.39 | R99: =O99-K99 -> 0 | S99: =L99-Q99 -> -2996.39
A100: =+B100&C100 -> Véhicules usagés | B100: Véhicules usagés
A101: =+B101&C101 -> Véhicules usagésVentes au Gros | B101: Véhicules usagés | C101: Ventes au Gros | D101: 25 | E101: =IF(D101=0,0,F101/D101) -> 500 | F101: 12500 | J101: 49 | K101: =IF(J101=0,0,L101/J101) -> 304.77714 | L101: 14934.08 | M101: =J101-D101 -> 24 | N101: =L101-F101 -> 2434.08 | O101: 15 | P101: =IF(O101=0,0,Q101/O101) -> 613.864 | Q101: 9207.96 | R101: =J101-O101 -> 34 | S101: =L101-Q101 -> 5726.12
A102: =+B102&C102 -> Véhicules usagés | B102: Véhicules usagés
A103: =+B103&C103 -> Véhicules usagésRev. Finances | B103: Véhicules usagés | C103: Rev. Finances | E103: =IF(D97=0,0,F103/D97) -> 350 | F103: 8750 | K103: =IF(J97=0,0,L103/J97) -> 253.281 | L103: 2532.81 | N103: =L103-F103 -> -6217.19 | P103: =IF(O97=0,0,Q103/O97) -> 605.96318 | Q103: 13331.19 | R103: =O103-K103 -> -253.281 | S103: =L103-Q103 -> -10798.38
A104: =+B104&C104 -> Véhicules usagésRev. Protections | B104: Véhicules usagés | C104: Rev. Protections | E104: =IF(D97=0,0,F104/D97) -> 950 | F104: 23750 | K104: =IF(J97=0,0,L104/J97) -> 670.776 | L104: 6707.76 | N104: =L104-F104 -> -17042.24 | P104: =IF(O97=0,0,Q104/O97) -> 1538.4391 | Q104: 33845.66 | R104: =O104-K104 -> -670.776 | S104: =L104-Q104 -> -27137.9
A105: =+B105&C105 -> Véhicules usagésRev. Autres | B105: Véhicules usagés | C105: Rev. Autres | E105: =IF(D97=0,0,F105/D97) -> 200 | F105: 5000 | K105: =IF(J97=0,0,L105/J97) -> 28.5 | L105: 285 | N105: =L105-F105 -> -4715 | P105: =IF(O97=0,0,Q105/O97) -> 191.39773 | Q105: 4210.75 | R105: =O105-K105 -> -28.5 | S105: =L105-Q105 -> -3925.75
...

Sheet Mois 2
C1: BMW Sherbrooke | K1: Véhicules neufs | S1: Réalisé, Mai 2026
D2: X | E2: O | F2: U | J2: NB | L2: $ | O2: X | P2: O | Q2: U
D3: BUDGET ORIGINAL | J3: RÉALISATION | M3: ÉCART réel / Budget | O3: ANNÉE PRÉCÉDENTE | R3: ECART (réel/ Ann.Préc.)
D4: UNITE | E4: $P/UNITÉ | F4: $PROFITS | J4: UNITE | K4: $P/UNITE | L4: $PROFITS | M4: UNFTÉ | N4: $PROFITS | O4: UNITE | P4: $P/UNITÉ | Q4: $PROFITS | R4: UNITE | S4: $PROFITS
A5: =+B5&C5 -> Véhicules neufsVentes nettes | B5: =+$K$1 -> Véhicules neufs | C5: Ventes nettes | F5: 3877423.6 | L5: 4159629.3 | Q5: 3847659.5
A6: =+B6&C6 -> Véhicules neufsAutos détail | B6: =+$K$1 -> Véhicules neufs | C6: Autos détail | D6: 9 | E6: =IF(D6=0,0,F6/D6) -> 4701.1765 | F6: 42310.588 | J6: 17 | K6: =IF(J6=0,0,L6/J6) -> 5664.9376 | L6: 96303.94 | M6: =J6-D6 -> 8 | N6: =L6-F6 -> 53993.352 | O6: 12 | P6: =IF(O6=0,0,Q6/O6) -> 5958.9625 | Q6: 71507.55 | R6: =J6-O6 -> 5 | S6: =L6-Q6 -> 24796.39
A7: =+B7&C7 -> Véhicules neufsCamions détail | B7: =+$K$1 -> Véhicules neufs | C7: Camions détail | D7: 31 | E7: =IF(D7=0,0,F7/D7) -> 3928.5 | F7: 121783.5 | J7: 18 | K7: =IF(J7=0,0,L7/J7) -> 3509.155 | L7: 63164.79 | M7: =J7-D7 -> -13 | N7: =L7-F7 -> -58618.71 | O7: 23 | P7: =IF(O7=0,0,Q7/O7) -> 3685.7178 | Q7: 84771.51 | R7: =J7-O7 -> -5 | S7: =L7-Q7 -> -21606.72
A8: =+B8&C8 -> Véhicules neufsSprinter | B8: =+$K$1 -> Véhicules neufs | C8: Sprinter | D8: 0 | E8: =IF(D8=0,0,F8/D8) -> 0 | F8: 0 | J8: 0 | K8: =IF(J8=0,0,L8/J8) -> 0 | L8: 0 | M8: =J8-D8 -> 0 | N8: =L8-F8 -> 0 | O8: 0 | P8: =IF(O8=0,0,Q8/O8) -> 0 | Q8: 0 | R8: =J8-O8 -> 0 | S8: =L8-Q8 -> 0
A9: =+B9&C9 -> Véhicules neufsMoto détail | B9: =+$K$1 -> Véhicules neufs | C9: Moto détail | D9: 0 | E9: =IF(D9=0,0,F9/D9) -> 0 | F9: 0 | J9: 0 | K9: =IF(J9=0,0,L9/J9) -> 0 | L9: 0 | M9: =J9-D9 -> 0 | N9: =L9-F9 -> 0 | O9: 0 | P9: =IF(O9=0,0,Q9/O9) -> 0 | Q9: 0 | R9: =J9-O9 -> 0 | S9: =L9-Q9 -> 0
A10: =+B10&C10 -> Véhicules neufs[...] | B10: =+$K$1 -> Véhicules neufs | C10: [...] | D10: 0 | E10: =IF(D10=0,0,F10/D10) -> 0 | F10: 0 | J10: 0 | K10: =IF(J10=0,0,L10/J10) -> 0 | L10: 0 | M10: =J10-D10 -> 0 | N10: =L10-F10 -> 0 | O10: 0 | P10: =IF(O10=0,0,Q10/O10) -> 0 | Q10: 0 | R10: =J10-O10 -> 0 | S10: =L10-Q10 -> 0
A11: =+B11&C11 -> Véhicules neufs[...] | B11: =+$K$1 -> Véhicules neufs | C11: [...] | D11: 0 | E11: =IF(D11=0,0,F11/D11) -> 0 | F11: 0 | J11: 0 | K11: =IF(J11=0,0,L11/J11) -> 0 | L11: 0 | M11: =J11-D11 -> 0 | N11: =L11-F11 -> 0 | O11: 0 | P11: =IF(O11=0,0,Q11/O11) -> 0 | Q11: 0 | R11: =J11-O11 -> 0 | S11: =L11-Q11 -> 0
A12: =+B12&C12 -> Véhicules neufs[...] | B12: =+$K$1 -> Véhicules neufs | C12: [...] | D12: 0 | E12: =IF(D12=0,0,F12/D12) -> 0 | F12: 0 | J12: 0 | K12: =IF(J12=0,0,L12/J12) -> 0 | L12: 0 | M12: =J12-D12 -> 0 | N12: =L12-F12 -> 0 | O12: 0 | P12: =IF(O12=0,0,Q12/O12) -> 0 | Q12: 0 | R12: =J12-O12 -> 0 | S12: =L12-Q12 -> 0
A13: =+B13&C13 -> Véhicules neufsTotal Neufs | B13: =+$K$1 -> Véhicules neufs | C13: Total Neufs | D13: =+SUM(D6:D12) -> 40 | E13: =IF(D13<=0,0,F13/D13) -> 4102.3522 | F13: =+SUM(F6:F12) -> 164094.09 | J13: =+SUM(J6:J12) -> 35 | K13: =IF(J13<=0,0,L13/J13) -> 4556.2494 | L13: =+SUM(L6:L12) -> 159468.73 | M13: =+SUM(M6:M12) -> -5 | N13: =+SUM(N6:N12) -> -4625.3582 | O13: =+SUM(O6:O12) -> 35 | P13: =IF(O13<=0,0,Q13/O13) -> 4465.116 | Q13: =+SUM(Q6:Q12) -> 156279.06 | R13: =+SUM(R6:R12) -> 0 | S13: =+SUM(S6:S12) -> 3189.67
A14: =+B14&C14 -> Véhicules neufs | B14: =+$K$1 -> Véhicules neufs | M14: =IF(D13=0,0,M13/D13) -> -0.125 | N14: =IF(F13=0,0,N13/F13) -> -0.028187233 | R14: =R13/O13 -> 0 | S14: =IF(Q13=0,0,(S13/Q13)) -> 0.020410092
A15: =+B15&C15 -> Véhicules neufsEx-Démos et courtoisies | B15: =+$K$1 -> Véhicules neufs | C15: Ex-Démos et courtoisies | D15: 3 | E15: =IF(D15=0,0,F15/D15) -> 1200 | F15: 3600 | J15: 8 | K15: =IF(J15=0,0,L15/J15) -> 309.51125 | L15: 2476.09 | M15: =J15-D15 -> 5 | N15: =L15-F15 -> -1123.91 | O15: 9 | P15: =IF(O15=0,0,Q15/O15) -> 3505.6622 | Q15: 31550.96 | R15: =J15-O15 -> -1 | S15: =L15-Q15 -> -29074.87
A16: =+B16&C16 -> Véhicules neufs | B16: =+$K$1 -> Véhicules neufs
A17: =+B17&C17 -> Véhicules neufsFlottes | B17: =+$K$1 -> Véhicules neufs | C17: Flottes | D17: 2 | E17: =IF(D17=0,0,F17/D17) -> 750 | F17: 1500 | J17: 0 | K17: =IF(J17=0,0,L17/J17) -> 0 | L17: 0 | M17: =J17-D17 -> -2 | N17: =L17-F17 -> -1500 | O17: 0 | P17: =IF(O17=0,0,Q17/O17) -> 0 | Q17: 0 | R17: =J17-O17 -> 0 | S17: =L17-Q17 -> 0
A18: =+B18&C18 -> Véhicules neufs | B18: =+$K$1 -> Véhicules neufs
B19: =+$K$1 -> Véhicules neufs
A20: =+B20&C20 -> Véhicules neufs | B20: =+$K$1 -> Véhicules neufs
A21: =+B21&C21 -> Véhicules neufsRev. Finances | B21: =+$K$1 -> Véhicules neufs | C21: Rev. Finances | E21: =IF(D13=0,0,F21/(D13+D15)) -> 7 | F21: 301 | K21: =IF(J13=0,0,L21/(J13+J15)) -> 0 | L21: 0 | N21: =L21-F21 -> -301 | P21: =IF(O13=0,0,Q21/(O13+O15)) -> 0 | Q21: 0 | R21: =O21-K21 -> 0 | S21: =L21-Q21 -> 0
A22: =+B22&C22 -> Véhicules neufsRev. Protections | B22: =+$K$1 -> Véhicules neufs | C22: Rev. Protections | E22: =IF(D13=0,0,F22/(D13+D15)) -> 1150 | F22: 49450 | K22: =IF(J13=0,0,L22/(J13+J15)) -> 530.09302 | L22: 22794 | N22: =L22-F22 -> -26656 | P22: =IF(O13=0,0,Q22/(O13+O15)) -> 1383.58 | Q22: 60877.52 | R22: =O22-K22 -> -530.09302 | S22: =L22-Q22 -> -38083.52
A23: =+B23&C23 -> Véhicules neufsRev. Autres | B23: =+$K$1 -> Véhicules neufs | C23: Rev. Autres | E23: =IF(D13=0,0,F23/(D13+D15)) -> 443 | F23: 19049 | K23: =IF(J13=0,0,L23/(J13+J15)) -> 550.17512 | L23: 23657.53 | N23: =L23-F23 -> 4608.53 | P23: =IF(O13=0,0,Q23/(O13+O15)) -> 730.50318 | Q23: 32142.14 | R23: =O23-K23 -> -550.17512 | S23: =L23-Q23 -> -8484.61
A24: =+B24&C24 -> Véhicules neufsTotal F&I | B24: =+$K$1 -> Véhicules neufs | C24: Total F&I | D24: =+D15+D13 -> 43 | E24: =IF(D24<=0,0,F24/D24) -> 1600 | F24: =F21+F22+F23 -> 68800 | J24: =+J15+J13 -> 43 | K24: =IF(J24<=0,0,L24/J24) -> 1080.2681 | L24: =L21+L22+L23 -> 46451.53 | M24: =J24-D24 -> 0 | N24: =L24-F24 -> -22348.47 | O24: =+O15+O13 -> 44 | P24: =IF(O24<=0,0,Q24/O24) -> 2114.0832 | Q24: =Q21+Q22+Q23 -> 93019.66 | S24: =L24-Q24 -> -46568.13
A25: =+B25&C25 -> Véhicules neufs | B25: =+$K$1 -> Véhicules neufs | N25: =IF(N24=0,0,N24/F24) -> -0.32483241 | S25: =IF(Q24=0,0,(S24/Q24)) -> -0.50062675
A26: =+B26&C26 -> Véhicules neufs | B26: =+$K$1 -> Véhicules neufs
A27: =+B27&C27 -> Véhicules neufsTotal Dépt. Neufs | B27: =+$K$1 -> Véhicules neufs | C27: Total Dépt. Neufs | D27: =+D13+D15+D17 -> 45 | E27: =IF(D27<=0,0,F27/D27) -> 5288.7575 | F27: =F13+F17+F24+F15 -> 237994.09 | J27: =+J13+J15+J17 -> 43 | K27: =IF(J27<=0,0,L27/J27) -> 4846.4267 | L27: =L13+L17+L24+L15 -> 208396.35 | M27: =J27-D27 -> -2 | N27: =L27-F27 -> -29597.738 | O27: =+O13+O15+O17 -> 44 | P27: =IF(O27<=0,0,Q27/O27) -> 6382.9473 | Q27: =Q13+Q17+Q24+Q15 -> 280849.68 | R27: =J27-O27 -> -1 | S27: =L27-Q27 -> -72453.33
A28: =+B28&C28 -> Véhicules neufs | B28: =+$K$1 -> Véhicules neufs | M28: =M27/D27 -> -0.044444444 | N28: =N27/F27 -> -0.12436333 | R28: =R27/O27 -> -0.022727273 | S28: =IF(Q27=0,0,S27/Q27) -> -0.25797904
A29: =+B29&C29 -> Véhicules neufs | B29: =+$K$1 -> Véhicules neufs
A30: =+B30&C30 -> Véhicules neufsDEPENSES | B30: =+$K$1 -> Véhicules neufs | C30: DEPENSES
A31: =+B31&C31 -> Véhicules neufsComm. vendeurs | B31: =+$K$1 -> Véhicules neufs | C31: Comm. vendeurs | D31: =F31/(F13+F15) -> 0.26746308 | E31: =F31/D$24 -> 1043.0692 | F31: 44851.977 | J31: =L31/(L13+L15) -> 0.28095798 | K31: =IF(L31=0,0,L31/J$24) -> 1058.1323 | L31: 45499.69 | N31: =L31-F31 -> 647.71309 | O31: =Q31/(Q13+Q15+Q17) -> 0.26266919 | P31: =Q31/O$24 -> 1121.2991 | Q31: 49337.16 | S31: =L31-Q31 -> -3837.47
A32: =+B32&C32 -> Véhicules neufsComm. F&I | B32: =+$K$1 -> Véhicules neufs | C32: Comm. F&I | D32: =F32/F24 -> 0.305 | E32: =F32/D$24 -> 488 | F32: 20984 | J32: =L32/L24 -> 0.21132953 | K32: =IF(L32=0,0,L32/J$24) -> 228.29256 | L32: 9816.58 | N32: =L32-F32 -> -11167.42 | O32: =Q32/Q24 -> 0.33628934 | P32: =Q32/O$24 -> 710.94364 | Q32: 31281.52 | S32: =L32-Q32 -> -21464.94
A33: =+B33&C33 -> Véhicules neufsFrais de livraison | B33: =+$K$1 -> Véhicules neufs | C33: Frais de livraison | E33: =F33/D$24 -> 120 | F33: 5160 | K33: =IF(L33=0,0,L33/J$24) -> 94.995581 | L33: 4084.81 | N33: =L33-F33 -> -1075.19 | P33: =Q33/O$24 -> 77.407727 | Q33: 3405.94 | S33: =L33-Q33 -> 678.87
A34: =+B34&C34 -> Véhicules neufsService gratuit 1 | B34: =+$K$1 -> Véhicules neufs | C34: Service gratuit 1 | E34: =F34/D$24 -> 35 | F34: 1505 | K34: =IF(L34=0,0,L34/J$24) -> 33.011628 | L34: 1419.5 | N34: =L34-F34 -> -85.5 | P34: =Q34/O$24 -> 38.5175 | Q34: 1694.77 | S34: =L34-Q34 -> -275.27
A35: =+B35&C35 -> Véhicules neufsEntretien stock | B35: =+$K$1 -> Véhicules neufs | C35: Entretien stock | E35: =F35/D$24 -> 94.162791 | F35: 4049 | K35: =IF(L35=0,0,L35/J$24) -> 53.356977 | L35: 2294.35 | N35: =L35-F35 -> -1754.65 | P35: =Q35/O$24 -> 38.751818 | Q35: 1705.08 | S35: =L35-Q35 -> 589.27
A36: =+B36&C36 -> Véhicules neufsPublicité 1 | B36: =+$K$1 -> Véhicules neufs | C36: Publicité 1 | E36: =F36/D$24 -> 234.88788 | F36: 10100.179 | K36: =IF(L36=0,0,L36/J$24) -> 147.20814 | L36: 6329.95 | N36: =L36-F36 -> -3770.2288 | P36: =Q36/O$24 -> 421.36636 | Q36: 18540.12 | S36: =L36-Q36 -> -12210.17
A37: =+B37&C37 -> Véhicules neufsIntérêt de gros | B37: =+$K$1 -> Véhicules neufs | C37: Intérêt de gros | E37: =F37/D$24 -> 575.03984 | F37: 24726.713 | K37: =IF(L37=0,0,L37/J$24) -> 530.82279 | L37: 22825.38 | N37: =L37-F37 -> -1901.3331 | P37: =Q37/O$24 -> 600.04409 | Q37: 26401.94 | S37: =L37-Q37 -> -3576.56 | V37: 22825
A38: =+B38&C38 -> Véhicules neufs[...] | B38: =+$K$1 -> Véhicules neufs | C38: [...] | E38: =F38/D$24 -> 0 | F38: 0 | K38: =IF(L38=0,0,L38/J$24) -> 0 | L38: 0 | N38: =L38-F38 -> 0 | P38: =Q38/O$24 -> 0 | Q38: 0 | S38: =L38-Q38 -> 0
A39: =+B39&C39 -> Véhicules neufs[...] | B39: =+$K$1 -> Véhicules neufs | C39: [...] | E39: =F39/D$24 -> 0 | F39: 0 | K39: =IF(L39=0,0,L39/J$24) -> 0 | L39: 0 | N39: =L39-F39 -> 0 | P39: =Q39/O$24 -> 0 | Q39: 0 | S39: =L39-Q39 -> 0
A40: =+B40&C40 -> Véhicules neufs[...] | B40: =+$K$1 -> Véhicules neufs | C40: [...] | E40: =F40/D$24 -> 0 | F40: 0 | K40: =IF(L40=0,0,L40/J$24) -> 0 | L40: 0 | N40: =L40-F40 -> 0 | P40: =Q40/O$24 -> 0 | Q40: 0 | S40: =L40-Q40 -> 0
A41: =+B41&C41 -> Véhicules neufsTOTAL VARIABLES | B41: =+$K$1 -> Véhicules neufs | C41: TOTAL VARIABLES | D41: % brut | E41: =F41/F$27 -> 0.46798166 | F41: =SUM(F31:F40) -> 111376.87 | J41: % brut | K41: =L41/L$27 -> 0.44276332 | L41: =SUM(L31:L40) -> 92270.26 | N41: =L41-F41 -> -19106.609 | O41: % brut | P41: =Q41/Q$27 -> 0.47130739 | Q41: =SUM(Q31:Q40) -> 132366.53 | S41: =L41-Q41 -> -40096.27
A42: =+B42&C42 -> Véhicules neufsSalaires cadres | B42: =+$K$1 -> Véhicules neufs | C42: Salaires cadres | F42: 13734.578 | L42: 10986.09 | N42: =L42-F42 -> -2748.4883 | Q42: 15912.54 | S42: =L42-Q42 -> -4926.45
A43: =+B43&C43 -> Véhicules neufsSalaires commis | B43: =+$K$1 -> Véhicules neufs | C43: Salaires commis | F43: 4897.8543 | L43: 4347.34 | N43: =L43-F43 -> -550.5143 | Q43: 10268.57 | S43: =L43-Q43 -> -5921.23
A44: =+B44&C44 -> Véhicules neufsSalaires autres | B44: =+$K$1 -> Véhicules neufs | C44: Salaires autres | F44: 0 | L44: 430 | N44: =L44-F44 -> 430 | Q44: 342 | S44: =L44-Q44 -> 88 | V44: Francis Pellerin - renouvellement Volks
A45: =+B45&C45 -> Véhicules neufsSalaires spécialistes | B45: =+$K$1 -> Véhicules neufs | C45: Salaires spécialistes | F45: 0 | L45: 0 | N45: =L45-F45 -> 0 | Q45: 0 | S45: =L45-Q45 -> 0
A46: =+B46&C46 -> Véhicules neufs[...] | B46: =+$K$1 -> Véhicules neufs | C46: [...] | F46: 0 | L46: 0 | N46: =L46-F46 -> 0 | Q46: 0 | S46: =L46-Q46 -> 0
A47: =+B47&C47 -> Véhicules neufs[...] | B47: =+$K$1 -> Véhicules neufs | C47: [...] | F47: 0 | L47: 0 | N47: =L47-F47 -> 0 | Q47: 0 | S47: =L47-Q47 -> 0
A48: =+B48&C48 -> Véhicules neufs[...] | B48: =+$K$1 -> Véhicules neufs | C48: [...] | F48: 0 | L48: 0 | N48: =L48-F48 -> 0 | Q48: 0 | S48: =L48-Q48 -> 0
A49: =+B49&C49 -> Véhicules neufsSalaires en absences | B49: =+$K$1 -> Véhicules neufs | C49: Salaires en absences | F49: 11161.79 | L49: 6889.7 | N49: =L49-F49 -> -4272.0905 | Q49: 9389.52 | S49: =L49-Q49 -> -2499.82
A50: =+B50&C50 -> Véhicules neufsDéduction à la source | B50: =+$K$1 -> Véhicules neufs | C50: Déduction à la source | F50: 12280.58 | L50: 8836.57 | N50: =L50-F50 -> -3444.0101 | Q50: 14580.12 | S50: =L50-Q50 -> -5743.55
A51: =+B51&C51 -> Véhicules neufsBénéfices marginaux | B51: =+$K$1 -> Véhicules neufs | C51: Bénéfices marginaux | F51: 7959.6353 | L51: 3451.84 | N51: =L51-F51 -> -4507.7953 | Q51: 5134.16 | S51: =L51-Q51 -> -1682.32
A52: =+B52&C52 -> Véhicules neufsCsst | B52: =+$K$1 -> Véhicules neufs | C52: Csst | F52: 2228.6979 | L52: 1374.42 | N52: =L52-F52 -> -854.27787 | Q52: 1956.39 | S52: =L52-Q52 -> -581.97
A53: =+B53&C53 -> Véhicules neufs[...] | B53: =+$K$1 -> Véhicules neufs | C53: [...] | D53: =VLOOKUP(C53,$B$2:$B$46,1,FALSE) -> #N/A | F53: 0 | L53: 0 | N53: =L53-F53 -> 0 | Q53: 0 | S53: =L53-Q53 -> 0
A54: =+B54&C54 -> Véhicules neufsTOTAL PERSONNEL | B54: =+$K$1 -> Véhicules neufs | C54: TOTAL PERSONNEL | D54: % brut | E54: =F54/F$27 -> 0.21959846 | F54: =+SUM(F42:F53) -> 52263.136 | J54: % brut | K54: =L54/L$27 -> 0.1742639 | L54: =+SUM(L42:L53) -> 36315.96 | N54: =+SUM(N42:N53) -> -15947.176 | O54: % brut | P54: =Q54/Q$27 -> 0.20503246 | Q54: =+SUM(Q42:Q53) -> 57583.3 | S54: =+SUM(S42:S53) -> -21267.34
A55: =+B55&C55 -> Véhicules neufsPublicité 2 | B55: =+$K$1 -> Véhicules neufs | C55: Publicité 2 | F55: 0 | L55: 0 | N55: =L55-F55 -> 0 | Q55: 0 | S55: =L55-Q55 -> 0
A56: =+B56&C56 -> Véhicules neufsService gratuit 2 | B56: =+$K$1 -> Véhicules neufs | C56: Service gratuit 2 | F56: 0 | L56: 0 | N56: =L56-F56 -> 0 | Q56: 0 | S56: =L56-Q56 -> 0
A57: =+B57&C57 -> Véhicules neufsFrais véhicules de cie | B57: =+$K$1 -> Véhicules neufs | C57: Frais véhicules de cie | F57: 2036.5 | L57: 1119.99 | N57: =L57-F57 -> -916.51 | Q57: 9801.83 | S57: =L57-Q57 -> -8681.84
A58: =+B58&C58 -> Véhicules neufsInformatique | B58: =+$K$1 -> Véhicules neufs | C58: Informatique | F58: 9195.3522 | L58: 9326.56 | N58: =L58-F58 -> 131.20783 | Q58: 5604.87 | S58: =L58-Q58 -> 3721.69
A59: =+B59&C59 -> Véhicules neufsFrais de déplacement | B59: =+$K$1 -> Véhicules neufs | C59: Frais de déplacement | F59: 1330 | L59: 5164.31 | N59: =L59-F59 -> 3834.31 | Q59: 1141.13 | S59: =L59-Q59 -> 4023.18 | V59: Meeting Nashville + Repas vente privée
A60: =+B60&C60 -> Véhicules neufsServices extérieurs | B60: =+$K$1 -> Véhicules neufs | C60: Services extérieurs | F60: 2672.3603 | L60: 4390.13 | N60: =L60-F60 -> 1717.7697 | Q60: 3411.25 | S60: =L60-Q60 -> 978.88 | V60: +2.8k lavage vitre
A61: =+B61&C61 -> Véhicules neufsFournitures autres | B61: =+$K$1 -> Véhicules neufs | C61: Fournitures autres | F61: 75 | L61: 100.56 | N61: =L61-F61 -> 25.56 | Q61: 0 | S61: =L61-Q61 -> 100.56
A62: =+B62&C62 -> Véhicules neufsUniformes | B62: =+$K$1 -> Véhicules neufs | C62: Uniformes | F62: 30 | L62: 74.1 | N62: =L62-F62 -> 44.1 | Q62: 0 | S62: =L62-Q62 -> 74.1
A63: =+B63&C63 -> Véhicules neufsPapeterie | B63: =+$K$1 -> Véhicules neufs | C63: Papeterie | F63: 580 | L63: 736.53 | N63: =L63-F63 -> 156.53 | Q63: 368.11 | S63: =L63-Q63 -> 368.42
A64: =+B64&C64 -> Véhicules neufsTéléphone | B64: =+$K$1 -> Véhicules neufs | C64: Téléphone | F64: 157.6 | L64: 176.07 | N64: =L64-F64 -> 18.47 | Q64: 193.41 | S64: =L64-Q64 -> -17.34
A65: =+B65&C65 -> Véhicules neufsFrais postaux | B65: =+$K$1 -> Véhicules neufs | C65: Frais postaux | F65: 226.66667 | L65: 40.92 | N65: =L65-F65 -> -185.74667 | Q65: 199.38 | S65: =L65-Q65 -> -158.46
A66: =+B66&C66 -> Véhicules neufsDivers | B66: =+$K$1 -> Véhicules neufs | C66: Divers | F66: 629.08333 | L66: 479.59 | N66: =L66-F66 -> -149.49333 | Q66: 866.69 | S66: =L66-Q66 -> -387.1
A67: =+B67&C67 -> Véhicules neufsFormation | B67: =+$K$1 -> Véhicules neufs | C67: Formation | F67: 321.59467 | L67: -654.79 | N67: =L67-F67 -> -976.38467 | Q67: 73.3 | S67: =L67-Q67 -> -728.09
A68: =+B68&C68 -> Véhicules neufsFrais bancaires | B68: =+$K$1 -> Véhicules neufs | C68: Frais bancaires | F68: 4787.6725 | L68: 3974.2 | N68: =L68-F68 -> -813.47252 | Q68: 4388.48 | S68: =L68-Q68 -> -414.28
A69: =+B69&C69 -> Véhicules neufs[...] | B69: =+$K$1 -> Véhicules neufs | C69: [...] | F69: 0 | N69: =L69-F69 -> 0 | Q69: 0 | S69: =L69-Q69 -> 0
A70: =+B70&C70 -> Véhicules neufs[...] | B70: =+$K$1 -> Véhicules neufs | C70: [...] | F70: 0 | L70: 0 | N70: =L70-F70 -> 0 | Q70: 0 | S70: =L70-Q70 -> 0
A71: =+B71&C71 -> Véhicules neufs[...] | B71: =+$K$1 -> Véhicules neufs | C71: [...] | F71: 0 | L71: 0 | N71: =L71-F71 -> 0 | Q71: 0 | S71: =L71-Q71 -> 0
A72: =+B72&C72 -> Véhicules neufsTOTAL SEMI-FIXES | B72: =+$K$1 -> Véhicules neufs | C72: TOTAL SEMI-FIXES | D72: % brut | E72: =F72/F$27 -> 0.09261503 | F72: =+SUM(F55:F71) -> 22041.83 | J72: % brut | K72: =L72/L$27 -> 0.11961903 | L72: =+SUM(L55:L71) -> 24928.17 | N72: =+SUM(N55:N71) -> 2886.3403 | O72: % brut | P72: =Q72/Q$27 -> 0.092748726 | Q72: =+SUM(Q55:Q71) -> 26048.45 | S72: =+SUM(S55:S71) -> -1120.28
A73: =+B73&C73 -> Véhicules neufs | B73: =+$K$1 -> Véhicules neufs
A74: =+B74&C74 -> Véhicules neufsTOTAL DES DÉPENSES | B74: =+$K$1 -> Véhicules neufs | C74: TOTAL DES DÉPENSES | D74: % brut | E74: =F74/F$27 -> 0.78019516 | F74: =F41+F54+F72 -> 185681.83 | J74: % brut | K74: =L74/L$27 -> 0.73664625 | L74: =L41+L54+L72 -> 153514.39 | N74: =L74-F74 -> -32167.445 | O74: % brut | P74: =Q74/Q$27 -> 0.76908857 | Q74: =Q41+Q54+Q72 -> 215998.28 | S74: =L74-Q74 -> -62483.89
A75: =+B75&C75 -> Véhicules neufsRBSC neuf | B75: =+$K$1 -> Véhicules neufs | C75: RBSC neuf | F75: 62037.996 | L75: 61961.34 | N75: =L75-F75 -> -76.656429 | Q75: 64585.66 | S75: =L75-Q75 -> -2624.32
A76: =+B76&C76 -> Véhicules neufsProgramme neuf 2 | B76: =+$K$1 -> Véhicules neufs | C76: Programme neuf 2 | F76: 0 | L76: 0 | N76: =L76-F76 -> 0 | Q76: 0 | S76: =L76-Q76 -> 0
A77: =+B77&C77 -> Véhicules neufsProgramme neuf 3 | B77: =+$K$1 -> Véhicules neufs | C77: Programme neuf 3 | F77: 0 | L77: 0 | N77: =L77-F77 -> 0 | Q77: 0 | S77: =L77-Q77 -> 0
A78: =+B78&C78 -> Véhicules neufsHoldbacks | B78: =+$K$1 -> Véhicules neufs | C78: Holdbacks | F78: 75197.571 | L78: 73463 | N78: =L78-F78 -> -1734.5714 | Q78: 76338.4 | S78: =L78-Q78 -> -2875.4
A79: =+B79&C79 -> Véhicules neufs[...] | B79: =+$K$1 -> Véhicules neufs | C79: [...] | F79: 0 | L79: 0 | N79: =L79-F79 -> 0 | Q79: 0 | S79: =L79-Q79 -> 0
A80: =+B80&C80 -> Véhicules neufs[...] | B80: =+$K$1 -> Véhicules neufs | C80: [...] | F80: 0 | L80: 0 | N80: =L80-F80 -> 0 | Q80: 0 | S80: =L80-Q80 -> 0
A81: =+B81&C81 -> Véhicules neufs[...] | B81: =+$K$1 -> Véhicules neufs | C81: [...] | F81: 0 | L81: 0 | N81: =L81-F81 -> 0 | Q81: 0 | S81: =L81-Q81 -> 0
A82: =+B82&C82 -> Véhicules neufsFrais administration | B82: =+$K$1 -> Véhicules neufs | C82: Frais administration | F82: 25073.3 | L82: 24990 | N82: =L82-F82 -> -83.3 | Q82: 26180 | S82: =L82-Q82 -> -1190 | V82: =L82/595 -> 42 | W82: =V82/J27 -> 0.97674419
A83: =+B83&C83 -> Véhicules neufsAUTRES REVENUS | B83: =+$K$1 -> Véhicules neufs | C83: AUTRES REVENUS | F83: =+SUM(F75:F82) -> 162308.87 | L83: =+SUM(L75:L82) -> 160414.34 | N83: =+SUM(N75:N82) -> -1894.5279 | Q83: =+SUM(Q75:Q82) -> 167104.06 | S83: =+SUM(S75:S82) -> -6689.72
A84: =+B84&C84 -> Véhicules neufs | B84: =+$K$1 -> Véhicules neufs
A85: =+B85&C85 -> Véhicules neufsPROFIT DÉPARTEMENTAL | B85: =+$K$1 -> Véhicules neufs | C85: PROFIT DÉPARTEMENTAL | F85: =F27-F74+F83 -> 214621.12 | L85: =L27-L74+L83 -> 215296.3 | N85: =N27-N41-N54-N72+N83 -> 675.1787 | Q85: =Q27-Q74+Q83 -> 231955.46 | S85: =S27-S41-S54-S72+S83 -> -16659.16
C89: =C1 -> BMW Sherbrooke | K89: Véhicules usagés | S89: =$S$1 -> Réalisé, Mai 2026
D91: BUDGET ORIGINAL | J91: RÉALISATION | M91: ÉCART réel / Budget | O91: ANNÉE PRÉCÉDENTE | R91: ECART (réel/ Ann.Préc.)
D92: UNITE | E92: $P/UNITÉ | F92: $PROFITS | J92: UNITE | K92: $P/UNITE | L92: $PROFITS | M92: UNFTÉ | N92: $PROFFTS | O92: UNITE | P92: $P/UNITÉ | Q92: $PROFITS | R92: UNITE | S92: $PROFITS
A93: =+B93&C93 -> Véhicules usagésVentes nettes | B93: Véhicules usagés | C93: Ventes nettes | F93: 2037857.7 | L93: 2056434.5 | Q93: 1870178.5
A94: =+B94&C94 -> Véhicules usagésCertifié | B94: Véhicules usagés | C94: Certifié | D94: 12 | E94: =IF(D94=0,0,F94/D94) -> 2400 | F94: 28800 | J94: 11 | K94: =IF(J94=0,0,L94/J94) -> 2140.5991 | L94: 23546.59 | M94: =J94-D94 -> -1 | N94: =L94-F94 -> -5253.41 | O94: 3 | P94: =IF(O94=0,0,Q94/O94) -> 2327.8833 | Q94: 6983.65 | R94: =J94-O94 -> 8 | S94: =L94-Q94 -> 16562.94
A95: =+B95&C95 -> Véhicules usagésNon Certifié | B95: Véhicules usagés | C95: Non Certifié | D95: 3 | E95: =IF(D95=0,0,F95/D95) -> 1400 | F95: 4200 | J95: 5 | K95: =IF(J95=0,0,L95/J95) -> 5520.974 | L95: 27604.87 | M95: =J95-D95 -> 2 | N95: =L95-F95 -> 23404.87 | O95: 4 | P95: =IF(O95=0,0,Q95/O95) -> 1818.91 | Q95: 7275.64 | R95: =J95-O95 -> 1 | S95: =L95-Q95 -> 20329.23
A96: =+B96&C96 -> Véhicules usagésAutres marques | B96: Véhicules usagés | C96: Autres marques | D96: 5 | E96: =IF(D96=0,0,F96/D96) -> 1500 | F96: 7500 | J96: 8 | K96: =IF(J96=0,0,L96/J96) -> 2384.345 | L96: 19074.76 | M96: =J96-D96 -> 3 | N96: =L96-F96 -> 11574.76 | O96: 8 | P96: =IF(O96=0,0,Q96/O96) -> 1148.935 | Q96: 9191.48 | R96: =J96-O96 -> 0 | S96: =L96-Q96 -> 9883.28
A97: =+B97&C97 -> Véhicules usagésTotal Usagés | B97: Véhicules usagés | C97: Total Usagés | D97: =+D95+D94+D96 -> 20 | E97: =IF(D97=0,0,F97/D97) -> 2025 | F97: =+F94+F95+F96 -> 40500 | J97: =+J94+J95+J96 -> 24 | K97: =IF(J97<=0,0,L97/J97) -> 2926.0925 | L97: =+L94+L95+L96 -> 70226.22 | M97: =J97-D97 -> 4 | N97: =L97-F97 -> 29726.22 | O97: =+O95+O94+O96 -> 15 | P97: =IF(O97=0,0,Q97/O97) -> 1563.3847 | Q97: =+Q94+Q95+Q96 -> 23450.77 | R97: =J97-O97 -> 9 | S97: =L97-Q97 -> 46775.45
A98: =+B98&C98 -> Véhicules usagés | B98: Véhicules usagés | M98: =M97/D97 -> 0.2 | N98: =N97/F97 -> 0.73398074 | R98: =R97/O97 -> 0.6 | S98: =IF(Q97=0,0,(S97/Q97)) -> 1.9946232
A99: =+B99&C99 -> Véhicules neufsRachat bail | B99: =+$K$1 -> Véhicules neufs | C99: Rachat bail | D99: 0 | E99: =IF(D99=0,0,F99/D99) -> 0 | F99: 2834.7472 | L99: 3997.58 | N99: =L99-F99 -> 1162.8328 | Q99: 2498 | R99: =O99-K99 -> 0 | S99: =L99-Q99 -> 1499.58
A100: =+B100&C100 -> Véhicules usagés | B100: Véhicules usagés
A101: =+B101&C101 -> Véhicules usagésVentes au Gros | B101: Véhicules usagés | C101: Ventes au Gros | D101: 30 | E101: =IF(D101=0,0,F101/D101) -> 500 | F101: 15000 | J101: 21 | K101: =IF(J101=0,0,L101/J101) -> 752.67048 | L101: 15806.08 | M101: =J101-D101 -> -9 | N101: =L101-F101 -> 806.08 | O101: 34 | P101: =IF(O101=0,0,Q101/O101) -> 500.41294 | Q101: 17014.04 | R101: =J101-O101 -> -13 | S101: =L101-Q101 -> -1207.96
A102: =+B102&C102 -> Véhicules usagés | B102: Véhicules usagés
A103: =+B103&C103 -> Véhicules usagésRev. Finances | B103: Véhicules usagés | C103: Rev. Finances | E103: =IF(D97=0,0,F103/D97) -> 350 | F103: 7000 | K103: =IF(J97=0,0,L103/J97) -> 317.96583 | L103: 7631.18 | N103: =L103-F103 -> 631.18 | P103: =IF(O97=0,0,Q103/O97) -> 879.48267 | Q103: 13192.24 | R103: =O103-K103 -> -317.96583 | S103: =L103-Q103 -> -5561.06
A104: =+B104&C104 -> Véhicules usagésRev. Protections | B104: Véhicules usagés | C104: Rev. Protections | E104: =IF(D97=0,0,F104/D97) -> 950 | F104: 19000 | K104: =IF(J97=0,0,L104/J97) -> 400.25 | L104: 9606 | N104: =L104-F104 -> -9394 | P104: =IF(O97=0,0,Q104/O97) -> 1715.4953 | Q104: 25732.43 | R104: =O104-K104 -> -400.25 | S104: =L104-Q104 -> -16126.43
...

Sheet Mois 3
C1: BMW Sherbrooke | K1: Véhicules neufs | S1: Réalisé, Juin 2026
D2: X | E2: O | F2: U | J2: NB | L2: $ | O2: X | P2: O | Q2: U
D3: BUDGET ORIGINAL | J3: RÉALISATION | M3: ÉCART réel / Budget | O3: ANNÉE PRÉCÉDENTE | R3: ECART (réel/ Ann.Préc.)
D4: UNITE | E4: $P/UNITÉ | F4: $PROFITS | J4: UNITE | K4: $P/UNITE | L4: $PROFITS | M4: UNFTÉ | N4: $PROFITS | O4: UNITE | P4: $P/UNITÉ | Q4: $PROFITS | R4: UNITE | S4: $PROFITS
A5: =+B5&C5 -> Véhicules neufsVentes nettes | B5: =+$K$1 -> Véhicules neufs | C5: Ventes nettes | F5: 2474272 | L5: 2992808.7 | Q5: 1932819
A6: =+B6&C6 -> Véhicules neufsAutos détail | B6: =+$K$1 -> Véhicules neufs | C6: Autos détail | D6: 9 | E6: =IF(D6=0,0,F6/D6) -> 4701.1765 | F6: 42310.588 | J6: 10 | K6: =IF(J6=0,0,L6/J6) -> 6645.185 | L6: 66451.85 | M6: =J6-D6 -> 1 | N6: =L6-F6 -> 24141.262 | O6: 9 | P6: =IF(O6=0,0,Q6/O6) -> 5820.6267 | Q6: 52385.64 | R6: =J6-O6 -> 1 | S6: =L6-Q6 -> 14066.21
A7: =+B7&C7 -> Véhicules neufsCamions détail | B7: =+$K$1 -> Véhicules neufs | C7: Camions détail | D7: 14 | E7: =IF(D7=0,0,F7/D7) -> 3928.5 | F7: 54999 | J7: 12 | K7: =IF(J7=0,0,L7/J7) -> 4707.7525 | L7: 56493.03 | M7: =J7-D7 -> -2 | N7: =L7-F7 -> 1494.03 | O7: 7 | P7: =IF(O7=0,0,Q7/O7) -> 3544.4671 | Q7: 24811.27 | R7: =J7-O7 -> 5 | S7: =L7-Q7 -> 31681.76
A8: =+B8&C8 -> Véhicules neufsSprinter | B8: =+$K$1 -> Véhicules neufs | C8: Sprinter | D8: 0 | E8: =IF(D8=0,0,F8/D8) -> 0 | F8: 0 | J8: 0 | K8: =IF(J8=0,0,L8/J8) -> 0 | L8: 0 | M8: =J8-D8 -> 0 | N8: =L8-F8 -> 0 | O8: 0 | P8: =IF(O8=0,0,Q8/O8) -> 0 | Q8: 0 | R8: =J8-O8 -> 0 | S8: =L8-Q8 -> 0
A9: =+B9&C9 -> Véhicules neufsMoto détail | B9: =+$K$1 -> Véhicules neufs | C9: Moto détail | D9: 0 | E9: =IF(D9=0,0,F9/D9) -> 0 | F9: 0 | J9: 0 | K9: =IF(J9=0,0,L9/J9) -> 0 | L9: 0 | M9: =J9-D9 -> 0 | N9: =L9-F9 -> 0 | O9: 0 | P9: =IF(O9=0,0,Q9/O9) -> 0 | Q9: 0 | R9: =J9-O9 -> 0 | S9: =L9-Q9 -> 0
A10: =+B10&C10 -> Véhicules neufs[...] | B10: =+$K$1 -> Véhicules neufs | C10: [...] | D10: 0 | E10: =IF(D10=0,0,F10/D10) -> 0 | F10: 0 | J10: 0 | K10: =IF(J10=0,0,L10/J10) -> 0 | L10: 0 | M10: =J10-D10 -> 0 | N10: =L10-F10 -> 0 | O10: 0 | P10: =IF(O10=0,0,Q10/O10) -> 0 | Q10: 0 | R10: =J10-O10 -> 0 | S10: =L10-Q10 -> 0
A11: =+B11&C11 -> Véhicules neufs[...] | B11: =+$K$1 -> Véhicules neufs | C11: [...] | D11: 0 | E11: =IF(D11=0,0,F11/D11) -> 0 | F11: 0 | J11: 0 | K11: =IF(J11=0,0,L11/J11) -> 0 | L11: 0 | M11: =J11-D11 -> 0 | N11: =L11-F11 -> 0 | O11: 0 | P11: =IF(O11=0,0,Q11/O11) -> 0 | Q11: 0 | R11: =J11-O11 -> 0 | S11: =L11-Q11 -> 0
A12: =+B12&C12 -> Véhicules neufs[...] | B12: =+$K$1 -> Véhicules neufs | C12: [...] | D12: 0 | E12: =IF(D12=0,0,F12/D12) -> 0 | F12: 0 | J12: 0 | K12: =IF(J12=0,0,L12/J12) -> 0 | L12: 0 | M12: =J12-D12 -> 0 | N12: =L12-F12 -> 0 | O12: 0 | P12: =IF(O12=0,0,Q12/O12) -> 0 | Q12: 0 | R12: =J12-O12 -> 0 | S12: =L12-Q12 -> 0
A13: =+B13&C13 -> Véhicules neufsTotal Neufs | B13: =+$K$1 -> Véhicules neufs | C13: Total Neufs | D13: =+SUM(D6:D12) -> 23 | E13: =IF(D13<=0,0,F13/D13) -> 4230.8517 | F13: =+SUM(F6:F12) -> 97309.588 | J13: =+SUM(J6:J12) -> 22 | K13: =IF(J13<=0,0,L13/J13) -> 5588.4036 | L13: =+SUM(L6:L12) -> 122944.88 | M13: =+SUM(M6:M12) -> -1 | N13: =+SUM(N6:N12) -> 25635.292 | O13: =+SUM(O6:O12) -> 16 | P13: =IF(O13<=0,0,Q13/O13) -> 4824.8069 | Q13: =+SUM(Q6:Q12) -> 77196.91 | R13: =+SUM(R6:R12) -> 6 | S13: =+SUM(S6:S12) -> 45747.97
A14: =+B14&C14 -> Véhicules neufs | B14: =+$K$1 -> Véhicules neufs | M14: =IF(D13=0,0,M13/D13) -> -0.043478261 | N14: =IF(F13=0,0,N13/F13) -> 0.26344055 | R14: =R13/O13 -> 0.375 | S14: =IF(Q13=0,0,(S13/Q13)) -> 0.592614
A15: =+B15&C15 -> Véhicules neufsEx-Démos et courtoisies | B15: =+$K$1 -> Véhicules neufs | C15: Ex-Démos et courtoisies | D15: 3 | E15: =IF(D15=0,0,F15/D15) -> 1200 | F15: 3600 | J15: 2 | K15: =IF(J15=0,0,L15/J15) -> 39.025 | L15: 78.05 | M15: =J15-D15 -> -1 | N15: =L15-F15 -> -3521.95 | O15: 4 | P15: =IF(O15=0,0,Q15/O15) -> 2445.1975 | Q15: 9780.79 | R15: =J15-O15 -> -2 | S15: =L15-Q15 -> -9702.74
A16: =+B16&C16 -> Véhicules neufs | B16: =+$K$1 -> Véhicules neufs
A17: =+B17&C17 -> Véhicules neufsFlottes | B17: =+$K$1 -> Véhicules neufs | C17: Flottes | D17: 2 | E17: =IF(D17=0,0,F17/D17) -> 750 | F17: 1500 | J17: 6 | K17: =IF(J17=0,0,L17/J17) -> 0 | L17: 0 | M17: =J17-D17 -> 4 | N17: =L17-F17 -> -1500 | O17: 0 | P17: =IF(O17=0,0,Q17/O17) -> 0 | Q17: 0 | R17: =J17-O17 -> 6 | S17: =L17-Q17 -> 0
A18: =+B18&C18 -> Véhicules neufs | B18: =+$K$1 -> Véhicules neufs
B19: =+$K$1 -> Véhicules neufs
A20: =+B20&C20 -> Véhicules neufs | B20: =+$K$1 -> Véhicules neufs
A21: =+B21&C21 -> Véhicules neufsRev. Finances | B21: =+$K$1 -> Véhicules neufs | C21: Rev. Finances | E21: =IF(D13=0,0,F21/(D13+D15)) -> 7 | F21: 182 | K21: =IF(J13=0,0,L21/(J13+J15)) -> 0 | L21: 0 | N21: =L21-F21 -> -182 | P21: =IF(O13=0,0,Q21/(O13+O15)) -> 0 | Q21: 0 | R21: =O21-K21 -> 0 | S21: =L21-Q21 -> 0
A22: =+B22&C22 -> Véhicules neufsRev. Protections | B22: =+$K$1 -> Véhicules neufs | C22: Rev. Protections | E22: =IF(D13=0,0,F22/(D13+D15)) -> 1150 | F22: 29900 | K22: =IF(J13=0,0,L22/(J13+J15)) -> 489.09583 | L22: 11738.3 | N22: =L22-F22 -> -18161.7 | P22: =IF(O13=0,0,Q22/(O13+O15)) -> 1336.1695 | Q22: 26723.39 | R22: =O22-K22 -> -489.09583 | S22: =L22-Q22 -> -14985.09
A23: =+B23&C23 -> Véhicules neufsRev. Autres | B23: =+$K$1 -> Véhicules neufs | C23: Rev. Autres | E23: =IF(D13=0,0,F23/(D13+D15)) -> 443 | F23: 11518 | K23: =IF(J13=0,0,L23/(J13+J15)) -> 445.25708 | L23: 10686.17 | N23: =L23-F23 -> -831.83 | P23: =IF(O13=0,0,Q23/(O13+O15)) -> 902.6705 | Q23: 18053.41 | R23: =O23-K23 -> -445.25708 | S23: =L23-Q23 -> -7367.24
A24: =+B24&C24 -> Véhicules neufsTotal F&I | B24: =+$K$1 -> Véhicules neufs | C24: Total F&I | D24: =+D15+D13 -> 26 | E24: =IF(D24<=0,0,F24/D24) -> 1600 | F24: =F21+F22+F23 -> 41600 | J24: =+J15+J13 -> 24 | K24: =IF(J24<=0,0,L24/J24) -> 934.35292 | L24: =L21+L22+L23 -> 22424.47 | M24: =J24-D24 -> -2 | N24: =L24-F24 -> -19175.53 | O24: =+O15+O13 -> 20 | P24: =IF(O24<=0,0,Q24/O24) -> 2238.84 | Q24: =Q21+Q22+Q23 -> 44776.8 | S24: =L24-Q24 -> -22352.33
A25: =+B25&C25 -> Véhicules neufs | B25: =+$K$1 -> Véhicules neufs | N25: =IF(N24=0,0,N24/F24) -> -0.46095024 | S25: =IF(Q24=0,0,(S24/Q24)) -> -0.49919445
A26: =+B26&C26 -> Véhicules neufs | B26: =+$K$1 -> Véhicules neufs
A27: =+B27&C27 -> Véhicules neufsTotal Dépt. Neufs | B27: =+$K$1 -> Véhicules neufs | C27: Total Dépt. Neufs | D27: =+D13+D15+D17 -> 28 | E27: =IF(D27<=0,0,F27/D27) -> 5143.1996 | F27: =F13+F17+F24+F15 -> 144009.59 | J27: =+J13+J15+J17 -> 30 | K27: =IF(J27<=0,0,L27/J27) -> 4848.2467 | L27: =L13+L17+L24+L15 -> 145447.4 | M27: =J27-D27 -> 2 | N27: =L27-F27 -> 1437.8118 | O27: =+O13+O15+O17 -> 20 | P27: =IF(O27<=0,0,Q27/O27) -> 6587.725 | Q27: =Q13+Q17+Q24+Q15 -> 131754.5 | R27: =J27-O27 -> 10 | S27: =L27-Q27 -> 13692.9
A28: =+B28&C28 -> Véhicules neufs | B28: =+$K$1 -> Véhicules neufs | M28: =M27/D27 -> 0.071428571 | N28: =N27/F27 -> 0.0099841391 | R28: =R27/O27 -> 0.5 | S28: =IF(Q27=0,0,S27/Q27) -> 0.10392738
A29: =+B29&C29 -> Véhicules neufs | B29: =+$K$1 -> Véhicules neufs
A30: =+B30&C30 -> Véhicules neufsDEPENSES | B30: =+$K$1 -> Véhicules neufs | C30: DEPENSES
A31: =+B31&C31 -> Véhicules neufsComm. vendeurs | B31: =+$K$1 -> Véhicules neufs | C31: Comm. vendeurs | D31: =F31/(F13+F15) -> 0.28393389 | E31: =F31/D$24 -> 1101.9866 | F31: 28651.652 | J31: =L31/(L13+L15) -> 0.28455614 | K31: =IF(L31=0,0,L31/J$24) -> 1458.6221 | L31: 35006.93 | N31: =L31-F31 -> 6355.2782 | O31: =Q31/(Q13+Q15+Q17) -> 0.25746726 | P31: =Q31/O$24 -> 1119.6955 | Q31: 22393.91 | S31: =L31-Q31 -> 12613.02
A32: =+B32&C32 -> Véhicules neufsComm. F&I | B32: =+$K$1 -> Véhicules neufs | C32: Comm. F&I | D32: =F32/F24 -> 0.305 | E32: =F32/D$24 -> 488 | F32: 12688 | J32: =L32/L24 -> 0.22188395 | K32: =IF(L32=0,0,L32/J$24) -> 207.31792 | L32: 4975.63 | N32: =L32-F32 -> -7712.37 | O32: =Q32/Q24 -> 0.34309151 | P32: =Q32/O$24 -> 768.127 | Q32: 15362.54 | S32: =L32-Q32 -> -10386.91
A33: =+B33&C33 -> Véhicules neufsFrais de livraison | B33: =+$K$1 -> Véhicules neufs | C33: Frais de livraison | E33: =F33/D$24 -> 120 | F33: 3120 | K33: =IF(L33=0,0,L33/J$24) -> 276.80167 | L33: 6643.24 | N33: =L33-F33 -> 3523.24 | P33: =Q33/O$24 -> 207.3525 | Q33: 4147.05 | S33: =L33-Q33 -> 2496.19 | V33: Essences + transport
A34: =+B34&C34 -> Véhicules neufsService gratuit 1 | B34: =+$K$1 -> Véhicules neufs | C34: Service gratuit 1 | E34: =F34/D$24 -> 35 | F34: 910 | K34: =IF(L34=0,0,L34/J$24) -> 95.290833 | L34: 2286.98 | N34: =L34-F34 -> 1376.98 | P34: =Q34/O$24 -> 0 | Q34: 0 | S34: =L34-Q34 -> 2286.98 | V34: 1.4K Freins ancien démo Yvon vendu janv 2026
A35: =+B35&C35 -> Véhicules neufsEntretien stock | B35: =+$K$1 -> Véhicules neufs | C35: Entretien stock | E35: =F35/D$24 -> 98.192308 | F35: 2553 | K35: =IF(L35=0,0,L35/J$24) -> 210.72917 | L35: 5057.5 | N35: =L35-F35 -> 2504.5 | P35: =Q35/O$24 -> 103.6725 | Q35: 2073.45 | S35: =L35-Q35 -> 2984.05 | V35: 2k Lavavage ligne essaie
A36: =+B36&C36 -> Véhicules neufsPublicité 1 | B36: =+$K$1 -> Véhicules neufs | C36: Publicité 1 | E36: =F36/D$24 -> 234.88788 | F36: 6107.0848 | K36: =IF(L36=0,0,L36/J$24) -> 230.78417 | L36: 5538.82 | N36: =L36-F36 -> -568.26485 | P36: =Q36/O$24 -> 508.9305 | Q36: 10178.61 | S36: =L36-Q36 -> -4639.79
A37: =+B37&C37 -> Véhicules neufsIntérêt de gros | B37: =+$K$1 -> Véhicules neufs | C37: Intérêt de gros | E37: =F37/D$24 -> 809.52174 | F37: 21047.565 | K37: =IF(L37=0,0,L37/J$24) -> 881.08 | L37: 21145.92 | N37: =L37-F37 -> 98.354754 | P37: =Q37/O$24 -> 1163.8995 | Q37: 23277.99 | S37: =L37-Q37 -> -2132.07 | V37: 21146
A38: =+B38&C38 -> Véhicules neufs[...] | B38: =+$K$1 -> Véhicules neufs | C38: [...] | E38: =F38/D$24 -> 0 | F38: 0 | K38: =IF(L38=0,0,L38/J$24) -> 0 | L38: 0 | N38: =L38-F38 -> 0 | P38: =Q38/O$24 -> 0 | Q38: 0 | S38: =L38-Q38 -> 0
A39: =+B39&C39 -> Véhicules neufs[...] | B39: =+$K$1 -> Véhicules neufs | C39: [...] | E39: =F39/D$24 -> 0 | F39: 0 | K39: =IF(L39=0,0,L39/J$24) -> 0 | L39: 0 | N39: =L39-F39 -> 0 | P39: =Q39/O$24 -> 0 | Q39: 0 | S39: =L39-Q39 -> 0
A40: =+B40&C40 -> Véhicules neufs[...] | B40: =+$K$1 -> Véhicules neufs | C40: [...] | E40: =F40/D$24 -> 0 | F40: 0 | K40: =IF(L40=0,0,L40/J$24) -> 0 | L40: 0 | N40: =L40-F40 -> 0 | P40: =Q40/O$24 -> 0 | Q40: 0 | S40: =L40-Q40 -> 0
A41: =+B41&C41 -> Véhicules neufsTOTAL VARIABLES | B41: =+$K$1 -> Véhicules neufs | C41: TOTAL VARIABLES | D41: % brut | E41: =F41/F$27 -> 0.52133544 | F41: =SUM(F31:F40) -> 75077.302 | J41: % brut | K41: =L41/L$27 -> 0.5545305 | L41: =SUM(L31:L40) -> 80655.02 | N41: =L41-F41 -> 5577.7181 | O41: % brut | P41: =Q41/Q$27 -> 0.58771086 | Q41: =SUM(Q31:Q40) -> 77433.55 | S41: =L41-Q41 -> 3221.47
A42: =+B42&C42 -> Véhicules neufsSalaires cadres | B42: =+$K$1 -> Véhicules neufs | C42: Salaires cadres | F42: 12465.762 | L42: 9762.51 | N42: =L42-F42 -> -2703.2521 | Q42: 12424.49 | S42: =L42-Q42 -> -2661.98
A43: =+B43&C43 -> Véhicules neufsSalaires commis | B43: =+$K$1 -> Véhicules neufs | C43: Salaires commis | F43: 5131.0855 | L43: 4255.62 | N43: =L43-F43 -> -875.46546 | Q43: 8970.87 | S43: =L43-Q43 -> -4715.25
A44: =+B44&C44 -> Véhicules neufsSalaires autres | B44: =+$K$1 -> Véhicules neufs | C44: Salaires autres | F44: 0 | L44: 90 | N44: =L44-F44 -> 90 | Q44: 342 | S44: =L44-Q44 -> -252 | V44: Francis Pellerin - renouvellement Volks
A45: =+B45&C45 -> Véhicules neufsSalaires spécialistes | B45: =+$K$1 -> Véhicules neufs | C45: Salaires spécialistes | F45: 0 | L45: 0 | N45: =L45-F45 -> 0 | Q45: 0 | S45: =L45-Q45 -> 0
A46: =+B46&C46 -> Véhicules neufs[...] | B46: =+$K$1 -> Véhicules neufs | C46: [...] | F46: 0 | L46: 0 | N46: =L46-F46 -> 0 | Q46: 0 | S46: =L46-Q46 -> 0
A47: =+B47&C47 -> Véhicules neufs[...] | B47: =+$K$1 -> Véhicules neufs | C47: [...] | F47: 0 | L47: 0 | N47: =L47-F47 -> 0 | Q47: 0 | S47: =L47-Q47 -> 0
A48: =+B48&C48 -> Véhicules neufs[...] | B48: =+$K$1 -> Véhicules neufs | C48: [...] | F48: 0 | L48: 0 | N48: =L48-F48 -> 0 | Q48: 0 | S48: =L48-Q48 -> 0
A49: =+B49&C49 -> Véhicules neufsSalaires en absences | B49: =+$K$1 -> Véhicules neufs | C49: Salaires en absences | F49: 8711.2105 | L49: 8083.96 | N49: =L49-F49 -> -627.25053 | Q49: 9776.36 | S49: =L49-Q49 -> -1692.4
A50: =+B50&C50 -> Véhicules neufsDéduction à la source | B50: =+$K$1 -> Véhicules neufs | C50: Déduction à la source | F50: 8869.9791 | L50: 9540.19 | N50: =L50-F50 -> 670.21086 | Q50: 11933.83 | S50: =L50-Q50 -> -2393.64
A51: =+B51&C51 -> Véhicules neufsBénéfices marginaux | B51: =+$K$1 -> Véhicules neufs | C51: Bénéfices marginaux | F51: 5749.0606 | L51: 4627.74 | N51: =L51-F51 -> -1121.3206 | Q51: 4599.38 | S51: =L51-Q51 -> 28.36
A52: =+B52&C52 -> Véhicules neufsCsst | B52: =+$K$1 -> Véhicules neufs | C52: Csst | F52: 1609.737 | L52: 1507.88 | N52: =L52-F52 -> -101.85696 | Q52: 3165.52 | S52: =L52-Q52 -> -1657.64
A53: =+B53&C53 -> Véhicules neufs[...] | B53: =+$K$1 -> Véhicules neufs | C53: [...] | D53: =VLOOKUP(C53,$B$2:$B$46,1,FALSE) -> #N/A | F53: 0 | L53: 0 | N53: =L53-F53 -> 0 | Q53: 0 | S53: =L53-Q53 -> 0
A54: =+B54&C54 -> Véhicules neufsTOTAL PERSONNEL | B54: =+$K$1 -> Véhicules neufs | C54: TOTAL PERSONNEL | D54: % brut | E54: =F54/F$27 -> 0.29537502 | F54: =+SUM(F42:F53) -> 42536.835 | J54: % brut | K54: =L54/L$27 -> 0.2603546 | L54: =+SUM(L42:L53) -> 37867.9 | N54: =+SUM(N42:N53) -> -4668.9348 | O54: % brut | P54: =Q54/Q$27 -> 0.38869602 | Q54: =+SUM(Q42:Q53) -> 51212.45 | S54: =+SUM(S42:S53) -> -13344.55
A55: =+B55&C55 -> Véhicules neufsPublicité 2 | B55: =+$K$1 -> Véhicules neufs | C55: Publicité 2 | F55: 0 | L55: 0 | N55: =L55-F55 -> 0 | Q55: 0 | S55: =L55-Q55 -> 0
A56: =+B56&C56 -> Véhicules neufsService gratuit 2 | B56: =+$K$1 -> Véhicules neufs | C56: Service gratuit 2 | F56: 0 | L56: 0 | N56: =L56-F56 -> 0 | Q56: 0 | S56: =L56-Q56 -> 0
A57: =+B57&C57 -> Véhicules neufsFrais véhicules de cie | B57: =+$K$1 -> Véhicules neufs | C57: Frais véhicules de cie | F57: 2036.5 | L57: 1284.45 | N57: =L57-F57 -> -752.05 | Q57: 9596.17 | S57: =L57-Q57 -> -8311.72
A58: =+B58&C58 -> Véhicules neufsInformatique | B58: =+$K$1 -> Véhicules neufs | C58: Informatique | F58: 9195.3522 | L58: 9247.47 | N58: =L58-F58 -> 52.117833 | Q58: 4851.72 | S58: =L58-Q58 -> 4395.75
A59: =+B59&C59 -> Véhicules neufsFrais de déplacement | B59: =+$K$1 -> Véhicules neufs | C59: Frais de déplacement | F59: 1330 | L59: 2184.94 | N59: =L59-F59 -> 854.94 | Q59: 429.47 | S59: =L59-Q59 -> 1755.47
A60: =+B60&C60 -> Véhicules neufsServices extérieurs | B60: =+$K$1 -> Véhicules neufs | C60: Services extérieurs | F60: 2672.3603 | L60: 3167.58 | N60: =L60-F60 -> 495.21967 | Q60: 2489.44 | S60: =L60-Q60 -> 678.14
A61: =+B61&C61 -> Véhicules neufsFournitures autres | B61: =+$K$1 -> Véhicules neufs | C61: Fournitures autres | F61: 75 | L61: 55.5 | N61: =L61-F61 -> -19.5 | Q61: 138.66 | S61: =L61-Q61 -> -83.16
A62: =+B62&C62 -> Véhicules neufsUniformes | B62: =+$K$1 -> Véhicules neufs | C62: Uniformes | F62: 30 | L62: 0 | N62: =L62-F62 -> -30 | Q62: 0 | S62: =L62-Q62 -> 0
A63: =+B63&C63 -> Véhicules neufsPapeterie | B63: =+$K$1 -> Véhicules neufs | C63: Papeterie | F63: 580 | L63: 438.31 | N63: =L63-F63 -> -141.69 | Q63: 735.07 | S63: =L63-Q63 -> -296.76
A64: =+B64&C64 -> Véhicules neufsTéléphone | B64: =+$K$1 -> Véhicules neufs | C64: Téléphone | F64: 157.6 | L64: 198.07 | N64: =L64-F64 -> 40.47 | Q64: 183.2 | S64: =L64-Q64 -> 14.87
A65: =+B65&C65 -> Véhicules neufsFrais postaux | B65: =+$K$1 -> Véhicules neufs | C65: Frais postaux | F65: 226.66667 | L65: 52.12 | N65: =L65-F65 -> -174.54667 | Q65: 309.75 | S65: =L65-Q65 -> -257.63
A66: =+B66&C66 -> Véhicules neufsDivers | B66: =+$K$1 -> Véhicules neufs | C66: Divers | F66: 629.08333 | L66: 756.6 | N66: =L66-F66 -> 127.51667 | Q66: 1827.48 | S66: =L66-Q66 -> -1070.88
... A68: =+B68&C68 -> Véhicules neufsFrais bancaires | B68: =+$K$1 -> Véhicules neufs | C68: Frais bancaires | F68: 3978.2237 | L68: 2922.42 | N68: =L68-F68 -> -1055.8037 | Q68: 2634.17 | S68: =L68-Q68 -> 288.25
A69: =+B69&C69 -> Véhicules neufs[...] | B69: =+$K$1 -> Véhicules neufs | C69: [...] | F69: 0 | N69: =L69-F69 -> 0 | Q69: 0 | S69: =L69-Q69 -> 0
A70: =+B70&C70 -> Véhicules neufs[...] | B70: =+$K$1 -> Véhicules neufs | C70: [...] | F70: 0 | L70: 0 | N70: =L70-F70 -> 0 | Q70: 0 | S70: =L70-Q70 -> 0
A71: =+B71&C71 -> Véhicules neufs[...] | B71: =+$K$1 -> Véhicules neufs | C71: [...] | F71: 0 | L71: 0 | N71: =L71-F71 -> 0 | Q71: 0 | S71: =L71-Q71 -> 0
A72: =+B72&C72 -> Véhicules neufsTOTAL SEMI-FIXES | B72: =+$K$1 -> Véhicules neufs | C72: TOTAL SEMI-FIXES | D72: % brut | E72: =F72/F$27 -> 0.14743727 | F72: =+SUM(F55:F71) -> 21232.381 | J72: % brut | K72: =L72/L$27 -> 0.13910032 | L72: =+SUM(L55:L71) -> 20231.78 | N72: =+SUM(N55:N71) -> -1000.6009 | O72: % brut | P72: =Q72/Q$27 -> 0.17997609 | Q72: =+SUM(Q55:Q71) -> 23712.66 | S72: =+SUM(S55:S71) -> -3480.88
A73: =+B73&C73 -> Véhicules neufs | B73: =+$K$1 -> Véhicules neufs
A74: =+B74&C74 -> Véhicules neufsTOTAL DES DÉPENSES | B74: =+$K$1 -> Véhicules neufs | C74: TOTAL DES DÉPENSES | D74: % brut | E74: =F74/F$27 -> 0.96414773 | F74: =F41+F54+F72 -> 138846.52 | J74: % brut | K74: =L74/L$27 -> 0.95398543 | L74: =L41+L54+L72 -> 138754.7 | N74: =L74-F74 -> -91.817594 | O74: % brut | P74: =Q74/Q$27 -> 1.156383 | Q74: =Q41+Q54+Q72 -> 152358.66 | S74: =L74-Q74 -> -13603.96
A75: =+B75&C75 -> Véhicules neufsRBSC neuf | B75: =+$K$1 -> Véhicules neufs | C75: RBSC neuf | F75: 38601.42 | L75: 34403.28 | N75: =L75-F75 -> -4198.14 | Q75: 38986.85 | S75: =L75-Q75 -> -4583.57
A76: =+B76&C76 -> Véhicules neufsProgramme neuf 2 | B76: =+$K$1 -> Véhicules neufs | C76: Programme neuf 2 | F76: 0 | L76: 0 | N76: =L76-F76 -> 0 | Q76: 0 | S76: =L76-Q76 -> 0
A77: =+B77&C77 -> Véhicules neufsProgramme neuf 3 | B77: =+$K$1 -> Véhicules neufs | C77: Programme neuf 3 | F77: 0 | L77: 0 | N77: =L77-F77 -> 0 | Q77: 0 | S77: =L77-Q77 -> 0
A78: =+B78&C78 -> Véhicules neufsHoldbacks | B78: =+$K$1 -> Véhicules neufs | C78: Holdbacks | F78: 46789.6 | L78: 37951.8 | N78: =L78-F78 -> -8837.8 | Q78: 30943.4 | S78: =L78-Q78 -> 7008.4
A79: =+B79&C79 -> Véhicules neufs[...] | B79: =+$K$1 -> Véhicules neufs | C79: [...] | F79: 0 | L79: 0 | N79: =L79-F79 -> 0 | Q79: 0 | S79: =L79-Q79 -> 0
A80: =+B80&C80 -> Véhicules neufs[...] | B80: =+$K$1 -> Véhicules neufs | C80: [...] | F80: 0 | L80: 0 | N80: =L80-F80 -> 0 | Q80: 0 | S80: =L80-Q80 -> 0
A81: =+B81&C81 -> Véhicules neufs[...] | B81: =+$K$1 -> Véhicules neufs | C81: [...] | F81: 0 | L81: 0 | N81: =L81-F81 -> 0 | Q81: 0 | S81: =L81-Q81 -> 0
A82: =+B82&C82 -> Véhicules neufsFrais administration | B82: =+$K$1 -> Véhicules neufs | C82: Frais administration | F82: 15160.6 | L82: 14280 | N82: =L82-F82 -> -880.6 | Q82: 11900 | S82: =L82-Q82 -> 2380 | V82: =L82/595 -> 24 | W82: =V82/J27 -> 0.8
A83: =+B83&C83 -> Véhicules neufsAUTRES REVENUS | B83: =+$K$1 -> Véhicules neufs | C83: AUTRES REVENUS | F83: =+SUM(F75:F82) -> 100551.62 | L83: =+SUM(L75:L82) -> 86635.08 | N83: =+SUM(N75:N82) -> -13916.54 | Q83: =+SUM(Q75:Q82) -> 81830.25 | S83: =+SUM(S75:S82) -> 4804.83
A84: =+B84&C84 -> Véhicules neufs | B84: =+$K$1 -> Véhicules neufs
A85: =+B85&C85 -> Véhicules neufsPROFIT DÉPARTEMENTAL | B85: =+$K$1 -> Véhicules neufs | C85: PROFIT DÉPARTEMENTAL | F85: =F27-F74+F83 -> 105714.69 | L85: =L27-L74+L83 -> 93327.78 | N85: =N27-N41-N54-N72+N83 -> -12386.911 | Q85: =Q27-Q74+Q83 -> 61226.09 | S85: =S27-S41-S54-S72+S83 -> 32101.69
C89: =C1 -> BMW Sherbrooke | K89: Véhicules usagés | S89: =$S$1 -> Réalisé, Juin 2026
D91: BUDGET ORIGINAL | J91: RÉALISATION | M91: ÉCART réel / Budget | O91: ANNÉE PRÉCÉDENTE | R91: ECART (réel/ Ann.Préc.)
D92: UNITE | E92: $P/UNITÉ | F92: $PROFITS | J92: UNITE | K92: $P/UNITE | L92: $PROFITS | M92: UNFTÉ | N92: $PROFFTS | O92: UNITE | P92: $P/UNITÉ | Q92: $PROFITS | R92: UNITE | S92: $PROFITS
A93: =+B93&C93 -> Véhicules usagésVentes nettes | B93: Véhicules usagés | C93: Ventes nettes | F93: 2452221.9 | L93: 2841713.5 | Q93: 1387819.5
A94: =+B94&C94 -> Véhicules usagésCertifié | B94: Véhicules usagés | C94: Certifié | D94: 19 | E94: =IF(D94=0,0,F94/D94) -> 2400 | F94: 45600 | J94: 17 | K94: =IF(J94=0,0,L94/J94) -> 1337.7129 | L94: 22741.12 | M94: =J94-D94 -> -2 | N94: =L94-F94 -> -22858.88 | O94: 6 | P94: =IF(O94=0,0,Q94/O94) -> 2132.8233 | Q94: 12796.94 | R94: =J94-O94 -> 11 | S94: =L94-Q94 -> 9944.18
A95: =+B95&C95 -> Véhicules usagésNon Certifié | B95: Véhicules usagés | C95: Non Certifié | D95: 5 | E95: =IF(D95=0,0,F95/D95) -> 1400 | F95: 7000 | J95: 4 | K95: =IF(J95=0,0,L95/J95) -> 804.2825 | L95: 3217.13 | M95: =J95-D95 -> -1 | N95: =L95-F95 -> -3782.87 | O95: 13 | P95: =IF(O95=0,0,Q95/O95) -> 1919.1208 | Q95: 24948.57 | R95: =J95-O95 -> -9 | S95: =L95-Q95 -> -21731.44
A96: =+B96&C96 -> Véhicules usagésAutres marques | B96: Véhicules usagés | C96: Autres marques | D96: 8 | E96: =IF(D96=0,0,F96/D96) -> 1500 | F96: 12000 | J96: 8 | K96: =IF(J96=0,0,L96/J96) -> 1476.4362 | L96: 11811.49 | M96: =J96-D96 -> 0 | N96: =L96-F96 -> -188.51 | O96: 6 | P96: =IF(O96=0,0,Q96/O96) -> 1460.9367 | Q96: 8765.62 | R96: =J96-O96 -> 2 | S96: =L96-Q96 -> 3045.87
A97: =+B97&C97 -> Véhicules usagésTotal Usagés | B97: Véhicules usagés | C97: Total Usagés | D97: =+D95+D94+D96 -> 32 | E97: =IF(D97=0,0,F97/D97) -> 2018.75 | F97: =+F94+F95+F96 -> 64600 | J97: =+J94+J95+J96 -> 29 | K97: =IF(J97<=0,0,L97/J97) -> 1302.4048 | L97: =+L94+L95+L96 -> 37769.74 | M97: =J97-D97 -> -3 | N97: =L97-F97 -> -26830.26 | O97: =+O95+O94+O96 -> 25 | P97: =IF(O97=0,0,Q97/O97) -> 1860.4452 | Q97: =+Q94+Q95+Q96 -> 46511.13 | R97: =J97-O97 -> 4 | S97: =L97-Q97 -> -8741.39
A98: =+B98&C98 -> Véhicules usagés | B98: Véhicules usagés | M98: =M97/D97 -> -0.09375 | N98: =N97/F97 -> -0.4153291 | R98: =R97/O97 -> 0.16 | S98: =IF(Q97=0,0,(S97/Q97)) -> -0.1879419
A99: =+B99&C99 -> Véhicules neufsRachat bail | B99: =+$K$1 -> Véhicules neufs | C99: Rachat bail | D99: 0 | E99: =IF(D99=0,0,F99/D99) -> 0 | F99: 1509.8237 | L99: 4986.43 | N99: =L99-F99 -> 3476.6063 | Q99: 563.25 | R99: =O99-K99 -> 0 | S99: =L99-Q99 -> 4423.18
A100: =+B100&C100 -> Véhicules usagés | B100: Véhicules usagés
A101: =+B101&C101 -> Véhicules usagésVentes au Gros | B101: Véhicules usagés | C101: Ventes au Gros | D101: 26 | E101: =IF(D101=0,0,F101/D101) -> 500 | F101: 13000 | J101: 38 | K101: =IF(J101=0,0,L101/J101) -> 993.30079 | L101: 37745.43 | M101: =J101-D101 -> 12 | N101: =L101-F101 -> 24745.43 | O101: 11 | P101: =IF(O101=0,0,Q101/O101) -> -175.90818 | Q101: -1934.99 | R101: =J101-O101 -> 27 | S101: =L101-Q101 -> 39680.42
A102: =+B102&C102 -> Véhicules usagés | B102: Véhicules usagés
A103: =+B103&C103 -> Véhicules usagésRev. Finances | B103: Véhicules usagés | C103: Rev. Finances | E103: =IF(D97=0,0,F103/D97) -> 350 | F103: 11200 | K103: =IF(J97=0,0,L103/J97) -> 464.98172 | L103: 13484.47 | N103: =L103-F103 -> 2284.47 | P103: =IF(O97=0,0,Q103/O97) -> 336.268 | Q103: 8406.7 | R103: =O103-K103 -> -464.98172 | S103: =L103-Q103 -> 5077.77
A104: =+B104&C104 -> Véhicules usagésRev. Protections | B104: Véhicules usagés | C104: Rev. Protections | E104: =IF(D97=0,0,F104/D97) -> 950 | F104: 30400 | K104: =IF(J97=0,0,L104/J97) -> 521.03793 | L104: 15110.1 | N104: =L104-F104 -> -15289.9 | P104: =IF(O97=0,0,Q104/O97) -> 1091.892 | Q104: 27297.3 | R104: =O104-K104 -> -521.03793 | S104: =L104-Q104 -> -12187.2
A105: =+B105&C105 -> Véhicules usagésRev. Autres | B105: Véhicules usagés | C105: Rev. Autres | E105: =IF(D97=0,0,F105/D97) -> 200 | F105: 6400 | K105: =IF(J97=0,0,L105/J97) -> 72.758621 | L105: 2110 | N105: =L105-F105 -> -4290 | P105: =IF(O97=0,0,Q105/O97) -> 340.778 | Q105: 8519.45 | R105: =O105-K105 -> -72.758621 | S105: =L105-Q105 -> -6409.45
...

Sheet END
