Workbook
Name _Dates_Conc: [1]Dealers!$BF$37:$KA$63
Name _Dates_Conc: #REF!
Name _scen: '[1]Scen & Sens'!$E$26
Name _scen: #REF!
Name _scen1: '[1]Scen & Sens'!$E$27
Name _scen1: #REF!
Name _scen2: '[1]Scen & Sens'!$E$28
Name _scen2: #REF!
Name _SCenarios: '[1]Scen & Sens'!$J$26:$O$26
Name _SCenarios: #REF!
Name _Sens1: '[1]Scen & Sens'!$F$9
Name _Sens1: #REF!
Name _Sens2: '[1]Scen & Sens'!$F$10
Name _Sens2: #REF!
Name _sensRes1: '[1]Scen & Sens'!$E$15
Name _sensRes1: #REF!
Name _sensRes2: '[1]Scen & Sens'!$E$16
Name _sensRes2: #REF!
Name _sensRes3: '[1]Scen & Sens'!$E$17
Name _sensRes3: #REF!
Name _sensRes4: '[1]Scen & Sens'!$E$18
Name _sensRes4: #REF!
Name _sensRes5: '[1]Scen & Sens'!$E$19
Name _sensRes5: #REF!
Name _sensRes6: '[1]Scen & Sens'!$E$20
Name _sensRes6: #REF!
Name _sensRes7: '[1]Scen & Sens'!$E$21
Name _sensRes7: #REF!
Name Compco1: {"Page1",#N/A,FALSE,"CompCo";"Page2",#N/A,FALSE,"CompCo"}
Name Compco2: {"Page1",#N/A,FALSE,"CompCo";"Page2",#N/A,FALSE,"CompCo"}
Name DateRange: [1]Volkswagen!$BF$6:$DY$6
Name DateRange: #REF!
Name DateRangePr: OFFSET([2]!DateRangePriceMain,5,0,COUNTA([2]!DateRangePriceMain)-COUNTA(#REF!),1)
Name DateRangePrice: OFFSET([3]!DateRangePriceMain,5,0,COUNTA([3]!DateRangePriceMain)-COUNTA(#REF!),1)
Name DateRangePrice1: OFFSET([3]!DateRangePriceMain,5,0,COUNTA([3]!DateRangePriceMain)-COUNTA(#REF!),1)
Name DateRangePrice2: OFFSET([2]!DateRangePriceMain,5,0,COUNTA([2]!DateRangePriceMain)-COUNTA(#REF!),1)
Name ERT: {"execsum",#N/A,FALSE,"ExecSum";"finstatement",#N/A,FALSE,"Fin_St"}
Name hn.Delete015: '[4]CREDIT STATS'!$B$9:$K$14,'[4]CREDIT STATS'!$O$11:$X$18,'[4]CREDIT STATS'!$B$28:$K$37,'[4]CREDIT STATS'!$O$28:$X$32,'[4]CREDIT STATS'!$O$46:$X$46
Name kjjkghkhj: {"finana",#N/A,FALSE,"Fin"}
Name lkhkhj: {"sub1",#N/A,FALSE,"Subs";"pac1",#N/A,FALSE,"Packages";"rev1",#N/A,FALSE,"2. Revenues"}
Name Monetary_Unit: [1]Parameters!$B$15
Name Monetary_Unit: #REF!
Name Months: [1]Parameters!$E$9:$E$20
Name Months: #REF!
Name PriceRange: OFFSET([3]!PriceRangeMain,5,0,COUNTA([3]!PriceRangeMain)-COUNTA(#REF!),1)
Name PriceRange2: OFFSET([2]!PriceRangeMain,5,0,COUNTA([2]!PriceRangeMain)-COUNTA(#REF!),1)
Name Rng_Dealers_Names: [1]!Tbl_Dealers[Dealer Name]
Name Rng_Dealers_Names: #REF!
Name Rng_Dlr_Dates: [1]!Tbl_V_Dlr_Dates[Date]
Name Rng_Dlr_Dates: #REF!
Name test: {"execsum",#N/A,FALSE,"ExecSum";"finstatement",#N/A,FALSE,"Fin_St"}
Name test21: OFFSET([2]!DateRangePriceMain,5,0,COUNTA([2]!DateRangePriceMain)-COUNTA(#REF!),1)
Name Ticker: #REF!
Name Ticker: #REF!
Name Titre: [1]Front!$A$9
Name Titre: #REF!
Name value: OFFSET([3]!DateRangePriceMain,5,0,COUNTA([3]!DateRangePriceMain)-COUNTA(#REF!),1)
Name value2: OFFSET([2]!DateRangePriceMain,5,0,COUNTA([2]!DateRangePriceMain)-COUNTA(#REF!),1)
Name wrn.amendement.: {#N/A,#N/A,FALSE,"amendement"}
Name wrn.amendement..: {#N/A,#N/A,FALSE,"amendement"}

Sheet Parametres
A1: Compagnie | B1: BMW Sherbrooke
G2: 1-Mémo | M2: Mois | N2: YTD
A3: Mois Courant | B3: Avril | C3: =+VLOOKUP(B3,$K$3:$L$14,2,0) -> 4 | G3: 10-Compte compteur | K3: Janvier | L3: 1 | M3: =+IF($K3=$B$3,"X","") | N3: =+IF(K3=B3,"X",IF(L3<=$C$3,"X","")) -> X
A4: Année | B4: 2025 | K4: Février | L4: 2 | M4: =+IF($K4=$B$3,"X","") | N4: =+IF(K4=B4,"X",IF(L4<=$C$3,"X","")) -> X
K5: Mars | L5: 3 | M5: =+IF($K5=$B$3,"X","") | N5: =+IF(K5=B5,"X",IF(L5<=$C$3,"X","")) -> X
K6: Avril | L6: 4 | M6: =+IF($K6=$B$3,"X","") -> X | N6: =+IF(K6=B6,"X",IF(L6<=$C$3,"X","")) -> X
K7: Mai | L7: 5 | M7: =+IF($K7=$B$3,"X","") | N7: =+IF(K7=B7,"X",IF(L7<=$C$3,"X",""))
K8: Juin | L8: 6 | M8: =+IF($K8=$B$3,"X","") | N8: =+IF(K8=B8,"X",IF(L8<=$C$3,"X",""))
A9: Sélectionner le mois en B3 | K9: Juillet | L9: 7 | M9: =+IF($K9=$B$3,"X","") | N9: =+IF(K9=B9,"X",IF(L9<=$C$3,"X",""))
A10: Coller les balances de vérification respectives en cellule A1 dans les onglets BV_Data_An_Cour et BV_Data_An_Prec | K10: Août | L10: 8 | M10: =+IF($K10=$B$3,"X","") | N10: =+IF(K10=B10,"X",IF(L10<=$C$3,"X",""))
A11: Vérifier s'il y a des #N/A dans les colonnes T à X des onlgets de BV | K11: Septembre | L11: 9 | M11: =+IF($K11=$B$3,"X","") | N11: =+IF(K11=B11,"X",IF(L11<=$C$3,"X",""))
A12: Vérifier les chiffres avec l'état financier et les réalisés an passé pour les résultat net mois et aad | K12: Octobre | L12: 10 | M12: =+IF($K12=$B$3,"X","") | N12: =+IF(K12=B12,"X",IF(L12<=$C$3,"X",""))
K13: Novembre | L13: 11 | M13: =+IF($K13=$B$3,"X","") | N13: =+IF(K13=B13,"X",IF(L13<=$C$3,"X",""))
K14: Décembre | L14: 12 | M14: =+IF($K14=$B$3,"X","") | N14: =+IF(K14=B14,"X",IF(L14<=$C$3,"X",""))

Sheet Bilan
A1: BILAN
A2: =+Parametres!B1 -> BMW Sherbrooke
A3: =CONCATENATE("",,Parametres!B3," ",Parametres!B4) -> Avril 2025
A5: Encaisse | B5: =SUMIFS(BV_Data_An_Cour!$P:$P,BV_Data_An_Cour!$U:$U,$A$1,BV_Data_An_Cour!$V:$V,$A5) -> 1999437.1 | D5: Marge de crédit | E5: =-SUMIFS(BV_Data_An_Cour!$P:$P,BV_Data_An_Cour!$U:$U,$A$1,BV_Data_An_Cour!$V:$V,$D5) -> 0
A6: Total Trésorerie et équivalent de Trésorerie | B6: =SUM(B5) -> 1999437.1
D7: Portion Court Terme de la Dette Long Terme | E7: =-SUMIFS(BV_Data_An_Cour!$P:$P,BV_Data_An_Cour!$U:$U,$A$1,BV_Data_An_Cour!$V:$V,$D7) -> 0
A8: Recevables Contrats en Transit | B8: =SUMIFS(BV_Data_An_Cour!$P:$P,BV_Data_An_Cour!$U:$U,$A$1,BV_Data_An_Cour!$V:$V,$A8) -> 1458301.8
A9: Recevables Véhicules | B9: =SUMIFS(BV_Data_An_Cour!$P:$P,BV_Data_An_Cour!$U:$U,$A$1,BV_Data_An_Cour!$V:$V,$A9) -> 146427.85 | D9: Avances à payer | E9: =-SUMIFS(BV_Data_An_Cour!$P:$P,BV_Data_An_Cour!$U:$U,$A$1,BV_Data_An_Cour!$V:$V,$D9) -> 0
A10: Recevables Manufacturier | B10: =SUMIFS(BV_Data_An_Cour!$P:$P,BV_Data_An_Cour!$U:$U,$A$1,BV_Data_An_Cour!$V:$V,$A10) -> 131631.39 | D10: Comptes à Payer Fournisseurs | E10: =-SUMIFS(BV_Data_An_Cour!$P:$P,BV_Data_An_Cour!$U:$U,$A$1,BV_Data_An_Cour!$V:$V,$D10) -> 198236.38
A11: Recevables Pièces et Service | B11: =SUMIFS(BV_Data_An_Cour!$P:$P,BV_Data_An_Cour!$U:$U,$A$1,BV_Data_An_Cour!$V:$V,$A11) -> 83181.14 | D11: Taxes de Vente à Payer | E11: =-SUMIFS(BV_Data_An_Cour!$P:$P,BV_Data_An_Cour!$U:$U,$A$1,BV_Data_An_Cour!$V:$V,$D11) -> 83154.01
A12: Recevables Garantie Manufacturier | B12: =SUMIFS(BV_Data_An_Cour!$P:$P,BV_Data_An_Cour!$U:$U,$A$1,BV_Data_An_Cour!$V:$V,$A12) -> 9862.56 | D12: Impôts à payer | E12: =-SUMIFS(BV_Data_An_Cour!$P:$P,BV_Data_An_Cour!$U:$U,$A$1,BV_Data_An_Cour!$V:$V,$D12) -> 867228.05
A13: Recevables Carrosserie | B13: =SUMIFS(BV_Data_An_Cour!$P:$P,BV_Data_An_Cour!$U:$U,$A$1,BV_Data_An_Cour!$V:$V,$A13) -> 0 | D13: Dépôts de Client | E13: =-SUMIFS(BV_Data_An_Cour!$P:$P,BV_Data_An_Cour!$U:$U,$A$1,BV_Data_An_Cour!$V:$V,$D13) -> 99853.99
A14: Recevables Intercos | B14: =SUMIFS(BV_Data_An_Cour!$P:$P,BV_Data_An_Cour!$U:$U,$A$1,BV_Data_An_Cour!$V:$V,$A14) -> 86400 | D14: Payables Intercos | E14: =-SUMIFS(BV_Data_An_Cour!$P:$P,BV_Data_An_Cour!$U:$U,$A$1,BV_Data_An_Cour!$V:$V,$D14) -> 163854.91
A15: Recevables Autres | B15: =SUMIFS(BV_Data_An_Cour!$P:$P,BV_Data_An_Cour!$U:$U,$A$1,BV_Data_An_Cour!$V:$V,$A15) -> 17533.8 | D15: Autres Comptes à Payer | E15: =-SUMIFS(BV_Data_An_Cour!$P:$P,BV_Data_An_Cour!$U:$U,$A$1,BV_Data_An_Cour!$V:$V,$D15) -> 382442.56
A16: Total Comptes à Recevoir | B16: =+SUM(B8:B15) -> 1933338.5 | D16: Total Comptes à Payer | E16: =+SUM(E10:E15) -> 1794769.9
A18: Inventaire Véhicules Neufs | B18: =SUMIFS(BV_Data_An_Cour!$P:$P,BV_Data_An_Cour!$U:$U,$A$1,BV_Data_An_Cour!$V:$V,$A18) -> 6367035 | D18: Effet à Payer Véhicules Neufs | E18: =-SUMIFS(BV_Data_An_Cour!$P:$P,BV_Data_An_Cour!$U:$U,$A$1,BV_Data_An_Cour!$V:$V,$D18) -> 8488042.7
A19: Inventaire Véhicules Usagés | B19: =SUMIFS(BV_Data_An_Cour!$P:$P,BV_Data_An_Cour!$U:$U,$A$1,BV_Data_An_Cour!$V:$V,$A19) -> 2063058.6 | D19: Effet à Payer Véhicules Usagés | E19: =-SUMIFS(BV_Data_An_Cour!$P:$P,BV_Data_An_Cour!$U:$U,$A$1,BV_Data_An_Cour!$V:$V,$D19) -> 937246.05
A20: Inventaire Pièces, Pneus, Huile | B20: =SUMIFS(BV_Data_An_Cour!$P:$P,BV_Data_An_Cour!$U:$U,$A$1,BV_Data_An_Cour!$V:$V,$A20) -> 520521 | D20: Total Effets à Payer | E20: =+SUM(E18:E19) -> 9425288.7
A21: Total Inventaires | B21: =SUM(B18:B20) -> 8950614.7
D22: Salaires à Payer | E22: =-SUMIFS(BV_Data_An_Cour!$P:$P,BV_Data_An_Cour!$U:$U,$A$1,BV_Data_An_Cour!$V:$V,$D22) -> 346036.22
A23: Avances à recevoir | B23: =SUMIFS(BV_Data_An_Cour!$P:$P,BV_Data_An_Cour!$U:$U,$A$1,BV_Data_An_Cour!$V:$V,$A23) -> 0 | D23: DAS à Payer | E23: =-SUMIFS(BV_Data_An_Cour!$P:$P,BV_Data_An_Cour!$U:$U,$A$1,BV_Data_An_Cour!$V:$V,$D23) -> 8220.3
A24: Travaux en Cours | B24: =SUMIFS(BV_Data_An_Cour!$P:$P,BV_Data_An_Cour!$U:$U,$A$1,BV_Data_An_Cour!$V:$V,$A24) -> 8749.73 | D24: Autres Courus | E24: =-SUMIFS(BV_Data_An_Cour!$P:$P,BV_Data_An_Cour!$U:$U,$A$1,BV_Data_An_Cour!$V:$V,$D24) -> 206376.49
A25: Sous-Traitance | B25: =SUMIFS(BV_Data_An_Cour!$P:$P,BV_Data_An_Cour!$U:$U,$A$1,BV_Data_An_Cour!$V:$V,$A25) -> 321.29 | D25: [...] | E25: =-SUMIFS(BV_Data_An_Cour!$P:$P,BV_Data_An_Cour!$U:$U,$A$1,BV_Data_An_Cour!$V:$V,$D25) -> 0
A26: Frais Payés d'Avance | B26: =SUMIFS(BV_Data_An_Cour!$P:$P,BV_Data_An_Cour!$U:$U,$A$1,BV_Data_An_Cour!$V:$V,$A26) -> -37207.24 | D26: [...] | E26: =-SUMIFS(BV_Data_An_Cour!$P:$P,BV_Data_An_Cour!$U:$U,$A$1,BV_Data_An_Cour!$V:$V,$D26) -> 0
A27: [...] | B27: =SUMIFS(BV_Data_An_Cour!$P:$P,BV_Data_An_Cour!$U:$U,$A$1,BV_Data_An_Cour!$V:$V,$A27) -> 0 | D27: [...] | E27: =-SUMIFS(BV_Data_An_Cour!$P:$P,BV_Data_An_Cour!$U:$U,$A$1,BV_Data_An_Cour!$V:$V,$D27) -> 0
A28: [...] | B28: =SUMIFS(BV_Data_An_Cour!$P:$P,BV_Data_An_Cour!$U:$U,$A$1,BV_Data_An_Cour!$V:$V,$A28) -> 0 | D28: Total Frais Courus | E28: =SUM(E22:E24) -> 560633.01
A29: [...] | B29: =SUMIFS(BV_Data_An_Cour!$P:$P,BV_Data_An_Cour!$U:$U,$A$1,BV_Data_An_Cour!$V:$V,$A29) -> 0
A30: Total Autres | B30: =SUM(B23:B29) -> -28136.22 | D30: Total Passif Court Terme | E30: =+E5+E7+E16+E20+E28 -> 11780692
A32: Total Actif Court Terme | B32: =+B6+B16+B21+B30 -> 12855254
D33: Impôts Futurs à payer | E33: =-SUMIFS(BV_Data_An_Cour!$P:$P,BV_Data_An_Cour!$U:$U,$A$1,BV_Data_An_Cour!$V:$V,$D33) -> 1101731
A35: Terrain | B35: =SUMIFS(BV_Data_An_Cour!$P:$P,BV_Data_An_Cour!$U:$U,$A$1,BV_Data_An_Cour!$V:$V,$A35) -> 0 | D35: Avances Long Terme à Payer | E35: =-SUMIFS(BV_Data_An_Cour!$P:$P,BV_Data_An_Cour!$U:$U,$A$1,BV_Data_An_Cour!$V:$V,$D35) -> 0
A36: Bâtisse | B36: =SUMIFS(BV_Data_An_Cour!$P:$P,BV_Data_An_Cour!$U:$U,$A$1,BV_Data_An_Cour!$V:$V,$A36) -> 0 | D36: Hypothèque à Payer | E36: =-SUMIFS(BV_Data_An_Cour!$P:$P,BV_Data_An_Cour!$U:$U,$A$1,BV_Data_An_Cour!$V:$V,$D36) -> 0
A37: Améliorations Locatives | B37: =SUMIFS(BV_Data_An_Cour!$P:$P,BV_Data_An_Cour!$U:$U,$A$1,BV_Data_An_Cour!$V:$V,$A37) -> 608743.91 | D37: Dette à Long Terme | E37: =-SUMIFS(BV_Data_An_Cour!$P:$P,BV_Data_An_Cour!$U:$U,$A$1,BV_Data_An_Cour!$V:$V,$D37) -> 0
A38: Améliorations Locatives Permanentes | B38: =SUMIFS(BV_Data_An_Cour!$P:$P,BV_Data_An_Cour!$U:$U,$A$1,BV_Data_An_Cour!$V:$V,$A38) -> 0 | D38: Autres Dettes à Long Terme | E38: =-SUMIFS(BV_Data_An_Cour!$P:$P,BV_Data_An_Cour!$U:$U,$A$1,BV_Data_An_Cour!$V:$V,$D38) -> 0
A39: Équipements Service | B39: =SUMIFS(BV_Data_An_Cour!$P:$P,BV_Data_An_Cour!$U:$U,$A$1,BV_Data_An_Cour!$V:$V,$A39) -> 207862.96 | D39: [...] | E39: =-SUMIFS(BV_Data_An_Cour!$P:$P,BV_Data_An_Cour!$U:$U,$A$1,BV_Data_An_Cour!$V:$V,$D39) -> 0
A40: Mobilier | B40: =SUMIFS(BV_Data_An_Cour!$P:$P,BV_Data_An_Cour!$U:$U,$A$1,BV_Data_An_Cour!$V:$V,$A40) -> 219658.95 | D40: [...] | E40: =-SUMIFS(BV_Data_An_Cour!$P:$P,BV_Data_An_Cour!$U:$U,$A$1,BV_Data_An_Cour!$V:$V,$D40) -> 0
A41: Équipements Informatique | B41: =SUMIFS(BV_Data_An_Cour!$P:$P,BV_Data_An_Cour!$U:$U,$A$1,BV_Data_An_Cour!$V:$V,$A41) -> 16966.63 | D41: [...] | E41: =-SUMIFS(BV_Data_An_Cour!$P:$P,BV_Data_An_Cour!$U:$U,$A$1,BV_Data_An_Cour!$V:$V,$D41) -> 0
A42: Équipements Téléphonique | B42: =SUMIFS(BV_Data_An_Cour!$P:$P,BV_Data_An_Cour!$U:$U,$A$1,BV_Data_An_Cour!$V:$V,$A42) -> 0 | D42: Total Passif long terme | E42: =+SUM(E33:E38) -> 1101731
A43: Enseigne | B43: =SUMIFS(BV_Data_An_Cour!$P:$P,BV_Data_An_Cour!$U:$U,$A$1,BV_Data_An_Cour!$V:$V,$A43) -> 12885.77
A44: Total Immobilisations Nettes | B44: =SUM(B35:B43) -> 1066118.2
D45: Total Passifs | E45: =+E42+E30 -> 12882423
A46: Avances à Recevoir Long Terme | B46: =SUMIFS(BV_Data_An_Cour!$P:$P,BV_Data_An_Cour!$U:$U,$A$1,BV_Data_An_Cour!$V:$V,$A46) -> 2500000
A48: Achalandage | B48: =SUMIFS(BV_Data_An_Cour!$P:$P,BV_Data_An_Cour!$U:$U,$A$1,BV_Data_An_Cour!$V:$V,$A48) -> 4854961.3 | D48: Capital Actions | E48: =-SUMIFS(BV_Data_An_Cour!$P:$P,BV_Data_An_Cour!$U:$U,$A$1,BV_Data_An_Cour!$V:$V,$D48) -> 4390685.6
D49: Apport | E49: =-SUMIFS(BV_Data_An_Cour!$P:$P,BV_Data_An_Cour!$U:$U,$A$1,BV_Data_An_Cour!$V:$V,$D49) -> 0
A50: [...] | B50: =SUMIFS(BV_Data_An_Cour!$P:$P,BV_Data_An_Cour!$U:$U,$A$1,BV_Data_An_Cour!$V:$V,$A50) -> 0 | D50: Bénéfices non répartis | E50: =-SUMIFS(BV_Data_An_Cour!$P:$P,BV_Data_An_Cour!$U:$U,$A$1,BV_Data_An_Cour!$V:$V,$D50)+Print_AAD!AF502 -> 4003225.3
A51: [...] | B51: =SUMIFS(BV_Data_An_Cour!$P:$P,BV_Data_An_Cour!$U:$U,$A$1,BV_Data_An_Cour!$V:$V,$A51) -> 0 | D51: Dividendes | E51: =-SUMIFS(BV_Data_An_Cour!$P:$P,BV_Data_An_Cour!$U:$U,$A$1,BV_Data_An_Cour!$V:$V,$D51) -> 0
A52: [...] | B52: =SUMIFS(BV_Data_An_Cour!$P:$P,BV_Data_An_Cour!$U:$U,$A$1,BV_Data_An_Cour!$V:$V,$A52) -> 0
A53: Total Actif Long Terme | B53: =+B44+B48+B46 -> 8421079.5 | D53: Total Capitaux Propres / Avoir | E53: =SUM(E48:E51) -> 8393910.9
A56: Total Actif | B56: =+B32+B53 -> 21276334 | D56: Total Passif et Capitaux Propres / Avoir | E56: =+E53+E45 -> 21276334
E65: =+B56-E56 -> 0

Sheet Budget original
B1: ="Budget 2023 Mensuel"&" "&Parametres!$B$1 -> Budget 2023 Mensuel BMW Sherbrooke
B2: Mois | F2: =+IF(Parametres!$B$3=F$6,"X","") | G2: =+IF(Parametres!$B$3=F$6,"O","") | H2: =+IF(Parametres!$B$3=F$6,"U","") | I2: =+IF(Parametres!$B$3=I$6,"X","") | J2: =+IF(Parametres!$B$3=I$6,"O","") | K2: =+IF(Parametres!$B$3=I$6,"U","") | L2: =+IF(Parametres!$B$3=L$6,"X","") | M2: =+IF(Parametres!$B$3=L$6,"O","") | N2: =+IF(Parametres!$B$3=L$6,"U","") | O2: =+IF(Parametres!$B$3=O$6,"X","") -> X | P2: =+IF(Parametres!$B$3=O$6,"O","") -> O | Q2: =+IF(Parametres!$B$3=O$6,"U","") -> U | R2: =+IF(Parametres!$B$3=R$6,"X","") | S2: =+IF(Parametres!$B$3=R$6,"O","") | T2: =+IF(Parametres!$B$3=R$6,"U","") | U2: =+IF(Parametres!$B$3=U$6,"X","") | V2: =+IF(Parametres!$B$3=U$6,"O","") | W2: =+IF(Parametres!$B$3=U$6,"U","") | X2: =+IF(Parametres!$B$3=X$6,"X","") | Y2: =+IF(Parametres!$B$3=X$6,"O","") | Z2: =+IF(Parametres!$B$3=X$6,"U","") | AA2: =+IF(Parametres!$B$3=AA$6,"X","") | AB2: =+IF(Parametres!$B$3=AA$6,"O","") | AC2: =+IF(Parametres!$B$3=AA$6,"U","") | AD2: =+IF(Parametres!$B$3=AD$6,"X","") | AE2: =+IF(Parametres!$B$3=AD$6,"O","") | AF2: =+IF(Parametres!$B$3=AD$6,"U","") | AG2: =+IF(Parametres!$B$3=AG$6,"X","") | AH2: =+IF(Parametres!$B$3=AG$6,"O","") | AI2: =+IF(Parametres!$B$3=AG$6,"U","") | AJ2: =+IF(Parametres!$B$3=AJ$6,"X","") | AK2: =+IF(Parametres!$B$3=AJ$6,"O","") | AL2: =+IF(Parametres!$B$3=AJ$6,"U","") | AM2: =+IF(Parametres!$B$3=AM$6,"X","") | AN2: =+IF(Parametres!$B$3=AM$6,"O","") | AO2: =+IF(Parametres!$B$3=AM$6,"U","")
B3: YTD | F3: =+IF(VLOOKUP(F$6,Parametres!$K$3:$N$14,4,0)="X","X","") -> X | G3: =+IF(VLOOKUP(F$6,Parametres!$K$3:$N$14,4,0)="X","O","") -> O | H3: =+IF(VLOOKUP(F$6,Parametres!$K$3:$N$14,4,0)="X","U","") -> U | I3: =+IF(VLOOKUP(I$6,Parametres!$K$3:$N$14,4,0)="X","X","") -> X | J3: =+IF(VLOOKUP(I$6,Parametres!$K$3:$N$14,4,0)="X","O","") -> O | K3: =+IF(VLOOKUP(I$6,Parametres!$K$3:$N$14,4,0)="X","U","") -> U | L3: =+IF(VLOOKUP(L$6,Parametres!$K$3:$N$14,4,0)="X","X","") -> X | M3: =+IF(VLOOKUP(L$6,Parametres!$K$3:$N$14,4,0)="X","O","") -> O | N3: =+IF(VLOOKUP(L$6,Parametres!$K$3:$N$14,4,0)="X","U","") -> U | O3: =+IF(VLOOKUP(O$6,Parametres!$K$3:$N$14,4,0)="X","X","") -> X | P3: =+IF(VLOOKUP(O$6,Parametres!$K$3:$N$14,4,0)="X","O","") -> O | Q3: =+IF(VLOOKUP(O$6,Parametres!$K$3:$N$14,4,0)="X","U","") -> U | R3: =+IF(VLOOKUP(R$6,Parametres!$K$3:$N$14,4,0)="X","X","") | S3: =+IF(VLOOKUP(R$6,Parametres!$K$3:$N$14,4,0)="X","O","") | T3: =+IF(VLOOKUP(R$6,Parametres!$K$3:$N$14,4,0)="X","U","") | U3: =+IF(VLOOKUP(U$6,Parametres!$K$3:$N$14,4,0)="X","X","") | V3: =+IF(VLOOKUP(U$6,Parametres!$K$3:$N$14,4,0)="X","O","") | W3: =+IF(VLOOKUP(U$6,Parametres!$K$3:$N$14,4,0)="X","U","") | X3: =+IF(VLOOKUP(X$6,Parametres!$K$3:$N$14,4,0)="X","X","") | Y3: =+IF(VLOOKUP(X$6,Parametres!$K$3:$N$14,4,0)="X","O","") | Z3: =+IF(VLOOKUP(X$6,Parametres!$K$3:$N$14,4,0)="X","U","") | AA3: =+IF(VLOOKUP(AA$6,Parametres!$K$3:$N$14,4,0)="X","X","") | AB3: =+IF(VLOOKUP(AA$6,Parametres!$K$3:$N$14,4,0)="X","O","") | AC3: =+IF(VLOOKUP(AA$6,Parametres!$K$3:$N$14,4,0)="X","U","") | AD3: =+IF(VLOOKUP(AD$6,Parametres!$K$3:$N$14,4,0)="X","X","") | AE3: =+IF(VLOOKUP(AD$6,Parametres!$K$3:$N$14,4,0)="X","O","") | AF3: =+IF(VLOOKUP(AD$6,Parametres!$K$3:$N$14,4,0)="X","U","") | AG3: =+IF(VLOOKUP(AG$6,Parametres!$K$3:$N$14,4,0)="X","X","") | AH3: =+IF(VLOOKUP(AG$6,Parametres!$K$3:$N$14,4,0)="X","O","") | AI3: =+IF(VLOOKUP(AG$6,Parametres!$K$3:$N$14,4,0)="X","U","") | AJ3: =+IF(VLOOKUP(AJ$6,Parametres!$K$3:$N$14,4,0)="X","X","") | AK3: =+IF(VLOOKUP(AJ$6,Parametres!$K$3:$N$14,4,0)="X","O","") | AL3: =+IF(VLOOKUP(AJ$6,Parametres!$K$3:$N$14,4,0)="X","U","") | AM3: =+IF(VLOOKUP(AM$6,Parametres!$K$3:$N$14,4,0)="X","X","") | AN3: =+IF(VLOOKUP(AM$6,Parametres!$K$3:$N$14,4,0)="X","O","") | AO3: =+IF(VLOOKUP(AM$6,Parametres!$K$3:$N$14,4,0)="X","U","")
B4: Budget 2025 | C4: Véhicules neufs
B6: Mois | C6: 2025 | F6: Janvier | I6: Février | L6: Mars | O6: Avril | R6: Mai | U6: Juin | X6: Juillet | AA6: Août | AD6: Septembre | AG6: Octobre | AJ6: Novembre | AM6: Décembre
C7: UNITE | D7: $P/UNITE | E7: $PROFITS | F7: UNITE | G7: $P/UNITE | H7: $PROFITS | I7: UNITE | J7: $P/UNITE | K7: $PROFITS | L7: UNITE | M7: $P/UNITE | N7: $PROFITS | O7: UNITE | P7: $P/UNITE | Q7: $PROFITS | R7: UNITE | S7: $P/UNITE | T7: $PROFITS | U7: UNITE | V7: $P/UNITE | W7: $PROFITS | X7: UNITE | Y7: $P/UNITE | Z7: $PROFITS | AA7: UNITE | AB7: $P/UNITE | AC7: $PROFITS | AD7: UNITE | AE7: $P/UNITE | AF7: $PROFITS | AG7: UNITE | AH7: $P/UNITE | AI7: $PROFITS | AJ7: UNITE | AK7: $P/UNITE | AL7: $PROFITS | AM7: UNITE | AN7: $P/UNITE | AO7: $PROFITS
A8: =+$C$4&B8 -> Véhicules neufsVentes nettes | B8: Ventes nettes | E8: 25300742 | H8: 1392233.6 | K8: 1203869.3 | N8: 2376592 | Q8: 3027277.1 | T8: 3315725.1 | W8: 2132666.7 | Z8: 1576929.9 | AC8: 2044724.1 | AF8: 2351226.7 | AI8: 2297872.1 | AL8: 1921112.5 | AO8: 1660512.8
A9: =+$C$4&B9 -> Véhicules neufsAutos détail | B9: Autos détail | C9: 86 | D9: 4306.3953 | E9: 370350 | F9: 5 | G9: 4306.3953 | H9: 21531.977 | I9: 4 | J9: 4306.3953 | K9: 17225.581 | L9: 8 | M9: 4306.3953 | N9: 34451.163 | O9: 10 | P9: 4306.3953 | Q9: 43063.953 | R9: 11 | S9: 4306.3953 | T9: 47370.349 | U9: 7 | V9: 4306.3953 | W9: 30144.767 | X9: 5 | Y9: 4306.3953 | Z9: 21531.977 | AA9: 7 | AB9: 4306.3953 | AC9: 30144.767 | AD9: 8 | AE9: 4306.3953 | AF9: 34451.163 | AG9: 8 | AH9: 4306.3953 | AI9: 34451.163 | AJ9: 7 | AK9: 4306.3953 | AL9: 30144.767 | AM9: 6 | AN9: 4306.3953 | AO9: 25838.372
A10: =+$C$4&B10 -> Véhicules neufsCamions détail | B10: Camions détail | C10: 151 | D10: 4000.3311 | E10: 604050 | F10: 8 | G10: 4000.3311 | H10: 32002.649 | I10: 7 | J10: 4000.3311 | K10: 28002.318 | L10: 14 | M10: 4000.3311 | N10: 56004.636 | O10: 18 | P10: 4000.3311 | Q10: 72005.96 | R10: 20 | S10: 4000.3311 | T10: 80006.623 | U10: 13 | V10: 4000.3311 | W10: 52004.305 | X10: 10 | Y10: 4000.3311 | Z10: 40003.311 | AA10: 12 | AB10: 4000.3311 | AC10: 48003.974 | AD10: 14 | AE10: 4000.3311 | AF10: 56004.636 | AG10: 14 | AH10: 4000.3311 | AI10: 56004.636 | AJ10: 11 | AK10: 4000.3311 | AL10: 44003.642 | AM10: 10 | AN10: 4000.3311 | AO10: 40003.311
A11: =+$C$4&B11 -> Véhicules neufsSprinter | B11: Sprinter | C11: 0 | D11: 0 | E11: 0 | F11: 0 | G11: 0 | H11: 0 | I11: 0 | J11: 0 | K11: 0 | L11: 0 | M11: 0 | N11: 0 | O11: 0 | P11: 0 | Q11: 0 | R11: 0 | S11: 0 | T11: 0 | U11: 0 | V11: 0 | W11: 0 | X11: 0 | Y11: 0 | Z11: 0 | AA11: 0 | AB11: 0 | AC11: 0 | AD11: 0 | AE11: 0 | AF11: 0 | AG11: 0 | AH11: 0 | AI11: 0 | AJ11: 0 | AK11: 0 | AL11: 0 | AM11: 0 | AN11: 0 | AO11: 0
A12: =+$C$4&B12 -> Véhicules neufsMoto détail | B12: Moto détail | C12: 0 | D12: 0 | E12: 0 | F12: 0 | G12: 0 | H12: 0 | I12: 0 | J12: 0 | K12: 0 | L12: 0 | M12: 0 | N12: 0 | O12: 0 | P12: 0 | Q12: 0 | R12: 0 | S12: 0 | T12: 0 | U12: 0 | V12: 0 | W12: 0 | X12: 0 | Y12: 0 | Z12: 0 | AA12: 0 | AB12: 0 | AC12: 0 | AD12: 0 | AE12: 0 | AF12: 0 | AG12: 0 | AH12: 0 | AI12: 0 | AJ12: 0 | AK12: 0 | AL12: 0 | AM12: 0 | AN12: 0 | AO12: 0
A13: =+$C$4&B13 -> Véhicules neufs[...] | B13: [...] | C13: 0 | D13: 0 | E13: 0 | G13: 0 | J13: 0 | M13: 0 | P13: 0 | S13: 0 | V13: 0 | Y13: 0 | AB13: 0 | AE13: 0 | AH13: 0 | AK13: 0 | AN13: 0
A14: =+$C$4&B14 -> Véhicules neufs[...] | B14: [...] | C14: 0 | D14: 0 | E14: 0 | G14: 0 | J14: 0 | M14: 0 | P14: 0 | S14: 0 | V14: 0 | Y14: 0 | AB14: 0 | AE14: 0 | AH14: 0 | AK14: 0 | AN14: 0
A15: =+$C$4&B15 -> Véhicules neufs[...] | B15: [...] | C15: 0 | D15: 0 | E15: 0 | G15: 0 | J15: 0 | M15: 0 | P15: 0 | S15: 0 | V15: 0 | Y15: 0 | AB15: 0 | AE15: 0 | AH15: 0 | AK15: 0 | AN15: 0
A16: =+$C$4&B16 -> Véhicules neufsTotal Neufs | B16: Total Neufs | C16: 237 | D16: 4111.3924 | E16: 974400 | F16: 13 | G16: 4118.0481 | H16: 53534.626 | I16: 11 | J16: 4111.6272 | K16: 45227.899 | L16: 22 | M16: 4111.6272 | N16: 90455.799 | O16: 28 | P16: 4109.6398 | Q16: 115069.91 | R16: 31 | S16: 4108.9346 | T16: 127376.97 | U16: 20 | V16: 4107.4536 | W16: 82149.072 | X16: 15 | Y16: 4102.3525 | Z16: 61535.288 | AA16: 19 | AB16: 4113.0916 | AC16: 78148.741 | AD16: 22 | AE16: 4111.6272 | AF16: 90455.799 | AG16: 22 | AH16: 4111.6272 | AI16: 90455.799 | AJ16: 18 | AK16: 4119.3561 | AL16: 74148.41 | AM16: 16 | AN16: 4115.1052 | AO16: 65841.683
A17: =+$C$4&B17 -> Véhicules neufs
A18: =+$C$4&B18 -> Véhicules neufsEx-Démos et courtoisies | B18: Ex-Démos et courtoisies | C18: 35 | D18: 750 | E18: 26250 | F18: 2 | G18: 750 | H18: 1500 | I18: 2 | J18: 750 | K18: 1500 | L18: 3 | M18: 750 | N18: 2250 | O18: 4 | P18: 750 | Q18: 3000 | R18: 5 | S18: 750 | T18: 3750 | U18: 3 | V18: 750 | W18: 2250 | X18: 2 | Y18: 750 | Z18: 1500 | AA18: 3 | AB18: 750 | AC18: 2250 | AD18: 3 | AE18: 750 | AF18: 2250 | AG18: 3 | AH18: 750 | AI18: 2250 | AJ18: 3 | AK18: 750 | AL18: 2250 | AM18: 2 | AN18: 750 | AO18: 1500
A19: =+$C$4&B19 -> Véhicules neufs
A20: =+$C$4&B20 -> Véhicules neufsFlottes | B20: Flottes | C20: 3 | D20: 0 | E20: 0 | F20: 0 | G20: 0 | H20: 0 | I20: 0 | J20: 0 | K20: 0 | L20: 1 | M20: 0 | N20: 0 | O20: 1 | P20: 0 | Q20: 0 | R20: 0 | S20: 0 | T20: 0 | U20: 0 | V20: 0 | W20: 0 | X20: 0 | Y20: 0 | Z20: 0 | AA20: 0 | AB20: 0 | AC20: 0 | AD20: 1 | AE20: 0 | AF20: 0 | AG20: 0 | AH20: 0 | AI20: 0 | AJ20: 0 | AK20: 0 | AL20: 0 | AM20: 0 | AN20: 0 | AO20: 0
A21: =+$C$4&B21 -> Véhicules neufs
A22: =+$C$4&B22 -> Véhicules neufsRachat bail | B22: Rachat bail | E22: 29970 | H22: 2006.507 | K22: 1744.6741 | N22: 2495.9768 | Q22: 3500.0986 | T22: 4034.9001 | W22: 3007.1267 | Z22: 2178.6402 | AC22: 3072.8225 | AF22: 1622.1855 | AI22: 2471.1767 | AL22: 1909.7847 | AO22: 1926.1072
A23: =+$C$4&B23 -> Véhicules neufs
A24: =+$C$4&B24 -> Véhicules neufsRev. Finances | B24: Rev. Finances | D24: 25 | E24: 6800 | G24: 25 | H24: 375 | J24: 25 | K24: 325 | M24: 25 | N24: 625 | P24: 25 | Q24: 800 | S24: 25 | T24: 900 | V24: 25 | W24: 575 | Y24: 25 | Z24: 425 | AB24: 25 | AC24: 550 | AE24: 25 | AF24: 625 | AH24: 25 | AI24: 625 | AK24: 25 | AL24: 525 | AN24: 25 | AO24: 450
A25: =+$C$4&B25 -> Véhicules neufsRev. Protections | B25: Rev. Protections | D25: 1150 | E25: 312800 | G25: 1150 | H25: 17250 | J25: 1150 | K25: 14950 | M25: 1150 | N25: 28750 | P25: 1150 | Q25: 36800 | S25: 1150 | T25: 41400 | V25: 1150 | W25: 26450 | Y25: 1150 | Z25: 19550 | AB25: 1150 | AC25: 25300 | AE25: 1150 | AF25: 28750 | AH25: 1150 | AI25: 28750 | AK25: 1150 | AL25: 24150 | AN25: 1150 | AO25: 20700
A26: =+$C$4&B26 -> Véhicules neufsRev. Autres | B26: Rev. Autres | D26: 480 | E26: 130560 | G26: 480 | H26: 7200 | J26: 480 | K26: 6240 | M26: 480 | N26: 12000 | P26: 480 | Q26: 15360 | S26: 480 | T26: 17280 | V26: 480 | W26: 11040 | Y26: 480 | Z26: 8160 | AB26: 480 | AC26: 10560 | AE26: 480 | AF26: 12000 | AH26: 480 | AI26: 12000 | AK26: 480 | AL26: 10080 | AN26: 480 | AO26: 8640
A27: =+$C$4&B27 -> Véhicules neufsTotal F&I | B27: Total F&I | C27: 272 | D27: 1655 | E27: 450160 | F27: 15 | G27: 1655 | H27: 24825 | I27: 13 | J27: 1655 | K27: 21515 | L27: 25 | M27: 1655 | N27: 41375 | O27: 32 | P27: 1655 | Q27: 52960 | R27: 36 | S27: 1655 | T27: 59580 | U27: 23 | V27: 1655 | W27: 38065 | X27: 17 | Y27: 1655 | Z27: 28135 | AA27: 22 | AB27: 1655 | AC27: 36410 | AD27: 25 | AE27: 1655 | AF27: 41375 | AG27: 25 | AH27: 1655 | AI27: 41375 | AJ27: 21 | AK27: 1655 | AL27: 34755 | AM27: 18 | AN27: 1655 | AO27: 29790
A28: =+$C$4&B28 -> Véhicules neufs
A29: =+$C$4&B29 -> Véhicules neufs
A30: =+$C$4&B30 -> Véhicules neufsTotal Dépt. Neufs | B30: Total Dépt. Neufs | C30: 275 | D30: 5384.6545 | E30: 1480780 | F30: 15 | G30: 5457.7422 | H30: 81866.133 | I30: 13 | J30: 5383.6595 | K30: 69987.573 | L30: 26 | M30: 5252.9529 | N30: 136576.78 | O30: 33 | P30: 5288.7883 | Q30: 174530.01 | R30: 36 | S30: 5409.4964 | T30: 194741.87 | U30: 23 | V30: 5455.2695 | W30: 125471.2 | X30: 17 | Y30: 5491.1134 | Z30: 93348.928 | AA30: 22 | AB30: 5449.162 | AC30: 119881.56 | AD30: 26 | AE30: 5219.3455 | AF30: 135702.98 | AG30: 25 | AH30: 5462.079 | AI30: 136551.98 | AJ30: 21 | AK30: 5383.9616 | AL30: 113063.19 | AM30: 18 | AN30: 5503.2106 | AO30: 99057.791
A31: =+$C$4&B31 -> Véhicules neufs
A32: =+$C$4&B32 -> Véhicules neufs
A33: =+$C$4&B33 -> Véhicules neufsDEPENSES | B33: DEPENSES
A34: =+$C$4&B34 -> Véhicules neufsComm. vendeurs | B34: Comm. vendeurs | C34: 0.29126568 | D34: 1071.5257 | E34: 291455 | F34: 0.31323602 | G34: 1149.2551 | H34: 17238.827 | I34: 0.31476231 | J34: 1131.3986 | K34: 14708.182 | L34: 0.28606608 | M34: 1060.7994 | N34: 26519.984 | O34: 0.2815412 | P34: 1038.7983 | Q34: 33241.545 | R34: 0.27942009 | S34: 1017.7642 | T34: 36639.51 | U34: 0.29112986 | V34: 1068.3083 | W34: 24571.09 | X34: 0.30589257 | Y34: 1134.2368 | Z34: 19282.026 | AA34: 0.2933806 | AB34: 1072.156 | AC34: 23587.431 | AD34: 0.28510663 | AE34: 1057.2415 | AF34: 26431.038 | AG34: 0.28879302 | AH34: 1070.9115 | AI34: 26772.788 | AJ34: 0.29015116 | AK34: 1055.5756 | AL34: 22167.087 | AM34: 0.30138082 | AN34: 1127.5273 | AO34: 20295.492
A35: =+$C$4&B35 -> Véhicules neufsComm. F&I | B35: Comm. F&I | C35: 0.275 | D35: 455.125 | E35: 123794 | F35: 0.275 | G35: 455.125 | H35: 6826.875 | I35: 0.275 | J35: 455.125 | K35: 5916.625 | L35: 0.275 | M35: 455.125 | N35: 11378.125 | O35: 0.275 | P35: 455.125 | Q35: 14564 | R35: 0.275 | S35: 455.125 | T35: 16384.5 | U35: 0.275 | V35: 455.125 | W35: 10467.875 | X35: 0.275 | Y35: 455.125 | Z35: 7737.125 | AA35: 0.275 | AB35: 455.125 | AC35: 10012.75 | AD35: 0.275 | AE35: 455.125 | AF35: 11378.125 | AG35: 0.275 | AH35: 455.125 | AI35: 11378.125 | AJ35: 0.275 | AK35: 455.125 | AL35: 9557.625 | AM35: 0.275 | AN35: 455.125 | AO35: 8192.25
A36: =+$C$4&B36 -> Véhicules neufsFrais de livraison | B36: Frais de livraison | D36: 130 | E36: 35360 | G36: 130 | H36: 1950 | J36: 130 | K36: 1690 | M36: 130 | N36: 3250 | P36: 130 | Q36: 4160 | S36: 130 | T36: 4680 | V36: 130 | W36: 2990 | Y36: 130 | Z36: 2210 | AB36: 130 | AC36: 2860 | AE36: 130 | AF36: 3250 | AH36: 130 | AI36: 3250 | AK36: 130 | AL36: 2730 | AN36: 130 | AO36: 2340
A37: =+$C$4&B37 -> Véhicules neufsService gratuit 1 | B37: Service gratuit 1 | D37: 37 | E37: 10064 | G37: 37 | H37: 555 | J37: 37 | K37: 481 | M37: 37 | N37: 925 | P37: 37 | Q37: 1184 | S37: 37 | T37: 1332 | V37: 37 | W37: 851 | Y37: 37 | Z37: 629 | AB37: 37 | AC37: 814 | AE37: 37 | AF37: 925 | AH37: 37 | AI37: 925 | AK37: 37 | AL37: 777 | AN37: 37 | AO37: 666
A38: =+$C$4&B38 -> Véhicules neufsEntretien stock | B38: Entretien stock | D38: 61.617647 | E38: 16760 | G38: 65 | H38: 975 | J38: 66.538462 | K38: 865 | M38: 61 | N38: 1525 | P38: 59.6875 | Q38: 1910 | S38: 59.166667 | T38: 2130 | V38: 61.521739 | W38: 1415 | Y38: 63.823529 | Z38: 1085 | AB38: 61.818182 | AC38: 1360 | AE38: 61 | AF38: 1525 | AH38: 61 | AI38: 1525 | AK38: 62.142857 | AL38: 1305 | AN38: 63.333333 | AO38: 1140
A39: =+$C$4&B39 -> Véhicules neufsPublicité 1 | B39: Publicité 1 | D39: 513.97059 | E39: 139800 | G39: 513.97059 | H39: 7709.5588 | J39: 513.97059 | K39: 6681.6176 | M39: 513.97059 | N39: 12849.265 | P39: 513.97059 | Q39: 16447.059 | S39: 513.97059 | T39: 18502.941 | V39: 513.97059 | W39: 11821.324 | Y39: 513.97059 | Z39: 8737.5 | AB39: 513.97059 | AC39: 11307.353 | AE39: 513.97059 | AF39: 12849.265 | AH39: 513.97059 | AI39: 12849.265 | AK39: 513.97059 | AL39: 10793.382 | AN39: 513.97059 | AO39: 9251.4706
A40: =+$C$4&B40 -> Véhicules neufsIntérêt de gros | B40: Intérêt de gros | D40: 1186.9396 | E40: 322847.56 | G40: 1702.2597 | H40: 25533.896 | J40: 1969.1431 | K40: 25598.861 | M40: 1230.2634 | N40: 30756.585 | P40: 974.98576 | Q40: 31199.544 | S40: 835.15872 | T40: 30065.714 | V40: 1107.6277 | W40: 25475.438 | Y40: 1525.2108 | Z40: 25928.583 | AB40: 1242.6971 | AC40: 27339.336 | AE40: 1069.1875 | AF40: 26729.688 | AH40: 1057.7885 | AI40: 26444.712 | AK40: 1149.0993 | AL40: 24131.086 | AN40: 1313.5622 | AO40: 23644.12
A41: =+$C$4&B41 -> Véhicules neufs[...] | B41: [...] | D41: 0 | E41: 0 | G41: 0 | J41: 0 | M41: 0 | P41: 0 | S41: 0 | V41: 0 | Y41: 0 | AB41: 0 | AE41: 0 | AH41: 0 | AK41: 0 | AN41: 0
A42: =+$C$4&B42 -> Véhicules neufs[...] | B42: [...] | D42: 0 | E42: 0 | G42: 0 | J42: 0 | M42: 0 | P42: 0 | S42: 0 | V42: 0 | Y42: 0 | AB42: 0 | AE42: 0 | AH42: 0 | AK42: 0 | AN42: 0
A43: =+$C$4&B43 -> Véhicules neufs[...] | B43: [...] | D43: 0 | E43: 0 | G43: 0 | J43: 0 | M43: 0 | P43: 0 | S43: 0 | V43: 0 | Y43: 0 | AB43: 0 | AE43: 0 | AH43: 0 | AK43: 0 | AN43: 0
A44: =+$C$4&B44 -> Véhicules neufsTOTAL VARIABLES | B44: TOTAL VARIABLES | C44: % brut | D44: 0.63485498 | E44: 940080.56 | F44: % brut | G44: 0.7425434 | H44: 60789.157 | I44: % brut | J44: 0.79930311 | K44: 55941.285 | L44: % brut | M44: 0.63849771 | N44: 87203.959 | O44: % brut | P44: 0.5884727 | Q44: 102706.15 | R44: % brut | S44: 0.56348778 | T44: 109734.66 | U44: % brut | V44: 0.61840269 | W44: 77591.727 | X44: % brut | Y44: 0.70283864 | Z44: 65609.234 | AA44: % brut | AB44: 0.6446435 | AC44: 77280.871 | AD44: % brut | AE44: 0.61227921 | AF44: 83088.116 | AG44: % brut | AH44: 0.60888823 | AI44: 83144.89 | AJ44: % brut | AK44: 0.63204636 | AL44: 71461.18 | AM44: % brut | AN44: 0.66152629 | AO44: 65529.333
A45: =+$C$4&B45 -> Véhicules neufsSalaires cadres | B45: Salaires cadres | E45: 150304.6 | H45: 12763.084 | K45: 12192.602 | N45: 12382.763 | Q45: 12572.924 | T45: 12572.924 | W45: 12382.763 | Z45: 12763.084 | AC45: 12382.763 | AF45: 12572.924 | AI45: 12763.084 | AL45: 12192.602 | AO45: 12763.084
A46: =+$C$4&B46 -> Véhicules neufsSalaires commis | B46: Salaires commis | E46: 115883.2 | H46: 10583.905 | K46: 9514.1736 | N46: 9192.4172 | Q46: 9200.6609 | T46: 9035.6609 | W46: 9357.4172 | Z46: 10473.905 | AC46: 9412.4172 | AF46: 9585.6609 | AI46: 10033.905 | AL46: 9074.1736 | AO46: 10418.905
A47: =+$C$4&B47 -> Véhicules neufsSalaires autres | B47: Salaires autres | E47: 4104 | H47: 342 | K47: 342 | N47: 342 | Q47: 342 | T47: 342 | W47: 342 | Z47: 342 | AC47: 342 | AF47: 342 | AI47: 342 | AL47: 342 | AO47: 342
A48: =+$C$4&B48 -> Véhicules neufsSalaires spécialistes | B48: Salaires spécialistes | E48: 0 | H48: 0 | K48: 0 | N48: 0 | Q48: 0 | T48: 0 | W48: 0 | Z48: 0 | AC48: 0 | AF48: 0 | AI48: 0 | AL48: 0 | AO48: 0
A49: =+$C$4&B49 -> Véhicules neufs[...] | B49: [...] | E49: 0 | H49: 0 | K49: 0 | N49: 0 | Q49: 0 | T49: 0 | W49: 0 | Z49: 0 | AC49: 0 | AF49: 0 | AI49: 0 | AL49: 0 | AO49: 0
A50: =+$C$4&B50 -> Véhicules neufs[...] | B50: [...] | E50: 0 | H50: 0 | K50: 0 | N50: 0 | Q50: 0 | T50: 0 | W50: 0 | Z50: 0 | AC50: 0 | AF50: 0 | AI50: 0 | AL50: 0 | AO50: 0
A51: =+$C$4&B51 -> Véhicules neufs[...] | B51: [...] | E51: 0 | H51: 0 | K51: 0 | N51: 0 | Q51: 0 | T51: 0 | W51: 0 | Z51: 0 | AC51: 0 | AF51: 0 | AI51: 0 | AL51: 0 | AO51: 0
A52: =+$C$4&B52 -> Véhicules neufsSalaires en absences | B52: Salaires en absences | E52: 88637.498 | H52: 7667.9796 | K52: 4479.9346 | N52: 6075.5394 | Q52: 8894.4548 | T52: 9483.1921 | W52: 7379.722 | Z52: 6666.8064 | AC52: 5700.37 | AF52: 7774.7124 | AI52: 7912.4149 | AL52: 5460.6459 | AO52: 11141.726
A53: =+$C$4&B53 -> Véhicules neufsDéduction à la source | B53: Déduction à la source | E53: 101920.84 | H53: 9462.3847 | K53: 7766.8432 | N53: 9179.3476 | Q53: 10383.075 | T53: 10868.251 | W53: 8488.1399 | Z53: 7668.146 | AC53: 8147.8115 | AF53: 8275.1095 | AI53: 8082.0911 | AL53: 6914.8396 | AO53: 6684.7959
A54: =+$C$4&B54 -> Véhicules neufsBénéfices marginaux | B54: Bénéfices marginaux | E54: 53342.478 | H54: 3806.7065 | K54: 3408.6459 | N54: 4622.693 | Q54: 5344.2295 | T54: 5697.9721 | W54: 4434.1029 | Z54: 4005.7479 | AC54: 4337.2381 | AF54: 4671.4328 | AI54: 4754.1712 | AL54: 4154.8393 | AO54: 4104.6992
A55: =+$C$4&B55 -> Véhicules neufsCsst | B55: Csst | E55: 11430.531 | H55: 815.72282 | K55: 730.42412 | N55: 990.57708 | Q55: 1145.192 | T55: 1220.994 | W55: 950.16492 | Z55: 858.37455 | AC55: 929.40816 | AF55: 1001.0213 | AI55: 1018.751 | AL55: 890.3227 | AO55: 879.57841
A56: =+$C$4&B56 -> Véhicules neufs[...] | B56: [...] | E56: 0
A57: =+$C$4&B57 -> Véhicules neufsTOTAL PERSONNEL | B57: TOTAL PERSONNEL | C57: % brut | D57: 0.3549637 | E57: 525623.14 | F57: % brut | G57: 0.55507426 | H57: 45441.783 | I57: % brut | J57: 0.54916353 | K57: 38434.623 | L57: % brut | M57: 0.31326949 | N57: 42785.337 | O57: % brut | P57: 0.2743513 | Q57: 47882.535 | R57: % brut | S57: 0.25274993 | T57: 49220.994 | U57: % brut | V57: 0.34537256 | W57: 43334.31 | X57: % brut | Y57: 0.45825983 | Z57: 42778.064 | AA57: % brut | AB57: 0.34410635 | AC57: 41252.008 | AD57: % brut | AE57: 0.32587979 | AF57: 44222.861 | AG57: % brut | AH57: 0.32885952 | AI57: 44906.417 | AJ57: % brut | AK57: 0.34520007 | AL57: 39029.423 | AM57: % brut | AN57: 0.46775512 | AO57: 46334.788
A58: =+$C$4&B58 -> Véhicules neufsPublicité 2 | B58: Publicité 2 | E58: 0 | H58: 0 | K58: 0 | N58: 0 | Q58: 0 | T58: 0 | W58: 0 | Z58: 0 | AC58: 0 | AF58: 0 | AI58: 0 | AL58: 0 | AO58: 0
A59: =+$C$4&B59 -> Véhicules neufsService gratuit 2 | B59: Service gratuit 2 | E59: 0 | H59: 0 | K59: 0 | N59: 0 | Q59: 0 | T59: 0 | W59: 0 | Z59: 0 | AC59: 0 | AF59: 0 | AI59: 0 | AL59: 0 | AO59: 0
A60: =+$C$4&B60 -> Véhicules neufsFrais véhicules de cie | B60: Frais véhicules de cie | E60: 79451.2 | H60: 6620.9333 | K60: 6620.9333 | N60: 6620.9333 | Q60: 6620.9333 | T60: 6620.9333 | W60: 6620.9333 | Z60: 6620.9333 | AC60: 6620.9333 | AF60: 6620.9333 | AI60: 6620.9333 | AL60: 6620.9333 | AO60: 6620.9333
A61: =+$C$4&B61 -> Véhicules neufsInformatique | B61: Informatique | E61: 58539.6 | H61: 4878.3 | K61: 4878.3 | N61: 4878.3 | Q61: 4878.3 | T61: 4878.3 | W61: 4878.3 | Z61: 4878.3 | AC61: 4878.3 | AF61: 4878.3 | AI61: 4878.3 | AL61: 4878.3 | AO61: 4878.3
A62: =+$C$4&B62 -> Véhicules neufsFrais de déplacement | B62: Frais de déplacement | E62: 9900 | H62: 825 | K62: 825 | N62: 825 | Q62: 825 | T62: 825 | W62: 825 | Z62: 825 | AC62: 825 | AF62: 825 | AI62: 825 | AL62: 825 | AO62: 825
A63: =+$C$4&B63 -> Véhicules neufsServices extérieurs | B63: Services extérieurs | E63: 39776.4 | H63: 3314.7 | K63: 3314.7 | N63: 3314.7 | Q63: 3314.7 | T63: 3314.7 | W63: 3314.7 | Z63: 3314.7 | AC63: 3314.7 | AF63: 3314.7 | AI63: 3314.7 | AL63: 3314.7 | AO63: 3314.7
A64: =+$C$4&B64 -> Véhicules neufsFournitures autres | B64: Fournitures autres | E64: 480 | H64: 40 | K64: 40 | N64: 40 | Q64: 40 | T64: 40 | W64: 40 | Z64: 40 | AC64: 40 | AF64: 40 | AI64: 40 | AL64: 40 | AO64: 40
A65: =+$C$4&B65 -> Véhicules neufsUniformes | B65: Uniformes | E65: 360 | H65: 30 | K65: 30 | N65: 30 | Q65: 30 | T65: 30 | W65: 30 | Z65: 30 | AC65: 30 | AF65: 30 | AI65: 30 | AL65: 30 | AO65: 30
A66: =+$C$4&B66 -> Véhicules neufsPapeterie | B66: Papeterie | E66: 8505 | H66: 708.75 | K66: 708.75 | N66: 708.75 | Q66: 708.75 | T66: 708.75 | W66: 708.75 | Z66: 708.75 | AC66: 708.75 | AF66: 708.75 | AI66: 708.75 | AL66: 708.75 | AO66: 708.75
A67: =+$C$4&B67 -> Véhicules neufsTéléphone | B67: Téléphone | E67: 2524.8 | H67: 210.4 | K67: 210.4 | N67: 210.4 | Q67: 210.4 | T67: 210.4 | W67: 210.4 | Z67: 210.4 | AC67: 210.4 | AF67: 210.4 | AI67: 210.4 | AL67: 210.4 | AO67: 210.4
A68: =+$C$4&B68 -> Véhicules neufsFrais postaux | B68: Frais postaux | E68: 2430 | H68: 202.5 | K68: 202.5 | N68: 202.5 | Q68: 202.5 | T68: 202.5 | W68: 202.5 | Z68: 202.5 | AC68: 202.5 | AF68: 202.5 | AI68: 202.5 | AL68: 202.5 | AO68: 202.5
A69: =+$C$4&B69 -> Véhicules neufsDivers | B69: Divers | E69: 9401.4 | H69: 783.45 | K69: 783.45 | N69: 783.45 | Q69: 783.45 | T69: 783.45 | W69: 783.45 | Z69: 783.45 | AC69: 783.45 | AF69: 783.45 | AI69: 783.45 | AL69: 783.45 | AO69: 783.45
... A71: =+$C$4&B71 -> Véhicules neufsFrais bancaires | B71: Frais bancaires | E71: 35336.858 | H71: 1978.1525 | K71: 1924.5835 | N71: 3086.1064 | Q71: 4083.397 | T71: 4231.9164 | W71: 2960.1437 | Z71: 2687.6326 | AC71: 3142.637 | AF71: 3122.0301 | AI71: 3106.8634 | AL71: 2870.8288 | AO71: 2142.5664
A72: =+$C$4&B72 -> Véhicules neufs[...] | B72: [...] | E72: 0
A73: =+$C$4&B73 -> Véhicules neufs[...] | B73: [...] | E73: 0
A74: =+$C$4&B74 -> Véhicules neufs[...] | B74: [...] | E74: 0
A75: =+$C$4&B75 -> Véhicules neufsTOTAL SEMI-FIXES | B75: TOTAL SEMI-FIXES | C75: % brut | D75: 0.17112836 | E75: 253403.46 | F75: % brut | G75: 0.24613804 | H75: 20150.369 | I75: % brut | J75: 0.28714812 | K75: 20096.8 | L75: % brut | M75: 0.15565108 | N75: 21258.323 | O75: % brut | P75: 0.1275174 | Q75: 22255.614 | R75: % brut | S75: 0.11504528 | T75: 22404.133 | U75: % brut | V75: 0.16842399 | W75: 21132.361 | X75: % brut | Y75: 0.22346105 | Z75: 20859.849 | AA75: % brut | AB75: 0.17779927 | AC75: 21314.854 | AD75: % brut | AE75: 0.15691804 | AF75: 21294.247 | AG75: % brut | AH75: 0.15583136 | AI75: 21279.08 | AJ75: % brut | AK75: 0.18611756 | AL75: 21043.046 | AM75: % brut | AN75: 0.20508012 | AO75: 20314.783
A76: =+$C$4&B76 -> Véhicules neufs
A77: =+$C$4&B77 -> Véhicules neufsTOTAL DES DÉPENSES | B77: TOTAL DES DÉPENSES | C77: % brut | D77: 1.160947 | E77: 1719107.2 | F77: % brut | G77: 1.5437557 | H77: 126381.31 | I77: % brut | J77: 1.6356148 | K77: 114472.71 | L77: % brut | M77: 1.1074183 | N77: 151247.62 | O77: % brut | P77: 0.9903414 | Q77: 172844.3 | R77: % brut | S77: 0.93128299 | T77: 181359.79 | U77: % brut | V77: 1.1321992 | W77: 142058.4 | X77: % brut | Y77: 1.3845595 | Z77: 129247.15 | AA77: % brut | AB77: 1.1665491 | AC77: 139847.73 | AD77: % brut | AE77: 1.095077 | AF77: 148605.22 | AG77: % brut | AH77: 1.0935791 | AI77: 149330.39 | AJ77: % brut | AK77: 1.163364 | AL77: 131533.65 | AM77: % brut | AN77: 1.3343615 | AO77: 132178.9
A78: =+$C$4&B78 -> Véhicules neufsRBSC neuf | B78: RBSC neuf | E78: 435312.81 | H78: 23744.335 | K78: 20578.424 | N78: 41156.847 | Q78: 52237.537 | T78: 56986.404 | W78: 36407.98 | Z78: 26910.246 | AC78: 34825.025 | AF78: 41156.847 | AI78: 39573.892 | AL78: 33242.069 | AO78: 28493.202
A79: =+$C$4&B79 -> Véhicules neufsProgramme neuf 2 | B79: Programme neuf 2 | E79: 0 | H79: 0 | K79: 0 | N79: 0 | Q79: 0 | T79: 0 | W79: 0 | Z79: 0 | AC79: 0 | AF79: 0 | AI79: 0 | AL79: 0 | AO79: 0
A80: =+$C$4&B80 -> Véhicules neufsProgramme neuf 3 | B80: Programme neuf 3 | E80: 0 | H80: 0 | K80: 0 | N80: 0 | Q80: 0 | T80: 0 | W80: 0 | Z80: 0 | AC80: 0 | AF80: 0 | AI80: 0 | AL80: 0 | AO80: 0
A81: =+$C$4&B81 -> Véhicules neufsHoldbacks | B81: Holdbacks | E81: 470608.44 | H81: 25669.551 | K81: 22246.944 | N81: 44493.889 | Q81: 56473.013 | T81: 61606.923 | W81: 39359.979 | Z81: 29092.158 | AC81: 37648.675 | AF81: 44493.889 | AI81: 42782.585 | AL81: 35937.372 | AO81: 30803.462
A82: =+$C$4&B82 -> Véhicules neufs[...] | B82: [...] | E82: 0 | H82: 0 | K82: 0 | N82: 0 | Q82: 0 | T82: 0 | W82: 0 | Z82: 0 | AC82: 0 | AF82: 0 | AI82: 0 | AL82: 0 | AO82: 0
A83: =+$C$4&B83 -> Véhicules neufs[...] | B83: [...] | E83: 0 | H83: 0 | K83: 0 | N83: 0 | Q83: 0 | T83: 0 | W83: 0 | Z83: 0 | AC83: 0 | AF83: 0 | AI83: 0 | AL83: 0 | AO83: 0
A84: =+$C$4&B84 -> Véhicules neufs[...] | B84: [...] | E84: 0 | H84: 0 | K84: 0 | N84: 0 | Q84: 0 | T84: 0 | W84: 0 | Z84: 0 | AC84: 0 | AF84: 0 | AI84: 0 | AL84: 0 | AO84: 0
A85: =+$C$4&B85 -> Véhicules neufsFrais administration | B85: Frais administration | E85: 159412.4 | H85: 8791.125 | K85: 7618.975 | N85: 14651.875 | Q85: 18754.4 | T85: 21098.7 | W85: 13479.725 | Z85: 9963.275 | AC85: 12893.65 | AF85: 14651.875 | AI85: 14651.875 | AL85: 12307.575 | AO85: 10549.35
A86: =+$C$4&B86 -> Véhicules neufsAUTRES REVENUS | B86: AUTRES REVENUS | E86: 1065333.6 | H86: 58205.011 | K86: 50444.343 | N86: 100302.61 | Q86: 127464.95 | T86: 139692.03 | W86: 89247.684 | Z86: 65965.679 | AC86: 85367.35 | AF86: 100302.61 | AI86: 97008.352 | AL86: 81487.016 | AO86: 69846.013
A87: =+$C$4&B87 -> Véhicules neufs
A88: =+$C$4&B88 -> Véhicules neufsPROFIT DÉPARTEMENTAL | B88: PROFIT DÉPARTEMENTAL | E88: 827006.48 | H88: 13689.835 | K88: 5959.2077 | N88: 85631.768 | Q88: 129150.66 | T88: 153074.11 | W88: 72660.486 | Z88: 30067.46 | AC88: 65401.181 | AF88: 87400.372 | AI88: 84229.94 | AL88: 63016.561 | AO88: 36724.9
B92: Budget 2025 | C92: Véhicules usagés
B94: Mois | C94: 2025 | F94: Janvier | I94: Février | L94: Mars | O94: Avril | R94: Mai | U94: Juin | X94: Juillet | AA94: Août | AD94: Septembre | AG94: Octobre | AJ94: Novembre | AM94: Décembre
C95: UNITE | D95: $P/UNITE | E95: $PROFITS | F95: UNITE | G95: $P/UNITE | H95: $PROFITS | I95: UNITE | J95: $P/UNITE | K95: $PROFITS | L95: UNITE | M95: $P/UNITE | N95: $PROFITS | O95: UNITE | P95: $P/UNITE | Q95: $PROFITS | R95: UNITE | S95: $P/UNITE | T95: $PROFITS | U95: UNITE | V95: $P/UNITE | W95: $PROFITS | X95: UNITE | Y95: $P/UNITE | Z95: $PROFITS | AA95: UNITE | AB95: $P/UNITE | AC95: $PROFITS | AD95: UNITE | AE95: $P/UNITE | AF95: $PROFITS | AG95: UNITE | AH95: $P/UNITE | AI95: $PROFITS | AJ95: UNITE | AK95: $P/UNITE | AL95: $PROFITS | AM95: UNITE | AN95: $P/UNITE | AO95: $PROFITS
A96: =+$C$92&B96 -> Véhicules usagésVentes nettes | B96: Ventes nettes | E96: 17054706 | H96: 950117.65 | K96: 1083647.1 | N96: 1377176.5 | Q96: 2001764.7 | T96: 1804235.3 | W96: 1409176.5 | Z96: 1606705.9 | AC96: 1804235.3 | AF96: 1409176.5 | AI96: 1377176.5 | AL96: 1345176.5 | AO96: 886117.65
A97: =+$C$92&B97 -> Véhicules usagésCertifié | B97: Certifié | C97: 75 | D97: 2300 | E97: 172500 | F97: 4 | G97: 2300 | H97: 9200 | I97: 5 | J97: 2300 | K97: 11500 | L97: 6 | M97: 2300 | N97: 13800 | O97: 9 | P97: 2300 | Q97: 20700 | R97: 8 | S97: 2300 | T97: 18400 | U97: 6 | V97: 2300 | W97: 13800 | X97: 7 | Y97: 2300 | Z97: 16100 | AA97: 8 | AB97: 2300 | AC97: 18400 | AD97: 6 | AE97: 2300 | AF97: 13800 | AG97: 6 | AH97: 2300 | AI97: 13800 | AJ97: 6 | AK97: 2300 | AL97: 13800 | AM97: 4 | AN97: 2300 | AO97: 9200
A98: =+$C$92&B98 -> Véhicules usagésNon Certifié | B98: Non Certifié | C98: 75 | D98: 1600 | E98: 120000 | F98: 4 | G98: 1600 | H98: 6400 | I98: 5 | J98: 1600 | K98: 8000 | L98: 6 | M98: 1600 | N98: 9600 | O98: 9 | P98: 1600 | Q98: 14400 | R98: 8 | S98: 1600 | T98: 12800 | U98: 6 | V98: 1600 | W98: 9600 | X98: 7 | Y98: 1600 | Z98: 11200 | AA98: 8 | AB98: 1600 | AC98: 12800 | AD98: 6 | AE98: 1600 | AF98: 9600 | AG98: 6 | AH98: 1600 | AI98: 9600 | AJ98: 6 | AK98: 1600 | AL98: 9600 | AM98: 4 | AN98: 1600 | AO98: 6400
A99: =+$C$92&B99 -> Véhicules usagésAutres Marques | B99: Autres Marques | C99: 75 | D99: 1500 | E99: 112500 | F99: 4 | G99: 1500 | H99: 6000 | I99: 5 | J99: 1500 | K99: 7500 | L99: 6 | M99: 1500 | N99: 9000 | O99: 9 | P99: 1500 | Q99: 13500 | R99: 8 | S99: 1500 | T99: 12000 | U99: 6 | V99: 1500 | W99: 9000 | X99: 7 | Y99: 1500 | Z99: 10500 | AA99: 8 | AB99: 1500 | AC99: 12000 | AD99: 6 | AE99: 1500 | AF99: 9000 | AG99: 6 | AH99: 1500 | AI99: 9000 | AJ99: 6 | AK99: 1500 | AL99: 9000 | AM99: 4 | AN99: 1500 | AO99: 6000
A100: =+$C$92&B100 -> Véhicules usagésTotal Usagés | B100: Total Usagés | C100: 225 | D100: 1800 | E100: 405000 | F100: 12 | G100: 1800 | H100: 21600 | I100: 15 | J100: 1800 | K100: 27000 | L100: 18 | M100: 1800 | N100: 32400 | O100: 27 | P100: 1800 | Q100: 48600 | R100: 24 | S100: 1800 | T100: 43200 | U100: 18 | V100: 1800 | W100: 32400 | X100: 21 | Y100: 1800 | Z100: 37800 | AA100: 24 | AB100: 1800 | AC100: 43200 | AD100: 18 | AE100: 1800 | AF100: 32400 | AG100: 18 | AH100: 1800 | AI100: 32400 | AJ100: 18 | AK100: 1800 | AL100: 32400 | AM100: 12 | AN100: 1800 | AO100: 21600
A101: =+$C$92&B101 -> Véhicules usagés
A102: =+$C$92&B102 -> Véhicules usagés | F102: 0 | H102: 0
A103: =+$C$92&B103 -> Véhicules usagésVentes au Gros | B103: Ventes au Gros | C103: 220 | D103: 350 | E103: 77000 | F103: 13 | G103: 350 | H103: 4550 | I103: 13 | J103: 350 | K103: 4550 | L103: 18 | M103: 350 | N103: 6300 | O103: 25 | P103: 350 | Q103: 8750 | R103: 23 | S103: 350 | T103: 8050 | U103: 19 | V103: 350 | W103: 6650 | X103: 21 | Y103: 350 | Z103: 7350 | AA103: 23 | AB103: 350 | AC103: 8050 | AD103: 19 | AE103: 350 | AF103: 6650 | AG103: 18 | AH103: 350 | AI103: 6300 | AJ103: 17 | AK103: 350 | AL103: 5950 | AM103: 11 | AN103: 350 | AO103: 3850
A104: =+$C$92&B104 -> Véhicules usagés
A105: =+$C$92&B105 -> Véhicules usagésRev. Finances | B105: Rev. Finances | D105: 380 | E105: 85500 | G105: 380 | H105: 4560 | J105: 380 | K105: 5700 | M105: 380 | N105: 6840 | P105: 380 | Q105: 10260 | S105: 380 | T105: 9120 | V105: 380 | W105: 6840 | Y105: 380 | Z105: 7980 | AB105: 380 | AC105: 9120 | AE105: 380 | AF105: 6840 | AH105: 380 | AI105: 6840 | AK105: 380 | AL105: 6840 | AN105: 380 | AO105: 4560
A106: =+$C$92&B106 -> Véhicules usagésRev. Protections | B106: Rev. Protections | D106: 850 | E106: 191250 | G106: 850 | H106: 10200 | J106: 850 | K106: 12750 | M106: 850 | N106: 15300 | P106: 850 | Q106: 22950 | S106: 850 | T106: 20400 | V106: 850 | W106: 15300 | Y106: 850 | Z106: 17850 | AB106: 850 | AC106: 20400 | AE106: 850 | AF106: 15300 | AH106: 850 | AI106: 15300 | AK106: 850 | AL106: 15300 | AN106: 850 | AO106: 10200
...

Sheet Réel 2024
B1: ="Budget 2023 Mensuel"&" "&Parametres!$B$1 -> Budget 2023 Mensuel BMW Sherbrooke
B2: Mois | F2: =+IF(Parametres!$B$3=F$6,"X","") | G2: =+IF(Parametres!$B$3=F$6,"O","") | H2: =+IF(Parametres!$B$3=F$6,"U","") | I2: =+IF(Parametres!$B$3=I$6,"X","") | J2: =+IF(Parametres!$B$3=I$6,"O","") | K2: =+IF(Parametres!$B$3=I$6,"U","") | L2: =+IF(Parametres!$B$3=L$6,"X","") | M2: =+IF(Parametres!$B$3=L$6,"O","") | N2: =+IF(Parametres!$B$3=L$6,"U","") | O2: =+IF(Parametres!$B$3=O$6,"X","") -> X | P2: =+IF(Parametres!$B$3=O$6,"O","") -> O | Q2: =+IF(Parametres!$B$3=O$6,"U","") -> U | R2: =+IF(Parametres!$B$3=R$6,"X","") | S2: =+IF(Parametres!$B$3=R$6,"O","") | T2: =+IF(Parametres!$B$3=R$6,"U","") | U2: =+IF(Parametres!$B$3=U$6,"X","") | V2: =+IF(Parametres!$B$3=U$6,"O","") | W2: =+IF(Parametres!$B$3=U$6,"U","") | X2: =+IF(Parametres!$B$3=X$6,"X","") | Y2: =+IF(Parametres!$B$3=X$6,"O","") | Z2: =+IF(Parametres!$B$3=X$6,"U","") | AA2: =+IF(Parametres!$B$3=AA$6,"X","") | AB2: =+IF(Parametres!$B$3=AA$6,"O","") | AC2: =+IF(Parametres!$B$3=AA$6,"U","") | AD2: =+IF(Parametres!$B$3=AD$6,"X","") | AE2: =+IF(Parametres!$B$3=AD$6,"O","") | AF2: =+IF(Parametres!$B$3=AD$6,"U","") | AG2: =+IF(Parametres!$B$3=AG$6,"X","") | AH2: =+IF(Parametres!$B$3=AG$6,"O","") | AI2: =+IF(Parametres!$B$3=AG$6,"U","") | AJ2: =+IF(Parametres!$B$3=AJ$6,"X","") | AK2: =+IF(Parametres!$B$3=AJ$6,"O","") | AL2: =+IF(Parametres!$B$3=AJ$6,"U","") | AM2: =+IF(Parametres!$B$3=AM$6,"X","") | AN2: =+IF(Parametres!$B$3=AM$6,"O","") | AO2: =+IF(Parametres!$B$3=AM$6,"U","")
B3: YTD | F3: =+IF(VLOOKUP(F$6,Parametres!$K$3:$N$14,4,0)="X","X","") -> X | G3: =+IF(VLOOKUP(F$6,Parametres!$K$3:$N$14,4,0)="X","O","") -> O | H3: =+IF(VLOOKUP(F$6,Parametres!$K$3:$N$14,4,0)="X","U","") -> U | I3: =+IF(VLOOKUP(I$6,Parametres!$K$3:$N$14,4,0)="X","X","") -> X | J3: =+IF(VLOOKUP(I$6,Parametres!$K$3:$N$14,4,0)="X","O","") -> O | K3: =+IF(VLOOKUP(I$6,Parametres!$K$3:$N$14,4,0)="X","U","") -> U | L3: =+IF(VLOOKUP(L$6,Parametres!$K$3:$N$14,4,0)="X","X","") -> X | M3: =+IF(VLOOKUP(L$6,Parametres!$K$3:$N$14,4,0)="X","O","") -> O | N3: =+IF(VLOOKUP(L$6,Parametres!$K$3:$N$14,4,0)="X","U","") -> U | O3: =+IF(VLOOKUP(O$6,Parametres!$K$3:$N$14,4,0)="X","X","") -> X | P3: =+IF(VLOOKUP(O$6,Parametres!$K$3:$N$14,4,0)="X","O","") -> O | Q3: =+IF(VLOOKUP(O$6,Parametres!$K$3:$N$14,4,0)="X","U","") -> U | R3: =+IF(VLOOKUP(R$6,Parametres!$K$3:$N$14,4,0)="X","X","") | S3: =+IF(VLOOKUP(R$6,Parametres!$K$3:$N$14,4,0)="X","O","") | T3: =+IF(VLOOKUP(R$6,Parametres!$K$3:$N$14,4,0)="X","U","") | U3: =+IF(VLOOKUP(U$6,Parametres!$K$3:$N$14,4,0)="X","X","") | V3: =+IF(VLOOKUP(U$6,Parametres!$K$3:$N$14,4,0)="X","O","") | W3: =+IF(VLOOKUP(U$6,Parametres!$K$3:$N$14,4,0)="X","U","") | X3: =+IF(VLOOKUP(X$6,Parametres!$K$3:$N$14,4,0)="X","X","") | Y3: =+IF(VLOOKUP(X$6,Parametres!$K$3:$N$14,4,0)="X","O","") | Z3: =+IF(VLOOKUP(X$6,Parametres!$K$3:$N$14,4,0)="X","U","") | AA3: =+IF(VLOOKUP(AA$6,Parametres!$K$3:$N$14,4,0)="X","X","") | AB3: =+IF(VLOOKUP(AA$6,Parametres!$K$3:$N$14,4,0)="X","O","") | AC3: =+IF(VLOOKUP(AA$6,Parametres!$K$3:$N$14,4,0)="X","U","") | AD3: =+IF(VLOOKUP(AD$6,Parametres!$K$3:$N$14,4,0)="X","X","") | AE3: =+IF(VLOOKUP(AD$6,Parametres!$K$3:$N$14,4,0)="X","O","") | AF3: =+IF(VLOOKUP(AD$6,Parametres!$K$3:$N$14,4,0)="X","U","") | AG3: =+IF(VLOOKUP(AG$6,Parametres!$K$3:$N$14,4,0)="X","X","") | AH3: =+IF(VLOOKUP(AG$6,Parametres!$K$3:$N$14,4,0)="X","O","") | AI3: =+IF(VLOOKUP(AG$6,Parametres!$K$3:$N$14,4,0)="X","U","") | AJ3: =+IF(VLOOKUP(AJ$6,Parametres!$K$3:$N$14,4,0)="X","X","") | AK3: =+IF(VLOOKUP(AJ$6,Parametres!$K$3:$N$14,4,0)="X","O","") | AL3: =+IF(VLOOKUP(AJ$6,Parametres!$K$3:$N$14,4,0)="X","U","") | AM3: =+IF(VLOOKUP(AM$6,Parametres!$K$3:$N$14,4,0)="X","X","") | AN3: =+IF(VLOOKUP(AM$6,Parametres!$K$3:$N$14,4,0)="X","O","") | AO3: =+IF(VLOOKUP(AM$6,Parametres!$K$3:$N$14,4,0)="X","U","")
B4: Réel 2024 | C4: Véhicules neufs
B6: Mois | C6: 2024 | F6: Janvier | I6: Février | L6: Mars | O6: Avril | R6: Mai | U6: Juin | X6: Juillet | AA6: Août | AD6: Septembre | AG6: Octobre | AJ6: Novembre | AM6: Décembre
C7: UNITE | D7: $P/UNITE | E7: $PROFITS | F7: UNITE | G7: $P/UNITE | H7: $PROFITS | I7: UNITE | J7: $P/UNITE | K7: $PROFITS | L7: UNITE | M7: $P/UNITE | N7: $PROFITS | O7: UNITE | P7: $P/UNITE | Q7: $PROFITS | R7: UNITE | S7: $P/UNITE | T7: $PROFITS | U7: UNITE | V7: $P/UNITE | W7: $PROFITS | X7: UNITE | Y7: $P/UNITE | Z7: $PROFITS | AA7: UNITE | AB7: $P/UNITE | AC7: $PROFITS | AD7: UNITE | AE7: $P/UNITE | AF7: $PROFITS | AG7: UNITE | AH7: $P/UNITE | AI7: $PROFITS | AJ7: UNITE | AK7: $P/UNITE | AL7: $PROFITS | AM7: UNITE | AN7: $P/UNITE | AO7: $PROFITS
A8: =+$C$4&B8 -> Véhicules neufsVentes nettes | B8: Ventes nettes | E8: 25487207 | H8: 926822.67 | K8: 745667.64 | N8: 1972302.3 | Q8: 2814437.6 | T8: 3270847.4 | W8: 1710445.6 | Z8: 1425137.4 | AC8: 1468150.1 | AF8: 3148461.5 | AI8: 2092480.4 | AL8: 3424221 | AO8: 2488233.6
A9: =+$C$4&B9 -> Véhicules neufsAutos détail | B9: Autos détail | C9: 87 | D9: 5158.778 | E9: 448813.69 | F9: 2 | G9: 4853.565 | H9: 9707.13 | I9: 5 | J9: 4773.302 | K9: 23866.51 | L9: 4 | M9: 6596.215 | N9: 26384.86 | O9: 13 | P9: 5336.7323 | Q9: 69377.52 | R9: 12 | S9: 4900.445 | T9: 58805.34 | U9: 7 | V9: 4333.9529 | W9: 30337.67 | X9: 0 | Y9: 0 | Z9: -205.85 | AA9: 8 | AB9: 2390.5312 | AC9: 19124.25 | AD9: 5 | AE9: 5369.06 | AF9: 26845.3 | AG9: 10 | AH9: 5653.279 | AI9: 56532.79 | AJ9: 9 | AK9: 5377.2044 | AL9: 48394.84 | AM9: 12 | AN9: 6636.9442 | AO9: 79643.33
A10: =+$C$4&B10 -> Véhicules neufsCamions détail | B10: Camions détail | C10: 142 | D10: 4574.8696 | E10: 649631.49 | F10: 4 | G10: 6340.385 | H10: 25361.54 | I10: 1 | J10: 7866.05 | K10: 7866.05 | L10: 12 | M10: 4793.2275 | N10: 57518.73 | O10: 12 | P10: 4634.92 | Q10: 55619.04 | R10: 22 | S10: 4523.4468 | T10: 99515.83 | U10: 10 | V10: 4305.352 | W10: 43053.52 | X10: 13 | Y10: 4541.1208 | Z10: 59034.57 | AA10: 4 | AB10: 4085.98 | AC10: 16343.92 | AD10: 17 | AE10: 5159.5535 | AF10: 87712.41 | AG10: 13 | AH10: 4282.34 | AI10: 55670.42 | AJ10: 23 | AK10: 3739.0257 | AL10: 85997.59 | AM10: 11 | AN10: 5085.2609 | AO10: 55937.87
A11: =+$C$4&B11 -> Véhicules neufsSprinter | B11: Sprinter | C11: 0 | D11: 0 | E11: 0 | F11: 0 | G11: 0 | H11: 0 | I11: 0 | J11: 0 | K11: 0 | L11: 0 | M11: 0 | N11: 0 | O11: 0 | P11: 0 | Q11: 0 | R11: 0 | S11: 0 | T11: 0 | U11: 0 | V11: 0 | W11: 0 | X11: 0 | Y11: 0 | Z11: 0 | AA11: 0 | AB11: 0 | AC11: 0 | AD11: 0 | AE11: 0 | AF11: 0 | AG11: 0 | AH11: 0 | AI11: 0 | AJ11: 0 | AK11: 0 | AL11: 0 | AM11: 0 | AN11: 0 | AO11: 0
A12: =+$C$4&B12 -> Véhicules neufsMoto détail | B12: Moto détail | C12: 0 | D12: 0 | E12: 0 | F12: 0 | G12: 0 | H12: 0 | I12: 0 | J12: 0 | K12: 0 | L12: 0 | M12: 0 | N12: 0 | O12: 0 | P12: 0 | Q12: 0 | R12: 0 | S12: 0 | T12: 0 | U12: 0 | V12: 0 | W12: 0 | X12: 0 | Y12: 0 | Z12: 0 | AA12: 0 | AB12: 0 | AC12: 0 | AD12: 0 | AE12: 0 | AF12: 0 | AG12: 0 | AH12: 0 | AI12: 0 | AJ12: 0 | AK12: 0 | AL12: 0 | AM12: 0 | AN12: 0 | AO12: 0
A13: =+$C$4&B13 -> Véhicules neufs[...] | B13: [...] | C13: 0 | D13: 0 | E13: 0 | G13: 0 | J13: 0 | M13: 0 | P13: 0 | S13: 0 | V13: 0 | Y13: 0 | AB13: 0 | AE13: 0 | AH13: 0 | AK13: 0 | AN13: 0
A14: =+$C$4&B14 -> Véhicules neufs[...] | B14: [...] | C14: 0 | D14: 0 | E14: 0 | G14: 0 | J14: 0 | M14: 0 | P14: 0 | S14: 0 | V14: 0 | Y14: 0 | AB14: 0 | AE14: 0 | AH14: 0 | AK14: 0 | AN14: 0
A15: =+$C$4&B15 -> Véhicules neufs[...] | B15: [...] | C15: 0 | D15: 0 | E15: 0 | G15: 0 | J15: 0 | M15: 0 | P15: 0 | S15: 0 | V15: 0 | Y15: 0 | AB15: 0 | AE15: 0 | AH15: 0 | AK15: 0 | AN15: 0
A16: =+$C$4&B16 -> Véhicules neufsTotal Neufs | B16: Total Neufs | C16: 229 | D16: 4796.7038 | E16: 1098445.2 | F16: 6 | G16: 5844.7783 | H16: 35068.67 | I16: 6 | J16: 5288.76 | K16: 31732.56 | L16: 16 | M16: 5243.9744 | N16: 83903.59 | O16: 25 | P16: 4999.8624 | Q16: 124996.56 | R16: 34 | S16: 4656.505 | T16: 158321.17 | U16: 17 | V16: 4317.1288 | W16: 73391.19 | X16: 13 | Y16: 4525.2862 | Z16: 58828.72 | AA16: 12 | AB16: 2955.6808 | AC16: 35468.17 | AD16: 22 | AE16: 5207.1686 | AF16: 114557.71 | AG16: 23 | AH16: 4878.4004 | AI16: 112203.21 | AJ16: 32 | AK16: 4199.7634 | AL16: 134392.43 | AM16: 23 | AN16: 5894.8348 | AO16: 135581.2
A17: =+$C$4&B17 -> Véhicules neufs
A18: =+$C$4&B18 -> Véhicules neufsEx-Démos et courtoisies | B18: Ex-Démos et courtoisies | C18: 36 | D18: 1369.8803 | E18: 49315.69 | F18: 2 | G18: 2993.705 | H18: 5987.41 | I18: 3 | J18: 1500 | K18: 4500 | L18: 5 | M18: 3624.56 | N18: 18122.8 | O18: 5 | P18: 3098.878 | Q18: 15494.39 | R18: 5 | S18: 588.606 | T18: 2943.03 | U18: 1 | V18: 1250 | W18: 1250 | X18: 1 | Y18: 10720.5 | Z18: 10720.5 | AA18: 2 | AB18: 1513.885 | AC18: 3027.77 | AD18: 7 | AE18: 403.89429 | AF18: 2827.26 | AG18: 0 | AH18: 0 | AI18: 0 | AJ18: 3 | AK18: -5578.1033 | AL18: -16734.31 | AM18: 2 | AN18: 588.42 | AO18: 1176.84
A19: =+$C$4&B19 -> Véhicules neufs
A20: =+$C$4&B20 -> Véhicules neufsFlottes | B20: Flottes | C20: 5 | D20: 2686.786 | E20: 13433.93 | F20: 1 | G20: 0 | H20: 0 | I20: 0 | J20: 0 | K20: 0 | L20: 0 | M20: 0 | N20: 0 | O20: 0 | P20: 0 | Q20: 0 | R20: 0 | S20: 0 | T20: 0 | U20: 0 | V20: 0 | W20: 0 | X20: 0 | Y20: 0 | Z20: 0 | AA20: 1 | AB20: 12964.17 | AC20: 12964.17 | AD20: 0 | AE20: 0 | AF20: 0 | AG20: 1 | AH20: 416.18 | AI20: 416.18 | AJ20: 2 | AK20: 26.79 | AL20: 53.58 | AM20: 0 | AN20: 0 | AO20: 0
A21: =+$C$4&B21 -> Véhicules neufs
A22: =+$C$4&B22 -> Véhicules neufsRachat bail | B22: Rachat bail | E22: 45746.46 | H22: 3995.96 | K22: 967.39 | N22: 2976.42 | Q22: 3495.39 | T22: 8901.11 | W22: 5993.9 | Z22: 5547.05 | AC22: 5620.95 | AF22: 2371.4 | AI22: 3371.01 | AL22: 999 | AO22: 1506.88
A23: =+$C$4&B23 -> Véhicules neufs
A24: =+$C$4&B24 -> Véhicules neufsRev. Finances | B24: Rev. Finances | D24: 11.362226 | E24: 3010.99 | G24: 0 | H24: 0 | J24: 0 | K24: 0 | M24: 135.6519 | N24: 2848.69 | P24: 0 | Q24: 0 | S24: -31.520769 | T24: -1229.31 | V24: 0 | W24: 0 | Y24: 0 | Z24: 0 | AB24: 0 | AC24: 0 | AE24: 5.1724138 | AF24: 150 | AH24: 0 | AI24: 0 | AK24: 0 | AL24: 0 | AN24: 49.6644 | AO24: 1241.61
A25: =+$C$4&B25 -> Véhicules neufsRev. Protections | B25: Rev. Protections | D25: 1161.4258 | E25: 307777.85 | G25: 1221.5 | H25: 9772 | J25: 1291.0111 | K25: 11619.1 | M25: 1102.7619 | N25: 23158 | P25: 1293.3413 | Q25: 38800.24 | S25: 1158.741 | T25: 45190.9 | V25: 1118.0944 | W25: 20125.7 | Y25: 1086 | Z25: 15204 | AB25: 1140.7714 | AC25: 15970.8 | AE25: 1040.6897 | AF25: 30180 | AH25: 854.43913 | AI25: 19652.1 | AK25: 1455.2969 | AL25: 50935.39 | AN25: 1086.7848 | AO25: 27169.62
A26: =+$C$4&B26 -> Véhicules neufsRev. Autres | B26: Rev. Autres | D26: 470.32717 | E26: 124636.7 | G26: 536.58625 | H26: 4292.69 | J26: 408.33333 | K26: 3675 | M26: 532.99524 | N26: 11192.9 | P26: 448.63467 | Q26: 13459.04 | S26: 440.92179 | T26: 17195.95 | V26: 536.78333 | W26: 9662.1 | Y26: 442.14286 | Z26: 6190 | AB26: 419.92857 | AC26: 5879 | AE26: 564.99621 | AF26: 16384.89 | AH26: 416.13652 | AI26: 9571.14 | AK26: 446.45571 | AL26: 15625.95 | AN26: 460.3216 | AO26: 11508.04
A27: =+$C$4&B27 -> Véhicules neufsTotal F&I | B27: Total F&I | C27: 265 | D27: 1643.1152 | E27: 435425.54 | F27: 8 | G27: 1758.0862 | H27: 14064.69 | I27: 9 | J27: 1699.3444 | K27: 15294.1 | L27: 21 | M27: 1771.409 | N27: 37199.59 | O27: 30 | P27: 1741.976 | Q27: 52259.28 | R27: 39 | S27: 1568.1421 | T27: 61157.54 | U27: 18 | V27: 1654.8778 | W27: 29787.8 | X27: 14 | Y27: 1528.1429 | Z27: 21394 | AA27: 14 | AB27: 1560.7 | AC27: 21849.8 | AD27: 29 | AE27: 1610.8583 | AF27: 46714.89 | AG27: 23 | AH27: 1270.5757 | AI27: 29223.24 | AJ27: 35 | AK27: 1901.7526 | AL27: 66561.34 | AM27: 25 | AN27: 1596.7708 | AO27: 39919.27
A28: =+$C$4&B28 -> Véhicules neufs
A29: =+$C$4&B29 -> Véhicules neufs
A30: =+$C$4&B30 -> Véhicules neufsTotal Dépt. Neufs | B30: Total Dépt. Neufs | C30: 270 | D30: 6082.84 | E30: 1642366.8 | F30: 9 | G30: 6568.5256 | H30: 59116.73 | I30: 9 | J30: 5832.6722 | K30: 52494.05 | L30: 21 | M30: 6771.5429 | N30: 142202.4 | O30: 30 | P30: 6541.5207 | Q30: 196245.62 | R30: 39 | S30: 5931.3551 | T30: 231322.85 | U30: 18 | V30: 6134.605 | W30: 110422.89 | X30: 14 | Y30: 6892.1621 | Z30: 96490.27 | AA30: 15 | AB30: 5262.0573 | AC30: 78930.86 | AD30: 29 | AE30: 5740.3883 | AF30: 166471.26 | AG30: 24 | AH30: 6050.5683 | AI30: 145213.64 | AJ30: 37 | AK30: 5007.3524 | AL30: 185272.04 | AM30: 25 | AN30: 7127.3676 | AO30: 178184.19
A31: =+$C$4&B31 -> Véhicules neufs
A32: =+$C$4&B32 -> Véhicules neufs
A33: =+$C$4&B33 -> Véhicules neufsDEPENSES | B33: DEPENSES
A34: =+$C$4&B34 -> Véhicules neufsComm. vendeurs | B34: Comm. vendeurs | C34: 0.29664052 | D34: 1284.8014 | E34: 340472.38 | F34: 0.33530405 | G34: 1720.7838 | H34: 13766.27 | I34: 0.28977555 | J34: 1166.59 | K34: 10499.31 | L34: 0.26922113 | M34: 1307.9838 | N34: 27467.66 | O34: 0.26502027 | P34: 1241.0983 | Q34: 37232.95 | R34: 0.3222737 | S34: 1332.5951 | T34: 51971.21 | U34: 0.26405313 | V34: 1094.9578 | W34: 19709.24 | X34: 0.26899798 | Y34: 1336.3286 | Z34: 18708.6 | AA34: 0.38257541 | AB34: 1051.9714 | AC34: 14727.6 | AD34: 0.28573266 | AE34: 1156.5766 | AF34: 33540.72 | AG34: 0.27481745 | AH34: 1340.6696 | AI34: 30835.4 | AJ34: 0.39274263 | AK34: 1320.2674 | AL34: 46209.36 | AM34: 0.26180589 | AN34: 1432.1624 | AO34: 35804.06
A35: =+$C$4&B35 -> Véhicules neufsComm. F&I | B35: Comm. F&I | C35: 0.3769204 | D35: 619.32366 | E35: 164120.77 | F35: 0.42523724 | G35: 747.60375 | H35: 5980.83 | I35: 0.38730752 | J35: 658.16889 | K35: 5923.52 | L35: 0.42129228 | M35: 746.28095 | N35: 15671.9 | O35: 0.4073422 | P35: 709.58033 | Q35: 21287.41 | R35: 0.37678559 | S35: 590.85333 | T35: 23043.28 | U35: 0.35239091 | V35: 583.16389 | W35: 10496.95 | X35: 0.3458694 | Y35: 528.53786 | Z35: 7399.53 | AA35: 0.35585955 | AB35: 555.39 | AC35: 7775.46 | AD35: 0.36937388 | AE35: 595.00897 | AF35: 17255.26 | AG35: 0.27134705 | AH35: 344.76696 | AI35: 7929.64 | AJ35: 0.42129741 | AK35: 801.20343 | AL35: 28042.12 | AM35: 0.33354493 | AN35: 532.5948 | AO35: 13314.87
A36: =+$C$4&B36 -> Véhicules neufsFrais de livraison | B36: Frais de livraison | D36: 120.09117 | E36: 31824.16 | G36: 113.19 | H36: 905.52 | J36: 238.40556 | K36: 2145.65 | M36: 117.48429 | N36: 2467.17 | P36: 73.194667 | Q36: 2195.84 | S36: 82.459231 | T36: 3215.91 | V36: 105.80833 | W36: 1904.55 | Y36: 228.45786 | Z36: 3198.41 | AB36: 306.69786 | AC36: 4293.77 | AE36: 128.05552 | AF36: 3713.61 | AH36: 125.91261 | AI36: 2895.99 | AK36: 67.887429 | AL36: 2376.06 | AN36: 100.4672 | AO36: 2511.68
A37: =+$C$4&B37 -> Véhicules neufsService gratuit 1 | B37: Service gratuit 1 | D37: 38.97834 | E37: 10329.26 | G37: 142.45125 | H37: 1139.61 | J37: 57.473333 | K37: 517.26 | M37: 9.5395238 | N37: 200.33 | P37: 26.899 | Q37: 806.97 | S37: 29.536923 | T37: 1151.94 | V37: 18.017778 | W37: 324.32 | Y37: 51.135714 | Z37: 715.9 | AB37: -3.7521429 | AC37: -52.53 | AE37: 73.190345 | AF37: 2122.52 | AH37: 30.172174 | AI37: 693.96 | AK37: 50.454571 | AL37: 1765.91 | AN37: 37.7228 | AO37: 943.07
A38: =+$C$4&B38 -> Véhicules neufsEntretien stock | B38: Entretien stock | D38: 65.46034 | E38: 17346.99 | G38: 120.0625 | H38: 960.5 | J38: 164.54444 | K38: 1480.9 | M38: 30.904762 | N38: 649 | P38: 62.396 | Q38: 1871.88 | S38: 25.282051 | T38: 986 | V38: 50.046111 | W38: 900.83 | Y38: 53.571429 | Z38: 750 | AB38: 115.575 | AC38: 1618.05 | AE38: 60.215862 | AF38: 1746.26 | AH38: 79.394348 | AI38: 1826.07 | AK38: 70.689429 | AL38: 2474.13 | AN38: 83.3348 | AO38: 2083.37
A39: =+$C$4&B39 -> Véhicules neufsPublicité 1 | B39: Publicité 1 | D39: 632.89355 | E39: 167716.79 | G39: 495.99125 | H39: 3967.93 | J39: 981.97778 | K39: 8837.8 | M39: 675.90762 | N39: 14194.06 | P39: 512.11267 | Q39: 15363.38 | S39: 373.90333 | T39: 14582.23 | V39: 750.24333 | W39: 13504.38 | Y39: 759.74143 | Z39: 10636.38 | AB39: 841.815 | AC39: 11785.41 | AE39: 712.53414 | AF39: 20663.49 | AH39: 956.57609 | AI39: 22001.25 | AK39: 338.084 | AL39: 11832.94 | AN39: 813.9016 | AO39: 20347.54
A40: =+$C$4&B40 -> Véhicules neufsIntérêt de gros | B40: Intérêt de gros | D40: 1381.9589 | E40: 366219.1 | G40: 3359.8812 | H40: 26879.05 | J40: 3226.1567 | K40: 29035.41 | M40: 1752.6862 | N40: 36806.41 | P40: 1210.5003 | Q40: 36315.01 | S40: 899.60974 | T40: 35084.78 | V40: 1767.2572 | W40: 31810.63 | Y40: 2453.1979 | Z40: 34344.77 | AB40: 2515.3971 | AC40: 35215.56 | AE40: 721.52345 | AF40: 20924.18 | AH40: 801.96174 | AI40: 18445.12 | AK40: 986.472 | AL40: 34526.52 | AN40: 1073.2664 | AO40: 26831.66
A41: =+$C$4&B41 -> Véhicules neufs[...] | B41: [...] | D41: 0 | E41: 0 | G41: 0 | J41: 0 | M41: 0 | P41: 0 | S41: 0 | V41: 0 | Y41: 0 | AB41: 0 | AE41: 0 | AH41: 0 | AK41: 0 | AN41: 0
A42: =+$C$4&B42 -> Véhicules neufs[...] | B42: [...] | D42: 0 | E42: 0 | G42: 0 | J42: 0 | M42: 0 | P42: 0 | S42: 0 | V42: 0 | Y42: 0 | AB42: 0 | AE42: 0 | AH42: 0 | AK42: 0 | AN42: 0
A43: =+$C$4&B43 -> Véhicules neufs[...] | B43: [...] | D43: 0 | E43: 0 | G43: 0 | J43: 0 | M43: 0 | P43: 0 | S43: 0 | V43: 0 | Y43: 0 | AB43: 0 | AE43: 0 | AH43: 0 | AK43: 0 | AN43: 0
A44: =+$C$4&B44 -> Véhicules neufsTOTAL VARIABLES | B44: TOTAL VARIABLES | C44: % brut | D44: 0.6685653 | E44: 1098029.4 | F44: % brut | G44: 0.90667583 | H44: 53599.71 | I44: % brut | J44: 1.1132662 | K44: 58439.85 | L44: % brut | M44: 0.68533675 | N44: 97456.53 | O44: % brut | P44: 0.58637456 | Q44: 115073.44 | R44: % brut | S44: 0.56213794 | T44: 130035.35 | U44: % brut | V44: 0.71226989 | W44: 78650.9 | X44: % brut | Y44: 0.78509046 | Z44: 75753.59 | AA44: % brut | AB44: 0.95480171 | AC44: 75363.32 | AD44: % brut | AE44: 0.60050029 | AF44: 99966.04 | AG44: % brut | AH44: 0.58277879 | AI44: 84627.43 | AJ44: % brut | AK44: 0.68670394 | AL44: 127227.04 | AM44: % brut | AN44: 0.57152237 | AO44: 101836.25
A45: =+$C$4&B45 -> Véhicules neufsSalaires cadres | B45: Salaires cadres | E45: 145432.02 | H45: 12096.22 | K45: 12651.8 | N45: 11492.2 | Q45: 12302.2 | T45: 12792.2 | W45: 9969.7 | Z45: 11969.7 | AC45: 11451.95 | AF45: 13019.7 | AI45: 13952.2 | AL45: 13561.95 | AO45: 10172.2
A46: =+$C$4&B46 -> Véhicules neufsSalaires commis | B46: Salaires commis | E46: 109318.68 | H46: 7908.3 | K46: 8941.86 | N46: 8376.56 | Q46: 8037.27 | T46: 9961.38 | W46: 8615.69 | Z46: 8642.68 | AC46: 8557.83 | AF46: 9046.16 | AI46: 9673.21 | AL46: 10795.04 | AO46: 10762.7
A47: =+$C$4&B47 -> Véhicules neufsSalaires autres | B47: Salaires autres | E47: 4104 | H47: 342 | K47: 342 | N47: 342 | Q47: 342 | T47: 342 | W47: 342 | Z47: 342 | AC47: 342 | AF47: 342 | AI47: 342 | AL47: 342 | AO47: 342
A48: =+$C$4&B48 -> Véhicules neufsSalaires spécialistes | B48: Salaires spécialistes | E48: 0 | H48: 0 | K48: 0 | N48: 0 | Q48: 0 | T48: 0 | W48: 0 | Z48: 0 | AC48: 0 | AF48: 0 | AI48: 0 | AL48: 0 | AO48: 0
A49: =+$C$4&B49 -> Véhicules neufs[...] | B49: [...] | E49: 0 | H49: 0 | K49: 0 | N49: 0 | Q49: 0 | T49: 0 | W49: 0 | Z49: 0 | AC49: 0 | AF49: 0 | AI49: 0 | AL49: 0 | AO49: 0
A50: =+$C$4&B50 -> Véhicules neufs[...] | B50: [...] | E50: 0 | H50: 0 | K50: 0 | N50: 0 | Q50: 0 | T50: 0 | W50: 0 | Z50: 0 | AC50: 0 | AF50: 0 | AI50: 0 | AL50: 0 | AO50: 0
A51: =+$C$4&B51 -> Véhicules neufs[...] | B51: [...] | E51: 0 | H51: 0 | K51: 0 | N51: 0 | Q51: 0 | T51: 0 | W51: 0 | Z51: 0 | AC51: 0 | AF51: 0 | AI51: 0 | AL51: 0 | AO51: 0
A52: =+$C$4&B52 -> Véhicules neufsSalaires en absences | B52: Salaires en absences | E52: 100107.48 | H52: 10797.57 | K52: 11191.66 | N52: 4727.83 | Q52: 4466.22 | T52: 9459.39 | W52: 10700.38 | Z52: 7289.01 | AC52: 5930.68 | AF52: 7379.94 | AI52: 7007.4 | AL52: 6518.5 | AO52: 14638.9
A53: =+$C$4&B53 -> Véhicules neufsDéduction à la source | B53: Déduction à la source | E53: 103363.31 | H53: 10270.36 | K53: 8943.52 | N53: 9317.44 | Q53: 10796.69 | T53: 13673.1 | W53: 8568.67 | Z53: 7392.17 | AC53: 5915.02 | AF53: 6007.24 | AI53: 7096.33 | AL53: 6563.34 | AO53: 8819.43
A54: =+$C$4&B54 -> Véhicules neufsBénéfices marginaux | B54: Bénéfices marginaux | E54: 53589.77 | H54: 3996.97 | K54: 4653.52 | N54: 3583.12 | Q54: 4198.83 | T54: 5353.05 | W54: 4031.8 | Z54: 4431.35 | AC54: 4874.64 | AF54: 4219.84 | AI54: 5643.58 | AL54: 2314.07 | AO54: 6289
A55: =+$C$4&B55 -> Véhicules neufsCsst | B55: Csst | E55: 8279.19 | H55: 1045.42 | K55: 1552.53 | N55: 879.83 | Q55: 1249.8 | T55: 1671.23 | W55: 1229.54 | Z55: -241.94 | AC55: 299.43 | AF55: 169.34 | AI55: 142.2 | AL55: 157.28 | AO55: 124.53
A56: =+$C$4&B56 -> Véhicules neufs[...] | B56: [...] | E56: 0
A57: =+$C$4&B57 -> Véhicules neufsTOTAL PERSONNEL | B57: TOTAL PERSONNEL | C57: % brut | D57: 0.31917015 | E57: 524194.45 | F57: % brut | G57: 0.78584928 | H57: 46456.84 | I57: % brut | J57: 0.91966404 | K57: 48276.89 | L57: % brut | M57: 0.27228078 | N57: 38718.98 | O57: % brut | P57: 0.2109245 | Q57: 41393.01 | R57: % brut | S57: 0.2109245 | T57: 53252.35 | U57: % brut | V57: 1.2109245 | W57: 43457.78 | X57: % brut | Y57: 1.2109245 | Z57: 39824.97 | AA57: % brut | AB57: 1.2109245 | AC57: 37371.55 | AD57: % brut | AE57: 1.2109245 | AF57: 40184.22 | AG57: % brut | AH57: 1.2109245 | AI57: 43856.92 | AJ57: % brut | AK57: 1.2109245 | AL57: 40252.18 | AM57: % brut | AN57: 1.2109245 | AO57: 51148.76
A58: =+$C$4&B58 -> Véhicules neufsPublicité 2 | B58: Publicité 2 | E58: 0 | H58: 0 | K58: 0 | N58: 0 | Q58: 0 | T58: 0 | W58: 0 | Z58: 0 | AC58: 0 | AF58: 0 | AI58: 0 | AL58: 0 | AO58: 0
A59: =+$C$4&B59 -> Véhicules neufsService gratuit 2 | B59: Service gratuit 2 | E59: 0 | H59: 0 | K59: 0 | N59: 0 | Q59: 0 | T59: 0 | W59: 0 | Z59: 0 | AC59: 0 | AF59: 0 | AI59: 0 | AL59: 0 | AO59: 0
A60: =+$C$4&B60 -> Véhicules neufsFrais véhicules de cie | B60: Frais véhicules de cie | E60: 88238.2 | H60: 5793.89 | K60: 5116.88 | N60: 5238.06 | Q60: 4993.44 | T60: 8441.26 | W60: 7316.83 | Z60: 6626.51 | AC60: 7910.75 | AF60: 9006.47 | AI60: 8049.91 | AL60: 9735.27 | AO60: 10008.93
A61: =+$C$4&B61 -> Véhicules neufsInformatique | B61: Informatique | E61: 54831.46 | H61: 4749.88 | K61: 4371.2 | N61: 4371.2 | Q61: 4537.54 | T61: 5260.81 | W61: 4468.35 | Z61: 4489.6 | AC61: 4562.82 | AF61: 4246.2 | AI61: 4885.13 | AL61: 4394.94 | AO61: 4493.79
A62: =+$C$4&B62 -> Véhicules neufsFrais de déplacement | B62: Frais de déplacement | E62: 15061.78 | H62: 607.84 | K62: 341.03 | N62: 1556.43 | Q62: 1481.23 | T62: 1088.52 | W62: 1461.62 | Z62: 3268.68 | AC62: 1080.66 | AF62: 975.02 | AI62: 874.14 | AL62: 1199.4 | AO62: 1127.21
A63: =+$C$4&B63 -> Véhicules neufsServices extérieurs | B63: Services extérieurs | E63: 41147.01 | H63: 3166.27 | K63: 3357.94 | N63: 2655.91 | Q63: 3008.26 | T63: 3645.57 | W63: 3629.84 | Z63: 3200.5 | AC63: 3483.32 | AF63: 3699.01 | AI63: 3076.7 | AL63: 3731.16 | AO63: 4492.53
A64: =+$C$4&B64 -> Véhicules neufsFournitures autres | B64: Fournitures autres | E64: 928.47 | H64: 0 | K64: 7.5 | N64: 0 | Q64: 2.49 | T64: 32.58 | W64: 0 | Z64: 10.99 | AC64: 75.79 | AF64: 0 | AI64: 301.85 | AL64: 10.79 | AO64: 486.48
A65: =+$C$4&B65 -> Véhicules neufsUniformes | B65: Uniformes | E65: 554.66 | H65: 0 | K65: 0 | N65: 0 | Q65: 0 | T65: 0 | W65: 78.08 | Z65: 229.08 | AC65: 247.5 | AF65: 0 | AI65: 0 | AL65: 0 | AO65: 0
A66: =+$C$4&B66 -> Véhicules neufsPapeterie | B66: Papeterie | E66: 7259.26 | H66: 499.83 | K66: 652.7 | N66: 157.66 | Q66: 431.9 | T66: 899.59 | W66: 502.79 | Z66: 751.32 | AC66: 884.8 | AF66: 336.26 | AI66: 856.73 | AL66: 802.33 | AO66: 483.35
A67: =+$C$4&B67 -> Véhicules neufsTéléphone | B67: Téléphone | E67: 2891.49 | H67: 203.83 | K67: 203.33 | N67: 254.73 | Q67: 235.92 | T67: 222.63 | W67: 364.45 | Z67: 203.57 | AC67: 205.77 | AF67: 205.64 | AI67: 213.35 | AL67: 387.42 | AO67: 190.85
A68: =+$C$4&B68 -> Véhicules neufsFrais postaux | B68: Frais postaux | E68: 2023 | H68: 202.86 | K68: 164.96 | N68: 179.07 | Q68: 258.2 | T68: 312.69 | W68: 82.69 | Z68: 239.74 | AC68: 143.9 | AF68: 58.8 | AI68: 82.64 | AL68: 55.24 | AO68: 242.21
A69: =+$C$4&B69 -> Véhicules neufsDivers | B69: Divers | E69: 9075.88 | H69: 961.56 | K69: 653.18 | N69: 726.53 | Q69: 832.95 | T69: 650.7 | W69: 650.7 | Z69: 650.7 | AC69: 832.95 | AF69: 650.7 | AI69: 650.7 | AL69: 739.8 | AO69: 1075.41
... A71: =+$C$4&B71 -> Véhicules neufsFrais bancaires | B71: Frais bancaires | E71: 35883.2 | H71: 1581.19 | K71: 1642.46 | N71: 2750.36 | Q71: 4388.05 | T71: 4109.05 | W71: 2461.66 | Z71: 2993.76 | AC71: 1997.75 | AF71: 2664.71 | AI71: 3948.54 | AL71: 4789.05 | AO71: 2556.62
A72: =+$C$4&B72 -> Véhicules neufs[...] | B72: [...] | E72: 0
A73: =+$C$4&B73 -> Véhicules neufs[...] | B73: [...] | E73: 0
A74: =+$C$4&B74 -> Véhicules neufs[...] | B74: [...] | E74: 0
A75: =+$C$4&B75 -> Véhicules neufsTOTAL SEMI-FIXES | B75: TOTAL SEMI-FIXES | C75: % brut | D75: 0.15925343 | E75: 261552.55 | F75: % brut | G75: 0.27902169 | H75: 16494.85 | I75: % brut | J75: 0.3263808 | K75: 17133.05 | L75: % brut | M75: 0.13072937 | N75: 18590.03 | O75: % brut | P75: 0.10541998 | Q75: 20688.21 | R75: % brut | S75: 0.1027515 | T75: 23768.77 | U75: % brut | V75: 0.1875037 | W75: 20704.7 | X75: % brut | Y75: 0.24613404 | Z75: 23749.54 | AA75: % brut | AB75: 0.28380509 | AC75: 22400.98 | AD75: % brut | AE75: 0.132291 | AF75: 22022.65 | AG75: % brut | AH75: 0.1608915 | AI75: 23363.64 | AJ75: % brut | AK75: 0.14652502 | AL75: 27146.99 | AM75: % brut | AN75: 0.14304939 | AO75: 25489.14
A76: =+$C$4&B76 -> Véhicules neufs
A77: =+$C$4&B77 -> Véhicules neufsTOTAL DES DÉPENSES | B77: TOTAL DES DÉPENSES | C77: % brut | D77: 1.1469889 | E77: 1883776.4 | F77: % brut | G77: 1.9715468 | H77: 116551.4 | I77: % brut | J77: 2.359311 | K77: 123849.79 | L77: % brut | M77: 1.0883469 | N77: 154765.54 | O77: % brut | P77: 0.90271905 | Q77: 177154.66 | R77: % brut | S77: 0.89509735 | T77: 207056.47 | U77: % brut | V77: 1.2933313 | W77: 142813.38 | X77: % brut | Y77: 1.4439601 | Z77: 139328.1 | AA77: % brut | AB77: 1.7120788 | AC77: 135135.85 | AD77: % brut | AE77: 0.97417963 | AF77: 162172.91 | AG77: % brut | AH77: 1.0456868 | AI77: 151847.99 | AJ77: % brut | AK77: 1.0504888 | AL77: 194626.21 | AM77: % brut | AN77: 1.0016273 | AO77: 178474.15
A78: =+$C$4&B78 -> Véhicules neufsRBSC neuf | B78: RBSC neuf | E78: 413289.73 | H78: 18905 | K78: 2278.07 | N78: 33136.94 | Q78: 56342.42 | T78: 57768.59 | W78: 27489.53 | Z78: 12290.01 | AC78: 19618.69 | AF78: 54073.89 | AI78: 46412.76 | AL78: 53053.83 | AO78: 31920
A79: =+$C$4&B79 -> Véhicules neufsProgramme neuf 2 | B79: Programme neuf 2 | E79: 0 | H79: 0 | K79: 0 | N79: 0 | Q79: 0 | T79: 0 | W79: 0 | Z79: 0 | AC79: 0 | AF79: 0 | AI79: 0 | AL79: 0 | AO79: 0
A80: =+$C$4&B80 -> Véhicules neufsProgramme neuf 3 | B80: Programme neuf 3 | E80: 0 | H80: 0 | K80: 0 | N80: 0 | Q80: 0 | T80: 0 | W80: 0 | Z80: 0 | AC80: 0 | AF80: 0 | AI80: 0 | AL80: 0 | AO80: 0
A81: =+$C$4&B81 -> Véhicules neufsHoldbacks | B81: Holdbacks | E81: 480905.6 | H81: 17420.1 | K81: 16676.2 | N81: 40227.1 | Q81: 47079 | T81: 57980.4 | W81: 37435.7 | Z81: 22240.8 | AC81: 31297.6 | AF81: 54160.1 | AI81: 35867.6 | AL81: 76456 | AO81: 44065
A82: =+$C$4&B82 -> Véhicules neufs[...] | B82: [...] | E82: 0 | H82: 0 | K82: 0 | N82: 0 | Q82: 0 | T82: 0 | W82: 0 | Z82: 0 | AC82: 0 | AF82: 0 | AI82: 0 | AL82: 0 | AO82: 0
A83: =+$C$4&B83 -> Véhicules neufs[...] | B83: [...] | E83: 0 | H83: 0 | K83: 0 | N83: 0 | Q83: 0 | T83: 0 | W83: 0 | Z83: 0 | AC83: 0 | AF83: 0 | AI83: 0 | AL83: 0 | AO83: 0
A84: =+$C$4&B84 -> Véhicules neufs[...] | B84: [...] | E84: 0 | H84: 0 | K84: 0 | N84: 0 | Q84: 0 | T84: 0 | W84: 0 | Z84: 0 | AC84: 0 | AF84: 0 | AI84: 0 | AL84: 0 | AO84: 0
A85: =+$C$4&B85 -> Véhicules neufsFrais administration | B85: Frais administration | E85: 157675 | H85: 4165 | K85: 5355 | N85: 11900 | Q85: 17850 | T85: 23800 | W85: 10710 | Z85: 8330 | AC85: 8925 | AF85: 17255 | AI85: 13685 | AL85: 20825 | AO85: 14875
A86: =+$C$4&B86 -> Véhicules neufsAUTRES REVENUS | B86: AUTRES REVENUS | E86: 1051870.3 | H86: 40490.1 | K86: 24309.27 | N86: 85264.04 | Q86: 121271.42 | T86: 139548.99 | W86: 75635.23 | Z86: 42860.81 | AC86: 59841.29 | AF86: 125488.99 | AI86: 95965.36 | AL86: 150334.83 | AO86: 90860
A87: =+$C$4&B87 -> Véhicules neufs
A88: =+$C$4&B88 -> Véhicules neufsPROFIT DÉPARTEMENTAL | B88: PROFIT DÉPARTEMENTAL | E88: 810460.68 | H88: -16944.57 | K88: -47046.47 | N88: 72700.9 | Q88: 140362.38 | T88: 163815.37 | W88: 43244.74 | Z88: 22.98 | AC88: 3636.3 | AF88: 129787.34 | AI88: 89331.01 | AL88: 140980.66 | AO88: 90570.04
B92: Budget 2024 | C92: Véhicules usagés
B94: Mois | C94: 2024 | F94: Janvier | I94: Février | L94: Mars | O94: Avril | R94: Mai | U94: Juin | X94: Juillet | AA94: Août | AD94: Septembre | AG94: Octobre | AJ94: Novembre | AM94: Décembre
C95: UNITE | D95: $P/UNITE | E95: $PROFITS | F95: UNITE | G95: $P/UNITE | H95: $PROFITS | I95: UNITE | J95: $P/UNITE | K95: $PROFITS | L95: UNITE | M95: $P/UNITE | N95: $PROFITS | O95: UNITE | P95: $P/UNITE | Q95: $PROFITS | R95: UNITE | S95: $P/UNITE | T95: $PROFITS | U95: UNITE | V95: $P/UNITE | W95: $PROFITS | X95: UNITE | Y95: $P/UNITE | Z95: $PROFITS | AA95: UNITE | AB95: $P/UNITE | AC95: $PROFITS | AD95: UNITE | AE95: $P/UNITE | AF95: $PROFITS | AG95: UNITE | AH95: $P/UNITE | AI95: $PROFITS | AJ95: UNITE | AK95: $P/UNITE | AL95: $PROFITS | AM95: UNITE | AN95: $P/UNITE | AO95: $PROFITS
A96: =+$C$92&B96 -> Véhicules usagésVentes nettes | B96: Ventes nettes | E96: 16016262 | H96: 1066829 | K96: 899970.03 | N96: 1070294.8 | Q96: 1837134.2 | T96: 1654438.7 | W96: 1477403.6 | Z96: 1396670.8 | AC96: 1096552.7 | AF96: 1877677.9 | AI96: 1387184.8 | AL96: 842711.86 | AO96: 1409394.1
A97: =+$C$92&B97 -> Véhicules usagésCertifié | B97: Certifié | C97: 62 | D97: 2319.78 | E97: 143826.36 | F97: 2 | G97: 3535.92 | H97: 7071.84 | I97: 9 | J97: 2012.4589 | K97: 18112.13 | L97: 6 | M97: 3773.94 | N97: 22643.64 | O97: 7 | P97: 1622.3443 | Q97: 11356.41 | R97: 6 | S97: 1976.7783 | T97: 11860.67 | U97: 9 | V97: 2507.04 | W97: 22563.36 | X97: 4 | Y97: 1431.6625 | Z97: 5726.65 | AA97: 3 | AB97: 1558.9767 | AC97: 4676.93 | AD97: 4 | AE97: 3820.39 | AF97: 15281.56 | AG97: 5 | AH97: 2141.454 | AI97: 10707.27 | AJ97: 2 | AK97: 1366.475 | AL97: 2732.95 | AM97: 5 | AN97: 2218.59 | AO97: 11092.95
A98: =+$C$92&B98 -> Véhicules usagésNon Certifié | B98: Non Certifié | C98: 73 | D98: 1814.3649 | E98: 132448.64 | F98: 7 | G98: 2276.44 | H98: 15935.08 | I98: 3 | J98: 1481.3967 | K98: 4444.19 | L98: 3 | M98: 2281.9767 | N98: 6845.93 | O98: 9 | P98: 1875.23 | Q98: 16877.07 | R98: 13 | S98: 1923.2669 | T98: 25002.47 | U98: 5 | V98: 1368.93 | W98: 6844.65 | X98: 5 | Y98: 3000.86 | Z98: 15004.3 | AA98: 8 | AB98: 1068.4225 | AC98: 8547.38 | AD98: 6 | AE98: 1556.0783 | AF98: 9336.47 | AG98: 5 | AH98: 4364.8 | AI98: 21824 | AJ98: 2 | AK98: 1534.64 | AL98: 3069.28 | AM98: 7 | AN98: -183.16857 | AO98: -1282.18
A99: =+$C$92&B99 -> Véhicules usagésAutres Marques | B99: Autres Marques | C99: 63 | D99: 1119.7821 | E99: 70546.27 | F99: 3 | G99: 1247.35 | H99: 3742.05 | I99: 1 | J99: 500 | K99: 500 | L99: 5 | M99: 1395.21 | N99: 6976.05 | O99: 12 | P99: 862.97167 | Q99: 10355.66 | R99: 5 | S99: 981.526 | T99: 4907.63 | U99: 5 | V99: 1005.798 | W99: 5028.99 | X99: 9 | Y99: 1597.0133 | Z99: 14373.12 | AA99: 8 | AB99: 1447.5125 | AC99: 11580.1 | AD99: 7 | AE99: 874.92 | AF99: 6124.44 | AG99: 4 | AH99: 1300.255 | AI99: 5201.02 | AJ99: 3 | AK99: 419.07 | AL99: 1257.21 | AM99: 1 | AN99: 500 | AO99: 500
A100: =+$C$92&B100 -> Véhicules usagésTotal Usagés | B100: Total Usagés | C100: 198 | D100: 1751.6226 | E100: 346821.27 | F100: 12 | G100: 2229.0808 | H100: 26748.97 | I100: 13 | J100: 1773.5631 | K100: 23056.32 | L100: 14 | M100: 2604.6871 | N100: 36465.62 | O100: 28 | P100: 1378.1836 | Q100: 38589.14 | R100: 24 | S100: 1740.4487 | T100: 41770.77 | U100: 19 | V100: 1812.4737 | W100: 34437 | X100: 18 | Y100: 1950.2261 | Z100: 35104.07 | AA100: 19 | AB100: 1305.4953 | AC100: 24804.41 | AD100: 17 | AE100: 1808.3806 | AF100: 30742.47 | AG100: 14 | AH100: 2695.1636 | AI100: 37732.29 | AJ100: 7 | AK100: 1008.4914 | AL100: 7059.44 | AM100: 13 | AN100: 793.13615 | AO100: 10310.77
A101: =+$C$92&B101 -> Véhicules usagés
A102: =+$C$92&B102 -> Véhicules usagés
A103: =+$C$92&B103 -> Véhicules usagésVentes au Gros | B103: Ventes au Gros | C103: 230 | D103: 434.93061 | E103: 100034.04 | F103: 10 | G103: 687.648 | H103: 6876.48 | I103: 13 | J103: 508.23923 | K103: 6607.11 | L103: 14 | M103: -135.83286 | N103: -1901.66 | O103: 16 | P103: 462.19375 | Q103: 7395.1 | R103: 21 | S103: 72.271429 | T103: 1517.7 | U103: 27 | V103: 42.867407 | W103: 1157.42 | X103: 20 | Y103: 179.1265 | Z103: 3582.53 | AA103: 17 | AB103: 419.75235 | AC103: 7135.79 | AD103: 29 | AE103: 654.29103 | AF103: 18974.44 | AG103: 20 | AH103: 614.648 | AI103: 12292.96 | AJ103: 20 | AK103: 1233.664 | AL103: 24673.28 | AM103: 23 | AN103: 509.69087 | AO103: 11722.89
A104: =+$C$92&B104 -> Véhicules usagés
A105: =+$C$92&B105 -> Véhicules usagésRev. Finances | B105: Rev. Finances | D105: 360.57232 | E105: 71393.32 | G105: 305.60833 | H105: 3667.3 | J105: 667.32308 | K105: 8675.2 | M105: 109.73357 | N105: 1536.27 | P105: 469.70679 | Q105: 13151.79 | S105: 327.625 | T105: 7863 | V105: 392.41895 | W105: 7455.96 | Y105: 503.19722 | Z105: 9057.55 | AB105: 17.800526 | AC105: 338.21 | AE105: 458.39647 | AF105: 7792.74 | AH105: 533.38786 | AI105: 7467.43 | AK105: 203.58714 | AL105: 1425.11 | AN105: 227.90462 | AO105: 2962.76
A106: =+$C$92&B106 -> Véhicules usagésRev. Protections | B106: Rev. Protections | D106: 827.98833 | E106: 163941.69 | G106: 1144.1475 | H106: 13729.77 | J106: 1323.5146 | K106: 17205.69 | M106: 499.5 | N106: 6993 | P106: 654.39286 | Q106: 18323 | S106: 1132.5679 | T106: 27181.63 | V106: 558.47368 | W106: 10611 | Y106: 806.55556 | Z106: 14518 | AB106: 535.84211 | AC106: 10181 | AE106: 683.78235 | AF106: 11624.3 | AH106: 720.94286 | AI106: 10093.2 | AK106: 1359.7143 | AL106: 9518 | AN106: 1074.0846 | AO106: 13963.1
...

Sheet Capex
A1: CONCESSION
A2: Forecast Immobilisation 2025 | H2: 1 | I2: 2 | J2: 3 | K2: 4 | L2: 5 | M2: 6 | N2: 7 | O2: 8 | P2: 9 | Q2: 10 | R2: 11 | S2: 12
H3: =+IF(VLOOKUP(H2,Parametres!$L$3:$N$14,3,0)="X","REEL","FORECAST") -> REEL | I3: =+IF(VLOOKUP(I2,Parametres!$L$3:$N$14,3,0)="X","REEL","FORECAST") -> REEL | J3: =+IF(VLOOKUP(J2,Parametres!$L$3:$N$14,3,0)="X","REEL","FORECAST") -> REEL | K3: =+IF(VLOOKUP(K2,Parametres!$L$3:$N$14,3,0)="X","REEL","FORECAST") -> REEL | L3: =+IF(VLOOKUP(L2,Parametres!$L$3:$N$14,3,0)="X","REEL","FORECAST") -> FORECAST | M3: =+IF(VLOOKUP(M2,Parametres!$L$3:$N$14,3,0)="X","REEL","FORECAST") -> FORECAST | N3: =+IF(VLOOKUP(N2,Parametres!$L$3:$N$14,3,0)="X","REEL","FORECAST") -> FORECAST | O3: =+IF(VLOOKUP(O2,Parametres!$L$3:$N$14,3,0)="X","REEL","FORECAST") -> FORECAST | ... S3: =+IF(VLOOKUP(S2,Parametres!$L$3:$N$14,3,0)="X","REEL","FORECAST") -> FORECAST
A4: Concession | B4: Budgété / Non budgété | C4: Projet | D4: Catégorie Immo | E4: Total forecast | F4: Budget Annuel | G4: Écart vs budget | H4: January | I4: February | J4: March | K4: April | L4: May | M4: June | N4: July | O4: August | P4: September | Q4: October | R4: November | S4: December | T4: Raison / Description
C5: Total | E5: =+SUM(E6:E40) -> 130039.14 | F5: =+SUM(F6:F40) -> 233000 | G5: =+SUM(G6:G40) -> -102960.86 | H5: =+SUM(H6:H40) -> 120701.21 | I5: =+SUM(I6:I40) -> 4893.17 | J5: =+SUM(J6:J40) -> 3886.16 | K5: =+SUM(K6:K40) -> 558.6 | L5: =+SUM(L6:L40) -> 0 | ... S5: =+SUM(S6:S40) -> 0 | X5: Terrain
A6: =+Parametres!$B$1 -> BMW Sherbrooke | B6: oui | C6: Outils obligatoire | E6: =+SUM(H6:S6) -> 3155.1 | F6: 10000 | G6: =+E6-F6 -> -6844.9 | I6: 1139.34 | J6: 1457.16 | K6: 558.6 | X6: Bâtisse
A7: =+Parametres!$B$1 -> BMW Sherbrooke | B7: oui | C7: Pilon enseigne | E7: =+SUM(H7:S7) -> 0 | F7: 25000 | G7: =+E7-F7 -> -25000 | X7: Améliorations Locatives
A8: =+Parametres!$B$1 -> BMW Sherbrooke | B8: oui | C8: Mise à niveau entreposage | E8: =+SUM(H8:S8) -> 3958.9 | F8: 20000 | G8: =+E8-F8 -> -16041.1 | H8: 1000 | I8: 1672.9 | J8: 1286 | X8: Améliorations Locatives Permanentes
A9: =+Parametres!$B$1 -> BMW Sherbrooke | B9: oui | C9: Borne électrique | E9: =+SUM(H9:S9) -> 109701.21 | F9: 150000 | G9: =+E9-F9 -> -40298.79 | H9: 109701.21 | X9: Équipements Service
A10: =+Parametres!$B$1 -> BMW Sherbrooke | B10: oui | C10: Lift | E10: =+SUM(H10:S10) -> 0 | F10: 10000 | G10: =+E10-F10 -> -10000 | X10: Mobilier
A11: =+Parametres!$B$1 -> BMW Sherbrooke | B11: oui | C11: Machine AC | E11: =+SUM(H11:S11) -> 10000 | F11: 10000 | G11: =+E11-F11 -> 0 | H11: 10000 | X11: Équipements Informatique
A12: =+Parametres!$B$1 -> BMW Sherbrooke | B12: oui | C12: Ordinateur | E12: =+SUM(H12:S12) -> 2496.5 | F12: 6000 | G12: =+E12-F12 -> -3503.5 | I12: 1353.5 | J12: 1143 | X12: Équipements Téléphonique
A13: =+Parametres!$B$1 -> BMW Sherbrooke | B13: oui | C13: 1 chargeur baterie | E13: =+SUM(H13:S13) -> 0 | F13: 2000 | G13: =+E13-F13 -> -2000 | X13: Enseigne
A14: =+Parametres!$B$1 -> BMW Sherbrooke | C14: Equipement esthétique | E14: =+SUM(H14:S14) -> 727.43 | G14: =+E14-F14 -> 727.43 | I14: 727.43
A15: =+Parametres!$B$1 -> BMW Sherbrooke | E15: =+SUM(H15:S15) -> 0 | G15: =+E15-F15 -> 0
A16: =+Parametres!$B$1 -> BMW Sherbrooke | E16: =+SUM(H16:S16) -> 0 | G16: =+E16-F16 -> 0
A17: =+Parametres!$B$1 -> BMW Sherbrooke | E17: =+SUM(H17:S17) -> 0 | G17: =+E17-F17 -> 0
A18: =+Parametres!$B$1 -> BMW Sherbrooke | E18: =+SUM(H18:S18) -> 0 | G18: =+E18-F18 -> 0
A19: =+Parametres!$B$1 -> BMW Sherbrooke | E19: =+SUM(H19:S19) -> 0 | G19: =+E19-F19 -> 0
A20: =+Parametres!$B$1 -> BMW Sherbrooke | E20: =+SUM(H20:S20) -> 0 | G20: =+E20-F20 -> 0
A21: =+Parametres!$B$1 -> BMW Sherbrooke | E21: =+SUM(H21:S21) -> 0 | G21: =+E21-F21 -> 0
A22: =+Parametres!$B$1 -> BMW Sherbrooke | E22: =+SUM(H22:S22) -> 0 | G22: =+E22-F22 -> 0
A23: =+Parametres!$B$1 -> BMW Sherbrooke | E23: =+SUM(H23:S23) -> 0 | G23: =+E23-F23 -> 0
A24: =+Parametres!$B$1 -> BMW Sherbrooke | E24: =+SUM(H24:S24) -> 0 | G24: =+E24-F24 -> 0
A25: =+Parametres!$B$1 -> BMW Sherbrooke | E25: =+SUM(H25:S25) -> 0 | G25: =+E25-F25 -> 0
A26: =+Parametres!$B$1 -> BMW Sherbrooke | E26: =+SUM(H26:S26) -> 0 | G26: =+E26-F26 -> 0
... A35: =+Parametres!$B$1 -> BMW Sherbrooke | E35: =+SUM(H35:S35) -> 0 | G35: =+E35-F35 -> 0
A36: =+Parametres!$B$1 -> BMW Sherbrooke | E36: =+SUM(H36:S36) -> 0 | G36: =+E36-F36 -> 0 | X36: oui
A37: =+Parametres!$B$1 -> BMW Sherbrooke | E37: =+SUM(H37:S37) -> 0 | G37: =+E37-F37 -> 0 | X37: non
A38: =+Parametres!$B$1 -> BMW Sherbrooke | E38: =+SUM(H38:S38) -> 0 | G38: =+E38-F38 -> 0
A39: =+Parametres!$B$1 -> BMW Sherbrooke | E39: =+SUM(H39:S39) -> 0 | G39: =+E39-F39 -> 0
A40: =+Parametres!$B$1 -> BMW Sherbrooke | E40: =+SUM(H40:S40) -> 0 | G40: =+E40-F40 -> 0
E48: 23

Sheet Inventaire_Neuf
A1: #Contrôle | B1: Année | C1: Marque | D1: Modèle | E1: $ Inventaire | F1: $ Financé | G1: NIV | H1: Jours en stock | L1: $ Inventaire | M1: $ Financé
A2: 23019 | B2: 2023 | C2: BMW | D2: 430 | E2: 65121.87 | F2: -60905.25 | G2: WBA73AP05PCL27730 | H2: 478 | K2: CTRL | L2: =+SUM(E2:E10000) -> 3938633.3 | M2: =+SUM(F2:F10000) -> -3910068
A3: 23020 | B3: 2023 | C3: BMW | D3: 430 | E3: 63963.67 | G3: WBA73AP06PCL26036 | H3: 465 | L3: =+COUNT(E2:E10000) -> 45
A4: 23084 | B4: 2023 | C4: BMW | D4: 530xe | E4: 75509.5 | G4: WBA33AG06PCL42221 | H4: 411
A5: 23218 | B5: 2023 | C5: BMW SAV | D5: X3 | E5: 84833.61 | F5: -88452 | G5: 5UX83DP04P9T17873 | H5: 146
A6: 23221 | B6: 2023 | C6: BMW | D6: SERIE 2 | E6: 66617.36 | F6: -69326.25 | G6: 3MW53CM06P8D70441 | H6: 151
A7: 23228 | B7: 2023 | C7: BMW SAV | D7: X3 | E7: 73335.37 | F7: -69809.25 | G7: 5UX53DP06P9T28635 | H7: 143
A8: 23240 | B8: 2023 | C8: BMW SAV | D8: X1 | E8: 50471.49 | F8: -50473.5 | G8: WBX73EF02P5X85602 | H8: 67
A9: 23241 | B9: 2023 | C9: BMW SAV | D9: X1 | E9: 50262.11 | F9: -52143 | G9: WBX73EF00P5X86053 | H9: 58
A10: 24019 | B10: 2024 | C10: BMW SAV | D10: X5 | E10: 95266.49 | F10: -95303.25 | G10: 5UX23EU05R9T15522 | H10: 158
A11: 24023 | B11: 2024 | C11: BMW SAV | D11: X7 | E11: 126612.36 | F11: -131675.25 | G11: 5UX23EM04R9T23238 | H11: 149
A12: 24024 | B12: 2024 | C12: BMWI | D12: IX40 | E12: 97633.14 | F12: -97203.75 | G12: WB513CF03RCN76497 | H12: 152
A13: 24032 | B13: 2024 | C13: BMW SAV | D13: X6 | E13: 103328.55 | F13: -107651.25 | G13: 5UX33EX02R9T31595 | H13: 144
A14: 24034 | B14: 2024 | C14: BMW | D14: SERIE 4 | E14: 66533.61 | F14: -69237 | G14: WBA73AP07RCN92250 | H14: 144
A15: 24038 | B15: 2024 | C15: BMWI | D15: I7 | E15: 159476.47 | F15: -173664.75 | G15: WBY53EJ01RCN94634 | H15: 142
A16: 24051 | B16: 2024 | C16: BMW | D16: SERIE 3 | E16: 62907.21 | F16: -60149.52 | G16: 3MW89FF00R8D80878 | H16: 117
... A46: 24130 | B46: 2024 | C46: BMW SAV | D46: X3 | E46: 65370 | F46: -68638.5 | G46: 5UX53DP06R9U99484 | H46: 9

Sheet Inventaire_Used
A1: #Contrôle | B1: Année | C1: Marque | D1: Description | E1: Amount | F1: Financé | G1: NIV | H1: Jours en stock | L1: $ Inventaire | M1: $ Financé
A2: P0512 | B2: 2004 | C2: CHEVROLET TRUCK | D2: SILVERADO 2500 | E2: 3856.45 | G2: 1GCGK23U14F218132 | H2: 1482 | K2: CTRL | L2: =+SUM(E2:E9999) -> 1972155.4 | M2: =+SUM(F2:F9999) -> -1357394.6
A3: P2173 | B3: 2022 | C3: BMW | D3: 540i | E3: 75917.21 | F3: -50220 | G3: WBA73BJ07NWX54871 | H3: 490 | L3: =+COUNT(E2:E10000) -> 50
A4: P2259 | B4: 2021 | C4: BMW SAV | D4: X5 | E4: 75668.81 | F4: -55025 | G4: 5UXTA6C07M9G89398 | H4: 306
A5: P2282 | B5: 2019 | C5: BMW | D5: Z4 | E5: 61477.55 | F5: -55037.5 | G5: WBAHF3C57KWW21386 | H5: 235
A6: P2321 | B6: 2021 | C6: JEEP | D6: GLADIATOR 4X4 | E6: 57247.58 | F6: -48210.15 | G6: 1C6HJTAG8ML543623 | H6: 144
A7: P2327 | B7: 2023 | C7: BMW SAV | D7: X1 | E7: 51697.81 | F7: -49599.39 | G7: WBX73EF03P5W40276 | H7: 137
A8: 23231A | B8: 2020 | C8: MINI | D8: COUNTRYMAN | E8: 35295.85 | F8: -20589.76 | G8: WMZYZ9C04L3L18702 | H8: 125
A9: P2334 | B9: 2019 | C9: BMW | D9: 330i | E9: 31287.41 | F9: -23537.41 | G9: WBA5R7C54KFH22955 | H9: 111
A10: 23193A | B10: 2022 | C10: VOLVO | D10: XC60 | E10: 58424.95 | F10: -80500 | G10: LYV062RL8NB979235 | H10: 108
A11: P2335 | B11: 2020 | C11: BMW SAV | D11: X3 | E11: 30904.85 | F11: -21000 | G11: 5UXTY5C03L9D44647 | H11: 103
A12: 24082A | B12: 2023 | C12: MAZDA | D12: MX-5 | E12: 34707.45 | F12: -32060.23 | G12: JM1NDAD7XP0552574 | H12: 73
A13: 23225A | B13: 2023 | C13: BMW | D13: 330i | E13: 54482.17 | F13: -37837.25 | G13: WBA83FF0XPFN75280 | H13: 72
A14: P2342A | B14: 2023 | C14: BMW | D14: 530e | E14: 65103.95 | F14: -45150 | G14: WBA33AG00PCL72878 | H14: 72
A15: P2343 | B15: 2023 | C15: ACURA | D15: Integra | E15: 39059.95 | F15: -35100 | G15: 19UDE4G72PA800656 | H15: 67
... A28: P2356 | B28: 2021 | C28: ACURA | D28: TLX | E28: 39793.95 | F28: -35550 | G28: 19UUB6F51MA801958 | H28: 38
A29: 24098A | B29: 2015 | C29: MINI | D29: 5 DOOR | E29: 8000 | G29: WMWXS5C59FT837198 | H29: 38
A30: 23116B | B30: 2021 | C30: JEEP | D30: Wrangler Unlim | E30: 43899.95 | F30: -30450 | G30: 1C4HJXEN3MW680010 | H30: 37
A31: 24078A | B31: 2023 | C31: VOLKSWAGEN | D31: ID.4 | E31: 47899.95 | F31: -34300 | G31: 1V2JNPE8XPC021183 | H31: 31
A32: 23243A | B32: 2020 | C32: BMW | D32: 2 SERIES | E32: 29024.85 | F32: -19599.51 | G32: WBA73AK0XL7G01503 | H32: 26
A33: P2361 | B33: 2014 | C33: BMW | D33: 320i | E33: 11164.86 | G33: WBA3C3C57EK200069 | H33: 22
A34: P2362 | B34: 2023 | C34: BMW | D34: M240i xDrive | E34: 53250.2 | F34: -52796.25 | G34: 3MW53CM03P8C99750 | H34: 20
A35: P2363 | B35: 2023 | C35: BMW | D35: 230i | E35: 42103.5 | F35: -41658.65 | G35: 3MW33CM08P8C93109 | H35: 18
A36: P2364 | B36: 2017 | C36: BMW SAV | D36: X4 | E36: 27407.01 | F36: -24300 | G36: 5UXXW3C37H0T79741 | H36: 17
A37: 24040A | B37: 2023 | C37: BMW SAV | D37: X4 | E37: 58745 | F37: -45726.94 | G37: 5UX33DT01P9N56202 | H37: 13
A38: P2367 | B38: 2019 | C38: NISSAN | D38: Micra | E38: 11000 | F38: -9900 | G38: 3N1CK3CP5KL236170 | H38: 10
A39: 23244A | B39: 2019 | C39: BMW SAV | D39: X2 | E39: 26995 | F39: -16020.18 | G39: WBXYJ5C54K5N01549 | H39: 10
A40: 24103A | B40: 2021 | C40: BMW SAV | D40: X3 | E40: 42500 | F40: -30072.18 | G40: 5UXTS1C06M9H64396 | H40: 10
A41: P2223A | B41: 2023 | C41: BMW | D41: I4 | E41: 51776.06 | F41: -29211.39 | G41: WBY43AW09PFP45888 | H41: 10
A42: P2366 | B42: 2012 | C42: BMW | D42: M3 | E42: 37500 | G42: WBSKG9C53CE798848 | H42: 10
A43: P2365 | B43: 2021 | C43: DODGE TRUCK | D43: RAM 1500 Class | E43: 32547.15 | F43: -32547.15 | G43: 3C6RR7KG7MG709002 | H43: 9
A44: 23227A | B44: 2017 | C44: HONDA | D44: CIVIC HATCHBAC | E44: 14000 | G44: SHHFK7H26HU304092 | H44: 9
A45: 24097A | B45: 2018 | C45: AUDI | D45: A5 Sportback | E45: 18500 | G45: WAUANCF51JA004190 | H45: 3
A46: 24126A | B46: 2017 | C46: BMW | D46: 2 SERIES | E46: 28000 | G46: WBA2L3C32HV667851 | H46: 3
A47: 24091B | B47: 2013 | C47: VOLKSWAGEN | D47: JETTA | E47: 1500 | G47: 3VW1K7AJ9DM416983 | H47: 2
A48: 24125B | B48: 2017 | C48: BMW | D48: 650i | E48: 37000 | G48: WBA6F7C50HD930698 | H48: 2
A49: 23122A | B49: 2022 | C49: BMW | D49: 2 SERIES | E49: 37500 | G49: WBA13AL03N7K75967 | H49: 2
A50: 24125A | B50: 2021 | C50: BMW SAV | D50: X5 | E50: 60000 | G50: 5UXJU4C08M9E22693 | H50: 2
A51: 24104B | B51: 2019 | C51: BMW SAV | D51: X2 | E51: 31000 | G51: WBXYN1C56K5N23209 | H51: 0

Sheet Démo
B1: Suivi de Démo
B2: # Stock | C2: NIV | D2: Année | E2: Marque | F2: Modèle | G2: $ Valeur | H2: Nom | I2: Prénom | J2: Titre / Fonction
H4: Rosa | I4: Yvon | J4: Conseiller aux ventes
H5: Beaudoin | I5: Sébastien | J5: VPDG
E48: 23

Sheet Wholesale
C1: ="Analyse Wholesale "&Parametres!B1 -> Analyse Wholesale BMW Sherbrooke
D2: $ | F2: X | G2: U | L2: $ | N2: X | O2: U
E4: =CONCATENATE("Pièces Wholesale ",Parametres!B3," ",Parametres!B4) -> Pièces Wholesale Avril 2025 | J4: =CONCATENATE("Pièces Wholesale AAD ",Parametres!B4) -> Pièces Wholesale AAD 2025
E5: Réel | F5: Budget | G5: ▲ $ | H5: ▲ % | J5: Réel | K5: Budget | L5: ▲ $ | M5: ▲ %
C6: NB de livraisons | E6: =SUMIF(A37:A48,"X",E37:E48) -> 37 | F6: =SUMIF(A37:A48,"X",F37:F48) -> 22 | G6: =E6-F6 -> 15 | H6: =G6/F6 -> 0.68181818 | J6: =SUMIF($B$37:$B$48,"X",$E$37:$E$48) -> 115 | K6: =SUMIF($B$37:$B$48,"X",$F$37:$F$48) -> 88 | L6: =J6-K6 -> 27 | M6: =L6/K6 -> 0.30681818
A7: =B7&C7 -> piècesVentes de Gros | B7: pièces | C7: Ventes de Gros | E7: =-SUMIFS(BV_Data_An_Cour!$O:$O,BV_Data_An_Cour!$X:$X,"Oui",BV_Data_An_Cour!$U:$U,$B7,BV_Data_An_Cour!$V:$V,$C7) -> 72740.67 | F7: =+INDEX('Budget original'!$A$2:$AO$501,MATCH($A7,'Budget original'!$A$2:$A$501,0),MATCH(F$2,'Budget original'!$A$2:$AO$2,0)) -> 38846.442 | G7: =E7-F7 -> 33894.228 | H7: =G7/F7 -> 0.8725182 | J7: =-SUMIFS(BV_Data_An_Cour!$P:$P,BV_Data_An_Cour!$X:$X,"Oui",BV_Data_An_Cour!$U:$U,$B7,BV_Data_An_Cour!$V:$V,$C7) -> 229043.23 | K7: {=+SUMPRODUCT(('Budget original'!$A$8:$A$501=$A7)*('Budget original'!$C$3:$AO$3=N$2),'Budget original'!$C$8:$AO$501)} -> 196645.76 | L7: =J7-K7 -> 32397.469 | M7: =L7/K7 -> 0.16475041
C8: Coûts | E8: =E7-E9 -> 56135.46 | F8: =F7-F9 -> 28882.954 | G8: =E8-F8 -> 27252.506 | H8: =G8/F8 -> 0.94354983 | J8: =J7-J9 -> 175916.6 | K8: =K7-K9 -> 146654.26 | L8: =J8-K8 -> 29262.341 | M8: =L8/K8 -> 0.19953284
C9: Profit brut | E9: =E12+E11 -> 16605.21 | F9: =F12+F11 -> 9963.4884 | G9: =E9-F9 -> 6641.7216 | H9: =G9/F9 -> 0.66660604 | J9: =J12+J11 -> 53126.63 | K9: =K12+K11 -> 49991.502 | L9: =J9-K9 -> 3135.1278 | M9: =L9/K9 -> 0.062713215
C10: % avant redevances | E10: =E9/E7 -> 0.22827959 | F10: =F9/F7 -> 0.25648394 | G10: =E10-F10 -> -0.028204352 | J10: =J9/J7 -> 0.23195023 | K10: =K9/K7 -> 0.2542211 | L10: =J10-K10 -> -0.022270872
C11: Coûts de redevance | E11: =SUMIFS(BV_Data_An_Cour!$O:$O,BV_Data_An_Cour!$W:$W,$D$2,BV_Data_An_Cour!L:L,C31) -> 2579.53 | F11: =SUMIF($A$37:$A$48,"X",$G$37:$G$48) -> 2194.2 | G11: =E11-F11 -> 385.33 | H11: =G11/F11 -> 0.17561298 | J11: =SUMIFS(BV_Data_An_Cour!$P:$P,BV_Data_An_Cour!$W:$W,$L$2,BV_Data_An_Cour!T:T,C31) -> 6884.92 | K11: =SUMIF($B$37:$B$48,"X",$G$37:$G$48) -> 10662.35 | L11: =J11-K11 -> -3777.43 | M11: =L11/K11 -> -0.35427743
A12: Ventes de Gros | B12: pièces | C12: Profit | E12: =-SUMIFS(BV_Data_An_Cour!$O:$O,BV_Data_An_Cour!$U:$U,$B12,BV_Data_An_Cour!$V:$V,$A12,BV_Data_An_Cour!$W:$W,$D$2) -> 14025.68 | F12: =+INDEX('Budget original'!$A$2:$AO$501,MATCH(B12&$A12,'Budget original'!$A$2:$A$501,0),MATCH(G$2,'Budget original'!$A$2:$AO$2,0)) -> 7769.2884 | G12: =E12-F12 -> 6256.3916 | H12: =G12/F12 -> 0.80527214 | J12: =-SUMIFS(BV_Data_An_Cour!$P:$P,BV_Data_An_Cour!$U:$U,$B12,BV_Data_An_Cour!$V:$V,$A12,BV_Data_An_Cour!$W:$W,$D$2) -> 46241.71 | K12: {=+SUMPRODUCT(('Budget original'!$A$8:$A$501=B12&$A12)*('Budget original'!$C$3:$AO$3=O$2),'Budget original'!$C$8:$AO$501)} -> 39329.152 | L12: =J12-K12 -> 6912.5578 | M12: =L12/K12 -> 0.17576168
C13: % brut | E13: =(E12)/E7 -> 0.19281758 | F13: =(F12)/F7 -> 0.2 | G13: =E13-F13 -> -0.0071824194 | J13: =(J12)/J7 -> 0.20189075 | K13: =(K12)/K7 -> 0.2 | L13: =J13-K13 -> 0.0018907522
C14: Coûts de livraison | E14: =SUMIFS(BV_Data_An_Cour!$O:$O,BV_Data_An_Cour!$W:$W,$D$2,BV_Data_An_Cour!L:L,C33) -> 925 | F14: =SUMIF(A37:A48,"X",F37:F48)*$G$33 -> 550 | G14: =E14-F14 -> 375 | H14: =G14/F14 -> 0.68181818 | J14: =SUMIFS(BV_Data_An_Cour!$P:$P,BV_Data_An_Cour!$W:$W,$L$2,BV_Data_An_Cour!T:T,C33) -> 2875 | K14: =SUMIF(B37:B48,"X",F37:F48)*$G$33 -> 2200 | L14: =J14-K14 -> 675 | M14: =L14/K14 -> 0.30681818
C15: Profit net | E15: =E12-E14 -> 13100.68 | F15: =F12-F14 -> 7219.2884 | G15: =E15-F15 -> 5881.3916 | H15: =G15/F15 -> 0.81467746 | J15: =J12-J14 -> 43366.71 | K15: =K12-K14 -> 37129.152 | L15: =J15-K15 -> 6237.5578 | M15: =L15/K15 -> 0.16799624
C16: % net | E16: =E15/E7 -> 0.18010117 | F16: =F15/F7 -> 0.18584169 | G16: =E16-F16 -> -0.0057405162 | J16: =J15/J7 -> 0.18933854 | K16: =K15/K7 -> 0.18881237 | L16: =J16-K16 -> 0.00052616659
E18: =CONCATENATE("Pièces Wholesale $ / livraison ",Parametres!B3," ",Parametres!B4) -> Pièces Wholesale $ / livraison Avril 2025 | J18: =CONCATENATE("Pièces Wholesale AAD $ / livraison ",Parametres!B4) -> Pièces Wholesale AAD $ / livraison 2025
E19: Réel | F19: Budget | G19: ▲ $ | H19: ▲ % | J19: Réel | K19: Budget | L19: ▲ $ | M19: ▲ %
C20: Ventes de Gros | E20: =E7/E$6 -> 1965.9641 | F20: =F7/F$6 -> 1765.7474 | G20: =E20-F20 -> 200.21668 | H20: =G20/F20 -> 0.1133892 | J20: =J7/J$6 -> 1991.6803 | K20: =K7/K$6 -> 2234.6109 | L20: =J20-K20 -> -242.93066 | M20: =L20/K20 -> -0.10871273
C21: Coûts | E21: =E8/E$6 -> 1517.1746 | F21: =F8/F$6 -> 1312.8615 | G21: =E21-F21 -> 204.31306 | H21: =G21/F21 -> 0.15562422 | J21: =J8/J$6 -> 1529.7096 | K21: =K8/K$6 -> 1666.5257 | L21: =J21-K21 -> -136.8161 | M21: =L21/K21 -> -0.082096607
C22: Profit brut | E22: =E9/E$6 -> 448.78946 | F22: =F9/F$6 -> 452.88584 | G22: =E22-F22 -> -4.0963791 | H22: =G22/F22 -> -0.0090450589 | J22: =J9/J$6 -> 461.9707 | K22: =K9/K$6 -> 568.08525 | L22: =J22-K22 -> -106.11456 | M22: =L22/K22 -> -0.18679337
C23: Coûts de redevance | E23: =E11/E$6 -> 69.717027 | F23: =F11/F$6 -> 99.736364 | G23: =E23-F23 -> -30.019337 | H23: =G23/F23 -> -0.30098688 | J23: =J11/J$6 -> 59.86887 | K23: =K11/K$6 -> 121.16307 | L23: =J23-K23 -> -61.294199 | M23: =L23/K23 -> -0.50588186
C24: Profit | E24: =E12/E$6 -> 379.07243 | F24: =F12/F$6 -> 353.14947 | G24: =E24-F24 -> 25.922958 | H24: =G24/F24 -> 0.073405058 | J24: =J12/J$6 -> 402.10183 | K24: =K12/K$6 -> 446.92218 | L24: =J24-K24 -> -44.820358 | M24: =L24/K24 -> -0.10028672
C25: Coûts de livraison | E25: =E14/E$6 -> 25 | F25: =F14/F$6 -> 25 | G25: =E25-F25 -> 0 | H25: =G25/F25 -> 0 | J25: =J14/J$6 -> 25 | K25: =K14/K$6 -> 25 | L25: =J25-K25 -> 0 | M25: =L25/K25 -> 0
C26: Profit net | E26: =E15/E$6 -> 354.07243 | F26: =F15/F$6 -> 328.14947 | G26: =E26-F26 -> 25.922958 | H26: =G26/F26 -> 0.078997407 | J26: =J15/J$6 -> 377.10183 | K26: =K15/K$6 -> 421.92218 | L26: =J26-K26 -> -44.820358 | M26: =L26/K26 -> -0.10622897
C29: Inscrire les GL
C30: Couts de redevance | E30: Contrôle mois | G30: =SUMIF(A37:A48,"X",E37:E48)*$G$33-E14 -> 0 | H30: frais de livraison doit être de 25$ / livraison
C31: 675L | E31: Contrôle YTD | G31: =SUMIF(B37:B48,"X",E37:E48)*$G$33-J14 -> 0 | H31: frais de livraison doit être de 25$ / livraison
C32: GL livraison
C33: 70L | E33: Coût / livraison | G33: 25
E35: NB de livraison
A36: Mois | B36: YTD | C36: Mois | E36: Réel | F36: Budgeté | G36: Coûts de redevance budgeté | H36: =+IF(Parametres!$B$3=H$38,"X","") | I36: =+IF(Parametres!$B$3=I$38,"X","") | J36: =+IF(Parametres!$B$3=J$38,"X","") | K36: =+IF(Parametres!$B$3=K$38,"X","") | L36: =+IF(Parametres!$B$3=L$38,"X","") | M36: =+IF(Parametres!$B$3=M$38,"X","") | N36: =+IF(Parametres!$B$3=N$38,"X","") | O36: =+IF(Parametres!$B$3=O$38,"X","") | ... S36: =+IF(Parametres!$B$3=S$38,"X","") | U36: =+IF(Parametres!$B$3=N$7,"X","") | V36: =+IF(Parametres!$B$3=N$7,"O","") | W36: =+IF(Parametres!$B$3=N$7,"U","") | X36: =+IF(Parametres!$B$3=Q$7,"X","") | Y36: =+IF(Parametres!$B$3=Q$7,"O","") | Z36: =+IF(Parametres!$B$3=Q$7,"U","") | AA36: =+IF(Parametres!$B$3=T$7,"X","") | AB36: =+IF(Parametres!$B$3=T$7,"O","") | AC36: =+IF(Parametres!$B$3=T$7,"U","") | AD36: =+IF(Parametres!$B$3=W$7,"X","") | AE36: =+IF(Parametres!$B$3=W$7,"O","") | AF36: =+IF(Parametres!$B$3=W$7,"U","") | AG36: =+IF(Parametres!$B$3=Z$7,"X","") | AH36: =+IF(Parametres!$B$3=Z$7,"O","") | AI36: =+IF(Parametres!$B$3=Z$7,"U","") | AJ36: =+IF(Parametres!$B$3=AC$7,"X","") | AK36: =+IF(Parametres!$B$3=AC$7,"O","") | AL36: =+IF(Parametres!$B$3=AC$7,"U","") | AM36: =+IF(Parametres!$B$3=AF$7,"X","") | AN36: =+IF(Parametres!$B$3=AF$7,"O","") | AO36: =+IF(Parametres!$B$3=AF$7,"U","")
A37: =+IF(Parametres!$B$3=$C37,"X","") | B37: =+IF(VLOOKUP($C37,Parametres!$K$3:$N$14,4,0)="X","X","") -> X | C37: Janvier | E37: 14 | F37: 22 | G37: 2662.04
A38: =+IF(Parametres!$B$3=$C38,"X","") | B38: =+IF(VLOOKUP($C38,Parametres!$K$3:$N$14,4,0)="X","X","") -> X | C38: Février | E38: 34 | F38: 22 | G38: 2686.35
A39: =+IF(Parametres!$B$3=$C39,"X","") | B39: =+IF(VLOOKUP($C39,Parametres!$K$3:$N$14,4,0)="X","X","") -> X | C39: Mars | E39: 30 | F39: 22 | G39: 3119.76
A40: =+IF(Parametres!$B$3=$C40,"X","") -> X | B40: =+IF(VLOOKUP($C40,Parametres!$K$3:$N$14,4,0)="X","X","") -> X | C40: Avril | E40: 37 | F40: 22 | G40: 2194.2
A41: =+IF(Parametres!$B$3=$C41,"X","") | B41: =+IF(VLOOKUP($C41,Parametres!$K$3:$N$14,4,0)="X","X","") | C41: Mai | F41: 22 | G41: 3569.08
A42: =+IF(Parametres!$B$3=$C42,"X","") | B42: =+IF(VLOOKUP($C42,Parametres!$K$3:$N$14,4,0)="X","X","") | C42: Juin | F42: 22 | G42: 2969.14
A43: =+IF(Parametres!$B$3=$C43,"X","") | B43: =+IF(VLOOKUP($C43,Parametres!$K$3:$N$14,4,0)="X","X","") | C43: Juillet | F43: 22 | G43: 2322.39
A44: =+IF(Parametres!$B$3=$C44,"X","") | B44: =+IF(VLOOKUP($C44,Parametres!$K$3:$N$14,4,0)="X","X","") | C44: Août | F44: 22 | G44: 2796.57
A45: =+IF(Parametres!$B$3=$C45,"X","") | B45: =+IF(VLOOKUP($C45,Parametres!$K$3:$N$14,4,0)="X","X","") | C45: Septembre | F45: 22 | G45: 3451.22
A46: =+IF(Parametres!$B$3=$C46,"X","") | B46: =+IF(VLOOKUP($C46,Parametres!$K$3:$N$14,4,0)="X","X","") | C46: Octobre | F46: 22 | G46: 2901.53
A47: =+IF(Parametres!$B$3=$C47,"X","") | B47: =+IF(VLOOKUP($C47,Parametres!$K$3:$N$14,4,0)="X","X","") | C47: Novembre | F47: 22 | G47: 2924.65
A48: =+IF(Parametres!$B$3=$C48,"X","") | B48: =+IF(VLOOKUP($C48,Parametres!$K$3:$N$14,4,0)="X","X","") | C48: Décembre | F48: 22 | G48: 2943.06

Sheet Print_Mois
C1: =Parametres!B1 -> BMW Sherbrooke | K1: Véhicules neufs | S1: =CONCATENATE("Réalisé,"," ",Parametres!B3," ",Parametres!B4) -> Réalisé, Avril 2025
D2: X | E2: O | F2: U | J2: NB | L2: $ | O2: X | P2: O | Q2: U
D3: BUDGET ORIGINAL | J3: RÉALISATION | M3: ÉCART réel / Budget | O3: ANNÉE PRÉCÉDENTE | R3: ECART (réel/ Ann.Préc.)
D4: UNITE | E4: $P/UNITÉ | F4: $PROFITS | J4: UNITE | K4: $P/UNITE | L4: $PROFITS | M4: UNFTÉ | N4: $PROFITS | O4: UNITE | P4: $P/UNITÉ | Q4: $PROFITS | R4: UNITE | S4: $PROFITS
A5: =+B5&C5 -> Véhicules neufsVentes nettes | B5: =+$K$1 -> Véhicules neufs | C5: Ventes nettes | F5: =+INDEX('Budget original'!$A$2:$AO$501,MATCH($A5,'Budget original'!$A$2:$A$501,0),MATCH(F$2,'Budget original'!$A$2:$AO$2,0)) -> 3027277.1 | L5: =-SUMIFS(BV_Data_An_Cour!$O:$O,BV_Data_An_Cour!$X:$X,"Oui",BV_Data_An_Cour!$U:$U,$B5) -> 2822748.8 | Q5: {=+INDEX('Réel 2024'!$A$2:$AO$501,MATCH($A5,'Réel 2024'!$A$2:$A$501,0),MATCH(Q$2,'Réel 2024'!$A$2:$AO$2,0))} -> 2814437.6
A6: =+B6&C6 -> Véhicules neufsAutos détail | B6: =+$K$1 -> Véhicules neufs | C6: Autos détail | D6: =+INDEX('Budget original'!$A$2:$AO$501,MATCH($A6,'Budget original'!$A$2:$A$501,0),MATCH(D$2,'Budget original'!$A$2:$AO$2,0)) -> 10 | E6: =IF(D6=0,0,F6/D6) -> 4306.3953 | F6: =+INDEX('Budget original'!$A$2:$AO$501,MATCH($A6,'Budget original'!$A$2:$A$501,0),MATCH(F$2,'Budget original'!$A$2:$AO$2,0)) -> 43063.953 | J6: =-SUMIFS(BV_Data_An_Cour!$O:$O,BV_Data_An_Cour!$U:$U,$B6,BV_Data_An_Cour!$V:$V,$C6,BV_Data_An_Cour!$W:$W,J$2) -> 6 | K6: =IF(J6=0,0,L6/J6) -> 6338.2117 | L6: =-SUMIFS(BV_Data_An_Cour!$O:$O,BV_Data_An_Cour!$U:$U,$B6,BV_Data_An_Cour!$V:$V,$C6,BV_Data_An_Cour!$W:$W,L$2) -> 38029.27 | M6: =J6-D6 -> -4 | N6: =L6-F6 -> -5034.6835 | O6: =+INDEX('Réel 2024'!$A$2:$AO$501,MATCH($A6,'Réel 2024'!$A$2:$A$501,0),MATCH(O$2,'Réel 2024'!$A$2:$AO$2,0)) -> 13 | P6: =IF(O6=0,0,Q6/O6) -> 5336.7323 | Q6: {=+INDEX('Réel 2024'!$A$2:$AO$501,MATCH($A6,'Réel 2024'!$A$2:$A$501,0),MATCH(Q$2,'Réel 2024'!$A$2:$AO$2,0))} -> 69377.52 | R6: =J6-O6 -> -7 | S6: =L6-Q6 -> -31348.25
A7: =+B7&C7 -> Véhicules neufsCamions détail | B7: =+$K$1 -> Véhicules neufs | C7: Camions détail | D7: =+INDEX('Budget original'!$A$2:$AO$501,MATCH($A7,'Budget original'!$A$2:$A$501,0),MATCH(D$2,'Budget original'!$A$2:$AO$2,0)) -> 18 | E7: =IF(D7=0,0,F7/D7) -> 4000.3311 | F7: =+INDEX('Budget original'!$A$2:$AO$501,MATCH($A7,'Budget original'!$A$2:$A$501,0),MATCH(F$2,'Budget original'!$A$2:$AO$2,0)) -> 72005.96 | J7: =-SUMIFS(BV_Data_An_Cour!$O:$O,BV_Data_An_Cour!$U:$U,$B7,BV_Data_An_Cour!$V:$V,$C7,BV_Data_An_Cour!$W:$W,J$2) -> 15 | K7: =IF(J7=0,0,L7/J7) -> 4719.5127 | L7: =-SUMIFS(BV_Data_An_Cour!$O:$O,BV_Data_An_Cour!$U:$U,$B7,BV_Data_An_Cour!$V:$V,$C7,BV_Data_An_Cour!$W:$W,L$2) -> 70792.69 | M7: =J7-D7 -> -3 | N7: =L7-F7 -> -1213.2703 | O7: {=+INDEX('Réel 2024'!$A$2:$AO$501,MATCH($A7,'Réel 2024'!$A$2:$A$501,0),MATCH(O$2,'Réel 2024'!$A$2:$AO$2,0))} -> 12 | P7: =IF(O7=0,0,Q7/O7) -> 4634.92 | Q7: {=+INDEX('Réel 2024'!$A$2:$AO$501,MATCH($A7,'Réel 2024'!$A$2:$A$501,0),MATCH(Q$2,'Réel 2024'!$A$2:$AO$2,0))} -> 55619.04 | R7: =J7-O7 -> 3 | S7: =L7-Q7 -> 15173.65
A8: =+B8&C8 -> Véhicules neufsSprinter | B8: =+$K$1 -> Véhicules neufs | C8: Sprinter | D8: =+INDEX('Budget original'!$A$2:$AO$501,MATCH($A8,'Budget original'!$A$2:$A$501,0),MATCH(D$2,'Budget original'!$A$2:$AO$2,0)) -> 0 | E8: =IF(D8=0,0,F8/D8) -> 0 | F8: =+INDEX('Budget original'!$A$2:$AO$501,MATCH($A8,'Budget original'!$A$2:$A$501,0),MATCH(F$2,'Budget original'!$A$2:$AO$2,0)) -> 0 | J8: =-SUMIFS(BV_Data_An_Cour!$O:$O,BV_Data_An_Cour!$U:$U,$B8,BV_Data_An_Cour!$V:$V,$C8,BV_Data_An_Cour!$W:$W,J$2) -> 0 | K8: =IF(J8=0,0,L8/J8) -> 0 | L8: =-SUMIFS(BV_Data_An_Cour!$O:$O,BV_Data_An_Cour!$U:$U,$B8,BV_Data_An_Cour!$V:$V,$C8,BV_Data_An_Cour!$W:$W,L$2) -> 0 | M8: =J8-D8 -> 0 | N8: =L8-F8 -> 0 | O8: {=+INDEX('Réel 2024'!$A$2:$AO$501,MATCH($A8,'Réel 2024'!$A$2:$A$501,0),MATCH(O$2,'Réel 2024'!$A$2:$AO$2,0))} -> 0 | P8: =IF(O8=0,0,Q8/O8) -> 0 | Q8: {=+INDEX('Réel 2024'!$A$2:$AO$501,MATCH($A8,'Réel 2024'!$A$2:$A$501,0),MATCH(Q$2,'Réel 2024'!$A$2:$AO$2,0))} -> 0 | R8: =J8-O8 -> 0 | S8: =L8-Q8 -> 0
A9: =+B9&C9 -> Véhicules neufsMoto détail | B9: =+$K$1 -> Véhicules neufs | C9: Moto détail | D9: =+INDEX('Budget original'!$A$2:$AO$501,MATCH($A9,'Budget original'!$A$2:$A$501,0),MATCH(D$2,'Budget original'!$A$2:$AO$2,0)) -> 0 | E9: =IF(D9=0,0,F9/D9) -> 0 | F9: =+INDEX('Budget original'!$A$2:$AO$501,MATCH($A9,'Budget original'!$A$2:$A$501,0),MATCH(F$2,'Budget original'!$A$2:$AO$2,0)) -> 0 | J9: =-SUMIFS(BV_Data_An_Cour!$O:$O,BV_Data_An_Cour!$U:$U,$B9,BV_Data_An_Cour!$V:$V,$C9,BV_Data_An_Cour!$W:$W,J$2) -> 0 | K9: =IF(J9=0,0,L9/J9) -> 0 | L9: =-SUMIFS(BV_Data_An_Cour!$O:$O,BV_Data_An_Cour!$U:$U,$B9,BV_Data_An_Cour!$V:$V,$C9,BV_Data_An_Cour!$W:$W,L$2) -> 0 | M9: =J9-D9 -> 0 | N9: =L9-F9 -> 0 | O9: {=+INDEX('Réel 2024'!$A$2:$AO$501,MATCH($A9,'Réel 2024'!$A$2:$A$501,0),MATCH(O$2,'Réel 2024'!$A$2:$AO$2,0))} -> 0 | P9: =IF(O9=0,0,Q9/O9) -> 0 | Q9: {=+INDEX('Réel 2024'!$A$2:$AO$501,MATCH($A9,'Réel 2024'!$A$2:$A$501,0),MATCH(Q$2,'Réel 2024'!$A$2:$AO$2,0))} -> 0 | R9: =J9-O9 -> 0 | S9: =L9-Q9 -> 0
A10: =+B10&C10 -> Véhicules neufs[...] | B10: =+$K$1 -> Véhicules neufs | C10: [...] | D10: =+INDEX('Budget original'!$A$2:$AO$501,MATCH($A10,'Budget original'!$A$2:$A$501,0),MATCH(D$2,'Budget original'!$A$2:$AO$2,0)) -> 0 | E10: =IF(D10=0,0,F10/D10) -> 0 | F10: =+INDEX('Budget original'!$A$2:$AO$501,MATCH($A10,'Budget original'!$A$2:$A$501,0),MATCH(F$2,'Budget original'!$A$2:$AO$2,0)) -> 0 | J10: =-SUMIFS(BV_Data_An_Cour!$O:$O,BV_Data_An_Cour!$U:$U,$B10,BV_Data_An_Cour!$V:$V,$C10,BV_Data_An_Cour!$W:$W,J$2) -> 0 | K10: =IF(J10=0,0,L10/J10) -> 0 | L10: =-SUMIFS(BV_Data_An_Cour!$O:$O,BV_Data_An_Cour!$U:$U,$B10,BV_Data_An_Cour!$V:$V,$C10,BV_Data_An_Cour!$W:$W,L$2) -> 0 | M10: =J10-D10 -> 0 | N10: =L10-F10 -> 0 | O10: {=+INDEX('Réel 2024'!$A$2:$AO$501,MATCH($A10,'Réel 2024'!$A$2:$A$501,0),MATCH(O$2,'Réel 2024'!$A$2:$AO$2,0))} -> 0 | P10: =IF(O10=0,0,Q10/O10) -> 0 | Q10: {=+INDEX('Réel 2024'!$A$2:$AO$501,MATCH($A10,'Réel 2024'!$A$2:$A$501,0),MATCH(Q$2,'Réel 2024'!$A$2:$AO$2,0))} -> 0 | R10: =J10-O10 -> 0 | S10: =L10-Q10 -> 0
A11: =+B11&C11 -> Véhicules neufs[...] | B11: =+$K$1 -> Véhicules neufs | C11: [...] | D11: =+INDEX('Budget original'!$A$2:$AO$501,MATCH($A11,'Budget original'!$A$2:$A$501,0),MATCH(D$2,'Budget original'!$A$2:$AO$2,0)) -> 0 | E11: =IF(D11=0,0,F11/D11) -> 0 | F11: =+INDEX('Budget original'!$A$2:$AO$501,MATCH($A11,'Budget original'!$A$2:$A$501,0),MATCH(F$2,'Budget original'!$A$2:$AO$2,0)) -> 0 | J11: =-SUMIFS(BV_Data_An_Cour!$O:$O,BV_Data_An_Cour!$U:$U,$B11,BV_Data_An_Cour!$V:$V,$C11,BV_Data_An_Cour!$W:$W,J$2) -> 0 | K11: =IF(J11=0,0,L11/J11) -> 0 | L11: =-SUMIFS(BV_Data_An_Cour!$O:$O,BV_Data_An_Cour!$U:$U,$B11,BV_Data_An_Cour!$V:$V,$C11,BV_Data_An_Cour!$W:$W,L$2) -> 0 | M11: =J11-D11 -> 0 | N11: =L11-F11 -> 0 | O11: {=+INDEX('Réel 2024'!$A$2:$AO$501,MATCH($A11,'Réel 2024'!$A$2:$A$501,0),MATCH(O$2,'Réel 2024'!$A$2:$AO$2,0))} -> 0 | P11: =IF(O11=0,0,Q11/O11) -> 0 | Q11: {=+INDEX('Réel 2024'!$A$2:$AO$501,MATCH($A11,'Réel 2024'!$A$2:$A$501,0),MATCH(Q$2,'Réel 2024'!$A$2:$AO$2,0))} -> 0 | R11: =J11-O11 -> 0 | S11: =L11-Q11 -> 0
A12: =+B12&C12 -> Véhicules neufs[...] | B12: =+$K$1 -> Véhicules neufs | C12: [...] | D12: =+INDEX('Budget original'!$A$2:$AO$501,MATCH($A12,'Budget original'!$A$2:$A$501,0),MATCH(D$2,'Budget original'!$A$2:$AO$2,0)) -> 0 | E12: =IF(D12=0,0,F12/D12) -> 0 | F12: =+INDEX('Budget original'!$A$2:$AO$501,MATCH($A12,'Budget original'!$A$2:$A$501,0),MATCH(F$2,'Budget original'!$A$2:$AO$2,0)) -> 0 | J12: =-SUMIFS(BV_Data_An_Cour!$O:$O,BV_Data_An_Cour!$U:$U,$B12,BV_Data_An_Cour!$V:$V,$C12,BV_Data_An_Cour!$W:$W,J$2) -> 0 | K12: =IF(J12=0,0,L12/J12) -> 0 | L12: =-SUMIFS(BV_Data_An_Cour!$O:$O,BV_Data_An_Cour!$U:$U,$B12,BV_Data_An_Cour!$V:$V,$C12,BV_Data_An_Cour!$W:$W,L$2) -> 0 | M12: =J12-D12 -> 0 | N12: =L12-F12 -> 0 | O12: {=+INDEX('Réel 2024'!$A$2:$AO$501,MATCH($A12,'Réel 2024'!$A$2:$A$501,0),MATCH(O$2,'Réel 2024'!$A$2:$AO$2,0))} -> 0 | P12: =IF(O12=0,0,Q12/O12) -> 0 | Q12: {=+INDEX('Réel 2024'!$A$2:$AO$501,MATCH($A12,'Réel 2024'!$A$2:$A$501,0),MATCH(Q$2,'Réel 2024'!$A$2:$AO$2,0))} -> 0 | R12: =J12-O12 -> 0 | S12: =L12-Q12 -> 0
A13: =+B13&C13 -> Véhicules neufsTotal Neufs | B13: =+$K$1 -> Véhicules neufs | C13: Total Neufs | D13: =+SUM(D6:D12) -> 28 | E13: =IF(D13<=0,0,F13/D13) -> 4109.6398 | F13: =+SUM(F6:F12) -> 115069.91 | J13: =+SUM(J6:J12) -> 21 | K13: =IF(J13<=0,0,L13/J13) -> 5181.9981 | L13: =+SUM(L6:L12) -> 108821.96 | M13: =+SUM(M6:M12) -> -7 | N13: =+SUM(N6:N12) -> -6247.9538 | O13: =+SUM(O6:O12) -> 25 | P13: =IF(O13<=0,0,Q13/O13) -> 4999.8624 | Q13: =+SUM(Q6:Q12) -> 124996.56 | R13: =+SUM(R6:R12) -> -4 | S13: =+SUM(S6:S12) -> -16174.6
A14: =+B14&C14 -> Véhicules neufs | B14: =+$K$1 -> Véhicules neufs | M14: =IF(D13=0,0,M13/D13) -> -0.25 | N14: =IF(F13=0,0,N13/F13) -> -0.054297023 | R14: =R13/O13 -> -0.16 | S14: =IF(Q13=0,0,(S13/Q13)) -> -0.12940036
A15: =+B15&C15 -> Véhicules neufsEx-Démos et courtoisies | B15: =+$K$1 -> Véhicules neufs | C15: Ex-Démos et courtoisies | D15: =+INDEX('Budget original'!$A$2:$AO$501,MATCH($A15,'Budget original'!$A$2:$A$501,0),MATCH(D$2,'Budget original'!$A$2:$AO$2,0)) -> 4 | E15: =IF(D15=0,0,F15/D15) -> 750 | F15: =+INDEX('Budget original'!$A$2:$AO$501,MATCH($A15,'Budget original'!$A$2:$A$501,0),MATCH(F$2,'Budget original'!$A$2:$AO$2,0)) -> 3000 | J15: =-SUMIFS(BV_Data_An_Cour!$O:$O,BV_Data_An_Cour!$U:$U,$B15,BV_Data_An_Cour!$V:$V,$C15,BV_Data_An_Cour!$W:$W,J$2) -> 8 | K15: =IF(J15=0,0,L15/J15) -> 2225.18 | L15: =-SUMIFS(BV_Data_An_Cour!$O:$O,BV_Data_An_Cour!$U:$U,$B15,BV_Data_An_Cour!$V:$V,$C15,BV_Data_An_Cour!$W:$W,L$2) -> 17801.44 | M15: =J15-D15 -> 4 | N15: =L15-F15 -> 14801.44 | O15: {=+INDEX('Réel 2024'!$A$2:$AO$501,MATCH($A15,'Réel 2024'!$A$2:$A$501,0),MATCH(O$2,'Réel 2024'!$A$2:$AO$2,0))} -> 5 | P15: =IF(O15=0,0,Q15/O15) -> 3098.878 | Q15: {=+INDEX('Réel 2024'!$A$2:$AO$501,MATCH($A15,'Réel 2024'!$A$2:$A$501,0),MATCH(Q$2,'Réel 2024'!$A$2:$AO$2,0))} -> 15494.39 | R15: =J15-O15 -> 3 | S15: =L15-Q15 -> 2307.05
A16: =+B16&C16 -> Véhicules neufs | B16: =+$K$1 -> Véhicules neufs
A17: =+B17&C17 -> Véhicules neufsFlottes | B17: =+$K$1 -> Véhicules neufs | C17: Flottes | D17: =+INDEX('Budget original'!$A$2:$AO$501,MATCH($A17,'Budget original'!$A$2:$A$501,0),MATCH(D$2,'Budget original'!$A$2:$AO$2,0)) -> 1 | E17: =IF(D17=0,0,F17/D17) -> 0 | F17: =+INDEX('Budget original'!$A$2:$AO$501,MATCH($A17,'Budget original'!$A$2:$A$501,0),MATCH(F$2,'Budget original'!$A$2:$AO$2,0)) -> 0 | J17: =-SUMIFS(BV_Data_An_Cour!$O:$O,BV_Data_An_Cour!$U:$U,$B17,BV_Data_An_Cour!$V:$V,$C17,BV_Data_An_Cour!$W:$W,J$2) -> 0 | K17: =IF(J17=0,0,L17/J17) -> 0 | L17: =-SUMIFS(BV_Data_An_Cour!$O:$O,BV_Data_An_Cour!$U:$U,$B17,BV_Data_An_Cour!$V:$V,$C17,BV_Data_An_Cour!$W:$W,L$2) -> 0 | M17: =J17-D17 -> -1 | N17: =L17-F17 -> 0 | O17: {=+INDEX('Réel 2024'!$A$2:$AO$501,MATCH($A17,'Réel 2024'!$A$2:$A$501,0),MATCH(O$2,'Réel 2024'!$A$2:$AO$2,0))} -> 0 | P17: =IF(O17=0,0,Q17/O17) -> 0 | Q17: {=+INDEX('Réel 2024'!$A$2:$AO$501,MATCH($A17,'Réel 2024'!$A$2:$A$501,0),MATCH(Q$2,'Réel 2024'!$A$2:$AO$2,0))} -> 0 | R17: =J17-O17 -> 0 | S17: =L17-Q17 -> 0
A18: =+B18&C18 -> Véhicules neufs | B18: =+$K$1 -> Véhicules neufs
A19: =+B19&C19 -> Véhicules neufsRachat bail | B19: =+$K$1 -> Véhicules neufs | C19: Rachat bail | D19: =+INDEX('Budget original'!$A$2:$AO$501,MATCH($A19,'Budget original'!$A$2:$A$501,0),MATCH(D$2,'Budget original'!$A$2:$AO$2,0)) -> 0 | E19: =IF(D19=0,0,F19/D19) -> 0 | F19: =+INDEX('Budget original'!$A$2:$AO$501,MATCH($A19,'Budget original'!$A$2:$A$501,0),MATCH(F$2,'Budget original'!$A$2:$AO$2,0)) -> 3500.0986 | L19: =-SUMIFS(BV_Data_An_Cour!$O:$O,BV_Data_An_Cour!$U:$U,$B19,BV_Data_An_Cour!$V:$V,$C19,BV_Data_An_Cour!$W:$W,L$2) -> 3995.39 | N19: =L19-F19 -> 495.29136 | Q19: {=+INDEX('Réel 2024'!$A$2:$AO$501,MATCH($A19,'Réel 2024'!$A$2:$A$501,0),MATCH(Q$2,'Réel 2024'!$A$2:$AO$2,0))} -> 3495.39 | R19: =O19-K19 -> 0 | S19: =L19-Q19 -> 500
A20: =+B20&C20 -> Véhicules neufs | B20: =+$K$1 -> Véhicules neufs
A21: =+B21&C21 -> Véhicules neufsRev. Finances | B21: =+$K$1 -> Véhicules neufs | C21: Rev. Finances | D21: =+INDEX('Budget original'!$A$2:$AO$501,MATCH($A21,'Budget original'!$A$2:$A$501,0),MATCH(D$2,'Budget original'!$A$2:$AO$2,0)) -> 0 | E21: =IF(D21=0,0,F21/D21) -> 0 | F21: =+INDEX('Budget original'!$A$2:$AO$501,MATCH($A21,'Budget original'!$A$2:$A$501,0),MATCH(F$2,'Budget original'!$A$2:$AO$2,0)) -> 800 | K21: =IF(J13=0,0,L21/(J13+J15)) -> 16.962414 | L21: =-SUMIFS(BV_Data_An_Cour!$O:$O,BV_Data_An_Cour!$U:$U,$B21,BV_Data_An_Cour!$V:$V,$C21,BV_Data_An_Cour!$W:$W,L$2) -> 491.91 | N21: =L21-F21 -> -308.09 | Q21: {=+INDEX('Réel 2024'!$A$2:$AO$501,MATCH($A21,'Réel 2024'!$A$2:$A$501,0),MATCH(Q$2,'Réel 2024'!$A$2:$AO$2,0))} -> 0 | R21: =O21-K21 -> -16.962414 | S21: =L21-Q21 -> 491.91
A22: =+B22&C22 -> Véhicules neufsRev. Protections | B22: =+$K$1 -> Véhicules neufs | C22: Rev. Protections | D22: =+INDEX('Budget original'!$A$2:$AO$501,MATCH($A22,'Budget original'!$A$2:$A$501,0),MATCH(D$2,'Budget original'!$A$2:$AO$2,0)) -> 0 | E22: =IF(D22=0,0,F22/D22) -> 0 | F22: =+INDEX('Budget original'!$A$2:$AO$501,MATCH($A22,'Budget original'!$A$2:$A$501,0),MATCH(F$2,'Budget original'!$A$2:$AO$2,0)) -> 36800 | K22: =IF(J13=0,0,L22/(J13+J15)) -> 1674.7852 | L22: =-SUMIFS(BV_Data_An_Cour!$O:$O,BV_Data_An_Cour!$U:$U,$B22,BV_Data_An_Cour!$V:$V,$C22,BV_Data_An_Cour!$W:$W,L$2) -> 48568.77 | N22: =L22-F22 -> 11768.77 | Q22: {=+INDEX('Réel 2024'!$A$2:$AO$501,MATCH($A22,'Réel 2024'!$A$2:$A$501,0),MATCH(Q$2,'Réel 2024'!$A$2:$AO$2,0))} -> 38800.24 | R22: =O22-K22 -> -1674.7852 | S22: =L22-Q22 -> 9768.53
A23: =+B23&C23 -> Véhicules neufsRev. Autres | B23: =+$K$1 -> Véhicules neufs | C23: Rev. Autres | D23: =+INDEX('Budget original'!$A$2:$AO$501,MATCH($A23,'Budget original'!$A$2:$A$501,0),MATCH(D$2,'Budget original'!$A$2:$AO$2,0)) -> 0 | E23: =IF(D23=0,0,F23/D23) -> 0 | F23: =+INDEX('Budget original'!$A$2:$AO$501,MATCH($A23,'Budget original'!$A$2:$A$501,0),MATCH(F$2,'Budget original'!$A$2:$AO$2,0)) -> 15360 | K23: =IF(J13=0,0,L23/(J13+J15)) -> 843.75828 | L23: =-SUMIFS(BV_Data_An_Cour!$O:$O,BV_Data_An_Cour!$U:$U,$B23,BV_Data_An_Cour!$V:$V,$C23,BV_Data_An_Cour!$W:$W,L$2) -> 24468.99 | N23: =L23-F23 -> 9108.99 | Q23: {=+INDEX('Réel 2024'!$A$2:$AO$501,MATCH($A23,'Réel 2024'!$A$2:$A$501,0),MATCH(Q$2,'Réel 2024'!$A$2:$AO$2,0))} -> 13459.04 | R23: =O23-K23 -> -843.75828 | S23: =L23-Q23 -> 11009.95
A24: =+B24&C24 -> Véhicules neufsTotal F&I | B24: =+$K$1 -> Véhicules neufs | C24: Total F&I | D24: =+D15+D13 -> 32 | E24: =IF(D24<=0,0,F24/D24) -> 1655 | F24: =F21+F22+F23 -> 52960 | J24: =+J15+J13 -> 29 | K24: =IF(J24<=0,0,L24/J24) -> 2535.5059 | L24: =L21+L22+L23 -> 73529.67 | M24: =J24-D24 -> -3 | N24: =L24-F24 -> 20569.67 | O24: =+O15+O13 -> 30 | P24: =IF(O24<=0,0,Q24/O24) -> 1741.976 | Q24: =Q21+Q22+Q23 -> 52259.28 | S24: =L24-Q24 -> 21270.39
A25: =+B25&C25 -> Véhicules neufs | B25: =+$K$1 -> Véhicules neufs | N25: =IF(N24=0,0,N24/F24) -> 0.38840011 | S25: =IF(Q24=0,0,(S24/Q24)) -> 0.40701651
A26: =+B26&C26 -> Véhicules neufs | B26: =+$K$1 -> Véhicules neufs
A27: =+B27&C27 -> Véhicules neufsTotal Dépt. Neufs | B27: =+$K$1 -> Véhicules neufs | C27: Total Dépt. Neufs | D27: =+D13+D15+D17 -> 33 | E27: =IF(D27<=0,0,F27/D27) -> 5288.7883 | F27: =F13+F17+F24+F19+F15 -> 174530.01 | J27: =+J13+J15+J17 -> 29 | K27: =IF(J27<=0,0,L27/J27) -> 7039.6021 | L27: =L13+L17+L24+L19+L15 -> 204148.46 | M27: =J27-D27 -> -4 | N27: =L27-F27 -> 29618.448 | O27: =+O13+O15+O17 -> 30 | P27: =IF(O27<=0,0,Q27/O27) -> 6541.5207 | Q27: =Q13+Q17+Q24+Q19+Q15 -> 196245.62 | R27: =J27-O27 -> -1 | S27: =L27-Q27 -> 7902.84 | V27: FORECAST | W27: 185250 | X27: =L27-W27 -> 18898.46
A28: =+B28&C28 -> Véhicules neufs | B28: =+$K$1 -> Véhicules neufs | M28: =M27/D27 -> -0.12121212 | N28: =N27/F27 -> 0.16970404 | R28: =R27/O27 -> -0.033333333 | S28: =IF(Q27=0,0,S27/Q27) -> 0.040270147 | W28: 29 | X28: =J27-W28 -> 0
A29: =+B29&C29 -> Véhicules neufs | B29: =+$K$1 -> Véhicules neufs
A30: =+B30&C30 -> Véhicules neufsDEPENSES | B30: =+$K$1 -> Véhicules neufs | C30: DEPENSES
A31: =+B31&C31 -> Véhicules neufsComm. vendeurs | B31: =+$K$1 -> Véhicules neufs | C31: Comm. vendeurs | D31: =F31/(F13+F15) -> 0.2815412 | E31: =F31/D$24 -> 1038.7983 | F31: =+INDEX('Budget original'!$A$2:$AO$501,MATCH($A31,'Budget original'!$A$2:$A$501,0),MATCH(F$2,'Budget original'!$A$2:$AO$2,0)) -> 33241.545 | J31: =L31/(L13+L15) -> 0.24913105 | K31: =IF(L31=0,0,L31/J$24) -> 1087.7869 | L31: =SUMIFS(BV_Data_An_Cour!$O:$O,BV_Data_An_Cour!$U:$U,$B31,BV_Data_An_Cour!$V:$V,$C31,BV_Data_An_Cour!$W:$W,L$2) -> 31545.82 | N31: =L31-F31 -> -1695.7252 | O31: =Q31/(Q13+Q15+Q17) -> 0.26502027 | P31: =Q31/O$24 -> 1241.0983 | Q31: {=+INDEX('Réel 2024'!$A$2:$AO$501,MATCH($A31,'Réel 2024'!$A$2:$A$501,0),MATCH(Q$2,'Réel 2024'!$A$2:$AO$2,0))} -> 37232.95 | S31: =L31-Q31 -> -5687.13
A32: =+B32&C32 -> Véhicules neufsComm. F&I | B32: =+$K$1 -> Véhicules neufs | C32: Comm. F&I | D32: =F32/F24 -> 0.275 | E32: =F32/D$24 -> 455.125 | F32: =+INDEX('Budget original'!$A$2:$AO$501,MATCH($A32,'Budget original'!$A$2:$A$501,0),MATCH(F$2,'Budget original'!$A$2:$AO$2,0)) -> 14564 | J32: =L32/L24 -> 0.34564999 | K32: =IF(L32=0,0,L32/J$24) -> 876.39759 | L32: =SUMIFS(BV_Data_An_Cour!$O:$O,BV_Data_An_Cour!$U:$U,$B32,BV_Data_An_Cour!$V:$V,$C32,BV_Data_An_Cour!$W:$W,L$2) -> 25415.53 | N32: =L32-F32 -> 10851.53 | O32: =Q32/Q24 -> 0.4073422 | P32: =Q32/O$24 -> 709.58033 | Q32: {=+INDEX('Réel 2024'!$A$2:$AO$501,MATCH($A32,'Réel 2024'!$A$2:$A$501,0),MATCH(Q$2,'Réel 2024'!$A$2:$AO$2,0))} -> 21287.41 | S32: =L32-Q32 -> 4128.12 | V32: Farrah 30% + vendeur à 4 ou 5 %
A33: =+B33&C33 -> Véhicules neufsFrais de livraison | B33: =+$K$1 -> Véhicules neufs | C33: Frais de livraison | E33: =F33/D$24 -> 130 | F33: =+INDEX('Budget original'!$A$2:$AO$501,MATCH($A33,'Budget original'!$A$2:$A$501,0),MATCH(F$2,'Budget original'!$A$2:$AO$2,0)) -> 4160 | K33: =IF(L33=0,0,L33/J$24) -> 132.36483 | L33: =SUMIFS(BV_Data_An_Cour!$O:$O,BV_Data_An_Cour!$U:$U,$B33,BV_Data_An_Cour!$V:$V,$C33,BV_Data_An_Cour!$W:$W,L$2) -> 3838.58 | N33: =L33-F33 -> -321.42 | P33: =Q33/O$24 -> 73.194667 | Q33: {=+INDEX('Réel 2024'!$A$2:$AO$501,MATCH($A33,'Réel 2024'!$A$2:$A$501,0),MATCH(Q$2,'Réel 2024'!$A$2:$AO$2,0))} -> 2195.84 | S33: =L33-Q33 -> 1642.74
A34: =+B34&C34 -> Véhicules neufsService gratuit 1 | B34: =+$K$1 -> Véhicules neufs | C34: Service gratuit 1 | E34: =F34/D$24 -> 37 | F34: =+INDEX('Budget original'!$A$2:$AO$501,MATCH($A34,'Budget original'!$A$2:$A$501,0),MATCH(F$2,'Budget original'!$A$2:$AO$2,0)) -> 1184 | K34: =IF(L34=0,0,L34/J$24) -> 62.720345 | L34: =SUMIFS(BV_Data_An_Cour!$O:$O,BV_Data_An_Cour!$U:$U,$B34,BV_Data_An_Cour!$V:$V,$C34,BV_Data_An_Cour!$W:$W,L$2) -> 1818.89 | N34: =L34-F34 -> 634.89 | P34: =Q34/O$24 -> 26.899 | Q34: {=+INDEX('Réel 2024'!$A$2:$AO$501,MATCH($A34,'Réel 2024'!$A$2:$A$501,0),MATCH(Q$2,'Réel 2024'!$A$2:$AO$2,0))} -> 806.97 | S34: =L34-Q34 -> 1011.92
A35: =+B35&C35 -> Véhicules neufsEntretien stock | B35: =+$K$1 -> Véhicules neufs | C35: Entretien stock | E35: =F35/D$24 -> 59.6875 | F35: =+INDEX('Budget original'!$A$2:$AO$501,MATCH($A35,'Budget original'!$A$2:$A$501,0),MATCH(F$2,'Budget original'!$A$2:$AO$2,0)) -> 1910 | K35: =IF(L35=0,0,L35/J$24) -> 37.223793 | L35: =SUMIFS(BV_Data_An_Cour!$O:$O,BV_Data_An_Cour!$U:$U,$B35,BV_Data_An_Cour!$V:$V,$C35,BV_Data_An_Cour!$W:$W,L$2) -> 1079.49 | N35: =L35-F35 -> -830.51 | P35: =Q35/O$24 -> 62.396 | Q35: {=+INDEX('Réel 2024'!$A$2:$AO$501,MATCH($A35,'Réel 2024'!$A$2:$A$501,0),MATCH(Q$2,'Réel 2024'!$A$2:$AO$2,0))} -> 1871.88 | S35: =L35-Q35 -> -792.39
A36: =+B36&C36 -> Véhicules neufsPublicité 1 | B36: =+$K$1 -> Véhicules neufs | C36: Publicité 1 | E36: =F36/D$24 -> 513.97059 | F36: =+INDEX('Budget original'!$A$2:$AO$501,MATCH($A36,'Budget original'!$A$2:$A$501,0),MATCH(F$2,'Budget original'!$A$2:$AO$2,0)) -> 16447.059 | K36: =IF(L36=0,0,L36/J$24) -> 595.14138 | L36: =SUMIFS(BV_Data_An_Cour!$O:$O,BV_Data_An_Cour!$U:$U,$B36,BV_Data_An_Cour!$V:$V,$C36,BV_Data_An_Cour!$W:$W,L$2) -> 17259.1 | N36: =L36-F36 -> 812.04118 | P36: =Q36/O$24 -> 512.11267 | Q36: {=+INDEX('Réel 2024'!$A$2:$AO$501,MATCH($A36,'Réel 2024'!$A$2:$A$501,0),MATCH(Q$2,'Réel 2024'!$A$2:$AO$2,0))} -> 15363.38 | S36: =L36-Q36 -> 1895.72
A37: =+B37&C37 -> Véhicules neufsIntérêt de gros | B37: =+$K$1 -> Véhicules neufs | C37: Intérêt de gros | E37: =F37/D$24 -> 974.98576 | F37: =+INDEX('Budget original'!$A$2:$AO$501,MATCH($A37,'Budget original'!$A$2:$A$501,0),MATCH(F$2,'Budget original'!$A$2:$AO$2,0)) -> 31199.544 | K37: =IF(L37=0,0,L37/J$24) -> 853.67172 | L37: =SUMIFS(BV_Data_An_Cour!$O:$O,BV_Data_An_Cour!$U:$U,$B37,BV_Data_An_Cour!$V:$V,$C37,BV_Data_An_Cour!$W:$W,L$2) -> 24756.48 | N37: =L37-F37 -> -6443.0642 | P37: =Q37/O$24 -> 1210.5003 | Q37: {=+INDEX('Réel 2024'!$A$2:$AO$501,MATCH($A37,'Réel 2024'!$A$2:$A$501,0),MATCH(Q$2,'Réel 2024'!$A$2:$AO$2,0))} -> 36315.01 | S37: =L37-Q37 -> -11558.53
A38: =+B38&C38 -> Véhicules neufs[...] | B38: =+$K$1 -> Véhicules neufs | C38: [...] | E38: =F38/D$24 -> 0 | F38: =+INDEX('Budget original'!$A$2:$AO$501,MATCH($A38,'Budget original'!$A$2:$A$501,0),MATCH(F$2,'Budget original'!$A$2:$AO$2,0)) -> 0 | K38: =IF(L38=0,0,L38/J$24) -> 0 | L38: =SUMIFS(BV_Data_An_Cour!$O:$O,BV_Data_An_Cour!$U:$U,$B38,BV_Data_An_Cour!$V:$V,$C38,BV_Data_An_Cour!$W:$W,L$2) -> 0 | N38: =L38-F38 -> 0 | P38: =Q38/O$24 -> 0 | Q38: {=+INDEX('Réel 2024'!$A$2:$AO$501,MATCH($A38,'Réel 2024'!$A$2:$A$501,0),MATCH(Q$2,'Réel 2024'!$A$2:$AO$2,0))} -> 0 | S38: =L38-Q38 -> 0
A39: =+B39&C39 -> Véhicules neufs[...] | B39: =+$K$1 -> Véhicules neufs | C39: [...] | E39: =F39/D$24 -> 0 | F39: =+INDEX('Budget original'!$A$2:$AO$501,MATCH($A39,'Budget original'!$A$2:$A$501,0),MATCH(F$2,'Budget original'!$A$2:$AO$2,0)) -> 0 | K39: =IF(L39=0,0,L39/J$24) -> 0 | L39: =SUMIFS(BV_Data_An_Cour!$O:$O,BV_Data_An_Cour!$U:$U,$B39,BV_Data_An_Cour!$V:$V,$C39,BV_Data_An_Cour!$W:$W,L$2) -> 0 | N39: =L39-F39 -> 0 | P39: =Q39/O$24 -> 0 | Q39: {=+INDEX('Réel 2024'!$A$2:$AO$501,MATCH($A39,'Réel 2024'!$A$2:$A$501,0),MATCH(Q$2,'Réel 2024'!$A$2:$AO$2,0))} -> 0 | S39: =L39-Q39 -> 0
A40: =+B40&C40 -> Véhicules neufs[...] | B40: =+$K$1 -> Véhicules neufs | C40: [...] | E40: =F40/D$24 -> 0 | F40: =+INDEX('Budget original'!$A$2:$AO$501,MATCH($A40,'Budget original'!$A$2:$A$501,0),MATCH(F$2,'Budget original'!$A$2:$AO$2,0)) -> 0 | K40: =IF(L40=0,0,L40/J$24) -> 0 | L40: =SUMIFS(BV_Data_An_Cour!$O:$O,BV_Data_An_Cour!$U:$U,$B40,BV_Data_An_Cour!$V:$V,$C40,BV_Data_An_Cour!$W:$W,L$2) -> 0 | N40: =L40-F40 -> 0 | P40: =Q40/O$24 -> 0 | Q40: {=+INDEX('Réel 2024'!$A$2:$AO$501,MATCH($A40,'Réel 2024'!$A$2:$A$501,0),MATCH(Q$2,'Réel 2024'!$A$2:$AO$2,0))} -> 0 | S40: =L40-Q40 -> 0
A41: =+B41&C41 -> Véhicules neufsTOTAL VARIABLES | B41: =+$K$1 -> Véhicules neufs | C41: TOTAL VARIABLES | D41: % brut | E41: =F41/F$27 -> 0.5884727 | F41: =SUM(F31:F40) -> 102706.15 | J41: % brut | K41: =L41/L$27 -> 0.5178285 | L41: =SUM(L31:L40) -> 105713.89 | N41: =L41-F41 -> 3007.7417 | O41: % brut | P41: =Q41/Q$27 -> 0.58637456 | Q41: =SUM(Q31:Q40) -> 115073.44 | S41: =L41-Q41 -> -9359.55
A42: =+B42&C42 -> Véhicules neufsSalaires cadres | B42: =+$K$1 -> Véhicules neufs | C42: Salaires cadres | F42: =+INDEX('Budget original'!$A$2:$AO$501,MATCH($A42,'Budget original'!$A$2:$A$501,0),MATCH(F$2,'Budget original'!$A$2:$AO$2,0)) -> 12572.924 | L42: =SUMIFS(BV_Data_An_Cour!$O:$O,BV_Data_An_Cour!$U:$U,$B42,BV_Data_An_Cour!$V:$V,$C42,BV_Data_An_Cour!$W:$W,L$2) -> 13325.86 | N42: =L42-F42 -> 752.93644 | Q42: {=+INDEX('Réel 2024'!$A$2:$AO$501,MATCH($A42,'Réel 2024'!$A$2:$A$501,0),MATCH(Q$2,'Réel 2024'!$A$2:$AO$2,0))} -> 12302.2 | S42: =L42-Q42 -> 1023.66
A43: =+B43&C43 -> Véhicules neufsSalaires commis | B43: =+$K$1 -> Véhicules neufs | C43: Salaires commis | F43: =+INDEX('Budget original'!$A$2:$AO$501,MATCH($A43,'Budget original'!$A$2:$A$501,0),MATCH(F$2,'Budget original'!$A$2:$AO$2,0)) -> 9200.6609 | L43: =SUMIFS(BV_Data_An_Cour!$O:$O,BV_Data_An_Cour!$U:$U,$B43,BV_Data_An_Cour!$V:$V,$C43,BV_Data_An_Cour!$W:$W,L$2) -> 8772.33 | N43: =L43-F43 -> -428.33092 | Q43: {=+INDEX('Réel 2024'!$A$2:$AO$501,MATCH($A43,'Réel 2024'!$A$2:$A$501,0),MATCH(Q$2,'Réel 2024'!$A$2:$AO$2,0))} -> 8037.27 | S43: =L43-Q43 -> 735.06
A44: =+B44&C44 -> Véhicules neufsSalaires autres | B44: =+$K$1 -> Véhicules neufs | C44: Salaires autres | F44: =+INDEX('Budget original'!$A$2:$AO$501,MATCH($A44,'Budget original'!$A$2:$A$501,0),MATCH(F$2,'Budget original'!$A$2:$AO$2,0)) -> 342 | L44: =SUMIFS(BV_Data_An_Cour!$O:$O,BV_Data_An_Cour!$U:$U,$B44,BV_Data_An_Cour!$V:$V,$C44,BV_Data_An_Cour!$W:$W,L$2) -> 342 | N44: =L44-F44 -> 0 | Q44: {=+INDEX('Réel 2024'!$A$2:$AO$501,MATCH($A44,'Réel 2024'!$A$2:$A$501,0),MATCH(Q$2,'Réel 2024'!$A$2:$AO$2,0))} -> 342 | S44: =L44-Q44 -> 0
A45: =+B45&C45 -> Véhicules neufsSalaires spécialistes | B45: =+$K$1 -> Véhicules neufs | C45: Salaires spécialistes | F45: =+INDEX('Budget original'!$A$2:$AO$501,MATCH($A45,'Budget original'!$A$2:$A$501,0),MATCH(F$2,'Budget original'!$A$2:$AO$2,0)) -> 0 | L45: =SUMIFS(BV_Data_An_Cour!$O:$O,BV_Data_An_Cour!$U:$U,$B45,BV_Data_An_Cour!$V:$V,$C45,BV_Data_An_Cour!$W:$W,L$2) -> 0 | N45: =L45-F45 -> 0 | Q45: {=+INDEX('Réel 2024'!$A$2:$AO$501,MATCH($A45,'Réel 2024'!$A$2:$A$501,0),MATCH(Q$2,'Réel 2024'!$A$2:$AO$2,0))} -> 0 | S45: =L45-Q45 -> 0
A46: =+B46&C46 -> Véhicules neufs[...] | B46: =+$K$1 -> Véhicules neufs | C46: [...] | F46: =+INDEX('Budget original'!$A$2:$AO$501,MATCH($A46,'Budget original'!$A$2:$A$501,0),MATCH(F$2,'Budget original'!$A$2:$AO$2,0)) -> 0 | L46: =SUMIFS(BV_Data_An_Cour!$O:$O,BV_Data_An_Cour!$U:$U,$B46,BV_Data_An_Cour!$V:$V,$C46,BV_Data_An_Cour!$W:$W,L$2) -> 0 | N46: =L46-F46 -> 0 | Q46: {=+INDEX('Réel 2024'!$A$2:$AO$501,MATCH($A46,'Réel 2024'!$A$2:$A$501,0),MATCH(Q$2,'Réel 2024'!$A$2:$AO$2,0))} -> 0 | S46: =L46-Q46 -> 0
A47: =+B47&C47 -> Véhicules neufs[...] | B47: =+$K$1 -> Véhicules neufs | C47: [...] | F47: =+INDEX('Budget original'!$A$2:$AO$501,MATCH($A47,'Budget original'!$A$2:$A$501,0),MATCH(F$2,'Budget original'!$A$2:$AO$2,0)) -> 0 | L47: =SUMIFS(BV_Data_An_Cour!$O:$O,BV_Data_An_Cour!$U:$U,$B47,BV_Data_An_Cour!$V:$V,$C47,BV_Data_An_Cour!$W:$W,L$2) -> 0 | N47: =L47-F47 -> 0 | Q47: {=+INDEX('Réel 2024'!$A$2:$AO$501,MATCH($A47,'Réel 2024'!$A$2:$A$501,0),MATCH(Q$2,'Réel 2024'!$A$2:$AO$2,0))} -> 0 | S47: =L47-Q47 -> 0
A48: =+B48&C48 -> Véhicules neufs[...] | B48: =+$K$1 -> Véhicules neufs | C48: [...] | F48: =+INDEX('Budget original'!$A$2:$AO$501,MATCH($A48,'Budget original'!$A$2:$A$501,0),MATCH(F$2,'Budget original'!$A$2:$AO$2,0)) -> 0 | L48: =SUMIFS(BV_Data_An_Cour!$O:$O,BV_Data_An_Cour!$U:$U,$B48,BV_Data_An_Cour!$V:$V,$C48,BV_Data_An_Cour!$W:$W,L$2) -> 0 | N48: =L48-F48 -> 0 | Q48: {=+INDEX('Réel 2024'!$A$2:$AO$501,MATCH($A48,'Réel 2024'!$A$2:$A$501,0),MATCH(Q$2,'Réel 2024'!$A$2:$AO$2,0))} -> 0 | S48: =L48-Q48 -> 0
A49: =+B49&C49 -> Véhicules neufsSalaires en absences | B49: =+$K$1 -> Véhicules neufs | C49: Salaires en absences | F49: =+INDEX('Budget original'!$A$2:$AO$501,MATCH($A49,'Budget original'!$A$2:$A$501,0),MATCH(F$2,'Budget original'!$A$2:$AO$2,0)) -> 8894.4548 | L49: =SUMIFS(BV_Data_An_Cour!$O:$O,BV_Data_An_Cour!$U:$U,$B49,BV_Data_An_Cour!$V:$V,$C49,BV_Data_An_Cour!$W:$W,L$2) -> 9449.46 | N49: =L49-F49 -> 555.00519 | Q49: {=+INDEX('Réel 2024'!$A$2:$AO$501,MATCH($A49,'Réel 2024'!$A$2:$A$501,0),MATCH(Q$2,'Réel 2024'!$A$2:$AO$2,0))} -> 4466.22 | S49: =L49-Q49 -> 4983.24
A50: =+B50&C50 -> Véhicules neufsDéduction à la source | B50: =+$K$1 -> Véhicules neufs | C50: Déduction à la source | F50: =+INDEX('Budget original'!$A$2:$AO$501,MATCH($A50,'Budget original'!$A$2:$A$501,0),MATCH(F$2,'Budget original'!$A$2:$AO$2,0)) -> 10383.075 | L50: =SUMIFS(BV_Data_An_Cour!$O:$O,BV_Data_An_Cour!$U:$U,$B50,BV_Data_An_Cour!$V:$V,$C50,BV_Data_An_Cour!$W:$W,L$2) -> 11008.13 | N50: =L50-F50 -> 625.05548 | Q50: {=+INDEX('Réel 2024'!$A$2:$AO$501,MATCH($A50,'Réel 2024'!$A$2:$A$501,0),MATCH(Q$2,'Réel 2024'!$A$2:$AO$2,0))} -> 10796.69 | S50: =L50-Q50 -> 211.44
A51: =+B51&C51 -> Véhicules neufsBénéfices marginaux | B51: =+$K$1 -> Véhicules neufs | C51: Bénéfices marginaux | F51: =+INDEX('Budget original'!$A$2:$AO$501,MATCH($A51,'Budget original'!$A$2:$A$501,0),MATCH(F$2,'Budget original'!$A$2:$AO$2,0)) -> 5344.2295 | L51: =SUMIFS(BV_Data_An_Cour!$O:$O,BV_Data_An_Cour!$U:$U,$B51,BV_Data_An_Cour!$V:$V,$C51,BV_Data_An_Cour!$W:$W,L$2) -> 4701.09 | N51: =L51-F51 -> -643.13953 | Q51: {=+INDEX('Réel 2024'!$A$2:$AO$501,MATCH($A51,'Réel 2024'!$A$2:$A$501,0),MATCH(Q$2,'Réel 2024'!$A$2:$AO$2,0))} -> 4198.83 | S51: =L51-Q51 -> 502.26
A52: =+B52&C52 -> Véhicules neufsCsst | B52: =+$K$1 -> Véhicules neufs | C52: Csst | F52: =+INDEX('Budget original'!$A$2:$AO$501,MATCH($A52,'Budget original'!$A$2:$A$501,0),MATCH(F$2,'Budget original'!$A$2:$AO$2,0)) -> 1145.192 | L52: =SUMIFS(BV_Data_An_Cour!$O:$O,BV_Data_An_Cour!$U:$U,$B52,BV_Data_An_Cour!$V:$V,$C52,BV_Data_An_Cour!$W:$W,L$2) -> 1835.54 | N52: =L52-F52 -> 690.34796 | Q52: {=+INDEX('Réel 2024'!$A$2:$AO$501,MATCH($A52,'Réel 2024'!$A$2:$A$501,0),MATCH(Q$2,'Réel 2024'!$A$2:$AO$2,0))} -> 1249.8 | S52: =L52-Q52 -> 585.74
A53: =+B53&C53 -> Véhicules neufs[...] | B53: =+$K$1 -> Véhicules neufs | C53: [...] | D53: =VLOOKUP(C53,$B$2:$B$46,1,FALSE) -> #N/A | F53: =+INDEX('Budget original'!$A$2:$AO$501,MATCH($A53,'Budget original'!$A$2:$A$501,0),MATCH(F$2,'Budget original'!$A$2:$AO$2,0)) -> 0 | L53: =SUMIFS(BV_Data_An_Cour!$O:$O,BV_Data_An_Cour!$U:$U,$B53,BV_Data_An_Cour!$V:$V,$C53,BV_Data_An_Cour!$W:$W,L$2) -> 0 | N53: =L53-F53 -> 0 | Q53: {=+INDEX('Réel 2024'!$A$2:$AO$501,MATCH($A53,'Réel 2024'!$A$2:$A$501,0),MATCH(Q$2,'Réel 2024'!$A$2:$AO$2,0))} -> 0 | S53: =L53-Q53 -> 0
A54: =+B54&C54 -> Véhicules neufsTOTAL PERSONNEL | B54: =+$K$1 -> Véhicules neufs | C54: TOTAL PERSONNEL | D54: % brut | E54: =F54/F$27 -> 0.2743513 | F54: =+SUM(F42:F53) -> 47882.535 | J54: % brut | K54: =L54/L$27 -> 0.24214932 | L54: =+SUM(L42:L53) -> 49434.41 | N54: =+SUM(N42:N53) -> 1551.8746 | O54: % brut | P54: =Q54/Q$27 -> 0.2109245 | Q54: =+SUM(Q42:Q53) -> 41393.01 | S54: =+SUM(S42:S53) -> 8041.4
A55: =+B55&C55 -> Véhicules neufsPublicité 2 | B55: =+$K$1 -> Véhicules neufs | C55: Publicité 2 | F55: =+INDEX('Budget original'!$A$2:$AO$501,MATCH($A55,'Budget original'!$A$2:$A$501,0),MATCH(F$2,'Budget original'!$A$2:$AO$2,0)) -> 0 | L55: =SUMIFS(BV_Data_An_Cour!$O:$O,BV_Data_An_Cour!$U:$U,$B55,BV_Data_An_Cour!$V:$V,$C55,BV_Data_An_Cour!$W:$W,L$2) -> 0 | N55: =L55-F55 -> 0 | Q55: {=+INDEX('Réel 2024'!$A$2:$AO$501,MATCH($A55,'Réel 2024'!$A$2:$A$501,0),MATCH(Q$2,'Réel 2024'!$A$2:$AO$2,0))} -> 0 | S55: =L55-Q55 -> 0
A56: =+B56&C56 -> Véhicules neufsService gratuit 2 | B56: =+$K$1 -> Véhicules neufs | C56: Service gratuit 2 | F56: =+INDEX('Budget original'!$A$2:$AO$501,MATCH($A56,'Budget original'!$A$2:$A$501,0),MATCH(F$2,'Budget original'!$A$2:$AO$2,0)) -> 0 | L56: =SUMIFS(BV_Data_An_Cour!$O:$O,BV_Data_An_Cour!$U:$U,$B56,BV_Data_An_Cour!$V:$V,$C56,BV_Data_An_Cour!$W:$W,L$2) -> 0 | N56: =L56-F56 -> 0 | Q56: {=+INDEX('Réel 2024'!$A$2:$AO$501,MATCH($A56,'Réel 2024'!$A$2:$A$501,0),MATCH(Q$2,'Réel 2024'!$A$2:$AO$2,0))} -> 0 | S56: =L56-Q56 -> 0
A57: =+B57&C57 -> Véhicules neufsFrais véhicules de cie | B57: =+$K$1 -> Véhicules neufs | C57: Frais véhicules de cie | F57: =+INDEX('Budget original'!$A$2:$AO$501,MATCH($A57,'Budget original'!$A$2:$A$501,0),MATCH(F$2,'Budget original'!$A$2:$AO$2,0)) -> 6620.9333 | L57: =SUMIFS(BV_Data_An_Cour!$O:$O,BV_Data_An_Cour!$U:$U,$B57,BV_Data_An_Cour!$V:$V,$C57,BV_Data_An_Cour!$W:$W,L$2) -> 8435.32 | N57: =L57-F57 -> 1814.3867 | Q57: {=+INDEX('Réel 2024'!$A$2:$AO$501,MATCH($A57,'Réel 2024'!$A$2:$A$501,0),MATCH(Q$2,'Réel 2024'!$A$2:$AO$2,0))} -> 4993.44 | S57: =L57-Q57 -> 3441.88 | V57: Dépréciation démos ventes
A58: =+B58&C58 -> Véhicules neufsInformatique | B58: =+$K$1 -> Véhicules neufs | C58: Informatique | F58: =+INDEX('Budget original'!$A$2:$AO$501,MATCH($A58,'Budget original'!$A$2:$A$501,0),MATCH(F$2,'Budget original'!$A$2:$AO$2,0)) -> 4878.3 | L58: =SUMIFS(BV_Data_An_Cour!$O:$O,BV_Data_An_Cour!$U:$U,$B58,BV_Data_An_Cour!$V:$V,$C58,BV_Data_An_Cour!$W:$W,L$2) -> 4823.25 | N58: =L58-F58 -> -55.05 | Q58: {=+INDEX('Réel 2024'!$A$2:$AO$501,MATCH($A58,'Réel 2024'!$A$2:$A$501,0),MATCH(Q$2,'Réel 2024'!$A$2:$AO$2,0))} -> 4537.54 | S58: =L58-Q58 -> 285.71
A59: =+B59&C59 -> Véhicules neufsFrais de déplacement | B59: =+$K$1 -> Véhicules neufs | C59: Frais de déplacement | F59: =+INDEX('Budget original'!$A$2:$AO$501,MATCH($A59,'Budget original'!$A$2:$A$501,0),MATCH(F$2,'Budget original'!$A$2:$AO$2,0)) -> 825 | L59: =SUMIFS(BV_Data_An_Cour!$O:$O,BV_Data_An_Cour!$U:$U,$B59,BV_Data_An_Cour!$V:$V,$C59,BV_Data_An_Cour!$W:$W,L$2) -> 1180.26 | N59: =L59-F59 -> 355.26 | Q59: {=+INDEX('Réel 2024'!$A$2:$AO$501,MATCH($A59,'Réel 2024'!$A$2:$A$501,0),MATCH(Q$2,'Réel 2024'!$A$2:$AO$2,0))} -> 1481.23 | S59: =L59-Q59 -> -300.97
A60: =+B60&C60 -> Véhicules neufsServices extérieurs | B60: =+$K$1 -> Véhicules neufs | C60: Services extérieurs | F60: =+INDEX('Budget original'!$A$2:$AO$501,MATCH($A60,'Budget original'!$A$2:$A$501,0),MATCH(F$2,'Budget original'!$A$2:$AO$2,0)) -> 3314.7 | L60: =SUMIFS(BV_Data_An_Cour!$O:$O,BV_Data_An_Cour!$U:$U,$B60,BV_Data_An_Cour!$V:$V,$C60,BV_Data_An_Cour!$W:$W,L$2) -> 4615.6 | N60: =L60-F60 -> 1300.9 | Q60: {=+INDEX('Réel 2024'!$A$2:$AO$501,MATCH($A60,'Réel 2024'!$A$2:$A$501,0),MATCH(Q$2,'Réel 2024'!$A$2:$AO$2,0))} -> 3008.26 | S60: =L60-Q60 -> 1607.34 | V60: Réparation portes de garages lavages
A61: =+B61&C61 -> Véhicules neufsFournitures autres | B61: =+$K$1 -> Véhicules neufs | C61: Fournitures autres | F61: =+INDEX('Budget original'!$A$2:$AO$501,MATCH($A61,'Budget original'!$A$2:$A$501,0),MATCH(F$2,'Budget original'!$A$2:$AO$2,0)) -> 40 | L61: =SUMIFS(BV_Data_An_Cour!$O:$O,BV_Data_An_Cour!$U:$U,$B61,BV_Data_An_Cour!$V:$V,$C61,BV_Data_An_Cour!$W:$W,L$2) -> 0 | N61: =L61-F61 -> -40 | Q61: {=+INDEX('Réel 2024'!$A$2:$AO$501,MATCH($A61,'Réel 2024'!$A$2:$A$501,0),MATCH(Q$2,'Réel 2024'!$A$2:$AO$2,0))} -> 2.49 | S61: =L61-Q61 -> -2.49
A62: =+B62&C62 -> Véhicules neufsUniformes | B62: =+$K$1 -> Véhicules neufs | C62: Uniformes | F62: =+INDEX('Budget original'!$A$2:$AO$501,MATCH($A62,'Budget original'!$A$2:$A$501,0),MATCH(F$2,'Budget original'!$A$2:$AO$2,0)) -> 30 | L62: =SUMIFS(BV_Data_An_Cour!$O:$O,BV_Data_An_Cour!$U:$U,$B62,BV_Data_An_Cour!$V:$V,$C62,BV_Data_An_Cour!$W:$W,L$2) -> 297 | N62: =L62-F62 -> 267 | Q62: {=+INDEX('Réel 2024'!$A$2:$AO$501,MATCH($A62,'Réel 2024'!$A$2:$A$501,0),MATCH(Q$2,'Réel 2024'!$A$2:$AO$2,0))} -> 0 | S62: =L62-Q62 -> 297
A63: =+B63&C63 -> Véhicules neufsPapeterie | B63: =+$K$1 -> Véhicules neufs | C63: Papeterie | F63: =+INDEX('Budget original'!$A$2:$AO$501,MATCH($A63,'Budget original'!$A$2:$A$501,0),MATCH(F$2,'Budget original'!$A$2:$AO$2,0)) -> 708.75 | L63: =SUMIFS(BV_Data_An_Cour!$O:$O,BV_Data_An_Cour!$U:$U,$B63,BV_Data_An_Cour!$V:$V,$C63,BV_Data_An_Cour!$W:$W,L$2) -> 527.44 | N63: =L63-F63 -> -181.31 | Q63: {=+INDEX('Réel 2024'!$A$2:$AO$501,MATCH($A63,'Réel 2024'!$A$2:$A$501,0),MATCH(Q$2,'Réel 2024'!$A$2:$AO$2,0))} -> 431.9 | S63: =L63-Q63 -> 95.54
A64: =+B64&C64 -> Véhicules neufsTéléphone | B64: =+$K$1 -> Véhicules neufs | C64: Téléphone | F64: =+INDEX('Budget original'!$A$2:$AO$501,MATCH($A64,'Budget original'!$A$2:$A$501,0),MATCH(F$2,'Budget original'!$A$2:$AO$2,0)) -> 210.4 | L64: =SUMIFS(BV_Data_An_Cour!$O:$O,BV_Data_An_Cour!$U:$U,$B64,BV_Data_An_Cour!$V:$V,$C64,BV_Data_An_Cour!$W:$W,L$2) -> 183.22 | N64: =L64-F64 -> -27.18 | Q64: {=+INDEX('Réel 2024'!$A$2:$AO$501,MATCH($A64,'Réel 2024'!$A$2:$A$501,0),MATCH(Q$2,'Réel 2024'!$A$2:$AO$2,0))} -> 235.92 | S64: =L64-Q64 -> -52.7
A65: =+B65&C65 -> Véhicules neufsFrais postaux | B65: =+$K$1 -> Véhicules neufs | C65: Frais postaux | F65: =+INDEX('Budget original'!$A$2:$AO$501,MATCH($A65,'Budget original'!$A$2:$A$501,0),MATCH(F$2,'Budget original'!$A$2:$AO$2,0)) -> 202.5 | L65: =SUMIFS(BV_Data_An_Cour!$O:$O,BV_Data_An_Cour!$U:$U,$B65,BV_Data_An_Cour!$V:$V,$C65,BV_Data_An_Cour!$W:$W,L$2) -> 222.71 | N65: =L65-F65 -> 20.21 | Q65: {=+INDEX('Réel 2024'!$A$2:$AO$501,MATCH($A65,'Réel 2024'!$A$2:$A$501,0),MATCH(Q$2,'Réel 2024'!$A$2:$AO$2,0))} -> 258.2 | S65: =L65-Q65 -> -35.49
A66: =+B66&C66 -> Véhicules neufsDivers | B66: =+$K$1 -> Véhicules neufs | C66: Divers | F66: =+INDEX('Budget original'!$A$2:$AO$501,MATCH($A66,'Budget original'!$A$2:$A$501,0),MATCH(F$2,'Budget original'!$A$2:$AO$2,0)) -> 783.45 | L66: =SUMIFS(BV_Data_An_Cour!$O:$O,BV_Data_An_Cour!$U:$U,$B66,BV_Data_An_Cour!$V:$V,$C66,BV_Data_An_Cour!$W:$W,L$2) -> 682.2 | N66: =L66-F66 -> -101.25 | Q66: {=+INDEX('Réel 2024'!$A$2:$AO$501,MATCH($A66,'Réel 2024'!$A$2:$A$501,0),MATCH(Q$2,'Réel 2024'!$A$2:$AO$2,0))} -> 832.95 | S66: =L66-Q66 -> -150.75
A67: =+B67&C67 -> Véhicules neufsFormation | B67: =+$K$1 -> Véhicules neufs | C67: Formation | F67: =+INDEX('Budget original'!$A$2:$AO$501,MATCH($A67,'Budget original'!$A$2:$A$501,0),MATCH(F$2,'Budget original'!$A$2:$AO$2,0)) -> 558.18351 | L67: =SUMIFS(BV_Data_An_Cour!$O:$O,BV_Data_An_Cour!$U:$U,$B67,BV_Data_An_Cour!$V:$V,$C67,BV_Data_An_Cour!$W:$W,L$2) -> 548.25 | N67: =L67-F67 -> -9.93351 | Q67: {=+INDEX('Réel 2024'!$A$2:$AO$501,MATCH($A67,'Réel 2024'!$A$2:$A$501,0),MATCH(Q$2,'Réel 2024'!$A$2:$AO$2,0))} -> 518.23 | S67: =L67-Q67 -> 30.02
A68: =+B68&C68 -> Véhicules neufsFrais bancaires | B68: =+$K$1 -> Véhicules neufs | C68: Frais bancaires | F68: =+INDEX('Budget original'!$A$2:$AO$501,MATCH($A68,'Budget original'!$A$2:$A$501,0),MATCH(F$2,'Budget original'!$A$2:$AO$2,0)) -> 4083.397 | L68: =SUMIFS(BV_Data_An_Cour!$O:$O,BV_Data_An_Cour!$U:$U,$B68,BV_Data_An_Cour!$V:$V,$C68,BV_Data_An_Cour!$W:$W,L$2) -> 4475.89 | N68: =L68-F68 -> 392.49295 | Q68: {=+INDEX('Réel 2024'!$A$2:$AO$501,MATCH($A68,'Réel 2024'!$A$2:$A$501,0),MATCH(Q$2,'Réel 2024'!$A$2:$AO$2,0))} -> 4388.05 | S68: =L68-Q68 -> 87.84
A69: =+B69&C69 -> Véhicules neufs[...] | B69: =+$K$1 -> Véhicules neufs | C69: [...] | F69: =+INDEX('Budget original'!$A$2:$AO$501,MATCH($A69,'Budget original'!$A$2:$A$501,0),MATCH(F$2,'Budget original'!$A$2:$AO$2,0)) -> 0 | N69: =L69-F69 -> 0 | Q69: {=+INDEX('Réel 2024'!$A$2:$AO$501,MATCH($A69,'Réel 2024'!$A$2:$A$501,0),MATCH(Q$2,'Réel 2024'!$A$2:$AO$2,0))} -> 0 | S69: =L69-Q69 -> 0
A70: =+B70&C70 -> Véhicules neufs[...] | B70: =+$K$1 -> Véhicules neufs | C70: [...] | F70: =+INDEX('Budget original'!$A$2:$AO$501,MATCH($A70,'Budget original'!$A$2:$A$501,0),MATCH(F$2,'Budget original'!$A$2:$AO$2,0)) -> 0 | L70: =SUMIFS(BV_Data_An_Cour!$O:$O,BV_Data_An_Cour!$U:$U,$B70,BV_Data_An_Cour!$V:$V,$C70,BV_Data_An_Cour!$W:$W,L$2) -> 0 | N70: =L70-F70 -> 0 | Q70: {=+INDEX('Réel 2024'!$A$2:$AO$501,MATCH($A70,'Réel 2024'!$A$2:$A$501,0),MATCH(Q$2,'Réel 2024'!$A$2:$AO$2,0))} -> 0 | S70: =L70-Q70 -> 0
A71: =+B71&C71 -> Véhicules neufs[...] | B71: =+$K$1 -> Véhicules neufs | C71: [...] | F71: =+INDEX('Budget original'!$A$2:$AO$501,MATCH($A71,'Budget original'!$A$2:$A$501,0),MATCH(F$2,'Budget original'!$A$2:$AO$2,0)) -> 0 | L71: =SUMIFS(BV_Data_An_Cour!$O:$O,BV_Data_An_Cour!$U:$U,$B71,BV_Data_An_Cour!$V:$V,$C71,BV_Data_An_Cour!$W:$W,L$2)*0.32 -> 0 | N71: =L71-F71 -> 0 | Q71: {=+INDEX('Réel 2024'!$A$2:$AO$501,MATCH($A71,'Réel 2024'!$A$2:$A$501,0),MATCH(Q$2,'Réel 2024'!$A$2:$AO$2,0))} -> 0 | S71: =L71-Q71 -> 0
A72: =+B72&C72 -> Véhicules neufsTOTAL SEMI-FIXES | B72: =+$K$1 -> Véhicules neufs | C72: TOTAL SEMI-FIXES | D72: % brut | E72: =F72/F$27 -> 0.1275174 | F72: =+SUM(F55:F71) -> 22255.614 | J72: % brut | K72: =L72/L$27 -> 0.1273149 | L72: =+SUM(L55:L71) -> 25991.14 | N72: =+SUM(N55:N71) -> 3735.5261 | O72: % brut | P72: =Q72/Q$27 -> 0.10541998 | Q72: =+SUM(Q55:Q71) -> 20688.21 | S72: =+SUM(S55:S71) -> 5302.93
A73: =+B73&C73 -> Véhicules neufs | B73: =+$K$1 -> Véhicules neufs
A74: =+B74&C74 -> Véhicules neufsTOTAL DES DÉPENSES | B74: =+$K$1 -> Véhicules neufs | C74: TOTAL DES DÉPENSES | D74: % brut | E74: =F74/F$27 -> 0.9903414 | F74: =F41+F54+F72 -> 172844.3 | J74: % brut | K74: =L74/L$27 -> 0.88729271 | L74: =L41+L54+L72 -> 181139.44 | N74: =L74-F74 -> 8295.1424 | O74: % brut | P74: =Q74/Q$27 -> 0.90271905 | Q74: =Q41+Q54+Q72 -> 177154.66 | S74: =L74-Q74 -> 3984.78
A75: =+B75&C75 -> Véhicules neufsRBSC neuf | B75: =+$K$1 -> Véhicules neufs | C75: RBSC neuf | F75: =+INDEX('Budget original'!$A$2:$AO$501,MATCH($A75,'Budget original'!$A$2:$A$501,0),MATCH(F$2,'Budget original'!$A$2:$AO$2,0)) -> 52237.537 | L75: =-SUMIFS(BV_Data_An_Cour!$O:$O,BV_Data_An_Cour!$U:$U,$B75,BV_Data_An_Cour!$V:$V,$C75,BV_Data_An_Cour!$W:$W,L$2) -> 43701.85 | N75: =L75-F75 -> -8535.6868 | Q75: =+INDEX('Réel 2024'!$A$2:$AO$501,MATCH($A75,'Réel 2024'!$A$2:$A$501,0),MATCH(Q$2,'Réel 2024'!$A$2:$AO$2,0)) -> 56342.42 | S75: =L75-Q75 -> -12640.57
A76: =+B76&C76 -> Véhicules neufsProgramme neuf 2 | B76: =+$K$1 -> Véhicules neufs | C76: Programme neuf 2 | F76: =+INDEX('Budget original'!$A$2:$AO$501,MATCH($A76,'Budget original'!$A$2:$A$501,0),MATCH(F$2,'Budget original'!$A$2:$AO$2,0)) -> 0 | L76: =-SUMIFS(BV_Data_An_Cour!$O:$O,BV_Data_An_Cour!$U:$U,$B76,BV_Data_An_Cour!$V:$V,$C76,BV_Data_An_Cour!$W:$W,L$2) -> 0 | N76: =L76-F76 -> 0 | Q76: {=+INDEX('Réel 2024'!$A$2:$AO$501,MATCH($A76,'Réel 2024'!$A$2:$A$501,0),MATCH(Q$2,'Réel 2024'!$A$2:$AO$2,0))} -> 0 | S76: =L76-Q76 -> 0
A77: =+B77&C77 -> Véhicules neufsProgramme neuf 3 | B77: =+$K$1 -> Véhicules neufs | C77: Programme neuf 3 | F77: =+INDEX('Budget original'!$A$2:$AO$501,MATCH($A77,'Budget original'!$A$2:$A$501,0),MATCH(F$2,'Budget original'!$A$2:$AO$2,0)) -> 0 | L77: =-SUMIFS(BV_Data_An_Cour!$O:$O,BV_Data_An_Cour!$U:$U,$B77,BV_Data_An_Cour!$V:$V,$C77,BV_Data_An_Cour!$W:$W,L$2) -> 0 | N77: =L77-F77 -> 0 | Q77: {=+INDEX('Réel 2024'!$A$2:$AO$501,MATCH($A77,'Réel 2024'!$A$2:$A$501,0),MATCH(Q$2,'Réel 2024'!$A$2:$AO$2,0))} -> 0 | S77: =L77-Q77 -> 0
A78: =+B78&C78 -> Véhicules neufsHoldbacks | B78: =+$K$1 -> Véhicules neufs | C78: Holdbacks | F78: =+INDEX('Budget original'!$A$2:$AO$501,MATCH($A78,'Budget original'!$A$2:$A$501,0),MATCH(F$2,'Budget original'!$A$2:$AO$2,0)) -> 56473.013 | L78: =-SUMIFS(BV_Data_An_Cour!$O:$O,BV_Data_An_Cour!$U:$U,$B78,BV_Data_An_Cour!$V:$V,$C78,BV_Data_An_Cour!$W:$W,L$2) -> 52973 | N78: =L78-F78 -> -3500.0128 | Q78: {=+INDEX('Réel 2024'!$A$2:$AO$501,MATCH($A78,'Réel 2024'!$A$2:$A$501,0),MATCH(Q$2,'Réel 2024'!$A$2:$AO$2,0))} -> 47079 | S78: =L78-Q78 -> 5894
A79: =+B79&C79 -> Véhicules neufs[...] | B79: =+$K$1 -> Véhicules neufs | C79: [...] | F79: =+INDEX('Budget original'!$A$2:$AO$501,MATCH($A79,'Budget original'!$A$2:$A$501,0),MATCH(F$2,'Budget original'!$A$2:$AO$2,0)) -> 0 | L79: =-SUMIFS(BV_Data_An_Cour!$O:$O,BV_Data_An_Cour!$U:$U,$B79,BV_Data_An_Cour!$V:$V,$C79,BV_Data_An_Cour!$W:$W,L$2) -> 0 | N79: =L79-F79 -> 0 | Q79: {=+INDEX('Réel 2024'!$A$2:$AO$501,MATCH($A79,'Réel 2024'!$A$2:$A$501,0),MATCH(Q$2,'Réel 2024'!$A$2:$AO$2,0))} -> 0 | S79: =L79-Q79 -> 0
A80: =+B80&C80 -> Véhicules neufs[...] | B80: =+$K$1 -> Véhicules neufs | C80: [...] | F80: =+INDEX('Budget original'!$A$2:$AO$501,MATCH($A80,'Budget original'!$A$2:$A$501,0),MATCH(F$2,'Budget original'!$A$2:$AO$2,0)) -> 0 | L80: =-SUMIFS(BV_Data_An_Cour!$O:$O,BV_Data_An_Cour!$U:$U,$B80,BV_Data_An_Cour!$V:$V,$C80,BV_Data_An_Cour!$W:$W,L$2) -> 0 | N80: =L80-F80 -> 0 | Q80: {=+INDEX('Réel 2024'!$A$2:$AO$501,MATCH($A80,'Réel 2024'!$A$2:$A$501,0),MATCH(Q$2,'Réel 2024'!$A$2:$AO$2,0))} -> 0 | S80: =L80-Q80 -> 0
A81: =+B81&C81 -> Véhicules neufs[...] | B81: =+$K$1 -> Véhicules neufs | C81: [...] | F81: =+INDEX('Budget original'!$A$2:$AO$501,MATCH($A81,'Budget original'!$A$2:$A$501,0),MATCH(F$2,'Budget original'!$A$2:$AO$2,0)) -> 0 | L81: =-SUMIFS(BV_Data_An_Cour!$O:$O,BV_Data_An_Cour!$U:$U,$B81,BV_Data_An_Cour!$V:$V,$C81,BV_Data_An_Cour!$W:$W,L$2) -> 0 | N81: =L81-F81 -> 0 | Q81: {=+INDEX('Réel 2024'!$A$2:$AO$501,MATCH($A81,'Réel 2024'!$A$2:$A$501,0),MATCH(Q$2,'Réel 2024'!$A$2:$AO$2,0))} -> 0 | S81: =L81-Q81 -> 0
A82: =+B82&C82 -> Véhicules neufsFrais administration | B82: =+$K$1 -> Véhicules neufs | C82: Frais administration | F82: =+INDEX('Budget original'!$A$2:$AO$501,MATCH($A82,'Budget original'!$A$2:$A$501,0),MATCH(F$2,'Budget original'!$A$2:$AO$2,0)) -> 18754.4 | L82: =-SUMIFS(BV_Data_An_Cour!$O:$O,BV_Data_An_Cour!$U:$U,$B82,BV_Data_An_Cour!$V:$V,$C82,BV_Data_An_Cour!$W:$W,L$2) -> 17255 | N82: =L82-F82 -> -1499.4 | Q82: {=+INDEX('Réel 2024'!$A$2:$AO$501,MATCH($A82,'Réel 2024'!$A$2:$A$501,0),MATCH(Q$2,'Réel 2024'!$A$2:$AO$2,0))} -> 17850 | S82: =L82-Q82 -> -595 | V82: =L82/595 -> 29 | W82: =V82/J27 -> 1
A83: =+B83&C83 -> Véhicules neufsAUTRES REVENUS | B83: =+$K$1 -> Véhicules neufs | C83: AUTRES REVENUS | F83: =+SUM(F75:F82) -> 127464.95 | L83: =+SUM(L75:L82) -> 113929.85 | N83: =+SUM(N75:N82) -> -13535.1 | Q83: =+SUM(Q75:Q82) -> 121271.42 | S83: =+SUM(S75:S82) -> -7341.57
A84: =+B84&C84 -> Véhicules neufs | B84: =+$K$1 -> Véhicules neufs
A85: =+B85&C85 -> Véhicules neufsPROFIT DÉPARTEMENTAL | B85: =+$K$1 -> Véhicules neufs | C85: PROFIT DÉPARTEMENTAL | F85: =F27-F74+F83 -> 129150.66 | L85: =L27-L74+L83 -> 136938.87 | N85: =N27-N41-N54-N72+N83 -> 7788.2055 | Q85: =Q27-Q74+Q83 -> 140362.38 | S85: =S27-S41-S54-S72+S83 -> -3423.51
C89: =C1 -> BMW Sherbrooke | K89: Véhicules usagés | S89: =$S$1 -> Réalisé, Avril 2025
D91: BUDGET ORIGINAL | J91: RÉALISATION | M91: ÉCART réel / Budget | O91: ANNÉE PRÉCÉDENTE | R91: ECART (réel/ Ann.Préc.)
D92: UNITE | E92: $P/UNITÉ | F92: $PROFITS | J92: UNITE | K92: $P/UNITE | L92: $PROFITS | M92: UNFTÉ | N92: $PROFFTS | O92: UNITE | P92: $P/UNITÉ | Q92: $PROFITS | R92: UNITE | S92: $PROFITS
A93: =+B93&C93 -> Véhicules usagésVentes nettes | B93: Véhicules usagés | C93: Ventes nettes | F93: =+INDEX('Budget original'!$A$2:$AO$501,MATCH($A93,'Budget original'!$A$2:$A$501,0),MATCH(F$2,'Budget original'!$A$2:$AO$2,0)) -> 2001764.7 | L93: =-SUMIFS(BV_Data_An_Cour!$O:$O,BV_Data_An_Cour!$X:$X,"Oui",BV_Data_An_Cour!$U:$U,$B93) -> 1384484.5 | Q93: {=+INDEX('Réel 2024'!$A$2:$AO$501,MATCH($A93,'Réel 2024'!$A$2:$A$501,0),MATCH(Q$2,'Réel 2024'!$A$2:$AO$2,0))} -> 1837134.2
A94: =+B94&C94 -> Véhicules usagésCertifié | B94: Véhicules usagés | C94: Certifié | D94: =+INDEX('Budget original'!$A$2:$AO$501,MATCH($A94,'Budget original'!$A$2:$A$501,0),MATCH(D$2,'Budget original'!$A$2:$AO$2,0)) -> 9 | E94: =IF(D94=0,0,F94/D94) -> 2300 | F94: =+INDEX('Budget original'!$A$2:$AO$501,MATCH($A94,'Budget original'!$A$2:$A$501,0),MATCH(F$2,'Budget original'!$A$2:$AO$2,0)) -> 20700 | J94: =-SUMIFS(BV_Data_An_Cour!$O:$O,BV_Data_An_Cour!$U:$U,$B94,BV_Data_An_Cour!$V:$V,$C94,BV_Data_An_Cour!$W:$W,J$2) -> 5 | K94: =IF(J94=0,0,L94/J94) -> 3241.292 | L94: =-SUMIFS(BV_Data_An_Cour!$O:$O,BV_Data_An_Cour!$U:$U,$B94,BV_Data_An_Cour!$V:$V,$C94,BV_Data_An_Cour!$W:$W,$L2) -> 16206.46 | M94: =J94-D94 -> -4 | N94: =L94-F94 -> -4493.54 | O94: {=+INDEX('Réel 2024'!$A$2:$AO$501,MATCH($A94,'Réel 2024'!$A$2:$A$501,0),MATCH(O$2,'Réel 2024'!$A$2:$AO$2,0))} -> 7 | P94: =IF(O94=0,0,Q94/O94) -> 1622.3443 | Q94: {=+INDEX('Réel 2024'!$A$2:$AO$501,MATCH($A94,'Réel 2024'!$A$2:$A$501,0),MATCH(Q$2,'Réel 2024'!$A$2:$AO$2,0))} -> 11356.41 | R94: =J94-O94 -> -2 | S94: =L94-Q94 -> 4850.05
A95: =+B95&C95 -> Véhicules usagésNon Certifié | B95: Véhicules usagés | C95: Non Certifié | D95: =+INDEX('Budget original'!$A$2:$AO$501,MATCH($A95,'Budget original'!$A$2:$A$501,0),MATCH(D$2,'Budget original'!$A$2:$AO$2,0)) -> 9 | E95: =IF(D95=0,0,F95/D95) -> 1600 | F95: =+INDEX('Budget original'!$A$2:$AO$501,MATCH($A95,'Budget original'!$A$2:$A$501,0),MATCH(F$2,'Budget original'!$A$2:$AO$2,0)) -> 14400 | J95: =-SUMIFS(BV_Data_An_Cour!$O:$O,BV_Data_An_Cour!$U:$U,$B95,BV_Data_An_Cour!$V:$V,$C95,BV_Data_An_Cour!$W:$W,J$2) -> 12 | K95: =IF(J95=0,0,L95/J95) -> 1852.42 | L95: =-SUMIFS(BV_Data_An_Cour!$O:$O,BV_Data_An_Cour!$U:$U,$B95,BV_Data_An_Cour!$V:$V,$C95,BV_Data_An_Cour!$W:$W,$L2) -> 22229.04 | M95: =J95-D95 -> 3 | N95: =L95-F95 -> 7829.04 | O95: {=+INDEX('Réel 2024'!$A$2:$AO$501,MATCH($A95,'Réel 2024'!$A$2:$A$501,0),MATCH(O$2,'Réel 2024'!$A$2:$AO$2,0))} -> 9 | P95: =IF(O95=0,0,Q95/O95) -> 1875.23 | Q95: {=+INDEX('Réel 2024'!$A$2:$AO$501,MATCH($A95,'Réel 2024'!$A$2:$A$501,0),MATCH(Q$2,'Réel 2024'!$A$2:$AO$2,0))} -> 16877.07 | R95: =J95-O95 -> 3 | S95: =L95-Q95 -> 5351.97
A96: =+B96&C96 -> Véhicules usagésAutres marques | B96: Véhicules usagés | C96: Autres marques | D96: =+INDEX('Budget original'!$A$2:$AO$501,MATCH($A96,'Budget original'!$A$2:$A$501,0),MATCH(D$2,'Budget original'!$A$2:$AO$2,0)) -> 9 | E96: =IF(D96=0,0,F96/D96) -> 1500 | F96: =+INDEX('Budget original'!$A$2:$AO$501,MATCH($A96,'Budget original'!$A$2:$A$501,0),MATCH(F$2,'Budget original'!$A$2:$AO$2,0)) -> 13500 | J96: =-SUMIFS(BV_Data_An_Cour!$O:$O,BV_Data_An_Cour!$U:$U,$B96,BV_Data_An_Cour!$V:$V,$C96,BV_Data_An_Cour!$W:$W,J$2) -> 5 | K96: =IF(J96=0,0,L96/J96) -> 1888.092 | L96: =-SUMIFS(BV_Data_An_Cour!$O:$O,BV_Data_An_Cour!$U:$U,$B96,BV_Data_An_Cour!$V:$V,$C96,BV_Data_An_Cour!$W:$W,$L2) -> 9440.46 | M96: =J96-D96 -> -4 | N96: =L96-F96 -> -4059.54 | O96: =+INDEX('Réel 2024'!$A$2:$AO$501,MATCH($A96,'Réel 2024'!$A$2:$A$501,0),MATCH(O$2,'Réel 2024'!$A$2:$AO$2,0)) -> 12 | P96: =IF(O96=0,0,Q96/O96) -> 862.97167 | Q96: =+INDEX('Réel 2024'!$A$2:$AO$501,MATCH($A96,'Réel 2024'!$A$2:$A$501,0),MATCH(Q$2,'Réel 2024'!$A$2:$AO$2,0)) -> 10355.66 | R96: =J96-O96 -> -7 | S96: =L96-Q96 -> -915.2
A97: =+B97&C97 -> Véhicules usagésTotal Usagés | B97: Véhicules usagés | C97: Total Usagés | D97: =+D95+D94+D96 -> 27 | E97: =IF(D97=0,0,F97/D97) -> 1800 | F97: =+F94+F95+F96 -> 48600 | J97: =+J94+J95+J96 -> 22 | K97: =IF(J97<=0,0,L97/J97) -> 2176.18 | L97: =+L94+L95+L96 -> 47875.96 | M97: =J97-D97 -> -5 | N97: =L97-F97 -> -724.04 | O97: =+O95+O94+O96 -> 28 | P97: =IF(O97=0,0,Q97/O97) -> 1378.1836 | Q97: =+Q94+Q95+Q96 -> 38589.14 | R97: =J97-O97 -> -6 | S97: =S94+S95 -> 10202.02
A98: =+B98&C98 -> Véhicules usagés | B98: Véhicules usagés | M98: =M97/D97 -> -0.18518519 | N98: =N97/F97 -> -0.014897942 | R98: =R97/O97 -> -0.21428571 | S98: =IF(Q97=0,0,(S97/Q97)) -> 0.26437542
A99: =+B99&C99 -> Véhicules usagés | B99: Véhicules usagés
A100: =+B100&C100 -> Véhicules usagésVentes au Gros | B100: Véhicules usagés | C100: Ventes au Gros | D100: =+INDEX('Budget original'!$A$2:$AO$501,MATCH($A100,'Budget original'!$A$2:$A$501,0),MATCH(D$2,'Budget original'!$A$2:$AO$2,0)) -> 25 | E100: =IF(D100=0,0,F100/D100) -> 350 | F100: =+INDEX('Budget original'!$A$2:$AO$501,MATCH($A100,'Budget original'!$A$2:$A$501,0),MATCH(F$2,'Budget original'!$A$2:$AO$2,0)) -> 8750 | J100: =-SUMIFS(BV_Data_An_Cour!$O:$O,BV_Data_An_Cour!$U:$U,$B100,BV_Data_An_Cour!$V:$V,$C100,BV_Data_An_Cour!$W:$W,J$2) -> 15 | K100: =IF(J100=0,0,L100/J100) -> 613.864 | L100: =-SUMIFS(BV_Data_An_Cour!$O:$O,BV_Data_An_Cour!$U:$U,$B100,BV_Data_An_Cour!$V:$V,$C100,BV_Data_An_Cour!$W:$W,L$2) -> 9207.96 | M100: =J100-D100 -> -10 | N100: =L100-F100 -> 457.96 | O100: {=+INDEX('Réel 2024'!$A$2:$AO$501,MATCH($A100,'Réel 2024'!$A$2:$A$501,0),MATCH(O$2,'Réel 2024'!$A$2:$AO$2,0))} -> 16 | P100: =IF(O100=0,0,Q100/O100) -> 462.19375 | Q100: {=+INDEX('Réel 2024'!$A$2:$AO$501,MATCH($A100,'Réel 2024'!$A$2:$A$501,0),MATCH(Q$2,'Réel 2024'!$A$2:$AO$2,0))} -> 7395.1 | R100: =J100-O100 -> -1 | S100: =L100-Q100 -> 1812.86
A101: =+B101&C101 -> Véhicules usagés | B101: Véhicules usagés
A102: =+B102&C102 -> Véhicules usagésRev. Finances | B102: Véhicules usagés | C102: Rev. Finances | D102: =+INDEX('Budget original'!$A$2:$AO$501,MATCH($A102,'Budget original'!$A$2:$A$501,0),MATCH(D$2,'Budget original'!$A$2:$AO$2,0)) -> 0 | E102: =IF(D102=0,0,F102/D102) -> 0 | F102: =+INDEX('Budget original'!$A$2:$AO$501,MATCH($A102,'Budget original'!$A$2:$A$501,0),MATCH(F$2,'Budget original'!$A$2:$AO$2,0)) -> 10260 | K102: =IF(J97=0,0,L102/J97) -> 605.96318 | L102: =-SUMIFS(BV_Data_An_Cour!$O:$O,BV_Data_An_Cour!$U:$U,$B102,BV_Data_An_Cour!$V:$V,$C102,BV_Data_An_Cour!$W:$W,$L2) -> 13331.19 | N102: =L102-F102 -> 3071.19 | Q102: {=+INDEX('Réel 2024'!$A$2:$AO$501,MATCH($A102,'Réel 2024'!$A$2:$A$501,0),MATCH(Q$2,'Réel 2024'!$A$2:$AO$2,0))} -> 13151.79 | R102: =O102-K102 -> -605.96318 | S102: =L102-Q102 -> 179.4
A103: =+B103&C103 -> Véhicules usagésRev. Protections | B103: Véhicules usagés | C103: Rev. Protections | D103: =+INDEX('Budget original'!$A$2:$AO$501,MATCH($A103,'Budget original'!$A$2:$A$501,0),MATCH(D$2,'Budget original'!$A$2:$AO$2,0)) -> 0 | E103: =IF(D103=0,0,F103/D103) -> 0 | F103: =+INDEX('Budget original'!$A$2:$AO$501,MATCH($A103,'Budget original'!$A$2:$A$501,0),MATCH(F$2,'Budget original'!$A$2:$AO$2,0)) -> 22950 | K103: =IF(J97=0,0,L103/J97) -> 1538.4391 | L103: =-SUMIFS(BV_Data_An_Cour!$O:$O,BV_Data_An_Cour!$U:$U,$B103,BV_Data_An_Cour!$V:$V,$C103,BV_Data_An_Cour!$W:$W,$L2) -> 33845.66 | N103: =L103-F103 -> 10895.66 | Q103: {=+INDEX('Réel 2024'!$A$2:$AO$501,MATCH($A103,'Réel 2024'!$A$2:$A$501,0),MATCH(Q$2,'Réel 2024'!$A$2:$AO$2,0))} -> 18323 | R103: =O103-K103 -> -1538.4391 | S103: =L103-Q103 -> 15522.66
A104: =+B104&C104 -> Véhicules usagésRev. Autres | B104: Véhicules usagés | C104: Rev. Autres | D104: =+INDEX('Budget original'!$A$2:$AO$501,MATCH($A104,'Budget original'!$A$2:$A$501,0),MATCH(D$2,'Budget original'!$A$2:$AO$2,0)) -> 0 | E104: =IF(D104=0,0,F104/D104) -> 0 | F104: =+INDEX('Budget original'!$A$2:$AO$501,MATCH($A104,'Budget original'!$A$2:$A$501,0),MATCH(F$2,'Budget original'!$A$2:$AO$2,0)) -> 5940 | K104: =IF(J97=0,0,L104/J97) -> 191.39773 | L104: =-SUMIFS(BV_Data_An_Cour!$O:$O,BV_Data_An_Cour!$U:$U,$B104,BV_Data_An_Cour!$V:$V,$C104,BV_Data_An_Cour!$W:$W,$L$2) -> 4210.75 | N104: =L104-F104 -> -1729.25 | Q104: {=+INDEX('Réel 2024'!$A$2:$AO$501,MATCH($A104,'Réel 2024'!$A$2:$A$501,0),MATCH(Q$2,'Réel 2024'!$A$2:$AO$2,0))} -> 4262 | R104: =O104-K104 -> -191.39773 | S104: =L104-Q104 -> -51.25
...

Sheet Print_AAD
C1: =Parametres!B1 -> BMW Sherbrooke | K1: Véhicules neufs | S1: =CONCATENATE("Réalisé,"," ",Parametres!B3," ",Parametres!B4," AAD") -> Réalisé, Avril 2025 AAD
D2: X | E2: O | F2: U | J2: NB | L2: $ | O2: X | P2: O | Q2: U | X2: X | Y2: O | Z2: U | AJ2: X | AK2: O | AL2: U
D3: BUDGET ORIGINAL | J3: RÉALISATION | M3: ÉCART réel / Budget | O3: ANNÉE PRÉCÉDENTE | R3: ECART (réel/ Ann.Préc.)
D4: UNITE | E4: $P/UNITÉ | F4: $PROFITS | J4: UNITE | K4: $P/UNITE | L4: $PROFITS | M4: UNFTÉ | N4: $PROFITS | O4: UNITE | P4: $P/UNITÉ | Q4: $PROFITS | R4: UNITE | S4: $PROFITS
A5: =+B5&C5 -> Véhicules neufsVentes nettes | B5: =+$K$1 -> Véhicules neufs | C5: Ventes nettes | F5: {=+SUMPRODUCT(('Budget original'!$A$8:$A$501=$A5)*('Budget original'!$C$3:$AO$3=F$2),'Budget original'!$C$8:$AO$501)} -> 7999972 | L5: =-SUMIFS(BV_Data_An_Cour!$P:$P,BV_Data_An_Cour!$X:$X,"Oui",BV_Data_An_Cour!$U:$U,$B5) -> 7289100.5 | Q5: {=+SUMPRODUCT(('Réel 2024'!$A$8:$A$501=$A5)*('Réel 2024'!$C$3:$AO$3=Q$2),'Réel 2024'!$C$8:$AO$501)} -> 6459230.3
A6: =+B6&C6 -> Véhicules neufsAutos détail | B6: =+$K$1 -> Véhicules neufs | C6: Autos détail | D6: {=+SUMPRODUCT(('Budget original'!$A$8:$A$501=$A6)*('Budget original'!$C$3:$AO$3=D$2),'Budget original'!$C$8:$AO$501)} -> 27 | E6: =IF(D6=0,0,F6/D6) -> 4306.3953 | F6: {=+SUMPRODUCT(('Budget original'!$A$8:$A$501=$A6)*('Budget original'!$C$3:$AO$3=F$2),'Budget original'!$C$8:$AO$501)} -> 116272.67 | J6: =-SUMIFS(BV_Data_An_Cour!$P:$P,BV_Data_An_Cour!$U:$U,$B6,BV_Data_An_Cour!$V:$V,$C6,BV_Data_An_Cour!$W:$W,J$2) -> 21 | K6: =IF(J6=0,0,L6/J6) -> 4597.7219 | L6: =-SUMIFS(BV_Data_An_Cour!$P:$P,BV_Data_An_Cour!$U:$U,$B6,BV_Data_An_Cour!$V:$V,$C6,BV_Data_An_Cour!$W:$W,L$2) -> 96552.16 | M6: =J6-D6 -> -6 | N6: =L6-F6 -> -19720.514 | O6: {=+SUMPRODUCT(('Réel 2024'!$A$8:$A$501=$A6)*('Réel 2024'!$C$3:$AO$3=O$2),'Réel 2024'!$C$8:$AO$501)} -> 24 | P6: =IF(O6=0,0,Q6/O6) -> 5389.0008 | Q6: {=+SUMPRODUCT(('Réel 2024'!$A$8:$A$501=$A6)*('Réel 2024'!$C$3:$AO$3=Q$2),'Réel 2024'!$C$8:$AO$501)} -> 129336.02 | R6: =J6-O6 -> -3 | S6: =L6-Q6 -> -32783.86
A7: =+B7&C7 -> Véhicules neufsCamions détail | B7: =+$K$1 -> Véhicules neufs | C7: Camions détail | D7: {=+SUMPRODUCT(('Budget original'!$A$8:$A$501=$A7)*('Budget original'!$C$3:$AO$3=D$2),'Budget original'!$C$8:$AO$501)} -> 47 | E7: =IF(D7=0,0,F7/D7) -> 4000.3311 | F7: {=+SUMPRODUCT(('Budget original'!$A$8:$A$501=$A7)*('Budget original'!$C$3:$AO$3=F$2),'Budget original'!$C$8:$AO$501)} -> 188015.56 | J7: =-SUMIFS(BV_Data_An_Cour!$P:$P,BV_Data_An_Cour!$U:$U,$B7,BV_Data_An_Cour!$V:$V,$C7,BV_Data_An_Cour!$W:$W,J$2) -> 44 | K7: =IF(J7=0,0,L7/J7) -> 4472.04 | L7: =-SUMIFS(BV_Data_An_Cour!$P:$P,BV_Data_An_Cour!$U:$U,$B7,BV_Data_An_Cour!$V:$V,$C7,BV_Data_An_Cour!$W:$W,L$2) -> 196769.76 | M7: =J7-D7 -> -3 | N7: =L7-F7 -> 8754.1971 | O7: {=+SUMPRODUCT(('Réel 2024'!$A$8:$A$501=$A7)*('Réel 2024'!$C$3:$AO$3=O$2),'Réel 2024'!$C$8:$AO$501)} -> 29 | P7: =IF(O7=0,0,Q7/O7) -> 5047.0814 | Q7: {=+SUMPRODUCT(('Réel 2024'!$A$8:$A$501=$A7)*('Réel 2024'!$C$3:$AO$3=Q$2),'Réel 2024'!$C$8:$AO$501)} -> 146365.36 | R7: =J7-O7 -> 15 | S7: =L7-Q7 -> 50404.4
A8: =+B8&C8 -> Véhicules neufsSprinter | B8: =+$K$1 -> Véhicules neufs | C8: Sprinter | D8: {=+SUMPRODUCT(('Budget original'!$A$8:$A$501=$A8)*('Budget original'!$C$3:$AO$3=D$2),'Budget original'!$C$8:$AO$501)} -> 0 | E8: =IF(D8=0,0,F8/D8) -> 0 | F8: {=+SUMPRODUCT(('Budget original'!$A$8:$A$501=$A8)*('Budget original'!$C$3:$AO$3=F$2),'Budget original'!$C$8:$AO$501)} -> 0 | J8: =-SUMIFS(BV_Data_An_Cour!$P:$P,BV_Data_An_Cour!$U:$U,$B8,BV_Data_An_Cour!$V:$V,$C8,BV_Data_An_Cour!$W:$W,J$2) -> 0 | K8: =IF(J8=0,0,L8/J8) -> 0 | L8: =-SUMIFS(BV_Data_An_Cour!$P:$P,BV_Data_An_Cour!$U:$U,$B8,BV_Data_An_Cour!$V:$V,$C8,BV_Data_An_Cour!$W:$W,L$2) -> 0 | M8: =J8-D8 -> 0 | N8: =L8-F8 -> 0 | O8: {=+SUMPRODUCT(('Réel 2024'!$A$8:$A$501=$A8)*('Réel 2024'!$C$3:$AO$3=O$2),'Réel 2024'!$C$8:$AO$501)} -> 0 | P8: =IF(O8=0,0,Q8/O8) -> 0 | Q8: {=+SUMPRODUCT(('Réel 2024'!$A$8:$A$501=$A8)*('Réel 2024'!$C$3:$AO$3=Q$2),'Réel 2024'!$C$8:$AO$501)} -> 0 | R8: =J8-O8 -> 0 | S8: =L8-Q8 -> 0
A9: =+B9&C9 -> Véhicules neufsMoto détail | B9: =+$K$1 -> Véhicules neufs | C9: Moto détail | D9: {=+SUMPRODUCT(('Budget original'!$A$8:$A$501=$A9)*('Budget original'!$C$3:$AO$3=D$2),'Budget original'!$C$8:$AO$501)} -> 0 | E9: =IF(D9=0,0,F9/D9) -> 0 | F9: {=+SUMPRODUCT(('Budget original'!$A$8:$A$501=$A9)*('Budget original'!$C$3:$AO$3=F$2),'Budget original'!$C$8:$AO$501)} -> 0 | J9: =-SUMIFS(BV_Data_An_Cour!$P:$P,BV_Data_An_Cour!$U:$U,$B9,BV_Data_An_Cour!$V:$V,$C9,BV_Data_An_Cour!$W:$W,J$2) -> 0 | K9: =IF(J9=0,0,L9/J9) -> 0 | L9: =-SUMIFS(BV_Data_An_Cour!$P:$P,BV_Data_An_Cour!$U:$U,$B9,BV_Data_An_Cour!$V:$V,$C9,BV_Data_An_Cour!$W:$W,L$2) -> 0 | M9: =J9-D9 -> 0 | N9: =L9-F9 -> 0 | O9: {=+SUMPRODUCT(('Réel 2024'!$A$8:$A$501=$A9)*('Réel 2024'!$C$3:$AO$3=O$2),'Réel 2024'!$C$8:$AO$501)} -> 0 | P9: =IF(O9=0,0,Q9/O9) -> 0 | Q9: {=+SUMPRODUCT(('Réel 2024'!$A$8:$A$501=$A9)*('Réel 2024'!$C$3:$AO$3=Q$2),'Réel 2024'!$C$8:$AO$501)} -> 0 | R9: =J9-O9 -> 0 | S9: =L9-Q9 -> 0
A10: =+B10&C10 -> Véhicules neufs[...] | B10: =+$K$1 -> Véhicules neufs | C10: [...] | D10: {=+SUMPRODUCT(('Budget original'!$A$8:$A$501=$A10)*('Budget original'!$C$3:$AO$3=D$2),'Budget original'!$C$8:$AO$501)} -> 0 | E10: =IF(D10=0,0,F10/D10) -> 0 | F10: {=+SUMPRODUCT(('Budget original'!$A$8:$A$501=$A10)*('Budget original'!$C$3:$AO$3=F$2),'Budget original'!$C$8:$AO$501)} -> 0 | J10: =-SUMIFS(BV_Data_An_Cour!$P:$P,BV_Data_An_Cour!$U:$U,$B10,BV_Data_An_Cour!$V:$V,$C10,BV_Data_An_Cour!$W:$W,J$2) -> 0 | K10: =IF(J10=0,0,L10/J10) -> 0 | L10: =-SUMIFS(BV_Data_An_Cour!$P:$P,BV_Data_An_Cour!$U:$U,$B10,BV_Data_An_Cour!$V:$V,$C10,BV_Data_An_Cour!$W:$W,L$2) -> 0 | M10: =J10-D10 -> 0 | N10: =L10-F10 -> 0 | O10: {=+SUMPRODUCT(('Réel 2024'!$A$8:$A$501=$A10)*('Réel 2024'!$C$3:$AO$3=O$2),'Réel 2024'!$C$8:$AO$501)} -> 0 | P10: =IF(O10=0,0,Q10/O10) -> 0 | Q10: {=+SUMPRODUCT(('Réel 2024'!$A$8:$A$501=$A10)*('Réel 2024'!$C$3:$AO$3=Q$2),'Réel 2024'!$C$8:$AO$501)} -> 0 | R10: =J10-O10 -> 0 | S10: =L10-Q10 -> 0
A11: =+B11&C11 -> Véhicules neufs[...] | B11: =+$K$1 -> Véhicules neufs | C11: [...] | D11: {=+SUMPRODUCT(('Budget original'!$A$8:$A$501=$A11)*('Budget original'!$C$3:$AO$3=D$2),'Budget original'!$C$8:$AO$501)} -> 0 | E11: =IF(D11=0,0,F11/D11) -> 0 | F11: {=+SUMPRODUCT(('Budget original'!$A$8:$A$501=$A11)*('Budget original'!$C$3:$AO$3=F$2),'Budget original'!$C$8:$AO$501)} -> 0 | J11: =-SUMIFS(BV_Data_An_Cour!$P:$P,BV_Data_An_Cour!$U:$U,$B11,BV_Data_An_Cour!$V:$V,$C11,BV_Data_An_Cour!$W:$W,J$2) -> 0 | K11: =IF(J11=0,0,L11/J11) -> 0 | L11: =-SUMIFS(BV_Data_An_Cour!$P:$P,BV_Data_An_Cour!$U:$U,$B11,BV_Data_An_Cour!$V:$V,$C11,BV_Data_An_Cour!$W:$W,L$2) -> 0 | M11: =J11-D11 -> 0 | N11: =L11-F11 -> 0 | O11: {=+SUMPRODUCT(('Réel 2024'!$A$8:$A$501=$A11)*('Réel 2024'!$C$3:$AO$3=O$2),'Réel 2024'!$C$8:$AO$501)} -> 0 | P11: =IF(O11=0,0,Q11/O11) -> 0 | Q11: {=+SUMPRODUCT(('Réel 2024'!$A$8:$A$501=$A11)*('Réel 2024'!$C$3:$AO$3=Q$2),'Réel 2024'!$C$8:$AO$501)} -> 0 | R11: =J11-O11 -> 0 | S11: =L11-Q11 -> 0
A12: =+B12&C12 -> Véhicules neufs[...] | B12: =+$K$1 -> Véhicules neufs | C12: [...] | D12: {=+SUMPRODUCT(('Budget original'!$A$8:$A$501=$A12)*('Budget original'!$C$3:$AO$3=D$2),'Budget original'!$C$8:$AO$501)} -> 0 | E12: =IF(D12=0,0,F12/D12) -> 0 | F12: {=+SUMPRODUCT(('Budget original'!$A$8:$A$501=$A12)*('Budget original'!$C$3:$AO$3=F$2),'Budget original'!$C$8:$AO$501)} -> 0 | J12: =-SUMIFS(BV_Data_An_Cour!$P:$P,BV_Data_An_Cour!$U:$U,$B12,BV_Data_An_Cour!$V:$V,$C12,BV_Data_An_Cour!$W:$W,J$2) -> 0 | K12: =IF(J12=0,0,L12/J12) -> 0 | L12: =-SUMIFS(BV_Data_An_Cour!$P:$P,BV_Data_An_Cour!$U:$U,$B12,BV_Data_An_Cour!$V:$V,$C12,BV_Data_An_Cour!$W:$W,L$2) -> 0 | M12: =J12-D12 -> 0 | N12: =L12-F12 -> 0 | O12: {=+SUMPRODUCT(('Réel 2024'!$A$8:$A$501=$A12)*('Réel 2024'!$C$3:$AO$3=O$2),'Réel 2024'!$C$8:$AO$501)} -> 0 | P12: =IF(O12=0,0,Q12/O12) -> 0 | Q12: {=+SUMPRODUCT(('Réel 2024'!$A$8:$A$501=$A12)*('Réel 2024'!$C$3:$AO$3=Q$2),'Réel 2024'!$C$8:$AO$501)} -> 0 | R12: =J12-O12 -> 0 | S12: =L12-Q12 -> 0
A13: =+B13&C13 -> Véhicules neufsTotal Neufs | B13: =+$K$1 -> Véhicules neufs | C13: Total Neufs | D13: =+SUM(D6:D12) -> 74 | E13: =IF(D13<=0,0,F13/D13) -> 4112.0032 | F13: =+SUM(F6:F12) -> 304288.24 | J13: =+SUM(J6:J12) -> 65 | K13: =IF(J13<=0,0,L13/J13) -> 4512.6449 | L13: =+SUM(L6:L12) -> 293321.92 | M13: =+SUM(M6:M12) -> -9 | N13: =+SUM(N6:N12) -> -10966.317 | O13: =+SUM(O6:O12) -> 53 | P13: =IF(O13<=0,0,Q13/O13) -> 5201.9128 | Q13: =+SUM(Q6:Q12) -> 275701.38 | R13: =+SUM(R6:R12) -> 12 | S13: =+SUM(S6:S12) -> 17620.54
A14: =+B14&C14 -> Véhicules neufs | B14: =+$K$1 -> Véhicules neufs | M14: =IF(D13=0,0,M13/D13) -> -0.12162162 | N14: =IF(F13=0,0,N13/F13) -> -0.036039242 | R14: =R13/O13 -> 0.22641509 | S14: =IF(Q13=0,0,(S13/Q13)) -> 0.063911686
A15: =+B15&C15 -> Véhicules neufsEx-Démos et courtoisies | B15: =+$K$1 -> Véhicules neufs | C15: Ex-Démos et courtoisies | D15: {=+SUMPRODUCT(('Budget original'!$A$8:$A$501=$A15)*('Budget original'!$C$3:$AO$3=D$2),'Budget original'!$C$8:$AO$501)} -> 11 | E15: =IF(D15=0,0,F15/D15) -> 750 | F15: {=+SUMPRODUCT(('Budget original'!$A$8:$A$501=$A15)*('Budget original'!$C$3:$AO$3=F$2),'Budget original'!$C$8:$AO$501)} -> 8250 | J15: =-SUMIFS(BV_Data_An_Cour!$P:$P,BV_Data_An_Cour!$U:$U,$B15,BV_Data_An_Cour!$V:$V,$C15,BV_Data_An_Cour!$W:$W,J$2) -> 14 | K15: =IF(J15=0,0,L15/J15) -> 2404.6 | L15: =-SUMIFS(BV_Data_An_Cour!$P:$P,BV_Data_An_Cour!$U:$U,$B15,BV_Data_An_Cour!$V:$V,$C15,BV_Data_An_Cour!$W:$W,L$2) -> 33664.4 | M15: =J15-D15 -> 3 | N15: =L15-F15 -> 25414.4 | O15: {=+SUMPRODUCT(('Réel 2024'!$A$8:$A$501=$A15)*('Réel 2024'!$C$3:$AO$3=O$2),'Réel 2024'!$C$8:$AO$501)} -> 15 | P15: =IF(O15=0,0,Q15/O15) -> 2940.3067 | Q15: {=+SUMPRODUCT(('Réel 2024'!$A$8:$A$501=$A15)*('Réel 2024'!$C$3:$AO$3=Q$2),'Réel 2024'!$C$8:$AO$501)} -> 44104.6 | R15: =J15-O15 -> -1 | S15: =L15-Q15 -> -10440.2
A16: =+B16&C16 -> Véhicules neufs | B16: =+$K$1 -> Véhicules neufs
A17: =+B17&C17 -> Véhicules neufsFlottes | B17: =+$K$1 -> Véhicules neufs | C17: Flottes | D17: {=+SUMPRODUCT(('Budget original'!$A$8:$A$501=$A17)*('Budget original'!$C$3:$AO$3=D$2),'Budget original'!$C$8:$AO$501)} -> 2 | E17: =IF(D17=0,0,F17/D17) -> 0 | F17: {=+SUMPRODUCT(('Budget original'!$A$8:$A$501=$A17)*('Budget original'!$C$3:$AO$3=F$2),'Budget original'!$C$8:$AO$501)} -> 0 | J17: =-SUMIFS(BV_Data_An_Cour!$P:$P,BV_Data_An_Cour!$U:$U,$B17,BV_Data_An_Cour!$V:$V,$C17,BV_Data_An_Cour!$W:$W,J$2) -> 0 | K17: =IF(J17=0,0,L17/J17) -> 0 | L17: =-SUMIFS(BV_Data_An_Cour!$P:$P,BV_Data_An_Cour!$U:$U,$B17,BV_Data_An_Cour!$V:$V,$C17,BV_Data_An_Cour!$W:$W,L$2) -> 0 | M17: =J17-D17 -> -2 | N17: =L17-F17 -> 0 | O17: {=+SUMPRODUCT(('Réel 2024'!$A$8:$A$501=$A17)*('Réel 2024'!$C$3:$AO$3=O$2),'Réel 2024'!$C$8:$AO$501)} -> 1 | P17: =IF(O17=0,0,Q17/O17) -> 0 | Q17: {=+SUMPRODUCT(('Réel 2024'!$A$8:$A$501=$A17)*('Réel 2024'!$C$3:$AO$3=Q$2),'Réel 2024'!$C$8:$AO$501)} -> 0 | R17: =J17-O17 -> -1 | S17: =L17-Q17 -> 0
A18: =+B18&C18 -> Véhicules neufs | B18: =+$K$1 -> Véhicules neufs
A19: =+B19&C19 -> Véhicules neufsRachat bail | B19: =+$K$1 -> Véhicules neufs | C19: Rachat bail | D19: {=+SUMPRODUCT(('Budget original'!$A$8:$A$501=$A19)*('Budget original'!$C$3:$AO$3=D$2),'Budget original'!$C$8:$AO$501)} -> 0 | E19: =IF(D19=0,0,F19/D19) -> 0 | F19: {=+SUMPRODUCT(('Budget original'!$A$8:$A$501=$A19)*('Budget original'!$C$3:$AO$3=F$2),'Budget original'!$C$8:$AO$501)} -> 9747.2565 | L19: =-SUMIFS(BV_Data_An_Cour!$P:$P,BV_Data_An_Cour!$U:$U,$B19,BV_Data_An_Cour!$V:$V,$C19,BV_Data_An_Cour!$W:$W,L$2) -> 12925.72 | N19: =L19-F19 -> 3178.4635 | O19: {=+SUMPRODUCT(('Réel 2024'!$A$8:$A$501=$A19)*('Réel 2024'!$C$3:$AO$3=O$2),'Réel 2024'!$C$8:$AO$501)} -> 0 | P19: =IF(O19=0,0,Q19/O19) -> 0 | Q19: {=+SUMPRODUCT(('Réel 2024'!$A$8:$A$501=$A19)*('Réel 2024'!$C$3:$AO$3=Q$2),'Réel 2024'!$C$8:$AO$501)} -> 11435.16 | R19: =O19-K19 -> 0 | S19: =L19-Q19 -> 1490.56
A20: =+B20&C20 -> Véhicules neufs | B20: =+$K$1 -> Véhicules neufs
A21: =+B21&C21 -> Véhicules neufsRev. Finances | B21: =+$K$1 -> Véhicules neufs | C21: Rev. Finances | F21: {=+SUMPRODUCT(('Budget original'!$A$8:$A$501=$A21)*('Budget original'!$C$3:$AO$3=F$2),'Budget original'!$C$8:$AO$501)} -> 2125 | K21: =IF(J13=0,0,L21/(J13+J15)) -> 44.504304 | L21: =-SUMIFS(BV_Data_An_Cour!$P:$P,BV_Data_An_Cour!$U:$U,$B21,BV_Data_An_Cour!$V:$V,$C21,BV_Data_An_Cour!$W:$W,L$2) -> 3515.84 | N21: =L21-F21 -> 1390.84 | Q21: {=+SUMPRODUCT(('Réel 2024'!$A$8:$A$501=$A21)*('Réel 2024'!$C$3:$AO$3=Q$2),'Réel 2024'!$C$8:$AO$501)} -> 2848.69 | R21: =O21-K21 -> -44.504304 | S21: =L21-Q21 -> 667.15
A22: =+B22&C22 -> Véhicules neufsRev. Protections | B22: =+$K$1 -> Véhicules neufs | C22: Rev. Protections | F22: {=+SUMPRODUCT(('Budget original'!$A$8:$A$501=$A22)*('Budget original'!$C$3:$AO$3=F$2),'Budget original'!$C$8:$AO$501)} -> 97750 | K22: =IF(J13=0,0,L22/(J13+J15)) -> 1208.9252 | L22: =-SUMIFS(BV_Data_An_Cour!$P:$P,BV_Data_An_Cour!$U:$U,$B22,BV_Data_An_Cour!$V:$V,$C22,BV_Data_An_Cour!$W:$W,L$2) -> 95505.09 | N22: =L22-F22 -> -2244.91 | Q22: {=+SUMPRODUCT(('Réel 2024'!$A$8:$A$501=$A22)*('Réel 2024'!$C$3:$AO$3=Q$2),'Réel 2024'!$C$8:$AO$501)} -> 83349.34 | R22: =O22-K22 -> -1208.9252 | S22: =L22-Q22 -> 12155.75
A23: =+B23&C23 -> Véhicules neufsRev. Autres | B23: =+$K$1 -> Véhicules neufs | C23: Rev. Autres | F23: {=+SUMPRODUCT(('Budget original'!$A$8:$A$501=$A23)*('Budget original'!$C$3:$AO$3=F$2),'Budget original'!$C$8:$AO$501)} -> 40800 | K23: =IF(J13=0,0,L23/(J13+J15)) -> 596.63785 | L23: =-SUMIFS(BV_Data_An_Cour!$P:$P,BV_Data_An_Cour!$U:$U,$B23,BV_Data_An_Cour!$V:$V,$C23,BV_Data_An_Cour!$W:$W,L$2) -> 47134.39 | N23: =L23-F23 -> 6334.39 | Q23: {=+SUMPRODUCT(('Réel 2024'!$A$8:$A$501=$A23)*('Réel 2024'!$C$3:$AO$3=Q$2),'Réel 2024'!$C$8:$AO$501)} -> 32619.63 | R23: =O23-K23 -> -596.63785 | S23: =L23-Q23 -> 14514.76
A24: =+B24&C24 -> Véhicules neufsTotal F&I | B24: =+$K$1 -> Véhicules neufs | C24: Total F&I | D24: =+D15+D13 -> 85 | E24: =IF(D24<=0,0,F24/D24) -> 1655 | F24: =F21+F22+F23 -> 140675 | J24: =+J15+J13 -> 79 | K24: =IF(J24<=0,0,L24/J24) -> 1850.0673 | L24: =L21+L22+L23 -> 146155.32 | M24: =J24-D24 -> -6 | N24: =L24-F24 -> 5480.32 | O24: =+O15+O13 -> 68 | P24: =IF(O24<=0,0,Q24/O24) -> 1747.3185 | Q24: =Q21+Q22+Q23 -> 118817.66 | S24: =L24-Q24 -> 27337.66
A25: =+B25&C25 -> Véhicules neufs | B25: =+$K$1 -> Véhicules neufs | N25: =IF(N24=0,0,N24/F24) -> 0.038957313 | S25: =IF(Q24=0,0,(S24/Q24)) -> 0.23008078
A26: =+B26&C26 -> Véhicules neufs | B26: =+$K$1 -> Véhicules neufs
A27: =+B27&C27 -> Véhicules neufsTotal Dépt. Neufs | B27: =+$K$1 -> Véhicules neufs | C27: Total Dépt. Neufs | D27: =+D13+D15+D17 -> 87 | E27: =IF(D27<=0,0,F27/D27) -> 5321.385 | F27: =F13+F17+F24+F19+F15 -> 462960.49 | J27: =+J13+J15+J17 -> 79 | K27: =IF(J27<=0,0,L27/J27) -> 6152.7514 | L27: =L13+L17+L24+L19+L15 -> 486067.36 | M27: =J27-D27 -> -8 | N27: =L27-F27 -> 23106.866 | O27: =+O13+O15+O17 -> 69 | P27: =IF(O27<=0,0,Q27/O27) -> 6522.5913 | Q27: =Q13+Q17+Q24+Q19+Q15 -> 450058.8 | R27: =J27-O27 -> 10 | S27: =L27-Q27 -> 36008.56
A28: =+B28&C28 -> Véhicules neufs | B28: =+$K$1 -> Véhicules neufs | M28: =M27/D27 -> -0.091954023 | N28: =N27/F27 -> 0.049911097 | R28: =R27/O27 -> 0.14492754 | S28: =IF(Q27=0,0,S27/Q27) -> 0.080008568
A29: =+B29&C29 -> Véhicules neufs | B29: =+$K$1 -> Véhicules neufs
A30: =+B30&C30 -> Véhicules neufsDEPENSES | B30: =+$K$1 -> Véhicules neufs | C30: DEPENSES
A31: =+B31&C31 -> Véhicules neufsComm. vendeurs | B31: =+$K$1 -> Véhicules neufs | C31: Comm. vendeurs | E31: =F31/D$24 -> 1078.924 | F31: {=+SUMPRODUCT(('Budget original'!$A$8:$A$501=$A31)*('Budget original'!$C$3:$AO$3=F$2),'Budget original'!$C$8:$AO$501)} -> 91708.538 | J31: =L31/(L13+L15) -> 0.25198443 | K31: =IF(L31=0,0,L31/J$24) -> 1042.9805 | L31: =SUMIFS(BV_Data_An_Cour!$P:$P,BV_Data_An_Cour!$U:$U,$B31,BV_Data_An_Cour!$V:$V,$C31,BV_Data_An_Cour!$W:$W,L$2) -> 82395.46 | N31: =L31-F31 -> -9313.0782 | P31: =Q31/O$24 -> 1308.3263 | Q31: {=+SUMPRODUCT(('Réel 2024'!$A$8:$A$501=$A31)*('Réel 2024'!$C$3:$AO$3=Q$2),'Réel 2024'!$C$8:$AO$501)} -> 88966.19 | S31: =L31-Q31 -> -6570.73
A32: =+B32&C32 -> Véhicules neufsComm. F&I | B32: =+$K$1 -> Véhicules neufs | C32: Comm. F&I | E32: =F32/D$24 -> 455.125 | F32: {=+SUMPRODUCT(('Budget original'!$A$8:$A$501=$A32)*('Budget original'!$C$3:$AO$3=F$2),'Budget original'!$C$8:$AO$501)} -> 38685.625 | J32: =L32/L24 -> 0.28408641 | K32: =IF(L32=0,0,L32/J$24) -> 525.57899 | L32: =SUMIFS(BV_Data_An_Cour!$P:$P,BV_Data_An_Cour!$U:$U,$B32,BV_Data_An_Cour!$V:$V,$C32,BV_Data_An_Cour!$W:$W,L$2) -> 41520.74 | N32: =L32-F32 -> 2835.115 | P32: =Q32/O$24 -> 718.58324 | Q32: {=+SUMPRODUCT(('Réel 2024'!$A$8:$A$501=$A32)*('Réel 2024'!$C$3:$AO$3=Q$2),'Réel 2024'!$C$8:$AO$501)} -> 48863.66 | S32: =L32-Q32 -> -7342.92
A33: =+B33&C33 -> Véhicules neufsFrais de livraison | B33: =+$K$1 -> Véhicules neufs | C33: Frais de livraison | E33: =F33/D$24 -> 130 | F33: {=+SUMPRODUCT(('Budget original'!$A$8:$A$501=$A33)*('Budget original'!$C$3:$AO$3=F$2),'Budget original'!$C$8:$AO$501)} -> 11050 | K33: =IF(L33=0,0,L33/J$24) -> 83.048987 | L33: =SUMIFS(BV_Data_An_Cour!$P:$P,BV_Data_An_Cour!$U:$U,$B33,BV_Data_An_Cour!$V:$V,$C33,BV_Data_An_Cour!$W:$W,L$2) -> 6560.87 | N33: =L33-F33 -> -4489.13 | P33: =Q33/O$24 -> 113.44382 | Q33: {=+SUMPRODUCT(('Réel 2024'!$A$8:$A$501=$A33)*('Réel 2024'!$C$3:$AO$3=Q$2),'Réel 2024'!$C$8:$AO$501)} -> 7714.18 | S33: =L33-Q33 -> -1153.31
A34: =+B34&C34 -> Véhicules neufsService gratuit 1 | B34: =+$K$1 -> Véhicules neufs | C34: Service gratuit 1 | E34: =F34/D$24 -> 37 | F34: {=+SUMPRODUCT(('Budget original'!$A$8:$A$501=$A34)*('Budget original'!$C$3:$AO$3=F$2),'Budget original'!$C$8:$AO$501)} -> 3145 | K34: =IF(L34=0,0,L34/J$24) -> 35.478608 | L34: =SUMIFS(BV_Data_An_Cour!$P:$P,BV_Data_An_Cour!$U:$U,$B34,BV_Data_An_Cour!$V:$V,$C34,BV_Data_An_Cour!$W:$W,L$2) -> 2802.81 | N34: =L34-F34 -> -342.19 | P34: =Q34/O$24 -> 39.178971 | Q34: {=+SUMPRODUCT(('Réel 2024'!$A$8:$A$501=$A34)*('Réel 2024'!$C$3:$AO$3=Q$2),'Réel 2024'!$C$8:$AO$501)} -> 2664.17 | S34: =L34-Q34 -> 138.64
A35: =+B35&C35 -> Véhicules neufsEntretien stock | B35: =+$K$1 -> Véhicules neufs | C35: Entretien stock | E35: =F35/D$24 -> 62.058824 | F35: {=+SUMPRODUCT(('Budget original'!$A$8:$A$501=$A35)*('Budget original'!$C$3:$AO$3=F$2),'Budget original'!$C$8:$AO$501)} -> 5275 | K35: =IF(L35=0,0,L35/J$24) -> 74.960759 | L35: =SUMIFS(BV_Data_An_Cour!$P:$P,BV_Data_An_Cour!$U:$U,$B35,BV_Data_An_Cour!$V:$V,$C35,BV_Data_An_Cour!$W:$W,L$2) -> 5921.9 | N35: =L35-F35 -> 646.9 | P35: =Q35/O$24 -> 72.974706 | Q35: {=+SUMPRODUCT(('Réel 2024'!$A$8:$A$501=$A35)*('Réel 2024'!$C$3:$AO$3=Q$2),'Réel 2024'!$C$8:$AO$501)} -> 4962.28 | S35: =L35-Q35 -> 959.62
A36: =+B36&C36 -> Véhicules neufsPublicité 1 | B36: =+$K$1 -> Véhicules neufs | C36: Publicité 1 | E36: =F36/D$24 -> 513.97059 | F36: {=+SUMPRODUCT(('Budget original'!$A$8:$A$501=$A36)*('Budget original'!$C$3:$AO$3=F$2),'Budget original'!$C$8:$AO$501)} -> 43687.5 | K36: =IF(L36=0,0,L36/J$24) -> 650.16228 | L36: =SUMIFS(BV_Data_An_Cour!$P:$P,BV_Data_An_Cour!$U:$U,$B36,BV_Data_An_Cour!$V:$V,$C36,BV_Data_An_Cour!$W:$W,L$2) -> 51362.82 | N36: =L36-F36 -> 7675.32 | P36: =Q36/O$24 -> 622.98779 | Q36: {=+SUMPRODUCT(('Réel 2024'!$A$8:$A$501=$A36)*('Réel 2024'!$C$3:$AO$3=Q$2),'Réel 2024'!$C$8:$AO$501)} -> 42363.17 | S36: =L36-Q36 -> 8999.65
A37: =+B37&C37 -> Véhicules neufsIntérêt de gros | B37: =+$K$1 -> Véhicules neufs | C37: Intérêt de gros | E37: =F37/D$24 -> 1330.4575 | F37: {=+SUMPRODUCT(('Budget original'!$A$8:$A$501=$A37)*('Budget original'!$C$3:$AO$3=F$2),'Budget original'!$C$8:$AO$501)} -> 113088.89 | K37: =IF(L37=0,0,L37/J$24) -> 1172.5304 | L37: =SUMIFS(BV_Data_An_Cour!$P:$P,BV_Data_An_Cour!$U:$U,$B37,BV_Data_An_Cour!$V:$V,$C37,BV_Data_An_Cour!$W:$W,L$2) -> 92629.9 | N37: =L37-F37 -> -20458.986 | P37: =Q37/O$24 -> 1897.5865 | Q37: {=+SUMPRODUCT(('Réel 2024'!$A$8:$A$501=$A37)*('Réel 2024'!$C$3:$AO$3=Q$2),'Réel 2024'!$C$8:$AO$501)} -> 129035.88 | S37: =L37-Q37 -> -36405.98
A38: =+B38&C38 -> Véhicules neufs[...] | B38: =+$K$1 -> Véhicules neufs | C38: [...] | E38: =F38/D$24 -> 0 | F38: {=+SUMPRODUCT(('Budget original'!$A$8:$A$501=$A38)*('Budget original'!$C$3:$AO$3=F$2),'Budget original'!$C$8:$AO$501)} -> 0 | K38: =IF(L38=0,0,L38/J$24) -> 0 | L38: =SUMIFS(BV_Data_An_Cour!$P:$P,BV_Data_An_Cour!$U:$U,$B38,BV_Data_An_Cour!$V:$V,$C38,BV_Data_An_Cour!$W:$W,L$2) -> 0 | N38: =L38-F38 -> 0 | P38: =Q38/O$24 -> 0 | Q38: {=+SUMPRODUCT(('Réel 2024'!$A$8:$A$501=$A38)*('Réel 2024'!$C$3:$AO$3=Q$2),'Réel 2024'!$C$8:$AO$501)} -> 0 | S38: =L38-Q38 -> 0
A39: =+B39&C39 -> Véhicules neufs[...] | B39: =+$K$1 -> Véhicules neufs | C39: [...] | E39: =F39/D$24 -> 0 | F39: {=+SUMPRODUCT(('Budget original'!$A$8:$A$501=$A39)*('Budget original'!$C$3:$AO$3=F$2),'Budget original'!$C$8:$AO$501)} -> 0 | K39: =IF(L39=0,0,L39/J$24) -> 0 | L39: =SUMIFS(BV_Data_An_Cour!$P:$P,BV_Data_An_Cour!$U:$U,$B39,BV_Data_An_Cour!$V:$V,$C39,BV_Data_An_Cour!$W:$W,L$2) -> 0 | N39: =L39-F39 -> 0 | P39: =Q39/O$24 -> 0 | Q39: {=+SUMPRODUCT(('Réel 2024'!$A$8:$A$501=$A39)*('Réel 2024'!$C$3:$AO$3=Q$2),'Réel 2024'!$C$8:$AO$501)} -> 0 | S39: =L39-Q39 -> 0
A40: =+B40&C40 -> Véhicules neufs[...] | B40: =+$K$1 -> Véhicules neufs | C40: [...] | E40: =F40/D$24 -> 0 | F40: {=+SUMPRODUCT(('Budget original'!$A$8:$A$501=$A40)*('Budget original'!$C$3:$AO$3=F$2),'Budget original'!$C$8:$AO$501)} -> 0 | K40: =IF(L40=0,0,L40/J$24) -> 0 | L40: =SUMIFS(BV_Data_An_Cour!$P:$P,BV_Data_An_Cour!$U:$U,$B40,BV_Data_An_Cour!$V:$V,$C40,BV_Data_An_Cour!$W:$W,L$2) -> 0 | N40: =L40-F40 -> 0 | P40: =Q40/O$24 -> 0 | Q40: {=+SUMPRODUCT(('Réel 2024'!$A$8:$A$501=$A40)*('Réel 2024'!$C$3:$AO$3=Q$2),'Réel 2024'!$C$8:$AO$501)} -> 0 | S40: =L40-Q40 -> 0
A41: =+B41&C41 -> Véhicules neufsTOTAL VARIABLES | B41: =+$K$1 -> Véhicules neufs | C41: TOTAL VARIABLES | D41: % brut | E41: =F41/F$27 -> 0.66234712 | F41: =SUM(F31:F40) -> 306640.55 | J41: % brut | K41: =L41/L$27 -> 0.58262398 | L41: =SUM(L31:L40) -> 283194.5 | N41: =L41-F41 -> -23446.049 | O41: % brut | P41: =Q41/Q$27 -> 0.72117139 | Q41: =SUM(Q31:Q40) -> 324569.53 | S41: =L41-Q41 -> -41375.03
A42: =+B42&C42 -> Véhicules neufsSalaires cadres | B42: =+$K$1 -> Véhicules neufs | C42: Salaires cadres | F42: {=+SUMPRODUCT(('Budget original'!$A$8:$A$501=$A42)*('Budget original'!$C$3:$AO$3=F$2),'Budget original'!$C$8:$AO$501)} -> 49911.372 | L42: =SUMIFS(BV_Data_An_Cour!$P:$P,BV_Data_An_Cour!$U:$U,$B42,BV_Data_An_Cour!$V:$V,$C42,BV_Data_An_Cour!$W:$W,L$2) -> 52431.83 | N42: =L42-F42 -> 2520.4576 | Q42: {=+SUMPRODUCT(('Réel 2024'!$A$8:$A$501=$A42)*('Réel 2024'!$C$3:$AO$3=Q$2),'Réel 2024'!$C$8:$AO$501)} -> 48542.42
A43: =+B43&C43 -> Véhicules neufsSalaires commis | B43: =+$K$1 -> Véhicules neufs | C43: Salaires commis | F43: {=+SUMPRODUCT(('Budget original'!$A$8:$A$501=$A43)*('Budget original'!$C$3:$AO$3=F$2),'Budget original'!$C$8:$AO$501)} -> 38491.156 | L43: =SUMIFS(BV_Data_An_Cour!$P:$P,BV_Data_An_Cour!$U:$U,$B43,BV_Data_An_Cour!$V:$V,$C43,BV_Data_An_Cour!$W:$W,L$2) -> 37429.83 | N43: =L43-F43 -> -1061.3263 | Q43: {=+SUMPRODUCT(('Réel 2024'!$A$8:$A$501=$A43)*('Réel 2024'!$C$3:$AO$3=Q$2),'Réel 2024'!$C$8:$AO$501)} -> 33263.99 | S43: =L43-Q43 -> 4165.84
A44: =+B44&C44 -> Véhicules neufsSalaires autres | B44: =+$K$1 -> Véhicules neufs | C44: Salaires autres | F44: {=+SUMPRODUCT(('Budget original'!$A$8:$A$501=$A44)*('Budget original'!$C$3:$AO$3=F$2),'Budget original'!$C$8:$AO$501)} -> 1368 | L44: =SUMIFS(BV_Data_An_Cour!$P:$P,BV_Data_An_Cour!$U:$U,$B44,BV_Data_An_Cour!$V:$V,$C44,BV_Data_An_Cour!$W:$W,L$2) -> 1368 | N44: =L44-F44 -> 0 | Q44: {=+SUMPRODUCT(('Réel 2024'!$A$8:$A$501=$A44)*('Réel 2024'!$C$3:$AO$3=Q$2),'Réel 2024'!$C$8:$AO$501)} -> 1368 | S44: =L44-Q44 -> 0
A45: =+B45&C45 -> Véhicules neufsSalaires spécialistes | B45: =+$K$1 -> Véhicules neufs | C45: Salaires spécialistes | F45: {=+SUMPRODUCT(('Budget original'!$A$8:$A$501=$A45)*('Budget original'!$C$3:$AO$3=F$2),'Budget original'!$C$8:$AO$501)} -> 0 | L45: =SUMIFS(BV_Data_An_Cour!$P:$P,BV_Data_An_Cour!$U:$U,$B45,BV_Data_An_Cour!$V:$V,$C45,BV_Data_An_Cour!$W:$W,L$2) -> 0 | N45: =L45-F45 -> 0 | Q45: {=+SUMPRODUCT(('Réel 2024'!$A$8:$A$501=$A45)*('Réel 2024'!$C$3:$AO$3=Q$2),'Réel 2024'!$C$8:$AO$501)} -> 0 | S45: =L45-Q45 -> 0
A46: =+B46&C46 -> Véhicules neufs[...] | B46: =+$K$1 -> Véhicules neufs | C46: [...] | F46: {=+SUMPRODUCT(('Budget original'!$A$8:$A$501=$A46)*('Budget original'!$C$3:$AO$3=F$2),'Budget original'!$C$8:$AO$501)} -> 0 | L46: =SUMIFS(BV_Data_An_Cour!$P:$P,BV_Data_An_Cour!$U:$U,$B46,BV_Data_An_Cour!$V:$V,$C46,BV_Data_An_Cour!$W:$W,L$2) -> 0 | N46: =L46-F46 -> 0 | Q46: {=+SUMPRODUCT(('Réel 2024'!$A$8:$A$501=$A46)*('Réel 2024'!$C$3:$AO$3=Q$2),'Réel 2024'!$C$8:$AO$501)} -> 0 | S46: =L46-Q46 -> 0
A47: =+B47&C47 -> Véhicules neufs[...] | B47: =+$K$1 -> Véhicules neufs | C47: [...] | F47: {=+SUMPRODUCT(('Budget original'!$A$8:$A$501=$A47)*('Budget original'!$C$3:$AO$3=F$2),'Budget original'!$C$8:$AO$501)} -> 0 | L47: =SUMIFS(BV_Data_An_Cour!$P:$P,BV_Data_An_Cour!$U:$U,$B47,BV_Data_An_Cour!$V:$V,$C47,BV_Data_An_Cour!$W:$W,L$2) -> 0 | N47: =L47-F47 -> 0 | Q47: {=+SUMPRODUCT(('Réel 2024'!$A$8:$A$501=$A47)*('Réel 2024'!$C$3:$AO$3=Q$2),'Réel 2024'!$C$8:$AO$501)} -> 0 | S47: =L47-Q47 -> 0
A48: =+B48&C48 -> Véhicules neufs[...] | B48: =+$K$1 -> Véhicules neufs | C48: [...] | F48: {=+SUMPRODUCT(('Budget original'!$A$8:$A$501=$A48)*('Budget original'!$C$3:$AO$3=F$2),'Budget original'!$C$8:$AO$501)} -> 0 | L48: =SUMIFS(BV_Data_An_Cour!$P:$P,BV_Data_An_Cour!$U:$U,$B48,BV_Data_An_Cour!$V:$V,$C48,BV_Data_An_Cour!$W:$W,L$2) -> 0 | N48: =L48-F48 -> 0 | Q48: {=+SUMPRODUCT(('Réel 2024'!$A$8:$A$501=$A48)*('Réel 2024'!$C$3:$AO$3=Q$2),'Réel 2024'!$C$8:$AO$501)} -> 0 | S48: =L48-Q48 -> 0
A49: =+B49&C49 -> Véhicules neufsSalaires en absences | B49: =+$K$1 -> Véhicules neufs | C49: Salaires en absences | F49: {=+SUMPRODUCT(('Budget original'!$A$8:$A$501=$A49)*('Budget original'!$C$3:$AO$3=F$2),'Budget original'!$C$8:$AO$501)} -> 27117.908 | L49: =SUMIFS(BV_Data_An_Cour!$P:$P,BV_Data_An_Cour!$U:$U,$B49,BV_Data_An_Cour!$V:$V,$C49,BV_Data_An_Cour!$W:$W,L$2) -> 34182.69 | N49: =L49-F49 -> 7064.7815 | Q49: {=+SUMPRODUCT(('Réel 2024'!$A$8:$A$501=$A49)*('Réel 2024'!$C$3:$AO$3=Q$2),'Réel 2024'!$C$8:$AO$501)} -> 31183.28 | S49: =L49-Q49 -> 2999.41
A50: =+B50&C50 -> Véhicules neufsDéduction à la source | B50: =+$K$1 -> Véhicules neufs | C50: Déduction à la source | F50: {=+SUMPRODUCT(('Budget original'!$A$8:$A$501=$A50)*('Budget original'!$C$3:$AO$3=F$2),'Budget original'!$C$8:$AO$501)} -> 36791.65 | L50: =SUMIFS(BV_Data_An_Cour!$P:$P,BV_Data_An_Cour!$U:$U,$B50,BV_Data_An_Cour!$V:$V,$C50,BV_Data_An_Cour!$W:$W,L$2) -> 42331.95 | N50: =L50-F50 -> 5540.3 | Q50: {=+SUMPRODUCT(('Réel 2024'!$A$8:$A$501=$A50)*('Réel 2024'!$C$3:$AO$3=Q$2),'Réel 2024'!$C$8:$AO$501)} -> 39328.01 | S50: =L50-Q50 -> 3003.94
A51: =+B51&C51 -> Véhicules neufsBénéfices marginaux | B51: =+$K$1 -> Véhicules neufs | C51: Bénéfices marginaux | F51: {=+SUMPRODUCT(('Budget original'!$A$8:$A$501=$A51)*('Budget original'!$C$3:$AO$3=F$2),'Budget original'!$C$8:$AO$501)} -> 17182.275 | L51: =SUMIFS(BV_Data_An_Cour!$P:$P,BV_Data_An_Cour!$U:$U,$B51,BV_Data_An_Cour!$V:$V,$C51,BV_Data_An_Cour!$W:$W,L$2) -> 18343.35 | N51: =L51-F51 -> 1161.075 | Q51: {=+SUMPRODUCT(('Réel 2024'!$A$8:$A$501=$A51)*('Réel 2024'!$C$3:$AO$3=Q$2),'Réel 2024'!$C$8:$AO$501)} -> 16432.44 | S51: =L51-Q51 -> 1910.91
A52: =+B52&C52 -> Véhicules neufsCsst | B52: =+$K$1 -> Véhicules neufs | C52: Csst | F52: {=+SUMPRODUCT(('Budget original'!$A$8:$A$501=$A52)*('Budget original'!$C$3:$AO$3=F$2),'Budget original'!$C$8:$AO$501)} -> 3681.9161 | L52: =SUMIFS(BV_Data_An_Cour!$P:$P,BV_Data_An_Cour!$U:$U,$B52,BV_Data_An_Cour!$V:$V,$C52,BV_Data_An_Cour!$W:$W,L$2) -> 5909.11 | N52: =L52-F52 -> 2227.1939 | Q52: {=+SUMPRODUCT(('Réel 2024'!$A$8:$A$501=$A52)*('Réel 2024'!$C$3:$AO$3=Q$2),'Réel 2024'!$C$8:$AO$501)} -> 4727.58 | S52: =L52-Q52 -> 1181.53
A53: =+B53&C53 -> Véhicules neufs[...] | B53: =+$K$1 -> Véhicules neufs | C53: [...] | F53: {=+SUMPRODUCT(('Budget original'!$A$8:$A$501=$A53)*('Budget original'!$C$3:$AO$3=F$2),'Budget original'!$C$8:$AO$501)} -> 0 | L53: =SUMIFS(BV_Data_An_Cour!$P:$P,BV_Data_An_Cour!$U:$U,$B53,BV_Data_An_Cour!$V:$V,$C53,BV_Data_An_Cour!$W:$W,L$2) -> 0 | N53: =L53-F53 -> 0 | Q53: {=+SUMPRODUCT(('Réel 2024'!$A$8:$A$501=$A53)*('Réel 2024'!$C$3:$AO$3=Q$2),'Réel 2024'!$C$8:$AO$501)} -> 0 | S53: =L53-Q53 -> 0
A54: =+B54&C54 -> Véhicules neufsTOTAL PERSONNEL | B54: =+$K$1 -> Véhicules neufs | C54: TOTAL PERSONNEL | D54: % brut | E54: =F54/F$27 -> 0.37701765 | F54: =+SUM(F42:F53) -> 174544.28 | J54: % brut | K54: =L54/L$27 -> 0.39500031 | L54: =+SUM(L42:L53) -> 191996.76 | N54: =+SUM(N42:N53) -> 17452.482 | O54: % brut | P54: =Q54/Q$27 -> 0.38849528 | Q54: =+SUM(Q42:Q53) -> 174845.72 | S54: =+SUM(S42:S53) -> 13261.63
A55: =+B55&C55 -> Véhicules neufsPublicité 2 | B55: =+$K$1 -> Véhicules neufs | C55: Publicité 2 | F55: {=+SUMPRODUCT(('Budget original'!$A$8:$A$501=$A55)*('Budget original'!$C$3:$AO$3=F$2),'Budget original'!$C$8:$AO$501)} -> 0 | L55: =SUMIFS(BV_Data_An_Cour!$P:$P,BV_Data_An_Cour!$U:$U,$B55,BV_Data_An_Cour!$V:$V,$C55,BV_Data_An_Cour!$W:$W,L$2) -> 0 | N55: =L55-F55 -> 0 | Q55: {=+SUMPRODUCT(('Réel 2024'!$A$8:$A$501=$A55)*('Réel 2024'!$C$3:$AO$3=Q$2),'Réel 2024'!$C$8:$AO$501)} -> 0 | S55: =L55-Q55 -> 0
A56: =+B56&C56 -> Véhicules neufsService gratuit 2 | B56: =+$K$1 -> Véhicules neufs | C56: Service gratuit 2 | F56: {=+SUMPRODUCT(('Budget original'!$A$8:$A$501=$A56)*('Budget original'!$C$3:$AO$3=F$2),'Budget original'!$C$8:$AO$501)} -> 0 | L56: =SUMIFS(BV_Data_An_Cour!$P:$P,BV_Data_An_Cour!$U:$U,$B56,BV_Data_An_Cour!$V:$V,$C56,BV_Data_An_Cour!$W:$W,L$2) -> 0 | N56: =L56-F56 -> 0 | Q56: {=+SUMPRODUCT(('Réel 2024'!$A$8:$A$501=$A56)*('Réel 2024'!$C$3:$AO$3=Q$2),'Réel 2024'!$C$8:$AO$501)} -> 0 | S56: =L56-Q56 -> 0
A57: =+B57&C57 -> Véhicules neufsFrais véhicules de cie | B57: =+$K$1 -> Véhicules neufs | C57: Frais véhicules de cie | F57: {=+SUMPRODUCT(('Budget original'!$A$8:$A$501=$A57)*('Budget original'!$C$3:$AO$3=F$2),'Budget original'!$C$8:$AO$501)} -> 26483.733 | L57: =SUMIFS(BV_Data_An_Cour!$P:$P,BV_Data_An_Cour!$U:$U,$B57,BV_Data_An_Cour!$V:$V,$C57,BV_Data_An_Cour!$W:$W,L$2) -> 29273.18 | N57: 0 | Q57: {=+SUMPRODUCT(('Réel 2024'!$A$8:$A$501=$A57)*('Réel 2024'!$C$3:$AO$3=Q$2),'Réel 2024'!$C$8:$AO$501)} -> 21142.27 | S57: =L57-Q57 -> 8130.91
A58: =+B58&C58 -> Véhicules neufsInformatique | B58: =+$K$1 -> Véhicules neufs | C58: Informatique | F58: {=+SUMPRODUCT(('Budget original'!$A$8:$A$501=$A58)*('Budget original'!$C$3:$AO$3=F$2),'Budget original'!$C$8:$AO$501)} -> 19513.2 | L58: =SUMIFS(BV_Data_An_Cour!$P:$P,BV_Data_An_Cour!$U:$U,$B58,BV_Data_An_Cour!$V:$V,$C58,BV_Data_An_Cour!$W:$W,L$2) -> 20063.84 | N58: =L58-F58 -> 550.64 | Q58: {=+SUMPRODUCT(('Réel 2024'!$A$8:$A$501=$A58)*('Réel 2024'!$C$3:$AO$3=Q$2),'Réel 2024'!$C$8:$AO$501)} -> 18029.82 | S58: =L58-Q58 -> 2034.02
A59: =+B59&C59 -> Véhicules neufsFrais de déplacement | B59: =+$K$1 -> Véhicules neufs | C59: Frais de déplacement | F59: {=+SUMPRODUCT(('Budget original'!$A$8:$A$501=$A59)*('Budget original'!$C$3:$AO$3=F$2),'Budget original'!$C$8:$AO$501)} -> 3300 | L59: =SUMIFS(BV_Data_An_Cour!$P:$P,BV_Data_An_Cour!$U:$U,$B59,BV_Data_An_Cour!$V:$V,$C59,BV_Data_An_Cour!$W:$W,L$2) -> 3425.31 | N59: =L59-F59 -> 125.31 | Q59: {=+SUMPRODUCT(('Réel 2024'!$A$8:$A$501=$A59)*('Réel 2024'!$C$3:$AO$3=Q$2),'Réel 2024'!$C$8:$AO$501)} -> 3986.53 | S59: =L59-Q59 -> -561.22
A60: =+B60&C60 -> Véhicules neufsServices extérieurs | B60: =+$K$1 -> Véhicules neufs | C60: Services extérieurs | F60: {=+SUMPRODUCT(('Budget original'!$A$8:$A$501=$A60)*('Budget original'!$C$3:$AO$3=F$2),'Budget original'!$C$8:$AO$501)} -> 13258.8 | L60: =SUMIFS(BV_Data_An_Cour!$P:$P,BV_Data_An_Cour!$U:$U,$B60,BV_Data_An_Cour!$V:$V,$C60,BV_Data_An_Cour!$W:$W,L$2) -> 14699.56 | N60: =L60-F60 -> 1440.76 | Q60: {=+SUMPRODUCT(('Réel 2024'!$A$8:$A$501=$A60)*('Réel 2024'!$C$3:$AO$3=Q$2),'Réel 2024'!$C$8:$AO$501)} -> 12188.38 | S60: =L60-Q60 -> 2511.18
A61: =+B61&C61 -> Véhicules neufsFournitures autres | B61: =+$K$1 -> Véhicules neufs | C61: Fournitures autres | F61: {=+SUMPRODUCT(('Budget original'!$A$8:$A$501=$A61)*('Budget original'!$C$3:$AO$3=F$2),'Budget original'!$C$8:$AO$501)} -> 160 | L61: =SUMIFS(BV_Data_An_Cour!$P:$P,BV_Data_An_Cour!$U:$U,$B61,BV_Data_An_Cour!$V:$V,$C61,BV_Data_An_Cour!$W:$W,L$2) -> 127.27 | N61: =L61-F61 -> -32.73 | Q61: {=+SUMPRODUCT(('Réel 2024'!$A$8:$A$501=$A61)*('Réel 2024'!$C$3:$AO$3=Q$2),'Réel 2024'!$C$8:$AO$501)} -> 9.99 | S61: =L61-Q61 -> 117.28
A62: =+B62&C62 -> Véhicules neufsUniformes | B62: =+$K$1 -> Véhicules neufs | C62: Uniformes | F62: {=+SUMPRODUCT(('Budget original'!$A$8:$A$501=$A62)*('Budget original'!$C$3:$AO$3=F$2),'Budget original'!$C$8:$AO$501)} -> 120 | L62: =SUMIFS(BV_Data_An_Cour!$P:$P,BV_Data_An_Cour!$U:$U,$B62,BV_Data_An_Cour!$V:$V,$C62,BV_Data_An_Cour!$W:$W,L$2) -> 359.91 | N62: =L62-F62 -> 239.91 | Q62: {=+SUMPRODUCT(('Réel 2024'!$A$8:$A$501=$A62)*('Réel 2024'!$C$3:$AO$3=Q$2),'Réel 2024'!$C$8:$AO$501)} -> 0 | S62: =L62-Q62 -> 359.91
A63: =+B63&C63 -> Véhicules neufsPapeterie | B63: =+$K$1 -> Véhicules neufs | C63: Papeterie | F63: {=+SUMPRODUCT(('Budget original'!$A$8:$A$501=$A63)*('Budget original'!$C$3:$AO$3=F$2),'Budget original'!$C$8:$AO$501)} -> 2835 | L63: =SUMIFS(BV_Data_An_Cour!$P:$P,BV_Data_An_Cour!$U:$U,$B63,BV_Data_An_Cour!$V:$V,$C63,BV_Data_An_Cour!$W:$W,L$2) -> 2187.58 | N63: =L63-F63 -> -647.42 | Q63: {=+SUMPRODUCT(('Réel 2024'!$A$8:$A$501=$A63)*('Réel 2024'!$C$3:$AO$3=Q$2),'Réel 2024'!$C$8:$AO$501)} -> 1742.09 | S63: =L63-Q63 -> 445.49
A64: =+B64&C64 -> Véhicules neufsTéléphone | B64: =+$K$1 -> Véhicules neufs | C64: Téléphone | F64: {=+SUMPRODUCT(('Budget original'!$A$8:$A$501=$A64)*('Budget original'!$C$3:$AO$3=F$2),'Budget original'!$C$8:$AO$501)} -> 841.6 | L64: =SUMIFS(BV_Data_An_Cour!$P:$P,BV_Data_An_Cour!$U:$U,$B64,BV_Data_An_Cour!$V:$V,$C64,BV_Data_An_Cour!$W:$W,L$2) -> 1601.9 | N64: =L64-F64 -> 760.3 | Q64: {=+SUMPRODUCT(('Réel 2024'!$A$8:$A$501=$A64)*('Réel 2024'!$C$3:$AO$3=Q$2),'Réel 2024'!$C$8:$AO$501)} -> 897.81 | S64: =L64-Q64 -> 704.09
A65: =+B65&C65 -> Véhicules neufsFrais postaux | B65: =+$K$1 -> Véhicules neufs | C65: Frais postaux | F65: {=+SUMPRODUCT(('Budget original'!$A$8:$A$501=$A65)*('Budget original'!$C$3:$AO$3=F$2),'Budget original'!$C$8:$AO$501)} -> 810 | L65: =SUMIFS(BV_Data_An_Cour!$P:$P,BV_Data_An_Cour!$U:$U,$B65,BV_Data_An_Cour!$V:$V,$C65,BV_Data_An_Cour!$W:$W,L$2) -> 640.67 | N65: =L65-F65 -> -169.33 | Q65: {=+SUMPRODUCT(('Réel 2024'!$A$8:$A$501=$A65)*('Réel 2024'!$C$3:$AO$3=Q$2),'Réel 2024'!$C$8:$AO$501)} -> 805.09 | S65: =L65-Q65 -> -164.42
A66: =+B66&C66 -> Véhicules neufsDivers | B66: =+$K$1 -> Véhicules neufs | C66: Divers | F66: {=+SUMPRODUCT(('Budget original'!$A$8:$A$501=$A66)*('Budget original'!$C$3:$AO$3=F$2),'Budget original'!$C$8:$AO$501)} -> 3133.8 | L66: =SUMIFS(BV_Data_An_Cour!$P:$P,BV_Data_An_Cour!$U:$U,$B66,BV_Data_An_Cour!$V:$V,$C66,BV_Data_An_Cour!$W:$W,L$2) -> 2742.05 | N66: =L66-F66 -> -391.75 | Q66: {=+SUMPRODUCT(('Réel 2024'!$A$8:$A$501=$A66)*('Réel 2024'!$C$3:$AO$3=Q$2),'Réel 2024'!$C$8:$AO$501)} -> 3174.22 | S66: =L66-Q66 -> -432.17
A67: =+B67&C67 -> Véhicules neufsFormation | B67: =+$K$1 -> Véhicules neufs | C67: Formation | F67: {=+SUMPRODUCT(('Budget original'!$A$8:$A$501=$A67)*('Budget original'!$C$3:$AO$3=F$2),'Budget original'!$C$8:$AO$501)} -> 2232.734 | L67: =SUMIFS(BV_Data_An_Cour!$P:$P,BV_Data_An_Cour!$U:$U,$B67,BV_Data_An_Cour!$V:$V,$C67,BV_Data_An_Cour!$W:$W,L$2) -> 1803.69 | N67: =L67-F67 -> -429.04404 | Q67: {=+SUMPRODUCT(('Réel 2024'!$A$8:$A$501=$A67)*('Réel 2024'!$C$3:$AO$3=Q$2),'Réel 2024'!$C$8:$AO$501)} -> 567.88 | S67: =L67-Q67 -> 1235.81
A68: =+B68&C68 -> Véhicules neufsFrais bancaires | B68: =+$K$1 -> Véhicules neufs | C68: Frais bancaires | F68: {=+SUMPRODUCT(('Budget original'!$A$8:$A$501=$A68)*('Budget original'!$C$3:$AO$3=F$2),'Budget original'!$C$8:$AO$501)} -> 11072.239 | L68: =SUMIFS(BV_Data_An_Cour!$P:$P,BV_Data_An_Cour!$U:$U,$B68,BV_Data_An_Cour!$V:$V,$C68,BV_Data_An_Cour!$W:$W,L$2) -> 10988.16 | N68: =L68-F68 -> -84.07948 | Q68: {=+SUMPRODUCT(('Réel 2024'!$A$8:$A$501=$A68)*('Réel 2024'!$C$3:$AO$3=Q$2),'Réel 2024'!$C$8:$AO$501)} -> 10362.06 | S68: =L68-Q68 -> 626.1
A69: =+B69&C69 -> Véhicules neufs[...] | B69: =+$K$1 -> Véhicules neufs | C69: [...] | F69: {=+SUMPRODUCT(('Budget original'!$A$8:$A$501=$A69)*('Budget original'!$C$3:$AO$3=F$2),'Budget original'!$C$8:$AO$501)} -> 0 | N69: =L69-F69 -> 0 | Q69: {=+SUMPRODUCT(('Réel 2024'!$A$8:$A$501=$A69)*('Réel 2024'!$C$3:$AO$3=Q$2),'Réel 2024'!$C$8:$AO$501)} -> 0 | S69: =L69-Q69 -> 0
A70: =+B70&C70 -> Véhicules neufs[...] | B70: =+$K$1 -> Véhicules neufs | C70: [...] | F70: {=+SUMPRODUCT(('Budget original'!$A$8:$A$501=$A70)*('Budget original'!$C$3:$AO$3=F$2),'Budget original'!$C$8:$AO$501)} -> 0 | L70: =SUMIFS(BV_Data_An_Cour!$P:$P,BV_Data_An_Cour!$U:$U,$B70,BV_Data_An_Cour!$V:$V,$C70,BV_Data_An_Cour!$W:$W,L$2) -> 0 | N70: =L70-F70 -> 0 | Q70: {=+SUMPRODUCT(('Réel 2024'!$A$8:$A$501=$A70)*('Réel 2024'!$C$3:$AO$3=Q$2),'Réel 2024'!$C$8:$AO$501)} -> 0 | S70: =L70-Q70 -> 0
A71: =+B71&C71 -> Véhicules neufs[...] | B71: =+$K$1 -> Véhicules neufs | C71: [...] | F71: {=+SUMPRODUCT(('Budget original'!$A$8:$A$501=$A71)*('Budget original'!$C$3:$AO$3=F$2),'Budget original'!$C$8:$AO$501)} -> 0 | L71: =SUMIFS(BV_Data_An_Cour!$P:$P,BV_Data_An_Cour!$U:$U,$B71,BV_Data_An_Cour!$V:$V,$C71,BV_Data_An_Cour!$W:$W,L$2)*0.32 -> 0 | N71: =L71-F71 -> 0 | Q71: {=+SUMPRODUCT(('Réel 2024'!$A$8:$A$501=$A71)*('Réel 2024'!$C$3:$AO$3=Q$2),'Réel 2024'!$C$8:$AO$501)} -> 0 | S71: =L71-Q71 -> 0
A72: =+B72&C72 -> Véhicules neufsTOTAL SEMI-FIXES | B72: =+$K$1 -> Véhicules neufs | C72: TOTAL SEMI-FIXES | D72: % brut | E72: =F72/F$27 -> 0.18092496 | F72: =+SUM(F55:F71) -> 83761.107 | J72: % brut | K72: =L72/L$27 -> 0.18086613 | L72: =+SUM(L55:L71) -> 87913.12 | N72: =+SUM(N55:N71) -> 1362.5665 | O72: % brut | P72: =Q72/Q$27 -> 0.16199248 | Q72: =+SUM(Q55:Q71) -> 72906.14 | S72: =+SUM(S55:S71) -> 15006.98
A73: =+B73&C73 -> Véhicules neufs | B73: =+$K$1 -> Véhicules neufs
A74: =+B74&C74 -> Véhicules neufsTOTAL DES DÉPENSES | B74: =+$K$1 -> Véhicules neufs | C74: TOTAL DES DÉPENSES | D74: % brut | E74: =F74/F$27 -> 1.2202897 | F74: =F41+F54+F72 -> 564945.93 | J74: % brut | K74: =L74/L$27 -> 1.1584904 | L74: =L41+L54+L72 -> 563104.38 | N74: =L74-F74 -> -1841.5542 | O74: % brut | P74: =Q74/Q$27 -> 1.2716591 | Q74: =Q41+Q54+Q72 -> 572321.39 | S74: =L74-Q74 -> -9217.01
A75: =+B75&C75 -> Véhicules neufsRBSC neuf | B75: =+$K$1 -> Véhicules neufs | C75: RBSC neuf | F75: {=+SUMPRODUCT(('Budget original'!$A$8:$A$501=$A75)*('Budget original'!$C$3:$AO$3=F$2),'Budget original'!$C$8:$AO$501)} -> 137717.14 | L75: =-SUMIFS(BV_Data_An_Cour!$P:$P,BV_Data_An_Cour!$U:$U,$B75,BV_Data_An_Cour!$V:$V,$C75,BV_Data_An_Cour!$W:$W,L$2) -> 160463.64 | N75: =L75-F75 -> 22746.497 | Q75: {=+SUMPRODUCT(('Réel 2024'!$A$8:$A$501=$A75)*('Réel 2024'!$C$3:$AO$3=Q$2),'Réel 2024'!$C$8:$AO$501)} -> 110662.43 | S75: =L75-Q75 -> 49801.21
A76: =+B76&C76 -> Véhicules neufsProgramme neuf 2 | B76: =+$K$1 -> Véhicules neufs | C76: Programme neuf 2 | F76: {=+SUMPRODUCT(('Budget original'!$A$8:$A$501=$A76)*('Budget original'!$C$3:$AO$3=F$2),'Budget original'!$C$8:$AO$501)} -> 0 | L76: =-SUMIFS(BV_Data_An_Cour!$P:$P,BV_Data_An_Cour!$U:$U,$B76,BV_Data_An_Cour!$V:$V,$C76,BV_Data_An_Cour!$W:$W,L$2) -> 0 | N76: =L76-F76 -> 0 | Q76: {=+SUMPRODUCT(('Réel 2024'!$A$8:$A$501=$A76)*('Réel 2024'!$C$3:$AO$3=Q$2),'Réel 2024'!$C$8:$AO$501)} -> 0 | S76: =L76-Q76 -> 0
A77: =+B77&C77 -> Véhicules neufsProgramme neuf 3 | B77: =+$K$1 -> Véhicules neufs | C77: Programme neuf 3 | F77: {=+SUMPRODUCT(('Budget original'!$A$8:$A$501=$A77)*('Budget original'!$C$3:$AO$3=F$2),'Budget original'!$C$8:$AO$501)} -> 0 | L77: =-SUMIFS(BV_Data_An_Cour!$P:$P,BV_Data_An_Cour!$U:$U,$B77,BV_Data_An_Cour!$V:$V,$C77,BV_Data_An_Cour!$W:$W,L$2) -> 0 | N77: =L77-F77 -> 0 | Q77: {=+SUMPRODUCT(('Réel 2024'!$A$8:$A$501=$A77)*('Réel 2024'!$C$3:$AO$3=Q$2),'Réel 2024'!$C$8:$AO$501)} -> 0 | S77: =L77-Q77 -> 0
A78: =+B78&C78 -> Véhicules neufsHoldbacks | B78: =+$K$1 -> Véhicules neufs | C78: Holdbacks | F78: {=+SUMPRODUCT(('Budget original'!$A$8:$A$501=$A78)*('Budget original'!$C$3:$AO$3=F$2),'Budget original'!$C$8:$AO$501)} -> 148883.4 | L78: =-SUMIFS(BV_Data_An_Cour!$P:$P,BV_Data_An_Cour!$U:$U,$B78,BV_Data_An_Cour!$V:$V,$C78,BV_Data_An_Cour!$W:$W,L$2) -> 135836.4 | N78: =L78-F78 -> -13046.997 | Q78: {=+SUMPRODUCT(('Réel 2024'!$A$8:$A$501=$A78)*('Réel 2024'!$C$3:$AO$3=Q$2),'Réel 2024'!$C$8:$AO$501)} -> 121402.4 | S78: =L78-Q78 -> 14434
A79: =+B79&C79 -> Véhicules neufs[...] | B79: =+$K$1 -> Véhicules neufs | C79: [...] | F79: {=+SUMPRODUCT(('Budget original'!$A$8:$A$501=$A79)*('Budget original'!$C$3:$AO$3=F$2),'Budget original'!$C$8:$AO$501)} -> 0 | L79: =-SUMIFS(BV_Data_An_Cour!$P:$P,BV_Data_An_Cour!$U:$U,$B79,BV_Data_An_Cour!$V:$V,$C79,BV_Data_An_Cour!$W:$W,L$2) -> 0 | N79: =L79-F79 -> 0 | Q79: {=+SUMPRODUCT(('Réel 2024'!$A$8:$A$501=$A79)*('Réel 2024'!$C$3:$AO$3=Q$2),'Réel 2024'!$C$8:$AO$501)} -> 0 | S79: =L79-Q79 -> 0
A80: =+B80&C80 -> Véhicules neufs[...] | B80: =+$K$1 -> Véhicules neufs | C80: [...] | F80: {=+SUMPRODUCT(('Budget original'!$A$8:$A$501=$A80)*('Budget original'!$C$3:$AO$3=F$2),'Budget original'!$C$8:$AO$501)} -> 0 | L80: =-SUMIFS(BV_Data_An_Cour!$P:$P,BV_Data_An_Cour!$U:$U,$B80,BV_Data_An_Cour!$V:$V,$C80,BV_Data_An_Cour!$W:$W,L$2) -> 0 | N80: =L80-F80 -> 0 | Q80: {=+SUMPRODUCT(('Réel 2024'!$A$8:$A$501=$A80)*('Réel 2024'!$C$3:$AO$3=Q$2),'Réel 2024'!$C$8:$AO$501)} -> 0 | S80: =L80-Q80 -> 0
A81: =+B81&C81 -> Véhicules neufs[...] | B81: =+$K$1 -> Véhicules neufs | C81: [...] | F81: {=+SUMPRODUCT(('Budget original'!$A$8:$A$501=$A81)*('Budget original'!$C$3:$AO$3=F$2),'Budget original'!$C$8:$AO$501)} -> 0 | L81: =-SUMIFS(BV_Data_An_Cour!$P:$P,BV_Data_An_Cour!$U:$U,$B81,BV_Data_An_Cour!$V:$V,$C81,BV_Data_An_Cour!$W:$W,L$2) -> 0 | N81: =L81-F81 -> 0 | Q81: {=+SUMPRODUCT(('Réel 2024'!$A$8:$A$501=$A81)*('Réel 2024'!$C$3:$AO$3=Q$2),'Réel 2024'!$C$8:$AO$501)} -> 0 | S81: =L81-Q81 -> 0
A82: =+B82&C82 -> Véhicules neufsFrais administration | B82: =+$K$1 -> Véhicules neufs | C82: Frais administration | F82: {=+SUMPRODUCT(('Budget original'!$A$8:$A$501=$A82)*('Budget original'!$C$3:$AO$3=F$2),'Budget original'!$C$8:$AO$501)} -> 49816.375 | L82: =-SUMIFS(BV_Data_An_Cour!$P:$P,BV_Data_An_Cour!$U:$U,$B82,BV_Data_An_Cour!$V:$V,$C82,BV_Data_An_Cour!$W:$W,L$2) -> 47005 | N82: =L82-F82 -> -2811.375 | Q82: {=+SUMPRODUCT(('Réel 2024'!$A$8:$A$501=$A82)*('Réel 2024'!$C$3:$AO$3=Q$2),'Réel 2024'!$C$8:$AO$501)} -> 39270 | S82: =L82-Q82 -> 7735
A83: =+B83&C83 -> Véhicules neufsAUTRES REVENUS | B83: =+$K$1 -> Véhicules neufs | C83: AUTRES REVENUS | F83: =+SUM(F75:F82) -> 336416.91 | L83: =+SUM(L75:L82) -> 343305.04 | N83: =+SUM(N75:N82) -> 6888.125 | Q83: =+SUM(Q75:Q82) -> 271334.83 | S83: =+SUM(S75:S82) -> 71970.21
A84: =+B84&C84 -> Véhicules neufs | B84: =+$K$1 -> Véhicules neufs
A85: =+B85&C85 -> Véhicules neufsPROFIT DÉPARTEMENTAL | B85: =+$K$1 -> Véhicules neufs | C85: PROFIT DÉPARTEMENTAL | F85: =F27-F74+F83 -> 234431.47 | L85: =L27-L74+L83 -> 266268.02 | N85: =N27-N74+N83 -> 31836.545 | Q85: =Q27-Q74+Q83 -> 149072.24 | S85: =S27-S74+S83 -> 117195.78
C89: =C1 -> BMW Sherbrooke | K89: Véhicules usagés | S89: =$S$1 -> Réalisé, Avril 2025 AAD
D91: BUDGET ORIGINAL | J91: RÉALISATION | M91: ÉCART réel / Budget | O91: ANNÉE PRÉCÉDENTE | R91: ECART (réel/ Ann.Préc.)
D92: UNITE | E92: $P/UNITÉ | F92: $PROFITS | J92: UNITE | K92: $P/UNITE | L92: $PROFITS | M92: UNFTÉ | N92: $PROFFTS | O92: UNITE | P92: $P/UNITÉ | Q92: $PROFITS | R92: UNITE | S92: $PROFITS
A93: =+B93&C93 -> Véhicules usagésVentes nettes | B93: Véhicules usagés | C93: Ventes nettes | F93: {=+SUMPRODUCT(('Budget original'!$A$8:$A$501=$A93)*('Budget original'!$C$3:$AO$3=F$2),'Budget original'!$C$8:$AO$501)} -> 5412705.9 | L93: =-SUMIFS(BV_Data_An_Cour!$P:$P,BV_Data_An_Cour!$X:$X,"Oui",BV_Data_An_Cour!$U:$U,$B93) -> 4338017.9 | Q93: {=+SUMPRODUCT(('Réel 2024'!$A$8:$A$501=$A93)*('Réel 2024'!$C$3:$AO$3=Q$2),'Réel 2024'!$C$8:$AO$501)} -> 4874227.9
