Workbook
Name _Dates_Conc: #REF!
Name _Dates_Conc: #REF!
Name _scen: #REF!
Name _scen: #REF!
Name _scen1: #REF!
Name _scen1: #REF!
Name _scen2: #REF!
Name _scen2: #REF!
Name _SCenarios: #REF!
Name _SCenarios: #REF!
Name _Sens1: #REF!
Name _Sens1: #REF!
Name _Sens2: #REF!
Name _Sens2: #REF!
Name _sensRes1: #REF!
Name _sensRes1: #REF!
Name _sensRes2: #REF!
Name _sensRes2: #REF!
Name _sensRes3: #REF!
Name _sensRes3: #REF!
Name _sensRes4: #REF!
Name _sensRes4: #REF!
Name _sensRes5: #REF!
Name _sensRes5: #REF!
Name _sensRes6: #REF!
Name _sensRes6: #REF!
Name _sensRes7: #REF!
Name _sensRes7: #REF!
Name Compco1: {"Page1",#N/A,FALSE,"CompCo";"Page2",#N/A,FALSE,"CompCo"}
Name Compco2: {"Page1",#N/A,FALSE,"CompCo";"Page2",#N/A,FALSE,"CompCo"}
Name DateRange: #REF!
Name DateRange: #REF!
Name DateRangePr: OFFSET(#REF!,5,0,COUNTA(#REF!)-COUNTA(#REF!),1)
Name DateRangePrice: OFFSET(#REF!,5,0,COUNTA(#REF!)-COUNTA(#REF!),1)
Name DateRangePrice1: OFFSET(#REF!,5,0,COUNTA(#REF!)-COUNTA(#REF!),1)
Name DateRangePrice2: OFFSET(#REF!,5,0,COUNTA(#REF!)-COUNTA(#REF!),1)
Name ERT: {"execsum",#N/A,FALSE,"ExecSum";"finstatement",#N/A,FALSE,"Fin_St"}
Name hn.Delete015: #REF!,#REF!,#REF!,#REF!,#REF!
Name kjjkghkhj: {"finana",#N/A,FALSE,"Fin"}
Name lkhkhj: {"sub1",#N/A,FALSE,"Subs";"pac1",#N/A,FALSE,"Packages";"rev1",#N/A,FALSE,"2. Revenues"}
Name Monetary_Unit: #REF!
Name Monetary_Unit: #REF!
Name Months: #REF!
Name Months: #REF!
Name PriceRange: OFFSET(#REF!,5,0,COUNTA(#REF!)-COUNTA(#REF!),1)
Name PriceRange2: OFFSET(#REF!,5,0,COUNTA(#REF!)-COUNTA(#REF!),1)
Name Rng_Dealers_Names: #REF!
Name Rng_Dealers_Names: #REF!
Name Rng_Dlr_Dates: #REF!
Name Rng_Dlr_Dates: #REF!
Name test: {"execsum",#N/A,FALSE,"ExecSum";"finstatement",#N/A,FALSE,"Fin_St"}
Name test21: OFFSET(#REF!,5,0,COUNTA(#REF!)-COUNTA(#REF!),1)
Name Ticker: #REF!
Name Ticker: #REF!
Name Titre: #REF!
Name Titre: #REF!
Name value: OFFSET(#REF!,5,0,COUNTA(#REF!)-COUNTA(#REF!),1)
Name value2: OFFSET(#REF!,5,0,COUNTA(#REF!)-COUNTA(#REF!),1)
Name wrn.amendement.: {#N/A,#N/A,FALSE,"amendement"}
Name wrn.amendement..: {#N/A,#N/A,FALSE,"amendement"}

Sheet Parametres
A1: Compagnie | B1: BMW Sherbrooke
G2: 1-Mémo | M2: Mois | N2: YTD
A3: Mois Courant | B3: Décembre | C3: =+VLOOKUP(B3,$K$3:$L$14,2,0) -> 12 | G3: 10-Compte compteur | K3: Janvier | L3: 1 | M3: =+IF($K3=$B$3,"X","") | N3: =+IF(K3=B3,"X",IF(L3<=$C$3,"X","")) -> X
A4: Année | B4: 2025 | K4: Février | L4: 2 | M4: =+IF($K4=$B$3,"X","") | N4: =+IF(K4=B4,"X",IF(L4<=$C$3,"X","")) -> X
K5: Mars | L5: 3 | M5: =+IF($K5=$B$3,"X","") | N5: =+IF(K5=B5,"X",IF(L5<=$C$3,"X","")) -> X
K6: Avril | L6: 4 | M6: =+IF($K6=$B$3,"X","") | N6: =+IF(K6=B6,"X",IF(L6<=$C$3,"X","")) -> X
K7: Mai | L7: 5 | M7: =+IF($K7=$B$3,"X","") | N7: =+IF(K7=B7,"X",IF(L7<=$C$3,"X","")) -> X
K8: Juin | L8: 6 | M8: =+IF($K8=$B$3,"X","") | N8: =+IF(K8=B8,"X",IF(L8<=$C$3,"X","")) -> X
A9: Sélectionner le mois en B3 | K9: Juillet | L9: 7 | M9: =+IF($K9=$B$3,"X","") | N9: =+IF(K9=B9,"X",IF(L9<=$C$3,"X","")) -> X
A10: Coller les balances de vérification respectives en cellule A1 dans les onglets BV_Data_An_Cour et BV_Data_An_Prec | K10: Août | L10: 8 | M10: =+IF($K10=$B$3,"X","") | N10: =+IF(K10=B10,"X",IF(L10<=$C$3,"X","")) -> X
A11: Vérifier s'il y a des #N/A dans les colonnes T à X des onlgets de BV | K11: Septembre | L11: 9 | M11: =+IF($K11=$B$3,"X","") | N11: =+IF(K11=B11,"X",IF(L11<=$C$3,"X","")) -> X
A12: Vérifier les chiffres avec l'état financier et les réalisés an passé pour les résultat net mois et aad | K12: Octobre | L12: 10 | M12: =+IF($K12=$B$3,"X","") | N12: =+IF(K12=B12,"X",IF(L12<=$C$3,"X","")) -> X
K13: Novembre | L13: 11 | M13: =+IF($K13=$B$3,"X","") | N13: =+IF(K13=B13,"X",IF(L13<=$C$3,"X","")) -> X
K14: Décembre | L14: 12 | M14: =+IF($K14=$B$3,"X","") -> X | N14: =+IF(K14=B14,"X",IF(L14<=$C$3,"X","")) -> X

Sheet Bilan
A1: BILAN
A2: =+Parametres!B1 -> BMW Sherbrooke
A3: =CONCATENATE("",,Parametres!B3," ",Parametres!B4) -> Décembre 2025
A5: Encaisse | B5: =SUMIFS(BV_Data_An_Cour!$P:$P,BV_Data_An_Cour!$U:$U,$A$1,BV_Data_An_Cour!$V:$V,$A5) -> 1767433.1 | D5: Marge de crédit | E5: =-SUMIFS(BV_Data_An_Cour!$P:$P,BV_Data_An_Cour!$U:$U,$A$1,BV_Data_An_Cour!$V:$V,$D5) -> 0
A6: Total Trésorerie et équivalent de Trésorerie | B6: =SUM(B5) -> 1767433.1
D7: Portion Court Terme de la Dette Long Terme | E7: =-SUMIFS(BV_Data_An_Cour!$P:$P,BV_Data_An_Cour!$U:$U,$A$1,BV_Data_An_Cour!$V:$V,$D7) -> 0
A8: Recevables Contrats en Transit | B8: =SUMIFS(BV_Data_An_Cour!$P:$P,BV_Data_An_Cour!$U:$U,$A$1,BV_Data_An_Cour!$V:$V,$A8) -> 232113.53
A9: Recevables Véhicules | B9: =SUMIFS(BV_Data_An_Cour!$P:$P,BV_Data_An_Cour!$U:$U,$A$1,BV_Data_An_Cour!$V:$V,$A9) -> 306249.36 | D9: Avances à payer | E9: =-SUMIFS(BV_Data_An_Cour!$P:$P,BV_Data_An_Cour!$U:$U,$A$1,BV_Data_An_Cour!$V:$V,$D9) -> 0
A10: Recevables Manufacturier | B10: =SUMIFS(BV_Data_An_Cour!$P:$P,BV_Data_An_Cour!$U:$U,$A$1,BV_Data_An_Cour!$V:$V,$A10) -> 74541.55 | D10: Comptes à Payer Fournisseurs | E10: =-SUMIFS(BV_Data_An_Cour!$P:$P,BV_Data_An_Cour!$U:$U,$A$1,BV_Data_An_Cour!$V:$V,$D10) -> 242247.89
A11: Recevables Pièces et Service | B11: =SUMIFS(BV_Data_An_Cour!$P:$P,BV_Data_An_Cour!$U:$U,$A$1,BV_Data_An_Cour!$V:$V,$A11) -> 42239.3 | D11: Taxes de Vente à Payer | E11: =-SUMIFS(BV_Data_An_Cour!$P:$P,BV_Data_An_Cour!$U:$U,$A$1,BV_Data_An_Cour!$V:$V,$D11) -> 34034.82
A12: Recevables Garantie Manufacturier | B12: =SUMIFS(BV_Data_An_Cour!$P:$P,BV_Data_An_Cour!$U:$U,$A$1,BV_Data_An_Cour!$V:$V,$A12) -> 13736.45 | D12: Impôts à payer | E12: =-SUMIFS(BV_Data_An_Cour!$P:$P,BV_Data_An_Cour!$U:$U,$A$1,BV_Data_An_Cour!$V:$V,$D12) -> 0
A13: Recevables Carrosserie | B13: =SUMIFS(BV_Data_An_Cour!$P:$P,BV_Data_An_Cour!$U:$U,$A$1,BV_Data_An_Cour!$V:$V,$A13) -> 0 | D13: Dépôts de Client | E13: =-SUMIFS(BV_Data_An_Cour!$P:$P,BV_Data_An_Cour!$U:$U,$A$1,BV_Data_An_Cour!$V:$V,$D13) -> 153000
A14: Recevables Intercos | B14: =SUMIFS(BV_Data_An_Cour!$P:$P,BV_Data_An_Cour!$U:$U,$A$1,BV_Data_An_Cour!$V:$V,$A14) -> 0 | D14: Payables Intercos | E14: =-SUMIFS(BV_Data_An_Cour!$P:$P,BV_Data_An_Cour!$U:$U,$A$1,BV_Data_An_Cour!$V:$V,$D14) -> 0
A15: Recevables Autres | B15: =SUMIFS(BV_Data_An_Cour!$P:$P,BV_Data_An_Cour!$U:$U,$A$1,BV_Data_An_Cour!$V:$V,$A15) -> 16743 | D15: Autres Comptes à Payer | E15: =-SUMIFS(BV_Data_An_Cour!$P:$P,BV_Data_An_Cour!$U:$U,$A$1,BV_Data_An_Cour!$V:$V,$D15) -> 9572.83
A16: Total Comptes à Recevoir | B16: =+SUM(B8:B15) -> 685623.19 | D16: Total Comptes à Payer | E16: =+SUM(E10:E15) -> 438855.54
A18: Inventaire Véhicules Neufs | B18: =SUMIFS(BV_Data_An_Cour!$P:$P,BV_Data_An_Cour!$U:$U,$A$1,BV_Data_An_Cour!$V:$V,$A18) -> 6499673 | D18: Effet à Payer Véhicules Neufs | E18: =-SUMIFS(BV_Data_An_Cour!$P:$P,BV_Data_An_Cour!$U:$U,$A$1,BV_Data_An_Cour!$V:$V,$D18) -> 7321110
A19: Inventaire Véhicules Usagés | B19: =SUMIFS(BV_Data_An_Cour!$P:$P,BV_Data_An_Cour!$U:$U,$A$1,BV_Data_An_Cour!$V:$V,$A19) -> 1109201.6 | D19: Effet à Payer Véhicules Usagés | E19: =-SUMIFS(BV_Data_An_Cour!$P:$P,BV_Data_An_Cour!$U:$U,$A$1,BV_Data_An_Cour!$V:$V,$D19) -> 778872.67
A20: Inventaire Pièces, Pneus, Huile | B20: =SUMIFS(BV_Data_An_Cour!$P:$P,BV_Data_An_Cour!$U:$U,$A$1,BV_Data_An_Cour!$V:$V,$A20) -> 461686.26 | D20: Total Effets à Payer | E20: =+SUM(E18:E19) -> 8099982.7
A21: Total Inventaires | B21: =SUM(B18:B20) -> 8070560.9
D22: Salaires à Payer | E22: =-SUMIFS(BV_Data_An_Cour!$P:$P,BV_Data_An_Cour!$U:$U,$A$1,BV_Data_An_Cour!$V:$V,$D22) -> 232320.02
A23: Avances à recevoir | B23: =SUMIFS(BV_Data_An_Cour!$P:$P,BV_Data_An_Cour!$U:$U,$A$1,BV_Data_An_Cour!$V:$V,$A23) -> 0 | D23: DAS à Payer | E23: =-SUMIFS(BV_Data_An_Cour!$P:$P,BV_Data_An_Cour!$U:$U,$A$1,BV_Data_An_Cour!$V:$V,$D23) -> 28281.04
A24: Travaux en Cours | B24: =SUMIFS(BV_Data_An_Cour!$P:$P,BV_Data_An_Cour!$U:$U,$A$1,BV_Data_An_Cour!$V:$V,$A24) -> 2944.14 | D24: Autres Courus | E24: =-SUMIFS(BV_Data_An_Cour!$P:$P,BV_Data_An_Cour!$U:$U,$A$1,BV_Data_An_Cour!$V:$V,$D24) -> 148847
A25: Sous-Traitance | B25: =SUMIFS(BV_Data_An_Cour!$P:$P,BV_Data_An_Cour!$U:$U,$A$1,BV_Data_An_Cour!$V:$V,$A25) -> 140 | D25: [...] | E25: =-SUMIFS(BV_Data_An_Cour!$P:$P,BV_Data_An_Cour!$U:$U,$A$1,BV_Data_An_Cour!$V:$V,$D25) -> 0
A26: Frais Payés d'Avance | B26: =SUMIFS(BV_Data_An_Cour!$P:$P,BV_Data_An_Cour!$U:$U,$A$1,BV_Data_An_Cour!$V:$V,$A26) -> 53277.39 | D26: [...] | E26: =-SUMIFS(BV_Data_An_Cour!$P:$P,BV_Data_An_Cour!$U:$U,$A$1,BV_Data_An_Cour!$V:$V,$D26) -> 0
A27: [...] | B27: =SUMIFS(BV_Data_An_Cour!$P:$P,BV_Data_An_Cour!$U:$U,$A$1,BV_Data_An_Cour!$V:$V,$A27) -> 0 | D27: [...] | E27: =-SUMIFS(BV_Data_An_Cour!$P:$P,BV_Data_An_Cour!$U:$U,$A$1,BV_Data_An_Cour!$V:$V,$D27) -> 0
A28: [...] | B28: =SUMIFS(BV_Data_An_Cour!$P:$P,BV_Data_An_Cour!$U:$U,$A$1,BV_Data_An_Cour!$V:$V,$A28) -> 0 | D28: Total Frais Courus | E28: =SUM(E22:E24) -> 409448.06
A29: [...] | B29: =SUMIFS(BV_Data_An_Cour!$P:$P,BV_Data_An_Cour!$U:$U,$A$1,BV_Data_An_Cour!$V:$V,$A29) -> 0
A30: Total Autres | B30: =SUM(B23:B29) -> 56361.53 | D30: Total Passif Court Terme | E30: =+E5+E7+E16+E20+E28 -> 8948286.3
A32: Total Actif Court Terme | B32: =+B6+B16+B21+B30 -> 10579979
D33: Impôts Futurs à payer | E33: =-SUMIFS(BV_Data_An_Cour!$P:$P,BV_Data_An_Cour!$U:$U,$A$1,BV_Data_An_Cour!$V:$V,$D33) -> 0
A35: Terrain | B35: =SUMIFS(BV_Data_An_Cour!$P:$P,BV_Data_An_Cour!$U:$U,$A$1,BV_Data_An_Cour!$V:$V,$A35) -> 0 | D35: Avances Long Terme à Payer | E35: =-SUMIFS(BV_Data_An_Cour!$P:$P,BV_Data_An_Cour!$U:$U,$A$1,BV_Data_An_Cour!$V:$V,$D35) -> 5807487.8
A36: Bâtisse | B36: =SUMIFS(BV_Data_An_Cour!$P:$P,BV_Data_An_Cour!$U:$U,$A$1,BV_Data_An_Cour!$V:$V,$A36) -> 0 | D36: Hypothèque à Payer | E36: =-SUMIFS(BV_Data_An_Cour!$P:$P,BV_Data_An_Cour!$U:$U,$A$1,BV_Data_An_Cour!$V:$V,$D36) -> 0
A37: Améliorations Locatives | B37: =SUMIFS(BV_Data_An_Cour!$P:$P,BV_Data_An_Cour!$U:$U,$A$1,BV_Data_An_Cour!$V:$V,$A37) -> 0 | D37: Dette à Long Terme | E37: =-SUMIFS(BV_Data_An_Cour!$P:$P,BV_Data_An_Cour!$U:$U,$A$1,BV_Data_An_Cour!$V:$V,$D37) -> 5700000
A38: Améliorations Locatives Permanentes | B38: =SUMIFS(BV_Data_An_Cour!$P:$P,BV_Data_An_Cour!$U:$U,$A$1,BV_Data_An_Cour!$V:$V,$A38) -> 0 | D38: Autres Dettes à Long Terme | E38: =-SUMIFS(BV_Data_An_Cour!$P:$P,BV_Data_An_Cour!$U:$U,$A$1,BV_Data_An_Cour!$V:$V,$D38) -> 0
A39: Équipements Service | B39: =SUMIFS(BV_Data_An_Cour!$P:$P,BV_Data_An_Cour!$U:$U,$A$1,BV_Data_An_Cour!$V:$V,$A39) -> 195494.45 | D39: [...] | E39: =-SUMIFS(BV_Data_An_Cour!$P:$P,BV_Data_An_Cour!$U:$U,$A$1,BV_Data_An_Cour!$V:$V,$D39) -> 0
A40: Mobilier | B40: =SUMIFS(BV_Data_An_Cour!$P:$P,BV_Data_An_Cour!$U:$U,$A$1,BV_Data_An_Cour!$V:$V,$A40) -> 194969.73 | D40: [...] | E40: =-SUMIFS(BV_Data_An_Cour!$P:$P,BV_Data_An_Cour!$U:$U,$A$1,BV_Data_An_Cour!$V:$V,$D40) -> 0
A41: Équipements Informatique | B41: =SUMIFS(BV_Data_An_Cour!$P:$P,BV_Data_An_Cour!$U:$U,$A$1,BV_Data_An_Cour!$V:$V,$A41) -> 22861.12 | D41: [...] | E41: =-SUMIFS(BV_Data_An_Cour!$P:$P,BV_Data_An_Cour!$U:$U,$A$1,BV_Data_An_Cour!$V:$V,$D41) -> 0
A42: Équipements Téléphonique | B42: =SUMIFS(BV_Data_An_Cour!$P:$P,BV_Data_An_Cour!$U:$U,$A$1,BV_Data_An_Cour!$V:$V,$A42) -> 0 | D42: Total Passif long terme | E42: =+SUM(E33:E38) -> 11507488
A43: Enseigne | B43: =SUMIFS(BV_Data_An_Cour!$P:$P,BV_Data_An_Cour!$U:$U,$A$1,BV_Data_An_Cour!$V:$V,$A43) -> 9825.02
A44: Total Immobilisations Nettes | B44: =SUM(B35:B43) -> 423150.32
D45: Total Passifs | E45: =+E42+E30 -> 20455774
A46: Avances à Recevoir Long Terme | B46: =SUMIFS(BV_Data_An_Cour!$P:$P,BV_Data_An_Cour!$U:$U,$A$1,BV_Data_An_Cour!$V:$V,$A46) -> -90000
A48: Achalandage | B48: =SUMIFS(BV_Data_An_Cour!$P:$P,BV_Data_An_Cour!$U:$U,$A$1,BV_Data_An_Cour!$V:$V,$A48) -> 9500000 | D48: Capital Actions | E48: =-SUMIFS(BV_Data_An_Cour!$P:$P,BV_Data_An_Cour!$U:$U,$A$1,BV_Data_An_Cour!$V:$V,$D48) -> 0
D49: Apport | E49: =-SUMIFS(BV_Data_An_Cour!$P:$P,BV_Data_An_Cour!$U:$U,$A$1,BV_Data_An_Cour!$V:$V,$D49) -> 0
A50: [...] | B50: =SUMIFS(BV_Data_An_Cour!$P:$P,BV_Data_An_Cour!$U:$U,$A$1,BV_Data_An_Cour!$V:$V,$A50) -> 0 | D50: Bénéfices non répartis | E50: =-SUMIFS(BV_Data_An_Cour!$P:$P,BV_Data_An_Cour!$U:$U,$A$1,BV_Data_An_Cour!$V:$V,$D50)+Print_AAD!AF502 -> -42645.1
A51: [...] | B51: =SUMIFS(BV_Data_An_Cour!$P:$P,BV_Data_An_Cour!$U:$U,$A$1,BV_Data_An_Cour!$V:$V,$A51) -> 0 | D51: Dividendes | E51: =-SUMIFS(BV_Data_An_Cour!$P:$P,BV_Data_An_Cour!$U:$U,$A$1,BV_Data_An_Cour!$V:$V,$D51) -> 0
A52: [...] | B52: =SUMIFS(BV_Data_An_Cour!$P:$P,BV_Data_An_Cour!$U:$U,$A$1,BV_Data_An_Cour!$V:$V,$A52) -> 0
A53: Total Actif Long Terme | B53: =+B44+B48+B46 -> 9833150.3 | D53: Total Capitaux Propres / Avoir | E53: =SUM(E48:E51) -> -42645.1
A56: Total Actif | B56: =+B32+B53 -> 20413129 | D56: Total Passif et Capitaux Propres / Avoir | E56: =+E53+E45 -> 20413129
E65: =+B56-E56 -> 0

Sheet Inventaire_Neuf
A1: #Contrôle | B1: Année | C1: Marque | D1: Modèle | E1: $ Inventaire | F1: $ Financé | G1: NIV | H1: Jours en stock | L1: $ Inventaire | M1: $ Financé
A2: 23019 | B2: 2023 | C2: BMW | D2: 430 | E2: 65121.87 | F2: -60905.25 | G2: WBA73AP05PCL27730 | H2: 478 | K2: CTRL | L2: =+SUM(E2:E10000) -> 3938633.3 | M2: =+SUM(F2:F10000) -> -3910068
A3: 23020 | B3: 2023 | C3: BMW | D3: 430 | E3: 63963.67 | G3: WBA73AP06PCL26036 | H3: 465 | L3: =+COUNT(E2:E10000) -> 45
A4: 23084 | B4: 2023 | C4: BMW | D4: 530xe | E4: 75509.5 | G4: WBA33AG06PCL42221 | H4: 411
A5: 23218 | B5: 2023 | C5: BMW SAV | D5: X3 | E5: 84833.61 | F5: -88452 | G5: 5UX83DP04P9T17873 | H5: 146
A6: 23221 | B6: 2023 | C6: BMW | D6: SERIE 2 | E6: 66617.36 | F6: -69326.25 | G6: 3MW53CM06P8D70441 | H6: 151
A7: 23228 | B7: 2023 | C7: BMW SAV | D7: X3 | E7: 73335.37 | F7: -69809.25 | G7: 5UX53DP06P9T28635 | H7: 143
A8: 23240 | B8: 2023 | C8: BMW SAV | D8: X1 | E8: 50471.49 | F8: -50473.5 | G8: WBX73EF02P5X85602 | H8: 67
A9: 23241 | B9: 2023 | C9: BMW SAV | D9: X1 | E9: 50262.11 | F9: -52143 | G9: WBX73EF00P5X86053 | H9: 58
A10: 24019 | B10: 2024 | C10: BMW SAV | D10: X5 | E10: 95266.49 | F10: -95303.25 | G10: 5UX23EU05R9T15522 | H10: 158
A11: 24023 | B11: 2024 | C11: BMW SAV | D11: X7 | E11: 126612.36 | F11: -131675.25 | G11: 5UX23EM04R9T23238 | H11: 149
A12: 24024 | B12: 2024 | C12: BMWI | D12: IX40 | E12: 97633.14 | F12: -97203.75 | G12: WB513CF03RCN76497 | H12: 152
A13: 24032 | B13: 2024 | C13: BMW SAV | D13: X6 | E13: 103328.55 | F13: -107651.25 | G13: 5UX33EX02R9T31595 | H13: 144
A14: 24034 | B14: 2024 | C14: BMW | D14: SERIE 4 | E14: 66533.61 | F14: -69237 | G14: WBA73AP07RCN92250 | H14: 144
A15: 24038 | B15: 2024 | C15: BMWI | D15: I7 | E15: 159476.47 | F15: -173664.75 | G15: WBY53EJ01RCN94634 | H15: 142
A16: 24051 | B16: 2024 | C16: BMW | D16: SERIE 3 | E16: 62907.21 | F16: -60149.52 | G16: 3MW89FF00R8D80878 | H16: 117
... A46: 24130 | B46: 2024 | C46: BMW SAV | D46: X3 | E46: 65370 | F46: -68638.5 | G46: 5UX53DP06R9U99484 | H46: 9

Sheet Inventaire_Used
A1: #Contrôle | B1: Année | C1: Marque | D1: Description | E1: Amount | F1: Financé | G1: NIV | H1: Jours en stock | L1: $ Inventaire | M1: $ Financé
A2: P0512 | B2: 2004 | C2: CHEVROLET TRUCK | D2: SILVERADO 2500 | E2: 3856.45 | G2: 1GCGK23U14F218132 | H2: 1482 | K2: CTRL | L2: =+SUM(E2:E9999) -> 1972155.4 | M2: =+SUM(F2:F9999) -> -1357394.6
A3: P2173 | B3: 2022 | C3: BMW | D3: 540i | E3: 75917.21 | F3: -50220 | G3: WBA73BJ07NWX54871 | H3: 490 | L3: =+COUNT(E2:E10000) -> 50
A4: P2259 | B4: 2021 | C4: BMW SAV | D4: X5 | E4: 75668.81 | F4: -55025 | G4: 5UXTA6C07M9G89398 | H4: 306
A5: P2282 | B5: 2019 | C5: BMW | D5: Z4 | E5: 61477.55 | F5: -55037.5 | G5: WBAHF3C57KWW21386 | H5: 235
A6: P2321 | B6: 2021 | C6: JEEP | D6: GLADIATOR 4X4 | E6: 57247.58 | F6: -48210.15 | G6: 1C6HJTAG8ML543623 | H6: 144
A7: P2327 | B7: 2023 | C7: BMW SAV | D7: X1 | E7: 51697.81 | F7: -49599.39 | G7: WBX73EF03P5W40276 | H7: 137
A8: 23231A | B8: 2020 | C8: MINI | D8: COUNTRYMAN | E8: 35295.85 | F8: -20589.76 | G8: WMZYZ9C04L3L18702 | H8: 125
A9: P2334 | B9: 2019 | C9: BMW | D9: 330i | E9: 31287.41 | F9: -23537.41 | G9: WBA5R7C54KFH22955 | H9: 111
A10: 23193A | B10: 2022 | C10: VOLVO | D10: XC60 | E10: 58424.95 | F10: -80500 | G10: LYV062RL8NB979235 | H10: 108
A11: P2335 | B11: 2020 | C11: BMW SAV | D11: X3 | E11: 30904.85 | F11: -21000 | G11: 5UXTY5C03L9D44647 | H11: 103
A12: 24082A | B12: 2023 | C12: MAZDA | D12: MX-5 | E12: 34707.45 | F12: -32060.23 | G12: JM1NDAD7XP0552574 | H12: 73
A13: 23225A | B13: 2023 | C13: BMW | D13: 330i | E13: 54482.17 | F13: -37837.25 | G13: WBA83FF0XPFN75280 | H13: 72
A14: P2342A | B14: 2023 | C14: BMW | D14: 530e | E14: 65103.95 | F14: -45150 | G14: WBA33AG00PCL72878 | H14: 72
A15: P2343 | B15: 2023 | C15: ACURA | D15: Integra | E15: 39059.95 | F15: -35100 | G15: 19UDE4G72PA800656 | H15: 67
... A28: P2356 | B28: 2021 | C28: ACURA | D28: TLX | E28: 39793.95 | F28: -35550 | G28: 19UUB6F51MA801958 | H28: 38
A29: 24098A | B29: 2015 | C29: MINI | D29: 5 DOOR | E29: 8000 | G29: WMWXS5C59FT837198 | H29: 38
A30: 23116B | B30: 2021 | C30: JEEP | D30: Wrangler Unlim | E30: 43899.95 | F30: -30450 | G30: 1C4HJXEN3MW680010 | H30: 37
A31: 24078A | B31: 2023 | C31: VOLKSWAGEN | D31: ID.4 | E31: 47899.95 | F31: -34300 | G31: 1V2JNPE8XPC021183 | H31: 31
A32: 23243A | B32: 2020 | C32: BMW | D32: 2 SERIES | E32: 29024.85 | F32: -19599.51 | G32: WBA73AK0XL7G01503 | H32: 26
A33: P2361 | B33: 2014 | C33: BMW | D33: 320i | E33: 11164.86 | G33: WBA3C3C57EK200069 | H33: 22
A34: P2362 | B34: 2023 | C34: BMW | D34: M240i xDrive | E34: 53250.2 | F34: -52796.25 | G34: 3MW53CM03P8C99750 | H34: 20
A35: P2363 | B35: 2023 | C35: BMW | D35: 230i | E35: 42103.5 | F35: -41658.65 | G35: 3MW33CM08P8C93109 | H35: 18
A36: P2364 | B36: 2017 | C36: BMW SAV | D36: X4 | E36: 27407.01 | F36: -24300 | G36: 5UXXW3C37H0T79741 | H36: 17
A37: 24040A | B37: 2023 | C37: BMW SAV | D37: X4 | E37: 58745 | F37: -45726.94 | G37: 5UX33DT01P9N56202 | H37: 13
A38: P2367 | B38: 2019 | C38: NISSAN | D38: Micra | E38: 11000 | F38: -9900 | G38: 3N1CK3CP5KL236170 | H38: 10
A39: 23244A | B39: 2019 | C39: BMW SAV | D39: X2 | E39: 26995 | F39: -16020.18 | G39: WBXYJ5C54K5N01549 | H39: 10
A40: 24103A | B40: 2021 | C40: BMW SAV | D40: X3 | E40: 42500 | F40: -30072.18 | G40: 5UXTS1C06M9H64396 | H40: 10
A41: P2223A | B41: 2023 | C41: BMW | D41: I4 | E41: 51776.06 | F41: -29211.39 | G41: WBY43AW09PFP45888 | H41: 10
A42: P2366 | B42: 2012 | C42: BMW | D42: M3 | E42: 37500 | G42: WBSKG9C53CE798848 | H42: 10
A43: P2365 | B43: 2021 | C43: DODGE TRUCK | D43: RAM 1500 Class | E43: 32547.15 | F43: -32547.15 | G43: 3C6RR7KG7MG709002 | H43: 9
A44: 23227A | B44: 2017 | C44: HONDA | D44: CIVIC HATCHBAC | E44: 14000 | G44: SHHFK7H26HU304092 | H44: 9
A45: 24097A | B45: 2018 | C45: AUDI | D45: A5 Sportback | E45: 18500 | G45: WAUANCF51JA004190 | H45: 3
A46: 24126A | B46: 2017 | C46: BMW | D46: 2 SERIES | E46: 28000 | G46: WBA2L3C32HV667851 | H46: 3
A47: 24091B | B47: 2013 | C47: VOLKSWAGEN | D47: JETTA | E47: 1500 | G47: 3VW1K7AJ9DM416983 | H47: 2
A48: 24125B | B48: 2017 | C48: BMW | D48: 650i | E48: 37000 | G48: WBA6F7C50HD930698 | H48: 2
A49: 23122A | B49: 2022 | C49: BMW | D49: 2 SERIES | E49: 37500 | G49: WBA13AL03N7K75967 | H49: 2
A50: 24125A | B50: 2021 | C50: BMW SAV | D50: X5 | E50: 60000 | G50: 5UXJU4C08M9E22693 | H50: 2
A51: 24104B | B51: 2019 | C51: BMW SAV | D51: X2 | E51: 31000 | G51: WBXYN1C56K5N23209 | H51: 0

Sheet Print_Mois
C1: =Parametres!B1 -> BMW Sherbrooke | K1: Véhicules neufs | S1: =CONCATENATE("Réalisé,"," ",Parametres!B3," ",Parametres!B4) -> Réalisé, Décembre 2025
D2: X | E2: O | F2: U | J2: NB | L2: $ | O2: X | P2: O | Q2: U
D3: BUDGET ORIGINAL | J3: RÉALISATION | M3: ÉCART réel / Budget | O3: ANNÉE PRÉCÉDENTE | R3: ECART (réel/ Ann.Préc.)
D4: UNITE | E4: $P/UNITÉ | F4: $PROFITS | J4: UNITE | K4: $P/UNITE | L4: $PROFITS | M4: UNFTÉ | N4: $PROFITS | O4: UNITE | P4: $P/UNITÉ | Q4: $PROFITS | R4: UNITE | S4: $PROFITS
A5: =+B5&C5 -> Véhicules neufsVentes nettes | B5: =+$K$1 -> Véhicules neufs | C5: Ventes nettes | F5: =+INDEX('Budget original'!$A$2:$AO$501,MATCH($A5,'Budget original'!$A$2:$A$501,0),MATCH(F$2,'Budget original'!$A$2:$AO$2,0)) -> 1660512.8 | L5: =-SUMIFS(BV_Data_An_Cour!$O:$O,BV_Data_An_Cour!$X:$X,"Oui",BV_Data_An_Cour!$U:$U,$B5) -> 1337137.4 | Q5: {=+INDEX('Réel 2024'!$A$2:$AO$501,MATCH($A5,'Réel 2024'!$A$2:$A$501,0),MATCH(Q$2,'Réel 2024'!$A$2:$AO$2,0))} -> 2488233.6
A6: =+B6&C6 -> Véhicules neufsAutos détail | B6: =+$K$1 -> Véhicules neufs | C6: Autos détail | D6: =+INDEX('Budget original'!$A$2:$AO$501,MATCH($A6,'Budget original'!$A$2:$A$501,0),MATCH(D$2,'Budget original'!$A$2:$AO$2,0)) -> 6 | E6: =IF(D6=0,0,F6/D6) -> 4306.3953 | F6: =+INDEX('Budget original'!$A$2:$AO$501,MATCH($A6,'Budget original'!$A$2:$A$501,0),MATCH(F$2,'Budget original'!$A$2:$AO$2,0)) -> 25838.372 | J6: =-SUMIFS(BV_Data_An_Cour!$O:$O,BV_Data_An_Cour!$U:$U,$B6,BV_Data_An_Cour!$V:$V,$C6,BV_Data_An_Cour!$W:$W,J$2) -> 2 | K6: =IF(J6=0,0,L6/J6) -> 4989.53 | L6: =-SUMIFS(BV_Data_An_Cour!$O:$O,BV_Data_An_Cour!$U:$U,$B6,BV_Data_An_Cour!$V:$V,$C6,BV_Data_An_Cour!$W:$W,L$2) -> 9979.06 | M6: =J6-D6 -> -4 | N6: =L6-F6 -> -15859.312 | O6: =+INDEX('Réel 2024'!$A$2:$AO$501,MATCH($A6,'Réel 2024'!$A$2:$A$501,0),MATCH(O$2,'Réel 2024'!$A$2:$AO$2,0)) -> 12 | P6: =IF(O6=0,0,Q6/O6) -> 6636.9442 | Q6: {=+INDEX('Réel 2024'!$A$2:$AO$501,MATCH($A6,'Réel 2024'!$A$2:$A$501,0),MATCH(Q$2,'Réel 2024'!$A$2:$AO$2,0))} -> 79643.33 | R6: =J6-O6 -> -10 | S6: =L6-Q6 -> -69664.27
A7: =+B7&C7 -> Véhicules neufsCamions détail | B7: =+$K$1 -> Véhicules neufs | C7: Camions détail | D7: =+INDEX('Budget original'!$A$2:$AO$501,MATCH($A7,'Budget original'!$A$2:$A$501,0),MATCH(D$2,'Budget original'!$A$2:$AO$2,0)) -> 10 | E7: =IF(D7=0,0,F7/D7) -> 4000.3311 | F7: =+INDEX('Budget original'!$A$2:$AO$501,MATCH($A7,'Budget original'!$A$2:$A$501,0),MATCH(F$2,'Budget original'!$A$2:$AO$2,0)) -> 40003.311 | J7: =-SUMIFS(BV_Data_An_Cour!$O:$O,BV_Data_An_Cour!$U:$U,$B7,BV_Data_An_Cour!$V:$V,$C7,BV_Data_An_Cour!$W:$W,J$2) -> 6 | K7: =IF(J7=0,0,L7/J7) -> 3057.8933 | L7: =-SUMIFS(BV_Data_An_Cour!$O:$O,BV_Data_An_Cour!$U:$U,$B7,BV_Data_An_Cour!$V:$V,$C7,BV_Data_An_Cour!$W:$W,L$2) -> 18347.36 | M7: =J7-D7 -> -4 | N7: =L7-F7 -> -21655.951 | O7: {=+INDEX('Réel 2024'!$A$2:$AO$501,MATCH($A7,'Réel 2024'!$A$2:$A$501,0),MATCH(O$2,'Réel 2024'!$A$2:$AO$2,0))} -> 11 | P7: =IF(O7=0,0,Q7/O7) -> 5085.2609 | Q7: {=+INDEX('Réel 2024'!$A$2:$AO$501,MATCH($A7,'Réel 2024'!$A$2:$A$501,0),MATCH(Q$2,'Réel 2024'!$A$2:$AO$2,0))} -> 55937.87 | R7: =J7-O7 -> -5 | S7: =L7-Q7 -> -37590.51
A8: =+B8&C8 -> Véhicules neufsSprinter | B8: =+$K$1 -> Véhicules neufs | C8: Sprinter | D8: =+INDEX('Budget original'!$A$2:$AO$501,MATCH($A8,'Budget original'!$A$2:$A$501,0),MATCH(D$2,'Budget original'!$A$2:$AO$2,0)) -> 0 | E8: =IF(D8=0,0,F8/D8) -> 0 | F8: =+INDEX('Budget original'!$A$2:$AO$501,MATCH($A8,'Budget original'!$A$2:$A$501,0),MATCH(F$2,'Budget original'!$A$2:$AO$2,0)) -> 0 | J8: =-SUMIFS(BV_Data_An_Cour!$O:$O,BV_Data_An_Cour!$U:$U,$B8,BV_Data_An_Cour!$V:$V,$C8,BV_Data_An_Cour!$W:$W,J$2) -> 0 | K8: =IF(J8=0,0,L8/J8) -> 0 | L8: =-SUMIFS(BV_Data_An_Cour!$O:$O,BV_Data_An_Cour!$U:$U,$B8,BV_Data_An_Cour!$V:$V,$C8,BV_Data_An_Cour!$W:$W,L$2) -> 0 | M8: =J8-D8 -> 0 | N8: =L8-F8 -> 0 | O8: {=+INDEX('Réel 2024'!$A$2:$AO$501,MATCH($A8,'Réel 2024'!$A$2:$A$501,0),MATCH(O$2,'Réel 2024'!$A$2:$AO$2,0))} -> 0 | P8: =IF(O8=0,0,Q8/O8) -> 0 | Q8: {=+INDEX('Réel 2024'!$A$2:$AO$501,MATCH($A8,'Réel 2024'!$A$2:$A$501,0),MATCH(Q$2,'Réel 2024'!$A$2:$AO$2,0))} -> 0 | R8: =J8-O8 -> 0 | S8: =L8-Q8 -> 0
A9: =+B9&C9 -> Véhicules neufsMoto détail | B9: =+$K$1 -> Véhicules neufs | C9: Moto détail | D9: =+INDEX('Budget original'!$A$2:$AO$501,MATCH($A9,'Budget original'!$A$2:$A$501,0),MATCH(D$2,'Budget original'!$A$2:$AO$2,0)) -> 0 | E9: =IF(D9=0,0,F9/D9) -> 0 | F9: =+INDEX('Budget original'!$A$2:$AO$501,MATCH($A9,'Budget original'!$A$2:$A$501,0),MATCH(F$2,'Budget original'!$A$2:$AO$2,0)) -> 0 | J9: =-SUMIFS(BV_Data_An_Cour!$O:$O,BV_Data_An_Cour!$U:$U,$B9,BV_Data_An_Cour!$V:$V,$C9,BV_Data_An_Cour!$W:$W,J$2) -> 0 | K9: =IF(J9=0,0,L9/J9) -> 0 | L9: =-SUMIFS(BV_Data_An_Cour!$O:$O,BV_Data_An_Cour!$U:$U,$B9,BV_Data_An_Cour!$V:$V,$C9,BV_Data_An_Cour!$W:$W,L$2) -> 0 | M9: =J9-D9 -> 0 | N9: =L9-F9 -> 0 | O9: {=+INDEX('Réel 2024'!$A$2:$AO$501,MATCH($A9,'Réel 2024'!$A$2:$A$501,0),MATCH(O$2,'Réel 2024'!$A$2:$AO$2,0))} -> 0 | P9: =IF(O9=0,0,Q9/O9) -> 0 | Q9: {=+INDEX('Réel 2024'!$A$2:$AO$501,MATCH($A9,'Réel 2024'!$A$2:$A$501,0),MATCH(Q$2,'Réel 2024'!$A$2:$AO$2,0))} -> 0 | R9: =J9-O9 -> 0 | S9: =L9-Q9 -> 0
A10: =+B10&C10 -> Véhicules neufs[...] | B10: =+$K$1 -> Véhicules neufs | C10: [...] | D10: =+INDEX('Budget original'!$A$2:$AO$501,MATCH($A10,'Budget original'!$A$2:$A$501,0),MATCH(D$2,'Budget original'!$A$2:$AO$2,0)) -> 0 | E10: =IF(D10=0,0,F10/D10) -> 0 | F10: =+INDEX('Budget original'!$A$2:$AO$501,MATCH($A10,'Budget original'!$A$2:$A$501,0),MATCH(F$2,'Budget original'!$A$2:$AO$2,0)) -> 0 | J10: =-SUMIFS(BV_Data_An_Cour!$O:$O,BV_Data_An_Cour!$U:$U,$B10,BV_Data_An_Cour!$V:$V,$C10,BV_Data_An_Cour!$W:$W,J$2) -> 0 | K10: =IF(J10=0,0,L10/J10) -> 0 | L10: =-SUMIFS(BV_Data_An_Cour!$O:$O,BV_Data_An_Cour!$U:$U,$B10,BV_Data_An_Cour!$V:$V,$C10,BV_Data_An_Cour!$W:$W,L$2) -> 0 | M10: =J10-D10 -> 0 | N10: =L10-F10 -> 0 | O10: {=+INDEX('Réel 2024'!$A$2:$AO$501,MATCH($A10,'Réel 2024'!$A$2:$A$501,0),MATCH(O$2,'Réel 2024'!$A$2:$AO$2,0))} -> 0 | P10: =IF(O10=0,0,Q10/O10) -> 0 | Q10: {=+INDEX('Réel 2024'!$A$2:$AO$501,MATCH($A10,'Réel 2024'!$A$2:$A$501,0),MATCH(Q$2,'Réel 2024'!$A$2:$AO$2,0))} -> 0 | R10: =J10-O10 -> 0 | S10: =L10-Q10 -> 0
A11: =+B11&C11 -> Véhicules neufs[...] | B11: =+$K$1 -> Véhicules neufs | C11: [...] | D11: =+INDEX('Budget original'!$A$2:$AO$501,MATCH($A11,'Budget original'!$A$2:$A$501,0),MATCH(D$2,'Budget original'!$A$2:$AO$2,0)) -> 0 | E11: =IF(D11=0,0,F11/D11) -> 0 | F11: =+INDEX('Budget original'!$A$2:$AO$501,MATCH($A11,'Budget original'!$A$2:$A$501,0),MATCH(F$2,'Budget original'!$A$2:$AO$2,0)) -> 0 | J11: =-SUMIFS(BV_Data_An_Cour!$O:$O,BV_Data_An_Cour!$U:$U,$B11,BV_Data_An_Cour!$V:$V,$C11,BV_Data_An_Cour!$W:$W,J$2) -> 0 | K11: =IF(J11=0,0,L11/J11) -> 0 | L11: =-SUMIFS(BV_Data_An_Cour!$O:$O,BV_Data_An_Cour!$U:$U,$B11,BV_Data_An_Cour!$V:$V,$C11,BV_Data_An_Cour!$W:$W,L$2) -> 0 | M11: =J11-D11 -> 0 | N11: =L11-F11 -> 0 | O11: {=+INDEX('Réel 2024'!$A$2:$AO$501,MATCH($A11,'Réel 2024'!$A$2:$A$501,0),MATCH(O$2,'Réel 2024'!$A$2:$AO$2,0))} -> 0 | P11: =IF(O11=0,0,Q11/O11) -> 0 | Q11: {=+INDEX('Réel 2024'!$A$2:$AO$501,MATCH($A11,'Réel 2024'!$A$2:$A$501,0),MATCH(Q$2,'Réel 2024'!$A$2:$AO$2,0))} -> 0 | R11: =J11-O11 -> 0 | S11: =L11-Q11 -> 0
A12: =+B12&C12 -> Véhicules neufs[...] | B12: =+$K$1 -> Véhicules neufs | C12: [...] | D12: =+INDEX('Budget original'!$A$2:$AO$501,MATCH($A12,'Budget original'!$A$2:$A$501,0),MATCH(D$2,'Budget original'!$A$2:$AO$2,0)) -> 0 | E12: =IF(D12=0,0,F12/D12) -> 0 | F12: =+INDEX('Budget original'!$A$2:$AO$501,MATCH($A12,'Budget original'!$A$2:$A$501,0),MATCH(F$2,'Budget original'!$A$2:$AO$2,0)) -> 0 | J12: =-SUMIFS(BV_Data_An_Cour!$O:$O,BV_Data_An_Cour!$U:$U,$B12,BV_Data_An_Cour!$V:$V,$C12,BV_Data_An_Cour!$W:$W,J$2) -> 0 | K12: =IF(J12=0,0,L12/J12) -> 0 | L12: =-SUMIFS(BV_Data_An_Cour!$O:$O,BV_Data_An_Cour!$U:$U,$B12,BV_Data_An_Cour!$V:$V,$C12,BV_Data_An_Cour!$W:$W,L$2) -> 0 | M12: =J12-D12 -> 0 | N12: =L12-F12 -> 0 | O12: {=+INDEX('Réel 2024'!$A$2:$AO$501,MATCH($A12,'Réel 2024'!$A$2:$A$501,0),MATCH(O$2,'Réel 2024'!$A$2:$AO$2,0))} -> 0 | P12: =IF(O12=0,0,Q12/O12) -> 0 | Q12: {=+INDEX('Réel 2024'!$A$2:$AO$501,MATCH($A12,'Réel 2024'!$A$2:$A$501,0),MATCH(Q$2,'Réel 2024'!$A$2:$AO$2,0))} -> 0 | R12: =J12-O12 -> 0 | S12: =L12-Q12 -> 0
A13: =+B13&C13 -> Véhicules neufsTotal Neufs | B13: =+$K$1 -> Véhicules neufs | C13: Total Neufs | D13: =+SUM(D6:D12) -> 16 | E13: =IF(D13<=0,0,F13/D13) -> 4115.1052 | F13: =+SUM(F6:F12) -> 65841.683 | J13: =+SUM(J6:J12) -> 8 | K13: =IF(J13<=0,0,L13/J13) -> 3540.8025 | L13: =+SUM(L6:L12) -> 28326.42 | M13: =+SUM(M6:M12) -> -8 | N13: =+SUM(N6:N12) -> -37515.263 | O13: =+SUM(O6:O12) -> 23 | P13: =IF(O13<=0,0,Q13/O13) -> 5894.8348 | Q13: =+SUM(Q6:Q12) -> 135581.2 | R13: =+SUM(R6:R12) -> -15 | S13: =+SUM(S6:S12) -> -107254.78
A14: =+B14&C14 -> Véhicules neufs | B14: =+$K$1 -> Véhicules neufs | M14: =IF(D13=0,0,M13/D13) -> -0.5 | N14: =IF(F13=0,0,N13/F13) -> -0.56977983 | R14: =R13/O13 -> -0.65217391 | S14: =IF(Q13=0,0,(S13/Q13)) -> -0.79107413
A15: =+B15&C15 -> Véhicules neufsEx-Démos et courtoisies | B15: =+$K$1 -> Véhicules neufs | C15: Ex-Démos et courtoisies | D15: =+INDEX('Budget original'!$A$2:$AO$501,MATCH($A15,'Budget original'!$A$2:$A$501,0),MATCH(D$2,'Budget original'!$A$2:$AO$2,0)) -> 2 | E15: =IF(D15=0,0,F15/D15) -> 750 | F15: =+INDEX('Budget original'!$A$2:$AO$501,MATCH($A15,'Budget original'!$A$2:$A$501,0),MATCH(F$2,'Budget original'!$A$2:$AO$2,0)) -> 1500 | J15: =-SUMIFS(BV_Data_An_Cour!$O:$O,BV_Data_An_Cour!$U:$U,$B15,BV_Data_An_Cour!$V:$V,$C15,BV_Data_An_Cour!$W:$W,J$2) -> 0 | K15: =IF(J15=0,0,L15/J15) -> 0 | L15: =-SUMIFS(BV_Data_An_Cour!$O:$O,BV_Data_An_Cour!$U:$U,$B15,BV_Data_An_Cour!$V:$V,$C15,BV_Data_An_Cour!$W:$W,L$2) -> 0 | M15: =J15-D15 -> -2 | N15: =L15-F15 -> -1500 | O15: {=+INDEX('Réel 2024'!$A$2:$AO$501,MATCH($A15,'Réel 2024'!$A$2:$A$501,0),MATCH(O$2,'Réel 2024'!$A$2:$AO$2,0))} -> 2 | P15: =IF(O15=0,0,Q15/O15) -> 588.42 | Q15: {=+INDEX('Réel 2024'!$A$2:$AO$501,MATCH($A15,'Réel 2024'!$A$2:$A$501,0),MATCH(Q$2,'Réel 2024'!$A$2:$AO$2,0))} -> 1176.84 | R15: =J15-O15 -> -2 | S15: =L15-Q15 -> -1176.84
A16: =+B16&C16 -> Véhicules neufs | B16: =+$K$1 -> Véhicules neufs
A17: =+B17&C17 -> Véhicules neufsFlottes | B17: =+$K$1 -> Véhicules neufs | C17: Flottes | D17: =+INDEX('Budget original'!$A$2:$AO$501,MATCH($A17,'Budget original'!$A$2:$A$501,0),MATCH(D$2,'Budget original'!$A$2:$AO$2,0)) -> 0 | E17: =IF(D17=0,0,F17/D17) -> 0 | F17: =+INDEX('Budget original'!$A$2:$AO$501,MATCH($A17,'Budget original'!$A$2:$A$501,0),MATCH(F$2,'Budget original'!$A$2:$AO$2,0)) -> 0 | J17: =-SUMIFS(BV_Data_An_Cour!$O:$O,BV_Data_An_Cour!$U:$U,$B17,BV_Data_An_Cour!$V:$V,$C17,BV_Data_An_Cour!$W:$W,J$2) -> 4 | K17: =IF(J17=0,0,L17/J17) -> 1875.165 | L17: =-SUMIFS(BV_Data_An_Cour!$O:$O,BV_Data_An_Cour!$U:$U,$B17,BV_Data_An_Cour!$V:$V,$C17,BV_Data_An_Cour!$W:$W,L$2) -> 7500.66 | M17: =J17-D17 -> 4 | N17: =L17-F17 -> 7500.66 | O17: {=+INDEX('Réel 2024'!$A$2:$AO$501,MATCH($A17,'Réel 2024'!$A$2:$A$501,0),MATCH(O$2,'Réel 2024'!$A$2:$AO$2,0))} -> 0 | P17: =IF(O17=0,0,Q17/O17) -> 0 | Q17: {=+INDEX('Réel 2024'!$A$2:$AO$501,MATCH($A17,'Réel 2024'!$A$2:$A$501,0),MATCH(Q$2,'Réel 2024'!$A$2:$AO$2,0))} -> 0 | R17: =J17-O17 -> 4 | S17: =L17-Q17 -> 7500.66
A18: =+B18&C18 -> Véhicules neufs | B18: =+$K$1 -> Véhicules neufs
A19: =+B19&C19 -> Véhicules neufsRachat bail | B19: =+$K$1 -> Véhicules neufs | C19: Rachat bail | D19: =+INDEX('Budget original'!$A$2:$AO$501,MATCH($A19,'Budget original'!$A$2:$A$501,0),MATCH(D$2,'Budget original'!$A$2:$AO$2,0)) -> 0 | E19: =IF(D19=0,0,F19/D19) -> 0 | F19: =+INDEX('Budget original'!$A$2:$AO$501,MATCH($A19,'Budget original'!$A$2:$A$501,0),MATCH(F$2,'Budget original'!$A$2:$AO$2,0)) -> 1926.1072 | L19: =-SUMIFS(BV_Data_An_Cour!$O:$O,BV_Data_An_Cour!$U:$U,$B19,BV_Data_An_Cour!$V:$V,$C19,BV_Data_An_Cour!$W:$W,L$2) -> 999 | N19: =L19-F19 -> -927.10721 | Q19: {=+INDEX('Réel 2024'!$A$2:$AO$501,MATCH($A19,'Réel 2024'!$A$2:$A$501,0),MATCH(Q$2,'Réel 2024'!$A$2:$AO$2,0))} -> 1506.88 | R19: =O19-K19 -> 0 | S19: =L19-Q19 -> -507.88
A20: =+B20&C20 -> Véhicules neufs | B20: =+$K$1 -> Véhicules neufs
A21: =+B21&C21 -> Véhicules neufsRev. Finances | B21: =+$K$1 -> Véhicules neufs | C21: Rev. Finances | D21: =+INDEX('Budget original'!$A$2:$AO$501,MATCH($A21,'Budget original'!$A$2:$A$501,0),MATCH(D$2,'Budget original'!$A$2:$AO$2,0)) -> 0 | E21: =IF(D21=0,0,F21/D21) -> 0 | F21: =+INDEX('Budget original'!$A$2:$AO$501,MATCH($A21,'Budget original'!$A$2:$A$501,0),MATCH(F$2,'Budget original'!$A$2:$AO$2,0)) -> 450 | K21: =IF(J13=0,0,L21/(J13+J15)) -> 0 | L21: =-SUMIFS(BV_Data_An_Cour!$O:$O,BV_Data_An_Cour!$U:$U,$B21,BV_Data_An_Cour!$V:$V,$C21,BV_Data_An_Cour!$W:$W,L$2) -> 0 | N21: =L21-F21 -> -450 | Q21: {=+INDEX('Réel 2024'!$A$2:$AO$501,MATCH($A21,'Réel 2024'!$A$2:$A$501,0),MATCH(Q$2,'Réel 2024'!$A$2:$AO$2,0))} -> 1241.61 | R21: =O21-K21 -> 0 | S21: =L21-Q21 -> -1241.61
A22: =+B22&C22 -> Véhicules neufsRev. Protections | B22: =+$K$1 -> Véhicules neufs | C22: Rev. Protections | D22: =+INDEX('Budget original'!$A$2:$AO$501,MATCH($A22,'Budget original'!$A$2:$A$501,0),MATCH(D$2,'Budget original'!$A$2:$AO$2,0)) -> 0 | E22: =IF(D22=0,0,F22/D22) -> 0 | F22: =+INDEX('Budget original'!$A$2:$AO$501,MATCH($A22,'Budget original'!$A$2:$A$501,0),MATCH(F$2,'Budget original'!$A$2:$AO$2,0)) -> 20700 | K22: =IF(J13=0,0,L22/(J13+J15)) -> 912.25 | L22: =-SUMIFS(BV_Data_An_Cour!$O:$O,BV_Data_An_Cour!$U:$U,$B22,BV_Data_An_Cour!$V:$V,$C22,BV_Data_An_Cour!$W:$W,L$2) -> 7298 | N22: =L22-F22 -> -13402 | Q22: {=+INDEX('Réel 2024'!$A$2:$AO$501,MATCH($A22,'Réel 2024'!$A$2:$A$501,0),MATCH(Q$2,'Réel 2024'!$A$2:$AO$2,0))} -> 27169.62 | R22: =O22-K22 -> -912.25 | S22: =L22-Q22 -> -19871.62
A23: =+B23&C23 -> Véhicules neufsRev. Autres | B23: =+$K$1 -> Véhicules neufs | C23: Rev. Autres | D23: =+INDEX('Budget original'!$A$2:$AO$501,MATCH($A23,'Budget original'!$A$2:$A$501,0),MATCH(D$2,'Budget original'!$A$2:$AO$2,0)) -> 0 | E23: =IF(D23=0,0,F23/D23) -> 0 | F23: =+INDEX('Budget original'!$A$2:$AO$501,MATCH($A23,'Budget original'!$A$2:$A$501,0),MATCH(F$2,'Budget original'!$A$2:$AO$2,0)) -> 8640 | K23: =IF(J13=0,0,L23/(J13+J15)) -> 891.08125 | L23: =-SUMIFS(BV_Data_An_Cour!$O:$O,BV_Data_An_Cour!$U:$U,$B23,BV_Data_An_Cour!$V:$V,$C23,BV_Data_An_Cour!$W:$W,L$2) -> 7128.65 | N23: =L23-F23 -> -1511.35 | Q23: {=+INDEX('Réel 2024'!$A$2:$AO$501,MATCH($A23,'Réel 2024'!$A$2:$A$501,0),MATCH(Q$2,'Réel 2024'!$A$2:$AO$2,0))} -> 11508.04 | R23: =O23-K23 -> -891.08125 | S23: =L23-Q23 -> -4379.39
A24: =+B24&C24 -> Véhicules neufsTotal F&I | B24: =+$K$1 -> Véhicules neufs | C24: Total F&I | D24: =+D15+D13 -> 18 | E24: =IF(D24<=0,0,F24/D24) -> 1655 | F24: =F21+F22+F23 -> 29790 | J24: =+J15+J13 -> 8 | K24: =IF(J24<=0,0,L24/J24) -> 1803.3313 | L24: =L21+L22+L23 -> 14426.65 | M24: =J24-D24 -> -10 | N24: =L24-F24 -> -15363.35 | O24: =+O15+O13 -> 25 | P24: =IF(O24<=0,0,Q24/O24) -> 1596.7708 | Q24: =Q21+Q22+Q23 -> 39919.27 | S24: =L24-Q24 -> -25492.62
A25: =+B25&C25 -> Véhicules neufs | B25: =+$K$1 -> Véhicules neufs | N25: =IF(N24=0,0,N24/F24) -> -0.51572172 | S25: =IF(Q24=0,0,(S24/Q24)) -> -0.63860436
A26: =+B26&C26 -> Véhicules neufs | B26: =+$K$1 -> Véhicules neufs
A27: =+B27&C27 -> Véhicules neufsTotal Dépt. Neufs | B27: =+$K$1 -> Véhicules neufs | C27: Total Dépt. Neufs | D27: =+D13+D15+D17 -> 18 | E27: =IF(D27<=0,0,F27/D27) -> 5503.2106 | F27: =F13+F17+F24+F19+F15 -> 99057.791 | J27: =+J13+J15+J17 -> 12 | K27: =IF(J27<=0,0,L27/J27) -> 4271.0608 | L27: =L13+L17+L24+L19+L15 -> 51252.73 | M27: =J27-D27 -> -6 | N27: =L27-F27 -> -47805.061 | O27: =+O13+O15+O17 -> 25 | P27: =IF(O27<=0,0,Q27/O27) -> 7127.3676 | Q27: =Q13+Q17+Q24+Q19+Q15 -> 178184.19 | R27: =J27-O27 -> -13 | S27: =L27-Q27 -> -126931.46
A28: =+B28&C28 -> Véhicules neufs | B28: =+$K$1 -> Véhicules neufs | M28: =M27/D27 -> -0.33333333 | N28: =N27/F27 -> -0.48259769 | R28: =R27/O27 -> -0.52 | S28: =IF(Q27=0,0,S27/Q27) -> -0.71236096
A29: =+B29&C29 -> Véhicules neufs | B29: =+$K$1 -> Véhicules neufs
A30: =+B30&C30 -> Véhicules neufsDEPENSES | B30: =+$K$1 -> Véhicules neufs | C30: DEPENSES
A31: =+B31&C31 -> Véhicules neufsComm. vendeurs | B31: =+$K$1 -> Véhicules neufs | C31: Comm. vendeurs | D31: =F31/(F13+F15) -> 0.30138082 | E31: =F31/D$24 -> 1127.5273 | F31: =+INDEX('Budget original'!$A$2:$AO$501,MATCH($A31,'Budget original'!$A$2:$A$501,0),MATCH(F$2,'Budget original'!$A$2:$AO$2,0)) -> 20295.492 | J31: =L31/(L13+L15) -> 0.32221827 | K31: =IF(L31=0,0,L31/J$24) -> 1140.9113 | L31: =SUMIFS(BV_Data_An_Cour!$O:$O,BV_Data_An_Cour!$U:$U,$B31,BV_Data_An_Cour!$V:$V,$C31,BV_Data_An_Cour!$W:$W,L$2) -> 9127.29 | N31: =L31-F31 -> -11168.202 | O31: =Q31/(Q13+Q15+Q17) -> 0.26180589 | P31: =Q31/O$24 -> 1432.1624 | Q31: {=+INDEX('Réel 2024'!$A$2:$AO$501,MATCH($A31,'Réel 2024'!$A$2:$A$501,0),MATCH(Q$2,'Réel 2024'!$A$2:$AO$2,0))} -> 35804.06 | S31: =L31-Q31 -> -26676.77
A32: =+B32&C32 -> Véhicules neufsComm. F&I | B32: =+$K$1 -> Véhicules neufs | C32: Comm. F&I | D32: =F32/F24 -> 0.275 | E32: =F32/D$24 -> 455.125 | F32: =+INDEX('Budget original'!$A$2:$AO$501,MATCH($A32,'Budget original'!$A$2:$A$501,0),MATCH(F$2,'Budget original'!$A$2:$AO$2,0)) -> 8192.25 | J32: =L32/L24 -> 0.32295925 | K32: =IF(L32=0,0,L32/J$24) -> 582.4025 | L32: =SUMIFS(BV_Data_An_Cour!$O:$O,BV_Data_An_Cour!$U:$U,$B32,BV_Data_An_Cour!$V:$V,$C32,BV_Data_An_Cour!$W:$W,L$2) -> 4659.22 | N32: =L32-F32 -> -3533.03 | O32: =Q32/Q24 -> 0.33354493 | P32: =Q32/O$24 -> 532.5948 | Q32: {=+INDEX('Réel 2024'!$A$2:$AO$501,MATCH($A32,'Réel 2024'!$A$2:$A$501,0),MATCH(Q$2,'Réel 2024'!$A$2:$AO$2,0))} -> 13314.87 | S32: =L32-Q32 -> -8655.65 | V32: 30% Nadia + 2.3% vendeurs
A33: =+B33&C33 -> Véhicules neufsFrais de livraison | B33: =+$K$1 -> Véhicules neufs | C33: Frais de livraison | E33: =F33/D$24 -> 130 | F33: =+INDEX('Budget original'!$A$2:$AO$501,MATCH($A33,'Budget original'!$A$2:$A$501,0),MATCH(F$2,'Budget original'!$A$2:$AO$2,0)) -> 2340 | K33: =IF(L33=0,0,L33/J$24) -> 0.4625 | L33: =SUMIFS(BV_Data_An_Cour!$O:$O,BV_Data_An_Cour!$U:$U,$B33,BV_Data_An_Cour!$V:$V,$C33,BV_Data_An_Cour!$W:$W,L$2) -> 3.7 | N33: =L33-F33 -> -2336.3 | P33: =Q33/O$24 -> 100.4672 | Q33: {=+INDEX('Réel 2024'!$A$2:$AO$501,MATCH($A33,'Réel 2024'!$A$2:$A$501,0),MATCH(Q$2,'Réel 2024'!$A$2:$AO$2,0))} -> 2511.68 | S33: =L33-Q33 -> -2507.98 | V33: Prov Essence dec - profits sur échange entre concessionnaire
A34: =+B34&C34 -> Véhicules neufsService gratuit 1 | B34: =+$K$1 -> Véhicules neufs | C34: Service gratuit 1 | E34: =F34/D$24 -> 37 | F34: =+INDEX('Budget original'!$A$2:$AO$501,MATCH($A34,'Budget original'!$A$2:$A$501,0),MATCH(F$2,'Budget original'!$A$2:$AO$2,0)) -> 666 | K34: =IF(L34=0,0,L34/J$24) -> 0 | L34: =SUMIFS(BV_Data_An_Cour!$O:$O,BV_Data_An_Cour!$U:$U,$B34,BV_Data_An_Cour!$V:$V,$C34,BV_Data_An_Cour!$W:$W,L$2) -> 0 | N34: =L34-F34 -> -666 | P34: =Q34/O$24 -> 37.7228 | Q34: {=+INDEX('Réel 2024'!$A$2:$AO$501,MATCH($A34,'Réel 2024'!$A$2:$A$501,0),MATCH(Q$2,'Réel 2024'!$A$2:$AO$2,0))} -> 943.07 | S34: =L34-Q34 -> -943.07
A35: =+B35&C35 -> Véhicules neufsEntretien stock | B35: =+$K$1 -> Véhicules neufs | C35: Entretien stock | E35: =F35/D$24 -> 63.333333 | F35: =+INDEX('Budget original'!$A$2:$AO$501,MATCH($A35,'Budget original'!$A$2:$A$501,0),MATCH(F$2,'Budget original'!$A$2:$AO$2,0)) -> 1140 | K35: =IF(L35=0,0,L35/J$24) -> 356.60875 | L35: =SUMIFS(BV_Data_An_Cour!$O:$O,BV_Data_An_Cour!$U:$U,$B35,BV_Data_An_Cour!$V:$V,$C35,BV_Data_An_Cour!$W:$W,L$2) -> 2852.87 | N35: =L35-F35 -> 1712.87 | P35: =Q35/O$24 -> 83.3348 | Q35: {=+INDEX('Réel 2024'!$A$2:$AO$501,MATCH($A35,'Réel 2024'!$A$2:$A$501,0),MATCH(Q$2,'Réel 2024'!$A$2:$AO$2,0))} -> 2083.37 | S35: =L35-Q35 -> 769.5 | V35: Préparation show room - Quick out à la demande
A36: =+B36&C36 -> Véhicules neufsPublicité 1 | B36: =+$K$1 -> Véhicules neufs | C36: Publicité 1 | E36: =F36/D$24 -> 513.97059 | F36: =+INDEX('Budget original'!$A$2:$AO$501,MATCH($A36,'Budget original'!$A$2:$A$501,0),MATCH(F$2,'Budget original'!$A$2:$AO$2,0)) -> 9251.4706 | K36: =IF(L36=0,0,L36/J$24) -> 1325.5687 | L36: =SUMIFS(BV_Data_An_Cour!$O:$O,BV_Data_An_Cour!$U:$U,$B36,BV_Data_An_Cour!$V:$V,$C36,BV_Data_An_Cour!$W:$W,L$2) -> 10604.55 | N36: =L36-F36 -> 1353.0794 | P36: =Q36/O$24 -> 813.9016 | Q36: {=+INDEX('Réel 2024'!$A$2:$AO$501,MATCH($A36,'Réel 2024'!$A$2:$A$501,0),MATCH(Q$2,'Réel 2024'!$A$2:$AO$2,0))} -> 20347.54 | S36: =L36-Q36 -> -9742.99 | V36: Axifuge, SM360, Radio (-COOP)
A37: =+B37&C37 -> Véhicules neufsIntérêt de gros | B37: =+$K$1 -> Véhicules neufs | C37: Intérêt de gros | E37: =F37/D$24 -> 1313.5622 | F37: =+INDEX('Budget original'!$A$2:$AO$501,MATCH($A37,'Budget original'!$A$2:$A$501,0),MATCH(F$2,'Budget original'!$A$2:$AO$2,0)) -> 23644.12 | K37: =IF(L37=0,0,L37/J$24) -> 2816.66 | L37: =SUMIFS(BV_Data_An_Cour!$O:$O,BV_Data_An_Cour!$U:$U,$B37,BV_Data_An_Cour!$V:$V,$C37,BV_Data_An_Cour!$W:$W,L$2) -> 22533.28 | N37: =L37-F37 -> -1110.8404 | P37: =Q37/O$24 -> 1073.2664 | Q37: {=+INDEX('Réel 2024'!$A$2:$AO$501,MATCH($A37,'Réel 2024'!$A$2:$A$501,0),MATCH(Q$2,'Réel 2024'!$A$2:$AO$2,0))} -> 26831.66 | S37: =L37-Q37 -> -4298.38 | V37: BMO 1-2 dec + TD 3-31 dec | W37: =21204.8+1328.44 -> 22533.24
A38: =+B38&C38 -> Véhicules neufs[...] | B38: =+$K$1 -> Véhicules neufs | C38: [...] | E38: =F38/D$24 -> 0 | F38: =+INDEX('Budget original'!$A$2:$AO$501,MATCH($A38,'Budget original'!$A$2:$A$501,0),MATCH(F$2,'Budget original'!$A$2:$AO$2,0)) -> 0 | K38: =IF(L38=0,0,L38/J$24) -> 0 | L38: =SUMIFS(BV_Data_An_Cour!$O:$O,BV_Data_An_Cour!$U:$U,$B38,BV_Data_An_Cour!$V:$V,$C38,BV_Data_An_Cour!$W:$W,L$2) -> 0 | N38: =L38-F38 -> 0 | P38: =Q38/O$24 -> 0 | Q38: {=+INDEX('Réel 2024'!$A$2:$AO$501,MATCH($A38,'Réel 2024'!$A$2:$A$501,0),MATCH(Q$2,'Réel 2024'!$A$2:$AO$2,0))} -> 0 | S38: =L38-Q38 -> 0
A39: =+B39&C39 -> Véhicules neufs[...] | B39: =+$K$1 -> Véhicules neufs | C39: [...] | E39: =F39/D$24 -> 0 | F39: =+INDEX('Budget original'!$A$2:$AO$501,MATCH($A39,'Budget original'!$A$2:$A$501,0),MATCH(F$2,'Budget original'!$A$2:$AO$2,0)) -> 0 | K39: =IF(L39=0,0,L39/J$24) -> 0 | L39: =SUMIFS(BV_Data_An_Cour!$O:$O,BV_Data_An_Cour!$U:$U,$B39,BV_Data_An_Cour!$V:$V,$C39,BV_Data_An_Cour!$W:$W,L$2) -> 0 | N39: =L39-F39 -> 0 | P39: =Q39/O$24 -> 0 | Q39: {=+INDEX('Réel 2024'!$A$2:$AO$501,MATCH($A39,'Réel 2024'!$A$2:$A$501,0),MATCH(Q$2,'Réel 2024'!$A$2:$AO$2,0))} -> 0 | S39: =L39-Q39 -> 0
A40: =+B40&C40 -> Véhicules neufs[...] | B40: =+$K$1 -> Véhicules neufs | C40: [...] | E40: =F40/D$24 -> 0 | F40: =+INDEX('Budget original'!$A$2:$AO$501,MATCH($A40,'Budget original'!$A$2:$A$501,0),MATCH(F$2,'Budget original'!$A$2:$AO$2,0)) -> 0 | K40: =IF(L40=0,0,L40/J$24) -> 0 | L40: =SUMIFS(BV_Data_An_Cour!$O:$O,BV_Data_An_Cour!$U:$U,$B40,BV_Data_An_Cour!$V:$V,$C40,BV_Data_An_Cour!$W:$W,L$2) -> 0 | N40: =L40-F40 -> 0 | P40: =Q40/O$24 -> 0 | Q40: {=+INDEX('Réel 2024'!$A$2:$AO$501,MATCH($A40,'Réel 2024'!$A$2:$A$501,0),MATCH(Q$2,'Réel 2024'!$A$2:$AO$2,0))} -> 0 | S40: =L40-Q40 -> 0
A41: =+B41&C41 -> Véhicules neufsTOTAL VARIABLES | B41: =+$K$1 -> Véhicules neufs | C41: TOTAL VARIABLES | D41: % brut | E41: =F41/F$27 -> 0.66152629 | F41: =SUM(F31:F40) -> 65529.333 | J41: % brut | K41: =L41/L$27 -> 0.97128309 | L41: =SUM(L31:L40) -> 49780.91 | N41: =L41-F41 -> -15748.423 | O41: % brut | P41: =Q41/Q$27 -> 0.57152237 | Q41: =SUM(Q31:Q40) -> 101836.25 | S41: =L41-Q41 -> -52055.34
A42: =+B42&C42 -> Véhicules neufsSalaires cadres | B42: =+$K$1 -> Véhicules neufs | C42: Salaires cadres | F42: =+INDEX('Budget original'!$A$2:$AO$501,MATCH($A42,'Budget original'!$A$2:$A$501,0),MATCH(F$2,'Budget original'!$A$2:$AO$2,0)) -> 12763.084 | L42: =SUMIFS(BV_Data_An_Cour!$O:$O,BV_Data_An_Cour!$U:$U,$B42,BV_Data_An_Cour!$V:$V,$C42,BV_Data_An_Cour!$W:$W,L$2) -> 10268.97 | N42: =L42-F42 -> -2494.1145 | Q42: {=+INDEX('Réel 2024'!$A$2:$AO$501,MATCH($A42,'Réel 2024'!$A$2:$A$501,0),MATCH(Q$2,'Réel 2024'!$A$2:$AO$2,0))} -> 10172.2 | S42: =L42-Q42 -> 96.77
A43: =+B43&C43 -> Véhicules neufsSalaires commis | B43: =+$K$1 -> Véhicules neufs | C43: Salaires commis | F43: =+INDEX('Budget original'!$A$2:$AO$501,MATCH($A43,'Budget original'!$A$2:$A$501,0),MATCH(F$2,'Budget original'!$A$2:$AO$2,0)) -> 10418.905 | L43: =SUMIFS(BV_Data_An_Cour!$O:$O,BV_Data_An_Cour!$U:$U,$B43,BV_Data_An_Cour!$V:$V,$C43,BV_Data_An_Cour!$W:$W,L$2) -> 7244.51 | N43: =L43-F43 -> -3174.3946 | Q43: {=+INDEX('Réel 2024'!$A$2:$AO$501,MATCH($A43,'Réel 2024'!$A$2:$A$501,0),MATCH(Q$2,'Réel 2024'!$A$2:$AO$2,0))} -> 10762.7 | S43: =L43-Q43 -> -3518.19 | V43: Pas sal GPA et secrétaire ventes
A44: =+B44&C44 -> Véhicules neufsSalaires autres | B44: =+$K$1 -> Véhicules neufs | C44: Salaires autres | F44: =+INDEX('Budget original'!$A$2:$AO$501,MATCH($A44,'Budget original'!$A$2:$A$501,0),MATCH(F$2,'Budget original'!$A$2:$AO$2,0)) -> 342 | L44: =SUMIFS(BV_Data_An_Cour!$O:$O,BV_Data_An_Cour!$U:$U,$B44,BV_Data_An_Cour!$V:$V,$C44,BV_Data_An_Cour!$W:$W,L$2) -> 0 | N44: =L44-F44 -> -342 | Q44: {=+INDEX('Réel 2024'!$A$2:$AO$501,MATCH($A44,'Réel 2024'!$A$2:$A$501,0),MATCH(Q$2,'Réel 2024'!$A$2:$AO$2,0))} -> 342 | S44: =L44-Q44 -> -342 | V44: Pas sal GPA
A45: =+B45&C45 -> Véhicules neufsSalaires spécialistes | B45: =+$K$1 -> Véhicules neufs | C45: Salaires spécialistes | F45: =+INDEX('Budget original'!$A$2:$AO$501,MATCH($A45,'Budget original'!$A$2:$A$501,0),MATCH(F$2,'Budget original'!$A$2:$AO$2,0)) -> 0 | L45: =SUMIFS(BV_Data_An_Cour!$O:$O,BV_Data_An_Cour!$U:$U,$B45,BV_Data_An_Cour!$V:$V,$C45,BV_Data_An_Cour!$W:$W,L$2) -> 0 | N45: =L45-F45 -> 0 | Q45: {=+INDEX('Réel 2024'!$A$2:$AO$501,MATCH($A45,'Réel 2024'!$A$2:$A$501,0),MATCH(Q$2,'Réel 2024'!$A$2:$AO$2,0))} -> 0 | S45: =L45-Q45 -> 0
A46: =+B46&C46 -> Véhicules neufs[...] | B46: =+$K$1 -> Véhicules neufs | C46: [...] | F46: =+INDEX('Budget original'!$A$2:$AO$501,MATCH($A46,'Budget original'!$A$2:$A$501,0),MATCH(F$2,'Budget original'!$A$2:$AO$2,0)) -> 0 | L46: =SUMIFS(BV_Data_An_Cour!$O:$O,BV_Data_An_Cour!$U:$U,$B46,BV_Data_An_Cour!$V:$V,$C46,BV_Data_An_Cour!$W:$W,L$2) -> 0 | N46: =L46-F46 -> 0 | Q46: {=+INDEX('Réel 2024'!$A$2:$AO$501,MATCH($A46,'Réel 2024'!$A$2:$A$501,0),MATCH(Q$2,'Réel 2024'!$A$2:$AO$2,0))} -> 0 | S46: =L46-Q46 -> 0
A47: =+B47&C47 -> Véhicules neufs[...] | B47: =+$K$1 -> Véhicules neufs | C47: [...] | F47: =+INDEX('Budget original'!$A$2:$AO$501,MATCH($A47,'Budget original'!$A$2:$A$501,0),MATCH(F$2,'Budget original'!$A$2:$AO$2,0)) -> 0 | L47: =SUMIFS(BV_Data_An_Cour!$O:$O,BV_Data_An_Cour!$U:$U,$B47,BV_Data_An_Cour!$V:$V,$C47,BV_Data_An_Cour!$W:$W,L$2) -> 0 | N47: =L47-F47 -> 0 | Q47: {=+INDEX('Réel 2024'!$A$2:$AO$501,MATCH($A47,'Réel 2024'!$A$2:$A$501,0),MATCH(Q$2,'Réel 2024'!$A$2:$AO$2,0))} -> 0 | S47: =L47-Q47 -> 0
A48: =+B48&C48 -> Véhicules neufs[...] | B48: =+$K$1 -> Véhicules neufs | C48: [...] | F48: =+INDEX('Budget original'!$A$2:$AO$501,MATCH($A48,'Budget original'!$A$2:$A$501,0),MATCH(F$2,'Budget original'!$A$2:$AO$2,0)) -> 0 | L48: =SUMIFS(BV_Data_An_Cour!$O:$O,BV_Data_An_Cour!$U:$U,$B48,BV_Data_An_Cour!$V:$V,$C48,BV_Data_An_Cour!$W:$W,L$2) -> 0 | N48: =L48-F48 -> 0 | Q48: {=+INDEX('Réel 2024'!$A$2:$AO$501,MATCH($A48,'Réel 2024'!$A$2:$A$501,0),MATCH(Q$2,'Réel 2024'!$A$2:$AO$2,0))} -> 0 | S48: =L48-Q48 -> 0
A49: =+B49&C49 -> Véhicules neufsSalaires en absences | B49: =+$K$1 -> Véhicules neufs | C49: Salaires en absences | F49: =+INDEX('Budget original'!$A$2:$AO$501,MATCH($A49,'Budget original'!$A$2:$A$501,0),MATCH(F$2,'Budget original'!$A$2:$AO$2,0)) -> 11141.726 | L49: =SUMIFS(BV_Data_An_Cour!$O:$O,BV_Data_An_Cour!$U:$U,$B49,BV_Data_An_Cour!$V:$V,$C49,BV_Data_An_Cour!$W:$W,L$2) -> 179.64 | N49: =L49-F49 -> -10962.086 | Q49: {=+INDEX('Réel 2024'!$A$2:$AO$501,MATCH($A49,'Réel 2024'!$A$2:$A$501,0),MATCH(Q$2,'Réel 2024'!$A$2:$AO$2,0))} -> 14638.9 | S49: =L49-Q49 -> -14459.26
A50: =+B50&C50 -> Véhicules neufsDéduction à la source | B50: =+$K$1 -> Véhicules neufs | C50: Déduction à la source | F50: =+INDEX('Budget original'!$A$2:$AO$501,MATCH($A50,'Budget original'!$A$2:$A$501,0),MATCH(F$2,'Budget original'!$A$2:$AO$2,0)) -> 6684.7959 | L50: =SUMIFS(BV_Data_An_Cour!$O:$O,BV_Data_An_Cour!$U:$U,$B50,BV_Data_An_Cour!$V:$V,$C50,BV_Data_An_Cour!$W:$W,L$2) -> 6796.55 | N50: =L50-F50 -> 111.75408 | Q50: {=+INDEX('Réel 2024'!$A$2:$AO$501,MATCH($A50,'Réel 2024'!$A$2:$A$501,0),MATCH(Q$2,'Réel 2024'!$A$2:$AO$2,0))} -> 8819.43 | S50: =L50-Q50 -> -2022.88
A51: =+B51&C51 -> Véhicules neufsBénéfices marginaux | B51: =+$K$1 -> Véhicules neufs | C51: Bénéfices marginaux | F51: =+INDEX('Budget original'!$A$2:$AO$501,MATCH($A51,'Budget original'!$A$2:$A$501,0),MATCH(F$2,'Budget original'!$A$2:$AO$2,0)) -> 4104.6992 | L51: =SUMIFS(BV_Data_An_Cour!$O:$O,BV_Data_An_Cour!$U:$U,$B51,BV_Data_An_Cour!$V:$V,$C51,BV_Data_An_Cour!$W:$W,L$2) -> 3722.69 | N51: =L51-F51 -> -382.00925 | Q51: {=+INDEX('Réel 2024'!$A$2:$AO$501,MATCH($A51,'Réel 2024'!$A$2:$A$501,0),MATCH(Q$2,'Réel 2024'!$A$2:$AO$2,0))} -> 6289 | S51: =L51-Q51 -> -2566.31
A52: =+B52&C52 -> Véhicules neufsCsst | B52: =+$K$1 -> Véhicules neufs | C52: Csst | F52: =+INDEX('Budget original'!$A$2:$AO$501,MATCH($A52,'Budget original'!$A$2:$A$501,0),MATCH(F$2,'Budget original'!$A$2:$AO$2,0)) -> 879.57841 | L52: =SUMIFS(BV_Data_An_Cour!$O:$O,BV_Data_An_Cour!$U:$U,$B52,BV_Data_An_Cour!$V:$V,$C52,BV_Data_An_Cour!$W:$W,L$2) -> 1572.23 | N52: =L52-F52 -> 692.65159 | Q52: {=+INDEX('Réel 2024'!$A$2:$AO$501,MATCH($A52,'Réel 2024'!$A$2:$A$501,0),MATCH(Q$2,'Réel 2024'!$A$2:$AO$2,0))} -> 124.53 | S52: =L52-Q52 -> 1447.7
A53: =+B53&C53 -> Véhicules neufs[...] | B53: =+$K$1 -> Véhicules neufs | C53: [...] | D53: =VLOOKUP(C53,$B$2:$B$46,1,FALSE) -> #N/A | F53: =+INDEX('Budget original'!$A$2:$AO$501,MATCH($A53,'Budget original'!$A$2:$A$501,0),MATCH(F$2,'Budget original'!$A$2:$AO$2,0)) -> 0 | L53: =SUMIFS(BV_Data_An_Cour!$O:$O,BV_Data_An_Cour!$U:$U,$B53,BV_Data_An_Cour!$V:$V,$C53,BV_Data_An_Cour!$W:$W,L$2) -> 0 | N53: =L53-F53 -> 0 | Q53: {=+INDEX('Réel 2024'!$A$2:$AO$501,MATCH($A53,'Réel 2024'!$A$2:$A$501,0),MATCH(Q$2,'Réel 2024'!$A$2:$AO$2,0))} -> 0 | S53: =L53-Q53 -> 0
A54: =+B54&C54 -> Véhicules neufsTOTAL PERSONNEL | B54: =+$K$1 -> Véhicules neufs | C54: TOTAL PERSONNEL | D54: % brut | E54: =F54/F$27 -> 0.46775512 | F54: =+SUM(F42:F53) -> 46334.788 | J54: % brut | K54: =L54/L$27 -> 0.58113178 | L54: =+SUM(L42:L53) -> 29784.59 | N54: =+SUM(N42:N53) -> -16550.198 | O54: % brut | P54: =Q54/Q$27 -> 0.28705555 | Q54: =+SUM(Q42:Q53) -> 51148.76 | S54: =+SUM(S42:S53) -> -21364.17
A55: =+B55&C55 -> Véhicules neufsPublicité 2 | B55: =+$K$1 -> Véhicules neufs | C55: Publicité 2 | F55: =+INDEX('Budget original'!$A$2:$AO$501,MATCH($A55,'Budget original'!$A$2:$A$501,0),MATCH(F$2,'Budget original'!$A$2:$AO$2,0)) -> 0 | L55: =SUMIFS(BV_Data_An_Cour!$O:$O,BV_Data_An_Cour!$U:$U,$B55,BV_Data_An_Cour!$V:$V,$C55,BV_Data_An_Cour!$W:$W,L$2) -> 0 | N55: =L55-F55 -> 0 | Q55: {=+INDEX('Réel 2024'!$A$2:$AO$501,MATCH($A55,'Réel 2024'!$A$2:$A$501,0),MATCH(Q$2,'Réel 2024'!$A$2:$AO$2,0))} -> 0 | S55: =L55-Q55 -> 0
A56: =+B56&C56 -> Véhicules neufsService gratuit 2 | B56: =+$K$1 -> Véhicules neufs | C56: Service gratuit 2 | F56: =+INDEX('Budget original'!$A$2:$AO$501,MATCH($A56,'Budget original'!$A$2:$A$501,0),MATCH(F$2,'Budget original'!$A$2:$AO$2,0)) -> 0 | L56: =SUMIFS(BV_Data_An_Cour!$O:$O,BV_Data_An_Cour!$U:$U,$B56,BV_Data_An_Cour!$V:$V,$C56,BV_Data_An_Cour!$W:$W,L$2) -> 0 | N56: =L56-F56 -> 0 | Q56: {=+INDEX('Réel 2024'!$A$2:$AO$501,MATCH($A56,'Réel 2024'!$A$2:$A$501,0),MATCH(Q$2,'Réel 2024'!$A$2:$AO$2,0))} -> 0 | S56: =L56-Q56 -> 0
A57: =+B57&C57 -> Véhicules neufsFrais véhicules de cie | B57: =+$K$1 -> Véhicules neufs | C57: Frais véhicules de cie | F57: =+INDEX('Budget original'!$A$2:$AO$501,MATCH($A57,'Budget original'!$A$2:$A$501,0),MATCH(F$2,'Budget original'!$A$2:$AO$2,0)) -> 6620.9333 | L57: =SUMIFS(BV_Data_An_Cour!$O:$O,BV_Data_An_Cour!$U:$U,$B57,BV_Data_An_Cour!$V:$V,$C57,BV_Data_An_Cour!$W:$W,L$2) -> 2004.38 | N57: =L57-F57 -> -4616.5533 | Q57: {=+INDEX('Réel 2024'!$A$2:$AO$501,MATCH($A57,'Réel 2024'!$A$2:$A$501,0),MATCH(Q$2,'Réel 2024'!$A$2:$AO$2,0))} -> 10008.93 | S57: =L57-Q57 -> -8004.55
A58: =+B58&C58 -> Véhicules neufsInformatique | B58: =+$K$1 -> Véhicules neufs | C58: Informatique | F58: =+INDEX('Budget original'!$A$2:$AO$501,MATCH($A58,'Budget original'!$A$2:$A$501,0),MATCH(F$2,'Budget original'!$A$2:$AO$2,0)) -> 4878.3 | L58: =SUMIFS(BV_Data_An_Cour!$O:$O,BV_Data_An_Cour!$U:$U,$B58,BV_Data_An_Cour!$V:$V,$C58,BV_Data_An_Cour!$W:$W,L$2) -> 5491.56 | N58: =L58-F58 -> 613.26 | Q58: {=+INDEX('Réel 2024'!$A$2:$AO$501,MATCH($A58,'Réel 2024'!$A$2:$A$501,0),MATCH(Q$2,'Réel 2024'!$A$2:$AO$2,0))} -> 4493.79 | S58: =L58-Q58 -> 997.77
A59: =+B59&C59 -> Véhicules neufsFrais de déplacement | B59: =+$K$1 -> Véhicules neufs | C59: Frais de déplacement | F59: =+INDEX('Budget original'!$A$2:$AO$501,MATCH($A59,'Budget original'!$A$2:$A$501,0),MATCH(F$2,'Budget original'!$A$2:$AO$2,0)) -> 825 | L59: =SUMIFS(BV_Data_An_Cour!$O:$O,BV_Data_An_Cour!$U:$U,$B59,BV_Data_An_Cour!$V:$V,$C59,BV_Data_An_Cour!$W:$W,L$2) -> 229.19 | N59: =L59-F59 -> -595.81 | Q59: {=+INDEX('Réel 2024'!$A$2:$AO$501,MATCH($A59,'Réel 2024'!$A$2:$A$501,0),MATCH(Q$2,'Réel 2024'!$A$2:$AO$2,0))} -> 1127.21 | S59: =L59-Q59 -> -898.02
A60: =+B60&C60 -> Véhicules neufsServices extérieurs | B60: =+$K$1 -> Véhicules neufs | C60: Services extérieurs | F60: =+INDEX('Budget original'!$A$2:$AO$501,MATCH($A60,'Budget original'!$A$2:$A$501,0),MATCH(F$2,'Budget original'!$A$2:$AO$2,0)) -> 3314.7 | L60: =SUMIFS(BV_Data_An_Cour!$O:$O,BV_Data_An_Cour!$U:$U,$B60,BV_Data_An_Cour!$V:$V,$C60,BV_Data_An_Cour!$W:$W,L$2) -> 4998.77 | N60: =L60-F60 -> 1684.07 | Q60: {=+INDEX('Réel 2024'!$A$2:$AO$501,MATCH($A60,'Réel 2024'!$A$2:$A$501,0),MATCH(Q$2,'Réel 2024'!$A$2:$AO$2,0))} -> 4492.53 | S60: =L60-Q60 -> 506.24
A61: =+B61&C61 -> Véhicules neufsFournitures autres | B61: =+$K$1 -> Véhicules neufs | C61: Fournitures autres | F61: =+INDEX('Budget original'!$A$2:$AO$501,MATCH($A61,'Budget original'!$A$2:$A$501,0),MATCH(F$2,'Budget original'!$A$2:$AO$2,0)) -> 40 | L61: =SUMIFS(BV_Data_An_Cour!$O:$O,BV_Data_An_Cour!$U:$U,$B61,BV_Data_An_Cour!$V:$V,$C61,BV_Data_An_Cour!$W:$W,L$2) -> 13.12 | N61: =L61-F61 -> -26.88 | Q61: {=+INDEX('Réel 2024'!$A$2:$AO$501,MATCH($A61,'Réel 2024'!$A$2:$A$501,0),MATCH(Q$2,'Réel 2024'!$A$2:$AO$2,0))} -> 486.48 | S61: =L61-Q61 -> -473.36
A62: =+B62&C62 -> Véhicules neufsUniformes | B62: =+$K$1 -> Véhicules neufs | C62: Uniformes | F62: =+INDEX('Budget original'!$A$2:$AO$501,MATCH($A62,'Budget original'!$A$2:$A$501,0),MATCH(F$2,'Budget original'!$A$2:$AO$2,0)) -> 30 | L62: =SUMIFS(BV_Data_An_Cour!$O:$O,BV_Data_An_Cour!$U:$U,$B62,BV_Data_An_Cour!$V:$V,$C62,BV_Data_An_Cour!$W:$W,L$2) -> 0 | N62: =L62-F62 -> -30 | Q62: {=+INDEX('Réel 2024'!$A$2:$AO$501,MATCH($A62,'Réel 2024'!$A$2:$A$501,0),MATCH(Q$2,'Réel 2024'!$A$2:$AO$2,0))} -> 0 | S62: =L62-Q62 -> 0
A63: =+B63&C63 -> Véhicules neufsPapeterie | B63: =+$K$1 -> Véhicules neufs | C63: Papeterie | F63: =+INDEX('Budget original'!$A$2:$AO$501,MATCH($A63,'Budget original'!$A$2:$A$501,0),MATCH(F$2,'Budget original'!$A$2:$AO$2,0)) -> 708.75 | L63: =SUMIFS(BV_Data_An_Cour!$O:$O,BV_Data_An_Cour!$U:$U,$B63,BV_Data_An_Cour!$V:$V,$C63,BV_Data_An_Cour!$W:$W,L$2) -> 170.18 | N63: =L63-F63 -> -538.57 | Q63: {=+INDEX('Réel 2024'!$A$2:$AO$501,MATCH($A63,'Réel 2024'!$A$2:$A$501,0),MATCH(Q$2,'Réel 2024'!$A$2:$AO$2,0))} -> 483.35 | S63: =L63-Q63 -> -313.17
A64: =+B64&C64 -> Véhicules neufsTéléphone | B64: =+$K$1 -> Véhicules neufs | C64: Téléphone | F64: =+INDEX('Budget original'!$A$2:$AO$501,MATCH($A64,'Budget original'!$A$2:$A$501,0),MATCH(F$2,'Budget original'!$A$2:$AO$2,0)) -> 210.4 | L64: =SUMIFS(BV_Data_An_Cour!$O:$O,BV_Data_An_Cour!$U:$U,$B64,BV_Data_An_Cour!$V:$V,$C64,BV_Data_An_Cour!$W:$W,L$2) -> 350.52 | N64: =L64-F64 -> 140.12 | Q64: {=+INDEX('Réel 2024'!$A$2:$AO$501,MATCH($A64,'Réel 2024'!$A$2:$A$501,0),MATCH(Q$2,'Réel 2024'!$A$2:$AO$2,0))} -> 190.85 | S64: =L64-Q64 -> 159.67
A65: =+B65&C65 -> Véhicules neufsFrais postaux | B65: =+$K$1 -> Véhicules neufs | C65: Frais postaux | F65: =+INDEX('Budget original'!$A$2:$AO$501,MATCH($A65,'Budget original'!$A$2:$A$501,0),MATCH(F$2,'Budget original'!$A$2:$AO$2,0)) -> 202.5 | L65: =SUMIFS(BV_Data_An_Cour!$O:$O,BV_Data_An_Cour!$U:$U,$B65,BV_Data_An_Cour!$V:$V,$C65,BV_Data_An_Cour!$W:$W,L$2) -> 88.66 | N65: =L65-F65 -> -113.84 | Q65: {=+INDEX('Réel 2024'!$A$2:$AO$501,MATCH($A65,'Réel 2024'!$A$2:$A$501,0),MATCH(Q$2,'Réel 2024'!$A$2:$AO$2,0))} -> 242.21 | S65: =L65-Q65 -> -153.55
A66: =+B66&C66 -> Véhicules neufsDivers | B66: =+$K$1 -> Véhicules neufs | C66: Divers | F66: =+INDEX('Budget original'!$A$2:$AO$501,MATCH($A66,'Budget original'!$A$2:$A$501,0),MATCH(F$2,'Budget original'!$A$2:$AO$2,0)) -> 783.45 | L66: =SUMIFS(BV_Data_An_Cour!$O:$O,BV_Data_An_Cour!$U:$U,$B66,BV_Data_An_Cour!$V:$V,$C66,BV_Data_An_Cour!$W:$W,L$2) -> 203.99 | N66: =L66-F66 -> -579.46 | Q66: {=+INDEX('Réel 2024'!$A$2:$AO$501,MATCH($A66,'Réel 2024'!$A$2:$A$501,0),MATCH(Q$2,'Réel 2024'!$A$2:$AO$2,0))} -> 1075.41 | S66: =L66-Q66 -> -871.42
... A68: =+B68&C68 -> Véhicules neufsFrais bancaires | B68: =+$K$1 -> Véhicules neufs | C68: Frais bancaires | F68: =+INDEX('Budget original'!$A$2:$AO$501,MATCH($A68,'Budget original'!$A$2:$A$501,0),MATCH(F$2,'Budget original'!$A$2:$AO$2,0)) -> 2142.5664 | L68: =SUMIFS(BV_Data_An_Cour!$O:$O,BV_Data_An_Cour!$U:$U,$B68,BV_Data_An_Cour!$V:$V,$C68,BV_Data_An_Cour!$W:$W,L$2) -> 2301.85 | N68: =L68-F68 -> 159.28357 | Q68: {=+INDEX('Réel 2024'!$A$2:$AO$501,MATCH($A68,'Réel 2024'!$A$2:$A$501,0),MATCH(Q$2,'Réel 2024'!$A$2:$AO$2,0))} -> 2556.62 | S68: =L68-Q68 -> -254.77
A69: =+B69&C69 -> Véhicules neufs[...] | B69: =+$K$1 -> Véhicules neufs | C69: [...] | F69: =+INDEX('Budget original'!$A$2:$AO$501,MATCH($A69,'Budget original'!$A$2:$A$501,0),MATCH(F$2,'Budget original'!$A$2:$AO$2,0)) -> 0 | N69: =L69-F69 -> 0 | Q69: {=+INDEX('Réel 2024'!$A$2:$AO$501,MATCH($A69,'Réel 2024'!$A$2:$A$501,0),MATCH(Q$2,'Réel 2024'!$A$2:$AO$2,0))} -> 0 | S69: =L69-Q69 -> 0
A70: =+B70&C70 -> Véhicules neufs[...] | B70: =+$K$1 -> Véhicules neufs | C70: [...] | F70: =+INDEX('Budget original'!$A$2:$AO$501,MATCH($A70,'Budget original'!$A$2:$A$501,0),MATCH(F$2,'Budget original'!$A$2:$AO$2,0)) -> 0 | L70: =SUMIFS(BV_Data_An_Cour!$O:$O,BV_Data_An_Cour!$U:$U,$B70,BV_Data_An_Cour!$V:$V,$C70,BV_Data_An_Cour!$W:$W,L$2) -> 0 | N70: =L70-F70 -> 0 | Q70: {=+INDEX('Réel 2024'!$A$2:$AO$501,MATCH($A70,'Réel 2024'!$A$2:$A$501,0),MATCH(Q$2,'Réel 2024'!$A$2:$AO$2,0))} -> 0 | S70: =L70-Q70 -> 0
A71: =+B71&C71 -> Véhicules neufs[...] | B71: =+$K$1 -> Véhicules neufs | C71: [...] | F71: =+INDEX('Budget original'!$A$2:$AO$501,MATCH($A71,'Budget original'!$A$2:$A$501,0),MATCH(F$2,'Budget original'!$A$2:$AO$2,0)) -> 0 | L71: =SUMIFS(BV_Data_An_Cour!$O:$O,BV_Data_An_Cour!$U:$U,$B71,BV_Data_An_Cour!$V:$V,$C71,BV_Data_An_Cour!$W:$W,L$2)*0.32 -> 0 | N71: =L71-F71 -> 0 | Q71: {=+INDEX('Réel 2024'!$A$2:$AO$501,MATCH($A71,'Réel 2024'!$A$2:$A$501,0),MATCH(Q$2,'Réel 2024'!$A$2:$AO$2,0))} -> 0 | S71: =L71-Q71 -> 0
A72: =+B72&C72 -> Véhicules neufsTOTAL SEMI-FIXES | B72: =+$K$1 -> Véhicules neufs | C72: TOTAL SEMI-FIXES | D72: % brut | E72: =F72/F$27 -> 0.20508012 | F72: =+SUM(F55:F71) -> 20314.783 | J72: % brut | K72: =L72/L$27 -> 0.32735329 | L72: =+SUM(L55:L71) -> 16777.75 | N72: =+SUM(N55:N71) -> -3537.0333 | O72: % brut | P72: =Q72/Q$27 -> 0.14304939 | Q72: =+SUM(Q55:Q71) -> 25489.14 | S72: =+SUM(S55:S71) -> -8711.39
A73: =+B73&C73 -> Véhicules neufs | B73: =+$K$1 -> Véhicules neufs
A74: =+B74&C74 -> Véhicules neufsTOTAL DES DÉPENSES | B74: =+$K$1 -> Véhicules neufs | C74: TOTAL DES DÉPENSES | D74: % brut | E74: =F74/F$27 -> 1.3343615 | F74: =F41+F54+F72 -> 132178.9 | J74: % brut | K74: =L74/L$27 -> 1.8797682 | L74: =L41+L54+L72 -> 96343.25 | N74: =L74-F74 -> -35835.654 | O74: % brut | P74: =Q74/Q$27 -> 1.0016273 | Q74: =Q41+Q54+Q72 -> 178474.15 | S74: =L74-Q74 -> -82130.9
A75: =+B75&C75 -> Véhicules neufsRBSC neuf | B75: =+$K$1 -> Véhicules neufs | C75: RBSC neuf | F75: =+INDEX('Budget original'!$A$2:$AO$501,MATCH($A75,'Budget original'!$A$2:$A$501,0),MATCH(F$2,'Budget original'!$A$2:$AO$2,0)) -> 28493.202 | L75: =-SUMIFS(BV_Data_An_Cour!$O:$O,BV_Data_An_Cour!$U:$U,$B75,BV_Data_An_Cour!$V:$V,$C75,BV_Data_An_Cour!$W:$W,L$2) -> 20598 | N75: =L75-F75 -> -7895.2019 | Q75: =+INDEX('Réel 2024'!$A$2:$AO$501,MATCH($A75,'Réel 2024'!$A$2:$A$501,0),MATCH(Q$2,'Réel 2024'!$A$2:$AO$2,0)) -> 31920 | S75: =L75-Q75 -> -11322
A76: =+B76&C76 -> Véhicules neufsProgramme neuf 2 | B76: =+$K$1 -> Véhicules neufs | C76: Programme neuf 2 | F76: =+INDEX('Budget original'!$A$2:$AO$501,MATCH($A76,'Budget original'!$A$2:$A$501,0),MATCH(F$2,'Budget original'!$A$2:$AO$2,0)) -> 0 | L76: =-SUMIFS(BV_Data_An_Cour!$O:$O,BV_Data_An_Cour!$U:$U,$B76,BV_Data_An_Cour!$V:$V,$C76,BV_Data_An_Cour!$W:$W,L$2) -> 0 | N76: =L76-F76 -> 0 | Q76: {=+INDEX('Réel 2024'!$A$2:$AO$501,MATCH($A76,'Réel 2024'!$A$2:$A$501,0),MATCH(Q$2,'Réel 2024'!$A$2:$AO$2,0))} -> 0 | S76: =L76-Q76 -> 0
A77: =+B77&C77 -> Véhicules neufsProgramme neuf 3 | B77: =+$K$1 -> Véhicules neufs | C77: Programme neuf 3 | F77: =+INDEX('Budget original'!$A$2:$AO$501,MATCH($A77,'Budget original'!$A$2:$A$501,0),MATCH(F$2,'Budget original'!$A$2:$AO$2,0)) -> 0 | L77: =-SUMIFS(BV_Data_An_Cour!$O:$O,BV_Data_An_Cour!$U:$U,$B77,BV_Data_An_Cour!$V:$V,$C77,BV_Data_An_Cour!$W:$W,L$2) -> 0 | N77: =L77-F77 -> 0 | Q77: {=+INDEX('Réel 2024'!$A$2:$AO$501,MATCH($A77,'Réel 2024'!$A$2:$A$501,0),MATCH(Q$2,'Réel 2024'!$A$2:$AO$2,0))} -> 0 | S77: =L77-Q77 -> 0
A78: =+B78&C78 -> Véhicules neufsHoldbacks | B78: =+$K$1 -> Véhicules neufs | C78: Holdbacks | F78: =+INDEX('Budget original'!$A$2:$AO$501,MATCH($A78,'Budget original'!$A$2:$A$501,0),MATCH(F$2,'Budget original'!$A$2:$AO$2,0)) -> 30803.462 | L78: =-SUMIFS(BV_Data_An_Cour!$O:$O,BV_Data_An_Cour!$U:$U,$B78,BV_Data_An_Cour!$V:$V,$C78,BV_Data_An_Cour!$W:$W,L$2) -> 32718 | N78: =L78-F78 -> 1914.5385 | Q78: {=+INDEX('Réel 2024'!$A$2:$AO$501,MATCH($A78,'Réel 2024'!$A$2:$A$501,0),MATCH(Q$2,'Réel 2024'!$A$2:$AO$2,0))} -> 44065 | S78: =L78-Q78 -> -11347
A79: =+B79&C79 -> Véhicules neufs[...] | B79: =+$K$1 -> Véhicules neufs | C79: [...] | F79: =+INDEX('Budget original'!$A$2:$AO$501,MATCH($A79,'Budget original'!$A$2:$A$501,0),MATCH(F$2,'Budget original'!$A$2:$AO$2,0)) -> 0 | L79: =-SUMIFS(BV_Data_An_Cour!$O:$O,BV_Data_An_Cour!$U:$U,$B79,BV_Data_An_Cour!$V:$V,$C79,BV_Data_An_Cour!$W:$W,L$2) -> 0 | N79: =L79-F79 -> 0 | Q79: {=+INDEX('Réel 2024'!$A$2:$AO$501,MATCH($A79,'Réel 2024'!$A$2:$A$501,0),MATCH(Q$2,'Réel 2024'!$A$2:$AO$2,0))} -> 0 | S79: =L79-Q79 -> 0
A80: =+B80&C80 -> Véhicules neufs[...] | B80: =+$K$1 -> Véhicules neufs | C80: [...] | F80: =+INDEX('Budget original'!$A$2:$AO$501,MATCH($A80,'Budget original'!$A$2:$A$501,0),MATCH(F$2,'Budget original'!$A$2:$AO$2,0)) -> 0 | L80: =-SUMIFS(BV_Data_An_Cour!$O:$O,BV_Data_An_Cour!$U:$U,$B80,BV_Data_An_Cour!$V:$V,$C80,BV_Data_An_Cour!$W:$W,L$2) -> 0 | N80: =L80-F80 -> 0 | Q80: {=+INDEX('Réel 2024'!$A$2:$AO$501,MATCH($A80,'Réel 2024'!$A$2:$A$501,0),MATCH(Q$2,'Réel 2024'!$A$2:$AO$2,0))} -> 0 | S80: =L80-Q80 -> 0
A81: =+B81&C81 -> Véhicules neufs[...] | B81: =+$K$1 -> Véhicules neufs | C81: [...] | F81: =+INDEX('Budget original'!$A$2:$AO$501,MATCH($A81,'Budget original'!$A$2:$A$501,0),MATCH(F$2,'Budget original'!$A$2:$AO$2,0)) -> 0 | L81: =-SUMIFS(BV_Data_An_Cour!$O:$O,BV_Data_An_Cour!$U:$U,$B81,BV_Data_An_Cour!$V:$V,$C81,BV_Data_An_Cour!$W:$W,L$2) -> 0 | N81: =L81-F81 -> 0 | Q81: {=+INDEX('Réel 2024'!$A$2:$AO$501,MATCH($A81,'Réel 2024'!$A$2:$A$501,0),MATCH(Q$2,'Réel 2024'!$A$2:$AO$2,0))} -> 0 | S81: =L81-Q81 -> 0
A82: =+B82&C82 -> Véhicules neufsFrais administration | B82: =+$K$1 -> Véhicules neufs | C82: Frais administration | F82: =+INDEX('Budget original'!$A$2:$AO$501,MATCH($A82,'Budget original'!$A$2:$A$501,0),MATCH(F$2,'Budget original'!$A$2:$AO$2,0)) -> 10549.35 | L82: =-SUMIFS(BV_Data_An_Cour!$O:$O,BV_Data_An_Cour!$U:$U,$B82,BV_Data_An_Cour!$V:$V,$C82,BV_Data_An_Cour!$W:$W,L$2) -> 4165 | N82: =L82-F82 -> -6384.35 | Q82: {=+INDEX('Réel 2024'!$A$2:$AO$501,MATCH($A82,'Réel 2024'!$A$2:$A$501,0),MATCH(Q$2,'Réel 2024'!$A$2:$AO$2,0))} -> 14875 | S82: =L82-Q82 -> -10710 | V82: =L82/595 -> 7 | W82: =V82/J27 -> 0.58333333
A83: =+B83&C83 -> Véhicules neufsAUTRES REVENUS | B83: =+$K$1 -> Véhicules neufs | C83: AUTRES REVENUS | F83: =+SUM(F75:F82) -> 69846.013 | L83: =+SUM(L75:L82) -> 57481 | N83: =+SUM(N75:N82) -> -12365.013 | Q83: =+SUM(Q75:Q82) -> 90860 | S83: =+SUM(S75:S82) -> -33379
A84: =+B84&C84 -> Véhicules neufs | B84: =+$K$1 -> Véhicules neufs
A85: =+B85&C85 -> Véhicules neufsPROFIT DÉPARTEMENTAL | B85: =+$K$1 -> Véhicules neufs | C85: PROFIT DÉPARTEMENTAL | F85: =F27-F74+F83 -> 36724.9 | L85: =L27-L74+L83 -> 12390.48 | N85: =N27-N41-N54-N72+N83 -> -24334.42 | Q85: =Q27-Q74+Q83 -> 90570.04 | S85: =S27-S41-S54-S72+S83 -> -78179.56
C89: =C1 -> BMW Sherbrooke | K89: Véhicules usagés | S89: =$S$1 -> Réalisé, Décembre 2025
D91: BUDGET ORIGINAL | J91: RÉALISATION | M91: ÉCART réel / Budget | O91: ANNÉE PRÉCÉDENTE | R91: ECART (réel/ Ann.Préc.)
D92: UNITE | E92: $P/UNITÉ | F92: $PROFITS | J92: UNITE | K92: $P/UNITE | L92: $PROFITS | M92: UNFTÉ | N92: $PROFFTS | O92: UNITE | P92: $P/UNITÉ | Q92: $PROFITS | R92: UNITE | S92: $PROFITS
A93: =+B93&C93 -> Véhicules usagésVentes nettes | B93: Véhicules usagés | C93: Ventes nettes | F93: =+INDEX('Budget original'!$A$2:$AO$501,MATCH($A93,'Budget original'!$A$2:$A$501,0),MATCH(F$2,'Budget original'!$A$2:$AO$2,0)) -> 886117.65 | L93: =-SUMIFS(BV_Data_An_Cour!$O:$O,BV_Data_An_Cour!$X:$X,"Oui",BV_Data_An_Cour!$U:$U,$B93) -> 324028.28 | Q93: {=+INDEX('Réel 2024'!$A$2:$AO$501,MATCH($A93,'Réel 2024'!$A$2:$A$501,0),MATCH(Q$2,'Réel 2024'!$A$2:$AO$2,0))} -> 1409394.1
A94: =+B94&C94 -> Véhicules usagésCertifié | B94: Véhicules usagés | C94: Certifié | D94: =+INDEX('Budget original'!$A$2:$AO$501,MATCH($A94,'Budget original'!$A$2:$A$501,0),MATCH(D$2,'Budget original'!$A$2:$AO$2,0)) -> 4 | E94: =IF(D94=0,0,F94/D94) -> 2300 | F94: =+INDEX('Budget original'!$A$2:$AO$501,MATCH($A94,'Budget original'!$A$2:$A$501,0),MATCH(F$2,'Budget original'!$A$2:$AO$2,0)) -> 9200 | J94: =-SUMIFS(BV_Data_An_Cour!$O:$O,BV_Data_An_Cour!$U:$U,$B94,BV_Data_An_Cour!$V:$V,$C94,BV_Data_An_Cour!$W:$W,J$2) -> 3 | K94: =IF(J94=0,0,L94/J94) -> 1877.2533 | L94: =-SUMIFS(BV_Data_An_Cour!$O:$O,BV_Data_An_Cour!$U:$U,$B94,BV_Data_An_Cour!$V:$V,$C94,BV_Data_An_Cour!$W:$W,$L2) -> 5631.76 | M94: =J94-D94 -> -1 | N94: =L94-F94 -> -3568.24 | O94: {=+INDEX('Réel 2024'!$A$2:$AO$501,MATCH($A94,'Réel 2024'!$A$2:$A$501,0),MATCH(O$2,'Réel 2024'!$A$2:$AO$2,0))} -> 5 | P94: =IF(O94=0,0,Q94/O94) -> 2218.59 | Q94: {=+INDEX('Réel 2024'!$A$2:$AO$501,MATCH($A94,'Réel 2024'!$A$2:$A$501,0),MATCH(Q$2,'Réel 2024'!$A$2:$AO$2,0))} -> 11092.95 | R94: =J94-O94 -> -2 | S94: =L94-Q94 -> -5461.19
A95: =+B95&C95 -> Véhicules usagésNon Certifié | B95: Véhicules usagés | C95: Non Certifié | D95: =+INDEX('Budget original'!$A$2:$AO$501,MATCH($A95,'Budget original'!$A$2:$A$501,0),MATCH(D$2,'Budget original'!$A$2:$AO$2,0)) -> 4 | E95: =IF(D95=0,0,F95/D95) -> 1600 | F95: =+INDEX('Budget original'!$A$2:$AO$501,MATCH($A95,'Budget original'!$A$2:$A$501,0),MATCH(F$2,'Budget original'!$A$2:$AO$2,0)) -> 6400 | J95: =-SUMIFS(BV_Data_An_Cour!$O:$O,BV_Data_An_Cour!$U:$U,$B95,BV_Data_An_Cour!$V:$V,$C95,BV_Data_An_Cour!$W:$W,J$2) -> 2 | K95: =IF(J95=0,0,L95/J95) -> 968.675 | L95: =-SUMIFS(BV_Data_An_Cour!$O:$O,BV_Data_An_Cour!$U:$U,$B95,BV_Data_An_Cour!$V:$V,$C95,BV_Data_An_Cour!$W:$W,$L2) -> 1937.35 | M95: =J95-D95 -> -2 | N95: =L95-F95 -> -4462.65 | O95: {=+INDEX('Réel 2024'!$A$2:$AO$501,MATCH($A95,'Réel 2024'!$A$2:$A$501,0),MATCH(O$2,'Réel 2024'!$A$2:$AO$2,0))} -> 7 | P95: =IF(O95=0,0,Q95/O95) -> -183.16857 | Q95: {=+INDEX('Réel 2024'!$A$2:$AO$501,MATCH($A95,'Réel 2024'!$A$2:$A$501,0),MATCH(Q$2,'Réel 2024'!$A$2:$AO$2,0))} -> -1282.18 | R95: =J95-O95 -> -5 | S95: =L95-Q95 -> 3219.53
A96: =+B96&C96 -> Véhicules usagésAutres marques | B96: Véhicules usagés | C96: Autres marques | D96: =+INDEX('Budget original'!$A$2:$AO$501,MATCH($A96,'Budget original'!$A$2:$A$501,0),MATCH(D$2,'Budget original'!$A$2:$AO$2,0)) -> 4 | E96: =IF(D96=0,0,F96/D96) -> 1500 | F96: =+INDEX('Budget original'!$A$2:$AO$501,MATCH($A96,'Budget original'!$A$2:$A$501,0),MATCH(F$2,'Budget original'!$A$2:$AO$2,0)) -> 6000 | J96: =-SUMIFS(BV_Data_An_Cour!$O:$O,BV_Data_An_Cour!$U:$U,$B96,BV_Data_An_Cour!$V:$V,$C96,BV_Data_An_Cour!$W:$W,J$2) -> 0 | K96: =IF(J96=0,0,L96/J96) -> 0 | L96: =-SUMIFS(BV_Data_An_Cour!$O:$O,BV_Data_An_Cour!$U:$U,$B96,BV_Data_An_Cour!$V:$V,$C96,BV_Data_An_Cour!$W:$W,$L2) -> 0 | M96: =J96-D96 -> -4 | N96: =L96-F96 -> -6000 | O96: =+INDEX('Réel 2024'!$A$2:$AO$501,MATCH($A96,'Réel 2024'!$A$2:$A$501,0),MATCH(O$2,'Réel 2024'!$A$2:$AO$2,0)) -> 1 | P96: =IF(O96=0,0,Q96/O96) -> 500 | Q96: =+INDEX('Réel 2024'!$A$2:$AO$501,MATCH($A96,'Réel 2024'!$A$2:$A$501,0),MATCH(Q$2,'Réel 2024'!$A$2:$AO$2,0)) -> 500 | R96: =J96-O96 -> -1 | S96: =L96-Q96 -> -500
A97: =+B97&C97 -> Véhicules usagésTotal Usagés | B97: Véhicules usagés | C97: Total Usagés | D97: =+D95+D94+D96 -> 12 | E97: =IF(D97=0,0,F97/D97) -> 1800 | F97: =+F94+F95+F96 -> 21600 | J97: =+J94+J95+J96 -> 5 | K97: =IF(J97<=0,0,L97/J97) -> 1513.822 | L97: =+L94+L95+L96 -> 7569.11 | M97: =J97-D97 -> -7 | N97: =L97-F97 -> -14030.89 | O97: =+O95+O94+O96 -> 13 | P97: =IF(O97=0,0,Q97/O97) -> 793.13615 | Q97: =+Q94+Q95+Q96 -> 10310.77 | R97: =J97-O97 -> -8 | S97: =L97-Q97 -> -2741.66
A98: =+B98&C98 -> Véhicules usagés | B98: Véhicules usagés | M98: =M97/D97 -> -0.58333333 | N98: =N97/F97 -> -0.64957824 | R98: =R97/O97 -> -0.61538462 | S98: =IF(Q97=0,0,(S97/Q97)) -> -0.26590255
A99: =+B99&C99 -> Véhicules usagés | B99: Véhicules usagés
A100: =+B100&C100 -> Véhicules usagésVentes au Gros | B100: Véhicules usagés | C100: Ventes au Gros | D100: =+INDEX('Budget original'!$A$2:$AO$501,MATCH($A100,'Budget original'!$A$2:$A$501,0),MATCH(D$2,'Budget original'!$A$2:$AO$2,0)) -> 11 | E100: =IF(D100=0,0,F100/D100) -> 350 | F100: =+INDEX('Budget original'!$A$2:$AO$501,MATCH($A100,'Budget original'!$A$2:$A$501,0),MATCH(F$2,'Budget original'!$A$2:$AO$2,0)) -> 3850 | J100: =-SUMIFS(BV_Data_An_Cour!$O:$O,BV_Data_An_Cour!$U:$U,$B100,BV_Data_An_Cour!$V:$V,$C100,BV_Data_An_Cour!$W:$W,J$2) -> 2 | K100: =IF(J100=0,0,L100/J100) -> 788.05 | L100: =-SUMIFS(BV_Data_An_Cour!$O:$O,BV_Data_An_Cour!$U:$U,$B100,BV_Data_An_Cour!$V:$V,$C100,BV_Data_An_Cour!$W:$W,L$2) -> 1576.1 | M100: =J100-D100 -> -9 | N100: =L100-F100 -> -2273.9 | O100: {=+INDEX('Réel 2024'!$A$2:$AO$501,MATCH($A100,'Réel 2024'!$A$2:$A$501,0),MATCH(O$2,'Réel 2024'!$A$2:$AO$2,0))} -> 23 | P100: =IF(O100=0,0,Q100/O100) -> 509.69087 | Q100: {=+INDEX('Réel 2024'!$A$2:$AO$501,MATCH($A100,'Réel 2024'!$A$2:$A$501,0),MATCH(Q$2,'Réel 2024'!$A$2:$AO$2,0))} -> 11722.89 | R100: =J100-O100 -> -21 | S100: =L100-Q100 -> -10146.79
A101: =+B101&C101 -> Véhicules usagés | B101: Véhicules usagés
A102: =+B102&C102 -> Véhicules usagésRev. Finances | B102: Véhicules usagés | C102: Rev. Finances | D102: =+INDEX('Budget original'!$A$2:$AO$501,MATCH($A102,'Budget original'!$A$2:$A$501,0),MATCH(D$2,'Budget original'!$A$2:$AO$2,0)) -> 0 | E102: =IF(D102=0,0,F102/D102) -> 0 | F102: =+INDEX('Budget original'!$A$2:$AO$501,MATCH($A102,'Budget original'!$A$2:$A$501,0),MATCH(F$2,'Budget original'!$A$2:$AO$2,0)) -> 4560 | K102: =IF(J97=0,0,L102/J97) -> 648.386 | L102: =-SUMIFS(BV_Data_An_Cour!$O:$O,BV_Data_An_Cour!$U:$U,$B102,BV_Data_An_Cour!$V:$V,$C102,BV_Data_An_Cour!$W:$W,$L2) -> 3241.93 | N102: =L102-F102 -> -1318.07 | Q102: {=+INDEX('Réel 2024'!$A$2:$AO$501,MATCH($A102,'Réel 2024'!$A$2:$A$501,0),MATCH(Q$2,'Réel 2024'!$A$2:$AO$2,0))} -> 2962.76 | R102: =O102-K102 -> -648.386 | S102: =L102-Q102 -> 279.17
A103: =+B103&C103 -> Véhicules usagésRev. Protections | B103: Véhicules usagés | C103: Rev. Protections | D103: =+INDEX('Budget original'!$A$2:$AO$501,MATCH($A103,'Budget original'!$A$2:$A$501,0),MATCH(D$2,'Budget original'!$A$2:$AO$2,0)) -> 0 | E103: =IF(D103=0,0,F103/D103) -> 0 | F103: =+INDEX('Budget original'!$A$2:$AO$501,MATCH($A103,'Budget original'!$A$2:$A$501,0),MATCH(F$2,'Budget original'!$A$2:$AO$2,0)) -> 10200 | K103: =IF(J97=0,0,L103/J97) -> 2259.6 | L103: =-SUMIFS(BV_Data_An_Cour!$O:$O,BV_Data_An_Cour!$U:$U,$B103,BV_Data_An_Cour!$V:$V,$C103,BV_Data_An_Cour!$W:$W,$L2) -> 11298 | N103: =L103-F103 -> 1098 | Q103: {=+INDEX('Réel 2024'!$A$2:$AO$501,MATCH($A103,'Réel 2024'!$A$2:$A$501,0),MATCH(Q$2,'Réel 2024'!$A$2:$AO$2,0))} -> 13963.1 | R103: =O103-K103 -> -2259.6 | S103: =L103-Q103 -> -2665.1
A104: =+B104&C104 -> Véhicules usagésRev. Autres | B104: Véhicules usagés | C104: Rev. Autres | D104: =+INDEX('Budget original'!$A$2:$AO$501,MATCH($A104,'Budget original'!$A$2:$A$501,0),MATCH(D$2,'Budget original'!$A$2:$AO$2,0)) -> 0 | E104: =IF(D104=0,0,F104/D104) -> 0 | F104: =+INDEX('Budget original'!$A$2:$AO$501,MATCH($A104,'Budget original'!$A$2:$A$501,0),MATCH(F$2,'Budget original'!$A$2:$AO$2,0)) -> 2640 | K104: =IF(J97=0,0,L104/J97) -> 387.6 | L104: =-SUMIFS(BV_Data_An_Cour!$O:$O,BV_Data_An_Cour!$U:$U,$B104,BV_Data_An_Cour!$V:$V,$C104,BV_Data_An_Cour!$W:$W,$L$2) -> 1938 | N104: =L104-F104 -> -702 | Q104: {=+INDEX('Réel 2024'!$A$2:$AO$501,MATCH($A104,'Réel 2024'!$A$2:$A$501,0),MATCH(Q$2,'Réel 2024'!$A$2:$AO$2,0))} -> 1645 | R104: =O104-K104 -> -387.6 | S104: =L104-Q104 -> 293
A105: =+B105&C105 -> Véhicules usagésTotal F&I | B105: Véhicules usagés | C105: Total F&I | D105: =D97 -> 12 | E105: =IF(D105=0,0,F105/D105) -> 1450 | F105: =F102+F103+F104 -> 17400 | J105: =J97 -> 5 | K105: =IF(J105<=0,0,L105/J105) -> 3295.586 | L105: =L102+L103+L104 -> 16477.93 | M105: =J105-D105 -> -7 | N105: =L105-F105 -> -922.07 | O105: =O97 -> 13 | P105: =IF(O105=0,0,Q105/O105) -> 1428.5277 | Q105: =Q102+Q103+Q104 -> 18570.86 | S105: =L105-Q105 -> -2092.93
...

Sheet Print_AAD
C1: =Parametres!B1 -> BMW Sherbrooke | K1: Véhicules neufs | S1: =CONCATENATE("Réalisé,"," ",Parametres!B3," ",Parametres!B4," AAD") -> Réalisé, Décembre 2025 AAD
D2: X | E2: O | F2: U | J2: NB | L2: $ | O2: X | P2: O | Q2: U | X2: X | Y2: O | Z2: U | AJ2: X | AK2: O | AL2: U
D3: BUDGET ORIGINAL | J3: RÉALISATION | M3: ÉCART réel / Budget | O3: ANNÉE PRÉCÉDENTE | R3: ECART (réel/ Ann.Préc.)
D4: UNITE | E4: $P/UNITÉ | F4: $PROFITS | J4: UNITE | K4: $P/UNITE | L4: $PROFITS | M4: UNFTÉ | N4: $PROFITS | O4: UNITE | P4: $P/UNITÉ | Q4: $PROFITS | R4: UNITE | S4: $PROFITS
A5: =+B5&C5 -> Véhicules neufsVentes nettes | B5: =+$K$1 -> Véhicules neufs | C5: Ventes nettes | F5: {=+SUMPRODUCT(('Budget original'!$A$8:$A$501=$A5)*('Budget original'!$C$3:$AO$3=F$2),'Budget original'!$C$8:$AO$501)} -> 25300742 | L5: =-SUMIFS(BV_Data_An_Cour!$P:$P,BV_Data_An_Cour!$X:$X,"Oui",BV_Data_An_Cour!$U:$U,$B5) -> 1337137.4 | Q5: {=+SUMPRODUCT(('Réel 2024'!$A$8:$A$501=$A5)*('Réel 2024'!$C$3:$AO$3=Q$2),'Réel 2024'!$C$8:$AO$501)} -> 25487207
A6: =+B6&C6 -> Véhicules neufsAutos détail | B6: =+$K$1 -> Véhicules neufs | C6: Autos détail | D6: {=+SUMPRODUCT(('Budget original'!$A$8:$A$501=$A6)*('Budget original'!$C$3:$AO$3=D$2),'Budget original'!$C$8:$AO$501)} -> 86 | E6: =IF(D6=0,0,F6/D6) -> 4306.3953 | F6: {=+SUMPRODUCT(('Budget original'!$A$8:$A$501=$A6)*('Budget original'!$C$3:$AO$3=F$2),'Budget original'!$C$8:$AO$501)} -> 370350 | J6: =-SUMIFS(BV_Data_An_Cour!$P:$P,BV_Data_An_Cour!$U:$U,$B6,BV_Data_An_Cour!$V:$V,$C6,BV_Data_An_Cour!$W:$W,J$2) -> 2 | K6: =IF(J6=0,0,L6/J6) -> 4989.53 | L6: =-SUMIFS(BV_Data_An_Cour!$P:$P,BV_Data_An_Cour!$U:$U,$B6,BV_Data_An_Cour!$V:$V,$C6,BV_Data_An_Cour!$W:$W,L$2) -> 9979.06 | M6: =J6-D6 -> -84 | N6: =L6-F6 -> -360370.94 | O6: {=+SUMPRODUCT(('Réel 2024'!$A$8:$A$501=$A6)*('Réel 2024'!$C$3:$AO$3=O$2),'Réel 2024'!$C$8:$AO$501)} -> 87 | P6: =IF(O6=0,0,Q6/O6) -> 5158.778 | Q6: {=+SUMPRODUCT(('Réel 2024'!$A$8:$A$501=$A6)*('Réel 2024'!$C$3:$AO$3=Q$2),'Réel 2024'!$C$8:$AO$501)} -> 448813.69 | R6: =J6-O6 -> -85 | S6: =L6-Q6 -> -438834.63
A7: =+B7&C7 -> Véhicules neufsCamions détail | B7: =+$K$1 -> Véhicules neufs | C7: Camions détail | D7: {=+SUMPRODUCT(('Budget original'!$A$8:$A$501=$A7)*('Budget original'!$C$3:$AO$3=D$2),'Budget original'!$C$8:$AO$501)} -> 151 | E7: =IF(D7=0,0,F7/D7) -> 4000.3311 | F7: {=+SUMPRODUCT(('Budget original'!$A$8:$A$501=$A7)*('Budget original'!$C$3:$AO$3=F$2),'Budget original'!$C$8:$AO$501)} -> 604050 | J7: =-SUMIFS(BV_Data_An_Cour!$P:$P,BV_Data_An_Cour!$U:$U,$B7,BV_Data_An_Cour!$V:$V,$C7,BV_Data_An_Cour!$W:$W,J$2) -> 6 | K7: =IF(J7=0,0,L7/J7) -> 3057.8933 | L7: =-SUMIFS(BV_Data_An_Cour!$P:$P,BV_Data_An_Cour!$U:$U,$B7,BV_Data_An_Cour!$V:$V,$C7,BV_Data_An_Cour!$W:$W,L$2) -> 18347.36 | M7: =J7-D7 -> -145 | N7: =L7-F7 -> -585702.64 | O7: {=+SUMPRODUCT(('Réel 2024'!$A$8:$A$501=$A7)*('Réel 2024'!$C$3:$AO$3=O$2),'Réel 2024'!$C$8:$AO$501)} -> 142 | P7: =IF(O7=0,0,Q7/O7) -> 4574.8696 | Q7: {=+SUMPRODUCT(('Réel 2024'!$A$8:$A$501=$A7)*('Réel 2024'!$C$3:$AO$3=Q$2),'Réel 2024'!$C$8:$AO$501)} -> 649631.49 | R7: =J7-O7 -> -136 | S7: =L7-Q7 -> -631284.13
A8: =+B8&C8 -> Véhicules neufsSprinter | B8: =+$K$1 -> Véhicules neufs | C8: Sprinter | D8: {=+SUMPRODUCT(('Budget original'!$A$8:$A$501=$A8)*('Budget original'!$C$3:$AO$3=D$2),'Budget original'!$C$8:$AO$501)} -> 0 | E8: =IF(D8=0,0,F8/D8) -> 0 | F8: {=+SUMPRODUCT(('Budget original'!$A$8:$A$501=$A8)*('Budget original'!$C$3:$AO$3=F$2),'Budget original'!$C$8:$AO$501)} -> 0 | J8: =-SUMIFS(BV_Data_An_Cour!$P:$P,BV_Data_An_Cour!$U:$U,$B8,BV_Data_An_Cour!$V:$V,$C8,BV_Data_An_Cour!$W:$W,J$2) -> 0 | K8: =IF(J8=0,0,L8/J8) -> 0 | L8: =-SUMIFS(BV_Data_An_Cour!$P:$P,BV_Data_An_Cour!$U:$U,$B8,BV_Data_An_Cour!$V:$V,$C8,BV_Data_An_Cour!$W:$W,L$2) -> 0 | M8: =J8-D8 -> 0 | N8: =L8-F8 -> 0 | O8: {=+SUMPRODUCT(('Réel 2024'!$A$8:$A$501=$A8)*('Réel 2024'!$C$3:$AO$3=O$2),'Réel 2024'!$C$8:$AO$501)} -> 0 | P8: =IF(O8=0,0,Q8/O8) -> 0 | Q8: {=+SUMPRODUCT(('Réel 2024'!$A$8:$A$501=$A8)*('Réel 2024'!$C$3:$AO$3=Q$2),'Réel 2024'!$C$8:$AO$501)} -> 0 | R8: =J8-O8 -> 0 | S8: =L8-Q8 -> 0
A9: =+B9&C9 -> Véhicules neufsMoto détail | B9: =+$K$1 -> Véhicules neufs | C9: Moto détail | D9: {=+SUMPRODUCT(('Budget original'!$A$8:$A$501=$A9)*('Budget original'!$C$3:$AO$3=D$2),'Budget original'!$C$8:$AO$501)} -> 0 | E9: =IF(D9=0,0,F9/D9) -> 0 | F9: {=+SUMPRODUCT(('Budget original'!$A$8:$A$501=$A9)*('Budget original'!$C$3:$AO$3=F$2),'Budget original'!$C$8:$AO$501)} -> 0 | J9: =-SUMIFS(BV_Data_An_Cour!$P:$P,BV_Data_An_Cour!$U:$U,$B9,BV_Data_An_Cour!$V:$V,$C9,BV_Data_An_Cour!$W:$W,J$2) -> 0 | K9: =IF(J9=0,0,L9/J9) -> 0 | L9: =-SUMIFS(BV_Data_An_Cour!$P:$P,BV_Data_An_Cour!$U:$U,$B9,BV_Data_An_Cour!$V:$V,$C9,BV_Data_An_Cour!$W:$W,L$2) -> 0 | M9: =J9-D9 -> 0 | N9: =L9-F9 -> 0 | O9: {=+SUMPRODUCT(('Réel 2024'!$A$8:$A$501=$A9)*('Réel 2024'!$C$3:$AO$3=O$2),'Réel 2024'!$C$8:$AO$501)} -> 0 | P9: =IF(O9=0,0,Q9/O9) -> 0 | Q9: {=+SUMPRODUCT(('Réel 2024'!$A$8:$A$501=$A9)*('Réel 2024'!$C$3:$AO$3=Q$2),'Réel 2024'!$C$8:$AO$501)} -> 0 | R9: =J9-O9 -> 0 | S9: =L9-Q9 -> 0
A10: =+B10&C10 -> Véhicules neufs[...] | B10: =+$K$1 -> Véhicules neufs | C10: [...] | D10: {=+SUMPRODUCT(('Budget original'!$A$8:$A$501=$A10)*('Budget original'!$C$3:$AO$3=D$2),'Budget original'!$C$8:$AO$501)} -> 0 | E10: =IF(D10=0,0,F10/D10) -> 0 | F10: {=+SUMPRODUCT(('Budget original'!$A$8:$A$501=$A10)*('Budget original'!$C$3:$AO$3=F$2),'Budget original'!$C$8:$AO$501)} -> 0 | J10: =-SUMIFS(BV_Data_An_Cour!$P:$P,BV_Data_An_Cour!$U:$U,$B10,BV_Data_An_Cour!$V:$V,$C10,BV_Data_An_Cour!$W:$W,J$2) -> 0 | K10: =IF(J10=0,0,L10/J10) -> 0 | L10: =-SUMIFS(BV_Data_An_Cour!$P:$P,BV_Data_An_Cour!$U:$U,$B10,BV_Data_An_Cour!$V:$V,$C10,BV_Data_An_Cour!$W:$W,L$2) -> 0 | M10: =J10-D10 -> 0 | N10: =L10-F10 -> 0 | O10: {=+SUMPRODUCT(('Réel 2024'!$A$8:$A$501=$A10)*('Réel 2024'!$C$3:$AO$3=O$2),'Réel 2024'!$C$8:$AO$501)} -> 0 | P10: =IF(O10=0,0,Q10/O10) -> 0 | Q10: {=+SUMPRODUCT(('Réel 2024'!$A$8:$A$501=$A10)*('Réel 2024'!$C$3:$AO$3=Q$2),'Réel 2024'!$C$8:$AO$501)} -> 0 | R10: =J10-O10 -> 0 | S10: =L10-Q10 -> 0
A11: =+B11&C11 -> Véhicules neufs[...] | B11: =+$K$1 -> Véhicules neufs | C11: [...] | D11: {=+SUMPRODUCT(('Budget original'!$A$8:$A$501=$A11)*('Budget original'!$C$3:$AO$3=D$2),'Budget original'!$C$8:$AO$501)} -> 0 | E11: =IF(D11=0,0,F11/D11) -> 0 | F11: {=+SUMPRODUCT(('Budget original'!$A$8:$A$501=$A11)*('Budget original'!$C$3:$AO$3=F$2),'Budget original'!$C$8:$AO$501)} -> 0 | J11: =-SUMIFS(BV_Data_An_Cour!$P:$P,BV_Data_An_Cour!$U:$U,$B11,BV_Data_An_Cour!$V:$V,$C11,BV_Data_An_Cour!$W:$W,J$2) -> 0 | K11: =IF(J11=0,0,L11/J11) -> 0 | L11: =-SUMIFS(BV_Data_An_Cour!$P:$P,BV_Data_An_Cour!$U:$U,$B11,BV_Data_An_Cour!$V:$V,$C11,BV_Data_An_Cour!$W:$W,L$2) -> 0 | M11: =J11-D11 -> 0 | N11: =L11-F11 -> 0 | O11: {=+SUMPRODUCT(('Réel 2024'!$A$8:$A$501=$A11)*('Réel 2024'!$C$3:$AO$3=O$2),'Réel 2024'!$C$8:$AO$501)} -> 0 | P11: =IF(O11=0,0,Q11/O11) -> 0 | Q11: {=+SUMPRODUCT(('Réel 2024'!$A$8:$A$501=$A11)*('Réel 2024'!$C$3:$AO$3=Q$2),'Réel 2024'!$C$8:$AO$501)} -> 0 | R11: =J11-O11 -> 0 | S11: =L11-Q11 -> 0
A12: =+B12&C12 -> Véhicules neufs[...] | B12: =+$K$1 -> Véhicules neufs | C12: [...] | D12: {=+SUMPRODUCT(('Budget original'!$A$8:$A$501=$A12)*('Budget original'!$C$3:$AO$3=D$2),'Budget original'!$C$8:$AO$501)} -> 0 | E12: =IF(D12=0,0,F12/D12) -> 0 | F12: {=+SUMPRODUCT(('Budget original'!$A$8:$A$501=$A12)*('Budget original'!$C$3:$AO$3=F$2),'Budget original'!$C$8:$AO$501)} -> 0 | J12: =-SUMIFS(BV_Data_An_Cour!$P:$P,BV_Data_An_Cour!$U:$U,$B12,BV_Data_An_Cour!$V:$V,$C12,BV_Data_An_Cour!$W:$W,J$2) -> 0 | K12: =IF(J12=0,0,L12/J12) -> 0 | L12: =-SUMIFS(BV_Data_An_Cour!$P:$P,BV_Data_An_Cour!$U:$U,$B12,BV_Data_An_Cour!$V:$V,$C12,BV_Data_An_Cour!$W:$W,L$2) -> 0 | M12: =J12-D12 -> 0 | N12: =L12-F12 -> 0 | O12: {=+SUMPRODUCT(('Réel 2024'!$A$8:$A$501=$A12)*('Réel 2024'!$C$3:$AO$3=O$2),'Réel 2024'!$C$8:$AO$501)} -> 0 | P12: =IF(O12=0,0,Q12/O12) -> 0 | Q12: {=+SUMPRODUCT(('Réel 2024'!$A$8:$A$501=$A12)*('Réel 2024'!$C$3:$AO$3=Q$2),'Réel 2024'!$C$8:$AO$501)} -> 0 | R12: =J12-O12 -> 0 | S12: =L12-Q12 -> 0
A13: =+B13&C13 -> Véhicules neufsTotal Neufs | B13: =+$K$1 -> Véhicules neufs | C13: Total Neufs | D13: =+SUM(D6:D12) -> 237 | E13: =IF(D13<=0,0,F13/D13) -> 4111.3924 | F13: =+SUM(F6:F12) -> 974400 | J13: =+SUM(J6:J12) -> 8 | K13: =IF(J13<=0,0,L13/J13) -> 3540.8025 | L13: =+SUM(L6:L12) -> 28326.42 | M13: =+SUM(M6:M12) -> -229 | N13: =+SUM(N6:N12) -> -946073.58 | O13: =+SUM(O6:O12) -> 229 | P13: =IF(O13<=0,0,Q13/O13) -> 4796.7038 | Q13: =+SUM(Q6:Q12) -> 1098445.2 | R13: =+SUM(R6:R12) -> -221 | S13: =+SUM(S6:S12) -> -1070118.8
A14: =+B14&C14 -> Véhicules neufs | B14: =+$K$1 -> Véhicules neufs | M14: =IF(D13=0,0,M13/D13) -> -0.96624473 | N14: =IF(F13=0,0,N13/F13) -> -0.97092937 | R14: =R13/O13 -> -0.9650655 | S14: =IF(Q13=0,0,(S13/Q13)) -> -0.97421226
A15: =+B15&C15 -> Véhicules neufsEx-Démos et courtoisies | B15: =+$K$1 -> Véhicules neufs | C15: Ex-Démos et courtoisies | D15: {=+SUMPRODUCT(('Budget original'!$A$8:$A$501=$A15)*('Budget original'!$C$3:$AO$3=D$2),'Budget original'!$C$8:$AO$501)} -> 35 | E15: =IF(D15=0,0,F15/D15) -> 750 | F15: {=+SUMPRODUCT(('Budget original'!$A$8:$A$501=$A15)*('Budget original'!$C$3:$AO$3=F$2),'Budget original'!$C$8:$AO$501)} -> 26250 | J15: =-SUMIFS(BV_Data_An_Cour!$P:$P,BV_Data_An_Cour!$U:$U,$B15,BV_Data_An_Cour!$V:$V,$C15,BV_Data_An_Cour!$W:$W,J$2) -> 0 | K15: =IF(J15=0,0,L15/J15) -> 0 | L15: =-SUMIFS(BV_Data_An_Cour!$P:$P,BV_Data_An_Cour!$U:$U,$B15,BV_Data_An_Cour!$V:$V,$C15,BV_Data_An_Cour!$W:$W,L$2) -> 0 | M15: =J15-D15 -> -35 | N15: =L15-F15 -> -26250 | O15: {=+SUMPRODUCT(('Réel 2024'!$A$8:$A$501=$A15)*('Réel 2024'!$C$3:$AO$3=O$2),'Réel 2024'!$C$8:$AO$501)} -> 36 | P15: =IF(O15=0,0,Q15/O15) -> 1369.8803 | Q15: {=+SUMPRODUCT(('Réel 2024'!$A$8:$A$501=$A15)*('Réel 2024'!$C$3:$AO$3=Q$2),'Réel 2024'!$C$8:$AO$501)} -> 49315.69 | R15: =J15-O15 -> -36 | S15: =L15-Q15 -> -49315.69
A16: =+B16&C16 -> Véhicules neufs | B16: =+$K$1 -> Véhicules neufs
A17: =+B17&C17 -> Véhicules neufsFlottes | B17: =+$K$1 -> Véhicules neufs | C17: Flottes | D17: {=+SUMPRODUCT(('Budget original'!$A$8:$A$501=$A17)*('Budget original'!$C$3:$AO$3=D$2),'Budget original'!$C$8:$AO$501)} -> 3 | E17: =IF(D17=0,0,F17/D17) -> 0 | F17: {=+SUMPRODUCT(('Budget original'!$A$8:$A$501=$A17)*('Budget original'!$C$3:$AO$3=F$2),'Budget original'!$C$8:$AO$501)} -> 0 | J17: =-SUMIFS(BV_Data_An_Cour!$P:$P,BV_Data_An_Cour!$U:$U,$B17,BV_Data_An_Cour!$V:$V,$C17,BV_Data_An_Cour!$W:$W,J$2) -> 4 | K17: =IF(J17=0,0,L17/J17) -> 1875.165 | L17: =-SUMIFS(BV_Data_An_Cour!$P:$P,BV_Data_An_Cour!$U:$U,$B17,BV_Data_An_Cour!$V:$V,$C17,BV_Data_An_Cour!$W:$W,L$2) -> 7500.66 | M17: =J17-D17 -> 1 | N17: =L17-F17 -> 7500.66 | O17: {=+SUMPRODUCT(('Réel 2024'!$A$8:$A$501=$A17)*('Réel 2024'!$C$3:$AO$3=O$2),'Réel 2024'!$C$8:$AO$501)} -> 5 | P17: =IF(O17=0,0,Q17/O17) -> 2686.786 | Q17: {=+SUMPRODUCT(('Réel 2024'!$A$8:$A$501=$A17)*('Réel 2024'!$C$3:$AO$3=Q$2),'Réel 2024'!$C$8:$AO$501)} -> 13433.93 | R17: =J17-O17 -> -1 | S17: =L17-Q17 -> -5933.27
A18: =+B18&C18 -> Véhicules neufs | B18: =+$K$1 -> Véhicules neufs
A19: =+B19&C19 -> Véhicules neufsRachat bail | B19: =+$K$1 -> Véhicules neufs | C19: Rachat bail | D19: {=+SUMPRODUCT(('Budget original'!$A$8:$A$501=$A19)*('Budget original'!$C$3:$AO$3=D$2),'Budget original'!$C$8:$AO$501)} -> 0 | E19: =IF(D19=0,0,F19/D19) -> 0 | F19: {=+SUMPRODUCT(('Budget original'!$A$8:$A$501=$A19)*('Budget original'!$C$3:$AO$3=F$2),'Budget original'!$C$8:$AO$501)} -> 29970 | L19: =-SUMIFS(BV_Data_An_Cour!$P:$P,BV_Data_An_Cour!$U:$U,$B19,BV_Data_An_Cour!$V:$V,$C19,BV_Data_An_Cour!$W:$W,L$2) -> 999 | N19: =L19-F19 -> -28971 | O19: {=+SUMPRODUCT(('Réel 2024'!$A$8:$A$501=$A19)*('Réel 2024'!$C$3:$AO$3=O$2),'Réel 2024'!$C$8:$AO$501)} -> 0 | P19: =IF(O19=0,0,Q19/O19) -> 0 | Q19: {=+SUMPRODUCT(('Réel 2024'!$A$8:$A$501=$A19)*('Réel 2024'!$C$3:$AO$3=Q$2),'Réel 2024'!$C$8:$AO$501)} -> 45746.46 | R19: =O19-K19 -> 0 | S19: =L19-Q19 -> -44747.46
A20: =+B20&C20 -> Véhicules neufs | B20: =+$K$1 -> Véhicules neufs
A21: =+B21&C21 -> Véhicules neufsRev. Finances | B21: =+$K$1 -> Véhicules neufs | C21: Rev. Finances | F21: {=+SUMPRODUCT(('Budget original'!$A$8:$A$501=$A21)*('Budget original'!$C$3:$AO$3=F$2),'Budget original'!$C$8:$AO$501)} -> 6800 | K21: =IF(J13=0,0,L21/(J13+J15)) -> 0 | L21: =-SUMIFS(BV_Data_An_Cour!$P:$P,BV_Data_An_Cour!$U:$U,$B21,BV_Data_An_Cour!$V:$V,$C21,BV_Data_An_Cour!$W:$W,L$2) -> 0 | N21: =L21-F21 -> -6800 | Q21: {=+SUMPRODUCT(('Réel 2024'!$A$8:$A$501=$A21)*('Réel 2024'!$C$3:$AO$3=Q$2),'Réel 2024'!$C$8:$AO$501)} -> 3010.99 | R21: =O21-K21 -> 0 | S21: =L21-Q21 -> -3010.99
A22: =+B22&C22 -> Véhicules neufsRev. Protections | B22: =+$K$1 -> Véhicules neufs | C22: Rev. Protections | F22: {=+SUMPRODUCT(('Budget original'!$A$8:$A$501=$A22)*('Budget original'!$C$3:$AO$3=F$2),'Budget original'!$C$8:$AO$501)} -> 312800 | K22: =IF(J13=0,0,L22/(J13+J15)) -> 912.25 | L22: =-SUMIFS(BV_Data_An_Cour!$P:$P,BV_Data_An_Cour!$U:$U,$B22,BV_Data_An_Cour!$V:$V,$C22,BV_Data_An_Cour!$W:$W,L$2) -> 7298 | N22: =L22-F22 -> -305502 | Q22: {=+SUMPRODUCT(('Réel 2024'!$A$8:$A$501=$A22)*('Réel 2024'!$C$3:$AO$3=Q$2),'Réel 2024'!$C$8:$AO$501)} -> 307777.85 | R22: =O22-K22 -> -912.25 | S22: =L22-Q22 -> -300479.85
A23: =+B23&C23 -> Véhicules neufsRev. Autres | B23: =+$K$1 -> Véhicules neufs | C23: Rev. Autres | F23: {=+SUMPRODUCT(('Budget original'!$A$8:$A$501=$A23)*('Budget original'!$C$3:$AO$3=F$2),'Budget original'!$C$8:$AO$501)} -> 130560 | K23: =IF(J13=0,0,L23/(J13+J15)) -> 891.08125 | L23: =-SUMIFS(BV_Data_An_Cour!$P:$P,BV_Data_An_Cour!$U:$U,$B23,BV_Data_An_Cour!$V:$V,$C23,BV_Data_An_Cour!$W:$W,L$2) -> 7128.65 | N23: =L23-F23 -> -123431.35 | Q23: {=+SUMPRODUCT(('Réel 2024'!$A$8:$A$501=$A23)*('Réel 2024'!$C$3:$AO$3=Q$2),'Réel 2024'!$C$8:$AO$501)} -> 124636.7 | R23: =O23-K23 -> -891.08125 | S23: =L23-Q23 -> -117508.05
A24: =+B24&C24 -> Véhicules neufsTotal F&I | B24: =+$K$1 -> Véhicules neufs | C24: Total F&I | D24: =+D15+D13 -> 272 | E24: =IF(D24<=0,0,F24/D24) -> 1655 | F24: =F21+F22+F23 -> 450160 | J24: =+J15+J13 -> 8 | K24: =IF(J24<=0,0,L24/J24) -> 1803.3313 | L24: =L21+L22+L23 -> 14426.65 | M24: =J24-D24 -> -264 | N24: =L24-F24 -> -435733.35 | O24: =+O15+O13 -> 265 | P24: =IF(O24<=0,0,Q24/O24) -> 1643.1152 | Q24: =Q21+Q22+Q23 -> 435425.54 | S24: =L24-Q24 -> -420998.89
A25: =+B25&C25 -> Véhicules neufs | B25: =+$K$1 -> Véhicules neufs | N25: =IF(N24=0,0,N24/F24) -> -0.96795217 | S25: =IF(Q24=0,0,(S24/Q24)) -> -0.9668677
A26: =+B26&C26 -> Véhicules neufs | B26: =+$K$1 -> Véhicules neufs
A27: =+B27&C27 -> Véhicules neufsTotal Dépt. Neufs | B27: =+$K$1 -> Véhicules neufs | C27: Total Dépt. Neufs | D27: =+D13+D15+D17 -> 275 | E27: =IF(D27<=0,0,F27/D27) -> 5384.6545 | F27: =F13+F17+F24+F19+F15 -> 1480780 | J27: =+J13+J15+J17 -> 12 | K27: =IF(J27<=0,0,L27/J27) -> 4271.0608 | L27: =L13+L17+L24+L19+L15 -> 51252.73 | M27: =J27-D27 -> -263 | N27: =L27-F27 -> -1429527.3 | O27: =+O13+O15+O17 -> 270 | P27: =IF(O27<=0,0,Q27/O27) -> 6082.84 | Q27: =Q13+Q17+Q24+Q19+Q15 -> 1642366.8 | R27: =J27-O27 -> -258 | S27: =L27-Q27 -> -1591114.1
A28: =+B28&C28 -> Véhicules neufs | B28: =+$K$1 -> Véhicules neufs | M28: =M27/D27 -> -0.95636364 | N28: =N27/F27 -> -0.96538802 | R28: =R27/O27 -> -0.95555556 | S28: =IF(Q27=0,0,S27/Q27) -> -0.96879337
A29: =+B29&C29 -> Véhicules neufs | B29: =+$K$1 -> Véhicules neufs
A30: =+B30&C30 -> Véhicules neufsDEPENSES | B30: =+$K$1 -> Véhicules neufs | C30: DEPENSES
A31: =+B31&C31 -> Véhicules neufsComm. vendeurs | B31: =+$K$1 -> Véhicules neufs | C31: Comm. vendeurs | E31: =F31/D$24 -> 1071.5257 | F31: {=+SUMPRODUCT(('Budget original'!$A$8:$A$501=$A31)*('Budget original'!$C$3:$AO$3=F$2),'Budget original'!$C$8:$AO$501)} -> 291455 | J31: =L31/(L13+L15) -> 0.32221827 | K31: =IF(L31=0,0,L31/J$24) -> 1140.9113 | L31: =SUMIFS(BV_Data_An_Cour!$P:$P,BV_Data_An_Cour!$U:$U,$B31,BV_Data_An_Cour!$V:$V,$C31,BV_Data_An_Cour!$W:$W,L$2) -> 9127.29 | N31: =L31-F31 -> -282327.71 | P31: =Q31/O$24 -> 1284.8014 | Q31: {=+SUMPRODUCT(('Réel 2024'!$A$8:$A$501=$A31)*('Réel 2024'!$C$3:$AO$3=Q$2),'Réel 2024'!$C$8:$AO$501)} -> 340472.38 | S31: =L31-Q31 -> -331345.09
A32: =+B32&C32 -> Véhicules neufsComm. F&I | B32: =+$K$1 -> Véhicules neufs | C32: Comm. F&I | E32: =F32/D$24 -> 455.125 | F32: {=+SUMPRODUCT(('Budget original'!$A$8:$A$501=$A32)*('Budget original'!$C$3:$AO$3=F$2),'Budget original'!$C$8:$AO$501)} -> 123794 | J32: =L32/L24 -> 0.32295925 | K32: =IF(L32=0,0,L32/J$24) -> 582.4025 | L32: =SUMIFS(BV_Data_An_Cour!$P:$P,BV_Data_An_Cour!$U:$U,$B32,BV_Data_An_Cour!$V:$V,$C32,BV_Data_An_Cour!$W:$W,L$2) -> 4659.22 | N32: =L32-F32 -> -119134.78 | P32: =Q32/O$24 -> 619.32366 | Q32: {=+SUMPRODUCT(('Réel 2024'!$A$8:$A$501=$A32)*('Réel 2024'!$C$3:$AO$3=Q$2),'Réel 2024'!$C$8:$AO$501)} -> 164120.77 | S32: =L32-Q32 -> -159461.55
A33: =+B33&C33 -> Véhicules neufsFrais de livraison | B33: =+$K$1 -> Véhicules neufs | C33: Frais de livraison | E33: =F33/D$24 -> 130 | F33: {=+SUMPRODUCT(('Budget original'!$A$8:$A$501=$A33)*('Budget original'!$C$3:$AO$3=F$2),'Budget original'!$C$8:$AO$501)} -> 35360 | K33: =IF(L33=0,0,L33/J$24) -> 0.4625 | L33: =SUMIFS(BV_Data_An_Cour!$P:$P,BV_Data_An_Cour!$U:$U,$B33,BV_Data_An_Cour!$V:$V,$C33,BV_Data_An_Cour!$W:$W,L$2) -> 3.7 | N33: =L33-F33 -> -35356.3 | P33: =Q33/O$24 -> 120.09117 | Q33: {=+SUMPRODUCT(('Réel 2024'!$A$8:$A$501=$A33)*('Réel 2024'!$C$3:$AO$3=Q$2),'Réel 2024'!$C$8:$AO$501)} -> 31824.16 | S33: =L33-Q33 -> -31820.46
A34: =+B34&C34 -> Véhicules neufsService gratuit 1 | B34: =+$K$1 -> Véhicules neufs | C34: Service gratuit 1 | E34: =F34/D$24 -> 37 | F34: {=+SUMPRODUCT(('Budget original'!$A$8:$A$501=$A34)*('Budget original'!$C$3:$AO$3=F$2),'Budget original'!$C$8:$AO$501)} -> 10064 | K34: =IF(L34=0,0,L34/J$24) -> 0 | L34: =SUMIFS(BV_Data_An_Cour!$P:$P,BV_Data_An_Cour!$U:$U,$B34,BV_Data_An_Cour!$V:$V,$C34,BV_Data_An_Cour!$W:$W,L$2) -> 0 | N34: =L34-F34 -> -10064 | P34: =Q34/O$24 -> 38.97834 | Q34: {=+SUMPRODUCT(('Réel 2024'!$A$8:$A$501=$A34)*('Réel 2024'!$C$3:$AO$3=Q$2),'Réel 2024'!$C$8:$AO$501)} -> 10329.26 | S34: =L34-Q34 -> -10329.26
A35: =+B35&C35 -> Véhicules neufsEntretien stock | B35: =+$K$1 -> Véhicules neufs | C35: Entretien stock | E35: =F35/D$24 -> 61.617647 | F35: {=+SUMPRODUCT(('Budget original'!$A$8:$A$501=$A35)*('Budget original'!$C$3:$AO$3=F$2),'Budget original'!$C$8:$AO$501)} -> 16760 | K35: =IF(L35=0,0,L35/J$24) -> 356.60875 | L35: =SUMIFS(BV_Data_An_Cour!$P:$P,BV_Data_An_Cour!$U:$U,$B35,BV_Data_An_Cour!$V:$V,$C35,BV_Data_An_Cour!$W:$W,L$2) -> 2852.87 | N35: =L35-F35 -> -13907.13 | P35: =Q35/O$24 -> 65.46034 | Q35: {=+SUMPRODUCT(('Réel 2024'!$A$8:$A$501=$A35)*('Réel 2024'!$C$3:$AO$3=Q$2),'Réel 2024'!$C$8:$AO$501)} -> 17346.99 | S35: =L35-Q35 -> -14494.12
A36: =+B36&C36 -> Véhicules neufsPublicité 1 | B36: =+$K$1 -> Véhicules neufs | C36: Publicité 1 | E36: =F36/D$24 -> 513.97059 | F36: {=+SUMPRODUCT(('Budget original'!$A$8:$A$501=$A36)*('Budget original'!$C$3:$AO$3=F$2),'Budget original'!$C$8:$AO$501)} -> 139800 | K36: =IF(L36=0,0,L36/J$24) -> 1325.5687 | L36: =SUMIFS(BV_Data_An_Cour!$P:$P,BV_Data_An_Cour!$U:$U,$B36,BV_Data_An_Cour!$V:$V,$C36,BV_Data_An_Cour!$W:$W,L$2) -> 10604.55 | N36: =L36-F36 -> -129195.45 | P36: =Q36/O$24 -> 632.89355 | Q36: {=+SUMPRODUCT(('Réel 2024'!$A$8:$A$501=$A36)*('Réel 2024'!$C$3:$AO$3=Q$2),'Réel 2024'!$C$8:$AO$501)} -> 167716.79 | S36: =L36-Q36 -> -157112.24
A37: =+B37&C37 -> Véhicules neufsIntérêt de gros | B37: =+$K$1 -> Véhicules neufs | C37: Intérêt de gros | E37: =F37/D$24 -> 1186.9396 | F37: {=+SUMPRODUCT(('Budget original'!$A$8:$A$501=$A37)*('Budget original'!$C$3:$AO$3=F$2),'Budget original'!$C$8:$AO$501)} -> 322847.56 | K37: =IF(L37=0,0,L37/J$24) -> 2816.66 | L37: =SUMIFS(BV_Data_An_Cour!$P:$P,BV_Data_An_Cour!$U:$U,$B37,BV_Data_An_Cour!$V:$V,$C37,BV_Data_An_Cour!$W:$W,L$2) -> 22533.28 | N37: =L37-F37 -> -300314.28 | P37: =Q37/O$24 -> 1381.9589 | Q37: {=+SUMPRODUCT(('Réel 2024'!$A$8:$A$501=$A37)*('Réel 2024'!$C$3:$AO$3=Q$2),'Réel 2024'!$C$8:$AO$501)} -> 366219.1 | S37: =L37-Q37 -> -343685.82
A38: =+B38&C38 -> Véhicules neufs[...] | B38: =+$K$1 -> Véhicules neufs | C38: [...] | E38: =F38/D$24 -> 0 | F38: {=+SUMPRODUCT(('Budget original'!$A$8:$A$501=$A38)*('Budget original'!$C$3:$AO$3=F$2),'Budget original'!$C$8:$AO$501)} -> 0 | K38: =IF(L38=0,0,L38/J$24) -> 0 | L38: =SUMIFS(BV_Data_An_Cour!$P:$P,BV_Data_An_Cour!$U:$U,$B38,BV_Data_An_Cour!$V:$V,$C38,BV_Data_An_Cour!$W:$W,L$2) -> 0 | N38: =L38-F38 -> 0 | P38: =Q38/O$24 -> 0 | Q38: {=+SUMPRODUCT(('Réel 2024'!$A$8:$A$501=$A38)*('Réel 2024'!$C$3:$AO$3=Q$2),'Réel 2024'!$C$8:$AO$501)} -> 0 | S38: =L38-Q38 -> 0
A39: =+B39&C39 -> Véhicules neufs[...] | B39: =+$K$1 -> Véhicules neufs | C39: [...] | E39: =F39/D$24 -> 0 | F39: {=+SUMPRODUCT(('Budget original'!$A$8:$A$501=$A39)*('Budget original'!$C$3:$AO$3=F$2),'Budget original'!$C$8:$AO$501)} -> 0 | K39: =IF(L39=0,0,L39/J$24) -> 0 | L39: =SUMIFS(BV_Data_An_Cour!$P:$P,BV_Data_An_Cour!$U:$U,$B39,BV_Data_An_Cour!$V:$V,$C39,BV_Data_An_Cour!$W:$W,L$2) -> 0 | N39: =L39-F39 -> 0 | P39: =Q39/O$24 -> 0 | Q39: {=+SUMPRODUCT(('Réel 2024'!$A$8:$A$501=$A39)*('Réel 2024'!$C$3:$AO$3=Q$2),'Réel 2024'!$C$8:$AO$501)} -> 0 | S39: =L39-Q39 -> 0
A40: =+B40&C40 -> Véhicules neufs[...] | B40: =+$K$1 -> Véhicules neufs | C40: [...] | E40: =F40/D$24 -> 0 | F40: {=+SUMPRODUCT(('Budget original'!$A$8:$A$501=$A40)*('Budget original'!$C$3:$AO$3=F$2),'Budget original'!$C$8:$AO$501)} -> 0 | K40: =IF(L40=0,0,L40/J$24) -> 0 | L40: =SUMIFS(BV_Data_An_Cour!$P:$P,BV_Data_An_Cour!$U:$U,$B40,BV_Data_An_Cour!$V:$V,$C40,BV_Data_An_Cour!$W:$W,L$2) -> 0 | N40: =L40-F40 -> 0 | P40: =Q40/O$24 -> 0 | Q40: {=+SUMPRODUCT(('Réel 2024'!$A$8:$A$501=$A40)*('Réel 2024'!$C$3:$AO$3=Q$2),'Réel 2024'!$C$8:$AO$501)} -> 0 | S40: =L40-Q40 -> 0
A41: =+B41&C41 -> Véhicules neufsTOTAL VARIABLES | B41: =+$K$1 -> Véhicules neufs | C41: TOTAL VARIABLES | D41: % brut | E41: =F41/F$27 -> 0.63485498 | F41: =SUM(F31:F40) -> 940080.56 | J41: % brut | K41: =L41/L$27 -> 0.97128309 | L41: =SUM(L31:L40) -> 49780.91 | N41: =L41-F41 -> -890299.65 | O41: % brut | P41: =Q41/Q$27 -> 0.6685653 | Q41: =SUM(Q31:Q40) -> 1098029.4 | S41: =L41-Q41 -> -1048248.5
A42: =+B42&C42 -> Véhicules neufsSalaires cadres | B42: =+$K$1 -> Véhicules neufs | C42: Salaires cadres | F42: {=+SUMPRODUCT(('Budget original'!$A$8:$A$501=$A42)*('Budget original'!$C$3:$AO$3=F$2),'Budget original'!$C$8:$AO$501)} -> 150304.6 | L42: =SUMIFS(BV_Data_An_Cour!$P:$P,BV_Data_An_Cour!$U:$U,$B42,BV_Data_An_Cour!$V:$V,$C42,BV_Data_An_Cour!$W:$W,L$2) -> 10268.97 | N42: =L42-F42 -> -140035.63 | Q42: {=+SUMPRODUCT(('Réel 2024'!$A$8:$A$501=$A42)*('Réel 2024'!$C$3:$AO$3=Q$2),'Réel 2024'!$C$8:$AO$501)} -> 145432.02
A43: =+B43&C43 -> Véhicules neufsSalaires commis | B43: =+$K$1 -> Véhicules neufs | C43: Salaires commis | F43: {=+SUMPRODUCT(('Budget original'!$A$8:$A$501=$A43)*('Budget original'!$C$3:$AO$3=F$2),'Budget original'!$C$8:$AO$501)} -> 115883.2 | L43: =SUMIFS(BV_Data_An_Cour!$P:$P,BV_Data_An_Cour!$U:$U,$B43,BV_Data_An_Cour!$V:$V,$C43,BV_Data_An_Cour!$W:$W,L$2) -> 7244.51 | N43: =L43-F43 -> -108638.69 | Q43: {=+SUMPRODUCT(('Réel 2024'!$A$8:$A$501=$A43)*('Réel 2024'!$C$3:$AO$3=Q$2),'Réel 2024'!$C$8:$AO$501)} -> 109318.68 | S43: =L43-Q43 -> -102074.17
A44: =+B44&C44 -> Véhicules neufsSalaires autres | B44: =+$K$1 -> Véhicules neufs | C44: Salaires autres | F44: {=+SUMPRODUCT(('Budget original'!$A$8:$A$501=$A44)*('Budget original'!$C$3:$AO$3=F$2),'Budget original'!$C$8:$AO$501)} -> 4104 | L44: =SUMIFS(BV_Data_An_Cour!$P:$P,BV_Data_An_Cour!$U:$U,$B44,BV_Data_An_Cour!$V:$V,$C44,BV_Data_An_Cour!$W:$W,L$2) -> 0 | N44: =L44-F44 -> -4104 | Q44: {=+SUMPRODUCT(('Réel 2024'!$A$8:$A$501=$A44)*('Réel 2024'!$C$3:$AO$3=Q$2),'Réel 2024'!$C$8:$AO$501)} -> 4104 | S44: =L44-Q44 -> -4104
A45: =+B45&C45 -> Véhicules neufsSalaires spécialistes | B45: =+$K$1 -> Véhicules neufs | C45: Salaires spécialistes | F45: {=+SUMPRODUCT(('Budget original'!$A$8:$A$501=$A45)*('Budget original'!$C$3:$AO$3=F$2),'Budget original'!$C$8:$AO$501)} -> 0 | L45: =SUMIFS(BV_Data_An_Cour!$P:$P,BV_Data_An_Cour!$U:$U,$B45,BV_Data_An_Cour!$V:$V,$C45,BV_Data_An_Cour!$W:$W,L$2) -> 0 | N45: =L45-F45 -> 0 | Q45: {=+SUMPRODUCT(('Réel 2024'!$A$8:$A$501=$A45)*('Réel 2024'!$C$3:$AO$3=Q$2),'Réel 2024'!$C$8:$AO$501)} -> 0 | S45: =L45-Q45 -> 0
A46: =+B46&C46 -> Véhicules neufs[...] | B46: =+$K$1 -> Véhicules neufs | C46: [...] | F46: {=+SUMPRODUCT(('Budget original'!$A$8:$A$501=$A46)*('Budget original'!$C$3:$AO$3=F$2),'Budget original'!$C$8:$AO$501)} -> 0 | L46: =SUMIFS(BV_Data_An_Cour!$P:$P,BV_Data_An_Cour!$U:$U,$B46,BV_Data_An_Cour!$V:$V,$C46,BV_Data_An_Cour!$W:$W,L$2) -> 0 | N46: =L46-F46 -> 0 | Q46: {=+SUMPRODUCT(('Réel 2024'!$A$8:$A$501=$A46)*('Réel 2024'!$C$3:$AO$3=Q$2),'Réel 2024'!$C$8:$AO$501)} -> 0 | S46: =L46-Q46 -> 0
A47: =+B47&C47 -> Véhicules neufs[...] | B47: =+$K$1 -> Véhicules neufs | C47: [...] | F47: {=+SUMPRODUCT(('Budget original'!$A$8:$A$501=$A47)*('Budget original'!$C$3:$AO$3=F$2),'Budget original'!$C$8:$AO$501)} -> 0 | L47: =SUMIFS(BV_Data_An_Cour!$P:$P,BV_Data_An_Cour!$U:$U,$B47,BV_Data_An_Cour!$V:$V,$C47,BV_Data_An_Cour!$W:$W,L$2) -> 0 | N47: =L47-F47 -> 0 | Q47: {=+SUMPRODUCT(('Réel 2024'!$A$8:$A$501=$A47)*('Réel 2024'!$C$3:$AO$3=Q$2),'Réel 2024'!$C$8:$AO$501)} -> 0 | S47: =L47-Q47 -> 0
A48: =+B48&C48 -> Véhicules neufs[...] | B48: =+$K$1 -> Véhicules neufs | C48: [...] | F48: {=+SUMPRODUCT(('Budget original'!$A$8:$A$501=$A48)*('Budget original'!$C$3:$AO$3=F$2),'Budget original'!$C$8:$AO$501)} -> 0 | L48: =SUMIFS(BV_Data_An_Cour!$P:$P,BV_Data_An_Cour!$U:$U,$B48,BV_Data_An_Cour!$V:$V,$C48,BV_Data_An_Cour!$W:$W,L$2) -> 0 | N48: =L48-F48 -> 0 | Q48: {=+SUMPRODUCT(('Réel 2024'!$A$8:$A$501=$A48)*('Réel 2024'!$C$3:$AO$3=Q$2),'Réel 2024'!$C$8:$AO$501)} -> 0 | S48: =L48-Q48 -> 0
A49: =+B49&C49 -> Véhicules neufsSalaires en absences | B49: =+$K$1 -> Véhicules neufs | C49: Salaires en absences | F49: {=+SUMPRODUCT(('Budget original'!$A$8:$A$501=$A49)*('Budget original'!$C$3:$AO$3=F$2),'Budget original'!$C$8:$AO$501)} -> 88637.498 | L49: =SUMIFS(BV_Data_An_Cour!$P:$P,BV_Data_An_Cour!$U:$U,$B49,BV_Data_An_Cour!$V:$V,$C49,BV_Data_An_Cour!$W:$W,L$2) -> 179.64 | N49: =L49-F49 -> -88457.858 | Q49: {=+SUMPRODUCT(('Réel 2024'!$A$8:$A$501=$A49)*('Réel 2024'!$C$3:$AO$3=Q$2),'Réel 2024'!$C$8:$AO$501)} -> 100107.48 | S49: =L49-Q49 -> -99927.84
A50: =+B50&C50 -> Véhicules neufsDéduction à la source | B50: =+$K$1 -> Véhicules neufs | C50: Déduction à la source | F50: {=+SUMPRODUCT(('Budget original'!$A$8:$A$501=$A50)*('Budget original'!$C$3:$AO$3=F$2),'Budget original'!$C$8:$AO$501)} -> 101920.84 | L50: =SUMIFS(BV_Data_An_Cour!$P:$P,BV_Data_An_Cour!$U:$U,$B50,BV_Data_An_Cour!$V:$V,$C50,BV_Data_An_Cour!$W:$W,L$2) -> 6796.55 | N50: =L50-F50 -> -95124.285 | Q50: {=+SUMPRODUCT(('Réel 2024'!$A$8:$A$501=$A50)*('Réel 2024'!$C$3:$AO$3=Q$2),'Réel 2024'!$C$8:$AO$501)} -> 103363.31 | S50: =L50-Q50 -> -96566.76
A51: =+B51&C51 -> Véhicules neufsBénéfices marginaux | B51: =+$K$1 -> Véhicules neufs | C51: Bénéfices marginaux | F51: {=+SUMPRODUCT(('Budget original'!$A$8:$A$501=$A51)*('Budget original'!$C$3:$AO$3=F$2),'Budget original'!$C$8:$AO$501)} -> 53342.478 | L51: =SUMIFS(BV_Data_An_Cour!$P:$P,BV_Data_An_Cour!$U:$U,$B51,BV_Data_An_Cour!$V:$V,$C51,BV_Data_An_Cour!$W:$W,L$2) -> 3722.69 | N51: =L51-F51 -> -49619.788 | Q51: {=+SUMPRODUCT(('Réel 2024'!$A$8:$A$501=$A51)*('Réel 2024'!$C$3:$AO$3=Q$2),'Réel 2024'!$C$8:$AO$501)} -> 53589.77 | S51: =L51-Q51 -> -49867.08
A52: =+B52&C52 -> Véhicules neufsCsst | B52: =+$K$1 -> Véhicules neufs | C52: Csst | F52: {=+SUMPRODUCT(('Budget original'!$A$8:$A$501=$A52)*('Budget original'!$C$3:$AO$3=F$2),'Budget original'!$C$8:$AO$501)} -> 11430.531 | L52: =SUMIFS(BV_Data_An_Cour!$P:$P,BV_Data_An_Cour!$U:$U,$B52,BV_Data_An_Cour!$V:$V,$C52,BV_Data_An_Cour!$W:$W,L$2) -> 1572.23 | N52: =L52-F52 -> -9858.3011 | Q52: {=+SUMPRODUCT(('Réel 2024'!$A$8:$A$501=$A52)*('Réel 2024'!$C$3:$AO$3=Q$2),'Réel 2024'!$C$8:$AO$501)} -> 8279.19 | S52: =L52-Q52 -> -6706.96
A53: =+B53&C53 -> Véhicules neufs[...] | B53: =+$K$1 -> Véhicules neufs | C53: [...] | F53: {=+SUMPRODUCT(('Budget original'!$A$8:$A$501=$A53)*('Budget original'!$C$3:$AO$3=F$2),'Budget original'!$C$8:$AO$501)} -> 0 | L53: =SUMIFS(BV_Data_An_Cour!$P:$P,BV_Data_An_Cour!$U:$U,$B53,BV_Data_An_Cour!$V:$V,$C53,BV_Data_An_Cour!$W:$W,L$2) -> 0 | N53: =L53-F53 -> 0 | Q53: {=+SUMPRODUCT(('Réel 2024'!$A$8:$A$501=$A53)*('Réel 2024'!$C$3:$AO$3=Q$2),'Réel 2024'!$C$8:$AO$501)} -> 0 | S53: =L53-Q53 -> 0
A54: =+B54&C54 -> Véhicules neufsTOTAL PERSONNEL | B54: =+$K$1 -> Véhicules neufs | C54: TOTAL PERSONNEL | D54: % brut | E54: =F54/F$27 -> 0.3549637 | F54: =+SUM(F42:F53) -> 525623.14 | J54: % brut | K54: =L54/L$27 -> 0.58113178 | L54: =+SUM(L42:L53) -> 29784.59 | N54: =+SUM(N42:N53) -> -495838.55 | O54: % brut | P54: =Q54/Q$27 -> 0.31917015 | Q54: =+SUM(Q42:Q53) -> 524194.45 | S54: =+SUM(S42:S53) -> -359246.81
A55: =+B55&C55 -> Véhicules neufsPublicité 2 | B55: =+$K$1 -> Véhicules neufs | C55: Publicité 2 | F55: {=+SUMPRODUCT(('Budget original'!$A$8:$A$501=$A55)*('Budget original'!$C$3:$AO$3=F$2),'Budget original'!$C$8:$AO$501)} -> 0 | L55: =SUMIFS(BV_Data_An_Cour!$P:$P,BV_Data_An_Cour!$U:$U,$B55,BV_Data_An_Cour!$V:$V,$C55,BV_Data_An_Cour!$W:$W,L$2) -> 0 | N55: =L55-F55 -> 0 | Q55: {=+SUMPRODUCT(('Réel 2024'!$A$8:$A$501=$A55)*('Réel 2024'!$C$3:$AO$3=Q$2),'Réel 2024'!$C$8:$AO$501)} -> 0 | S55: =L55-Q55 -> 0
A56: =+B56&C56 -> Véhicules neufsService gratuit 2 | B56: =+$K$1 -> Véhicules neufs | C56: Service gratuit 2 | F56: {=+SUMPRODUCT(('Budget original'!$A$8:$A$501=$A56)*('Budget original'!$C$3:$AO$3=F$2),'Budget original'!$C$8:$AO$501)} -> 0 | L56: =SUMIFS(BV_Data_An_Cour!$P:$P,BV_Data_An_Cour!$U:$U,$B56,BV_Data_An_Cour!$V:$V,$C56,BV_Data_An_Cour!$W:$W,L$2) -> 0 | N56: =L56-F56 -> 0 | Q56: {=+SUMPRODUCT(('Réel 2024'!$A$8:$A$501=$A56)*('Réel 2024'!$C$3:$AO$3=Q$2),'Réel 2024'!$C$8:$AO$501)} -> 0 | S56: =L56-Q56 -> 0
A57: =+B57&C57 -> Véhicules neufsFrais véhicules de cie | B57: =+$K$1 -> Véhicules neufs | C57: Frais véhicules de cie | F57: {=+SUMPRODUCT(('Budget original'!$A$8:$A$501=$A57)*('Budget original'!$C$3:$AO$3=F$2),'Budget original'!$C$8:$AO$501)} -> 79451.2 | L57: =SUMIFS(BV_Data_An_Cour!$P:$P,BV_Data_An_Cour!$U:$U,$B57,BV_Data_An_Cour!$V:$V,$C57,BV_Data_An_Cour!$W:$W,L$2) -> 2004.38 | N57: 0 | Q57: {=+SUMPRODUCT(('Réel 2024'!$A$8:$A$501=$A57)*('Réel 2024'!$C$3:$AO$3=Q$2),'Réel 2024'!$C$8:$AO$501)} -> 88238.2 | S57: =L57-Q57 -> -86233.82
A58: =+B58&C58 -> Véhicules neufsInformatique | B58: =+$K$1 -> Véhicules neufs | C58: Informatique | F58: {=+SUMPRODUCT(('Budget original'!$A$8:$A$501=$A58)*('Budget original'!$C$3:$AO$3=F$2),'Budget original'!$C$8:$AO$501)} -> 58539.6 | L58: =SUMIFS(BV_Data_An_Cour!$P:$P,BV_Data_An_Cour!$U:$U,$B58,BV_Data_An_Cour!$V:$V,$C58,BV_Data_An_Cour!$W:$W,L$2) -> 5491.56 | N58: =L58-F58 -> -53048.04 | Q58: {=+SUMPRODUCT(('Réel 2024'!$A$8:$A$501=$A58)*('Réel 2024'!$C$3:$AO$3=Q$2),'Réel 2024'!$C$8:$AO$501)} -> 54831.46 | S58: =L58-Q58 -> -49339.9
A59: =+B59&C59 -> Véhicules neufsFrais de déplacement | B59: =+$K$1 -> Véhicules neufs | C59: Frais de déplacement | F59: {=+SUMPRODUCT(('Budget original'!$A$8:$A$501=$A59)*('Budget original'!$C$3:$AO$3=F$2),'Budget original'!$C$8:$AO$501)} -> 9900 | L59: =SUMIFS(BV_Data_An_Cour!$P:$P,BV_Data_An_Cour!$U:$U,$B59,BV_Data_An_Cour!$V:$V,$C59,BV_Data_An_Cour!$W:$W,L$2) -> 229.19 | N59: =L59-F59 -> -9670.81 | Q59: {=+SUMPRODUCT(('Réel 2024'!$A$8:$A$501=$A59)*('Réel 2024'!$C$3:$AO$3=Q$2),'Réel 2024'!$C$8:$AO$501)} -> 15061.78 | S59: =L59-Q59 -> -14832.59
A60: =+B60&C60 -> Véhicules neufsServices extérieurs | B60: =+$K$1 -> Véhicules neufs | C60: Services extérieurs | F60: {=+SUMPRODUCT(('Budget original'!$A$8:$A$501=$A60)*('Budget original'!$C$3:$AO$3=F$2),'Budget original'!$C$8:$AO$501)} -> 39776.4 | L60: =SUMIFS(BV_Data_An_Cour!$P:$P,BV_Data_An_Cour!$U:$U,$B60,BV_Data_An_Cour!$V:$V,$C60,BV_Data_An_Cour!$W:$W,L$2) -> 4998.77 | N60: =L60-F60 -> -34777.63 | Q60: {=+SUMPRODUCT(('Réel 2024'!$A$8:$A$501=$A60)*('Réel 2024'!$C$3:$AO$3=Q$2),'Réel 2024'!$C$8:$AO$501)} -> 41147.01 | S60: =L60-Q60 -> -36148.24
A61: =+B61&C61 -> Véhicules neufsFournitures autres | B61: =+$K$1 -> Véhicules neufs | C61: Fournitures autres | F61: {=+SUMPRODUCT(('Budget original'!$A$8:$A$501=$A61)*('Budget original'!$C$3:$AO$3=F$2),'Budget original'!$C$8:$AO$501)} -> 480 | L61: =SUMIFS(BV_Data_An_Cour!$P:$P,BV_Data_An_Cour!$U:$U,$B61,BV_Data_An_Cour!$V:$V,$C61,BV_Data_An_Cour!$W:$W,L$2) -> 13.12 | N61: =L61-F61 -> -466.88 | Q61: {=+SUMPRODUCT(('Réel 2024'!$A$8:$A$501=$A61)*('Réel 2024'!$C$3:$AO$3=Q$2),'Réel 2024'!$C$8:$AO$501)} -> 928.47 | S61: =L61-Q61 -> -915.35
A62: =+B62&C62 -> Véhicules neufsUniformes | B62: =+$K$1 -> Véhicules neufs | C62: Uniformes | F62: {=+SUMPRODUCT(('Budget original'!$A$8:$A$501=$A62)*('Budget original'!$C$3:$AO$3=F$2),'Budget original'!$C$8:$AO$501)} -> 360 | L62: =SUMIFS(BV_Data_An_Cour!$P:$P,BV_Data_An_Cour!$U:$U,$B62,BV_Data_An_Cour!$V:$V,$C62,BV_Data_An_Cour!$W:$W,L$2) -> 0 | N62: =L62-F62 -> -360 | Q62: {=+SUMPRODUCT(('Réel 2024'!$A$8:$A$501=$A62)*('Réel 2024'!$C$3:$AO$3=Q$2),'Réel 2024'!$C$8:$AO$501)} -> 554.66 | S62: =L62-Q62 -> -554.66
A63: =+B63&C63 -> Véhicules neufsPapeterie | B63: =+$K$1 -> Véhicules neufs | C63: Papeterie | F63: {=+SUMPRODUCT(('Budget original'!$A$8:$A$501=$A63)*('Budget original'!$C$3:$AO$3=F$2),'Budget original'!$C$8:$AO$501)} -> 8505 | L63: =SUMIFS(BV_Data_An_Cour!$P:$P,BV_Data_An_Cour!$U:$U,$B63,BV_Data_An_Cour!$V:$V,$C63,BV_Data_An_Cour!$W:$W,L$2) -> 170.18 | N63: =L63-F63 -> -8334.82 | Q63: {=+SUMPRODUCT(('Réel 2024'!$A$8:$A$501=$A63)*('Réel 2024'!$C$3:$AO$3=Q$2),'Réel 2024'!$C$8:$AO$501)} -> 7259.26 | S63: =L63-Q63 -> -7089.08
A64: =+B64&C64 -> Véhicules neufsTéléphone | B64: =+$K$1 -> Véhicules neufs | C64: Téléphone | F64: {=+SUMPRODUCT(('Budget original'!$A$8:$A$501=$A64)*('Budget original'!$C$3:$AO$3=F$2),'Budget original'!$C$8:$AO$501)} -> 2524.8 | L64: =SUMIFS(BV_Data_An_Cour!$P:$P,BV_Data_An_Cour!$U:$U,$B64,BV_Data_An_Cour!$V:$V,$C64,BV_Data_An_Cour!$W:$W,L$2) -> 350.52 | N64: =L64-F64 -> -2174.28 | Q64: {=+SUMPRODUCT(('Réel 2024'!$A$8:$A$501=$A64)*('Réel 2024'!$C$3:$AO$3=Q$2),'Réel 2024'!$C$8:$AO$501)} -> 2891.49 | S64: =L64-Q64 -> -2540.97
A65: =+B65&C65 -> Véhicules neufsFrais postaux | B65: =+$K$1 -> Véhicules neufs | C65: Frais postaux | F65: {=+SUMPRODUCT(('Budget original'!$A$8:$A$501=$A65)*('Budget original'!$C$3:$AO$3=F$2),'Budget original'!$C$8:$AO$501)} -> 2430 | L65: =SUMIFS(BV_Data_An_Cour!$P:$P,BV_Data_An_Cour!$U:$U,$B65,BV_Data_An_Cour!$V:$V,$C65,BV_Data_An_Cour!$W:$W,L$2) -> 88.66 | N65: =L65-F65 -> -2341.34 | Q65: {=+SUMPRODUCT(('Réel 2024'!$A$8:$A$501=$A65)*('Réel 2024'!$C$3:$AO$3=Q$2),'Réel 2024'!$C$8:$AO$501)} -> 2023 | S65: =L65-Q65 -> -1934.34
A66: =+B66&C66 -> Véhicules neufsDivers | B66: =+$K$1 -> Véhicules neufs | C66: Divers | F66: {=+SUMPRODUCT(('Budget original'!$A$8:$A$501=$A66)*('Budget original'!$C$3:$AO$3=F$2),'Budget original'!$C$8:$AO$501)} -> 9401.4 | L66: =SUMIFS(BV_Data_An_Cour!$P:$P,BV_Data_An_Cour!$U:$U,$B66,BV_Data_An_Cour!$V:$V,$C66,BV_Data_An_Cour!$W:$W,L$2) -> 203.99 | N66: =L66-F66 -> -9197.41 | Q66: {=+SUMPRODUCT(('Réel 2024'!$A$8:$A$501=$A66)*('Réel 2024'!$C$3:$AO$3=Q$2),'Réel 2024'!$C$8:$AO$501)} -> 9075.88 | S66: =L66-Q66 -> -8871.89
A67: =+B67&C67 -> Véhicules neufsFormation | B67: =+$K$1 -> Véhicules neufs | C67: Formation | F67: {=+SUMPRODUCT(('Budget original'!$A$8:$A$501=$A67)*('Budget original'!$C$3:$AO$3=F$2),'Budget original'!$C$8:$AO$501)} -> 6698.2021 | L67: =SUMIFS(BV_Data_An_Cour!$P:$P,BV_Data_An_Cour!$U:$U,$B67,BV_Data_An_Cour!$V:$V,$C67,BV_Data_An_Cour!$W:$W,L$2) -> 925.53 | N67: =L67-F67 -> -5772.6721 | Q67: {=+SUMPRODUCT(('Réel 2024'!$A$8:$A$501=$A67)*('Réel 2024'!$C$3:$AO$3=Q$2),'Réel 2024'!$C$8:$AO$501)} -> 3658.14 | S67: =L67-Q67 -> -2732.61
A68: =+B68&C68 -> Véhicules neufsFrais bancaires | B68: =+$K$1 -> Véhicules neufs | C68: Frais bancaires | F68: {=+SUMPRODUCT(('Budget original'!$A$8:$A$501=$A68)*('Budget original'!$C$3:$AO$3=F$2),'Budget original'!$C$8:$AO$501)} -> 35336.858 | L68: =SUMIFS(BV_Data_An_Cour!$P:$P,BV_Data_An_Cour!$U:$U,$B68,BV_Data_An_Cour!$V:$V,$C68,BV_Data_An_Cour!$W:$W,L$2) -> 2301.85 | N68: =L68-F68 -> -33035.008 | Q68: {=+SUMPRODUCT(('Réel 2024'!$A$8:$A$501=$A68)*('Réel 2024'!$C$3:$AO$3=Q$2),'Réel 2024'!$C$8:$AO$501)} -> 35883.2 | S68: =L68-Q68 -> -33581.35
A69: =+B69&C69 -> Véhicules neufs[...] | B69: =+$K$1 -> Véhicules neufs | C69: [...] | F69: {=+SUMPRODUCT(('Budget original'!$A$8:$A$501=$A69)*('Budget original'!$C$3:$AO$3=F$2),'Budget original'!$C$8:$AO$501)} -> 0 | N69: =L69-F69 -> 0 | Q69: {=+SUMPRODUCT(('Réel 2024'!$A$8:$A$501=$A69)*('Réel 2024'!$C$3:$AO$3=Q$2),'Réel 2024'!$C$8:$AO$501)} -> 0 | S69: =L69-Q69 -> 0
A70: =+B70&C70 -> Véhicules neufs[...] | B70: =+$K$1 -> Véhicules neufs | C70: [...] | F70: {=+SUMPRODUCT(('Budget original'!$A$8:$A$501=$A70)*('Budget original'!$C$3:$AO$3=F$2),'Budget original'!$C$8:$AO$501)} -> 0 | L70: =SUMIFS(BV_Data_An_Cour!$P:$P,BV_Data_An_Cour!$U:$U,$B70,BV_Data_An_Cour!$V:$V,$C70,BV_Data_An_Cour!$W:$W,L$2) -> 0 | N70: =L70-F70 -> 0 | Q70: {=+SUMPRODUCT(('Réel 2024'!$A$8:$A$501=$A70)*('Réel 2024'!$C$3:$AO$3=Q$2),'Réel 2024'!$C$8:$AO$501)} -> 0 | S70: =L70-Q70 -> 0
A71: =+B71&C71 -> Véhicules neufs[...] | B71: =+$K$1 -> Véhicules neufs | C71: [...] | F71: {=+SUMPRODUCT(('Budget original'!$A$8:$A$501=$A71)*('Budget original'!$C$3:$AO$3=F$2),'Budget original'!$C$8:$AO$501)} -> 0 | L71: =SUMIFS(BV_Data_An_Cour!$P:$P,BV_Data_An_Cour!$U:$U,$B71,BV_Data_An_Cour!$V:$V,$C71,BV_Data_An_Cour!$W:$W,L$2)*0.32 -> 0 | N71: =L71-F71 -> 0 | Q71: {=+SUMPRODUCT(('Réel 2024'!$A$8:$A$501=$A71)*('Réel 2024'!$C$3:$AO$3=Q$2),'Réel 2024'!$C$8:$AO$501)} -> 0 | S71: =L71-Q71 -> 0
A72: =+B72&C72 -> Véhicules neufsTOTAL SEMI-FIXES | B72: =+$K$1 -> Véhicules neufs | C72: TOTAL SEMI-FIXES | D72: % brut | E72: =F72/F$27 -> 0.17112836 | F72: =+SUM(F55:F71) -> 253403.46 | J72: % brut | K72: =L72/L$27 -> 0.32735329 | L72: =+SUM(L55:L71) -> 16777.75 | N72: =+SUM(N55:N71) -> -159178.89 | O72: % brut | P72: =Q72/Q$27 -> 0.15925343 | Q72: =+SUM(Q55:Q71) -> 261552.55 | S72: =+SUM(S55:S71) -> -244774.8
A73: =+B73&C73 -> Véhicules neufs | B73: =+$K$1 -> Véhicules neufs
A74: =+B74&C74 -> Véhicules neufsTOTAL DES DÉPENSES | B74: =+$K$1 -> Véhicules neufs | C74: TOTAL DES DÉPENSES | D74: % brut | E74: =F74/F$27 -> 1.160947 | F74: =F41+F54+F72 -> 1719107.2 | J74: % brut | K74: =L74/L$27 -> 1.8797682 | L74: =L41+L54+L72 -> 96343.25 | N74: =L74-F74 -> -1622763.9 | O74: % brut | P74: =Q74/Q$27 -> 1.1469889 | Q74: =Q41+Q54+Q72 -> 1883776.4 | S74: =L74-Q74 -> -1787433.2
A75: =+B75&C75 -> Véhicules neufsRBSC neuf | B75: =+$K$1 -> Véhicules neufs | C75: RBSC neuf | F75: {=+SUMPRODUCT(('Budget original'!$A$8:$A$501=$A75)*('Budget original'!$C$3:$AO$3=F$2),'Budget original'!$C$8:$AO$501)} -> 435312.81 | L75: =-SUMIFS(BV_Data_An_Cour!$P:$P,BV_Data_An_Cour!$U:$U,$B75,BV_Data_An_Cour!$V:$V,$C75,BV_Data_An_Cour!$W:$W,L$2) -> 20598 | N75: =L75-F75 -> -414714.81 | Q75: {=+SUMPRODUCT(('Réel 2024'!$A$8:$A$501=$A75)*('Réel 2024'!$C$3:$AO$3=Q$2),'Réel 2024'!$C$8:$AO$501)} -> 413289.73 | S75: =L75-Q75 -> -392691.73
A76: =+B76&C76 -> Véhicules neufsProgramme neuf 2 | B76: =+$K$1 -> Véhicules neufs | C76: Programme neuf 2 | F76: {=+SUMPRODUCT(('Budget original'!$A$8:$A$501=$A76)*('Budget original'!$C$3:$AO$3=F$2),'Budget original'!$C$8:$AO$501)} -> 0 | L76: =-SUMIFS(BV_Data_An_Cour!$P:$P,BV_Data_An_Cour!$U:$U,$B76,BV_Data_An_Cour!$V:$V,$C76,BV_Data_An_Cour!$W:$W,L$2) -> 0 | N76: =L76-F76 -> 0 | Q76: {=+SUMPRODUCT(('Réel 2024'!$A$8:$A$501=$A76)*('Réel 2024'!$C$3:$AO$3=Q$2),'Réel 2024'!$C$8:$AO$501)} -> 0 | S76: =L76-Q76 -> 0
A77: =+B77&C77 -> Véhicules neufsProgramme neuf 3 | B77: =+$K$1 -> Véhicules neufs | C77: Programme neuf 3 | F77: {=+SUMPRODUCT(('Budget original'!$A$8:$A$501=$A77)*('Budget original'!$C$3:$AO$3=F$2),'Budget original'!$C$8:$AO$501)} -> 0 | L77: =-SUMIFS(BV_Data_An_Cour!$P:$P,BV_Data_An_Cour!$U:$U,$B77,BV_Data_An_Cour!$V:$V,$C77,BV_Data_An_Cour!$W:$W,L$2) -> 0 | N77: =L77-F77 -> 0 | Q77: {=+SUMPRODUCT(('Réel 2024'!$A$8:$A$501=$A77)*('Réel 2024'!$C$3:$AO$3=Q$2),'Réel 2024'!$C$8:$AO$501)} -> 0 | S77: =L77-Q77 -> 0
A78: =+B78&C78 -> Véhicules neufsHoldbacks | B78: =+$K$1 -> Véhicules neufs | C78: Holdbacks | F78: {=+SUMPRODUCT(('Budget original'!$A$8:$A$501=$A78)*('Budget original'!$C$3:$AO$3=F$2),'Budget original'!$C$8:$AO$501)} -> 470608.44 | L78: =-SUMIFS(BV_Data_An_Cour!$P:$P,BV_Data_An_Cour!$U:$U,$B78,BV_Data_An_Cour!$V:$V,$C78,BV_Data_An_Cour!$W:$W,L$2) -> 32718 | N78: =L78-F78 -> -437890.44 | Q78: {=+SUMPRODUCT(('Réel 2024'!$A$8:$A$501=$A78)*('Réel 2024'!$C$3:$AO$3=Q$2),'Réel 2024'!$C$8:$AO$501)} -> 480905.6 | S78: =L78-Q78 -> -448187.6
A79: =+B79&C79 -> Véhicules neufs[...] | B79: =+$K$1 -> Véhicules neufs | C79: [...] | F79: {=+SUMPRODUCT(('Budget original'!$A$8:$A$501=$A79)*('Budget original'!$C$3:$AO$3=F$2),'Budget original'!$C$8:$AO$501)} -> 0 | L79: =-SUMIFS(BV_Data_An_Cour!$P:$P,BV_Data_An_Cour!$U:$U,$B79,BV_Data_An_Cour!$V:$V,$C79,BV_Data_An_Cour!$W:$W,L$2) -> 0 | N79: =L79-F79 -> 0 | Q79: {=+SUMPRODUCT(('Réel 2024'!$A$8:$A$501=$A79)*('Réel 2024'!$C$3:$AO$3=Q$2),'Réel 2024'!$C$8:$AO$501)} -> 0 | S79: =L79-Q79 -> 0
A80: =+B80&C80 -> Véhicules neufs[...] | B80: =+$K$1 -> Véhicules neufs | C80: [...] | F80: {=+SUMPRODUCT(('Budget original'!$A$8:$A$501=$A80)*('Budget original'!$C$3:$AO$3=F$2),'Budget original'!$C$8:$AO$501)} -> 0 | L80: =-SUMIFS(BV_Data_An_Cour!$P:$P,BV_Data_An_Cour!$U:$U,$B80,BV_Data_An_Cour!$V:$V,$C80,BV_Data_An_Cour!$W:$W,L$2) -> 0 | N80: =L80-F80 -> 0 | Q80: {=+SUMPRODUCT(('Réel 2024'!$A$8:$A$501=$A80)*('Réel 2024'!$C$3:$AO$3=Q$2),'Réel 2024'!$C$8:$AO$501)} -> 0 | S80: =L80-Q80 -> 0
A81: =+B81&C81 -> Véhicules neufs[...] | B81: =+$K$1 -> Véhicules neufs | C81: [...] | F81: {=+SUMPRODUCT(('Budget original'!$A$8:$A$501=$A81)*('Budget original'!$C$3:$AO$3=F$2),'Budget original'!$C$8:$AO$501)} -> 0 | L81: =-SUMIFS(BV_Data_An_Cour!$P:$P,BV_Data_An_Cour!$U:$U,$B81,BV_Data_An_Cour!$V:$V,$C81,BV_Data_An_Cour!$W:$W,L$2) -> 0 | N81: =L81-F81 -> 0 | Q81: {=+SUMPRODUCT(('Réel 2024'!$A$8:$A$501=$A81)*('Réel 2024'!$C$3:$AO$3=Q$2),'Réel 2024'!$C$8:$AO$501)} -> 0 | S81: =L81-Q81 -> 0
A82: =+B82&C82 -> Véhicules neufsFrais administration | B82: =+$K$1 -> Véhicules neufs | C82: Frais administration | F82: {=+SUMPRODUCT(('Budget original'!$A$8:$A$501=$A82)*('Budget original'!$C$3:$AO$3=F$2),'Budget original'!$C$8:$AO$501)} -> 159412.4 | L82: =-SUMIFS(BV_Data_An_Cour!$P:$P,BV_Data_An_Cour!$U:$U,$B82,BV_Data_An_Cour!$V:$V,$C82,BV_Data_An_Cour!$W:$W,L$2) -> 4165 | N82: =L82-F82 -> -155247.4 | Q82: {=+SUMPRODUCT(('Réel 2024'!$A$8:$A$501=$A82)*('Réel 2024'!$C$3:$AO$3=Q$2),'Réel 2024'!$C$8:$AO$501)} -> 157675 | S82: =L82-Q82 -> -153510
A83: =+B83&C83 -> Véhicules neufsAUTRES REVENUS | B83: =+$K$1 -> Véhicules neufs | C83: AUTRES REVENUS | F83: =+SUM(F75:F82) -> 1065333.6 | L83: =+SUM(L75:L82) -> 57481 | N83: =+SUM(N75:N82) -> -1007852.6 | Q83: =+SUM(Q75:Q82) -> 1051870.3 | S83: =+SUM(S75:S82) -> -994389.33
A84: =+B84&C84 -> Véhicules neufs | B84: =+$K$1 -> Véhicules neufs
A85: =+B85&C85 -> Véhicules neufsPROFIT DÉPARTEMENTAL | B85: =+$K$1 -> Véhicules neufs | C85: PROFIT DÉPARTEMENTAL | F85: =F27-F74+F83 -> 827006.48 | L85: =L27-L74+L83 -> 12390.48 | N85: =N27-N74+N83 -> -814616 | Q85: =Q27-Q74+Q83 -> 810460.68 | S85: =S27-S74+S83 -> -798070.2
C89: =C1 -> BMW Sherbrooke | K89: Véhicules usagés | S89: =$S$1 -> Réalisé, Décembre 2025 AAD
D91: BUDGET ORIGINAL | J91: RÉALISATION | M91: ÉCART réel / Budget | O91: ANNÉE PRÉCÉDENTE | R91: ECART (réel/ Ann.Préc.)
D92: UNITE | E92: $P/UNITÉ | F92: $PROFITS | J92: UNITE | K92: $P/UNITE | L92: $PROFITS | M92: UNFTÉ | N92: $PROFFTS | O92: UNITE | P92: $P/UNITÉ | Q92: $PROFITS | R92: UNITE | S92: $PROFITS
A93: =+B93&C93 -> Véhicules usagésVentes nettes | B93: Véhicules usagés | C93: Ventes nettes | F93: {=+SUMPRODUCT(('Budget original'!$A$8:$A$501=$A93)*('Budget original'!$C$3:$AO$3=F$2),'Budget original'!$C$8:$AO$501)} -> 17054706 | L93: =-SUMIFS(BV_Data_An_Cour!$P:$P,BV_Data_An_Cour!$X:$X,"Oui",BV_Data_An_Cour!$U:$U,$B93) -> 324028.28 | Q93: {=+SUMPRODUCT(('Réel 2024'!$A$8:$A$501=$A93)*('Réel 2024'!$C$3:$AO$3=Q$2),'Réel 2024'!$C$8:$AO$501)} -> 16016262
A94: =+B94&C94 -> Véhicules usagésCertifié | B94: Véhicules usagés | C94: Certifié | D94: {=+SUMPRODUCT(('Budget original'!$A$8:$A$501=$A94)*('Budget original'!$C$3:$AO$3=D$2),'Budget original'!$C$8:$AO$501)} -> 75 | E94: =IF(D94=0,0,F94/D94) -> 2300 | F94: {=+SUMPRODUCT(('Budget original'!$A$8:$A$501=$A94)*('Budget original'!$C$3:$AO$3=F$2),'Budget original'!$C$8:$AO$501)} -> 172500 | J94: =-SUMIFS(BV_Data_An_Cour!$P:$P,BV_Data_An_Cour!$U:$U,$B94,BV_Data_An_Cour!$V:$V,$C94,BV_Data_An_Cour!$W:$W,J$2) -> 3 | K94: =IF(J94=0,0,L94/J94) -> 1877.2533 | L94: =-SUMIFS(BV_Data_An_Cour!$P:$P,BV_Data_An_Cour!$U:$U,$B94,BV_Data_An_Cour!$V:$V,$C94,BV_Data_An_Cour!$W:$W,$L2) -> 5631.76 | M94: =J94-D94 -> -72 | N94: =L94-F94 -> -166868.24 | O94: {=+SUMPRODUCT(('Réel 2024'!$A$8:$A$501=$A94)*('Réel 2024'!$C$3:$AO$3=O$2),'Réel 2024'!$C$8:$AO$501)} -> 62 | P94: =IF(O94=0,0,Q94/O94) -> 2319.78 | Q94: {=+SUMPRODUCT(('Réel 2024'!$A$8:$A$501=$A94)*('Réel 2024'!$C$3:$AO$3=Q$2),'Réel 2024'!$C$8:$AO$501)} -> 143826.36 | R94: =J94-O94 -> -59 | S94: =L94-Q94 -> -138194.6
A95: =+B95&C95 -> Véhicules usagésNon Certifié | B95: Véhicules usagés | C95: Non Certifié | D95: {=+SUMPRODUCT(('Budget original'!$A$8:$A$501=$A95)*('Budget original'!$C$3:$AO$3=D$2),'Budget original'!$C$8:$AO$501)} -> 75 | E95: =IF(D95=0,0,F95/D95) -> 1600 | F95: {=+SUMPRODUCT(('Budget original'!$A$8:$A$501=$A95)*('Budget original'!$C$3:$AO$3=F$2),'Budget original'!$C$8:$AO$501)} -> 120000 | J95: =-SUMIFS(BV_Data_An_Cour!$P:$P,BV_Data_An_Cour!$U:$U,$B95,BV_Data_An_Cour!$V:$V,$C95,BV_Data_An_Cour!$W:$W,J$2) -> 2 | K95: =IF(J95=0,0,L95/J95) -> 968.675 | L95: =-SUMIFS(BV_Data_An_Cour!$P:$P,BV_Data_An_Cour!$U:$U,$B95,BV_Data_An_Cour!$V:$V,$C95,BV_Data_An_Cour!$W:$W,$L2) -> 1937.35 | M95: =J95-D95 -> -73 | N95: =L95-F95 -> -118062.65 | O95: {=+SUMPRODUCT(('Réel 2024'!$A$8:$A$501=$A95)*('Réel 2024'!$C$3:$AO$3=O$2),'Réel 2024'!$C$8:$AO$501)} -> 73 | P95: =IF(O95=0,0,Q95/O95) -> 1814.3649 | Q95: {=+SUMPRODUCT(('Réel 2024'!$A$8:$A$501=$A95)*('Réel 2024'!$C$3:$AO$3=Q$2),'Réel 2024'!$C$8:$AO$501)} -> 132448.64 | R95: =J95-O95 -> -71 | S95: =L95-Q95 -> -130511.29
A96: =+B96&C96 -> Véhicules usagésAutres marques | B96: Véhicules usagés | C96: Autres marques | D96: {=+SUMPRODUCT(('Budget original'!$A$8:$A$501=$A96)*('Budget original'!$C$3:$AO$3=D$2),'Budget original'!$C$8:$AO$501)} -> 75 | E96: =IF(D96=0,0,F96/D96) -> 1500 | F96: {=+SUMPRODUCT(('Budget original'!$A$8:$A$501=$A96)*('Budget original'!$C$3:$AO$3=F$2),'Budget original'!$C$8:$AO$501)} -> 112500 | J96: =-SUMIFS(BV_Data_An_Cour!$P:$P,BV_Data_An_Cour!$U:$U,$B96,BV_Data_An_Cour!$V:$V,$C96,BV_Data_An_Cour!$W:$W,J$2) -> 0 | K96: =IF(J96=0,0,L96/J96) -> 0 | L96: =-SUMIFS(BV_Data_An_Cour!$P:$P,BV_Data_An_Cour!$U:$U,$B96,BV_Data_An_Cour!$V:$V,$C96,BV_Data_An_Cour!$W:$W,$L2) -> 0 | M96: =J96-D96 -> -75 | N96: =L96-F96 -> -112500 | O96: {=+SUMPRODUCT(('Réel 2024'!$A$8:$A$501=$A96)*('Réel 2024'!$C$3:$AO$3=O$2),'Réel 2024'!$C$8:$AO$501)} -> 63 | P96: =IF(O96=0,0,Q96/O96) -> 1119.7821 | Q96: {=+SUMPRODUCT(('Réel 2024'!$A$8:$A$501=$A96)*('Réel 2024'!$C$3:$AO$3=Q$2),'Réel 2024'!$C$8:$AO$501)} -> 70546.27 | R96: =J96-O96 -> -63 | S96: =L96-Q96 -> -70546.27
A97: =+B97&C97 -> Véhicules usagésTotal Usagés | B97: Véhicules usagés | C97: Total Usagés | D97: =+D95+D94+D96 -> 225 | E97: =IF(D97=0,0,F97/D97) -> 1800 | F97: =+F94+F95+F96 -> 405000 | J97: =+J94+J95+J96 -> 5 | K97: =IF(J97<=0,0,L97/J97) -> 1513.822 | L97: =+L94+L95+L96 -> 7569.11 | M97: =J97-D97 -> -220 | N97: =L97-F97 -> -397430.89 | O97: =+O95+O94+O96 -> 198 | P97: =IF(O97=0,0,Q97/O97) -> 1751.6226 | Q97: =+Q94+Q95+Q96 -> 346821.27 | R97: =J97-O97 -> -193 | S97: =L97-Q97 -> -339252.16
A98: =+B98&C98 -> Véhicules usagés | B98: Véhicules usagés | M98: =M97/D97 -> -0.97777778 | N98: =N97/F97 -> -0.98131084 | R98: =R97/O97 -> -0.97474747 | S98: =IF(Q97=0,0,(S97/Q97)) -> -0.97817576
A99: =+B99&C99 -> Véhicules usagés | B99: Véhicules usagés
A100: =+B100&C100 -> Véhicules usagésVentes au Gros | B100: Véhicules usagés | C100: Ventes au Gros | D100: {=+SUMPRODUCT(('Budget original'!$A$8:$A$501=$A100)*('Budget original'!$C$3:$AO$3=D$2),'Budget original'!$C$8:$AO$501)} -> 220 | E100: =IF(D100=0,0,F100/D100) -> 350 | F100: {=+SUMPRODUCT(('Budget original'!$A$8:$A$501=$A100)*('Budget original'!$C$3:$AO$3=F$2),'Budget original'!$C$8:$AO$501)} -> 77000 | J100: =-SUMIFS(BV_Data_An_Cour!$P:$P,BV_Data_An_Cour!$U:$U,$B100,BV_Data_An_Cour!$V:$V,$C100,BV_Data_An_Cour!$W:$W,J$2) -> 2 | K100: =IF(J100=0,0,L100/J100) -> 788.05 | L100: =-SUMIFS(BV_Data_An_Cour!$P:$P,BV_Data_An_Cour!$U:$U,$B100,BV_Data_An_Cour!$V:$V,$C100,BV_Data_An_Cour!$W:$W,L$2) -> 1576.1 | M100: =J100-D100 -> -218 | N100: =L100-F100 -> -75423.9 | O100: {=+SUMPRODUCT(('Réel 2024'!$A$8:$A$501=$A100)*('Réel 2024'!$C$3:$AO$3=O$2),'Réel 2024'!$C$8:$AO$501)} -> 230 | P100: =IF(O100=0,0,Q100/O100) -> 434.93061 | Q100: {=+SUMPRODUCT(('Réel 2024'!$A$8:$A$501=$A100)*('Réel 2024'!$C$3:$AO$3=Q$2),'Réel 2024'!$C$8:$AO$501)} -> 100034.04 | R100: =J100-O100 -> -228 | S100: =L100-Q100 -> -98457.94
A101: =+B101&C101 -> Véhicules usagés | B101: Véhicules usagés
A102: =+B102&C102 -> Véhicules usagésRev. Finances | B102: Véhicules usagés | C102: Rev. Finances | D102: {=+SUMPRODUCT(('Budget original'!$A$8:$A$501=$A102)*('Budget original'!$C$3:$AO$3=D$2),'Budget original'!$C$8:$AO$501)} -> 0 | E102: =IF(D102=0,0,F102/D102) -> 0 | F102: {=+SUMPRODUCT(('Budget original'!$A$8:$A$501=$A102)*('Budget original'!$C$3:$AO$3=F$2),'Budget original'!$C$8:$AO$501)} -> 85500 | K102: =IF(J97=0,0,L102/J97) -> 648.386 | L102: =-SUMIFS(BV_Data_An_Cour!$P:$P,BV_Data_An_Cour!$U:$U,$B102,BV_Data_An_Cour!$V:$V,$C102,BV_Data_An_Cour!$W:$W,$L2) -> 3241.93 | N102: =L102-F102 -> -82258.07 | O102: {=+SUMPRODUCT(('Réel 2024'!$A$8:$A$501=$A102)*('Réel 2024'!$C$3:$AO$3=O$2),'Réel 2024'!$C$8:$AO$501)} -> 0 | P102: =IF(O102=0,0,Q102/O102) -> 0 | Q102: {=+SUMPRODUCT(('Réel 2024'!$A$8:$A$501=$A102)*('Réel 2024'!$C$3:$AO$3=Q$2),'Réel 2024'!$C$8:$AO$501)} -> 71393.32 | R102: =O102-K102 -> -648.386 | S102: =L102-Q102 -> -68151.39
A103: =+B103&C103 -> Véhicules usagésRev. Protections | B103: Véhicules usagés | C103: Rev. Protections | D103: {=+SUMPRODUCT(('Budget original'!$A$8:$A$501=$A103)*('Budget original'!$C$3:$AO$3=D$2),'Budget original'!$C$8:$AO$501)} -> 0 | E103: =IF(D103=0,0,F103/D103) -> 0 | F103: {=+SUMPRODUCT(('Budget original'!$A$8:$A$501=$A103)*('Budget original'!$C$3:$AO$3=F$2),'Budget original'!$C$8:$AO$501)} -> 191250 | K103: =IF(J97=0,0,L103/J97) -> 2259.6 | L103: =-SUMIFS(BV_Data_An_Cour!$P:$P,BV_Data_An_Cour!$U:$U,$B103,BV_Data_An_Cour!$V:$V,$C103,BV_Data_An_Cour!$W:$W,$L2) -> 11298 | N103: =L103-F103 -> -179952 | O103: {=+SUMPRODUCT(('Réel 2024'!$A$8:$A$501=$A103)*('Réel 2024'!$C$3:$AO$3=O$2),'Réel 2024'!$C$8:$AO$501)} -> 0 | P103: =IF(O103=0,0,Q103/O103) -> 0 | Q103: {=+SUMPRODUCT(('Réel 2024'!$A$8:$A$501=$A103)*('Réel 2024'!$C$3:$AO$3=Q$2),'Réel 2024'!$C$8:$AO$501)} -> 163941.69 | R103: =O103-K103 -> -2259.6 | S103: =L103-Q103 -> -152643.69
A104: =+B104&C104 -> Véhicules usagésRev. Autres | B104: Véhicules usagés | C104: Rev. Autres | D104: {=+SUMPRODUCT(('Budget original'!$A$8:$A$501=$A104)*('Budget original'!$C$3:$AO$3=D$2),'Budget original'!$C$8:$AO$501)} -> 0 | E104: =IF(D104=0,0,F104/D104) -> 0 | F104: {=+SUMPRODUCT(('Budget original'!$A$8:$A$501=$A104)*('Budget original'!$C$3:$AO$3=F$2),'Budget original'!$C$8:$AO$501)} -> 49500 | K104: =IF(J97=0,0,L104/J97) -> 387.6 | L104: =-SUMIFS(BV_Data_An_Cour!$P:$P,BV_Data_An_Cour!$U:$U,$B104,BV_Data_An_Cour!$V:$V,$C104,BV_Data_An_Cour!$W:$W,$L$2) -> 1938 | N104: =L104-F104 -> -47562 | O104: {=+SUMPRODUCT(('Réel 2024'!$A$8:$A$501=$A104)*('Réel 2024'!$C$3:$AO$3=O$2),'Réel 2024'!$C$8:$AO$501)} -> 63 | P104: =IF(O104=0,0,Q104/O104) -> 509.69905 | Q104: {=+SUMPRODUCT(('Réel 2024'!$A$8:$A$501=$A104)*('Réel 2024'!$C$3:$AO$3=Q$2),'Réel 2024'!$C$8:$AO$501)} -> 32111.04 | R104: =O104-K104 -> -324.6 | S104: =L104-Q104 -> -30173.04
...

Sheet BV_Data_An_Cour
A1: Description | B1: #Compte | C1: Solde d'ouverture | D1: Solde courant | E1: Solde de fin | F1: Type compte | G1: #Groupe | H1: Préfixe | I1: CUC/Mémo solde début | J1: CUC/Mémo solde actuel | K1: CUC/Mémo solde fin | L1: #Compte | M1: Description | N1: Solde d'ouverture | O1: Solde courant | P1: Solde de fin | Q1: Type compte | R1: #Groupe | S1: Préfixe | T1: Valid GL # | U1: Debits | V1: Classification | W1: $ / NB | X1: Ventes
A2: DEC. NB VENTE NEUF BMW AUTO | B2: 121B | F2: 1-Mémo | G2: 120 | H2: _ | I2: 0 | J2: 0.04 | K2: 0.04 | L2: =+B2 -> 121B | M2: =+A2 -> DEC. NB VENTE NEUF BMW AUTO | N2: =+IF(OR($Q2=Parametres!$G$2,$Q2=Parametres!$G$3),I2,C2) -> 0 | O2: =+IF(OR($Q2=Parametres!$G$2,$Q2=Parametres!$G$3),J2,D2) -> 0.04 | P2: =+IF(OR($Q2=Parametres!$G$2,$Q2=Parametres!$G$3),K2,E2) -> 0.04 | Q2: =+F2 -> 1-Mémo | R2: =+G2 -> 120 | S2: =+H2 -> _ | T2: =+VLOOKUP($L2,Data_Validation!$A:$D,1,0) -> #N/A | U2: =+VLOOKUP($L2,Data_Validation!$A:$D,3,0) -> #N/A | V2: =+VLOOKUP($L2,Data_Validation!$A:$D,4,0) -> #N/A | W2: =+VLOOKUP($L2,Data_Validation!$A:$E,5,0) -> #N/A | X2: =+VLOOKUP($L2,Data_Validation!$A:$F,6,0) -> #N/A
A3: DEC. NB VENTE NEUF BMW CAMION | B3: 121Z | F3: 1-Mémo | G3: 126 | H3: _ | I3: 0 | J3: 0.08 | K3: 0.08 | L3: =+B3 -> 121Z | M3: =+A3 -> DEC. NB VENTE NEUF BMW CAMION | N3: =+IF(OR($Q3=Parametres!$G$2,$Q3=Parametres!$G$3),I3,C3) -> 0 | O3: =+IF(OR($Q3=Parametres!$G$2,$Q3=Parametres!$G$3),J3,D3) -> 0.08 | P3: =+IF(OR($Q3=Parametres!$G$2,$Q3=Parametres!$G$3),K3,E3) -> 0.08 | Q3: =+F3 -> 1-Mémo | R3: =+G3 -> 126 | S3: =+H3 -> _ | T3: =+VLOOKUP($L3,Data_Validation!$A:$D,1,0) -> #N/A | U3: =+VLOOKUP($L3,Data_Validation!$A:$D,3,0) -> #N/A | V3: =+VLOOKUP($L3,Data_Validation!$A:$D,4,0) -> #N/A | W3: =+VLOOKUP($L3,Data_Validation!$A:$E,5,0) -> #N/A | X3: =+VLOOKUP($L3,Data_Validation!$A:$F,6,0) -> #N/A
A4: DEC. NB VENTE USAGE DETAIL | B4: 125B | F4: 1-Mémo | G4: 124 | H4: _ | I4: 0 | J4: 0.05 | K4: 0.05 | L4: =+B4 -> 125B | M4: =+A4 -> DEC. NB VENTE USAGE DETAIL | N4: =+IF(OR($Q4=Parametres!$G$2,$Q4=Parametres!$G$3),I4,C4) -> 0 | O4: =+IF(OR($Q4=Parametres!$G$2,$Q4=Parametres!$G$3),J4,D4) -> 0.05 | P4: =+IF(OR($Q4=Parametres!$G$2,$Q4=Parametres!$G$3),K4,E4) -> 0.05 | Q4: =+F4 -> 1-Mémo | R4: =+G4 -> 124 | S4: =+H4 -> _ | T4: =+VLOOKUP($L4,Data_Validation!$A:$D,1,0) -> #N/A | U4: =+VLOOKUP($L4,Data_Validation!$A:$D,3,0) -> #N/A | V4: =+VLOOKUP($L4,Data_Validation!$A:$D,4,0) -> #N/A | W4: =+VLOOKUP($L4,Data_Validation!$A:$E,5,0) -> #N/A | X4: =+VLOOKUP($L4,Data_Validation!$A:$F,6,0) -> #N/A
A5: DEC. NB VENTE USAGE GROS | B5: 128B | F5: 1-Mémo | G5: 127 | H5: _ | I5: 0 | J5: 0.02 | K5: 0.02 | L5: =+B5 -> 128B | M5: =+A5 -> DEC. NB VENTE USAGE GROS | N5: =+IF(OR($Q5=Parametres!$G$2,$Q5=Parametres!$G$3),I5,C5) -> 0 | O5: =+IF(OR($Q5=Parametres!$G$2,$Q5=Parametres!$G$3),J5,D5) -> 0.02 | P5: =+IF(OR($Q5=Parametres!$G$2,$Q5=Parametres!$G$3),K5,E5) -> 0.02 | Q5: =+F5 -> 1-Mémo | R5: =+G5 -> 127 | S5: =+H5 -> _ | T5: =+VLOOKUP($L5,Data_Validation!$A:$D,1,0) -> #N/A | U5: =+VLOOKUP($L5,Data_Validation!$A:$D,3,0) -> #N/A | V5: =+VLOOKUP($L5,Data_Validation!$A:$D,4,0) -> #N/A | W5: =+VLOOKUP($L5,Data_Validation!$A:$E,5,0) -> #N/A | X5: =+VLOOKUP($L5,Data_Validation!$A:$F,6,0) -> #N/A
A6: FONDS DE ROULEMENT REQUIS | B6: 145 | F6: 1-Mémo | G6: 145 | H6: _ | I6: 0 | J6: 1051751 | K6: 1051751 | L6: =+B6 -> 145 | M6: =+A6 -> FONDS DE ROULEMENT REQUIS | N6: =+IF(OR($Q6=Parametres!$G$2,$Q6=Parametres!$G$3),I6,C6) -> 0 | O6: =+IF(OR($Q6=Parametres!$G$2,$Q6=Parametres!$G$3),J6,D6) -> 1051751 | P6: =+IF(OR($Q6=Parametres!$G$2,$Q6=Parametres!$G$3),K6,E6) -> 1051751 | Q6: =+F6 -> 1-Mémo | R6: =+G6 -> 145 | S6: =+H6 -> _ | T6: =+VLOOKUP($L6,Data_Validation!$A:$D,1,0) -> 145 | U6: =+VLOOKUP($L6,Data_Validation!$A:$D,3,0) -> Autres | V6: =+VLOOKUP($L6,Data_Validation!$A:$D,4,0) -> 0 | W6: =+VLOOKUP($L6,Data_Validation!$A:$E,5,0) -> 0 | X6: =+VLOOKUP($L6,Data_Validation!$A:$F,6,0) -> 0
A7: NB EMP. PROPRIETAIRE ADMIN. | B7: 160Z | F7: 1-Mémo | G7: 160Z | H7: _ | I7: 0 | J7: 1 | K7: 1 | L7: =+B7 -> 160Z | M7: =+A7 -> NB EMP. PROPRIETAIRE ADMIN. | N7: =+IF(OR($Q7=Parametres!$G$2,$Q7=Parametres!$G$3),I7,C7) -> 0 | O7: =+IF(OR($Q7=Parametres!$G$2,$Q7=Parametres!$G$3),J7,D7) -> 1 | P7: =+IF(OR($Q7=Parametres!$G$2,$Q7=Parametres!$G$3),K7,E7) -> 1 | Q7: =+F7 -> 1-Mémo | R7: =+G7 -> 160Z | S7: =+H7 -> _ | T7: =+VLOOKUP($L7,Data_Validation!$A:$D,1,0) -> 160Z | U7: =+VLOOKUP($L7,Data_Validation!$A:$D,3,0) -> Autres | V7: =+VLOOKUP($L7,Data_Validation!$A:$D,4,0) -> 0 | W7: =+VLOOKUP($L7,Data_Validation!$A:$E,5,0) -> 0 | X7: =+VLOOKUP($L7,Data_Validation!$A:$F,6,0) -> 0
A8: NB EMP. SUPERVISION - NEUF | B8: 161A | F8: 1-Mémo | G8: 161 | H8: _ | I8: 0 | J8: 0.5 | K8: 0.5 | L8: =+B8 -> 161A | M8: =+A8 -> NB EMP. SUPERVISION - NEUF | N8: =+IF(OR($Q8=Parametres!$G$2,$Q8=Parametres!$G$3),I8,C8) -> 0 | O8: =+IF(OR($Q8=Parametres!$G$2,$Q8=Parametres!$G$3),J8,D8) -> 0.5 | P8: =+IF(OR($Q8=Parametres!$G$2,$Q8=Parametres!$G$3),K8,E8) -> 0.5 | Q8: =+F8 -> 1-Mémo | R8: =+G8 -> 161 | S8: =+H8 -> _ | T8: =+VLOOKUP($L8,Data_Validation!$A:$D,1,0) -> 161A | U8: =+VLOOKUP($L8,Data_Validation!$A:$D,3,0) -> Autres | V8: =+VLOOKUP($L8,Data_Validation!$A:$D,4,0) -> 0 | W8: =+VLOOKUP($L8,Data_Validation!$A:$E,5,0) -> 0 | X8: =+VLOOKUP($L8,Data_Validation!$A:$F,6,0) -> 0
A9: NB EMP. SUPERVISION - USAGE | B9: 161B | F9: 1-Mémo | G9: 161 | H9: _ | I9: 0 | J9: 0.5 | K9: 0.5 | L9: =+B9 -> 161B | M9: =+A9 -> NB EMP. SUPERVISION - USAGE | N9: =+IF(OR($Q9=Parametres!$G$2,$Q9=Parametres!$G$3),I9,C9) -> 0 | O9: =+IF(OR($Q9=Parametres!$G$2,$Q9=Parametres!$G$3),J9,D9) -> 0.5 | P9: =+IF(OR($Q9=Parametres!$G$2,$Q9=Parametres!$G$3),K9,E9) -> 0.5 | Q9: =+F9 -> 1-Mémo | R9: =+G9 -> 161 | S9: =+H9 -> _ | T9: =+VLOOKUP($L9,Data_Validation!$A:$D,1,0) -> 161B | U9: =+VLOOKUP($L9,Data_Validation!$A:$D,3,0) -> Autres | V9: =+VLOOKUP($L9,Data_Validation!$A:$D,4,0) -> 0 | W9: =+VLOOKUP($L9,Data_Validation!$A:$E,5,0) -> 0 | X9: =+VLOOKUP($L9,Data_Validation!$A:$F,6,0) -> 0
A10: NB EMP. SUPERBISION - SERVICE | B10: 161C | F10: 1-Mémo | G10: 161 | H10: _ | I10: 0 | J10: 0.5 | K10: 0.5 | L10: =+B10 -> 161C | M10: =+A10 -> NB EMP. SUPERBISION - SERVICE | N10: =+IF(OR($Q10=Parametres!$G$2,$Q10=Parametres!$G$3),I10,C10) -> 0 | O10: =+IF(OR($Q10=Parametres!$G$2,$Q10=Parametres!$G$3),J10,D10) -> 0.5 | P10: =+IF(OR($Q10=Parametres!$G$2,$Q10=Parametres!$G$3),K10,E10) -> 0.5 | Q10: =+F10 -> 1-Mémo | R10: =+G10 -> 161 | S10: =+H10 -> _ | T10: =+VLOOKUP($L10,Data_Validation!$A:$D,1,0) -> 161C | U10: =+VLOOKUP($L10,Data_Validation!$A:$D,3,0) -> Autres | V10: =+VLOOKUP($L10,Data_Validation!$A:$D,4,0) -> 0 | W10: =+VLOOKUP($L10,Data_Validation!$A:$E,5,0) -> 0 | X10: =+VLOOKUP($L10,Data_Validation!$A:$F,6,0) -> 0
A11: NB EMP. SUPERVISION - PIECES | B11: 161D | F11: 1-Mémo | G11: 161 | H11: _ | I11: 0 | J11: 0.5 | K11: 0.5 | L11: =+B11 -> 161D | M11: =+A11 -> NB EMP. SUPERVISION - PIECES | N11: =+IF(OR($Q11=Parametres!$G$2,$Q11=Parametres!$G$3),I11,C11) -> 0 | O11: =+IF(OR($Q11=Parametres!$G$2,$Q11=Parametres!$G$3),J11,D11) -> 0.5 | P11: =+IF(OR($Q11=Parametres!$G$2,$Q11=Parametres!$G$3),K11,E11) -> 0.5 | Q11: =+F11 -> 1-Mémo | R11: =+G11 -> 161 | S11: =+H11 -> _ | T11: =+VLOOKUP($L11,Data_Validation!$A:$D,1,0) -> 161D | U11: =+VLOOKUP($L11,Data_Validation!$A:$D,3,0) -> Autres | V11: =+VLOOKUP($L11,Data_Validation!$A:$D,4,0) -> 0 | W11: =+VLOOKUP($L11,Data_Validation!$A:$E,5,0) -> 0 | X11: =+VLOOKUP($L11,Data_Validation!$A:$F,6,0) -> 0
A12: NB EMP. SUPERVISION - ADMIN. | B12: 161Z | F12: 1-Mémo | G12: 161 | H12: _ | I12: 0 | J12: 1 | K12: 1 | L12: =+B12 -> 161Z | M12: =+A12 -> NB EMP. SUPERVISION - ADMIN. | N12: =+IF(OR($Q12=Parametres!$G$2,$Q12=Parametres!$G$3),I12,C12) -> 0 | O12: =+IF(OR($Q12=Parametres!$G$2,$Q12=Parametres!$G$3),J12,D12) -> 1 | P12: =+IF(OR($Q12=Parametres!$G$2,$Q12=Parametres!$G$3),K12,E12) -> 1 | Q12: =+F12 -> 1-Mémo | R12: =+G12 -> 161 | S12: =+H12 -> _ | T12: =+VLOOKUP($L12,Data_Validation!$A:$D,1,0) -> 161Z | U12: =+VLOOKUP($L12,Data_Validation!$A:$D,3,0) -> Autres | V12: =+VLOOKUP($L12,Data_Validation!$A:$D,4,0) -> 0 | W12: =+VLOOKUP($L12,Data_Validation!$A:$E,5,0) -> 0 | X12: =+VLOOKUP($L12,Data_Validation!$A:$F,6,0) -> 0
A13: NB EMP. VENDEURS BMW - F&I | B13: 164 | F13: 1-Mémo | G13: 164 | H13: _ | I13: 0 | J13: 1 | K13: 1 | L13: =+B13 -> 164 | M13: =+A13 -> NB EMP. VENDEURS BMW - F&I | N13: =+IF(OR($Q13=Parametres!$G$2,$Q13=Parametres!$G$3),I13,C13) -> 0 | O13: =+IF(OR($Q13=Parametres!$G$2,$Q13=Parametres!$G$3),J13,D13) -> 1 | P13: =+IF(OR($Q13=Parametres!$G$2,$Q13=Parametres!$G$3),K13,E13) -> 1 | Q13: =+F13 -> 1-Mémo | R13: =+G13 -> 164 | S13: =+H13 -> _ | T13: =+VLOOKUP($L13,Data_Validation!$A:$D,1,0) -> 164 | U13: =+VLOOKUP($L13,Data_Validation!$A:$D,3,0) -> Autres | V13: =+VLOOKUP($L13,Data_Validation!$A:$D,4,0) -> 0 | W13: =+VLOOKUP($L13,Data_Validation!$A:$E,5,0) -> 0 | X13: =+VLOOKUP($L13,Data_Validation!$A:$F,6,0) -> 0
... A31: NOMBRE DE JOURS OUVRABLE SERVICE | B31: 179 | F31: 1-Mémo | G31: 179 | H31: _ | I31: 0 | J31: 0.19 | K31: 0.19 | L31: =+B31 -> 179 | M31: =+A31 -> NOMBRE DE JOURS OUVRABLE SERVICE | N31: =+IF(OR($Q31=Parametres!$G$2,$Q31=Parametres!$G$3),I31,C31) -> 0 | O31: =+IF(OR($Q31=Parametres!$G$2,$Q31=Parametres!$G$3),J31,D31) -> 0.19 | P31: =+IF(OR($Q31=Parametres!$G$2,$Q31=Parametres!$G$3),K31,E31) -> 0.19 | Q31: =+F31 -> 1-Mémo | R31: =+G31 -> 179 | S31: =+H31 -> _ | T31: =+VLOOKUP($L31,Data_Validation!$A:$D,1,0) -> 179 | U31: =+VLOOKUP($L31,Data_Validation!$A:$D,3,0) -> Autres | V31: =+VLOOKUP($L31,Data_Validation!$A:$D,4,0) -> 0 | W31: =+VLOOKUP($L31,Data_Validation!$A:$E,5,0) -> 0 | X31: =+VLOOKUP($L31,Data_Validation!$A:$F,6,0) -> 0
A32: PETITE CAISSE | B32: 200 | C32: 0 | D32: 700 | E32: 700 | F32: 2-Actifs | G32: 200 | H32: _ | L32: =+B32 -> 200 | M32: =+A32 -> PETITE CAISSE | N32: =+IF(OR($Q32=Parametres!$G$2,$Q32=Parametres!$G$3),I32,C32) -> 0 | O32: =+IF(OR($Q32=Parametres!$G$2,$Q32=Parametres!$G$3),J32,D32) -> 700 | P32: =+IF(OR($Q32=Parametres!$G$2,$Q32=Parametres!$G$3),K32,E32) -> 700 | Q32: =+F32 -> 2-Actifs | R32: =+G32 -> 200 | S32: =+H32 -> _ | T32: =+VLOOKUP($L32,Data_Validation!$A:$D,1,0) -> 200 | U32: =+VLOOKUP($L32,Data_Validation!$A:$D,3,0) -> Bilan | V32: =+VLOOKUP($L32,Data_Validation!$A:$D,4,0) -> encaisse | W32: =+VLOOKUP($L32,Data_Validation!$A:$E,5,0) -> $ | X32: =+VLOOKUP($L32,Data_Validation!$A:$F,6,0) -> 0
A33: ENCAISSE | B33: 202 | C33: 0 | D33: 466733.09 | E33: 466733.09 | F33: 2-Actifs | G33: 202 | H33: _ | L33: =+B33 -> 202 | M33: =+A33 -> ENCAISSE | N33: =+IF(OR($Q33=Parametres!$G$2,$Q33=Parametres!$G$3),I33,C33) -> 0 | O33: =+IF(OR($Q33=Parametres!$G$2,$Q33=Parametres!$G$3),J33,D33) -> 466733.09 | P33: =+IF(OR($Q33=Parametres!$G$2,$Q33=Parametres!$G$3),K33,E33) -> 466733.09 | Q33: =+F33 -> 2-Actifs | R33: =+G33 -> 202 | S33: =+H33 -> _ | T33: =+VLOOKUP($L33,Data_Validation!$A:$D,1,0) -> 202 | U33: =+VLOOKUP($L33,Data_Validation!$A:$D,3,0) -> Bilan | V33: =+VLOOKUP($L33,Data_Validation!$A:$D,4,0) -> encaisse | W33: =+VLOOKUP($L33,Data_Validation!$A:$E,5,0) -> $ | X33: =+VLOOKUP($L33,Data_Validation!$A:$F,6,0) -> 0
A34: PAIEMENTS FORFAITAIRES FLOOR PLAN | B34: 202B | C34: 0 | D34: 1300000 | E34: 1300000 | F34: 2-Actifs | G34: 202 | H34: _ | L34: =+B34 -> 202B | M34: =+A34 -> PAIEMENTS FORFAITAIRES FLOOR PLAN | N34: =+IF(OR($Q34=Parametres!$G$2,$Q34=Parametres!$G$3),I34,C34) -> 0 | O34: =+IF(OR($Q34=Parametres!$G$2,$Q34=Parametres!$G$3),J34,D34) -> 1300000 | P34: =+IF(OR($Q34=Parametres!$G$2,$Q34=Parametres!$G$3),K34,E34) -> 1300000 | Q34: =+F34 -> 2-Actifs | R34: =+G34 -> 202 | S34: =+H34 -> _ | T34: =+VLOOKUP($L34,Data_Validation!$A:$D,1,0) -> 202B | U34: =+VLOOKUP($L34,Data_Validation!$A:$D,3,0) -> bilan | V34: =+VLOOKUP($L34,Data_Validation!$A:$D,4,0) -> Encaisse | W34: =+VLOOKUP($L34,Data_Validation!$A:$E,5,0) -> $ | X34: =+VLOOKUP($L34,Data_Validation!$A:$F,6,0) -> 0
A35: CONTRATS EN TRANSIT | B35: 205 | C35: 0 | D35: 232113.53 | E35: 232113.53 | F35: 2-Actifs | G35: 205 | H35: _ | L35: =+B35 -> 205 | M35: =+A35 -> CONTRATS EN TRANSIT | N35: =+IF(OR($Q35=Parametres!$G$2,$Q35=Parametres!$G$3),I35,C35) -> 0 | O35: =+IF(OR($Q35=Parametres!$G$2,$Q35=Parametres!$G$3),J35,D35) -> 232113.53 | P35: =+IF(OR($Q35=Parametres!$G$2,$Q35=Parametres!$G$3),K35,E35) -> 232113.53 | Q35: =+F35 -> 2-Actifs | R35: =+G35 -> 205 | S35: =+H35 -> _ | T35: =+VLOOKUP($L35,Data_Validation!$A:$D,1,0) -> 205 | U35: =+VLOOKUP($L35,Data_Validation!$A:$D,3,0) -> Bilan | V35: =+VLOOKUP($L35,Data_Validation!$A:$D,4,0) -> Recevables Contrats en Transit | W35: =+VLOOKUP($L35,Data_Validation!$A:$E,5,0) -> $ | X35: =+VLOOKUP($L35,Data_Validation!$A:$F,6,0) -> 0
A36: RECEVABLES VEHICULES | B36: 210 | C36: 0 | D36: -1253.62 | E36: -1253.62 | F36: 2-Actifs | G36: 210 | H36: _ | L36: =+B36 -> 210 | M36: =+A36 -> RECEVABLES VEHICULES | N36: =+IF(OR($Q36=Parametres!$G$2,$Q36=Parametres!$G$3),I36,C36) -> 0 | O36: =+IF(OR($Q36=Parametres!$G$2,$Q36=Parametres!$G$3),J36,D36) -> -1253.62 | P36: =+IF(OR($Q36=Parametres!$G$2,$Q36=Parametres!$G$3),K36,E36) -> -1253.62 | Q36: =+F36 -> 2-Actifs | R36: =+G36 -> 210 | S36: =+H36 -> _ | T36: =+VLOOKUP($L36,Data_Validation!$A:$D,1,0) -> 210 | U36: =+VLOOKUP($L36,Data_Validation!$A:$D,3,0) -> Bilan | V36: =+VLOOKUP($L36,Data_Validation!$A:$D,4,0) -> Recevables Véhicules | W36: =+VLOOKUP($L36,Data_Validation!$A:$E,5,0) -> $ | X36: =+VLOOKUP($L36,Data_Validation!$A:$F,6,0) -> 0
A37: WHOLESALE & ECHANGE A/R | B37: 210A | C37: 0 | D37: 307502.98 | E37: 307502.98 | F37: 2-Actifs | G37: 210 | H37: _ | L37: =+B37 -> 210A | M37: =+A37 -> WHOLESALE & ECHANGE A/R | N37: =+IF(OR($Q37=Parametres!$G$2,$Q37=Parametres!$G$3),I37,C37) -> 0 | O37: =+IF(OR($Q37=Parametres!$G$2,$Q37=Parametres!$G$3),J37,D37) -> 307502.98 | P37: =+IF(OR($Q37=Parametres!$G$2,$Q37=Parametres!$G$3),K37,E37) -> 307502.98 | Q37: =+F37 -> 2-Actifs | R37: =+G37 -> 210 | S37: =+H37 -> _ | T37: =+VLOOKUP($L37,Data_Validation!$A:$D,1,0) -> 210A | U37: =+VLOOKUP($L37,Data_Validation!$A:$D,3,0) -> Bilan | V37: =+VLOOKUP($L37,Data_Validation!$A:$D,4,0) -> Recevables Véhicules | W37: =+VLOOKUP($L37,Data_Validation!$A:$E,5,0) -> $ | X37: =+VLOOKUP($L37,Data_Validation!$A:$F,6,0) -> 0
A38: RECEVABLES PIECES ET SERVICE | B38: 220 | C38: 0 | D38: 42239.3 | E38: 42239.3 | F38: 2-Actifs | G38: 220 | H38: _ | L38: =+B38 -> 220 | M38: =+A38 -> RECEVABLES PIECES ET SERVICE | N38: =+IF(OR($Q38=Parametres!$G$2,$Q38=Parametres!$G$3),I38,C38) -> 0 | O38: =+IF(OR($Q38=Parametres!$G$2,$Q38=Parametres!$G$3),J38,D38) -> 42239.3 | P38: =+IF(OR($Q38=Parametres!$G$2,$Q38=Parametres!$G$3),K38,E38) -> 42239.3 | Q38: =+F38 -> 2-Actifs | R38: =+G38 -> 220 | S38: =+H38 -> _ | T38: =+VLOOKUP($L38,Data_Validation!$A:$D,1,0) -> 220 | U38: =+VLOOKUP($L38,Data_Validation!$A:$D,3,0) -> Bilan | V38: =+VLOOKUP($L38,Data_Validation!$A:$D,4,0) -> Recevables Pièces et Service | W38: =+VLOOKUP($L38,Data_Validation!$A:$E,5,0) -> $ | X38: =+VLOOKUP($L38,Data_Validation!$A:$F,6,0) -> 0
A39: RECEVABLE RECOURS COLLECTIF | B39: 220C | C39: 0 | D39: -10000 | E39: -10000 | F39: 2-Actifs | G39: 220 | H39: _ | L39: =+B39 -> 220C | M39: =+A39 -> RECEVABLE RECOURS COLLECTIF | N39: =+IF(OR($Q39=Parametres!$G$2,$Q39=Parametres!$G$3),I39,C39) -> 0 | O39: =+IF(OR($Q39=Parametres!$G$2,$Q39=Parametres!$G$3),J39,D39) -> -10000 | P39: =+IF(OR($Q39=Parametres!$G$2,$Q39=Parametres!$G$3),K39,E39) -> -10000 | Q39: =+F39 -> 2-Actifs | R39: =+G39 -> 220 | S39: =+H39 -> _ | T39: =+VLOOKUP($L39,Data_Validation!$A:$D,1,0) -> 220C | U39: =+VLOOKUP($L39,Data_Validation!$A:$D,3,0) -> Bilan | V39: =+VLOOKUP($L39,Data_Validation!$A:$D,4,0) -> Autres Courus | W39: =+VLOOKUP($L39,Data_Validation!$A:$E,5,0) -> $ | X39: =+VLOOKUP($L39,Data_Validation!$A:$F,6,0) -> 0
A40: BONIS A/R MANUFACTURIER | B40: 221 | C40: 0 | D40: 39769.55 | E40: 39769.55 | F40: 2-Actifs | G40: 221 | H40: _ | L40: =+B40 -> 221 | M40: =+A40 -> BONIS A/R MANUFACTURIER | N40: =+IF(OR($Q40=Parametres!$G$2,$Q40=Parametres!$G$3),I40,C40) -> 0 | O40: =+IF(OR($Q40=Parametres!$G$2,$Q40=Parametres!$G$3),J40,D40) -> 39769.55 | P40: =+IF(OR($Q40=Parametres!$G$2,$Q40=Parametres!$G$3),K40,E40) -> 39769.55 | Q40: =+F40 -> 2-Actifs | R40: =+G40 -> 221 | S40: =+H40 -> _ | T40: =+VLOOKUP($L40,Data_Validation!$A:$D,1,0) -> 221 | U40: =+VLOOKUP($L40,Data_Validation!$A:$D,3,0) -> Bilan | V40: =+VLOOKUP($L40,Data_Validation!$A:$D,4,0) -> Recevables Manufacturier | W40: =+VLOOKUP($L40,Data_Validation!$A:$E,5,0) -> $ | X40: =+VLOOKUP($L40,Data_Validation!$A:$F,6,0) -> 0
A41: PROGRAMMES A/R MANUFACTURIER | B41: 221A | C41: 0 | D41: 34772 | E41: 34772 | F41: 2-Actifs | G41: 221A | H41: _ | L41: =+B41 -> 221A | M41: =+A41 -> PROGRAMMES A/R MANUFACTURIER | N41: =+IF(OR($Q41=Parametres!$G$2,$Q41=Parametres!$G$3),I41,C41) -> 0 | O41: =+IF(OR($Q41=Parametres!$G$2,$Q41=Parametres!$G$3),J41,D41) -> 34772 | P41: =+IF(OR($Q41=Parametres!$G$2,$Q41=Parametres!$G$3),K41,E41) -> 34772 | Q41: =+F41 -> 2-Actifs | R41: =+G41 -> 221A | S41: =+H41 -> _ | T41: =+VLOOKUP($L41,Data_Validation!$A:$D,1,0) -> 221A | U41: =+VLOOKUP($L41,Data_Validation!$A:$D,3,0) -> Bilan | V41: =+VLOOKUP($L41,Data_Validation!$A:$D,4,0) -> Recevables Manufacturier | W41: =+VLOOKUP($L41,Data_Validation!$A:$E,5,0) -> $ | X41: =+VLOOKUP($L41,Data_Validation!$A:$F,6,0) -> 0
A42: RECLAMATION GARANTIE A/R BMW | B42: 222A | C42: 0 | D42: 13736.45 | E42: 13736.45 | F42: 2-Actifs | G42: 222 | H42: _ | L42: =+B42 -> 222A | M42: =+A42 -> RECLAMATION GARANTIE A/R BMW | N42: =+IF(OR($Q42=Parametres!$G$2,$Q42=Parametres!$G$3),I42,C42) -> 0 | O42: =+IF(OR($Q42=Parametres!$G$2,$Q42=Parametres!$G$3),J42,D42) -> 13736.45 | P42: =+IF(OR($Q42=Parametres!$G$2,$Q42=Parametres!$G$3),K42,E42) -> 13736.45 | Q42: =+F42 -> 2-Actifs | R42: =+G42 -> 222 | S42: =+H42 -> _ | T42: =+VLOOKUP($L42,Data_Validation!$A:$D,1,0) -> 222A | U42: =+VLOOKUP($L42,Data_Validation!$A:$D,3,0) -> Bilan | V42: =+VLOOKUP($L42,Data_Validation!$A:$D,4,0) -> Recevables Garantie Manufacturier | W42: =+VLOOKUP($L42,Data_Validation!$A:$E,5,0) -> $ | X42: =+VLOOKUP($L42,Data_Validation!$A:$F,6,0) -> 0
A43: INV. VOITURES NEUVES BMW | B43: 230 | C43: 0 | D43: 1471532 | E43: 1471532 | F43: 2-Actifs | G43: 230 | H43: _ | L43: =+B43 -> 230 | M43: =+A43 -> INV. VOITURES NEUVES BMW | N43: =+IF(OR($Q43=Parametres!$G$2,$Q43=Parametres!$G$3),I43,C43) -> 0 | O43: =+IF(OR($Q43=Parametres!$G$2,$Q43=Parametres!$G$3),J43,D43) -> 1471532 | P43: =+IF(OR($Q43=Parametres!$G$2,$Q43=Parametres!$G$3),K43,E43) -> 1471532 | Q43: =+F43 -> 2-Actifs | R43: =+G43 -> 230 | S43: =+H43 -> _ | T43: =+VLOOKUP($L43,Data_Validation!$A:$D,1,0) -> 230 | U43: =+VLOOKUP($L43,Data_Validation!$A:$D,3,0) -> Bilan | V43: =+VLOOKUP($L43,Data_Validation!$A:$D,4,0) -> Inventaire Véhicules Neufs | W43: =+VLOOKUP($L43,Data_Validation!$A:$E,5,0) -> $ | X43: =+VLOOKUP($L43,Data_Validation!$A:$F,6,0) -> 0
... A373: REVENU RBSC BMW | B373: 815 | C373: 0 | D373: -20598 | E373: -20598 | F373: 8-Autres revenus | G373: 815 | H373: _ | L373: =+B373 -> 815 | M373: =+A373 -> REVENU RBSC BMW | N373: =+IF(OR($Q373=Parametres!$G$2,$Q373=Parametres!$G$3),I373,C373) -> 0 | O373: =+IF(OR($Q373=Parametres!$G$2,$Q373=Parametres!$G$3),J373,D373) -> -20598 | P373: =+IF(OR($Q373=Parametres!$G$2,$Q373=Parametres!$G$3),K373,E373) -> -20598 | Q373: =+F373 -> 8-Autres revenus | R373: =+G373 -> 815 | S373: =+H373 -> _ | T373: =+VLOOKUP($L373,Data_Validation!$A:$D,1,0) -> 815 | U373: =+VLOOKUP($L373,Data_Validation!$A:$D,3,0) -> Véhicules neufs | V373: =+VLOOKUP($L373,Data_Validation!$A:$D,4,0) -> RBSC NEUF | W373: =+VLOOKUP($L373,Data_Validation!$A:$E,5,0) -> $ | X373: =+VLOOKUP($L373,Data_Validation!$A:$F,6,0) -> 0
A374: # DE VOITURES NEUVES BMW | B374: 230@ | F374: 10-Compte compteur | G374: 230 | H374: _ | I374: 0 | J374: 18 | K374: 18 | L374: =+B374 -> 230@ | M374: =+A374 -> # DE VOITURES NEUVES BMW | N374: =+IF(OR($Q374=Parametres!$G$2,$Q374=Parametres!$G$3),I374,C374) -> 0 | O374: =+IF(OR($Q374=Parametres!$G$2,$Q374=Parametres!$G$3),J374,D374) -> 18 | P374: =+IF(OR($Q374=Parametres!$G$2,$Q374=Parametres!$G$3),K374,E374) -> 18 | Q374: =+F374 -> 10-Compte compteur | R374: =+G374 -> 230 | S374: =+H374 -> _ | T374: =+VLOOKUP($L374,Data_Validation!$A:$D,1,0) -> 230@ | U374: =+VLOOKUP($L374,Data_Validation!$A:$D,3,0) -> Autres | V374: =+VLOOKUP($L374,Data_Validation!$A:$D,4,0) -> 0 | W374: =+VLOOKUP($L374,Data_Validation!$A:$E,5,0) -> 0 | X374: =+VLOOKUP($L374,Data_Validation!$A:$F,6,0) -> 0
A375: # DE CAMIONS NEUFS BMW | B375: 232@ | F375: 10-Compte compteur | G375: 232 | H375: _ | I375: 0 | J375: 42 | K375: 42 | L375: =+B375 -> 232@ | M375: =+A375 -> # DE CAMIONS NEUFS BMW | N375: =+IF(OR($Q375=Parametres!$G$2,$Q375=Parametres!$G$3),I375,C375) -> 0 | O375: =+IF(OR($Q375=Parametres!$G$2,$Q375=Parametres!$G$3),J375,D375) -> 42 | P375: =+IF(OR($Q375=Parametres!$G$2,$Q375=Parametres!$G$3),K375,E375) -> 42 | Q375: =+F375 -> 10-Compte compteur | R375: =+G375 -> 232 | S375: =+H375 -> _ | T375: =+VLOOKUP($L375,Data_Validation!$A:$D,1,0) -> 232@ | U375: =+VLOOKUP($L375,Data_Validation!$A:$D,3,0) -> Autres | V375: =+VLOOKUP($L375,Data_Validation!$A:$D,4,0) -> 0 | W375: =+VLOOKUP($L375,Data_Validation!$A:$E,5,0) -> 0 | X375: =+VLOOKUP($L375,Data_Validation!$A:$F,6,0) -> 0
A376: # OF INVENTAIRE VEHICULES I | B376: 234@ | F376: 10-Compte compteur | G376: 234 | H376: _ | I376: 0 | J376: 14 | K376: 14 | L376: =+B376 -> 234@ | M376: =+A376 -> # OF INVENTAIRE VEHICULES I | N376: =+IF(OR($Q376=Parametres!$G$2,$Q376=Parametres!$G$3),I376,C376) -> 0 | O376: =+IF(OR($Q376=Parametres!$G$2,$Q376=Parametres!$G$3),J376,D376) -> 14 | P376: =+IF(OR($Q376=Parametres!$G$2,$Q376=Parametres!$G$3),K376,E376) -> 14 | Q376: =+F376 -> 10-Compte compteur | R376: =+G376 -> 234 | S376: =+H376 -> _ | T376: =+VLOOKUP($L376,Data_Validation!$A:$D,1,0) -> 234@ | U376: =+VLOOKUP($L376,Data_Validation!$A:$D,3,0) -> Autres | V376: =+VLOOKUP($L376,Data_Validation!$A:$D,4,0) -> 0 | W376: =+VLOOKUP($L376,Data_Validation!$A:$E,5,0) -> 0 | X376: =+VLOOKUP($L376,Data_Validation!$A:$F,6,0) -> 0
A377: # DE VOITURES USAGEES BMW | B377: 240A@ | F377: 10-Compte compteur | G377: 240A | H377: _ | I377: 0 | J377: 9 | K377: 9 | L377: =+B377 -> 240A@ | M377: =+A377 -> # DE VOITURES USAGEES BMW | N377: =+IF(OR($Q377=Parametres!$G$2,$Q377=Parametres!$G$3),I377,C377) -> 0 | O377: =+IF(OR($Q377=Parametres!$G$2,$Q377=Parametres!$G$3),J377,D377) -> 9 | P377: =+IF(OR($Q377=Parametres!$G$2,$Q377=Parametres!$G$3),K377,E377) -> 9 | Q377: =+F377 -> 10-Compte compteur | R377: =+G377 -> 240A | S377: =+H377 -> _ | T377: =+VLOOKUP($L377,Data_Validation!$A:$D,1,0) -> 240A@ | U377: =+VLOOKUP($L377,Data_Validation!$A:$D,3,0) -> Autres | V377: =+VLOOKUP($L377,Data_Validation!$A:$D,4,0) -> 0 | W377: =+VLOOKUP($L377,Data_Validation!$A:$E,5,0) -> 0 | X377: =+VLOOKUP($L377,Data_Validation!$A:$F,6,0) -> 0
A378: # DE VEHICULES USAGES AUTRES | B378: 240C@ | F378: 10-Compte compteur | G378: 240C | H378: _ | I378: 0 | J378: 7 | K378: 7 | L378: =+B378 -> 240C@ | M378: =+A378 -> # DE VEHICULES USAGES AUTRES | N378: =+IF(OR($Q378=Parametres!$G$2,$Q378=Parametres!$G$3),I378,C378) -> 0 | O378: =+IF(OR($Q378=Parametres!$G$2,$Q378=Parametres!$G$3),J378,D378) -> 7 | P378: =+IF(OR($Q378=Parametres!$G$2,$Q378=Parametres!$G$3),K378,E378) -> 7 | Q378: =+F378 -> 10-Compte compteur | R378: =+G378 -> 240C | S378: =+H378 -> _ | T378: =+VLOOKUP($L378,Data_Validation!$A:$D,1,0) -> 240C@ | U378: =+VLOOKUP($L378,Data_Validation!$A:$D,3,0) -> Autres | V378: =+VLOOKUP($L378,Data_Validation!$A:$D,4,0) -> 0 | W378: =+VLOOKUP($L378,Data_Validation!$A:$E,5,0) -> 0 | X378: =+VLOOKUP($L378,Data_Validation!$A:$F,6,0) -> 0
A379: # DE CAMIONS USAGES BMW | B379: 242A@ | F379: 10-Compte compteur | G379: 242A | H379: _ | I379: 0 | J379: 11 | K379: 11 | L379: =+B379 -> 242A@ | M379: =+A379 -> # DE CAMIONS USAGES BMW | N379: =+IF(OR($Q379=Parametres!$G$2,$Q379=Parametres!$G$3),I379,C379) -> 0 | O379: =+IF(OR($Q379=Parametres!$G$2,$Q379=Parametres!$G$3),J379,D379) -> 11 | P379: =+IF(OR($Q379=Parametres!$G$2,$Q379=Parametres!$G$3),K379,E379) -> 11 | Q379: =+F379 -> 10-Compte compteur | R379: =+G379 -> 242A | S379: =+H379 -> _ | T379: =+VLOOKUP($L379,Data_Validation!$A:$D,1,0) -> 242A@ | U379: =+VLOOKUP($L379,Data_Validation!$A:$D,3,0) -> Autres | V379: =+VLOOKUP($L379,Data_Validation!$A:$D,4,0) -> 0 | W379: =+VLOOKUP($L379,Data_Validation!$A:$E,5,0) -> 0 | X379: =+VLOOKUP($L379,Data_Validation!$A:$F,6,0) -> 0
A380: M340I XDRIVE | B380: 412C@ | F380: 10-Compte compteur | G380: 412C | H380: _ | I380: 0 | J380: -1 | K380: -1 | L380: =+B380 -> 412C@ | M380: =+A380 -> M340I XDRIVE | N380: =+IF(OR($Q380=Parametres!$G$2,$Q380=Parametres!$G$3),I380,C380) -> 0 | O380: =+IF(OR($Q380=Parametres!$G$2,$Q380=Parametres!$G$3),J380,D380) -> -1 | P380: =+IF(OR($Q380=Parametres!$G$2,$Q380=Parametres!$G$3),K380,E380) -> -1 | Q380: =+F380 -> 10-Compte compteur | R380: =+G380 -> 412C | S380: =+H380 -> _ | T380: =+VLOOKUP($L380,Data_Validation!$A:$D,1,0) -> 412C@ | U380: =+VLOOKUP($L380,Data_Validation!$A:$D,3,0) -> Véhicules neufs | V380: =+VLOOKUP($L380,Data_Validation!$A:$D,4,0) -> Autos détail | W380: =+VLOOKUP($L380,Data_Validation!$A:$E,5,0) -> NB | X380: =+VLOOKUP($L380,Data_Validation!$A:$F,6,0) -> 0
A381: # DE VTE - X1 XDRIVE 28I | B381: 416@ | F381: 10-Compte compteur | G381: 416 | H381: _ | I381: 0 | J381: -1 | K381: -1 | L381: =+B381 -> 416@ | M381: =+A381 -> # DE VTE - X1 XDRIVE 28I | N381: =+IF(OR($Q381=Parametres!$G$2,$Q381=Parametres!$G$3),I381,C381) -> 0 | O381: =+IF(OR($Q381=Parametres!$G$2,$Q381=Parametres!$G$3),J381,D381) -> -1 | P381: =+IF(OR($Q381=Parametres!$G$2,$Q381=Parametres!$G$3),K381,E381) -> -1 | Q381: =+F381 -> 10-Compte compteur | R381: =+G381 -> 416 | S381: =+H381 -> _ | T381: =+VLOOKUP($L381,Data_Validation!$A:$D,1,0) -> 416@ | U381: =+VLOOKUP($L381,Data_Validation!$A:$D,3,0) -> Véhicules neufs | V381: =+VLOOKUP($L381,Data_Validation!$A:$D,4,0) -> Camions détail | W381: =+VLOOKUP($L381,Data_Validation!$A:$E,5,0) -> nb | X381: =+VLOOKUP($L381,Data_Validation!$A:$F,6,0) -> 0
A382: # DE VTE - FLEET VOITURE BMW | B382: 419@ | F382: 10-Compte compteur | G382: 419 | H382: _ | I382: 0 | J382: -3 | K382: -3 | L382: =+B382 -> 419@ | M382: =+A382 -> # DE VTE - FLEET VOITURE BMW | N382: =+IF(OR($Q382=Parametres!$G$2,$Q382=Parametres!$G$3),I382,C382) -> 0 | O382: =+IF(OR($Q382=Parametres!$G$2,$Q382=Parametres!$G$3),J382,D382) -> -3 | P382: =+IF(OR($Q382=Parametres!$G$2,$Q382=Parametres!$G$3),K382,E382) -> -3 | Q382: =+F382 -> 10-Compte compteur | R382: =+G382 -> 419 | S382: =+H382 -> _ | T382: =+VLOOKUP($L382,Data_Validation!$A:$D,1,0) -> 419@ | U382: =+VLOOKUP($L382,Data_Validation!$A:$D,3,0) -> Véhicules neufs | V382: =+VLOOKUP($L382,Data_Validation!$A:$D,4,0) -> Flottes | W382: =+VLOOKUP($L382,Data_Validation!$A:$E,5,0) -> nb | X382: =+VLOOKUP($L382,Data_Validation!$A:$F,6,0) -> 0
A383: # DE VTE - FLEET CAMION BMW | B383: 419A@ | F383: 10-Compte compteur | G383: 419A | H383: _ | I383: 0 | J383: -1 | K383: -1 | L383: =+B383 -> 419A@ | M383: =+A383 -> # DE VTE - FLEET CAMION BMW | N383: =+IF(OR($Q383=Parametres!$G$2,$Q383=Parametres!$G$3),I383,C383) -> 0 | O383: =+IF(OR($Q383=Parametres!$G$2,$Q383=Parametres!$G$3),J383,D383) -> -1 | P383: =+IF(OR($Q383=Parametres!$G$2,$Q383=Parametres!$G$3),K383,E383) -> -1 | Q383: =+F383 -> 10-Compte compteur | R383: =+G383 -> 419A | S383: =+H383 -> _ | T383: =+VLOOKUP($L383,Data_Validation!$A:$D,1,0) -> 419A@ | U383: =+VLOOKUP($L383,Data_Validation!$A:$D,3,0) -> Véhicules neufs | V383: =+VLOOKUP($L383,Data_Validation!$A:$D,4,0) -> Flottes | W383: =+VLOOKUP($L383,Data_Validation!$A:$E,5,0) -> nb | X383: =+VLOOKUP($L383,Data_Validation!$A:$F,6,0) -> 0
A384: # DE VTE - X6 M60i | B384: 422C@ | F384: 10-Compte compteur | G384: 422C | H384: _ | I384: 0 | J384: -2 | K384: -2 | L384: =+B384 -> 422C@ | M384: =+A384 -> # DE VTE - X6 M60i | N384: =+IF(OR($Q384=Parametres!$G$2,$Q384=Parametres!$G$3),I384,C384) -> 0 | O384: =+IF(OR($Q384=Parametres!$G$2,$Q384=Parametres!$G$3),J384,D384) -> -2 | P384: =+IF(OR($Q384=Parametres!$G$2,$Q384=Parametres!$G$3),K384,E384) -> -2 | Q384: =+F384 -> 10-Compte compteur | R384: =+G384 -> 422C | S384: =+H384 -> _ | T384: =+VLOOKUP($L384,Data_Validation!$A:$D,1,0) -> 422C@ | U384: =+VLOOKUP($L384,Data_Validation!$A:$D,3,0) -> Véhicules neufs | V384: =+VLOOKUP($L384,Data_Validation!$A:$D,4,0) -> Camions détail | W384: =+VLOOKUP($L384,Data_Validation!$A:$E,5,0) -> NB | X384: =+VLOOKUP($L384,Data_Validation!$A:$F,6,0) -> 0
A385: # DE VTE - X5 xDRIVE50e | B385: 423F@ | F385: 10-Compte compteur | G385: 423F | H385: _ | I385: 0 | J385: -1 | K385: -1 | L385: =+B385 -> 423F@ | M385: =+A385 -> # DE VTE - X5 xDRIVE50e | N385: =+IF(OR($Q385=Parametres!$G$2,$Q385=Parametres!$G$3),I385,C385) -> 0 | O385: =+IF(OR($Q385=Parametres!$G$2,$Q385=Parametres!$G$3),J385,D385) -> -1 | P385: =+IF(OR($Q385=Parametres!$G$2,$Q385=Parametres!$G$3),K385,E385) -> -1 | Q385: =+F385 -> 10-Compte compteur | R385: =+G385 -> 423F | S385: =+H385 -> _ | T385: =+VLOOKUP($L385,Data_Validation!$A:$D,1,0) -> 423F@ | U385: =+VLOOKUP($L385,Data_Validation!$A:$D,3,0) -> Véhicules neufs | V385: =+VLOOKUP($L385,Data_Validation!$A:$D,4,0) -> Camions détail | W385: =+VLOOKUP($L385,Data_Validation!$A:$E,5,0) -> NB | X385: =+VLOOKUP($L385,Data_Validation!$A:$F,6,0) -> 0
... A444: # DE VTE - HUILE & GRAISSE | B444: 489B@ | F444: 10-Compte compteur | G444: 489A | H444: _ | I444: 0 | J444: -76 | K444: -76 | L444: =+B444 -> 489B@ | M444: =+A444 -> # DE VTE - HUILE & GRAISSE | N444: =+IF(OR($Q444=Parametres!$G$2,$Q444=Parametres!$G$3),I444,C444) -> 0 | O444: =+IF(OR($Q444=Parametres!$G$2,$Q444=Parametres!$G$3),J444,D444) -> -76 | P444: =+IF(OR($Q444=Parametres!$G$2,$Q444=Parametres!$G$3),K444,E444) -> -76 | Q444: =+F444 -> 10-Compte compteur | R444: =+G444 -> 489A | S444: =+H444 -> _ | T444: =+VLOOKUP($L444,Data_Validation!$A:$D,1,0) -> 489B@ | U444: =+VLOOKUP($L444,Data_Validation!$A:$D,3,0) -> pièces | V444: =+VLOOKUP($L444,Data_Validation!$A:$D,4,0) -> Huiles et Graisse | W444: =+VLOOKUP($L444,Data_Validation!$A:$E,5,0) -> nb | X444: =+VLOOKUP($L444,Data_Validation!$A:$F,6,0) -> 0
L445: =+B445 -> 0 | M445: =+A445 -> 0 | N445: =+IF(OR($Q445=Parametres!$G$2,$Q445=Parametres!$G$3),I445,C445) -> 0 | O445: =+IF(OR($Q445=Parametres!$G$2,$Q445=Parametres!$G$3),J445,D445) -> 0 | P445: =+IF(OR($Q445=Parametres!$G$2,$Q445=Parametres!$G$3),K445,E445) -> 0 | Q445: =+F445 -> 0 | R445: =+G445 -> 0 | S445: =+H445 -> 0 | T445: =+VLOOKUP($L445,Data_Validation!$A:$D,1,0) -> #N/A | U445: =+VLOOKUP($L445,Data_Validation!$A:$D,3,0) -> #N/A | V445: =+VLOOKUP($L445,Data_Validation!$A:$D,4,0) -> #N/A | W445: =+VLOOKUP($L445,Data_Validation!$A:$E,5,0) -> #N/A | X445: =+VLOOKUP($L445,Data_Validation!$A:$F,6,0) -> #N/A
L446: =+B446 -> 0 | M446: =+A446 -> 0 | N446: =+IF(OR($Q446=Parametres!$G$2,$Q446=Parametres!$G$3),I446,C446) -> 0 | O446: =+IF(OR($Q446=Parametres!$G$2,$Q446=Parametres!$G$3),J446,D446) -> 0 | P446: =+IF(OR($Q446=Parametres!$G$2,$Q446=Parametres!$G$3),K446,E446) -> 0 | Q446: =+F446 -> 0 | R446: =+G446 -> 0 | S446: =+H446 -> 0 | T446: =+VLOOKUP($L446,Data_Validation!$A:$D,1,0) -> #N/A | U446: =+VLOOKUP($L446,Data_Validation!$A:$D,3,0) -> #N/A | V446: =+VLOOKUP($L446,Data_Validation!$A:$D,4,0) -> #N/A | W446: =+VLOOKUP($L446,Data_Validation!$A:$E,5,0) -> #N/A | X446: =+VLOOKUP($L446,Data_Validation!$A:$F,6,0) -> #N/A
L447: =+B447 -> 0 | M447: =+A447 -> 0 | N447: =+IF(OR($Q447=Parametres!$G$2,$Q447=Parametres!$G$3),I447,C447) -> 0 | O447: =+IF(OR($Q447=Parametres!$G$2,$Q447=Parametres!$G$3),J447,D447) -> 0 | P447: =+IF(OR($Q447=Parametres!$G$2,$Q447=Parametres!$G$3),K447,E447) -> 0 | Q447: =+F447 -> 0 | R447: =+G447 -> 0 | S447: =+H447 -> 0 | T447: =+VLOOKUP($L447,Data_Validation!$A:$D,1,0) -> #N/A | U447: =+VLOOKUP($L447,Data_Validation!$A:$D,3,0) -> #N/A | V447: =+VLOOKUP($L447,Data_Validation!$A:$D,4,0) -> #N/A | W447: =+VLOOKUP($L447,Data_Validation!$A:$E,5,0) -> #N/A | X447: =+VLOOKUP($L447,Data_Validation!$A:$F,6,0) -> #N/A
L448: =+B448 -> 0 | M448: =+A448 -> 0 | N448: =+IF(OR($Q448=Parametres!$G$2,$Q448=Parametres!$G$3),I448,C448) -> 0 | O448: =+IF(OR($Q448=Parametres!$G$2,$Q448=Parametres!$G$3),J448,D448) -> 0 | P448: =+IF(OR($Q448=Parametres!$G$2,$Q448=Parametres!$G$3),K448,E448) -> 0 | Q448: =+F448 -> 0 | R448: =+G448 -> 0 | S448: =+H448 -> 0 | T448: =+VLOOKUP($L448,Data_Validation!$A:$D,1,0) -> #N/A | U448: =+VLOOKUP($L448,Data_Validation!$A:$D,3,0) -> #N/A | V448: =+VLOOKUP($L448,Data_Validation!$A:$D,4,0) -> #N/A | W448: =+VLOOKUP($L448,Data_Validation!$A:$E,5,0) -> #N/A | X448: =+VLOOKUP($L448,Data_Validation!$A:$F,6,0) -> #N/A
L449: =+B449 -> 0 | M449: =+A449 -> 0 | N449: =+IF(OR($Q449=Parametres!$G$2,$Q449=Parametres!$G$3),I449,C449) -> 0 | O449: =+IF(OR($Q449=Parametres!$G$2,$Q449=Parametres!$G$3),J449,D449) -> 0 | P449: =+IF(OR($Q449=Parametres!$G$2,$Q449=Parametres!$G$3),K449,E449) -> 0 | Q449: =+F449 -> 0 | R449: =+G449 -> 0 | S449: =+H449 -> 0 | T449: =+VLOOKUP($L449,Data_Validation!$A:$D,1,0) -> #N/A | U449: =+VLOOKUP($L449,Data_Validation!$A:$D,3,0) -> #N/A | V449: =+VLOOKUP($L449,Data_Validation!$A:$D,4,0) -> #N/A | W449: =+VLOOKUP($L449,Data_Validation!$A:$E,5,0) -> #N/A | X449: =+VLOOKUP($L449,Data_Validation!$A:$F,6,0) -> #N/A
L450: =+B450 -> 0 | M450: =+A450 -> 0 | N450: =+IF(OR($Q450=Parametres!$G$2,$Q450=Parametres!$G$3),I450,C450) -> 0 | O450: =+IF(OR($Q450=Parametres!$G$2,$Q450=Parametres!$G$3),J450,D450) -> 0 | P450: =+IF(OR($Q450=Parametres!$G$2,$Q450=Parametres!$G$3),K450,E450) -> 0 | Q450: =+F450 -> 0 | R450: =+G450 -> 0 | S450: =+H450 -> 0 | T450: =+VLOOKUP($L450,Data_Validation!$A:$D,1,0) -> #N/A | U450: =+VLOOKUP($L450,Data_Validation!$A:$D,3,0) -> #N/A | V450: =+VLOOKUP($L450,Data_Validation!$A:$D,4,0) -> #N/A | W450: =+VLOOKUP($L450,Data_Validation!$A:$E,5,0) -> #N/A | X450: =+VLOOKUP($L450,Data_Validation!$A:$F,6,0) -> #N/A
L451: =+B451 -> 0 | M451: =+A451 -> 0 | N451: =+IF(OR($Q451=Parametres!$G$2,$Q451=Parametres!$G$3),I451,C451) -> 0 | O451: =+IF(OR($Q451=Parametres!$G$2,$Q451=Parametres!$G$3),J451,D451) -> 0 | P451: =+IF(OR($Q451=Parametres!$G$2,$Q451=Parametres!$G$3),K451,E451) -> 0 | Q451: =+F451 -> 0 | R451: =+G451 -> 0 | S451: =+H451 -> 0 | T451: =+VLOOKUP($L451,Data_Validation!$A:$D,1,0) -> #N/A | U451: =+VLOOKUP($L451,Data_Validation!$A:$D,3,0) -> #N/A | V451: =+VLOOKUP($L451,Data_Validation!$A:$D,4,0) -> #N/A | W451: =+VLOOKUP($L451,Data_Validation!$A:$E,5,0) -> #N/A | X451: =+VLOOKUP($L451,Data_Validation!$A:$F,6,0) -> #N/A
L452: =+B452 -> 0 | M452: =+A452 -> 0 | N452: =+IF(OR($Q452=Parametres!$G$2,$Q452=Parametres!$G$3),I452,C452) -> 0 | O452: =+IF(OR($Q452=Parametres!$G$2,$Q452=Parametres!$G$3),J452,D452) -> 0 | P452: =+IF(OR($Q452=Parametres!$G$2,$Q452=Parametres!$G$3),K452,E452) -> 0 | Q452: =+F452 -> 0 | R452: =+G452 -> 0 | S452: =+H452 -> 0 | T452: =+VLOOKUP($L452,Data_Validation!$A:$D,1,0) -> #N/A | U452: =+VLOOKUP($L452,Data_Validation!$A:$D,3,0) -> #N/A | V452: =+VLOOKUP($L452,Data_Validation!$A:$D,4,0) -> #N/A | W452: =+VLOOKUP($L452,Data_Validation!$A:$E,5,0) -> #N/A | X452: =+VLOOKUP($L452,Data_Validation!$A:$F,6,0) -> #N/A
L453: =+B453 -> 0 | M453: =+A453 -> 0 | N453: =+IF(OR($Q453=Parametres!$G$2,$Q453=Parametres!$G$3),I453,C453) -> 0 | O453: =+IF(OR($Q453=Parametres!$G$2,$Q453=Parametres!$G$3),J453,D453) -> 0 | P453: =+IF(OR($Q453=Parametres!$G$2,$Q453=Parametres!$G$3),K453,E453) -> 0 | Q453: =+F453 -> 0 | R453: =+G453 -> 0 | S453: =+H453 -> 0 | T453: =+VLOOKUP($L453,Data_Validation!$A:$D,1,0) -> #N/A | U453: =+VLOOKUP($L453,Data_Validation!$A:$D,3,0) -> #N/A | V453: =+VLOOKUP($L453,Data_Validation!$A:$D,4,0) -> #N/A | W453: =+VLOOKUP($L453,Data_Validation!$A:$E,5,0) -> #N/A | X453: =+VLOOKUP($L453,Data_Validation!$A:$F,6,0) -> #N/A
L454: =+B454 -> 0 | M454: =+A454 -> 0 | N454: =+IF(OR($Q454=Parametres!$G$2,$Q454=Parametres!$G$3),I454,C454) -> 0 | O454: =+IF(OR($Q454=Parametres!$G$2,$Q454=Parametres!$G$3),J454,D454) -> 0 | P454: =+IF(OR($Q454=Parametres!$G$2,$Q454=Parametres!$G$3),K454,E454) -> 0 | Q454: =+F454 -> 0 | R454: =+G454 -> 0 | S454: =+H454 -> 0 | T454: =+VLOOKUP($L454,Data_Validation!$A:$D,1,0) -> #N/A | U454: =+VLOOKUP($L454,Data_Validation!$A:$D,3,0) -> #N/A | V454: =+VLOOKUP($L454,Data_Validation!$A:$D,4,0) -> #N/A | W454: =+VLOOKUP($L454,Data_Validation!$A:$E,5,0) -> #N/A | X454: =+VLOOKUP($L454,Data_Validation!$A:$F,6,0) -> #N/A
L455: =+B455 -> 0 | M455: =+A455 -> 0 | N455: =+IF(OR($Q455=Parametres!$G$2,$Q455=Parametres!$G$3),I455,C455) -> 0 | O455: =+IF(OR($Q455=Parametres!$G$2,$Q455=Parametres!$G$3),J455,D455) -> 0 | P455: =+IF(OR($Q455=Parametres!$G$2,$Q455=Parametres!$G$3),K455,E455) -> 0 | Q455: =+F455 -> 0 | R455: =+G455 -> 0 | S455: =+H455 -> 0 | T455: =+VLOOKUP($L455,Data_Validation!$A:$D,1,0) -> #N/A | U455: =+VLOOKUP($L455,Data_Validation!$A:$D,3,0) -> #N/A | V455: =+VLOOKUP($L455,Data_Validation!$A:$D,4,0) -> #N/A | W455: =+VLOOKUP($L455,Data_Validation!$A:$E,5,0) -> #N/A | X455: =+VLOOKUP($L455,Data_Validation!$A:$F,6,0) -> #N/A
L456: =+B456 -> 0 | M456: =+A456 -> 0 | N456: =+IF(OR($Q456=Parametres!$G$2,$Q456=Parametres!$G$3),I456,C456) -> 0 | O456: =+IF(OR($Q456=Parametres!$G$2,$Q456=Parametres!$G$3),J456,D456) -> 0 | P456: =+IF(OR($Q456=Parametres!$G$2,$Q456=Parametres!$G$3),K456,E456) -> 0 | Q456: =+F456 -> 0 | R456: =+G456 -> 0 | S456: =+H456 -> 0 | T456: =+VLOOKUP($L456,Data_Validation!$A:$D,1,0) -> #N/A | U456: =+VLOOKUP($L456,Data_Validation!$A:$D,3,0) -> #N/A | V456: =+VLOOKUP($L456,Data_Validation!$A:$D,4,0) -> #N/A | W456: =+VLOOKUP($L456,Data_Validation!$A:$E,5,0) -> #N/A | X456: =+VLOOKUP($L456,Data_Validation!$A:$F,6,0) -> #N/A
... L523: =+B523 -> 0 | M523: =+A523 -> 0 | N523: =+IF(OR($Q523=Parametres!$G$2,$Q523=Parametres!$G$3),I523,C523) -> 0 | O523: =+IF(OR($Q523=Parametres!$G$2,$Q523=Parametres!$G$3),J523,D523) -> 0 | P523: =+IF(OR($Q523=Parametres!$G$2,$Q523=Parametres!$G$3),K523,E523) -> 0 | Q523: =+F523 -> 0 | R523: =+G523 -> 0 | S523: =+H523 -> 0 | T523: =+VLOOKUP($L523,Data_Validation!$A:$D,1,0) -> #N/A | U523: =+VLOOKUP($L523,Data_Validation!$A:$D,3,0) -> #N/A | V523: =+VLOOKUP($L523,Data_Validation!$A:$D,4,0) -> #N/A | W523: =+VLOOKUP($L523,Data_Validation!$A:$E,5,0) -> #N/A | X523: =+VLOOKUP($L523,Data_Validation!$A:$F,6,0) -> #N/A
L524: =+B524 -> 0 | M524: =+A524 -> 0 | N524: =+IF(OR($Q524=Parametres!$G$2,$Q524=Parametres!$G$3),I524,C524) -> 0 | O524: =+IF(OR($Q524=Parametres!$G$2,$Q524=Parametres!$G$3),J524,D524) -> 0 | P524: =+IF(OR($Q524=Parametres!$G$2,$Q524=Parametres!$G$3),K524,E524) -> 0 | Q524: =+F524 -> 0 | R524: =+G524 -> 0 | S524: =+H524 -> 0 | T524: =+VLOOKUP($L524,Data_Validation!$A:$E,1,0) -> #N/A | U524: =+VLOOKUP($L524,Data_Validation!$A:$E,3,0) -> #N/A | V524: =+VLOOKUP($L524,Data_Validation!$A:$E,4,0) -> #N/A | W524: =VLOOKUP($L524,Data_Validation!$A:$E,5,FALSE) -> #N/A | X524: =+VLOOKUP($L524,Data_Validation!$A:$F,6,0) -> #N/A
L525: =+B525 -> 0 | M525: =+A525 -> 0 | N525: =+IF(OR($Q525=Parametres!$G$2,$Q525=Parametres!$G$3),I525,C525) -> 0 | O525: =+IF(OR($Q525=Parametres!$G$2,$Q525=Parametres!$G$3),J525,D525) -> 0 | P525: =+IF(OR($Q525=Parametres!$G$2,$Q525=Parametres!$G$3),K525,E525) -> 0 | Q525: =+F525 -> 0 | R525: =+G525 -> 0 | S525: =+H525 -> 0 | T525: =+VLOOKUP($L525,Data_Validation!$A:$D,1,0) -> #N/A | U525: =+VLOOKUP($L525,Data_Validation!$A:$D,3,0) -> #N/A | V525: =+VLOOKUP($L525,Data_Validation!$A:$D,4,0) -> #N/A | W525: =+VLOOKUP($L525,Data_Validation!$A:$E,5,0) -> #N/A | X525: =+VLOOKUP($L525,Data_Validation!$A:$F,6,0) -> #N/A
L526: =+B526 -> 0 | M526: =+A526 -> 0 | N526: =+IF(OR($Q526=Parametres!$G$2,$Q526=Parametres!$G$3),I526,C526) -> 0 | O526: =+IF(OR($Q526=Parametres!$G$2,$Q526=Parametres!$G$3),J526,D526) -> 0 | P526: =+IF(OR($Q526=Parametres!$G$2,$Q526=Parametres!$G$3),K526,E526) -> 0 | Q526: =+F526 -> 0 | R526: =+G526 -> 0 | S526: =+H526 -> 0 | T526: =+VLOOKUP($L526,Data_Validation!$A:$D,1,0) -> #N/A | U526: =+VLOOKUP($L526,Data_Validation!$A:$D,3,0) -> #N/A | V526: =+VLOOKUP($L526,Data_Validation!$A:$D,4,0) -> #N/A | W526: =+VLOOKUP($L526,Data_Validation!$A:$E,5,0) -> #N/A | X526: =+VLOOKUP($L526,Data_Validation!$A:$F,6,0) -> #N/A
L527: =+B527 -> 0 | M527: =+A527 -> 0 | N527: =+IF(OR($Q527=Parametres!$G$2,$Q527=Parametres!$G$3),I527,C527) -> 0 | O527: =+IF(OR($Q527=Parametres!$G$2,$Q527=Parametres!$G$3),J527,D527) -> 0 | P527: =+IF(OR($Q527=Parametres!$G$2,$Q527=Parametres!$G$3),K527,E527) -> 0 | Q527: =+F527 -> 0 | R527: =+G527 -> 0 | S527: =+H527 -> 0 | T527: =+VLOOKUP($L527,Data_Validation!$A:$D,1,0) -> #N/A | U527: =+VLOOKUP($L527,Data_Validation!$A:$D,3,0) -> #N/A | V527: =+VLOOKUP($L527,Data_Validation!$A:$D,4,0) -> #N/A | W527: =+VLOOKUP($L527,Data_Validation!$A:$E,5,0) -> #N/A | X527: =+VLOOKUP($L527,Data_Validation!$A:$F,6,0) -> #N/A
L528: =+B528 -> 0 | M528: =+A528 -> 0 | N528: =+IF(OR($Q528=Parametres!$G$2,$Q528=Parametres!$G$3),I528,C528) -> 0 | O528: =+IF(OR($Q528=Parametres!$G$2,$Q528=Parametres!$G$3),J528,D528) -> 0 | P528: =+IF(OR($Q528=Parametres!$G$2,$Q528=Parametres!$G$3),K528,E528) -> 0 | Q528: =+F528 -> 0 | R528: =+G528 -> 0 | S528: =+H528 -> 0 | T528: =+VLOOKUP($L528,Data_Validation!$A:$D,1,0) -> #N/A | U528: =+VLOOKUP($L528,Data_Validation!$A:$D,3,0) -> #N/A | V528: =+VLOOKUP($L528,Data_Validation!$A:$D,4,0) -> #N/A | W528: =+VLOOKUP($L528,Data_Validation!$A:$E,5,0) -> #N/A | X528: =+VLOOKUP($L528,Data_Validation!$A:$F,6,0) -> #N/A
L529: =+B529 -> 0 | M529: =+A529 -> 0 | N529: =+IF(OR($Q529=Parametres!$G$2,$Q529=Parametres!$G$3),I529,C529) -> 0 | O529: =+IF(OR($Q529=Parametres!$G$2,$Q529=Parametres!$G$3),J529,D529) -> 0 | P529: =+IF(OR($Q529=Parametres!$G$2,$Q529=Parametres!$G$3),K529,E529) -> 0 | Q529: =+F529 -> 0 | R529: =+G529 -> 0 | S529: =+H529 -> 0 | T529: =+VLOOKUP($L529,Data_Validation!$A:$D,1,0) -> #N/A | U529: =+VLOOKUP($L529,Data_Validation!$A:$D,3,0) -> #N/A | V529: =+VLOOKUP($L529,Data_Validation!$A:$D,4,0) -> #N/A | W529: =+VLOOKUP($L529,Data_Validation!$A:$E,5,0) -> #N/A | X529: =+VLOOKUP($L529,Data_Validation!$A:$F,6,0) -> #N/A
L530: =+B530 -> 0 | M530: =+A530 -> 0 | N530: =+IF(OR($Q530=Parametres!$G$2,$Q530=Parametres!$G$3),I530,C530) -> 0 | O530: =+IF(OR($Q530=Parametres!$G$2,$Q530=Parametres!$G$3),J530,D530) -> 0 | P530: =+IF(OR($Q530=Parametres!$G$2,$Q530=Parametres!$G$3),K530,E530) -> 0 | Q530: =+F530 -> 0 | R530: =+G530 -> 0 | S530: =+H530 -> 0 | T530: =+VLOOKUP($L530,Data_Validation!$A:$D,1,0) -> #N/A | U530: =+VLOOKUP($L530,Data_Validation!$A:$D,3,0) -> #N/A | V530: =+VLOOKUP($L530,Data_Validation!$A:$D,4,0) -> #N/A | W530: =+VLOOKUP($L530,Data_Validation!$A:$E,5,0) -> #N/A | X530: =+VLOOKUP($L530,Data_Validation!$A:$F,6,0) -> #N/A
L531: =+B531 -> 0 | M531: =+A531 -> 0 | N531: =+IF(OR($Q531=Parametres!$G$2,$Q531=Parametres!$G$3),I531,C531) -> 0 | O531: =+IF(OR($Q531=Parametres!$G$2,$Q531=Parametres!$G$3),J531,D531) -> 0 | P531: =+IF(OR($Q531=Parametres!$G$2,$Q531=Parametres!$G$3),K531,E531) -> 0 | Q531: =+F531 -> 0 | R531: =+G531 -> 0 | S531: =+H531 -> 0 | T531: =+VLOOKUP($L531,Data_Validation!$A:$D,1,0) -> #N/A | U531: =+VLOOKUP($L531,Data_Validation!$A:$D,3,0) -> #N/A | V531: =+VLOOKUP($L531,Data_Validation!$A:$D,4,0) -> #N/A | W531: =+VLOOKUP($L531,Data_Validation!$A:$E,5,0) -> #N/A | X531: =+VLOOKUP($L531,Data_Validation!$A:$F,6,0) -> #N/A
L532: =+B532 -> 0 | M532: =+A532 -> 0 | N532: =+IF(OR($Q532=Parametres!$G$2,$Q532=Parametres!$G$3),I532,C532) -> 0 | O532: =+IF(OR($Q532=Parametres!$G$2,$Q532=Parametres!$G$3),J532,D532) -> 0 | P532: =+IF(OR($Q532=Parametres!$G$2,$Q532=Parametres!$G$3),K532,E532) -> 0 | Q532: =+F532 -> 0 | R532: =+G532 -> 0 | S532: =+H532 -> 0 | T532: =+VLOOKUP($L532,Data_Validation!$A:$D,1,0) -> #N/A | U532: =+VLOOKUP($L532,Data_Validation!$A:$D,3,0) -> #N/A | V532: =+VLOOKUP($L532,Data_Validation!$A:$D,4,0) -> #N/A | W532: =+VLOOKUP($L532,Data_Validation!$A:$E,5,0) -> #N/A | X532: =+VLOOKUP($L532,Data_Validation!$A:$F,6,0) -> #N/A
L533: =+B533 -> 0 | M533: =+A533 -> 0 | N533: =+IF(OR($Q533=Parametres!$G$2,$Q533=Parametres!$G$3),I533,C533) -> 0 | O533: =+IF(OR($Q533=Parametres!$G$2,$Q533=Parametres!$G$3),J533,D533) -> 0 | P533: =+IF(OR($Q533=Parametres!$G$2,$Q533=Parametres!$G$3),K533,E533) -> 0 | Q533: =+F533 -> 0 | R533: =+G533 -> 0 | S533: =+H533 -> 0 | T533: =+VLOOKUP($L533,Data_Validation!$A:$D,1,0) -> #N/A | U533: =+VLOOKUP($L533,Data_Validation!$A:$D,3,0) -> #N/A | V533: =+VLOOKUP($L533,Data_Validation!$A:$D,4,0) -> #N/A | W533: =+VLOOKUP($L533,Data_Validation!$A:$E,5,0) -> #N/A | X533: =+VLOOKUP($L533,Data_Validation!$A:$F,6,0) -> #N/A
L534: =+B534 -> 0 | M534: =+A534 -> 0 | N534: =+IF(OR($Q534=Parametres!$G$2,$Q534=Parametres!$G$3),I534,C534) -> 0 | O534: =+IF(OR($Q534=Parametres!$G$2,$Q534=Parametres!$G$3),J534,D534) -> 0 | P534: =+IF(OR($Q534=Parametres!$G$2,$Q534=Parametres!$G$3),K534,E534) -> 0 | Q534: =+F534 -> 0 | R534: =+G534 -> 0 | S534: =+H534 -> 0 | T534: =+VLOOKUP($L534,Data_Validation!$A:$D,1,0) -> #N/A | U534: =+VLOOKUP($L534,Data_Validation!$A:$D,3,0) -> #N/A | V534: =+VLOOKUP($L534,Data_Validation!$A:$D,4,0) -> #N/A | W534: =+VLOOKUP($L534,Data_Validation!$A:$E,5,0) -> #N/A | X534: =+VLOOKUP($L534,Data_Validation!$A:$F,6,0) -> #N/A
L535: =+B535 -> 0 | M535: =+A535 -> 0 | N535: =+IF(OR($Q535=Parametres!$G$2,$Q535=Parametres!$G$3),I535,C535) -> 0 | O535: =+IF(OR($Q535=Parametres!$G$2,$Q535=Parametres!$G$3),J535,D535) -> 0 | P535: =+IF(OR($Q535=Parametres!$G$2,$Q535=Parametres!$G$3),K535,E535) -> 0 | Q535: =+F535 -> 0 | R535: =+G535 -> 0 | S535: =+H535 -> 0 | T535: =+VLOOKUP($L535,Data_Validation!$A:$D,1,0) -> #N/A | U535: =+VLOOKUP($L535,Data_Validation!$A:$D,3,0) -> #N/A | V535: =+VLOOKUP($L535,Data_Validation!$A:$D,4,0) -> #N/A | W535: =+VLOOKUP($L535,Data_Validation!$A:$E,5,0) -> #N/A | X535: =+VLOOKUP($L535,Data_Validation!$A:$F,6,0) -> #N/A
L536: =+B536 -> 0 | M536: =+A536 -> 0 | N536: =+IF(OR($Q536=Parametres!$G$2,$Q536=Parametres!$G$3),I536,C536) -> 0 | O536: =+IF(OR($Q536=Parametres!$G$2,$Q536=Parametres!$G$3),J536,D536) -> 0 | P536: =+IF(OR($Q536=Parametres!$G$2,$Q536=Parametres!$G$3),K536,E536) -> 0 | Q536: =+F536 -> 0 | R536: =+G536 -> 0 | S536: =+H536 -> 0 | T536: =+VLOOKUP($L536,Data_Validation!$A:$D,1,0) -> #N/A | U536: =+VLOOKUP($L536,Data_Validation!$A:$D,3,0) -> #N/A | V536: =+VLOOKUP($L536,Data_Validation!$A:$D,4,0) -> #N/A | W536: =+VLOOKUP($L536,Data_Validation!$A:$E,5,0) -> #N/A | X536: =+VLOOKUP($L536,Data_Validation!$A:$F,6,0) -> #N/A
... L717: =+B717 -> 0 | M717: =+A717 -> 0 | N717: =+IF(OR($Q717=Parametres!$G$2,$Q717=Parametres!$G$3),I717,C717) -> 0 | O717: =+IF(OR($Q717=Parametres!$G$2,$Q717=Parametres!$G$3),J717,D717) -> 0 | P717: =+IF(OR($Q717=Parametres!$G$2,$Q717=Parametres!$G$3),K717,E717) -> 0 | Q717: =+F717 -> 0 | R717: =+G717 -> 0 | S717: =+H717 -> 0 | T717: =+VLOOKUP($L717,Data_Validation!$A:$D,1,0) -> #N/A | U717: =+VLOOKUP($L717,Data_Validation!$A:$D,3,0) -> #N/A | V717: =+VLOOKUP($L717,Data_Validation!$A:$D,4,0) -> #N/A | W717: =+VLOOKUP($L717,Data_Validation!$A:$E,5,0) -> #N/A | X717: =+VLOOKUP($L717,Data_Validation!$A:$F,6,0) -> #N/A
L718: =+B718 -> 0 | M718: =+A718 -> 0 | N718: =+IF(OR($Q718=Parametres!$G$2,$Q718=Parametres!$G$3),I718,C718) -> 0 | O718: =+IF(OR($Q718=Parametres!$G$2,$Q718=Parametres!$G$3),J718,D718) -> 0 | P718: =+IF(OR($Q718=Parametres!$G$2,$Q718=Parametres!$G$3),K718,E718) -> 0 | Q718: =+F718 -> 0 | R718: =+G718 -> 0 | S718: =+H718 -> 0 | T718: =+VLOOKUP($L718,Data_Validation!$A:$D,1,0) -> #N/A | U718: =+VLOOKUP($L718,Data_Validation!$A:$D,3,0) -> #N/A | V718: =+VLOOKUP($L718,Data_Validation!$A:$D,4,0) -> #N/A | W718: =+VLOOKUP($L718,Data_Validation!$A:$E,5,0) -> #N/A
L719: =+B719 -> 0 | M719: =+A719 -> 0 | N719: =+IF(OR($Q719=Parametres!$G$2,$Q719=Parametres!$G$3),I719,C719) -> 0 | O719: =+IF(OR($Q719=Parametres!$G$2,$Q719=Parametres!$G$3),J719,D719) -> 0 | P719: =+IF(OR($Q719=Parametres!$G$2,$Q719=Parametres!$G$3),K719,E719) -> 0 | Q719: =+F719 -> 0 | R719: =+G719 -> 0 | S719: =+H719 -> 0 | T719: =+VLOOKUP($L719,Data_Validation!$A:$D,1,0) -> #N/A | U719: =+VLOOKUP($L719,Data_Validation!$A:$D,3,0) -> #N/A | V719: =+VLOOKUP($L719,Data_Validation!$A:$D,4,0) -> #N/A | W719: =+VLOOKUP($L719,Data_Validation!$A:$E,5,0) -> #N/A
L720: =+B720 -> 0 | M720: =+A720 -> 0 | N720: =+IF(OR($Q720=Parametres!$G$2,$Q720=Parametres!$G$3),I720,C720) -> 0 | O720: =+IF(OR($Q720=Parametres!$G$2,$Q720=Parametres!$G$3),J720,D720) -> 0 | P720: =+IF(OR($Q720=Parametres!$G$2,$Q720=Parametres!$G$3),K720,E720) -> 0 | Q720: =+F720 -> 0 | R720: =+G720 -> 0 | S720: =+H720 -> 0 | T720: =+VLOOKUP($L720,Data_Validation!$A:$D,1,0) -> #N/A | U720: =+VLOOKUP($L720,Data_Validation!$A:$D,3,0) -> #N/A | V720: =+VLOOKUP($L720,Data_Validation!$A:$D,4,0) -> #N/A | W720: =+VLOOKUP($L720,Data_Validation!$A:$E,5,0) -> #N/A
L721: =+B721 -> 0 | M721: =+A721 -> 0 | N721: =+IF(OR($Q721=Parametres!$G$2,$Q721=Parametres!$G$3),I721,C721) -> 0 | O721: =+IF(OR($Q721=Parametres!$G$2,$Q721=Parametres!$G$3),J721,D721) -> 0 | P721: =+IF(OR($Q721=Parametres!$G$2,$Q721=Parametres!$G$3),K721,E721) -> 0 | Q721: =+F721 -> 0 | R721: =+G721 -> 0 | S721: =+H721 -> 0 | T721: =+VLOOKUP($L721,Data_Validation!$A:$D,1,0) -> #N/A | U721: =+VLOOKUP($L721,Data_Validation!$A:$D,3,0) -> #N/A | V721: =+VLOOKUP($L721,Data_Validation!$A:$D,4,0) -> #N/A | W721: =+VLOOKUP($L721,Data_Validation!$A:$E,5,0) -> #N/A
L722: =+B722 -> 0 | M722: =+A722 -> 0 | N722: =+IF(OR($Q722=Parametres!$G$2,$Q722=Parametres!$G$3),I722,C722) -> 0 | O722: =+IF(OR($Q722=Parametres!$G$2,$Q722=Parametres!$G$3),J722,D722) -> 0 | P722: =+IF(OR($Q722=Parametres!$G$2,$Q722=Parametres!$G$3),K722,E722) -> 0 | Q722: =+F722 -> 0 | R722: =+G722 -> 0 | S722: =+H722 -> 0 | T722: =+VLOOKUP($L722,Data_Validation!$A:$D,1,0) -> #N/A | U722: =+VLOOKUP($L722,Data_Validation!$A:$D,3,0) -> #N/A | V722: =+VLOOKUP($L722,Data_Validation!$A:$D,4,0) -> #N/A | W722: =+VLOOKUP($L722,Data_Validation!$A:$E,5,0) -> #N/A
L723: =+B723 -> 0 | M723: =+A723 -> 0 | N723: =+IF(OR($Q723=Parametres!$G$2,$Q723=Parametres!$G$3),I723,C723) -> 0 | O723: =+IF(OR($Q723=Parametres!$G$2,$Q723=Parametres!$G$3),J723,D723) -> 0 | P723: =+IF(OR($Q723=Parametres!$G$2,$Q723=Parametres!$G$3),K723,E723) -> 0 | Q723: =+F723 -> 0 | R723: =+G723 -> 0 | S723: =+H723 -> 0 | T723: =+VLOOKUP($L723,Data_Validation!$A:$D,1,0) -> #N/A | U723: =+VLOOKUP($L723,Data_Validation!$A:$D,3,0) -> #N/A | V723: =+VLOOKUP($L723,Data_Validation!$A:$D,4,0) -> #N/A | W723: =+VLOOKUP($L723,Data_Validation!$A:$E,5,0) -> #N/A
L724: =+B724 -> 0 | M724: =+A724 -> 0 | N724: =+IF(OR($Q724=Parametres!$G$2,$Q724=Parametres!$G$3),I724,C724) -> 0 | O724: =+IF(OR($Q724=Parametres!$G$2,$Q724=Parametres!$G$3),J724,D724) -> 0 | P724: =+IF(OR($Q724=Parametres!$G$2,$Q724=Parametres!$G$3),K724,E724) -> 0 | Q724: =+F724 -> 0 | R724: =+G724 -> 0 | S724: =+H724 -> 0 | T724: =+VLOOKUP($L724,Data_Validation!$A:$D,1,0) -> #N/A | U724: =+VLOOKUP($L724,Data_Validation!$A:$D,3,0) -> #N/A | V724: =+VLOOKUP($L724,Data_Validation!$A:$D,4,0) -> #N/A | W724: =+VLOOKUP($L724,Data_Validation!$A:$E,5,0) -> #N/A
L725: =+B725 -> 0 | M725: =+A725 -> 0 | N725: =+IF(OR($Q725=Parametres!$G$2,$Q725=Parametres!$G$3),I725,C725) -> 0 | O725: =+IF(OR($Q725=Parametres!$G$2,$Q725=Parametres!$G$3),J725,D725) -> 0 | P725: =+IF(OR($Q725=Parametres!$G$2,$Q725=Parametres!$G$3),K725,E725) -> 0 | Q725: =+F725 -> 0 | R725: =+G725 -> 0 | S725: =+H725 -> 0 | T725: =+VLOOKUP($L725,Data_Validation!$A:$D,1,0) -> #N/A | U725: =+VLOOKUP($L725,Data_Validation!$A:$D,3,0) -> #N/A | V725: =+VLOOKUP($L725,Data_Validation!$A:$D,4,0) -> #N/A | W725: =+VLOOKUP($L725,Data_Validation!$A:$E,5,0) -> #N/A
L726: =+B726 -> 0 | M726: =+A726 -> 0 | N726: =+IF(OR($Q726=Parametres!$G$2,$Q726=Parametres!$G$3),I726,C726) -> 0 | O726: =+IF(OR($Q726=Parametres!$G$2,$Q726=Parametres!$G$3),J726,D726) -> 0 | P726: =+IF(OR($Q726=Parametres!$G$2,$Q726=Parametres!$G$3),K726,E726) -> 0 | Q726: =+F726 -> 0 | R726: =+G726 -> 0 | S726: =+H726 -> 0 | T726: =+VLOOKUP($L726,Data_Validation!$A:$D,1,0) -> #N/A | U726: =+VLOOKUP($L726,Data_Validation!$A:$D,3,0) -> #N/A | V726: =+VLOOKUP($L726,Data_Validation!$A:$D,4,0) -> #N/A | W726: =+VLOOKUP($L726,Data_Validation!$A:$E,5,0) -> #N/A
L727: =+B727 -> 0 | M727: =+A727 -> 0 | N727: =+IF(OR($Q727=Parametres!$G$2,$Q727=Parametres!$G$3),I727,C727) -> 0 | O727: =+IF(OR($Q727=Parametres!$G$2,$Q727=Parametres!$G$3),J727,D727) -> 0 | P727: =+IF(OR($Q727=Parametres!$G$2,$Q727=Parametres!$G$3),K727,E727) -> 0 | Q727: =+F727 -> 0 | R727: =+G727 -> 0 | S727: =+H727 -> 0 | T727: =+VLOOKUP($L727,Data_Validation!$A:$D,1,0) -> #N/A | U727: =+VLOOKUP($L727,Data_Validation!$A:$D,3,0) -> #N/A | V727: =+VLOOKUP($L727,Data_Validation!$A:$D,4,0) -> #N/A | W727: =+VLOOKUP($L727,Data_Validation!$A:$E,5,0) -> #N/A
L728: =+B728 -> 0 | M728: =+A728 -> 0 | N728: =+IF(OR($Q728=Parametres!$G$2,$Q728=Parametres!$G$3),I728,C728) -> 0 | O728: =+IF(OR($Q728=Parametres!$G$2,$Q728=Parametres!$G$3),J728,D728) -> 0 | P728: =+IF(OR($Q728=Parametres!$G$2,$Q728=Parametres!$G$3),K728,E728) -> 0 | Q728: =+F728 -> 0 | R728: =+G728 -> 0 | S728: =+H728 -> 0 | T728: =+VLOOKUP($L728,Data_Validation!$A:$D,1,0) -> #N/A | U728: =+VLOOKUP($L728,Data_Validation!$A:$D,3,0) -> #N/A | V728: =+VLOOKUP($L728,Data_Validation!$A:$D,4,0) -> #N/A | W728: =+VLOOKUP($L728,Data_Validation!$A:$E,5,0) -> #N/A
L729: =+B729 -> 0 | M729: =+A729 -> 0 | N729: =+IF(OR($Q729=Parametres!$G$2,$Q729=Parametres!$G$3),I729,C729) -> 0 | O729: =+IF(OR($Q729=Parametres!$G$2,$Q729=Parametres!$G$3),J729,D729) -> 0 | P729: =+IF(OR($Q729=Parametres!$G$2,$Q729=Parametres!$G$3),K729,E729) -> 0 | Q729: =+F729 -> 0 | R729: =+G729 -> 0 | S729: =+H729 -> 0 | T729: =+VLOOKUP($L729,Data_Validation!$A:$D,1,0) -> #N/A | U729: =+VLOOKUP($L729,Data_Validation!$A:$D,3,0) -> #N/A | V729: =+VLOOKUP($L729,Data_Validation!$A:$D,4,0) -> #N/A | W729: =+VLOOKUP($L729,Data_Validation!$A:$E,5,0) -> #N/A
... L735: =+B735 -> 0 | M735: =+A735 -> 0 | N735: =+IF(OR($Q735=Parametres!$G$2,$Q735=Parametres!$G$3),I735,C735) -> 0 | O735: =+IF(OR($Q735=Parametres!$G$2,$Q735=Parametres!$G$3),J735,D735) -> 0 | P735: =+IF(OR($Q735=Parametres!$G$2,$Q735=Parametres!$G$3),K735,E735) -> 0 | Q735: =+F735 -> 0 | R735: =+G735 -> 0 | S735: =+H735 -> 0 | T735: =+VLOOKUP($L735,Data_Validation!$A:$D,1,0) -> #N/A | U735: =+VLOOKUP($L735,Data_Validation!$A:$D,3,0) -> #N/A | V735: =+VLOOKUP($L735,Data_Validation!$A:$D,4,0) -> #N/A | W735: =+VLOOKUP($L735,Data_Validation!$A:$E,5,0) -> #N/A
L736: =+B736 -> 0 | M736: =+A736 -> 0 | N736: =+IF(OR($Q736=Parametres!$G$2,$Q736=Parametres!$G$3),I736,C736) -> 0 | O736: =+IF(OR($Q736=Parametres!$G$2,$Q736=Parametres!$G$3),J736,D736) -> 0 | P736: =+IF(OR($Q736=Parametres!$G$2,$Q736=Parametres!$G$3),K736,E736) -> 0 | Q736: =+F736 -> 0 | R736: =+G736 -> 0 | S736: =+H736 -> 0 | T736: =+VLOOKUP($L736,Data_Validation!$A:$D,1,0) -> #N/A | U736: =+VLOOKUP($L736,Data_Validation!$A:$D,3,0) -> #N/A | V736: =+VLOOKUP($L736,Data_Validation!$A:$D,4,0) -> #N/A | W736: =+VLOOKUP($L736,Data_Validation!$A:$E,5,0) -> #N/A | X736: =+VLOOKUP($L736,Data_Validation!$A:$F,6,0) -> #N/A
L737: =+B737 -> 0 | M737: =+A737 -> 0 | N737: =+IF(OR($Q737=Parametres!$G$2,$Q737=Parametres!$G$3),I737,C737) -> 0 | O737: =+IF(OR($Q737=Parametres!$G$2,$Q737=Parametres!$G$3),J737,D737) -> 0 | P737: =+IF(OR($Q737=Parametres!$G$2,$Q737=Parametres!$G$3),K737,E737) -> 0 | Q737: =+F737 -> 0 | R737: =+G737 -> 0 | S737: =+H737 -> 0 | T737: =+VLOOKUP($L737,Data_Validation!$A:$D,1,0) -> #N/A | U737: =+VLOOKUP($L737,Data_Validation!$A:$D,3,0) -> #N/A | V737: =+VLOOKUP($L737,Data_Validation!$A:$D,4,0) -> #N/A | W737: =+VLOOKUP($L737,Data_Validation!$A:$E,5,0) -> #N/A
L738: =+B738 -> 0 | M738: =+A738 -> 0 | N738: =+IF(OR($Q738=Parametres!$G$2,$Q738=Parametres!$G$3),I738,C738) -> 0 | O738: =+IF(OR($Q738=Parametres!$G$2,$Q738=Parametres!$G$3),J738,D738) -> 0 | P738: =+IF(OR($Q738=Parametres!$G$2,$Q738=Parametres!$G$3),K738,E738) -> 0 | Q738: =+F738 -> 0 | R738: =+G738 -> 0 | S738: =+H738 -> 0 | T738: =+VLOOKUP($L738,Data_Validation!$A:$D,1,0) -> #N/A | U738: =+VLOOKUP($L738,Data_Validation!$A:$D,3,0) -> #N/A | V738: =+VLOOKUP($L738,Data_Validation!$A:$D,4,0) -> #N/A | W738: =+VLOOKUP($L738,Data_Validation!$A:$E,5,0) -> #N/A
L739: =+B739 -> 0 | M739: =+A739 -> 0 | N739: =+IF(OR($Q739=Parametres!$G$2,$Q739=Parametres!$G$3),I739,C739) -> 0 | O739: =+IF(OR($Q739=Parametres!$G$2,$Q739=Parametres!$G$3),J739,D739) -> 0 | P739: =+IF(OR($Q739=Parametres!$G$2,$Q739=Parametres!$G$3),K739,E739) -> 0 | Q739: =+F739 -> 0 | R739: =+G739 -> 0 | S739: =+H739 -> 0 | T739: =+VLOOKUP($L739,Data_Validation!$A:$D,1,0) -> #N/A | U739: =+VLOOKUP($L739,Data_Validation!$A:$D,3,0) -> #N/A | V739: =+VLOOKUP($L739,Data_Validation!$A:$D,4,0) -> #N/A | W739: =+VLOOKUP($L739,Data_Validation!$A:$E,5,0) -> #N/A
L740: =+B740 -> 0 | M740: =+A740 -> 0 | N740: =+IF(OR($Q740=Parametres!$G$2,$Q740=Parametres!$G$3),I740,C740) -> 0 | O740: =+IF(OR($Q740=Parametres!$G$2,$Q740=Parametres!$G$3),J740,D740) -> 0 | P740: =+IF(OR($Q740=Parametres!$G$2,$Q740=Parametres!$G$3),K740,E740) -> 0 | Q740: =+F740 -> 0 | R740: =+G740 -> 0 | S740: =+H740 -> 0 | T740: =+VLOOKUP($L740,Data_Validation!$A:$D,1,0) -> #N/A | U740: =+VLOOKUP($L740,Data_Validation!$A:$D,3,0) -> #N/A | V740: =+VLOOKUP($L740,Data_Validation!$A:$D,4,0) -> #N/A | W740: =+VLOOKUP($L740,Data_Validation!$A:$E,5,0) -> #N/A
L741: =+B741 -> 0 | M741: =+A741 -> 0 | N741: =+IF(OR($Q741=Parametres!$G$2,$Q741=Parametres!$G$3),I741,C741) -> 0 | O741: =+IF(OR($Q741=Parametres!$G$2,$Q741=Parametres!$G$3),J741,D741) -> 0 | P741: =+IF(OR($Q741=Parametres!$G$2,$Q741=Parametres!$G$3),K741,E741) -> 0 | Q741: =+F741 -> 0 | R741: =+G741 -> 0 | S741: =+H741 -> 0 | T741: =+VLOOKUP($L741,Data_Validation!$A:$D,1,0) -> #N/A | U741: =+VLOOKUP($L741,Data_Validation!$A:$D,3,0) -> #N/A | V741: =+VLOOKUP($L741,Data_Validation!$A:$D,4,0) -> #N/A | W741: =+VLOOKUP($L741,Data_Validation!$A:$E,5,0) -> #N/A
L742: =+B742 -> 0 | M742: =+A742 -> 0 | N742: =+IF(OR($Q742=Parametres!$G$2,$Q742=Parametres!$G$3),I742,C742) -> 0 | O742: =+IF(OR($Q742=Parametres!$G$2,$Q742=Parametres!$G$3),J742,D742) -> 0 | P742: =+IF(OR($Q742=Parametres!$G$2,$Q742=Parametres!$G$3),K742,E742) -> 0 | Q742: =+F742 -> 0 | R742: =+G742 -> 0 | S742: =+H742 -> 0 | T742: =+VLOOKUP($L742,Data_Validation!$A:$D,1,0) -> #N/A | U742: =+VLOOKUP($L742,Data_Validation!$A:$D,3,0) -> #N/A | V742: =+VLOOKUP($L742,Data_Validation!$A:$D,4,0) -> #N/A | W742: =+VLOOKUP($L742,Data_Validation!$A:$E,5,0) -> #N/A | X742: =+VLOOKUP($L742,Data_Validation!$A:$F,6,0) -> #N/A
L743: =+B743 -> 0 | M743: =+A743 -> 0 | N743: =+IF(OR($Q743=Parametres!$G$2,$Q743=Parametres!$G$3),I743,C743) -> 0 | O743: =+IF(OR($Q743=Parametres!$G$2,$Q743=Parametres!$G$3),J743,D743) -> 0 | P743: =+IF(OR($Q743=Parametres!$G$2,$Q743=Parametres!$G$3),K743,E743) -> 0 | Q743: =+F743 -> 0 | R743: =+G743 -> 0 | S743: =+H743 -> 0 | T743: =+VLOOKUP($L743,Data_Validation!$A:$D,1,0) -> #N/A | U743: =+VLOOKUP($L743,Data_Validation!$A:$D,3,0) -> #N/A | V743: =+VLOOKUP($L743,Data_Validation!$A:$D,4,0) -> #N/A | W743: =+VLOOKUP($L743,Data_Validation!$A:$E,5,0) -> #N/A
L744: =+B744 -> 0 | M744: =+A744 -> 0 | N744: =+IF(OR($Q744=Parametres!$G$2,$Q744=Parametres!$G$3),I744,C744) -> 0 | O744: =+IF(OR($Q744=Parametres!$G$2,$Q744=Parametres!$G$3),J744,D744) -> 0 | P744: =+IF(OR($Q744=Parametres!$G$2,$Q744=Parametres!$G$3),K744,E744) -> 0 | Q744: =+F744 -> 0 | R744: =+G744 -> 0 | S744: =+H744 -> 0 | T744: =+VLOOKUP($L744,Data_Validation!$A:$D,1,0) -> #N/A | U744: =+VLOOKUP($L744,Data_Validation!$A:$D,3,0) -> #N/A | V744: =+VLOOKUP($L744,Data_Validation!$A:$D,4,0) -> #N/A | W744: =+VLOOKUP($L744,Data_Validation!$A:$E,5,0) -> #N/A
L745: =+B745 -> 0 | M745: =+A745 -> 0 | N745: =+IF(OR($Q745=Parametres!$G$2,$Q745=Parametres!$G$3),I745,C745) -> 0 | O745: =+IF(OR($Q745=Parametres!$G$2,$Q745=Parametres!$G$3),J745,D745) -> 0 | P745: =+IF(OR($Q745=Parametres!$G$2,$Q745=Parametres!$G$3),K745,E745) -> 0 | Q745: =+F745 -> 0 | R745: =+G745 -> 0 | S745: =+H745 -> 0 | T745: =+VLOOKUP($L745,Data_Validation!$A:$D,1,0) -> #N/A | U745: =+VLOOKUP($L745,Data_Validation!$A:$D,3,0) -> #N/A | V745: =+VLOOKUP($L745,Data_Validation!$A:$D,4,0) -> #N/A | W745: =+VLOOKUP($L745,Data_Validation!$A:$E,5,0) -> #N/A
L746: =+B746 -> 0 | M746: =+A746 -> 0 | N746: =+IF(OR($Q746=Parametres!$G$2,$Q746=Parametres!$G$3),I746,C746) -> 0 | O746: =+IF(OR($Q746=Parametres!$G$2,$Q746=Parametres!$G$3),J746,D746) -> 0 | P746: =+IF(OR($Q746=Parametres!$G$2,$Q746=Parametres!$G$3),K746,E746) -> 0 | Q746: =+F746 -> 0 | R746: =+G746 -> 0 | S746: =+H746 -> 0 | T746: =+VLOOKUP($L746,Data_Validation!$A:$D,1,0) -> #N/A | U746: =+VLOOKUP($L746,Data_Validation!$A:$D,3,0) -> #N/A | V746: =+VLOOKUP($L746,Data_Validation!$A:$D,4,0) -> #N/A | W746: =+VLOOKUP($L746,Data_Validation!$A:$E,5,0) -> #N/A | X746: =+VLOOKUP($L746,Data_Validation!$A:$F,6,0) -> #N/A
L747: =+B747 -> 0 | M747: =+A747 -> 0 | N747: =+IF(OR($Q747=Parametres!$G$2,$Q747=Parametres!$G$3),I747,C747) -> 0 | O747: =+IF(OR($Q747=Parametres!$G$2,$Q747=Parametres!$G$3),J747,D747) -> 0 | P747: =+IF(OR($Q747=Parametres!$G$2,$Q747=Parametres!$G$3),K747,E747) -> 0 | Q747: =+F747 -> 0 | R747: =+G747 -> 0 | S747: =+H747 -> 0 | T747: =+VLOOKUP($L747,Data_Validation!$A:$D,1,0) -> #N/A | U747: =+VLOOKUP($L747,Data_Validation!$A:$D,3,0) -> #N/A | V747: =+VLOOKUP($L747,Data_Validation!$A:$D,4,0) -> #N/A | W747: =+VLOOKUP($L747,Data_Validation!$A:$E,5,0) -> #N/A | X747: =+VLOOKUP($L747,Data_Validation!$A:$F,6,0) -> #N/A
L748: =+B748 -> 0 | M748: =+A748 -> 0 | N748: =+IF(OR($Q748=Parametres!$G$2,$Q748=Parametres!$G$3),I748,C748) -> 0 | O748: =+IF(OR($Q748=Parametres!$G$2,$Q748=Parametres!$G$3),J748,D748) -> 0 | P748: =+IF(OR($Q748=Parametres!$G$2,$Q748=Parametres!$G$3),K748,E748) -> 0 | Q748: =+F748 -> 0 | R748: =+G748 -> 0 | S748: =+H748 -> 0 | T748: =+VLOOKUP($L748,Data_Validation!$A:$D,1,0) -> #N/A | U748: =+VLOOKUP($L748,Data_Validation!$A:$D,3,0) -> #N/A | V748: =+VLOOKUP($L748,Data_Validation!$A:$D,4,0) -> #N/A | W748: =+VLOOKUP($L748,Data_Validation!$A:$E,5,0) -> #N/A
L749: =+B749 -> 0 | M749: =+A749 -> 0 | N749: =+IF(OR($Q749=Parametres!$G$2,$Q749=Parametres!$G$3),I749,C749) -> 0 | O749: =+IF(OR($Q749=Parametres!$G$2,$Q749=Parametres!$G$3),J749,D749) -> 0 | P749: =+IF(OR($Q749=Parametres!$G$2,$Q749=Parametres!$G$3),K749,E749) -> 0 | Q749: =+F749 -> 0 | R749: =+G749 -> 0 | S749: =+H749 -> 0 | T749: =+VLOOKUP($L749,Data_Validation!$A:$D,1,0) -> #N/A | U749: =+VLOOKUP($L749,Data_Validation!$A:$D,3,0) -> #N/A | V749: =+VLOOKUP($L749,Data_Validation!$A:$D,4,0) -> #N/A | W749: =+VLOOKUP($L749,Data_Validation!$A:$E,5,0) -> #N/A
L750: =+B750 -> 0 | M750: =+A750 -> 0 | N750: =+IF(OR($Q750=Parametres!$G$2,$Q750=Parametres!$G$3),I750,C750) -> 0 | O750: =+IF(OR($Q750=Parametres!$G$2,$Q750=Parametres!$G$3),J750,D750) -> 0 | P750: =+IF(OR($Q750=Parametres!$G$2,$Q750=Parametres!$G$3),K750,E750) -> 0 | Q750: =+F750 -> 0 | R750: =+G750 -> 0 | S750: =+H750 -> 0 | T750: =+VLOOKUP($L750,Data_Validation!$A:$D,1,0) -> #N/A | U750: =+VLOOKUP($L750,Data_Validation!$A:$D,3,0) -> #N/A | V750: =+VLOOKUP($L750,Data_Validation!$A:$D,4,0) -> #N/A | W750: =+VLOOKUP($L750,Data_Validation!$A:$E,5,0) -> #N/A
L751: =+B751 -> 0 | M751: =+A751 -> 0 | N751: =+IF(OR($Q751=Parametres!$G$2,$Q751=Parametres!$G$3),I751,C751) -> 0 | O751: =+IF(OR($Q751=Parametres!$G$2,$Q751=Parametres!$G$3),J751,D751) -> 0 | P751: =+IF(OR($Q751=Parametres!$G$2,$Q751=Parametres!$G$3),K751,E751) -> 0 | Q751: =+F751 -> 0 | R751: =+G751 -> 0 | S751: =+H751 -> 0 | T751: =+VLOOKUP($L751,Data_Validation!$A:$D,1,0) -> #N/A | U751: =+VLOOKUP($L751,Data_Validation!$A:$D,3,0) -> #N/A | V751: =+VLOOKUP($L751,Data_Validation!$A:$D,4,0) -> #N/A | W751: =+VLOOKUP($L751,Data_Validation!$A:$E,5,0) -> #N/A
L752: =+B752 -> 0 | M752: =+A752 -> 0 | N752: =+IF(OR($Q752=Parametres!$G$2,$Q752=Parametres!$G$3),I752,C752) -> 0 | O752: =+IF(OR($Q752=Parametres!$G$2,$Q752=Parametres!$G$3),J752,D752) -> 0 | P752: =+IF(OR($Q752=Parametres!$G$2,$Q752=Parametres!$G$3),K752,E752) -> 0 | Q752: =+F752 -> 0 | R752: =+G752 -> 0 | S752: =+H752 -> 0 | T752: =+VLOOKUP($L752,Data_Validation!$A:$D,1,0) -> #N/A | U752: =+VLOOKUP($L752,Data_Validation!$A:$D,3,0) -> #N/A | V752: =+VLOOKUP($L752,Data_Validation!$A:$D,4,0) -> #N/A | W752: =+VLOOKUP($L752,Data_Validation!$A:$E,5,0) -> #N/A
L753: =+B753 -> 0 | M753: =+A753 -> 0 | N753: =+IF(OR($Q753=Parametres!$G$2,$Q753=Parametres!$G$3),I753,C753) -> 0 | O753: =+IF(OR($Q753=Parametres!$G$2,$Q753=Parametres!$G$3),J753,D753) -> 0 | P753: =+IF(OR($Q753=Parametres!$G$2,$Q753=Parametres!$G$3),K753,E753) -> 0 | Q753: =+F753 -> 0 | R753: =+G753 -> 0 | S753: =+H753 -> 0 | T753: =+VLOOKUP($L753,Data_Validation!$A:$D,1,0) -> #N/A | U753: =+VLOOKUP($L753,Data_Validation!$A:$D,3,0) -> #N/A | V753: =+VLOOKUP($L753,Data_Validation!$A:$D,4,0) -> #N/A | W753: =+VLOOKUP($L753,Data_Validation!$A:$E,5,0) -> #N/A
L754: =+B754 -> 0 | M754: =+A754 -> 0 | N754: =+IF(OR($Q754=Parametres!$G$2,$Q754=Parametres!$G$3),I754,C754) -> 0 | O754: =+IF(OR($Q754=Parametres!$G$2,$Q754=Parametres!$G$3),J754,D754) -> 0 | P754: =+IF(OR($Q754=Parametres!$G$2,$Q754=Parametres!$G$3),K754,E754) -> 0 | Q754: =+F754 -> 0 | R754: =+G754 -> 0 | S754: =+H754 -> 0 | T754: =+VLOOKUP($L754,Data_Validation!$A:$D,1,0) -> #N/A | U754: =+VLOOKUP($L754,Data_Validation!$A:$D,3,0) -> #N/A | V754: =+VLOOKUP($L754,Data_Validation!$A:$D,4,0) -> #N/A | W754: =+VLOOKUP($L754,Data_Validation!$A:$E,5,0) -> #N/A
L755: =+B755 -> 0 | M755: =+A755 -> 0 | N755: =+IF(OR($Q755=Parametres!$G$2,$Q755=Parametres!$G$3),I755,C755) -> 0 | O755: =+IF(OR($Q755=Parametres!$G$2,$Q755=Parametres!$G$3),J755,D755) -> 0 | P755: =+IF(OR($Q755=Parametres!$G$2,$Q755=Parametres!$G$3),K755,E755) -> 0 | Q755: =+F755 -> 0 | R755: =+G755 -> 0 | S755: =+H755 -> 0 | T755: =+VLOOKUP($L755,Data_Validation!$A:$D,1,0) -> #N/A | U755: =+VLOOKUP($L755,Data_Validation!$A:$D,3,0) -> #N/A | V755: =+VLOOKUP($L755,Data_Validation!$A:$D,4,0) -> #N/A | W755: =+VLOOKUP($L755,Data_Validation!$A:$E,5,0) -> #N/A
...

Sheet BV_Data_An_Prec
A1: Description | B1: #Compte | C1: Solde d'ouverture | D1: Solde courant | E1: Solde de fin | F1: Type compte | G1: #Groupe | H1: Préfixe | I1: CUC/Mémo solde début | J1: CUC/Mémo solde actuel | K1: CUC/Mémo solde fin | L1: #Compte | M1: Description | N1: Solde d'ouverture | O1: Solde courant | P1: Solde de fin | Q1: Type compte | R1: #Groupe | S1: Préfixe | T1: Valid GL # | U1: Debits | V1: Classification | W1: $ / NB | X1: Ventes
A2: PROFIT JANVIER | B2: 101 | F2: 1-Mémo | G2: 101 | I2: -87636 | J2: 0 | K2: -87636 | L2: =+B2 -> 101 | M2: =+A2 -> PROFIT JANVIER | N2: =+IF(OR($Q2=Parametres!$G$2,$Q2=Parametres!$G$3),I2,C2) -> -87636 | O2: =+IF(OR($Q2=Parametres!$G$2,$Q2=Parametres!$G$3),J2,D2) -> 0 | P2: =+IF(OR($Q2=Parametres!$G$2,$Q2=Parametres!$G$3),K2,E2) -> -87636 | Q2: =+F2 -> 1-Mémo | R2: =+G2 -> 101 | S2: =+H2 -> 0 | T2: =+VLOOKUP($L2,Data_Validation!$A:$E,1,0) -> 101 | U2: =+VLOOKUP($L2,Data_Validation!$A:$E,3,0) -> Autres | V2: =+VLOOKUP($L2,Data_Validation!$A:$E,4,0) -> 0 | W2: =VLOOKUP($L2,Data_Validation!$A:$E,5,FALSE) -> 0 | X2: =+VLOOKUP($L2,Data_Validation!$A:$F,6,0) -> 0
A3: PROFIT FEVRIER | B3: 102 | F3: 1-Mémo | G3: 102 | I3: 3380 | J3: 0 | K3: 3380 | L3: =+B3 -> 102 | M3: =+A3 -> PROFIT FEVRIER | N3: =+IF(OR($Q3=Parametres!$G$2,$Q3=Parametres!$G$3),I3,C3) -> 3380 | O3: =+IF(OR($Q3=Parametres!$G$2,$Q3=Parametres!$G$3),J3,D3) -> 0 | P3: =+IF(OR($Q3=Parametres!$G$2,$Q3=Parametres!$G$3),K3,E3) -> 3380 | Q3: =+F3 -> 1-Mémo | R3: =+G3 -> 102 | S3: =+H3 -> 0 | T3: =+VLOOKUP($L3,Data_Validation!$A:$D,1,0) -> 102 | U3: =+VLOOKUP($L3,Data_Validation!$A:$D,3,0) -> Autres | V3: =+VLOOKUP($L3,Data_Validation!$A:$D,4,0) -> 0 | W3: =+VLOOKUP($L3,Data_Validation!$A:$E,5,0) -> 0 | X3: =+VLOOKUP($L3,Data_Validation!$A:$F,6,0) -> 0
A4: PROFIT MARS | B4: 103 | F4: 1-Mémo | G4: 103 | I4: 242199 | J4: 0 | K4: 242199 | L4: =+B4 -> 103 | M4: =+A4 -> PROFIT MARS | N4: =+IF(OR($Q4=Parametres!$G$2,$Q4=Parametres!$G$3),I4,C4) -> 242199 | O4: =+IF(OR($Q4=Parametres!$G$2,$Q4=Parametres!$G$3),J4,D4) -> 0 | P4: =+IF(OR($Q4=Parametres!$G$2,$Q4=Parametres!$G$3),K4,E4) -> 242199 | Q4: =+F4 -> 1-Mémo | R4: =+G4 -> 103 | S4: =+H4 -> 0 | T4: =+VLOOKUP($L4,Data_Validation!$A:$D,1,0) -> 103 | U4: =+VLOOKUP($L4,Data_Validation!$A:$D,3,0) -> Autres | V4: =+VLOOKUP($L4,Data_Validation!$A:$D,4,0) -> 0 | W4: =+VLOOKUP($L4,Data_Validation!$A:$E,5,0) -> 0 | X4: =+VLOOKUP($L4,Data_Validation!$A:$F,6,0) -> 0
A5: PROFIT AVRIL | B5: 104 | F5: 1-Mémo | G5: 104 | I5: 218221 | J5: 0 | K5: 218221 | L5: =+B5 -> 104 | M5: =+A5 -> PROFIT AVRIL | N5: =+IF(OR($Q5=Parametres!$G$2,$Q5=Parametres!$G$3),I5,C5) -> 218221 | O5: =+IF(OR($Q5=Parametres!$G$2,$Q5=Parametres!$G$3),J5,D5) -> 0 | P5: =+IF(OR($Q5=Parametres!$G$2,$Q5=Parametres!$G$3),K5,E5) -> 218221 | Q5: =+F5 -> 1-Mémo | R5: =+G5 -> 104 | S5: =+H5 -> 0 | T5: =+VLOOKUP($L5,Data_Validation!$A:$D,1,0) -> 104 | U5: =+VLOOKUP($L5,Data_Validation!$A:$D,3,0) -> Autres | V5: =+VLOOKUP($L5,Data_Validation!$A:$D,4,0) -> 0 | W5: =+VLOOKUP($L5,Data_Validation!$A:$E,5,0) -> 0 | X5: =+VLOOKUP($L5,Data_Validation!$A:$F,6,0) -> 0
A6: PROFIT MAI | B6: 105 | F6: 1-Mémo | G6: 105 | I6: 202342 | J6: 0 | K6: 202342 | L6: =+B6 -> 105 | M6: =+A6 -> PROFIT MAI | N6: =+IF(OR($Q6=Parametres!$G$2,$Q6=Parametres!$G$3),I6,C6) -> 202342 | O6: =+IF(OR($Q6=Parametres!$G$2,$Q6=Parametres!$G$3),J6,D6) -> 0 | P6: =+IF(OR($Q6=Parametres!$G$2,$Q6=Parametres!$G$3),K6,E6) -> 202342 | Q6: =+F6 -> 1-Mémo | R6: =+G6 -> 105 | S6: =+H6 -> 0 | T6: =+VLOOKUP($L6,Data_Validation!$A:$D,1,0) -> 105 | U6: =+VLOOKUP($L6,Data_Validation!$A:$D,3,0) -> Autres | V6: =+VLOOKUP($L6,Data_Validation!$A:$D,4,0) -> 0 | W6: =+VLOOKUP($L6,Data_Validation!$A:$E,5,0) -> 0 | X6: =+VLOOKUP($L6,Data_Validation!$A:$F,6,0) -> 0
A7: PROFIT JUIN | B7: 106 | F7: 1-Mémo | G7: 106 | I7: 171402 | J7: 0 | K7: 171402 | L7: =+B7 -> 106 | M7: =+A7 -> PROFIT JUIN | N7: =+IF(OR($Q7=Parametres!$G$2,$Q7=Parametres!$G$3),I7,C7) -> 171402 | O7: =+IF(OR($Q7=Parametres!$G$2,$Q7=Parametres!$G$3),J7,D7) -> 0 | P7: =+IF(OR($Q7=Parametres!$G$2,$Q7=Parametres!$G$3),K7,E7) -> 171402 | Q7: =+F7 -> 1-Mémo | R7: =+G7 -> 106 | S7: =+H7 -> 0 | T7: =+VLOOKUP($L7,Data_Validation!$A:$D,1,0) -> 106 | U7: =+VLOOKUP($L7,Data_Validation!$A:$D,3,0) -> Autres | V7: =+VLOOKUP($L7,Data_Validation!$A:$D,4,0) -> 0 | W7: =+VLOOKUP($L7,Data_Validation!$A:$E,5,0) -> 0 | X7: =+VLOOKUP($L7,Data_Validation!$A:$F,6,0) -> 0
A8: PROFIT JUILLET | B8: 107 | F8: 1-Mémo | G8: 107 | I8: 123120 | J8: 0 | K8: 123120 | L8: =+B8 -> 107 | M8: =+A8 -> PROFIT JUILLET | N8: =+IF(OR($Q8=Parametres!$G$2,$Q8=Parametres!$G$3),I8,C8) -> 123120 | O8: =+IF(OR($Q8=Parametres!$G$2,$Q8=Parametres!$G$3),J8,D8) -> 0 | P8: =+IF(OR($Q8=Parametres!$G$2,$Q8=Parametres!$G$3),K8,E8) -> 123120 | Q8: =+F8 -> 1-Mémo | R8: =+G8 -> 107 | S8: =+H8 -> 0 | T8: =+VLOOKUP($L8,Data_Validation!$A:$D,1,0) -> 107 | U8: =+VLOOKUP($L8,Data_Validation!$A:$D,3,0) -> Autres | V8: =+VLOOKUP($L8,Data_Validation!$A:$D,4,0) -> 0 | W8: =+VLOOKUP($L8,Data_Validation!$A:$E,5,0) -> 0 | X8: =+VLOOKUP($L8,Data_Validation!$A:$F,6,0) -> 0
A9: PROFIT AOUT | B9: 108 | F9: 1-Mémo | G9: 108 | I9: 70058 | J9: 0 | K9: 70058 | L9: =+B9 -> 108 | M9: =+A9 -> PROFIT AOUT | N9: =+IF(OR($Q9=Parametres!$G$2,$Q9=Parametres!$G$3),I9,C9) -> 70058 | O9: =+IF(OR($Q9=Parametres!$G$2,$Q9=Parametres!$G$3),J9,D9) -> 0 | P9: =+IF(OR($Q9=Parametres!$G$2,$Q9=Parametres!$G$3),K9,E9) -> 70058 | Q9: =+F9 -> 1-Mémo | R9: =+G9 -> 108 | S9: =+H9 -> 0 | T9: =+VLOOKUP($L9,Data_Validation!$A:$D,1,0) -> 108 | U9: =+VLOOKUP($L9,Data_Validation!$A:$D,3,0) -> Autres | V9: =+VLOOKUP($L9,Data_Validation!$A:$D,4,0) -> 0 | W9: =+VLOOKUP($L9,Data_Validation!$A:$E,5,0) -> 0 | X9: =+VLOOKUP($L9,Data_Validation!$A:$F,6,0) -> 0
A10: PROFIT SPTEMBRE | B10: 109 | F10: 1-Mémo | G10: 109 | I10: 63471 | J10: 0 | K10: 63471 | L10: =+B10 -> 109 | M10: =+A10 -> PROFIT SPTEMBRE | N10: =+IF(OR($Q10=Parametres!$G$2,$Q10=Parametres!$G$3),I10,C10) -> 63471 | O10: =+IF(OR($Q10=Parametres!$G$2,$Q10=Parametres!$G$3),J10,D10) -> 0 | P10: =+IF(OR($Q10=Parametres!$G$2,$Q10=Parametres!$G$3),K10,E10) -> 63471 | Q10: =+F10 -> 1-Mémo | R10: =+G10 -> 109 | S10: =+H10 -> 0 | T10: =+VLOOKUP($L10,Data_Validation!$A:$D,1,0) -> 109 | U10: =+VLOOKUP($L10,Data_Validation!$A:$D,3,0) -> Autres | V10: =+VLOOKUP($L10,Data_Validation!$A:$D,4,0) -> 0 | W10: =+VLOOKUP($L10,Data_Validation!$A:$E,5,0) -> 0 | X10: =+VLOOKUP($L10,Data_Validation!$A:$F,6,0) -> 0
A11: PROFIT OCTOBRE | B11: 110 | F11: 1-Mémo | G11: 110 | I11: -181040 | J11: 0 | K11: -181040 | L11: =+B11 -> 110 | M11: =+A11 -> PROFIT OCTOBRE | N11: =+IF(OR($Q11=Parametres!$G$2,$Q11=Parametres!$G$3),I11,C11) -> -181040 | O11: =+IF(OR($Q11=Parametres!$G$2,$Q11=Parametres!$G$3),J11,D11) -> 0 | P11: =+IF(OR($Q11=Parametres!$G$2,$Q11=Parametres!$G$3),K11,E11) -> -181040 | Q11: =+F11 -> 1-Mémo | R11: =+G11 -> 110 | S11: =+H11 -> 0 | T11: =+VLOOKUP($L11,Data_Validation!$A:$D,1,0) -> 110 | U11: =+VLOOKUP($L11,Data_Validation!$A:$D,3,0) -> Autres | V11: =+VLOOKUP($L11,Data_Validation!$A:$D,4,0) -> 0 | W11: =+VLOOKUP($L11,Data_Validation!$A:$E,5,0) -> 0 | X11: =+VLOOKUP($L11,Data_Validation!$A:$F,6,0) -> 0
A12: PROFIT NOVEMBRE | B12: 111 | F12: 1-Mémo | G12: 111 | I12: 93899 | J12: 0 | K12: 93899 | L12: =+B12 -> 111 | M12: =+A12 -> PROFIT NOVEMBRE | N12: =+IF(OR($Q12=Parametres!$G$2,$Q12=Parametres!$G$3),I12,C12) -> 93899 | O12: =+IF(OR($Q12=Parametres!$G$2,$Q12=Parametres!$G$3),J12,D12) -> 0 | P12: =+IF(OR($Q12=Parametres!$G$2,$Q12=Parametres!$G$3),K12,E12) -> 93899 | Q12: =+F12 -> 1-Mémo | R12: =+G12 -> 111 | S12: =+H12 -> 0 | T12: =+VLOOKUP($L12,Data_Validation!$A:$D,1,0) -> 111 | U12: =+VLOOKUP($L12,Data_Validation!$A:$D,3,0) -> Autres | V12: =+VLOOKUP($L12,Data_Validation!$A:$D,4,0) -> 0 | W12: =+VLOOKUP($L12,Data_Validation!$A:$E,5,0) -> 0 | X12: =+VLOOKUP($L12,Data_Validation!$A:$F,6,0) -> 0
A13: JANV. NB VENTE NEUF BMW AUTO | B13: 120A | F13: 1-Mémo | G13: 120 | I13: 0.03 | J13: 0 | K13: 0.03 | L13: =+B13 -> 120A | M13: =+A13 -> JANV. NB VENTE NEUF BMW AUTO | N13: =+IF(OR($Q13=Parametres!$G$2,$Q13=Parametres!$G$3),I13,C13) -> 0.03 | O13: =+IF(OR($Q13=Parametres!$G$2,$Q13=Parametres!$G$3),J13,D13) -> 0 | P13: =+IF(OR($Q13=Parametres!$G$2,$Q13=Parametres!$G$3),K13,E13) -> 0.03 | Q13: =+F13 -> 1-Mémo | R13: =+G13 -> 120 | S13: =+H13 -> 0 | T13: =+VLOOKUP($L13,Data_Validation!$A:$D,1,0) -> 120A | U13: =+VLOOKUP($L13,Data_Validation!$A:$D,3,0) -> Autres | V13: =+VLOOKUP($L13,Data_Validation!$A:$D,4,0) -> 0 | W13: =+VLOOKUP($L13,Data_Validation!$A:$E,5,0) -> 0 | X13: =+VLOOKUP($L13,Data_Validation!$A:$F,6,0) -> 0
