Workbook
Name _Dates_Conc: #REF!
Name _Dates_Conc: #REF!
Name _scen: #REF!
Name _scen: #REF!
Name _scen1: #REF!
Name _scen1: #REF!
Name _scen2: #REF!
Name _scen2: #REF!
Name _SCenarios: #REF!
Name _SCenarios: #REF!
Name _Sens1: #REF!
Name _Sens1: #REF!
Name _Sens2: #REF!
Name _Sens2: #REF!
Name _sensRes1: #REF!
Name _sensRes1: #REF!
Name _sensRes2: #REF!
Name _sensRes2: #REF!
Name _sensRes3: #REF!
Name _sensRes3: #REF!
Name _sensRes4: #REF!
Name _sensRes4: #REF!
Name _sensRes5: #REF!
Name _sensRes5: #REF!
Name _sensRes6: #REF!
Name _sensRes6: #REF!
Name _sensRes7: #REF!
Name _sensRes7: #REF!
Name Compco1: {"Page1",#N/A,FALSE,"CompCo";"Page2",#N/A,FALSE,"CompCo"}
Name Compco2: {"Page1",#N/A,FALSE,"CompCo";"Page2",#N/A,FALSE,"CompCo"}
Name DateRange: #REF!
Name DateRange: #REF!
Name DateRangePr: OFFSET(#REF!,5,0,COUNTA(#REF!)-COUNTA(#REF!),1)
Name DateRangePrice: OFFSET(#REF!,5,0,COUNTA(#REF!)-COUNTA(#REF!),1)
Name DateRangePrice1: OFFSET(#REF!,5,0,COUNTA(#REF!)-COUNTA(#REF!),1)
Name DateRangePrice2: OFFSET(#REF!,5,0,COUNTA(#REF!)-COUNTA(#REF!),1)
Name ERT: {"execsum",#N/A,FALSE,"ExecSum";"finstatement",#N/A,FALSE,"Fin_St"}
Name hn.Delete015: #REF!,#REF!,#REF!,#REF!,#REF!
Name kjjkghkhj: {"finana",#N/A,FALSE,"Fin"}
Name lkhkhj: {"sub1",#N/A,FALSE,"Subs";"pac1",#N/A,FALSE,"Packages";"rev1",#N/A,FALSE,"2. Revenues"}
Name Monetary_Unit: #REF!
Name Monetary_Unit: #REF!
Name Months: #REF!
Name Months: #REF!
Name PriceRange: OFFSET(#REF!,5,0,COUNTA(#REF!)-COUNTA(#REF!),1)
Name PriceRange2: OFFSET(#REF!,5,0,COUNTA(#REF!)-COUNTA(#REF!),1)
Name Rng_Dealers_Names: #REF!
Name Rng_Dealers_Names: #REF!
Name Rng_Dlr_Dates: #REF!
Name Rng_Dlr_Dates: #REF!
Name test: {"execsum",#N/A,FALSE,"ExecSum";"finstatement",#N/A,FALSE,"Fin_St"}
Name test21: OFFSET(#REF!,5,0,COUNTA(#REF!)-COUNTA(#REF!),1)
Name Ticker: #REF!
Name Ticker: #REF!
Name Titre: #REF!
Name Titre: #REF!
Name value: OFFSET(#REF!,5,0,COUNTA(#REF!)-COUNTA(#REF!),1)
Name value2: OFFSET(#REF!,5,0,COUNTA(#REF!)-COUNTA(#REF!),1)
Name wrn.amendement.: {#N/A,#N/A,FALSE,"amendement"}
Name wrn.amendement..: {#N/A,#N/A,FALSE,"amendement"}

Sheet Parametres
A1: Compagnie | B1: BMW Sherbrooke
G2: 1-Mémo | M2: Mois | N2: YTD
A3: Mois Courant | B3: Juin | C3: =+VLOOKUP(B3,$K$3:$L$14,2,0) -> 6 | G3: 10-Compte compteur | K3: Janvier | L3: 1 | M3: =+IF($K3=$B$3,"X","") | N3: =+IF(K3=B3,"X",IF(L3<=$C$3,"X","")) -> X
A4: Année | B4: 2026 | K4: Février | L4: 2 | M4: =+IF($K4=$B$3,"X","") | N4: =+IF(K4=B4,"X",IF(L4<=$C$3,"X","")) -> X
K5: Mars | L5: 3 | M5: =+IF($K5=$B$3,"X","") | N5: =+IF(K5=B5,"X",IF(L5<=$C$3,"X","")) -> X
K6: Avril | L6: 4 | M6: =+IF($K6=$B$3,"X","") | N6: =+IF(K6=B6,"X",IF(L6<=$C$3,"X","")) -> X
K7: Mai | L7: 5 | M7: =+IF($K7=$B$3,"X","") | N7: =+IF(K7=B7,"X",IF(L7<=$C$3,"X","")) -> X
K8: Juin | L8: 6 | M8: =+IF($K8=$B$3,"X","") -> X | N8: =+IF(K8=B8,"X",IF(L8<=$C$3,"X","")) -> X
A9: Sélectionner le mois en B3 | K9: Juillet | L9: 7 | M9: =+IF($K9=$B$3,"X","") | N9: =+IF(K9=B9,"X",IF(L9<=$C$3,"X",""))
A10: Coller les balances de vérification respectives en cellule A1 dans les onglets BV_Data_An_Cour et BV_Data_An_Prec | K10: Août | L10: 8 | M10: =+IF($K10=$B$3,"X","") | N10: =+IF(K10=B10,"X",IF(L10<=$C$3,"X",""))
A11: Vérifier s'il y a des #N/A dans les colonnes T à X des onlgets de BV | K11: Septembre | L11: 9 | M11: =+IF($K11=$B$3,"X","") | N11: =+IF(K11=B11,"X",IF(L11<=$C$3,"X",""))
A12: Vérifier les chiffres avec l'état financier et les réalisés an passé pour les résultat net mois et aad | K12: Octobre | L12: 10 | M12: =+IF($K12=$B$3,"X","") | N12: =+IF(K12=B12,"X",IF(L12<=$C$3,"X",""))
K13: Novembre | L13: 11 | M13: =+IF($K13=$B$3,"X","") | N13: =+IF(K13=B13,"X",IF(L13<=$C$3,"X",""))
K14: Décembre | L14: 12 | M14: =+IF($K14=$B$3,"X","") | N14: =+IF(K14=B14,"X",IF(L14<=$C$3,"X",""))

Sheet Bilan
A1: BILAN
A2: =+Parametres!B1 -> BMW Sherbrooke
A3: =CONCATENATE("",,Parametres!B3," ",Parametres!B4) -> Juin 2026
A5: Encaisse | B5: =SUMIFS(BV_Data_An_Cour!$P:$P,BV_Data_An_Cour!$U:$U,$A$1,BV_Data_An_Cour!$V:$V,$A5) -> 1514025.7 | D5: Marge de crédit | E5: =-SUMIFS(BV_Data_An_Cour!$P:$P,BV_Data_An_Cour!$U:$U,$A$1,BV_Data_An_Cour!$V:$V,$D5) -> 0
A6: Total Trésorerie et équivalent de Trésorerie | B6: =SUM(B5) -> 1514025.7
D7: Portion Court Terme de la Dette Long Terme | E7: =-SUMIFS(BV_Data_An_Cour!$P:$P,BV_Data_An_Cour!$U:$U,$A$1,BV_Data_An_Cour!$V:$V,$D7) -> 0
A8: Recevables Contrats en Transit | B8: =SUMIFS(BV_Data_An_Cour!$P:$P,BV_Data_An_Cour!$U:$U,$A$1,BV_Data_An_Cour!$V:$V,$A8) -> 1303189.8
A9: Recevables Véhicules | B9: =SUMIFS(BV_Data_An_Cour!$P:$P,BV_Data_An_Cour!$U:$U,$A$1,BV_Data_An_Cour!$V:$V,$A9) -> 143841.73 | D9: Avances à payer | E9: =-SUMIFS(BV_Data_An_Cour!$P:$P,BV_Data_An_Cour!$U:$U,$A$1,BV_Data_An_Cour!$V:$V,$D9) -> 0
A10: Recevables Manufacturier | B10: =SUMIFS(BV_Data_An_Cour!$P:$P,BV_Data_An_Cour!$U:$U,$A$1,BV_Data_An_Cour!$V:$V,$A10) -> 225476.84 | D10: Comptes à Payer Fournisseurs | E10: =-SUMIFS(BV_Data_An_Cour!$P:$P,BV_Data_An_Cour!$U:$U,$A$1,BV_Data_An_Cour!$V:$V,$D10) -> 178046.18
A11: Recevables Pièces et Service | B11: =SUMIFS(BV_Data_An_Cour!$P:$P,BV_Data_An_Cour!$U:$U,$A$1,BV_Data_An_Cour!$V:$V,$A11) -> 167071.97 | D11: Taxes de Vente à Payer | E11: =-SUMIFS(BV_Data_An_Cour!$P:$P,BV_Data_An_Cour!$U:$U,$A$1,BV_Data_An_Cour!$V:$V,$D11) -> 9549.47
A12: Recevables Garantie Manufacturier | B12: =SUMIFS(BV_Data_An_Cour!$P:$P,BV_Data_An_Cour!$U:$U,$A$1,BV_Data_An_Cour!$V:$V,$A12) -> 81342.3 | D12: Impôts à payer | E12: =-SUMIFS(BV_Data_An_Cour!$P:$P,BV_Data_An_Cour!$U:$U,$A$1,BV_Data_An_Cour!$V:$V,$D12) -> 0
A13: Recevables Carrosserie | B13: =SUMIFS(BV_Data_An_Cour!$P:$P,BV_Data_An_Cour!$U:$U,$A$1,BV_Data_An_Cour!$V:$V,$A13) -> 0 | D13: Dépôts de Client | E13: =-SUMIFS(BV_Data_An_Cour!$P:$P,BV_Data_An_Cour!$U:$U,$A$1,BV_Data_An_Cour!$V:$V,$D13) -> 88092
A14: Recevables Intercos | B14: =SUMIFS(BV_Data_An_Cour!$P:$P,BV_Data_An_Cour!$U:$U,$A$1,BV_Data_An_Cour!$V:$V,$A14) -> 511009.67 | D14: Payables Intercos | E14: =-SUMIFS(BV_Data_An_Cour!$P:$P,BV_Data_An_Cour!$U:$U,$A$1,BV_Data_An_Cour!$V:$V,$D14) -> -7272.58
A15: Recevables Autres | B15: =SUMIFS(BV_Data_An_Cour!$P:$P,BV_Data_An_Cour!$U:$U,$A$1,BV_Data_An_Cour!$V:$V,$A15) -> 189329.77 | D15: Autres Comptes à Payer | E15: =-SUMIFS(BV_Data_An_Cour!$P:$P,BV_Data_An_Cour!$U:$U,$A$1,BV_Data_An_Cour!$V:$V,$D15) -> 21261.4
A16: Total Comptes à Recevoir | B16: =+SUM(B8:B15) -> 2621262.1 | D16: Total Comptes à Payer | E16: =+SUM(E10:E15) -> 289676.47
A18: Inventaire Véhicules Neufs | B18: =SUMIFS(BV_Data_An_Cour!$P:$P,BV_Data_An_Cour!$U:$U,$A$1,BV_Data_An_Cour!$V:$V,$A18) -> 6853697.9 | D18: Effet à Payer Véhicules Neufs | E18: =-SUMIFS(BV_Data_An_Cour!$P:$P,BV_Data_An_Cour!$U:$U,$A$1,BV_Data_An_Cour!$V:$V,$D18) -> 8390410.8
A19: Inventaire Véhicules Usagés | B19: =SUMIFS(BV_Data_An_Cour!$P:$P,BV_Data_An_Cour!$U:$U,$A$1,BV_Data_An_Cour!$V:$V,$A19) -> 2870817.2 | D19: Effet à Payer Véhicules Usagés | E19: =-SUMIFS(BV_Data_An_Cour!$P:$P,BV_Data_An_Cour!$U:$U,$A$1,BV_Data_An_Cour!$V:$V,$D19) -> 2388609.2
A20: Inventaire Pièces, Pneus, Huile | B20: =SUMIFS(BV_Data_An_Cour!$P:$P,BV_Data_An_Cour!$U:$U,$A$1,BV_Data_An_Cour!$V:$V,$A20) -> 459789.78 | D20: Total Effets à Payer | E20: =+SUM(E18:E19) -> 10779020
A21: Total Inventaires | B21: =SUM(B18:B20) -> 10184305
D22: Salaires à Payer | E22: =-SUMIFS(BV_Data_An_Cour!$P:$P,BV_Data_An_Cour!$U:$U,$A$1,BV_Data_An_Cour!$V:$V,$D22) -> 274230.53
A23: Avances à recevoir | B23: =SUMIFS(BV_Data_An_Cour!$P:$P,BV_Data_An_Cour!$U:$U,$A$1,BV_Data_An_Cour!$V:$V,$A23) -> 0 | D23: DAS à Payer | E23: =-SUMIFS(BV_Data_An_Cour!$P:$P,BV_Data_An_Cour!$U:$U,$A$1,BV_Data_An_Cour!$V:$V,$D23) -> 674.57
A24: Travaux en Cours | B24: =SUMIFS(BV_Data_An_Cour!$P:$P,BV_Data_An_Cour!$U:$U,$A$1,BV_Data_An_Cour!$V:$V,$A24) -> 7366.75 | D24: Autres Courus | E24: =-SUMIFS(BV_Data_An_Cour!$P:$P,BV_Data_An_Cour!$U:$U,$A$1,BV_Data_An_Cour!$V:$V,$D24) -> 286667.63
A25: Sous-Traitance | B25: =SUMIFS(BV_Data_An_Cour!$P:$P,BV_Data_An_Cour!$U:$U,$A$1,BV_Data_An_Cour!$V:$V,$A25) -> -15287.65 | D25: [...] | E25: =-SUMIFS(BV_Data_An_Cour!$P:$P,BV_Data_An_Cour!$U:$U,$A$1,BV_Data_An_Cour!$V:$V,$D25) -> 0
A26: Frais Payés d'Avance | B26: =SUMIFS(BV_Data_An_Cour!$P:$P,BV_Data_An_Cour!$U:$U,$A$1,BV_Data_An_Cour!$V:$V,$A26) -> 374795.63 | D26: [...] | E26: =-SUMIFS(BV_Data_An_Cour!$P:$P,BV_Data_An_Cour!$U:$U,$A$1,BV_Data_An_Cour!$V:$V,$D26) -> 0
A27: [...] | B27: =SUMIFS(BV_Data_An_Cour!$P:$P,BV_Data_An_Cour!$U:$U,$A$1,BV_Data_An_Cour!$V:$V,$A27) -> 0 | D27: [...] | E27: =-SUMIFS(BV_Data_An_Cour!$P:$P,BV_Data_An_Cour!$U:$U,$A$1,BV_Data_An_Cour!$V:$V,$D27) -> 0
A28: [...] | B28: =SUMIFS(BV_Data_An_Cour!$P:$P,BV_Data_An_Cour!$U:$U,$A$1,BV_Data_An_Cour!$V:$V,$A28) -> 0 | D28: Total Frais Courus | E28: =SUM(E22:E24) -> 561572.73
A29: [...] | B29: =SUMIFS(BV_Data_An_Cour!$P:$P,BV_Data_An_Cour!$U:$U,$A$1,BV_Data_An_Cour!$V:$V,$A29) -> 0
A30: Total Autres | B30: =SUM(B23:B29) -> 366874.73 | D30: Total Passif Court Terme | E30: =+E5+E7+E16+E20+E28 -> 11630269
A32: Total Actif Court Terme | B32: =+B6+B16+B21+B30 -> 14686467
D33: Impôts Futurs à payer | E33: =-SUMIFS(BV_Data_An_Cour!$P:$P,BV_Data_An_Cour!$U:$U,$A$1,BV_Data_An_Cour!$V:$V,$D33) -> 0
A35: Terrain | B35: =SUMIFS(BV_Data_An_Cour!$P:$P,BV_Data_An_Cour!$U:$U,$A$1,BV_Data_An_Cour!$V:$V,$A35) -> 0 | D35: Avances Long Terme à Payer | E35: =-SUMIFS(BV_Data_An_Cour!$P:$P,BV_Data_An_Cour!$U:$U,$A$1,BV_Data_An_Cour!$V:$V,$D35) -> 10494016
A36: Bâtisse | B36: =SUMIFS(BV_Data_An_Cour!$P:$P,BV_Data_An_Cour!$U:$U,$A$1,BV_Data_An_Cour!$V:$V,$A36) -> 0 | D36: Hypothèque à Payer | E36: =-SUMIFS(BV_Data_An_Cour!$P:$P,BV_Data_An_Cour!$U:$U,$A$1,BV_Data_An_Cour!$V:$V,$D36) -> 0
A37: Améliorations Locatives | B37: =SUMIFS(BV_Data_An_Cour!$P:$P,BV_Data_An_Cour!$U:$U,$A$1,BV_Data_An_Cour!$V:$V,$A37) -> 1841 | D37: Dette à Long Terme | E37: =-SUMIFS(BV_Data_An_Cour!$P:$P,BV_Data_An_Cour!$U:$U,$A$1,BV_Data_An_Cour!$V:$V,$D37) -> 10281476
A38: Améliorations Locatives Permanentes | B38: =SUMIFS(BV_Data_An_Cour!$P:$P,BV_Data_An_Cour!$U:$U,$A$1,BV_Data_An_Cour!$V:$V,$A38) -> 0 | D38: Autres Dettes à Long Terme | E38: =-SUMIFS(BV_Data_An_Cour!$P:$P,BV_Data_An_Cour!$U:$U,$A$1,BV_Data_An_Cour!$V:$V,$D38) -> 0
A39: Équipements Service | B39: =SUMIFS(BV_Data_An_Cour!$P:$P,BV_Data_An_Cour!$U:$U,$A$1,BV_Data_An_Cour!$V:$V,$A39) -> 208761.14 | D39: [...] | E39: =-SUMIFS(BV_Data_An_Cour!$P:$P,BV_Data_An_Cour!$U:$U,$A$1,BV_Data_An_Cour!$V:$V,$D39) -> 0
A40: Mobilier | B40: =SUMIFS(BV_Data_An_Cour!$P:$P,BV_Data_An_Cour!$U:$U,$A$1,BV_Data_An_Cour!$V:$V,$A40) -> 189875.51 | D40: [...] | E40: =-SUMIFS(BV_Data_An_Cour!$P:$P,BV_Data_An_Cour!$U:$U,$A$1,BV_Data_An_Cour!$V:$V,$D40) -> 0
A41: Équipements Informatique | B41: =SUMIFS(BV_Data_An_Cour!$P:$P,BV_Data_An_Cour!$U:$U,$A$1,BV_Data_An_Cour!$V:$V,$A41) -> 27372.98 | D41: [...] | E41: =-SUMIFS(BV_Data_An_Cour!$P:$P,BV_Data_An_Cour!$U:$U,$A$1,BV_Data_An_Cour!$V:$V,$D41) -> 0
A42: Équipements Téléphonique | B42: =SUMIFS(BV_Data_An_Cour!$P:$P,BV_Data_An_Cour!$U:$U,$A$1,BV_Data_An_Cour!$V:$V,$A42) -> 0 | D42: Total Passif long terme | E42: =+SUM(E33:E38) -> 20775492
A43: Enseigne | B43: =SUMIFS(BV_Data_An_Cour!$P:$P,BV_Data_An_Cour!$U:$U,$A$1,BV_Data_An_Cour!$V:$V,$A43) -> 9327.02
A44: Total Immobilisations Nettes | B44: =SUM(B35:B43) -> 437177.65
D45: Total Passifs | E45: =+E42+E30 -> 32405761
A46: Avances à Recevoir Long Terme | B46: =SUMIFS(BV_Data_An_Cour!$P:$P,BV_Data_An_Cour!$U:$U,$A$1,BV_Data_An_Cour!$V:$V,$A46) -> 8700000
A48: Achalandage | B48: =SUMIFS(BV_Data_An_Cour!$P:$P,BV_Data_An_Cour!$U:$U,$A$1,BV_Data_An_Cour!$V:$V,$A48) -> 9500000 | D48: Capital Actions | E48: =-SUMIFS(BV_Data_An_Cour!$P:$P,BV_Data_An_Cour!$U:$U,$A$1,BV_Data_An_Cour!$V:$V,$D48) -> 0
D49: Apport | E49: =-SUMIFS(BV_Data_An_Cour!$P:$P,BV_Data_An_Cour!$U:$U,$A$1,BV_Data_An_Cour!$V:$V,$D49) -> 0
A50: [...] | B50: =SUMIFS(BV_Data_An_Cour!$P:$P,BV_Data_An_Cour!$U:$U,$A$1,BV_Data_An_Cour!$V:$V,$A50) -> 0 | D50: Bénéfices non répartis | E50: =-SUMIFS(BV_Data_An_Cour!$P:$P,BV_Data_An_Cour!$U:$U,$A$1,BV_Data_An_Cour!$V:$V,$D50)+'Réalisé AAD'!AF503 -> 917883.97
A51: [...] | B51: =SUMIFS(BV_Data_An_Cour!$P:$P,BV_Data_An_Cour!$U:$U,$A$1,BV_Data_An_Cour!$V:$V,$A51) -> 0 | D51: Dividendes | E51: =-SUMIFS(BV_Data_An_Cour!$P:$P,BV_Data_An_Cour!$U:$U,$A$1,BV_Data_An_Cour!$V:$V,$D51) -> 0
A52: [...] | B52: =SUMIFS(BV_Data_An_Cour!$P:$P,BV_Data_An_Cour!$U:$U,$A$1,BV_Data_An_Cour!$V:$V,$A52) -> 0
A53: Total Actif Long Terme | B53: =+B44+B48+B46 -> 18637178 | D53: Total Capitaux Propres / Avoir | E53: =SUM(E48:E51) -> 917883.97
A56: Total Actif | B56: =+B32+B53 -> 33323645 | D56: Total Passif et Capitaux Propres / Avoir | E56: =+E53+E45 -> 33323645
E65: =+B56-E56 -> 0

Sheet Inventaire_Neuf
A1: #Contrôle | B1: Année | C1: Marque | D1: Modèle | E1: $ Inventaire | F1: $ Financé | G1: NIV | H1: Jours en stock | L1: $ Inventaire | M1: $ Financé
A2: 23019 | B2: 2023 | C2: BMW | D2: 430 | E2: 65121.87 | F2: -60905.25 | G2: WBA73AP05PCL27730 | H2: 478 | K2: CTRL | L2: =+SUM(E2:E10000) -> 3938633.3 | M2: =+SUM(F2:F10000) -> -3910068
A3: 23020 | B3: 2023 | C3: BMW | D3: 430 | E3: 63963.67 | G3: WBA73AP06PCL26036 | H3: 465 | L3: =+COUNT(E2:E10000) -> 45
A4: 23084 | B4: 2023 | C4: BMW | D4: 530xe | E4: 75509.5 | G4: WBA33AG06PCL42221 | H4: 411
A5: 23218 | B5: 2023 | C5: BMW SAV | D5: X3 | E5: 84833.61 | F5: -88452 | G5: 5UX83DP04P9T17873 | H5: 146
A6: 23221 | B6: 2023 | C6: BMW | D6: SERIE 2 | E6: 66617.36 | F6: -69326.25 | G6: 3MW53CM06P8D70441 | H6: 151
A7: 23228 | B7: 2023 | C7: BMW SAV | D7: X3 | E7: 73335.37 | F7: -69809.25 | G7: 5UX53DP06P9T28635 | H7: 143
A8: 23240 | B8: 2023 | C8: BMW SAV | D8: X1 | E8: 50471.49 | F8: -50473.5 | G8: WBX73EF02P5X85602 | H8: 67
A9: 23241 | B9: 2023 | C9: BMW SAV | D9: X1 | E9: 50262.11 | F9: -52143 | G9: WBX73EF00P5X86053 | H9: 58
A10: 24019 | B10: 2024 | C10: BMW SAV | D10: X5 | E10: 95266.49 | F10: -95303.25 | G10: 5UX23EU05R9T15522 | H10: 158
A11: 24023 | B11: 2024 | C11: BMW SAV | D11: X7 | E11: 126612.36 | F11: -131675.25 | G11: 5UX23EM04R9T23238 | H11: 149
A12: 24024 | B12: 2024 | C12: BMWI | D12: IX40 | E12: 97633.14 | F12: -97203.75 | G12: WB513CF03RCN76497 | H12: 152
A13: 24032 | B13: 2024 | C13: BMW SAV | D13: X6 | E13: 103328.55 | F13: -107651.25 | G13: 5UX33EX02R9T31595 | H13: 144
A14: 24034 | B14: 2024 | C14: BMW | D14: SERIE 4 | E14: 66533.61 | F14: -69237 | G14: WBA73AP07RCN92250 | H14: 144
A15: 24038 | B15: 2024 | C15: BMWI | D15: I7 | E15: 159476.47 | F15: -173664.75 | G15: WBY53EJ01RCN94634 | H15: 142
A16: 24051 | B16: 2024 | C16: BMW | D16: SERIE 3 | E16: 62907.21 | F16: -60149.52 | G16: 3MW89FF00R8D80878 | H16: 117
... A46: 24130 | B46: 2024 | C46: BMW SAV | D46: X3 | E46: 65370 | F46: -68638.5 | G46: 5UX53DP06R9U99484 | H46: 9

Sheet Inventaire_Used
A1: #Contrôle | B1: Année | C1: Marque | D1: Description | E1: Amount | F1: Financé | G1: NIV | H1: Jours en stock | L1: $ Inventaire | M1: $ Financé
A2: P0512 | B2: 2004 | C2: CHEVROLET TRUCK | D2: SILVERADO 2500 | E2: 3856.45 | G2: 1GCGK23U14F218132 | H2: 1482 | K2: CTRL | L2: =+SUM(E2:E9999) -> 1972155.4 | M2: =+SUM(F2:F9999) -> -1357394.6
A3: P2173 | B3: 2022 | C3: BMW | D3: 540i | E3: 75917.21 | F3: -50220 | G3: WBA73BJ07NWX54871 | H3: 490 | L3: =+COUNT(E2:E10000) -> 50
A4: P2259 | B4: 2021 | C4: BMW SAV | D4: X5 | E4: 75668.81 | F4: -55025 | G4: 5UXTA6C07M9G89398 | H4: 306
A5: P2282 | B5: 2019 | C5: BMW | D5: Z4 | E5: 61477.55 | F5: -55037.5 | G5: WBAHF3C57KWW21386 | H5: 235
A6: P2321 | B6: 2021 | C6: JEEP | D6: GLADIATOR 4X4 | E6: 57247.58 | F6: -48210.15 | G6: 1C6HJTAG8ML543623 | H6: 144
A7: P2327 | B7: 2023 | C7: BMW SAV | D7: X1 | E7: 51697.81 | F7: -49599.39 | G7: WBX73EF03P5W40276 | H7: 137
A8: 23231A | B8: 2020 | C8: MINI | D8: COUNTRYMAN | E8: 35295.85 | F8: -20589.76 | G8: WMZYZ9C04L3L18702 | H8: 125
A9: P2334 | B9: 2019 | C9: BMW | D9: 330i | E9: 31287.41 | F9: -23537.41 | G9: WBA5R7C54KFH22955 | H9: 111
A10: 23193A | B10: 2022 | C10: VOLVO | D10: XC60 | E10: 58424.95 | F10: -80500 | G10: LYV062RL8NB979235 | H10: 108
A11: P2335 | B11: 2020 | C11: BMW SAV | D11: X3 | E11: 30904.85 | F11: -21000 | G11: 5UXTY5C03L9D44647 | H11: 103
A12: 24082A | B12: 2023 | C12: MAZDA | D12: MX-5 | E12: 34707.45 | F12: -32060.23 | G12: JM1NDAD7XP0552574 | H12: 73
A13: 23225A | B13: 2023 | C13: BMW | D13: 330i | E13: 54482.17 | F13: -37837.25 | G13: WBA83FF0XPFN75280 | H13: 72
A14: P2342A | B14: 2023 | C14: BMW | D14: 530e | E14: 65103.95 | F14: -45150 | G14: WBA33AG00PCL72878 | H14: 72
A15: P2343 | B15: 2023 | C15: ACURA | D15: Integra | E15: 39059.95 | F15: -35100 | G15: 19UDE4G72PA800656 | H15: 67
... A28: P2356 | B28: 2021 | C28: ACURA | D28: TLX | E28: 39793.95 | F28: -35550 | G28: 19UUB6F51MA801958 | H28: 38
A29: 24098A | B29: 2015 | C29: MINI | D29: 5 DOOR | E29: 8000 | G29: WMWXS5C59FT837198 | H29: 38
A30: 23116B | B30: 2021 | C30: JEEP | D30: Wrangler Unlim | E30: 43899.95 | F30: -30450 | G30: 1C4HJXEN3MW680010 | H30: 37
A31: 24078A | B31: 2023 | C31: VOLKSWAGEN | D31: ID.4 | E31: 47899.95 | F31: -34300 | G31: 1V2JNPE8XPC021183 | H31: 31
A32: 23243A | B32: 2020 | C32: BMW | D32: 2 SERIES | E32: 29024.85 | F32: -19599.51 | G32: WBA73AK0XL7G01503 | H32: 26
A33: P2361 | B33: 2014 | C33: BMW | D33: 320i | E33: 11164.86 | G33: WBA3C3C57EK200069 | H33: 22
A34: P2362 | B34: 2023 | C34: BMW | D34: M240i xDrive | E34: 53250.2 | F34: -52796.25 | G34: 3MW53CM03P8C99750 | H34: 20
A35: P2363 | B35: 2023 | C35: BMW | D35: 230i | E35: 42103.5 | F35: -41658.65 | G35: 3MW33CM08P8C93109 | H35: 18
A36: P2364 | B36: 2017 | C36: BMW SAV | D36: X4 | E36: 27407.01 | F36: -24300 | G36: 5UXXW3C37H0T79741 | H36: 17
A37: 24040A | B37: 2023 | C37: BMW SAV | D37: X4 | E37: 58745 | F37: -45726.94 | G37: 5UX33DT01P9N56202 | H37: 13
A38: P2367 | B38: 2019 | C38: NISSAN | D38: Micra | E38: 11000 | F38: -9900 | G38: 3N1CK3CP5KL236170 | H38: 10
A39: 23244A | B39: 2019 | C39: BMW SAV | D39: X2 | E39: 26995 | F39: -16020.18 | G39: WBXYJ5C54K5N01549 | H39: 10
A40: 24103A | B40: 2021 | C40: BMW SAV | D40: X3 | E40: 42500 | F40: -30072.18 | G40: 5UXTS1C06M9H64396 | H40: 10
A41: P2223A | B41: 2023 | C41: BMW | D41: I4 | E41: 51776.06 | F41: -29211.39 | G41: WBY43AW09PFP45888 | H41: 10
A42: P2366 | B42: 2012 | C42: BMW | D42: M3 | E42: 37500 | G42: WBSKG9C53CE798848 | H42: 10
A43: P2365 | B43: 2021 | C43: DODGE TRUCK | D43: RAM 1500 Class | E43: 32547.15 | F43: -32547.15 | G43: 3C6RR7KG7MG709002 | H43: 9
A44: 23227A | B44: 2017 | C44: HONDA | D44: CIVIC HATCHBAC | E44: 14000 | G44: SHHFK7H26HU304092 | H44: 9
A45: 24097A | B45: 2018 | C45: AUDI | D45: A5 Sportback | E45: 18500 | G45: WAUANCF51JA004190 | H45: 3
A46: 24126A | B46: 2017 | C46: BMW | D46: 2 SERIES | E46: 28000 | G46: WBA2L3C32HV667851 | H46: 3
A47: 24091B | B47: 2013 | C47: VOLKSWAGEN | D47: JETTA | E47: 1500 | G47: 3VW1K7AJ9DM416983 | H47: 2
A48: 24125B | B48: 2017 | C48: BMW | D48: 650i | E48: 37000 | G48: WBA6F7C50HD930698 | H48: 2
A49: 23122A | B49: 2022 | C49: BMW | D49: 2 SERIES | E49: 37500 | G49: WBA13AL03N7K75967 | H49: 2
A50: 24125A | B50: 2021 | C50: BMW SAV | D50: X5 | E50: 60000 | G50: 5UXJU4C08M9E22693 | H50: 2
A51: 24104B | B51: 2019 | C51: BMW SAV | D51: X2 | E51: 31000 | G51: WBXYN1C56K5N23209 | H51: 0

Sheet Réalisé Mois
C1: =Parametres!B1 -> BMW Sherbrooke | K1: Véhicules neufs | S1: =CONCATENATE("Réalisé,"," ",Parametres!B3," ",Parametres!B4) -> Réalisé, Juin 2026
D2: X | E2: O | F2: U | J2: NB | L2: $ | O2: X | P2: O | Q2: U
D3: BUDGET ORIGINAL | J3: RÉALISATION | M3: ÉCART réel / Budget | O3: ANNÉE PRÉCÉDENTE | R3: ECART (réel/ Ann.Préc.)
D4: UNITE | E4: $P/UNITÉ | F4: $PROFITS | J4: UNITE | K4: $P/UNITE | L4: $PROFITS | M4: UNFTÉ | N4: $PROFITS | O4: UNITE | P4: $P/UNITÉ | Q4: $PROFITS | R4: UNITE | S4: $PROFITS
A5: =+B5&C5 -> Véhicules neufsVentes nettes | B5: =+$K$1 -> Véhicules neufs | C5: Ventes nettes | F5: =+INDEX('Budget original'!$A$2:$AO$501,MATCH($A5,'Budget original'!$A$2:$A$501,0),MATCH(F$2,'Budget original'!$A$2:$AO$2,0)) -> 2474272 | L5: =-SUMIFS(BV_Data_An_Cour!$O:$O,BV_Data_An_Cour!$X:$X,"Oui",BV_Data_An_Cour!$U:$U,$B5) -> 2992808.7 | Q5: {=+INDEX('Réel 2025'!$A$2:$AO$500,MATCH($A5,'Réel 2025'!$A$2:$A$500,0),MATCH(Q$2,'Réel 2025'!$A$2:$AO$2,0))} -> 1932819
A6: =+B6&C6 -> Véhicules neufsAutos détail | B6: =+$K$1 -> Véhicules neufs | C6: Autos détail | D6: =+INDEX('Budget original'!$A$2:$AO$501,MATCH($A6,'Budget original'!$A$2:$A$501,0),MATCH(D$2,'Budget original'!$A$2:$AO$2,0)) -> 9 | E6: =IF(D6=0,0,F6/D6) -> 4701.1765 | F6: =+INDEX('Budget original'!$A$2:$AO$501,MATCH($A6,'Budget original'!$A$2:$A$501,0),MATCH(F$2,'Budget original'!$A$2:$AO$2,0)) -> 42310.588 | J6: =-SUMIFS(BV_Data_An_Cour!$O:$O,BV_Data_An_Cour!$U:$U,$B6,BV_Data_An_Cour!$V:$V,$C6,BV_Data_An_Cour!$W:$W,J$2) -> 10 | K6: =IF(J6=0,0,L6/J6) -> 6645.185 | L6: =-SUMIFS(BV_Data_An_Cour!$O:$O,BV_Data_An_Cour!$U:$U,$B6,BV_Data_An_Cour!$V:$V,$C6,BV_Data_An_Cour!$W:$W,L$2) -> 66451.85 | M6: =J6-D6 -> 1 | N6: =L6-F6 -> 24141.262 | O6: =+INDEX('Réel 2025'!$A$2:$AO$500,MATCH($A6,'Réel 2025'!$A$2:$A$500,0),MATCH(O$2,'Réel 2025'!$A$2:$AO$2,0)) -> 9 | P6: =IF(O6=0,0,Q6/O6) -> 5820.6267 | Q6: {=+INDEX('Réel 2025'!$A$2:$AO$500,MATCH($A6,'Réel 2025'!$A$2:$A$500,0),MATCH(Q$2,'Réel 2025'!$A$2:$AO$2,0))} -> 52385.64 | R6: =J6-O6 -> 1 | S6: =L6-Q6 -> 14066.21
A7: =+B7&C7 -> Véhicules neufsCamions détail | B7: =+$K$1 -> Véhicules neufs | C7: Camions détail | D7: =+INDEX('Budget original'!$A$2:$AO$501,MATCH($A7,'Budget original'!$A$2:$A$501,0),MATCH(D$2,'Budget original'!$A$2:$AO$2,0)) -> 14 | E7: =IF(D7=0,0,F7/D7) -> 3928.5 | F7: =+INDEX('Budget original'!$A$2:$AO$501,MATCH($A7,'Budget original'!$A$2:$A$501,0),MATCH(F$2,'Budget original'!$A$2:$AO$2,0)) -> 54999 | J7: =-SUMIFS(BV_Data_An_Cour!$O:$O,BV_Data_An_Cour!$U:$U,$B7,BV_Data_An_Cour!$V:$V,$C7,BV_Data_An_Cour!$W:$W,J$2) -> 12 | K7: =IF(J7=0,0,L7/J7) -> 4707.7525 | L7: =-SUMIFS(BV_Data_An_Cour!$O:$O,BV_Data_An_Cour!$U:$U,$B7,BV_Data_An_Cour!$V:$V,$C7,BV_Data_An_Cour!$W:$W,L$2) -> 56493.03 | M7: =J7-D7 -> -2 | N7: =L7-F7 -> 1494.03 | O7: {=+INDEX('Réel 2025'!$A$2:$AO$500,MATCH($A7,'Réel 2025'!$A$2:$A$500,0),MATCH(O$2,'Réel 2025'!$A$2:$AO$2,0))} -> 7 | P7: =IF(O7=0,0,Q7/O7) -> 3544.4671 | Q7: {=+INDEX('Réel 2025'!$A$2:$AO$500,MATCH($A7,'Réel 2025'!$A$2:$A$500,0),MATCH(Q$2,'Réel 2025'!$A$2:$AO$2,0))} -> 24811.27 | R7: =J7-O7 -> 5 | S7: =L7-Q7 -> 31681.76
A8: =+B8&C8 -> Véhicules neufsSprinter | B8: =+$K$1 -> Véhicules neufs | C8: Sprinter | D8: =+INDEX('Budget original'!$A$2:$AO$501,MATCH($A8,'Budget original'!$A$2:$A$501,0),MATCH(D$2,'Budget original'!$A$2:$AO$2,0)) -> 0 | E8: =IF(D8=0,0,F8/D8) -> 0 | F8: =+INDEX('Budget original'!$A$2:$AO$501,MATCH($A8,'Budget original'!$A$2:$A$501,0),MATCH(F$2,'Budget original'!$A$2:$AO$2,0)) -> 0 | J8: =-SUMIFS(BV_Data_An_Cour!$O:$O,BV_Data_An_Cour!$U:$U,$B8,BV_Data_An_Cour!$V:$V,$C8,BV_Data_An_Cour!$W:$W,J$2) -> 0 | K8: =IF(J8=0,0,L8/J8) -> 0 | L8: =-SUMIFS(BV_Data_An_Cour!$O:$O,BV_Data_An_Cour!$U:$U,$B8,BV_Data_An_Cour!$V:$V,$C8,BV_Data_An_Cour!$W:$W,L$2) -> 0 | M8: =J8-D8 -> 0 | N8: =L8-F8 -> 0 | O8: {=+INDEX('Réel 2025'!$A$2:$AO$500,MATCH($A8,'Réel 2025'!$A$2:$A$500,0),MATCH(O$2,'Réel 2025'!$A$2:$AO$2,0))} -> 0 | P8: =IF(O8=0,0,Q8/O8) -> 0 | Q8: {=+INDEX('Réel 2025'!$A$2:$AO$500,MATCH($A8,'Réel 2025'!$A$2:$A$500,0),MATCH(Q$2,'Réel 2025'!$A$2:$AO$2,0))} -> 0 | R8: =J8-O8 -> 0 | S8: =L8-Q8 -> 0
A9: =+B9&C9 -> Véhicules neufsMoto détail | B9: =+$K$1 -> Véhicules neufs | C9: Moto détail | D9: =+INDEX('Budget original'!$A$2:$AO$501,MATCH($A9,'Budget original'!$A$2:$A$501,0),MATCH(D$2,'Budget original'!$A$2:$AO$2,0)) -> 0 | E9: =IF(D9=0,0,F9/D9) -> 0 | F9: =+INDEX('Budget original'!$A$2:$AO$501,MATCH($A9,'Budget original'!$A$2:$A$501,0),MATCH(F$2,'Budget original'!$A$2:$AO$2,0)) -> 0 | J9: =-SUMIFS(BV_Data_An_Cour!$O:$O,BV_Data_An_Cour!$U:$U,$B9,BV_Data_An_Cour!$V:$V,$C9,BV_Data_An_Cour!$W:$W,J$2) -> 0 | K9: =IF(J9=0,0,L9/J9) -> 0 | L9: =-SUMIFS(BV_Data_An_Cour!$O:$O,BV_Data_An_Cour!$U:$U,$B9,BV_Data_An_Cour!$V:$V,$C9,BV_Data_An_Cour!$W:$W,L$2) -> 0 | M9: =J9-D9 -> 0 | N9: =L9-F9 -> 0 | O9: {=+INDEX('Réel 2025'!$A$2:$AO$500,MATCH($A9,'Réel 2025'!$A$2:$A$500,0),MATCH(O$2,'Réel 2025'!$A$2:$AO$2,0))} -> 0 | P9: =IF(O9=0,0,Q9/O9) -> 0 | Q9: {=+INDEX('Réel 2025'!$A$2:$AO$500,MATCH($A9,'Réel 2025'!$A$2:$A$500,0),MATCH(Q$2,'Réel 2025'!$A$2:$AO$2,0))} -> 0 | R9: =J9-O9 -> 0 | S9: =L9-Q9 -> 0
A10: =+B10&C10 -> Véhicules neufs[...] | B10: =+$K$1 -> Véhicules neufs | C10: [...] | D10: =+INDEX('Budget original'!$A$2:$AO$501,MATCH($A10,'Budget original'!$A$2:$A$501,0),MATCH(D$2,'Budget original'!$A$2:$AO$2,0)) -> 0 | E10: =IF(D10=0,0,F10/D10) -> 0 | F10: =+INDEX('Budget original'!$A$2:$AO$501,MATCH($A10,'Budget original'!$A$2:$A$501,0),MATCH(F$2,'Budget original'!$A$2:$AO$2,0)) -> 0 | J10: =-SUMIFS(BV_Data_An_Cour!$O:$O,BV_Data_An_Cour!$U:$U,$B10,BV_Data_An_Cour!$V:$V,$C10,BV_Data_An_Cour!$W:$W,J$2) -> 0 | K10: =IF(J10=0,0,L10/J10) -> 0 | L10: =-SUMIFS(BV_Data_An_Cour!$O:$O,BV_Data_An_Cour!$U:$U,$B10,BV_Data_An_Cour!$V:$V,$C10,BV_Data_An_Cour!$W:$W,L$2) -> 0 | M10: =J10-D10 -> 0 | N10: =L10-F10 -> 0 | O10: {=+INDEX('Réel 2025'!$A$2:$AO$500,MATCH($A10,'Réel 2025'!$A$2:$A$500,0),MATCH(O$2,'Réel 2025'!$A$2:$AO$2,0))} -> 0 | P10: =IF(O10=0,0,Q10/O10) -> 0 | Q10: {=+INDEX('Réel 2025'!$A$2:$AO$500,MATCH($A10,'Réel 2025'!$A$2:$A$500,0),MATCH(Q$2,'Réel 2025'!$A$2:$AO$2,0))} -> 0 | R10: =J10-O10 -> 0 | S10: =L10-Q10 -> 0
A11: =+B11&C11 -> Véhicules neufs[...] | B11: =+$K$1 -> Véhicules neufs | C11: [...] | D11: =+INDEX('Budget original'!$A$2:$AO$501,MATCH($A11,'Budget original'!$A$2:$A$501,0),MATCH(D$2,'Budget original'!$A$2:$AO$2,0)) -> 0 | E11: =IF(D11=0,0,F11/D11) -> 0 | F11: =+INDEX('Budget original'!$A$2:$AO$501,MATCH($A11,'Budget original'!$A$2:$A$501,0),MATCH(F$2,'Budget original'!$A$2:$AO$2,0)) -> 0 | J11: =-SUMIFS(BV_Data_An_Cour!$O:$O,BV_Data_An_Cour!$U:$U,$B11,BV_Data_An_Cour!$V:$V,$C11,BV_Data_An_Cour!$W:$W,J$2) -> 0 | K11: =IF(J11=0,0,L11/J11) -> 0 | L11: =-SUMIFS(BV_Data_An_Cour!$O:$O,BV_Data_An_Cour!$U:$U,$B11,BV_Data_An_Cour!$V:$V,$C11,BV_Data_An_Cour!$W:$W,L$2) -> 0 | M11: =J11-D11 -> 0 | N11: =L11-F11 -> 0 | O11: {=+INDEX('Réel 2025'!$A$2:$AO$500,MATCH($A11,'Réel 2025'!$A$2:$A$500,0),MATCH(O$2,'Réel 2025'!$A$2:$AO$2,0))} -> 0 | P11: =IF(O11=0,0,Q11/O11) -> 0 | Q11: {=+INDEX('Réel 2025'!$A$2:$AO$500,MATCH($A11,'Réel 2025'!$A$2:$A$500,0),MATCH(Q$2,'Réel 2025'!$A$2:$AO$2,0))} -> 0 | R11: =J11-O11 -> 0 | S11: =L11-Q11 -> 0
A12: =+B12&C12 -> Véhicules neufs[...] | B12: =+$K$1 -> Véhicules neufs | C12: [...] | D12: =+INDEX('Budget original'!$A$2:$AO$501,MATCH($A12,'Budget original'!$A$2:$A$501,0),MATCH(D$2,'Budget original'!$A$2:$AO$2,0)) -> 0 | E12: =IF(D12=0,0,F12/D12) -> 0 | F12: =+INDEX('Budget original'!$A$2:$AO$501,MATCH($A12,'Budget original'!$A$2:$A$501,0),MATCH(F$2,'Budget original'!$A$2:$AO$2,0)) -> 0 | J12: =-SUMIFS(BV_Data_An_Cour!$O:$O,BV_Data_An_Cour!$U:$U,$B12,BV_Data_An_Cour!$V:$V,$C12,BV_Data_An_Cour!$W:$W,J$2) -> 0 | K12: =IF(J12=0,0,L12/J12) -> 0 | L12: =-SUMIFS(BV_Data_An_Cour!$O:$O,BV_Data_An_Cour!$U:$U,$B12,BV_Data_An_Cour!$V:$V,$C12,BV_Data_An_Cour!$W:$W,L$2) -> 0 | M12: =J12-D12 -> 0 | N12: =L12-F12 -> 0 | O12: {=+INDEX('Réel 2025'!$A$2:$AO$500,MATCH($A12,'Réel 2025'!$A$2:$A$500,0),MATCH(O$2,'Réel 2025'!$A$2:$AO$2,0))} -> 0 | P12: =IF(O12=0,0,Q12/O12) -> 0 | Q12: {=+INDEX('Réel 2025'!$A$2:$AO$500,MATCH($A12,'Réel 2025'!$A$2:$A$500,0),MATCH(Q$2,'Réel 2025'!$A$2:$AO$2,0))} -> 0 | R12: =J12-O12 -> 0 | S12: =L12-Q12 -> 0
A13: =+B13&C13 -> Véhicules neufsTotal Neufs | B13: =+$K$1 -> Véhicules neufs | C13: Total Neufs | D13: =+SUM(D6:D12) -> 23 | E13: =IF(D13<=0,0,F13/D13) -> 4230.8517 | F13: =+SUM(F6:F12) -> 97309.588 | J13: =+SUM(J6:J12) -> 22 | K13: =IF(J13<=0,0,L13/J13) -> 5588.4036 | L13: =+SUM(L6:L12) -> 122944.88 | M13: =+SUM(M6:M12) -> -1 | N13: =+SUM(N6:N12) -> 25635.292 | O13: =+SUM(O6:O12) -> 16 | P13: =IF(O13<=0,0,Q13/O13) -> 4824.8069 | Q13: =+SUM(Q6:Q12) -> 77196.91 | R13: =+SUM(R6:R12) -> 6 | S13: =+SUM(S6:S12) -> 45747.97
A14: =+B14&C14 -> Véhicules neufs | B14: =+$K$1 -> Véhicules neufs | M14: =IF(D13=0,0,M13/D13) -> -0.043478261 | N14: =IF(F13=0,0,N13/F13) -> 0.26344055 | R14: =R13/O13 -> 0.375 | S14: =IF(Q13=0,0,(S13/Q13)) -> 0.592614
A15: =+B15&C15 -> Véhicules neufsEx-Démos et courtoisies | B15: =+$K$1 -> Véhicules neufs | C15: Ex-Démos et courtoisies | D15: =+INDEX('Budget original'!$A$2:$AO$501,MATCH($A15,'Budget original'!$A$2:$A$501,0),MATCH(D$2,'Budget original'!$A$2:$AO$2,0)) -> 3 | E15: =IF(D15=0,0,F15/D15) -> 1200 | F15: =+INDEX('Budget original'!$A$2:$AO$501,MATCH($A15,'Budget original'!$A$2:$A$501,0),MATCH(F$2,'Budget original'!$A$2:$AO$2,0)) -> 3600 | J15: =-SUMIFS(BV_Data_An_Cour!$O:$O,BV_Data_An_Cour!$U:$U,$B15,BV_Data_An_Cour!$V:$V,$C15,BV_Data_An_Cour!$W:$W,J$2) -> 2 | K15: =IF(J15=0,0,L15/J15) -> 39.025 | L15: =-SUMIFS(BV_Data_An_Cour!$O:$O,BV_Data_An_Cour!$U:$U,$B15,BV_Data_An_Cour!$V:$V,$C15,BV_Data_An_Cour!$W:$W,L$2) -> 78.05 | M15: =J15-D15 -> -1 | N15: =L15-F15 -> -3521.95 | O15: {=+INDEX('Réel 2025'!$A$2:$AO$500,MATCH($A15,'Réel 2025'!$A$2:$A$500,0),MATCH(O$2,'Réel 2025'!$A$2:$AO$2,0))} -> 4 | P15: =IF(O15=0,0,Q15/O15) -> 2445.1975 | Q15: {=+INDEX('Réel 2025'!$A$2:$AO$500,MATCH($A15,'Réel 2025'!$A$2:$A$500,0),MATCH(Q$2,'Réel 2025'!$A$2:$AO$2,0))} -> 9780.79 | R15: =J15-O15 -> -2 | S15: =L15-Q15 -> -9702.74
A16: =+B16&C16 -> Véhicules neufs | B16: =+$K$1 -> Véhicules neufs
A17: =+B17&C17 -> Véhicules neufsFlottes | B17: =+$K$1 -> Véhicules neufs | C17: Flottes | D17: =+INDEX('Budget original'!$A$2:$AO$501,MATCH($A17,'Budget original'!$A$2:$A$501,0),MATCH(D$2,'Budget original'!$A$2:$AO$2,0)) -> 2 | E17: =IF(D17=0,0,F17/D17) -> 750 | F17: =+INDEX('Budget original'!$A$2:$AO$501,MATCH($A17,'Budget original'!$A$2:$A$501,0),MATCH(F$2,'Budget original'!$A$2:$AO$2,0)) -> 1500 | J17: =-SUMIFS(BV_Data_An_Cour!$O:$O,BV_Data_An_Cour!$U:$U,$B17,BV_Data_An_Cour!$V:$V,$C17,BV_Data_An_Cour!$W:$W,J$2) -> 6 | K17: =IF(J17=0,0,L17/J17) -> 0 | L17: =-SUMIFS(BV_Data_An_Cour!$O:$O,BV_Data_An_Cour!$U:$U,$B17,BV_Data_An_Cour!$V:$V,$C17,BV_Data_An_Cour!$W:$W,L$2) -> 0 | M17: =J17-D17 -> 4 | N17: =L17-F17 -> -1500 | O17: {=+INDEX('Réel 2025'!$A$2:$AO$500,MATCH($A17,'Réel 2025'!$A$2:$A$500,0),MATCH(O$2,'Réel 2025'!$A$2:$AO$2,0))} -> 0 | P17: =IF(O17=0,0,Q17/O17) -> 0 | Q17: {=+INDEX('Réel 2025'!$A$2:$AO$500,MATCH($A17,'Réel 2025'!$A$2:$A$500,0),MATCH(Q$2,'Réel 2025'!$A$2:$AO$2,0))} -> 0 | R17: =J17-O17 -> 6 | S17: =L17-Q17 -> 0
A18: =+B18&C18 -> Véhicules neufs | B18: =+$K$1 -> Véhicules neufs
B19: =+$K$1 -> Véhicules neufs
A20: =+B20&C20 -> Véhicules neufs | B20: =+$K$1 -> Véhicules neufs
A21: =+B21&C21 -> Véhicules neufsRev. Finances | B21: =+$K$1 -> Véhicules neufs | C21: Rev. Finances | E21: =IF(D13=0,0,F21/(D13+D15)) -> 7 | F21: =+INDEX('Budget original'!$A$2:$AO$501,MATCH($A21,'Budget original'!$A$2:$A$501,0),MATCH(F$2,'Budget original'!$A$2:$AO$2,0)) -> 182 | K21: =IF(J13=0,0,L21/(J13+J15)) -> 0 | L21: =-SUMIFS(BV_Data_An_Cour!$O:$O,BV_Data_An_Cour!$U:$U,$B21,BV_Data_An_Cour!$V:$V,$C21,BV_Data_An_Cour!$W:$W,L$2) -> 0 | N21: =L21-F21 -> -182 | P21: =IF(O13=0,0,Q21/(O13+O15)) -> 0 | Q21: {=+INDEX('Réel 2025'!$A$2:$AO$500,MATCH($A21,'Réel 2025'!$A$2:$A$500,0),MATCH(Q$2,'Réel 2025'!$A$2:$AO$2,0))} -> 0 | R21: =O21-K21 -> 0 | S21: =L21-Q21 -> 0
A22: =+B22&C22 -> Véhicules neufsRev. Protections | B22: =+$K$1 -> Véhicules neufs | C22: Rev. Protections | E22: =IF(D13=0,0,F22/(D13+D15)) -> 1150 | F22: =+INDEX('Budget original'!$A$2:$AO$501,MATCH($A22,'Budget original'!$A$2:$A$501,0),MATCH(F$2,'Budget original'!$A$2:$AO$2,0)) -> 29900 | K22: =IF(J13=0,0,L22/(J13+J15)) -> 489.09583 | L22: =-SUMIFS(BV_Data_An_Cour!$O:$O,BV_Data_An_Cour!$U:$U,$B22,BV_Data_An_Cour!$V:$V,$C22,BV_Data_An_Cour!$W:$W,L$2) -> 11738.3 | N22: =L22-F22 -> -18161.7 | P22: =IF(O13=0,0,Q22/(O13+O15)) -> 1336.1695 | Q22: {=+INDEX('Réel 2025'!$A$2:$AO$500,MATCH($A22,'Réel 2025'!$A$2:$A$500,0),MATCH(Q$2,'Réel 2025'!$A$2:$AO$2,0))} -> 26723.39 | R22: =O22-K22 -> -489.09583 | S22: =L22-Q22 -> -14985.09
A23: =+B23&C23 -> Véhicules neufsRev. Autres | B23: =+$K$1 -> Véhicules neufs | C23: Rev. Autres | E23: =IF(D13=0,0,F23/(D13+D15)) -> 443 | F23: =+INDEX('Budget original'!$A$2:$AO$501,MATCH($A23,'Budget original'!$A$2:$A$501,0),MATCH(F$2,'Budget original'!$A$2:$AO$2,0)) -> 11518 | K23: =IF(J13=0,0,L23/(J13+J15)) -> 445.25708 | L23: =-SUMIFS(BV_Data_An_Cour!$O:$O,BV_Data_An_Cour!$U:$U,$B23,BV_Data_An_Cour!$V:$V,$C23,BV_Data_An_Cour!$W:$W,L$2) -> 10686.17 | N23: =L23-F23 -> -831.83 | P23: =IF(O13=0,0,Q23/(O13+O15)) -> 902.6705 | Q23: {=+INDEX('Réel 2025'!$A$2:$AO$500,MATCH($A23,'Réel 2025'!$A$2:$A$500,0),MATCH(Q$2,'Réel 2025'!$A$2:$AO$2,0))} -> 18053.41 | R23: =O23-K23 -> -445.25708 | S23: =L23-Q23 -> -7367.24
A24: =+B24&C24 -> Véhicules neufsTotal F&I | B24: =+$K$1 -> Véhicules neufs | C24: Total F&I | D24: =+D15+D13 -> 26 | E24: =IF(D24<=0,0,F24/D24) -> 1600 | F24: =F21+F22+F23 -> 41600 | J24: =+J15+J13 -> 24 | K24: =IF(J24<=0,0,L24/J24) -> 934.35292 | L24: =L21+L22+L23 -> 22424.47 | M24: =J24-D24 -> -2 | N24: =L24-F24 -> -19175.53 | O24: =+O15+O13 -> 20 | P24: =IF(O24<=0,0,Q24/O24) -> 2238.84 | Q24: =Q21+Q22+Q23 -> 44776.8 | S24: =L24-Q24 -> -22352.33
A25: =+B25&C25 -> Véhicules neufs | B25: =+$K$1 -> Véhicules neufs | N25: =IF(N24=0,0,N24/F24) -> -0.46095024 | S25: =IF(Q24=0,0,(S24/Q24)) -> -0.49919445
A26: =+B26&C26 -> Véhicules neufs | B26: =+$K$1 -> Véhicules neufs
A27: =+B27&C27 -> Véhicules neufsTotal Dépt. Neufs | B27: =+$K$1 -> Véhicules neufs | C27: Total Dépt. Neufs | D27: =+D13+D15+D17 -> 28 | E27: =IF(D27<=0,0,F27/D27) -> 5143.1996 | F27: =F13+F17+F24+F15 -> 144009.59 | J27: =+J13+J15+J17 -> 30 | K27: =IF(J27<=0,0,L27/J27) -> 4848.2467 | L27: =L13+L17+L24+L15 -> 145447.4 | M27: =J27-D27 -> 2 | N27: =L27-F27 -> 1437.8118 | O27: =+O13+O15+O17 -> 20 | P27: =IF(O27<=0,0,Q27/O27) -> 6587.725 | Q27: =Q13+Q17+Q24+Q15 -> 131754.5 | R27: =J27-O27 -> 10 | S27: =L27-Q27 -> 13692.9
A28: =+B28&C28 -> Véhicules neufs | B28: =+$K$1 -> Véhicules neufs | M28: =M27/D27 -> 0.071428571 | N28: =N27/F27 -> 0.0099841391 | R28: =R27/O27 -> 0.5 | S28: =IF(Q27=0,0,S27/Q27) -> 0.10392738
A29: =+B29&C29 -> Véhicules neufs | B29: =+$K$1 -> Véhicules neufs
A30: =+B30&C30 -> Véhicules neufsDEPENSES | B30: =+$K$1 -> Véhicules neufs | C30: DEPENSES
A31: =+B31&C31 -> Véhicules neufsComm. vendeurs | B31: =+$K$1 -> Véhicules neufs | C31: Comm. vendeurs | D31: =F31/(F13+F15) -> 0.28393389 | E31: =F31/D$24 -> 1101.9866 | F31: =+INDEX('Budget original'!$A$2:$AO$501,MATCH($A31,'Budget original'!$A$2:$A$501,0),MATCH(F$2,'Budget original'!$A$2:$AO$2,0)) -> 28651.652 | J31: =L31/(L13+L15) -> 0.28455614 | K31: =IF(L31=0,0,L31/J$24) -> 1458.6221 | L31: =SUMIFS(BV_Data_An_Cour!$O:$O,BV_Data_An_Cour!$U:$U,$B31,BV_Data_An_Cour!$V:$V,$C31,BV_Data_An_Cour!$W:$W,L$2) -> 35006.93 | N31: =L31-F31 -> 6355.2782 | O31: =Q31/(Q13+Q15+Q17) -> 0.25746726 | P31: =Q31/O$24 -> 1119.6955 | Q31: {=+INDEX('Réel 2025'!$A$2:$AO$500,MATCH($A31,'Réel 2025'!$A$2:$A$500,0),MATCH(Q$2,'Réel 2025'!$A$2:$AO$2,0))} -> 22393.91 | S31: =L31-Q31 -> 12613.02
A32: =+B32&C32 -> Véhicules neufsComm. F&I | B32: =+$K$1 -> Véhicules neufs | C32: Comm. F&I | D32: =F32/F24 -> 0.305 | E32: =F32/D$24 -> 488 | F32: =+INDEX('Budget original'!$A$2:$AO$501,MATCH($A32,'Budget original'!$A$2:$A$501,0),MATCH(F$2,'Budget original'!$A$2:$AO$2,0)) -> 12688 | J32: =L32/L24 -> 0.22188395 | K32: =IF(L32=0,0,L32/J$24) -> 207.31792 | L32: =SUMIFS(BV_Data_An_Cour!$O:$O,BV_Data_An_Cour!$U:$U,$B32,BV_Data_An_Cour!$V:$V,$C32,BV_Data_An_Cour!$W:$W,L$2) -> 4975.63 | N32: =L32-F32 -> -7712.37 | O32: =Q32/Q24 -> 0.34309151 | P32: =Q32/O$24 -> 768.127 | Q32: {=+INDEX('Réel 2025'!$A$2:$AO$500,MATCH($A32,'Réel 2025'!$A$2:$A$500,0),MATCH(Q$2,'Réel 2025'!$A$2:$AO$2,0))} -> 15362.54 | S32: =L32-Q32 -> -10386.91
A33: =+B33&C33 -> Véhicules neufsFrais de livraison | B33: =+$K$1 -> Véhicules neufs | C33: Frais de livraison | E33: =F33/D$24 -> 120 | F33: =+INDEX('Budget original'!$A$2:$AO$501,MATCH($A33,'Budget original'!$A$2:$A$501,0),MATCH(F$2,'Budget original'!$A$2:$AO$2,0)) -> 3120 | K33: =IF(L33=0,0,L33/J$24) -> 276.80167 | L33: =SUMIFS(BV_Data_An_Cour!$O:$O,BV_Data_An_Cour!$U:$U,$B33,BV_Data_An_Cour!$V:$V,$C33,BV_Data_An_Cour!$W:$W,L$2) -> 6643.24 | N33: =L33-F33 -> 3523.24 | P33: =Q33/O$24 -> 207.3525 | Q33: {=+INDEX('Réel 2025'!$A$2:$AO$500,MATCH($A33,'Réel 2025'!$A$2:$A$500,0),MATCH(Q$2,'Réel 2025'!$A$2:$AO$2,0))} -> 4147.05 | S33: =L33-Q33 -> 2496.19 | V33: Essences + transport
A34: =+B34&C34 -> Véhicules neufsService gratuit 1 | B34: =+$K$1 -> Véhicules neufs | C34: Service gratuit 1 | E34: =F34/D$24 -> 35 | F34: =+INDEX('Budget original'!$A$2:$AO$501,MATCH($A34,'Budget original'!$A$2:$A$501,0),MATCH(F$2,'Budget original'!$A$2:$AO$2,0)) -> 910 | K34: =IF(L34=0,0,L34/J$24) -> 95.290833 | L34: =SUMIFS(BV_Data_An_Cour!$O:$O,BV_Data_An_Cour!$U:$U,$B34,BV_Data_An_Cour!$V:$V,$C34,BV_Data_An_Cour!$W:$W,L$2) -> 2286.98 | N34: =L34-F34 -> 1376.98 | P34: =Q34/O$24 -> 0 | Q34: {=+INDEX('Réel 2025'!$A$2:$AO$500,MATCH($A34,'Réel 2025'!$A$2:$A$500,0),MATCH(Q$2,'Réel 2025'!$A$2:$AO$2,0))} -> 0 | S34: =L34-Q34 -> 2286.98 | V34: 1.4K Freins ancien démo Yvon vendu janv 2026
A35: =+B35&C35 -> Véhicules neufsEntretien stock | B35: =+$K$1 -> Véhicules neufs | C35: Entretien stock | E35: =F35/D$24 -> 98.192308 | F35: =+INDEX('Budget original'!$A$2:$AO$501,MATCH($A35,'Budget original'!$A$2:$A$501,0),MATCH(F$2,'Budget original'!$A$2:$AO$2,0)) -> 2553 | K35: =IF(L35=0,0,L35/J$24) -> 210.72917 | L35: =SUMIFS(BV_Data_An_Cour!$O:$O,BV_Data_An_Cour!$U:$U,$B35,BV_Data_An_Cour!$V:$V,$C35,BV_Data_An_Cour!$W:$W,L$2) -> 5057.5 | N35: =L35-F35 -> 2504.5 | P35: =Q35/O$24 -> 103.6725 | Q35: {=+INDEX('Réel 2025'!$A$2:$AO$500,MATCH($A35,'Réel 2025'!$A$2:$A$500,0),MATCH(Q$2,'Réel 2025'!$A$2:$AO$2,0))} -> 2073.45 | S35: =L35-Q35 -> 2984.05 | V35: 2k Lavavage ligne essaie
A36: =+B36&C36 -> Véhicules neufsPublicité 1 | B36: =+$K$1 -> Véhicules neufs | C36: Publicité 1 | E36: =F36/D$24 -> 234.88788 | F36: =+INDEX('Budget original'!$A$2:$AO$501,MATCH($A36,'Budget original'!$A$2:$A$501,0),MATCH(F$2,'Budget original'!$A$2:$AO$2,0)) -> 6107.0848 | K36: =IF(L36=0,0,L36/J$24) -> 230.78417 | L36: =SUMIFS(BV_Data_An_Cour!$O:$O,BV_Data_An_Cour!$U:$U,$B36,BV_Data_An_Cour!$V:$V,$C36,BV_Data_An_Cour!$W:$W,L$2) -> 5538.82 | N36: =L36-F36 -> -568.26485 | P36: =Q36/O$24 -> 508.9305 | Q36: {=+INDEX('Réel 2025'!$A$2:$AO$500,MATCH($A36,'Réel 2025'!$A$2:$A$500,0),MATCH(Q$2,'Réel 2025'!$A$2:$AO$2,0))} -> 10178.61 | S36: =L36-Q36 -> -4639.79
A37: =+B37&C37 -> Véhicules neufsIntérêt de gros | B37: =+$K$1 -> Véhicules neufs | C37: Intérêt de gros | E37: =F37/D$24 -> 809.52174 | F37: =+INDEX('Budget original'!$A$2:$AO$501,MATCH($A37,'Budget original'!$A$2:$A$501,0),MATCH(F$2,'Budget original'!$A$2:$AO$2,0)) -> 21047.565 | K37: =IF(L37=0,0,L37/J$24) -> 881.08 | L37: =SUMIFS(BV_Data_An_Cour!$O:$O,BV_Data_An_Cour!$U:$U,$B37,BV_Data_An_Cour!$V:$V,$C37,BV_Data_An_Cour!$W:$W,L$2) -> 21145.92 | N37: =L37-F37 -> 98.354754 | P37: =Q37/O$24 -> 1163.8995 | Q37: {=+INDEX('Réel 2025'!$A$2:$AO$500,MATCH($A37,'Réel 2025'!$A$2:$A$500,0),MATCH(Q$2,'Réel 2025'!$A$2:$AO$2,0))} -> 23277.99 | S37: =L37-Q37 -> -2132.07 | V37: 21146
A38: =+B38&C38 -> Véhicules neufs[...] | B38: =+$K$1 -> Véhicules neufs | C38: [...] | E38: =F38/D$24 -> 0 | F38: =+INDEX('Budget original'!$A$2:$AO$501,MATCH($A38,'Budget original'!$A$2:$A$501,0),MATCH(F$2,'Budget original'!$A$2:$AO$2,0)) -> 0 | K38: =IF(L38=0,0,L38/J$24) -> 0 | L38: =SUMIFS(BV_Data_An_Cour!$O:$O,BV_Data_An_Cour!$U:$U,$B38,BV_Data_An_Cour!$V:$V,$C38,BV_Data_An_Cour!$W:$W,L$2) -> 0 | N38: =L38-F38 -> 0 | P38: =Q38/O$24 -> 0 | Q38: {=+INDEX('Réel 2025'!$A$2:$AO$500,MATCH($A38,'Réel 2025'!$A$2:$A$500,0),MATCH(Q$2,'Réel 2025'!$A$2:$AO$2,0))} -> 0 | S38: =L38-Q38 -> 0
A39: =+B39&C39 -> Véhicules neufs[...] | B39: =+$K$1 -> Véhicules neufs | C39: [...] | E39: =F39/D$24 -> 0 | F39: =+INDEX('Budget original'!$A$2:$AO$501,MATCH($A39,'Budget original'!$A$2:$A$501,0),MATCH(F$2,'Budget original'!$A$2:$AO$2,0)) -> 0 | K39: =IF(L39=0,0,L39/J$24) -> 0 | L39: =SUMIFS(BV_Data_An_Cour!$O:$O,BV_Data_An_Cour!$U:$U,$B39,BV_Data_An_Cour!$V:$V,$C39,BV_Data_An_Cour!$W:$W,L$2) -> 0 | N39: =L39-F39 -> 0 | P39: =Q39/O$24 -> 0 | Q39: {=+INDEX('Réel 2025'!$A$2:$AO$500,MATCH($A39,'Réel 2025'!$A$2:$A$500,0),MATCH(Q$2,'Réel 2025'!$A$2:$AO$2,0))} -> 0 | S39: =L39-Q39 -> 0
A40: =+B40&C40 -> Véhicules neufs[...] | B40: =+$K$1 -> Véhicules neufs | C40: [...] | E40: =F40/D$24 -> 0 | F40: =+INDEX('Budget original'!$A$2:$AO$501,MATCH($A40,'Budget original'!$A$2:$A$501,0),MATCH(F$2,'Budget original'!$A$2:$AO$2,0)) -> 0 | K40: =IF(L40=0,0,L40/J$24) -> 0 | L40: =SUMIFS(BV_Data_An_Cour!$O:$O,BV_Data_An_Cour!$U:$U,$B40,BV_Data_An_Cour!$V:$V,$C40,BV_Data_An_Cour!$W:$W,L$2) -> 0 | N40: =L40-F40 -> 0 | P40: =Q40/O$24 -> 0 | Q40: {=+INDEX('Réel 2025'!$A$2:$AO$500,MATCH($A40,'Réel 2025'!$A$2:$A$500,0),MATCH(Q$2,'Réel 2025'!$A$2:$AO$2,0))} -> 0 | S40: =L40-Q40 -> 0
A41: =+B41&C41 -> Véhicules neufsTOTAL VARIABLES | B41: =+$K$1 -> Véhicules neufs | C41: TOTAL VARIABLES | D41: % brut | E41: =F41/F$27 -> 0.52133544 | F41: =SUM(F31:F40) -> 75077.302 | J41: % brut | K41: =L41/L$27 -> 0.5545305 | L41: =SUM(L31:L40) -> 80655.02 | N41: =L41-F41 -> 5577.7181 | O41: % brut | P41: =Q41/Q$27 -> 0.58771086 | Q41: =SUM(Q31:Q40) -> 77433.55 | S41: =L41-Q41 -> 3221.47
A42: =+B42&C42 -> Véhicules neufsSalaires cadres | B42: =+$K$1 -> Véhicules neufs | C42: Salaires cadres | F42: =+INDEX('Budget original'!$A$2:$AO$501,MATCH($A42,'Budget original'!$A$2:$A$501,0),MATCH(F$2,'Budget original'!$A$2:$AO$2,0)) -> 12465.762 | L42: =SUMIFS(BV_Data_An_Cour!$O:$O,BV_Data_An_Cour!$U:$U,$B42,BV_Data_An_Cour!$V:$V,$C42,BV_Data_An_Cour!$W:$W,L$2) -> 9762.51 | N42: =L42-F42 -> -2703.2521 | Q42: {=+INDEX('Réel 2025'!$A$2:$AO$500,MATCH($A42,'Réel 2025'!$A$2:$A$500,0),MATCH(Q$2,'Réel 2025'!$A$2:$AO$2,0))} -> 12424.49 | S42: =L42-Q42 -> -2661.98
A43: =+B43&C43 -> Véhicules neufsSalaires commis | B43: =+$K$1 -> Véhicules neufs | C43: Salaires commis | F43: =+INDEX('Budget original'!$A$2:$AO$501,MATCH($A43,'Budget original'!$A$2:$A$501,0),MATCH(F$2,'Budget original'!$A$2:$AO$2,0)) -> 5131.0855 | L43: =SUMIFS(BV_Data_An_Cour!$O:$O,BV_Data_An_Cour!$U:$U,$B43,BV_Data_An_Cour!$V:$V,$C43,BV_Data_An_Cour!$W:$W,L$2) -> 4255.62 | N43: =L43-F43 -> -875.46546 | Q43: {=+INDEX('Réel 2025'!$A$2:$AO$500,MATCH($A43,'Réel 2025'!$A$2:$A$500,0),MATCH(Q$2,'Réel 2025'!$A$2:$AO$2,0))} -> 8970.87 | S43: =L43-Q43 -> -4715.25
A44: =+B44&C44 -> Véhicules neufsSalaires autres | B44: =+$K$1 -> Véhicules neufs | C44: Salaires autres | F44: =+INDEX('Budget original'!$A$2:$AO$501,MATCH($A44,'Budget original'!$A$2:$A$501,0),MATCH(F$2,'Budget original'!$A$2:$AO$2,0)) -> 0 | L44: =SUMIFS(BV_Data_An_Cour!$O:$O,BV_Data_An_Cour!$U:$U,$B44,BV_Data_An_Cour!$V:$V,$C44,BV_Data_An_Cour!$W:$W,L$2) -> 90 | N44: =L44-F44 -> 90 | Q44: {=+INDEX('Réel 2025'!$A$2:$AO$500,MATCH($A44,'Réel 2025'!$A$2:$A$500,0),MATCH(Q$2,'Réel 2025'!$A$2:$AO$2,0))} -> 342 | S44: =L44-Q44 -> -252 | V44: Francis Pellerin - renouvellement Volks
A45: =+B45&C45 -> Véhicules neufsSalaires spécialistes | B45: =+$K$1 -> Véhicules neufs | C45: Salaires spécialistes | F45: =+INDEX('Budget original'!$A$2:$AO$501,MATCH($A45,'Budget original'!$A$2:$A$501,0),MATCH(F$2,'Budget original'!$A$2:$AO$2,0)) -> 0 | L45: =SUMIFS(BV_Data_An_Cour!$O:$O,BV_Data_An_Cour!$U:$U,$B45,BV_Data_An_Cour!$V:$V,$C45,BV_Data_An_Cour!$W:$W,L$2) -> 0 | N45: =L45-F45 -> 0 | Q45: {=+INDEX('Réel 2025'!$A$2:$AO$500,MATCH($A45,'Réel 2025'!$A$2:$A$500,0),MATCH(Q$2,'Réel 2025'!$A$2:$AO$2,0))} -> 0 | S45: =L45-Q45 -> 0
A46: =+B46&C46 -> Véhicules neufs[...] | B46: =+$K$1 -> Véhicules neufs | C46: [...] | F46: =+INDEX('Budget original'!$A$2:$AO$501,MATCH($A46,'Budget original'!$A$2:$A$501,0),MATCH(F$2,'Budget original'!$A$2:$AO$2,0)) -> 0 | L46: =SUMIFS(BV_Data_An_Cour!$O:$O,BV_Data_An_Cour!$U:$U,$B46,BV_Data_An_Cour!$V:$V,$C46,BV_Data_An_Cour!$W:$W,L$2) -> 0 | N46: =L46-F46 -> 0 | Q46: {=+INDEX('Réel 2025'!$A$2:$AO$500,MATCH($A46,'Réel 2025'!$A$2:$A$500,0),MATCH(Q$2,'Réel 2025'!$A$2:$AO$2,0))} -> 0 | S46: =L46-Q46 -> 0
A47: =+B47&C47 -> Véhicules neufs[...] | B47: =+$K$1 -> Véhicules neufs | C47: [...] | F47: =+INDEX('Budget original'!$A$2:$AO$501,MATCH($A47,'Budget original'!$A$2:$A$501,0),MATCH(F$2,'Budget original'!$A$2:$AO$2,0)) -> 0 | L47: =SUMIFS(BV_Data_An_Cour!$O:$O,BV_Data_An_Cour!$U:$U,$B47,BV_Data_An_Cour!$V:$V,$C47,BV_Data_An_Cour!$W:$W,L$2) -> 0 | N47: =L47-F47 -> 0 | Q47: {=+INDEX('Réel 2025'!$A$2:$AO$500,MATCH($A47,'Réel 2025'!$A$2:$A$500,0),MATCH(Q$2,'Réel 2025'!$A$2:$AO$2,0))} -> 0 | S47: =L47-Q47 -> 0
A48: =+B48&C48 -> Véhicules neufs[...] | B48: =+$K$1 -> Véhicules neufs | C48: [...] | F48: =+INDEX('Budget original'!$A$2:$AO$501,MATCH($A48,'Budget original'!$A$2:$A$501,0),MATCH(F$2,'Budget original'!$A$2:$AO$2,0)) -> 0 | L48: =SUMIFS(BV_Data_An_Cour!$O:$O,BV_Data_An_Cour!$U:$U,$B48,BV_Data_An_Cour!$V:$V,$C48,BV_Data_An_Cour!$W:$W,L$2) -> 0 | N48: =L48-F48 -> 0 | Q48: {=+INDEX('Réel 2025'!$A$2:$AO$500,MATCH($A48,'Réel 2025'!$A$2:$A$500,0),MATCH(Q$2,'Réel 2025'!$A$2:$AO$2,0))} -> 0 | S48: =L48-Q48 -> 0
A49: =+B49&C49 -> Véhicules neufsSalaires en absences | B49: =+$K$1 -> Véhicules neufs | C49: Salaires en absences | F49: =+INDEX('Budget original'!$A$2:$AO$501,MATCH($A49,'Budget original'!$A$2:$A$501,0),MATCH(F$2,'Budget original'!$A$2:$AO$2,0)) -> 8711.2105 | L49: =SUMIFS(BV_Data_An_Cour!$O:$O,BV_Data_An_Cour!$U:$U,$B49,BV_Data_An_Cour!$V:$V,$C49,BV_Data_An_Cour!$W:$W,L$2) -> 8083.96 | N49: =L49-F49 -> -627.25053 | Q49: {=+INDEX('Réel 2025'!$A$2:$AO$500,MATCH($A49,'Réel 2025'!$A$2:$A$500,0),MATCH(Q$2,'Réel 2025'!$A$2:$AO$2,0))} -> 9776.36 | S49: =L49-Q49 -> -1692.4
A50: =+B50&C50 -> Véhicules neufsDéduction à la source | B50: =+$K$1 -> Véhicules neufs | C50: Déduction à la source | F50: =+INDEX('Budget original'!$A$2:$AO$501,MATCH($A50,'Budget original'!$A$2:$A$501,0),MATCH(F$2,'Budget original'!$A$2:$AO$2,0)) -> 8869.9791 | L50: =SUMIFS(BV_Data_An_Cour!$O:$O,BV_Data_An_Cour!$U:$U,$B50,BV_Data_An_Cour!$V:$V,$C50,BV_Data_An_Cour!$W:$W,L$2) -> 9540.19 | N50: =L50-F50 -> 670.21086 | Q50: {=+INDEX('Réel 2025'!$A$2:$AO$500,MATCH($A50,'Réel 2025'!$A$2:$A$500,0),MATCH(Q$2,'Réel 2025'!$A$2:$AO$2,0))} -> 11933.83 | S50: =L50-Q50 -> -2393.64
A51: =+B51&C51 -> Véhicules neufsBénéfices marginaux | B51: =+$K$1 -> Véhicules neufs | C51: Bénéfices marginaux | F51: =+INDEX('Budget original'!$A$2:$AO$501,MATCH($A51,'Budget original'!$A$2:$A$501,0),MATCH(F$2,'Budget original'!$A$2:$AO$2,0)) -> 5749.0606 | L51: =SUMIFS(BV_Data_An_Cour!$O:$O,BV_Data_An_Cour!$U:$U,$B51,BV_Data_An_Cour!$V:$V,$C51,BV_Data_An_Cour!$W:$W,L$2) -> 4627.74 | N51: =L51-F51 -> -1121.3206 | Q51: {=+INDEX('Réel 2025'!$A$2:$AO$500,MATCH($A51,'Réel 2025'!$A$2:$A$500,0),MATCH(Q$2,'Réel 2025'!$A$2:$AO$2,0))} -> 4599.38 | S51: =L51-Q51 -> 28.36
A52: =+B52&C52 -> Véhicules neufsCsst | B52: =+$K$1 -> Véhicules neufs | C52: Csst | F52: =+INDEX('Budget original'!$A$2:$AO$501,MATCH($A52,'Budget original'!$A$2:$A$501,0),MATCH(F$2,'Budget original'!$A$2:$AO$2,0)) -> 1609.737 | L52: =SUMIFS(BV_Data_An_Cour!$O:$O,BV_Data_An_Cour!$U:$U,$B52,BV_Data_An_Cour!$V:$V,$C52,BV_Data_An_Cour!$W:$W,L$2) -> 1507.88 | N52: =L52-F52 -> -101.85696 | Q52: {=+INDEX('Réel 2025'!$A$2:$AO$500,MATCH($A52,'Réel 2025'!$A$2:$A$500,0),MATCH(Q$2,'Réel 2025'!$A$2:$AO$2,0))} -> 3165.52 | S52: =L52-Q52 -> -1657.64
A53: =+B53&C53 -> Véhicules neufs[...] | B53: =+$K$1 -> Véhicules neufs | C53: [...] | D53: =VLOOKUP(C53,$B$2:$B$46,1,FALSE) -> #N/A | F53: =+INDEX('Budget original'!$A$2:$AO$501,MATCH($A53,'Budget original'!$A$2:$A$501,0),MATCH(F$2,'Budget original'!$A$2:$AO$2,0)) -> 0 | L53: =SUMIFS(BV_Data_An_Cour!$O:$O,BV_Data_An_Cour!$U:$U,$B53,BV_Data_An_Cour!$V:$V,$C53,BV_Data_An_Cour!$W:$W,L$2) -> 0 | N53: =L53-F53 -> 0 | Q53: {=+INDEX('Réel 2025'!$A$2:$AO$500,MATCH($A53,'Réel 2025'!$A$2:$A$500,0),MATCH(Q$2,'Réel 2025'!$A$2:$AO$2,0))} -> 0 | S53: =L53-Q53 -> 0
A54: =+B54&C54 -> Véhicules neufsTOTAL PERSONNEL | B54: =+$K$1 -> Véhicules neufs | C54: TOTAL PERSONNEL | D54: % brut | E54: =F54/F$27 -> 0.29537502 | F54: =+SUM(F42:F53) -> 42536.835 | J54: % brut | K54: =L54/L$27 -> 0.2603546 | L54: =+SUM(L42:L53) -> 37867.9 | N54: =+SUM(N42:N53) -> -4668.9348 | O54: % brut | P54: =Q54/Q$27 -> 0.38869602 | Q54: =+SUM(Q42:Q53) -> 51212.45 | S54: =+SUM(S42:S53) -> -13344.55
A55: =+B55&C55 -> Véhicules neufsPublicité 2 | B55: =+$K$1 -> Véhicules neufs | C55: Publicité 2 | F55: =+INDEX('Budget original'!$A$2:$AO$501,MATCH($A55,'Budget original'!$A$2:$A$501,0),MATCH(F$2,'Budget original'!$A$2:$AO$2,0)) -> 0 | L55: =SUMIFS(BV_Data_An_Cour!$O:$O,BV_Data_An_Cour!$U:$U,$B55,BV_Data_An_Cour!$V:$V,$C55,BV_Data_An_Cour!$W:$W,L$2) -> 0 | N55: =L55-F55 -> 0 | Q55: {=+INDEX('Réel 2025'!$A$2:$AO$500,MATCH($A55,'Réel 2025'!$A$2:$A$500,0),MATCH(Q$2,'Réel 2025'!$A$2:$AO$2,0))} -> 0 | S55: =L55-Q55 -> 0
A56: =+B56&C56 -> Véhicules neufsService gratuit 2 | B56: =+$K$1 -> Véhicules neufs | C56: Service gratuit 2 | F56: =+INDEX('Budget original'!$A$2:$AO$501,MATCH($A56,'Budget original'!$A$2:$A$501,0),MATCH(F$2,'Budget original'!$A$2:$AO$2,0)) -> 0 | L56: =SUMIFS(BV_Data_An_Cour!$O:$O,BV_Data_An_Cour!$U:$U,$B56,BV_Data_An_Cour!$V:$V,$C56,BV_Data_An_Cour!$W:$W,L$2) -> 0 | N56: =L56-F56 -> 0 | Q56: {=+INDEX('Réel 2025'!$A$2:$AO$500,MATCH($A56,'Réel 2025'!$A$2:$A$500,0),MATCH(Q$2,'Réel 2025'!$A$2:$AO$2,0))} -> 0 | S56: =L56-Q56 -> 0
A57: =+B57&C57 -> Véhicules neufsFrais véhicules de cie | B57: =+$K$1 -> Véhicules neufs | C57: Frais véhicules de cie | F57: =+INDEX('Budget original'!$A$2:$AO$501,MATCH($A57,'Budget original'!$A$2:$A$501,0),MATCH(F$2,'Budget original'!$A$2:$AO$2,0)) -> 2036.5 | L57: =SUMIFS(BV_Data_An_Cour!$O:$O,BV_Data_An_Cour!$U:$U,$B57,BV_Data_An_Cour!$V:$V,$C57,BV_Data_An_Cour!$W:$W,L$2) -> 1284.45 | N57: =L57-F57 -> -752.05 | Q57: {=+INDEX('Réel 2025'!$A$2:$AO$500,MATCH($A57,'Réel 2025'!$A$2:$A$500,0),MATCH(Q$2,'Réel 2025'!$A$2:$AO$2,0))} -> 9596.17 | S57: =L57-Q57 -> -8311.72
A58: =+B58&C58 -> Véhicules neufsInformatique | B58: =+$K$1 -> Véhicules neufs | C58: Informatique | F58: =+INDEX('Budget original'!$A$2:$AO$501,MATCH($A58,'Budget original'!$A$2:$A$501,0),MATCH(F$2,'Budget original'!$A$2:$AO$2,0)) -> 9195.3522 | L58: =SUMIFS(BV_Data_An_Cour!$O:$O,BV_Data_An_Cour!$U:$U,$B58,BV_Data_An_Cour!$V:$V,$C58,BV_Data_An_Cour!$W:$W,L$2) -> 9247.47 | N58: =L58-F58 -> 52.117833 | Q58: {=+INDEX('Réel 2025'!$A$2:$AO$500,MATCH($A58,'Réel 2025'!$A$2:$A$500,0),MATCH(Q$2,'Réel 2025'!$A$2:$AO$2,0))} -> 4851.72 | S58: =L58-Q58 -> 4395.75
A59: =+B59&C59 -> Véhicules neufsFrais de déplacement | B59: =+$K$1 -> Véhicules neufs | C59: Frais de déplacement | F59: =+INDEX('Budget original'!$A$2:$AO$501,MATCH($A59,'Budget original'!$A$2:$A$501,0),MATCH(F$2,'Budget original'!$A$2:$AO$2,0)) -> 1330 | L59: =SUMIFS(BV_Data_An_Cour!$O:$O,BV_Data_An_Cour!$U:$U,$B59,BV_Data_An_Cour!$V:$V,$C59,BV_Data_An_Cour!$W:$W,L$2) -> 2184.94 | N59: =L59-F59 -> 854.94 | Q59: {=+INDEX('Réel 2025'!$A$2:$AO$500,MATCH($A59,'Réel 2025'!$A$2:$A$500,0),MATCH(Q$2,'Réel 2025'!$A$2:$AO$2,0))} -> 429.47 | S59: =L59-Q59 -> 1755.47
A60: =+B60&C60 -> Véhicules neufsServices extérieurs | B60: =+$K$1 -> Véhicules neufs | C60: Services extérieurs | F60: =+INDEX('Budget original'!$A$2:$AO$501,MATCH($A60,'Budget original'!$A$2:$A$501,0),MATCH(F$2,'Budget original'!$A$2:$AO$2,0)) -> 2672.3603 | L60: =SUMIFS(BV_Data_An_Cour!$O:$O,BV_Data_An_Cour!$U:$U,$B60,BV_Data_An_Cour!$V:$V,$C60,BV_Data_An_Cour!$W:$W,L$2) -> 3167.58 | N60: =L60-F60 -> 495.21967 | Q60: {=+INDEX('Réel 2025'!$A$2:$AO$500,MATCH($A60,'Réel 2025'!$A$2:$A$500,0),MATCH(Q$2,'Réel 2025'!$A$2:$AO$2,0))} -> 2489.44 | S60: =L60-Q60 -> 678.14
A61: =+B61&C61 -> Véhicules neufsFournitures autres | B61: =+$K$1 -> Véhicules neufs | C61: Fournitures autres | F61: =+INDEX('Budget original'!$A$2:$AO$501,MATCH($A61,'Budget original'!$A$2:$A$501,0),MATCH(F$2,'Budget original'!$A$2:$AO$2,0)) -> 75 | L61: =SUMIFS(BV_Data_An_Cour!$O:$O,BV_Data_An_Cour!$U:$U,$B61,BV_Data_An_Cour!$V:$V,$C61,BV_Data_An_Cour!$W:$W,L$2) -> 55.5 | N61: =L61-F61 -> -19.5 | Q61: {=+INDEX('Réel 2025'!$A$2:$AO$500,MATCH($A61,'Réel 2025'!$A$2:$A$500,0),MATCH(Q$2,'Réel 2025'!$A$2:$AO$2,0))} -> 138.66 | S61: =L61-Q61 -> -83.16
A62: =+B62&C62 -> Véhicules neufsUniformes | B62: =+$K$1 -> Véhicules neufs | C62: Uniformes | F62: =+INDEX('Budget original'!$A$2:$AO$501,MATCH($A62,'Budget original'!$A$2:$A$501,0),MATCH(F$2,'Budget original'!$A$2:$AO$2,0)) -> 30 | L62: =SUMIFS(BV_Data_An_Cour!$O:$O,BV_Data_An_Cour!$U:$U,$B62,BV_Data_An_Cour!$V:$V,$C62,BV_Data_An_Cour!$W:$W,L$2) -> 0 | N62: =L62-F62 -> -30 | Q62: {=+INDEX('Réel 2025'!$A$2:$AO$500,MATCH($A62,'Réel 2025'!$A$2:$A$500,0),MATCH(Q$2,'Réel 2025'!$A$2:$AO$2,0))} -> 0 | S62: =L62-Q62 -> 0
A63: =+B63&C63 -> Véhicules neufsPapeterie | B63: =+$K$1 -> Véhicules neufs | C63: Papeterie | F63: =+INDEX('Budget original'!$A$2:$AO$501,MATCH($A63,'Budget original'!$A$2:$A$501,0),MATCH(F$2,'Budget original'!$A$2:$AO$2,0)) -> 580 | L63: =SUMIFS(BV_Data_An_Cour!$O:$O,BV_Data_An_Cour!$U:$U,$B63,BV_Data_An_Cour!$V:$V,$C63,BV_Data_An_Cour!$W:$W,L$2) -> 438.31 | N63: =L63-F63 -> -141.69 | Q63: {=+INDEX('Réel 2025'!$A$2:$AO$500,MATCH($A63,'Réel 2025'!$A$2:$A$500,0),MATCH(Q$2,'Réel 2025'!$A$2:$AO$2,0))} -> 735.07 | S63: =L63-Q63 -> -296.76
A64: =+B64&C64 -> Véhicules neufsTéléphone | B64: =+$K$1 -> Véhicules neufs | C64: Téléphone | F64: =+INDEX('Budget original'!$A$2:$AO$501,MATCH($A64,'Budget original'!$A$2:$A$501,0),MATCH(F$2,'Budget original'!$A$2:$AO$2,0)) -> 157.6 | L64: =SUMIFS(BV_Data_An_Cour!$O:$O,BV_Data_An_Cour!$U:$U,$B64,BV_Data_An_Cour!$V:$V,$C64,BV_Data_An_Cour!$W:$W,L$2) -> 198.07 | N64: =L64-F64 -> 40.47 | Q64: {=+INDEX('Réel 2025'!$A$2:$AO$500,MATCH($A64,'Réel 2025'!$A$2:$A$500,0),MATCH(Q$2,'Réel 2025'!$A$2:$AO$2,0))} -> 183.2 | S64: =L64-Q64 -> 14.87
A65: =+B65&C65 -> Véhicules neufsFrais postaux | B65: =+$K$1 -> Véhicules neufs | C65: Frais postaux | F65: =+INDEX('Budget original'!$A$2:$AO$501,MATCH($A65,'Budget original'!$A$2:$A$501,0),MATCH(F$2,'Budget original'!$A$2:$AO$2,0)) -> 226.66667 | L65: =SUMIFS(BV_Data_An_Cour!$O:$O,BV_Data_An_Cour!$U:$U,$B65,BV_Data_An_Cour!$V:$V,$C65,BV_Data_An_Cour!$W:$W,L$2) -> 52.12 | N65: =L65-F65 -> -174.54667 | Q65: {=+INDEX('Réel 2025'!$A$2:$AO$500,MATCH($A65,'Réel 2025'!$A$2:$A$500,0),MATCH(Q$2,'Réel 2025'!$A$2:$AO$2,0))} -> 309.75 | S65: =L65-Q65 -> -257.63
A66: =+B66&C66 -> Véhicules neufsDivers | B66: =+$K$1 -> Véhicules neufs | C66: Divers | F66: =+INDEX('Budget original'!$A$2:$AO$501,MATCH($A66,'Budget original'!$A$2:$A$501,0),MATCH(F$2,'Budget original'!$A$2:$AO$2,0)) -> 629.08333 | L66: =SUMIFS(BV_Data_An_Cour!$O:$O,BV_Data_An_Cour!$U:$U,$B66,BV_Data_An_Cour!$V:$V,$C66,BV_Data_An_Cour!$W:$W,L$2) -> 756.6 | N66: =L66-F66 -> 127.51667 | Q66: {=+INDEX('Réel 2025'!$A$2:$AO$500,MATCH($A66,'Réel 2025'!$A$2:$A$500,0),MATCH(Q$2,'Réel 2025'!$A$2:$AO$2,0))} -> 1827.48 | S66: =L66-Q66 -> -1070.88
... A68: =+B68&C68 -> Véhicules neufsFrais bancaires | B68: =+$K$1 -> Véhicules neufs | C68: Frais bancaires | F68: =+INDEX('Budget original'!$A$2:$AO$501,MATCH($A68,'Budget original'!$A$2:$A$501,0),MATCH(F$2,'Budget original'!$A$2:$AO$2,0)) -> 3978.2237 | L68: =SUMIFS(BV_Data_An_Cour!$O:$O,BV_Data_An_Cour!$U:$U,$B68,BV_Data_An_Cour!$V:$V,$C68,BV_Data_An_Cour!$W:$W,L$2) -> 2922.42 | N68: =L68-F68 -> -1055.8037 | Q68: {=+INDEX('Réel 2025'!$A$2:$AO$500,MATCH($A68,'Réel 2025'!$A$2:$A$500,0),MATCH(Q$2,'Réel 2025'!$A$2:$AO$2,0))} -> 2634.17 | S68: =L68-Q68 -> 288.25
A69: =+B69&C69 -> Véhicules neufs[...] | B69: =+$K$1 -> Véhicules neufs | C69: [...] | F69: =+INDEX('Budget original'!$A$2:$AO$501,MATCH($A69,'Budget original'!$A$2:$A$501,0),MATCH(F$2,'Budget original'!$A$2:$AO$2,0)) -> 0 | N69: =L69-F69 -> 0 | Q69: {=+INDEX('Réel 2025'!$A$2:$AO$500,MATCH($A69,'Réel 2025'!$A$2:$A$500,0),MATCH(Q$2,'Réel 2025'!$A$2:$AO$2,0))} -> 0 | S69: =L69-Q69 -> 0
A70: =+B70&C70 -> Véhicules neufs[...] | B70: =+$K$1 -> Véhicules neufs | C70: [...] | F70: =+INDEX('Budget original'!$A$2:$AO$501,MATCH($A70,'Budget original'!$A$2:$A$501,0),MATCH(F$2,'Budget original'!$A$2:$AO$2,0)) -> 0 | L70: =SUMIFS(BV_Data_An_Cour!$O:$O,BV_Data_An_Cour!$U:$U,$B70,BV_Data_An_Cour!$V:$V,$C70,BV_Data_An_Cour!$W:$W,L$2) -> 0 | N70: =L70-F70 -> 0 | Q70: {=+INDEX('Réel 2025'!$A$2:$AO$500,MATCH($A70,'Réel 2025'!$A$2:$A$500,0),MATCH(Q$2,'Réel 2025'!$A$2:$AO$2,0))} -> 0 | S70: =L70-Q70 -> 0
A71: =+B71&C71 -> Véhicules neufs[...] | B71: =+$K$1 -> Véhicules neufs | C71: [...] | F71: =+INDEX('Budget original'!$A$2:$AO$501,MATCH($A71,'Budget original'!$A$2:$A$501,0),MATCH(F$2,'Budget original'!$A$2:$AO$2,0)) -> 0 | L71: =SUMIFS(BV_Data_An_Cour!$O:$O,BV_Data_An_Cour!$U:$U,$B71,BV_Data_An_Cour!$V:$V,$C71,BV_Data_An_Cour!$W:$W,L$2)*0.32 -> 0 | N71: =L71-F71 -> 0 | Q71: {=+INDEX('Réel 2025'!$A$2:$AO$500,MATCH($A71,'Réel 2025'!$A$2:$A$500,0),MATCH(Q$2,'Réel 2025'!$A$2:$AO$2,0))} -> 0 | S71: =L71-Q71 -> 0
A72: =+B72&C72 -> Véhicules neufsTOTAL SEMI-FIXES | B72: =+$K$1 -> Véhicules neufs | C72: TOTAL SEMI-FIXES | D72: % brut | E72: =F72/F$27 -> 0.14743727 | F72: =+SUM(F55:F71) -> 21232.381 | J72: % brut | K72: =L72/L$27 -> 0.13910032 | L72: =+SUM(L55:L71) -> 20231.78 | N72: =+SUM(N55:N71) -> -1000.6009 | O72: % brut | P72: =Q72/Q$27 -> 0.17997609 | Q72: =+SUM(Q55:Q71) -> 23712.66 | S72: =+SUM(S55:S71) -> -3480.88
A73: =+B73&C73 -> Véhicules neufs | B73: =+$K$1 -> Véhicules neufs
A74: =+B74&C74 -> Véhicules neufsTOTAL DES DÉPENSES | B74: =+$K$1 -> Véhicules neufs | C74: TOTAL DES DÉPENSES | D74: % brut | E74: =F74/F$27 -> 0.96414773 | F74: =F41+F54+F72 -> 138846.52 | J74: % brut | K74: =L74/L$27 -> 0.95398543 | L74: =L41+L54+L72 -> 138754.7 | N74: =L74-F74 -> -91.817594 | O74: % brut | P74: =Q74/Q$27 -> 1.156383 | Q74: =Q41+Q54+Q72 -> 152358.66 | S74: =L74-Q74 -> -13603.96
A75: =+B75&C75 -> Véhicules neufsRBSC neuf | B75: =+$K$1 -> Véhicules neufs | C75: RBSC neuf | F75: =+INDEX('Budget original'!$A$2:$AO$501,MATCH($A75,'Budget original'!$A$2:$A$501,0),MATCH(F$2,'Budget original'!$A$2:$AO$2,0)) -> 38601.42 | L75: =-SUMIFS(BV_Data_An_Cour!$O:$O,BV_Data_An_Cour!$U:$U,$B75,BV_Data_An_Cour!$V:$V,$C75,BV_Data_An_Cour!$W:$W,L$2) -> 34403.28 | N75: =L75-F75 -> -4198.14 | Q75: =+INDEX('Réel 2025'!$A$2:$AO$500,MATCH($A75,'Réel 2025'!$A$2:$A$500,0),MATCH(Q$2,'Réel 2025'!$A$2:$AO$2,0)) -> 38986.85 | S75: =L75-Q75 -> -4583.57
A76: =+B76&C76 -> Véhicules neufsProgramme neuf 2 | B76: =+$K$1 -> Véhicules neufs | C76: Programme neuf 2 | F76: =+INDEX('Budget original'!$A$2:$AO$501,MATCH($A76,'Budget original'!$A$2:$A$501,0),MATCH(F$2,'Budget original'!$A$2:$AO$2,0)) -> 0 | L76: =-SUMIFS(BV_Data_An_Cour!$O:$O,BV_Data_An_Cour!$U:$U,$B76,BV_Data_An_Cour!$V:$V,$C76,BV_Data_An_Cour!$W:$W,L$2) -> 0 | N76: =L76-F76 -> 0 | Q76: {=+INDEX('Réel 2025'!$A$2:$AO$500,MATCH($A76,'Réel 2025'!$A$2:$A$500,0),MATCH(Q$2,'Réel 2025'!$A$2:$AO$2,0))} -> 0 | S76: =L76-Q76 -> 0
A77: =+B77&C77 -> Véhicules neufsProgramme neuf 3 | B77: =+$K$1 -> Véhicules neufs | C77: Programme neuf 3 | F77: =+INDEX('Budget original'!$A$2:$AO$501,MATCH($A77,'Budget original'!$A$2:$A$501,0),MATCH(F$2,'Budget original'!$A$2:$AO$2,0)) -> 0 | L77: =-SUMIFS(BV_Data_An_Cour!$O:$O,BV_Data_An_Cour!$U:$U,$B77,BV_Data_An_Cour!$V:$V,$C77,BV_Data_An_Cour!$W:$W,L$2) -> 0 | N77: =L77-F77 -> 0 | Q77: {=+INDEX('Réel 2025'!$A$2:$AO$500,MATCH($A77,'Réel 2025'!$A$2:$A$500,0),MATCH(Q$2,'Réel 2025'!$A$2:$AO$2,0))} -> 0 | S77: =L77-Q77 -> 0
A78: =+B78&C78 -> Véhicules neufsHoldbacks | B78: =+$K$1 -> Véhicules neufs | C78: Holdbacks | F78: =+INDEX('Budget original'!$A$2:$AO$501,MATCH($A78,'Budget original'!$A$2:$A$501,0),MATCH(F$2,'Budget original'!$A$2:$AO$2,0)) -> 46789.6 | L78: =-SUMIFS(BV_Data_An_Cour!$O:$O,BV_Data_An_Cour!$U:$U,$B78,BV_Data_An_Cour!$V:$V,$C78,BV_Data_An_Cour!$W:$W,L$2) -> 37951.8 | N78: =L78-F78 -> -8837.8 | Q78: {=+INDEX('Réel 2025'!$A$2:$AO$500,MATCH($A78,'Réel 2025'!$A$2:$A$500,0),MATCH(Q$2,'Réel 2025'!$A$2:$AO$2,0))} -> 30943.4 | S78: =L78-Q78 -> 7008.4
A79: =+B79&C79 -> Véhicules neufs[...] | B79: =+$K$1 -> Véhicules neufs | C79: [...] | F79: =+INDEX('Budget original'!$A$2:$AO$501,MATCH($A79,'Budget original'!$A$2:$A$501,0),MATCH(F$2,'Budget original'!$A$2:$AO$2,0)) -> 0 | L79: =-SUMIFS(BV_Data_An_Cour!$O:$O,BV_Data_An_Cour!$U:$U,$B79,BV_Data_An_Cour!$V:$V,$C79,BV_Data_An_Cour!$W:$W,L$2) -> 0 | N79: =L79-F79 -> 0 | Q79: {=+INDEX('Réel 2025'!$A$2:$AO$500,MATCH($A79,'Réel 2025'!$A$2:$A$500,0),MATCH(Q$2,'Réel 2025'!$A$2:$AO$2,0))} -> 0 | S79: =L79-Q79 -> 0
A80: =+B80&C80 -> Véhicules neufs[...] | B80: =+$K$1 -> Véhicules neufs | C80: [...] | F80: =+INDEX('Budget original'!$A$2:$AO$501,MATCH($A80,'Budget original'!$A$2:$A$501,0),MATCH(F$2,'Budget original'!$A$2:$AO$2,0)) -> 0 | L80: =-SUMIFS(BV_Data_An_Cour!$O:$O,BV_Data_An_Cour!$U:$U,$B80,BV_Data_An_Cour!$V:$V,$C80,BV_Data_An_Cour!$W:$W,L$2) -> 0 | N80: =L80-F80 -> 0 | Q80: {=+INDEX('Réel 2025'!$A$2:$AO$500,MATCH($A80,'Réel 2025'!$A$2:$A$500,0),MATCH(Q$2,'Réel 2025'!$A$2:$AO$2,0))} -> 0 | S80: =L80-Q80 -> 0
A81: =+B81&C81 -> Véhicules neufs[...] | B81: =+$K$1 -> Véhicules neufs | C81: [...] | F81: =+INDEX('Budget original'!$A$2:$AO$501,MATCH($A81,'Budget original'!$A$2:$A$501,0),MATCH(F$2,'Budget original'!$A$2:$AO$2,0)) -> 0 | L81: =-SUMIFS(BV_Data_An_Cour!$O:$O,BV_Data_An_Cour!$U:$U,$B81,BV_Data_An_Cour!$V:$V,$C81,BV_Data_An_Cour!$W:$W,L$2) -> 0 | N81: =L81-F81 -> 0 | Q81: {=+INDEX('Réel 2025'!$A$2:$AO$500,MATCH($A81,'Réel 2025'!$A$2:$A$500,0),MATCH(Q$2,'Réel 2025'!$A$2:$AO$2,0))} -> 0 | S81: =L81-Q81 -> 0
A82: =+B82&C82 -> Véhicules neufsFrais administration | B82: =+$K$1 -> Véhicules neufs | C82: Frais administration | F82: =+INDEX('Budget original'!$A$2:$AO$501,MATCH($A82,'Budget original'!$A$2:$A$501,0),MATCH(F$2,'Budget original'!$A$2:$AO$2,0)) -> 15160.6 | L82: =-SUMIFS(BV_Data_An_Cour!$O:$O,BV_Data_An_Cour!$U:$U,$B82,BV_Data_An_Cour!$V:$V,$C82,BV_Data_An_Cour!$W:$W,L$2) -> 14280 | N82: =L82-F82 -> -880.6 | Q82: {=+INDEX('Réel 2025'!$A$2:$AO$500,MATCH($A82,'Réel 2025'!$A$2:$A$500,0),MATCH(Q$2,'Réel 2025'!$A$2:$AO$2,0))} -> 11900 | S82: =L82-Q82 -> 2380 | V82: =L82/595 -> 24 | W82: =V82/J27 -> 0.8
A83: =+B83&C83 -> Véhicules neufsAUTRES REVENUS | B83: =+$K$1 -> Véhicules neufs | C83: AUTRES REVENUS | F83: =+SUM(F75:F82) -> 100551.62 | L83: =+SUM(L75:L82) -> 86635.08 | N83: =+SUM(N75:N82) -> -13916.54 | Q83: =+SUM(Q75:Q82) -> 81830.25 | S83: =+SUM(S75:S82) -> 4804.83
A84: =+B84&C84 -> Véhicules neufs | B84: =+$K$1 -> Véhicules neufs
A85: =+B85&C85 -> Véhicules neufsPROFIT DÉPARTEMENTAL | B85: =+$K$1 -> Véhicules neufs | C85: PROFIT DÉPARTEMENTAL | F85: =F27-F74+F83 -> 105714.69 | L85: =L27-L74+L83 -> 93327.78 | N85: =N27-N41-N54-N72+N83 -> -12386.911 | Q85: =Q27-Q74+Q83 -> 61226.09 | S85: =S27-S41-S54-S72+S83 -> 32101.69
C89: =C1 -> BMW Sherbrooke | K89: Véhicules usagés | S89: =$S$1 -> Réalisé, Juin 2026
D91: BUDGET ORIGINAL | J91: RÉALISATION | M91: ÉCART réel / Budget | O91: ANNÉE PRÉCÉDENTE | R91: ECART (réel/ Ann.Préc.)
D92: UNITE | E92: $P/UNITÉ | F92: $PROFITS | J92: UNITE | K92: $P/UNITE | L92: $PROFITS | M92: UNFTÉ | N92: $PROFFTS | O92: UNITE | P92: $P/UNITÉ | Q92: $PROFITS | R92: UNITE | S92: $PROFITS
A93: =+B93&C93 -> Véhicules usagésVentes nettes | B93: Véhicules usagés | C93: Ventes nettes | F93: =+INDEX('Budget original'!$A$2:$AO$501,MATCH($A93,'Budget original'!$A$2:$A$501,0),MATCH(F$2,'Budget original'!$A$2:$AO$2,0)) -> 2452221.9 | L93: =-SUMIFS(BV_Data_An_Cour!$O:$O,BV_Data_An_Cour!$X:$X,"Oui",BV_Data_An_Cour!$U:$U,$B93) -> 2841713.5 | Q93: {=+INDEX('Réel 2025'!$A$2:$AO$500,MATCH($A93,'Réel 2025'!$A$2:$A$500,0),MATCH(Q$2,'Réel 2025'!$A$2:$AO$2,0))} -> 1387819.5
A94: =+B94&C94 -> Véhicules usagésCertifié | B94: Véhicules usagés | C94: Certifié | D94: =+INDEX('Budget original'!$A$2:$AO$501,MATCH($A94,'Budget original'!$A$2:$A$501,0),MATCH(D$2,'Budget original'!$A$2:$AO$2,0)) -> 19 | E94: =IF(D94=0,0,F94/D94) -> 2400 | F94: =+INDEX('Budget original'!$A$2:$AO$501,MATCH($A94,'Budget original'!$A$2:$A$501,0),MATCH(F$2,'Budget original'!$A$2:$AO$2,0)) -> 45600 | J94: =-SUMIFS(BV_Data_An_Cour!$O:$O,BV_Data_An_Cour!$U:$U,$B94,BV_Data_An_Cour!$V:$V,$C94,BV_Data_An_Cour!$W:$W,J$2) -> 17 | K94: =IF(J94=0,0,L94/J94) -> 1337.7129 | L94: =-SUMIFS(BV_Data_An_Cour!$O:$O,BV_Data_An_Cour!$U:$U,$B94,BV_Data_An_Cour!$V:$V,$C94,BV_Data_An_Cour!$W:$W,$L2) -> 22741.12 | M94: =J94-D94 -> -2 | N94: =L94-F94 -> -22858.88 | O94: {=+INDEX('Réel 2025'!$A$2:$AO$500,MATCH($A94,'Réel 2025'!$A$2:$A$500,0),MATCH(O$2,'Réel 2025'!$A$2:$AO$2,0))} -> 6 | P94: =IF(O94=0,0,Q94/O94) -> 2132.8233 | Q94: {=+INDEX('Réel 2025'!$A$2:$AO$500,MATCH($A94,'Réel 2025'!$A$2:$A$500,0),MATCH(Q$2,'Réel 2025'!$A$2:$AO$2,0))} -> 12796.94 | R94: =J94-O94 -> 11 | S94: =L94-Q94 -> 9944.18
A95: =+B95&C95 -> Véhicules usagésNon Certifié | B95: Véhicules usagés | C95: Non Certifié | D95: =+INDEX('Budget original'!$A$2:$AO$501,MATCH($A95,'Budget original'!$A$2:$A$501,0),MATCH(D$2,'Budget original'!$A$2:$AO$2,0)) -> 5 | E95: =IF(D95=0,0,F95/D95) -> 1400 | F95: =+INDEX('Budget original'!$A$2:$AO$501,MATCH($A95,'Budget original'!$A$2:$A$501,0),MATCH(F$2,'Budget original'!$A$2:$AO$2,0)) -> 7000 | J95: =-SUMIFS(BV_Data_An_Cour!$O:$O,BV_Data_An_Cour!$U:$U,$B95,BV_Data_An_Cour!$V:$V,$C95,BV_Data_An_Cour!$W:$W,J$2) -> 4 | K95: =IF(J95=0,0,L95/J95) -> 804.2825 | L95: =-SUMIFS(BV_Data_An_Cour!$O:$O,BV_Data_An_Cour!$U:$U,$B95,BV_Data_An_Cour!$V:$V,$C95,BV_Data_An_Cour!$W:$W,$L2) -> 3217.13 | M95: =J95-D95 -> -1 | N95: =L95-F95 -> -3782.87 | O95: {=+INDEX('Réel 2025'!$A$2:$AO$500,MATCH($A95,'Réel 2025'!$A$2:$A$500,0),MATCH(O$2,'Réel 2025'!$A$2:$AO$2,0))} -> 13 | P95: =IF(O95=0,0,Q95/O95) -> 1919.1208 | Q95: {=+INDEX('Réel 2025'!$A$2:$AO$500,MATCH($A95,'Réel 2025'!$A$2:$A$500,0),MATCH(Q$2,'Réel 2025'!$A$2:$AO$2,0))} -> 24948.57 | R95: =J95-O95 -> -9 | S95: =L95-Q95 -> -21731.44
A96: =+B96&C96 -> Véhicules usagésAutres marques | B96: Véhicules usagés | C96: Autres marques | D96: =+INDEX('Budget original'!$A$2:$AO$501,MATCH($A96,'Budget original'!$A$2:$A$501,0),MATCH(D$2,'Budget original'!$A$2:$AO$2,0)) -> 8 | E96: =IF(D96=0,0,F96/D96) -> 1500 | F96: =+INDEX('Budget original'!$A$2:$AO$501,MATCH($A96,'Budget original'!$A$2:$A$501,0),MATCH(F$2,'Budget original'!$A$2:$AO$2,0)) -> 12000 | J96: =-SUMIFS(BV_Data_An_Cour!$O:$O,BV_Data_An_Cour!$U:$U,$B96,BV_Data_An_Cour!$V:$V,$C96,BV_Data_An_Cour!$W:$W,J$2) -> 8 | K96: =IF(J96=0,0,L96/J96) -> 1476.4362 | L96: =-SUMIFS(BV_Data_An_Cour!$O:$O,BV_Data_An_Cour!$U:$U,$B96,BV_Data_An_Cour!$V:$V,$C96,BV_Data_An_Cour!$W:$W,$L2) -> 11811.49 | M96: =J96-D96 -> 0 | N96: =L96-F96 -> -188.51 | O96: =+INDEX('Réel 2025'!$A$2:$AO$500,MATCH($A96,'Réel 2025'!$A$2:$A$500,0),MATCH(O$2,'Réel 2025'!$A$2:$AO$2,0)) -> 6 | P96: =IF(O96=0,0,Q96/O96) -> 1460.9367 | Q96: =+INDEX('Réel 2025'!$A$2:$AO$500,MATCH($A96,'Réel 2025'!$A$2:$A$500,0),MATCH(Q$2,'Réel 2025'!$A$2:$AO$2,0)) -> 8765.62 | R96: =J96-O96 -> 2 | S96: =L96-Q96 -> 3045.87
A97: =+B97&C97 -> Véhicules usagésTotal Usagés | B97: Véhicules usagés | C97: Total Usagés | D97: =+D95+D94+D96 -> 32 | E97: =IF(D97=0,0,F97/D97) -> 2018.75 | F97: =+F94+F95+F96 -> 64600 | J97: =+J94+J95+J96 -> 29 | K97: =IF(J97<=0,0,L97/J97) -> 1302.4048 | L97: =+L94+L95+L96 -> 37769.74 | M97: =J97-D97 -> -3 | N97: =L97-F97 -> -26830.26 | O97: =+O95+O94+O96 -> 25 | P97: =IF(O97=0,0,Q97/O97) -> 1860.4452 | Q97: =+Q94+Q95+Q96 -> 46511.13 | R97: =J97-O97 -> 4 | S97: =L97-Q97 -> -8741.39
A98: =+B98&C98 -> Véhicules usagés | B98: Véhicules usagés | M98: =M97/D97 -> -0.09375 | N98: =N97/F97 -> -0.4153291 | R98: =R97/O97 -> 0.16 | S98: =IF(Q97=0,0,(S97/Q97)) -> -0.1879419
A99: =+B99&C99 -> Véhicules neufsRachat bail | B99: =+$K$1 -> Véhicules neufs | C99: Rachat bail | D99: =+INDEX('Budget original'!$A$2:$AO$501,MATCH($A99,'Budget original'!$A$2:$A$501,0),MATCH(D$2,'Budget original'!$A$2:$AO$2,0)) -> 0 | E99: =IF(D99=0,0,F99/D99) -> 0 | F99: =+INDEX('Budget original'!$A$2:$AO$501,MATCH($A99,'Budget original'!$A$2:$A$501,0),MATCH(F$2,'Budget original'!$A$2:$AO$2,0)) -> 1509.8237 | L99: =-SUMIFS(BV_Data_An_Cour!$O:$O,BV_Data_An_Cour!$U:$U,$B99,BV_Data_An_Cour!$V:$V,$C99,BV_Data_An_Cour!$W:$W,L$2) -> 4986.43 | N99: =L99-F99 -> 3476.6063 | Q99: {=+INDEX('Réel 2025'!$A$2:$AO$500,MATCH($A99,'Réel 2025'!$A$2:$A$500,0),MATCH(Q$2,'Réel 2025'!$A$2:$AO$2,0))} -> 563.25 | R99: =O99-K99 -> 0 | S99: =L99-Q99 -> 4423.18
A100: =+B100&C100 -> Véhicules usagés | B100: Véhicules usagés
A101: =+B101&C101 -> Véhicules usagésVentes au Gros | B101: Véhicules usagés | C101: Ventes au Gros | D101: =+INDEX('Budget original'!$A$2:$AO$501,MATCH($A101,'Budget original'!$A$2:$A$501,0),MATCH(D$2,'Budget original'!$A$2:$AO$2,0)) -> 26 | E101: =IF(D101=0,0,F101/D101) -> 500 | F101: =+INDEX('Budget original'!$A$2:$AO$501,MATCH($A101,'Budget original'!$A$2:$A$501,0),MATCH(F$2,'Budget original'!$A$2:$AO$2,0)) -> 13000 | J101: =-SUMIFS(BV_Data_An_Cour!$O:$O,BV_Data_An_Cour!$U:$U,$B101,BV_Data_An_Cour!$V:$V,$C101,BV_Data_An_Cour!$W:$W,J$2) -> 38 | K101: =IF(J101=0,0,L101/J101) -> 993.30079 | L101: =-SUMIFS(BV_Data_An_Cour!$O:$O,BV_Data_An_Cour!$U:$U,$B101,BV_Data_An_Cour!$V:$V,$C101,BV_Data_An_Cour!$W:$W,L$2) -> 37745.43 | M101: =J101-D101 -> 12 | N101: =L101-F101 -> 24745.43 | O101: {=+INDEX('Réel 2025'!$A$2:$AO$500,MATCH($A101,'Réel 2025'!$A$2:$A$500,0),MATCH(O$2,'Réel 2025'!$A$2:$AO$2,0))} -> 11 | P101: =IF(O101=0,0,Q101/O101) -> -175.90818 | Q101: {=+INDEX('Réel 2025'!$A$2:$AO$500,MATCH($A101,'Réel 2025'!$A$2:$A$500,0),MATCH(Q$2,'Réel 2025'!$A$2:$AO$2,0))} -> -1934.99 | R101: =J101-O101 -> 27 | S101: =L101-Q101 -> 39680.42
A102: =+B102&C102 -> Véhicules usagés | B102: Véhicules usagés
A103: =+B103&C103 -> Véhicules usagésRev. Finances | B103: Véhicules usagés | C103: Rev. Finances | E103: =IF(D97=0,0,F103/D97) -> 350 | F103: =+INDEX('Budget original'!$A$2:$AO$501,MATCH($A103,'Budget original'!$A$2:$A$501,0),MATCH(F$2,'Budget original'!$A$2:$AO$2,0)) -> 11200 | K103: =IF(J97=0,0,L103/J97) -> 464.98172 | L103: =-SUMIFS(BV_Data_An_Cour!$O:$O,BV_Data_An_Cour!$U:$U,$B103,BV_Data_An_Cour!$V:$V,$C103,BV_Data_An_Cour!$W:$W,$L2) -> 13484.47 | N103: =L103-F103 -> 2284.47 | P103: =IF(O97=0,0,Q103/O97) -> 336.268 | Q103: {=+INDEX('Réel 2025'!$A$2:$AO$500,MATCH($A103,'Réel 2025'!$A$2:$A$500,0),MATCH(Q$2,'Réel 2025'!$A$2:$AO$2,0))} -> 8406.7 | R103: =O103-K103 -> -464.98172 | S103: =L103-Q103 -> 5077.77
A104: =+B104&C104 -> Véhicules usagésRev. Protections | B104: Véhicules usagés | C104: Rev. Protections | E104: =IF(D97=0,0,F104/D97) -> 950 | F104: =+INDEX('Budget original'!$A$2:$AO$501,MATCH($A104,'Budget original'!$A$2:$A$501,0),MATCH(F$2,'Budget original'!$A$2:$AO$2,0)) -> 30400 | K104: =IF(J97=0,0,L104/J97) -> 521.03793 | L104: =-SUMIFS(BV_Data_An_Cour!$O:$O,BV_Data_An_Cour!$U:$U,$B104,BV_Data_An_Cour!$V:$V,$C104,BV_Data_An_Cour!$W:$W,$L2) -> 15110.1 | N104: =L104-F104 -> -15289.9 | P104: =IF(O97=0,0,Q104/O97) -> 1091.892 | Q104: {=+INDEX('Réel 2025'!$A$2:$AO$500,MATCH($A104,'Réel 2025'!$A$2:$A$500,0),MATCH(Q$2,'Réel 2025'!$A$2:$AO$2,0))} -> 27297.3 | R104: =O104-K104 -> -521.03793 | S104: =L104-Q104 -> -12187.2
A105: =+B105&C105 -> Véhicules usagésRev. Autres | B105: Véhicules usagés | C105: Rev. Autres | E105: =IF(D97=0,0,F105/D97) -> 200 | F105: =+INDEX('Budget original'!$A$2:$AO$501,MATCH($A105,'Budget original'!$A$2:$A$501,0),MATCH(F$2,'Budget original'!$A$2:$AO$2,0)) -> 6400 | K105: =IF(J97=0,0,L105/J97) -> 72.758621 | L105: =-SUMIFS(BV_Data_An_Cour!$O:$O,BV_Data_An_Cour!$U:$U,$B105,BV_Data_An_Cour!$V:$V,$C105,BV_Data_An_Cour!$W:$W,$L$2) -> 2110 | N105: =L105-F105 -> -4290 | P105: =IF(O97=0,0,Q105/O97) -> 340.778 | Q105: {=+INDEX('Réel 2025'!$A$2:$AO$500,MATCH($A105,'Réel 2025'!$A$2:$A$500,0),MATCH(Q$2,'Réel 2025'!$A$2:$AO$2,0))} -> 8519.45 | R105: =O105-K105 -> -72.758621 | S105: =L105-Q105 -> -6409.45
...

Sheet Réalisé AAD
C1: =Parametres!B1 -> BMW Sherbrooke | K1: Véhicules neufs | S1: =CONCATENATE("Réalisé,"," ",Parametres!B3," ",Parametres!B4," AAD") -> Réalisé, Juin 2026 AAD
D2: X | E2: O | F2: U | J2: NB | L2: $ | O2: X | P2: O | Q2: U | X2: X | Y2: O | Z2: U | AJ2: X | AK2: O | AL2: U
D3: BUDGET ORIGINAL | J3: RÉALISATION | M3: ÉCART réel / Budget | O3: ANNÉE PRÉCÉDENTE | R3: ECART (réel/ Ann.Préc.)
D4: UNITE | E4: $P/UNITÉ | F4: $PROFITS | J4: UNITE | K4: $P/UNITE | L4: $PROFITS | M4: UNFTÉ | N4: $PROFITS | O4: UNITE | P4: $P/UNITÉ | Q4: $PROFITS | R4: UNITE | S4: $PROFITS
A5: =+B5&C5 -> Véhicules neufsVentes nettes | B5: =+$K$1 -> Véhicules neufs | C5: Ventes nettes | F5: {=+SUMPRODUCT(('Budget original'!$A$8:$A$501=$A5)*('Budget original'!$C$3:$AO$3=F$2),'Budget original'!$C$8:$AO$501)} -> 15771359 | L5: =-SUMIFS(BV_Data_An_Cour!$P:$P,BV_Data_An_Cour!$X:$X,"Oui",BV_Data_An_Cour!$U:$U,$B5) -> 15645004 | Q5: {=+SUMPRODUCT(('Réel 2025'!$A$8:$A$500=$A5)*('Réel 2025'!$C$3:$AO$3=Q$2),'Réel 2025'!$C$8:$AO$500)} -> 13069579
A6: =+B6&C6 -> Véhicules neufsAutos détail | B6: =+$K$1 -> Véhicules neufs | C6: Autos détail | D6: {=+SUMPRODUCT(('Budget original'!$A$8:$A$501=$A6)*('Budget original'!$C$3:$AO$3=D$2),'Budget original'!$C$8:$AO$501)} -> 44 | E6: =IF(D6=0,0,F6/D6) -> 4701.1765 | F6: {=+SUMPRODUCT(('Budget original'!$A$8:$A$501=$A6)*('Budget original'!$C$3:$AO$3=F$2),'Budget original'!$C$8:$AO$501)} -> 206851.76 | J6: =-SUMIFS(BV_Data_An_Cour!$P:$P,BV_Data_An_Cour!$U:$U,$B6,BV_Data_An_Cour!$V:$V,$C6,BV_Data_An_Cour!$W:$W,J$2) -> 44 | K6: =IF(J6=0,0,L6/J6) -> 5508.025 | L6: =-SUMIFS(BV_Data_An_Cour!$P:$P,BV_Data_An_Cour!$U:$U,$B6,BV_Data_An_Cour!$V:$V,$C6,BV_Data_An_Cour!$W:$W,L$2) -> 242353.1 | M6: =J6-D6 -> 0 | N6: =L6-F6 -> 35501.335 | O6: {=+SUMPRODUCT(('Réel 2025'!$A$8:$A$500=$A6)*('Réel 2025'!$C$3:$AO$3=O$2),'Réel 2025'!$C$8:$AO$500)} -> 42 | P6: =IF(O6=0,0,Q6/O6) -> 5248.6988 | Q6: {=+SUMPRODUCT(('Réel 2025'!$A$8:$A$500=$A6)*('Réel 2025'!$C$3:$AO$3=Q$2),'Réel 2025'!$C$8:$AO$500)} -> 220445.35 | R6: =J6-O6 -> 2 | S6: =L6-Q6 -> 21907.75
A7: =+B7&C7 -> Véhicules neufsCamions détail | B7: =+$K$1 -> Véhicules neufs | C7: Camions détail | D7: {=+SUMPRODUCT(('Budget original'!$A$8:$A$501=$A7)*('Budget original'!$C$3:$AO$3=D$2),'Budget original'!$C$8:$AO$501)} -> 104 | E7: =IF(D7=0,0,F7/D7) -> 3928.5 | F7: {=+SUMPRODUCT(('Budget original'!$A$8:$A$501=$A7)*('Budget original'!$C$3:$AO$3=F$2),'Budget original'!$C$8:$AO$501)} -> 408564 | J7: =-SUMIFS(BV_Data_An_Cour!$P:$P,BV_Data_An_Cour!$U:$U,$B7,BV_Data_An_Cour!$V:$V,$C7,BV_Data_An_Cour!$W:$W,J$2) -> 74 | K7: =IF(J7=0,0,L7/J7) -> 3986.0123 | L7: =-SUMIFS(BV_Data_An_Cour!$P:$P,BV_Data_An_Cour!$U:$U,$B7,BV_Data_An_Cour!$V:$V,$C7,BV_Data_An_Cour!$W:$W,L$2) -> 294964.91 | M7: =J7-D7 -> -30 | N7: =L7-F7 -> -113599.09 | O7: {=+SUMPRODUCT(('Réel 2025'!$A$8:$A$500=$A7)*('Réel 2025'!$C$3:$AO$3=O$2),'Réel 2025'!$C$8:$AO$500)} -> 74 | P7: =IF(O7=0,0,Q7/O7) -> 4139.8992 | Q7: {=+SUMPRODUCT(('Réel 2025'!$A$8:$A$500=$A7)*('Réel 2025'!$C$3:$AO$3=Q$2),'Réel 2025'!$C$8:$AO$500)} -> 306352.54 | R7: =J7-O7 -> 0 | S7: =L7-Q7 -> -11387.63
A8: =+B8&C8 -> Véhicules neufsSprinter | B8: =+$K$1 -> Véhicules neufs | C8: Sprinter | D8: {=+SUMPRODUCT(('Budget original'!$A$8:$A$501=$A8)*('Budget original'!$C$3:$AO$3=D$2),'Budget original'!$C$8:$AO$501)} -> 0 | E8: =IF(D8=0,0,F8/D8) -> 0 | F8: {=+SUMPRODUCT(('Budget original'!$A$8:$A$501=$A8)*('Budget original'!$C$3:$AO$3=F$2),'Budget original'!$C$8:$AO$501)} -> 0 | J8: =-SUMIFS(BV_Data_An_Cour!$P:$P,BV_Data_An_Cour!$U:$U,$B8,BV_Data_An_Cour!$V:$V,$C8,BV_Data_An_Cour!$W:$W,J$2) -> 0 | K8: =IF(J8=0,0,L8/J8) -> 0 | L8: =-SUMIFS(BV_Data_An_Cour!$P:$P,BV_Data_An_Cour!$U:$U,$B8,BV_Data_An_Cour!$V:$V,$C8,BV_Data_An_Cour!$W:$W,L$2) -> 0 | M8: =J8-D8 -> 0 | N8: =L8-F8 -> 0 | O8: {=+SUMPRODUCT(('Réel 2025'!$A$8:$A$500=$A8)*('Réel 2025'!$C$3:$AO$3=O$2),'Réel 2025'!$C$8:$AO$500)} -> 0 | P8: =IF(O8=0,0,Q8/O8) -> 0 | Q8: {=+SUMPRODUCT(('Réel 2025'!$A$8:$A$500=$A8)*('Réel 2025'!$C$3:$AO$3=Q$2),'Réel 2025'!$C$8:$AO$500)} -> 0 | R8: =J8-O8 -> 0 | S8: =L8-Q8 -> 0
A9: =+B9&C9 -> Véhicules neufsMoto détail | B9: =+$K$1 -> Véhicules neufs | C9: Moto détail | D9: {=+SUMPRODUCT(('Budget original'!$A$8:$A$501=$A9)*('Budget original'!$C$3:$AO$3=D$2),'Budget original'!$C$8:$AO$501)} -> 0 | E9: =IF(D9=0,0,F9/D9) -> 0 | F9: {=+SUMPRODUCT(('Budget original'!$A$8:$A$501=$A9)*('Budget original'!$C$3:$AO$3=F$2),'Budget original'!$C$8:$AO$501)} -> 0 | J9: =-SUMIFS(BV_Data_An_Cour!$P:$P,BV_Data_An_Cour!$U:$U,$B9,BV_Data_An_Cour!$V:$V,$C9,BV_Data_An_Cour!$W:$W,J$2) -> 0 | K9: =IF(J9=0,0,L9/J9) -> 0 | L9: =-SUMIFS(BV_Data_An_Cour!$P:$P,BV_Data_An_Cour!$U:$U,$B9,BV_Data_An_Cour!$V:$V,$C9,BV_Data_An_Cour!$W:$W,L$2) -> 0 | M9: =J9-D9 -> 0 | N9: =L9-F9 -> 0 | O9: {=+SUMPRODUCT(('Réel 2025'!$A$8:$A$500=$A9)*('Réel 2025'!$C$3:$AO$3=O$2),'Réel 2025'!$C$8:$AO$500)} -> 0 | P9: =IF(O9=0,0,Q9/O9) -> 0 | Q9: {=+SUMPRODUCT(('Réel 2025'!$A$8:$A$500=$A9)*('Réel 2025'!$C$3:$AO$3=Q$2),'Réel 2025'!$C$8:$AO$500)} -> 0 | R9: =J9-O9 -> 0 | S9: =L9-Q9 -> 0
A10: =+B10&C10 -> Véhicules neufs[...] | B10: =+$K$1 -> Véhicules neufs | C10: [...] | D10: {=+SUMPRODUCT(('Budget original'!$A$8:$A$501=$A10)*('Budget original'!$C$3:$AO$3=D$2),'Budget original'!$C$8:$AO$501)} -> 0 | E10: =IF(D10=0,0,F10/D10) -> 0 | F10: {=+SUMPRODUCT(('Budget original'!$A$8:$A$501=$A10)*('Budget original'!$C$3:$AO$3=F$2),'Budget original'!$C$8:$AO$501)} -> 0 | J10: =-SUMIFS(BV_Data_An_Cour!$P:$P,BV_Data_An_Cour!$U:$U,$B10,BV_Data_An_Cour!$V:$V,$C10,BV_Data_An_Cour!$W:$W,J$2) -> 0 | K10: =IF(J10=0,0,L10/J10) -> 0 | L10: =-SUMIFS(BV_Data_An_Cour!$P:$P,BV_Data_An_Cour!$U:$U,$B10,BV_Data_An_Cour!$V:$V,$C10,BV_Data_An_Cour!$W:$W,L$2) -> 0 | M10: =J10-D10 -> 0 | N10: =L10-F10 -> 0 | O10: {=+SUMPRODUCT(('Réel 2025'!$A$8:$A$500=$A10)*('Réel 2025'!$C$3:$AO$3=O$2),'Réel 2025'!$C$8:$AO$500)} -> 0 | P10: =IF(O10=0,0,Q10/O10) -> 0 | Q10: {=+SUMPRODUCT(('Réel 2025'!$A$8:$A$500=$A10)*('Réel 2025'!$C$3:$AO$3=Q$2),'Réel 2025'!$C$8:$AO$500)} -> 0 | R10: =J10-O10 -> 0 | S10: =L10-Q10 -> 0
A11: =+B11&C11 -> Véhicules neufs[...] | B11: =+$K$1 -> Véhicules neufs | C11: [...] | D11: {=+SUMPRODUCT(('Budget original'!$A$8:$A$501=$A11)*('Budget original'!$C$3:$AO$3=D$2),'Budget original'!$C$8:$AO$501)} -> 0 | E11: =IF(D11=0,0,F11/D11) -> 0 | F11: {=+SUMPRODUCT(('Budget original'!$A$8:$A$501=$A11)*('Budget original'!$C$3:$AO$3=F$2),'Budget original'!$C$8:$AO$501)} -> 0 | J11: =-SUMIFS(BV_Data_An_Cour!$P:$P,BV_Data_An_Cour!$U:$U,$B11,BV_Data_An_Cour!$V:$V,$C11,BV_Data_An_Cour!$W:$W,J$2) -> 0 | K11: =IF(J11=0,0,L11/J11) -> 0 | L11: =-SUMIFS(BV_Data_An_Cour!$P:$P,BV_Data_An_Cour!$U:$U,$B11,BV_Data_An_Cour!$V:$V,$C11,BV_Data_An_Cour!$W:$W,L$2) -> 0 | M11: =J11-D11 -> 0 | N11: =L11-F11 -> 0 | O11: {=+SUMPRODUCT(('Réel 2025'!$A$8:$A$500=$A11)*('Réel 2025'!$C$3:$AO$3=O$2),'Réel 2025'!$C$8:$AO$500)} -> 0 | P11: =IF(O11=0,0,Q11/O11) -> 0 | Q11: {=+SUMPRODUCT(('Réel 2025'!$A$8:$A$500=$A11)*('Réel 2025'!$C$3:$AO$3=Q$2),'Réel 2025'!$C$8:$AO$500)} -> 0 | R11: =J11-O11 -> 0 | S11: =L11-Q11 -> 0
A12: =+B12&C12 -> Véhicules neufs[...] | B12: =+$K$1 -> Véhicules neufs | C12: [...] | D12: {=+SUMPRODUCT(('Budget original'!$A$8:$A$501=$A12)*('Budget original'!$C$3:$AO$3=D$2),'Budget original'!$C$8:$AO$501)} -> 0 | E12: =IF(D12=0,0,F12/D12) -> 0 | F12: {=+SUMPRODUCT(('Budget original'!$A$8:$A$501=$A12)*('Budget original'!$C$3:$AO$3=F$2),'Budget original'!$C$8:$AO$501)} -> 0 | J12: =-SUMIFS(BV_Data_An_Cour!$P:$P,BV_Data_An_Cour!$U:$U,$B12,BV_Data_An_Cour!$V:$V,$C12,BV_Data_An_Cour!$W:$W,J$2) -> 0 | K12: =IF(J12=0,0,L12/J12) -> 0 | L12: =-SUMIFS(BV_Data_An_Cour!$P:$P,BV_Data_An_Cour!$U:$U,$B12,BV_Data_An_Cour!$V:$V,$C12,BV_Data_An_Cour!$W:$W,L$2) -> 0 | M12: =J12-D12 -> 0 | N12: =L12-F12 -> 0 | O12: {=+SUMPRODUCT(('Réel 2025'!$A$8:$A$500=$A12)*('Réel 2025'!$C$3:$AO$3=O$2),'Réel 2025'!$C$8:$AO$500)} -> 0 | P12: =IF(O12=0,0,Q12/O12) -> 0 | Q12: {=+SUMPRODUCT(('Réel 2025'!$A$8:$A$500=$A12)*('Réel 2025'!$C$3:$AO$3=Q$2),'Réel 2025'!$C$8:$AO$500)} -> 0 | R12: =J12-O12 -> 0 | S12: =L12-Q12 -> 0
A13: =+B13&C13 -> Véhicules neufsTotal Neufs | B13: =+$K$1 -> Véhicules neufs | C13: Total Neufs | D13: =+SUM(D6:D12) -> 148 | E13: =IF(D13<=0,0,F13/D13) -> 4158.2146 | F13: =+SUM(F6:F12) -> 615415.76 | J13: =+SUM(J6:J12) -> 118 | K13: =IF(J13<=0,0,L13/J13) -> 4553.5425 | L13: =+SUM(L6:L12) -> 537318.01 | M13: =+SUM(M6:M12) -> -30 | N13: =+SUM(N6:N12) -> -78097.755 | O13: =+SUM(O6:O12) -> 116 | P13: =IF(O13<=0,0,Q13/O13) -> 4541.3611 | Q13: =+SUM(Q6:Q12) -> 526797.89 | R13: =+SUM(R6:R12) -> 2 | S13: =+SUM(S6:S12) -> 10520.12
A14: =+B14&C14 -> Véhicules neufs | B14: =+$K$1 -> Véhicules neufs | M14: =IF(D13=0,0,M13/D13) -> -0.2027027 | N14: =IF(F13=0,0,N13/F13) -> -0.12690243 | R14: =R13/O13 -> 0.017241379 | S14: =IF(Q13=0,0,(S13/Q13)) -> 0.019969936
A15: =+B15&C15 -> Véhicules neufsEx-Démos et courtoisies | B15: =+$K$1 -> Véhicules neufs | C15: Ex-Démos et courtoisies | D15: {=+SUMPRODUCT(('Budget original'!$A$8:$A$501=$A15)*('Budget original'!$C$3:$AO$3=D$2),'Budget original'!$C$8:$AO$501)} -> 24 | E15: =IF(D15=0,0,F15/D15) -> 1200 | F15: {=+SUMPRODUCT(('Budget original'!$A$8:$A$501=$A15)*('Budget original'!$C$3:$AO$3=F$2),'Budget original'!$C$8:$AO$501)} -> 28800 | J15: =-SUMIFS(BV_Data_An_Cour!$P:$P,BV_Data_An_Cour!$U:$U,$B15,BV_Data_An_Cour!$V:$V,$C15,BV_Data_An_Cour!$W:$W,J$2) -> 28 | K15: =IF(J15=0,0,L15/J15) -> 639.2325 | L15: =-SUMIFS(BV_Data_An_Cour!$P:$P,BV_Data_An_Cour!$U:$U,$B15,BV_Data_An_Cour!$V:$V,$C15,BV_Data_An_Cour!$W:$W,L$2) -> 17898.51 | M15: =J15-D15 -> 4 | N15: =L15-F15 -> -10901.49 | O15: {=+SUMPRODUCT(('Réel 2025'!$A$8:$A$500=$A15)*('Réel 2025'!$C$3:$AO$3=O$2),'Réel 2025'!$C$8:$AO$500)} -> 27 | P15: =IF(O15=0,0,Q15/O15) -> 2777.6352 | Q15: {=+SUMPRODUCT(('Réel 2025'!$A$8:$A$500=$A15)*('Réel 2025'!$C$3:$AO$3=Q$2),'Réel 2025'!$C$8:$AO$500)} -> 74996.15 | R15: =J15-O15 -> 1 | S15: =L15-Q15 -> -57097.64
A16: =+B16&C16 -> Véhicules neufs | B16: =+$K$1 -> Véhicules neufs
A17: =+B17&C17 -> Véhicules neufsFlottes | B17: =+$K$1 -> Véhicules neufs | C17: Flottes | D17: {=+SUMPRODUCT(('Budget original'!$A$8:$A$501=$A17)*('Budget original'!$C$3:$AO$3=D$2),'Budget original'!$C$8:$AO$501)} -> 10 | E17: =IF(D17=0,0,F17/D17) -> 750 | F17: {=+SUMPRODUCT(('Budget original'!$A$8:$A$501=$A17)*('Budget original'!$C$3:$AO$3=F$2),'Budget original'!$C$8:$AO$501)} -> 7500 | J17: =-SUMIFS(BV_Data_An_Cour!$P:$P,BV_Data_An_Cour!$U:$U,$B17,BV_Data_An_Cour!$V:$V,$C17,BV_Data_An_Cour!$W:$W,J$2) -> 17 | K17: =IF(J17=0,0,L17/J17) -> 2339.4729 | L17: =-SUMIFS(BV_Data_An_Cour!$P:$P,BV_Data_An_Cour!$U:$U,$B17,BV_Data_An_Cour!$V:$V,$C17,BV_Data_An_Cour!$W:$W,L$2) -> 39771.04 | M17: =J17-D17 -> 7 | N17: =L17-F17 -> 32271.04 | O17: {=+SUMPRODUCT(('Réel 2025'!$A$8:$A$500=$A17)*('Réel 2025'!$C$3:$AO$3=O$2),'Réel 2025'!$C$8:$AO$500)} -> 0 | P17: =IF(O17=0,0,Q17/O17) -> 0 | Q17: {=+SUMPRODUCT(('Réel 2025'!$A$8:$A$500=$A17)*('Réel 2025'!$C$3:$AO$3=Q$2),'Réel 2025'!$C$8:$AO$500)} -> 0 | R17: =J17-O17 -> 17 | S17: =L17-Q17 -> 39771.04 | V17: -9 unités fleet Maxim
A18: =+B18&C18 -> Véhicules neufs | B18: =+$K$1 -> Véhicules neufs
B19: =+$K$1 -> Véhicules neufs
A20: =+B20&C20 -> Véhicules neufs | B20: =+$K$1 -> Véhicules neufs
A21: =+B21&C21 -> Véhicules neufsRev. Finances | B21: =+$K$1 -> Véhicules neufs | C21: Rev. Finances | E21: =IF(D13=0,0,F21/(D13+D15)) -> 7 | F21: {=+SUMPRODUCT(('Budget original'!$A$8:$A$501=$A21)*('Budget original'!$C$3:$AO$3=F$2),'Budget original'!$C$8:$AO$501)} -> 1204 | K21: =IF(J13=0,0,L21/(J13+J15)) -> 28.668973 | L21: =-SUMIFS(BV_Data_An_Cour!$P:$P,BV_Data_An_Cour!$U:$U,$B21,BV_Data_An_Cour!$V:$V,$C21,BV_Data_An_Cour!$W:$W,L$2) -> 4185.67 | N21: =L21-F21 -> 2981.67 | P21: =IF(O13=0,0,Q21/(O13+O15)) -> 24.586294 | Q21: {=+SUMPRODUCT(('Réel 2025'!$A$8:$A$500=$A21)*('Réel 2025'!$C$3:$AO$3=Q$2),'Réel 2025'!$C$8:$AO$500)} -> 3515.84 | R21: =O21-K21 -> -28.668973 | S21: =L21-Q21 -> 669.83
A22: =+B22&C22 -> Véhicules neufsRev. Protections | B22: =+$K$1 -> Véhicules neufs | C22: Rev. Protections | E22: =IF(D13=0,0,F22/(D13+D15)) -> 1150 | F22: {=+SUMPRODUCT(('Budget original'!$A$8:$A$501=$A22)*('Budget original'!$C$3:$AO$3=F$2),'Budget original'!$C$8:$AO$501)} -> 197800 | K22: =IF(J13=0,0,L22/(J13+J15)) -> 696.18644 | L22: =-SUMIFS(BV_Data_An_Cour!$P:$P,BV_Data_An_Cour!$U:$U,$B22,BV_Data_An_Cour!$V:$V,$C22,BV_Data_An_Cour!$W:$W,L$2) -> 101643.22 | N22: =L22-F22 -> -96156.78 | P22: =IF(O13=0,0,Q22/(O13+O15)) -> 1280.4615 | Q22: {=+SUMPRODUCT(('Réel 2025'!$A$8:$A$500=$A22)*('Réel 2025'!$C$3:$AO$3=Q$2),'Réel 2025'!$C$8:$AO$500)} -> 183106 | R22: =O22-K22 -> -696.18644 | S22: =L22-Q22 -> -81462.78
A23: =+B23&C23 -> Véhicules neufsRev. Autres | B23: =+$K$1 -> Véhicules neufs | C23: Rev. Autres | E23: =IF(D13=0,0,F23/(D13+D15)) -> 443 | F23: {=+SUMPRODUCT(('Budget original'!$A$8:$A$501=$A23)*('Budget original'!$C$3:$AO$3=F$2),'Budget original'!$C$8:$AO$501)} -> 76196 | K23: =IF(J13=0,0,L23/(J13+J15)) -> 470.32781 | L23: =-SUMIFS(BV_Data_An_Cour!$P:$P,BV_Data_An_Cour!$U:$U,$B23,BV_Data_An_Cour!$V:$V,$C23,BV_Data_An_Cour!$W:$W,L$2) -> 68667.86 | N23: =L23-F23 -> -7528.14 | P23: =IF(O13=0,0,Q23/(O13+O15)) -> 680.62895 | Q23: {=+SUMPRODUCT(('Réel 2025'!$A$8:$A$500=$A23)*('Réel 2025'!$C$3:$AO$3=Q$2),'Réel 2025'!$C$8:$AO$500)} -> 97329.94 | R23: =O23-K23 -> -470.32781 | S23: =L23-Q23 -> -28662.08
A24: =+B24&C24 -> Véhicules neufsTotal F&I | B24: =+$K$1 -> Véhicules neufs | C24: Total F&I | D24: =+D15+D13 -> 172 | E24: =IF(D24<=0,0,F24/D24) -> 1600 | F24: =F21+F22+F23 -> 275200 | J24: =+J15+J13 -> 146 | K24: =IF(J24<=0,0,L24/J24) -> 1195.1832 | L24: =L21+L22+L23 -> 174496.75 | M24: =J24-D24 -> -26 | N24: =L24-F24 -> -100703.25 | O24: =+O15+O13 -> 143 | P24: =IF(O24<=0,0,Q24/O24) -> 1985.6768 | Q24: =Q21+Q22+Q23 -> 283951.78 | S24: =L24-Q24 -> -109455.03
A25: =+B25&C25 -> Véhicules neufs | B25: =+$K$1 -> Véhicules neufs | N25: =IF(N24=0,0,N24/F24) -> -0.36592751 | S25: =IF(Q24=0,0,(S24/Q24)) -> -0.38547048
A26: =+B26&C26 -> Véhicules neufs | B26: =+$K$1 -> Véhicules neufs
A27: =+B27&C27 -> Véhicules neufsTotal Dépt. Neufs | B27: =+$K$1 -> Véhicules neufs | C27: Total Dépt. Neufs | D27: =+D13+D15+D17 -> 182 | E27: =IF(D27<=0,0,F27/D27) -> 5092.9438 | F27: =F13+F17+F24+F15 -> 926915.76 | J27: =+J13+J15+J17 -> 163 | K27: =IF(J27<=0,0,L27/J27) -> 4720.7626 | L27: =L13+L17+L24+L15 -> 769484.31 | M27: =J27-D27 -> -19 | N27: =L27-F27 -> -157431.45 | O27: =+O13+O15+O17 -> 143 | P27: =IF(O27<=0,0,Q27/O27) -> 6194.0267 | Q27: =Q13+Q17+Q24+Q15 -> 885745.82 | R27: =J27-O27 -> 20 | S27: =L27-Q27 -> -116261.51
A28: =+B28&C28 -> Véhicules neufs | B28: =+$K$1 -> Véhicules neufs | M28: =M27/D27 -> -0.1043956 | N28: =N27/F27 -> -0.1698444 | R28: =R27/O27 -> 0.13986014 | S28: =IF(Q27=0,0,S27/Q27) -> -0.13125832
A29: =+B29&C29 -> Véhicules neufs | B29: =+$K$1 -> Véhicules neufs
A30: =+B30&C30 -> Véhicules neufsDEPENSES | B30: =+$K$1 -> Véhicules neufs | C30: DEPENSES
A31: =+B31&C31 -> Véhicules neufsComm. vendeurs | B31: =+$K$1 -> Véhicules neufs | C31: Comm. vendeurs | E31: =F31/D$24 -> 1049.7241 | F31: {=+SUMPRODUCT(('Budget original'!$A$8:$A$501=$A31)*('Budget original'!$C$3:$AO$3=F$2),'Budget original'!$C$8:$AO$501)} -> 180552.55 | J31: =L31/(L13+L15) -> 0.29512049 | K31: =IF(L31=0,0,L31/J$24) -> 1122.2998 | L31: =SUMIFS(BV_Data_An_Cour!$P:$P,BV_Data_An_Cour!$U:$U,$B31,BV_Data_An_Cour!$V:$V,$C31,BV_Data_An_Cour!$W:$W,L$2) -> 163855.77 | N31: =L31-F31 -> -16696.776 | P31: =Q31/O$24 -> 1077.8079 | Q31: {=+SUMPRODUCT(('Réel 2025'!$A$8:$A$500=$A31)*('Réel 2025'!$C$3:$AO$3=Q$2),'Réel 2025'!$C$8:$AO$500)} -> 154126.53 | S31: =L31-Q31 -> 9729.24
A32: =+B32&C32 -> Véhicules neufsComm. F&I | B32: =+$K$1 -> Véhicules neufs | C32: Comm. F&I | E32: =F32/D$24 -> 488 | F32: {=+SUMPRODUCT(('Budget original'!$A$8:$A$501=$A32)*('Budget original'!$C$3:$AO$3=F$2),'Budget original'!$C$8:$AO$501)} -> 83936 | J32: =L32/L24 -> 0.25958661 | K32: =IF(L32=0,0,L32/J$24) -> 310.25356 | L32: =SUMIFS(BV_Data_An_Cour!$P:$P,BV_Data_An_Cour!$U:$U,$B32,BV_Data_An_Cour!$V:$V,$C32,BV_Data_An_Cour!$W:$W,L$2) -> 45297.02 | N32: =L32-F32 -> -38638.98 | P32: =Q32/O$24 -> 616.53706 | Q32: {=+SUMPRODUCT(('Réel 2025'!$A$8:$A$500=$A32)*('Réel 2025'!$C$3:$AO$3=Q$2),'Réel 2025'!$C$8:$AO$500)} -> 88164.8 | S32: =L32-Q32 -> -42867.78
A33: =+B33&C33 -> Véhicules neufsFrais de livraison | B33: =+$K$1 -> Véhicules neufs | C33: Frais de livraison | E33: =F33/D$24 -> 120 | F33: {=+SUMPRODUCT(('Budget original'!$A$8:$A$501=$A33)*('Budget original'!$C$3:$AO$3=F$2),'Budget original'!$C$8:$AO$501)} -> 20640 | K33: =IF(L33=0,0,L33/J$24) -> 145.29808 | L33: =SUMIFS(BV_Data_An_Cour!$P:$P,BV_Data_An_Cour!$U:$U,$B33,BV_Data_An_Cour!$V:$V,$C33,BV_Data_An_Cour!$W:$W,L$2) -> 21213.52 | N33: =L33-F33 -> 573.52 | P33: =Q33/O$24 -> 98.698322 | Q33: {=+SUMPRODUCT(('Réel 2025'!$A$8:$A$500=$A33)*('Réel 2025'!$C$3:$AO$3=Q$2),'Réel 2025'!$C$8:$AO$500)} -> 14113.86 | S33: =L33-Q33 -> 7099.66
A34: =+B34&C34 -> Véhicules neufsService gratuit 1 | B34: =+$K$1 -> Véhicules neufs | C34: Service gratuit 1 | E34: =F34/D$24 -> 35 | F34: {=+SUMPRODUCT(('Budget original'!$A$8:$A$501=$A34)*('Budget original'!$C$3:$AO$3=F$2),'Budget original'!$C$8:$AO$501)} -> 6020 | K34: =IF(L34=0,0,L34/J$24) -> 45.968288 | L34: =SUMIFS(BV_Data_An_Cour!$P:$P,BV_Data_An_Cour!$U:$U,$B34,BV_Data_An_Cour!$V:$V,$C34,BV_Data_An_Cour!$W:$W,L$2) -> 6711.37 | N34: =L34-F34 -> 691.37 | P34: =Q34/O$24 -> 31.451608 | Q34: {=+SUMPRODUCT(('Réel 2025'!$A$8:$A$500=$A34)*('Réel 2025'!$C$3:$AO$3=Q$2),'Réel 2025'!$C$8:$AO$500)} -> 4497.58 | S34: =L34-Q34 -> 2213.79
A35: =+B35&C35 -> Véhicules neufsEntretien stock | B35: =+$K$1 -> Véhicules neufs | C35: Entretien stock | E35: =F35/D$24 -> 97.244186 | F35: {=+SUMPRODUCT(('Budget original'!$A$8:$A$501=$A35)*('Budget original'!$C$3:$AO$3=F$2),'Budget original'!$C$8:$AO$501)} -> 16726 | K35: =IF(L35=0,0,L35/J$24) -> 112.72801 | L35: =SUMIFS(BV_Data_An_Cour!$P:$P,BV_Data_An_Cour!$U:$U,$B35,BV_Data_An_Cour!$V:$V,$C35,BV_Data_An_Cour!$W:$W,L$2) -> 16458.29 | N35: =L35-F35 -> -267.71 | P35: =Q35/O$24 -> 67.835175 | Q35: {=+SUMPRODUCT(('Réel 2025'!$A$8:$A$500=$A35)*('Réel 2025'!$C$3:$AO$3=Q$2),'Réel 2025'!$C$8:$AO$500)} -> 9700.43 | S35: =L35-Q35 -> 6757.86
A36: =+B36&C36 -> Véhicules neufsPublicité 1 | B36: =+$K$1 -> Véhicules neufs | C36: Publicité 1 | E36: =F36/D$24 -> 234.88788 | F36: {=+SUMPRODUCT(('Budget original'!$A$8:$A$501=$A36)*('Budget original'!$C$3:$AO$3=F$2),'Budget original'!$C$8:$AO$501)} -> 40400.715 | K36: =IF(L36=0,0,L36/J$24) -> 200.45459 | L36: =SUMIFS(BV_Data_An_Cour!$P:$P,BV_Data_An_Cour!$U:$U,$B36,BV_Data_An_Cour!$V:$V,$C36,BV_Data_An_Cour!$W:$W,L$2) -> 29266.37 | N36: =L36-F36 -> -11134.345 | P36: =Q36/O$24 -> 560.01084 | Q36: {=+SUMPRODUCT(('Réel 2025'!$A$8:$A$500=$A36)*('Réel 2025'!$C$3:$AO$3=Q$2),'Réel 2025'!$C$8:$AO$500)} -> 80081.55 | S36: =L36-Q36 -> -50815.18
A37: =+B37&C37 -> Véhicules neufsIntérêt de gros | B37: =+$K$1 -> Véhicules neufs | C37: Intérêt de gros | E37: =F37/D$24 -> 790.44912 | F37: {=+SUMPRODUCT(('Budget original'!$A$8:$A$501=$A37)*('Budget original'!$C$3:$AO$3=F$2),'Budget original'!$C$8:$AO$501)} -> 135957.25 | K37: =IF(L37=0,0,L37/J$24) -> 856.32993 | L37: =SUMIFS(BV_Data_An_Cour!$P:$P,BV_Data_An_Cour!$U:$U,$B37,BV_Data_An_Cour!$V:$V,$C37,BV_Data_An_Cour!$W:$W,L$2) -> 125024.17 | N37: =L37-F37 -> -10933.079 | P37: =Q37/O$24 -> 995.17364 | Q37: {=+SUMPRODUCT(('Réel 2025'!$A$8:$A$500=$A37)*('Réel 2025'!$C$3:$AO$3=Q$2),'Réel 2025'!$C$8:$AO$500)} -> 142309.83 | S37: =L37-Q37 -> -17285.66
A38: =+B38&C38 -> Véhicules neufs[...] | B38: =+$K$1 -> Véhicules neufs | C38: [...] | E38: =F38/D$24 -> 0 | F38: {=+SUMPRODUCT(('Budget original'!$A$8:$A$501=$A38)*('Budget original'!$C$3:$AO$3=F$2),'Budget original'!$C$8:$AO$501)} -> 0 | K38: =IF(L38=0,0,L38/J$24) -> 0 | L38: =SUMIFS(BV_Data_An_Cour!$P:$P,BV_Data_An_Cour!$U:$U,$B38,BV_Data_An_Cour!$V:$V,$C38,BV_Data_An_Cour!$W:$W,L$2) -> 0 | N38: =L38-F38 -> 0 | P38: =Q38/O$24 -> 0 | Q38: {=+SUMPRODUCT(('Réel 2025'!$A$8:$A$500=$A38)*('Réel 2025'!$C$3:$AO$3=Q$2),'Réel 2025'!$C$8:$AO$500)} -> 0 | S38: =L38-Q38 -> 0
A39: =+B39&C39 -> Véhicules neufs[...] | B39: =+$K$1 -> Véhicules neufs | C39: [...] | E39: =F39/D$24 -> 0 | F39: {=+SUMPRODUCT(('Budget original'!$A$8:$A$501=$A39)*('Budget original'!$C$3:$AO$3=F$2),'Budget original'!$C$8:$AO$501)} -> 0 | K39: =IF(L39=0,0,L39/J$24) -> 0 | L39: =SUMIFS(BV_Data_An_Cour!$P:$P,BV_Data_An_Cour!$U:$U,$B39,BV_Data_An_Cour!$V:$V,$C39,BV_Data_An_Cour!$W:$W,L$2) -> 0 | N39: =L39-F39 -> 0 | P39: =Q39/O$24 -> 0 | Q39: {=+SUMPRODUCT(('Réel 2025'!$A$8:$A$500=$A39)*('Réel 2025'!$C$3:$AO$3=Q$2),'Réel 2025'!$C$8:$AO$500)} -> 0 | S39: =L39-Q39 -> 0
A40: =+B40&C40 -> Véhicules neufs[...] | B40: =+$K$1 -> Véhicules neufs | C40: [...] | E40: =F40/D$24 -> 0 | F40: {=+SUMPRODUCT(('Budget original'!$A$8:$A$501=$A40)*('Budget original'!$C$3:$AO$3=F$2),'Budget original'!$C$8:$AO$501)} -> 0 | K40: =IF(L40=0,0,L40/J$24) -> 0 | L40: =SUMIFS(BV_Data_An_Cour!$P:$P,BV_Data_An_Cour!$U:$U,$B40,BV_Data_An_Cour!$V:$V,$C40,BV_Data_An_Cour!$W:$W,L$2) -> 0 | N40: =L40-F40 -> 0 | P40: =Q40/O$24 -> 0 | Q40: {=+SUMPRODUCT(('Réel 2025'!$A$8:$A$500=$A40)*('Réel 2025'!$C$3:$AO$3=Q$2),'Réel 2025'!$C$8:$AO$500)} -> 0 | S40: =L40-Q40 -> 0
A41: =+B41&C41 -> Véhicules neufsTOTAL VARIABLES | B41: =+$K$1 -> Véhicules neufs | C41: TOTAL VARIABLES | D41: % brut | E41: =F41/F$27 -> 0.52241264 | F41: =SUM(F31:F40) -> 484232.51 | J41: % brut | K41: =L41/L$27 -> 0.52999977 | L41: =SUM(L31:L40) -> 407826.51 | N41: =L41-F41 -> -76406 | O41: % brut | P41: =Q41/Q$27 -> 0.55658697 | Q41: =SUM(Q31:Q40) -> 492994.58 | S41: =L41-Q41 -> -85168.07
A42: =+B42&C42 -> Véhicules neufsSalaires cadres | B42: =+$K$1 -> Véhicules neufs | C42: Salaires cadres | F42: {=+SUMPRODUCT(('Budget original'!$A$8:$A$501=$A42)*('Budget original'!$C$3:$AO$3=F$2),'Budget original'!$C$8:$AO$501)} -> 74927.027 | L42: =SUMIFS(BV_Data_An_Cour!$P:$P,BV_Data_An_Cour!$U:$U,$B42,BV_Data_An_Cour!$V:$V,$C42,BV_Data_An_Cour!$W:$W,L$2) -> 58826.38 | N42: =L42-F42 -> -16100.647 | Q42: {=+SUMPRODUCT(('Réel 2025'!$A$8:$A$500=$A42)*('Réel 2025'!$C$3:$AO$3=Q$2),'Réel 2025'!$C$8:$AO$500)} -> 80768.86
A43: =+B43&C43 -> Véhicules neufsSalaires commis | B43: =+$K$1 -> Véhicules neufs | C43: Salaires commis | F43: {=+SUMPRODUCT(('Budget original'!$A$8:$A$501=$A43)*('Budget original'!$C$3:$AO$3=F$2),'Budget original'!$C$8:$AO$501)} -> 30086.819 | L43: =SUMIFS(BV_Data_An_Cour!$P:$P,BV_Data_An_Cour!$U:$U,$B43,BV_Data_An_Cour!$V:$V,$C43,BV_Data_An_Cour!$W:$W,L$2) -> 27120.48 | N43: =L43-F43 -> -2966.3393 | Q43: {=+SUMPRODUCT(('Réel 2025'!$A$8:$A$500=$A43)*('Réel 2025'!$C$3:$AO$3=Q$2),'Réel 2025'!$C$8:$AO$500)} -> 56669.27 | S43: =L43-Q43 -> -29548.79
A44: =+B44&C44 -> Véhicules neufsSalaires autres | B44: =+$K$1 -> Véhicules neufs | C44: Salaires autres | F44: {=+SUMPRODUCT(('Budget original'!$A$8:$A$501=$A44)*('Budget original'!$C$3:$AO$3=F$2),'Budget original'!$C$8:$AO$501)} -> 0 | L44: =SUMIFS(BV_Data_An_Cour!$P:$P,BV_Data_An_Cour!$U:$U,$B44,BV_Data_An_Cour!$V:$V,$C44,BV_Data_An_Cour!$W:$W,L$2) -> 520 | N44: =L44-F44 -> 520 | Q44: {=+SUMPRODUCT(('Réel 2025'!$A$8:$A$500=$A44)*('Réel 2025'!$C$3:$AO$3=Q$2),'Réel 2025'!$C$8:$AO$500)} -> 2052 | S44: =L44-Q44 -> -1532
A45: =+B45&C45 -> Véhicules neufsSalaires spécialistes | B45: =+$K$1 -> Véhicules neufs | C45: Salaires spécialistes | F45: {=+SUMPRODUCT(('Budget original'!$A$8:$A$501=$A45)*('Budget original'!$C$3:$AO$3=F$2),'Budget original'!$C$8:$AO$501)} -> 0 | L45: =SUMIFS(BV_Data_An_Cour!$P:$P,BV_Data_An_Cour!$U:$U,$B45,BV_Data_An_Cour!$V:$V,$C45,BV_Data_An_Cour!$W:$W,L$2) -> 0 | N45: =L45-F45 -> 0 | Q45: {=+SUMPRODUCT(('Réel 2025'!$A$8:$A$500=$A45)*('Réel 2025'!$C$3:$AO$3=Q$2),'Réel 2025'!$C$8:$AO$500)} -> 0 | S45: =L45-Q45 -> 0
A46: =+B46&C46 -> Véhicules neufs[...] | B46: =+$K$1 -> Véhicules neufs | C46: [...] | F46: {=+SUMPRODUCT(('Budget original'!$A$8:$A$501=$A46)*('Budget original'!$C$3:$AO$3=F$2),'Budget original'!$C$8:$AO$501)} -> 0 | L46: =SUMIFS(BV_Data_An_Cour!$P:$P,BV_Data_An_Cour!$U:$U,$B46,BV_Data_An_Cour!$V:$V,$C46,BV_Data_An_Cour!$W:$W,L$2) -> 0 | N46: =L46-F46 -> 0 | Q46: {=+SUMPRODUCT(('Réel 2025'!$A$8:$A$500=$A46)*('Réel 2025'!$C$3:$AO$3=Q$2),'Réel 2025'!$C$8:$AO$500)} -> 0 | S46: =L46-Q46 -> 0
A47: =+B47&C47 -> Véhicules neufs[...] | B47: =+$K$1 -> Véhicules neufs | C47: [...] | F47: {=+SUMPRODUCT(('Budget original'!$A$8:$A$501=$A47)*('Budget original'!$C$3:$AO$3=F$2),'Budget original'!$C$8:$AO$501)} -> 0 | L47: =SUMIFS(BV_Data_An_Cour!$P:$P,BV_Data_An_Cour!$U:$U,$B47,BV_Data_An_Cour!$V:$V,$C47,BV_Data_An_Cour!$W:$W,L$2) -> 0 | N47: =L47-F47 -> 0 | Q47: {=+SUMPRODUCT(('Réel 2025'!$A$8:$A$500=$A47)*('Réel 2025'!$C$3:$AO$3=Q$2),'Réel 2025'!$C$8:$AO$500)} -> 0 | S47: =L47-Q47 -> 0
A48: =+B48&C48 -> Véhicules neufs[...] | B48: =+$K$1 -> Véhicules neufs | C48: [...] | F48: {=+SUMPRODUCT(('Budget original'!$A$8:$A$501=$A48)*('Budget original'!$C$3:$AO$3=F$2),'Budget original'!$C$8:$AO$501)} -> 0 | L48: =SUMIFS(BV_Data_An_Cour!$P:$P,BV_Data_An_Cour!$U:$U,$B48,BV_Data_An_Cour!$V:$V,$C48,BV_Data_An_Cour!$W:$W,L$2) -> 0 | N48: =L48-F48 -> 0 | Q48: {=+SUMPRODUCT(('Réel 2025'!$A$8:$A$500=$A48)*('Réel 2025'!$C$3:$AO$3=Q$2),'Réel 2025'!$C$8:$AO$500)} -> 0 | S48: =L48-Q48 -> 0
A49: =+B49&C49 -> Véhicules neufsSalaires en absences | B49: =+$K$1 -> Véhicules neufs | C49: Salaires en absences | F49: {=+SUMPRODUCT(('Budget original'!$A$8:$A$501=$A49)*('Budget original'!$C$3:$AO$3=F$2),'Budget original'!$C$8:$AO$501)} -> 51391.94 | L49: =SUMIFS(BV_Data_An_Cour!$P:$P,BV_Data_An_Cour!$U:$U,$B49,BV_Data_An_Cour!$V:$V,$C49,BV_Data_An_Cour!$W:$W,L$2) -> 38007.3 | N49: =L49-F49 -> -13384.64 | Q49: {=+SUMPRODUCT(('Réel 2025'!$A$8:$A$500=$A49)*('Réel 2025'!$C$3:$AO$3=Q$2),'Réel 2025'!$C$8:$AO$500)} -> 53348.57 | S49: =L49-Q49 -> -15341.27
A50: =+B50&C50 -> Véhicules neufsDéduction à la source | B50: =+$K$1 -> Véhicules neufs | C50: Déduction à la source | F50: {=+SUMPRODUCT(('Budget original'!$A$8:$A$501=$A50)*('Budget original'!$C$3:$AO$3=F$2),'Budget original'!$C$8:$AO$501)} -> 55255.513 | L50: =SUMIFS(BV_Data_An_Cour!$P:$P,BV_Data_An_Cour!$U:$U,$B50,BV_Data_An_Cour!$V:$V,$C50,BV_Data_An_Cour!$W:$W,L$2) -> 46313.34 | N50: =L50-F50 -> -8942.1727 | Q50: {=+SUMPRODUCT(('Réel 2025'!$A$8:$A$500=$A50)*('Réel 2025'!$C$3:$AO$3=Q$2),'Réel 2025'!$C$8:$AO$500)} -> 68845.9 | S50: =L50-Q50 -> -22532.56
A51: =+B51&C51 -> Véhicules neufsBénéfices marginaux | B51: =+$K$1 -> Véhicules neufs | C51: Bénéfices marginaux | F51: {=+SUMPRODUCT(('Budget original'!$A$8:$A$501=$A51)*('Budget original'!$C$3:$AO$3=F$2),'Budget original'!$C$8:$AO$501)} -> 35813.758 | L51: =SUMIFS(BV_Data_An_Cour!$P:$P,BV_Data_An_Cour!$U:$U,$B51,BV_Data_An_Cour!$V:$V,$C51,BV_Data_An_Cour!$W:$W,L$2) -> 23249.74 | N51: =L51-F51 -> -12564.018 | Q51: {=+SUMPRODUCT(('Réel 2025'!$A$8:$A$500=$A51)*('Réel 2025'!$C$3:$AO$3=Q$2),'Réel 2025'!$C$8:$AO$500)} -> 28076.89 | S51: =L51-Q51 -> -4827.15
A52: =+B52&C52 -> Véhicules neufsCsst | B52: =+$K$1 -> Véhicules neufs | C52: Csst | F52: {=+SUMPRODUCT(('Budget original'!$A$8:$A$501=$A52)*('Budget original'!$C$3:$AO$3=F$2),'Budget original'!$C$8:$AO$501)} -> 10027.852 | L52: =SUMIFS(BV_Data_An_Cour!$P:$P,BV_Data_An_Cour!$U:$U,$B52,BV_Data_An_Cour!$V:$V,$C52,BV_Data_An_Cour!$W:$W,L$2) -> 7398.43 | N52: =L52-F52 -> -2629.4223 | Q52: {=+SUMPRODUCT(('Réel 2025'!$A$8:$A$500=$A52)*('Réel 2025'!$C$3:$AO$3=Q$2),'Réel 2025'!$C$8:$AO$500)} -> 11031.02 | S52: =L52-Q52 -> -3632.59
A53: =+B53&C53 -> Véhicules neufs[...] | B53: =+$K$1 -> Véhicules neufs | C53: [...] | F53: {=+SUMPRODUCT(('Budget original'!$A$8:$A$501=$A53)*('Budget original'!$C$3:$AO$3=F$2),'Budget original'!$C$8:$AO$501)} -> 0 | L53: =SUMIFS(BV_Data_An_Cour!$P:$P,BV_Data_An_Cour!$U:$U,$B53,BV_Data_An_Cour!$V:$V,$C53,BV_Data_An_Cour!$W:$W,L$2) -> 0 | N53: =L53-F53 -> 0 | Q53: {=+SUMPRODUCT(('Réel 2025'!$A$8:$A$500=$A53)*('Réel 2025'!$C$3:$AO$3=Q$2),'Réel 2025'!$C$8:$AO$500)} -> 0 | S53: =L53-Q53 -> 0
A54: =+B54&C54 -> Véhicules neufsTOTAL PERSONNEL | B54: =+$K$1 -> Véhicules neufs | C54: TOTAL PERSONNEL | D54: % brut | E54: =F54/F$27 -> 0.27780616 | F54: =+SUM(F42:F53) -> 257502.91 | J54: % brut | K54: =L54/L$27 -> 0.26178009 | L54: =+SUM(L42:L53) -> 201435.67 | N54: =+SUM(N42:N53) -> -56067.24 | O54: % brut | P54: =Q54/Q$27 -> 0.33959236 | Q54: =+SUM(Q42:Q53) -> 300792.51 | S54: =+SUM(S42:S53) -> -77414.36
A55: =+B55&C55 -> Véhicules neufsPublicité 2 | B55: =+$K$1 -> Véhicules neufs | C55: Publicité 2 | F55: {=+SUMPRODUCT(('Budget original'!$A$8:$A$501=$A55)*('Budget original'!$C$3:$AO$3=F$2),'Budget original'!$C$8:$AO$501)} -> 0 | L55: =SUMIFS(BV_Data_An_Cour!$P:$P,BV_Data_An_Cour!$U:$U,$B55,BV_Data_An_Cour!$V:$V,$C55,BV_Data_An_Cour!$W:$W,L$2) -> 0 | N55: =L55-F55 -> 0 | Q55: {=+SUMPRODUCT(('Réel 2025'!$A$8:$A$500=$A55)*('Réel 2025'!$C$3:$AO$3=Q$2),'Réel 2025'!$C$8:$AO$500)} -> 0 | S55: =L55-Q55 -> 0
A56: =+B56&C56 -> Véhicules neufsService gratuit 2 | B56: =+$K$1 -> Véhicules neufs | C56: Service gratuit 2 | F56: {=+SUMPRODUCT(('Budget original'!$A$8:$A$501=$A56)*('Budget original'!$C$3:$AO$3=F$2),'Budget original'!$C$8:$AO$501)} -> 0 | L56: =SUMIFS(BV_Data_An_Cour!$P:$P,BV_Data_An_Cour!$U:$U,$B56,BV_Data_An_Cour!$V:$V,$C56,BV_Data_An_Cour!$W:$W,L$2) -> 0 | N56: =L56-F56 -> 0 | Q56: {=+SUMPRODUCT(('Réel 2025'!$A$8:$A$500=$A56)*('Réel 2025'!$C$3:$AO$3=Q$2),'Réel 2025'!$C$8:$AO$500)} -> 0 | S56: =L56-Q56 -> 0
A57: =+B57&C57 -> Véhicules neufsFrais véhicules de cie | B57: =+$K$1 -> Véhicules neufs | C57: Frais véhicules de cie | F57: {=+SUMPRODUCT(('Budget original'!$A$8:$A$501=$A57)*('Budget original'!$C$3:$AO$3=F$2),'Budget original'!$C$8:$AO$501)} -> 12219 | L57: =SUMIFS(BV_Data_An_Cour!$P:$P,BV_Data_An_Cour!$U:$U,$B57,BV_Data_An_Cour!$V:$V,$C57,BV_Data_An_Cour!$W:$W,L$2) -> 8217.78 | N57: =L57-F57 -> -4001.22 | Q57: {=+SUMPRODUCT(('Réel 2025'!$A$8:$A$500=$A57)*('Réel 2025'!$C$3:$AO$3=Q$2),'Réel 2025'!$C$8:$AO$500)} -> 48671.18 | S57: =L57-Q57 -> -40453.4
A58: =+B58&C58 -> Véhicules neufsInformatique | B58: =+$K$1 -> Véhicules neufs | C58: Informatique | F58: {=+SUMPRODUCT(('Budget original'!$A$8:$A$501=$A58)*('Budget original'!$C$3:$AO$3=F$2),'Budget original'!$C$8:$AO$501)} -> 55172.113 | L58: =SUMIFS(BV_Data_An_Cour!$P:$P,BV_Data_An_Cour!$U:$U,$B58,BV_Data_An_Cour!$V:$V,$C58,BV_Data_An_Cour!$W:$W,L$2) -> 54437.51 | N58: =L58-F58 -> -734.603 | Q58: {=+SUMPRODUCT(('Réel 2025'!$A$8:$A$500=$A58)*('Réel 2025'!$C$3:$AO$3=Q$2),'Réel 2025'!$C$8:$AO$500)} -> 30520.43 | S58: =L58-Q58 -> 23917.08
A59: =+B59&C59 -> Véhicules neufsFrais de déplacement | B59: =+$K$1 -> Véhicules neufs | C59: Frais de déplacement | F59: {=+SUMPRODUCT(('Budget original'!$A$8:$A$501=$A59)*('Budget original'!$C$3:$AO$3=F$2),'Budget original'!$C$8:$AO$501)} -> 7980 | L59: =SUMIFS(BV_Data_An_Cour!$P:$P,BV_Data_An_Cour!$U:$U,$B59,BV_Data_An_Cour!$V:$V,$C59,BV_Data_An_Cour!$W:$W,L$2) -> 12885.05 | N59: =L59-F59 -> 4905.05 | Q59: {=+SUMPRODUCT(('Réel 2025'!$A$8:$A$500=$A59)*('Réel 2025'!$C$3:$AO$3=Q$2),'Réel 2025'!$C$8:$AO$500)} -> 4995.91 | S59: =L59-Q59 -> 7889.14
A60: =+B60&C60 -> Véhicules neufsServices extérieurs | B60: =+$K$1 -> Véhicules neufs | C60: Services extérieurs | F60: {=+SUMPRODUCT(('Budget original'!$A$8:$A$501=$A60)*('Budget original'!$C$3:$AO$3=F$2),'Budget original'!$C$8:$AO$501)} -> 16034.162 | L60: =SUMIFS(BV_Data_An_Cour!$P:$P,BV_Data_An_Cour!$U:$U,$B60,BV_Data_An_Cour!$V:$V,$C60,BV_Data_An_Cour!$W:$W,L$2) -> 19024.86 | N60: =L60-F60 -> 2990.698 | Q60: {=+SUMPRODUCT(('Réel 2025'!$A$8:$A$500=$A60)*('Réel 2025'!$C$3:$AO$3=Q$2),'Réel 2025'!$C$8:$AO$500)} -> 20600.25 | S60: =L60-Q60 -> -1575.39
A61: =+B61&C61 -> Véhicules neufsFournitures autres | B61: =+$K$1 -> Véhicules neufs | C61: Fournitures autres | F61: {=+SUMPRODUCT(('Budget original'!$A$8:$A$501=$A61)*('Budget original'!$C$3:$AO$3=F$2),'Budget original'!$C$8:$AO$501)} -> 450 | L61: =SUMIFS(BV_Data_An_Cour!$P:$P,BV_Data_An_Cour!$U:$U,$B61,BV_Data_An_Cour!$V:$V,$C61,BV_Data_An_Cour!$W:$W,L$2) -> 657.25 | N61: =L61-F61 -> 207.25 | Q61: {=+SUMPRODUCT(('Réel 2025'!$A$8:$A$500=$A61)*('Réel 2025'!$C$3:$AO$3=Q$2),'Réel 2025'!$C$8:$AO$500)} -> 265.93 | S61: =L61-Q61 -> 391.32
A62: =+B62&C62 -> Véhicules neufsUniformes | B62: =+$K$1 -> Véhicules neufs | C62: Uniformes | F62: {=+SUMPRODUCT(('Budget original'!$A$8:$A$501=$A62)*('Budget original'!$C$3:$AO$3=F$2),'Budget original'!$C$8:$AO$501)} -> 180 | L62: =SUMIFS(BV_Data_An_Cour!$P:$P,BV_Data_An_Cour!$U:$U,$B62,BV_Data_An_Cour!$V:$V,$C62,BV_Data_An_Cour!$W:$W,L$2) -> 74.1 | N62: =L62-F62 -> -105.9 | Q62: {=+SUMPRODUCT(('Réel 2025'!$A$8:$A$500=$A62)*('Réel 2025'!$C$3:$AO$3=Q$2),'Réel 2025'!$C$8:$AO$500)} -> 359.91 | S62: =L62-Q62 -> -285.81
A63: =+B63&C63 -> Véhicules neufsPapeterie | B63: =+$K$1 -> Véhicules neufs | C63: Papeterie | F63: {=+SUMPRODUCT(('Budget original'!$A$8:$A$501=$A63)*('Budget original'!$C$3:$AO$3=F$2),'Budget original'!$C$8:$AO$501)} -> 3480 | L63: =SUMIFS(BV_Data_An_Cour!$P:$P,BV_Data_An_Cour!$U:$U,$B63,BV_Data_An_Cour!$V:$V,$C63,BV_Data_An_Cour!$W:$W,L$2) -> 3406.71 | N63: =L63-F63 -> -73.29 | Q63: {=+SUMPRODUCT(('Réel 2025'!$A$8:$A$500=$A63)*('Réel 2025'!$C$3:$AO$3=Q$2),'Réel 2025'!$C$8:$AO$500)} -> 3290.76 | S63: =L63-Q63 -> 115.95
A64: =+B64&C64 -> Véhicules neufsTéléphone | B64: =+$K$1 -> Véhicules neufs | C64: Téléphone | F64: {=+SUMPRODUCT(('Budget original'!$A$8:$A$501=$A64)*('Budget original'!$C$3:$AO$3=F$2),'Budget original'!$C$8:$AO$501)} -> 945.6 | L64: =SUMIFS(BV_Data_An_Cour!$P:$P,BV_Data_An_Cour!$U:$U,$B64,BV_Data_An_Cour!$V:$V,$C64,BV_Data_An_Cour!$W:$W,L$2) -> 1345.92 | N64: =L64-F64 -> 400.32 | Q64: {=+SUMPRODUCT(('Réel 2025'!$A$8:$A$500=$A64)*('Réel 2025'!$C$3:$AO$3=Q$2),'Réel 2025'!$C$8:$AO$500)} -> 1978.51 | S64: =L64-Q64 -> -632.59
A65: =+B65&C65 -> Véhicules neufsFrais postaux | B65: =+$K$1 -> Véhicules neufs | C65: Frais postaux | F65: {=+SUMPRODUCT(('Budget original'!$A$8:$A$501=$A65)*('Budget original'!$C$3:$AO$3=F$2),'Budget original'!$C$8:$AO$501)} -> 1360 | L65: =SUMIFS(BV_Data_An_Cour!$P:$P,BV_Data_An_Cour!$U:$U,$B65,BV_Data_An_Cour!$V:$V,$C65,BV_Data_An_Cour!$W:$W,L$2) -> 844.57 | N65: =L65-F65 -> -515.43 | Q65: {=+SUMPRODUCT(('Réel 2025'!$A$8:$A$500=$A65)*('Réel 2025'!$C$3:$AO$3=Q$2),'Réel 2025'!$C$8:$AO$500)} -> 1149.8 | S65: =L65-Q65 -> -305.23
A66: =+B66&C66 -> Véhicules neufsDivers | B66: =+$K$1 -> Véhicules neufs | C66: Divers | F66: {=+SUMPRODUCT(('Budget original'!$A$8:$A$501=$A66)*('Budget original'!$C$3:$AO$3=F$2),'Budget original'!$C$8:$AO$501)} -> 3774.5 | L66: =SUMIFS(BV_Data_An_Cour!$P:$P,BV_Data_An_Cour!$U:$U,$B66,BV_Data_An_Cour!$V:$V,$C66,BV_Data_An_Cour!$W:$W,L$2) -> 3703.91 | N66: =L66-F66 -> -70.59 | Q66: {=+SUMPRODUCT(('Réel 2025'!$A$8:$A$500=$A66)*('Réel 2025'!$C$3:$AO$3=Q$2),'Réel 2025'!$C$8:$AO$500)} -> 5436.22 | S66: =L66-Q66 -> -1732.31
... A68: =+B68&C68 -> Véhicules neufsFrais bancaires | B68: =+$K$1 -> Véhicules neufs | C68: Frais bancaires | F68: {=+SUMPRODUCT(('Budget original'!$A$8:$A$501=$A68)*('Budget original'!$C$3:$AO$3=F$2),'Budget original'!$C$8:$AO$501)} -> 21303.09 | L68: =SUMIFS(BV_Data_An_Cour!$P:$P,BV_Data_An_Cour!$U:$U,$B68,BV_Data_An_Cour!$V:$V,$C68,BV_Data_An_Cour!$W:$W,L$2) -> 16429.02 | N68: =L68-F68 -> -4874.0697 | Q68: {=+SUMPRODUCT(('Réel 2025'!$A$8:$A$500=$A68)*('Réel 2025'!$C$3:$AO$3=Q$2),'Réel 2025'!$C$8:$AO$500)} -> 18010.81 | S68: =L68-Q68 -> -1581.79
A69: =+B69&C69 -> Véhicules neufs[...] | B69: =+$K$1 -> Véhicules neufs | C69: [...] | F69: {=+SUMPRODUCT(('Budget original'!$A$8:$A$501=$A69)*('Budget original'!$C$3:$AO$3=F$2),'Budget original'!$C$8:$AO$501)} -> 0 | N69: =L69-F69 -> 0 | Q69: {=+SUMPRODUCT(('Réel 2025'!$A$8:$A$500=$A69)*('Réel 2025'!$C$3:$AO$3=Q$2),'Réel 2025'!$C$8:$AO$500)} -> 0 | S69: =L69-Q69 -> 0
A70: =+B70&C70 -> Véhicules neufs[...] | B70: =+$K$1 -> Véhicules neufs | C70: [...] | F70: {=+SUMPRODUCT(('Budget original'!$A$8:$A$501=$A70)*('Budget original'!$C$3:$AO$3=F$2),'Budget original'!$C$8:$AO$501)} -> 0 | L70: =SUMIFS(BV_Data_An_Cour!$P:$P,BV_Data_An_Cour!$U:$U,$B70,BV_Data_An_Cour!$V:$V,$C70,BV_Data_An_Cour!$W:$W,L$2) -> 0 | N70: =L70-F70 -> 0 | Q70: {=+SUMPRODUCT(('Réel 2025'!$A$8:$A$500=$A70)*('Réel 2025'!$C$3:$AO$3=Q$2),'Réel 2025'!$C$8:$AO$500)} -> 0 | S70: =L70-Q70 -> 0
A71: =+B71&C71 -> Véhicules neufs[...] | B71: =+$K$1 -> Véhicules neufs | C71: [...] | F71: {=+SUMPRODUCT(('Budget original'!$A$8:$A$501=$A71)*('Budget original'!$C$3:$AO$3=F$2),'Budget original'!$C$8:$AO$501)} -> 0 | L71: =SUMIFS(BV_Data_An_Cour!$P:$P,BV_Data_An_Cour!$U:$U,$B71,BV_Data_An_Cour!$V:$V,$C71,BV_Data_An_Cour!$W:$W,L$2)*0.32 -> 0 | N71: =L71-F71 -> 0 | Q71: {=+SUMPRODUCT(('Réel 2025'!$A$8:$A$500=$A71)*('Réel 2025'!$C$3:$AO$3=Q$2),'Réel 2025'!$C$8:$AO$500)} -> 0 | S71: =L71-Q71 -> 0
A72: =+B72&C72 -> Véhicules neufsTOTAL SEMI-FIXES | B72: =+$K$1 -> Véhicules neufs | C72: TOTAL SEMI-FIXES | D72: % brut | E72: =F72/F$27 -> 0.13467031 | F72: =+SUM(F55:F71) -> 124828.03 | J72: % brut | K72: =L72/L$27 -> 0.15901521 | L72: =+SUM(L55:L71) -> 122359.71 | N72: =+SUM(N55:N71) -> -2468.3227 | O72: % brut | P72: =Q72/Q$27 -> 0.15543311 | Q72: =+SUM(Q55:Q71) -> 137674.23 | S72: =+SUM(S55:S71) -> -15314.52
A73: =+B73&C73 -> Véhicules neufs | B73: =+$K$1 -> Véhicules neufs
A74: =+B74&C74 -> Véhicules neufsTOTAL DES DÉPENSES | B74: =+$K$1 -> Véhicules neufs | C74: TOTAL DES DÉPENSES | D74: % brut | E74: =F74/F$27 -> 0.93488911 | F74: =F41+F54+F72 -> 866563.45 | J74: % brut | K74: =L74/L$27 -> 0.95079507 | L74: =L41+L54+L72 -> 731621.89 | N74: =L74-F74 -> -134941.56 | O74: % brut | P74: =Q74/Q$27 -> 1.0516124 | Q74: =Q41+Q54+Q72 -> 931461.32 | S74: =L74-Q74 -> -199839.43
A75: =+B75&C75 -> Véhicules neufsRBSC neuf | B75: =+$K$1 -> Véhicules neufs | C75: RBSC neuf | F75: {=+SUMPRODUCT(('Budget original'!$A$8:$A$501=$A75)*('Budget original'!$C$3:$AO$3=F$2),'Budget original'!$C$8:$AO$501)} -> 250909.23 | L75: =-SUMIFS(BV_Data_An_Cour!$P:$P,BV_Data_An_Cour!$U:$U,$B75,BV_Data_An_Cour!$V:$V,$C75,BV_Data_An_Cour!$W:$W,L$2) -> 229935.92 | N75: =L75-F75 -> -20973.31 | Q75: {=+SUMPRODUCT(('Réel 2025'!$A$8:$A$500=$A75)*('Réel 2025'!$C$3:$AO$3=Q$2),'Réel 2025'!$C$8:$AO$500)} -> 264036.15 | S75: =L75-Q75 -> -34100.23
A76: =+B76&C76 -> Véhicules neufsProgramme neuf 2 | B76: =+$K$1 -> Véhicules neufs | C76: Programme neuf 2 | F76: {=+SUMPRODUCT(('Budget original'!$A$8:$A$501=$A76)*('Budget original'!$C$3:$AO$3=F$2),'Budget original'!$C$8:$AO$501)} -> 0 | L76: =-SUMIFS(BV_Data_An_Cour!$P:$P,BV_Data_An_Cour!$U:$U,$B76,BV_Data_An_Cour!$V:$V,$C76,BV_Data_An_Cour!$W:$W,L$2) -> 0 | N76: =L76-F76 -> 0 | Q76: {=+SUMPRODUCT(('Réel 2025'!$A$8:$A$500=$A76)*('Réel 2025'!$C$3:$AO$3=Q$2),'Réel 2025'!$C$8:$AO$500)} -> 0 | S76: =L76-Q76 -> 0
A77: =+B77&C77 -> Véhicules neufsProgramme neuf 3 | B77: =+$K$1 -> Véhicules neufs | C77: Programme neuf 3 | F77: {=+SUMPRODUCT(('Budget original'!$A$8:$A$501=$A77)*('Budget original'!$C$3:$AO$3=F$2),'Budget original'!$C$8:$AO$501)} -> 0 | L77: =-SUMIFS(BV_Data_An_Cour!$P:$P,BV_Data_An_Cour!$U:$U,$B77,BV_Data_An_Cour!$V:$V,$C77,BV_Data_An_Cour!$W:$W,L$2) -> 0 | N77: =L77-F77 -> 0 | Q77: {=+SUMPRODUCT(('Réel 2025'!$A$8:$A$500=$A77)*('Réel 2025'!$C$3:$AO$3=Q$2),'Réel 2025'!$C$8:$AO$500)} -> 0 | S77: =L77-Q77 -> 0
A78: =+B78&C78 -> Véhicules neufsHoldbacks | B78: =+$K$1 -> Véhicules neufs | C78: Holdbacks | F78: {=+SUMPRODUCT(('Budget original'!$A$8:$A$501=$A78)*('Budget original'!$C$3:$AO$3=F$2),'Budget original'!$C$8:$AO$501)} -> 304132.4 | L78: =-SUMIFS(BV_Data_An_Cour!$P:$P,BV_Data_An_Cour!$U:$U,$B78,BV_Data_An_Cour!$V:$V,$C78,BV_Data_An_Cour!$W:$W,L$2) -> 272630.8 | N78: =L78-F78 -> -31501.6 | Q78: {=+SUMPRODUCT(('Réel 2025'!$A$8:$A$500=$A78)*('Réel 2025'!$C$3:$AO$3=Q$2),'Réel 2025'!$C$8:$AO$500)} -> 243118.2 | S78: =L78-Q78 -> 29512.6
A79: =+B79&C79 -> Véhicules neufs[...] | B79: =+$K$1 -> Véhicules neufs | C79: [...] | F79: {=+SUMPRODUCT(('Budget original'!$A$8:$A$501=$A79)*('Budget original'!$C$3:$AO$3=F$2),'Budget original'!$C$8:$AO$501)} -> 0 | L79: =-SUMIFS(BV_Data_An_Cour!$P:$P,BV_Data_An_Cour!$U:$U,$B79,BV_Data_An_Cour!$V:$V,$C79,BV_Data_An_Cour!$W:$W,L$2) -> 0 | N79: =L79-F79 -> 0 | Q79: {=+SUMPRODUCT(('Réel 2025'!$A$8:$A$500=$A79)*('Réel 2025'!$C$3:$AO$3=Q$2),'Réel 2025'!$C$8:$AO$500)} -> 0 | S79: =L79-Q79 -> 0
A80: =+B80&C80 -> Véhicules neufs[...] | B80: =+$K$1 -> Véhicules neufs | C80: [...] | F80: {=+SUMPRODUCT(('Budget original'!$A$8:$A$501=$A80)*('Budget original'!$C$3:$AO$3=F$2),'Budget original'!$C$8:$AO$501)} -> 0 | L80: =-SUMIFS(BV_Data_An_Cour!$P:$P,BV_Data_An_Cour!$U:$U,$B80,BV_Data_An_Cour!$V:$V,$C80,BV_Data_An_Cour!$W:$W,L$2) -> 0 | N80: =L80-F80 -> 0 | Q80: {=+SUMPRODUCT(('Réel 2025'!$A$8:$A$500=$A80)*('Réel 2025'!$C$3:$AO$3=Q$2),'Réel 2025'!$C$8:$AO$500)} -> 0 | S80: =L80-Q80 -> 0
A81: =+B81&C81 -> Véhicules neufs[...] | B81: =+$K$1 -> Véhicules neufs | C81: [...] | F81: {=+SUMPRODUCT(('Budget original'!$A$8:$A$501=$A81)*('Budget original'!$C$3:$AO$3=F$2),'Budget original'!$C$8:$AO$501)} -> 0 | L81: =-SUMIFS(BV_Data_An_Cour!$P:$P,BV_Data_An_Cour!$U:$U,$B81,BV_Data_An_Cour!$V:$V,$C81,BV_Data_An_Cour!$W:$W,L$2) -> 0 | N81: =L81-F81 -> 0 | Q81: {=+SUMPRODUCT(('Réel 2025'!$A$8:$A$500=$A81)*('Réel 2025'!$C$3:$AO$3=Q$2),'Réel 2025'!$C$8:$AO$500)} -> 0 | S81: =L81-Q81 -> 0
A82: =+B82&C82 -> Véhicules neufsFrais administration | B82: =+$K$1 -> Véhicules neufs | C82: Frais administration | F82: {=+SUMPRODUCT(('Budget original'!$A$8:$A$501=$A82)*('Budget original'!$C$3:$AO$3=F$2),'Budget original'!$C$8:$AO$501)} -> 100293.2 | L82: =-SUMIFS(BV_Data_An_Cour!$P:$P,BV_Data_An_Cour!$U:$U,$B82,BV_Data_An_Cour!$V:$V,$C82,BV_Data_An_Cour!$W:$W,L$2) -> 87465 | N82: =L82-F82 -> -12828.2 | Q82: {=+SUMPRODUCT(('Réel 2025'!$A$8:$A$500=$A82)*('Réel 2025'!$C$3:$AO$3=Q$2),'Réel 2025'!$C$8:$AO$500)} -> 85085 | S82: =L82-Q82 -> 2380
A83: =+B83&C83 -> Véhicules neufsAUTRES REVENUS | B83: =+$K$1 -> Véhicules neufs | C83: AUTRES REVENUS | F83: =+SUM(F75:F82) -> 655334.83 | L83: =+SUM(L75:L82) -> 590031.72 | N83: =+SUM(N75:N82) -> -65303.11 | Q83: =+SUM(Q75:Q82) -> 592239.35 | S83: =+SUM(S75:S82) -> -2207.63
A84: =+B84&C84 -> Véhicules neufs | B84: =+$K$1 -> Véhicules neufs
A85: =+B85&C85 -> Véhicules neufsPROFIT DÉPARTEMENTAL | B85: =+$K$1 -> Véhicules neufs | C85: PROFIT DÉPARTEMENTAL | F85: =F27-F74+F83 -> 715687.14 | L85: =L27-L74+L83 -> 627894.14 | N85: =N27-N74+N83 -> -87793.002 | Q85: =Q27-Q74+Q83 -> 546523.85 | S85: =S27-S74+S83 -> 81370.29
C89: =C1 -> BMW Sherbrooke | K89: Véhicules usagés | S89: =$S$1 -> Réalisé, Juin 2026 AAD
D91: BUDGET ORIGINAL | J91: RÉALISATION | M91: ÉCART réel / Budget | O91: ANNÉE PRÉCÉDENTE | R91: ECART (réel/ Ann.Préc.)
D92: UNITE | E92: $P/UNITÉ | F92: $PROFITS | J92: UNITE | K92: $P/UNITE | L92: $PROFITS | M92: UNFTÉ | N92: $PROFFTS | O92: UNITE | P92: $P/UNITÉ | Q92: $PROFITS | R92: UNITE | S92: $PROFITS
A93: =+B93&C93 -> Véhicules usagésVentes nettes | B93: Véhicules usagés | C93: Ventes nettes | F93: {=+SUMPRODUCT(('Budget original'!$A$8:$A$501=$A93)*('Budget original'!$C$3:$AO$3=F$2),'Budget original'!$C$8:$AO$501)} -> 10345116 | L93: =-SUMIFS(BV_Data_An_Cour!$P:$P,BV_Data_An_Cour!$X:$X,"Oui",BV_Data_An_Cour!$U:$U,$B93) -> 11293152 | Q93: {=+SUMPRODUCT(('Réel 2025'!$A$8:$A$500=$A93)*('Réel 2025'!$C$3:$AO$3=Q$2),'Réel 2025'!$C$8:$AO$500)} -> 7596015.9
A94: =+B94&C94 -> Véhicules usagésCertifié | B94: Véhicules usagés | C94: Certifié | D94: {=+SUMPRODUCT(('Budget original'!$A$8:$A$501=$A94)*('Budget original'!$C$3:$AO$3=D$2),'Budget original'!$C$8:$AO$501)} -> 73 | E94: =IF(D94=0,0,F94/D94) -> 2400 | F94: {=+SUMPRODUCT(('Budget original'!$A$8:$A$501=$A94)*('Budget original'!$C$3:$AO$3=F$2),'Budget original'!$C$8:$AO$501)} -> 175200 | J94: =-SUMIFS(BV_Data_An_Cour!$P:$P,BV_Data_An_Cour!$U:$U,$B94,BV_Data_An_Cour!$V:$V,$C94,BV_Data_An_Cour!$W:$W,J$2) -> 63 | K94: =IF(J94=0,0,L94/J94) -> 1529.741 | L94: =-SUMIFS(BV_Data_An_Cour!$P:$P,BV_Data_An_Cour!$U:$U,$B94,BV_Data_An_Cour!$V:$V,$C94,BV_Data_An_Cour!$W:$W,$L2) -> 96373.68 | M94: =J94-D94 -> -10 | N94: =L94-F94 -> -78826.32 | O94: {=+SUMPRODUCT(('Réel 2025'!$A$8:$A$500=$A94)*('Réel 2025'!$C$3:$AO$3=O$2),'Réel 2025'!$C$8:$AO$500)} -> 27 | P94: =IF(O94=0,0,Q94/O94) -> 2657.4022 | Q94: {=+SUMPRODUCT(('Réel 2025'!$A$8:$A$500=$A94)*('Réel 2025'!$C$3:$AO$3=Q$2),'Réel 2025'!$C$8:$AO$500)} -> 71749.86 | R94: =J94-O94 -> 36 | S94: =L94-Q94 -> 24623.82
A95: =+B95&C95 -> Véhicules usagésNon Certifié | B95: Véhicules usagés | C95: Non Certifié | D95: {=+SUMPRODUCT(('Budget original'!$A$8:$A$501=$A95)*('Budget original'!$C$3:$AO$3=D$2),'Budget original'!$C$8:$AO$501)} -> 18 | E95: =IF(D95=0,0,F95/D95) -> 1400 | F95: {=+SUMPRODUCT(('Budget original'!$A$8:$A$501=$A95)*('Budget original'!$C$3:$AO$3=F$2),'Budget original'!$C$8:$AO$501)} -> 25200 | J95: =-SUMIFS(BV_Data_An_Cour!$P:$P,BV_Data_An_Cour!$U:$U,$B95,BV_Data_An_Cour!$V:$V,$C95,BV_Data_An_Cour!$W:$W,J$2) -> 14 | K95: =IF(J95=0,0,L95/J95) -> 3019.2357 | L95: =-SUMIFS(BV_Data_An_Cour!$P:$P,BV_Data_An_Cour!$U:$U,$B95,BV_Data_An_Cour!$V:$V,$C95,BV_Data_An_Cour!$W:$W,$L2) -> 42269.3 | M95: =J95-D95 -> -4 | N95: =L95-F95 -> 17069.3 | O95: {=+SUMPRODUCT(('Réel 2025'!$A$8:$A$500=$A95)*('Réel 2025'!$C$3:$AO$3=O$2),'Réel 2025'!$C$8:$AO$500)} -> 44 | P95: =IF(O95=0,0,Q95/O95) -> 1795.2448 | Q95: {=+SUMPRODUCT(('Réel 2025'!$A$8:$A$500=$A95)*('Réel 2025'!$C$3:$AO$3=Q$2),'Réel 2025'!$C$8:$AO$500)} -> 78990.77 | R95: =J95-O95 -> -30 | S95: =L95-Q95 -> -36721.47
A96: =+B96&C96 -> Véhicules usagésAutres marques | B96: Véhicules usagés | C96: Autres marques | D96: {=+SUMPRODUCT(('Budget original'!$A$8:$A$501=$A96)*('Budget original'!$C$3:$AO$3=D$2),'Budget original'!$C$8:$AO$501)} -> 31 | E96: =IF(D96=0,0,F96/D96) -> 1500 | F96: {=+SUMPRODUCT(('Budget original'!$A$8:$A$501=$A96)*('Budget original'!$C$3:$AO$3=F$2),'Budget original'!$C$8:$AO$501)} -> 46500 | J96: =-SUMIFS(BV_Data_An_Cour!$P:$P,BV_Data_An_Cour!$U:$U,$B96,BV_Data_An_Cour!$V:$V,$C96,BV_Data_An_Cour!$W:$W,J$2) -> 26 | K96: =IF(J96=0,0,L96/J96) -> 1861.4965 | L96: =-SUMIFS(BV_Data_An_Cour!$P:$P,BV_Data_An_Cour!$U:$U,$B96,BV_Data_An_Cour!$V:$V,$C96,BV_Data_An_Cour!$W:$W,$L2) -> 48398.91 | M96: =J96-D96 -> -5 | N96: =L96-F96 -> 1898.91 | O96: {=+SUMPRODUCT(('Réel 2025'!$A$8:$A$500=$A96)*('Réel 2025'!$C$3:$AO$3=O$2),'Réel 2025'!$C$8:$AO$500)} -> 35 | P96: =IF(O96=0,0,Q96/O96) -> 1454.7409 | Q96: {=+SUMPRODUCT(('Réel 2025'!$A$8:$A$500=$A96)*('Réel 2025'!$C$3:$AO$3=Q$2),'Réel 2025'!$C$8:$AO$500)} -> 50915.93 | R96: =J96-O96 -> -9 | S96: =L96-Q96 -> -2517.02
A97: =+B97&C97 -> Véhicules usagésTotal Usagés | B97: Véhicules usagés | C97: Total Usagés | D97: =+D95+D94+D96 -> 122 | E97: =IF(D97=0,0,F97/D97) -> 2023.7705 | F97: =+F94+F95+F96 -> 246900 | J97: =+J94+J95+J96 -> 103 | K97: =IF(J97<=0,0,L97/J97) -> 1815.9407 | L97: =+L94+L95+L96 -> 187041.89 | M97: =J97-D97 -> -19 | N97: =L97-F97 -> -59858.11 | O97: =+O95+O94+O96 -> 106 | P97: =IF(O97=0,0,Q97/O97) -> 1902.4204 | Q97: =+Q94+Q95+Q96 -> 201656.56 | R97: =J97-O97 -> -3 | S97: =L97-Q97 -> -14614.67
A98: =+B98&C98 -> Véhicules usagés | B98: Véhicules usagés | M98: =M97/D97 -> -0.1557377 | N98: =N97/F97 -> -0.24243868 | R98: =R97/O97 -> -0.028301887 | S98: =IF(Q97=0,0,(S97/Q97)) -> -0.07247307
A99: =+B99&C99 -> Véhicules neufsRachat bail | B99: =+$K$1 -> Véhicules neufs | C99: Rachat bail | D99: {=+SUMPRODUCT(('Budget original'!$A$8:$A$501=$A99)*('Budget original'!$C$3:$AO$3=D$2),'Budget original'!$C$8:$AO$501)} -> 0 | E99: =IF(D99=0,0,F99/D99) -> 0 | F99: {=+SUMPRODUCT(('Budget original'!$A$8:$A$501=$A99)*('Budget original'!$C$3:$AO$3=F$2),'Budget original'!$C$8:$AO$501)} -> 11451.882 | L99: =-SUMIFS(BV_Data_An_Cour!$P:$P,BV_Data_An_Cour!$U:$U,$B99,BV_Data_An_Cour!$V:$V,$C99,BV_Data_An_Cour!$W:$W,L$2) -> 16978.01 | N99: =L99-F99 -> 5526.1284 | O99: {=+SUMPRODUCT(('Réel 2025'!$A$8:$A$500=$A99)*('Réel 2025'!$C$3:$AO$3=O$2),'Réel 2025'!$C$8:$AO$500)} -> 0 | P99: =IF(O99=0,0,Q99/O99) -> 0 | Q99: {=+SUMPRODUCT(('Réel 2025'!$A$8:$A$500=$A99)*('Réel 2025'!$C$3:$AO$3=Q$2),'Réel 2025'!$C$8:$AO$500)} -> 15986.97 | R99: =O99-K99 -> 0 | S99: =L99-Q99 -> 991.04
A100: =+B100&C100 -> Véhicules usagés | B100: Véhicules usagés
A101: =+B101&C101 -> Véhicules usagésVentes au Gros | B101: Véhicules usagés | C101: Ventes au Gros | D101: {=+SUMPRODUCT(('Budget original'!$A$8:$A$501=$A101)*('Budget original'!$C$3:$AO$3=D$2),'Budget original'!$C$8:$AO$501)} -> 124 | E101: =IF(D101=0,0,F101/D101) -> 500 | F101: {=+SUMPRODUCT(('Budget original'!$A$8:$A$501=$A101)*('Budget original'!$C$3:$AO$3=F$2),'Budget original'!$C$8:$AO$501)} -> 62000 | J101: =-SUMIFS(BV_Data_An_Cour!$P:$P,BV_Data_An_Cour!$U:$U,$B101,BV_Data_An_Cour!$V:$V,$C101,BV_Data_An_Cour!$W:$W,J$2) -> 162 | K101: =IF(J101=0,0,L101/J101) -> 773.82488 | L101: =-SUMIFS(BV_Data_An_Cour!$P:$P,BV_Data_An_Cour!$U:$U,$B101,BV_Data_An_Cour!$V:$V,$C101,BV_Data_An_Cour!$W:$W,L$2) -> 125359.63 | M101: =J101-D101 -> 38 | N101: =L101-F101 -> 63359.63 | O101: {=+SUMPRODUCT(('Réel 2025'!$A$8:$A$500=$A101)*('Réel 2025'!$C$3:$AO$3=O$2),'Réel 2025'!$C$8:$AO$500)} -> 100 | P101: =IF(O101=0,0,Q101/O101) -> 384.5283 | Q101: {=+SUMPRODUCT(('Réel 2025'!$A$8:$A$500=$A101)*('Réel 2025'!$C$3:$AO$3=Q$2),'Réel 2025'!$C$8:$AO$500)} -> 38452.83 | R101: =J101-O101 -> 62 | S101: =L101-Q101 -> 86906.8
A102: =+B102&C102 -> Véhicules usagés | B102: Véhicules usagés
A103: =+B103&C103 -> Véhicules usagésRev. Finances | B103: Véhicules usagés | C103: Rev. Finances | E103: =IF(D97=0,0,F103/D97) -> 350 | F103: {=+SUMPRODUCT(('Budget original'!$A$8:$A$501=$A103)*('Budget original'!$C$3:$AO$3=F$2),'Budget original'!$C$8:$AO$501)} -> 42700 | K103: =IF(J97=0,0,L103/J97) -> 398.88563 | L103: =-SUMIFS(BV_Data_An_Cour!$P:$P,BV_Data_An_Cour!$U:$U,$B103,BV_Data_An_Cour!$V:$V,$C103,BV_Data_An_Cour!$W:$W,$L2) -> 41085.22 | N103: =L103-F103 -> -1614.78 | P103: =IF(O97=0,0,Q103/O97) -> 499.83726 | Q103: {=+SUMPRODUCT(('Réel 2025'!$A$8:$A$500=$A103)*('Réel 2025'!$C$3:$AO$3=Q$2),'Réel 2025'!$C$8:$AO$500)} -> 52982.75 | R103: =O103-K103 -> -398.88563 | S103: =L103-Q103 -> -11897.53
A104: =+B104&C104 -> Véhicules usagésRev. Protections | B104: Véhicules usagés | C104: Rev. Protections | E104: =IF(D97=0,0,F104/D97) -> 950 | F104: {=+SUMPRODUCT(('Budget original'!$A$8:$A$501=$A104)*('Budget original'!$C$3:$AO$3=F$2),'Budget original'!$C$8:$AO$501)} -> 115900 | K104: =IF(J97=0,0,L104/J97) -> 587.27049 | L104: =-SUMIFS(BV_Data_An_Cour!$P:$P,BV_Data_An_Cour!$U:$U,$B104,BV_Data_An_Cour!$V:$V,$C104,BV_Data_An_Cour!$W:$W,$L2) -> 60488.86 | N104: =L104-F104 -> -55411.14 | P104: =IF(O97=0,0,Q104/O97) -> 1050.7748 | Q104: {=+SUMPRODUCT(('Réel 2025'!$A$8:$A$500=$A104)*('Réel 2025'!$C$3:$AO$3=Q$2),'Réel 2025'!$C$8:$AO$500)} -> 111382.13 | R104: =O104-K104 -> -587.27049 | S104: =L104-Q104 -> -50893.27
A105: =+B105&C105 -> Véhicules usagésRev. Autres | B105: Véhicules usagés | C105: Rev. Autres | E105: =IF(D97=0,0,F105/D97) -> 200 | F105: {=+SUMPRODUCT(('Budget original'!$A$8:$A$501=$A105)*('Budget original'!$C$3:$AO$3=F$2),'Budget original'!$C$8:$AO$501)} -> 24400 | K105: =IF(J97=0,0,L105/J97) -> 167.45272 | L105: =-SUMIFS(BV_Data_An_Cour!$P:$P,BV_Data_An_Cour!$U:$U,$B105,BV_Data_An_Cour!$V:$V,$C105,BV_Data_An_Cour!$W:$W,$L$2) -> 17247.63 | N105: =L105-F105 -> -7152.37 | P105: =IF(O97=0,0,Q105/O97) -> 289.23519 | Q105: {=+SUMPRODUCT(('Réel 2025'!$A$8:$A$500=$A105)*('Réel 2025'!$C$3:$AO$3=Q$2),'Réel 2025'!$C$8:$AO$500)} -> 30658.93 | R105: =O105-K105 -> -167.45272 | S105: =L105-Q105 -> -13411.3
...

Sheet BV_Data_An_Cour
A1: Description | B1: #Compte | C1: Solde d'ouverture | D1: Solde courant | E1: Solde de fin | F1: Type compte | G1: #Groupe | H1: Préfixe | I1: CUC/Mémo solde début | J1: CUC/Mémo solde actuel | K1: CUC/Mémo solde fin | L1: #Compte | M1: Description | N1: Solde d'ouverture | O1: Solde courant | P1: Solde de fin | Q1: Type compte | R1: #Groupe | S1: Préfixe | T1: Valid GL # | U1: Debits | V1: Classification | W1: $ / NB | X1: Ventes
A2: PROFIT JANVIER | B2: 101 | F2: 1-Mémo | G2: 101 | H2: _ | I2: 19780 | J2: 0 | K2: 19780 | L2: =+B2 -> 101 | M2: =+A2 -> PROFIT JANVIER | N2: =+IF(OR($Q2=Parametres!$G$2,$Q2=Parametres!$G$3),I2,C2) -> 19780 | O2: =+IF(OR($Q2=Parametres!$G$2,$Q2=Parametres!$G$3),J2,D2) -> 0 | P2: =+IF(OR($Q2=Parametres!$G$2,$Q2=Parametres!$G$3),K2,E2) -> 19780 | Q2: =+F2 -> 1-Mémo | R2: =+G2 -> 101 | S2: =+H2 -> _ | T2: =+VLOOKUP($L2,Data_Validation!$A:$D,1,0) -> 101 | U2: =+VLOOKUP($L2,Data_Validation!$A:$D,3,0) -> Autres | V2: =+VLOOKUP($L2,Data_Validation!$A:$D,4,0) -> 0 | W2: =+VLOOKUP($L2,Data_Validation!$A:$E,5,0) -> 0 | X2: =+VLOOKUP($L2,Data_Validation!$A:$F,6,0) -> 0
A3: PROFIT FEVRIER | B3: 102 | F3: 1-Mémo | G3: 102 | H3: _ | I3: 75066 | J3: 0 | K3: 75066 | L3: =+B3 -> 102 | M3: =+A3 -> PROFIT FEVRIER | N3: =+IF(OR($Q3=Parametres!$G$2,$Q3=Parametres!$G$3),I3,C3) -> 75066 | O3: =+IF(OR($Q3=Parametres!$G$2,$Q3=Parametres!$G$3),J3,D3) -> 0 | P3: =+IF(OR($Q3=Parametres!$G$2,$Q3=Parametres!$G$3),K3,E3) -> 75066 | Q3: =+F3 -> 1-Mémo | R3: =+G3 -> 102 | S3: =+H3 -> _ | T3: =+VLOOKUP($L3,Data_Validation!$A:$D,1,0) -> 102 | U3: =+VLOOKUP($L3,Data_Validation!$A:$D,3,0) -> Autres | V3: =+VLOOKUP($L3,Data_Validation!$A:$D,4,0) -> 0 | W3: =+VLOOKUP($L3,Data_Validation!$A:$E,5,0) -> 0 | X3: =+VLOOKUP($L3,Data_Validation!$A:$F,6,0) -> 0
A4: PROFIT MARS | B4: 103 | F4: 1-Mémo | G4: 103 | H4: _ | I4: 107843 | J4: 0 | K4: 107843 | L4: =+B4 -> 103 | M4: =+A4 -> PROFIT MARS | N4: =+IF(OR($Q4=Parametres!$G$2,$Q4=Parametres!$G$3),I4,C4) -> 107843 | O4: =+IF(OR($Q4=Parametres!$G$2,$Q4=Parametres!$G$3),J4,D4) -> 0 | P4: =+IF(OR($Q4=Parametres!$G$2,$Q4=Parametres!$G$3),K4,E4) -> 107843 | Q4: =+F4 -> 1-Mémo | R4: =+G4 -> 103 | S4: =+H4 -> _ | T4: =+VLOOKUP($L4,Data_Validation!$A:$D,1,0) -> 103 | U4: =+VLOOKUP($L4,Data_Validation!$A:$D,3,0) -> Autres | V4: =+VLOOKUP($L4,Data_Validation!$A:$D,4,0) -> 0 | W4: =+VLOOKUP($L4,Data_Validation!$A:$E,5,0) -> 0 | X4: =+VLOOKUP($L4,Data_Validation!$A:$F,6,0) -> 0
A5: PROFIT AVRIL | B5: 104 | F5: 1-Mémo | G5: 104 | H5: _ | I5: 260079 | J5: 0 | K5: 260079 | L5: =+B5 -> 104 | M5: =+A5 -> PROFIT AVRIL | N5: =+IF(OR($Q5=Parametres!$G$2,$Q5=Parametres!$G$3),I5,C5) -> 260079 | O5: =+IF(OR($Q5=Parametres!$G$2,$Q5=Parametres!$G$3),J5,D5) -> 0 | P5: =+IF(OR($Q5=Parametres!$G$2,$Q5=Parametres!$G$3),K5,E5) -> 260079 | Q5: =+F5 -> 1-Mémo | R5: =+G5 -> 104 | S5: =+H5 -> _ | T5: =+VLOOKUP($L5,Data_Validation!$A:$D,1,0) -> 104 | U5: =+VLOOKUP($L5,Data_Validation!$A:$D,3,0) -> Autres | V5: =+VLOOKUP($L5,Data_Validation!$A:$D,4,0) -> 0 | W5: =+VLOOKUP($L5,Data_Validation!$A:$E,5,0) -> 0 | X5: =+VLOOKUP($L5,Data_Validation!$A:$F,6,0) -> 0
A6: PROFIT MAI | B6: 105 | F6: 1-Mémo | G6: 105 | H6: _ | I6: 0 | J6: 312701 | K6: 312701 | L6: =+B6 -> 105 | M6: =+A6 -> PROFIT MAI | N6: =+IF(OR($Q6=Parametres!$G$2,$Q6=Parametres!$G$3),I6,C6) -> 0 | O6: =+IF(OR($Q6=Parametres!$G$2,$Q6=Parametres!$G$3),J6,D6) -> 312701 | P6: =+IF(OR($Q6=Parametres!$G$2,$Q6=Parametres!$G$3),K6,E6) -> 312701 | Q6: =+F6 -> 1-Mémo | R6: =+G6 -> 105 | S6: =+H6 -> _ | T6: =+VLOOKUP($L6,Data_Validation!$A:$D,1,0) -> 105 | U6: =+VLOOKUP($L6,Data_Validation!$A:$D,3,0) -> Autres | V6: =+VLOOKUP($L6,Data_Validation!$A:$D,4,0) -> 0 | W6: =+VLOOKUP($L6,Data_Validation!$A:$E,5,0) -> 0 | X6: =+VLOOKUP($L6,Data_Validation!$A:$F,6,0) -> 0
A7: JANV. NB VENTE NEUF BMW AUTO | B7: 120A | F7: 1-Mémo | G7: 120 | H7: _ | I7: 0.03 | J7: 0 | K7: 0.03 | L7: =+B7 -> 120A | M7: =+A7 -> JANV. NB VENTE NEUF BMW AUTO | N7: =+IF(OR($Q7=Parametres!$G$2,$Q7=Parametres!$G$3),I7,C7) -> 0.03 | O7: =+IF(OR($Q7=Parametres!$G$2,$Q7=Parametres!$G$3),J7,D7) -> 0 | P7: =+IF(OR($Q7=Parametres!$G$2,$Q7=Parametres!$G$3),K7,E7) -> 0.03 | Q7: =+F7 -> 1-Mémo | R7: =+G7 -> 120 | S7: =+H7 -> _ | T7: =+VLOOKUP($L7,Data_Validation!$A:$D,1,0) -> 120A | U7: =+VLOOKUP($L7,Data_Validation!$A:$D,3,0) -> Autres | V7: =+VLOOKUP($L7,Data_Validation!$A:$D,4,0) -> 0 | W7: =+VLOOKUP($L7,Data_Validation!$A:$E,5,0) -> 0 | X7: =+VLOOKUP($L7,Data_Validation!$A:$F,6,0) -> 0
A8: FEV. NB VENTE NEUF BMW AUTO | B8: 120B | F8: 1-Mémo | G8: 120 | H8: _ | I8: 0.02 | J8: 0 | K8: 0.02 | L8: =+B8 -> 120B | M8: =+A8 -> FEV. NB VENTE NEUF BMW AUTO | N8: =+IF(OR($Q8=Parametres!$G$2,$Q8=Parametres!$G$3),I8,C8) -> 0.02 | O8: =+IF(OR($Q8=Parametres!$G$2,$Q8=Parametres!$G$3),J8,D8) -> 0 | P8: =+IF(OR($Q8=Parametres!$G$2,$Q8=Parametres!$G$3),K8,E8) -> 0.02 | Q8: =+F8 -> 1-Mémo | R8: =+G8 -> 120 | S8: =+H8 -> _ | T8: =+VLOOKUP($L8,Data_Validation!$A:$D,1,0) -> 120B | U8: =+VLOOKUP($L8,Data_Validation!$A:$D,3,0) -> Autres | V8: =+VLOOKUP($L8,Data_Validation!$A:$D,4,0) -> 0 | W8: =+VLOOKUP($L8,Data_Validation!$A:$E,5,0) -> 0 | X8: =+VLOOKUP($L8,Data_Validation!$A:$F,6,0) -> 0
A9: MARS NB VENTE NEUF BMW AUTO | B9: 120C | F9: 1-Mémo | G9: 120 | H9: _ | I9: 0.03 | J9: 0 | K9: 0.03 | L9: =+B9 -> 120C | M9: =+A9 -> MARS NB VENTE NEUF BMW AUTO | N9: =+IF(OR($Q9=Parametres!$G$2,$Q9=Parametres!$G$3),I9,C9) -> 0.03 | O9: =+IF(OR($Q9=Parametres!$G$2,$Q9=Parametres!$G$3),J9,D9) -> 0 | P9: =+IF(OR($Q9=Parametres!$G$2,$Q9=Parametres!$G$3),K9,E9) -> 0.03 | Q9: =+F9 -> 1-Mémo | R9: =+G9 -> 120 | S9: =+H9 -> _ | T9: =+VLOOKUP($L9,Data_Validation!$A:$D,1,0) -> 120C | U9: =+VLOOKUP($L9,Data_Validation!$A:$D,3,0) -> Autres | V9: =+VLOOKUP($L9,Data_Validation!$A:$D,4,0) -> 0 | W9: =+VLOOKUP($L9,Data_Validation!$A:$E,5,0) -> 0 | X9: =+VLOOKUP($L9,Data_Validation!$A:$F,6,0) -> 0
A10: AVRIL NB VENTE NEUF BMW AUTO | B10: 120D | F10: 1-Mémo | G10: 120 | H10: _ | I10: 0.11 | J10: 0 | K10: 0.11 | L10: =+B10 -> 120D | M10: =+A10 -> AVRIL NB VENTE NEUF BMW AUTO | N10: =+IF(OR($Q10=Parametres!$G$2,$Q10=Parametres!$G$3),I10,C10) -> 0.11 | O10: =+IF(OR($Q10=Parametres!$G$2,$Q10=Parametres!$G$3),J10,D10) -> 0 | P10: =+IF(OR($Q10=Parametres!$G$2,$Q10=Parametres!$G$3),K10,E10) -> 0.11 | Q10: =+F10 -> 1-Mémo | R10: =+G10 -> 120 | S10: =+H10 -> _ | T10: =+VLOOKUP($L10,Data_Validation!$A:$D,1,0) -> 120D | U10: =+VLOOKUP($L10,Data_Validation!$A:$D,3,0) -> Autres | V10: =+VLOOKUP($L10,Data_Validation!$A:$D,4,0) -> 0 | W10: =+VLOOKUP($L10,Data_Validation!$A:$E,5,0) -> 0 | X10: =+VLOOKUP($L10,Data_Validation!$A:$F,6,0) -> 0
A11: MAI NB VENTE NEUF BMW AUTO | B11: 120E | F11: 1-Mémo | G11: 120 | H11: _ | I11: 0.17 | J11: 0 | K11: 0.17 | L11: =+B11 -> 120E | M11: =+A11 -> MAI NB VENTE NEUF BMW AUTO | N11: =+IF(OR($Q11=Parametres!$G$2,$Q11=Parametres!$G$3),I11,C11) -> 0.17 | O11: =+IF(OR($Q11=Parametres!$G$2,$Q11=Parametres!$G$3),J11,D11) -> 0 | P11: =+IF(OR($Q11=Parametres!$G$2,$Q11=Parametres!$G$3),K11,E11) -> 0.17 | Q11: =+F11 -> 1-Mémo | R11: =+G11 -> 120 | S11: =+H11 -> _ | T11: =+VLOOKUP($L11,Data_Validation!$A:$D,1,0) -> 120E | U11: =+VLOOKUP($L11,Data_Validation!$A:$D,3,0) -> Autres | V11: =+VLOOKUP($L11,Data_Validation!$A:$D,4,0) -> 0 | W11: =+VLOOKUP($L11,Data_Validation!$A:$E,5,0) -> 0 | X11: =+VLOOKUP($L11,Data_Validation!$A:$F,6,0) -> 0
A12: JUIN NB VENTE NEUF BMW AUTO | B12: 120F | F12: 1-Mémo | G12: 120 | H12: _ | I12: 0 | J12: 0.1 | K12: 0.1 | L12: =+B12 -> 120F | M12: =+A12 -> JUIN NB VENTE NEUF BMW AUTO | N12: =+IF(OR($Q12=Parametres!$G$2,$Q12=Parametres!$G$3),I12,C12) -> 0 | O12: =+IF(OR($Q12=Parametres!$G$2,$Q12=Parametres!$G$3),J12,D12) -> 0.1 | P12: =+IF(OR($Q12=Parametres!$G$2,$Q12=Parametres!$G$3),K12,E12) -> 0.1 | Q12: =+F12 -> 1-Mémo | R12: =+G12 -> 120 | S12: =+H12 -> _ | T12: =+VLOOKUP($L12,Data_Validation!$A:$D,1,0) -> 120F | U12: =+VLOOKUP($L12,Data_Validation!$A:$D,3,0) -> Autres | V12: =+VLOOKUP($L12,Data_Validation!$A:$D,4,0) -> 0 | W12: =+VLOOKUP($L12,Data_Validation!$A:$E,5,0) -> 0 | X12: =+VLOOKUP($L12,Data_Validation!$A:$F,6,0) -> 0
A13: JANV. NB VENTE NEUF BMW I | B13: 122A | F13: 1-Mémo | G13: 122 | H13: _ | I13: 0.02 | J13: 0 | K13: 0.02 | L13: =+B13 -> 122A | M13: =+A13 -> JANV. NB VENTE NEUF BMW I | N13: =+IF(OR($Q13=Parametres!$G$2,$Q13=Parametres!$G$3),I13,C13) -> 0.02 | O13: =+IF(OR($Q13=Parametres!$G$2,$Q13=Parametres!$G$3),J13,D13) -> 0 | P13: =+IF(OR($Q13=Parametres!$G$2,$Q13=Parametres!$G$3),K13,E13) -> 0.02 | Q13: =+F13 -> 1-Mémo | R13: =+G13 -> 122 | S13: =+H13 -> _ | T13: =+VLOOKUP($L13,Data_Validation!$A:$D,1,0) -> 122A | U13: =+VLOOKUP($L13,Data_Validation!$A:$D,3,0) -> Autres | V13: =+VLOOKUP($L13,Data_Validation!$A:$D,4,0) -> 0 | W13: =+VLOOKUP($L13,Data_Validation!$A:$E,5,0) -> 0 | X13: =+VLOOKUP($L13,Data_Validation!$A:$F,6,0) -> 0
... A94: NOMBRE DE JOURS OUVRABLE SERVICE | B94: 179 | F94: 1-Mémo | G94: 179 | H94: _ | I94: 1.03 | J94: 0.21 | K94: 1.24 | L94: =+B94 -> 179 | M94: =+A94 -> NOMBRE DE JOURS OUVRABLE SERVICE | N94: =+IF(OR($Q94=Parametres!$G$2,$Q94=Parametres!$G$3),I94,C94) -> 1.03 | O94: =+IF(OR($Q94=Parametres!$G$2,$Q94=Parametres!$G$3),J94,D94) -> 0.21 | P94: =+IF(OR($Q94=Parametres!$G$2,$Q94=Parametres!$G$3),K94,E94) -> 1.24 | Q94: =+F94 -> 1-Mémo | R94: =+G94 -> 179 | S94: =+H94 -> _ | T94: =+VLOOKUP($L94,Data_Validation!$A:$D,1,0) -> 179 | U94: =+VLOOKUP($L94,Data_Validation!$A:$D,3,0) -> Autres | V94: =+VLOOKUP($L94,Data_Validation!$A:$D,4,0) -> 0 | W94: =+VLOOKUP($L94,Data_Validation!$A:$E,5,0) -> 0 | X94: =+VLOOKUP($L94,Data_Validation!$A:$F,6,0) -> 0
A95: CONTRATS EN TRANSIT | B95: 205 | C95: 1880104.6 | D95: -576914.84 | E95: 1303189.8 | F95: 2-Actifs | G95: 205 | H95: _ | L95: =+B95 -> 205 | M95: =+A95 -> CONTRATS EN TRANSIT | N95: =+IF(OR($Q95=Parametres!$G$2,$Q95=Parametres!$G$3),I95,C95) -> 1880104.6 | O95: =+IF(OR($Q95=Parametres!$G$2,$Q95=Parametres!$G$3),J95,D95) -> -576914.84 | P95: =+IF(OR($Q95=Parametres!$G$2,$Q95=Parametres!$G$3),K95,E95) -> 1303189.8 | Q95: =+F95 -> 2-Actifs | R95: =+G95 -> 205 | S95: =+H95 -> _ | T95: =+VLOOKUP($L95,Data_Validation!$A:$D,1,0) -> 205 | U95: =+VLOOKUP($L95,Data_Validation!$A:$D,3,0) -> Bilan | V95: =+VLOOKUP($L95,Data_Validation!$A:$D,4,0) -> Recevables Contrats en Transit | W95: =+VLOOKUP($L95,Data_Validation!$A:$E,5,0) -> $ | X95: =+VLOOKUP($L95,Data_Validation!$A:$F,6,0) -> 0
A96: PAIEMENTS FORFAITAIRES FLOOR PLAN | B96: 202B | C96: 1300000 | D96: -300000 | E96: 1000000 | F96: 2-Actifs | G96: 202 | H96: _ | L96: =+B96 -> 202B | M96: =+A96 -> PAIEMENTS FORFAITAIRES FLOOR PLAN | N96: =+IF(OR($Q96=Parametres!$G$2,$Q96=Parametres!$G$3),I96,C96) -> 1300000 | O96: =+IF(OR($Q96=Parametres!$G$2,$Q96=Parametres!$G$3),J96,D96) -> -300000 | P96: =+IF(OR($Q96=Parametres!$G$2,$Q96=Parametres!$G$3),K96,E96) -> 1000000 | Q96: =+F96 -> 2-Actifs | R96: =+G96 -> 202 | S96: =+H96 -> _ | T96: =+VLOOKUP($L96,Data_Validation!$A:$D,1,0) -> 202B | U96: =+VLOOKUP($L96,Data_Validation!$A:$D,3,0) -> bilan | V96: =+VLOOKUP($L96,Data_Validation!$A:$D,4,0) -> Encaisse | W96: =+VLOOKUP($L96,Data_Validation!$A:$E,5,0) -> $ | X96: =+VLOOKUP($L96,Data_Validation!$A:$F,6,0) -> 0
A97: ENCAISSE | B97: 202 | C97: 692155.78 | D97: -178830.04 | E97: 513325.74 | F97: 2-Actifs | G97: 202 | H97: _ | L97: =+B97 -> 202 | M97: =+A97 -> ENCAISSE | N97: =+IF(OR($Q97=Parametres!$G$2,$Q97=Parametres!$G$3),I97,C97) -> 692155.78 | O97: =+IF(OR($Q97=Parametres!$G$2,$Q97=Parametres!$G$3),J97,D97) -> -178830.04 | P97: =+IF(OR($Q97=Parametres!$G$2,$Q97=Parametres!$G$3),K97,E97) -> 513325.74 | Q97: =+F97 -> 2-Actifs | R97: =+G97 -> 202 | S97: =+H97 -> _ | T97: =+VLOOKUP($L97,Data_Validation!$A:$D,1,0) -> 202 | U97: =+VLOOKUP($L97,Data_Validation!$A:$D,3,0) -> Bilan | V97: =+VLOOKUP($L97,Data_Validation!$A:$D,4,0) -> encaisse | W97: =+VLOOKUP($L97,Data_Validation!$A:$E,5,0) -> $ | X97: =+VLOOKUP($L97,Data_Validation!$A:$F,6,0) -> 0
A98: INV. VOITURES USAGEES BMW | B98: 240A | C98: 730183.57 | D98: -117859.58 | E98: 612323.99 | F98: 2-Actifs | G98: 240A | H98: _ | L98: =+B98 -> 240A | M98: =+A98 -> INV. VOITURES USAGEES BMW | N98: =+IF(OR($Q98=Parametres!$G$2,$Q98=Parametres!$G$3),I98,C98) -> 730183.57 | O98: =+IF(OR($Q98=Parametres!$G$2,$Q98=Parametres!$G$3),J98,D98) -> -117859.58 | P98: =+IF(OR($Q98=Parametres!$G$2,$Q98=Parametres!$G$3),K98,E98) -> 612323.99 | Q98: =+F98 -> 2-Actifs | R98: =+G98 -> 240A | S98: =+H98 -> _ | T98: =+VLOOKUP($L98,Data_Validation!$A:$D,1,0) -> 240A | U98: =+VLOOKUP($L98,Data_Validation!$A:$D,3,0) -> Bilan | V98: =+VLOOKUP($L98,Data_Validation!$A:$D,4,0) -> Inventaire Véhicules Usagés | W98: =+VLOOKUP($L98,Data_Validation!$A:$E,5,0) -> $ | X98: =+VLOOKUP($L98,Data_Validation!$A:$F,6,0) -> 0
A99: INV. VEHICULES USAGES AUTRES | B99: 240C | C99: 842133.27 | D99: -78759.01 | E99: 763374.26 | F99: 2-Actifs | G99: 240C | H99: _ | L99: =+B99 -> 240C | M99: =+A99 -> INV. VEHICULES USAGES AUTRES | N99: =+IF(OR($Q99=Parametres!$G$2,$Q99=Parametres!$G$3),I99,C99) -> 842133.27 | O99: =+IF(OR($Q99=Parametres!$G$2,$Q99=Parametres!$G$3),J99,D99) -> -78759.01 | P99: =+IF(OR($Q99=Parametres!$G$2,$Q99=Parametres!$G$3),K99,E99) -> 763374.26 | Q99: =+F99 -> 2-Actifs | R99: =+G99 -> 240C | S99: =+H99 -> _ | T99: =+VLOOKUP($L99,Data_Validation!$A:$D,1,0) -> 240C | U99: =+VLOOKUP($L99,Data_Validation!$A:$D,3,0) -> Bilan | V99: =+VLOOKUP($L99,Data_Validation!$A:$D,4,0) -> Inventaire Véhicules Usagés | W99: =+VLOOKUP($L99,Data_Validation!$A:$E,5,0) -> $ | X99: =+VLOOKUP($L99,Data_Validation!$A:$F,6,0) -> 0
A100: PROGRAMMES A/R MANUFACTURIER | B100: 221A | C100: 121919.38 | D100: -32592 | E100: 89327.38 | F100: 2-Actifs | G100: 221A | H100: _ | L100: =+B100 -> 221A | M100: =+A100 -> PROGRAMMES A/R MANUFACTURIER | N100: =+IF(OR($Q100=Parametres!$G$2,$Q100=Parametres!$G$3),I100,C100) -> 121919.38 | O100: =+IF(OR($Q100=Parametres!$G$2,$Q100=Parametres!$G$3),J100,D100) -> -32592 | P100: =+IF(OR($Q100=Parametres!$G$2,$Q100=Parametres!$G$3),K100,E100) -> 89327.38 | Q100: =+F100 -> 2-Actifs | R100: =+G100 -> 221A | S100: =+H100 -> _ | T100: =+VLOOKUP($L100,Data_Validation!$A:$D,1,0) -> 221A | U100: =+VLOOKUP($L100,Data_Validation!$A:$D,3,0) -> Bilan | V100: =+VLOOKUP($L100,Data_Validation!$A:$D,4,0) -> Recevables Manufacturier | W100: =+VLOOKUP($L100,Data_Validation!$A:$E,5,0) -> $ | X100: =+VLOOKUP($L100,Data_Validation!$A:$F,6,0) -> 0
A101: INV. PNEUS | B101: 249 | C101: 171564.57 | D101: -4615.09 | E101: 166949.48 | F101: 2-Actifs | G101: 243A | H101: _ | L101: =+B101 -> 249 | M101: =+A101 -> INV. PNEUS | N101: =+IF(OR($Q101=Parametres!$G$2,$Q101=Parametres!$G$3),I101,C101) -> 171564.57 | O101: =+IF(OR($Q101=Parametres!$G$2,$Q101=Parametres!$G$3),J101,D101) -> -4615.09 | P101: =+IF(OR($Q101=Parametres!$G$2,$Q101=Parametres!$G$3),K101,E101) -> 166949.48 | Q101: =+F101 -> 2-Actifs | R101: =+G101 -> 243A | S101: =+H101 -> _ | T101: =+VLOOKUP($L101,Data_Validation!$A:$D,1,0) -> 249 | U101: =+VLOOKUP($L101,Data_Validation!$A:$D,3,0) -> Bilan | V101: =+VLOOKUP($L101,Data_Validation!$A:$D,4,0) -> Inventaire Pièces, Pneus, Huile | W101: =+VLOOKUP($L101,Data_Validation!$A:$E,5,0) -> $ | X101: =+VLOOKUP($L101,Data_Validation!$A:$F,6,0) -> 0
A102: INV. SOUS TRAITANCE | B102: 247 | C102: -11003.28 | D102: -4284.37 | E102: -15287.65 | F102: 2-Actifs | G102: 247 | H102: _ | L102: =+B102 -> 247 | M102: =+A102 -> INV. SOUS TRAITANCE | N102: =+IF(OR($Q102=Parametres!$G$2,$Q102=Parametres!$G$3),I102,C102) -> -11003.28 | O102: =+IF(OR($Q102=Parametres!$G$2,$Q102=Parametres!$G$3),J102,D102) -> -4284.37 | P102: =+IF(OR($Q102=Parametres!$G$2,$Q102=Parametres!$G$3),K102,E102) -> -15287.65 | Q102: =+F102 -> 2-Actifs | R102: =+G102 -> 247 | S102: =+H102 -> _ | T102: =+VLOOKUP($L102,Data_Validation!$A:$D,1,0) -> 247 | U102: =+VLOOKUP($L102,Data_Validation!$A:$D,3,0) -> Bilan | V102: =+VLOOKUP($L102,Data_Validation!$A:$D,4,0) -> Sous-Traitance | W102: =+VLOOKUP($L102,Data_Validation!$A:$E,5,0) -> $ | X102: =+VLOOKUP($L102,Data_Validation!$A:$F,6,0) -> 0
A103: ASSURANCES PAYES D'AVANCE | B103: 270D | C103: 21427.03 | D103: -3571.16 | E103: 17855.87 | F103: 2-Actifs | G103: 270 | H103: _ | L103: =+B103 -> 270D | M103: =+A103 -> ASSURANCES PAYES D'AVANCE | N103: =+IF(OR($Q103=Parametres!$G$2,$Q103=Parametres!$G$3),I103,C103) -> 21427.03 | O103: =+IF(OR($Q103=Parametres!$G$2,$Q103=Parametres!$G$3),J103,D103) -> -3571.16 | P103: =+IF(OR($Q103=Parametres!$G$2,$Q103=Parametres!$G$3),K103,E103) -> 17855.87 | Q103: =+F103 -> 2-Actifs | R103: =+G103 -> 270 | S103: =+H103 -> _ | T103: =+VLOOKUP($L103,Data_Validation!$A:$D,1,0) -> 270D | U103: =+VLOOKUP($L103,Data_Validation!$A:$D,3,0) -> Bilan | V103: =+VLOOKUP($L103,Data_Validation!$A:$D,4,0) -> Frais Payés d'Avance | W103: =+VLOOKUP($L103,Data_Validation!$A:$E,5,0) -> $ | X103: =+VLOOKUP($L103,Data_Validation!$A:$F,6,0) -> 0
A104: REYNOLDS | B104: 274A | C104: 13029.32 | D104: -2968.53 | E104: 10060.79 | F104: 2-Actifs | G104: 274 | H104: _ | L104: =+B104 -> 274A | M104: =+A104 -> REYNOLDS | N104: =+IF(OR($Q104=Parametres!$G$2,$Q104=Parametres!$G$3),I104,C104) -> 13029.32 | O104: =+IF(OR($Q104=Parametres!$G$2,$Q104=Parametres!$G$3),J104,D104) -> -2968.53 | P104: =+IF(OR($Q104=Parametres!$G$2,$Q104=Parametres!$G$3),K104,E104) -> 10060.79 | Q104: =+F104 -> 2-Actifs | R104: =+G104 -> 274 | S104: =+H104 -> _ | T104: =+VLOOKUP($L104,Data_Validation!$A:$D,1,0) -> 274A | U104: =+VLOOKUP($L104,Data_Validation!$A:$D,3,0) -> Bilan | V104: =+VLOOKUP($L104,Data_Validation!$A:$D,4,0) -> Frais Payés d'Avance | W104: =+VLOOKUP($L104,Data_Validation!$A:$E,5,0) -> $ | X104: =+VLOOKUP($L104,Data_Validation!$A:$F,6,0) -> 0
A105: BONIS A/R MANUFACTURIER | B105: 221 | C105: 138835.43 | D105: -2685.97 | E105: 136149.46 | F105: 2-Actifs | G105: 221 | H105: _ | L105: =+B105 -> 221 | M105: =+A105 -> BONIS A/R MANUFACTURIER | N105: =+IF(OR($Q105=Parametres!$G$2,$Q105=Parametres!$G$3),I105,C105) -> 138835.43 | O105: =+IF(OR($Q105=Parametres!$G$2,$Q105=Parametres!$G$3),J105,D105) -> -2685.97 | P105: =+IF(OR($Q105=Parametres!$G$2,$Q105=Parametres!$G$3),K105,E105) -> 136149.46 | Q105: =+F105 -> 2-Actifs | R105: =+G105 -> 221 | S105: =+H105 -> _ | T105: =+VLOOKUP($L105,Data_Validation!$A:$D,1,0) -> 221 | U105: =+VLOOKUP($L105,Data_Validation!$A:$D,3,0) -> Bilan | V105: =+VLOOKUP($L105,Data_Validation!$A:$D,4,0) -> Recevables Manufacturier | W105: =+VLOOKUP($L105,Data_Validation!$A:$E,5,0) -> $ | X105: =+VLOOKUP($L105,Data_Validation!$A:$F,6,0) -> 0
A106: INVENTAIRE VEHICULES I | B106: 234 | C106: 428757.81 | D106: -1659.02 | E106: 427098.79 | F106: 2-Actifs | G106: 234 | H106: _ | L106: =+B106 -> 234 | M106: =+A106 -> INVENTAIRE VEHICULES I | N106: =+IF(OR($Q106=Parametres!$G$2,$Q106=Parametres!$G$3),I106,C106) -> 428757.81 | O106: =+IF(OR($Q106=Parametres!$G$2,$Q106=Parametres!$G$3),J106,D106) -> -1659.02 | P106: =+IF(OR($Q106=Parametres!$G$2,$Q106=Parametres!$G$3),K106,E106) -> 427098.79 | Q106: =+F106 -> 2-Actifs | R106: =+G106 -> 234 | S106: =+H106 -> _ | T106: =+VLOOKUP($L106,Data_Validation!$A:$D,1,0) -> 234 | U106: =+VLOOKUP($L106,Data_Validation!$A:$D,3,0) -> Bilan | V106: =+VLOOKUP($L106,Data_Validation!$A:$D,4,0) -> Inventaire Véhicules Neufs | W106: =+VLOOKUP($L106,Data_Validation!$A:$E,5,0) -> $ | X106: =+VLOOKUP($L106,Data_Validation!$A:$F,6,0) -> 0
... A523: FONDS PENSIONS - SERV. BMW | B523: 29E | C523: 9943.89 | D523: 1878.61 | E523: 11822.5 | F523: 7-Dépenses | G523: 29 | H523: _ | L523: =+B523 -> 29E | M523: =+A523 -> FONDS PENSIONS - SERV. BMW | N523: =+IF(OR($Q523=Parametres!$G$2,$Q523=Parametres!$G$3),I523,C523) -> 9943.89 | O523: =+IF(OR($Q523=Parametres!$G$2,$Q523=Parametres!$G$3),J523,D523) -> 1878.61 | P523: =+IF(OR($Q523=Parametres!$G$2,$Q523=Parametres!$G$3),K523,E523) -> 11822.5 | Q523: =+F523 -> 7-Dépenses | R523: =+G523 -> 29 | S523: =+H523 -> _ | T523: =+VLOOKUP($L523,Data_Validation!$A:$D,1,0) -> 29E | U523: =+VLOOKUP($L523,Data_Validation!$A:$D,3,0) -> Service | V523: =+VLOOKUP($L523,Data_Validation!$A:$D,4,0) -> csst | W523: =+VLOOKUP($L523,Data_Validation!$A:$E,5,0) -> $ | X523: =+VLOOKUP($L523,Data_Validation!$A:$F,6,0) -> 0
A524: REMISE CARTE CREDIT - SERV. BMW | B524: 73E | C524: 8206.15 | D524: 1880.81 | E524: 10086.96 | F524: 7-Dépenses | G524: 73 | H524: _ | L524: =+B524 -> 73E | M524: =+A524 -> REMISE CARTE CREDIT - SERV. BMW | N524: =+IF(OR($Q524=Parametres!$G$2,$Q524=Parametres!$G$3),I524,C524) -> 8206.15 | O524: =+IF(OR($Q524=Parametres!$G$2,$Q524=Parametres!$G$3),J524,D524) -> 1880.81 | P524: =+IF(OR($Q524=Parametres!$G$2,$Q524=Parametres!$G$3),K524,E524) -> 10086.96 | Q524: =+F524 -> 7-Dépenses | R524: =+G524 -> 73 | S524: =+H524 -> _ | T524: =+VLOOKUP($L524,Data_Validation!$A:$E,1,0) -> 73E | U524: =+VLOOKUP($L524,Data_Validation!$A:$E,3,0) -> Service | V524: =+VLOOKUP($L524,Data_Validation!$A:$E,4,0) -> frais bancaires | W524: =VLOOKUP($L524,Data_Validation!$A:$E,5,FALSE) -> $ | X524: =+VLOOKUP($L524,Data_Validation!$A:$F,6,0) -> 0
A525: PUBLICITE - SERV. BMW | B525: 16E | C525: 8991.05 | D525: 1957.4 | E525: 10948.45 | F525: 7-Dépenses | G525: 16 | H525: _ | L525: =+B525 -> 16E | M525: =+A525 -> PUBLICITE - SERV. BMW | N525: =+IF(OR($Q525=Parametres!$G$2,$Q525=Parametres!$G$3),I525,C525) -> 8991.05 | O525: =+IF(OR($Q525=Parametres!$G$2,$Q525=Parametres!$G$3),J525,D525) -> 1957.4 | P525: =+IF(OR($Q525=Parametres!$G$2,$Q525=Parametres!$G$3),K525,E525) -> 10948.45 | Q525: =+F525 -> 7-Dépenses | R525: =+G525 -> 16 | S525: =+H525 -> _ | T525: =+VLOOKUP($L525,Data_Validation!$A:$D,1,0) -> 16E | U525: =+VLOOKUP($L525,Data_Validation!$A:$D,3,0) -> Service | V525: =+VLOOKUP($L525,Data_Validation!$A:$D,4,0) -> Publicité 2 | W525: =+VLOOKUP($L525,Data_Validation!$A:$E,5,0) -> $ | X525: =+VLOOKUP($L525,Data_Validation!$A:$F,6,0) -> 0
A526: TRANSPORT - PIECE BMW | B526: 78G | C526: 6603.32 | D526: 1984.2 | E526: 8587.52 | F526: 7-Dépenses | G526: 78 | H526: _ | L526: =+B526 -> 78G | M526: =+A526 -> TRANSPORT - PIECE BMW | N526: =+IF(OR($Q526=Parametres!$G$2,$Q526=Parametres!$G$3),I526,C526) -> 6603.32 | O526: =+IF(OR($Q526=Parametres!$G$2,$Q526=Parametres!$G$3),J526,D526) -> 1984.2 | P526: =+IF(OR($Q526=Parametres!$G$2,$Q526=Parametres!$G$3),K526,E526) -> 8587.52 | Q526: =+F526 -> 7-Dépenses | R526: =+G526 -> 78 | S526: =+H526 -> _ | T526: =+VLOOKUP($L526,Data_Validation!$A:$D,1,0) -> 78G | U526: =+VLOOKUP($L526,Data_Validation!$A:$D,3,0) -> pièces | V526: =+VLOOKUP($L526,Data_Validation!$A:$D,4,0) -> Frais postaux | W526: =+VLOOKUP($L526,Data_Validation!$A:$E,5,0) -> $ | X526: =+VLOOKUP($L526,Data_Validation!$A:$F,6,0) -> 0
A527: SAL. ADMIN. - PIECE BMW | B527: 22G | C527: 9465.05 | D527: 2062.76 | E527: 11527.81 | F527: 7-Dépenses | G527: 22 | H527: _ | L527: =+B527 -> 22G | M527: =+A527 -> SAL. ADMIN. - PIECE BMW | N527: =+IF(OR($Q527=Parametres!$G$2,$Q527=Parametres!$G$3),I527,C527) -> 9465.05 | O527: =+IF(OR($Q527=Parametres!$G$2,$Q527=Parametres!$G$3),J527,D527) -> 2062.76 | P527: =+IF(OR($Q527=Parametres!$G$2,$Q527=Parametres!$G$3),K527,E527) -> 11527.81 | Q527: =+F527 -> 7-Dépenses | R527: =+G527 -> 22 | S527: =+H527 -> _ | T527: =+VLOOKUP($L527,Data_Validation!$A:$D,1,0) -> 22G | U527: =+VLOOKUP($L527,Data_Validation!$A:$D,3,0) -> Pièces | V527: =+VLOOKUP($L527,Data_Validation!$A:$D,4,0) -> Salaires commis | W527: =+VLOOKUP($L527,Data_Validation!$A:$E,5,0) -> $ | X527: =+VLOOKUP($L527,Data_Validation!$A:$F,6,0) -> 0
A528: FRAIS REPRESENTATION - NEUF BMW | B528: 71A | C528: 10700.11 | D528: 2184.94 | E528: 12885.05 | F528: 7-Dépenses | G528: 71 | H528: _ | L528: =+B528 -> 71A | M528: =+A528 -> FRAIS REPRESENTATION - NEUF BMW | N528: =+IF(OR($Q528=Parametres!$G$2,$Q528=Parametres!$G$3),I528,C528) -> 10700.11 | O528: =+IF(OR($Q528=Parametres!$G$2,$Q528=Parametres!$G$3),J528,D528) -> 2184.94 | P528: =+IF(OR($Q528=Parametres!$G$2,$Q528=Parametres!$G$3),K528,E528) -> 12885.05 | Q528: =+F528 -> 7-Dépenses | R528: =+G528 -> 71 | S528: =+H528 -> _ | T528: =+VLOOKUP($L528,Data_Validation!$A:$D,1,0) -> 71A | U528: =+VLOOKUP($L528,Data_Validation!$A:$D,3,0) -> Véhicules neufs | V528: =+VLOOKUP($L528,Data_Validation!$A:$D,4,0) -> Frais de déplacement | W528: =+VLOOKUP($L528,Data_Validation!$A:$E,5,0) -> $ | X528: =+VLOOKUP($L528,Data_Validation!$A:$F,6,0) -> 0
A529: AVANT. SOCIAUX - USAGE BMW | B529: 27C | C529: 8987.38 | D529: 2237.79 | E529: 11225.17 | F529: 7-Dépenses | G529: 27 | H529: _ | L529: =+B529 -> 27C | M529: =+A529 -> AVANT. SOCIAUX - USAGE BMW | N529: =+IF(OR($Q529=Parametres!$G$2,$Q529=Parametres!$G$3),I529,C529) -> 8987.38 | O529: =+IF(OR($Q529=Parametres!$G$2,$Q529=Parametres!$G$3),J529,D529) -> 2237.79 | P529: =+IF(OR($Q529=Parametres!$G$2,$Q529=Parametres!$G$3),K529,E529) -> 11225.17 | Q529: =+F529 -> 7-Dépenses | R529: =+G529 -> 27 | S529: =+H529 -> _ | T529: =+VLOOKUP($L529,Data_Validation!$A:$D,1,0) -> 27C | U529: =+VLOOKUP($L529,Data_Validation!$A:$D,3,0) -> Véhicules usagés | V529: =+VLOOKUP($L529,Data_Validation!$A:$D,4,0) -> Bénéfices marginaux | W529: =+VLOOKUP($L529,Data_Validation!$A:$E,5,0) -> $ | X529: =+VLOOKUP($L529,Data_Validation!$A:$F,6,0) -> 0
A530: TRAV. GRACIEUX - NEUF BMW | B530: 68A | C530: 4022.95 | D530: 2286.98 | E530: 6309.93 | F530: 7-Dépenses | G530: 68 | H530: _ | L530: =+B530 -> 68A | M530: =+A530 -> TRAV. GRACIEUX - NEUF BMW | N530: =+IF(OR($Q530=Parametres!$G$2,$Q530=Parametres!$G$3),I530,C530) -> 4022.95 | O530: =+IF(OR($Q530=Parametres!$G$2,$Q530=Parametres!$G$3),J530,D530) -> 2286.98 | P530: =+IF(OR($Q530=Parametres!$G$2,$Q530=Parametres!$G$3),K530,E530) -> 6309.93 | Q530: =+F530 -> 7-Dépenses | R530: =+G530 -> 68 | S530: =+H530 -> _ | T530: =+VLOOKUP($L530,Data_Validation!$A:$D,1,0) -> 68A | U530: =+VLOOKUP($L530,Data_Validation!$A:$D,3,0) -> Véhicules neufs | V530: =+VLOOKUP($L530,Data_Validation!$A:$D,4,0) -> service gratuit 1 | W530: =+VLOOKUP($L530,Data_Validation!$A:$E,5,0) -> $ | X530: =+VLOOKUP($L530,Data_Validation!$A:$F,6,0) -> 0
A531: SAL. PROPRIETAIRE - USAGE BMW | B531: 20C | C531: 12351.97 | D531: 2409.82 | E531: 14761.79 | F531: 7-Dépenses | G531: 20 | H531: _ | L531: =+B531 -> 20C | M531: =+A531 -> SAL. PROPRIETAIRE - USAGE BMW | N531: =+IF(OR($Q531=Parametres!$G$2,$Q531=Parametres!$G$3),I531,C531) -> 12351.97 | O531: =+IF(OR($Q531=Parametres!$G$2,$Q531=Parametres!$G$3),J531,D531) -> 2409.82 | P531: =+IF(OR($Q531=Parametres!$G$2,$Q531=Parametres!$G$3),K531,E531) -> 14761.79 | Q531: =+F531 -> 7-Dépenses | R531: =+G531 -> 20 | S531: =+H531 -> _ | T531: =+VLOOKUP($L531,Data_Validation!$A:$D,1,0) -> 20C | U531: =+VLOOKUP($L531,Data_Validation!$A:$D,3,0) -> Véhicules usagés | V531: =+VLOOKUP($L531,Data_Validation!$A:$D,4,0) -> Salaires propriétaire | W531: =+VLOOKUP($L531,Data_Validation!$A:$E,5,0) -> $ | X531: =+VLOOKUP($L531,Data_Validation!$A:$F,6,0) -> 0
A532: DEPREC. EQUIP. - SERV. BMW | B532: 91E | C532: 12115.95 | D532: 2423.19 | E532: 14539.14 | F532: 7-Dépenses | G532: 91 | H532: _ | L532: =+B532 -> 91E | M532: =+A532 -> DEPREC. EQUIP. - SERV. BMW | N532: =+IF(OR($Q532=Parametres!$G$2,$Q532=Parametres!$G$3),I532,C532) -> 12115.95 | O532: =+IF(OR($Q532=Parametres!$G$2,$Q532=Parametres!$G$3),J532,D532) -> 2423.19 | P532: =+IF(OR($Q532=Parametres!$G$2,$Q532=Parametres!$G$3),K532,E532) -> 14539.14 | Q532: =+F532 -> 7-Dépenses | R532: =+G532 -> 91 | S532: =+H532 -> _ | T532: =+VLOOKUP($L532,Data_Validation!$A:$D,1,0) -> 91E | U532: =+VLOOKUP($L532,Data_Validation!$A:$D,3,0) -> Service | V532: =+VLOOKUP($L532,Data_Validation!$A:$D,4,0) -> amortissement | W532: =+VLOOKUP($L532,Data_Validation!$A:$E,5,0) -> $ | X532: =+VLOOKUP($L532,Data_Validation!$A:$F,6,0) -> 0
A533: TAXES BATISSE - NEUF BMW | B533: 84A | C533: 12693.25 | D533: 2538.65 | E533: 15231.9 | F533: 7-Dépenses | G533: 84 | H533: _ | L533: =+B533 -> 84A | M533: =+A533 -> TAXES BATISSE - NEUF BMW | N533: =+IF(OR($Q533=Parametres!$G$2,$Q533=Parametres!$G$3),I533,C533) -> 12693.25 | O533: =+IF(OR($Q533=Parametres!$G$2,$Q533=Parametres!$G$3),J533,D533) -> 2538.65 | P533: =+IF(OR($Q533=Parametres!$G$2,$Q533=Parametres!$G$3),K533,E533) -> 15231.9 | Q533: =+F533 -> 7-Dépenses | R533: =+G533 -> 84 | S533: =+H533 -> _ | T533: =+VLOOKUP($L533,Data_Validation!$A:$D,1,0) -> 84A | U533: =+VLOOKUP($L533,Data_Validation!$A:$D,3,0) -> Véhicules neufs | V533: =+VLOOKUP($L533,Data_Validation!$A:$D,4,0) -> Taxes foncières | W533: =+VLOOKUP($L533,Data_Validation!$A:$E,5,0) -> $ | X533: =+VLOOKUP($L533,Data_Validation!$A:$F,6,0) -> 0
A534: AVANT. SOCIAUX - PIECE BMW | B534: 27G | C534: 12544.18 | D534: 2549.7 | E534: 15093.88 | F534: 7-Dépenses | G534: 27 | H534: _ | L534: =+B534 -> 27G | M534: =+A534 -> AVANT. SOCIAUX - PIECE BMW | N534: =+IF(OR($Q534=Parametres!$G$2,$Q534=Parametres!$G$3),I534,C534) -> 12544.18 | O534: =+IF(OR($Q534=Parametres!$G$2,$Q534=Parametres!$G$3),J534,D534) -> 2549.7 | P534: =+IF(OR($Q534=Parametres!$G$2,$Q534=Parametres!$G$3),K534,E534) -> 15093.88 | Q534: =+F534 -> 7-Dépenses | R534: =+G534 -> 27 | S534: =+H534 -> _ | T534: =+VLOOKUP($L534,Data_Validation!$A:$D,1,0) -> 27G | U534: =+VLOOKUP($L534,Data_Validation!$A:$D,3,0) -> Pièces | V534: =+VLOOKUP($L534,Data_Validation!$A:$D,4,0) -> Bénéfices marginaux | W534: =+VLOOKUP($L534,Data_Validation!$A:$E,5,0) -> $ | X534: =+VLOOKUP($L534,Data_Validation!$A:$F,6,0) -> 0
A535: CHAUFF. ELECT. EAU - NEUF BMW | B535: 87A | C535: 13675.87 | D535: 2588.02 | E535: 16263.89 | F535: 7-Dépenses | G535: 87 | H535: _ | L535: =+B535 -> 87A | M535: =+A535 -> CHAUFF. ELECT. EAU - NEUF BMW | N535: =+IF(OR($Q535=Parametres!$G$2,$Q535=Parametres!$G$3),I535,C535) -> 13675.87 | O535: =+IF(OR($Q535=Parametres!$G$2,$Q535=Parametres!$G$3),J535,D535) -> 2588.02 | P535: =+IF(OR($Q535=Parametres!$G$2,$Q535=Parametres!$G$3),K535,E535) -> 16263.89 | Q535: =+F535 -> 7-Dépenses | R535: =+G535 -> 87 | S535: =+H535 -> _ | T535: =+VLOOKUP($L535,Data_Validation!$A:$D,1,0) -> 87A | U535: =+VLOOKUP($L535,Data_Validation!$A:$D,3,0) -> Véhicules neufs | V535: =+VLOOKUP($L535,Data_Validation!$A:$D,4,0) -> Chauffage, éclairage | W535: =+VLOOKUP($L535,Data_Validation!$A:$E,5,0) -> $ | X535: =+VLOOKUP($L535,Data_Validation!$A:$F,6,0) -> 0
A536: FRAIS INFORMATIQUE - PIECE BMW | B536: 69G | C536: 12439.65 | D536: 2630.81 | E536: 15070.46 | F536: 7-Dépenses | G536: 69 | H536: _ | L536: =+B536 -> 69G | M536: =+A536 -> FRAIS INFORMATIQUE - PIECE BMW | N536: =+IF(OR($Q536=Parametres!$G$2,$Q536=Parametres!$G$3),I536,C536) -> 12439.65 | O536: =+IF(OR($Q536=Parametres!$G$2,$Q536=Parametres!$G$3),J536,D536) -> 2630.81 | P536: =+IF(OR($Q536=Parametres!$G$2,$Q536=Parametres!$G$3),K536,E536) -> 15070.46 | Q536: =+F536 -> 7-Dépenses | R536: =+G536 -> 69 | S536: =+H536 -> _ | T536: =+VLOOKUP($L536,Data_Validation!$A:$D,1,0) -> 69G | U536: =+VLOOKUP($L536,Data_Validation!$A:$D,3,0) -> pièces | V536: =+VLOOKUP($L536,Data_Validation!$A:$D,4,0) -> informatique | W536: =+VLOOKUP($L536,Data_Validation!$A:$E,5,0) -> $ | X536: =+VLOOKUP($L536,Data_Validation!$A:$F,6,0) -> 0
... A591: AUTRES DEDUCTIONS | B591: 855 | C591: 0 | D591: 10 | E591: 10 | F591: 9-Autres déductions | G591: 855 | H591: _ | L591: =+B591 -> 855 | M591: =+A591 -> AUTRES DEDUCTIONS | N591: =+IF(OR($Q591=Parametres!$G$2,$Q591=Parametres!$G$3),I591,C591) -> 0 | O591: =+IF(OR($Q591=Parametres!$G$2,$Q591=Parametres!$G$3),J591,D591) -> 10 | P591: =+IF(OR($Q591=Parametres!$G$2,$Q591=Parametres!$G$3),K591,E591) -> 10 | Q591: =+F591 -> 9-Autres déductions | R591: =+G591 -> 855 | S591: =+H591 -> _ | T591: =+VLOOKUP($L591,Data_Validation!$A:$D,1,0) -> 855 | U591: =+VLOOKUP($L591,Data_Validation!$A:$D,3,0) -> TOTAL DES REVENUS ET DÉPENSES | V591: =+VLOOKUP($L591,Data_Validation!$A:$D,4,0) -> Revenus autres | W591: =+VLOOKUP($L591,Data_Validation!$A:$E,5,0) -> $ | X591: =+VLOOKUP($L591,Data_Validation!$A:$F,6,0) -> 0
A592: # DE VOITURES NEUVES BMW | B592: 230@ | F592: 10-Compte compteur | G592: 230 | H592: _ | I592: 21 | J592: 2 | K592: 23 | L592: =+B592 -> 230@ | M592: =+A592 -> # DE VOITURES NEUVES BMW | N592: =+IF(OR($Q592=Parametres!$G$2,$Q592=Parametres!$G$3),I592,C592) -> 21 | O592: =+IF(OR($Q592=Parametres!$G$2,$Q592=Parametres!$G$3),J592,D592) -> 2 | P592: =+IF(OR($Q592=Parametres!$G$2,$Q592=Parametres!$G$3),K592,E592) -> 23 | Q592: =+F592 -> 10-Compte compteur | R592: =+G592 -> 230 | S592: =+H592 -> _ | T592: =+VLOOKUP($L592,Data_Validation!$A:$D,1,0) -> 230@ | U592: =+VLOOKUP($L592,Data_Validation!$A:$D,3,0) -> Autres | V592: =+VLOOKUP($L592,Data_Validation!$A:$D,4,0) -> 0 | W592: =+VLOOKUP($L592,Data_Validation!$A:$E,5,0) -> 0 | X592: =+VLOOKUP($L592,Data_Validation!$A:$F,6,0) -> 0
A593: # DE CAMIONS NEUFS BMW | B593: 232@ | F593: 10-Compte compteur | G593: 232 | H593: _ | I593: 40 | J593: 19 | K593: 59 | L593: =+B593 -> 232@ | M593: =+A593 -> # DE CAMIONS NEUFS BMW | N593: =+IF(OR($Q593=Parametres!$G$2,$Q593=Parametres!$G$3),I593,C593) -> 40 | O593: =+IF(OR($Q593=Parametres!$G$2,$Q593=Parametres!$G$3),J593,D593) -> 19 | P593: =+IF(OR($Q593=Parametres!$G$2,$Q593=Parametres!$G$3),K593,E593) -> 59 | Q593: =+F593 -> 10-Compte compteur | R593: =+G593 -> 232 | S593: =+H593 -> _ | T593: =+VLOOKUP($L593,Data_Validation!$A:$D,1,0) -> 232@ | U593: =+VLOOKUP($L593,Data_Validation!$A:$D,3,0) -> Autres | V593: =+VLOOKUP($L593,Data_Validation!$A:$D,4,0) -> 0 | W593: =+VLOOKUP($L593,Data_Validation!$A:$E,5,0) -> 0 | X593: =+VLOOKUP($L593,Data_Validation!$A:$F,6,0) -> 0
A594: # OF INVENTAIRE VEHICULES I | B594: 234@ | F594: 10-Compte compteur | G594: 234 | H594: _ | I594: 4 | J594: 0 | K594: 4 | L594: =+B594 -> 234@ | M594: =+A594 -> # OF INVENTAIRE VEHICULES I | N594: =+IF(OR($Q594=Parametres!$G$2,$Q594=Parametres!$G$3),I594,C594) -> 4 | O594: =+IF(OR($Q594=Parametres!$G$2,$Q594=Parametres!$G$3),J594,D594) -> 0 | P594: =+IF(OR($Q594=Parametres!$G$2,$Q594=Parametres!$G$3),K594,E594) -> 4 | Q594: =+F594 -> 10-Compte compteur | R594: =+G594 -> 234 | S594: =+H594 -> _ | T594: =+VLOOKUP($L594,Data_Validation!$A:$D,1,0) -> 234@ | U594: =+VLOOKUP($L594,Data_Validation!$A:$D,3,0) -> Autres | V594: =+VLOOKUP($L594,Data_Validation!$A:$D,4,0) -> 0 | W594: =+VLOOKUP($L594,Data_Validation!$A:$E,5,0) -> 0 | X594: =+VLOOKUP($L594,Data_Validation!$A:$F,6,0) -> 0
A595: # DE VOITURES USAGEES BMW | B595: 240A@ | F595: 10-Compte compteur | G595: 240A | H595: _ | I595: 20 | J595: -5 | K595: 15 | L595: =+B595 -> 240A@ | M595: =+A595 -> # DE VOITURES USAGEES BMW | N595: =+IF(OR($Q595=Parametres!$G$2,$Q595=Parametres!$G$3),I595,C595) -> 20 | O595: =+IF(OR($Q595=Parametres!$G$2,$Q595=Parametres!$G$3),J595,D595) -> -5 | P595: =+IF(OR($Q595=Parametres!$G$2,$Q595=Parametres!$G$3),K595,E595) -> 15 | Q595: =+F595 -> 10-Compte compteur | R595: =+G595 -> 240A | S595: =+H595 -> _ | T595: =+VLOOKUP($L595,Data_Validation!$A:$D,1,0) -> 240A@ | U595: =+VLOOKUP($L595,Data_Validation!$A:$D,3,0) -> Autres | V595: =+VLOOKUP($L595,Data_Validation!$A:$D,4,0) -> 0 | W595: =+VLOOKUP($L595,Data_Validation!$A:$E,5,0) -> 0 | X595: =+VLOOKUP($L595,Data_Validation!$A:$F,6,0) -> 0
A596: # DE VEHICULES USAGES AUTRES | B596: 240C@ | F596: 10-Compte compteur | G596: 240C | H596: _ | I596: 23 | J596: 2 | K596: 25 | L596: =+B596 -> 240C@ | M596: =+A596 -> # DE VEHICULES USAGES AUTRES | N596: =+IF(OR($Q596=Parametres!$G$2,$Q596=Parametres!$G$3),I596,C596) -> 23 | O596: =+IF(OR($Q596=Parametres!$G$2,$Q596=Parametres!$G$3),J596,D596) -> 2 | P596: =+IF(OR($Q596=Parametres!$G$2,$Q596=Parametres!$G$3),K596,E596) -> 25 | Q596: =+F596 -> 10-Compte compteur | R596: =+G596 -> 240C | S596: =+H596 -> _ | T596: =+VLOOKUP($L596,Data_Validation!$A:$D,1,0) -> 240C@ | U596: =+VLOOKUP($L596,Data_Validation!$A:$D,3,0) -> Autres | V596: =+VLOOKUP($L596,Data_Validation!$A:$D,4,0) -> 0 | W596: =+VLOOKUP($L596,Data_Validation!$A:$E,5,0) -> 0 | X596: =+VLOOKUP($L596,Data_Validation!$A:$F,6,0) -> 0
A597: # DE CAMIONS USAGES BMW | B597: 242A@ | F597: 10-Compte compteur | G597: 242A | H597: _ | I597: 36 | J597: 0 | K597: 36 | L597: =+B597 -> 242A@ | M597: =+A597 -> # DE CAMIONS USAGES BMW | N597: =+IF(OR($Q597=Parametres!$G$2,$Q597=Parametres!$G$3),I597,C597) -> 36 | O597: =+IF(OR($Q597=Parametres!$G$2,$Q597=Parametres!$G$3),J597,D597) -> 0 | P597: =+IF(OR($Q597=Parametres!$G$2,$Q597=Parametres!$G$3),K597,E597) -> 36 | Q597: =+F597 -> 10-Compte compteur | R597: =+G597 -> 242A | S597: =+H597 -> _ | T597: =+VLOOKUP($L597,Data_Validation!$A:$D,1,0) -> 242A@ | U597: =+VLOOKUP($L597,Data_Validation!$A:$D,3,0) -> Autres | V597: =+VLOOKUP($L597,Data_Validation!$A:$D,4,0) -> 0 | W597: =+VLOOKUP($L597,Data_Validation!$A:$E,5,0) -> 0 | X597: =+VLOOKUP($L597,Data_Validation!$A:$F,6,0) -> 0
A598: # DE VTE - M240I COUPE | B598: 401A@ | F598: 10-Compte compteur | G598: 401A | H598: _ | I598: -1 | J598: 0 | K598: -1 | L598: =+B598 -> 401A@ | M598: =+A598 -> # DE VTE - M240I COUPE | N598: =+IF(OR($Q598=Parametres!$G$2,$Q598=Parametres!$G$3),I598,C598) -> -1 | O598: =+IF(OR($Q598=Parametres!$G$2,$Q598=Parametres!$G$3),J598,D598) -> 0 | P598: =+IF(OR($Q598=Parametres!$G$2,$Q598=Parametres!$G$3),K598,E598) -> -1 | Q598: =+F598 -> 10-Compte compteur | R598: =+G598 -> 401A | S598: =+H598 -> _ | T598: =+VLOOKUP($L598,Data_Validation!$A:$D,1,0) -> 401A@ | U598: =+VLOOKUP($L598,Data_Validation!$A:$D,3,0) -> Véhicules neufs | V598: =+VLOOKUP($L598,Data_Validation!$A:$D,4,0) -> Autos détail | W598: =+VLOOKUP($L598,Data_Validation!$A:$E,5,0) -> nb | X598: =+VLOOKUP($L598,Data_Validation!$A:$F,6,0) -> 0
A599: M2 CS | B599: 401G@ | F599: 10-Compte compteur | G599: 401 | H599: _ | I599: -1 | J599: 0 | K599: -1 | L599: =+B599 -> 401G@ | M599: =+A599 -> M2 CS | N599: =+IF(OR($Q599=Parametres!$G$2,$Q599=Parametres!$G$3),I599,C599) -> -1 | O599: =+IF(OR($Q599=Parametres!$G$2,$Q599=Parametres!$G$3),J599,D599) -> 0 | P599: =+IF(OR($Q599=Parametres!$G$2,$Q599=Parametres!$G$3),K599,E599) -> -1 | Q599: =+F599 -> 10-Compte compteur | R599: =+G599 -> 401 | S599: =+H599 -> _ | T599: =+VLOOKUP($L599,Data_Validation!$A:$D,1,0) -> 401G@ | U599: =+VLOOKUP($L599,Data_Validation!$A:$D,3,0) -> Véhicules neufs | V599: =+VLOOKUP($L599,Data_Validation!$A:$D,4,0) -> Autos détail | W599: =+VLOOKUP($L599,Data_Validation!$A:$E,5,0) -> NB | X599: =+VLOOKUP($L599,Data_Validation!$A:$F,6,0) -> 0
A600: IX XDRIVE60 | B600: 402E@ | F600: 10-Compte compteur | G600: 402 | H600: _ | I600: -1 | J600: -1 | K600: -2 | L600: =+B600 -> 402E@ | M600: =+A600 -> IX XDRIVE60 | N600: =+IF(OR($Q600=Parametres!$G$2,$Q600=Parametres!$G$3),I600,C600) -> -1 | O600: =+IF(OR($Q600=Parametres!$G$2,$Q600=Parametres!$G$3),J600,D600) -> -1 | P600: =+IF(OR($Q600=Parametres!$G$2,$Q600=Parametres!$G$3),K600,E600) -> -2 | Q600: =+F600 -> 10-Compte compteur | R600: =+G600 -> 402 | S600: =+H600 -> _ | T600: =+VLOOKUP($L600,Data_Validation!$A:$D,1,0) -> 402E@ | U600: =+VLOOKUP($L600,Data_Validation!$A:$D,3,0) -> Véhicules neufs | V600: =+VLOOKUP($L600,Data_Validation!$A:$D,4,0) -> Camions détail | W600: =+VLOOKUP($L600,Data_Validation!$A:$E,5,0) -> NB | X600: =+VLOOKUP($L600,Data_Validation!$A:$F,6,0) -> 0
A601: # OF VTES -i4 M50i XDRIVE GRAN COUPE | B601: 403I@ | F601: 10-Compte compteur | G601: 403I | H601: _ | I601: -2 | J601: 0 | K601: -2 | L601: =+B601 -> 403I@ | M601: =+A601 -> # OF VTES -i4 M50i XDRIVE GRAN COUPE | N601: =+IF(OR($Q601=Parametres!$G$2,$Q601=Parametres!$G$3),I601,C601) -> -2 | O601: =+IF(OR($Q601=Parametres!$G$2,$Q601=Parametres!$G$3),J601,D601) -> 0 | P601: =+IF(OR($Q601=Parametres!$G$2,$Q601=Parametres!$G$3),K601,E601) -> -2 | Q601: =+F601 -> 10-Compte compteur | R601: =+G601 -> 403I | S601: =+H601 -> _ | T601: =+VLOOKUP($L601,Data_Validation!$A:$D,1,0) -> 403I@ | U601: =+VLOOKUP($L601,Data_Validation!$A:$D,3,0) -> Véhicules neufs | V601: =+VLOOKUP($L601,Data_Validation!$A:$D,4,0) -> Autos détail | W601: =+VLOOKUP($L601,Data_Validation!$A:$E,5,0) -> NB | X601: =+VLOOKUP($L601,Data_Validation!$A:$F,6,0) -> 0
A602: I4 XDRIVE40 GRAN COUPE | B602: 404K@ | F602: 10-Compte compteur | G602: 404 | H602: _ | I602: 0 | J602: -1 | K602: -1 | L602: =+B602 -> 404K@ | M602: =+A602 -> I4 XDRIVE40 GRAN COUPE | N602: =+IF(OR($Q602=Parametres!$G$2,$Q602=Parametres!$G$3),I602,C602) -> 0 | O602: =+IF(OR($Q602=Parametres!$G$2,$Q602=Parametres!$G$3),J602,D602) -> -1 | P602: =+IF(OR($Q602=Parametres!$G$2,$Q602=Parametres!$G$3),K602,E602) -> -1 | Q602: =+F602 -> 10-Compte compteur | R602: =+G602 -> 404 | S602: =+H602 -> _ | T602: =+VLOOKUP($L602,Data_Validation!$A:$D,1,0) -> 404K@ | U602: =+VLOOKUP($L602,Data_Validation!$A:$D,3,0) -> Véhicules neufs | V602: =+VLOOKUP($L602,Data_Validation!$A:$D,4,0) -> Autos détail | W602: =+VLOOKUP($L602,Data_Validation!$A:$E,5,0) -> NB | X602: =+VLOOKUP($L602,Data_Validation!$A:$F,6,0) -> 0
A603: M4 CABRIOLET | B603: 405H@ | F603: 10-Compte compteur | G603: 405 | H603: _ | I603: -2 | J603: 0 | K603: -2 | L603: =+B603 -> 405H@ | M603: =+A603 -> M4 CABRIOLET | N603: =+IF(OR($Q603=Parametres!$G$2,$Q603=Parametres!$G$3),I603,C603) -> -2 | O603: =+IF(OR($Q603=Parametres!$G$2,$Q603=Parametres!$G$3),J603,D603) -> 0 | P603: =+IF(OR($Q603=Parametres!$G$2,$Q603=Parametres!$G$3),K603,E603) -> -2 | Q603: =+F603 -> 10-Compte compteur | R603: =+G603 -> 405 | S603: =+H603 -> _ | T603: =+VLOOKUP($L603,Data_Validation!$A:$D,1,0) -> 405H@ | U603: =+VLOOKUP($L603,Data_Validation!$A:$D,3,0) -> Véhicules neufs | V603: =+VLOOKUP($L603,Data_Validation!$A:$D,4,0) -> Autos détail | W603: =+VLOOKUP($L603,Data_Validation!$A:$E,5,0) -> NB | X603: =+VLOOKUP($L603,Data_Validation!$A:$F,6,0) -> 0
... A714: # DE VTE - HUILE & GRAISSE | B714: 489B@ | F714: 10-Compte compteur | G714: 489A | H714: _ | I714: -487 | J714: -137 | K714: -624 | L714: =+B714 -> 489B@ | M714: =+A714 -> # DE VTE - HUILE & GRAISSE | N714: =+IF(OR($Q714=Parametres!$G$2,$Q714=Parametres!$G$3),I714,C714) -> -487 | O714: =+IF(OR($Q714=Parametres!$G$2,$Q714=Parametres!$G$3),J714,D714) -> -137 | P714: =+IF(OR($Q714=Parametres!$G$2,$Q714=Parametres!$G$3),K714,E714) -> -624 | Q714: =+F714 -> 10-Compte compteur | R714: =+G714 -> 489A | S714: =+H714 -> _ | T714: =+VLOOKUP($L714,Data_Validation!$A:$D,1,0) -> 489B@ | U714: =+VLOOKUP($L714,Data_Validation!$A:$D,3,0) -> pièces | V714: =+VLOOKUP($L714,Data_Validation!$A:$D,4,0) -> Huiles et Graisse | W714: =+VLOOKUP($L714,Data_Validation!$A:$E,5,0) -> nb | X714: =+VLOOKUP($L714,Data_Validation!$A:$F,6,0) -> 0
L715: =+B715 -> 0 | M715: =+A715 -> 0 | N715: =+IF(OR($Q715=Parametres!$G$2,$Q715=Parametres!$G$3),I715,C715) -> 0 | O715: =+IF(OR($Q715=Parametres!$G$2,$Q715=Parametres!$G$3),J715,D715) -> 0 | P715: =+IF(OR($Q715=Parametres!$G$2,$Q715=Parametres!$G$3),K715,E715) -> 0 | Q715: =+F715 -> 0 | R715: =+G715 -> 0 | S715: =+H715 -> 0 | T715: =+VLOOKUP($L715,Data_Validation!$A:$D,1,0) -> #N/A | U715: =+VLOOKUP($L715,Data_Validation!$A:$D,3,0) -> #N/A | V715: =+VLOOKUP($L715,Data_Validation!$A:$D,4,0) -> #N/A | W715: =+VLOOKUP($L715,Data_Validation!$A:$E,5,0) -> #N/A | X715: =+VLOOKUP($L715,Data_Validation!$A:$F,6,0) -> #N/A
L716: =+B716 -> 0 | M716: =+A716 -> 0 | N716: =+IF(OR($Q716=Parametres!$G$2,$Q716=Parametres!$G$3),I716,C716) -> 0 | O716: =+IF(OR($Q716=Parametres!$G$2,$Q716=Parametres!$G$3),J716,D716) -> 0 | P716: =+IF(OR($Q716=Parametres!$G$2,$Q716=Parametres!$G$3),K716,E716) -> 0 | Q716: =+F716 -> 0 | R716: =+G716 -> 0 | S716: =+H716 -> 0 | T716: =+VLOOKUP($L716,Data_Validation!$A:$D,1,0) -> #N/A | U716: =+VLOOKUP($L716,Data_Validation!$A:$D,3,0) -> #N/A | V716: =+VLOOKUP($L716,Data_Validation!$A:$D,4,0) -> #N/A | W716: =+VLOOKUP($L716,Data_Validation!$A:$E,5,0) -> #N/A | X716: =+VLOOKUP($L716,Data_Validation!$A:$F,6,0) -> #N/A
L717: =+B717 -> 0 | M717: =+A717 -> 0 | N717: =+IF(OR($Q717=Parametres!$G$2,$Q717=Parametres!$G$3),I717,C717) -> 0 | O717: =+IF(OR($Q717=Parametres!$G$2,$Q717=Parametres!$G$3),J717,D717) -> 0 | P717: =+IF(OR($Q717=Parametres!$G$2,$Q717=Parametres!$G$3),K717,E717) -> 0 | Q717: =+F717 -> 0 | R717: =+G717 -> 0 | S717: =+H717 -> 0 | T717: =+VLOOKUP($L717,Data_Validation!$A:$D,1,0) -> #N/A | U717: =+VLOOKUP($L717,Data_Validation!$A:$D,3,0) -> #N/A | V717: =+VLOOKUP($L717,Data_Validation!$A:$D,4,0) -> #N/A | W717: =+VLOOKUP($L717,Data_Validation!$A:$E,5,0) -> #N/A | X717: =+VLOOKUP($L717,Data_Validation!$A:$F,6,0) -> #N/A
L718: =+B718 -> 0 | M718: =+A718 -> 0 | N718: =+IF(OR($Q718=Parametres!$G$2,$Q718=Parametres!$G$3),I718,C718) -> 0 | O718: =+IF(OR($Q718=Parametres!$G$2,$Q718=Parametres!$G$3),J718,D718) -> 0 | P718: =+IF(OR($Q718=Parametres!$G$2,$Q718=Parametres!$G$3),K718,E718) -> 0 | Q718: =+F718 -> 0 | R718: =+G718 -> 0 | S718: =+H718 -> 0 | T718: =+VLOOKUP($L718,Data_Validation!$A:$D,1,0) -> #N/A | U718: =+VLOOKUP($L718,Data_Validation!$A:$D,3,0) -> #N/A | V718: =+VLOOKUP($L718,Data_Validation!$A:$D,4,0) -> #N/A | W718: =+VLOOKUP($L718,Data_Validation!$A:$E,5,0) -> #N/A | X718: =+VLOOKUP($L718,Data_Validation!$A:$F,6,0) -> #N/A
L719: =+B719 -> 0 | M719: =+A719 -> 0 | N719: =+IF(OR($Q719=Parametres!$G$2,$Q719=Parametres!$G$3),I719,C719) -> 0 | O719: =+IF(OR($Q719=Parametres!$G$2,$Q719=Parametres!$G$3),J719,D719) -> 0 | P719: =+IF(OR($Q719=Parametres!$G$2,$Q719=Parametres!$G$3),K719,E719) -> 0 | Q719: =+F719 -> 0 | R719: =+G719 -> 0 | S719: =+H719 -> 0 | T719: =+VLOOKUP($L719,Data_Validation!$A:$D,1,0) -> #N/A | U719: =+VLOOKUP($L719,Data_Validation!$A:$D,3,0) -> #N/A | V719: =+VLOOKUP($L719,Data_Validation!$A:$D,4,0) -> #N/A | W719: =+VLOOKUP($L719,Data_Validation!$A:$E,5,0) -> #N/A | X719: =+VLOOKUP($L719,Data_Validation!$A:$F,6,0) -> #N/A
L720: =+B720 -> 0 | M720: =+A720 -> 0 | N720: =+IF(OR($Q720=Parametres!$G$2,$Q720=Parametres!$G$3),I720,C720) -> 0 | O720: =+IF(OR($Q720=Parametres!$G$2,$Q720=Parametres!$G$3),J720,D720) -> 0 | P720: =+IF(OR($Q720=Parametres!$G$2,$Q720=Parametres!$G$3),K720,E720) -> 0 | Q720: =+F720 -> 0 | R720: =+G720 -> 0 | S720: =+H720 -> 0 | T720: =+VLOOKUP($L720,Data_Validation!$A:$D,1,0) -> #N/A | U720: =+VLOOKUP($L720,Data_Validation!$A:$D,3,0) -> #N/A | V720: =+VLOOKUP($L720,Data_Validation!$A:$D,4,0) -> #N/A | W720: =+VLOOKUP($L720,Data_Validation!$A:$E,5,0) -> #N/A | X720: =+VLOOKUP($L720,Data_Validation!$A:$F,6,0) -> #N/A
L721: =+B721 -> 0 | M721: =+A721 -> 0 | N721: =+IF(OR($Q721=Parametres!$G$2,$Q721=Parametres!$G$3),I721,C721) -> 0 | O721: =+IF(OR($Q721=Parametres!$G$2,$Q721=Parametres!$G$3),J721,D721) -> 0 | P721: =+IF(OR($Q721=Parametres!$G$2,$Q721=Parametres!$G$3),K721,E721) -> 0 | Q721: =+F721 -> 0 | R721: =+G721 -> 0 | S721: =+H721 -> 0 | T721: =+VLOOKUP($L721,Data_Validation!$A:$D,1,0) -> #N/A | U721: =+VLOOKUP($L721,Data_Validation!$A:$D,3,0) -> #N/A | V721: =+VLOOKUP($L721,Data_Validation!$A:$D,4,0) -> #N/A | W721: =+VLOOKUP($L721,Data_Validation!$A:$E,5,0) -> #N/A | X721: =+VLOOKUP($L721,Data_Validation!$A:$F,6,0) -> #N/A
L722: =+B722 -> 0 | M722: =+A722 -> 0 | N722: =+IF(OR($Q722=Parametres!$G$2,$Q722=Parametres!$G$3),I722,C722) -> 0 | O722: =+IF(OR($Q722=Parametres!$G$2,$Q722=Parametres!$G$3),J722,D722) -> 0 | P722: =+IF(OR($Q722=Parametres!$G$2,$Q722=Parametres!$G$3),K722,E722) -> 0 | Q722: =+F722 -> 0 | R722: =+G722 -> 0 | S722: =+H722 -> 0 | T722: =+VLOOKUP($L722,Data_Validation!$A:$D,1,0) -> #N/A | U722: =+VLOOKUP($L722,Data_Validation!$A:$D,3,0) -> #N/A | V722: =+VLOOKUP($L722,Data_Validation!$A:$D,4,0) -> #N/A | W722: =+VLOOKUP($L722,Data_Validation!$A:$E,5,0) -> #N/A | X722: =+VLOOKUP($L722,Data_Validation!$A:$F,6,0) -> #N/A
L723: =+B723 -> 0 | M723: =+A723 -> 0 | N723: =+IF(OR($Q723=Parametres!$G$2,$Q723=Parametres!$G$3),I723,C723) -> 0 | O723: =+IF(OR($Q723=Parametres!$G$2,$Q723=Parametres!$G$3),J723,D723) -> 0 | P723: =+IF(OR($Q723=Parametres!$G$2,$Q723=Parametres!$G$3),K723,E723) -> 0 | Q723: =+F723 -> 0 | R723: =+G723 -> 0 | S723: =+H723 -> 0 | T723: =+VLOOKUP($L723,Data_Validation!$A:$D,1,0) -> #N/A | U723: =+VLOOKUP($L723,Data_Validation!$A:$D,3,0) -> #N/A | V723: =+VLOOKUP($L723,Data_Validation!$A:$D,4,0) -> #N/A | W723: =+VLOOKUP($L723,Data_Validation!$A:$E,5,0) -> #N/A | X723: =+VLOOKUP($L723,Data_Validation!$A:$F,6,0) -> #N/A
L724: =+B724 -> 0 | M724: =+A724 -> 0 | N724: =+IF(OR($Q724=Parametres!$G$2,$Q724=Parametres!$G$3),I724,C724) -> 0 | O724: =+IF(OR($Q724=Parametres!$G$2,$Q724=Parametres!$G$3),J724,D724) -> 0 | P724: =+IF(OR($Q724=Parametres!$G$2,$Q724=Parametres!$G$3),K724,E724) -> 0 | Q724: =+F724 -> 0 | R724: =+G724 -> 0 | S724: =+H724 -> 0 | T724: =+VLOOKUP($L724,Data_Validation!$A:$D,1,0) -> #N/A | U724: =+VLOOKUP($L724,Data_Validation!$A:$D,3,0) -> #N/A | V724: =+VLOOKUP($L724,Data_Validation!$A:$D,4,0) -> #N/A | W724: =+VLOOKUP($L724,Data_Validation!$A:$E,5,0) -> #N/A | X724: =+VLOOKUP($L724,Data_Validation!$A:$F,6,0) -> #N/A
L725: =+B725 -> 0 | M725: =+A725 -> 0 | N725: =+IF(OR($Q725=Parametres!$G$2,$Q725=Parametres!$G$3),I725,C725) -> 0 | O725: =+IF(OR($Q725=Parametres!$G$2,$Q725=Parametres!$G$3),J725,D725) -> 0 | P725: =+IF(OR($Q725=Parametres!$G$2,$Q725=Parametres!$G$3),K725,E725) -> 0 | Q725: =+F725 -> 0 | R725: =+G725 -> 0 | S725: =+H725 -> 0 | T725: =+VLOOKUP($L725,Data_Validation!$A:$D,1,0) -> #N/A | U725: =+VLOOKUP($L725,Data_Validation!$A:$D,3,0) -> #N/A | V725: =+VLOOKUP($L725,Data_Validation!$A:$D,4,0) -> #N/A | W725: =+VLOOKUP($L725,Data_Validation!$A:$E,5,0) -> #N/A | X725: =+VLOOKUP($L725,Data_Validation!$A:$F,6,0) -> #N/A
L726: =+B726 -> 0 | M726: =+A726 -> 0 | N726: =+IF(OR($Q726=Parametres!$G$2,$Q726=Parametres!$G$3),I726,C726) -> 0 | O726: =+IF(OR($Q726=Parametres!$G$2,$Q726=Parametres!$G$3),J726,D726) -> 0 | P726: =+IF(OR($Q726=Parametres!$G$2,$Q726=Parametres!$G$3),K726,E726) -> 0 | Q726: =+F726 -> 0 | R726: =+G726 -> 0 | S726: =+H726 -> 0 | T726: =+VLOOKUP($L726,Data_Validation!$A:$D,1,0) -> #N/A | U726: =+VLOOKUP($L726,Data_Validation!$A:$D,3,0) -> #N/A | V726: =+VLOOKUP($L726,Data_Validation!$A:$D,4,0) -> #N/A | W726: =+VLOOKUP($L726,Data_Validation!$A:$E,5,0) -> #N/A | X726: =+VLOOKUP($L726,Data_Validation!$A:$F,6,0) -> #N/A
... L1055: =+B1055 -> 0 | M1055: =+A1055 -> 0 | N1055: =+IF(OR($Q1055=Parametres!$G$2,$Q1055=Parametres!$G$3),I1055,C1055) -> 0 | O1055: =+IF(OR($Q1055=Parametres!$G$2,$Q1055=Parametres!$G$3),J1055,D1055) -> 0 | P1055: =+IF(OR($Q1055=Parametres!$G$2,$Q1055=Parametres!$G$3),K1055,E1055) -> 0 | Q1055: =+F1055 -> 0 | R1055: =+G1055 -> 0 | S1055: =+H1055 -> 0 | T1055: =+VLOOKUP($L1055,Data_Validation!$A:$D,1,0) -> #N/A | U1055: =+VLOOKUP($L1055,Data_Validation!$A:$D,3,0) -> #N/A | V1055: =+VLOOKUP($L1055,Data_Validation!$A:$D,4,0) -> #N/A | W1055: =+VLOOKUP($L1055,Data_Validation!$A:$E,5,0) -> #N/A | X1055: =+VLOOKUP($L1055,Data_Validation!$A:$F,6,0) -> #N/A

Sheet BV_Data_An_Prec
A1: Description | B1: #Compte | C1: Solde d'ouverture | D1: Solde courant | E1: Solde de fin | F1: Type compte | G1: #Groupe | H1: Préfixe | I1: CUC/Mémo solde début | J1: CUC/Mémo solde actuel | K1: CUC/Mémo solde fin | L1: #Compte | M1: Description | N1: Solde d'ouverture | O1: Solde courant | P1: Solde de fin | Q1: Type compte | R1: #Groupe | S1: Préfixe | T1: Valid GL # | U1: Debits | V1: Classification | W1: $ / NB | X1: Ventes
A2: PROFIT JANVIER | B2: 101 | F2: 1-Mémo | G2: 101 | I2: -87636 | J2: 0 | K2: -87636 | L2: =+B2 -> 101 | M2: =+A2 -> PROFIT JANVIER | N2: =+IF(OR($Q2=Parametres!$G$2,$Q2=Parametres!$G$3),I2,C2) -> -87636 | O2: =+IF(OR($Q2=Parametres!$G$2,$Q2=Parametres!$G$3),J2,D2) -> 0 | P2: =+IF(OR($Q2=Parametres!$G$2,$Q2=Parametres!$G$3),K2,E2) -> -87636 | Q2: =+F2 -> 1-Mémo | R2: =+G2 -> 101 | S2: =+H2 -> 0 | T2: =+VLOOKUP($L2,Data_Validation!$A:$E,1,0) -> 101 | U2: =+VLOOKUP($L2,Data_Validation!$A:$E,3,0) -> Autres | V2: =+VLOOKUP($L2,Data_Validation!$A:$E,4,0) -> 0 | W2: =VLOOKUP($L2,Data_Validation!$A:$E,5,FALSE) -> 0 | X2: =+VLOOKUP($L2,Data_Validation!$A:$F,6,0) -> 0
A3: PROFIT FEVRIER | B3: 102 | F3: 1-Mémo | G3: 102 | I3: 3380 | J3: 0 | K3: 3380 | L3: =+B3 -> 102 | M3: =+A3 -> PROFIT FEVRIER | N3: =+IF(OR($Q3=Parametres!$G$2,$Q3=Parametres!$G$3),I3,C3) -> 3380 | O3: =+IF(OR($Q3=Parametres!$G$2,$Q3=Parametres!$G$3),J3,D3) -> 0 | P3: =+IF(OR($Q3=Parametres!$G$2,$Q3=Parametres!$G$3),K3,E3) -> 3380 | Q3: =+F3 -> 1-Mémo | R3: =+G3 -> 102 | S3: =+H3 -> 0 | T3: =+VLOOKUP($L3,Data_Validation!$A:$D,1,0) -> 102 | U3: =+VLOOKUP($L3,Data_Validation!$A:$D,3,0) -> Autres | V3: =+VLOOKUP($L3,Data_Validation!$A:$D,4,0) -> 0 | W3: =+VLOOKUP($L3,Data_Validation!$A:$E,5,0) -> 0 | X3: =+VLOOKUP($L3,Data_Validation!$A:$F,6,0) -> 0
A4: PROFIT MARS | B4: 103 | F4: 1-Mémo | G4: 103 | I4: 242199 | J4: 0 | K4: 242199 | L4: =+B4 -> 103 | M4: =+A4 -> PROFIT MARS | N4: =+IF(OR($Q4=Parametres!$G$2,$Q4=Parametres!$G$3),I4,C4) -> 242199 | O4: =+IF(OR($Q4=Parametres!$G$2,$Q4=Parametres!$G$3),J4,D4) -> 0 | P4: =+IF(OR($Q4=Parametres!$G$2,$Q4=Parametres!$G$3),K4,E4) -> 242199 | Q4: =+F4 -> 1-Mémo | R4: =+G4 -> 103 | S4: =+H4 -> 0 | T4: =+VLOOKUP($L4,Data_Validation!$A:$D,1,0) -> 103 | U4: =+VLOOKUP($L4,Data_Validation!$A:$D,3,0) -> Autres | V4: =+VLOOKUP($L4,Data_Validation!$A:$D,4,0) -> 0 | W4: =+VLOOKUP($L4,Data_Validation!$A:$E,5,0) -> 0 | X4: =+VLOOKUP($L4,Data_Validation!$A:$F,6,0) -> 0
A5: PROFIT AVRIL | B5: 104 | F5: 1-Mémo | G5: 104 | I5: 218221 | J5: 0 | K5: 218221 | L5: =+B5 -> 104 | M5: =+A5 -> PROFIT AVRIL | N5: =+IF(OR($Q5=Parametres!$G$2,$Q5=Parametres!$G$3),I5,C5) -> 218221 | O5: =+IF(OR($Q5=Parametres!$G$2,$Q5=Parametres!$G$3),J5,D5) -> 0 | P5: =+IF(OR($Q5=Parametres!$G$2,$Q5=Parametres!$G$3),K5,E5) -> 218221 | Q5: =+F5 -> 1-Mémo | R5: =+G5 -> 104 | S5: =+H5 -> 0 | T5: =+VLOOKUP($L5,Data_Validation!$A:$D,1,0) -> 104 | U5: =+VLOOKUP($L5,Data_Validation!$A:$D,3,0) -> Autres | V5: =+VLOOKUP($L5,Data_Validation!$A:$D,4,0) -> 0 | W5: =+VLOOKUP($L5,Data_Validation!$A:$E,5,0) -> 0 | X5: =+VLOOKUP($L5,Data_Validation!$A:$F,6,0) -> 0
A6: PROFIT MAI | B6: 105 | F6: 1-Mémo | G6: 105 | I6: 202342 | J6: 0 | K6: 202342 | L6: =+B6 -> 105 | M6: =+A6 -> PROFIT MAI | N6: =+IF(OR($Q6=Parametres!$G$2,$Q6=Parametres!$G$3),I6,C6) -> 202342 | O6: =+IF(OR($Q6=Parametres!$G$2,$Q6=Parametres!$G$3),J6,D6) -> 0 | P6: =+IF(OR($Q6=Parametres!$G$2,$Q6=Parametres!$G$3),K6,E6) -> 202342 | Q6: =+F6 -> 1-Mémo | R6: =+G6 -> 105 | S6: =+H6 -> 0 | T6: =+VLOOKUP($L6,Data_Validation!$A:$D,1,0) -> 105 | U6: =+VLOOKUP($L6,Data_Validation!$A:$D,3,0) -> Autres | V6: =+VLOOKUP($L6,Data_Validation!$A:$D,4,0) -> 0 | W6: =+VLOOKUP($L6,Data_Validation!$A:$E,5,0) -> 0 | X6: =+VLOOKUP($L6,Data_Validation!$A:$F,6,0) -> 0
A7: PROFIT JUIN | B7: 106 | F7: 1-Mémo | G7: 106 | I7: 171402 | J7: 0 | K7: 171402 | L7: =+B7 -> 106 | M7: =+A7 -> PROFIT JUIN | N7: =+IF(OR($Q7=Parametres!$G$2,$Q7=Parametres!$G$3),I7,C7) -> 171402 | O7: =+IF(OR($Q7=Parametres!$G$2,$Q7=Parametres!$G$3),J7,D7) -> 0 | P7: =+IF(OR($Q7=Parametres!$G$2,$Q7=Parametres!$G$3),K7,E7) -> 171402 | Q7: =+F7 -> 1-Mémo | R7: =+G7 -> 106 | S7: =+H7 -> 0 | T7: =+VLOOKUP($L7,Data_Validation!$A:$D,1,0) -> 106 | U7: =+VLOOKUP($L7,Data_Validation!$A:$D,3,0) -> Autres | V7: =+VLOOKUP($L7,Data_Validation!$A:$D,4,0) -> 0 | W7: =+VLOOKUP($L7,Data_Validation!$A:$E,5,0) -> 0 | X7: =+VLOOKUP($L7,Data_Validation!$A:$F,6,0) -> 0
A8: PROFIT JUILLET | B8: 107 | F8: 1-Mémo | G8: 107 | I8: 123120 | J8: 0 | K8: 123120 | L8: =+B8 -> 107 | M8: =+A8 -> PROFIT JUILLET | N8: =+IF(OR($Q8=Parametres!$G$2,$Q8=Parametres!$G$3),I8,C8) -> 123120 | O8: =+IF(OR($Q8=Parametres!$G$2,$Q8=Parametres!$G$3),J8,D8) -> 0 | P8: =+IF(OR($Q8=Parametres!$G$2,$Q8=Parametres!$G$3),K8,E8) -> 123120 | Q8: =+F8 -> 1-Mémo | R8: =+G8 -> 107 | S8: =+H8 -> 0 | T8: =+VLOOKUP($L8,Data_Validation!$A:$D,1,0) -> 107 | U8: =+VLOOKUP($L8,Data_Validation!$A:$D,3,0) -> Autres | V8: =+VLOOKUP($L8,Data_Validation!$A:$D,4,0) -> 0 | W8: =+VLOOKUP($L8,Data_Validation!$A:$E,5,0) -> 0 | X8: =+VLOOKUP($L8,Data_Validation!$A:$F,6,0) -> 0
A9: PROFIT AOUT | B9: 108 | F9: 1-Mémo | G9: 108 | I9: 70058 | J9: 0 | K9: 70058 | L9: =+B9 -> 108 | M9: =+A9 -> PROFIT AOUT | N9: =+IF(OR($Q9=Parametres!$G$2,$Q9=Parametres!$G$3),I9,C9) -> 70058 | O9: =+IF(OR($Q9=Parametres!$G$2,$Q9=Parametres!$G$3),J9,D9) -> 0 | P9: =+IF(OR($Q9=Parametres!$G$2,$Q9=Parametres!$G$3),K9,E9) -> 70058 | Q9: =+F9 -> 1-Mémo | R9: =+G9 -> 108 | S9: =+H9 -> 0 | T9: =+VLOOKUP($L9,Data_Validation!$A:$D,1,0) -> 108 | U9: =+VLOOKUP($L9,Data_Validation!$A:$D,3,0) -> Autres | V9: =+VLOOKUP($L9,Data_Validation!$A:$D,4,0) -> 0 | W9: =+VLOOKUP($L9,Data_Validation!$A:$E,5,0) -> 0 | X9: =+VLOOKUP($L9,Data_Validation!$A:$F,6,0) -> 0
A10: PROFIT SPTEMBRE | B10: 109 | F10: 1-Mémo | G10: 109 | I10: 63471 | J10: 0 | K10: 63471 | L10: =+B10 -> 109 | M10: =+A10 -> PROFIT SPTEMBRE | N10: =+IF(OR($Q10=Parametres!$G$2,$Q10=Parametres!$G$3),I10,C10) -> 63471 | O10: =+IF(OR($Q10=Parametres!$G$2,$Q10=Parametres!$G$3),J10,D10) -> 0 | P10: =+IF(OR($Q10=Parametres!$G$2,$Q10=Parametres!$G$3),K10,E10) -> 63471 | Q10: =+F10 -> 1-Mémo | R10: =+G10 -> 109 | S10: =+H10 -> 0 | T10: =+VLOOKUP($L10,Data_Validation!$A:$D,1,0) -> 109 | U10: =+VLOOKUP($L10,Data_Validation!$A:$D,3,0) -> Autres | V10: =+VLOOKUP($L10,Data_Validation!$A:$D,4,0) -> 0 | W10: =+VLOOKUP($L10,Data_Validation!$A:$E,5,0) -> 0 | X10: =+VLOOKUP($L10,Data_Validation!$A:$F,6,0) -> 0
A11: PROFIT OCTOBRE | B11: 110 | F11: 1-Mémo | G11: 110 | I11: -181040 | J11: 0 | K11: -181040 | L11: =+B11 -> 110 | M11: =+A11 -> PROFIT OCTOBRE | N11: =+IF(OR($Q11=Parametres!$G$2,$Q11=Parametres!$G$3),I11,C11) -> -181040 | O11: =+IF(OR($Q11=Parametres!$G$2,$Q11=Parametres!$G$3),J11,D11) -> 0 | P11: =+IF(OR($Q11=Parametres!$G$2,$Q11=Parametres!$G$3),K11,E11) -> -181040 | Q11: =+F11 -> 1-Mémo | R11: =+G11 -> 110 | S11: =+H11 -> 0 | T11: =+VLOOKUP($L11,Data_Validation!$A:$D,1,0) -> 110 | U11: =+VLOOKUP($L11,Data_Validation!$A:$D,3,0) -> Autres | V11: =+VLOOKUP($L11,Data_Validation!$A:$D,4,0) -> 0 | W11: =+VLOOKUP($L11,Data_Validation!$A:$E,5,0) -> 0 | X11: =+VLOOKUP($L11,Data_Validation!$A:$F,6,0) -> 0
A12: PROFIT NOVEMBRE | B12: 111 | F12: 1-Mémo | G12: 111 | I12: 93899 | J12: 0 | K12: 93899 | L12: =+B12 -> 111 | M12: =+A12 -> PROFIT NOVEMBRE | N12: =+IF(OR($Q12=Parametres!$G$2,$Q12=Parametres!$G$3),I12,C12) -> 93899 | O12: =+IF(OR($Q12=Parametres!$G$2,$Q12=Parametres!$G$3),J12,D12) -> 0 | P12: =+IF(OR($Q12=Parametres!$G$2,$Q12=Parametres!$G$3),K12,E12) -> 93899 | Q12: =+F12 -> 1-Mémo | R12: =+G12 -> 111 | S12: =+H12 -> 0 | T12: =+VLOOKUP($L12,Data_Validation!$A:$D,1,0) -> 111 | U12: =+VLOOKUP($L12,Data_Validation!$A:$D,3,0) -> Autres | V12: =+VLOOKUP($L12,Data_Validation!$A:$D,4,0) -> 0 | W12: =+VLOOKUP($L12,Data_Validation!$A:$E,5,0) -> 0 | X12: =+VLOOKUP($L12,Data_Validation!$A:$F,6,0) -> 0
A13: JANV. NB VENTE NEUF BMW AUTO | B13: 120A | F13: 1-Mémo | G13: 120 | I13: 0.03 | J13: 0 | K13: 0.03 | L13: =+B13 -> 120A | M13: =+A13 -> JANV. NB VENTE NEUF BMW AUTO | N13: =+IF(OR($Q13=Parametres!$G$2,$Q13=Parametres!$G$3),I13,C13) -> 0.03 | O13: =+IF(OR($Q13=Parametres!$G$2,$Q13=Parametres!$G$3),J13,D13) -> 0 | P13: =+IF(OR($Q13=Parametres!$G$2,$Q13=Parametres!$G$3),K13,E13) -> 0.03 | Q13: =+F13 -> 1-Mémo | R13: =+G13 -> 120 | S13: =+H13 -> 0 | T13: =+VLOOKUP($L13,Data_Validation!$A:$D,1,0) -> 120A | U13: =+VLOOKUP($L13,Data_Validation!$A:$D,3,0) -> Autres | V13: =+VLOOKUP($L13,Data_Validation!$A:$D,4,0) -> 0 | W13: =+VLOOKUP($L13,Data_Validation!$A:$E,5,0) -> 0 | X13: =+VLOOKUP($L13,Data_Validation!$A:$F,6,0) -> 0
A14: FEV. NB VENTE NEUF BMW AUTO | B14: 120B | F14: 1-Mémo | G14: 120 | I14: 0.04 | J14: 0 | K14: 0.04 | L14: =+B14 -> 120B | M14: =+A14 -> FEV. NB VENTE NEUF BMW AUTO | N14: =+IF(OR($Q14=Parametres!$G$2,$Q14=Parametres!$G$3),I14,C14) -> 0.04 | O14: =+IF(OR($Q14=Parametres!$G$2,$Q14=Parametres!$G$3),J14,D14) -> 0 | P14: =+IF(OR($Q14=Parametres!$G$2,$Q14=Parametres!$G$3),K14,E14) -> 0.04 | Q14: =+F14 -> 1-Mémo | R14: =+G14 -> 120 | S14: =+H14 -> 0 | T14: =+VLOOKUP($L14,Data_Validation!$A:$D,1,0) -> 120B | U14: =+VLOOKUP($L14,Data_Validation!$A:$D,3,0) -> Autres | V14: =+VLOOKUP($L14,Data_Validation!$A:$D,4,0) -> 0 | W14: =+VLOOKUP($L14,Data_Validation!$A:$E,5,0) -> 0 | X14: =+VLOOKUP($L14,Data_Validation!$A:$F,6,0) -> 0
... A129: NOMBRE DE JOURS OUVRABLE SERVICE | B129: 179 | F129: 1-Mémo | G129: 179 | I129: 2.09 | J129: 0.19 | K129: 2.28 | L129: =+B129 -> 179 | M129: =+A129 -> NOMBRE DE JOURS OUVRABLE SERVICE | N129: =+IF(OR($Q129=Parametres!$G$2,$Q129=Parametres!$G$3),I129,C129) -> 2.09 | O129: =+IF(OR($Q129=Parametres!$G$2,$Q129=Parametres!$G$3),J129,D129) -> 0.19 | P129: =+IF(OR($Q129=Parametres!$G$2,$Q129=Parametres!$G$3),K129,E129) -> 2.28 | Q129: =+F129 -> 1-Mémo | R129: =+G129 -> 179 | S129: =+H129 -> 0 | T129: =+VLOOKUP($L129,Data_Validation!$A:$D,1,0) -> 179 | U129: =+VLOOKUP($L129,Data_Validation!$A:$D,3,0) -> Autres | V129: =+VLOOKUP($L129,Data_Validation!$A:$D,4,0) -> 0 | W129: =+VLOOKUP($L129,Data_Validation!$A:$E,5,0) -> 0 | X129: =+VLOOKUP($L129,Data_Validation!$A:$F,6,0) -> 0
A130: PETITE CAISSE | B130: 200 | C130: 700 | D130: 0 | E130: 700 | F130: 2-Actifs | G130: 200 | L130: =+B130 -> 200 | M130: =+A130 -> PETITE CAISSE | N130: =+IF(OR($Q130=Parametres!$G$2,$Q130=Parametres!$G$3),I130,C130) -> 700 | O130: =+IF(OR($Q130=Parametres!$G$2,$Q130=Parametres!$G$3),J130,D130) -> 0 | P130: =+IF(OR($Q130=Parametres!$G$2,$Q130=Parametres!$G$3),K130,E130) -> 700 | Q130: =+F130 -> 2-Actifs | R130: =+G130 -> 200 | S130: =+H130 -> 0 | T130: =+VLOOKUP($L130,Data_Validation!$A:$D,1,0) -> 200 | U130: =+VLOOKUP($L130,Data_Validation!$A:$D,3,0) -> Bilan | V130: =+VLOOKUP($L130,Data_Validation!$A:$D,4,0) -> encaisse | W130: =+VLOOKUP($L130,Data_Validation!$A:$E,5,0) -> $ | X130: =+VLOOKUP($L130,Data_Validation!$A:$F,6,0) -> 0
A131: ENCAISSE | B131: 202 | C131: 25648.25 | D131: 129996.87 | E131: 155645.12 | F131: 2-Actifs | G131: 202 | L131: =+B131 -> 202 | M131: =+A131 -> ENCAISSE | N131: =+IF(OR($Q131=Parametres!$G$2,$Q131=Parametres!$G$3),I131,C131) -> 25648.25 | O131: =+IF(OR($Q131=Parametres!$G$2,$Q131=Parametres!$G$3),J131,D131) -> 129996.87 | P131: =+IF(OR($Q131=Parametres!$G$2,$Q131=Parametres!$G$3),K131,E131) -> 155645.12 | Q131: =+F131 -> 2-Actifs | R131: =+G131 -> 202 | S131: =+H131 -> 0 | T131: =+VLOOKUP($L131,Data_Validation!$A:$D,1,0) -> 202 | U131: =+VLOOKUP($L131,Data_Validation!$A:$D,3,0) -> Bilan | V131: =+VLOOKUP($L131,Data_Validation!$A:$D,4,0) -> encaisse | W131: =+VLOOKUP($L131,Data_Validation!$A:$E,5,0) -> $ | X131: =+VLOOKUP($L131,Data_Validation!$A:$F,6,0) -> 0
A132: PAIEMENTS FORFAITAIRES FLOOR PLAN | B132: 202B | C132: 2750000 | D132: 0 | E132: 2750000 | F132: 2-Actifs | G132: 202 | L132: =+B132 -> 202B | M132: =+A132 -> PAIEMENTS FORFAITAIRES FLOOR PLAN | N132: =+IF(OR($Q132=Parametres!$G$2,$Q132=Parametres!$G$3),I132,C132) -> 2750000 | O132: =+IF(OR($Q132=Parametres!$G$2,$Q132=Parametres!$G$3),J132,D132) -> 0 | P132: =+IF(OR($Q132=Parametres!$G$2,$Q132=Parametres!$G$3),K132,E132) -> 2750000 | Q132: =+F132 -> 2-Actifs | R132: =+G132 -> 202 | S132: =+H132 -> 0 | T132: =+VLOOKUP($L132,Data_Validation!$A:$D,1,0) -> 202B | U132: =+VLOOKUP($L132,Data_Validation!$A:$D,3,0) -> bilan | V132: =+VLOOKUP($L132,Data_Validation!$A:$D,4,0) -> Encaisse | W132: =+VLOOKUP($L132,Data_Validation!$A:$E,5,0) -> $ | X132: =+VLOOKUP($L132,Data_Validation!$A:$F,6,0) -> 0
A133: CONTRATS EN TRANSIT | B133: 205 | C133: 311612.44 | D133: -207282.88 | E133: 104329.56 | F133: 2-Actifs | G133: 205 | L133: =+B133 -> 205 | M133: =+A133 -> CONTRATS EN TRANSIT | N133: =+IF(OR($Q133=Parametres!$G$2,$Q133=Parametres!$G$3),I133,C133) -> 311612.44 | O133: =+IF(OR($Q133=Parametres!$G$2,$Q133=Parametres!$G$3),J133,D133) -> -207282.88 | P133: =+IF(OR($Q133=Parametres!$G$2,$Q133=Parametres!$G$3),K133,E133) -> 104329.56 | Q133: =+F133 -> 2-Actifs | R133: =+G133 -> 205 | S133: =+H133 -> 0 | T133: =+VLOOKUP($L133,Data_Validation!$A:$D,1,0) -> 205 | U133: =+VLOOKUP($L133,Data_Validation!$A:$D,3,0) -> Bilan | V133: =+VLOOKUP($L133,Data_Validation!$A:$D,4,0) -> Recevables Contrats en Transit | W133: =+VLOOKUP($L133,Data_Validation!$A:$E,5,0) -> $ | X133: =+VLOOKUP($L133,Data_Validation!$A:$F,6,0) -> 0
A134: RECEVABLES VEHICULES | B134: 210 | C134: 60598.53 | D134: 38101.02 | E134: 98699.55 | F134: 2-Actifs | G134: 210 | L134: =+B134 -> 210 | M134: =+A134 -> RECEVABLES VEHICULES | N134: =+IF(OR($Q134=Parametres!$G$2,$Q134=Parametres!$G$3),I134,C134) -> 60598.53 | O134: =+IF(OR($Q134=Parametres!$G$2,$Q134=Parametres!$G$3),J134,D134) -> 38101.02 | P134: =+IF(OR($Q134=Parametres!$G$2,$Q134=Parametres!$G$3),K134,E134) -> 98699.55 | Q134: =+F134 -> 2-Actifs | R134: =+G134 -> 210 | S134: =+H134 -> 0 | T134: =+VLOOKUP($L134,Data_Validation!$A:$D,1,0) -> 210 | U134: =+VLOOKUP($L134,Data_Validation!$A:$D,3,0) -> Bilan | V134: =+VLOOKUP($L134,Data_Validation!$A:$D,4,0) -> Recevables Véhicules | W134: =+VLOOKUP($L134,Data_Validation!$A:$E,5,0) -> $ | X134: =+VLOOKUP($L134,Data_Validation!$A:$F,6,0) -> 0
A135: WHOLESALE & ECHANGE A/R | B135: 210A | C135: 389343.06 | D135: -312972.04 | E135: 76371.02 | F135: 2-Actifs | G135: 210 | L135: =+B135 -> 210A | M135: =+A135 -> WHOLESALE & ECHANGE A/R | N135: =+IF(OR($Q135=Parametres!$G$2,$Q135=Parametres!$G$3),I135,C135) -> 389343.06 | O135: =+IF(OR($Q135=Parametres!$G$2,$Q135=Parametres!$G$3),J135,D135) -> -312972.04 | P135: =+IF(OR($Q135=Parametres!$G$2,$Q135=Parametres!$G$3),K135,E135) -> 76371.02 | Q135: =+F135 -> 2-Actifs | R135: =+G135 -> 210 | S135: =+H135 -> 0 | T135: =+VLOOKUP($L135,Data_Validation!$A:$D,1,0) -> 210A | U135: =+VLOOKUP($L135,Data_Validation!$A:$D,3,0) -> Bilan | V135: =+VLOOKUP($L135,Data_Validation!$A:$D,4,0) -> Recevables Véhicules | W135: =+VLOOKUP($L135,Data_Validation!$A:$E,5,0) -> $ | X135: =+VLOOKUP($L135,Data_Validation!$A:$F,6,0) -> 0
A136: A/R INTERCO WHOLESALE & ECHANGE | B136: 210L | C136: 137799.5 | D136: -137799.5 | E136: 0 | F136: 2-Actifs | G136: 210 | L136: =+B136 -> 210L | M136: =+A136 -> A/R INTERCO WHOLESALE & ECHANGE | N136: =+IF(OR($Q136=Parametres!$G$2,$Q136=Parametres!$G$3),I136,C136) -> 137799.5 | O136: =+IF(OR($Q136=Parametres!$G$2,$Q136=Parametres!$G$3),J136,D136) -> -137799.5 | P136: =+IF(OR($Q136=Parametres!$G$2,$Q136=Parametres!$G$3),K136,E136) -> 0 | Q136: =+F136 -> 2-Actifs | R136: =+G136 -> 210 | S136: =+H136 -> 0 | T136: =+VLOOKUP($L136,Data_Validation!$A:$D,1,0) -> 210L | U136: =+VLOOKUP($L136,Data_Validation!$A:$D,3,0) -> bilan | V136: =+VLOOKUP($L136,Data_Validation!$A:$D,4,0) -> Recevables Intercos | W136: =+VLOOKUP($L136,Data_Validation!$A:$E,5,0) -> $ | X136: =+VLOOKUP($L136,Data_Validation!$A:$F,6,0) -> 0
A137: RECEVABLES PIECES ET SERVICE | B137: 220 | C137: 128724.04 | D137: -497.78 | E137: 128226.26 | F137: 2-Actifs | G137: 220 | L137: =+B137 -> 220 | M137: =+A137 -> RECEVABLES PIECES ET SERVICE | N137: =+IF(OR($Q137=Parametres!$G$2,$Q137=Parametres!$G$3),I137,C137) -> 128724.04 | O137: =+IF(OR($Q137=Parametres!$G$2,$Q137=Parametres!$G$3),J137,D137) -> -497.78 | P137: =+IF(OR($Q137=Parametres!$G$2,$Q137=Parametres!$G$3),K137,E137) -> 128226.26 | Q137: =+F137 -> 2-Actifs | R137: =+G137 -> 220 | S137: =+H137 -> 0 | T137: =+VLOOKUP($L137,Data_Validation!$A:$D,1,0) -> 220 | U137: =+VLOOKUP($L137,Data_Validation!$A:$D,3,0) -> Bilan | V137: =+VLOOKUP($L137,Data_Validation!$A:$D,4,0) -> Recevables Pièces et Service | W137: =+VLOOKUP($L137,Data_Validation!$A:$E,5,0) -> $ | X137: =+VLOOKUP($L137,Data_Validation!$A:$F,6,0) -> 0
A138: ASS COLLECTIVE EMPLOYES A/R | B138: 220A | C138: -681.89 | D138: 2014.45 | E138: 1332.56 | F138: 2-Actifs | G138: 220 | L138: =+B138 -> 220A | M138: =+A138 -> ASS COLLECTIVE EMPLOYES A/R | N138: =+IF(OR($Q138=Parametres!$G$2,$Q138=Parametres!$G$3),I138,C138) -> -681.89 | O138: =+IF(OR($Q138=Parametres!$G$2,$Q138=Parametres!$G$3),J138,D138) -> 2014.45 | P138: =+IF(OR($Q138=Parametres!$G$2,$Q138=Parametres!$G$3),K138,E138) -> 1332.56 | Q138: =+F138 -> 2-Actifs | R138: =+G138 -> 220 | S138: =+H138 -> 0 | T138: =+VLOOKUP($L138,Data_Validation!$A:$D,1,0) -> 220A | U138: =+VLOOKUP($L138,Data_Validation!$A:$D,3,0) -> Bilan | V138: =+VLOOKUP($L138,Data_Validation!$A:$D,4,0) -> Recevables Autres | W138: =+VLOOKUP($L138,Data_Validation!$A:$E,5,0) -> $ | X138: =+VLOOKUP($L138,Data_Validation!$A:$F,6,0) -> 0
A139: CSST A/R | B139: 220B | C139: 9919 | D139: 0 | E139: 9919 | F139: 2-Actifs | G139: 220 | L139: =+B139 -> 220B | M139: =+A139 -> CSST A/R | N139: =+IF(OR($Q139=Parametres!$G$2,$Q139=Parametres!$G$3),I139,C139) -> 9919 | O139: =+IF(OR($Q139=Parametres!$G$2,$Q139=Parametres!$G$3),J139,D139) -> 0 | P139: =+IF(OR($Q139=Parametres!$G$2,$Q139=Parametres!$G$3),K139,E139) -> 9919 | Q139: =+F139 -> 2-Actifs | R139: =+G139 -> 220 | S139: =+H139 -> 0 | T139: =+VLOOKUP($L139,Data_Validation!$A:$D,1,0) -> 220B | U139: =+VLOOKUP($L139,Data_Validation!$A:$D,3,0) -> Bilan | V139: =+VLOOKUP($L139,Data_Validation!$A:$D,4,0) -> Recevables Autres | W139: =+VLOOKUP($L139,Data_Validation!$A:$E,5,0) -> $ | X139: =+VLOOKUP($L139,Data_Validation!$A:$F,6,0) -> 0
A140: A/R INTERCOS P&S | B140: 220L | C140: 479.47 | D140: 4528.41 | E140: 5007.88 | F140: 2-Actifs | G140: 220 | L140: =+B140 -> 220L | M140: =+A140 -> A/R INTERCOS P&S | N140: =+IF(OR($Q140=Parametres!$G$2,$Q140=Parametres!$G$3),I140,C140) -> 479.47 | O140: =+IF(OR($Q140=Parametres!$G$2,$Q140=Parametres!$G$3),J140,D140) -> 4528.41 | P140: =+IF(OR($Q140=Parametres!$G$2,$Q140=Parametres!$G$3),K140,E140) -> 5007.88 | Q140: =+F140 -> 2-Actifs | R140: =+G140 -> 220 | S140: =+H140 -> 0 | T140: =+VLOOKUP($L140,Data_Validation!$A:$D,1,0) -> 220L | U140: =+VLOOKUP($L140,Data_Validation!$A:$D,3,0) -> Bilan | V140: =+VLOOKUP($L140,Data_Validation!$A:$D,4,0) -> Recevables Intercos | W140: =+VLOOKUP($L140,Data_Validation!$A:$E,5,0) -> $ | X140: =+VLOOKUP($L140,Data_Validation!$A:$F,6,0) -> 0
A141: BONIS A/R MANUFACTURIER | B141: 221 | C141: 64465.15 | D141: -20932.15 | E141: 43533 | F141: 2-Actifs | G141: 221 | L141: =+B141 -> 221 | M141: =+A141 -> BONIS A/R MANUFACTURIER | N141: =+IF(OR($Q141=Parametres!$G$2,$Q141=Parametres!$G$3),I141,C141) -> 64465.15 | O141: =+IF(OR($Q141=Parametres!$G$2,$Q141=Parametres!$G$3),J141,D141) -> -20932.15 | P141: =+IF(OR($Q141=Parametres!$G$2,$Q141=Parametres!$G$3),K141,E141) -> 43533 | Q141: =+F141 -> 2-Actifs | R141: =+G141 -> 221 | S141: =+H141 -> 0 | T141: =+VLOOKUP($L141,Data_Validation!$A:$D,1,0) -> 221 | U141: =+VLOOKUP($L141,Data_Validation!$A:$D,3,0) -> Bilan | V141: =+VLOOKUP($L141,Data_Validation!$A:$D,4,0) -> Recevables Manufacturier | W141: =+VLOOKUP($L141,Data_Validation!$A:$E,5,0) -> $ | X141: =+VLOOKUP($L141,Data_Validation!$A:$F,6,0) -> 0
... A672: AUTRES DEDUCTIONS | B672: 855 | C672: -202.97 | D672: 0 | E672: -202.97 | F672: 9-Autres déductions | G672: 855 | L672: =+B672 -> 855 | M672: =+A672 -> AUTRES DEDUCTIONS | N672: =+IF(OR($Q672=Parametres!$G$2,$Q672=Parametres!$G$3),I672,C672) -> -202.97 | O672: =+IF(OR($Q672=Parametres!$G$2,$Q672=Parametres!$G$3),J672,D672) -> 0 | P672: =+IF(OR($Q672=Parametres!$G$2,$Q672=Parametres!$G$3),K672,E672) -> -202.97 | Q672: =+F672 -> 9-Autres déductions | R672: =+G672 -> 855 | S672: =+H672 -> 0 | T672: =+VLOOKUP($L672,Data_Validation!$A:$D,1,0) -> 855 | U672: =+VLOOKUP($L672,Data_Validation!$A:$D,3,0) -> TOTAL DES REVENUS ET DÉPENSES | V672: =+VLOOKUP($L672,Data_Validation!$A:$D,4,0) -> Revenus autres | W672: =+VLOOKUP($L672,Data_Validation!$A:$E,5,0) -> $ | X672: =+VLOOKUP($L672,Data_Validation!$A:$F,6,0) -> 0
A673: # DE VOITURES NEUVES BMW | B673: 230@ | F673: 10-Compte compteur | G673: 230 | I673: 15 | J673: 2 | K673: 17 | L673: =+B673 -> 230@ | M673: =+A673 -> # DE VOITURES NEUVES BMW | N673: =+IF(OR($Q673=Parametres!$G$2,$Q673=Parametres!$G$3),I673,C673) -> 15 | O673: =+IF(OR($Q673=Parametres!$G$2,$Q673=Parametres!$G$3),J673,D673) -> 2 | P673: =+IF(OR($Q673=Parametres!$G$2,$Q673=Parametres!$G$3),K673,E673) -> 17 | Q673: =+F673 -> 10-Compte compteur | R673: =+G673 -> 230 | S673: =+H673 -> 0 | T673: =+VLOOKUP($L673,Data_Validation!$A:$D,1,0) -> 230@ | U673: =+VLOOKUP($L673,Data_Validation!$A:$D,3,0) -> Autres | V673: =+VLOOKUP($L673,Data_Validation!$A:$D,4,0) -> 0 | W673: =+VLOOKUP($L673,Data_Validation!$A:$E,5,0) -> 0 | X673: =+VLOOKUP($L673,Data_Validation!$A:$F,6,0) -> 0
A674: # DE CAMIONS NEUFS BMW | B674: 232@ | F674: 10-Compte compteur | G674: 232 | I674: 17 | J674: -1 | K674: 16 | L674: =+B674 -> 232@ | M674: =+A674 -> # DE CAMIONS NEUFS BMW | N674: =+IF(OR($Q674=Parametres!$G$2,$Q674=Parametres!$G$3),I674,C674) -> 17 | O674: =+IF(OR($Q674=Parametres!$G$2,$Q674=Parametres!$G$3),J674,D674) -> -1 | P674: =+IF(OR($Q674=Parametres!$G$2,$Q674=Parametres!$G$3),K674,E674) -> 16 | Q674: =+F674 -> 10-Compte compteur | R674: =+G674 -> 232 | S674: =+H674 -> 0 | T674: =+VLOOKUP($L674,Data_Validation!$A:$D,1,0) -> 232@ | U674: =+VLOOKUP($L674,Data_Validation!$A:$D,3,0) -> Autres | V674: =+VLOOKUP($L674,Data_Validation!$A:$D,4,0) -> 0 | W674: =+VLOOKUP($L674,Data_Validation!$A:$E,5,0) -> 0 | X674: =+VLOOKUP($L674,Data_Validation!$A:$F,6,0) -> 0
A675: # OF INVENTAIRE VEHICULES I | B675: 234@ | F675: 10-Compte compteur | G675: 234 | I675: 8 | J675: -2 | K675: 6 | L675: =+B675 -> 234@ | M675: =+A675 -> # OF INVENTAIRE VEHICULES I | N675: =+IF(OR($Q675=Parametres!$G$2,$Q675=Parametres!$G$3),I675,C675) -> 8 | O675: =+IF(OR($Q675=Parametres!$G$2,$Q675=Parametres!$G$3),J675,D675) -> -2 | P675: =+IF(OR($Q675=Parametres!$G$2,$Q675=Parametres!$G$3),K675,E675) -> 6 | Q675: =+F675 -> 10-Compte compteur | R675: =+G675 -> 234 | S675: =+H675 -> 0 | T675: =+VLOOKUP($L675,Data_Validation!$A:$D,1,0) -> 234@ | U675: =+VLOOKUP($L675,Data_Validation!$A:$D,3,0) -> Autres | V675: =+VLOOKUP($L675,Data_Validation!$A:$D,4,0) -> 0 | W675: =+VLOOKUP($L675,Data_Validation!$A:$E,5,0) -> 0 | X675: =+VLOOKUP($L675,Data_Validation!$A:$F,6,0) -> 0
A676: # DE VOITURES USAGEES BMW | B676: 240A@ | F676: 10-Compte compteur | G676: 240A | I676: 21 | J676: -3 | K676: 18 | L676: =+B676 -> 240A@ | M676: =+A676 -> # DE VOITURES USAGEES BMW | N676: =+IF(OR($Q676=Parametres!$G$2,$Q676=Parametres!$G$3),I676,C676) -> 21 | O676: =+IF(OR($Q676=Parametres!$G$2,$Q676=Parametres!$G$3),J676,D676) -> -3 | P676: =+IF(OR($Q676=Parametres!$G$2,$Q676=Parametres!$G$3),K676,E676) -> 18 | Q676: =+F676 -> 10-Compte compteur | R676: =+G676 -> 240A | S676: =+H676 -> 0 | T676: =+VLOOKUP($L676,Data_Validation!$A:$D,1,0) -> 240A@ | U676: =+VLOOKUP($L676,Data_Validation!$A:$D,3,0) -> Autres | V676: =+VLOOKUP($L676,Data_Validation!$A:$D,4,0) -> 0 | W676: =+VLOOKUP($L676,Data_Validation!$A:$E,5,0) -> 0 | X676: =+VLOOKUP($L676,Data_Validation!$A:$F,6,0) -> 0
A677: # DE VEHICULES USAGES AUTRES | B677: 240C@ | F677: 10-Compte compteur | G677: 240C | I677: 21 | J677: 2 | K677: 23 | L677: =+B677 -> 240C@ | M677: =+A677 -> # DE VEHICULES USAGES AUTRES | N677: =+IF(OR($Q677=Parametres!$G$2,$Q677=Parametres!$G$3),I677,C677) -> 21 | O677: =+IF(OR($Q677=Parametres!$G$2,$Q677=Parametres!$G$3),J677,D677) -> 2 | P677: =+IF(OR($Q677=Parametres!$G$2,$Q677=Parametres!$G$3),K677,E677) -> 23 | Q677: =+F677 -> 10-Compte compteur | R677: =+G677 -> 240C | S677: =+H677 -> 0 | T677: =+VLOOKUP($L677,Data_Validation!$A:$D,1,0) -> 240C@ | U677: =+VLOOKUP($L677,Data_Validation!$A:$D,3,0) -> Autres | V677: =+VLOOKUP($L677,Data_Validation!$A:$D,4,0) -> 0 | W677: =+VLOOKUP($L677,Data_Validation!$A:$E,5,0) -> 0 | X677: =+VLOOKUP($L677,Data_Validation!$A:$F,6,0) -> 0
A678: # DE CAMIONS USAGES BMW | B678: 242A@ | F678: 10-Compte compteur | G678: 242A | I678: 15 | J678: 3 | K678: 18 | L678: =+B678 -> 242A@ | M678: =+A678 -> # DE CAMIONS USAGES BMW | N678: =+IF(OR($Q678=Parametres!$G$2,$Q678=Parametres!$G$3),I678,C678) -> 15 | O678: =+IF(OR($Q678=Parametres!$G$2,$Q678=Parametres!$G$3),J678,D678) -> 3 | P678: =+IF(OR($Q678=Parametres!$G$2,$Q678=Parametres!$G$3),K678,E678) -> 18 | Q678: =+F678 -> 10-Compte compteur | R678: =+G678 -> 242A | S678: =+H678 -> 0 | T678: =+VLOOKUP($L678,Data_Validation!$A:$D,1,0) -> 242A@ | U678: =+VLOOKUP($L678,Data_Validation!$A:$D,3,0) -> Autres | V678: =+VLOOKUP($L678,Data_Validation!$A:$D,4,0) -> 0 | W678: =+VLOOKUP($L678,Data_Validation!$A:$E,5,0) -> 0 | X678: =+VLOOKUP($L678,Data_Validation!$A:$F,6,0) -> 0
A679: # DE VTE - IX XDRIVE 40 | B679: 402A@ | F679: 10-Compte compteur | G679: 402A | I679: -8 | J679: -1 | K679: -9 | L679: =+B679 -> 402A@ | M679: =+A679 -> # DE VTE - IX XDRIVE 40 | N679: =+IF(OR($Q679=Parametres!$G$2,$Q679=Parametres!$G$3),I679,C679) -> -8 | O679: =+IF(OR($Q679=Parametres!$G$2,$Q679=Parametres!$G$3),J679,D679) -> -1 | P679: =+IF(OR($Q679=Parametres!$G$2,$Q679=Parametres!$G$3),K679,E679) -> -9 | Q679: =+F679 -> 10-Compte compteur | R679: =+G679 -> 402A | S679: =+H679 -> 0 | T679: =+VLOOKUP($L679,Data_Validation!$A:$D,1,0) -> 402A@ | U679: =+VLOOKUP($L679,Data_Validation!$A:$D,3,0) -> Véhicules neufs | V679: =+VLOOKUP($L679,Data_Validation!$A:$D,4,0) -> Camions détail | W679: =+VLOOKUP($L679,Data_Validation!$A:$E,5,0) -> NB | X679: =+VLOOKUP($L679,Data_Validation!$A:$F,6,0) -> 0
