Workbook
Name _Dates_Conc: #REF!
Name _scen: #REF!
Name _scen1: #REF!
Name _scen2: #REF!
Name _SCenarios: #REF!
Name _Sens1: #REF!
Name _Sens2: #REF!
Name _sensRes1: #REF!
Name _sensRes2: #REF!
Name _sensRes3: #REF!
Name _sensRes4: #REF!
Name _sensRes5: #REF!
Name _sensRes6: #REF!
Name _sensRes7: #REF!
Name DateRange: #REF!
Name Monetary_Unit: #REF!
Name Months: #REF!
Name Rng_Dealers_Names: #REF!
Name Rng_Dlr_Dates: #REF!
Name Titre: #REF!

Sheet Paramètre
B3: Quarter | C3: Q3 2026
B6: BUDGET | F6: BUDGET RÉVISÉ | J6: ACTUAL | N6: LAST YEAR
B7: Ventes | C7: Profits bruts | D7: BAIIA | E7: EBIT | F7: Ventes | G7: Profits bruts | H7: BAIIA | I7: EBIT | J7: Ventes | K7: Profits bruts | L7: BAIIA | M7: EBIT | N7: Ventes | O7: Profits bruts | P7: BAIIA | Q7: EBIT
A8: CTRL | B8: =+B9-B10 -> 0 | C8: =+C9-C10 -> 0 | D8: =+D9-D10 -> 0 | E8: =+E9-E10 -> #N/A | F8: =+F9-F10 -> 0 | G8: =+G9-G10 -> 0 | H8: =+H9-H10 -> 0 | I8: =+I9-I10 -> 0 | ... Q8: =+Q9-Q10 -> 0
A9: CONSO | B9: =+Conso!$Z$406 -> 0 | C9: =+Conso!$Z$407 -> 0 | D9: =+Conso!$Z$483 -> 0 | E9: =+Conso!$Z$498 -> #N/A | F9: =+Conso!$AC$406 -> 0 | G9: =+Conso!$AC$407 -> 0 | H9: =+Conso!$AC$483 -> 0 | I9: =+Conso!$AC$498 -> 0 | J9: =+Conso!$AF$406 -> 0 | K9: =+Conso!$AF$407 -> 0 | L9: =+Conso!$AF$483 -> 0 | M9: =+Conso!$AF$498 -> 79425.5 | N9: =+Conso!$AL$406 -> 0 | O9: =+Conso!$AL$407 -> 0 | P9: =+Conso!$AL$483 -> 0 | Q9: =+Conso!$AL$498 -> -68069.87
A10: TOTAL | B10: =+SUM(B11:B13) -> 0 | C10: =+SUM(C11:C13) -> 0 | D10: =+SUM(D11:D13) -> 0 | E10: =+SUM(E11:E13) -> #N/A | F10: =+SUM(F11:F13) -> 0 | G10: =+SUM(G11:G13) -> 0 | H10: =+SUM(H11:H13) -> 0 | I10: =+SUM(I11:I13) -> 0 | ... Q10: =+SUM(Q11:Q13) -> -68069.87
A11: Mois 1 | B11: =+'Mois 1'!$Z$406 -> 0 | C11: =+'Mois 1'!$Z$407 -> 0 | D11: =+'Mois 1'!$Z$483 -> 0 | E11: =+'Mois 1'!$Z$498 -> 0 | F11: =+'Mois 1'!$AC$406 -> 0 | G11: =+'Mois 1'!$AC$407 -> 0 | H11: =+'Mois 1'!$AC$483 -> 0 | I11: =+'Mois 1'!$AC$498 -> 0 | J11: =+'Mois 1'!$AF$406 -> 0 | K11: =+'Mois 1'!$AF$407 -> 0 | L11: =+'Mois 1'!$AF$483 -> 0 | M11: =+'Mois 1'!$AF$498 -> 54212.21 | N11: =+'Mois 1'!$AL$406 -> 0 | O11: =+'Mois 1'!$AL$407 -> 0 | P11: =+'Mois 1'!$AL$483 -> 0 | Q11: =+'Mois 1'!$AL$498 -> -39608.48
A12: Mois 2 | B12: =+'Mois 2'!$Z$406 -> 0 | C12: =+'Mois 2'!$Z$407 -> 0 | D12: =+'Mois 2'!$Z$483 -> 0 | E12: =+'Mois 2'!$Z$498 -> #N/A | F12: =+'Mois 2'!$AC$406 -> 0 | G12: =+'Mois 2'!$AC$407 -> 0 | H12: =+'Mois 2'!$AC$483 -> 0 | I12: =+'Mois 2'!$AC$498 -> 0 | J12: =+'Mois 2'!$AF$406 -> 0 | K12: =+'Mois 2'!$AF$407 -> 0 | L12: =+'Mois 2'!$AF$483 -> 0 | M12: =+'Mois 2'!$AF$498 -> -2581.44 | N12: =+'Mois 2'!$AL$406 -> 0 | O12: =+'Mois 2'!$AL$407 -> 0 | P12: =+'Mois 2'!$AL$483 -> 0 | Q12: =+'Mois 2'!$AL$498 -> -22956.37
A13: Mois 3 | B13: =+'Mois 3'!$Z$406 -> 0 | C13: =+'Mois 3'!$Z$407 -> 0 | D13: =+'Mois 3'!$Z$483 -> 0 | E13: =+'Mois 3'!$Z$498 -> 0 | F13: =+'Mois 3'!$AC$406 -> 0 | G13: =+'Mois 3'!$AC$407 -> 0 | H13: =+'Mois 3'!$AC$483 -> 0 | I13: =+'Mois 3'!$AC$498 -> 0 | J13: =+'Mois 3'!$AF$406 -> 0 | K13: =+'Mois 3'!$AF$407 -> 0 | L13: =+'Mois 3'!$AF$483 -> 0 | M13: =+'Mois 3'!$AF$498 -> 27794.73 | N13: =+'Mois 3'!$AL$406 -> 0 | O13: =+'Mois 3'!$AL$407 -> 0 | P13: =+'Mois 3'!$AL$483 -> 0 | Q13: =+'Mois 3'!$AL$498 -> -5505.02

Sheet Conso
C1: Ste-Marie Auto | K1: Véhicules neufs | S1: =CONCATENATE("Réalisé"," ",Paramètre!$C$2," ",Paramètre!$C$3) -> Réalisé Q3 2026
D2: X | E2: O | F2: U | G2: X | H2: O | I2: U
D3: BUDGET ORIGINAL | G3: BUDGET REVISE | J3: RÉALISATION | M3: ÉCART réel / Budget | O3: ANNÉE PRÉCÉDENTE | R3: ECART (réel/ Ann.Préc.)
D4: UNITE | E4: $P/UNITÉ | F4: $PROFITS | G4: UNITE | H4: $P/UNITÉ | I4: $PROFITS | J4: UNITE | K4: $P/UNITE | L4: $PROFITS | M4: UNFTÉ | N4: $PROFITS | O4: UNITE | P4: $P/UNITE | Q4: $PROFITS | R4: UNITE | S4: $PROFITS
A5: =+B5&C5 -> Véhicules neufsVentes nettes | B5: =+$K$1 -> Véhicules neufs | C5: Ventes nettes | F5: =+SUM(START:END!F5) -> #N/A | I5: =+SUM(START:END!I5) -> 0 | L5: =+SUM(START:END!L5) -> 20559481 | Q5: =+SUM(START:END!Q5) -> 28344574
A6: =+B6&C6 -> Véhicules neufsAutos détail | B6: =+$K$1 -> Véhicules neufs | C6: Autos détail | D6: =+SUM(START:END!D6) -> #N/A | E6: =IF(D6=0,0,F6/D6) -> #N/A | F6: =+SUM(START:END!F6) -> #N/A | G6: =+SUM(START:END!G6) -> 0 | H6: =IF(G6=0,0,I6/G6) -> 0 | I6: =+SUM(START:END!I6) -> 0 | J6: =+SUM(START:END!J6) -> 2 | K6: =IF(J6=0,0,L6/J6) -> 6531.68 | L6: =+SUM(START:END!L6) -> 13063.36 | M6: =J6-D6 -> #N/A | N6: =L6-F6 -> #N/A | O6: =+SUM(START:END!O6) -> 2 | P6: =IF(O6=0,0,Q6/O6) -> 5561 | Q6: =+SUM(START:END!Q6) -> 11122 | R6: =J6-O6 -> 0 | S6: =L6-Q6 -> 1941.36
A7: =+B7&C7 -> Véhicules neufsCamions détail | B7: =+$K$1 -> Véhicules neufs | C7: Camions détail | D7: =+SUM(START:END!D7) -> #N/A | E7: =IF(D7=0,0,F7/D7) -> #N/A | F7: =+SUM(START:END!F7) -> #N/A | G7: =+SUM(START:END!G7) -> 0 | H7: =IF(G7=0,0,I7/G7) -> 0 | I7: =+SUM(START:END!I7) -> 0 | J7: =+SUM(START:END!J7) -> 88 | K7: =IF(J7=0,0,L7/J7) -> 2402.4967 | L7: =+SUM(START:END!L7) -> 211419.71 | M7: =J7-D7 -> #N/A | N7: =L7-F7 -> #N/A | O7: =+SUM(START:END!O7) -> 164 | P7: =IF(O7=0,0,Q7/O7) -> 2885.1216 | Q7: =+SUM(START:END!Q7) -> 473159.95 | R7: =J7-O7 -> -76 | S7: =L7-Q7 -> -261740.24
A8: =+B8&C8 -> Véhicules neufsSprinter | B8: =+$K$1 -> Véhicules neufs | C8: Sprinter | D8: =+SUM(START:END!D8) -> #N/A | E8: =IF(D8=0,0,F8/D8) -> #N/A | F8: =+SUM(START:END!F8) -> #N/A | G8: =+SUM(START:END!G8) -> 0 | H8: =IF(G8=0,0,I8/G8) -> 0 | I8: =+SUM(START:END!I8) -> 0 | J8: =+SUM(START:END!J8) -> 0 | K8: =IF(J8=0,0,L8/J8) -> 0 | L8: =+SUM(START:END!L8) -> 0 | M8: =J8-D8 -> #N/A | N8: =L8-F8 -> #N/A | O8: =+SUM(START:END!O8) -> 0 | P8: =IF(O8=0,0,Q8/O8) -> 0 | Q8: =+SUM(START:END!Q8) -> 0 | R8: =J8-O8 -> 0 | S8: =L8-Q8 -> 0
A9: =+B9&C9 -> Véhicules neufsMoto détail | B9: =+$K$1 -> Véhicules neufs | C9: Moto détail | D9: =+SUM(START:END!D9) -> #N/A | E9: =IF(D9=0,0,F9/D9) -> #N/A | F9: =+SUM(START:END!F9) -> #N/A | G9: =+SUM(START:END!G9) -> 0 | H9: =IF(G9=0,0,I9/G9) -> 0 | I9: =+SUM(START:END!I9) -> 0 | J9: =+SUM(START:END!J9) -> 96 | K9: =IF(J9=0,0,L9/J9) -> 1377.6127 | L9: =+SUM(START:END!L9) -> 132250.82 | M9: =J9-D9 -> #N/A | N9: =L9-F9 -> #N/A | O9: =+SUM(START:END!O9) -> 53 | P9: =IF(O9=0,0,Q9/O9) -> 1144.1613 | Q9: =+SUM(START:END!Q9) -> 60640.55 | R9: =J9-O9 -> 43 | S9: =L9-Q9 -> 71610.27
A10: =+B10&C10 -> Véhicules neufs[...] | B10: =+$K$1 -> Véhicules neufs | C10: [...] | D10: =+SUM(START:END!D10) -> #N/A | E10: =IF(D10=0,0,F10/D10) -> #N/A | F10: =+SUM(START:END!F10) -> #N/A | G10: =+SUM(START:END!G10) -> 0 | H10: =IF(G10=0,0,I10/G10) -> 0 | I10: =+SUM(START:END!I10) -> 0 | J10: =+SUM(START:END!J10) -> 0 | K10: =IF(J10=0,0,L10/J10) -> 0 | L10: =+SUM(START:END!L10) -> 0 | M10: =J10-D10 -> #N/A | N10: =L10-F10 -> #N/A | O10: =+SUM(START:END!O10) -> 0 | P10: =IF(O10=0,0,Q10/O10) -> 0 | Q10: =+SUM(START:END!Q10) -> 0 | R10: =J10-O10 -> 0 | S10: =L10-Q10 -> 0
A11: =+B11&C11 -> Véhicules neufs[...] | B11: =+$K$1 -> Véhicules neufs | C11: [...] | D11: =+SUM(START:END!D11) -> #N/A | E11: =IF(D11=0,0,F11/D11) -> #N/A | F11: =+SUM(START:END!F11) -> #N/A | G11: =+SUM(START:END!G11) -> 0 | H11: =IF(G11=0,0,I11/G11) -> 0 | I11: =+SUM(START:END!I11) -> 0 | J11: =+SUM(START:END!J11) -> 0 | K11: =IF(J11=0,0,L11/J11) -> 0 | L11: =+SUM(START:END!L11) -> 0 | M11: =J11-D11 -> #N/A | N11: =L11-F11 -> #N/A | O11: =+SUM(START:END!O11) -> 0 | P11: =IF(O11=0,0,Q11/O11) -> 0 | Q11: =+SUM(START:END!Q11) -> 0 | R11: =J11-O11 -> 0 | S11: =L11-Q11 -> 0
A12: =+B12&C12 -> Véhicules neufs[...] | B12: =+$K$1 -> Véhicules neufs | C12: [...] | D12: =+SUM(START:END!D12) -> #N/A | E12: =IF(D12=0,0,F12/D12) -> #N/A | F12: =+SUM(START:END!F12) -> #N/A | G12: =+SUM(START:END!G12) -> 0 | H12: =IF(G12=0,0,I12/G12) -> 0 | I12: =+SUM(START:END!I12) -> 0 | J12: =+SUM(START:END!J12) -> 0 | K12: =IF(J12=0,0,L12/J12) -> 0 | L12: =+SUM(START:END!L12) -> 0 | M12: =J12-D12 -> #N/A | N12: =L12-F12 -> #N/A | O12: =+SUM(START:END!O12) -> 0 | P12: =IF(O12=0,0,Q12/O12) -> 0 | Q12: =+SUM(START:END!Q12) -> 0 | R12: =J12-O12 -> 0 | S12: =L12-Q12 -> 0
A13: =+B13&C13 -> Véhicules neufsTotal Neufs | B13: =+$K$1 -> Véhicules neufs | C13: Total Neufs | D13: =+SUM(D6:D12) -> #N/A | E13: =IF(D13<=0,0,F13/D13) -> #N/A | F13: =+SUM(F6:F12) -> #N/A | G13: =+SUM(G6:G12) -> 0 | H13: =IF(G13<=0,0,I13/G13) -> 0 | I13: =+SUM(I6:I12) -> 0 | J13: =+SUM(J6:J12) -> 186 | K13: =IF(J13<=0,0,L13/J13) -> 1917.9241 | L13: =+SUM(L6:L12) -> 356733.89 | M13: =+SUM(M6:M12) -> #N/A | N13: =+SUM(N6:N12) -> #N/A | O13: =+SUM(O6:O12) -> 219 | P13: =IF(O13<=0,0,Q13/O13) -> 2488.2306 | Q13: =+SUM(Q6:Q12) -> 544922.5 | R13: =+SUM(R6:R12) -> -33 | S13: =+SUM(S6:S12) -> -188188.61
A14: =+B14&C14 -> Véhicules neufs | B14: =+$K$1 -> Véhicules neufs | M14: =IF(D13=0,0,M13/D13) -> #N/A | N14: =IF(F13=0,0,N13/F13) -> #N/A | R14: =R13/O13 -> -0.15068493 | S14: =IF(Q13=0,0,(S13/Q13)) -> -0.34534931
A15: =+B15&C15 -> Véhicules neufsEx-Démos et courtoisies | B15: =+$K$1 -> Véhicules neufs | C15: Ex-Démos et courtoisies | D15: =+SUM(START:END!D15) -> #N/A | E15: =IF(D15=0,0,F15/D15) -> #N/A | F15: =+SUM(START:END!F15) -> #N/A | G15: =+SUM(START:END!G15) -> 0 | H15: =IF(G15=0,0,I15/G15) -> 0 | I15: =+SUM(START:END!I15) -> 0 | J15: =+SUM(START:END!J15) -> 0 | K15: =IF(J15=0,0,L15/J15) -> 0 | L15: =+SUM(START:END!L15) -> 0 | M15: =J15-D15 -> #N/A | N15: =L15-F15 -> #N/A | O15: =+SUM(START:END!O15) -> 0 | P15: =IF(O15=0,0,Q15/O15) -> 0 | Q15: =+SUM(START:END!Q15) -> 0 | R15: =J15-O15 -> 0 | S15: =L15-Q15 -> 0
A16: =+B16&C16 -> Véhicules neufs | B16: =+$K$1 -> Véhicules neufs
A17: =+B17&C17 -> Véhicules neufsFlottes | B17: =+$K$1 -> Véhicules neufs | C17: Flottes | D17: =+SUM(START:END!D17) -> #N/A | E17: =IF(D17=0,0,F17/D17) -> #N/A | F17: =+SUM(START:END!F17) -> #N/A | G17: =+SUM(START:END!G17) -> 0 | H17: =IF(G17=0,0,I17/G17) -> 0 | I17: =+SUM(START:END!I17) -> 0 | J17: =+SUM(START:END!J17) -> 143 | K17: =IF(J17=0,0,L17/J17) -> 607.78049 | L17: =+SUM(START:END!L17) -> 86912.61 | M17: =J17-D17 -> #N/A | N17: =L17-F17 -> #N/A | O17: =+SUM(START:END!O17) -> 229 | P17: =IF(O17=0,0,Q17/O17) -> 627.69668 | Q17: =+SUM(START:END!Q17) -> 143742.54 | R17: =J17-O17 -> -86 | S17: =L17-Q17 -> -56829.93
A18: =+B18&C18 -> Véhicules neufs | B18: =+$K$1 -> Véhicules neufs
A19: =+B19&C19 -> Véhicules neufsRachat bail | B19: =+$K$1 -> Véhicules neufs | C19: Rachat bail | F19: =+SUM(START:END!F19) -> 0 | I19: =+SUM(START:END!I19) -> 0 | L19: =+SUM(START:END!L19) -> 0 | N19: =L19-F19 -> 0 | Q19: =+SUM(START:END!Q19) -> 0 | R19: =O19-K19 -> 0 | S19: =L19-Q19 -> 0
A20: =+B20&C20 -> Véhicules neufs | B20: =+$K$1 -> Véhicules neufs
A21: =+B21&C21 -> Véhicules neufsRev. Finances | B21: =+$K$1 -> Véhicules neufs | C21: Rev. Finances | D21: 0 | E21: =IF(D21=0,0,F21/D21) -> 0 | F21: =+SUM(START:END!F21) -> #N/A | G21: 0 | H21: =IF(G21=0,0,I21/G21) -> 0 | I21: =+SUM(START:END!I21) -> 0 | K21: =IF(J13=0,0,L21/(J13+J15)) -> -1.7697849 | L21: =+SUM(START:END!L21) -> -329.18 | N21: =L21-F21 -> #N/A | P21: =IF(O13=0,0,Q21/(O13+O15)) -> 8.0162557 | Q21: =+SUM(START:END!Q21) -> 1755.56 | R21: =O21-K21 -> 1.7697849 | S21: =L21-Q21 -> -2084.74
A22: =+B22&C22 -> Véhicules neufsRev. Protections | B22: =+$K$1 -> Véhicules neufs | C22: Rev. Protections | D22: 0 | E22: =IF(D22=0,0,F22/D22) -> 0 | F22: =+SUM(START:END!F22) -> #N/A | G22: 0 | H22: =IF(G22=0,0,I22/G22) -> 0 | I22: =+SUM(START:END!I22) -> 0 | K22: =IF(J13=0,0,L22/(J13+J15)) -> 559.97274 | L22: =+SUM(START:END!L22) -> 104154.93 | N22: =L22-F22 -> #N/A | P22: =IF(O13=0,0,Q22/(O13+O15)) -> 689.24918 | Q22: =+SUM(START:END!Q22) -> 150945.57 | R22: =O22-K22 -> -559.97274 | S22: =L22-Q22 -> -46790.64
A23: =+B23&C23 -> Véhicules neufsRev. Autres | B23: =+$K$1 -> Véhicules neufs | C23: Rev. Autres | D23: 0 | E23: =IF(D23=0,0,F23/D23) -> 0 | F23: =+SUM(START:END!F23) -> #N/A | G23: 0 | H23: =IF(G23=0,0,I23/G23) -> 0 | I23: =+SUM(START:END!I23) -> 0 | K23: =IF(J13=0,0,L23/(J13+J15)) -> 55.863656 | L23: =+SUM(START:END!L23) -> 10390.64 | N23: =L23-F23 -> #N/A | P23: =IF(O13=0,0,Q23/(O13+O15)) -> 123.58146 | Q23: =+SUM(START:END!Q23) -> 27064.34 | R23: =O23-K23 -> -55.863656 | S23: =L23-Q23 -> -16673.7
A24: =+B24&C24 -> Véhicules neufsTotal F&I | B24: =+$K$1 -> Véhicules neufs | C24: Total F&I | D24: =+D15+D13 -> #N/A | E24: =IF(D24<=0,0,F24/D24) -> #N/A | F24: =F21+F22+F23 -> #N/A | G24: =+G15+G13 -> 0 | H24: =IF(G24<=0,0,I24/G24) -> 0 | I24: =I21+I22+I23 -> 0 | J24: =+J15+J13 -> 186 | K24: =IF(J24<=0,0,L24/J24) -> 614.06661 | L24: =L21+L22+L23 -> 114216.39 | M24: =J24-D24 -> #N/A | N24: =L24-F24 -> #N/A | O24: =+O15+O13 -> 219 | P24: =IF(O24<=0,0,Q24/O24) -> 820.84689 | Q24: =Q21+Q22+Q23 -> 179765.47 | S24: =L24-Q24 -> -65549.08
A25: =+B25&C25 -> Véhicules neufs | B25: =+$K$1 -> Véhicules neufs | N25: =IF(N24=0,0,N24/F24) -> #N/A | S25: =IF(Q24=0,0,(S24/Q24)) -> -0.36463666
A26: =+B26&C26 -> Véhicules neufs | B26: =+$K$1 -> Véhicules neufs
A27: =+B27&C27 -> Véhicules neufsTotal Dépt. Neufs | B27: =+$K$1 -> Véhicules neufs | C27: Total Dépt. Neufs | D27: =+D13+D15+D17 -> #N/A | E27: =IF(D27<=0,0,F27/D27) -> #N/A | F27: =F13+F17+F24+F19+F15 -> #N/A | G27: =+G13+G15+G17 -> 0 | H27: =IF(G27<=0,0,I27/G27) -> 0 | I27: =I13+I17+I24+I19+I15 -> 0 | J27: =+J13+J15+J17 -> 329 | K27: =IF(J27<=0,0,L27/J27) -> 1695.6319 | L27: =L13+L17+L24+L19+L15 -> 557862.89 | M27: =J27-D27 -> #N/A | N27: =L27-F27 -> #N/A | O27: =+O13+O15+O17 -> 448 | P27: =IF(O27<=0,0,Q27/O27) -> 1938.461 | Q27: =Q13+Q17+Q24+Q19+Q15 -> 868430.51 | R27: =J27-O27 -> -119 | S27: =L27-Q27 -> -310567.62
A28: =+B28&C28 -> Véhicules neufs | B28: =+$K$1 -> Véhicules neufs | M28: =M27/D27 -> #N/A | N28: =N27/F27 -> #N/A | R28: =R27/O27 -> -0.265625 | S28: =IF(Q27=0,0,S27/Q27) -> -0.35761943
A29: =+B29&C29 -> Véhicules neufs | B29: =+$K$1 -> Véhicules neufs
A30: =+B30&C30 -> Véhicules neufsDEPENSES | B30: =+$K$1 -> Véhicules neufs | C30: DEPENSES
A31: =+B31&C31 -> Véhicules neufsComm. vendeurs | B31: =+$K$1 -> Véhicules neufs | C31: Comm. vendeurs | D31: =F31/(F13+F15) -> #N/A | E31: =F31/D$24 -> #N/A | F31: =+SUM(START:END!F31) -> #N/A | H31: =I31/G$24 -> #DIV/0! | I31: =+SUM(START:END!I31) -> 0 | J31: =L31/(L13+L15) -> 0.3566161 | K31: =IF(L31=0,0,L31/J$24) -> 683.96263 | L31: =+SUM(START:END!L31) -> 127217.05 | N31: =L31-F31 -> #N/A | O31: =Q31/(Q13+Q15+Q17) -> 0.24949816 | P31: =IF(Q31=0,0,Q31/O$24) -> 784.56922 | Q31: =+SUM(START:END!Q31) -> 171820.66 | S31: =L31-Q31 -> -44603.61
A32: =+B32&C32 -> Véhicules neufsComm. F&I | B32: =+$K$1 -> Véhicules neufs | C32: Comm. F&I | D32: =F32/F24 -> #N/A | E32: =F32/D$24 -> #N/A | F32: =+SUM(START:END!F32) -> #N/A | H32: =I32/G$24 -> #DIV/0! | I32: =+SUM(START:END!I32) -> 0 | J32: =L32/L24 -> 0.31187477 | K32: =IF(L32=0,0,L32/J$24) -> 191.51188 | L32: =+SUM(START:END!L32) -> 35621.21 | N32: =L32-F32 -> #N/A | O32: =Q32/Q24 -> 0.26191304 | P32: =IF(Q32=0,0,Q32/O$24) -> 214.9905 | Q32: =+SUM(START:END!Q32) -> 47082.92 | S32: =L32-Q32 -> -11461.71
A33: =+B33&C33 -> Véhicules neufsFrais de livraison | B33: =+$K$1 -> Véhicules neufs | C33: Frais de livraison | E33: =F33/D$24 -> #N/A | F33: =+SUM(START:END!F33) -> #N/A | H33: =I33/G$24 -> #DIV/0! | I33: =+SUM(START:END!I33) -> 0 | K33: =IF(L33=0,0,L33/J$24) -> 424.52414 | L33: =+SUM(START:END!L33) -> 78961.49 | N33: =L33-F33 -> #N/A | P33: =IF(Q33=0,0,Q33/O$24) -> -123.47598 | Q33: =+SUM(START:END!Q33) -> -27041.24 | S33: =L33-Q33 -> 106002.73
A34: =+B34&C34 -> Véhicules neufsService gratuit 1 | B34: =+$K$1 -> Véhicules neufs | C34: Service gratuit 1 | E34: =F34/D$24 -> #N/A | F34: =+SUM(START:END!F34) -> #N/A | H34: =I34/G$24 -> #DIV/0! | I34: =+SUM(START:END!I34) -> 0 | K34: =IF(L34=0,0,L34/J$24) -> 8.211828 | L34: =+SUM(START:END!L34) -> 1527.4 | N34: =L34-F34 -> #N/A | P34: =IF(Q34=0,0,Q34/O$24) -> 7.4466667 | Q34: =+SUM(START:END!Q34) -> 1630.82 | S34: =L34-Q34 -> -103.42
A35: =+B35&C35 -> Véhicules neufsEntretien stock | B35: =+$K$1 -> Véhicules neufs | C35: Entretien stock | E35: =F35/D$24 -> #N/A | F35: =+SUM(START:END!F35) -> #N/A | H35: =I35/G$24 -> #DIV/0! | I35: =+SUM(START:END!I35) -> 0 | K35: =IF(L35=0,0,L35/J$24) -> 52.831613 | L35: =+SUM(START:END!L35) -> 9826.68 | N35: =L35-F35 -> #N/A | P35: =IF(Q35=0,0,Q35/O$24) -> 0 | Q35: =+SUM(START:END!Q35) -> 0 | S35: =L35-Q35 -> 9826.68
A36: =+B36&C36 -> Véhicules neufsPublicité 1 | B36: =+$K$1 -> Véhicules neufs | C36: Publicité 1 | E36: =F36/D$24 -> #N/A | F36: =+SUM(START:END!F36) -> #N/A | H36: =I36/G$24 -> #DIV/0! | I36: =+SUM(START:END!I36) -> 0 | K36: =IF(L36=0,0,L36/J$24) -> -206.73672 | L36: =+SUM(START:END!L36) -> -38453.03 | N36: =L36-F36 -> #N/A | P36: =IF(Q36=0,0,Q36/O$24) -> -300.0332 | Q36: =+SUM(START:END!Q36) -> -65707.27 | S36: =L36-Q36 -> 27254.24
A37: =+B37&C37 -> Véhicules neufsIntérêt de gros | B37: =+$K$1 -> Véhicules neufs | C37: Intérêt de gros | E37: =F37/D$24 -> #N/A | F37: =+SUM(START:END!F37) -> #N/A | H37: =I37/G$24 -> #DIV/0! | I37: =+SUM(START:END!I37) -> 0 | K37: =IF(L37=0,0,L37/J$24) -> 666.81253 | L37: =+SUM(START:END!L37) -> 124027.13 | N37: =L37-F37 -> #N/A | P37: =IF(Q37=0,0,Q37/O$24) -> 833.86785 | Q37: =+SUM(START:END!Q37) -> 182617.06 | S37: =L37-Q37 -> -58589.93
A38: =+B38&C38 -> Véhicules neufsCrédit Intérêts Floor Plan | B38: =+$K$1 -> Véhicules neufs | C38: Crédit Intérêts Floor Plan | E38: =F38/D$24 -> #N/A | F38: =+SUM(START:END!F38) -> #N/A | H38: =I38/G$24 -> #DIV/0! | I38: =+SUM(START:END!I38) -> 0 | K38: =IF(L38=0,0,L38/J$24) -> -1753.4539 | L38: =+SUM(START:END!L38) -> -326142.42 | N38: =L38-F38 -> #N/A | P38: =IF(Q38=0,0,Q38/O$24) -> -2034.5403 | Q38: =+SUM(START:END!Q38) -> -445564.33 | S38: =L38-Q38 -> 119421.91
A39: =+B39&C39 -> Véhicules neufsCrédit Boni TD | B39: =+$K$1 -> Véhicules neufs | C39: Crédit Boni TD | E39: =F39/D$24 -> #N/A | F39: =+SUM(START:END!F39) -> #N/A | H39: =I39/G$24 -> #DIV/0! | I39: =+SUM(START:END!I39) -> 0 | K39: =IF(L39=0,0,L39/J$24) -> -167.32565 | L39: =+SUM(START:END!L39) -> -31122.57 | N39: =L39-F39 -> #N/A | P39: =IF(Q39=0,0,Q39/O$24) -> 0 | Q39: =+SUM(START:END!Q39) -> 0 | S39: =L39-Q39 -> -31122.57
A40: =+B40&C40 -> Véhicules neufs[...] | B40: =+$K$1 -> Véhicules neufs | C40: [...] | E40: =F40/D$24 -> #N/A | F40: =+SUM(START:END!F40) -> #N/A | H40: =I40/G$24 -> #DIV/0! | I40: =+SUM(START:END!I40) -> 0 | K40: =IF(L40=0,0,L40/J$24) -> 0 | L40: =+SUM(START:END!L40) -> 0 | N40: =L40-F40 -> #N/A | P40: =IF(Q40=0,0,Q40/O$24) -> 0 | Q40: =+SUM(START:END!Q40) -> 0 | S40: =L40-Q40 -> 0
A41: =+B41&C41 -> Véhicules neufsTOTAL VARIABLES | B41: =+$K$1 -> Véhicules neufs | C41: TOTAL VARIABLES | D41: % brut | E41: =F41/F$27 -> #N/A | F41: =SUM(F31:F40) -> #N/A | G41: % brut | H41: =I41/I$27 -> #DIV/0! | I41: =SUM(I31:I40) -> 0 | J41: % brut | K41: =L41/L$27 -> -0.033228702 | L41: =SUM(L31:L40) -> -18537.06 | N41: =L41-F41 -> #N/A | O41: % brut | P41: =Q41/Q$27 -> -0.15563868 | Q41: =SUM(Q31:Q40) -> -135161.38 | S41: =L41-Q41 -> 116624.32
A42: =+B42&C42 -> Véhicules neufsSalaires cadres | B42: =+$K$1 -> Véhicules neufs | C42: Salaires cadres | F42: =+SUM(START:END!F42) -> #N/A | I42: =+SUM(START:END!I42) -> 0 | L42: =+SUM(START:END!L42) -> 42554.86 | N42: =L42-F42 -> #N/A | Q42: =+SUM(START:END!Q42) -> 25212.01 | S42: =L42-Q42 -> 17342.85
A43: =+B43&C43 -> Véhicules neufsSalaires commis | B43: =+$K$1 -> Véhicules neufs | C43: Salaires commis | F43: =+SUM(START:END!F43) -> #N/A | I43: =+SUM(START:END!I43) -> 0 | L43: =+SUM(START:END!L43) -> 28600.69 | N43: =L43-F43 -> #N/A | Q43: =+SUM(START:END!Q43) -> 88313.65 | S43: =L43-Q43 -> -59712.96
A44: =+B44&C44 -> Véhicules neufsSalaires autres | B44: =+$K$1 -> Véhicules neufs | C44: Salaires autres | F44: =+SUM(START:END!F44) -> #N/A | I44: =+SUM(START:END!I44) -> 0 | L44: =+SUM(START:END!L44) -> 24202.14 | N44: =L44-F44 -> #N/A | Q44: =+SUM(START:END!Q44) -> 13784.28 | S44: =L44-Q44 -> 10417.86
A45: =+B45&C45 -> Véhicules neufsSalaires spécialistes | B45: =+$K$1 -> Véhicules neufs | C45: Salaires spécialistes | F45: =+SUM(START:END!F45) -> #N/A | I45: =+SUM(START:END!I45) -> 0 | L45: =+SUM(START:END!L45) -> 0 | N45: =L45-F45 -> #N/A | Q45: =+SUM(START:END!Q45) -> 0 | S45: =L45-Q45 -> 0
A46: =+B46&C46 -> Véhicules neufs[...] | B46: =+$K$1 -> Véhicules neufs | C46: [...] | F46: =+SUM(START:END!F46) -> #N/A | I46: =+SUM(START:END!I46) -> 0 | L46: =+SUM(START:END!L46) -> 0 | N46: =L46-F46 -> #N/A | Q46: =+SUM(START:END!Q46) -> 0 | S46: =L46-Q46 -> 0
A47: =+B47&C47 -> Véhicules neufs[...] | B47: =+$K$1 -> Véhicules neufs | C47: [...] | F47: =+SUM(START:END!F47) -> #N/A | I47: =+SUM(START:END!I47) -> 0 | L47: =+SUM(START:END!L47) -> 0 | N47: =L47-F47 -> #N/A | Q47: =+SUM(START:END!Q47) -> 0 | S47: =L47-Q47 -> 0
A48: =+B48&C48 -> Véhicules neufs[...] | B48: =+$K$1 -> Véhicules neufs | C48: [...] | F48: =+SUM(START:END!F48) -> #N/A | I48: =+SUM(START:END!I48) -> 0 | L48: =+SUM(START:END!L48) -> 0 | N48: =L48-F48 -> #N/A | Q48: =+SUM(START:END!Q48) -> 0 | S48: =L48-Q48 -> 0
A49: =+B49&C49 -> Véhicules neufsSalaires en absences | B49: =+$K$1 -> Véhicules neufs | C49: Salaires en absences | F49: =+SUM(START:END!F49) -> #N/A | I49: =+SUM(START:END!I49) -> 0 | L49: =+SUM(START:END!L49) -> 20651.02 | N49: =L49-F49 -> #N/A | Q49: =+SUM(START:END!Q49) -> 37852.63 | S49: =L49-Q49 -> -17201.61
A50: =+B50&C50 -> Véhicules neufsDéduction à la source | B50: =+$K$1 -> Véhicules neufs | C50: Déduction à la source | F50: =+SUM(START:END!F50) -> #N/A | I50: =+SUM(START:END!I50) -> 0 | L50: =+SUM(START:END!L50) -> 26952.98 | N50: =L50-F50 -> #N/A | Q50: =+SUM(START:END!Q50) -> 48777.33 | S50: =L50-Q50 -> -21824.35
A51: =+B51&C51 -> Véhicules neufsBénéfices marginaux | B51: =+$K$1 -> Véhicules neufs | C51: Bénéfices marginaux | F51: =+SUM(START:END!F51) -> #N/A | I51: =+SUM(START:END!I51) -> 0 | L51: =+SUM(START:END!L51) -> 5571.16 | N51: =L51-F51 -> #N/A | Q51: =+SUM(START:END!Q51) -> 12570.6 | S51: =L51-Q51 -> -6999.44
A52: =+B52&C52 -> Véhicules neufsCsst | B52: =+$K$1 -> Véhicules neufs | C52: Csst | F52: =+SUM(START:END!F52) -> #N/A | I52: =+SUM(START:END!I52) -> 0 | L52: =+SUM(START:END!L52) -> 10531.27 | N52: =L52-F52 -> #N/A | Q52: =+SUM(START:END!Q52) -> 48.05 | S52: =L52-Q52 -> 10483.22
A53: =+B53&C53 -> Véhicules neufs[...] | B53: =+$K$1 -> Véhicules neufs | C53: [...] | F53: =+SUM(START:END!F53) -> #N/A | I53: =+SUM(START:END!I53) -> 0 | L53: =+SUM(START:END!L53) -> 0 | N53: =L53-F53 -> #N/A | Q53: =+SUM(START:END!Q53) -> 0 | S53: =L53-Q53 -> 0
A54: =+B54&C54 -> Véhicules neufsTOTAL PERSONNEL | B54: =+$K$1 -> Véhicules neufs | C54: TOTAL PERSONNEL | D54: % brut | E54: =F54/F$27 -> #N/A | F54: =+SUM(F42:F53) -> #N/A | G54: % brut | H54: =I54/I$27 -> #DIV/0! | I54: =+SUM(I42:I53) -> 0 | J54: % brut | K54: =L54/L$27 -> 0.28513121 | L54: =+SUM(L42:L53) -> 159064.12 | N54: =+SUM(N42:N53) -> #N/A | O54: % brut | P54: =Q54/Q$27 -> 0.26088276 | Q54: =+SUM(Q42:Q53) -> 226558.55 | S54: =+SUM(S42:S53) -> -67494.43
A55: =+B55&C55 -> Véhicules neufsPublicité 2 | B55: =+$K$1 -> Véhicules neufs | C55: Publicité 2 | F55: =+SUM(START:END!F55) -> #N/A | I55: =+SUM(START:END!I55) -> 0 | L55: =+SUM(START:END!L55) -> 0 | N55: =L55-F55 -> #N/A | Q55: =+SUM(START:END!Q55) -> 0 | S55: =L55-Q55 -> 0
A56: =+B56&C56 -> Véhicules neufsService gratuit 2 | B56: =+$K$1 -> Véhicules neufs | C56: Service gratuit 2 | F56: =+SUM(START:END!F56) -> #N/A | I56: =+SUM(START:END!I56) -> 0 | L56: =+SUM(START:END!L56) -> 0 | N56: =L56-F56 -> #N/A | Q56: =+SUM(START:END!Q56) -> 0 | S56: =L56-Q56 -> 0
A57: =+B57&C57 -> Véhicules neufsFrais véhicules de cie | B57: =+$K$1 -> Véhicules neufs | C57: Frais véhicules de cie | F57: =+SUM(START:END!F57) -> #N/A | I57: =+SUM(START:END!I57) -> 0 | L57: =+SUM(START:END!L57) -> 17114.37 | N57: =L57-F57 -> #N/A | Q57: =+SUM(START:END!Q57) -> 34800.99 | S57: =L57-Q57 -> -17686.62
A58: =+B58&C58 -> Véhicules neufsInformatique | B58: =+$K$1 -> Véhicules neufs | C58: Informatique | F58: =+SUM(START:END!F58) -> #N/A | I58: =+SUM(START:END!I58) -> 0 | L58: =+SUM(START:END!L58) -> 12523.39 | N58: =L58-F58 -> #N/A | Q58: =+SUM(START:END!Q58) -> 12921.57 | S58: =L58-Q58 -> -398.18
A59: =+B59&C59 -> Véhicules neufsFrais de déplacement | B59: =+$K$1 -> Véhicules neufs | C59: Frais de déplacement | F59: =+SUM(START:END!F59) -> #N/A | I59: =+SUM(START:END!I59) -> 0 | L59: =+SUM(START:END!L59) -> 1557 | N59: =L59-F59 -> #N/A | Q59: =+SUM(START:END!Q59) -> 16462.69 | S59: =L59-Q59 -> -14905.69
A60: =+B60&C60 -> Véhicules neufsServices extérieurs | B60: =+$K$1 -> Véhicules neufs | C60: Services extérieurs | F60: =+SUM(START:END!F60) -> #N/A | I60: =+SUM(START:END!I60) -> 0 | L60: =+SUM(START:END!L60) -> 13369.61 | N60: =L60-F60 -> #N/A | Q60: =+SUM(START:END!Q60) -> 24120.4 | S60: =L60-Q60 -> -10750.79
A61: =+B61&C61 -> Véhicules neufsFournitures autres | B61: =+$K$1 -> Véhicules neufs | C61: Fournitures autres | F61: =+SUM(START:END!F61) -> #N/A | I61: =+SUM(START:END!I61) -> 0 | L61: =+SUM(START:END!L61) -> 805.38 | N61: =L61-F61 -> #N/A | Q61: =+SUM(START:END!Q61) -> 2175.19 | S61: =L61-Q61 -> -1369.81
A62: =+B62&C62 -> Véhicules neufsUniformes | B62: =+$K$1 -> Véhicules neufs | C62: Uniformes | F62: =+SUM(START:END!F62) -> #N/A | I62: =+SUM(START:END!I62) -> 0 | L62: =+SUM(START:END!L62) -> 0 | N62: =L62-F62 -> #N/A | Q62: =+SUM(START:END!Q62) -> 0 | S62: =L62-Q62 -> 0
A63: =+B63&C63 -> Véhicules neufsPapeterie | B63: =+$K$1 -> Véhicules neufs | C63: Papeterie | F63: =+SUM(START:END!F63) -> #N/A | I63: =+SUM(START:END!I63) -> 0 | L63: =+SUM(START:END!L63) -> 3445.65 | N63: =L63-F63 -> #N/A | Q63: =+SUM(START:END!Q63) -> 5070.45 | S63: =L63-Q63 -> -1624.8
A64: =+B64&C64 -> Véhicules neufsTéléphone | B64: =+$K$1 -> Véhicules neufs | C64: Téléphone | F64: =+SUM(START:END!F64) -> #N/A | I64: =+SUM(START:END!I64) -> 0 | L64: =+SUM(START:END!L64) -> 1935.79 | N64: =L64-F64 -> #N/A | Q64: =+SUM(START:END!Q64) -> 2156.52 | S64: =L64-Q64 -> -220.73
A65: =+B65&C65 -> Véhicules neufsFrais postaux | B65: =+$K$1 -> Véhicules neufs | C65: Frais postaux | F65: =+SUM(START:END!F65) -> #N/A | I65: =+SUM(START:END!I65) -> 0 | L65: =+SUM(START:END!L65) -> 2945.91 | N65: =L65-F65 -> #N/A | Q65: =+SUM(START:END!Q65) -> 3135.84 | S65: =L65-Q65 -> -189.93
A66: =+B66&C66 -> Véhicules neufsDivers | B66: =+$K$1 -> Véhicules neufs | C66: Divers | F66: =+SUM(START:END!F66) -> #N/A | I66: =+SUM(START:END!I66) -> 0 | L66: =+SUM(START:END!L66) -> 9764.15 | N66: =L66-F66 -> #N/A | Q66: =+SUM(START:END!Q66) -> 10354.27 | S66: =L66-Q66 -> -590.12
... A71: =+B71&C71 -> Véhicules neufs[...] | B71: =+$K$1 -> Véhicules neufs | C71: [...] | F71: =+SUM(START:END!F71) -> #N/A | I71: =+SUM(START:END!I71) -> 0 | L71: =+SUM(START:END!L71) -> 0 | N71: =L71-F71 -> #N/A | Q71: =+SUM(START:END!Q71) -> 0 | S71: =L71-Q71 -> 0
A72: =+B72&C72 -> Véhicules neufsTOTAL SEMI-FIXES | B72: =+$K$1 -> Véhicules neufs | C72: TOTAL SEMI-FIXES | D72: % brut | E72: =F72/F$27 -> #N/A | F72: =+SUM(F55:F71) -> #N/A | G72: % brut | H72: =I72/I$27 -> #DIV/0! | I72: =+SUM(I55:I71) -> 0 | J72: % brut | K72: =L72/L$27 -> 0.12623326 | L72: =+SUM(L55:L71) -> 70420.85 | N72: =+SUM(N55:N71) -> #N/A | O72: % brut | P72: =Q72/Q$27 -> 0.1318694 | Q72: =+SUM(Q55:Q71) -> 114519.41 | S72: =+SUM(S55:S71) -> -44098.56
A73: =+B73&C73 -> Véhicules neufs | B73: =+$K$1 -> Véhicules neufs
A74: =+B74&C74 -> Véhicules neufsTOTAL DES DÉPENSES | B74: =+$K$1 -> Véhicules neufs | C74: TOTAL DES DÉPENSES | D74: % brut | E74: =F74/F$27 -> #N/A | F74: =F41+F54+F72 -> #N/A | G74: % brut | H74: =I74/I$27 -> #DIV/0! | I74: =I41+I54+I72 -> 0 | J74: % brut | K74: =L74/L$27 -> 0.37813576 | L74: =L41+L54+L72 -> 210947.91 | N74: =L74-F74 -> #N/A | O74: % brut | P74: =Q74/Q$27 -> 0.23711348 | Q74: =Q41+Q54+Q72 -> 205916.58 | S74: =L74-Q74 -> 5031.33
A75: =+B75&C75 -> Véhicules neufsRBSC neuf | B75: =+$K$1 -> Véhicules neufs | C75: RBSC neuf | F75: =+SUM(START:END!F75) -> #N/A | I75: =+SUM(START:END!I75) -> 0 | L75: =+SUM(START:END!L75) -> 89171.54 | N75: =L75-F75 -> #N/A | Q75: =+SUM(START:END!Q75) -> 77373.09 | S75: =L75-Q75 -> 11798.45
A76: =+B76&C76 -> Véhicules neufsProgramme neuf 2 | B76: =+$K$1 -> Véhicules neufs | C76: Programme neuf 2 | F76: =+SUM(START:END!F76) -> #N/A | I76: =+SUM(START:END!I76) -> 0 | L76: =+SUM(START:END!L76) -> 0 | N76: =L76-F76 -> #N/A | Q76: =+SUM(START:END!Q76) -> 0 | S76: =L76-Q76 -> 0
A77: =+B77&C77 -> Véhicules neufsProgramme neuf 3 | B77: =+$K$1 -> Véhicules neufs | C77: Programme neuf 3 | F77: =+SUM(START:END!F77) -> #N/A | I77: =+SUM(START:END!I77) -> 0 | L77: =+SUM(START:END!L77) -> 0 | N77: =L77-F77 -> #N/A | Q77: =+SUM(START:END!Q77) -> 0 | S77: =L77-Q77 -> 0
A78: =+B78&C78 -> Véhicules neufsHoldbacks | B78: =+$K$1 -> Véhicules neufs | C78: Holdbacks | F78: =+SUM(START:END!F78) -> #N/A | I78: =+SUM(START:END!I78) -> 0 | L78: =+SUM(START:END!L78) -> 0 | N78: =L78-F78 -> #N/A | Q78: =+SUM(START:END!Q78) -> 0 | S78: =L78-Q78 -> 0
A79: =+B79&C79 -> Véhicules neufs[...] | B79: =+$K$1 -> Véhicules neufs | C79: [...] | F79: =+SUM(START:END!F79) -> #N/A | I79: =+SUM(START:END!I79) -> 0 | L79: =+SUM(START:END!L79) -> 0 | N79: =L79-F79 -> #N/A | Q79: =+SUM(START:END!Q79) -> 0 | S79: =L79-Q79 -> 0
A80: =+B80&C80 -> Véhicules neufs[...] | B80: =+$K$1 -> Véhicules neufs | C80: [...] | F80: =+SUM(START:END!F80) -> #N/A | I80: =+SUM(START:END!I80) -> 0 | L80: =+SUM(START:END!L80) -> 0 | N80: =L80-F80 -> #N/A | Q80: =+SUM(START:END!Q80) -> 0 | S80: =L80-Q80 -> 0
A81: =+B81&C81 -> Véhicules neufs[...] | B81: =+$K$1 -> Véhicules neufs | C81: [...] | F81: =+SUM(START:END!F81) -> #N/A | I81: =+SUM(START:END!I81) -> 0 | L81: =+SUM(START:END!L81) -> 0 | N81: =L81-F81 -> #N/A | Q81: =+SUM(START:END!Q81) -> 0 | S81: =L81-Q81 -> 0
A82: =+B82&C82 -> Véhicules neufsFrais administration | B82: =+$K$1 -> Véhicules neufs | C82: Frais administration | F82: =+SUM(START:END!F82) -> #N/A | I82: =+SUM(START:END!I82) -> 0 | L82: =+SUM(START:END!L82) -> 96182 | N82: =L82-F82 -> #N/A | Q82: =+SUM(START:END!Q82) -> 0 | S82: =L82-Q82 -> 96182
A83: =+B83&C83 -> Véhicules neufsAUTRES REVENUS | B83: =+$K$1 -> Véhicules neufs | C83: AUTRES REVENUS | F83: =+SUM(F75:F82) -> #N/A | I83: =+SUM(I75:I82) -> 0 | L83: =+SUM(L75:L82) -> 185353.54 | N83: =+SUM(N75:N82) -> #N/A | Q83: =+SUM(Q75:Q82) -> 77373.09 | S83: =+SUM(S75:S82) -> 107980.45
A84: =+B84&C84 -> Véhicules neufs | B84: =+$K$1 -> Véhicules neufs
A85: =+B85&C85 -> Véhicules neufsPROFIT DÉPARTEMENTAL | B85: =+$K$1 -> Véhicules neufs | C85: PROFIT DÉPARTEMENTAL | F85: =F27-F74+F83 -> #N/A | I85: =I27-I74+I83 -> 0 | L85: =L27-L74+L83 -> 532268.52 | N85: =N27-N41-N54-N72+N83 -> #N/A | Q85: =Q27-Q74+Q83 -> 739887.02 | S85: =S27-S41-S54-S72+S83 -> -207618.5
C89: =C1 -> Ste-Marie Auto | K89: Véhicules usagés | S89: =$S$1 -> Réalisé Q3 2026
D91: BUDGET ORIGINAL | G91: BUDGET RÉVISÉ | J91: RÉALISATION | M91: ÉCART réel / Budget | O91: ANNÉE PRÉCÉDENTE | R91: ECART (réel/ Ann.Préc.)
D92: UNITE | E92: $P/UNITÉ | F92: $PROFITS | G92: UNITE | H92: $P/UNITÉ | I92: $PROFITS | J92: UNITE | K92: $P/UNITE | L92: $PROFITS | M92: UNFTÉ | N92: $PROFFTS | O92: UNITE | P92: $P/UNITE | Q92: $PROFITS | R92: UNITE | S92: $PROFITS
A93: =+B93&C93 -> Véhicules usagésVentes nettes | B93: Véhicules usagés | C93: Ventes nettes | F93: =+SUM(START:END!F93) -> #N/A | I93: =+SUM(START:END!I93) -> 0 | L93: =+SUM(START:END!L93) -> 4914042.4 | Q93: =+SUM(START:END!Q93) -> 8423659
A94: =+B94&C94 -> Véhicules usagésCertifié | B94: Véhicules usagés | C94: Certifié | D94: =+SUM(START:END!D94) -> #N/A | E94: =IF(D94=0,0,F94/D94) -> #N/A | F94: =+SUM(START:END!F94) -> #N/A | G94: =+SUM(START:END!G94) -> 0 | H94: =IF(G94=0,0,I94/G94) -> 0 | I94: =+SUM(START:END!I94) -> 0 | J94: =+SUM(START:END!J94) -> 0 | K94: =IF(J94=0,0,L94/J94) -> 0 | L94: =+SUM(START:END!L94) -> 0 | M94: =J94-D94 -> #N/A | N94: =L94-F94 -> #N/A | O94: =+SUM(START:END!O94) -> 0 | P94: =IF(O94=0,0,Q94/O94) -> 0 | Q94: =+SUM(START:END!Q94) -> 0 | R94: =J94-O94 -> 0 | S94: =L94-Q94 -> 0
A95: =+B95&C95 -> Véhicules usagésNon Certifié | B95: Véhicules usagés | C95: Non Certifié | D95: =+SUM(START:END!D95) -> #N/A | E95: =IF(D95=0,0,F95/D95) -> #N/A | F95: =+SUM(START:END!F95) -> #N/A | G95: =+SUM(START:END!G95) -> 0 | H95: =IF(G95=0,0,I95/G95) -> 0 | I95: =+SUM(START:END!I95) -> 0 | J95: =+SUM(START:END!J95) -> 69 | K95: =IF(J95=0,0,L95/J95) -> 936.93043 | L95: =+SUM(START:END!L95) -> 64648.2 | M95: =J95-D95 -> #N/A | N95: =L95-F95 -> #N/A | O95: =+SUM(START:END!O95) -> 42 | P95: =IF(O95=0,0,Q95/O95) -> 842.59714 | Q95: =+SUM(START:END!Q95) -> 35389.08 | R95: =J95-O95 -> 27 | S95: =L95-Q95 -> 29259.12
A96: =+B96&C96 -> Véhicules usagésAutres marques | B96: Véhicules usagés | C96: Autres marques | D96: =+SUM(START:END!D96) -> #N/A | E96: =IF(D96=0,0,F96/D96) -> #N/A | F96: =+SUM(START:END!F96) -> #N/A | G96: =+SUM(START:END!G96) -> 0 | H96: =IF(G96=0,0,I96/G96) -> 0 | I96: =+SUM(START:END!I96) -> 0 | J96: =+SUM(START:END!J96) -> 0 | K96: =IF(J96=0,0,L96/J96) -> 0 | L96: =+SUM(START:END!L96) -> 0 | M96: =J96-D96 -> #N/A | N96: =L96-F96 -> #N/A | O96: =+SUM(START:END!O96) -> 0 | P96: =IF(O96=0,0,Q96/O96) -> 0 | Q96: =+SUM(START:END!Q96) -> 0 | R96: =J96-O96 -> 0 | S96: =L96-Q96 -> 0
A97: =+B97&C97 -> Véhicules usagésTotal Usagés | B97: Véhicules usagés | C97: Total Usagés | D97: =+D95+D94+D96 -> #N/A | E97: =IF(D97=0,0,F97/D97) -> #N/A | F97: =+F94+F95+F96 -> #N/A | G97: =+G95+G94+G96 -> 0 | H97: =IF(G97=0,0,I97/G97) -> 0 | I97: =+I94+I95+I96 -> 0 | J97: =+J95+J94+J96 -> 69 | K97: =IF(J97=0,0,L97/J97) -> 936.93043 | L97: =+L94+L95+L96 -> 64648.2 | M97: =J97-D97 -> #N/A | N97: =L97-F97 -> #N/A | O97: =+O95+O94+O96 -> 42 | P97: =IF(O97<=0,0,Q97/O97) -> 842.59714 | Q97: =+Q94+Q95+Q96 -> 35389.08 | R97: =J97-O97 -> 27 | S97: =L97-Q97 -> 29259.12
A98: =+B98&C98 -> Véhicules usagés | B98: Véhicules usagés | H98: =IF(G98=0,0,I98/G98) -> 0 | M98: =M97/D97 -> #N/A | N98: =N97/F97 -> #N/A | R98: =R97/O97 -> 0.64285714 | S98: =IF(Q97=0,0,(S97/Q97)) -> 0.82678386
A99: =+B99&C99 -> Véhicules neufsRachat bail | B99: =+$K$1 -> Véhicules neufs | C99: Rachat bail | F99: =+SUM(START:END!F99) -> 0 | I99: =+SUM(START:END!I99) -> 0 | L99: =+SUM(START:END!L99) -> 0 | N99: =L99-F99 -> 0 | Q99: =+SUM(START:END!Q99) -> 0 | R99: =O99-K99 -> 0 | S99: =L99-Q99 -> 0
A100: =+B100&C100 -> Véhicules usagés | B100: Véhicules usagés
A101: =+B101&C101 -> Véhicules usagésVentes au Gros | B101: Véhicules usagés | C101: Ventes au Gros | D101: =+SUM(START:END!D101) -> #N/A | E101: =IF(D101=0,0,F101/D101) -> #N/A | F101: =+SUM(START:END!F101) -> #N/A | G101: =+SUM(START:END!G101) -> 0 | H101: =IF(G101=0,0,I101/G101) -> 0 | I101: =+SUM(START:END!I101) -> 0 | J101: =+SUM(START:END!J101) -> 79 | K101: =IF(J101=0,0,L101/J101) -> -7.3640506 | L101: =+SUM(START:END!L101) -> -581.76 | M101: =J101-D101 -> #N/A | N101: =L101-F101 -> #N/A | O101: =+SUM(START:END!O101) -> 194 | P101: =IF(O101=0,0,Q101/O101) -> 751.20443 | Q101: =+SUM(START:END!Q101) -> 145733.66 | R101: =J101-O101 -> -115 | S101: =L101-Q101 -> -146315.42
A102: =+B102&C102 -> Véhicules usagés | B102: Véhicules usagés
A103: =+B103&C103 -> Véhicules usagésRev. Finances | B103: Véhicules usagés | C103: Rev. Finances | D103: =+SUM(START:END!D103) -> #N/A | E103: =IF(D103=0,0,F103/D103) -> #N/A | F103: =+SUM(START:END!F103) -> #N/A | G103: =+SUM(START:END!G103) -> 0 | H103: =IF(G103=0,0,I103/G103) -> 0 | I103: =+SUM(START:END!I103) -> 0 | J103: =+SUM(START:END!J103) -> 0 | K103: =IF(J97=0,0,L103/J97) -> 536.3513 | L103: =+SUM(START:END!L103) -> 37008.24 | N103: =L103-F103 -> #N/A | O103: =+SUM(START:END!O103) -> 0 | P103: =IF(O97=0,0,Q103/O97) -> 424.90143 | Q103: =+SUM(START:END!Q103) -> 17845.86 | R103: =O103-K103 -> -536.3513 | S103: =L103-Q103 -> 19162.38
A104: =+B104&C104 -> Véhicules usagésRev. Protections | B104: Véhicules usagés | C104: Rev. Protections | D104: =+SUM(START:END!D104) -> #N/A | E104: =IF(D104=0,0,F104/D104) -> #N/A | F104: =+SUM(START:END!F104) -> #N/A | G104: =+SUM(START:END!G104) -> 0 | H104: =IF(G104=0,0,I104/G104) -> 0 | I104: =+SUM(START:END!I104) -> 0 | J104: =+SUM(START:END!J104) -> 0 | K104: =IF(J97=0,0,L104/J97) -> 238.97928 | L104: =+SUM(START:END!L104) -> 16489.57 | N104: =L104-F104 -> #N/A | O104: =+SUM(START:END!O104) -> 0 | P104: =IF(O97=0,0,Q104/O97) -> 434.4931 | Q104: =+SUM(START:END!Q104) -> 18248.71 | R104: =O104-K104 -> -238.97928 | S104: =L104-Q104 -> -1759.14
A105: =+B105&C105 -> Véhicules usagésRev. Autres | B105: Véhicules usagés | C105: Rev. Autres | D105: =+SUM(START:END!D105) -> #N/A | E105: =IF(D105=0,0,F105/D105) -> #N/A | F105: =+SUM(START:END!F105) -> #N/A | G105: =+SUM(START:END!G105) -> 0 | H105: =IF(G105=0,0,I105/G105) -> 0 | I105: =+SUM(START:END!I105) -> 0 | J105: =+SUM(START:END!J105) -> 0 | K105: =IF(J97=0,0,L105/J97) -> 0 | L105: =+SUM(START:END!L105) -> 0 | N105: =L105-F105 -> #N/A | O105: =+SUM(START:END!O105) -> 0 | P105: =IF(O97=0,0,Q105/O97) -> 0 | Q105: =+SUM(START:END!Q105) -> 0 | R105: =O105-K105 -> 0 | S105: =L105-Q105 -> 0
A106: =+B106&C106 -> Véhicules usagésTotal F&I | B106: Véhicules usagés | C106: Total F&I | D106: =D98 -> 0 | E106: =IF(D106=0,0,F106/D106) -> 0 | F106: =F103+F104+F105 -> #N/A | G106: =G98 -> 0 | H106: =IF(G106=0,0,I106/G106) -> 0 | I106: =I103+I104+I105 -> 0 | J106: =J97 -> 69 | K106: =IF(J106<=0,0,L106/J106) -> 775.33058 | L106: =L103+L104+L105 -> 53497.81 | M106: =J106-D106 -> 69 | N106: =L106-F106 -> #N/A | O106: =O97 -> 42 | P106: =IF(O106<=0,0,Q106/O106) -> 859.39452 | Q106: =Q103+Q104+Q105 -> 36094.57 | R106: =SUM(R103:R105) -> -775.33058 | S106: =L106-Q106 -> 17403.24
A107: =+B107&C107 -> Véhicules usagés | B107: Véhicules usagés | N107: =N106/F106 -> #N/A | S107: =IF(Q106=0,0,(S106/Q106)) -> 0.48215673
A108: =+B108&C108 -> Véhicules usagés | B108: Véhicules usagés
...

Sheet START

Sheet Mois 1
C1: Ste-Marie Auto | K1: Véhicules neufs | S1: Réalisé, Juillet 2026
D2: X | E2: O | F2: U | J2: NB | L2: $ | O2: NB | Q2: $ | V2: *** NE PAS EFFACER / Pour An Précédente ***
D3: BUDGET ORIGINAL | J3: RÉALISATION | M3: ÉCART réel / Budget | O3: ANNÉE PRÉCÉDENTE | R3: ECART (réel/ Ann.Préc.) | V3: NEUF | W3: 0.45
D4: UNITE | E4: $P/UNITÉ | F4: $PROFITS | J4: UNITÉS | K4: $P/UNITE | L4: $PROFITS | M4: UNITÉS | N4: $PROFITS | O4: UNITÉS | P4: $P/UNITE | Q4: $PROFITS | R4: UNITÉS | S4: $PROFITS | V4: USAGE | W4: 0.1
A5: Véhicules neufsVentes nettes | B5: Véhicules neufs | C5: Ventes nettes | F5: 0 | L5: 7544009.9 | Q5: 11373985 | V5: SERVICE | W5: 0.225
A6: Véhicules neufsAutos détail | B6: Véhicules neufs | C6: Autos détail | D6: 0 | E6: =IF(D6=0,0,F6/D6) -> 0 | F6: 0 | J6: 1 | K6: =IF(J6=0,0,L6/J6) -> 1519 | L6: 1519 | M6: =J6-D6 -> 1 | N6: =L6-F6 -> 1519 | O6: 0 | P6: =IF(O6=0,0,Q6/O6) -> 0 | Q6: 0 | R6: =J6-O6 -> 1 | S6: =L6-Q6 -> 1519 | V6: CARROSSERIE | W6: 0.025
A7: Véhicules neufsCamions détail | B7: Véhicules neufs | C7: Camions détail | D7: 0 | E7: =IF(D7=0,0,F7/D7) -> 0 | F7: 0 | J7: 32 | K7: =IF(J7=0,0,L7/J7) -> 2924.1747 | L7: 93573.59 | M7: =J7-D7 -> 32 | N7: =L7-F7 -> 93573.59 | O7: 59 | P7: =IF(O7=0,0,Q7/O7) -> 3159.409 | Q7: 186405.13 | R7: =J7-O7 -> -27 | S7: =L7-Q7 -> -92831.54 | V7: PIECES | W7: 0.2
A8: Véhicules neufsSprinter | B8: Véhicules neufs | C8: Voitures electriques | D8: 0 | E8: =IF(D8=0,0,F8/D8) -> 0 | F8: 0 | J8: 0 | K8: =IF(J8=0,0,L8/J8) -> 0 | L8: 0 | M8: =J8-D8 -> 0 | N8: =L8-F8 -> 0 | O8: 0 | P8: =IF(O8=0,0,Q8/O8) -> 0 | Q8: 0 | R8: =J8-O8 -> 0 | S8: =L8-Q8 -> 0 | W8: =SUM(W3:W7) -> 1
A9: Véhicules neufsMoto détail | B9: Véhicules neufs | C9: Camions electriques | D9: 0 | E9: =IF(D9=0,0,F9/D9) -> 0 | F9: 0 | J9: 21 | K9: =IF(J9=0,0,L9/J9) -> 1565.2624 | L9: 32870.51 | M9: =J9-D9 -> 21 | N9: =L9-F9 -> 32870.51 | O9: 18 | P9: =IF(O9=0,0,Q9/O9) -> 815.97444 | Q9: 14687.54 | R9: =J9-O9 -> 3 | S9: =L9-Q9 -> 18182.97 | U9: Livre des ventes
A10: Véhicules neufs[...] | B10: Véhicules neufs | C10: [...] | D10: 0 | E10: =IF(D10=0,0,F10/D10) -> 0 | F10: 0 | J10: 0 | K10: =IF(J10=0,0,L10/J10) -> 0 | L10: 0 | M10: =J10-D10 -> 0 | N10: =L10-F10 -> 0 | O10: 0 | P10: =IF(O10=0,0,Q10/O10) -> 0 | Q10: 0 | R10: =J10-O10 -> 0 | S10: =L10-Q10 -> 0
A11: Véhicules neufs[...] | B11: Véhicules neufs | C11: [...] | D11: 0 | E11: =IF(D11=0,0,F11/D11) -> 0 | F11: 0 | J11: 0 | K11: =IF(J11=0,0,L11/J11) -> 0 | L11: 0 | M11: =J11-D11 -> 0 | N11: =L11-F11 -> 0 | O11: 0 | P11: =IF(O11=0,0,Q11/O11) -> 0 | Q11: 0 | R11: =J11-O11 -> 0 | S11: =L11-Q11 -> 0
A12: Véhicules neufs[...] | B12: Véhicules neufs | C12: [...] | D12: 0 | E12: =IF(D12=0,0,F12/D12) -> 0 | F12: 0 | J12: 0 | K12: =IF(J12=0,0,L12/J12) -> 0 | L12: 0 | M12: =J12-D12 -> 0 | N12: =L12-F12 -> 0 | O12: 0 | P12: =IF(O12=0,0,Q12/O12) -> 0 | Q12: 0 | R12: =J12-O12 -> 0 | S12: =L12-Q12 -> 0
A13: Véhicules neufsTotal Neufs | B13: Véhicules neufs | C13: Total Neufs | D13: =+SUM(D6:D12) -> 0 | E13: =IF(D13<=0,0,F13/D13) -> 0 | F13: =+SUM(F6:F12) -> 0 | J13: =+SUM(J6:J12) -> 54 | K13: =IF(J13<=0,0,L13/J13) -> 2369.687 | L13: =+SUM(L6:L12) -> 127963.1 | M13: =+SUM(M6:M12) -> 54 | N13: =+SUM(N6:N12) -> 127963.1 | O13: =+SUM(O6:O12) -> 77 | P13: =IF(O13<=0,0,Q13/O13) -> 2611.5931 | Q13: =+SUM(Q6:Q12) -> 201092.67 | R13: =+SUM(R6:R12) -> -23 | S13: =+SUM(S6:S12) -> -73129.57 | T13: 54 | U13: 127963 | V13: =L13-U13 -> 0.1
A14: Véhicules neufs | B14: Véhicules neufs | M14: =IF(D13=0,0,M13/D13) -> 0 | N14: =IF(F13=0,0,N13/F13) -> 0 | R14: =R13/O13 -> -0.2987013 | S14: =IF(Q13=0,0,(S13/Q13)) -> -0.36366104
A15: Véhicules neufsEx-Démos et courtoisies | B15: Véhicules neufs | C15: Ex-Démos et courtoisies | D15: 0 | E15: =IF(D15=0,0,F15/D15) -> 0 | F15: 0 | J15: 0 | K15: =IF(J15=0,0,L15/J15) -> 0 | L15: 0 | M15: =J15-D15 -> 0 | N15: =L15-F15 -> 0 | O15: 0 | P15: =IF(O15=0,0,Q15/O15) -> 0 | Q15: 0 | R15: =J15-O15 -> 0 | S15: =L15-Q15 -> 0
A16: Véhicules neufs | B16: Véhicules neufs
A17: Véhicules neufsFlottes | B17: Véhicules neufs | C17: Flottes | D17: 0 | E17: =IF(D17=0,0,F17/D17) -> 0 | F17: 0 | J17: 58 | K17: =IF(J17=0,0,L17/J17) -> 503.14414 | L17: 29182.36 | M17: =J17-D17 -> 58 | N17: =L17-F17 -> 29182.36 | O17: 93 | P17: =IF(O17=0,0,Q17/O17) -> 596.45914 | Q17: 55470.7 | R17: =J17-O17 -> -35 | S17: =L17-Q17 -> -26288.34 | T17: 58 | U17: 27397 | V17: =L17-U17 -> 1785.36
A18: Véhicules neufs | B18: Véhicules neufs
A19: Véhicules neufsRachat bail | B19: Véhicules neufs
A20: Véhicules neufs | B20: Véhicules neufs
A21: Véhicules neufsRev. Finances | B21: Véhicules neufs | C21: Rev. Finances | D21: 0 | E21: =IF(D21=0,0,F21/D21) -> 0 | F21: 0 | K21: =IF(J13=0,0,L21/(J13+J15)) -> 18.518519 | L21: 1000 | N21: =L21-F21 -> 1000 | P21: =IF(O13=0,0,Q21/(O13+O15)) -> 21.425455 | Q21: 1649.76 | R21: =P21-K21 -> 2.906936 | S21: =L21-Q21 -> -649.76
A22: Véhicules neufsRev. Protections | B22: Véhicules neufs | C22: Rev. Protections | D22: 0 | E22: =IF(D22=0,0,F22/D22) -> 0 | F22: 0 | K22: =IF(J13=0,0,L22/(J13+J15)) -> 576.52907 | L22: 31132.57 | N22: =L22-F22 -> 31132.57 | P22: =IF(O13=0,0,Q22/(O13+O15)) -> 572.09403 | Q22: 44051.24 | R22: =P22-K22 -> -4.4350481 | S22: =L22-Q22 -> -12918.67
A23: Véhicules neufsRev. Autres | B23: Véhicules neufs | C23: Rev. Autres | D23: 0 | E23: =IF(D23=0,0,F23/D23) -> 0 | F23: 0 | K23: =IF(J13=0,0,L23/(J13+J15)) -> 113.675 | L23: 6138.45 | N23: =L23-F23 -> 6138.45 | P23: =IF(O13=0,0,Q23/(O13+O15)) -> 106.58442 | Q23: 8207 | R23: =P23-K23 -> -7.0905844 | S23: =L23-Q23 -> -2068.55
A24: Véhicules neufsTotal F&I | B24: Véhicules neufs | C24: Total F&I | D24: =+D15+D13 -> 0 | E24: =IF(D24<=0,0,F24/D24) -> 0 | F24: =F21+F22+F23 -> 0 | J24: =+J15+J13 -> 54 | K24: =IF(J24<=0,0,L24/J24) -> 708.72259 | L24: =L21+L22+L23 -> 38271.02 | M24: =J24-D24 -> 54 | N24: =L24-F24 -> 38271.02 | O24: =+O15+O13 -> 77 | P24: =IF(O24<=0,0,Q24/O24) -> 700.1039 | Q24: =Q21+Q22+Q23 -> 53908 | R24: =P24-K24 -> -8.6186965 | S24: =L24-Q24 -> -15636.98 | U24: 38271 | V24: =L24-U24 -> 0.02
A25: Véhicules neufs | B25: Véhicules neufs | N25: =IF(N24=0,0,N24/F24) -> #DIV/0! | S25: =IF(Q24=0,0,(S24/Q24)) -> -0.29006789
A26: Véhicules neufs | B26: Véhicules neufs
A27: Véhicules neufsTotal Dépt. Neufs | B27: Véhicules neufs | C27: Total Dépt. Neufs | D27: =+D13+D15+D17 -> 0 | E27: =IF(D27<=0,0,F27/D27) -> 0 | F27: =F13+F17+F24+F19+F15 -> 0 | J27: =+J13+J15+J17 -> 112 | K27: =IF(J27<=0,0,L27/J27) -> 1744.79 | L27: =L13+L17+L24+L19+L15 -> 195416.48 | M27: =J27-D27 -> 112 | N27: =L27-F27 -> 195416.48 | O27: =+O13+O15+O17 -> 170 | P27: =IF(O27<=0,0,Q27/O27) -> 1826.3022 | Q27: =Q13+Q17+Q24+Q19+Q15 -> 310471.37 | R27: =J27-O27 -> -58 | S27: =L27-Q27 -> -115054.89 | U27: =SUM(U13:U26) -> 193631 | V27: =L27-U27 -> 1785.48
A28: Véhicules neufs | B28: Véhicules neufs | R28: =R27/O27 -> -0.34117647 | S28: =IF(Q27=0,0,S27/Q27) -> -0.37058132
A29: Véhicules neufs | B29: Véhicules neufs
A30: Véhicules neufsDEPENSES | B30: Véhicules neufs | C30: DEPENSES
A31: Véhicules neufsComm. vendeurs | B31: Véhicules neufs | C31: Comm. vendeurs | D31: =F31/(F13+F15) -> #DIV/0! | E31: =F31/D$24 -> #DIV/0! | F31: 0 | J31: =L31/(L15+L13+L17) -> 0.27118334 | K31: =IF(L31=0,0,L31/J$24) -> 789.17093 | L31: 42615.23 | N31: =L31-F31 -> 42615.23 | O31: =Q31/(Q15+Q13+Q17) -> 0.22474853 | P31: =IF(Q31=0,0,Q31/O$24) -> 748.86026 | Q31: 57662.24 | S31: =L31-Q31 -> -15047.01
A32: Véhicules neufsComm. F&I | B32: Véhicules neufs | C32: Comm. F&I | D32: =F32/F24 -> #DIV/0! | E32: =F32/D$24 -> #DIV/0! | F32: 0 | J32: =L32/L24 -> 0.32469947 | K32: =IF(L32=0,0,L32/J$24) -> 230.12185 | L32: 12426.58 | N32: =L32-F32 -> 12426.58 | O32: =Q32/Q24 -> 0.22351729 | P32: =IF(Q32=0,0,Q32/O$24) -> 156.48532 | Q32: 12049.37 | S32: =L32-Q32 -> 377.21
A33: Véhicules neufsFrais de livraison | B33: Véhicules neufs | C33: Frais de livraison | E33: =F33/D$24 -> #DIV/0! | F33: 0 | K33: =IF(L33=0,0,L33/J$24) -> 1001.7337 | L33: 54093.62 | N33: =L33-F33 -> 54093.62 | P33: =IF(Q33=0,0,Q33/O$24) -> -204.81558 | Q33: -15770.8 | S33: =L33-Q33 -> 69864.42 | U33: Frais document reclassé
A34: Véhicules neufsService gratuit 1 | B34: Véhicules neufs | C34: Service gratuit 1 | E34: =F34/D$24 -> #DIV/0! | F34: 0 | K34: =IF(L34=0,0,L34/J$24) -> 18.55963 | L34: 1002.22 | N34: =L34-F34 -> 1002.22 | P34: =IF(Q34=0,0,Q34/O$24) -> 8.701039 | Q34: 669.98 | S34: =L34-Q34 -> 332.24
A35: Véhicules neufsEntretien stock | B35: Véhicules neufs | C35: Entretien stock | E35: =F35/D$24 -> #DIV/0! | F35: 0 | K35: =IF(L35=0,0,L35/J$24) -> 92.806111 | L35: 5011.53 | N35: =L35-F35 -> 5011.53 | P35: =IF(Q35=0,0,Q35/O$24) -> 0 | Q35: 0 | S35: =L35-Q35 -> 5011.53
A36: Véhicules neufsPublicité 1 | B36: Véhicules neufs | C36: Publicité 1 | E36: =F36/D$24 -> #DIV/0! | F36: 0 | K36: =IF(L36=0,0,L36/J$24) -> 277.72907 | L36: 14997.37 | N36: =L36-F36 -> 14997.37 | P36: =IF(Q36=0,0,Q36/O$24) -> 241.33805 | Q36: 18583.03 | S36: =L36-Q36 -> -3585.66
A37: Véhicules neufsIntérêt de gros | B37: Véhicules neufs | C37: Intérêt de gros | E37: =F37/D$24 -> #DIV/0! | F37: 0 | K37: =IF(L37=0,0,L37/J$24) -> 1041.1037 | L37: 56219.6 | N37: =L37-F37 -> 56219.6 | P37: =IF(Q37=0,0,Q37/O$24) -> 824.55675 | Q37: 63490.87 | S37: =L37-Q37 -> -7271.27
A38: Véhicules neufs[...] | B38: Véhicules neufs | C38: Crédit Intérêts Floor Plan | E38: =F38/D$24 -> #DIV/0! | F38: 0 | K38: =IF(L38=0,0,L38/J$24) -> -2437.6989 | L38: -131635.74 | N38: =L38-F38 -> -131635.74 | P38: =IF(Q38=0,0,Q38/O$24) -> -1524.5636 | Q38: -117391.4 | S38: =L38-Q38 -> -14244.34
A39: Véhicules neufs[...] | B39: Véhicules neufs | C39: Crédit Boni TD | E39: =F39/D$24 -> #DIV/0! | F39: 0 | K39: =IF(L39=0,0,L39/J$24) -> -208.49852 | L39: -11258.92 | N39: =L39-F39 -> -11258.92 | P39: =IF(Q39=0,0,Q39/O$24) -> 0 | Q39: 0 | S39: =L39-Q39 -> -11258.92 | T39: -11259 | U39: =L39+L121+L194 -> -16826.18 | V39: Crédit de juin - décalé d'un mois ??
A40: Véhicules neufs[...] | B40: Véhicules neufs | C40: [...] | E40: =F40/D$24 -> #DIV/0! | F40: 0 | K40: =IF(L40=0,0,L40/J$24) -> 0 | L40: 0 | N40: =L40-F40 -> 0 | P40: =IF(Q40=0,0,Q40/O$24) -> 0 | Q40: 0 | S40: =L40-Q40 -> 0
A41: Véhicules neufsTOTAL VARIABLES | B41: Véhicules neufs | C41: TOTAL VARIABLES | D41: % brut | E41: =F41/F$27 -> #DIV/0! | F41: =SUM(F31:F40) -> 0 | J41: % brut | K41: =L41/L$27 -> 0.2224556 | L41: =SUM(L31:L40) -> 43471.49 | N41: =L41-F41 -> 43471.49 | O41: % brut | P41: =Q41/Q$27 -> 0.06214193 | Q41: =SUM(Q31:Q40) -> 19293.29 | S41: =L41-Q41 -> 24178.2
A42: Véhicules neufsSalaires cadres | B42: Véhicules neufs | C42: Salaires cadres | F42: 0 | L42: 15176.4 | N42: =L42-F42 -> 15176.4 | Q42: 9257.46 | S42: =L42-Q42 -> 5918.94
A43: Véhicules neufsSalaires commis | B43: Véhicules neufs | C43: Salaires commis | F43: 0 | L43: 10229.27 | N43: =L43-F43 -> 10229.27 | Q43: 27701.05 | S43: =L43-Q43 -> -17471.78
A44: Véhicules neufsSalaires autres | B44: Véhicules neufs | C44: Salaires autres | F44: 0 | L44: 6239.08 | N44: =L44-F44 -> 6239.08 | Q44: 4057.03 | S44: =L44-Q44 -> 2182.05
A45: Véhicules neufsSalaires spécialistes | B45: Véhicules neufs | C45: Salaires spécialistes | F45: 0 | L45: 0 | N45: =L45-F45 -> 0 | Q45: 0 | S45: =L45-Q45 -> 0
A46: Véhicules neufs[...] | B46: Véhicules neufs | C46: [...] | F46: 0 | L46: 0 | N46: =L46-F46 -> 0 | Q46: 0 | S46: =L46-Q46 -> 0
A47: Véhicules neufs[...] | B47: Véhicules neufs | C47: [...] | F47: 0 | L47: 0 | N47: =L47-F47 -> 0 | Q47: 0 | S47: =L47-Q47 -> 0
A48: Véhicules neufs[...] | B48: Véhicules neufs | C48: [...] | F48: 0 | L48: 0 | N48: =L48-F48 -> 0 | Q48: 0 | S48: =L48-Q48 -> 0
A49: Véhicules neufsSalaires en absences | B49: Véhicules neufs | C49: Salaires en absences | F49: 0 | L49: 6409.74 | N49: =L49-F49 -> 6409.74 | Q49: 18093.27 | S49: =L49-Q49 -> -11683.53
A50: Véhicules neufsDéduction à la source | B50: Véhicules neufs | C50: Déduction à la source | F50: 0 | L50: 10332.88 | N50: =L50-F50 -> 10332.88 | Q50: 19782.37 | S50: =L50-Q50 -> -9449.49
A51: Véhicules neufsBénéfices marginaux | B51: Véhicules neufs | C51: Bénéfices marginaux | F51: 0 | L51: 1310.91 | N51: =L51-F51 -> 1310.91 | Q51: 3563.38 | S51: =L51-Q51 -> -2252.47
A52: Véhicules neufsCsst | B52: Véhicules neufs | C52: Csst | F52: 0 | L52: 2914.45 | N52: =L52-F52 -> 2914.45 | Q52: 11.85 | S52: =L52-Q52 -> 2902.6
A53: Véhicules neufs[...] | B53: Véhicules neufs | C53: [...] | D53: =VLOOKUP(C53,$B$2:$B$46,1,FALSE) -> #N/A | F53: 0 | L53: 0 | N53: =L53-F53 -> 0 | Q53: 0 | S53: =L53-Q53 -> 0
A54: Véhicules neufsTOTAL PERSONNEL | B54: Véhicules neufs | C54: TOTAL PERSONNEL | D54: % brut | E54: =F54/F$27 -> #DIV/0! | F54: =+SUM(F42:F53) -> 0 | J54: % brut | K54: =L54/L$27 -> 0.26923384 | L54: =+SUM(L42:L53) -> 52612.73 | N54: =+SUM(N42:N53) -> 52612.73 | O54: % brut | P54: =Q54/Q$27 -> 0.26561679 | Q54: =+SUM(Q42:Q53) -> 82466.41 | S54: =+SUM(S42:S53) -> -29853.68
A55: Véhicules neufsPublicité 2 | B55: Véhicules neufs | C55: Publicité 2 | F55: 0 | L55: 0 | N55: =L55-F55 -> 0 | Q55: 0 | S55: =L55-Q55 -> 0
A56: Véhicules neufsService gratuit 2 | B56: Véhicules neufs | C56: Service gratuit 2 | F56: 0 | L56: 0 | N56: =L56-F56 -> 0 | Q56: 0 | S56: =L56-Q56 -> 0
A57: Véhicules neufsFrais véhicules de cie | B57: Véhicules neufs | C57: Frais véhicules de cie | F57: 0 | L57: 4689.38 | N57: =L57-F57 -> 4689.38 | Q57: 17239.51 | S57: =L57-Q57 -> -12550.13
A58: Véhicules neufsInformatique | B58: Véhicules neufs | C58: Informatique | F58: 0 | L58: 4264.88 | N58: =L58-F58 -> 4264.88 | Q58: 4373.82 | S58: =L58-Q58 -> -108.94
A59: Véhicules neufsFrais de déplacement | B59: Véhicules neufs | C59: Frais de déplacement | F59: 0 | L59: 987.72 | N59: =L59-F59 -> 987.72 | Q59: 3505.14 | S59: =L59-Q59 -> -2517.42
A60: Véhicules neufsServices extérieurs | B60: Véhicules neufs | C60: Services extérieurs | F60: 0 | L60: 5144.11 | N60: =L60-F60 -> 5144.11 | Q60: 7978.87 | S60: =L60-Q60 -> -2834.76
A61: Véhicules neufsFournitures autres | B61: Véhicules neufs | C61: Fournitures autres | F61: 0 | L61: 408.45 | N61: =L61-F61 -> 408.45 | Q61: 937.11 | S61: =L61-Q61 -> -528.66
A62: Véhicules neufsUniformes | B62: Véhicules neufs | C62: Uniformes | F62: 0 | L62: 0 | N62: =L62-F62 -> 0 | Q62: 0 | S62: =L62-Q62 -> 0
A63: Véhicules neufsPapeterie | B63: Véhicules neufs | C63: Papeterie | F63: 0 | L63: 1184.39 | N63: =L63-F63 -> 1184.39 | Q63: 791.39 | S63: =L63-Q63 -> 393
A64: Véhicules neufsTéléphone | B64: Véhicules neufs | C64: Téléphone | F64: 0 | L64: 630.25 | N64: =L64-F64 -> 630.25 | Q64: 1028.77 | S64: =L64-Q64 -> -398.52
A65: Véhicules neufsFrais postaux | B65: Véhicules neufs | C65: Frais postaux | F65: 0 | L65: 1095.87 | N65: =L65-F65 -> 1095.87 | Q65: 1004.89 | S65: =L65-Q65 -> 90.98
A66: Véhicules neufsDivers | B66: Véhicules neufs | C66: Divers | F66: 0 | L66: 2613.35 | N66: =L66-F66 -> 2613.35 | Q66: 2193.68 | S66: =L66-Q66 -> 419.67
... A68: Véhicules neufsFrais bancaires | B68: Véhicules neufs | C68: Frais bancaires | F68: 0 | L68: 1435.55 | N68: =L68-F68 -> 1435.55 | Q68: 341.48 | S68: =L68-Q68 -> 1094.07
A69: Véhicules neufs[...] | B69: Véhicules neufs | C69: [...] | F69: 0 | N69: =L69-F69 -> 0 | S69: =L69-Q69 -> 0
A70: Véhicules neufs[...] | B70: Véhicules neufs | C70: [...] | F70: 0 | L70: 0 | N70: =L70-F70 -> 0 | Q70: 0 | S70: =L70-Q70 -> 0
A71: Véhicules neufs[...] | B71: Véhicules neufs | C71: [...] | F71: 0 | L71: 0 | N71: =L71-F71 -> 0 | Q71: 0 | S71: =L71-Q71 -> 0
A72: Véhicules neufsTOTAL SEMI-FIXES | B72: Véhicules neufs | C72: TOTAL SEMI-FIXES | D72: % brut | E72: =F72/F$27 -> #DIV/0! | F72: =+SUM(F55:F71) -> 0 | J72: % brut | K72: =L72/L$27 -> 0.1178199 | L72: =+SUM(L55:L71) -> 23023.95 | N72: =+SUM(N55:N71) -> 23023.95 | O72: % brut | P72: =Q72/Q$27 -> 0.12902852 | Q72: =+SUM(Q55:Q71) -> 40059.66 | S72: =+SUM(S55:S71) -> -17035.71
A73: Véhicules neufs | B73: Véhicules neufs
A74: Véhicules neufsTOTAL DES DÉPENSES | B74: Véhicules neufs | C74: TOTAL DES DÉPENSES | D74: % brut | E74: =F74/F$27 -> #DIV/0! | F74: =F41+F54+F72 -> 0 | J74: % brut | K74: =L74/L$27 -> 0.60950934 | L74: =L41+L54+L72 -> 119108.17 | N74: =L74-F74 -> 119108.17 | O74: % brut | P74: =Q74/Q$27 -> 0.45678724 | Q74: =Q41+Q54+Q72 -> 141819.36 | S74: =L74-Q74 -> -22711.19
A75: Véhicules neufsProgramme neuf 1 | B75: Véhicules neufs | C75: Programme Excellence | F75: 0 | L75: 2794.39 | N75: =L75-F75 -> 2794.39 | Q75: 25095 | S75: =L75-Q75 -> -22300.61
A76: Véhicules neufsProgramme neuf 2 | B76: Véhicules neufs | C76: Programme neuf 2 | F76: 0 | L76: 0 | N76: =L76-F76 -> 0 | Q76: 0 | S76: =L76-Q76 -> 0
A77: Véhicules neufsProgramme neuf 3 | B77: Véhicules neufs | C77: Programme neuf 3 | F77: 0 | L77: 0 | N77: =L77-F77 -> 0 | Q77: 0 | S77: =L77-Q77 -> 0
A78: Véhicules neufsHoldbacks | B78: Véhicules neufs | C78: Holdbacks | E78: =+F78/D27 -> #DIV/0! | F78: 0 | K78: =+L78/J27 -> 0 | L78: 0 | N78: =L78-F78 -> 0 | P78: =+Q78/O27 -> 0 | Q78: 0 | S78: =L78-Q78 -> 0
A79: Véhicules neufs[...] | B79: Véhicules neufs | C79: [...] | F79: 0 | L79: 0 | N79: =L79-F79 -> 0 | Q79: 0 | S79: =L79-Q79 -> 0
A80: Véhicules neufs[...] | B80: Véhicules neufs | C80: [...] | F80: 0 | L80: 0 | N80: =L80-F80 -> 0 | Q80: 0 | S80: =L80-Q80 -> 0
A81: Véhicules neufs[...] | B81: Véhicules neufs | C81: [...] | F81: 0 | L81: 0 | N81: =L81-F81 -> 0 | Q81: 0 | S81: =L81-Q81 -> 0
A82: Véhicules neufsFrais administration | B82: Véhicules neufs | C82: Frais administration | D82: =E82/499 -> #DIV/0! | E82: =+F82/D24 -> #DIV/0! | F82: 0 | J82: =K82/699 -> 0.79907805 | K82: =+L82/J24 -> 558.55556 | L82: 30162 | N82: =L82-F82 -> 30162 | O82: =P82/699 -> 0 | P82: =+Q82/O24 -> 0 | Q82: 0 | S82: =L82-Q82 -> 30162
A83: Véhicules neufsAUTRES REVENUS | B83: Véhicules neufs | C83: AUTRES REVENUS | F83: =+SUM(F75:F82) -> 0 | L83: =+SUM(L75:L82) -> 32956.39 | N83: =+SUM(N75:N82) -> 32956.39 | Q83: =+SUM(Q75:Q82) -> 25095 | S83: =+SUM(S75:S82) -> 7861.39
A84: Véhicules neufs | B84: Véhicules neufs
A85: Véhicules neufsPROFIT DÉPARTEMENTAL | B85: Véhicules neufs | C85: PROFIT DÉPARTEMENTAL | F85: =F27-F74+F83 -> 0 | L85: =L27-L74+L83 -> 109264.7 | N85: =N27-N41-N54-N72+N83 -> 109264.7 | Q85: =Q27-Q74+Q83 -> 193747.01 | S85: =S27-S41-S54-S72+S83 -> -84482.31
C89: =C1 -> Ste-Marie Auto | K89: Véhicules usagés | S89: =$S$1 -> Réalisé, Juillet 2026
D91: BUDGET ORIGINAL | J91: RÉALISATION | M91: ÉCART réel / Budget | O91: ANNÉE PRÉCÉDENTE | R91: ECART (réel/ Ann.Préc.)
D92: UNITE | E92: $P/UNITÉ | F92: $PROFITS | J92: UNITÉS | K92: $P/UNITE | L92: $PROFITS | M92: UNITÉS | N92: $PROFITS | O92: UNITE | P92: $P/UNITÉ | Q92: $PROFITS | R92: UNITÉS | S92: $PROFITS
A93: Véhicules usagésVentes nettes | B93: Véhicules usagés | C93: Ventes nettes | F93: 0 | L93: 1470640.9 | Q93: 2050773.7
A94: Véhicules usagésCertifié | B94: Véhicules usagés | C94: Certifié | D94: 0 | E94: =IF(D94=0,0,F94/D94) -> 0 | F94: 0 | J94: 0 | K94: =IF(J94=0,0,L94/J94) -> 0 | L94: 0 | M94: =J94-D94 -> 0 | N94: =L94-F94 -> 0 | O94: 0 | P94: =IF(O94=0,0,Q94/O94) -> 0 | Q94: 0 | R94: =J94-O94 -> 0 | S94: =L94-Q94 -> 0
A95: Véhicules usagésNon Certifié | B95: Véhicules usagés | C95: Non Certifié | D95: 0 | E95: =IF(D95=0,0,F95/D95) -> 0 | F95: 0 | J95: 23 | K95: =IF(J95=0,0,L95/J95) -> 645.77435 | L95: 14852.81 | M95: =J95-D95 -> 23 | N95: =L95-F95 -> 14852.81 | O95: 12 | P95: =IF(O95=0,0,Q95/O95) -> 1196.0858 | Q95: 14353.03 | R95: =J95-O95 -> 11 | S95: =L95-Q95 -> 499.78 | U95: Livre des ventes
A96: =B96&C96 -> Véhicules usagésAutres Marques | B96: Véhicules usagés | C96: Autres Marques | D96: 0 | E96: =IF(D96=0,0,F96/D96) -> 0 | F96: 0 | J96: 0 | K96: =IF(J96=0,0,L96/J96) -> 0 | L96: 0 | M96: =J96-D96 -> 0 | N96: =L96-F96 -> 0 | O96: 0 | P96: =IF(O96=0,0,Q96/O96) -> 0 | Q96: 0 | R96: =J96-O96 -> 0 | S96: =L96-Q96 -> 0
A97: =B97&C97 -> Véhicules usagésTotal Usagés | B97: Véhicules usagés | C97: Total Usagés | D97: =+D95+D94+D96 -> 0 | E97: =IF(D97=0,0,F97/D97) -> 0 | F97: =+F94+F95+F96 -> 0 | J97: =+J94+J95+J96 -> 23 | K97: =IF(J97<=0,0,L97/J97) -> 645.77435 | L97: =+L94+L95+L96 -> 14852.81 | M97: =J97-D97 -> 23 | N97: =L97-F97 -> 14852.81 | O97: =+O94+O95+O96 -> 12 | P97: =IF(O97<=0,0,Q97/O97) -> 1196.0858 | Q97: =+Q94+Q95+Q96 -> 14353.03 | R97: =R94+R95 -> 11 | S97: =S94+S95 -> 499.78 | T97: 23 | U97: 14853 | V97: =L97-U97 -> -0.19
A98: =B98&C98 -> Véhicules usagés | B98: Véhicules usagés | E98: =IF(D98=0,0,F98/D98) -> 0 | R98: =R97/O97 -> 0.91666667 | S98: =IF(Q97=0,0,(S97/Q97)) -> 0.034820522
A99: =B99&C99 -> Véhicules usagésRachat bail | B99: Véhicules usagés | C99: Rachat bail | K99: =IF(J99=0,0,L99/J99) -> 0 | L99: 0 | M99: =J99-D99 -> 0 | N99: =L99-F99 -> 0 | P99: =IF(O99=0,0,Q99/O99) -> 0 | Q99: 0 | R99: =J99-O99 -> 0 | S99: =L99-Q99 -> 0
A100: =B100&C100 -> Véhicules usagés | B100: Véhicules usagés
A101: Véhicules usagésVentes au Gros | B101: Véhicules usagés | C101: Ventes au Gros | D101: 0 | E101: =IF(D101=0,0,F101/D101) -> 0 | F101: 0 | J101: 21 | K101: =IF(J101=0,0,L101/J101) -> 905.66 | L101: 19018.86 | M101: =J101-D101 -> 21 | N101: =L101-F101 -> 19018.86 | O101: 47 | P101: =IF(O101=0,0,Q101/O101) -> 821.43596 | Q101: 38607.49 | R101: =J101-O101 -> -26 | S101: =L101-Q101 -> -19588.63 | T101: 21 | U101: 19019 | V101: =L101-U101 -> -0.14
A102: Véhicules usagés | B102: Véhicules usagés
A103: Véhicules usagésRev. Finances | B103: Véhicules usagés | C103: Rev. Finances | D103: 0 | E103: =IF(D103=0,0,F103/D103) -> 0 | F103: 0 | K103: =IF(J97=0,0,L103/J97) -> 738.69565 | L103: 16990 | N103: =L103-F103 -> 16990 | P103: =IF(O97=0,0,Q103/O97) -> 489.49917 | Q103: 5873.99 | R103: =P103-K103 -> -249.19649 | S103: =L103-Q103 -> 11116.01
A104: Véhicules usagésRev. Protections | B104: Véhicules usagés | C104: Rev. Protections | D104: 0 | E104: =IF(D104=0,0,F104/D104) -> 0 | F104: 0 | K104: =IF(J97=0,0,L104/J97) -> 124.43478 | L104: 2862 | N104: =L104-F104 -> 2862 | P104: =IF(O97=0,0,Q104/O97) -> 250.55 | Q104: 3006.6 | R104: =P104-K104 -> 126.11522 | S104: =L104-Q104 -> -144.6
A105: Véhicules usagésRev. Autres | B105: Véhicules usagés | C105: Rev. Autres | D105: 0 | E105: =IF(D105=0,0,F105/D105) -> 0 | F105: 0 | K105: =IF(J97=0,0,L105/J97) -> 0 | L105: 0 | N105: =L105-F105 -> 0 | P105: =IF(O97=0,0,Q105/O97) -> 0 | Q105: 0 | R105: =P105-K105 -> 0 | S105: =L105-Q105 -> 0
...

Sheet Mois 2
C1: Ste-Marie Auto | K1: Véhicules neufs | S1: Réalisé, Aout 2026
D2: X | E2: O | F2: U | J2: NB | L2: $ | O2: NB | Q2: $ | V2: *** NE PAS EFFACER / Pour An Précédente ***
D3: BUDGET ORIGINAL | J3: RÉALISATION | M3: ÉCART réel / Budget | O3: ANNÉE PRÉCÉDENTE | R3: ECART (réel/ Ann.Préc.) | V3: NEUF | W3: 0.45
D4: UNITE | E4: $P/UNITÉ | F4: $PROFITS | J4: UNITÉS | K4: $P/UNITE | L4: $PROFITS | M4: UNITÉS | N4: $PROFITS | O4: UNITÉS | P4: $P/UNITE | Q4: $PROFITS | R4: UNITÉS | S4: $PROFITS | V4: USAGE | W4: 0.1
A5: Véhicules neufsVentes nettes | B5: Véhicules neufs | C5: Ventes nettes | F5: #N/A | L5: 5549753.4 | Q5: 8048046.4 | U5: =L5/AF493 -> 0.3978662 | V5: SERVICE | W5: 0.225
A6: Véhicules neufsAutos détail | B6: Véhicules neufs | C6: Autos détail | D6: #N/A | E6: =IF(D6=0,0,F6/D6) -> #N/A | F6: #N/A | J6: 0 | K6: =IF(J6=0,0,L6/J6) -> 0 | L6: 0 | M6: =J6-D6 -> #N/A | N6: =L6-F6 -> #N/A | O6: 2 | P6: =IF(O6=0,0,Q6/O6) -> 5561 | Q6: 11122 | R6: =J6-O6 -> -2 | S6: =L6-Q6 -> -11122 | V6: CARROSSERIE | W6: 0.025
A7: Véhicules neufsCamions détail | B7: Véhicules neufs | C7: Camions détail | D7: #N/A | E7: =IF(D7=0,0,F7/D7) -> #N/A | F7: #N/A | J7: 26 | K7: =IF(J7=0,0,L7/J7) -> 2497.6038 | L7: 64937.7 | M7: =J7-D7 -> #N/A | N7: =L7-F7 -> #N/A | O7: 67 | P7: =IF(O7=0,0,Q7/O7) -> 2643.707 | Q7: 177128.37 | R7: =J7-O7 -> -41 | S7: =L7-Q7 -> -112190.67 | V7: PIECES | W7: 0.2
A8: Véhicules neufsSprinter | B8: Véhicules neufs | C8: Voitures electriques | D8: #N/A | E8: =IF(D8=0,0,F8/D8) -> #N/A | F8: #N/A | J8: 0 | K8: =IF(J8=0,0,L8/J8) -> 0 | L8: 0 | M8: =J8-D8 -> #N/A | N8: =L8-F8 -> #N/A | O8: 0 | P8: =IF(O8=0,0,Q8/O8) -> 0 | Q8: 0 | R8: =J8-O8 -> 0 | S8: =L8-Q8 -> 0 | W8: =SUM(W3:W7) -> 1
A9: Véhicules neufsMoto détail | B9: Véhicules neufs | C9: Camions electriques | D9: #N/A | E9: =IF(D9=0,0,F9/D9) -> #N/A | F9: #N/A | J9: 27 | K9: =IF(J9=0,0,L9/J9) -> 1229.7707 | L9: 33203.81 | M9: =J9-D9 -> #N/A | N9: =L9-F9 -> #N/A | O9: 11 | P9: =IF(O9=0,0,Q9/O9) -> 900.23727 | Q9: 9902.61 | R9: =J9-O9 -> 16 | S9: =L9-Q9 -> 23301.2 | U9: Livre des ventes
A10: Véhicules neufs[...] | B10: Véhicules neufs | C10: [...] | D10: #N/A | E10: =IF(D10=0,0,F10/D10) -> #N/A | F10: #N/A | J10: 0 | K10: =IF(J10=0,0,L10/J10) -> 0 | L10: 0 | M10: =J10-D10 -> #N/A | N10: =L10-F10 -> #N/A | O10: 0 | P10: =IF(O10=0,0,Q10/O10) -> 0 | Q10: 0 | R10: =J10-O10 -> 0 | S10: =L10-Q10 -> 0
A11: Véhicules neufs[...] | B11: Véhicules neufs | C11: [...] | D11: #N/A | E11: =IF(D11=0,0,F11/D11) -> #N/A | F11: #N/A | J11: 0 | K11: =IF(J11=0,0,L11/J11) -> 0 | L11: 0 | M11: =J11-D11 -> #N/A | N11: =L11-F11 -> #N/A | O11: 0 | P11: =IF(O11=0,0,Q11/O11) -> 0 | Q11: 0 | R11: =J11-O11 -> 0 | S11: =L11-Q11 -> 0
A12: Véhicules neufs[...] | B12: Véhicules neufs | C12: [...] | D12: #N/A | E12: =IF(D12=0,0,F12/D12) -> #N/A | F12: #N/A | J12: 0 | K12: =IF(J12=0,0,L12/J12) -> 0 | L12: 0 | M12: =J12-D12 -> #N/A | N12: =L12-F12 -> #N/A | O12: 0 | P12: =IF(O12=0,0,Q12/O12) -> 0 | Q12: 0 | R12: =J12-O12 -> 0 | S12: =L12-Q12 -> 0
A13: Véhicules neufsTotal Neufs | B13: Véhicules neufs | C13: Total Neufs | D13: =+SUM(D6:D12) -> #N/A | E13: =IF(D13<=0,0,F13/D13) -> #N/A | F13: =+SUM(F6:F12) -> #N/A | J13: =+SUM(J6:J12) -> 53 | K13: =IF(J13<=0,0,L13/J13) -> 1851.7266 | L13: =+SUM(L6:L12) -> 98141.51 | M13: =+SUM(M6:M12) -> #N/A | N13: =+SUM(N6:N12) -> #N/A | O13: =+SUM(O6:O12) -> 80 | P13: =IF(O13<=0,0,Q13/O13) -> 2476.9123 | Q13: =+SUM(Q6:Q12) -> 198152.98 | R13: =+SUM(R6:R12) -> -27 | S13: =+SUM(S6:S12) -> -100011.47 | T13: 53 | U13: 98142 | V13: =L13-U13 -> -0.49
A14: Véhicules neufs | B14: Véhicules neufs | M14: =IF(D13=0,0,M13/D13) -> #N/A | N14: =IF(F13=0,0,N13/F13) -> #N/A | R14: =R13/O13 -> -0.3375 | S14: =IF(Q13=0,0,(S13/Q13)) -> -0.50471848
A15: Véhicules neufsEx-Démos et courtoisies | B15: Véhicules neufs | C15: Ex-Démos et courtoisies | D15: #N/A | E15: =IF(D15=0,0,F15/D15) -> #N/A | F15: #N/A | J15: 0 | K15: =IF(J15=0,0,L15/J15) -> 0 | L15: 0 | M15: =J15-D15 -> #N/A | N15: =L15-F15 -> #N/A | O15: 0 | P15: =IF(O15=0,0,Q15/O15) -> 0 | Q15: 0 | R15: =J15-O15 -> 0 | S15: =L15-Q15 -> 0
A16: Véhicules neufs | B16: Véhicules neufs
A17: Véhicules neufsFlottes | B17: Véhicules neufs | C17: Flottes | D17: #N/A | E17: =IF(D17=0,0,F17/D17) -> #N/A | F17: #N/A | J17: 34 | K17: =IF(J17=0,0,L17/J17) -> 587.26382 | L17: 19966.97 | M17: =J17-D17 -> #N/A | N17: =L17-F17 -> #N/A | O17: 54 | P17: =IF(O17=0,0,Q17/O17) -> 617.8963 | Q17: 33366.4 | R17: =J17-O17 -> -20 | S17: =L17-Q17 -> -13399.43 | T17: 34 | U17: 18817 | V17: =L17-U17 -> 1149.97
A18: Véhicules neufs | B18: Véhicules neufs
A19: Véhicules neufsRachat bail | B19: Véhicules neufs
A20: Véhicules neufs | B20: Véhicules neufs
A21: Véhicules neufsRev. Finances | B21: Véhicules neufs | C21: Rev. Finances | D21: #N/A | E21: =IF(D21=0,0,F21/D21) -> #N/A | F21: #N/A | K21: =IF(J13=0,0,L21/(J13+J15)) -> 0 | L21: 0 | N21: =L21-F21 -> #N/A | P21: =IF(O13=0,0,Q21/(O13+O15)) -> 1.3225 | Q21: 105.8 | R21: =P21-K21 -> 1.3225 | S21: =L21-Q21 -> -105.8
A22: Véhicules neufsRev. Protections | B22: Véhicules neufs | C22: Rev. Protections | D22: #N/A | E22: =IF(D22=0,0,F22/D22) -> #N/A | F22: #N/A | K22: =IF(J13=0,0,L22/(J13+J15)) -> 538.27321 | L22: 28528.48 | N22: =L22-F22 -> #N/A | P22: =IF(O13=0,0,Q22/(O13+O15)) -> 752.63388 | Q22: 60210.71 | R22: =P22-K22 -> 214.36067 | S22: =L22-Q22 -> -31682.23
A23: Véhicules neufsRev. Autres | B23: Véhicules neufs | C23: Rev. Autres | D23: #N/A | E23: =IF(D23=0,0,F23/D23) -> #N/A | F23: #N/A | K23: =IF(J13=0,0,L23/(J13+J15)) -> -21.713396 | L23: -1150.81 | N23: =L23-F23 -> #N/A | P23: =IF(O13=0,0,Q23/(O13+O15)) -> 180.2505 | Q23: 14420.04 | R23: =P23-K23 -> 201.9639 | S23: =L23-Q23 -> -15570.85
A24: Véhicules neufsTotal F&I | B24: Véhicules neufs | C24: Total F&I | D24: =+D15+D13 -> #N/A | E24: =IF(D24<=0,0,F24/D24) -> #N/A | F24: =F21+F22+F23 -> #N/A | J24: =+J15+J13 -> 53 | K24: =IF(J24<=0,0,L24/J24) -> 516.55981 | L24: =L21+L22+L23 -> 27377.67 | M24: =J24-D24 -> #N/A | N24: =L24-F24 -> #N/A | O24: =+O15+O13 -> 80 | P24: =IF(O24<=0,0,Q24/O24) -> 934.20688 | Q24: =Q21+Q22+Q23 -> 74736.55 | R24: =P24-K24 -> 417.64706 | S24: =L24-Q24 -> -47358.88 | U24: 27378 | V24: =L24-U24 -> -0.33
A25: Véhicules neufs | B25: Véhicules neufs | N25: =IF(N24=0,0,N24/F24) -> #N/A | S25: =IF(Q24=0,0,(S24/Q24)) -> -0.63367763
A26: Véhicules neufs | B26: Véhicules neufs
A27: Véhicules neufsTotal Dépt. Neufs | B27: Véhicules neufs | C27: Total Dépt. Neufs | D27: =+D13+D15+D17 -> #N/A | E27: =IF(D27<=0,0,F27/D27) -> #N/A | F27: =F13+F17+F24+F19+F15 -> #N/A | J27: =+J13+J15+J17 -> 87 | K27: =IF(J27<=0,0,L27/J27) -> 1672.2546 | L27: =L13+L17+L24+L19+L15 -> 145486.15 | M27: =J27-D27 -> #N/A | N27: =L27-F27 -> #N/A | O27: =+O13+O15+O17 -> 134 | P27: =IF(O27<=0,0,Q27/O27) -> 2285.492 | Q27: =Q13+Q17+Q24+Q19+Q15 -> 306255.93 | R27: =J27-O27 -> -47 | S27: =L27-Q27 -> -160769.78 | U27: =SUM(U13:U26) -> 144337 | V27: =L27-U27 -> 1149.15
A28: Véhicules neufs | B28: Véhicules neufs | R28: =R27/O27 -> -0.35074627 | S28: =IF(Q27=0,0,S27/Q27) -> -0.52495238
A29: Véhicules neufs | B29: Véhicules neufs
A30: Véhicules neufsDEPENSES | B30: Véhicules neufs | C30: DEPENSES
A31: Véhicules neufsComm. vendeurs | B31: Véhicules neufs | C31: Comm. vendeurs | D31: =F31/(F13+F15) -> #N/A | E31: =F31/D$24 -> #N/A | F31: #N/A | J31: =L31/(L15+L13+L17) -> 0.36190416 | K31: =IF(L31=0,0,L31/J$24) -> 806.48962 | L31: 42743.95 | N31: =L31-F31 -> #N/A | O31: =Q31/(Q15+Q13+Q17) -> 0.22591202 | P31: =IF(Q31=0,0,Q31/O$24) -> 653.78763 | Q31: 52303.01 | S31: =L31-Q31 -> -9559.06
A32: Véhicules neufsComm. F&I | B32: Véhicules neufs | C32: Comm. F&I | D32: =F32/F24 -> #N/A | E32: =F32/D$24 -> #N/A | F32: #N/A | J32: =L32/L24 -> 0.33094818 | K32: =IF(L32=0,0,L32/J$24) -> 170.95453 | L32: 9060.59 | N32: =L32-F32 -> #N/A | O32: =Q32/Q24 -> 0.24125358 | P32: =IF(Q32=0,0,Q32/O$24) -> 225.38075 | Q32: 18030.46 | S32: =L32-Q32 -> -8969.87
A33: Véhicules neufsFrais de livraison | B33: Véhicules neufs | C33: Frais de livraison | E33: =F33/D$24 -> #N/A | F33: #N/A | K33: =IF(L33=0,0,L33/J$24) -> -63.636981 | L33: -3372.76 | N33: =L33-F33 -> #N/A | P33: =IF(Q33=0,0,Q33/O$24) -> -114.10925 | Q33: -9128.74 | S33: =L33-Q33 -> 5755.98 | T33: =-3973+600 -> -3373 | U33: Frais document reclassé - correction charge de juillet
A34: Véhicules neufsService gratuit 1 | B34: Véhicules neufs | C34: Service gratuit 1 | E34: =F34/D$24 -> #N/A | F34: #N/A | K34: =IF(L34=0,0,L34/J$24) -> 0 | L34: 0 | N34: =L34-F34 -> #N/A | P34: =IF(Q34=0,0,Q34/O$24) -> 7.719375 | Q34: 617.55 | S34: =L34-Q34 -> -617.55
A35: Véhicules neufsEntretien stock | B35: Véhicules neufs | C35: Entretien stock | E35: =F35/D$24 -> #N/A | F35: #N/A | K35: =IF(L35=0,0,L35/J$24) -> 54.977925 | L35: 2913.83 | N35: =L35-F35 -> #N/A | P35: =IF(Q35=0,0,Q35/O$24) -> 0 | Q35: 0 | S35: =L35-Q35 -> 2913.83
A36: Véhicules neufsPublicité 1 | B36: Véhicules neufs | C36: Publicité 1 | E36: =F36/D$24 -> #N/A | F36: #N/A | K36: =IF(L36=0,0,L36/J$24) -> 241.13075 | L36: 12779.93 | N36: =L36-F36 -> #N/A | P36: =IF(Q36=0,0,Q36/O$24) -> 184.15988 | Q36: 14732.79 | S36: =L36-Q36 -> -1952.86
A37: Véhicules neufsIntérêt de gros | B37: Véhicules neufs | C37: Intérêt de gros | E37: =F37/D$24 -> #N/A | F37: #N/A | K37: =IF(L37=0,0,L37/J$24) -> 500.4666 | L37: 26524.73 | N37: =L37-F37 -> #N/A | P37: =IF(Q37=0,0,Q37/O$24) -> 944.36875 | Q37: 75549.5 | S37: =L37-Q37 -> -49024.77
A38: Véhicules neufs[...] | B38: Véhicules neufs | C38: Crédit Intérêts Floor Plan | E38: =F38/D$24 -> #N/A | F38: #N/A | K38: =IF(L38=0,0,L38/J$24) -> -1248.8064 | L38: -66186.74 | N38: =L38-F38 -> #N/A | P38: =IF(Q38=0,0,Q38/O$24) -> -1344.5761 | Q38: -107566.09 | S38: =L38-Q38 -> 41379.35 | T38: 64032
A39: Véhicules neufs[...] | B39: Véhicules neufs | C39: Crédit Boni TD | E39: =F39/D$24 -> #N/A | F39: #N/A | K39: =IF(L39=0,0,L39/J$24) -> -194.33566 | L39: -10299.79 | N39: =L39-F39 -> #N/A | P39: =IF(Q39=0,0,Q39/O$24) -> 0 | Q39: 0 | S39: =L39-Q39 -> -10299.79 | T39: -10300 | U39: =L39+L121+L194 -> -13851.27
A40: Véhicules neufs[...] | B40: Véhicules neufs | C40: [...] | E40: =F40/D$24 -> #N/A | F40: #N/A | K40: =IF(L40=0,0,L40/J$24) -> 0 | L40: 0 | N40: =L40-F40 -> #N/A | P40: =IF(Q40=0,0,Q40/O$24) -> 0 | Q40: 0 | S40: =L40-Q40 -> 0
A41: Véhicules neufsTOTAL VARIABLES | B41: Véhicules neufs | C41: TOTAL VARIABLES | D41: % brut | E41: =F41/F$27 -> #N/A | F41: =SUM(F31:F40) -> #N/A | J41: % brut | K41: =L41/L$27 -> 0.097354559 | L41: =SUM(L31:L40) -> 14163.74 | N41: =L41-F41 -> #N/A | O41: % brut | P41: =Q41/Q$27 -> 0.14542896 | Q41: =SUM(Q31:Q40) -> 44538.48 | S41: =L41-Q41 -> -30374.74
A42: Véhicules neufsSalaires cadres | B42: Véhicules neufs | C42: Salaires cadres | F42: #N/A | L42: 6326.88 | N42: =L42-F42 -> #N/A | Q42: 12759.15 | S42: =L42-Q42 -> -6432.27
A43: Véhicules neufsSalaires commis | B43: Véhicules neufs | C43: Salaires commis | F43: #N/A | L43: 8576.19 | N43: =L43-F43 -> #N/A | Q43: 27510.7 | S43: =L43-Q43 -> -18934.51
A44: Véhicules neufsSalaires autres | B44: Véhicules neufs | C44: Salaires autres | F44: #N/A | L44: 5167.58 | N44: =L44-F44 -> #N/A | Q44: 5112.2 | S44: =L44-Q44 -> 55.38
A45: Véhicules neufsSalaires spécialistes | B45: Véhicules neufs | C45: Salaires spécialistes | F45: #N/A | L45: 0 | N45: =L45-F45 -> #N/A | Q45: 0 | S45: =L45-Q45 -> 0
A46: Véhicules neufs[...] | B46: Véhicules neufs | C46: [...] | F46: #N/A | L46: 0 | N46: =L46-F46 -> #N/A | Q46: 0 | S46: =L46-Q46 -> 0
A47: Véhicules neufs[...] | B47: Véhicules neufs | C47: [...] | F47: #N/A | L47: 0 | N47: =L47-F47 -> #N/A | Q47: 0 | S47: =L47-Q47 -> 0
A48: Véhicules neufs[...] | B48: Véhicules neufs | C48: [...] | F48: #N/A | L48: 0 | N48: =L48-F48 -> #N/A | Q48: 0 | S48: =L48-Q48 -> 0
A49: Véhicules neufsSalaires en absences | B49: Véhicules neufs | C49: Salaires en absences | F49: #N/A | L49: 4857.21 | N49: =L49-F49 -> #N/A | Q49: 6372 | S49: =L49-Q49 -> -1514.79
A50: Véhicules neufsDéduction à la source | B50: Véhicules neufs | C50: Déduction à la source | F50: #N/A | L50: 9070.93 | N50: =L50-F50 -> #N/A | Q50: 14274.21 | S50: =L50-Q50 -> -5203.28
A51: Véhicules neufsBénéfices marginaux | B51: Véhicules neufs | C51: Bénéfices marginaux | F51: #N/A | L51: 1221.52 | N51: =L51-F51 -> #N/A | Q51: 4465.47 | S51: =L51-Q51 -> -3243.95
A52: Véhicules neufsCsst | B52: Véhicules neufs | C52: Csst | F52: #N/A | L52: 3803.17 | N52: =L52-F52 -> #N/A | Q52: 36.04 | S52: =L52-Q52 -> 3767.13
A53: Véhicules neufs[...] | B53: Véhicules neufs | C53: [...] | D53: =VLOOKUP(C53,$B$2:$B$46,1,FALSE) -> #N/A | F53: #N/A | L53: 0 | N53: =L53-F53 -> #N/A | Q53: 0 | S53: =L53-Q53 -> 0
A54: Véhicules neufsTOTAL PERSONNEL | B54: Véhicules neufs | C54: TOTAL PERSONNEL | D54: % brut | E54: =F54/F$27 -> #N/A | F54: =+SUM(F42:F53) -> #N/A | J54: % brut | K54: =L54/L$27 -> 0.26822814 | L54: =+SUM(L42:L53) -> 39023.48 | N54: =+SUM(N42:N53) -> #N/A | O54: % brut | P54: =Q54/Q$27 -> 0.23029683 | Q54: =+SUM(Q42:Q53) -> 70529.77 | S54: =+SUM(S42:S53) -> -31506.29
A55: Véhicules neufsPublicité 2 | B55: Véhicules neufs | C55: Publicité 2 | F55: #N/A | L55: 0 | N55: =L55-F55 -> #N/A | Q55: 0 | S55: =L55-Q55 -> 0
A56: Véhicules neufsService gratuit 2 | B56: Véhicules neufs | C56: Service gratuit 2 | F56: #N/A | L56: 0 | N56: =L56-F56 -> #N/A | Q56: 0 | S56: =L56-Q56 -> 0
A57: Véhicules neufsFrais véhicules de cie | B57: Véhicules neufs | C57: Frais véhicules de cie | F57: #N/A | L57: 5493.09 | N57: =L57-F57 -> #N/A | Q57: 8310.13 | S57: =L57-Q57 -> -2817.04
A58: Véhicules neufsInformatique | B58: Véhicules neufs | C58: Informatique | F58: #N/A | L58: 4814.83 | N58: =L58-F58 -> #N/A | Q58: 5512.46 | S58: =L58-Q58 -> -697.63
A59: Véhicules neufsFrais de déplacement | B59: Véhicules neufs | C59: Frais de déplacement | F59: #N/A | L59: 1084.04 | N59: =L59-F59 -> #N/A | Q59: 1258.02 | S59: =L59-Q59 -> -173.98
A60: Véhicules neufsServices extérieurs | B60: Véhicules neufs | C60: Services extérieurs | F60: #N/A | L60: 3548.7 | N60: =L60-F60 -> #N/A | Q60: 7441.35 | S60: =L60-Q60 -> -3892.65
A61: Véhicules neufsFournitures autres | B61: Véhicules neufs | C61: Fournitures autres | F61: #N/A | L61: 144.63 | N61: =L61-F61 -> #N/A | Q61: 982.81 | S61: =L61-Q61 -> -838.18
A62: Véhicules neufsUniformes | B62: Véhicules neufs | C62: Uniformes | F62: #N/A | L62: 0 | N62: =L62-F62 -> #N/A | Q62: 0 | S62: =L62-Q62 -> 0
A63: Véhicules neufsPapeterie | B63: Véhicules neufs | C63: Papeterie | F63: #N/A | L63: 1520.78 | N63: =L63-F63 -> #N/A | Q63: 1513.03 | S63: =L63-Q63 -> 7.75
A64: Véhicules neufsTéléphone | B64: Véhicules neufs | C64: Téléphone | F64: #N/A | L64: 672.35 | N64: =L64-F64 -> #N/A | Q64: 969.78 | S64: =L64-Q64 -> -297.43
A65: Véhicules neufsFrais postaux | B65: Véhicules neufs | C65: Frais postaux | F65: #N/A | L65: 535.69 | N65: =L65-F65 -> #N/A | Q65: 916.49 | S65: =L65-Q65 -> -380.8
A66: Véhicules neufsDivers | B66: Véhicules neufs | C66: Divers | F66: #N/A | L66: 3445.54 | N66: =L66-F66 -> #N/A | Q66: 3531.24 | S66: =L66-Q66 -> -85.7
... A68: Véhicules neufsFrais bancaires | B68: Véhicules neufs | C68: Frais bancaires | F68: #N/A | L68: 1424.71 | N68: =L68-F68 -> #N/A | Q68: 299.38 | S68: =L68-Q68 -> 1125.33
A69: Véhicules neufs[...] | B69: Véhicules neufs | C69: [...] | F69: #N/A | N69: =L69-F69 -> #N/A | S69: =L69-Q69 -> 0
A70: Véhicules neufs[...] | B70: Véhicules neufs | C70: [...] | F70: #N/A | L70: 0 | N70: =L70-F70 -> #N/A | Q70: 0 | S70: =L70-Q70 -> 0
A71: Véhicules neufs[...] | B71: Véhicules neufs | C71: [...] | F71: #N/A | L71: 0 | N71: =L71-F71 -> #N/A | Q71: 0 | S71: =L71-Q71 -> 0
A72: Véhicules neufsTOTAL SEMI-FIXES | B72: Véhicules neufs | C72: TOTAL SEMI-FIXES | D72: % brut | E72: =F72/F$27 -> #N/A | F72: =+SUM(F55:F71) -> #N/A | J72: % brut | K72: =L72/L$27 -> 0.15983899 | L72: =+SUM(L55:L71) -> 23254.36 | N72: =+SUM(N55:N71) -> #N/A | O72: % brut | P72: =Q72/Q$27 -> 0.10252761 | Q72: =+SUM(Q55:Q71) -> 31399.69 | S72: =+SUM(S55:S71) -> -8145.33
A73: Véhicules neufs | B73: Véhicules neufs
A74: Véhicules neufsTOTAL DES DÉPENSES | B74: Véhicules neufs | C74: TOTAL DES DÉPENSES | D74: % brut | E74: =F74/F$27 -> #N/A | F74: =F41+F54+F72 -> #N/A | J74: % brut | K74: =L74/L$27 -> 0.5254217 | L74: =L41+L54+L72 -> 76441.58 | N74: =L74-F74 -> #N/A | O74: % brut | P74: =Q74/Q$27 -> 0.4782534 | Q74: =Q41+Q54+Q72 -> 146467.94 | S74: =L74-Q74 -> -70026.36
A75: Véhicules neufsProgramme neuf 1 | B75: Véhicules neufs | C75: Programme Excellence | F75: #N/A | L75: 35241.44 | N75: =L75-F75 -> #N/A | Q75: 25446.58 | S75: =L75-Q75 -> 9794.86
A76: Véhicules neufsProgramme neuf 2 | B76: Véhicules neufs | C76: Programme neuf 2 | F76: #N/A | L76: 0 | N76: =L76-F76 -> #N/A | Q76: 0 | S76: =L76-Q76 -> 0
A77: Véhicules neufsProgramme neuf 3 | B77: Véhicules neufs | C77: Programme neuf 3 | F77: #N/A | L77: 0 | N77: =L77-F77 -> #N/A | Q77: 0 | S77: =L77-Q77 -> 0
A78: Véhicules neufsHoldbacks | B78: Véhicules neufs | C78: Holdbacks | E78: =+F78/D27 -> #N/A | F78: #N/A | K78: =+L78/J27 -> 0 | L78: 0 | N78: =L78-F78 -> #N/A | P78: =+Q78/O27 -> 0 | Q78: 0 | S78: =L78-Q78 -> 0
A79: Véhicules neufs[...] | B79: Véhicules neufs | C79: [...] | F79: #N/A | L79: 0 | N79: =L79-F79 -> #N/A | Q79: 0 | S79: =L79-Q79 -> 0
A80: Véhicules neufs[...] | B80: Véhicules neufs | C80: [...] | F80: #N/A | L80: 0 | N80: =L80-F80 -> #N/A | Q80: 0 | S80: =L80-Q80 -> 0
A81: Véhicules neufs[...] | B81: Véhicules neufs | C81: [...] | F81: #N/A | L81: 0 | N81: =L81-F81 -> #N/A | Q81: 0 | S81: =L81-Q81 -> 0
A82: Véhicules neufsFrais administration | B82: Véhicules neufs | C82: Frais administration | D82: =E82/499 -> #N/A | E82: =+F82/D24 -> #N/A | F82: #N/A | J82: =K82/699 -> 0.46929576 | K82: =+L82/J24 -> 328.03774 | L82: 17386 | N82: =L82-F82 -> #N/A | O82: =P82/699 -> 0 | P82: =+Q82/O24 -> 0 | Q82: 0 | S82: =L82-Q82 -> 17386 | T82: =16786+600 -> 17386 | U82: 14 à 699$ et 38 à 200$ = 52
A83: Véhicules neufsAUTRES REVENUS | B83: Véhicules neufs | C83: AUTRES REVENUS | F83: =+SUM(F75:F82) -> #N/A | L83: =+SUM(L75:L82) -> 52627.44 | N83: =+SUM(N75:N82) -> #N/A | Q83: =+SUM(Q75:Q82) -> 25446.58 | S83: =+SUM(S75:S82) -> 27180.86
A84: Véhicules neufs | B84: Véhicules neufs
A85: Véhicules neufsPROFIT DÉPARTEMENTAL | B85: Véhicules neufs | C85: PROFIT DÉPARTEMENTAL | F85: =F27-F74+F83 -> #N/A | L85: =L27-L74+L83 -> 121672.01 | N85: =N27-N41-N54-N72+N83 -> #N/A | Q85: =Q27-Q74+Q83 -> 185234.57 | S85: =S27-S41-S54-S72+S83 -> -63562.56
C89: =C1 -> Ste-Marie Auto | K89: Véhicules usagés | S89: =$S$1 -> Réalisé, Aout 2026
D91: BUDGET ORIGINAL | J91: RÉALISATION | M91: ÉCART réel / Budget | O91: ANNÉE PRÉCÉDENTE | R91: ECART (réel/ Ann.Préc.)
D92: UNITE | E92: $P/UNITÉ | F92: $PROFITS | J92: UNITÉS | K92: $P/UNITE | L92: $PROFITS | M92: UNITÉS | N92: $PROFITS | O92: UNITE | P92: $P/UNITÉ | Q92: $PROFITS | R92: UNITÉS | S92: $PROFITS
A93: Véhicules usagésVentes nettes | B93: Véhicules usagés | C93: Ventes nettes | F93: #N/A | L93: 2038487.7 | Q93: 3574806.1
A94: Véhicules usagésCertifié | B94: Véhicules usagés | C94: Certifié | D94: #N/A | E94: =IF(D94=0,0,F94/D94) -> #N/A | F94: #N/A | J94: 0 | K94: =IF(J94=0,0,L94/J94) -> 0 | L94: 0 | M94: =J94-D94 -> #N/A | N94: =L94-F94 -> #N/A | O94: 0 | P94: =IF(O94=0,0,Q94/O94) -> 0 | Q94: 0 | R94: =J94-O94 -> 0 | S94: =L94-Q94 -> 0
A95: Véhicules usagésNon Certifié | B95: Véhicules usagés | C95: Non Certifié | D95: #N/A | E95: =IF(D95=0,0,F95/D95) -> #N/A | F95: #N/A | J95: 24 | K95: =IF(J95=0,0,L95/J95) -> 575.65167 | L95: 13815.64 | M95: =J95-D95 -> #N/A | N95: =L95-F95 -> #N/A | O95: 16 | P95: =IF(O95=0,0,Q95/O95) -> 1085.3031 | Q95: 17364.85 | R95: =J95-O95 -> 8 | S95: =L95-Q95 -> -3549.21 | U95: Livre des ventes
A96: =B96&C96 -> Véhicules usagésAutres Marques | B96: Véhicules usagés | C96: Autres Marques | D96: #N/A | E96: =IF(D96=0,0,F96/D96) -> #N/A | F96: #N/A | J96: 0 | K96: =IF(J96=0,0,L96/J96) -> 0 | L96: 0 | M96: =J96-D96 -> #N/A | N96: =L96-F96 -> #N/A | O96: 0 | P96: =IF(O96=0,0,Q96/O96) -> 0 | Q96: 0 | R96: =J96-O96 -> 0 | S96: =L96-Q96 -> 0
A97: =B97&C97 -> Véhicules usagésTotal Usagés | B97: Véhicules usagés | C97: Total Usagés | D97: =+D95+D94+D96 -> #N/A | E97: =IF(D97=0,0,F97/D97) -> #N/A | F97: =+F94+F95+F96 -> #N/A | J97: =+J94+J95+J96 -> 24 | K97: =IF(J97<=0,0,L97/J97) -> 575.65167 | L97: =+L94+L95+L96 -> 13815.64 | M97: =J97-D97 -> #N/A | N97: =L97-F97 -> #N/A | O97: =+O94+O95+O96 -> 16 | P97: =IF(O97<=0,0,Q97/O97) -> 1085.3031 | Q97: =+Q94+Q95+Q96 -> 17364.85 | R97: =R94+R95 -> 8 | S97: =S94+S95 -> -3549.21 | T97: 24 | U97: 13816 | V97: =L97-U97 -> -0.36
A98: =B98&C98 -> Véhicules usagés | B98: Véhicules usagés | E98: =IF(D98=0,0,F98/D98) -> 0 | R98: =R97/O97 -> 0.5 | S98: =IF(Q97=0,0,(S97/Q97)) -> -0.20439048
A99: =B99&C99 -> Véhicules usagésRachat bail | B99: Véhicules usagés | C99: Rachat bail | K99: =IF(J99=0,0,L99/J99) -> 0 | L99: 0 | M99: =J99-D99 -> 0 | N99: =L99-F99 -> 0 | P99: =IF(O99=0,0,Q99/O99) -> 0 | Q99: 0 | R99: =J99-O99 -> 0 | S99: =L99-Q99 -> 0
A100: =B100&C100 -> Véhicules usagés | B100: Véhicules usagés
A101: Véhicules usagésVentes au Gros | B101: Véhicules usagés | C101: Ventes au Gros | D101: #N/A | E101: =IF(D101=0,0,F101/D101) -> #N/A | F101: #N/A | J101: 35 | K101: =IF(J101=0,0,L101/J101) -> -476.81886 | L101: -16688.66 | M101: =J101-D101 -> #N/A | N101: =L101-F101 -> #N/A | O101: 82 | P101: =IF(O101=0,0,Q101/O101) -> 40.515366 | Q101: 3322.26 | R101: =J101-O101 -> -47 | S101: =L101-Q101 -> -20010.92 | T101: 35 | U101: -16689 | V101: =L101-U101 -> 0.34
A102: Véhicules usagés | B102: Véhicules usagés
A103: Véhicules usagésRev. Finances | B103: Véhicules usagés | C103: Rev. Finances | D103: #N/A | E103: =IF(D103=0,0,F103/D103) -> #N/A | F103: #N/A | K103: =IF(J97=0,0,L103/J97) -> 639.0875 | L103: 15338.1 | N103: =L103-F103 -> #N/A | P103: =IF(O97=0,0,Q103/O97) -> 458.0925 | Q103: 7329.48 | R103: =P103-K103 -> -180.995 | S103: =L103-Q103 -> 8008.62
A104: Véhicules usagésRev. Protections | B104: Véhicules usagés | C104: Rev. Protections | D104: #N/A | E104: =IF(D104=0,0,F104/D104) -> #N/A | F104: #N/A | K104: =IF(J97=0,0,L104/J97) -> 484.48208 | L104: 11627.57 | N104: =L104-F104 -> #N/A | P104: =IF(O97=0,0,Q104/O97) -> 342.19437 | Q104: 5475.11 | R104: =P104-K104 -> -142.28771 | S104: =L104-Q104 -> 6152.46
A105: Véhicules usagésRev. Autres | B105: Véhicules usagés | C105: Rev. Autres | D105: #N/A | E105: =IF(D105=0,0,F105/D105) -> #N/A | F105: #N/A | K105: =IF(J97=0,0,L105/J97) -> 0 | L105: 0 | N105: =L105-F105 -> #N/A | P105: =IF(O97=0,0,Q105/O97) -> 0 | Q105: 0 | R105: =P105-K105 -> 0 | S105: =L105-Q105 -> 0
...

Sheet Mois 3
C1: Ste-Marie Auto | K1: Véhicules neufs | S1: Réalisé, Septembre 2026
D2: X | E2: O | F2: U | J2: NB | L2: $ | O2: NB | Q2: $ | V2: *** NE PAS EFFACER / Pour An Précédente ***
D3: BUDGET ORIGINAL | J3: RÉALISATION | M3: ÉCART réel / Budget | O3: ANNÉE PRÉCÉDENTE | R3: ECART (réel/ Ann.Préc.) | V3: NEUF | W3: 0.45
D4: UNITE | E4: $P/UNITÉ | F4: $PROFITS | J4: UNITÉS | K4: $P/UNITE | L4: $PROFITS | M4: UNITÉS | N4: $PROFITS | O4: UNITÉS | P4: $P/UNITE | Q4: $PROFITS | R4: UNITÉS | S4: $PROFITS | V4: USAGE | W4: 0.1
A5: Véhicules neufsVentes nettes | B5: Véhicules neufs | C5: Ventes nettes | F5: 0 | L5: 7465717.8 | Q5: 8922542.5 | U5: =L5/AF493 -> 0.66682387 | V5: SERVICE | W5: 0.225
A6: Véhicules neufsAutos détail | B6: Véhicules neufs | C6: Autos détail | D6: 0 | E6: =IF(D6=0,0,F6/D6) -> 0 | F6: 0 | J6: 1 | K6: =IF(J6=0,0,L6/J6) -> 11544.36 | L6: 11544.36 | M6: =J6-D6 -> 1 | N6: =L6-F6 -> 11544.36 | O6: 0 | P6: =IF(O6=0,0,Q6/O6) -> 0 | Q6: 0 | R6: =J6-O6 -> 1 | S6: =L6-Q6 -> 11544.36 | V6: CARROSSERIE | W6: 0.025
A7: Véhicules neufsCamions détail | B7: Véhicules neufs | C7: Camions détail | D7: 0 | E7: =IF(D7=0,0,F7/D7) -> 0 | F7: 0 | J7: 30 | K7: =IF(J7=0,0,L7/J7) -> 1763.614 | L7: 52908.42 | M7: =J7-D7 -> 30 | N7: =L7-F7 -> 52908.42 | O7: 38 | P7: =IF(O7=0,0,Q7/O7) -> 2884.9066 | Q7: 109626.45 | R7: =J7-O7 -> -8 | S7: =L7-Q7 -> -56718.03 | V7: PIECES | W7: 0.2
A8: Véhicules neufsSprinter | B8: Véhicules neufs | C8: Voitures electriques | D8: 0 | E8: =IF(D8=0,0,F8/D8) -> 0 | F8: 0 | J8: 0 | K8: =IF(J8=0,0,L8/J8) -> 0 | L8: 0 | M8: =J8-D8 -> 0 | N8: =L8-F8 -> 0 | O8: 0 | P8: =IF(O8=0,0,Q8/O8) -> 0 | Q8: 0 | R8: =J8-O8 -> 0 | S8: =L8-Q8 -> 0 | W8: =SUM(W3:W7) -> 1
A9: Véhicules neufsMoto détail | B9: Véhicules neufs | C9: Camions electriques | D9: 0 | E9: =IF(D9=0,0,F9/D9) -> 0 | F9: 0 | J9: 48 | K9: =IF(J9=0,0,L9/J9) -> 1378.6771 | L9: 66176.5 | M9: =J9-D9 -> 48 | N9: =L9-F9 -> 66176.5 | O9: 24 | P9: =IF(O9=0,0,Q9/O9) -> 1502.1 | Q9: 36050.4 | R9: =J9-O9 -> 24 | S9: =L9-Q9 -> 30126.1 | U9: Livre des ventes
A10: Véhicules neufs[...] | B10: Véhicules neufs | C10: [...] | D10: 0 | E10: =IF(D10=0,0,F10/D10) -> 0 | F10: 0 | J10: 0 | K10: =IF(J10=0,0,L10/J10) -> 0 | L10: 0 | M10: =J10-D10 -> 0 | N10: =L10-F10 -> 0 | O10: 0 | P10: =IF(O10=0,0,Q10/O10) -> 0 | Q10: 0 | R10: =J10-O10 -> 0 | S10: =L10-Q10 -> 0
A11: Véhicules neufs[...] | B11: Véhicules neufs | C11: [...] | D11: 0 | E11: =IF(D11=0,0,F11/D11) -> 0 | F11: 0 | J11: 0 | K11: =IF(J11=0,0,L11/J11) -> 0 | L11: 0 | M11: =J11-D11 -> 0 | N11: =L11-F11 -> 0 | O11: 0 | P11: =IF(O11=0,0,Q11/O11) -> 0 | Q11: 0 | R11: =J11-O11 -> 0 | S11: =L11-Q11 -> 0
A12: Véhicules neufs[...] | B12: Véhicules neufs | C12: [...] | D12: 0 | E12: =IF(D12=0,0,F12/D12) -> 0 | F12: 0 | J12: 0 | K12: =IF(J12=0,0,L12/J12) -> 0 | L12: 0 | M12: =J12-D12 -> 0 | N12: =L12-F12 -> 0 | O12: 0 | P12: =IF(O12=0,0,Q12/O12) -> 0 | Q12: 0 | R12: =J12-O12 -> 0 | S12: =L12-Q12 -> 0
A13: Véhicules neufsTotal Neufs | B13: Véhicules neufs | C13: Total Neufs | D13: =+SUM(D6:D12) -> 0 | E13: =IF(D13<=0,0,F13/D13) -> 0 | F13: =+SUM(F6:F12) -> 0 | J13: =+SUM(J6:J12) -> 79 | K13: =IF(J13<=0,0,L13/J13) -> 1653.5352 | L13: =+SUM(L6:L12) -> 130629.28 | M13: =+SUM(M6:M12) -> 79 | N13: =+SUM(N6:N12) -> 130629.28 | O13: =+SUM(O6:O12) -> 62 | P13: =IF(O13<=0,0,Q13/O13) -> 2349.6266 | Q13: =+SUM(Q6:Q12) -> 145676.85 | R13: =+SUM(R6:R12) -> 17 | S13: =+SUM(S6:S12) -> -15047.57 | T13: 79 | U13: 130630 | V13: =L13-U13 -> -0.72
A14: Véhicules neufs | B14: Véhicules neufs | M14: =IF(D13=0,0,M13/D13) -> 0 | N14: =IF(F13=0,0,N13/F13) -> 0 | R14: =R13/O13 -> 0.27419355 | S14: =IF(Q13=0,0,(S13/Q13)) -> -0.10329417
A15: Véhicules neufsEx-Démos et courtoisies | B15: Véhicules neufs | C15: Ex-Démos et courtoisies | D15: 0 | E15: =IF(D15=0,0,F15/D15) -> 0 | F15: 0 | J15: 0 | K15: =IF(J15=0,0,L15/J15) -> 0 | L15: 0 | M15: =J15-D15 -> 0 | N15: =L15-F15 -> 0 | O15: 0 | P15: =IF(O15=0,0,Q15/O15) -> 0 | Q15: 0 | R15: =J15-O15 -> 0 | S15: =L15-Q15 -> 0
A16: Véhicules neufs | B16: Véhicules neufs
A17: Véhicules neufsFlottes | B17: Véhicules neufs | C17: Flottes | D17: 0 | E17: =IF(D17=0,0,F17/D17) -> 0 | F17: 0 | J17: 51 | K17: =IF(J17=0,0,L17/J17) -> 740.45647 | L17: 37763.28 | M17: =J17-D17 -> 51 | N17: =L17-F17 -> 37763.28 | O17: 82 | P17: =IF(O17=0,0,Q17/O17) -> 669.57854 | Q17: 54905.44 | R17: =J17-O17 -> -31 | S17: =L17-Q17 -> -17142.16 | T17: 51 | U17: 38372 | V17: =L17-U17 -> -608.72
A18: Véhicules neufs | B18: Véhicules neufs
A19: Véhicules neufsRachat bail | B19: Véhicules neufs
A20: Véhicules neufs | B20: Véhicules neufs
A21: Véhicules neufsRev. Finances | B21: Véhicules neufs | C21: Rev. Finances | D21: 0 | E21: =IF(D21=0,0,F21/D21) -> 0 | F21: 0 | K21: =IF(J13=0,0,L21/(J13+J15)) -> -16.825063 | L21: -1329.18 | N21: =L21-F21 -> -1329.18 | P21: =IF(O13=0,0,Q21/(O13+O15)) -> 0 | Q21: 0 | R21: =P21-K21 -> 16.825063 | S21: =L21-Q21 -> -1329.18
A22: Véhicules neufsRev. Protections | B22: Véhicules neufs | C22: Rev. Protections | D22: 0 | E22: =IF(D22=0,0,F22/D22) -> 0 | F22: 0 | K22: =IF(J13=0,0,L22/(J13+J15)) -> 563.21367 | L22: 44493.88 | N22: =L22-F22 -> 44493.88 | P22: =IF(O13=0,0,Q22/(O13+O15)) -> 752.96161 | Q22: 46683.62 | R22: =P22-K22 -> 189.74794 | S22: =L22-Q22 -> -2189.74
A23: Véhicules neufsRev. Autres | B23: Véhicules neufs | C23: Rev. Autres | D23: 0 | E23: =IF(D23=0,0,F23/D23) -> 0 | F23: 0 | K23: =IF(J13=0,0,L23/(J13+J15)) -> 68.392405 | L23: 5403 | N23: =L23-F23 -> 5403 | P23: =IF(O13=0,0,Q23/(O13+O15)) -> 71.569355 | Q23: 4437.3 | R23: =P23-K23 -> 3.1769498 | S23: =L23-Q23 -> 965.7
A24: Véhicules neufsTotal F&I | B24: Véhicules neufs | C24: Total F&I | D24: =+D15+D13 -> 0 | E24: =IF(D24<=0,0,F24/D24) -> 0 | F24: =F21+F22+F23 -> 0 | J24: =+J15+J13 -> 79 | K24: =IF(J24<=0,0,L24/J24) -> 614.78101 | L24: =L21+L22+L23 -> 48567.7 | M24: =J24-D24 -> 79 | N24: =L24-F24 -> 48567.7 | O24: =+O15+O13 -> 62 | P24: =IF(O24<=0,0,Q24/O24) -> 824.53097 | Q24: =Q21+Q22+Q23 -> 51120.92 | R24: =P24-K24 -> 209.74996 | S24: =L24-Q24 -> -2553.22 | U24: 48568 | V24: =L24-U24 -> -0.3
A25: Véhicules neufs | B25: Véhicules neufs | N25: =IF(N24=0,0,N24/F24) -> #DIV/0! | S25: =IF(Q24=0,0,(S24/Q24)) -> -0.049944719
A26: Véhicules neufs | B26: Véhicules neufs
A27: Véhicules neufsTotal Dépt. Neufs | B27: Véhicules neufs | C27: Total Dépt. Neufs | D27: =+D13+D15+D17 -> 0 | E27: =IF(D27<=0,0,F27/D27) -> 0 | F27: =F13+F17+F24+F19+F15 -> 0 | J27: =+J13+J15+J17 -> 130 | K27: =IF(J27<=0,0,L27/J27) -> 1668.9251 | L27: =L13+L17+L24+L19+L15 -> 216960.26 | M27: =J27-D27 -> 130 | N27: =L27-F27 -> 216960.26 | O27: =+O13+O15+O17 -> 144 | P27: =IF(O27<=0,0,Q27/O27) -> 1747.939 | Q27: =Q13+Q17+Q24+Q19+Q15 -> 251703.21 | R27: =J27-O27 -> -14 | S27: =L27-Q27 -> -34742.95 | U27: =SUM(U13:U26) -> 217570 | V27: =L27-U27 -> -609.74
A28: Véhicules neufs | B28: Véhicules neufs | R28: =R27/O27 -> -0.097222222 | S28: =IF(Q27=0,0,S27/Q27) -> -0.13803141
A29: Véhicules neufs | B29: Véhicules neufs
A30: Véhicules neufsDEPENSES | B30: Véhicules neufs | C30: DEPENSES
A31: Véhicules neufsComm. vendeurs | B31: Véhicules neufs | C31: Comm. vendeurs | D31: =F31/(F13+F15) -> #DIV/0! | E31: =F31/D$24 -> #DIV/0! | F31: 0 | J31: =L31/(L15+L13+L17) -> 0.24857316 | K31: =IF(L31=0,0,L31/J$24) -> 529.84646 | L31: 41857.87 | N31: =L31-F31 -> 41857.87 | O31: =Q31/(Q15+Q13+Q17) -> 0.30837922 | P31: =IF(Q31=0,0,Q31/O$24) -> 997.6679 | Q31: 61855.41 | S31: =L31-Q31 -> -19997.54
A32: Véhicules neufsComm. F&I | B32: Véhicules neufs | C32: Comm. F&I | D32: =F32/F24 -> #DIV/0! | E32: =F32/D$24 -> #DIV/0! | F32: 0 | J32: =L32/L24 -> 0.29101728 | K32: =IF(L32=0,0,L32/J$24) -> 178.9119 | L32: 14134.04 | N32: =L32-F32 -> 14134.04 | O32: =Q32/Q24 -> 0.33260532 | P32: =IF(Q32=0,0,Q32/O$24) -> 274.24339 | Q32: 17003.09 | S32: =L32-Q32 -> -2869.05
A33: Véhicules neufsFrais de livraison | B33: Véhicules neufs | C33: Frais de livraison | E33: =F33/D$24 -> #DIV/0! | F33: 0 | K33: =IF(L33=0,0,L33/J$24) -> 357.47633 | L33: 28240.63 | N33: =L33-F33 -> 28240.63 | P33: =IF(Q33=0,0,Q33/O$24) -> -34.543548 | Q33: -2141.7 | S33: =L33-Q33 -> 30382.33 | T33: =-3973+600 -> -3373 | U33: Frais document reclassé - correction charge de juillet
A34: Véhicules neufsService gratuit 1 | B34: Véhicules neufs | C34: Service gratuit 1 | E34: =F34/D$24 -> #DIV/0! | F34: 0 | K34: =IF(L34=0,0,L34/J$24) -> 6.6478481 | L34: 525.18 | N34: =L34-F34 -> 525.18 | P34: =IF(Q34=0,0,Q34/O$24) -> 5.5369355 | Q34: 343.29 | S34: =L34-Q34 -> 181.89
A35: Véhicules neufsEntretien stock | B35: Véhicules neufs | C35: Entretien stock | E35: =F35/D$24 -> #DIV/0! | F35: 0 | K35: =IF(L35=0,0,L35/J$24) -> 24.067342 | L35: 1901.32 | N35: =L35-F35 -> 1901.32 | P35: =IF(Q35=0,0,Q35/O$24) -> 0 | Q35: 0 | S35: =L35-Q35 -> 1901.32
A36: Véhicules neufsPublicité 1 | B36: Véhicules neufs | C36: Publicité 1 | E36: =F36/D$24 -> #DIV/0! | F36: 0 | K36: =IF(L36=0,0,L36/J$24) -> -838.35861 | L36: -66230.33 | N36: =L36-F36 -> -66230.33 | P36: =IF(Q36=0,0,Q36/O$24) -> -1597.1466 | Q36: -99023.09 | S36: =L36-Q36 -> 32792.76
A37: Véhicules neufsIntérêt de gros | B37: Véhicules neufs | C37: Intérêt de gros | E37: =F37/D$24 -> #DIV/0! | F37: 0 | K37: =IF(L37=0,0,L37/J$24) -> 522.56709 | L37: 41282.8 | N37: =L37-F37 -> 41282.8 | P37: =IF(Q37=0,0,Q37/O$24) -> 702.84984 | Q37: 43576.69 | S37: =L37-Q37 -> -2293.89
A38: Véhicules neufs[...] | B38: Véhicules neufs | C38: Crédit Intérêts Floor Plan | E38: =F38/D$24 -> #DIV/0! | F38: 0 | K38: =IF(L38=0,0,L38/J$24) -> -1624.303 | L38: -128319.94 | N38: =L38-F38 -> -128319.94 | P38: =IF(Q38=0,0,Q38/O$24) -> -3558.1748 | Q38: -220606.84 | S38: =L38-Q38 -> 92286.9 | T38: 55741
A39: Véhicules neufs[...] | B39: Véhicules neufs | C39: Crédit Boni TD | E39: =F39/D$24 -> #DIV/0! | F39: 0 | K39: =IF(L39=0,0,L39/J$24) -> -121.06152 | L39: -9563.86 | N39: =L39-F39 -> -9563.86 | P39: =IF(Q39=0,0,Q39/O$24) -> 0 | Q39: 0 | S39: =L39-Q39 -> -9563.86 | T39: -9564 | U39: =L39+L121+L194 -> -11636.6
A40: Véhicules neufs[...] | B40: Véhicules neufs | C40: [...] | E40: =F40/D$24 -> #DIV/0! | F40: 0 | K40: =IF(L40=0,0,L40/J$24) -> 0 | L40: 0 | N40: =L40-F40 -> 0 | P40: =IF(Q40=0,0,Q40/O$24) -> 0 | Q40: 0 | S40: =L40-Q40 -> 0
A41: Véhicules neufsTOTAL VARIABLES | B41: Véhicules neufs | C41: TOTAL VARIABLES | D41: % brut | E41: =F41/F$27 -> #DIV/0! | F41: =SUM(F31:F40) -> 0 | J41: % brut | K41: =L41/L$27 -> -0.35108867 | L41: =SUM(L31:L40) -> -76172.29 | N41: =L41-F41 -> -76172.29 | O41: % brut | P41: =Q41/Q$27 -> -0.79058646 | Q41: =SUM(Q31:Q40) -> -198993.15 | S41: =L41-Q41 -> 122820.86
A42: Véhicules neufsSalaires cadres | B42: Véhicules neufs | C42: Salaires cadres | F42: 0 | L42: 21051.58 | N42: =L42-F42 -> 21051.58 | Q42: 3195.4 | S42: =L42-Q42 -> 17856.18
A43: Véhicules neufsSalaires commis | B43: Véhicules neufs | C43: Salaires commis | F43: 0 | L43: 9795.23 | N43: =L43-F43 -> 9795.23 | Q43: 33101.9 | S43: =L43-Q43 -> -23306.67
A44: Véhicules neufsSalaires autres | B44: Véhicules neufs | C44: Salaires autres | F44: 0 | L44: 12795.48 | N44: =L44-F44 -> 12795.48 | Q44: 4615.05 | S44: =L44-Q44 -> 8180.43
A45: Véhicules neufsSalaires spécialistes | B45: Véhicules neufs | C45: Salaires spécialistes | F45: 0 | L45: 0 | N45: =L45-F45 -> 0 | Q45: 0 | S45: =L45-Q45 -> 0
A46: Véhicules neufs[...] | B46: Véhicules neufs | C46: [...] | F46: 0 | L46: 0 | N46: =L46-F46 -> 0 | Q46: 0 | S46: =L46-Q46 -> 0
A47: Véhicules neufs[...] | B47: Véhicules neufs | C47: [...] | F47: 0 | L47: 0 | N47: =L47-F47 -> 0 | Q47: 0 | S47: =L47-Q47 -> 0
A48: Véhicules neufs[...] | B48: Véhicules neufs | C48: [...] | F48: 0 | L48: 0 | N48: =L48-F48 -> 0 | Q48: 0 | S48: =L48-Q48 -> 0
A49: Véhicules neufsSalaires en absences | B49: Véhicules neufs | C49: Salaires en absences | F49: 0 | L49: 9384.07 | N49: =L49-F49 -> 9384.07 | Q49: 13387.36 | S49: =L49-Q49 -> -4003.29
A50: Véhicules neufsDéduction à la source | B50: Véhicules neufs | C50: Déduction à la source | F50: 0 | L50: 7549.17 | N50: =L50-F50 -> 7549.17 | Q50: 14720.75 | S50: =L50-Q50 -> -7171.58
A51: Véhicules neufsBénéfices marginaux | B51: Véhicules neufs | C51: Bénéfices marginaux | F51: 0 | L51: 3038.73 | N51: =L51-F51 -> 3038.73 | Q51: 4541.75 | S51: =L51-Q51 -> -1503.02
A52: Véhicules neufsCsst | B52: Véhicules neufs | C52: Csst | F52: 0 | L52: 3813.65 | N52: =L52-F52 -> 3813.65 | Q52: 0.16 | S52: =L52-Q52 -> 3813.49
A53: Véhicules neufs[...] | B53: Véhicules neufs | C53: [...] | D53: =VLOOKUP(C53,$B$2:$B$46,1,FALSE) -> #N/A | F53: 0 | L53: 0 | N53: =L53-F53 -> 0 | Q53: 0 | S53: =L53-Q53 -> 0
A54: Véhicules neufsTOTAL PERSONNEL | B54: Véhicules neufs | C54: TOTAL PERSONNEL | D54: % brut | E54: =F54/F$27 -> #DIV/0! | F54: =+SUM(F42:F53) -> 0 | J54: % brut | K54: =L54/L$27 -> 0.31078461 | L54: =+SUM(L42:L53) -> 67427.91 | N54: =+SUM(N42:N53) -> 67427.91 | O54: % brut | P54: =Q54/Q$27 -> 0.29225837 | Q54: =+SUM(Q42:Q53) -> 73562.37 | S54: =+SUM(S42:S53) -> -6134.46
A55: Véhicules neufsPublicité 2 | B55: Véhicules neufs | C55: Publicité 2 | F55: 0 | L55: 0 | N55: =L55-F55 -> 0 | Q55: 0 | S55: =L55-Q55 -> 0
A56: Véhicules neufsService gratuit 2 | B56: Véhicules neufs | C56: Service gratuit 2 | F56: 0 | L56: 0 | N56: =L56-F56 -> 0 | Q56: 0 | S56: =L56-Q56 -> 0
A57: Véhicules neufsFrais véhicules de cie | B57: Véhicules neufs | C57: Frais véhicules de cie | F57: 0 | L57: 6931.9 | N57: =L57-F57 -> 6931.9 | Q57: 9251.35 | S57: =L57-Q57 -> -2319.45
A58: Véhicules neufsInformatique | B58: Véhicules neufs | C58: Informatique | F58: 0 | L58: 3443.68 | N58: =L58-F58 -> 3443.68 | Q58: 3035.29 | S58: =L58-Q58 -> 408.39
A59: Véhicules neufsFrais de déplacement | B59: Véhicules neufs | C59: Frais de déplacement | F59: 0 | L59: -514.76 | N59: =L59-F59 -> -514.76 | Q59: 11699.53 | S59: =L59-Q59 -> -12214.29
A60: Véhicules neufsServices extérieurs | B60: Véhicules neufs | C60: Services extérieurs | F60: 0 | L60: 4676.8 | N60: =L60-F60 -> 4676.8 | Q60: 8700.18 | S60: =L60-Q60 -> -4023.38
A61: Véhicules neufsFournitures autres | B61: Véhicules neufs | C61: Fournitures autres | F61: 0 | L61: 252.3 | N61: =L61-F61 -> 252.3 | Q61: 255.27 | S61: =L61-Q61 -> -2.97
A62: Véhicules neufsUniformes | B62: Véhicules neufs | C62: Uniformes | F62: 0 | L62: 0 | N62: =L62-F62 -> 0 | Q62: 0 | S62: =L62-Q62 -> 0
A63: Véhicules neufsPapeterie | B63: Véhicules neufs | C63: Papeterie | F63: 0 | L63: 740.48 | N63: =L63-F63 -> 740.48 | Q63: 2766.03 | S63: =L63-Q63 -> -2025.55
A64: Véhicules neufsTéléphone | B64: Véhicules neufs | C64: Téléphone | F64: 0 | L64: 633.19 | N64: =L64-F64 -> 633.19 | Q64: 157.97 | S64: =L64-Q64 -> 475.22
A65: Véhicules neufsFrais postaux | B65: Véhicules neufs | C65: Frais postaux | F65: 0 | L65: 1314.35 | N65: =L65-F65 -> 1314.35 | Q65: 1214.46 | S65: =L65-Q65 -> 99.89
A66: Véhicules neufsDivers | B66: Véhicules neufs | C66: Divers | F66: 0 | L66: 3705.26 | N66: =L66-F66 -> 3705.26 | Q66: 4629.35 | S66: =L66-Q66 -> -924.09
... A68: Véhicules neufsFrais bancaires | B68: Véhicules neufs | C68: Frais bancaires | F68: 0 | L68: 2389.34 | N68: =L68-F68 -> 2389.34 | Q68: 385.63 | S68: =L68-Q68 -> 2003.71
A69: Véhicules neufs[...] | B69: Véhicules neufs | C69: [...] | F69: 0 | N69: =L69-F69 -> 0 | S69: =L69-Q69 -> 0
A70: Véhicules neufs[...] | B70: Véhicules neufs | C70: [...] | F70: 0 | L70: 0 | N70: =L70-F70 -> 0 | Q70: 0 | S70: =L70-Q70 -> 0
A71: Véhicules neufs[...] | B71: Véhicules neufs | C71: [...] | F71: 0 | L71: 0 | N71: =L71-F71 -> 0 | Q71: 0 | S71: =L71-Q71 -> 0
A72: Véhicules neufsTOTAL SEMI-FIXES | B72: Véhicules neufs | C72: TOTAL SEMI-FIXES | D72: % brut | E72: =F72/F$27 -> #DIV/0! | F72: =+SUM(F55:F71) -> 0 | J72: % brut | K72: =L72/L$27 -> 0.11127632 | L72: =+SUM(L55:L71) -> 24142.54 | N72: =+SUM(N55:N71) -> 24142.54 | O72: % brut | P72: =Q72/Q$27 -> 0.17107474 | Q72: =+SUM(Q55:Q71) -> 43060.06 | S72: =+SUM(S55:S71) -> -18917.52
A73: Véhicules neufs | B73: Véhicules neufs
A74: Véhicules neufsTOTAL DES DÉPENSES | B74: Véhicules neufs | C74: TOTAL DES DÉPENSES | D74: % brut | E74: =F74/F$27 -> #DIV/0! | F74: =F41+F54+F72 -> 0 | J74: % brut | K74: =L74/L$27 -> 0.07097226 | L74: =L41+L54+L72 -> 15398.16 | N74: =L74-F74 -> 15398.16 | O74: % brut | P74: =Q74/Q$27 -> -0.32725336 | Q74: =Q41+Q54+Q72 -> -82370.72 | S74: =L74-Q74 -> 97768.88
A75: Véhicules neufsProgramme neuf 1 | B75: Véhicules neufs | C75: Programme Excellence | F75: 0 | L75: 51135.71 | N75: =L75-F75 -> 51135.71 | Q75: 26831.51 | S75: =L75-Q75 -> 24304.2
A76: Véhicules neufsProgramme neuf 2 | B76: Véhicules neufs | C76: Programme neuf 2 | F76: 0 | L76: 0 | N76: =L76-F76 -> 0 | Q76: 0 | S76: =L76-Q76 -> 0
A77: Véhicules neufsProgramme neuf 3 | B77: Véhicules neufs | C77: Programme neuf 3 | F77: 0 | L77: 0 | N77: =L77-F77 -> 0 | Q77: 0 | S77: =L77-Q77 -> 0
A78: Véhicules neufsHoldbacks | B78: Véhicules neufs | C78: Holdbacks | E78: =+F78/D27 -> #DIV/0! | F78: 0 | K78: =+L78/J27 -> 0 | L78: 0 | N78: =L78-F78 -> 0 | P78: =+Q78/O27 -> 0 | Q78: 0 | S78: =L78-Q78 -> 0
A79: Véhicules neufs[...] | B79: Véhicules neufs | C79: [...] | F79: 0 | L79: 0 | N79: =L79-F79 -> 0 | Q79: 0 | S79: =L79-Q79 -> 0
A80: Véhicules neufs[...] | B80: Véhicules neufs | C80: [...] | F80: 0 | L80: 0 | N80: =L80-F80 -> 0 | Q80: 0 | S80: =L80-Q80 -> 0
A81: Véhicules neufs[...] | B81: Véhicules neufs | C81: [...] | F81: 0 | L81: 0 | N81: =L81-F81 -> 0 | Q81: 0 | S81: =L81-Q81 -> 0
A82: Véhicules neufsFrais administration | B82: Véhicules neufs | C82: Frais administration | D82: =E82/499 -> #DIV/0! | E82: =+F82/D24 -> #DIV/0! | F82: 0 | J82: =K82/699 -> 0.88071567 | K82: =+L82/J24 -> 615.62025 | L82: 48634 | N82: =L82-F82 -> 48634 | O82: =P82/699 -> 0 | P82: =+Q82/O24 -> 0 | Q82: 0 | S82: =L82-Q82 -> 48634 | U82: Frais sur 77 dossiers (1 a 500$ et 10 à 200$)
A83: Véhicules neufsAUTRES REVENUS | B83: Véhicules neufs | C83: AUTRES REVENUS | F83: =+SUM(F75:F82) -> 0 | L83: =+SUM(L75:L82) -> 99769.71 | N83: =+SUM(N75:N82) -> 99769.71 | Q83: =+SUM(Q75:Q82) -> 26831.51 | S83: =+SUM(S75:S82) -> 72938.2
A84: Véhicules neufs | B84: Véhicules neufs
A85: Véhicules neufsPROFIT DÉPARTEMENTAL | B85: Véhicules neufs | C85: PROFIT DÉPARTEMENTAL | F85: =F27-F74+F83 -> 0 | L85: =L27-L74+L83 -> 301331.81 | N85: =N27-N41-N54-N72+N83 -> 301331.81 | Q85: =Q27-Q74+Q83 -> 360905.44 | S85: =S27-S41-S54-S72+S83 -> -59573.63
C89: =C1 -> Ste-Marie Auto | K89: Véhicules usagés | S89: =$S$1 -> Réalisé, Septembre 2026
D91: BUDGET ORIGINAL | J91: RÉALISATION | M91: ÉCART réel / Budget | O91: ANNÉE PRÉCÉDENTE | R91: ECART (réel/ Ann.Préc.)
D92: UNITE | E92: $P/UNITÉ | F92: $PROFITS | J92: UNITÉS | K92: $P/UNITE | L92: $PROFITS | M92: UNITÉS | N92: $PROFITS | O92: UNITE | P92: $P/UNITÉ | Q92: $PROFITS | R92: UNITÉS | S92: $PROFITS
A93: Véhicules usagésVentes nettes | B93: Véhicules usagés | C93: Ventes nettes | F93: 0 | L93: 1404913.7 | Q93: 2798079.1
A94: Véhicules usagésCertifié | B94: Véhicules usagés | C94: Certifié | D94: 0 | E94: =IF(D94=0,0,F94/D94) -> 0 | F94: 0 | J94: 0 | K94: =IF(J94=0,0,L94/J94) -> 0 | L94: 0 | M94: =J94-D94 -> 0 | N94: =L94-F94 -> 0 | O94: 0 | P94: =IF(O94=0,0,Q94/O94) -> 0 | Q94: 0 | R94: =J94-O94 -> 0 | S94: =L94-Q94 -> 0
A95: Véhicules usagésNon Certifié | B95: Véhicules usagés | C95: Non Certifié | D95: 0 | E95: =IF(D95=0,0,F95/D95) -> 0 | F95: 0 | J95: 22 | K95: =IF(J95=0,0,L95/J95) -> 1635.4432 | L95: 35979.75 | M95: =J95-D95 -> 22 | N95: =L95-F95 -> 35979.75 | O95: 14 | P95: =IF(O95=0,0,Q95/O95) -> 262.22857 | Q95: 3671.2 | R95: =J95-O95 -> 8 | S95: =L95-Q95 -> 32308.55 | U95: Livre des ventes
A96: =B96&C96 -> Véhicules usagésAutres Marques | B96: Véhicules usagés | C96: Autres Marques | D96: 0 | E96: =IF(D96=0,0,F96/D96) -> 0 | F96: 0 | J96: 0 | K96: =IF(J96=0,0,L96/J96) -> 0 | L96: 0 | M96: =J96-D96 -> 0 | N96: =L96-F96 -> 0 | O96: 0 | P96: =IF(O96=0,0,Q96/O96) -> 0 | Q96: 0 | R96: =J96-O96 -> 0 | S96: =L96-Q96 -> 0
A97: =B97&C97 -> Véhicules usagésTotal Usagés | B97: Véhicules usagés | C97: Total Usagés | D97: =+D95+D94+D96 -> 0 | E97: =IF(D97=0,0,F97/D97) -> 0 | F97: =+F94+F95+F96 -> 0 | J97: =+J94+J95+J96 -> 22 | K97: =IF(J97<=0,0,L97/J97) -> 1635.4432 | L97: =+L94+L95+L96 -> 35979.75 | M97: =J97-D97 -> 22 | N97: =L97-F97 -> 35979.75 | O97: =+O94+O95+O96 -> 14 | P97: =IF(O97<=0,0,Q97/O97) -> 262.22857 | Q97: =+Q94+Q95+Q96 -> 3671.2 | R97: =R94+R95 -> 8 | S97: =S94+S95 -> 32308.55 | T97: 22 | U97: 35980 | V97: =L97-U97 -> -0.25
A98: =B98&C98 -> Véhicules usagés | B98: Véhicules usagés | E98: =IF(D98=0,0,F98/D98) -> 0 | R98: =R97/O97 -> 0.57142857 | S98: =IF(Q97=0,0,(S97/Q97)) -> 8.8005421
A99: =B99&C99 -> Véhicules usagésRachat bail | B99: Véhicules usagés | C99: Rachat bail | K99: =IF(J99=0,0,L99/J99) -> 0 | L99: 0 | M99: =J99-D99 -> 0 | N99: =L99-F99 -> 0 | P99: =IF(O99=0,0,Q99/O99) -> 0 | Q99: 0 | R99: =J99-O99 -> 0 | S99: =L99-Q99 -> 0
A100: =B100&C100 -> Véhicules usagés | B100: Véhicules usagés
A101: Véhicules usagésVentes au Gros | B101: Véhicules usagés | C101: Ventes au Gros | D101: 0 | E101: =IF(D101=0,0,F101/D101) -> 0 | F101: 0 | J101: 23 | K101: =IF(J101=0,0,L101/J101) -> -126.60696 | L101: -2911.96 | M101: =J101-D101 -> 23 | N101: =L101-F101 -> -2911.96 | O101: 65 | P101: =IF(O101=0,0,Q101/O101) -> 1596.9832 | Q101: 103803.91 | R101: =J101-O101 -> -42 | S101: =L101-Q101 -> -106715.87 | T101: 23 | U101: -2912 | V101: =L101-U101 -> 0.04
A102: Véhicules usagés | B102: Véhicules usagés
A103: Véhicules usagésRev. Finances | B103: Véhicules usagés | C103: Rev. Finances | D103: 0 | E103: =IF(D103=0,0,F103/D103) -> 0 | F103: 0 | K103: =IF(J97=0,0,L103/J97) -> 212.73364 | L103: 4680.14 | N103: =L103-F103 -> 4680.14 | P103: =IF(O97=0,0,Q103/O97) -> 331.59929 | Q103: 4642.39 | R103: =P103-K103 -> 118.86565 | S103: =L103-Q103 -> 37.75
A104: Véhicules usagésRev. Protections | B104: Véhicules usagés | C104: Rev. Protections | D104: 0 | E104: =IF(D104=0,0,F104/D104) -> 0 | F104: 0 | K104: =IF(J97=0,0,L104/J97) -> 90.909091 | L104: 2000 | N104: =L104-F104 -> 2000 | P104: =IF(O97=0,0,Q104/O97) -> 697.64286 | Q104: 9767 | R104: =P104-K104 -> 606.73377 | S104: =L104-Q104 -> -7767
A105: Véhicules usagésRev. Autres | B105: Véhicules usagés | C105: Rev. Autres | D105: 0 | E105: =IF(D105=0,0,F105/D105) -> 0 | F105: 0 | K105: =IF(J97=0,0,L105/J97) -> 0 | L105: 0 | N105: =L105-F105 -> 0 | P105: =IF(O97=0,0,Q105/O97) -> 0 | Q105: 0 | R105: =P105-K105 -> 0 | S105: =L105-Q105 -> 0
...

Sheet END
