Workbook
Name Ticker: #REF!

Sheet Parametres
A1: Compagnie | B1: Ste-Marie Auto
M2: Mois | N2: YTD
A3: Mois Courant | B3: Décembre | C3: =+VLOOKUP(B3,$K$3:$L$14,2,0) -> 12 | K3: Janvier | L3: 1 | M3: =+IF($K3=$B$3,"X","") | N3: =+IF(K3=B3,"X",IF(L3<=$C$3,"X","")) -> X
A4: Année | B4: 2025 | K4: Février | L4: 2 | M4: =+IF($K4=$B$3,"X","") | N4: =+IF(K4=B4,"X",IF(L4<=$C$3,"X","")) -> X
K5: Mars | L5: 3 | M5: =+IF($K5=$B$3,"X","") | N5: =+IF(K5=B5,"X",IF(L5<=$C$3,"X","")) -> X
K6: Avril | L6: 4 | M6: =+IF($K6=$B$3,"X","") | N6: =+IF(K6=B6,"X",IF(L6<=$C$3,"X","")) -> X
K7: Mai | L7: 5 | M7: =+IF($K7=$B$3,"X","") | N7: =+IF(K7=B7,"X",IF(L7<=$C$3,"X","")) -> X
K8: Juin | L8: 6 | M8: =+IF($K8=$B$3,"X","") | N8: =+IF(K8=B8,"X",IF(L8<=$C$3,"X","")) -> X
A9: Sélectionner le mois en B3 | K9: Juillet | L9: 7 | M9: =+IF($K9=$B$3,"X","") | N9: =+IF(K9=B9,"X",IF(L9<=$C$3,"X","")) -> X
A10: Coller les balances de vérification respectives en cellule A1 dans les onglets BV_Data_An_Cour | K10: Août | L10: 8 | M10: =+IF($K10=$B$3,"X","") | N10: =+IF(K10=B10,"X",IF(L10<=$C$3,"X","")) -> X
A11: Vérifier s'il y a des #N/A dans les colonnes T à X des onlgets de BV | K11: Septembre | L11: 9 | M11: =+IF($K11=$B$3,"X","") | N11: =+IF(K11=B11,"X",IF(L11<=$C$3,"X","")) -> X
K12: Octobre | L12: 10 | M12: =+IF($K12=$B$3,"X","") | N12: =+IF(K12=B12,"X",IF(L12<=$C$3,"X","")) -> X
K13: Novembre | L13: 11 | M13: =+IF($K13=$B$3,"X","") | N13: =+IF(K13=B13,"X",IF(L13<=$C$3,"X","")) -> X
K14: Décembre | L14: 12 | M14: =+IF($K14=$B$3,"X","") -> X | N14: =+IF(K14=B14,"X",IF(L14<=$C$3,"X","")) -> X

Sheet Bilan
A1: BILAN
A2: =+Parametres!B1 -> Ste-Marie Auto
A3: =CONCATENATE("",,Parametres!B3," ",Parametres!B4) -> Décembre 2025
A5: Encaisse | B5: =SUMIFS(BV_Data_An_Cour!$AN:$AN,BV_Data_An_Cour!$AP:$AP,$A$1,BV_Data_An_Cour!$AQ:$AQ,$A5) -> 5616208.7 | D5: Marge de crédit | E5: =-SUMIFS(BV_Data_An_Cour!$AN:$AN,BV_Data_An_Cour!$AP:$AP,$A$1,BV_Data_An_Cour!$AQ:$AQ,$D5) -> 0
A6: Total Trésorerie et équivalent de Trésorerie | B6: =SUM(B5) -> 5616208.7
D7: Portion Court Terme de la Dette Long Terme | E7: =-SUMIFS(BV_Data_An_Cour!$AN:$AN,BV_Data_An_Cour!$AP:$AP,$A$1,BV_Data_An_Cour!$AQ:$AQ,$D7) -> 0
A8: Recevables Contrats en Transit | B8: =SUMIFS(BV_Data_An_Cour!$AN:$AN,BV_Data_An_Cour!$AP:$AP,$A$1,BV_Data_An_Cour!$AQ:$AQ,$A8) -> 788592.11
A9: Recevables Véhicules | B9: =SUMIFS(BV_Data_An_Cour!$AN:$AN,BV_Data_An_Cour!$AP:$AP,$A$1,BV_Data_An_Cour!$AQ:$AQ,$A9) -> 34777.63 | D9: Avances à payer | E9: =-SUMIFS(BV_Data_An_Cour!$AN:$AN,BV_Data_An_Cour!$AP:$AP,$A$1,BV_Data_An_Cour!$AQ:$AQ,$D9) -> 0
A10: Recevables Manufacturier | B10: =SUMIFS(BV_Data_An_Cour!$AN:$AN,BV_Data_An_Cour!$AP:$AP,$A$1,BV_Data_An_Cour!$AQ:$AQ,$A10) -> -56965.44 | D10: Comptes à Payer Fournisseurs | E10: =-SUMIFS(BV_Data_An_Cour!$AN:$AN,BV_Data_An_Cour!$AP:$AP,$A$1,BV_Data_An_Cour!$AQ:$AQ,$D10) -> 5711191.2
A11: Recevables Pièces et Service | B11: =SUMIFS(BV_Data_An_Cour!$AN:$AN,BV_Data_An_Cour!$AP:$AP,$A$1,BV_Data_An_Cour!$AQ:$AQ,$A11) -> 760891.2 | D11: Taxes de Vente à Payer | E11: =-SUMIFS(BV_Data_An_Cour!$AN:$AN,BV_Data_An_Cour!$AP:$AP,$A$1,BV_Data_An_Cour!$AQ:$AQ,$D11) -> -1695265.1
A12: Recevables Garantie Manufacturier | B12: =SUMIFS(BV_Data_An_Cour!$AN:$AN,BV_Data_An_Cour!$AP:$AP,$A$1,BV_Data_An_Cour!$AQ:$AQ,$A12) -> -9284.43 | D12: Impôts à payer | E12: =-SUMIFS(BV_Data_An_Cour!$AN:$AN,BV_Data_An_Cour!$AP:$AP,$A$1,BV_Data_An_Cour!$AQ:$AQ,$D12) -> 0
A13: Recevables Carrosserie | B13: =SUMIFS(BV_Data_An_Cour!$AN:$AN,BV_Data_An_Cour!$AP:$AP,$A$1,BV_Data_An_Cour!$AQ:$AQ,$A13) -> 35501.4 | D13: Dépôts de Client | E13: =-SUMIFS(BV_Data_An_Cour!$AN:$AN,BV_Data_An_Cour!$AP:$AP,$A$1,BV_Data_An_Cour!$AQ:$AQ,$D13) -> 0
A14: Recevables Intercos | B14: =SUMIFS(BV_Data_An_Cour!$AN:$AN,BV_Data_An_Cour!$AP:$AP,$A$1,BV_Data_An_Cour!$AQ:$AQ,$A14) -> 9552859.9 | D14: Payables Intercos | E14: =-SUMIFS(BV_Data_An_Cour!$AN:$AN,BV_Data_An_Cour!$AP:$AP,$A$1,BV_Data_An_Cour!$AQ:$AQ,$D14) -> 9732219.6 | G14: 30080
A15: Recevables Autres | B15: =SUMIFS(BV_Data_An_Cour!$AN:$AN,BV_Data_An_Cour!$AP:$AP,$A$1,BV_Data_An_Cour!$AQ:$AQ,$A15) -> 712073.66 | D15: Autres Comptes à Payer | E15: =-SUMIFS(BV_Data_An_Cour!$AN:$AN,BV_Data_An_Cour!$AP:$AP,$A$1,BV_Data_An_Cour!$AQ:$AQ,$D15) -> -57803.76 | G15: 33107
A16: Total Comptes à Recevoir | B16: =+SUM(B8:B15) -> 11818446 | D16: Total Comptes à Payer | E16: =+SUM(E10:E15) -> 13690342
A18: Inventaire Véhicules Neufs | B18: =SUMIFS(BV_Data_An_Cour!$AN:$AN,BV_Data_An_Cour!$AP:$AP,$A$1,BV_Data_An_Cour!$AQ:$AQ,$A18) -> 27819233 | D18: Effet à Payer Véhicules Neufs | E18: =-SUMIFS(BV_Data_An_Cour!$AN:$AN,BV_Data_An_Cour!$AP:$AP,$A$1,BV_Data_An_Cour!$AQ:$AQ,$D18) -> 27796998
A19: Inventaire Véhicules Usagés | B19: =SUMIFS(BV_Data_An_Cour!$AN:$AN,BV_Data_An_Cour!$AP:$AP,$A$1,BV_Data_An_Cour!$AQ:$AQ,$A19) -> 21035623 | D19: Effet à Payer Véhicules Usagés | E19: =-SUMIFS(BV_Data_An_Cour!$AN:$AN,BV_Data_An_Cour!$AP:$AP,$A$1,BV_Data_An_Cour!$AQ:$AQ,$D19) -> 19316937
A20: Inventaire Pièces, Pneus, Huile | B20: =SUMIFS(BV_Data_An_Cour!$AN:$AN,BV_Data_An_Cour!$AP:$AP,$A$1,BV_Data_An_Cour!$AQ:$AQ,$A20) -> 651553.54 | D20: Total Effets à Payer | E20: =+SUM(E18:E19) -> 47113935
A21: Total Inventaires | B21: =SUM(B18:B20) -> 49506410
D22: Salaires à Payer | E22: =-SUMIFS(BV_Data_An_Cour!$AN:$AN,BV_Data_An_Cour!$AP:$AP,$A$1,BV_Data_An_Cour!$AQ:$AQ,$D22) -> -2262416.8
A23: Avances à recevoir | B23: =SUMIFS(BV_Data_An_Cour!$AN:$AN,BV_Data_An_Cour!$AP:$AP,$A$1,BV_Data_An_Cour!$AQ:$AQ,$A23) -> 0 | D23: DAS à Payer | E23: =-SUMIFS(BV_Data_An_Cour!$AN:$AN,BV_Data_An_Cour!$AP:$AP,$A$1,BV_Data_An_Cour!$AQ:$AQ,$D23) -> 7093.33
A24: Travaux en Cours | B24: =SUMIFS(BV_Data_An_Cour!$AN:$AN,BV_Data_An_Cour!$AP:$AP,$A$1,BV_Data_An_Cour!$AQ:$AQ,$A24) -> 5681.21 | D24: Autres Courus | E24: =-SUMIFS(BV_Data_An_Cour!$AN:$AN,BV_Data_An_Cour!$AP:$AP,$A$1,BV_Data_An_Cour!$AQ:$AQ,$D24) -> 264053.15
A25: Sous-Traitance | B25: =SUMIFS(BV_Data_An_Cour!$AN:$AN,BV_Data_An_Cour!$AP:$AP,$A$1,BV_Data_An_Cour!$AQ:$AQ,$A25) -> 26584.49 | D25: [...] | E25: =-SUMIFS(BV_Data_An_Cour!$AN:$AN,BV_Data_An_Cour!$AP:$AP,$A$1,BV_Data_An_Cour!$AQ:$AQ,$D25) -> 0
A26: Frais Payés d'Avance | B26: =SUMIFS(BV_Data_An_Cour!$AN:$AN,BV_Data_An_Cour!$AP:$AP,$A$1,BV_Data_An_Cour!$AQ:$AQ,$A26) -> -61145.46 | D26: [...] | E26: =-SUMIFS(BV_Data_An_Cour!$AN:$AN,BV_Data_An_Cour!$AP:$AP,$A$1,BV_Data_An_Cour!$AQ:$AQ,$D26) -> 0
A27: [...] | B27: =SUMIFS(BV_Data_An_Cour!$AN:$AN,BV_Data_An_Cour!$AP:$AP,$A$1,BV_Data_An_Cour!$AQ:$AQ,$A27) -> 0 | D27: [...] | E27: =-SUMIFS(BV_Data_An_Cour!$AN:$AN,BV_Data_An_Cour!$AP:$AP,$A$1,BV_Data_An_Cour!$AQ:$AQ,$D27) -> 0
A28: [...] | B28: =SUMIFS(BV_Data_An_Cour!$AN:$AN,BV_Data_An_Cour!$AP:$AP,$A$1,BV_Data_An_Cour!$AQ:$AQ,$A28) -> 0 | D28: Total Frais Courus | E28: =SUM(E22:E24) -> -1991270.3
A29: [...] | B29: =SUMIFS(BV_Data_An_Cour!$AN:$AN,BV_Data_An_Cour!$AP:$AP,$A$1,BV_Data_An_Cour!$AQ:$AQ,$A29) -> 0
A30: Total Autres | B30: =SUM(B23:B29) -> -28879.76 | D30: Total Passif Court Terme | E30: =+E5+E7+E16+E20+E28 -> 58813007
A32: Total Actif Court Terme | B32: =+B6+B16+B21+B30 -> 66912185
D33: Impôts Futurs à payer | E33: =-SUMIFS(BV_Data_An_Cour!$AN:$AN,BV_Data_An_Cour!$AP:$AP,$A$1,BV_Data_An_Cour!$AQ:$AQ,$D33) -> 88167
A35: Terrain | B35: =SUMIFS(BV_Data_An_Cour!$AN:$AN,BV_Data_An_Cour!$AP:$AP,$A$1,BV_Data_An_Cour!$AQ:$AQ,$A35) -> 0 | D35: Avances Long Terme à Payer | E35: =-SUMIFS(BV_Data_An_Cour!$AN:$AN,BV_Data_An_Cour!$AP:$AP,$A$1,BV_Data_An_Cour!$AQ:$AQ,$D35) -> 0
A36: Bâtisse | B36: =SUMIFS(BV_Data_An_Cour!$AN:$AN,BV_Data_An_Cour!$AP:$AP,$A$1,BV_Data_An_Cour!$AQ:$AQ,$A36) -> 0 | D36: Hypothèque à Payer | E36: =-SUMIFS(BV_Data_An_Cour!$AN:$AN,BV_Data_An_Cour!$AP:$AP,$A$1,BV_Data_An_Cour!$AQ:$AQ,$D36) -> 0
A37: Améliorations Locatives | B37: =SUMIFS(BV_Data_An_Cour!$AN:$AN,BV_Data_An_Cour!$AP:$AP,$A$1,BV_Data_An_Cour!$AQ:$AQ,$A37) -> 133959.44 | D37: Dette à Long Terme | E37: =-SUMIFS(BV_Data_An_Cour!$AN:$AN,BV_Data_An_Cour!$AP:$AP,$A$1,BV_Data_An_Cour!$AQ:$AQ,$D37) -> 0
A38: Améliorations Locatives Permanentes | B38: =SUMIFS(BV_Data_An_Cour!$AN:$AN,BV_Data_An_Cour!$AP:$AP,$A$1,BV_Data_An_Cour!$AQ:$AQ,$A38) -> 0 | D38: Autres Dettes à Long Terme | E38: =-SUMIFS(BV_Data_An_Cour!$AN:$AN,BV_Data_An_Cour!$AP:$AP,$A$1,BV_Data_An_Cour!$AQ:$AQ,$D38) -> 0
A39: Équipements Service | B39: =SUMIFS(BV_Data_An_Cour!$AN:$AN,BV_Data_An_Cour!$AP:$AP,$A$1,BV_Data_An_Cour!$AQ:$AQ,$A39) -> 366219.78 | D39: [...] | E39: =-SUMIFS(BV_Data_An_Cour!$AN:$AN,BV_Data_An_Cour!$AP:$AP,$A$1,BV_Data_An_Cour!$AQ:$AQ,$D39) -> 0
A40: Mobilier | B40: =SUMIFS(BV_Data_An_Cour!$AN:$AN,BV_Data_An_Cour!$AP:$AP,$A$1,BV_Data_An_Cour!$AQ:$AQ,$A40) -> 52630.74 | D40: [...] | E40: =-SUMIFS(BV_Data_An_Cour!$AN:$AN,BV_Data_An_Cour!$AP:$AP,$A$1,BV_Data_An_Cour!$AQ:$AQ,$D40) -> 0
A41: Équipements Informatique | B41: =SUMIFS(BV_Data_An_Cour!$AN:$AN,BV_Data_An_Cour!$AP:$AP,$A$1,BV_Data_An_Cour!$AQ:$AQ,$A41) -> 66748.34 | D41: [...] | E41: =-SUMIFS(BV_Data_An_Cour!$AN:$AN,BV_Data_An_Cour!$AP:$AP,$A$1,BV_Data_An_Cour!$AQ:$AQ,$D41) -> 0
A42: Équipements Téléphonique | B42: =SUMIFS(BV_Data_An_Cour!$AN:$AN,BV_Data_An_Cour!$AP:$AP,$A$1,BV_Data_An_Cour!$AQ:$AQ,$A42) -> 0 | D42: Total Passif long terme | E42: =+SUM(E33:E38) -> 88167
A43: Enseigne | B43: =SUMIFS(BV_Data_An_Cour!$AN:$AN,BV_Data_An_Cour!$AP:$AP,$A$1,BV_Data_An_Cour!$AQ:$AQ,$A43) -> 6707.1
A44: Total Immobilisations Nettes | B44: =SUM(B35:B43) -> 626265.4
D45: Total Passifs | E45: =+E42+E30 -> 58901174
A46: Avances à Recevoir Long Terme | B46: =SUMIFS(BV_Data_An_Cour!$AN:$AN,BV_Data_An_Cour!$AP:$AP,$A$1,BV_Data_An_Cour!$AQ:$AQ,$A46) -> 14907.15
A48: Achalandage | B48: =SUMIFS(BV_Data_An_Cour!$AN:$AN,BV_Data_An_Cour!$AP:$AP,$A$1,BV_Data_An_Cour!$AQ:$AQ,$A48) -> 0 | D48: Capital Actions | E48: =-SUMIFS(BV_Data_An_Cour!$AN:$AN,BV_Data_An_Cour!$AP:$AP,$A$1,BV_Data_An_Cour!$AQ:$AQ,$D48) -> 236
D49: Apport | E49: =-SUMIFS(BV_Data_An_Cour!$AN:$AN,BV_Data_An_Cour!$AP:$AP,$A$1,BV_Data_An_Cour!$AQ:$AQ,$D49) -> 0
A50: [...] | B50: =SUMIFS(BV_Data_An_Cour!$AN:$AN,BV_Data_An_Cour!$AP:$AP,$A$1,BV_Data_An_Cour!$AQ:$AQ,$A50) -> 0 | D50: Bénéfices non répartis | E50: =-SUMIFS(BV_Data_An_Cour!$AN:$AN,BV_Data_An_Cour!$AP:$AP,$A$1,BV_Data_An_Cour!$AQ:$AQ,$D50)+Print_AAD!AF585 -> 9999245
A51: [...] | B51: =SUMIFS(BV_Data_An_Cour!$AN:$AN,BV_Data_An_Cour!$AP:$AP,$A$1,BV_Data_An_Cour!$AQ:$AQ,$A51) -> 0 | D51: Dividendes | E51: =-SUMIFS(BV_Data_An_Cour!$AN:$AN,BV_Data_An_Cour!$AP:$AP,$A$1,BV_Data_An_Cour!$AQ:$AQ,$D51) -> 0
A52: [...] | B52: =SUMIFS(BV_Data_An_Cour!$AN:$AN,BV_Data_An_Cour!$AP:$AP,$A$1,BV_Data_An_Cour!$AQ:$AQ,$A52) -> 0
A53: Total Actif Long Terme | B53: =+B44+B48+B46 -> 641172.55 | D53: Total Capitaux Propres / Avoir | E53: =SUM(E48:E51) -> 9999481
A56: Total Actif | B56: =+B32+B53 -> 67553358 | D56: Total Passif et Capitaux Propres / Avoir | E56: =+E53+E45 -> 68900655
E65: =+B56-E56 -> -1347297

Sheet Budget original
B1: ="Budget 2024 Mensuel Révisé"&" "&Parametres!$B$1 -> Budget 2024 Mensuel Révisé Ste-Marie Auto
B2: Mois | F2: =+IF(Parametres!$B$3=F$6,"X","") | G2: =+IF(Parametres!$B$3=F$6,"O","") | H2: =+IF(Parametres!$B$3=F$6,"U","") | I2: =+IF(Parametres!$B$3=I$6,"X","") | J2: =+IF(Parametres!$B$3=I$6,"O","") | K2: =+IF(Parametres!$B$3=I$6,"U","") | L2: =+IF(Parametres!$B$3=L$6,"X","") | M2: =+IF(Parametres!$B$3=L$6,"O","") | N2: =+IF(Parametres!$B$3=L$6,"U","") | O2: =+IF(Parametres!$B$3=O$6,"X","") | P2: =+IF(Parametres!$B$3=O$6,"O","") | Q2: =+IF(Parametres!$B$3=O$6,"U","") | R2: =+IF(Parametres!$B$3=R$6,"X","") | S2: =+IF(Parametres!$B$3=R$6,"O","") | T2: =+IF(Parametres!$B$3=R$6,"U","") | U2: =+IF(Parametres!$B$3=U$6,"X","") | V2: =+IF(Parametres!$B$3=U$6,"O","") | W2: =+IF(Parametres!$B$3=U$6,"U","") | X2: =+IF(Parametres!$B$3=X$6,"X","") | Y2: =+IF(Parametres!$B$3=X$6,"O","") | Z2: =+IF(Parametres!$B$3=X$6,"U","") | AA2: =+IF(Parametres!$B$3=AA$6,"X","") | AB2: =+IF(Parametres!$B$3=AA$6,"O","") | AC2: =+IF(Parametres!$B$3=AA$6,"U","") | AD2: =+IF(Parametres!$B$3=AD$6,"X","") | AE2: =+IF(Parametres!$B$3=AD$6,"O","") | AF2: =+IF(Parametres!$B$3=AD$6,"U","") | AG2: =+IF(Parametres!$B$3=AG$6,"X","") | AH2: =+IF(Parametres!$B$3=AG$6,"O","") | AI2: =+IF(Parametres!$B$3=AG$6,"U","") | AJ2: =+IF(Parametres!$B$3=AJ$6,"X","") | AK2: =+IF(Parametres!$B$3=AJ$6,"O","") | AL2: =+IF(Parametres!$B$3=AJ$6,"U","") | AM2: =+IF(Parametres!$B$3=AM$6,"X","") -> X | AN2: =+IF(Parametres!$B$3=AM$6,"O","") -> O | AO2: =+IF(Parametres!$B$3=AM$6,"U","") -> U
B3: YTD | F3: =+IF(VLOOKUP(F$6,Parametres!$K$3:$N$14,4,0)="X","X","") -> X | G3: =+IF(VLOOKUP(F$6,Parametres!$K$3:$N$14,4,0)="X","O","") -> O | H3: =+IF(VLOOKUP(F$6,Parametres!$K$3:$N$14,4,0)="X","U","") -> U | I3: =+IF(VLOOKUP(I$6,Parametres!$K$3:$N$14,4,0)="X","X","") -> X | J3: =+IF(VLOOKUP(I$6,Parametres!$K$3:$N$14,4,0)="X","O","") -> O | K3: =+IF(VLOOKUP(I$6,Parametres!$K$3:$N$14,4,0)="X","U","") -> U | L3: =+IF(VLOOKUP(L$6,Parametres!$K$3:$N$14,4,0)="X","X","") -> X | M3: =+IF(VLOOKUP(L$6,Parametres!$K$3:$N$14,4,0)="X","O","") -> O | N3: =+IF(VLOOKUP(L$6,Parametres!$K$3:$N$14,4,0)="X","U","") -> U | O3: =+IF(VLOOKUP(O$6,Parametres!$K$3:$N$14,4,0)="X","X","") -> X | P3: =+IF(VLOOKUP(O$6,Parametres!$K$3:$N$14,4,0)="X","O","") -> O | Q3: =+IF(VLOOKUP(O$6,Parametres!$K$3:$N$14,4,0)="X","U","") -> U | R3: =+IF(VLOOKUP(R$6,Parametres!$K$3:$N$14,4,0)="X","X","") -> X | S3: =+IF(VLOOKUP(R$6,Parametres!$K$3:$N$14,4,0)="X","O","") -> O | T3: =+IF(VLOOKUP(R$6,Parametres!$K$3:$N$14,4,0)="X","U","") -> U | U3: =+IF(VLOOKUP(U$6,Parametres!$K$3:$N$14,4,0)="X","X","") -> X | V3: =+IF(VLOOKUP(U$6,Parametres!$K$3:$N$14,4,0)="X","O","") -> O | W3: =+IF(VLOOKUP(U$6,Parametres!$K$3:$N$14,4,0)="X","U","") -> U | X3: =+IF(VLOOKUP(X$6,Parametres!$K$3:$N$14,4,0)="X","X","") -> X | Y3: =+IF(VLOOKUP(X$6,Parametres!$K$3:$N$14,4,0)="X","O","") -> O | Z3: =+IF(VLOOKUP(X$6,Parametres!$K$3:$N$14,4,0)="X","U","") -> U | AA3: =+IF(VLOOKUP(AA$6,Parametres!$K$3:$N$14,4,0)="X","X","") -> X | AB3: =+IF(VLOOKUP(AA$6,Parametres!$K$3:$N$14,4,0)="X","O","") -> O | AC3: =+IF(VLOOKUP(AA$6,Parametres!$K$3:$N$14,4,0)="X","U","") -> U | AD3: =+IF(VLOOKUP(AD$6,Parametres!$K$3:$N$14,4,0)="X","X","") -> X | AE3: =+IF(VLOOKUP(AD$6,Parametres!$K$3:$N$14,4,0)="X","O","") -> O | AF3: =+IF(VLOOKUP(AD$6,Parametres!$K$3:$N$14,4,0)="X","U","") -> U | AG3: =+IF(VLOOKUP(AG$6,Parametres!$K$3:$N$14,4,0)="X","X","") -> X | AH3: =+IF(VLOOKUP(AG$6,Parametres!$K$3:$N$14,4,0)="X","O","") -> O | AI3: =+IF(VLOOKUP(AG$6,Parametres!$K$3:$N$14,4,0)="X","U","") -> U | AJ3: =+IF(VLOOKUP(AJ$6,Parametres!$K$3:$N$14,4,0)="X","X","") -> X | AK3: =+IF(VLOOKUP(AJ$6,Parametres!$K$3:$N$14,4,0)="X","O","") -> O | AL3: =+IF(VLOOKUP(AJ$6,Parametres!$K$3:$N$14,4,0)="X","U","") -> U | AM3: =+IF(VLOOKUP(AM$6,Parametres!$K$3:$N$14,4,0)="X","X","") -> X | AN3: =+IF(VLOOKUP(AM$6,Parametres!$K$3:$N$14,4,0)="X","O","") -> O | AO3: =+IF(VLOOKUP(AM$6,Parametres!$K$3:$N$14,4,0)="X","U","") -> U
B4: Budget 2025 | C4: Véhicules neufs
B6: Mois | C6: TOTAL | F6: Janvier | I6: Février | L6: Mars | O6: Avril | R6: Mai | U6: Juin | X6: Juillet | AA6: Août | AD6: Septembre | AG6: Octobre | AJ6: Novembre | AM6: Décembre
C7: UNITE | D7: $P/UNITE | E7: $PROFITS | F7: UNITE | G7: $P/UNITE | H7: $PROFITS | I7: UNITE | J7: $P/UNITE | K7: $PROFITS | L7: UNITE | M7: $P/UNITE | N7: $PROFITS | O7: UNITE | P7: $P/UNITE | Q7: $PROFITS | R7: UNITE | S7: $P/UNITE | T7: $PROFITS | U7: UNITE | V7: $P/UNITE | W7: $PROFITS | X7: UNITE | Y7: $P/UNITE | Z7: $PROFITS | AA7: UNITE | AB7: $P/UNITE | AC7: $PROFITS | AD7: UNITE | AE7: $P/UNITE | AF7: $PROFITS | AG7: UNITE | AH7: $P/UNITE | AI7: $PROFITS | AJ7: UNITE | AK7: $P/UNITE | AL7: $PROFITS | AM7: UNITE | AN7: $P/UNITE | AO7: $PROFITS
A8: =+$C$4&B8 -> Véhicules neufsVentes nettes | B8: Ventes nettes
A9: =+$C$4&B9 -> Véhicules neufsAutos détail | B9: Autos détail
A10: =+$C$4&B10 -> Véhicules neufsCamions détail | B10: Camions détail
A11: =+$C$4&B11 -> Véhicules neufsSprinter | B11: Sprinter
A12: =+$C$4&B12 -> Véhicules neufsMoto détail | B12: Moto détail
A13: =+$C$4&B13 -> Véhicules neufs[...] | B13: [...]
A14: =+$C$4&B14 -> Véhicules neufs[...] | B14: [...]
A15: =+$C$4&B15 -> Véhicules neufs[...] | B15: [...]
A16: =+$C$4&B16 -> Véhicules neufsTotal Neufs | B16: Total Neufs
A17: =+$C$4&B17 -> Véhicules neufs
A18: =+$C$4&B18 -> Véhicules neufsEx-Démos et courtoisies | B18: Ex-Démos et courtoisies
A19: =+$C$4&B19 -> Véhicules neufs
A20: =+$C$4&B20 -> Véhicules neufsFlottes | B20: Flottes
A21: =+$C$4&B21 -> Véhicules neufs
A22: =+$C$4&B22 -> Véhicules neufsRachat bail | B22: Rachat bail
A23: =+$C$4&B23 -> Véhicules neufs
A24: =+$C$4&B24 -> Véhicules neufsRev. Finances | B24: Rev. Finances
A25: =+$C$4&B25 -> Véhicules neufsRev. Protections | B25: Rev. Protections
A26: =+$C$4&B26 -> Véhicules neufsRev. Autres | B26: Rev. Autres
A27: =+$C$4&B27 -> Véhicules neufsTotal F&I | B27: Total F&I
A28: =+$C$4&B28 -> Véhicules neufs
A29: =+$C$4&B29 -> Véhicules neufs
A30: =+$C$4&B30 -> Véhicules neufsTotal Dépt. Neufs | B30: Total Dépt. Neufs
A31: =+$C$4&B31 -> Véhicules neufs
A32: =+$C$4&B32 -> Véhicules neufs
A33: =+$C$4&B33 -> Véhicules neufsDEPENSES | B33: DEPENSES
A34: =+$C$4&B34 -> Véhicules neufsComm. vendeurs | B34: Comm. vendeurs
A35: =+$C$4&B35 -> Véhicules neufsComm. F&I | B35: Comm. F&I
A36: =+$C$4&B36 -> Véhicules neufsFrais de livraison | B36: Frais de livraison
A37: =+$C$4&B37 -> Véhicules neufsService gratuit 1 | B37: Service gratuit 1
A38: =+$C$4&B38 -> Véhicules neufsEntretien stock | B38: Entretien stock
A39: =+$C$4&B39 -> Véhicules neufsPublicité 1 | B39: Publicité 1
A40: =+$C$4&B40 -> Véhicules neufsIntérêt de gros | B40: Intérêt de gros
A41: =+$C$4&B41 -> Véhicules neufs[...] | B41: [...]
A42: =+$C$4&B42 -> Véhicules neufs[...] | B42: [...]
A43: =+$C$4&B43 -> Véhicules neufs[...] | B43: [...]
A44: =+$C$4&B44 -> Véhicules neufsTOTAL VARIABLES | B44: TOTAL VARIABLES
... A75: =+$C$4&B75 -> Véhicules neufsTOTAL SEMI-FIXES | B75: TOTAL SEMI-FIXES
A76: =+$C$4&B76 -> Véhicules neufs
A77: =+$C$4&B77 -> Véhicules neufsTOTAL DES DÉPENSES | B77: TOTAL DES DÉPENSES
A78: =+$C$4&B78 -> Véhicules neufsProgramme neuf 1 | B78: Programme neuf 1
A79: =+$C$4&B79 -> Véhicules neufsProgramme neuf 2 | B79: Programme neuf 2
A80: =+$C$4&B80 -> Véhicules neufsProgramme neuf 3 | B80: Programme neuf 3
A81: =+$C$4&B81 -> Véhicules neufsHoldbacks | B81: Holdbacks
A82: =+$C$4&B82 -> Véhicules neufs[...] | B82: [...]
A83: =+$C$4&B83 -> Véhicules neufs[...] | B83: [...]
A84: =+$C$4&B84 -> Véhicules neufs[...] | B84: [...]
A85: =+$C$4&B85 -> Véhicules neufsFrais administration | B85: Frais administration
A86: =+$C$4&B86 -> Véhicules neufsAUTRES REVENUS | B86: AUTRES REVENUS
A87: =+$C$4&B87 -> Véhicules neufs
A88: =+$C$4&B88 -> Véhicules neufsPROFIT DÉPARTEMENTAL | B88: PROFIT DÉPARTEMENTAL
B92: =B4 -> Budget 2025 | C92: Véhicules usagés
B94: Mois | C94: 2021 | F94: Janvier | I94: Février | L94: Mars | O94: Avril | R94: Mai | U94: Juin | X94: Juillet | AA94: Août | AD94: Septembre | AG94: Octobre | AJ94: Novembre | AM94: Décembre
C95: UNITE | D95: $P/UNITE | E95: $PROFITS | F95: UNITE | G95: $P/UNITE | H95: $PROFITS | I95: UNITE | J95: $P/UNITE | K95: $PROFITS | L95: UNITE | M95: $P/UNITE | N95: $PROFITS | O95: UNITE | P95: $P/UNITE | Q95: $PROFITS | R95: UNITE | S95: $P/UNITE | T95: $PROFITS | U95: UNITE | V95: $P/UNITE | W95: $PROFITS | X95: UNITE | Y95: $P/UNITE | Z95: $PROFITS | AA95: UNITE | AB95: $P/UNITE | AC95: $PROFITS | AD95: UNITE | AE95: $P/UNITE | AF95: $PROFITS | AG95: UNITE | AH95: $P/UNITE | AI95: $PROFITS | AJ95: UNITE | AK95: $P/UNITE | AL95: $PROFITS | AM95: UNITE | AN95: $P/UNITE | AO95: $PROFITS
A96: =+$C$92&B96 -> Véhicules usagésVentes nettes | B96: Ventes nettes
A97: =+$C$92&B97 -> Véhicules usagésCertifié | B97: Certifié
A98: =+$C$92&B98 -> Véhicules usagésNon Certifié | B98: Non Certifié
A99: =+$C$92&B99 -> Véhicules usagésAutres Marques | B99: Autres Marques
A100: =+$C$92&B100 -> Véhicules usagésTotal Usagés | B100: Total Usagés
A101: =+$C$92&B101 -> Véhicules usagés
A102: =+$C$92&B102 -> Véhicules usagés
A103: =+$C$92&B103 -> Véhicules usagésVentes au Gros | B103: Ventes au Gros
A104: =+$C$92&B104 -> Véhicules usagés
A105: =+$C$92&B105 -> Véhicules usagésRev. Finances | B105: Rev. Finances
A106: =+$C$92&B106 -> Véhicules usagésRev. Protections | B106: Rev. Protections
A107: =+$C$92&B107 -> Véhicules usagésRev. Autres | B107: Rev. Autres
A108: =+$C$92&B108 -> Véhicules usagésTotal F&I | B108: Total F&I
A109: =+$C$92&B109 -> Véhicules usagés
A110: =+$C$92&B110 -> Véhicules usagés
A111: =+$C$92&B111 -> Véhicules usagésTotal Dépt. Usagés | B111: Total Dépt. Usagés
A112: =+$C$92&B112 -> Véhicules usagés
A113: =+$C$92&B113 -> Véhicules usagés
A114: =+$C$92&B114 -> Véhicules usagésDEPENSES | B114: DEPENSES
A115: =+$C$92&B115 -> Véhicules usagésComm. vendeurs | B115: Comm. vendeurs
A116: =+$C$92&B116 -> Véhicules usagésComm. F&I | B116: Comm. F&I
A117: =+$C$92&B117 -> Véhicules usagésFrais de livraison | B117: Frais de livraison
A118: =+$C$92&B118 -> Véhicules usagésService gratuit 1 | B118: Service gratuit 1
A119: =+$C$92&B119 -> Véhicules usagésEntretien stock | B119: Entretien stock
A120: =+$C$92&B120 -> Véhicules usagésPublicité 1 | B120: Publicité 1
A121: =+$C$92&B121 -> Véhicules usagésIntérêt de gros | B121: Intérêt de gros
A122: =+$C$92&B122 -> Véhicules usagés[...] | B122: [...]
A123: =+$C$92&B123 -> Véhicules usagés[...] | B123: [...]
A124: =+$C$92&B124 -> Véhicules usagés[...] | B124: [...]
A125: =+$C$92&B125 -> Véhicules usagésTOTAL VARIABLES | B125: TOTAL VARIABLES
... A156: =+$C$92&B156 -> Véhicules usagésTOTAL SEMI-FIXES | B156: TOTAL SEMI-FIXES
A157: =+$C$92&B157 -> Véhicules usagés
A158: =+$C$92&B158 -> Véhicules usagésTOTAL DES DÉPENSES | B158: TOTAL DES DÉPENSES
A159: =+$C$92&B159 -> Véhicules usagésProgramme used 1 | B159: Programme used 1
A160: =+$C$92&B160 -> Véhicules usagésProgramme used 2 | B160: Programme used 2
A161: =+$C$92&B161 -> Véhicules usagésProgramme used 3 | B161: Programme used 3
A162: =+$C$92&B162 -> Véhicules usagés[...] | B162: [...]
A163: =+$C$92&B163 -> Véhicules usagés[...] | B163: [...]
A164: =+$C$92&B164 -> Véhicules usagés[...] | B164: [...]
A165: =+$C$92&B165 -> Véhicules usagésFrais administration | B165: Frais administration
...

Sheet Réel 2024
B1: ="Réel 2023 Mensuel Révisé"&" "&Parametres!$B$1 -> Réel 2023 Mensuel Révisé Ste-Marie Auto
B2: Mois | F2: =+IF(Parametres!$B$3=F$6,"X","") | G2: =+IF(Parametres!$B$3=F$6,"O","") | H2: =+IF(Parametres!$B$3=F$6,"U","") | I2: =+IF(Parametres!$B$3=I$6,"X","") | J2: =+IF(Parametres!$B$3=I$6,"O","") | K2: =+IF(Parametres!$B$3=I$6,"U","") | L2: =+IF(Parametres!$B$3=L$6,"X","") | M2: =+IF(Parametres!$B$3=L$6,"O","") | N2: =+IF(Parametres!$B$3=L$6,"U","") | O2: =+IF(Parametres!$B$3=O$6,"X","") | P2: =+IF(Parametres!$B$3=O$6,"O","") | Q2: =+IF(Parametres!$B$3=O$6,"U","") | R2: =+IF(Parametres!$B$3=R$6,"X","") | S2: =+IF(Parametres!$B$3=R$6,"O","") | T2: =+IF(Parametres!$B$3=R$6,"U","") | U2: =+IF(Parametres!$B$3=U$6,"X","") | V2: =+IF(Parametres!$B$3=U$6,"O","") | W2: =+IF(Parametres!$B$3=U$6,"U","") | X2: =+IF(Parametres!$B$3=X$6,"X","") | Y2: =+IF(Parametres!$B$3=X$6,"O","") | Z2: =+IF(Parametres!$B$3=X$6,"U","") | AA2: =+IF(Parametres!$B$3=AA$6,"X","") | AB2: =+IF(Parametres!$B$3=AA$6,"O","") | AC2: =+IF(Parametres!$B$3=AA$6,"U","") | AD2: =+IF(Parametres!$B$3=AD$6,"X","") | AE2: =+IF(Parametres!$B$3=AD$6,"O","") | AF2: =+IF(Parametres!$B$3=AD$6,"U","") | AG2: =+IF(Parametres!$B$3=AG$6,"X","") | AH2: =+IF(Parametres!$B$3=AG$6,"O","") | AI2: =+IF(Parametres!$B$3=AG$6,"U","") | AJ2: =+IF(Parametres!$B$3=AJ$6,"X","") | AK2: =+IF(Parametres!$B$3=AJ$6,"O","") | AL2: =+IF(Parametres!$B$3=AJ$6,"U","") | AM2: =+IF(Parametres!$B$3=AM$6,"X","") -> X | AN2: =+IF(Parametres!$B$3=AM$6,"O","") -> O | AO2: =+IF(Parametres!$B$3=AM$6,"U","") -> U
B3: YTD | F3: =+IF(VLOOKUP(F$6,Parametres!$K$3:$N$14,4,0)="X","X","") -> X | G3: =+IF(VLOOKUP(F$6,Parametres!$K$3:$N$14,4,0)="X","O","") -> O | H3: =+IF(VLOOKUP(F$6,Parametres!$K$3:$N$14,4,0)="X","U","") -> U | I3: =+IF(VLOOKUP(I$6,Parametres!$K$3:$N$14,4,0)="X","X","") -> X | J3: =+IF(VLOOKUP(I$6,Parametres!$K$3:$N$14,4,0)="X","O","") -> O | K3: =+IF(VLOOKUP(I$6,Parametres!$K$3:$N$14,4,0)="X","U","") -> U | L3: =+IF(VLOOKUP(L$6,Parametres!$K$3:$N$14,4,0)="X","X","") -> X | M3: =+IF(VLOOKUP(L$6,Parametres!$K$3:$N$14,4,0)="X","O","") -> O | N3: =+IF(VLOOKUP(L$6,Parametres!$K$3:$N$14,4,0)="X","U","") -> U | O3: =+IF(VLOOKUP(O$6,Parametres!$K$3:$N$14,4,0)="X","X","") -> X | P3: =+IF(VLOOKUP(O$6,Parametres!$K$3:$N$14,4,0)="X","O","") -> O | Q3: =+IF(VLOOKUP(O$6,Parametres!$K$3:$N$14,4,0)="X","U","") -> U | R3: =+IF(VLOOKUP(R$6,Parametres!$K$3:$N$14,4,0)="X","X","") -> X | S3: =+IF(VLOOKUP(R$6,Parametres!$K$3:$N$14,4,0)="X","O","") -> O | T3: =+IF(VLOOKUP(R$6,Parametres!$K$3:$N$14,4,0)="X","U","") -> U | U3: =+IF(VLOOKUP(U$6,Parametres!$K$3:$N$14,4,0)="X","X","") -> X | V3: =+IF(VLOOKUP(U$6,Parametres!$K$3:$N$14,4,0)="X","O","") -> O | W3: =+IF(VLOOKUP(U$6,Parametres!$K$3:$N$14,4,0)="X","U","") -> U | X3: =+IF(VLOOKUP(X$6,Parametres!$K$3:$N$14,4,0)="X","X","") -> X | Y3: =+IF(VLOOKUP(X$6,Parametres!$K$3:$N$14,4,0)="X","O","") -> O | Z3: =+IF(VLOOKUP(X$6,Parametres!$K$3:$N$14,4,0)="X","U","") -> U | AA3: =+IF(VLOOKUP(AA$6,Parametres!$K$3:$N$14,4,0)="X","X","") -> X | AB3: =+IF(VLOOKUP(AA$6,Parametres!$K$3:$N$14,4,0)="X","O","") -> O | AC3: =+IF(VLOOKUP(AA$6,Parametres!$K$3:$N$14,4,0)="X","U","") -> U | AD3: =+IF(VLOOKUP(AD$6,Parametres!$K$3:$N$14,4,0)="X","X","") -> X | AE3: =+IF(VLOOKUP(AD$6,Parametres!$K$3:$N$14,4,0)="X","O","") -> O | AF3: =+IF(VLOOKUP(AD$6,Parametres!$K$3:$N$14,4,0)="X","U","") -> U | AG3: =+IF(VLOOKUP(AG$6,Parametres!$K$3:$N$14,4,0)="X","X","") -> X | AH3: =+IF(VLOOKUP(AG$6,Parametres!$K$3:$N$14,4,0)="X","O","") -> O | AI3: =+IF(VLOOKUP(AG$6,Parametres!$K$3:$N$14,4,0)="X","U","") -> U | AJ3: =+IF(VLOOKUP(AJ$6,Parametres!$K$3:$N$14,4,0)="X","X","") -> X | AK3: =+IF(VLOOKUP(AJ$6,Parametres!$K$3:$N$14,4,0)="X","O","") -> O | AL3: =+IF(VLOOKUP(AJ$6,Parametres!$K$3:$N$14,4,0)="X","U","") -> U | AM3: =+IF(VLOOKUP(AM$6,Parametres!$K$3:$N$14,4,0)="X","X","") -> X | AN3: =+IF(VLOOKUP(AM$6,Parametres!$K$3:$N$14,4,0)="X","O","") -> O | AO3: =+IF(VLOOKUP(AM$6,Parametres!$K$3:$N$14,4,0)="X","U","") -> U
B4: Réel 2024 | C4: Véhicules neufs
B6: Mois | C6: 2024 | F6: Janvier | I6: Février | L6: Mars | O6: Avril | R6: Mai | U6: Juin | X6: Juillet | AA6: Août | AD6: Septembre | AG6: Octobre | AJ6: Novembre | AM6: Décembre
C7: UNITE | D7: $P/UNITE | E7: $PROFITS | F7: UNITE | G7: $P/UNITE | H7: $PROFITS | I7: UNITE | J7: $P/UNITE | K7: $PROFITS | L7: UNITE | M7: $P/UNITE | N7: $PROFITS | O7: UNITE | P7: $P/UNITE | Q7: $PROFITS | R7: UNITE | S7: $P/UNITE | T7: $PROFITS | U7: UNITE | V7: $P/UNITE | W7: $PROFITS | X7: UNITE | Y7: $P/UNITE | Z7: $PROFITS | AA7: UNITE | AB7: $P/UNITE | AC7: $PROFITS | AD7: UNITE | AE7: $P/UNITE | AF7: $PROFITS | AG7: UNITE | AH7: $P/UNITE | AI7: $PROFITS | AJ7: UNITE | AK7: $P/UNITE | AL7: $PROFITS | AM7: UNITE | AN7: $P/UNITE | AO7: $PROFITS
A8: =+$C$4&B8 -> Véhicules neufsVentes nettes | B8: Ventes nettes
A9: =+$C$4&B9 -> Véhicules neufsAutos détail | B9: Autos détail
A10: =+$C$4&B10 -> Véhicules neufsCamions détail | B10: Camions détail
A11: =+$C$4&B11 -> Véhicules neufsSprinter | B11: Sprinter
A12: =+$C$4&B12 -> Véhicules neufsMoto détail | B12: Moto détail
A13: =+$C$4&B13 -> Véhicules neufs[...] | B13: [...]
A14: =+$C$4&B14 -> Véhicules neufs[...] | B14: [...]
A15: =+$C$4&B15 -> Véhicules neufs[...] | B15: [...]
A16: =+$C$4&B16 -> Véhicules neufsTotal Neufs | B16: Total Neufs
A17: =+$C$4&B17 -> Véhicules neufs
A18: =+$C$4&B18 -> Véhicules neufsEx-Démos et courtoisies | B18: Ex-Démos et courtoisies
A19: =+$C$4&B19 -> Véhicules neufs
A20: =+$C$4&B20 -> Véhicules neufsFlottes | B20: Flottes
A21: =+$C$4&B21 -> Véhicules neufs
A22: =+$C$4&B22 -> Véhicules neufsRachat bail | B22: Rachat bail
A23: =+$C$4&B23 -> Véhicules neufs
A24: =+$C$4&B24 -> Véhicules neufsRev. Finances | B24: Rev. Finances
A25: =+$C$4&B25 -> Véhicules neufsRev. Protections | B25: Rev. Protections
A26: =+$C$4&B26 -> Véhicules neufsRev. Autres | B26: Rev. Autres
A27: =+$C$4&B27 -> Véhicules neufsTotal F&I | B27: Total F&I
A28: =+$C$4&B28 -> Véhicules neufs
A29: =+$C$4&B29 -> Véhicules neufs
A30: =+$C$4&B30 -> Véhicules neufsTotal Dépt. Neufs | B30: Total Dépt. Neufs
A31: =+$C$4&B31 -> Véhicules neufs
A32: =+$C$4&B32 -> Véhicules neufs
A33: =+$C$4&B33 -> Véhicules neufsDEPENSES | B33: DEPENSES
A34: =+$C$4&B34 -> Véhicules neufsComm. vendeurs | B34: Comm. vendeurs
A35: =+$C$4&B35 -> Véhicules neufsComm. F&I | B35: Comm. F&I
A36: =+$C$4&B36 -> Véhicules neufsFrais de livraison | B36: Frais de livraison
A37: =+$C$4&B37 -> Véhicules neufsService gratuit 1 | B37: Service gratuit 1
A38: =+$C$4&B38 -> Véhicules neufsEntretien stock | B38: Entretien stock
A39: =+$C$4&B39 -> Véhicules neufsPublicité 1 | B39: Publicité 1
A40: =+$C$4&B40 -> Véhicules neufsIntérêt de gros | B40: Intérêt de gros
A41: =+$C$4&B41 -> Véhicules neufs[...] | B41: [...]
A42: =+$C$4&B42 -> Véhicules neufs[...] | B42: [...]
A43: =+$C$4&B43 -> Véhicules neufs[...] | B43: [...]
A44: =+$C$4&B44 -> Véhicules neufsTOTAL VARIABLES | B44: TOTAL VARIABLES
... A75: =+$C$4&B75 -> Véhicules neufsTOTAL SEMI-FIXES | B75: TOTAL SEMI-FIXES
A76: =+$C$4&B76 -> Véhicules neufs
A77: =+$C$4&B77 -> Véhicules neufsTOTAL DES DÉPENSES | B77: TOTAL DES DÉPENSES
A78: =+$C$4&B78 -> Véhicules neufsProgramme neuf 1 | B78: Programme neuf 1
A79: =+$C$4&B79 -> Véhicules neufsProgramme neuf 2 | B79: Programme neuf 2
A80: =+$C$4&B80 -> Véhicules neufsProgramme neuf 3 | B80: Programme neuf 3
A81: =+$C$4&B81 -> Véhicules neufsHoldbacks | B81: Holdbacks
A82: =+$C$4&B82 -> Véhicules neufs[...] | B82: [...]
A83: =+$C$4&B83 -> Véhicules neufs[...] | B83: [...]
A84: =+$C$4&B84 -> Véhicules neufs[...] | B84: [...]
A85: =+$C$4&B85 -> Véhicules neufsFrais administration | B85: Frais administration
A86: =+$C$4&B86 -> Véhicules neufsAUTRES REVENUS | B86: AUTRES REVENUS
A87: =+$C$4&B87 -> Véhicules neufs
A88: =+$C$4&B88 -> Véhicules neufsPROFIT DÉPARTEMENTAL | B88: PROFIT DÉPARTEMENTAL
B92: Réel 2024 | C92: Véhicules usagés
B94: Mois | C94: 2025 | F94: Janvier | I94: Février | L94: Mars | O94: Avril | R94: Mai | U94: Juin | X94: Juillet | AA94: Août | AD94: Septembre | AG94: Octobre | AJ94: Novembre | AM94: Décembre
C95: UNITE | D95: $P/UNITE | E95: $PROFITS | F95: UNITE | G95: $P/UNITE | H95: $PROFITS | I95: UNITE | J95: $P/UNITE | K95: $PROFITS | L95: UNITE | M95: $P/UNITE | N95: $PROFITS | O95: UNITE | P95: $P/UNITE | Q95: $PROFITS | R95: UNITE | S95: $P/UNITE | T95: $PROFITS | U95: UNITE | V95: $P/UNITE | W95: $PROFITS | X95: UNITE | Y95: $P/UNITE | Z95: $PROFITS | AA95: UNITE | AB95: $P/UNITE | AC95: $PROFITS | AD95: UNITE | AE95: $P/UNITE | AF95: $PROFITS | AG95: UNITE | AH95: $P/UNITE | AI95: $PROFITS | AJ95: UNITE | AK95: $P/UNITE | AL95: $PROFITS | AM95: UNITE | AN95: $P/UNITE | AO95: $PROFITS
A96: =+$C$92&B96 -> Véhicules usagésVentes nettes | B96: Ventes nettes
A97: =+$C$92&B97 -> Véhicules usagésCertifié | B97: Certifié
A98: =+$C$92&B98 -> Véhicules usagésNon Certifié | B98: Non Certifié
A99: =+$C$92&B99 -> Véhicules usagésAutres Marques | B99: Autres Marques
A100: =+$C$92&B100 -> Véhicules usagésTotal Usagés | B100: Total Usagés
A101: =+$C$92&B101 -> Véhicules usagés
A102: =+$C$92&B102 -> Véhicules usagés
A103: =+$C$92&B103 -> Véhicules usagésVentes au Gros | B103: Ventes au Gros
A104: =+$C$92&B104 -> Véhicules usagés
A105: =+$C$92&B105 -> Véhicules usagésRev. Finances | B105: Rev. Finances
A106: =+$C$92&B106 -> Véhicules usagésRev. Protections | B106: Rev. Protections
A107: =+$C$92&B107 -> Véhicules usagésRev. Autres | B107: Rev. Autres
A108: =+$C$92&B108 -> Véhicules usagésTotal F&I | B108: Total F&I
A109: =+$C$92&B109 -> Véhicules usagés
A110: =+$C$92&B110 -> Véhicules usagés
A111: =+$C$92&B111 -> Véhicules usagésTotal Dépt. Usagés | B111: Total Dépt. Usagés
A112: =+$C$92&B112 -> Véhicules usagés
A113: =+$C$92&B113 -> Véhicules usagés
A114: =+$C$92&B114 -> Véhicules usagésDEPENSES | B114: DEPENSES
A115: =+$C$92&B115 -> Véhicules usagésComm. vendeurs | B115: Comm. vendeurs
A116: =+$C$92&B116 -> Véhicules usagésComm. F&I | B116: Comm. F&I
A117: =+$C$92&B117 -> Véhicules usagésFrais de livraison | B117: Frais de livraison
A118: =+$C$92&B118 -> Véhicules usagésService gratuit 1 | B118: Service gratuit 1
A119: =+$C$92&B119 -> Véhicules usagésEntretien stock | B119: Entretien stock
A120: =+$C$92&B120 -> Véhicules usagésPublicité 1 | B120: Publicité 1
A121: =+$C$92&B121 -> Véhicules usagésIntérêt de gros | B121: Intérêt de gros
A122: =+$C$92&B122 -> Véhicules usagés[...] | B122: [...]
A123: =+$C$92&B123 -> Véhicules usagés[...] | B123: [...]
A124: =+$C$92&B124 -> Véhicules usagés[...] | B124: [...]
A125: =+$C$92&B125 -> Véhicules usagésTOTAL VARIABLES | B125: TOTAL VARIABLES
... A156: =+$C$92&B156 -> Véhicules usagésTOTAL SEMI-FIXES | B156: TOTAL SEMI-FIXES
A157: =+$C$92&B157 -> Véhicules usagés
A158: =+$C$92&B158 -> Véhicules usagésTOTAL DES DÉPENSES | B158: TOTAL DES DÉPENSES
A159: =+$C$92&B159 -> Véhicules usagésProgramme used 1 | B159: Programme used 1
A160: =+$C$92&B160 -> Véhicules usagésProgramme used 2 | B160: Programme used 2
A161: =+$C$92&B161 -> Véhicules usagésProgramme used 3 | B161: Programme used 3
A162: =+$C$92&B162 -> Véhicules usagés
A163: =+$C$92&B163 -> Véhicules usagés[...] | B163: [...]
A164: =+$C$92&B164 -> Véhicules usagés[...] | B164: [...]
A165: =+$C$92&B165 -> Véhicules usagésFrais administration | B165: Frais administration
...

Sheet Capex
A1: PARK AVENUE VOLKSWAGEN | B1: PARK AVENUE VOLKSWAGEN
A2: Forecast Immobilisation 2022 | B2: Forecast Immobilisation 2025 | H2: 1 | I2: 2 | J2: 3 | K2: 4 | L2: 5 | M2: 6 | N2: 7 | O2: 8 | P2: 9 | Q2: 10 | R2: 11 | S2: 12
H3: =+IF(VLOOKUP(H2,Parametres!$L$3:$N$14,3,0)="X","REEL","FORECAST") -> REEL | I3: =+IF(VLOOKUP(I2,Parametres!$L$3:$N$14,3,0)="X","REEL","FORECAST") -> REEL | J3: =+IF(VLOOKUP(J2,Parametres!$L$3:$N$14,3,0)="X","REEL","FORECAST") -> REEL | K3: =+IF(VLOOKUP(K2,Parametres!$L$3:$N$14,3,0)="X","REEL","FORECAST") -> REEL | L3: =+IF(VLOOKUP(L2,Parametres!$L$3:$N$14,3,0)="X","REEL","FORECAST") -> REEL | M3: =+IF(VLOOKUP(M2,Parametres!$L$3:$N$14,3,0)="X","REEL","FORECAST") -> REEL | N3: =+IF(VLOOKUP(N2,Parametres!$L$3:$N$14,3,0)="X","REEL","FORECAST") -> REEL | O3: =+IF(VLOOKUP(O2,Parametres!$L$3:$N$14,3,0)="X","REEL","FORECAST") -> REEL | ... S3: =+IF(VLOOKUP(S2,Parametres!$L$3:$N$14,3,0)="X","REEL","FORECAST") -> REEL
A4: Concession | B4: Budgété / Non budgété | C4: Projet | D4: Catégorie Immo | E4: Total forecast | F4: Budget Annuel | G4: Écart vs budget | H4: January | I4: February | J4: March | K4: April | L4: May | M4: June | N4: July | O4: August | P4: September | Q4: October | R4: November | S4: December | T4: Raison / Description
C5: Total | E5: =+SUM(E6:E20) -> 30931.3 | F5: =+SUM(F6:F20) -> 40000 | G5: =+SUM(G6:G20) -> -9068.7 | H5: =+SUM(H6:H20) -> 30931.3 | I5: =+SUM(I6:I20) -> 0 | J5: =+SUM(J6:J20) -> 0 | K5: =+SUM(K6:K20) -> 0 | L5: =+SUM(L6:L20) -> 0 | ... S5: =+SUM(S6:S20) -> 0 | X5: Terrain
A6: =+Parametres!$B$1 -> Ste-Marie Auto | B6: oui | C6: Outils Spécialisés Volks | E6: =+SUM(H6:S6) -> 0 | F6: 40000 | G6: =+E6-F6 -> -40000 | X6: Bâtisse
A7: =+Parametres!$B$1 -> Ste-Marie Auto | B7: non | C7: Équipement informatique | E7: =+SUM(H7:S7) -> 0 | G7: =+E7-F7 -> 0 | X7: Améliorations Locatives
A8: =+Parametres!$B$1 -> Ste-Marie Auto | C8: Nouveau building | E8: =+SUM(H8:S8) -> 30931.3 | G8: =+E8-F8 -> 30931.3 | H8: 30931.3 | X8: Mobilier
A9: =+Parametres!$B$1 -> Ste-Marie Auto | E9: =+SUM(H9:S9) -> 0 | G9: =+E9-F9 -> 0 | X9: Équipements Informatique
A10: =+Parametres!$B$1 -> Ste-Marie Auto | E10: =+SUM(H10:S10) -> 0 | G10: =+E10-F10 -> 0 | X10: Équipements Téléphonique
A11: =+Parametres!$B$1 -> Ste-Marie Auto | E11: =+SUM(H11:S11) -> 0 | G11: =+E11-F11 -> 0 | X11: Enseigne
A12: =+Parametres!$B$1 -> Ste-Marie Auto | E12: =+SUM(H12:S12) -> 0 | G12: =+E12-F12 -> 0
A13: =+Parametres!$B$1 -> Ste-Marie Auto | E13: =+SUM(H13:S13) -> 0 | G13: =+E13-F13 -> 0
A14: =+Parametres!$B$1 -> Ste-Marie Auto | E14: =+SUM(H14:S14) -> 0 | G14: =+E14-F14 -> 0
A15: =+Parametres!$B$1 -> Ste-Marie Auto | E15: =+SUM(H15:S15) -> 0 | G15: =+E15-F15 -> 0
A16: =+Parametres!$B$1 -> Ste-Marie Auto | E16: =+SUM(H16:S16) -> 0 | G16: =+E16-F16 -> 0
A17: =+Parametres!$B$1 -> Ste-Marie Auto | E17: =+SUM(H17:S17) -> 0 | G17: =+E17-F17 -> 0 | X17: non
A18: =+Parametres!$B$1 -> Ste-Marie Auto | E18: =+SUM(H18:S18) -> 0 | G18: =+E18-F18 -> 0
A19: =+Parametres!$B$1 -> Ste-Marie Auto | E19: =+SUM(H19:S19) -> 0 | G19: =+E19-F19 -> 0
A20: =+Parametres!$B$1 -> Ste-Marie Auto | E20: =+SUM(H20:S20) -> 0 | G20: =+E20-F20 -> 0

Sheet Inventaire_Used
A1: #Contrôle | B1: Année | C1: Marque | D1: Modèle | E1: 1416 | F1: 2103 | G1: NIV | H1: Jours en stock | M1: 45169 | N1: $ Inventaire | O1: $ Financé
A2: 5291P | B2: 2020 | C2: VOLKSWAGEN | D2: E-GOLF | E2: 32007.51 | F2: -22494.36 | G2: WVWPR7AU2LW903993 | H2: 423 | M2: CTRL | N2: =+SUM(E:E) -> 2779322.1 | O2: =+SUM(F:F) -> -640715.53
A3: 230251A | B3: 2020 | C3: VOLKSWAGEN | D3: E-GOLF | E3: 24454.46 | G3: WVWPR7AU0LW907198 | H3: 306 | M3: Unités | N3: =COUNT(E:E) -> 111 | O3: =-O2/N2 -> 0.23052943
A4: 230425A | B4: 2021 | C4: VOLKSWAGEN | D4: ATLAS CROSS SPO | E4: 37735.15 | G4: 1V2LC2CAXMC211536 | H4: 188
A5: 230365A | B5: 2018 | C5: VOLKSWAGEN | D5: BEETLE CONVERTI | E5: 29929.55 | G5: 3VW5DAAT2JM518129 | H5: 187 | M5: Moyenne | N5: =+N2/N3 -> 25038.938
A6: 5485P | B6: 2018 | C6: VOLKSWAGEN | D6: ATLAS | E6: 31306.12 | G6: 1V2NR2CA5JC509107 | H6: 131
A7: 230554A | B7: 2014 | C7: SUBARU | D7: WRX | E7: 17680.42 | G7: JF1GR8H60EL238082 | H7: 121 | M7: Plus de 90 Jours | N7: =SUM(E2:E13) -> 337989.36 | O7: =+N7/N2 -> 0.12160856
A8: 230567A | B8: 2021 | C8: VOLKSWAGEN | D8: TIGUAN | E8: 28635.15 | F8: -31332.8 | G8: 3VV2B7AX6MM155874 | H8: 104 | N8: =COUNT(H2:H13) -> 12 | O8: =+N8/(N3) -> 0.10810811
A9: 240013A | B9: 2022 | C9: VOLKSWAGEN | D9: TIGUAN | E9: 38815.25 | G9: 3VV4B7AX3NM051496 | H9: 94
A10: 230392A | B10: 2020 | C10: VOLKSWAGEN | D10: TIGUAN | E10: 31315.25 | F10: -24944.54 | G10: 3VV4B7AX2LM114164 | H10: 94
A11: 230599A | B11: 2019 | C11: VOLKSWAGEN | D11: JETTA | E11: 21280.25 | F11: -10962 | G11: 3VWE57BU6KM254342 | H11: 94
A12: 230606A | B12: 2018 | C12: CHEVROLET | D12: VOLT | E12: 17550 | G12: 1G1RA6S50JU104989 | H12: 93
A13: 240015A | B13: 2019 | C13: VOLKSWAGEN | D13: GOLF GTI | E13: 27280.25 | F13: -17480.23 | G13: 3VW6T7AU5KM024755 | H13: 90
A14: 5511P | B14: 2022 | C14: VOLKSWAGEN | D14: ATLAS CROSS SPO | E14: 44105.05 | F14: -38250 | G14: 1V2BE2CA6NC212111 | H14: 88
A15: 240019A | B15: 2020 | C15: VOLKSWAGEN | D15: ATLAS CROSS SPO | E15: 36415.13 | F15: -26892 | G15: 1V2TE2CA8LC219420 | H15: 82
A16: 230596A | B16: 2020 | C16: VOLKSWAGEN | D16: TIGUAN | E16: 27935.05 | G16: 3VV2B7AX4LM005048 | H16: 76
A17: 5509PA | B17: 2017 | C17: AUDI | D17: A3 E-TRON | E17: 20050 | G17: WAUSPBFF5HA099610 | H17: 74
A18: 230626A | B18: 2018 | C18: VOLKSWAGEN | D18: TIGUAN | E18: 20497.05 | G18: 3VV4B7AX2JM130250 | H18: 72
A19: 5518P | B19: 2020 | C19: VOLKSWAGEN | D19: TIGUAN | E19: 28075.78 | F19: -23850 | G19: 3VV4B7AX0LM106225 | H19: 69
A20: 230593A | B20: 2019 | C20: VOLKSWAGEN | D20: TIGUAN | E20: 26815.25 | G20: 3VV4B7AX3KM183332 | H20: 69
A21: 5519P | B21: 2021 | C21: VOLKSWAGEN | D21: TIGUAN | E21: 28447.25 | F21: -24418.8 | G21: 3VV2B7AX4MM068281 | H21: 68
A22: 240044A | B22: 2019 | C22: VOLKSWAGEN | D22: ATLAS | E22: 29352 | G22: 1V2MR2CA6KC587280 | H22: 66
A23: 240041A | B23: 2018 | C23: VOLKSWAGEN | D23: GOLF | E23: 18787.5 | G23: 3VWG17AU2JM291103 | H23: 66
A24: 240056A | B24: 2020 | C24: VOLKSWAGEN | D24: JETTA | E24: 18043.82 | G24: 3VWN57BU2LM040420 | H24: 65
A25: 240036A | B25: 2021 | C25: VOLKSWAGEN | D25: ATLAS | E25: 40209.65 | G25: 1V2FR2CA8MC595926 | H25: 62
A26: 240079A | B26: 2020 | C26: VOLKSWAGEN | D26: TIGUAN | E26: 30620.3 | G26: 3VV4B7AX5LM110786 | H26: 62
A27: 230564B | B27: 2020 | C27: JEEP | D27: COMPASS | E27: 28211.38 | G27: 3C4NJDDBXLT155667 | H27: 62
A28: 230649A | B28: 2020 | C28: NISSAN | D28: ROGUE | E28: 23550 | G28: 5N1AT2MT7LC775762 | H28: 61
A29: 240086A | B29: 2022 | C29: VOLKSWAGEN | D29: TIGUAN | E29: 36524.6 | G29: 3VV4B7AX9NM096457 | H29: 60
A30: 5522P | B30: 2020 | C30: VOLKSWAGEN | D30: TIGUAN | E30: 24346.21 | F30: -16047.88 | G30: 3VV2B7AX7LM099068 | H30: 60
A31: 5521P | B31: 2019 | C31: VOLKSWAGEN | D31: GOLF | E31: 18530.25 | G31: 3VWG57AU3KM018998 | H31: 60
A32: 5523P | B32: 2021 | C32: VOLKSWAGEN | D32: TIGUAN | E32: 29670.31 | F32: -25505.1 | G32: 3VV2B7AX2MM078047 | H32: 59
A33: 240089A | B33: 2020 | C33: VOLKSWAGEN | D33: JETTA | E33: 22965.2 | G33: 3VWW57BU9LM006236 | H33: 55
A34: 5525P | B34: 2021 | C34: VOLKSWAGEN | D34: TIGUAN | E34: 31666.8 | F34: -33046.59 | G34: 3VV4B7AX1MM155614 | H34: 54
A35: 240059A | B35: 2019 | C35: VOLKSWAGEN | D35: TIGUAN | E35: 24846.26 | G35: 3VV2B7AX7KM049091 | H35: 53
A36: 240099A | B36: 2020 | C36: VOLKSWAGEN | D36: JETTA | E36: 19323.74 | G36: 3VWN57BU9LM077965 | H36: 51
A37: 240098A | B37: 2019 | C37: VOLKSWAGEN | D37: GOLF | E37: 18294.75 | G37: 3VWG57AU0KM034477 | H37: 48
A38: 240038B | B38: 2018 | C38: VOLKSWAGEN | D38: GOLF | E38: 16745.3 | G38: 3VWG17AU9JM275867 | H38: 48
A39: 240091A | B39: 2022 | C39: VOLKSWAGEN | D39: ATLAS | E39: 49927.29 | G39: 1V2FR2CA7NC504226 | H39: 47
A40: 5526P | B40: 2020 | C40: VOLKSWAGEN | D40: TIGUAN | E40: 24483.1 | F40: -18876 | G40: 3VV2B7AX9LM002520 | H40: 47
A41: 240109A | B41: 2019 | C41: VOLKSWAGEN | D41: GOLF | E41: 21779.6 | G41: 3VWG57AU6KM028375 | H41: 47
A42: 240111A | B42: 2021 | C42: VOLKSWAGEN | D42: GOLF | E42: 21350 | G42: 3VWW57AU1MM000790 | H42: 45
A43: 240108A | B43: 2019 | C43: VOLKSWAGEN | D43: JETTA | E43: 17488.18 | G43: 3VWG57BU3KM143398 | H43: 45
A44: 240100A | B44: 2020 | C44: VOLKSWAGEN | D44: JETTA | E44: 18370.25 | G44: 3VWCB7BU1LM050033 | H44: 44
A45: 5527P | B45: 2018 | C45: VOLKSWAGEN | D45: TIGUAN | E45: 20165.3 | G45: 3VV2B7AX0JM078401 | H45: 44
A46: 240121A | B46: 2015 | C46: JEEP | D46: CHEROKEE | E46: 15050 | G46: 1C4PJMBBXFW775848 | H46: 44
A47: 240062A | B47: 2020 | C47: VOLKSWAGEN | D47: JETTA | E47: 21360.2 | G47: 3VWEB7BU9LM051228 | H47: 41
A48: 5528P | B48: 2021 | C48: VOLKSWAGEN | D48: JETTA | E48: 25003.85 | F48: -21330 | G48: 3VWE57BU8MM046465 | H48: 40
A49: 240153A | B49: 2020 | C49: VOLKSWAGEN | D49: TIGUAN | E49: 24894.97 | G49: 3VV0B7AX5LM117185 | H49: 40
A50: 240127A | B50: 2019 | C50: VOLKSWAGEN | D50: TIGUAN | E50: 27870.3 | G50: 3VV4B7AX2KM185248 | H50: 40
A51: 240169A | B51: 2021 | C51: VOLKSWAGEN | D51: JETTA | E51: 24530.4 | G51: 3VWE57BU7MM077268 | H51: 37
A52: 240143A | B52: 2008 | C52: VOLKSWAGEN | D52: GTI | E52: 4314.03 | G52: WVWHV91K48W093414 | H52: 37
A53: 240183A | B53: 2021 | C53: VOLKSWAGEN | D53: JETTA | E53: 24447.5 | G53: 3VWE57BU5MM022575 | H53: 33
A54: 5530P | B54: 2019 | C54: VOLKSWAGEN | D54: GOLF | E54: 20373.45 | F54: -12553.38 | G54: 3VWG57AU5KM019568 | H54: 33
A55: 240105A | B55: 2021 | C55: VOLKSWAGEN | D55: GOLF GTI | E55: 32388.2 | G55: 3VW5T7AU9MM015944 | H55: 32
A56: 240151A | B56: 2020 | C56: VOLKSWAGEN | D56: PASSAT | E56: 23491.6 | G56: 1VWBA7A31LC005280 | H56: 32
A57: 240123A | B57: 2021 | C57: VOLKSWAGEN | D57: TIGUAN | E57: 29343.25 | G57: 3VV2B7AX9MM038886 | H57: 31
A58: 240198A | B58: 2020 | C58: VOLKSWAGEN | D58: TIGUAN | E58: 29950 | G58: 3VV4B7AX7LM138623 | H58: 31
A59: 5531P | B59: 2019 | C59: VOLKSWAGEN | D59: TIGUAN | E59: 21448.99 | F59: -18000 | G59: 3VV2B7AX5KM174266 | H59: 31
A60: 240195A | B60: 2019 | C60: VOLKSWAGEN | D60: GOLF ALLTRACK | E60: 23680.2 | G60: 3VWH17AU4KM517860 | H60: 31
A61: 240031A | B61: 2019 | C61: VOLKSWAGEN | D61: GOLF | E61: 19433.85 | G61: 3VWG57AU6KM019319 | H61: 31
A62: 240208A | B62: 2019 | C62: NISSAN | D62: ROGUE | E62: 17516.85 | G62: 5N1AT2MT2KC789311 | H62: 31
A63: 240200A | B63: 2021 | C63: VOLKSWAGEN | D63: TIGUAN | E63: 28418.09 | G63: 3VV2B7AX7MM017972 | H63: 30
A64: 240120A | B64: 2020 | C64: VOLKSWAGEN | D64: TIGUAN | E64: 26650 | G64: 3VV2B7AX5LM134416 | H64: 30
A65: 5532P | B65: 2019 | C65: VOLKSWAGEN | D65: TIGUAN | E65: 22943.2 | F65: -14910 | G65: 3VV2B7AXXKM175526 | H65: 27
A66: 5536P | B66: 2024 | C66: VOLKSWAGEN | D66: GOLF R | E66: 56282.9 | F66: -53444.44 | G66: WVWEB7CD1RW113067 | H66: 26
A67: 5535P | B67: 2023 | C67: VOLKSWAGEN | D67: TIGUAN | E67: 37343.25 | F67: -31500 | G67: 3VVMB7AX1PM006494 | H67: 26
A68: 5534P | B68: 2021 | C68: VOLKSWAGEN | D68: TIGUAN | E68: 27555.44 | F68: -26142.19 | G68: 3VV2B7AX0MM070822 | H68: 26
A69: 240090A | B69: 2019 | C69: VOLKSWAGEN | D69: JETTA | E69: 15050 | G69: 3VWW57BU7KM135400 | H69: 26
A70: 5539P | B70: 2020 | C70: VOLKSWAGEN | D70: E-GOLF | E70: 24148.3 | F70: -13011 | G70: WVWPR7AUXLW900758 | H70: 25
A71: 5537P | B71: 2017 | C71: VOLKSWAGEN | D71: TIGUAN | E71: 17323.25 | F71: -14400 | G71: WVGNV7AX9HW500724 | H71: 25
A72: 5540P | B72: 2020 | C72: VOLKSWAGEN | D72: TIGUAN | E72: 24729.89 | F72: -21121.07 | G72: 3VV2B7AX5LM104042 | H72: 24
A73: 240154A | B73: 2023 | C73: HYUNDAY | D73: SANTA CRUZ | E73: 39801.28 | G73: 5NTJEDAF3PH073751 | H73: 17
A74: 5542P | B74: 2020 | C74: VOLKSWAGEN | D74: TIGUAN | E74: 27897 | F74: -21259.15 | G74: 3VV2B7AX9LM116727 | H74: 17
A75: 5543P | B75: 2021 | C75: VOLKSWAGEN | D75: TIGUAN | E75: 29849.7 | F75: -25650 | G75: 3VV4B7AX3MM043848 | H75: 16
A76: 240222A | B76: 2021 | C76: VOLKSWAGEN | D76: JETTA | E76: 22734.85 | G76: 3VWE57BU8MM023008 | H76: 16
A77: 5544P | B77: 2020 | C77: VOLKSWAGEN | D77: TIGUAN | E77: 23937.85 | G77: 3VV2B7AX7LM009577 | H77: 16
A78: 240210A | B78: 2020 | C78: DODGE | D78: RAM 1500 | E78: 37860.38 | G78: 1C6SRFFT2LN407190 | H78: 16
A79: 240226A | B79: 2019 | C79: VOLKSWAGEN | D79: GOLF | E79: 17250 | F79: -10994 | G79: 3VWG57AU7KM033052 | H79: 16
A80: 240172A | B80: 2015 | C80: VOLKSWAGEN | D80: JETTA SEDAN | E80: 9050 | G80: 3VWG07AJ8FM218642 | H80: 13
A81: 5529PA | B81: 2014 | C81: NISSAN | D81: TRUCK PATHFINDER | E81: 10550 | G81: 5N1AR2MM1EC693147 | H81: 12
A82: 5545P | B82: 2022 | C82: VOLKSWAGEN | D82: GOLF R | E82: 48197.8 | F82: -42300 | G82: WVWEB7CD8NW157948 | H82: 11
A83: 240231A | B83: 2019 | C83: VOLKSWAGEN | D83: JETTA | E83: 21402.85 | G83: 3VWE57BU8KM269358 | H83: 11
A84: 240215A | B84: 2019 | C84: VOLKSWAGEN | D84: GOLF | E84: 18179.95 | G84: 3VWW57AU6KM035788 | H84: 11
A85: 5546P | B85: 2016 | C85: BMW | D85: SAV X5 | E85: 22550 | G85: 5UXKR0C55G0S87415 | H85: 11
A86: 0925RA | B86: 2010 | C86: TOYOTA | D86: COROLLA | E86: 5450 | G86: 2T1BU4EE1AC231280 | H86: 11
A87: 240191A | B87: 2019 | C87: VOLKSWAGEN | D87: TIGUAN | E87: 20650 | G87: 3VV2B7AX1KM022551 | H87: 10
A88: 240194A | B88: 2015 | C88: VOLKSWAGEN | D88: TIGUAN | E88: 8550 | G88: WVGJV7AX1FW576563 | H88: 10
A89: 240261A | B89: 2020 | C89: VOLKSWAGEN | D89: TIGUAN | E89: 25550 | G89: 3VV2B7AXXLM100701 | H89: 9
A90: 240035A | B90: 2020 | C90: HONDA | D90: PILOT | E90: 28550 | G90: 5FNYF6H72LB500902 | H90: 9
A91: 240229A | B91: 2019 | C91: VOLKSWAGEN | D91: GOLF | E91: 17050 | G91: 3VWW57AU0KM035463 | H91: 9
A92: 240178A | B92: 2022 | C92: VOLKSWAGEN | D92: TIGUAN | E92: 31300 | G92: 3VV8B7AX7NM005591 | H92: 8
A93: 5548P | B93: 2023 | C93: VOLKSWAGEN | D93: ATLAS | E93: 47388.75 | G93: 1V2SR2CA7PC517706 | H93: 4
A94: 240058A | B94: 2021 | C94: VOLKSWAGEN | D94: JETTA | E94: 24050 | G94: 3VW6T7BU9MM023626 | H94: 4
... A114: 5488P | B114: 2010 | C114: VOLKSWAGEN | D114: ROUTAN | E114: 11948.62 | G114: 2V4RW3DX0AR228009 | H114: 94

Sheet Inventaire_Neuf
A1: #Contrôle | B1: Année | C1: Marque | D1: Modèle | E1: 1402 | F1: 2101 | G1: NIV | H1: Jours en stock | K1: 45230 | L1: $ Inventaire | M1: $ Financé
A2: 230536 | B2: 2023 | C2: VOLKSWAGEN | D2: JETTA SEDAN | E2: 33666.97 | F2: -31504.85 | G2: 3VW2T7BU7PM053775 | H2: 142 | K2: CTRL | L2: =+SUM(E2:E9963) -> 3059537.1 | M2: =+SUM(F2:F9963) -> -2668372
A3: 240001 | B3: 2024 | C3: VOLKSWAGEN | D3: ATLAS | E3: 56706.1 | F3: -57628.2 | G3: 1V2BR2CA6RC502911 | H3: 142 | K3: Unités | L3: =COUNT(E:E) -> 71 | M3: =-M2/L2 -> 0.8721489
A4: 230574 | B4: 2023 | C4: VOLKSWAGEN | D4: JETTA SEDAN | E4: 31163.98 | F4: -32628.75 | G4: 3VWGM7BU3PM060824 | H4: 116
A5: 230581 | B5: 2023 | C5: VOLKSWAGEN | D5: TAOS | E5: 38081.07 | F5: -39936.75 | G5: 3VV4X7B27PM374246 | H5: 111
A6: 240003 | B6: 2024 | C6: VOLKSWAGEN | D6: ATLAS | E6: 50511.98 | F6: -51427.95 | G6: 1V2LR2CA2RC511786 | H6: 108 | K6: Plus de 90 jrs | L6: =SUM(E2:E12) -> 532950.79 | M6: =SUM(F2:F12) -> -378366.05
A7: 240009 | B7: 2024 | C7: VOLKSWAGEN | D7: ATLAS CROSS SPT | E7: 54659.17 | F7: -57051.75 | G7: 1V2BE2CA7RC206484 | H7: 104 | L7: 2
A8: 240011 | B8: 2024 | C8: VOLKSWAGEN | D8: ATLAS CROSS SPT | E8: 48328.17 | F8: -51136.05 | G8: 1V2LE2CA3RC208611 | H8: 97
A9: 240016 | B9: 2024 | C9: VOLKSWAGEN | D9: ATLAS CROSS SPT | E9: 57229.1 | G9: 1V2BE2CA1RC206996 | H9: 93 | K9: Plus de 180 jrs | L9: 0 | M9: 0
A10: 240022 | B10: 2024 | C10: VOLKSWAGEN | D10: ATLAS | E10: 58141.01 | G10: 1V2BR2CA4RC506228 | H10: 90 | L10: 0
A11: 240021 | B11: 2024 | C11: VOLKSWAGEN | D11: ATLAS | E11: 48171.23 | G11: 1V2LR2CA8RC516197 | H11: 90
A12: 240020 | B12: 2024 | C12: VOLKSWAGEN | D12: ATLAS CROSS SPT | E12: 56292.01 | F12: -57051.75 | G12: 1V2BE2CA5RC210341 | H12: 90
A13: 240027 | B13: 2024 | C13: VOLKSWAGEN | D13: ATLAS | E13: 56073.92 | F13: -58869.3 | G13: 1V2BR2CA1RC517137 | H13: 86
A14: 240026 | B14: 2024 | C14: VOLKSWAGEN | D14: GOLF GTI | E14: 37397 | F14: -39440.1 | G14: WVWGA7CD7RW121198 | H14: 86
A15: 240030 | B15: 2024 | C15: VOLKSWAGEN | D15: ATLAS CROSS SPT | E15: 56197.99 | F15: -58834.65 | G15: 1V2FE2CAXRC211373 | H15: 82
A16: 230639 | B16: 2023 | C16: VOLKSWAGEN | D16: TAOS | E16: 32135.51 | F16: -34034.7 | G16: 3VVEX7B23PM379190 | H16: 80
A17: 240042 | B17: 2024 | C17: VOLKSWAGEN | D17: ATLAS CROSS SPT | E17: 55950.97 | F17: -58834.65 | G17: 1V2FE2CA4RC210672 | H17: 74
A18: 240047 | B18: 2024 | C18: VOLKSWAGEN | D18: ATLAS CROSS SPT | E18: 55950.97 | F18: -58834.65 | G18: 1V2FE2CA0RC211429 | H18: 74
A19: 240045 | B19: 2024 | C19: VOLKSWAGEN | D19: JETTA SEDAN | E19: 26927 | F19: -28367.85 | G19: 3VWWM7BU5RM010702 | H19: 74
A20: 230643 | B20: 2023 | C20: VOLKSWAGEN | D20: TAOS | E20: 37610 | F20: -39461.1 | G20: 3VV4X7B2XPM382549 | H20: 73
A21: 240052 | B21: 2024 | C21: VOLKSWAGEN | D21: ATLAS CROSS SPT | E21: 55950.97 | F21: -58834.65 | G21: 1V2FE2CAXRC211504 | H21: 73
A22: 240050 | B22: 2024 | C22: VOLKSWAGEN | D22: JETTA SEDAN | E22: 29531 | F22: -31102.05 | G22: 3VWSM7BU4RM014707 | H22: 73
A23: 240070 | B23: 2024 | C23: VOLKSWAGEN | D23: ATLAS CROSS SPT | E23: 54250 | F23: -57051.75 | G23: 1V2BE2CA9RC212335 | H23: 68
... A27: 240083 | B27: 2024 | C27: VOLKSWAGEN | D27: JETTA SEDAN | E27: 32017.87 | F27: -33204.15 | G27: 3VWGM7BU7RM015582 | H27: 62
A28: 240125 | B28: 2024 | C28: VOLKSWAGEN | D28: JETTA GLI | E28: 31816.52 | G28: 3VW8T7BU7RM014696 | H28: 52
A29: 240129 | B29: 2024 | C29: VOLKSWAGEN | D29: JETTA GLI | E29: 31513 | G29: 3VW8T7BU8RM016912 | H29: 51
A30: 240137 | B30: 2024 | C30: VOLKSWAGEN | D30: ATLAS | E30: 48894 | F30: -51427.95 | G30: 1V2LR2CA9RC529461 | H30: 48
A31: 240141 | B31: 2024 | C31: VOLKSWAGEN | D31: ATLAS CROSS SPT | E31: 55948 | F31: -58834.65 | G31: 1V2FE2CA6RC216828 | H31: 48
A32: 240139 | B32: 2024 | C32: VOLKSWAGEN | D32: ATLAS CROSS SPT | E32: 54236.5 | G32: 1V2BE2CAXRC212764 | H32: 48
A33: 240138 | B33: 2024 | C33: VOLKSWAGEN | D33: TAOS | E33: 32864 | F33: -34706.7 | G33: 3VVEX7B22RM012347 | H33: 48
A34: 240147 | B34: 2024 | C34: VOLKSWAGEN | D34: ATLAS | E34: 55259.97 | F34: -58109.1 | G34: 1V2BR2CAXRC525513 | H34: 47
A35: 240156 | B35: 2024 | C35: VOLKSWAGEN | D35: ATLAS CROSS SPT | E35: 53794.97 | F35: -56570.85 | G35: 1V2BE2CA8RC216649 | H35: 45
A36: 240171 | B36: 2024 | C36: VOLKSWAGEN | D36: JETTA SEDAN | E36: 28629 | G36: 3VWEM7BU2RM001760 | H36: 44
A37: 240173 | B37: 2024 | C37: VOLKSWAGEN | D37: ATLAS | E37: 54801.97 | F37: -57628.2 | G37: 1V2BR2CA7RC532368 | H37: 41
A38: 240190 | B38: 2024 | C38: VOLKSWAGEN | D38: ATLAS | E38: 58249.97 | G38: 1V2FR2CA7RC531156 | H38: 38
A39: 240197 | B39: 2024 | C39: VOLKSWAGEN | D39: TIGUAN | E39: 45175.95 | F39: -47526.15 | G39: 3VV4B7AX2RM023873 | H39: 37
A40: 240203 | B40: 2024 | C40: VOLKSWAGEN | D40: TIGUAN | E40: 44101 | F40: -46474.05 | G40: 3VV4B7AX6RM025190 | H40: 34
A41: 240207 | B41: 2024 | C41: VOLKSWAGEN | D41: ATLAS | E41: 54806.97 | F41: -57628.2 | G41: 1V2BR2CA4RC531890 | H41: 33
A42: 240206 | B42: 2024 | C42: VOLKSWAGEN | D42: TAOS | E42: 38195 | F42: -40225.5 | G42: 3VV4X7B25RM012063 | H42: 33
A43: 240212 | B43: 2024 | C43: VOLKSWAGEN | D43: ATLAS CROSS SPT | E43: 56348.1 | F43: -58834.65 | G43: 1V2FE2CA5RC219798 | H43: 30
A44: 240213 | B44: 2024 | C44: VOLKSWAGEN | D44: TIGUAN | E44: 45762.95 | G44: 3VV4B7AX1RM023721 | H44: 30
A45: 240221 | B45: 2024 | C45: VOLKSWAGEN | D45: TAOS | E45: 37908 | F45: -39749.85 | G45: 3VV4X7B20RM013248 | H45: 25
A46: 240220 | B46: 2024 | C46: VOLKSWAGEN | D46: TAOS | E46: 32705 | F46: -34423.2 | G46: 3VVEX7B2XRM013066 | H46: 25
A47: 240223 | B47: 2024 | C47: VOLKSWAGEN | D47: TAOS | E47: 32705 | F47: -34423.2 | G47: 3VVEX7B25RM012259 | H47: 25
A48: 240219 | B48: 2024 | C48: VOLKSWAGEN | D48: TAOS | E48: 32700 | F48: -34423.2 | G48: 3VVEX7B20RM012928 | H48: 25
A49: 240232 | B49: 2024 | C49: VOLKSWAGEN | D49: TAOS | E49: 35661.95 | G49: 3VVVX7B23RM011742 | H49: 20
A50: 240230 | B50: 2024 | C50: VOLKSWAGEN | D50: TIGUAN | E50: 44107 | F50: -46474.05 | G50: 3VV4B7AX4RM047169 | H50: 20
A51: 240238 | B51: 2024 | C51: VOLKSWAGEN | D51: TAOS | E51: 37441.5 | G51: 3VV4X7B26RM014615 | H51: 16
A52: 240248 | B52: 2024 | C52: VOLKSWAGEN | D52: GOLF GTI | E52: 38207 | F52: -40179.3 | G52: WVWRA7CD4RW133320 | H52: 13
A53: 240241 | B53: 2024 | C53: VOLKSWAGEN | D53: TAOS | E53: 37773 | F53: -39749.85 | G53: 3VV4X7B2XRM023463 | H53: 13
A54: 240243 | B54: 2024 | C54: VOLKSWAGEN | D54: TAOS | E54: 37109 | F54: -39552.45 | G54: 3VV4X7B23RM025278 | H54: 13
A55: 240242 | B55: 2024 | C55: VOLKSWAGEN | D55: TAOS | E55: 34270 | F55: -36066.45 | G55: 3VVUX7B20RM026050 | H55: 13
A56: 240259 | B56: 2024 | C56: VOLKSWAGEN | D56: GOLF GTI | E56: 39384 | F56: -41836.2 | G56: WVWWA7CD4RW139864 | H56: 12
A57: 240256 | B57: 2024 | C57: VOLKSWAGEN | D57: GOLF R | E57: 49697 | F57: -52243.8 | G57: WVWEB7CD9RW139691 | H57: 12
A58: 240257 | B58: 2024 | C58: VOLKSWAGEN | D58: GOLF R | E58: 49697 | F58: -52243.8 | G58: WVWEB7CD9RW140162 | H58: 12
A59: 240255 | B59: 2024 | C59: VOLKSWAGEN | D59: TAOS | E59: 35568 | F59: -37434.6 | G59: 3VVVX7B24RM026699 | H59: 12
A60: 240254 | B60: 2024 | C60: VOLKSWAGEN | D60: TAOS | E60: 34265 | F60: -36066.45 | G60: 3VVUX7B25RM026254 | H60: 12
A61: 240250 | B61: 2024 | C61: VOLKSWAGEN | D61: TAOS | E61: 28211 | G61: 3VVCX7B23RM011327 | H61: 12
A62: 240253 | B62: 2024 | C62: VOLKSWAGEN | D62: TIGUAN | E62: 47482.92 | F62: -47526.15 | G62: 3VV4B7AX0RM043880 | H62: 12
A63: 240262 | B63: 2024 | C63: VOLKSWAGEN | D63: TIGUAN | E63: 40734 | F63: -43358.7 | G63: 3VV8B7AX4RM058738 | H63: 9
A64: 240266 | B64: 2024 | C64: VOLKSWAGEN | D64: GOLF GTI | E64: 37806 | F64: -40179.3 | G64: WVWRA7CD7RW142545 | H64: 3
A65: 240270 | B65: 2024 | C65: VOLKSWAGEN | D65: TIGUAN | E65: 44886 | F65: -47718.3 | G65: 3VV4B7AXXRM065708 | H65: 3
A66: 240263 | B66: 2024 | C66: VOLKSWAGEN | D66: TIGUAN | E66: 44154 | F66: -46949.7 | G66: 3VV4B7AXXRM047399 | H66: 3
A67: 240268 | B67: 2024 | C67: VOLKSWAGEN | D67: TIGUAN | E67: 44154 | F67: -46949.7 | G67: 3VV4B7AX3RM061712 | H67: 3
A68: 240264 | B68: 2024 | C68: VOLKSWAGEN | D68: TIGUAN | E68: 43701 | F68: -46474.05 | G68: 3VV4B7AX7RM058599 | H68: 3
A69: 240267 | B69: 2024 | C69: VOLKSWAGEN | D69: TIGUAN | E69: 43701 | F69: -46474.05 | G69: 3VV4B7AX9RM059415 | H69: 3
A70: 240269 | B70: 2024 | C70: VOLKSWAGEN | D70: TIGUAN | E70: 40734 | F70: -43358.7 | G70: 3VV8B7AX7RM066865 | H70: 3
A71: 240265 | B71: 2024 | C71: VOLKSWAGEN | D71: TIGUAN | E71: 39069 | F71: -41610.45 | G71: 3VVMB7AX2RM024991 | H71: 3
A72: 240273 | B72: 2024 | C72: VOLKSWAGEN | D72: TIGUAN | E72: 44154 | F72: -46949.7 | G72: 3VV4B7AX9RM059835 | H72: 2

Sheet 2pager
B1: =Parametres!$B$1&" "&"2 pager"&" "&Parametres!$B$3&" "&Parametres!$B$4 -> Ste-Marie Auto 2 pager Décembre 2025
B3: New | C3: Actual | D3: Budget | E3: 2023 | F3: ▲ Budget | G3: ▲2023 | H3: % ▲ Budget | I3: % ▲ 2023 | J3: Commentaires
B4: Units | C4: =+Print_Mois!$J$13+Print_Mois!$J$15 -> 54 | D4: =+Print_Mois!$D$13+Print_Mois!$D$15 -> 0 | E4: =+Print_Mois!$O$13+Print_Mois!$O$15 -> 0 | F4: =+IFERROR($C4-D4,"") -> 54 | G4: =+IFERROR($C4-E4,"") -> 54 | H4: =+IFERROR(F4/ABS($D4),"") | I4: =+IFERROR(G4/ABS($E4),"") | J4: L'arrêt des livraisons ID4 a eu un impact significatif sur le mois de septembre. Les profits unitaires au budget n'en tenaient pas tant compte mais la comptétion tant inter-dealers qu'inter-marques a relancé les négociations sur les prix. Notre bureau commercial est encore sous le coup du turnover. Les autres revenus sont la conséquence directe de la baisse de volume d'unités livrées.
B5: Front Margin | C5: =+Print_Mois!$L$13+Print_Mois!$L$15 -> 80534.51 | D5: =+Print_Mois!$F$13+Print_Mois!$F$15 -> 0 | E5: =+Print_Mois!$Q$13+Print_Mois!$Q$15 -> 0 | F5: =+IFERROR($C5-D5,"") -> 80534.51 | G5: =+IFERROR($C5-E5,"") -> 80534.51 | H5: =+IFERROR(F5/ABS($D5),"") | I5: =+IFERROR(G5/ABS($E5),"")
B6: Front margin / unit | C6: =+C5/C4 -> 1491.3798 | D6: =+D5/D4 -> #DIV/0! | E6: =+E5/E4 -> #DIV/0! | F6: =+IFERROR($C6-D6,"") | G6: =+IFERROR($C6-E6,"") | H6: =+IFERROR(F6/ABS($D6),"") | I6: =+IFERROR(G6/ABS($E6),"")
B7: $ Salaires et commission | C7: =+Print_Mois!$L$31 -> 40586.54 | D7: =+Print_Mois!$F$31 -> 0 | E7: =+Print_Mois!$Q$31 -> 0 | F7: =+IFERROR($C7-D7,"") -> 40586.54 | G7: =+IFERROR($C7-E7,"") -> 40586.54 | H7: =+IFERROR(F7/ABS($D7),"") | I7: =+IFERROR(G7/ABS($E7),"")
B8: % Salaires et commission | C8: =+C7/C5 -> 0.50396457 | D8: =+D7/D5 -> #DIV/0! | E8: =+E7/E5 -> #DIV/0! | F8: =+IFERROR($C8-D8,"") | G8: =+IFERROR($C8-E8,"") | H8: =+IFERROR(F8/ABS($D8),"") | I8: =+IFERROR(G8/ABS($E8),"")
B9: Back Margin | C9: =+Print_Mois!$L$24 -> 36941.92 | D9: =+Print_Mois!$F$24 -> 0 | E9: =+Print_Mois!$Q$24 -> 0 | F9: =+IFERROR($C9-D9,"") -> 36941.92 | G9: =+IFERROR($C9-E9,"") -> 36941.92 | H9: =+IFERROR(F9/ABS($D9),"") | I9: =+IFERROR(G9/ABS($E9),"")
B10: Back Margin / unit | C10: =+C9/C4 -> 684.10963 | D10: =+D9/D4 -> #DIV/0! | E10: =+E9/E4 -> #DIV/0! | F10: =+IFERROR($C10-D10,"") | G10: =+IFERROR($C10-E10,"") | H10: =+IFERROR(F10/ABS($D10),"") | I10: =+IFERROR(G10/ABS($E10),"")
B11: $ commission FI | C11: =+Print_Mois!$L$32 -> 12050.59 | D11: =+Print_Mois!$F$32 -> 0 | E11: =+Print_Mois!$Q$32 -> 0 | F11: =+IFERROR($C11-D11,"") -> 12050.59 | G11: =+IFERROR($C11-E11,"") -> 12050.59 | H11: =+IFERROR(F11/ABS($D11),"") | I11: =+IFERROR(G11/ABS($E11),"")
B12: % commission FI | C12: =+C11/C9 -> 0.32620367 | D12: =+D11/D9 -> #DIV/0! | E12: =+E11/E9 -> #DIV/0! | F12: =+IFERROR($C12-D12,"") | G12: =+IFERROR($C12-E12,"") | H12: =+IFERROR(F12/ABS($D12),"") | I12: =+IFERROR(G12/ABS($E12),"")
B13: Variable fees | C13: =+Print_Mois!$L$41-C7-C11 -> -292136.2 | D13: =+Print_Mois!$F$41-D7-D11 -> 0 | E13: =+Print_Mois!$Q$41-E7-E11 -> 0 | F13: =+IFERROR($C13-D13,"") -> -292136.2 | G13: =+IFERROR($C13-E13,"") -> -292136.2 | H13: =+IFERROR(F13/ABS($D13),"") | I13: =+IFERROR(G13/ABS($E13),"")
B14: Variable fees / units | C14: =+C13/C4 -> -5409.9296 | D14: =+D13/D4 -> #DIV/0! | E14: =+E13/E4 -> #DIV/0! | F14: =+IFERROR($C14-D14,"") | G14: =+IFERROR($C14-E14,"") | H14: =+IFERROR(F14/ABS($D14),"") | I14: =+IFERROR(G14/ABS($E14),"")
B15: Other Revenues | C15: =+Print_Mois!$L$83 -> 5621.93 | D15: =+Print_Mois!$F$83 -> 0 | E15: =+Print_Mois!$Q$83 -> 0 | F15: =+IFERROR($C15-D15,"") -> 5621.93 | G15: =+IFERROR($C15-E15,"") -> 5621.93 | H15: =+IFERROR(F15/ABS($D15),"") | I15: =+IFERROR(G15/ABS($E15),"")
B16: Inventory
B17: Units | C17: =Inventaire_Neuf!L3 -> 71 | D17: 61 | E17: 164 | F17: =+IFERROR($C17-D17,"") -> 10 | G17: =+IFERROR($C17-E17,"") -> -93 | H17: =+IFERROR(F17/ABS($D17),"") -> 0.16393443 | I17: =+IFERROR(G17/ABS($E17),"") -> -0.56707317
B18: $ | C18: =Inventaire_Neuf!L2 -> 3059537.1 | D18: 2233570 | E18: 5689693.2 | F18: =+IFERROR($C18-D18,"") -> 825967.15 | G18: =+IFERROR($C18-E18,"") -> -2630156 | H18: =+IFERROR(F18/ABS($D18),"") -> 0.36979685 | I18: =+IFERROR(G18/ABS($E18),"") -> -0.46226676
B20: Used | C20: Actual | D20: Budget | E20: =$E$3 -> 2023 | F20: ▲ Budget | G20: =$G$3 -> ▲2023 | H20: % ▲ Budget | I20: =$I$3 -> % ▲ 2023 | J20: Commentaires
B21: Units | C21: =+Print_Mois!$J$97 -> 15 | D21: =+Print_Mois!$D$97 -> 0 | E21: =+Print_Mois!$O$97 -> 0 | F21: =+IFERROR($C21-D21,"") -> 15 | G21: =+IFERROR($C21-E21,"") -> 15 | H21: =+IFERROR(F21/ABS($D21),"") | I21: =+IFERROR(G21/ABS($E21),"") | J21: Le volume et les résultats du bureau commercial sont maintenant en ligne avec les attentes. Le profit unitaire "front" est le dernier sujet d'ajustement côté chiffre en même temps que la prise de contrôle des leads, du temps de réponse et de ce que l'on en fait ! Invenaire sain, marchandisage optimisé. Il nous reste à être extrèmement vigilants et rigoureux dans le suivi de ces opérations.
B22: Front Margin | C22: =+Print_Mois!$L$97 -> 6927 | D22: =+Print_Mois!$F$97 -> 0 | E22: =+Print_Mois!$Q$97 -> 0 | F22: =+IFERROR($C22-D22,"") -> 6927 | G22: =+IFERROR($C22-E22,"") -> 6927 | H22: =+IFERROR(F22/ABS($D22),"") | I22: =+IFERROR(G22/ABS($E22),"")
B23: Front margin / unit | C23: =+C22/C21 -> 461.8 | D23: =+D22/D21 -> #DIV/0! | E23: =+E22/E21 -> #DIV/0! | F23: =+IFERROR($C23-D23,"") | G23: =+IFERROR($C23-E23,"") | H23: =+IFERROR(F23/ABS($D23),"") | I23: =+IFERROR(G23/ABS($E23),"")
B24: $ Salaires et commission | C24: =+Print_Mois!$L$113 -> 8616.29 | D24: =+Print_Mois!$F$113 -> 0 | E24: =+Print_Mois!$Q$113 -> 0 | F24: =+IFERROR($C24-D24,"") -> 8616.29 | G24: =+IFERROR($C24-E24,"") -> 8616.29 | H24: =+IFERROR(F24/ABS($D24),"") | I24: =+IFERROR(G24/ABS($E24),"")
B25: % Salaires et commission | C25: =+C24/C22 -> 1.2438704 | D25: =+D24/D22 -> #DIV/0! | E25: =+E24/E22 -> #DIV/0! | F25: =+IFERROR($C25-D25,"") | G25: =+IFERROR($C25-E25,"") | H25: =+IFERROR(F25/ABS($D25),"") | I25: =+IFERROR(G25/ABS($E25),"")
B26: Back Margin | C26: =+Print_Mois!$L$106 -> 14861.82 | D26: =+Print_Mois!$F$106 -> 0 | E26: =+Print_Mois!$Q$106 -> 0 | F26: =+IFERROR($C26-D26,"") -> 14861.82 | G26: =+IFERROR($C26-E26,"") -> 14861.82 | H26: =+IFERROR(F26/ABS($D26),"") | I26: =+IFERROR(G26/ABS($E26),"")
B27: Back Margin / unit | C27: =+C26/C21 -> 990.788 | D27: =+D26/D21 -> #DIV/0! | E27: =+E26/E21 -> #DIV/0! | F27: =+IFERROR($C27-D27,"") | G27: =+IFERROR($C27-E27,"") | H27: =+IFERROR(F27/ABS($D27),"") | I27: =+IFERROR(G27/ABS($E27),"")
B28: $ commission FI | C28: =+Print_Mois!$L$114 -> 6835.57 | D28: =+Print_Mois!$F$114 -> 0 | E28: =+Print_Mois!$Q$114 -> 0 | F28: =+IFERROR($C28-D28,"") -> 6835.57 | G28: =+IFERROR($C28-E28,"") -> 6835.57 | H28: =+IFERROR(F28/ABS($D28),"") | I28: =+IFERROR(G28/ABS($E28),"")
B29: % commission FI | C29: =+C28/C26 -> 0.45994165 | D29: =+D28/D26 -> #DIV/0! | E29: =+E28/E26 -> #DIV/0! | F29: =+IFERROR($C29-D29,"") | G29: =+IFERROR($C29-E29,"") | H29: =+IFERROR(F29/ABS($D29),"") | I29: =+IFERROR(G29/ABS($E29),"")
B30: Variable fees | C30: =+Print_Mois!$L$123-C24-C28 -> 58937.18 | D30: =+Print_Mois!$F$123-D24-D28 -> 0 | E30: =+Print_Mois!$Q$123-E24-E28 -> 0 | F30: =+IFERROR($C30-D30,"") -> 58937.18 | G30: =+IFERROR($C30-E30,"") -> 58937.18 | H30: =+IFERROR(F30/ABS($D30),"") | I30: =+IFERROR(G30/ABS($E30),"")
B31: Variable fees / units | C31: =+C30/C21 -> 3929.1453 | D31: =+D30/D21 -> #DIV/0! | E31: =+E30/E21 -> #DIV/0! | F31: =+IFERROR($C31-D31,"") | G31: =+IFERROR($C31-E31,"") | H31: =+IFERROR(F31/ABS($D31),"") | I31: =+IFERROR(G31/ABS($E31),"")
B32: Other Revenues | C32: =+Print_Mois!$L$164 -> 0 | D32: =+Print_Mois!$F$164 -> 0 | E32: =+Print_Mois!$Q$164 -> 0 | F32: =+IFERROR($C32-D32,"") -> 0 | G32: =+IFERROR($C32-E32,"") -> 0 | H32: =+IFERROR(F32/ABS($D32),"") | I32: =+IFERROR(G32/ABS($E32),"")
B33: Inventory
B34: Units | C34: =Inventaire_Used!N3 -> 111 | D34: 68 | E34: 92 | F34: =+IFERROR($C34-D34,"") -> 43 | G34: =+IFERROR($C34-E34,"") -> 19 | H34: =+IFERROR(F34/ABS($D34),"") -> 0.63235294 | I34: =+IFERROR(G34/ABS($E34),"") -> 0.20652174
B35: $ | C35: =Inventaire_Used!N2 -> 2779322.1 | D35: 1072231 | E35: 1510979 | F35: =+IFERROR($C35-D35,"") -> 1707091.1 | G35: =+IFERROR($C35-E35,"") -> 1268343.1 | H35: =+IFERROR(F35/ABS($D35),"") -> 1.5920927 | I35: =+IFERROR(G35/ABS($E35),"") -> 0.83941809
B37: Service | C37: Actual | D37: Budget | E37: =$E$3 -> 2023 | F37: ▲ Budget | G37: =$G$3 -> ▲2023 | H37: % ▲ Budget | I37: =$I$3 -> % ▲ 2023 | J37: Commentaires
B38: Revenus | C38: =+Print_Mois!$K$268 -> 184608.29 | D38: =+Print_Mois!$E$268 -> 0 | E38: =+Print_Mois!$P$268 -> 0 | F38: =+IFERROR($C38-D38,"") -> 184608.29 | G38: =+IFERROR($C38-E38,"") -> 184608.29 | H38: =+IFERROR(F38/ABS($D38),"") | I38: =+IFERROR(G38/ABS($E38),"") | J38: Très belle progression versus 2023, autant sur le fait de voir monter le brut globalement que sur le contrôle des dépenses. Le modèle de fonctionnement de la mixité de véhicules de courtoisies, Uber Pro et chauffeurs fonctionne. Bon mois de Csi à côté de la performance financière.
B39: Gross margin | C39: =+Print_Mois!$L$268 -> 122970.84 | D39: =+Print_Mois!$F$268 -> 0 | E39: =+Print_Mois!$Q$268 -> 0 | F39: =+IFERROR($C39-D39,"") -> 122970.84 | G39: =+IFERROR($C39-E39,"") -> 122970.84 | H39: =+IFERROR(F39/ABS($D39),"") | I39: =+IFERROR(G39/ABS($E39),"")
B40: $ Revenus / #WO client | C40: =+Print_Mois!$K$246/Print_Mois!$J$246 -> 433.76617 | D40: =+IFERROR(Print_Mois!$E$246/Print_Mois!$D$246,"") | E40: =+Print_Mois!$P$246/Print_Mois!$O$246 -> #DIV/0! | F40: =+IFERROR($C40-D40,"") | G40: =+IFERROR($C40-E40,"") | H40: =+IFERROR(F40/ABS($D40),"") | I40: =+IFERROR(G40/ABS($E40),"")
B41: $ Revenus / #WO garantie | C41: =+Print_Mois!$K$249/Print_Mois!$J$249 -> 153.82413 | D41: =+IFERROR(Print_Mois!$E$249/Print_Mois!$D$249,"") | E41: =+Print_Mois!$P$249/Print_Mois!$O$249 -> #DIV/0! | F41: =+IFERROR($C41-D41,"") | G41: =+IFERROR($C41-E41,"") | H41: =+IFERROR(F41/ABS($D41),"") | I41: =+IFERROR(G41/ABS($E41),"")
B42: Lost time | C42: =+Print_Mois!$L$258 -> -3012.8 | D42: =+Print_Mois!$F$258 -> 0 | E42: =+Print_Mois!$Q$258 -> 0 | F42: =+IFERROR($C42-D42,"") -> -3012.8 | G42: =+IFERROR($C42-E42,"") -> -3012.8 | H42: =+IFERROR(F42/ABS($D42),"") | I42: =+IFERROR(G42/ABS($E42),"")
B43: Total salaries | C43: =+Print_Mois!$L$284 -> 139149.86 | D43: =+Print_Mois!$F$284 -> 0 | E43: =+Print_Mois!$Q$284 -> 0 | F43: =+IFERROR($C43-D43,"") -> 139149.86 | G43: =+IFERROR($C43-E43,"") -> 139149.86 | H43: =+IFERROR(F43/ABS($D43),"") | I43: =+IFERROR(G43/ABS($E43),"")
B44: Salaries | C44: =+SUM(Print_Mois!$L$272:$L$278) -> 57090.3 | D44: =+SUM(Print_Mois!$F$272:$F$278) -> 0 | E44: =+SUM(Print_Mois!$Q$272:$Q$278) -> 0 | F44: =+IFERROR($C44-D44,"") -> 57090.3 | G44: =+IFERROR($C44-E44,"") -> 57090.3 | H44: =+IFERROR(F44/ABS($D44),"") | I44: =+IFERROR(G44/ABS($E44),"")
B45: Fringes | C45: =+SUM(Print_Mois!$L$279:$L$283) -> 82059.56 | D45: =+SUM(Print_Mois!$F$279:$F$283) -> 0 | E45: =+SUM(Print_Mois!$Q$279:$Q$283) -> 0 | F45: =+IFERROR($C45-D45,"") -> 82059.56 | G45: =+IFERROR($C45-E45,"") -> 82059.56 | H45: =+IFERROR(F45/ABS($D45),"") | I45: =+IFERROR(G45/ABS($E45),"")
B46: Total salaries / Revenus | C46: =+C43/C38 -> 0.75375737 | D46: =+D43/D38 -> #DIV/0! | E46: =+E43/E38 -> #DIV/0! | F46: =+IFERROR($C46-D46,"") | G46: =+IFERROR($C46-E46,"") | H46: =+IFERROR(F46/ABS($D46),"") | I46: =+IFERROR(G46/ABS($E46),"")
B47: Frais véhicules de cie | C47: =+Print_Mois!$L$287 -> 4024.06 | D47: =+Print_Mois!$F$287 -> 0 | E47: =+Print_Mois!$Q$287 -> 0 | F47: =+IFERROR($C47-D47,"") -> 4024.06 | G47: =+IFERROR($C47-E47,"") -> 4024.06 | H47: =+IFERROR(F47/ABS($D47),"") | I47: =+IFERROR(G47/ABS($E47),"")
B49: Pieces | C49: Actual | D49: Budget | E49: =$E$3 -> 2023 | F49: ▲ Budget | G49: =$G$3 -> ▲2023 | H49: % ▲ Budget | I49: =$I$3 -> % ▲ 2023 | J49: Commentaires
B50: Revenus | C50: =+Print_Mois!$J$390 -> 351621.17 | D50: =+Print_Mois!$D$390 -> 0 | E50: =+Print_Mois!$O$390 -> 0 | F50: =+IFERROR($C50-D50,"") -> 351621.17 | G50: =+IFERROR($C50-E50,"") -> 351621.17 | H50: =+IFERROR(F50/ABS($D50),"") | I50: =+IFERROR(G50/ABS($E50),"") | J50: Le wholesale est LA machine du département. Analyse rapide mais son point le plus avantageux est la portion de booster le volume d'achats chez l'OEM. Car en fait de $ de ventes, on mobilise quasiment 1 employé, beaucoup d'espace et la quasi-totalité de nos crédits de retour gratuits chez VW. Notre commis sénior n'a pas la maturité analytique pour faire des choix d'anticipation stratégique. Sujet à creuser avant fin q4.
B51: Clients | C51: =+Print_Mois!$J$371 -> 66753.26 | D51: =+Print_Mois!$D$371 -> 0 | E51: =+Print_Mois!$O$371 -> 0 | F51: =+IFERROR($C51-D51,"") -> 66753.26 | G51: =+IFERROR($C51-E51,"") -> 66753.26 | H51: =+IFERROR(F51/ABS($D51),"") | I51: =+IFERROR(G51/ABS($E51),"")
B52: Garantie | C52: =+Print_Mois!$J$373 -> 32778.91 | D52: =+Print_Mois!$D$373 -> 0 | E52: =+Print_Mois!$O$373 -> 0 | F52: =+IFERROR($C52-D52,"") -> 32778.91 | G52: =+IFERROR($C52-E52,"") -> 32778.91 | H52: =+IFERROR(F52/ABS($D52),"") | I52: =+IFERROR(G52/ABS($E52),"")
B53: Wholesale | C53: =+Print_Mois!$J$376 -> 123480.3 | D53: =+Print_Mois!$D$376 -> 0 | E53: =+Print_Mois!$O$376 -> 0 | F53: =+IFERROR($C53-D53,"") -> 123480.3 | G53: =+IFERROR($C53-E53,"") -> 123480.3 | H53: =+IFERROR(F53/ABS($D53),"") | I53: =+IFERROR(G53/ABS($E53),"")
B54: Tires | C54: =+Print_Mois!$J$383 -> 51352.29 | D54: =+Print_Mois!$D$383 -> 0 | E54: =+Print_Mois!$O$383 -> 0 | F54: =+IFERROR($C54-D54,"") -> 51352.29 | G54: =+IFERROR($C54-E54,"") -> 51352.29 | H54: =+IFERROR(F54/ABS($D54),"") | I54: =+IFERROR(G54/ABS($E54),"")
B55: All others | C55: =+C50-SUM(C51:C54) -> 77256.41 | D55: =+D50-SUM(D51:D54) -> 0 | E55: =+E50-SUM(E51:E54) -> 0 | F55: =+IFERROR($C55-D55,"") -> 77256.41 | G55: =+IFERROR($C55-E55,"") -> 77256.41 | H55: =+IFERROR(F55/ABS($D55),"") | I55: =+IFERROR(G55/ABS($E55),"")
B56: Gross margin | C56: =+Print_Mois!$L$390 -> 299756.48 | D56: =+Print_Mois!$F$390 -> 0 | E56: =+Print_Mois!$Q$390 -> 0 | F56: =+IFERROR($C56-D56,"") -> 299756.48 | G56: =+IFERROR($C56-E56,"") -> 299756.48 | H56: =+IFERROR(F56/ABS($D56),"") | I56: =+IFERROR(G56/ABS($E56),"")
B57: $ Revenus / #WO client | C57: =+Print_Mois!$J$371/Print_Mois!$J$246 -> 370.85144 | D57: =+IFERROR(Print_Mois!$D$371/Print_Mois!$D$246,"") | E57: =+Print_Mois!$O$371/Print_Mois!$O$246 -> #DIV/0! | F57: =+IFERROR($C57-D57,"") | G57: =+IFERROR($C57-E57,"") | H57: =+IFERROR(F57/ABS($D57),"") | I57: =+IFERROR(G57/ABS($E57),"")
B58: $ Revenus / #WO garantie | C58: =+Print_Mois!$J$373/Print_Mois!$J$249 -> 130.07504 | D58: =+IFERROR(Print_Mois!$D$373/Print_Mois!$D$249,"") | E58: =+Print_Mois!$O$373/Print_Mois!$O$249 -> #DIV/0! | F58: =+IFERROR($C58-D58,"") | G58: =+IFERROR($C58-E58,"") | H58: =+IFERROR(F58/ABS($D58),"") | I58: =+IFERROR(G58/ABS($E58),"")
B59: Salaires autres | C59: =+Print_Mois!$L$396 -> 19204.73 | D59: =+Print_Mois!$F$396 -> 0 | E59: =+Print_Mois!$Q$396 -> 0 | F59: =+IFERROR($C59-D59,"") -> 19204.73 | G59: =+IFERROR($C59-E59,"") -> 19204.73 | H59: =+IFERROR(F59/ABS($D59),"") | I59: =+IFERROR(G59/ABS($E59),"")
B61: Others | C61: Actual | D61: Budget | E61: =$E$3 -> 2023 | F61: ▲ Budget | G61: =$G$3 -> ▲2023 | H61: % ▲ Budget | I61: =$I$3 -> % ▲ 2023 | J61: Commentaires
B62: Total salaries / Gross profits | C62: =+Print_Mois!$AF$520/Print_Mois!$AF$494 -> 0.64414133 | D62: =+Print_Mois!$Z$520/Print_Mois!$Z$494 -> #REF! | E62: =+Print_Mois!$AL$520/Print_Mois!$AL$494 -> #DIV/0! | F62: =+IFERROR($C62-D62,"") | G62: =+IFERROR($C62-E62,"") | H62: =+IFERROR(F62/ABS($D62),"") | I62: =+IFERROR(G62/ABS($E62),"")
B63: Headcounts | C63: 57 | D63: 59 | E63: 56 | F63: =+IFERROR($C63-D63,"") -> -2 | G63: =+IFERROR($C63-E63,"") -> 1 | H63: =+IFERROR(F63/ABS($D63),"") -> -0.033898305 | I63: =+IFERROR(G63/ABS($E63),"") -> 0.017857143
B64: Marketing | C64: =N17+Print_Mois!$AF$501+Print_Mois!$AF$521 -> -100483.81 | D64: =+Print_Mois!$Z$501+Print_Mois!$Z$521 -> 0 | E64: =+Print_Mois!$AL$501+Print_Mois!$AL$521 -> 0 | F64: =+IFERROR($C64-D64,"") -> -100483.81 | G64: =+IFERROR($C64-E64,"") -> -100483.81 | H64: =+IFERROR(F64/ABS($D64),"") | I64: =+IFERROR(G64/ABS($E64),"")
B65: Other semi-fixed expenses | C65: =+Print_Mois!$AF$539-Print_Mois!$AF$521 -> 92453.01 | D65: =+Print_Mois!$Z$539-Print_Mois!$Z$521 -> 0 | E65: =+Print_Mois!$AL$539-Print_Mois!$AL$521 -> 0 | F65: =+IFERROR($C65-D65,"") -> 92453.01 | G65: =+IFERROR($C65-E65,"") -> 92453.01 | H65: =+IFERROR(F65/ABS($D65),"") | I65: =+IFERROR(G65/ABS($E65),"")
B66: Floor plan interest | C66: =+Print_Mois!$AF$502 -> 138376.22 | D66: =+Print_Mois!$Z$502 -> 0 | E66: =+Print_Mois!$AL$502 -> 0 | F66: =+IFERROR($C66-D66,"") -> 138376.22 | G66: =+IFERROR($C66-E66,"") -> 138376.22 | H66: =+IFERROR(F66/ABS($D66),"") | I66: =+IFERROR(G66/ABS($E66),"")
B67: Others Revenues | C67: =+Print_Mois!$AF$568-C32-C15 -> 832915.41 | D67: =+Print_Mois!$Z$568-D32-D15 -> 0 | E67: =+Print_Mois!$AL$568-E32-E15 -> 0 | F67: =+IFERROR($C67-D67,"") -> 832915.41 | G67: =+IFERROR($C67-E67,"") -> 832915.41 | H67: =+IFERROR(F67/ABS($D67),"") | I67: =+IFERROR(G67/ABS($E67),"")
B69: P&L | C69: Actual | D69: Budget | E69: =$E$3 -> 2023 | F69: ▲ Budget | G69: =$G$3 -> ▲2023 | H69: % ▲ Budget | I69: =$I$3 -> % ▲ 2023 | J69: Commentaires
B70: Selling and Marketing | C70: =+Print_Mois!$AF$506-Print_Mois!$AF$502+Print_Mois!$AF$521+Print_Mois!$AF$522+Print_Mois!$AF$523 -> -239278.15 | D70: =+Print_Mois!$Z$506-Print_Mois!$Z$502+Print_Mois!$Z$521+Print_Mois!$Z$522+Print_Mois!$Z$523 -> 0 | E70: =+Print_Mois!$AL$506-Print_Mois!$AL$502+Print_Mois!$AL$521+Print_Mois!$AL$522+Print_Mois!$AL$523 -> 0 | F70: =+IFERROR($C70-D70,"") -> -239278.15 | G70: =+IFERROR($C70-E70,"") -> -239278.15 | H70: =+IFERROR(F70/ABS($D70),"") | I70: =+IFERROR(G70/ABS($E70),"") | J70: Malgré une baisse des bruts aux ventes nous restons forts sur nos coût et donc cela génère une amélioration légère de notre EBITDA versus 2023, c'est notre objectif qui sera aussi celui des derniers mois de 2024.
B71: S&M / Brut | C71: =+C70/Print_Mois!$AF$494 -> -0.27266145 | D71: =+D70/Print_Mois!$Z$494 -> #REF! | E71: =+E70/Print_Mois!$AL$494 -> #DIV/0! | F71: =+IFERROR($C71-D71,"") | G71: =+IFERROR($C71-E71,"") | H71: =+IFERROR(F71/ABS($D71),"") | I71: =+IFERROR(G71/ABS($E71),"")
B72: General & administrative | C72: =+Print_Mois!$AF$553+Print_Mois!$AF$520+Print_Mois!$AF$524+Print_Mois!$AF$526+SUM(Print_Mois!$AF$527:$AF$535)+Print_Mois!$AF$525 -> 715434.67 | D72: =+Print_Mois!$Z$553+Print_Mois!$Z$520+Print_Mois!$Z$524+Print_Mois!$Z$526+SUM(Print_Mois!$Z$527:$Z$535)+Print_Mois!$Z$525 -> 0 | E72: =+Print_Mois!$AL$553+Print_Mois!$AL$520+Print_Mois!$AL$524+Print_Mois!$AL$526+SUM(Print_Mois!$AL$527:$AL$535)+Print_Mois!$AL$525 -> 0 | F72: =+IFERROR($C72-D72,"") -> 715434.67 | G72: =+IFERROR($C72-E72,"") -> 715434.67 | H72: =+IFERROR(F72/ABS($D72),"") | I72: =+IFERROR(G72/ABS($E72),"")
B73: G&A / Brut | C73: =+C72/Print_Mois!$AF$494 -> 0.81524976 | D73: =+D72/Print_Mois!$Z$494 -> #REF! | E73: =+E72/Print_Mois!$AL$494 -> #DIV/0! | F73: =+IFERROR($C73-D73,"") | G73: =+IFERROR($C73-E73,"") | H73: =+IFERROR(F73/ABS($D73),"") | I73: =+IFERROR(G73/ABS($E73),"")
B74: EBITDA | C74: =+Print_Mois!$AF$570+Print_Mois!$AF$502 -> 1239945.8 | D74: =+Print_Mois!$Z$570+Print_Mois!$Z$502 -> #REF! | E74: =+Print_Mois!$AL$570+Print_Mois!$AL$502 -> 0 | F74: =+IFERROR($C74-D74,"") | G74: =+IFERROR($C74-E74,"") -> 1239945.8 | H74: =+IFERROR(F74/ABS($D74),"") | I74: =+IFERROR(G74/ABS($E74),"")
B75: EBITDA % | C75: =+C74/Print_Mois!$AF$493 -> 0.065150336 | D75: =+D74/Print_Mois!$Z$493 -> #REF! | E75: =+E74/Print_Mois!$AL$493 -> #DIV/0! | F75: =+IFERROR($C75-D75,"") | G75: =+IFERROR($C75-E75,"") | H75: =+IFERROR(F75/ABS($D75),"") | I75: =+IFERROR(G75/ABS($E75),"")
B76: EBIT | C76: =N9+Print_Mois!$AF$585 -> 1060791.4 | D76: =+Print_Mois!$Z$585 -> #REF! | E76: =+Print_Mois!$AL$585 -> 0 | F76: =+IFERROR($C76-D76,"") | G76: =+IFERROR($C76-E76,"") -> 1060791.4 | H76: =+IFERROR(F76/ABS($D76),"") | I76: =+IFERROR(G76/ABS($E76),"")
B77: EBIT % | C77: =+C76/Print_Mois!$AF$493 -> 0.055737043 | D77: =+D76/Print_Mois!$Z$493 -> #REF! | E77: =+E76/Print_Mois!$AL$493 -> #DIV/0! | F77: =+IFERROR($C77-D77,"") | G77: =+IFERROR($C77-E77,"") | H77: =+IFERROR(F77/ABS($D77),"") | I77: =+IFERROR(G77/ABS($E77),"")
B79: "Pacing" du 30
B80: EBITDA | C80: 59525 | D80: 0.011
B81: Écart Fav / (Défav) | C81: =+C74-C80 -> 1180420.8
B83: EBIT | C83: -23522 | D83: -0.004
B84: Écart Fav / (Défav) | C84: =+C76-C83 -> 1084313.4
B86: =+Parametres!B1 -> Ste-Marie Auto | C86: =Parametres!$B$3&" "&Parametres!$B$4 -> Décembre 2025 | D86: AAJ
B87: =CONCATENATE("Réalisé ",Parametres!$B$3," ",Parametres!$B$4) -> Réalisé Décembre 2025 | C87: =+C76 -> 1060791.4 | D87: =+Print_AAD!AF585 -> 5055351
B88: =CONCATENATE("Budget ",Parametres!$B$3," ",Parametres!$B$4) -> Budget Décembre 2025 | C88: =+D76 -> #REF! | D88: =+Print_AAD!Z585 -> #REF!
B89: =CONCATENATE("Réalisé ",Parametres!$B$3," ",Parametres!$B$4-1) -> Réalisé Décembre 2024 | C89: =+E76 -> 0 | D89: =+Print_AAD!AL585 -> 0

Sheet Print_Mois
C1: =Parametres!B1 -> Ste-Marie Auto | K1: Véhicules neufs | S1: =CONCATENATE("Réalisé,"," ",Parametres!B3," ",Parametres!B4) -> Réalisé, Décembre 2025
D2: X | E2: O | F2: U | J2: NB | L2: $ | O2: NB | Q2: $ | V2: *** NE PAS EFFACER / Pour An Précédente ***
D3: BUDGET ORIGINAL | J3: RÉALISATION | M3: ÉCART réel / Budget | O3: ANNÉE PRÉCÉDENTE | R3: ECART (réel/ Ann.Préc.) | V3: NEUF | W3: 0.45
D4: UNITE | E4: $P/UNITÉ | F4: $PROFITS | J4: UNITÉS | K4: $P/UNITE | L4: $PROFITS | M4: UNITÉS | N4: $PROFITS | O4: UNITÉS | P4: $P/UNITE | Q4: $PROFITS | R4: UNITÉS | S4: $PROFITS | V4: USAGE | W4: 0.1
A5: Véhicules neufsVentes nettes | B5: Véhicules neufs | C5: Ventes nettes | F5: =+INDEX('Budget original'!$A$2:$AO$501,MATCH($A5,'Budget original'!$A$2:$A$501,0),MATCH(F$2,'Budget original'!$A$2:$AO$2,0)) -> 0 | L5: =-SUMIFS(BV_Data_An_Cour!$AM:$AM,BV_Data_An_Cour!$AS:$AS,"Oui",BV_Data_An_Cour!$AP:$AP,$B5) -> 7771980 | Q5: =-SUMIFS(BV_Data_An_Prec!$AM:$AM,BV_Data_An_Prec!$AS:$AS,"Oui",BV_Data_An_Prec!$AP:$AP,$B5) -> 0 | V5: SERVICE | W5: 0.225
A6: Véhicules neufsAutos détail | B6: Véhicules neufs | C6: Autos détail | D6: =+INDEX('Budget original'!$A$2:$AO$501,MATCH($A6,'Budget original'!$A$2:$A$501,0),MATCH(D$2,'Budget original'!$A$2:$AO$2,0)) -> 0 | E6: =IF(D6=0,0,F6/D6) -> 0 | F6: =+INDEX('Budget original'!$A$2:$AO$501,MATCH($A6,'Budget original'!$A$2:$A$501,0),MATCH(F$2,'Budget original'!$A$2:$AO$2,0)) -> 0 | J6: =SUMIFS(BV_Data_An_Cour!$AW:$AW,BV_Data_An_Cour!$AP:$AP,$B6,BV_Data_An_Cour!$AQ:$AQ,$C6,BV_Data_An_Cour!$AY:$AY,J$2) -> 0 | K6: =IF(J6=0,0,L6/J6) -> 0 | L6: =-SUMIFS(BV_Data_An_Cour!$AM:$AM,BV_Data_An_Cour!$AP:$AP,$B6,BV_Data_An_Cour!$AQ:$AQ,$C6,BV_Data_An_Cour!$AR:$AR,L$2) -> 0 | M6: =J6-D6 -> 0 | N6: =L6-F6 -> 0 | O6: =SUMIFS(BV_Data_An_Prec!$AW:$AW,BV_Data_An_Prec!$AP:$AP,$B6,BV_Data_An_Prec!$AQ:$AQ,$C6,BV_Data_An_Prec!$AY:$AY,O$2) -> 0 | P6: =IF(O6=0,0,Q6/O6) -> 0 | Q6: =-SUMIFS(BV_Data_An_Prec!$AM:$AM,BV_Data_An_Prec!$AP:$AP,$B6,BV_Data_An_Prec!$AQ:$AQ,$C6,BV_Data_An_Prec!$AR:$AR,Q$2) -> 0 | R6: =J6-O6 -> 0 | S6: =L6-Q6 -> 0 | V6: CARROSSERIE | W6: 0.025
A7: Véhicules neufsCamions détail | B7: Véhicules neufs | C7: Camions détail | D7: =+INDEX('Budget original'!$A$2:$AO$501,MATCH($A7,'Budget original'!$A$2:$A$501,0),MATCH(D$2,'Budget original'!$A$2:$AO$2,0)) -> 0 | E7: =IF(D7=0,0,F7/D7) -> 0 | F7: =+INDEX('Budget original'!$A$2:$AO$501,MATCH($A7,'Budget original'!$A$2:$A$501,0),MATCH(F$2,'Budget original'!$A$2:$AO$2,0)) -> 0 | J7: =SUMIFS(BV_Data_An_Cour!$AW:$AW,BV_Data_An_Cour!$AP:$AP,$B7,BV_Data_An_Cour!$AQ:$AQ,$C7,BV_Data_An_Cour!$AY:$AY,J$2) -> 37 | K7: =IF(J7=0,0,L7/J7) -> 1976.2027 | L7: =-SUMIFS(BV_Data_An_Cour!$AM:$AM,BV_Data_An_Cour!$AP:$AP,$B7,BV_Data_An_Cour!$AQ:$AQ,$C7,BV_Data_An_Cour!$AR:$AR,L$2) -> 73119.5 | M7: =J7-D7 -> 37 | N7: =L7-F7 -> 73119.5 | O7: =SUMIFS(BV_Data_An_Prec!$AW:$AW,BV_Data_An_Prec!$AP:$AP,$B7,BV_Data_An_Prec!$AQ:$AQ,$C7,BV_Data_An_Prec!$AY:$AY,O$2) -> 0 | P7: =IF(O7=0,0,Q7/O7) -> 0 | Q7: =-SUMIFS(BV_Data_An_Prec!$AM:$AM,BV_Data_An_Prec!$AP:$AP,$B7,BV_Data_An_Prec!$AQ:$AQ,$C7,BV_Data_An_Prec!$AR:$AR,Q$2) -> 0 | R7: =J7-O7 -> 37 | S7: =L7-Q7 -> 73119.5 | V7: PIECES | W7: 0.2
A8: Véhicules neufsSprinter | B8: Véhicules neufs | C8: Voitures electriques | D8: =+INDEX('Budget original'!$A$2:$AO$501,MATCH($A8,'Budget original'!$A$2:$A$501,0),MATCH(D$2,'Budget original'!$A$2:$AO$2,0)) -> 0 | E8: =IF(D8=0,0,F8/D8) -> 0 | F8: =+INDEX('Budget original'!$A$2:$AO$501,MATCH($A8,'Budget original'!$A$2:$A$501,0),MATCH(F$2,'Budget original'!$A$2:$AO$2,0)) -> 0 | J8: =SUMIFS(BV_Data_An_Cour!$AW:$AW,BV_Data_An_Cour!$AP:$AP,$B8,BV_Data_An_Cour!$AQ:$AQ,$C8,BV_Data_An_Cour!$AY:$AY,J$2) -> 0 | K8: =IF(J8=0,0,L8/J8) -> 0 | L8: =-SUMIFS(BV_Data_An_Cour!$AM:$AM,BV_Data_An_Cour!$AP:$AP,$B8,BV_Data_An_Cour!$AQ:$AQ,$C8,BV_Data_An_Cour!$AR:$AR,L$2) -> 0 | M8: =J8-D8 -> 0 | N8: =L8-F8 -> 0 | O8: =SUMIFS(BV_Data_An_Prec!$AW:$AW,BV_Data_An_Prec!$AP:$AP,$B8,BV_Data_An_Prec!$AQ:$AQ,$C8,BV_Data_An_Prec!$AY:$AY,O$2) -> 0 | P8: =IF(O8=0,0,Q8/O8) -> 0 | Q8: =-SUMIFS(BV_Data_An_Prec!$AM:$AM,BV_Data_An_Prec!$AP:$AP,$B8,BV_Data_An_Prec!$AQ:$AQ,$C8,BV_Data_An_Prec!$AR:$AR,Q$2) -> 0 | R8: =J8-O8 -> 0 | S8: =L8-Q8 -> 0 | W8: =SUM(W3:W7) -> 1
A9: Véhicules neufsMoto détail | B9: Véhicules neufs | C9: Camions electriques | D9: =+INDEX('Budget original'!$A$2:$AO$501,MATCH($A9,'Budget original'!$A$2:$A$501,0),MATCH(D$2,'Budget original'!$A$2:$AO$2,0)) -> 0 | E9: =IF(D9=0,0,F9/D9) -> 0 | F9: =+INDEX('Budget original'!$A$2:$AO$501,MATCH($A9,'Budget original'!$A$2:$A$501,0),MATCH(F$2,'Budget original'!$A$2:$AO$2,0)) -> 0 | J9: =SUMIFS(BV_Data_An_Cour!$AW:$AW,BV_Data_An_Cour!$AP:$AP,$B9,BV_Data_An_Cour!$AQ:$AQ,$C9,BV_Data_An_Cour!$AY:$AY,J$2) -> 17 | K9: =IF(J9=0,0,L9/J9) -> 436.17706 | L9: =-SUMIFS(BV_Data_An_Cour!$AM:$AM,BV_Data_An_Cour!$AP:$AP,$B9,BV_Data_An_Cour!$AQ:$AQ,$C9,BV_Data_An_Cour!$AR:$AR,L$2) -> 7415.01 | M9: =J9-D9 -> 17 | N9: =L9-F9 -> 7415.01 | O9: =SUMIFS(BV_Data_An_Prec!$AW:$AW,BV_Data_An_Prec!$AP:$AP,$B9,BV_Data_An_Prec!$AQ:$AQ,$C9,BV_Data_An_Prec!$AY:$AY,O$2) -> 0 | P9: =IF(O9=0,0,Q9/O9) -> 0 | Q9: =-SUMIFS(BV_Data_An_Prec!$AM:$AM,BV_Data_An_Prec!$AP:$AP,$B9,BV_Data_An_Prec!$AQ:$AQ,$C9,BV_Data_An_Prec!$AR:$AR,Q$2) -> 0 | R9: =J9-O9 -> 17 | S9: =L9-Q9 -> 7415.01
A10: Véhicules neufs[...] | B10: Véhicules neufs | C10: [...] | D10: =+INDEX('Budget original'!$A$2:$AO$501,MATCH($A10,'Budget original'!$A$2:$A$501,0),MATCH(D$2,'Budget original'!$A$2:$AO$2,0)) -> 0 | E10: =IF(D10=0,0,F10/D10) -> 0 | F10: =+INDEX('Budget original'!$A$2:$AO$501,MATCH($A10,'Budget original'!$A$2:$A$501,0),MATCH(F$2,'Budget original'!$A$2:$AO$2,0)) -> 0 | J10: =-SUMIFS(BV_Data_An_Cour!$AM:$AM,BV_Data_An_Cour!$AP:$AP,$B10,BV_Data_An_Cour!$AQ:$AQ,$C10,BV_Data_An_Cour!$AR:$AR,J$2) -> 0 | K10: =IF(J10=0,0,L10/J10) -> 0 | L10: =-SUMIFS(BV_Data_An_Cour!$AM:$AM,BV_Data_An_Cour!$AP:$AP,$B10,BV_Data_An_Cour!$AQ:$AQ,$C10,BV_Data_An_Cour!$AR:$AR,L$2) -> 0 | M10: =J10-D10 -> 0 | N10: =L10-F10 -> 0 | O10: =-SUMIFS(BV_Data_An_Prec!$AM:$AM,BV_Data_An_Prec!$AP:$AP,$B10,BV_Data_An_Prec!$AQ:$AQ,$C10,BV_Data_An_Prec!$AR:$AR,O$2) -> 0 | P10: =IF(O10=0,0,Q10/O10) -> 0 | Q10: =-SUMIFS(BV_Data_An_Prec!$AM:$AM,BV_Data_An_Prec!$AP:$AP,$B10,BV_Data_An_Prec!$AQ:$AQ,$C10,BV_Data_An_Prec!$AR:$AR,Q$2) -> 0 | R10: =J10-O10 -> 0 | S10: =L10-Q10 -> 0
A11: Véhicules neufs[...] | B11: Véhicules neufs | C11: [...] | D11: =+INDEX('Budget original'!$A$2:$AO$501,MATCH($A11,'Budget original'!$A$2:$A$501,0),MATCH(D$2,'Budget original'!$A$2:$AO$2,0)) -> 0 | E11: =IF(D11=0,0,F11/D11) -> 0 | F11: =+INDEX('Budget original'!$A$2:$AO$501,MATCH($A11,'Budget original'!$A$2:$A$501,0),MATCH(F$2,'Budget original'!$A$2:$AO$2,0)) -> 0 | J11: =-SUMIFS(BV_Data_An_Cour!$AM:$AM,BV_Data_An_Cour!$AP:$AP,$B11,BV_Data_An_Cour!$AQ:$AQ,$C11,BV_Data_An_Cour!$AR:$AR,J$2) -> 0 | K11: =IF(J11=0,0,L11/J11) -> 0 | L11: =-SUMIFS(BV_Data_An_Cour!$AM:$AM,BV_Data_An_Cour!$AP:$AP,$B11,BV_Data_An_Cour!$AQ:$AQ,$C11,BV_Data_An_Cour!$AR:$AR,L$2) -> 0 | M11: =J11-D11 -> 0 | N11: =L11-F11 -> 0 | O11: =-SUMIFS(BV_Data_An_Prec!$AM:$AM,BV_Data_An_Prec!$AP:$AP,$B11,BV_Data_An_Prec!$AQ:$AQ,$C11,BV_Data_An_Prec!$AR:$AR,O$2) -> 0 | P11: =IF(O11=0,0,Q11/O11) -> 0 | Q11: =-SUMIFS(BV_Data_An_Prec!$AM:$AM,BV_Data_An_Prec!$AP:$AP,$B11,BV_Data_An_Prec!$AQ:$AQ,$C11,BV_Data_An_Prec!$AR:$AR,Q$2) -> 0 | R11: =J11-O11 -> 0 | S11: =L11-Q11 -> 0
A12: Véhicules neufs[...] | B12: Véhicules neufs | C12: [...] | D12: =+INDEX('Budget original'!$A$2:$AO$501,MATCH($A12,'Budget original'!$A$2:$A$501,0),MATCH(D$2,'Budget original'!$A$2:$AO$2,0)) -> 0 | E12: =IF(D12=0,0,F12/D12) -> 0 | F12: =+INDEX('Budget original'!$A$2:$AO$501,MATCH($A12,'Budget original'!$A$2:$A$501,0),MATCH(F$2,'Budget original'!$A$2:$AO$2,0)) -> 0 | J12: =-SUMIFS(BV_Data_An_Cour!$AM:$AM,BV_Data_An_Cour!$AP:$AP,$B12,BV_Data_An_Cour!$AQ:$AQ,$C12,BV_Data_An_Cour!$AR:$AR,J$2) -> 0 | K12: =IF(J12=0,0,L12/J12) -> 0 | L12: =-SUMIFS(BV_Data_An_Cour!$AM:$AM,BV_Data_An_Cour!$AP:$AP,$B12,BV_Data_An_Cour!$AQ:$AQ,$C12,BV_Data_An_Cour!$AR:$AR,L$2) -> 0 | M12: =J12-D12 -> 0 | N12: =L12-F12 -> 0 | O12: =-SUMIFS(BV_Data_An_Prec!$AM:$AM,BV_Data_An_Prec!$AP:$AP,$B12,BV_Data_An_Prec!$AQ:$AQ,$C12,BV_Data_An_Prec!$AR:$AR,O$2) -> 0 | P12: =IF(O12=0,0,Q12/O12) -> 0 | Q12: =-SUMIFS(BV_Data_An_Prec!$AM:$AM,BV_Data_An_Prec!$AP:$AP,$B12,BV_Data_An_Prec!$AQ:$AQ,$C12,BV_Data_An_Prec!$AR:$AR,Q$2) -> 0 | R12: =J12-O12 -> 0 | S12: =L12-Q12 -> 0
A13: Véhicules neufsTotal Neufs | B13: Véhicules neufs | C13: Total Neufs | D13: =+SUM(D6:D12) -> 0 | E13: =IF(D13<=0,0,F13/D13) -> 0 | F13: =+SUM(F6:F12) -> 0 | J13: =+SUM(J6:J12) -> 54 | K13: =IF(J13<=0,0,L13/J13) -> 1491.3798 | L13: =+SUM(L6:L12) -> 80534.51 | M13: =+SUM(M6:M12) -> 54 | N13: =+SUM(N6:N12) -> 80534.51 | O13: =+SUM(O6:O12) -> 0 | P13: =IF(O13<=0,0,Q13/O13) -> 0 | Q13: =+SUM(Q6:Q12) -> 0 | R13: =+SUM(R6:R12) -> 54 | S13: =+SUM(S6:S12) -> 80534.51
A14: Véhicules neufs | B14: Véhicules neufs | M14: =IF(D13=0,0,M13/D13) -> 0 | N14: =IF(F13=0,0,N13/F13) -> 0 | R14: =R13/O13 -> #DIV/0! | S14: =IF(Q13=0,0,(S13/Q13)) -> 0 | AD14: 20 | AE14: 1000 | AF14: =AD14*AE14 -> 20000
A15: Véhicules neufsEx-Démos et courtoisies | B15: Véhicules neufs | C15: Ex-Démos et courtoisies | D15: =+INDEX('Budget original'!$A$2:$AO$501,MATCH($A15,'Budget original'!$A$2:$A$501,0),MATCH(D$2,'Budget original'!$A$2:$AO$2,0)) -> 0 | E15: =IF(D15=0,0,F15/D15) -> 0 | F15: =+INDEX('Budget original'!$A$2:$AO$501,MATCH($A15,'Budget original'!$A$2:$A$501,0),MATCH(F$2,'Budget original'!$A$2:$AO$2,0)) -> 0 | J15: =SUMIFS(BV_Data_An_Cour!$AW:$AW,BV_Data_An_Cour!$AP:$AP,$B15,BV_Data_An_Cour!$AQ:$AQ,$C15,BV_Data_An_Cour!$AY:$AY,J$2) -> 0 | K15: =IF(J15=0,0,L15/J15) -> 0 | L15: =-SUMIFS(BV_Data_An_Cour!$AM:$AM,BV_Data_An_Cour!$AP:$AP,$B15,BV_Data_An_Cour!$AQ:$AQ,$C15,BV_Data_An_Cour!$AR:$AR,L$2) -> 0 | M15: =J15-D15 -> 0 | N15: =L15-F15 -> 0 | O15: =SUMIFS(BV_Data_An_Prec!$AW:$AW,BV_Data_An_Prec!$AP:$AP,$B15,BV_Data_An_Prec!$AQ:$AQ,$C15,BV_Data_An_Prec!$AY:$AY,O$2) -> 0 | P15: =IF(O15=0,0,Q15/O15) -> 0 | Q15: =-SUMIFS(BV_Data_An_Prec!$AM:$AM,BV_Data_An_Prec!$AP:$AP,$B15,BV_Data_An_Prec!$AQ:$AQ,$C15,BV_Data_An_Prec!$AR:$AR,Q$2) -> 0 | R15: =J15-O15 -> 0 | S15: =L15-Q15 -> 0 | AD15: 25 | AE15: =AF15/AD15 -> 800 | AF15: =AF14 -> 20000
A16: Véhicules neufs | B16: Véhicules neufs
A17: Véhicules neufsFlottes | B17: Véhicules neufs | C17: Flottes | D17: =+INDEX('Budget original'!$A$2:$AO$501,MATCH($A17,'Budget original'!$A$2:$A$501,0),MATCH(D$2,'Budget original'!$A$2:$AO$2,0)) -> 0 | E17: =IF(D17=0,0,F17/D17) -> 0 | F17: =+INDEX('Budget original'!$A$2:$AO$501,MATCH($A17,'Budget original'!$A$2:$A$501,0),MATCH(F$2,'Budget original'!$A$2:$AO$2,0)) -> 0 | J17: =SUMIFS(BV_Data_An_Cour!$AW:$AW,BV_Data_An_Cour!$AP:$AP,$B17,BV_Data_An_Cour!$AQ:$AQ,$C17,BV_Data_An_Cour!$AY:$AY,J$2) -> 63 | K17: =IF(J17=0,0,L17/J17) -> 79.291587 | L17: =-SUMIFS(BV_Data_An_Cour!$AM:$AM,BV_Data_An_Cour!$AP:$AP,$B17,BV_Data_An_Cour!$AQ:$AQ,$C17,BV_Data_An_Cour!$AR:$AR,L$2) -> 4995.37 | M17: =J17-D17 -> 63 | N17: =L17-F17 -> 4995.37 | O17: =SUMIFS(BV_Data_An_Prec!$AW:$AW,BV_Data_An_Prec!$AP:$AP,$B17,BV_Data_An_Prec!$AQ:$AQ,$C17,BV_Data_An_Prec!$AY:$AY,O$2) -> 0 | P17: =IF(O17=0,0,Q17/O17) -> 0 | Q17: =-SUMIFS(BV_Data_An_Prec!$AM:$AM,BV_Data_An_Prec!$AP:$AP,$B17,BV_Data_An_Prec!$AQ:$AQ,$C17,BV_Data_An_Prec!$AR:$AR,Q$2) -> 0 | R17: =J17-O17 -> 63 | S17: =L17-Q17 -> 4995.37
A18: Véhicules neufs | B18: Véhicules neufs
A19: Véhicules neufsRachat bail | B19: Véhicules neufs
A20: Véhicules neufs | B20: Véhicules neufs
A21: Véhicules neufsRev. Finances | B21: Véhicules neufs | C21: Rev. Finances | D21: =+INDEX('Budget original'!$A$2:$AO$501,MATCH($A21,'Budget original'!$A$2:$A$501,0),MATCH(D$2,'Budget original'!$A$2:$AO$2,0)) -> 0 | E21: =IF(D21=0,0,F21/D21) -> 0 | F21: =+INDEX('Budget original'!$A$2:$AO$501,MATCH($A21,'Budget original'!$A$2:$A$501,0),MATCH(F$2,'Budget original'!$A$2:$AO$2,0)) -> 0 | K21: =IF(J13=0,0,L21/(J13+J15)) -> 22.222222 | L21: =-SUMIFS(BV_Data_An_Cour!$AM:$AM,BV_Data_An_Cour!$AP:$AP,$B21,BV_Data_An_Cour!$AQ:$AQ,$C21,BV_Data_An_Cour!$AR:$AR,L$2) -> 1200 | N21: =L21-F21 -> 1200 | P21: =IF(O13=0,0,Q21/(O13+O15)) -> 0 | Q21: =-SUMIFS(BV_Data_An_Prec!$AM:$AM,BV_Data_An_Prec!$AP:$AP,$B21,BV_Data_An_Prec!$AQ:$AQ,$C21,BV_Data_An_Prec!$AR:$AR,Q$2) -> 0 | R21: =P21-K21 -> -22.222222 | S21: =L21-Q21 -> 1200
A22: Véhicules neufsRev. Protections | B22: Véhicules neufs | C22: Rev. Protections | D22: =+INDEX('Budget original'!$A$2:$AO$501,MATCH($A22,'Budget original'!$A$2:$A$501,0),MATCH(D$2,'Budget original'!$A$2:$AO$2,0)) -> 0 | E22: =IF(D22=0,0,F22/D22) -> 0 | F22: =+INDEX('Budget original'!$A$2:$AO$501,MATCH($A22,'Budget original'!$A$2:$A$501,0),MATCH(F$2,'Budget original'!$A$2:$AO$2,0)) -> 0 | K22: =IF(J13=0,0,L22/(J13+J15)) -> 620.12593 | L22: =-SUMIFS(BV_Data_An_Cour!$AM:$AM,BV_Data_An_Cour!$AP:$AP,$B22,BV_Data_An_Cour!$AQ:$AQ,$C22,BV_Data_An_Cour!$AR:$AR,L$2) -> 33486.8 | N22: =L22-F22 -> 33486.8 | P22: =IF(O13=0,0,Q22/(O13+O15)) -> 0 | Q22: =-SUMIFS(BV_Data_An_Prec!$AM:$AM,BV_Data_An_Prec!$AP:$AP,$B22,BV_Data_An_Prec!$AQ:$AQ,$C22,BV_Data_An_Prec!$AR:$AR,Q$2) -> 0 | R22: =P22-K22 -> -620.12593 | S22: =L22-Q22 -> 33486.8
A23: Véhicules neufsRev. Autres | B23: Véhicules neufs | C23: Rev. Autres | D23: =+INDEX('Budget original'!$A$2:$AO$501,MATCH($A23,'Budget original'!$A$2:$A$501,0),MATCH(D$2,'Budget original'!$A$2:$AO$2,0)) -> 0 | E23: =IF(D23=0,0,F23/D23) -> 0 | F23: =+INDEX('Budget original'!$A$2:$AO$501,MATCH($A23,'Budget original'!$A$2:$A$501,0),MATCH(F$2,'Budget original'!$A$2:$AO$2,0)) -> 0 | K23: =IF(J13=0,0,L23/(J13+J15)) -> 41.761481 | L23: =-SUMIFS(BV_Data_An_Cour!$AM:$AM,BV_Data_An_Cour!$AP:$AP,$B23,BV_Data_An_Cour!$AQ:$AQ,$C23,BV_Data_An_Cour!$AR:$AR,L$2) -> 2255.12 | N23: =L23-F23 -> 2255.12 | P23: =IF(O13=0,0,Q23/(O13+O15)) -> 0 | Q23: =-SUMIFS(BV_Data_An_Prec!$AM:$AM,BV_Data_An_Prec!$AP:$AP,$B23,BV_Data_An_Prec!$AQ:$AQ,$C23,BV_Data_An_Prec!$AR:$AR,Q$2) -> 0 | R23: =P23-K23 -> -41.761481 | S23: =L23-Q23 -> 2255.12
A24: Véhicules neufsTotal F&I | B24: Véhicules neufs | C24: Total F&I | D24: =+D15+D13 -> 0 | E24: =IF(D24<=0,0,F24/D24) -> 0 | F24: =F21+F22+F23 -> 0 | J24: =+J15+J13 -> 54 | K24: =IF(J24<=0,0,L24/J24) -> 684.10963 | L24: =L21+L22+L23 -> 36941.92 | M24: =J24-D24 -> 54 | N24: =L24-F24 -> 36941.92 | O24: =+O15+O13 -> 0 | P24: =IF(O24<=0,0,Q24/O24) -> 0 | Q24: =Q21+Q22+Q23 -> 0 | R24: =P24-K24 -> -684.10963 | S24: =L24-Q24 -> 36941.92
A25: Véhicules neufs | B25: Véhicules neufs | N25: =IF(N24=0,0,N24/F24) -> #DIV/0! | S25: =IF(Q24=0,0,(S24/Q24)) -> 0
A26: Véhicules neufs | B26: Véhicules neufs
A27: Véhicules neufsTotal Dépt. Neufs | B27: Véhicules neufs | C27: Total Dépt. Neufs | D27: =+D13+D15+D17 -> 0 | E27: =IF(D27<=0,0,F27/D27) -> 0 | F27: =F13+F17+F24+F19+F15 -> 0 | J27: =+J13+J15+J17 -> 117 | K27: =IF(J27<=0,0,L27/J27) -> 1046.7675 | L27: =L13+L17+L24+L19+L15 -> 122471.8 | M27: =J27-D27 -> 117 | N27: =L27-F27 -> 122471.8 | O27: =+O13+O15+O17 -> 0 | P27: =IF(O27<=0,0,Q27/O27) -> 0 | Q27: =Q13+Q17+Q24+Q19+Q15 -> 0 | R27: =J27-O27 -> 117 | S27: =L27-Q27 -> 122471.8
A28: Véhicules neufs | B28: Véhicules neufs | R28: =R27/O27 -> #DIV/0! | S28: =IF(Q27=0,0,S27/Q27) -> 0
A29: Véhicules neufs | B29: Véhicules neufs
A30: Véhicules neufsDEPENSES | B30: Véhicules neufs | C30: DEPENSES
A31: Véhicules neufsComm. vendeurs | B31: Véhicules neufs | C31: Comm. vendeurs | D31: =F31/(F13+F15) -> #DIV/0! | E31: =F31/D$24 -> #DIV/0! | F31: =+INDEX('Budget original'!$A$2:$AO$501,MATCH($A31,'Budget original'!$A$2:$A$501,0),MATCH(F$2,'Budget original'!$A$2:$AO$2,0)) -> 0 | J31: =L31/(L15+L13+L17) -> 0.47453054 | K31: =IF(L31=0,0,L31/J$24) -> 751.60259 | L31: =SUMIFS(BV_Data_An_Cour!$AM:$AM,BV_Data_An_Cour!$AP:$AP,$B31,BV_Data_An_Cour!$AQ:$AQ,$C31,BV_Data_An_Cour!$AR:$AR,L$2) -> 40586.54 | N31: =L31-F31 -> 40586.54 | O31: =Q31/(Q15+Q13+Q17) -> #DIV/0! | P31: =IF(Q31=0,0,Q31/O$24) -> 0 | Q31: =SUMIFS(BV_Data_An_Prec!$AM:$AM,BV_Data_An_Prec!$AP:$AP,$B31,BV_Data_An_Prec!$AQ:$AQ,$C31,BV_Data_An_Prec!$AR:$AR,Q$2) -> 0 | S31: =L31-Q31 -> 40586.54
A32: Véhicules neufsComm. F&I | B32: Véhicules neufs | C32: Comm. F&I | D32: =F32/F24 -> #DIV/0! | E32: =F32/D$24 -> #DIV/0! | F32: =+INDEX('Budget original'!$A$2:$AO$501,MATCH($A32,'Budget original'!$A$2:$A$501,0),MATCH(F$2,'Budget original'!$A$2:$AO$2,0)) -> 0 | J32: =L32/L24 -> 0.32620367 | K32: =IF(L32=0,0,L32/J$24) -> 223.15907 | L32: =SUMIFS(BV_Data_An_Cour!$AM:$AM,BV_Data_An_Cour!$AP:$AP,$B32,BV_Data_An_Cour!$AQ:$AQ,$C32,BV_Data_An_Cour!$AR:$AR,L$2) -> 12050.59 | N32: =L32-F32 -> 12050.59 | O32: =Q32/Q24 -> #DIV/0! | P32: =IF(Q32=0,0,Q32/O$24) -> 0 | Q32: =SUMIFS(BV_Data_An_Prec!$AM:$AM,BV_Data_An_Prec!$AP:$AP,$B32,BV_Data_An_Prec!$AQ:$AQ,$C32,BV_Data_An_Prec!$AR:$AR,Q$2) -> 0 | S32: =L32-Q32 -> 12050.59
A33: Véhicules neufsFrais de livraison | B33: Véhicules neufs | C33: Frais de livraison | E33: =F33/D$24 -> #DIV/0! | F33: =+INDEX('Budget original'!$A$2:$AO$501,MATCH($A33,'Budget original'!$A$2:$A$501,0),MATCH(F$2,'Budget original'!$A$2:$AO$2,0)) -> 0 | K33: =IF(L33=0,0,L33/J$24) -> -227.61833 | L33: =SUMIFS(BV_Data_An_Cour!$AM:$AM,BV_Data_An_Cour!$AP:$AP,$B33,BV_Data_An_Cour!$AQ:$AQ,$C33,BV_Data_An_Cour!$AR:$AR,L$2) -> -12291.39 | N33: =L33-F33 -> -12291.39 | P33: =IF(Q33=0,0,Q33/O$24) -> 0 | Q33: =SUMIFS(BV_Data_An_Prec!$AM:$AM,BV_Data_An_Prec!$AP:$AP,$B33,BV_Data_An_Prec!$AQ:$AQ,$C33,BV_Data_An_Prec!$AR:$AR,Q$2) -> 0 | S33: =L33-Q33 -> -12291.39
A34: Véhicules neufsService gratuit 1 | B34: Véhicules neufs | C34: Service gratuit 1 | E34: =F34/D$24 -> #DIV/0! | F34: =+INDEX('Budget original'!$A$2:$AO$501,MATCH($A34,'Budget original'!$A$2:$A$501,0),MATCH(F$2,'Budget original'!$A$2:$AO$2,0)) -> 0 | K34: =IF(L34=0,0,L34/J$24) -> 0 | L34: =SUMIFS(BV_Data_An_Cour!$AM:$AM,BV_Data_An_Cour!$AP:$AP,$B34,BV_Data_An_Cour!$AQ:$AQ,$C34,BV_Data_An_Cour!$AR:$AR,L$2) -> 0 | N34: =L34-F34 -> 0 | P34: =IF(Q34=0,0,Q34/O$24) -> 0 | Q34: =SUMIFS(BV_Data_An_Prec!$AM:$AM,BV_Data_An_Prec!$AP:$AP,$B34,BV_Data_An_Prec!$AQ:$AQ,$C34,BV_Data_An_Prec!$AR:$AR,Q$2) -> 0 | S34: =L34-Q34 -> 0
A35: Véhicules neufsEntretien stock | B35: Véhicules neufs | C35: Entretien stock | E35: =F35/D$24 -> #DIV/0! | F35: =+INDEX('Budget original'!$A$2:$AO$501,MATCH($A35,'Budget original'!$A$2:$A$501,0),MATCH(F$2,'Budget original'!$A$2:$AO$2,0)) -> 0 | K35: =IF(L35=0,0,L35/J$24) -> 0 | L35: =SUMIFS(BV_Data_An_Cour!$AM:$AM,BV_Data_An_Cour!$AP:$AP,$B35,BV_Data_An_Cour!$AQ:$AQ,$C35,BV_Data_An_Cour!$AR:$AR,L$2) -> 0 | N35: =L35-F35 -> 0 | P35: =IF(Q35=0,0,Q35/O$24) -> 0 | Q35: =SUMIFS(BV_Data_An_Prec!$AM:$AM,BV_Data_An_Prec!$AP:$AP,$B35,BV_Data_An_Prec!$AQ:$AQ,$C35,BV_Data_An_Prec!$AR:$AR,Q$2) -> 0 | S35: =L35-Q35 -> 0
A36: Véhicules neufsPublicité 1 | B36: Véhicules neufs | C36: Publicité 1 | E36: =F36/D$24 -> #DIV/0! | F36: =+INDEX('Budget original'!$A$2:$AO$501,MATCH($A36,'Budget original'!$A$2:$A$501,0),MATCH(F$2,'Budget original'!$A$2:$AO$2,0)) -> 0 | K36: =IF(L36=0,0,L36/J$24) -> -2429.652 | L36: =SUMIFS(BV_Data_An_Cour!$AM:$AM,BV_Data_An_Cour!$AP:$AP,$B36,BV_Data_An_Cour!$AQ:$AQ,$C36,BV_Data_An_Cour!$AR:$AR,L$2) -> -131201.21 | N36: =L36-F36 -> -131201.21 | P36: =IF(Q36=0,0,Q36/O$24) -> 0 | Q36: =SUMIFS(BV_Data_An_Prec!$AM:$AM,BV_Data_An_Prec!$AP:$AP,$B36,BV_Data_An_Prec!$AQ:$AQ,$C36,BV_Data_An_Prec!$AR:$AR,Q$2) -> 0 | S36: =L36-Q36 -> -131201.21
A37: Véhicules neufsIntérêt de gros | B37: Véhicules neufs | C37: Intérêt de gros | E37: =F37/D$24 -> #DIV/0! | F37: =+INDEX('Budget original'!$A$2:$AO$501,MATCH($A37,'Budget original'!$A$2:$A$501,0),MATCH(F$2,'Budget original'!$A$2:$AO$2,0)) -> 0 | K37: =IF(L37=0,0,L37/J$24) -> 1645.118 | L37: =SUMIFS(BV_Data_An_Cour!$AM:$AM,BV_Data_An_Cour!$AP:$AP,$B37,BV_Data_An_Cour!$AQ:$AQ,$C37,BV_Data_An_Cour!$AR:$AR,L$2) -> 88836.37 | N37: =L37-F37 -> 88836.37 | P37: =IF(Q37=0,0,Q37/O$24) -> 0 | Q37: =SUMIFS(BV_Data_An_Prec!$AM:$AM,BV_Data_An_Prec!$AP:$AP,$B37,BV_Data_An_Prec!$AQ:$AQ,$C37,BV_Data_An_Prec!$AR:$AR,Q$2) -> 0 | S37: =L37-Q37 -> 88836.37
A38: Véhicules neufs[...] | B38: Véhicules neufs | C38: Crédit Intérêts Floor Plan | E38: =F38/D$24 -> #DIV/0! | F38: =+INDEX('Budget original'!$A$2:$AO$501,MATCH($A38,'Budget original'!$A$2:$A$501,0),MATCH(F$2,'Budget original'!$A$2:$AO$2,0)) -> 0 | K38: =IF(L38=0,0,L38/J$24) -> -4397.7772 | L38: =SUMIFS(BV_Data_An_Cour!$AM:$AM,BV_Data_An_Cour!$AP:$AP,$B38,BV_Data_An_Cour!$AQ:$AQ,$C38,BV_Data_An_Cour!$AR:$AR,L$2) -> -237479.97 | N38: =L38-F38 -> -237479.97 | P38: =IF(Q38=0,0,Q38/O$24) -> 0 | Q38: =SUMIFS(BV_Data_An_Prec!$AM:$AM,BV_Data_An_Prec!$AP:$AP,$B38,BV_Data_An_Prec!$AQ:$AQ,$C38,BV_Data_An_Prec!$AR:$AR,Q$2) -> 0 | S38: =L38-Q38 -> -237479.97
A39: Véhicules neufs[...] | B39: Véhicules neufs | C39: Crédit Boni TD | E39: =F39/D$24 -> #DIV/0! | F39: =+INDEX('Budget original'!$A$2:$AO$501,MATCH($A39,'Budget original'!$A$2:$A$501,0),MATCH(F$2,'Budget original'!$A$2:$AO$2,0)) -> 0 | K39: =IF(L39=0,0,L39/J$24) -> 0 | L39: =SUMIFS(BV_Data_An_Cour!$AM:$AM,BV_Data_An_Cour!$AP:$AP,$B39,BV_Data_An_Cour!$AQ:$AQ,$C39,BV_Data_An_Cour!$AR:$AR,L$2) -> 0 | N39: =L39-F39 -> 0 | P39: =IF(Q39=0,0,Q39/O$24) -> 0 | Q39: =SUMIFS(BV_Data_An_Prec!$AM:$AM,BV_Data_An_Prec!$AP:$AP,$B39,BV_Data_An_Prec!$AQ:$AQ,$C39,BV_Data_An_Prec!$AR:$AR,Q$2) -> 0 | S39: =L39-Q39 -> 0
A40: Véhicules neufs[...] | B40: Véhicules neufs | C40: [...] | E40: =F40/D$24 -> #DIV/0! | F40: =+INDEX('Budget original'!$A$2:$AO$501,MATCH($A40,'Budget original'!$A$2:$A$501,0),MATCH(F$2,'Budget original'!$A$2:$AO$2,0)) -> 0 | K40: =IF(L40=0,0,L40/J$24) -> 0 | L40: =SUMIFS(BV_Data_An_Cour!$AM:$AM,BV_Data_An_Cour!$AP:$AP,$B40,BV_Data_An_Cour!$AQ:$AQ,$C40,BV_Data_An_Cour!$AR:$AR,L$2) -> 0 | N40: =L40-F40 -> 0 | P40: =IF(Q40=0,0,Q40/O$24) -> 0 | Q40: =SUMIFS(BV_Data_An_Prec!$AM:$AM,BV_Data_An_Prec!$AP:$AP,$B40,BV_Data_An_Prec!$AQ:$AQ,$C40,BV_Data_An_Prec!$AR:$AR,Q$2) -> 0 | S40: =L40-Q40 -> 0
A41: Véhicules neufsTOTAL VARIABLES | B41: Véhicules neufs | C41: TOTAL VARIABLES | D41: % brut | E41: =F41/F$27 -> #DIV/0! | F41: =SUM(F31:F40) -> 0 | J41: % brut | K41: =L41/L$27 -> -1.9555446 | L41: =SUM(L31:L40) -> -239499.07 | N41: =L41-F41 -> -239499.07 | O41: % brut | P41: =Q41/Q$27 -> #DIV/0! | Q41: =SUM(Q31:Q40) -> 0 | S41: =L41-Q41 -> -239499.07
A42: Véhicules neufsSalaires cadres | B42: Véhicules neufs | C42: Salaires cadres | F42: =+INDEX('Budget original'!$A$2:$AO$501,MATCH($A42,'Budget original'!$A$2:$A$501,0),MATCH(F$2,'Budget original'!$A$2:$AO$2,0)) -> 0 | L42: =SUMIFS(BV_Data_An_Cour!$AM:$AM,BV_Data_An_Cour!$AP:$AP,$B42,BV_Data_An_Cour!$AQ:$AQ,$C42,BV_Data_An_Cour!$AR:$AR,L$2) -> 19931.38 | N42: =L42-F42 -> 19931.38 | Q42: =SUMIFS(BV_Data_An_Prec!$AM:$AM,BV_Data_An_Prec!$AP:$AP,$B42,BV_Data_An_Prec!$AQ:$AQ,$C42,BV_Data_An_Prec!$AR:$AR,Q$2) -> 0 | S42: =L42-Q42 -> 19931.38
A43: Véhicules neufsSalaires commis | B43: Véhicules neufs | C43: Salaires commis | F43: =+INDEX('Budget original'!$A$2:$AO$501,MATCH($A43,'Budget original'!$A$2:$A$501,0),MATCH(F$2,'Budget original'!$A$2:$AO$2,0)) -> 0 | L43: =SUMIFS(BV_Data_An_Cour!$AM:$AM,BV_Data_An_Cour!$AP:$AP,$B43,BV_Data_An_Cour!$AQ:$AQ,$C43,BV_Data_An_Cour!$AR:$AR,L$2) -> 28728.45 | N43: =L43-F43 -> 28728.45 | Q43: =SUMIFS(BV_Data_An_Prec!$AM:$AM,BV_Data_An_Prec!$AP:$AP,$B43,BV_Data_An_Prec!$AQ:$AQ,$C43,BV_Data_An_Prec!$AR:$AR,Q$2) -> 0 | S43: =L43-Q43 -> 28728.45
A44: Véhicules neufsSalaires autres | B44: Véhicules neufs | C44: Salaires autres | F44: =+INDEX('Budget original'!$A$2:$AO$501,MATCH($A44,'Budget original'!$A$2:$A$501,0),MATCH(F$2,'Budget original'!$A$2:$AO$2,0)) -> 0 | L44: =SUMIFS(BV_Data_An_Cour!$AM:$AM,BV_Data_An_Cour!$AP:$AP,$B44,BV_Data_An_Cour!$AQ:$AQ,$C44,BV_Data_An_Cour!$AR:$AR,L$2) -> 3322.96 | N44: =L44-F44 -> 3322.96 | Q44: =SUMIFS(BV_Data_An_Prec!$AM:$AM,BV_Data_An_Prec!$AP:$AP,$B44,BV_Data_An_Prec!$AQ:$AQ,$C44,BV_Data_An_Prec!$AR:$AR,Q$2) -> 0 | S44: =L44-Q44 -> 3322.96
A45: Véhicules neufsSalaires spécialistes | B45: Véhicules neufs | C45: Salaires spécialistes | F45: =+INDEX('Budget original'!$A$2:$AO$501,MATCH($A45,'Budget original'!$A$2:$A$501,0),MATCH(F$2,'Budget original'!$A$2:$AO$2,0)) -> 0 | L45: =SUMIFS(BV_Data_An_Cour!$AM:$AM,BV_Data_An_Cour!$AP:$AP,$B45,BV_Data_An_Cour!$AQ:$AQ,$C45,BV_Data_An_Cour!$AR:$AR,L$2) -> 0 | N45: =L45-F45 -> 0 | Q45: =SUMIFS(BV_Data_An_Prec!$AM:$AM,BV_Data_An_Prec!$AP:$AP,$B45,BV_Data_An_Prec!$AQ:$AQ,$C45,BV_Data_An_Prec!$AR:$AR,Q$2) -> 0 | S45: =L45-Q45 -> 0
A46: Véhicules neufs[...] | B46: Véhicules neufs | C46: [...] | F46: =+INDEX('Budget original'!$A$2:$AO$501,MATCH($A46,'Budget original'!$A$2:$A$501,0),MATCH(F$2,'Budget original'!$A$2:$AO$2,0)) -> 0 | L46: =SUMIFS(BV_Data_An_Cour!$AM:$AM,BV_Data_An_Cour!$AP:$AP,$B46,BV_Data_An_Cour!$AQ:$AQ,$C46,BV_Data_An_Cour!$AR:$AR,L$2) -> 0 | N46: =L46-F46 -> 0 | Q46: =SUMIFS(BV_Data_An_Prec!$AM:$AM,BV_Data_An_Prec!$AP:$AP,$B46,BV_Data_An_Prec!$AQ:$AQ,$C46,BV_Data_An_Prec!$AR:$AR,Q$2) -> 0 | S46: =L46-Q46 -> 0
A47: Véhicules neufs[...] | B47: Véhicules neufs | C47: [...] | F47: =+INDEX('Budget original'!$A$2:$AO$501,MATCH($A47,'Budget original'!$A$2:$A$501,0),MATCH(F$2,'Budget original'!$A$2:$AO$2,0)) -> 0 | L47: =SUMIFS(BV_Data_An_Cour!$AM:$AM,BV_Data_An_Cour!$AP:$AP,$B47,BV_Data_An_Cour!$AQ:$AQ,$C47,BV_Data_An_Cour!$AR:$AR,L$2) -> 0 | N47: =L47-F47 -> 0 | Q47: =SUMIFS(BV_Data_An_Prec!$AM:$AM,BV_Data_An_Prec!$AP:$AP,$B47,BV_Data_An_Prec!$AQ:$AQ,$C47,BV_Data_An_Prec!$AR:$AR,Q$2) -> 0 | S47: =L47-Q47 -> 0
A48: Véhicules neufs[...] | B48: Véhicules neufs | C48: [...] | F48: =+INDEX('Budget original'!$A$2:$AO$501,MATCH($A48,'Budget original'!$A$2:$A$501,0),MATCH(F$2,'Budget original'!$A$2:$AO$2,0)) -> 0 | L48: =SUMIFS(BV_Data_An_Cour!$AM:$AM,BV_Data_An_Cour!$AP:$AP,$B48,BV_Data_An_Cour!$AQ:$AQ,$C48,BV_Data_An_Cour!$AR:$AR,L$2) -> 0 | N48: =L48-F48 -> 0 | Q48: =SUMIFS(BV_Data_An_Prec!$AM:$AM,BV_Data_An_Prec!$AP:$AP,$B48,BV_Data_An_Prec!$AQ:$AQ,$C48,BV_Data_An_Prec!$AR:$AR,Q$2) -> 0 | S48: =L48-Q48 -> 0
A49: Véhicules neufsSalaires en absences | B49: Véhicules neufs | C49: Salaires en absences | F49: =+INDEX('Budget original'!$A$2:$AO$501,MATCH($A49,'Budget original'!$A$2:$A$501,0),MATCH(F$2,'Budget original'!$A$2:$AO$2,0)) -> 0 | L49: =SUMIFS(BV_Data_An_Cour!$AM:$AM,BV_Data_An_Cour!$AP:$AP,$B49,BV_Data_An_Cour!$AQ:$AQ,$C49,BV_Data_An_Cour!$AR:$AR,L$2) -> 1663.23 | N49: =L49-F49 -> 1663.23 | Q49: =SUMIFS(BV_Data_An_Prec!$AM:$AM,BV_Data_An_Prec!$AP:$AP,$B49,BV_Data_An_Prec!$AQ:$AQ,$C49,BV_Data_An_Prec!$AR:$AR,Q$2) -> 0 | S49: =L49-Q49 -> 1663.23
A50: Véhicules neufsDéduction à la source | B50: Véhicules neufs | C50: Déduction à la source | F50: =+INDEX('Budget original'!$A$2:$AO$501,MATCH($A50,'Budget original'!$A$2:$A$501,0),MATCH(F$2,'Budget original'!$A$2:$AO$2,0)) -> 0 | L50: =SUMIFS(BV_Data_An_Cour!$AM:$AM,BV_Data_An_Cour!$AP:$AP,$B50,BV_Data_An_Cour!$AQ:$AQ,$C50,BV_Data_An_Cour!$AR:$AR,L$2) -> 15343.14 | N50: =L50-F50 -> 15343.14 | Q50: =SUMIFS(BV_Data_An_Prec!$AM:$AM,BV_Data_An_Prec!$AP:$AP,$B50,BV_Data_An_Prec!$AQ:$AQ,$C50,BV_Data_An_Prec!$AR:$AR,Q$2) -> 0 | S50: =L50-Q50 -> 15343.14
A51: Véhicules neufsBénéfices marginaux | B51: Véhicules neufs | C51: Bénéfices marginaux | F51: =+INDEX('Budget original'!$A$2:$AO$501,MATCH($A51,'Budget original'!$A$2:$A$501,0),MATCH(F$2,'Budget original'!$A$2:$AO$2,0)) -> 0 | L51: =SUMIFS(BV_Data_An_Cour!$AM:$AM,BV_Data_An_Cour!$AP:$AP,$B51,BV_Data_An_Cour!$AQ:$AQ,$C51,BV_Data_An_Cour!$AR:$AR,L$2) -> 27024.39 | N51: =L51-F51 -> 27024.39 | Q51: =SUMIFS(BV_Data_An_Prec!$AM:$AM,BV_Data_An_Prec!$AP:$AP,$B51,BV_Data_An_Prec!$AQ:$AQ,$C51,BV_Data_An_Prec!$AR:$AR,Q$2) -> 0 | S51: =L51-Q51 -> 27024.39
A52: Véhicules neufsCsst | B52: Véhicules neufs | C52: Csst | F52: =+INDEX('Budget original'!$A$2:$AO$501,MATCH($A52,'Budget original'!$A$2:$A$501,0),MATCH(F$2,'Budget original'!$A$2:$AO$2,0)) -> 0 | L52: =SUMIFS(BV_Data_An_Cour!$AM:$AM,BV_Data_An_Cour!$AP:$AP,$B52,BV_Data_An_Cour!$AQ:$AQ,$C52,BV_Data_An_Cour!$AR:$AR,L$2) -> -7470.17 | N52: =L52-F52 -> -7470.17 | Q52: =SUMIFS(BV_Data_An_Prec!$AM:$AM,BV_Data_An_Prec!$AP:$AP,$B52,BV_Data_An_Prec!$AQ:$AQ,$C52,BV_Data_An_Prec!$AR:$AR,Q$2) -> 0 | S52: =L52-Q52 -> -7470.17
A53: Véhicules neufs[...] | B53: Véhicules neufs | C53: [...] | D53: =VLOOKUP(C53,$B$2:$B$46,1,FALSE) -> #N/A | F53: =+INDEX('Budget original'!$A$2:$AO$501,MATCH($A53,'Budget original'!$A$2:$A$501,0),MATCH(F$2,'Budget original'!$A$2:$AO$2,0)) -> 0 | L53: =SUMIFS(BV_Data_An_Cour!$AM:$AM,BV_Data_An_Cour!$AP:$AP,$B53,BV_Data_An_Cour!$AQ:$AQ,$C53,BV_Data_An_Cour!$AR:$AR,L$2) -> 0 | N53: =L53-F53 -> 0 | Q53: =SUMIFS(BV_Data_An_Prec!$AM:$AM,BV_Data_An_Prec!$AP:$AP,$B53,BV_Data_An_Prec!$AQ:$AQ,$C53,BV_Data_An_Prec!$AR:$AR,Q$2) -> 0 | S53: =L53-Q53 -> 0
A54: Véhicules neufsTOTAL PERSONNEL | B54: Véhicules neufs | C54: TOTAL PERSONNEL | D54: % brut | E54: =F54/F$27 -> #DIV/0! | F54: =+SUM(F42:F53) -> 0 | J54: % brut | K54: =L54/L$27 -> 0.72296953 | L54: =+SUM(L42:L53) -> 88543.38 | N54: =+SUM(N42:N53) -> 88543.38 | O54: % brut | P54: =Q54/Q$27 -> #DIV/0! | Q54: =+SUM(Q42:Q53) -> 0 | S54: =+SUM(S42:S53) -> 88543.38
A55: Véhicules neufsPublicité 2 | B55: Véhicules neufs | C55: Publicité 2 | F55: =+INDEX('Budget original'!$A$2:$AO$501,MATCH($A55,'Budget original'!$A$2:$A$501,0),MATCH(F$2,'Budget original'!$A$2:$AO$2,0)) -> 0 | L55: =SUMIFS(BV_Data_An_Cour!$AM:$AM,BV_Data_An_Cour!$AP:$AP,$B55,BV_Data_An_Cour!$AQ:$AQ,$C55,BV_Data_An_Cour!$AR:$AR,L$2) -> 0 | N55: =L55-F55 -> 0 | Q55: =SUMIFS(BV_Data_An_Prec!$AM:$AM,BV_Data_An_Prec!$AP:$AP,$B55,BV_Data_An_Prec!$AQ:$AQ,$C55,BV_Data_An_Prec!$AR:$AR,Q$2) -> 0 | S55: =L55-Q55 -> 0
A56: Véhicules neufsService gratuit 2 | B56: Véhicules neufs | C56: Service gratuit 2 | F56: =+INDEX('Budget original'!$A$2:$AO$501,MATCH($A56,'Budget original'!$A$2:$A$501,0),MATCH(F$2,'Budget original'!$A$2:$AO$2,0)) -> 0 | L56: =SUMIFS(BV_Data_An_Cour!$AM:$AM,BV_Data_An_Cour!$AP:$AP,$B56,BV_Data_An_Cour!$AQ:$AQ,$C56,BV_Data_An_Cour!$AR:$AR,L$2) -> 0 | N56: =L56-F56 -> 0 | Q56: =SUMIFS(BV_Data_An_Prec!$AM:$AM,BV_Data_An_Prec!$AP:$AP,$B56,BV_Data_An_Prec!$AQ:$AQ,$C56,BV_Data_An_Prec!$AR:$AR,Q$2) -> 0 | S56: =L56-Q56 -> 0
A57: Véhicules neufsFrais véhicules de cie | B57: Véhicules neufs | C57: Frais véhicules de cie | F57: =+INDEX('Budget original'!$A$2:$AO$501,MATCH($A57,'Budget original'!$A$2:$A$501,0),MATCH(F$2,'Budget original'!$A$2:$AO$2,0)) -> 0 | L57: =SUMIFS(BV_Data_An_Cour!$AM:$AM,BV_Data_An_Cour!$AP:$AP,$B57,BV_Data_An_Cour!$AQ:$AQ,$C57,BV_Data_An_Cour!$AR:$AR,L$2) -> 7762.07 | N57: =L57-F57 -> 7762.07 | Q57: =SUMIFS(BV_Data_An_Prec!$AM:$AM,BV_Data_An_Prec!$AP:$AP,$B57,BV_Data_An_Prec!$AQ:$AQ,$C57,BV_Data_An_Prec!$AR:$AR,Q$2) -> 0 | S57: =L57-Q57 -> 7762.07
A58: Véhicules neufsInformatique | B58: Véhicules neufs | C58: Informatique | F58: =+INDEX('Budget original'!$A$2:$AO$501,MATCH($A58,'Budget original'!$A$2:$A$501,0),MATCH(F$2,'Budget original'!$A$2:$AO$2,0)) -> 0 | L58: =SUMIFS(BV_Data_An_Cour!$AM:$AM,BV_Data_An_Cour!$AP:$AP,$B58,BV_Data_An_Cour!$AQ:$AQ,$C58,BV_Data_An_Cour!$AR:$AR,L$2) -> 4007.85 | N58: =L58-F58 -> 4007.85 | Q58: =SUMIFS(BV_Data_An_Prec!$AM:$AM,BV_Data_An_Prec!$AP:$AP,$B58,BV_Data_An_Prec!$AQ:$AQ,$C58,BV_Data_An_Prec!$AR:$AR,Q$2) -> 0 | S58: =L58-Q58 -> 4007.85
A59: Véhicules neufsFrais de déplacement | B59: Véhicules neufs | C59: Frais de déplacement | F59: =+INDEX('Budget original'!$A$2:$AO$501,MATCH($A59,'Budget original'!$A$2:$A$501,0),MATCH(F$2,'Budget original'!$A$2:$AO$2,0)) -> 0 | L59: =SUMIFS(BV_Data_An_Cour!$AM:$AM,BV_Data_An_Cour!$AP:$AP,$B59,BV_Data_An_Cour!$AQ:$AQ,$C59,BV_Data_An_Cour!$AR:$AR,L$2) -> -4684.22 | N59: =L59-F59 -> -4684.22 | Q59: =SUMIFS(BV_Data_An_Prec!$AM:$AM,BV_Data_An_Prec!$AP:$AP,$B59,BV_Data_An_Prec!$AQ:$AQ,$C59,BV_Data_An_Prec!$AR:$AR,Q$2) -> 0 | S59: =L59-Q59 -> -4684.22
A60: Véhicules neufsServices extérieurs | B60: Véhicules neufs | C60: Services extérieurs | F60: =+INDEX('Budget original'!$A$2:$AO$501,MATCH($A60,'Budget original'!$A$2:$A$501,0),MATCH(F$2,'Budget original'!$A$2:$AO$2,0)) -> 0 | L60: =SUMIFS(BV_Data_An_Cour!$AM:$AM,BV_Data_An_Cour!$AP:$AP,$B60,BV_Data_An_Cour!$AQ:$AQ,$C60,BV_Data_An_Cour!$AR:$AR,L$2) -> 5658.47 | N60: =L60-F60 -> 5658.47 | Q60: =SUMIFS(BV_Data_An_Prec!$AM:$AM,BV_Data_An_Prec!$AP:$AP,$B60,BV_Data_An_Prec!$AQ:$AQ,$C60,BV_Data_An_Prec!$AR:$AR,Q$2) -> 0 | S60: =L60-Q60 -> 5658.47
A61: Véhicules neufsFournitures autres | B61: Véhicules neufs | C61: Fournitures autres | F61: =+INDEX('Budget original'!$A$2:$AO$501,MATCH($A61,'Budget original'!$A$2:$A$501,0),MATCH(F$2,'Budget original'!$A$2:$AO$2,0)) -> 0 | L61: =SUMIFS(BV_Data_An_Cour!$AM:$AM,BV_Data_An_Cour!$AP:$AP,$B61,BV_Data_An_Cour!$AQ:$AQ,$C61,BV_Data_An_Cour!$AR:$AR,L$2) -> 106.03 | N61: =L61-F61 -> 106.03 | Q61: =SUMIFS(BV_Data_An_Prec!$AM:$AM,BV_Data_An_Prec!$AP:$AP,$B61,BV_Data_An_Prec!$AQ:$AQ,$C61,BV_Data_An_Prec!$AR:$AR,Q$2) -> 0 | S61: =L61-Q61 -> 106.03
A62: Véhicules neufsUniformes | B62: Véhicules neufs | C62: Uniformes | F62: =+INDEX('Budget original'!$A$2:$AO$501,MATCH($A62,'Budget original'!$A$2:$A$501,0),MATCH(F$2,'Budget original'!$A$2:$AO$2,0)) -> 0 | L62: =SUMIFS(BV_Data_An_Cour!$AM:$AM,BV_Data_An_Cour!$AP:$AP,$B62,BV_Data_An_Cour!$AQ:$AQ,$C62,BV_Data_An_Cour!$AR:$AR,L$2) -> 0 | N62: =L62-F62 -> 0 | Q62: =SUMIFS(BV_Data_An_Prec!$AM:$AM,BV_Data_An_Prec!$AP:$AP,$B62,BV_Data_An_Prec!$AQ:$AQ,$C62,BV_Data_An_Prec!$AR:$AR,Q$2) -> 0 | S62: =L62-Q62 -> 0
A63: Véhicules neufsPapeterie | B63: Véhicules neufs | C63: Papeterie | F63: =+INDEX('Budget original'!$A$2:$AO$501,MATCH($A63,'Budget original'!$A$2:$A$501,0),MATCH(F$2,'Budget original'!$A$2:$AO$2,0)) -> 0 | L63: =SUMIFS(BV_Data_An_Cour!$AM:$AM,BV_Data_An_Cour!$AP:$AP,$B63,BV_Data_An_Cour!$AQ:$AQ,$C63,BV_Data_An_Cour!$AR:$AR,L$2) -> 2616.03 | N63: =L63-F63 -> 2616.03 | Q63: =SUMIFS(BV_Data_An_Prec!$AM:$AM,BV_Data_An_Prec!$AP:$AP,$B63,BV_Data_An_Prec!$AQ:$AQ,$C63,BV_Data_An_Prec!$AR:$AR,Q$2) -> 0 | S63: =L63-Q63 -> 2616.03
A64: Véhicules neufsTéléphone | B64: Véhicules neufs | C64: Téléphone | F64: =+INDEX('Budget original'!$A$2:$AO$501,MATCH($A64,'Budget original'!$A$2:$A$501,0),MATCH(F$2,'Budget original'!$A$2:$AO$2,0)) -> 0 | L64: =SUMIFS(BV_Data_An_Cour!$AM:$AM,BV_Data_An_Cour!$AP:$AP,$B64,BV_Data_An_Cour!$AQ:$AQ,$C64,BV_Data_An_Cour!$AR:$AR,L$2) -> 312.32 | N64: =L64-F64 -> 312.32 | Q64: =SUMIFS(BV_Data_An_Prec!$AM:$AM,BV_Data_An_Prec!$AP:$AP,$B64,BV_Data_An_Prec!$AQ:$AQ,$C64,BV_Data_An_Prec!$AR:$AR,Q$2) -> 0 | S64: =L64-Q64 -> 312.32
A65: Véhicules neufsFrais postaux | B65: Véhicules neufs | C65: Frais postaux | F65: =+INDEX('Budget original'!$A$2:$AO$501,MATCH($A65,'Budget original'!$A$2:$A$501,0),MATCH(F$2,'Budget original'!$A$2:$AO$2,0)) -> 0 | L65: =SUMIFS(BV_Data_An_Cour!$AM:$AM,BV_Data_An_Cour!$AP:$AP,$B65,BV_Data_An_Cour!$AQ:$AQ,$C65,BV_Data_An_Cour!$AR:$AR,L$2) -> 1611.42 | N65: =L65-F65 -> 1611.42 | Q65: =SUMIFS(BV_Data_An_Prec!$AM:$AM,BV_Data_An_Prec!$AP:$AP,$B65,BV_Data_An_Prec!$AQ:$AQ,$C65,BV_Data_An_Prec!$AR:$AR,Q$2) -> 0 | S65: =L65-Q65 -> 1611.42
A66: Véhicules neufsDivers | B66: Véhicules neufs | C66: Divers | F66: =+INDEX('Budget original'!$A$2:$AO$501,MATCH($A66,'Budget original'!$A$2:$A$501,0),MATCH(F$2,'Budget original'!$A$2:$AO$2,0)) -> 0 | L66: =SUMIFS(BV_Data_An_Cour!$AM:$AM,BV_Data_An_Cour!$AP:$AP,$B66,BV_Data_An_Cour!$AQ:$AQ,$C66,BV_Data_An_Cour!$AR:$AR,L$2) -> 4754.81 | N66: =L66-F66 -> 4754.81 | Q66: =SUMIFS(BV_Data_An_Prec!$AM:$AM,BV_Data_An_Prec!$AP:$AP,$B66,BV_Data_An_Prec!$AQ:$AQ,$C66,BV_Data_An_Prec!$AR:$AR,Q$2) -> 0 | S66: =L66-Q66 -> 4754.81
... A68: Véhicules neufsFrais bancaires | B68: Véhicules neufs | C68: Frais bancaires | F68: =+INDEX('Budget original'!$A$2:$AO$501,MATCH($A68,'Budget original'!$A$2:$A$501,0),MATCH(F$2,'Budget original'!$A$2:$AO$2,0)) -> 0 | L68: =SUMIFS(BV_Data_An_Cour!$AM:$AM,BV_Data_An_Cour!$AP:$AP,$B68,BV_Data_An_Cour!$AQ:$AQ,$C68,BV_Data_An_Cour!$AR:$AR,L$2) -> 1669.72 | N68: =L68-F68 -> 1669.72 | Q68: =SUMIFS(BV_Data_An_Prec!$AM:$AM,BV_Data_An_Prec!$AP:$AP,$B68,BV_Data_An_Prec!$AQ:$AQ,$C68,BV_Data_An_Prec!$AR:$AR,Q$2) -> 0 | S68: =L68-Q68 -> 1669.72
A69: Véhicules neufs[...] | B69: Véhicules neufs | C69: [...] | F69: =+INDEX('Budget original'!$A$2:$AO$501,MATCH($A69,'Budget original'!$A$2:$A$501,0),MATCH(F$2,'Budget original'!$A$2:$AO$2,0)) -> 0 | N69: =L69-F69 -> 0 | S69: =L69-Q69 -> 0
A70: Véhicules neufs[...] | B70: Véhicules neufs | C70: [...] | F70: =+INDEX('Budget original'!$A$2:$AO$501,MATCH($A70,'Budget original'!$A$2:$A$501,0),MATCH(F$2,'Budget original'!$A$2:$AO$2,0)) -> 0 | L70: =SUMIFS(BV_Data_An_Cour!$AM:$AM,BV_Data_An_Cour!$AP:$AP,$B70,BV_Data_An_Cour!$AQ:$AQ,$C70,BV_Data_An_Cour!$AR:$AR,L$2) -> 0 | N70: =L70-F70 -> 0 | Q70: =SUMIFS(BV_Data_An_Prec!$AM:$AM,BV_Data_An_Prec!$AP:$AP,$B70,BV_Data_An_Prec!$AQ:$AQ,$C70,BV_Data_An_Prec!$AR:$AR,Q$2) -> 0 | S70: =L70-Q70 -> 0
A71: Véhicules neufs[...] | B71: Véhicules neufs | C71: [...] | F71: =+INDEX('Budget original'!$A$2:$AO$501,MATCH($A71,'Budget original'!$A$2:$A$501,0),MATCH(F$2,'Budget original'!$A$2:$AO$2,0)) -> 0 | L71: =SUMIFS(BV_Data_An_Cour!$AM:$AM,BV_Data_An_Cour!$AP:$AP,$B71,BV_Data_An_Cour!$AQ:$AQ,$C71,BV_Data_An_Cour!$AR:$AR,L$2)*0.32 -> 0 | N71: =L71-F71 -> 0 | Q71: =SUMIFS(BV_Data_An_Prec!$AM:$AM,BV_Data_An_Prec!$AP:$AP,$B71,BV_Data_An_Prec!$AQ:$AQ,$C71,BV_Data_An_Prec!$AR:$AR,Q$2)*0.32 -> 0 | S71: =L71-Q71 -> 0
A72: Véhicules neufsTOTAL SEMI-FIXES | B72: Véhicules neufs | C72: TOTAL SEMI-FIXES | D72: % brut | E72: =F72/F$27 -> #DIV/0! | F72: =+SUM(F55:F71) -> 0 | J72: % brut | K72: =L72/L$27 -> 0.20065435 | L72: =+SUM(L55:L71) -> 24574.5 | N72: =+SUM(N55:N71) -> 24574.5 | O72: % brut | P72: =Q72/Q$27 -> #DIV/0! | Q72: =+SUM(Q55:Q71) -> 0 | S72: =+SUM(S55:S71) -> 24574.5
A73: Véhicules neufs | B73: Véhicules neufs
A74: Véhicules neufsTOTAL DES DÉPENSES | B74: Véhicules neufs | C74: TOTAL DES DÉPENSES | D74: % brut | E74: =F74/F$27 -> #DIV/0! | F74: =F41+F54+F72 -> 0 | J74: % brut | K74: =L74/L$27 -> -1.0319207 | L74: =L41+L54+L72 -> -126381.19 | N74: =L74-F74 -> -126381.19 | O74: % brut | P74: =Q74/Q$27 -> #DIV/0! | Q74: =Q41+Q54+Q72 -> 0 | S74: =L74-Q74 -> -126381.19
A75: Véhicules neufsProgramme neuf 1 | B75: Véhicules neufs | C75: Programme Excellence | F75: =+INDEX('Budget original'!$A$2:$AO$501,MATCH($A75,'Budget original'!$A$2:$A$501,0),MATCH(F$2,'Budget original'!$A$2:$AO$2,0)) -> 0 | L75: =-SUMIFS(BV_Data_An_Cour!$AM:$AM,BV_Data_An_Cour!$AP:$AP,$B75,BV_Data_An_Cour!$AQ:$AQ,$C75,BV_Data_An_Cour!$AR:$AR,L$2)-L157 -> 5621.93 | N75: =L75-F75 -> 5621.93 | Q75: =-SUMIFS(BV_Data_An_Prec!$AM:$AM,BV_Data_An_Prec!$AP:$AP,$B75,BV_Data_An_Prec!$AQ:$AQ,$C75,BV_Data_An_Prec!$AR:$AR,Q$2)-Q157 -> 0 | S75: =L75-Q75 -> 5621.93
A76: Véhicules neufsProgramme neuf 2 | B76: Véhicules neufs | C76: Programme neuf 2 | F76: =+INDEX('Budget original'!$A$2:$AO$501,MATCH($A76,'Budget original'!$A$2:$A$501,0),MATCH(F$2,'Budget original'!$A$2:$AO$2,0)) -> 0 | L76: =-SUMIFS(BV_Data_An_Cour!$AM:$AM,BV_Data_An_Cour!$AP:$AP,$B76,BV_Data_An_Cour!$AQ:$AQ,$C76,BV_Data_An_Cour!$AR:$AR,L$2) -> 0 | N76: =L76-F76 -> 0 | Q76: =-SUMIFS(BV_Data_An_Prec!$AM:$AM,BV_Data_An_Prec!$AP:$AP,$B76,BV_Data_An_Prec!$AQ:$AQ,$C76,BV_Data_An_Prec!$AR:$AR,Q$2) -> 0 | S76: =L76-Q76 -> 0
A77: Véhicules neufsProgramme neuf 3 | B77: Véhicules neufs | C77: Programme neuf 3 | F77: =+INDEX('Budget original'!$A$2:$AO$501,MATCH($A77,'Budget original'!$A$2:$A$501,0),MATCH(F$2,'Budget original'!$A$2:$AO$2,0)) -> 0 | L77: =-SUMIFS(BV_Data_An_Cour!$AM:$AM,BV_Data_An_Cour!$AP:$AP,$B77,BV_Data_An_Cour!$AQ:$AQ,$C77,BV_Data_An_Cour!$AR:$AR,L$2) -> 0 | N77: =L77-F77 -> 0 | Q77: =-SUMIFS(BV_Data_An_Prec!$AM:$AM,BV_Data_An_Prec!$AP:$AP,$B77,BV_Data_An_Prec!$AQ:$AQ,$C77,BV_Data_An_Prec!$AR:$AR,Q$2) -> 0 | S77: =L77-Q77 -> 0
A78: Véhicules neufsHoldbacks | B78: Véhicules neufs | C78: Holdbacks | E78: =+F78/D27 -> #DIV/0! | F78: =+INDEX('Budget original'!$A$2:$AO$501,MATCH($A78,'Budget original'!$A$2:$A$501,0),MATCH(F$2,'Budget original'!$A$2:$AO$2,0)) -> 0 | K78: =+L78/J27 -> 0 | L78: =-SUMIFS(BV_Data_An_Cour!$AM:$AM,BV_Data_An_Cour!$AP:$AP,$B78,BV_Data_An_Cour!$AQ:$AQ,$C78,BV_Data_An_Cour!$AR:$AR,L$2) -> 0 | N78: =L78-F78 -> 0 | P78: =+Q78/O27 -> #DIV/0! | Q78: =-SUMIFS(BV_Data_An_Prec!$AM:$AM,BV_Data_An_Prec!$AP:$AP,$B78,BV_Data_An_Prec!$AQ:$AQ,$C78,BV_Data_An_Prec!$AR:$AR,Q$2) -> 0 | S78: =L78-Q78 -> 0
A79: Véhicules neufs[...] | B79: Véhicules neufs | C79: [...] | F79: =+INDEX('Budget original'!$A$2:$AO$501,MATCH($A79,'Budget original'!$A$2:$A$501,0),MATCH(F$2,'Budget original'!$A$2:$AO$2,0)) -> 0 | L79: =-SUMIFS(BV_Data_An_Cour!$AM:$AM,BV_Data_An_Cour!$AP:$AP,$B79,BV_Data_An_Cour!$AQ:$AQ,$C79,BV_Data_An_Cour!$AR:$AR,L$2) -> 0 | N79: =L79-F79 -> 0 | Q79: =-SUMIFS(BV_Data_An_Prec!$AM:$AM,BV_Data_An_Prec!$AP:$AP,$B79,BV_Data_An_Prec!$AQ:$AQ,$C79,BV_Data_An_Prec!$AR:$AR,Q$2) -> 0 | S79: =L79-Q79 -> 0
A80: Véhicules neufs[...] | B80: Véhicules neufs | C80: [...] | F80: =+INDEX('Budget original'!$A$2:$AO$501,MATCH($A80,'Budget original'!$A$2:$A$501,0),MATCH(F$2,'Budget original'!$A$2:$AO$2,0)) -> 0 | L80: =-SUMIFS(BV_Data_An_Cour!$AM:$AM,BV_Data_An_Cour!$AP:$AP,$B80,BV_Data_An_Cour!$AQ:$AQ,$C80,BV_Data_An_Cour!$AR:$AR,L$2) -> 0 | N80: =L80-F80 -> 0 | Q80: =-SUMIFS(BV_Data_An_Prec!$AM:$AM,BV_Data_An_Prec!$AP:$AP,$B80,BV_Data_An_Prec!$AQ:$AQ,$C80,BV_Data_An_Prec!$AR:$AR,Q$2) -> 0 | S80: =L80-Q80 -> 0
A81: Véhicules neufs[...] | B81: Véhicules neufs | C81: [...] | F81: =+INDEX('Budget original'!$A$2:$AO$501,MATCH($A81,'Budget original'!$A$2:$A$501,0),MATCH(F$2,'Budget original'!$A$2:$AO$2,0)) -> 0 | L81: =-SUMIFS(BV_Data_An_Cour!$AM:$AM,BV_Data_An_Cour!$AP:$AP,$B81,BV_Data_An_Cour!$AQ:$AQ,$C81,BV_Data_An_Cour!$AR:$AR,L$2) -> 0 | N81: =L81-F81 -> 0 | Q81: =-SUMIFS(BV_Data_An_Prec!$AM:$AM,BV_Data_An_Prec!$AP:$AP,$B81,BV_Data_An_Prec!$AQ:$AQ,$C81,BV_Data_An_Prec!$AR:$AR,Q$2) -> 0 | S81: =L81-Q81 -> 0
A82: Véhicules neufsFrais administration | B82: Véhicules neufs | C82: Frais administration | D82: =E82/499 -> #DIV/0! | E82: =+F82/D24 -> #DIV/0! | F82: =+INDEX('Budget original'!$A$2:$AO$501,MATCH($A82,'Budget original'!$A$2:$A$501,0),MATCH(F$2,'Budget original'!$A$2:$AO$2,0)) -> 0 | J82: =K82/699 -> 0 | K82: =+L82/J24 -> 0 | L82: =-SUMIFS(BV_Data_An_Cour!$AM:$AM,BV_Data_An_Cour!$AP:$AP,$B82,BV_Data_An_Cour!$AQ:$AQ,$C82,BV_Data_An_Cour!$AR:$AR,L$2) -> 0 | N82: =L82-F82 -> 0 | O82: =P82/699 -> #DIV/0! | P82: =+Q82/O24 -> #DIV/0! | Q82: =-SUMIFS(BV_Data_An_Prec!$AM:$AM,BV_Data_An_Prec!$AP:$AP,$B82,BV_Data_An_Prec!$AQ:$AQ,$C82,BV_Data_An_Prec!$AR:$AR,Q$2) -> 0 | S82: =L82-Q82 -> 0
A83: Véhicules neufsAUTRES REVENUS | B83: Véhicules neufs | C83: AUTRES REVENUS | F83: =+SUM(F75:F82) -> 0 | L83: =+SUM(L75:L82) -> 5621.93 | N83: =+SUM(N75:N82) -> 5621.93 | Q83: =+SUM(Q75:Q82) -> 0 | S83: =+SUM(S75:S82) -> 5621.93
A84: Véhicules neufs | B84: Véhicules neufs
A85: Véhicules neufsPROFIT DÉPARTEMENTAL | B85: Véhicules neufs | C85: PROFIT DÉPARTEMENTAL | F85: =F27-F74+F83 -> 0 | L85: =L27-L74+L83 -> 254474.92 | N85: =N27-N41-N54-N72+N83 -> 254474.92 | Q85: =Q27-Q74+Q83 -> 0 | S85: =S27-S41-S54-S72+S83 -> 254474.92
C89: =C1 -> Ste-Marie Auto | K89: Véhicules usagés | S89: =$S$1 -> Réalisé, Décembre 2025
D91: BUDGET ORIGINAL | J91: RÉALISATION | M91: ÉCART réel / Budget | O91: ANNÉE PRÉCÉDENTE | R91: ECART (réel/ Ann.Préc.)
D92: UNITE | E92: $P/UNITÉ | F92: $PROFITS | J92: UNITÉS | K92: $P/UNITE | L92: $PROFITS | M92: UNITÉS | N92: $PROFITS | O92: UNITE | P92: $P/UNITÉ | Q92: $PROFITS | R92: UNITÉS | S92: $PROFITS
A93: Véhicules usagésVentes nettes | B93: Véhicules usagés | C93: Ventes nettes | F93: =+INDEX('Budget original'!$A$2:$AO$501,MATCH($A93,'Budget original'!$A$2:$A$501,0),MATCH(F$2,'Budget original'!$A$2:$AO$2,0)) -> 0 | L93: =-SUMIFS(BV_Data_An_Cour!$AM:$AM,BV_Data_An_Cour!$AS:$AS,"Oui",BV_Data_An_Cour!$AP:$AP,$B93) -> 1626253.6 | Q93: =-SUMIFS(BV_Data_An_Prec!$AM:$AM,BV_Data_An_Prec!$AS:$AS,"Oui",BV_Data_An_Prec!$AP:$AP,$B93) -> 0
A94: Véhicules usagésCertifié | B94: Véhicules usagés | C94: Certifié | D94: =+INDEX('Budget original'!$A$2:$AO$501,MATCH($A94,'Budget original'!$A$2:$A$501,0),MATCH(D$2,'Budget original'!$A$2:$AO$2,0)) -> 0 | E94: =IF(D94=0,0,F94/D94) -> 0 | F94: =+INDEX('Budget original'!$A$2:$AO$501,MATCH($A94,'Budget original'!$A$2:$A$501,0),MATCH(F$2,'Budget original'!$A$2:$AO$2,0)) -> 0 | J94: =SUMIFS(BV_Data_An_Cour!$AW:$AW,BV_Data_An_Cour!$AP:$AP,$B94,BV_Data_An_Cour!$AQ:$AQ,$C94,BV_Data_An_Cour!$AY:$AY,J$2) -> 0 | K94: =IF(J94=0,0,L94/J94) -> 0 | L94: =-SUMIFS(BV_Data_An_Cour!$AM:$AM,BV_Data_An_Cour!$AP:$AP,$B94,BV_Data_An_Cour!$AQ:$AQ,$C94,BV_Data_An_Cour!$AR:$AR,$L2) -> 0 | M94: =J94-D94 -> 0 | N94: =L94-F94 -> 0 | O94: =SUMIFS(BV_Data_An_Prec!$AW:$AW,BV_Data_An_Prec!$AP:$AP,$B94,BV_Data_An_Prec!$AQ:$AQ,$C94,BV_Data_An_Prec!$AY:$AY,O$2) -> 0 | P94: =IF(O94=0,0,Q94/O94) -> 0 | Q94: =-SUMIFS(BV_Data_An_Prec!$AM:$AM,BV_Data_An_Prec!$AP:$AP,$B94,BV_Data_An_Prec!$AQ:$AQ,$C94,BV_Data_An_Prec!$AR:$AR,$L2) -> 0 | R94: =J94-O94 -> 0 | S94: =L94-Q94 -> 0
A95: Véhicules usagésNon Certifié | B95: Véhicules usagés | C95: Non Certifié | D95: =+INDEX('Budget original'!$A$2:$AO$501,MATCH($A95,'Budget original'!$A$2:$A$501,0),MATCH(D$2,'Budget original'!$A$2:$AO$2,0)) -> 0 | E95: =IF(D95=0,0,F95/D95) -> 0 | F95: =+INDEX('Budget original'!$A$2:$AO$501,MATCH($A95,'Budget original'!$A$2:$A$501,0),MATCH(F$2,'Budget original'!$A$2:$AO$2,0)) -> 0 | J95: =SUMIFS(BV_Data_An_Cour!$AW:$AW,BV_Data_An_Cour!$AP:$AP,$B95,BV_Data_An_Cour!$AQ:$AQ,$C95,BV_Data_An_Cour!$AY:$AY,J$2) -> 15 | K95: =IF(J95=0,0,L95/J95) -> 461.8 | L95: =-SUMIFS(BV_Data_An_Cour!$AM:$AM,BV_Data_An_Cour!$AP:$AP,$B95,BV_Data_An_Cour!$AQ:$AQ,$C95,BV_Data_An_Cour!$AR:$AR,$L2) -> 6927 | M95: =J95-D95 -> 15 | N95: =L95-F95 -> 6927 | O95: =SUMIFS(BV_Data_An_Prec!$AW:$AW,BV_Data_An_Prec!$AP:$AP,$B95,BV_Data_An_Prec!$AQ:$AQ,$C95,BV_Data_An_Prec!$AY:$AY,O$2) -> 0 | P95: =IF(O95=0,0,Q95/O95) -> 0 | Q95: =-SUMIFS(BV_Data_An_Prec!$AM:$AM,BV_Data_An_Prec!$AP:$AP,$B95,BV_Data_An_Prec!$AQ:$AQ,$C95,BV_Data_An_Prec!$AR:$AR,$L2) -> 0 | R95: =J95-O95 -> 15 | S95: =L95-Q95 -> 6927
A96: =B96&C96 -> Véhicules usagésAutres Marques | B96: Véhicules usagés | C96: Autres Marques | D96: =+INDEX('Budget original'!$A$2:$AO$501,MATCH($A96,'Budget original'!$A$2:$A$501,0),MATCH(D$2,'Budget original'!$A$2:$AO$2,0)) -> 0 | E96: =IF(D96=0,0,F96/D96) -> 0 | F96: =+INDEX('Budget original'!$A$2:$AO$501,MATCH($A96,'Budget original'!$A$2:$A$501,0),MATCH(F$2,'Budget original'!$A$2:$AO$2,0)) -> 0 | J96: =SUMIFS(BV_Data_An_Cour!$AW:$AW,BV_Data_An_Cour!$AP:$AP,$B96,BV_Data_An_Cour!$AQ:$AQ,$C96,BV_Data_An_Cour!$AY:$AY,J$2) -> 0 | K96: =IF(J96=0,0,L96/J96) -> 0 | L96: =-SUMIFS(BV_Data_An_Cour!$AM:$AM,BV_Data_An_Cour!$AP:$AP,$B96,BV_Data_An_Cour!$AQ:$AQ,$C96,BV_Data_An_Cour!$AR:$AR,$L2) -> 0 | M96: =J96-D96 -> 0 | N96: =L96-F96 -> 0 | O96: =SUMIFS(BV_Data_An_Prec!$AW:$AW,BV_Data_An_Prec!$AP:$AP,$B96,BV_Data_An_Prec!$AQ:$AQ,$C96,BV_Data_An_Prec!$AY:$AY,O$2) -> 0 | P96: =IF(O96=0,0,Q96/O96) -> 0 | Q96: =-SUMIFS(BV_Data_An_Prec!$AM:$AM,BV_Data_An_Prec!$AP:$AP,$B96,BV_Data_An_Prec!$AQ:$AQ,$C96,BV_Data_An_Prec!$AR:$AR,$L2) -> 0 | R96: =J96-O96 -> 0 | S96: =L96-Q96 -> 0
A97: =B97&C97 -> Véhicules usagésTotal Usagés | B97: Véhicules usagés | C97: Total Usagés | D97: =+D95+D94+D96 -> 0 | E97: =IF(D97=0,0,F97/D97) -> 0 | F97: =+F94+F95+F96 -> 0 | J97: =+J94+J95+J96 -> 15 | K97: =IF(J97<=0,0,L97/J97) -> 461.8 | L97: =+L94+L95+L96 -> 6927 | M97: =J97-D97 -> 15 | N97: =L97-F97 -> 6927 | O97: =+O94+O95+O96 -> 0 | P97: =IF(O97<=0,0,Q97/O97) -> 0 | Q97: =+Q94+Q95+Q96 -> 0 | R97: =R94+R95 -> 15 | S97: =S94+S95 -> 6927
A98: =B98&C98 -> Véhicules usagés | B98: Véhicules usagés | E98: =IF(D98=0,0,F98/D98) -> 0 | R98: =R97/O97 -> #DIV/0! | S98: =IF(Q97=0,0,(S97/Q97)) -> 0
A99: =B99&C99 -> Véhicules usagésRachat bail | B99: Véhicules usagés | C99: Rachat bail | J99: =SUMIFS(BV_Data_An_Cour!$AW:$AW,BV_Data_An_Cour!$AP:$AP,$B99,BV_Data_An_Cour!$AQ:$AQ,$C99,BV_Data_An_Cour!$AY:$AY,J$2) -> 0 | K99: =IF(J99=0,0,L99/J99) -> 0 | L99: =-SUMIFS(BV_Data_An_Cour!$AM:$AM,BV_Data_An_Cour!$AP:$AP,$B99,BV_Data_An_Cour!$AQ:$AQ,$C99,BV_Data_An_Cour!$AR:$AR,L$2) -> 0 | M99: =J99-D99 -> 0 | N99: =L99-F99 -> 0 | O99: =SUMIFS(BV_Data_An_Prec!$AW:$AW,BV_Data_An_Prec!$AP:$AP,$B99,BV_Data_An_Prec!$AQ:$AQ,$C99,BV_Data_An_Prec!$AY:$AY,O$2) -> 0 | P99: =IF(O99=0,0,Q99/O99) -> 0 | Q99: =-SUMIFS(BV_Data_An_Prec!$AM:$AM,BV_Data_An_Prec!$AP:$AP,$B99,BV_Data_An_Prec!$AQ:$AQ,$C99,BV_Data_An_Prec!$AR:$AR,Q$2) -> 0 | R99: =J99-O99 -> 0 | S99: =L99-Q99 -> 0
A100: =B100&C100 -> Véhicules usagés | B100: Véhicules usagés
A101: Véhicules usagésVentes au Gros | B101: Véhicules usagés | C101: Ventes au Gros | D101: =+INDEX('Budget original'!$A$2:$AO$501,MATCH($A101,'Budget original'!$A$2:$A$501,0),MATCH(D$2,'Budget original'!$A$2:$AO$2,0)) -> 0 | E101: =IF(D101=0,0,F101/D101) -> 0 | F101: =+INDEX('Budget original'!$A$2:$AO$501,MATCH($A101,'Budget original'!$A$2:$A$501,0),MATCH(F$2,'Budget original'!$A$2:$AO$2,0)) -> 0 | J101: =SUMIFS(BV_Data_An_Cour!$AW:$AW,BV_Data_An_Cour!$AP:$AP,$B101,BV_Data_An_Cour!$AQ:$AQ,$C101,BV_Data_An_Cour!$AY:$AY,J$2) -> 29 | K101: =IF(J101=0,0,L101/J101) -> -30.503103 | L101: =-SUMIFS(BV_Data_An_Cour!$AM:$AM,BV_Data_An_Cour!$AP:$AP,$B101,BV_Data_An_Cour!$AQ:$AQ,$C101,BV_Data_An_Cour!$AR:$AR,L$2) -> -884.59 | M101: =J101-D101 -> 29 | N101: =L101-F101 -> -884.59 | O101: =SUMIFS(BV_Data_An_Prec!$AW:$AW,BV_Data_An_Prec!$AP:$AP,$B101,BV_Data_An_Prec!$AQ:$AQ,$C101,BV_Data_An_Prec!$AY:$AY,O$2) -> 0 | P101: =IF(O101=0,0,Q101/O101) -> 0 | Q101: =-SUMIFS(BV_Data_An_Prec!$AM:$AM,BV_Data_An_Prec!$AP:$AP,$B101,BV_Data_An_Prec!$AQ:$AQ,$C101,BV_Data_An_Prec!$AR:$AR,Q$2) -> 0 | R101: =J101-O101 -> 29 | S101: =L101-Q101 -> -884.59
A102: Véhicules usagés | B102: Véhicules usagés
A103: Véhicules usagésRev. Finances | B103: Véhicules usagés | C103: Rev. Finances | D103: =+INDEX('Budget original'!$A$2:$AO$501,MATCH($A103,'Budget original'!$A$2:$A$501,0),MATCH(D$2,'Budget original'!$A$2:$AO$2,0)) -> 0 | E103: =IF(D103=0,0,F103/D103) -> 0 | F103: =+INDEX('Budget original'!$A$2:$AO$501,MATCH($A103,'Budget original'!$A$2:$A$501,0),MATCH(F$2,'Budget original'!$A$2:$AO$2,0)) -> 0 | K103: =IF(J97=0,0,L103/J97) -> 145.474 | L103: =-SUMIFS(BV_Data_An_Cour!$AM:$AM,BV_Data_An_Cour!$AP:$AP,$B103,BV_Data_An_Cour!$AQ:$AQ,$C103,BV_Data_An_Cour!$AR:$AR,$L2) -> 2182.11 | N103: =L103-F103 -> 2182.11 | P103: =IF(O97=0,0,Q103/O97) -> 0 | Q103: =-SUMIFS(BV_Data_An_Prec!$AM:$AM,BV_Data_An_Prec!$AP:$AP,$B103,BV_Data_An_Prec!$AQ:$AQ,$C103,BV_Data_An_Prec!$AR:$AR,$L2) -> 0 | R103: =P103-K103 -> -145.474 | S103: =L103-Q103 -> 2182.11
A104: Véhicules usagésRev. Protections | B104: Véhicules usagés | C104: Rev. Protections | D104: =+INDEX('Budget original'!$A$2:$AO$501,MATCH($A104,'Budget original'!$A$2:$A$501,0),MATCH(D$2,'Budget original'!$A$2:$AO$2,0)) -> 0 | E104: =IF(D104=0,0,F104/D104) -> 0 | F104: =+INDEX('Budget original'!$A$2:$AO$501,MATCH($A104,'Budget original'!$A$2:$A$501,0),MATCH(F$2,'Budget original'!$A$2:$AO$2,0)) -> 0 | K104: =IF(J97=0,0,L104/J97) -> 845.314 | L104: =-SUMIFS(BV_Data_An_Cour!$AM:$AM,BV_Data_An_Cour!$AP:$AP,$B104,BV_Data_An_Cour!$AQ:$AQ,$C104,BV_Data_An_Cour!$AR:$AR,$L2) -> 12679.71 | N104: =L104-F104 -> 12679.71 | P104: =IF(O97=0,0,Q104/O97) -> 0 | Q104: =-SUMIFS(BV_Data_An_Prec!$AM:$AM,BV_Data_An_Prec!$AP:$AP,$B104,BV_Data_An_Prec!$AQ:$AQ,$C104,BV_Data_An_Prec!$AR:$AR,$L2) -> 0 | R104: =P104-K104 -> -845.314 | S104: =L104-Q104 -> 12679.71
A105: Véhicules usagésRev. Autres | B105: Véhicules usagés | C105: Rev. Autres | D105: =+INDEX('Budget original'!$A$2:$AO$501,MATCH($A105,'Budget original'!$A$2:$A$501,0),MATCH(D$2,'Budget original'!$A$2:$AO$2,0)) -> 0 | E105: =IF(D105=0,0,F105/D105) -> 0 | F105: =+INDEX('Budget original'!$A$2:$AO$501,MATCH($A105,'Budget original'!$A$2:$A$501,0),MATCH(F$2,'Budget original'!$A$2:$AO$2,0)) -> 0 | K105: =IF(J97=0,0,L105/J97) -> 0 | L105: =-SUMIFS(BV_Data_An_Cour!$AM:$AM,BV_Data_An_Cour!$AP:$AP,$B105,BV_Data_An_Cour!$AQ:$AQ,$C105,BV_Data_An_Cour!$AR:$AR,$L$2) -> 0 | N105: =L105-F105 -> 0 | P105: =IF(O97=0,0,Q105/O97) -> 0 | Q105: =-SUMIFS(BV_Data_An_Prec!$AM:$AM,BV_Data_An_Prec!$AP:$AP,$B105,BV_Data_An_Prec!$AQ:$AQ,$C105,BV_Data_An_Prec!$AR:$AR,$L$2) -> 0 | R105: =P105-K105 -> 0 | S105: =L105-Q105 -> 0
...

Sheet Print_AAD
C1: =Parametres!B1 -> Ste-Marie Auto | K1: Véhicules neufs | S1: =CONCATENATE("Réalisé AAD,"," ",Parametres!B3," ",Parametres!B4) -> Réalisé AAD, Décembre 2025
D2: X | E2: O | F2: U | J2: NB | L2: $ | O2: NB | Q2: $ | X2: X | Y2: O | Z2: U | AJ2: X | AK2: O | AL2: U
D3: BUDGET ORIGINAL | J3: RÉALISATION | M3: ÉCART réel / Budget | O3: ANNÉE PRÉCÉDENTE | R3: ECART (réel/ Ann.Préc.) | V3: NEUF | W3: 0.45
D4: UNITE | E4: $P/UNITÉ | F4: $PROFITS | J4: UNITÉS | K4: $P/UNITE | L4: $PROFITS | M4: UNITÉS | N4: $PROFITS | O4: UNITÉS | P4: $P/UNITE | Q4: $PROFITS | R4: UNITÉS | S4: $PROFITS | V4: USAGE | W4: 0.1
A5: =+B5&C5 -> Véhicules neufsVentes nettes | B5: =+$K$1 -> Véhicules neufs | C5: Ventes nettes | F5: {=+SUMPRODUCT(('Budget original'!$A$8:$A$501=$A5)*('Budget original'!$C$3:$AO$3=F$2),'Budget original'!$C$8:$AO$501)} -> 0 | L5: =-SUMIFS(BV_Data_An_Cour!$AN:$AN,BV_Data_An_Cour!$AS:$AS,"Oui",BV_Data_An_Cour!$AP:$AP,$B5) -> 1.483535e+08 | Q5: =-SUMIFS(BV_Data_An_Prec!$AN:$AN,BV_Data_An_Prec!$AS:$AS,"Oui",BV_Data_An_Prec!$AP:$AP,$B5) -> 0 | V5: SERVICE | W5: 0.225
A6: =+B6&C6 -> Véhicules neufsAutos détail | B6: =+$K$1 -> Véhicules neufs | C6: Autos détail | D6: {=+SUMPRODUCT(('Budget original'!$A$8:$A$501=$A6)*('Budget original'!$C$3:$AO$3=D$2),'Budget original'!$C$8:$AO$501)} -> 0 | E6: =IF(D6=0,0,F6/D6) -> 0 | F6: {=+SUMPRODUCT(('Budget original'!$A$8:$A$501=$A6)*('Budget original'!$C$3:$AO$3=F$2),'Budget original'!$C$8:$AO$501)} -> 0 | J6: =SUMIFS(BV_Data_An_Cour!$AX:$AX,BV_Data_An_Cour!$AP:$AP,$B6,BV_Data_An_Cour!$AQ:$AQ,$C6,BV_Data_An_Cour!$AY:$AY,J$2) -> 9 | K6: =IF(J6=0,0,L6/J6) -> 6187.9378 | L6: =-SUMIFS(BV_Data_An_Cour!$AN:$AN,BV_Data_An_Cour!$AP:$AP,$B6,BV_Data_An_Cour!$AQ:$AQ,$C6,BV_Data_An_Cour!$AR:$AR,L$2) -> 55691.44 | M6: =J6-D6 -> 9 | N6: =L6-F6 -> 55691.44 | O6: =SUMIFS(BV_Data_An_Prec!$AX:$AX,BV_Data_An_Prec!$AP:$AP,$B6,BV_Data_An_Prec!$AQ:$AQ,$C6,BV_Data_An_Prec!$AY:$AY,O$2) -> 0 | P6: =IF(O6=0,0,Q6/O6) -> 0 | Q6: =-SUMIFS(BV_Data_An_Prec!$AN:$AN,BV_Data_An_Prec!$AP:$AP,$B6,BV_Data_An_Prec!$AQ:$AQ,$C6,BV_Data_An_Prec!$AR:$AR,Q$2) -> 0 | R6: =J6-O6 -> 9 | S6: =L6-Q6 -> 55691.44 | V6: CARROSSERIE | W6: 0.025
A7: =+B7&C7 -> Véhicules neufsCamions détail | B7: =+$K$1 -> Véhicules neufs | C7: Camions détail | D7: {=+SUMPRODUCT(('Budget original'!$A$8:$A$501=$A7)*('Budget original'!$C$3:$AO$3=D$2),'Budget original'!$C$8:$AO$501)} -> 0 | E7: =IF(D7=0,0,F7/D7) -> 0 | F7: {=+SUMPRODUCT(('Budget original'!$A$8:$A$501=$A7)*('Budget original'!$C$3:$AO$3=F$2),'Budget original'!$C$8:$AO$501)} -> 0 | J7: =SUMIFS(BV_Data_An_Cour!$AX:$AX,BV_Data_An_Cour!$AP:$AP,$B7,BV_Data_An_Cour!$AQ:$AQ,$C7,BV_Data_An_Cour!$AY:$AY,J$2) -> 552 | K7: =IF(J7=0,0,L7/J7) -> 2895.9229 | L7: =-SUMIFS(BV_Data_An_Cour!$AN:$AN,BV_Data_An_Cour!$AP:$AP,$B7,BV_Data_An_Cour!$AQ:$AQ,$C7,BV_Data_An_Cour!$AR:$AR,L$2) -> 1598549.4 | M7: =J7-D7 -> 552 | N7: =L7-F7 -> 1598549.4 | O7: =SUMIFS(BV_Data_An_Prec!$AX:$AX,BV_Data_An_Prec!$AP:$AP,$B7,BV_Data_An_Prec!$AQ:$AQ,$C7,BV_Data_An_Prec!$AY:$AY,O$2) -> 0 | P7: =IF(O7=0,0,Q7/O7) -> 0 | Q7: =-SUMIFS(BV_Data_An_Prec!$AN:$AN,BV_Data_An_Prec!$AP:$AP,$B7,BV_Data_An_Prec!$AQ:$AQ,$C7,BV_Data_An_Prec!$AR:$AR,Q$2) -> 0 | R7: =J7-O7 -> 552 | S7: =L7-Q7 -> 1598549.4 | V7: PIECES | W7: 0.2
A8: =+B8&C8 -> Véhicules neufsVoitures electriques | B8: =+$K$1 -> Véhicules neufs | C8: Voitures electriques | D8: {=+SUMPRODUCT(('Budget original'!$A$8:$A$501=$A8)*('Budget original'!$C$3:$AO$3=D$2),'Budget original'!$C$8:$AO$501)} -> 0 | E8: =IF(D8=0,0,F8/D8) -> 0 | F8: {=+SUMPRODUCT(('Budget original'!$A$8:$A$501=$A8)*('Budget original'!$C$3:$AO$3=F$2),'Budget original'!$C$8:$AO$501)} -> 0 | J8: =SUMIFS(BV_Data_An_Cour!$AX:$AX,BV_Data_An_Cour!$AP:$AP,$B8,BV_Data_An_Cour!$AQ:$AQ,$C8,BV_Data_An_Cour!$AY:$AY,J$2) -> 0 | K8: =IF(J8=0,0,L8/J8) -> 0 | L8: =-SUMIFS(BV_Data_An_Cour!$AN:$AN,BV_Data_An_Cour!$AP:$AP,$B8,BV_Data_An_Cour!$AQ:$AQ,$C8,BV_Data_An_Cour!$AR:$AR,L$2) -> 0 | M8: =J8-D8 -> 0 | N8: =L8-F8 -> 0 | O8: =SUMIFS(BV_Data_An_Prec!$AX:$AX,BV_Data_An_Prec!$AP:$AP,$B8,BV_Data_An_Prec!$AQ:$AQ,$C8,BV_Data_An_Prec!$AY:$AY,O$2) -> 0 | P8: =IF(O8=0,0,Q8/O8) -> 0 | Q8: =-SUMIFS(BV_Data_An_Prec!$AN:$AN,BV_Data_An_Prec!$AP:$AP,$B8,BV_Data_An_Prec!$AQ:$AQ,$C8,BV_Data_An_Prec!$AR:$AR,Q$2) -> 0 | R8: =J8-O8 -> 0 | S8: =L8-Q8 -> 0 | W8: =SUM(W3:W7) -> 1
A9: =+B9&C9 -> Véhicules neufsCamions electriques | B9: =+$K$1 -> Véhicules neufs | C9: Camions electriques | D9: {=+SUMPRODUCT(('Budget original'!$A$8:$A$501=$A9)*('Budget original'!$C$3:$AO$3=D$2),'Budget original'!$C$8:$AO$501)} -> 0 | E9: =IF(D9=0,0,F9/D9) -> 0 | F9: {=+SUMPRODUCT(('Budget original'!$A$8:$A$501=$A9)*('Budget original'!$C$3:$AO$3=F$2),'Budget original'!$C$8:$AO$501)} -> 0 | J9: =SUMIFS(BV_Data_An_Cour!$AX:$AX,BV_Data_An_Cour!$AP:$AP,$B9,BV_Data_An_Cour!$AQ:$AQ,$C9,BV_Data_An_Cour!$AY:$AY,J$2) -> 195 | K9: =IF(J9=0,0,L9/J9) -> 1142.8646 | L9: =-SUMIFS(BV_Data_An_Cour!$AN:$AN,BV_Data_An_Cour!$AP:$AP,$B9,BV_Data_An_Cour!$AQ:$AQ,$C9,BV_Data_An_Cour!$AR:$AR,L$2) -> 222858.59 | M9: =J9-D9 -> 195 | N9: =L9-F9 -> 222858.59 | O9: =SUMIFS(BV_Data_An_Prec!$AX:$AX,BV_Data_An_Prec!$AP:$AP,$B9,BV_Data_An_Prec!$AQ:$AQ,$C9,BV_Data_An_Prec!$AY:$AY,O$2) -> 0 | P9: =IF(O9=0,0,Q9/O9) -> 0 | Q9: =-SUMIFS(BV_Data_An_Prec!$AN:$AN,BV_Data_An_Prec!$AP:$AP,$B9,BV_Data_An_Prec!$AQ:$AQ,$C9,BV_Data_An_Prec!$AR:$AR,Q$2) -> 0 | R9: =J9-O9 -> 195 | S9: =L9-Q9 -> 222858.59
A10: =+B10&C10 -> Véhicules neufs[...] | B10: =+$K$1 -> Véhicules neufs | C10: [...] | D10: {=+SUMPRODUCT(('Budget original'!$A$8:$A$501=$A10)*('Budget original'!$C$3:$AO$3=D$2),'Budget original'!$C$8:$AO$501)} -> 0 | E10: =IF(D10=0,0,F10/D10) -> 0 | F10: {=+SUMPRODUCT(('Budget original'!$A$8:$A$501=$A10)*('Budget original'!$C$3:$AO$3=F$2),'Budget original'!$C$8:$AO$501)} -> 0 | J10: =-SUMIFS(BV_Data_An_Cour!$AN:$AN,BV_Data_An_Cour!$AP:$AP,$B10,BV_Data_An_Cour!$AQ:$AQ,$C10,BV_Data_An_Cour!$AR:$AR,J$2) -> 0 | K10: =IF(J10=0,0,L10/J10) -> 0 | L10: =-SUMIFS(BV_Data_An_Cour!$AN:$AN,BV_Data_An_Cour!$AP:$AP,$B10,BV_Data_An_Cour!$AQ:$AQ,$C10,BV_Data_An_Cour!$AR:$AR,L$2) -> 0 | M10: =J10-D10 -> 0 | N10: =L10-F10 -> 0 | O10: =-SUMIFS(BV_Data_An_Prec!$AN:$AN,BV_Data_An_Prec!$AP:$AP,$B10,BV_Data_An_Prec!$AQ:$AQ,$C10,BV_Data_An_Prec!$AR:$AR,O$2) -> 0 | P10: =IF(O10=0,0,Q10/O10) -> 0 | Q10: =-SUMIFS(BV_Data_An_Prec!$AN:$AN,BV_Data_An_Prec!$AP:$AP,$B10,BV_Data_An_Prec!$AQ:$AQ,$C10,BV_Data_An_Prec!$AR:$AR,Q$2) -> 0 | R10: =J10-O10 -> 0 | S10: =L10-Q10 -> 0
A11: =+B11&C11 -> Véhicules neufs[...] | B11: =+$K$1 -> Véhicules neufs | C11: [...] | D11: {=+SUMPRODUCT(('Budget original'!$A$8:$A$501=$A11)*('Budget original'!$C$3:$AO$3=D$2),'Budget original'!$C$8:$AO$501)} -> 0 | E11: =IF(D11=0,0,F11/D11) -> 0 | F11: {=+SUMPRODUCT(('Budget original'!$A$8:$A$501=$A11)*('Budget original'!$C$3:$AO$3=F$2),'Budget original'!$C$8:$AO$501)} -> 0 | J11: =-SUMIFS(BV_Data_An_Cour!$AN:$AN,BV_Data_An_Cour!$AP:$AP,$B11,BV_Data_An_Cour!$AQ:$AQ,$C11,BV_Data_An_Cour!$AR:$AR,J$2) -> 0 | K11: =IF(J11=0,0,L11/J11) -> 0 | L11: =-SUMIFS(BV_Data_An_Cour!$AN:$AN,BV_Data_An_Cour!$AP:$AP,$B11,BV_Data_An_Cour!$AQ:$AQ,$C11,BV_Data_An_Cour!$AR:$AR,L$2) -> 0 | M11: =J11-D11 -> 0 | N11: =L11-F11 -> 0 | O11: =-SUMIFS(BV_Data_An_Prec!$AN:$AN,BV_Data_An_Prec!$AP:$AP,$B11,BV_Data_An_Prec!$AQ:$AQ,$C11,BV_Data_An_Prec!$AR:$AR,O$2) -> 0 | P11: =IF(O11=0,0,Q11/O11) -> 0 | Q11: =-SUMIFS(BV_Data_An_Prec!$AN:$AN,BV_Data_An_Prec!$AP:$AP,$B11,BV_Data_An_Prec!$AQ:$AQ,$C11,BV_Data_An_Prec!$AR:$AR,Q$2) -> 0 | R11: =J11-O11 -> 0 | S11: =L11-Q11 -> 0
A12: =+B12&C12 -> Véhicules neufs[...] | B12: =+$K$1 -> Véhicules neufs | C12: [...] | D12: {=+SUMPRODUCT(('Budget original'!$A$8:$A$501=$A12)*('Budget original'!$C$3:$AO$3=D$2),'Budget original'!$C$8:$AO$501)} -> 0 | E12: =IF(D12=0,0,F12/D12) -> 0 | F12: {=+SUMPRODUCT(('Budget original'!$A$8:$A$501=$A12)*('Budget original'!$C$3:$AO$3=F$2),'Budget original'!$C$8:$AO$501)} -> 0 | J12: =-SUMIFS(BV_Data_An_Cour!$AN:$AN,BV_Data_An_Cour!$AP:$AP,$B12,BV_Data_An_Cour!$AQ:$AQ,$C12,BV_Data_An_Cour!$AR:$AR,J$2) -> 0 | K12: =IF(J12=0,0,L12/J12) -> 0 | L12: =-SUMIFS(BV_Data_An_Cour!$AN:$AN,BV_Data_An_Cour!$AP:$AP,$B12,BV_Data_An_Cour!$AQ:$AQ,$C12,BV_Data_An_Cour!$AR:$AR,L$2) -> 0 | M12: =J12-D12 -> 0 | N12: =L12-F12 -> 0 | O12: =-SUMIFS(BV_Data_An_Prec!$AN:$AN,BV_Data_An_Prec!$AP:$AP,$B12,BV_Data_An_Prec!$AQ:$AQ,$C12,BV_Data_An_Prec!$AR:$AR,O$2) -> 0 | P12: =IF(O12=0,0,Q12/O12) -> 0 | Q12: =-SUMIFS(BV_Data_An_Prec!$AN:$AN,BV_Data_An_Prec!$AP:$AP,$B12,BV_Data_An_Prec!$AQ:$AQ,$C12,BV_Data_An_Prec!$AR:$AR,Q$2) -> 0 | R12: =J12-O12 -> 0 | S12: =L12-Q12 -> 0
A13: =+B13&C13 -> Véhicules neufsTotal Neufs | B13: =+$K$1 -> Véhicules neufs | C13: Total Neufs | D13: =+SUM(D6:D12) -> 0 | E13: =IF(D13<=0,0,F13/D13) -> 0 | F13: =+SUM(F6:F12) -> 0 | J13: =+SUM(J6:J12) -> 756 | K13: =IF(J13<=0,0,L13/J13) -> 2482.9358 | L13: =+SUM(L6:L12) -> 1877099.5 | M13: =+SUM(M6:M12) -> 756 | N13: =+SUM(N6:N12) -> 1877099.5 | O13: =+SUM(O6:O12) -> 0 | P13: =IF(O13<=0,0,Q13/O13) -> 0 | Q13: =+SUM(Q6:Q12) -> 0 | R13: =+SUM(R6:R12) -> 756 | S13: =+SUM(S6:S12) -> 1877099.5
A14: =+B14&C14 -> Véhicules neufs | B14: =+$K$1 -> Véhicules neufs | M14: =IF(D13=0,0,M13/D13) -> 0 | N14: =IF(F13=0,0,N13/F13) -> 0 | R14: =R13/O13 -> #DIV/0! | S14: =IF(Q13=0,0,(S13/Q13)) -> 0
A15: =+B15&C15 -> Véhicules neufsEx-Démos et courtoisies | B15: =+$K$1 -> Véhicules neufs | C15: Ex-Démos et courtoisies | D15: {=+SUMPRODUCT(('Budget original'!$A$8:$A$501=$A15)*('Budget original'!$C$3:$AO$3=D$2),'Budget original'!$C$8:$AO$501)} -> 0 | E15: =IF(D15=0,0,F15/D15) -> 0 | F15: {=+SUMPRODUCT(('Budget original'!$A$8:$A$501=$A15)*('Budget original'!$C$3:$AO$3=F$2),'Budget original'!$C$8:$AO$501)} -> 0 | J15: =SUMIFS(BV_Data_An_Cour!$AX:$AX,BV_Data_An_Cour!$AP:$AP,$B15,BV_Data_An_Cour!$AQ:$AQ,$C15,BV_Data_An_Cour!$AY:$AY,J$2) -> 0 | K15: =IF(J15=0,0,L15/J15) -> 0 | L15: =-SUMIFS(BV_Data_An_Cour!$AN:$AN,BV_Data_An_Cour!$AP:$AP,$B15,BV_Data_An_Cour!$AQ:$AQ,$C15,BV_Data_An_Cour!$AR:$AR,L$2) -> 0 | M15: =J15-D15 -> 0 | N15: =L15-F15 -> 0 | O15: =SUMIFS(BV_Data_An_Prec!$AX:$AX,BV_Data_An_Prec!$AP:$AP,$B15,BV_Data_An_Prec!$AQ:$AQ,$C15,BV_Data_An_Prec!$AY:$AY,O$2) -> 0 | P15: =IF(O15=0,0,Q15/O15) -> 0 | Q15: =-SUMIFS(BV_Data_An_Prec!$AN:$AN,BV_Data_An_Prec!$AP:$AP,$B15,BV_Data_An_Prec!$AQ:$AQ,$C15,BV_Data_An_Prec!$AR:$AR,Q$2) -> 0 | R15: =J15-O15 -> 0 | S15: =L15-Q15 -> 0
A16: =+B16&C16 -> Véhicules neufs | B16: =+$K$1 -> Véhicules neufs
A17: =+B17&C17 -> Véhicules neufsFlottes | B17: =+$K$1 -> Véhicules neufs | C17: Flottes | D17: {=+SUMPRODUCT(('Budget original'!$A$8:$A$501=$A17)*('Budget original'!$C$3:$AO$3=D$2),'Budget original'!$C$8:$AO$501)} -> 0 | E17: =IF(D17=0,0,F17/D17) -> 0 | F17: {=+SUMPRODUCT(('Budget original'!$A$8:$A$501=$A17)*('Budget original'!$C$3:$AO$3=F$2),'Budget original'!$C$8:$AO$501)} -> 0 | J17: =SUMIFS(BV_Data_An_Cour!$AX:$AX,BV_Data_An_Cour!$AP:$AP,$B17,BV_Data_An_Cour!$AQ:$AQ,$C17,BV_Data_An_Cour!$AY:$AY,J$2) -> 1607 | K17: =IF(J17=0,0,L17/J17) -> 612.29521 | L17: =-SUMIFS(BV_Data_An_Cour!$AN:$AN,BV_Data_An_Cour!$AP:$AP,$B17,BV_Data_An_Cour!$AQ:$AQ,$C17,BV_Data_An_Cour!$AR:$AR,L$2) -> 983958.4 | M17: =J17-D17 -> 1607 | N17: =L17-F17 -> 983958.4 | O17: =SUMIFS(BV_Data_An_Prec!$AX:$AX,BV_Data_An_Prec!$AP:$AP,$B17,BV_Data_An_Prec!$AQ:$AQ,$C17,BV_Data_An_Prec!$AY:$AY,O$2) -> 0 | P17: =IF(O17=0,0,Q17/O17) -> 0 | Q17: =-SUMIFS(BV_Data_An_Prec!$AN:$AN,BV_Data_An_Prec!$AP:$AP,$B17,BV_Data_An_Prec!$AQ:$AQ,$C17,BV_Data_An_Prec!$AR:$AR,Q$2) -> 0 | R17: =J17-O17 -> 1607 | S17: =L17-Q17 -> 983958.4
A18: =+B18&C18 -> Véhicules neufs | B18: =+$K$1 -> Véhicules neufs
A19: =+B19&C19 -> Véhicules neufs | B19: =+$K$1 -> Véhicules neufs
A20: =+B20&C20 -> Véhicules neufs | B20: =+$K$1 -> Véhicules neufs
A21: =+B21&C21 -> Véhicules neufsRev. Finances | B21: =+$K$1 -> Véhicules neufs | C21: Rev. Finances | F21: {=+SUMPRODUCT(('Budget original'!$A$8:$A$501=$A21)*('Budget original'!$C$3:$AO$3=F$2),'Budget original'!$C$8:$AO$501)} -> 0 | K21: =IF(J13=0,0,L21/(J13+J15)) -> 10.071997 | L21: =-SUMIFS(BV_Data_An_Cour!$AN:$AN,BV_Data_An_Cour!$AP:$AP,$B21,BV_Data_An_Cour!$AQ:$AQ,$C21,BV_Data_An_Cour!$AR:$AR,L$2) -> 7614.43 | N21: =L21-F21 -> 7614.43 | P21: =IF(O13=0,0,Q21/(O13+O15)) -> 0 | Q21: =-SUMIFS(BV_Data_An_Prec!$AN:$AN,BV_Data_An_Prec!$AP:$AP,$B21,BV_Data_An_Prec!$AQ:$AQ,$C21,BV_Data_An_Prec!$AR:$AR,Q$2) -> 0 | R21: =P21-K21 -> -10.071997 | S21: =L21-Q21 -> 7614.43
A22: =+B22&C22 -> Véhicules neufsRev. Protections | B22: =+$K$1 -> Véhicules neufs | C22: Rev. Protections | F22: {=+SUMPRODUCT(('Budget original'!$A$8:$A$501=$A22)*('Budget original'!$C$3:$AO$3=F$2),'Budget original'!$C$8:$AO$501)} -> 0 | K22: =IF(J13=0,0,L22/(J13+J15)) -> 672.16431 | L22: =-SUMIFS(BV_Data_An_Cour!$AN:$AN,BV_Data_An_Cour!$AP:$AP,$B22,BV_Data_An_Cour!$AQ:$AQ,$C22,BV_Data_An_Cour!$AR:$AR,L$2) -> 508156.22 | N22: =L22-F22 -> 508156.22 | P22: =IF(O13=0,0,Q22/(O13+O15)) -> 0 | Q22: =-SUMIFS(BV_Data_An_Prec!$AN:$AN,BV_Data_An_Prec!$AP:$AP,$B22,BV_Data_An_Prec!$AQ:$AQ,$C22,BV_Data_An_Prec!$AR:$AR,Q$2) -> 0 | R22: =P22-K22 -> -672.16431 | S22: =L22-Q22 -> 508156.22
A23: =+B23&C23 -> Véhicules neufsRev. Autres | B23: =+$K$1 -> Véhicules neufs | C23: Rev. Autres | F23: {=+SUMPRODUCT(('Budget original'!$A$8:$A$501=$A23)*('Budget original'!$C$3:$AO$3=F$2),'Budget original'!$C$8:$AO$501)} -> 0 | K23: =IF(J13=0,0,L23/(J13+J15)) -> 57.821164 | L23: =-SUMIFS(BV_Data_An_Cour!$AN:$AN,BV_Data_An_Cour!$AP:$AP,$B23,BV_Data_An_Cour!$AQ:$AQ,$C23,BV_Data_An_Cour!$AR:$AR,L$2) -> 43712.8 | N23: =L23-F23 -> 43712.8 | P23: =IF(O13=0,0,Q23/(O13+O15)) -> 0 | Q23: =-SUMIFS(BV_Data_An_Prec!$AN:$AN,BV_Data_An_Prec!$AP:$AP,$B23,BV_Data_An_Prec!$AQ:$AQ,$C23,BV_Data_An_Prec!$AR:$AR,Q$2) -> 0 | R23: =P23-K23 -> -57.821164 | S23: =L23-Q23 -> 43712.8
A24: =+B24&C24 -> Véhicules neufsTotal F&I | B24: =+$K$1 -> Véhicules neufs | C24: Total F&I | D24: =+D15+D13 -> 0 | E24: =IF(D24<=0,0,F24/D24) -> 0 | F24: =F21+F22+F23 -> 0 | J24: =+J15+J13 -> 756 | K24: =IF(J24<=0,0,L24/J24) -> 740.05747 | L24: =L21+L22+L23 -> 559483.45 | M24: =J24-D24 -> 756 | N24: =L24-F24 -> 559483.45 | O24: =+O15+O13 -> 0 | P24: =IF(O24<=0,0,Q24/O24) -> 0 | Q24: =Q21+Q22+Q23 -> 0 | R24: =P24-K24 -> -740.05747 | S24: =L24-Q24 -> 559483.45
A25: =+B25&C25 -> Véhicules neufs | B25: =+$K$1 -> Véhicules neufs | N25: =IF(N24=0,0,N24/F24) -> #DIV/0! | S25: =IF(Q24=0,0,(S24/Q24)) -> 0
A26: =+B26&C26 -> Véhicules neufs | B26: =+$K$1 -> Véhicules neufs
A27: =+B27&C27 -> Véhicules neufsTotal Dépt. Neufs | B27: =+$K$1 -> Véhicules neufs | C27: Total Dépt. Neufs | D27: =+D13+D15+D17 -> 0 | E27: =IF(D27<=0,0,F27/D27) -> 0 | F27: =F13+F17+F24+F19+F15 -> 0 | J27: =+J13+J15+J17 -> 2363 | K27: =IF(J27<=0,0,L27/J27) -> 1447.5418 | L27: =L13+L17+L24+L19+L15 -> 3420541.3 | M27: =J27-D27 -> 2363 | N27: =L27-F27 -> 3420541.3 | O27: =+O13+O15+O17 -> 0 | P27: =IF(O27<=0,0,Q27/O27) -> 0 | Q27: =Q13+Q17+Q24+Q19+Q15 -> 0 | R27: =J27-O27 -> 2363 | S27: =L27-Q27 -> 3420541.3
A28: =+B28&C28 -> Véhicules neufs | B28: =+$K$1 -> Véhicules neufs | Q28: =+Q27/K27 -> 0 | R28: =R27/O27 -> #DIV/0! | S28: =IF(Q27=0,0,S27/Q27) -> 0
A29: =+B29&C29 -> Véhicules neufs | B29: =+$K$1 -> Véhicules neufs
A30: =+B30&C30 -> Véhicules neufsDEPENSES | B30: =+$K$1 -> Véhicules neufs | C30: DEPENSES
A31: =+B31&C31 -> Véhicules neufsComm. vendeurs | B31: =+$K$1 -> Véhicules neufs | C31: Comm. vendeurs | E31: =F31/D$24 -> #DIV/0! | F31: {=+SUMPRODUCT(('Budget original'!$A$8:$A$501=$A31)*('Budget original'!$C$3:$AO$3=F$2),'Budget original'!$C$8:$AO$501)} -> 0 | J31: =L31/(L15+L13+L17) -> 0.22781661 | K31: =IF(L31=0,0,L31/J$24) -> 862.1647 | L31: =SUMIFS(BV_Data_An_Cour!$AN:$AN,BV_Data_An_Cour!$AP:$AP,$B31,BV_Data_An_Cour!$AQ:$AQ,$C31,BV_Data_An_Cour!$AR:$AR,L$2) -> 651796.51 | N31: =L31-F31 -> 651796.51 | O31: =Q31/(Q15+Q13+Q17) -> #DIV/0! | P31: =IF(Q31=0,0,Q31/O$24) -> 0 | Q31: =SUMIFS(BV_Data_An_Prec!$AN:$AN,BV_Data_An_Prec!$AP:$AP,$B31,BV_Data_An_Prec!$AQ:$AQ,$C31,BV_Data_An_Prec!$AR:$AR,Q$2) -> 0 | S31: =L31-Q31 -> 651796.51
A32: =+B32&C32 -> Véhicules neufsComm. F&I | B32: =+$K$1 -> Véhicules neufs | C32: Comm. F&I | E32: =F32/D$24 -> #DIV/0! | F32: {=+SUMPRODUCT(('Budget original'!$A$8:$A$501=$A32)*('Budget original'!$C$3:$AO$3=F$2),'Budget original'!$C$8:$AO$501)} -> 0 | J32: =L32/L24 -> 0.27945284 | K32: =IF(L32=0,0,L32/J$24) -> 206.81116 | L32: =SUMIFS(BV_Data_An_Cour!$AN:$AN,BV_Data_An_Cour!$AP:$AP,$B32,BV_Data_An_Cour!$AQ:$AQ,$C32,BV_Data_An_Cour!$AR:$AR,L$2) -> 156349.24 | N32: =L32-F32 -> 156349.24 | O32: =Q32/Q24 -> #DIV/0! | P32: =IF(Q32=0,0,Q32/O$24) -> 0 | Q32: =SUMIFS(BV_Data_An_Prec!$AN:$AN,BV_Data_An_Prec!$AP:$AP,$B32,BV_Data_An_Prec!$AQ:$AQ,$C32,BV_Data_An_Prec!$AR:$AR,Q$2) -> 0 | S32: =L32-Q32 -> 156349.24
A33: =+B33&C33 -> Véhicules neufsFrais de livraison | B33: =+$K$1 -> Véhicules neufs | C33: Frais de livraison | E33: =F33/D$24 -> #DIV/0! | F33: {=+SUMPRODUCT(('Budget original'!$A$8:$A$501=$A33)*('Budget original'!$C$3:$AO$3=F$2),'Budget original'!$C$8:$AO$501)} -> 0 | K33: =IF(L33=0,0,L33/J$24) -> -76.17328 | L33: =SUMIFS(BV_Data_An_Cour!$AN:$AN,BV_Data_An_Cour!$AP:$AP,$B33,BV_Data_An_Cour!$AQ:$AQ,$C33,BV_Data_An_Cour!$AR:$AR,L$2) -> -57587 | N33: =L33-F33 -> -57587 | P33: =IF(Q33=0,0,Q33/O$24) -> 0 | Q33: =SUMIFS(BV_Data_An_Prec!$AN:$AN,BV_Data_An_Prec!$AP:$AP,$B33,BV_Data_An_Prec!$AQ:$AQ,$C33,BV_Data_An_Prec!$AR:$AR,Q$2) -> 0 | S33: =L33-Q33 -> -57587
A34: =+B34&C34 -> Véhicules neufsService gratuit 1 | B34: =+$K$1 -> Véhicules neufs | C34: Service gratuit 1 | E34: =F34/D$24 -> #DIV/0! | F34: {=+SUMPRODUCT(('Budget original'!$A$8:$A$501=$A34)*('Budget original'!$C$3:$AO$3=F$2),'Budget original'!$C$8:$AO$501)} -> 0 | K34: =IF(L34=0,0,L34/J$24) -> 8.8531085 | L34: =SUMIFS(BV_Data_An_Cour!$AN:$AN,BV_Data_An_Cour!$AP:$AP,$B34,BV_Data_An_Cour!$AQ:$AQ,$C34,BV_Data_An_Cour!$AR:$AR,L$2) -> 6692.95 | N34: =L34-F34 -> 6692.95 | P34: =IF(Q34=0,0,Q34/O$24) -> 0 | Q34: =SUMIFS(BV_Data_An_Prec!$AN:$AN,BV_Data_An_Prec!$AP:$AP,$B34,BV_Data_An_Prec!$AQ:$AQ,$C34,BV_Data_An_Prec!$AR:$AR,Q$2) -> 0 | S34: =L34-Q34 -> 6692.95
A35: =+B35&C35 -> Véhicules neufsEntretien stock | B35: =+$K$1 -> Véhicules neufs | C35: Entretien stock | E35: =F35/D$24 -> #DIV/0! | F35: {=+SUMPRODUCT(('Budget original'!$A$8:$A$501=$A35)*('Budget original'!$C$3:$AO$3=F$2),'Budget original'!$C$8:$AO$501)} -> 0 | K35: =IF(L35=0,0,L35/J$24) -> 0 | L35: =SUMIFS(BV_Data_An_Cour!$AN:$AN,BV_Data_An_Cour!$AP:$AP,$B35,BV_Data_An_Cour!$AQ:$AQ,$C35,BV_Data_An_Cour!$AR:$AR,L$2) -> 0 | N35: =L35-F35 -> 0 | P35: =IF(Q35=0,0,Q35/O$24) -> 0 | Q35: =SUMIFS(BV_Data_An_Prec!$AN:$AN,BV_Data_An_Prec!$AP:$AP,$B35,BV_Data_An_Prec!$AQ:$AQ,$C35,BV_Data_An_Prec!$AR:$AR,Q$2) -> 0 | S35: =L35-Q35 -> 0
A36: =+B36&C36 -> Véhicules neufsPublicité 1 | B36: =+$K$1 -> Véhicules neufs | C36: Publicité 1 | E36: =F36/D$24 -> #DIV/0! | F36: {=+SUMPRODUCT(('Budget original'!$A$8:$A$501=$A36)*('Budget original'!$C$3:$AO$3=F$2),'Budget original'!$C$8:$AO$501)} -> 0 | K36: =IF(L36=0,0,L36/J$24) -> -459.37279 | L36: =SUMIFS(BV_Data_An_Cour!$AN:$AN,BV_Data_An_Cour!$AP:$AP,$B36,BV_Data_An_Cour!$AQ:$AQ,$C36,BV_Data_An_Cour!$AR:$AR,L$2) -> -347285.83 | N36: =L36-F36 -> -347285.83 | P36: =IF(Q36=0,0,Q36/O$24) -> 0 | Q36: =SUMIFS(BV_Data_An_Prec!$AN:$AN,BV_Data_An_Prec!$AP:$AP,$B36,BV_Data_An_Prec!$AQ:$AQ,$C36,BV_Data_An_Prec!$AR:$AR,Q$2) -> 0 | S36: =L36-Q36 -> -347285.83
A37: =+B37&C37 -> Véhicules neufsIntérêt de gros | B37: =+$K$1 -> Véhicules neufs | C37: Intérêt de gros | E37: =F37/D$24 -> #DIV/0! | F37: {=+SUMPRODUCT(('Budget original'!$A$8:$A$501=$A37)*('Budget original'!$C$3:$AO$3=F$2),'Budget original'!$C$8:$AO$501)} -> 0 | K37: =IF(L37=0,0,L37/J$24) -> 1334.8437 | L37: =SUMIFS(BV_Data_An_Cour!$AN:$AN,BV_Data_An_Cour!$AP:$AP,$B37,BV_Data_An_Cour!$AQ:$AQ,$C37,BV_Data_An_Cour!$AR:$AR,L$2) -> 1009141.8 | N37: =L37-F37 -> 1009141.8 | P37: =IF(Q37=0,0,Q37/O$24) -> 0 | Q37: =SUMIFS(BV_Data_An_Prec!$AN:$AN,BV_Data_An_Prec!$AP:$AP,$B37,BV_Data_An_Prec!$AQ:$AQ,$C37,BV_Data_An_Prec!$AR:$AR,Q$2) -> 0 | S37: =L37-Q37 -> 1009141.8
A38: =+B38&C38 -> Véhicules neufsCrédit Intérêts Floor Plan | B38: =+$K$1 -> Véhicules neufs | C38: Crédit Intérêts Floor Plan | E38: =F38/D$24 -> #DIV/0! | F38: {=+SUMPRODUCT(('Budget original'!$A$8:$A$501=$A38)*('Budget original'!$C$3:$AO$3=F$2),'Budget original'!$C$8:$AO$501)} -> 0 | K38: =IF(L38=0,0,L38/J$24) -> -4131.8905 | L38: =SUMIFS(BV_Data_An_Cour!$AN:$AN,BV_Data_An_Cour!$AP:$AP,$B38,BV_Data_An_Cour!$AQ:$AQ,$C38,BV_Data_An_Cour!$AR:$AR,L$2) -> -3123709.2 | N38: =L38-F38 -> -3123709.2 | P38: =IF(Q38=0,0,Q38/O$24) -> 0 | Q38: =SUMIFS(BV_Data_An_Prec!$AN:$AN,BV_Data_An_Prec!$AP:$AP,$B38,BV_Data_An_Prec!$AQ:$AQ,$C38,BV_Data_An_Prec!$AR:$AR,Q$2) -> 0 | S38: =L38-Q38 -> -3123709.2
A39: =+B39&C39 -> Véhicules neufsCrédit Boni TD | B39: =+$K$1 -> Véhicules neufs | C39: Crédit Boni TD | E39: =F39/D$24 -> #DIV/0! | F39: {=+SUMPRODUCT(('Budget original'!$A$8:$A$501=$A39)*('Budget original'!$C$3:$AO$3=F$2),'Budget original'!$C$8:$AO$501)} -> 0 | K39: =IF(L39=0,0,L39/J$24) -> 0 | L39: =SUMIFS(BV_Data_An_Cour!$AN:$AN,BV_Data_An_Cour!$AP:$AP,$B39,BV_Data_An_Cour!$AQ:$AQ,$C39,BV_Data_An_Cour!$AR:$AR,L$2) -> 0 | N39: =L39-F39 -> 0 | P39: =IF(Q39=0,0,Q39/O$24) -> 0 | Q39: =SUMIFS(BV_Data_An_Prec!$AN:$AN,BV_Data_An_Prec!$AP:$AP,$B39,BV_Data_An_Prec!$AQ:$AQ,$C39,BV_Data_An_Prec!$AR:$AR,Q$2) -> 0 | S39: =L39-Q39 -> 0
A40: =+B40&C40 -> Véhicules neufs[...] | B40: =+$K$1 -> Véhicules neufs | C40: [...] | E40: =F40/D$24 -> #DIV/0! | F40: {=+SUMPRODUCT(('Budget original'!$A$8:$A$501=$A40)*('Budget original'!$C$3:$AO$3=F$2),'Budget original'!$C$8:$AO$501)} -> 0 | K40: =IF(L40=0,0,L40/J$24) -> 0 | L40: =SUMIFS(BV_Data_An_Cour!$AN:$AN,BV_Data_An_Cour!$AP:$AP,$B40,BV_Data_An_Cour!$AQ:$AQ,$C40,BV_Data_An_Cour!$AR:$AR,L$2) -> 0 | N40: =L40-F40 -> 0 | P40: =IF(Q40=0,0,Q40/O$24) -> 0 | Q40: =SUMIFS(BV_Data_An_Prec!$AN:$AN,BV_Data_An_Prec!$AP:$AP,$B40,BV_Data_An_Prec!$AQ:$AQ,$C40,BV_Data_An_Prec!$AR:$AR,Q$2) -> 0 | S40: =L40-Q40 -> 0
A41: =+B41&C41 -> Véhicules neufsTOTAL VARIABLES | B41: =+$K$1 -> Véhicules neufs | C41: TOTAL VARIABLES | D41: % brut | E41: =F41/F$27 -> #DIV/0! | F41: =SUM(F31:F40) -> 0 | J41: % brut | K41: =L41/L$27 -> -0.49834261 | L41: =SUM(L31:L40) -> -1704601.5 | N41: =L41-F41 -> -1704601.5 | O41: % brut | P41: =Q41/Q$27 -> #DIV/0! | Q41: =SUM(Q31:Q40) -> 0 | S41: =L41-Q41 -> -1704601.5
A42: =+B42&C42 -> Véhicules neufsSalaires cadres | B42: =+$K$1 -> Véhicules neufs | C42: Salaires cadres | F42: {=+SUMPRODUCT(('Budget original'!$A$8:$A$501=$A42)*('Budget original'!$C$3:$AO$3=F$2),'Budget original'!$C$8:$AO$501)} -> 0 | L42: =SUMIFS(BV_Data_An_Cour!$AN:$AN,BV_Data_An_Cour!$AP:$AP,$B42,BV_Data_An_Cour!$AQ:$AQ,$C42,BV_Data_An_Cour!$AR:$AR,L$2) -> 169977.2 | N42: =L42-F42 -> 169977.2 | Q42: =SUMIFS(BV_Data_An_Prec!$AN:$AN,BV_Data_An_Prec!$AP:$AP,$B42,BV_Data_An_Prec!$AQ:$AQ,$C42,BV_Data_An_Prec!$AR:$AR,Q$2) -> 0
A43: =+B43&C43 -> Véhicules neufsSalaires commis | B43: =+$K$1 -> Véhicules neufs | C43: Salaires commis | F43: {=+SUMPRODUCT(('Budget original'!$A$8:$A$501=$A43)*('Budget original'!$C$3:$AO$3=F$2),'Budget original'!$C$8:$AO$501)} -> 0 | L43: =SUMIFS(BV_Data_An_Cour!$AN:$AN,BV_Data_An_Cour!$AP:$AP,$B43,BV_Data_An_Cour!$AQ:$AQ,$C43,BV_Data_An_Cour!$AR:$AR,L$2) -> 323031.2 | N43: =L43-F43 -> 323031.2 | Q43: =SUMIFS(BV_Data_An_Prec!$AN:$AN,BV_Data_An_Prec!$AP:$AP,$B43,BV_Data_An_Prec!$AQ:$AQ,$C43,BV_Data_An_Prec!$AR:$AR,Q$2) -> 0 | S43: =L43-Q43 -> 323031.2
A44: =+B44&C44 -> Véhicules neufsSalaires autres | B44: =+$K$1 -> Véhicules neufs | C44: Salaires autres | F44: {=+SUMPRODUCT(('Budget original'!$A$8:$A$501=$A44)*('Budget original'!$C$3:$AO$3=F$2),'Budget original'!$C$8:$AO$501)} -> 0 | L44: =SUMIFS(BV_Data_An_Cour!$AN:$AN,BV_Data_An_Cour!$AP:$AP,$B44,BV_Data_An_Cour!$AQ:$AQ,$C44,BV_Data_An_Cour!$AR:$AR,L$2) -> 41995.49 | N44: =L44-F44 -> 41995.49 | Q44: =SUMIFS(BV_Data_An_Prec!$AN:$AN,BV_Data_An_Prec!$AP:$AP,$B44,BV_Data_An_Prec!$AQ:$AQ,$C44,BV_Data_An_Prec!$AR:$AR,Q$2) -> 0 | S44: =L44-Q44 -> 41995.49
A45: =+B45&C45 -> Véhicules neufsSalaires spécialistes | B45: =+$K$1 -> Véhicules neufs | C45: Salaires spécialistes | F45: {=+SUMPRODUCT(('Budget original'!$A$8:$A$501=$A45)*('Budget original'!$C$3:$AO$3=F$2),'Budget original'!$C$8:$AO$501)} -> 0 | L45: =SUMIFS(BV_Data_An_Cour!$AN:$AN,BV_Data_An_Cour!$AP:$AP,$B45,BV_Data_An_Cour!$AQ:$AQ,$C45,BV_Data_An_Cour!$AR:$AR,L$2) -> 0 | N45: =L45-F45 -> 0 | Q45: =SUMIFS(BV_Data_An_Prec!$AN:$AN,BV_Data_An_Prec!$AP:$AP,$B45,BV_Data_An_Prec!$AQ:$AQ,$C45,BV_Data_An_Prec!$AR:$AR,Q$2) -> 0 | S45: =L45-Q45 -> 0
A46: =+B46&C46 -> Véhicules neufs[...] | B46: =+$K$1 -> Véhicules neufs | C46: [...] | F46: {=+SUMPRODUCT(('Budget original'!$A$8:$A$501=$A46)*('Budget original'!$C$3:$AO$3=F$2),'Budget original'!$C$8:$AO$501)} -> 0 | L46: =SUMIFS(BV_Data_An_Cour!$AN:$AN,BV_Data_An_Cour!$AP:$AP,$B46,BV_Data_An_Cour!$AQ:$AQ,$C46,BV_Data_An_Cour!$AR:$AR,L$2) -> 0 | N46: =L46-F46 -> 0 | Q46: =SUMIFS(BV_Data_An_Prec!$AN:$AN,BV_Data_An_Prec!$AP:$AP,$B46,BV_Data_An_Prec!$AQ:$AQ,$C46,BV_Data_An_Prec!$AR:$AR,Q$2) -> 0 | S46: =L46-Q46 -> 0
A47: =+B47&C47 -> Véhicules neufs[...] | B47: =+$K$1 -> Véhicules neufs | C47: [...] | F47: {=+SUMPRODUCT(('Budget original'!$A$8:$A$501=$A47)*('Budget original'!$C$3:$AO$3=F$2),'Budget original'!$C$8:$AO$501)} -> 0 | L47: =SUMIFS(BV_Data_An_Cour!$AN:$AN,BV_Data_An_Cour!$AP:$AP,$B47,BV_Data_An_Cour!$AQ:$AQ,$C47,BV_Data_An_Cour!$AR:$AR,L$2) -> 0 | N47: =L47-F47 -> 0 | Q47: =SUMIFS(BV_Data_An_Prec!$AN:$AN,BV_Data_An_Prec!$AP:$AP,$B47,BV_Data_An_Prec!$AQ:$AQ,$C47,BV_Data_An_Prec!$AR:$AR,Q$2) -> 0 | S47: =L47-Q47 -> 0
A48: =+B48&C48 -> Véhicules neufs[...] | B48: =+$K$1 -> Véhicules neufs | C48: [...] | F48: {=+SUMPRODUCT(('Budget original'!$A$8:$A$501=$A48)*('Budget original'!$C$3:$AO$3=F$2),'Budget original'!$C$8:$AO$501)} -> 0 | L48: =SUMIFS(BV_Data_An_Cour!$AN:$AN,BV_Data_An_Cour!$AP:$AP,$B48,BV_Data_An_Cour!$AQ:$AQ,$C48,BV_Data_An_Cour!$AR:$AR,L$2) -> 0 | N48: =L48-F48 -> 0 | Q48: =SUMIFS(BV_Data_An_Prec!$AN:$AN,BV_Data_An_Prec!$AP:$AP,$B48,BV_Data_An_Prec!$AQ:$AQ,$C48,BV_Data_An_Prec!$AR:$AR,Q$2) -> 0 | S48: =L48-Q48 -> 0
A49: =+B49&C49 -> Véhicules neufsSalaires en absences | B49: =+$K$1 -> Véhicules neufs | C49: Salaires en absences | F49: {=+SUMPRODUCT(('Budget original'!$A$8:$A$501=$A49)*('Budget original'!$C$3:$AO$3=F$2),'Budget original'!$C$8:$AO$501)} -> 0 | L49: =SUMIFS(BV_Data_An_Cour!$AN:$AN,BV_Data_An_Cour!$AP:$AP,$B49,BV_Data_An_Cour!$AQ:$AQ,$C49,BV_Data_An_Cour!$AR:$AR,L$2) -> 132603.98 | N49: =L49-F49 -> 132603.98 | Q49: =SUMIFS(BV_Data_An_Prec!$AN:$AN,BV_Data_An_Prec!$AP:$AP,$B49,BV_Data_An_Prec!$AQ:$AQ,$C49,BV_Data_An_Prec!$AR:$AR,Q$2) -> 0 | S49: =L49-Q49 -> 132603.98
A50: =+B50&C50 -> Véhicules neufsDéduction à la source | B50: =+$K$1 -> Véhicules neufs | C50: Déduction à la source | F50: {=+SUMPRODUCT(('Budget original'!$A$8:$A$501=$A50)*('Budget original'!$C$3:$AO$3=F$2),'Budget original'!$C$8:$AO$501)} -> 0 | L50: =SUMIFS(BV_Data_An_Cour!$AN:$AN,BV_Data_An_Cour!$AP:$AP,$B50,BV_Data_An_Cour!$AQ:$AQ,$C50,BV_Data_An_Cour!$AR:$AR,L$2) -> 226649.79 | N50: =L50-F50 -> 226649.79 | Q50: =SUMIFS(BV_Data_An_Prec!$AN:$AN,BV_Data_An_Prec!$AP:$AP,$B50,BV_Data_An_Prec!$AQ:$AQ,$C50,BV_Data_An_Prec!$AR:$AR,Q$2) -> 0 | S50: =L50-Q50 -> 226649.79
A51: =+B51&C51 -> Véhicules neufsBénéfices marginaux | B51: =+$K$1 -> Véhicules neufs | C51: Bénéfices marginaux | F51: {=+SUMPRODUCT(('Budget original'!$A$8:$A$501=$A51)*('Budget original'!$C$3:$AO$3=F$2),'Budget original'!$C$8:$AO$501)} -> 0 | L51: =SUMIFS(BV_Data_An_Cour!$AN:$AN,BV_Data_An_Cour!$AP:$AP,$B51,BV_Data_An_Cour!$AQ:$AQ,$C51,BV_Data_An_Cour!$AR:$AR,L$2) -> 88098.38 | N51: =L51-F51 -> 88098.38 | Q51: =SUMIFS(BV_Data_An_Prec!$AN:$AN,BV_Data_An_Prec!$AP:$AP,$B51,BV_Data_An_Prec!$AQ:$AQ,$C51,BV_Data_An_Prec!$AR:$AR,Q$2) -> 0 | S51: =L51-Q51 -> 88098.38
A52: =+B52&C52 -> Véhicules neufsCsst | B52: =+$K$1 -> Véhicules neufs | C52: Csst | F52: {=+SUMPRODUCT(('Budget original'!$A$8:$A$501=$A52)*('Budget original'!$C$3:$AO$3=F$2),'Budget original'!$C$8:$AO$501)} -> 0 | L52: =SUMIFS(BV_Data_An_Cour!$AN:$AN,BV_Data_An_Cour!$AP:$AP,$B52,BV_Data_An_Cour!$AQ:$AQ,$C52,BV_Data_An_Cour!$AR:$AR,L$2) -> -6656.61 | N52: =L52-F52 -> -6656.61 | Q52: =SUMIFS(BV_Data_An_Prec!$AN:$AN,BV_Data_An_Prec!$AP:$AP,$B52,BV_Data_An_Prec!$AQ:$AQ,$C52,BV_Data_An_Prec!$AR:$AR,Q$2) -> 0 | S52: =L52-Q52 -> -6656.61
A53: =+B53&C53 -> Véhicules neufs[...] | B53: =+$K$1 -> Véhicules neufs | C53: [...] | F53: {=+SUMPRODUCT(('Budget original'!$A$8:$A$501=$A53)*('Budget original'!$C$3:$AO$3=F$2),'Budget original'!$C$8:$AO$501)} -> 0 | L53: =SUMIFS(BV_Data_An_Cour!$AN:$AN,BV_Data_An_Cour!$AP:$AP,$B53,BV_Data_An_Cour!$AQ:$AQ,$C53,BV_Data_An_Cour!$AR:$AR,L$2) -> 0 | N53: =L53-F53 -> 0 | Q53: =SUMIFS(BV_Data_An_Prec!$AN:$AN,BV_Data_An_Prec!$AP:$AP,$B53,BV_Data_An_Prec!$AQ:$AQ,$C53,BV_Data_An_Prec!$AR:$AR,Q$2) -> 0 | S53: =L53-Q53 -> 0
A54: =+B54&C54 -> Véhicules neufsTOTAL PERSONNEL | B54: =+$K$1 -> Véhicules neufs | C54: TOTAL PERSONNEL | D54: % brut | E54: =F54/F$27 -> #DIV/0! | F54: =+SUM(F42:F53) -> 0 | J54: % brut | K54: =L54/L$27 -> 0.28524708 | L54: =+SUM(L42:L53) -> 975699.43 | N54: =+SUM(N42:N53) -> 975699.43 | O54: % brut | P54: =Q54/Q$27 -> #DIV/0! | Q54: =+SUM(Q42:Q53) -> 0 | S54: =+SUM(S42:S53) -> 805722.23
A55: =+B55&C55 -> Véhicules neufsPublicité 2 | B55: =+$K$1 -> Véhicules neufs | C55: Publicité 2 | F55: {=+SUMPRODUCT(('Budget original'!$A$8:$A$501=$A55)*('Budget original'!$C$3:$AO$3=F$2),'Budget original'!$C$8:$AO$501)} -> 0 | L55: =SUMIFS(BV_Data_An_Cour!$AN:$AN,BV_Data_An_Cour!$AP:$AP,$B55,BV_Data_An_Cour!$AQ:$AQ,$C55,BV_Data_An_Cour!$AR:$AR,L$2) -> 0 | N55: =L55-F55 -> 0 | Q55: =SUMIFS(BV_Data_An_Prec!$AN:$AN,BV_Data_An_Prec!$AP:$AP,$B55,BV_Data_An_Prec!$AQ:$AQ,$C55,BV_Data_An_Prec!$AR:$AR,Q$2) -> 0 | S55: =L55-Q55 -> 0
A56: =+B56&C56 -> Véhicules neufsService gratuit 2 | B56: =+$K$1 -> Véhicules neufs | C56: Service gratuit 2 | F56: {=+SUMPRODUCT(('Budget original'!$A$8:$A$501=$A56)*('Budget original'!$C$3:$AO$3=F$2),'Budget original'!$C$8:$AO$501)} -> 0 | L56: =SUMIFS(BV_Data_An_Cour!$AN:$AN,BV_Data_An_Cour!$AP:$AP,$B56,BV_Data_An_Cour!$AQ:$AQ,$C56,BV_Data_An_Cour!$AR:$AR,L$2) -> 0 | N56: =L56-F56 -> 0 | Q56: =SUMIFS(BV_Data_An_Prec!$AN:$AN,BV_Data_An_Prec!$AP:$AP,$B56,BV_Data_An_Prec!$AQ:$AQ,$C56,BV_Data_An_Prec!$AR:$AR,Q$2) -> 0 | S56: =L56-Q56 -> 0
A57: =+B57&C57 -> Véhicules neufsFrais véhicules de cie | B57: =+$K$1 -> Véhicules neufs | C57: Frais véhicules de cie | F57: {=+SUMPRODUCT(('Budget original'!$A$8:$A$501=$A57)*('Budget original'!$C$3:$AO$3=F$2),'Budget original'!$C$8:$AO$501)} -> 0 | L57: =SUMIFS(BV_Data_An_Cour!$AN:$AN,BV_Data_An_Cour!$AP:$AP,$B57,BV_Data_An_Cour!$AQ:$AQ,$C57,BV_Data_An_Cour!$AR:$AR,L$2) -> 138425.68 | N57: =L57-F57 -> 138425.68 | Q57: =SUMIFS(BV_Data_An_Prec!$AN:$AN,BV_Data_An_Prec!$AP:$AP,$B57,BV_Data_An_Prec!$AQ:$AQ,$C57,BV_Data_An_Prec!$AR:$AR,Q$2) -> 0 | S57: =L57-Q57 -> 138425.68
A58: =+B58&C58 -> Véhicules neufsInformatique | B58: =+$K$1 -> Véhicules neufs | C58: Informatique | F58: {=+SUMPRODUCT(('Budget original'!$A$8:$A$501=$A58)*('Budget original'!$C$3:$AO$3=F$2),'Budget original'!$C$8:$AO$501)} -> 0 | L58: =SUMIFS(BV_Data_An_Cour!$AN:$AN,BV_Data_An_Cour!$AP:$AP,$B58,BV_Data_An_Cour!$AQ:$AQ,$C58,BV_Data_An_Cour!$AR:$AR,L$2) -> 50643.05 | N58: =L58-F58 -> 50643.05 | Q58: =SUMIFS(BV_Data_An_Prec!$AN:$AN,BV_Data_An_Prec!$AP:$AP,$B58,BV_Data_An_Prec!$AQ:$AQ,$C58,BV_Data_An_Prec!$AR:$AR,Q$2) -> 0 | S58: =L58-Q58 -> 50643.05
A59: =+B59&C59 -> Véhicules neufsFrais de déplacement | B59: =+$K$1 -> Véhicules neufs | C59: Frais de déplacement | F59: {=+SUMPRODUCT(('Budget original'!$A$8:$A$501=$A59)*('Budget original'!$C$3:$AO$3=F$2),'Budget original'!$C$8:$AO$501)} -> 0 | L59: =SUMIFS(BV_Data_An_Cour!$AN:$AN,BV_Data_An_Cour!$AP:$AP,$B59,BV_Data_An_Cour!$AQ:$AQ,$C59,BV_Data_An_Cour!$AR:$AR,L$2) -> 43975.39 | N59: =L59-F59 -> 43975.39 | Q59: =SUMIFS(BV_Data_An_Prec!$AN:$AN,BV_Data_An_Prec!$AP:$AP,$B59,BV_Data_An_Prec!$AQ:$AQ,$C59,BV_Data_An_Prec!$AR:$AR,Q$2) -> 0 | S59: =L59-Q59 -> 43975.39
A60: =+B60&C60 -> Véhicules neufsServices extérieurs | B60: =+$K$1 -> Véhicules neufs | C60: Services extérieurs | F60: {=+SUMPRODUCT(('Budget original'!$A$8:$A$501=$A60)*('Budget original'!$C$3:$AO$3=F$2),'Budget original'!$C$8:$AO$501)} -> 0 | L60: =SUMIFS(BV_Data_An_Cour!$AN:$AN,BV_Data_An_Cour!$AP:$AP,$B60,BV_Data_An_Cour!$AQ:$AQ,$C60,BV_Data_An_Cour!$AR:$AR,L$2) -> 86098.82 | N60: =L60-F60 -> 86098.82 | Q60: =SUMIFS(BV_Data_An_Prec!$AN:$AN,BV_Data_An_Prec!$AP:$AP,$B60,BV_Data_An_Prec!$AQ:$AQ,$C60,BV_Data_An_Prec!$AR:$AR,Q$2) -> 0 | S60: =L60-Q60 -> 86098.82
A61: =+B61&C61 -> Véhicules neufsFournitures autres | B61: =+$K$1 -> Véhicules neufs | C61: Fournitures autres | F61: {=+SUMPRODUCT(('Budget original'!$A$8:$A$501=$A61)*('Budget original'!$C$3:$AO$3=F$2),'Budget original'!$C$8:$AO$501)} -> 0 | L61: =SUMIFS(BV_Data_An_Cour!$AN:$AN,BV_Data_An_Cour!$AP:$AP,$B61,BV_Data_An_Cour!$AQ:$AQ,$C61,BV_Data_An_Cour!$AR:$AR,L$2) -> 7111.2 | N61: =L61-F61 -> 7111.2 | Q61: =SUMIFS(BV_Data_An_Prec!$AN:$AN,BV_Data_An_Prec!$AP:$AP,$B61,BV_Data_An_Prec!$AQ:$AQ,$C61,BV_Data_An_Prec!$AR:$AR,Q$2) -> 0 | S61: =L61-Q61 -> 7111.2
A62: =+B62&C62 -> Véhicules neufsUniformes | B62: =+$K$1 -> Véhicules neufs | C62: Uniformes | F62: {=+SUMPRODUCT(('Budget original'!$A$8:$A$501=$A62)*('Budget original'!$C$3:$AO$3=F$2),'Budget original'!$C$8:$AO$501)} -> 0 | L62: =SUMIFS(BV_Data_An_Cour!$AN:$AN,BV_Data_An_Cour!$AP:$AP,$B62,BV_Data_An_Cour!$AQ:$AQ,$C62,BV_Data_An_Cour!$AR:$AR,L$2) -> 0 | N62: =L62-F62 -> 0 | Q62: =SUMIFS(BV_Data_An_Prec!$AN:$AN,BV_Data_An_Prec!$AP:$AP,$B62,BV_Data_An_Prec!$AQ:$AQ,$C62,BV_Data_An_Prec!$AR:$AR,Q$2) -> 0 | S62: =L62-Q62 -> 0
A63: =+B63&C63 -> Véhicules neufsPapeterie | B63: =+$K$1 -> Véhicules neufs | C63: Papeterie | F63: {=+SUMPRODUCT(('Budget original'!$A$8:$A$501=$A63)*('Budget original'!$C$3:$AO$3=F$2),'Budget original'!$C$8:$AO$501)} -> 0 | L63: =SUMIFS(BV_Data_An_Cour!$AN:$AN,BV_Data_An_Cour!$AP:$AP,$B63,BV_Data_An_Cour!$AQ:$AQ,$C63,BV_Data_An_Cour!$AR:$AR,L$2) -> 25484 | N63: =L63-F63 -> 25484 | Q63: =SUMIFS(BV_Data_An_Prec!$AN:$AN,BV_Data_An_Prec!$AP:$AP,$B63,BV_Data_An_Prec!$AQ:$AQ,$C63,BV_Data_An_Prec!$AR:$AR,Q$2) -> 0 | S63: =L63-Q63 -> 25484
A64: =+B64&C64 -> Véhicules neufsTéléphone | B64: =+$K$1 -> Véhicules neufs | C64: Téléphone | F64: {=+SUMPRODUCT(('Budget original'!$A$8:$A$501=$A64)*('Budget original'!$C$3:$AO$3=F$2),'Budget original'!$C$8:$AO$501)} -> 0 | L64: =SUMIFS(BV_Data_An_Cour!$AN:$AN,BV_Data_An_Cour!$AP:$AP,$B64,BV_Data_An_Cour!$AQ:$AQ,$C64,BV_Data_An_Cour!$AR:$AR,L$2) -> 10073.33 | N64: =L64-F64 -> 10073.33 | Q64: =SUMIFS(BV_Data_An_Prec!$AN:$AN,BV_Data_An_Prec!$AP:$AP,$B64,BV_Data_An_Prec!$AQ:$AQ,$C64,BV_Data_An_Prec!$AR:$AR,Q$2) -> 0 | S64: =L64-Q64 -> 10073.33
A65: =+B65&C65 -> Véhicules neufsFrais postaux | B65: =+$K$1 -> Véhicules neufs | C65: Frais postaux | F65: {=+SUMPRODUCT(('Budget original'!$A$8:$A$501=$A65)*('Budget original'!$C$3:$AO$3=F$2),'Budget original'!$C$8:$AO$501)} -> 0 | L65: =SUMIFS(BV_Data_An_Cour!$AN:$AN,BV_Data_An_Cour!$AP:$AP,$B65,BV_Data_An_Cour!$AQ:$AQ,$C65,BV_Data_An_Cour!$AR:$AR,L$2) -> 11511.44 | N65: =L65-F65 -> 11511.44 | Q65: =SUMIFS(BV_Data_An_Prec!$AN:$AN,BV_Data_An_Prec!$AP:$AP,$B65,BV_Data_An_Prec!$AQ:$AQ,$C65,BV_Data_An_Prec!$AR:$AR,Q$2) -> 0 | S65: =L65-Q65 -> 11511.44
A66: =+B66&C66 -> Véhicules neufsDivers | B66: =+$K$1 -> Véhicules neufs | C66: Divers | F66: {=+SUMPRODUCT(('Budget original'!$A$8:$A$501=$A66)*('Budget original'!$C$3:$AO$3=F$2),'Budget original'!$C$8:$AO$501)} -> 0 | L66: =SUMIFS(BV_Data_An_Cour!$AN:$AN,BV_Data_An_Cour!$AP:$AP,$B66,BV_Data_An_Cour!$AQ:$AQ,$C66,BV_Data_An_Cour!$AR:$AR,L$2) -> 38627.03 | N66: =L66-F66 -> 38627.03 | Q66: =SUMIFS(BV_Data_An_Prec!$AN:$AN,BV_Data_An_Prec!$AP:$AP,$B66,BV_Data_An_Prec!$AQ:$AQ,$C66,BV_Data_An_Prec!$AR:$AR,Q$2) -> 0 | S66: =L66-Q66 -> 38627.03
... A68: =+B68&C68 -> Véhicules neufsFrais bancaires | B68: =+$K$1 -> Véhicules neufs | C68: Frais bancaires | F68: {=+SUMPRODUCT(('Budget original'!$A$8:$A$501=$A68)*('Budget original'!$C$3:$AO$3=F$2),'Budget original'!$C$8:$AO$501)} -> 0 | L68: =SUMIFS(BV_Data_An_Cour!$AN:$AN,BV_Data_An_Cour!$AP:$AP,$B68,BV_Data_An_Cour!$AQ:$AQ,$C68,BV_Data_An_Cour!$AR:$AR,L$2) -> 6036.62 | N68: =L68-F68 -> 6036.62 | Q68: =SUMIFS(BV_Data_An_Prec!$AN:$AN,BV_Data_An_Prec!$AP:$AP,$B68,BV_Data_An_Prec!$AQ:$AQ,$C68,BV_Data_An_Prec!$AR:$AR,Q$2) -> 0 | S68: =L68-Q68 -> 6036.62
A69: =+B69&C69 -> Véhicules neufs[...] | B69: =+$K$1 -> Véhicules neufs | C69: [...] | F69: {=+SUMPRODUCT(('Budget original'!$A$8:$A$501=$A69)*('Budget original'!$C$3:$AO$3=F$2),'Budget original'!$C$8:$AO$501)} -> 0 | N69: =L69-F69 -> 0 | S69: =L69-Q69 -> 0
A70: =+B70&C70 -> Véhicules neufs[...] | B70: =+$K$1 -> Véhicules neufs | C70: [...] | F70: {=+SUMPRODUCT(('Budget original'!$A$8:$A$501=$A70)*('Budget original'!$C$3:$AO$3=F$2),'Budget original'!$C$8:$AO$501)} -> 0 | L70: =SUMIFS(BV_Data_An_Cour!$AN:$AN,BV_Data_An_Cour!$AP:$AP,$B70,BV_Data_An_Cour!$AQ:$AQ,$C70,BV_Data_An_Cour!$AR:$AR,L$2) -> 0 | N70: =L70-F70 -> 0 | Q70: =SUMIFS(BV_Data_An_Prec!$AN:$AN,BV_Data_An_Prec!$AP:$AP,$B70,BV_Data_An_Prec!$AQ:$AQ,$C70,BV_Data_An_Prec!$AR:$AR,Q$2) -> 0 | S70: =L70-Q70 -> 0
A71: =+B71&C71 -> Véhicules neufs[...] | B71: =+$K$1 -> Véhicules neufs | C71: [...] | F71: {=+SUMPRODUCT(('Budget original'!$A$8:$A$501=$A71)*('Budget original'!$C$3:$AO$3=F$2),'Budget original'!$C$8:$AO$501)} -> 0 | L71: =SUMIFS(BV_Data_An_Cour!$AN:$AN,BV_Data_An_Cour!$AP:$AP,$B71,BV_Data_An_Cour!$AQ:$AQ,$C71,BV_Data_An_Cour!$AR:$AR,L$2)*0.32 -> 0 | N71: =L71-F71 -> 0 | Q71: =SUMIFS(BV_Data_An_Prec!$AN:$AN,BV_Data_An_Prec!$AP:$AP,$B71,BV_Data_An_Prec!$AQ:$AQ,$C71,BV_Data_An_Prec!$AR:$AR,Q$2)*0.32 -> 0 | S71: =L71-Q71 -> 0
A72: =+B72&C72 -> Véhicules neufsTOTAL SEMI-FIXES | B72: =+$K$1 -> Véhicules neufs | C72: TOTAL SEMI-FIXES | D72: % brut | E72: =F72/F$27 -> #DIV/0! | F72: =+SUM(F55:F71) -> 0 | J72: % brut | K72: =L72/L$27 -> 0.12477194 | L72: =+SUM(L55:L71) -> 426787.59 | N72: =+SUM(N55:N71) -> 426787.59 | O72: % brut | P72: =Q72/Q$27 -> #DIV/0! | Q72: =+SUM(Q55:Q71) -> 0 | S72: =+SUM(S55:S71) -> 426787.59
A73: =+B73&C73 -> Véhicules neufs | B73: =+$K$1 -> Véhicules neufs
A74: =+B74&C74 -> Véhicules neufsTOTAL DES DÉPENSES | B74: =+$K$1 -> Véhicules neufs | C74: TOTAL DES DÉPENSES | D74: % brut | E74: =F74/F$27 -> #DIV/0! | F74: =F41+F54+F72 -> 0 | J74: % brut | K74: =L74/L$27 -> -0.088323579 | L74: =L41+L54+L72 -> -302114.45 | N74: =L74-F74 -> -302114.45 | O74: % brut | P74: =Q74/Q$27 -> #DIV/0! | Q74: =Q41+Q54+Q72 -> 0 | S74: =L74-Q74 -> -302114.45
A75: =+B75&C75 -> Véhicules neufsProgramme Excellence | B75: =+$K$1 -> Véhicules neufs | C75: Programme Excellence | F75: {=+SUMPRODUCT(('Budget original'!$A$8:$A$501=$A75)*('Budget original'!$C$3:$AO$3=F$2),'Budget original'!$C$8:$AO$501)} -> 0 | L75: =-SUMIFS(BV_Data_An_Cour!$AN:$AN,BV_Data_An_Cour!$AP:$AP,$B75,BV_Data_An_Cour!$AQ:$AQ,$C75,BV_Data_An_Cour!$AR:$AR,L$2) -> 332501.82 | N75: =L75-F75 -> 332501.82 | Q75: =-SUMIFS(BV_Data_An_Prec!$AN:$AN,BV_Data_An_Prec!$AP:$AP,$B75,BV_Data_An_Prec!$AQ:$AQ,$C75,BV_Data_An_Prec!$AR:$AR,Q$2) -> 0
A76: =+B76&C76 -> Véhicules neufsProgramme neuf 2 | B76: =+$K$1 -> Véhicules neufs | C76: Programme neuf 2 | F76: {=+SUMPRODUCT(('Budget original'!$A$8:$A$501=$A76)*('Budget original'!$C$3:$AO$3=F$2),'Budget original'!$C$8:$AO$501)} -> 0 | L76: =-SUMIFS(BV_Data_An_Cour!$AN:$AN,BV_Data_An_Cour!$AP:$AP,$B76,BV_Data_An_Cour!$AQ:$AQ,$C76,BV_Data_An_Cour!$AR:$AR,L$2) -> 0 | N76: =L76-F76 -> 0 | Q76: =-SUMIFS(BV_Data_An_Prec!$AN:$AN,BV_Data_An_Prec!$AP:$AP,$B76,BV_Data_An_Prec!$AQ:$AQ,$C76,BV_Data_An_Prec!$AR:$AR,Q$2) -> 0 | S76: =L76-Q76 -> 0
A77: =+B77&C77 -> Véhicules neufsProgramme neuf 3 | B77: =+$K$1 -> Véhicules neufs | C77: Programme neuf 3 | F77: {=+SUMPRODUCT(('Budget original'!$A$8:$A$501=$A77)*('Budget original'!$C$3:$AO$3=F$2),'Budget original'!$C$8:$AO$501)} -> 0 | L77: =-SUMIFS(BV_Data_An_Cour!$AN:$AN,BV_Data_An_Cour!$AP:$AP,$B77,BV_Data_An_Cour!$AQ:$AQ,$C77,BV_Data_An_Cour!$AR:$AR,L$2) -> 0 | N77: =L77-F77 -> 0 | Q77: =-SUMIFS(BV_Data_An_Prec!$AN:$AN,BV_Data_An_Prec!$AP:$AP,$B77,BV_Data_An_Prec!$AQ:$AQ,$C77,BV_Data_An_Prec!$AR:$AR,Q$2) -> 0 | S77: =L77-Q77 -> 0
A78: =+B78&C78 -> Véhicules neufsHoldbacks | B78: =+$K$1 -> Véhicules neufs | C78: Holdbacks | F78: {=+SUMPRODUCT(('Budget original'!$A$8:$A$501=$A78)*('Budget original'!$C$3:$AO$3=F$2),'Budget original'!$C$8:$AO$501)} -> 0 | L78: =-SUMIFS(BV_Data_An_Cour!$AN:$AN,BV_Data_An_Cour!$AP:$AP,$B78,BV_Data_An_Cour!$AQ:$AQ,$C78,BV_Data_An_Cour!$AR:$AR,L$2) -> 0 | N78: =L78-F78 -> 0 | Q78: =-SUMIFS(BV_Data_An_Prec!$AN:$AN,BV_Data_An_Prec!$AP:$AP,$B78,BV_Data_An_Prec!$AQ:$AQ,$C78,BV_Data_An_Prec!$AR:$AR,Q$2) -> 0 | S78: =L78-Q78 -> 0
A79: =+B79&C79 -> Véhicules neufs[...] | B79: =+$K$1 -> Véhicules neufs | C79: [...] | F79: {=+SUMPRODUCT(('Budget original'!$A$8:$A$501=$A79)*('Budget original'!$C$3:$AO$3=F$2),'Budget original'!$C$8:$AO$501)} -> 0 | L79: =-SUMIFS(BV_Data_An_Cour!$AN:$AN,BV_Data_An_Cour!$AP:$AP,$B79,BV_Data_An_Cour!$AQ:$AQ,$C79,BV_Data_An_Cour!$AR:$AR,L$2) -> 0 | N79: =L79-F79 -> 0 | Q79: =-SUMIFS(BV_Data_An_Prec!$AN:$AN,BV_Data_An_Prec!$AP:$AP,$B79,BV_Data_An_Prec!$AQ:$AQ,$C79,BV_Data_An_Prec!$AR:$AR,Q$2) -> 0 | S79: =L79-Q79 -> 0
A80: =+B80&C80 -> Véhicules neufs[...] | B80: =+$K$1 -> Véhicules neufs | C80: [...] | F80: {=+SUMPRODUCT(('Budget original'!$A$8:$A$501=$A80)*('Budget original'!$C$3:$AO$3=F$2),'Budget original'!$C$8:$AO$501)} -> 0 | L80: =-SUMIFS(BV_Data_An_Cour!$AN:$AN,BV_Data_An_Cour!$AP:$AP,$B80,BV_Data_An_Cour!$AQ:$AQ,$C80,BV_Data_An_Cour!$AR:$AR,L$2) -> 0 | N80: =L80-F80 -> 0 | Q80: =-SUMIFS(BV_Data_An_Prec!$AN:$AN,BV_Data_An_Prec!$AP:$AP,$B80,BV_Data_An_Prec!$AQ:$AQ,$C80,BV_Data_An_Prec!$AR:$AR,Q$2) -> 0 | S80: =L80-Q80 -> 0
A81: =+B81&C81 -> Véhicules neufs[...] | B81: =+$K$1 -> Véhicules neufs | C81: [...] | F81: {=+SUMPRODUCT(('Budget original'!$A$8:$A$501=$A81)*('Budget original'!$C$3:$AO$3=F$2),'Budget original'!$C$8:$AO$501)} -> 0 | L81: =-SUMIFS(BV_Data_An_Cour!$AN:$AN,BV_Data_An_Cour!$AP:$AP,$B81,BV_Data_An_Cour!$AQ:$AQ,$C81,BV_Data_An_Cour!$AR:$AR,L$2) -> 0 | N81: =L81-F81 -> 0 | Q81: =-SUMIFS(BV_Data_An_Prec!$AN:$AN,BV_Data_An_Prec!$AP:$AP,$B81,BV_Data_An_Prec!$AQ:$AQ,$C81,BV_Data_An_Prec!$AR:$AR,Q$2) -> 0 | S81: =L81-Q81 -> 0
A82: =+B82&C82 -> Véhicules neufsFrais administration | B82: =+$K$1 -> Véhicules neufs | C82: Frais administration | F82: {=+SUMPRODUCT(('Budget original'!$A$8:$A$501=$A82)*('Budget original'!$C$3:$AO$3=F$2),'Budget original'!$C$8:$AO$501)} -> 0 | J82: =K82/699 -> 0 | K82: =+L82/J24 -> 0 | L82: =-SUMIFS(BV_Data_An_Cour!$AN:$AN,BV_Data_An_Cour!$AP:$AP,$B82,BV_Data_An_Cour!$AQ:$AQ,$C82,BV_Data_An_Cour!$AR:$AR,L$2) -> 0 | N82: =L82-F82 -> 0 | Q82: =-SUMIFS(BV_Data_An_Prec!$AN:$AN,BV_Data_An_Prec!$AP:$AP,$B82,BV_Data_An_Prec!$AQ:$AQ,$C82,BV_Data_An_Prec!$AR:$AR,Q$2) -> 0 | S82: =L82-Q82 -> 0
A83: =+B83&C83 -> Véhicules neufsAUTRES REVENUS | B83: =+$K$1 -> Véhicules neufs | C83: AUTRES REVENUS | F83: =+SUM(F75:F82) -> 0 | L83: =+SUM(L75:L82) -> 332501.82 | N83: =+SUM(N75:N82) -> 332501.82 | Q83: =+SUM(Q75:Q82) -> 0 | S83: =+SUM(S75:S82) -> 0
A84: =+B84&C84 -> Véhicules neufs | B84: =+$K$1 -> Véhicules neufs
A85: =+B85&C85 -> Véhicules neufsPROFIT DÉPARTEMENTAL | B85: =+$K$1 -> Véhicules neufs | C85: PROFIT DÉPARTEMENTAL | F85: =F27-F74+F83 -> 0 | L85: =L27-L74+L83 -> 4055157.6 | N85: =N27-N41-N54-N72+N83 -> 4055157.6 | Q85: =Q27-Q74+Q83 -> 0 | S85: =L85-Q85 -> 4055157.6
C89: =C1 -> Ste-Marie Auto | K89: Véhicules usagés | S89: =$S$1 -> Réalisé AAD, Décembre 2025
D91: BUDGET ORIGINAL | J91: RÉALISATION | M91: ÉCART réel / Budget | O91: ANNÉE PRÉCÉDENTE | R91: ECART (réel/ Ann.Préc.)
D92: UNITE | E92: $P/UNITÉ | F92: $PROFITS | J92: UNITÉS | K92: $P/UNITE | L92: $PROFITS | M92: UNITÉS | N92: $PROFITS | O92: UNITE | P92: $P/UNITÉ | Q92: $PROFITS | R92: UNITÉS | S92: $PROFITS
A93: =+B93&C93 -> Véhicules usagésVentes nettes | B93: Véhicules usagés | C93: Ventes nettes | F93: {=+SUMPRODUCT(('Budget original'!$A$8:$A$501=$A93)*('Budget original'!$C$3:$AO$3=F$2),'Budget original'!$C$8:$AO$501)} -> 0 | L93: =-SUMIFS(BV_Data_An_Cour!$AN:$AN,BV_Data_An_Cour!$AS:$AS,"Oui",BV_Data_An_Cour!$AP:$AP,$B93) -> 28121031 | Q93: =-SUMIFS(BV_Data_An_Prec!$AN:$AN,BV_Data_An_Prec!$AS:$AS,"Oui",BV_Data_An_Prec!$AP:$AP,$B93) -> 0
A94: =+B94&C94 -> Véhicules usagésCertifié | B94: Véhicules usagés | C94: Certifié | D94: {=+SUMPRODUCT(('Budget original'!$A$8:$A$501=$A94)*('Budget original'!$C$3:$AO$3=D$2),'Budget original'!$C$8:$AO$501)} -> 0 | E94: =IF(D94=0,0,F94/D94) -> 0 | F94: {=+SUMPRODUCT(('Budget original'!$A$8:$A$501=$A94)*('Budget original'!$C$3:$AO$3=F$2),'Budget original'!$C$8:$AO$501)} -> 0 | J94: =SUMIFS(BV_Data_An_Cour!$AX:$AX,BV_Data_An_Cour!$AP:$AP,$B94,BV_Data_An_Cour!$AQ:$AQ,$C94,BV_Data_An_Cour!$AY:$AY,J$2) -> 0 | K94: =IF(J94=0,0,L94/J94) -> 0 | L94: =-SUMIFS(BV_Data_An_Cour!$AN:$AN,BV_Data_An_Cour!$AP:$AP,$B94,BV_Data_An_Cour!$AQ:$AQ,$C94,BV_Data_An_Cour!$AR:$AR,$L2) -> 0 | M94: =J94-D94 -> 0 | N94: =L94-F94 -> 0 | O94: =SUMIFS(BV_Data_An_Prec!$AX:$AX,BV_Data_An_Prec!$AP:$AP,$B94,BV_Data_An_Prec!$AQ:$AQ,$C94,BV_Data_An_Prec!$AY:$AY,O$2) -> 0 | P94: =IF(O94=0,0,Q94/O94) -> 0 | Q94: =-SUMIFS(BV_Data_An_Prec!$AN:$AN,BV_Data_An_Prec!$AP:$AP,$B94,BV_Data_An_Prec!$AQ:$AQ,$C94,BV_Data_An_Prec!$AR:$AR,$L2) -> 0 | R94: =J94-O94 -> 0 | S94: =L94-Q94 -> 0
A95: =+B95&C95 -> Véhicules usagésNon Certifié | B95: Véhicules usagés | C95: Non Certifié | D95: {=+SUMPRODUCT(('Budget original'!$A$8:$A$501=$A95)*('Budget original'!$C$3:$AO$3=D$2),'Budget original'!$C$8:$AO$501)} -> 0 | E95: =IF(D95=0,0,F95/D95) -> 0 | F95: {=+SUMPRODUCT(('Budget original'!$A$8:$A$501=$A95)*('Budget original'!$C$3:$AO$3=F$2),'Budget original'!$C$8:$AO$501)} -> 0 | J95: =SUMIFS(BV_Data_An_Cour!$AX:$AX,BV_Data_An_Cour!$AP:$AP,$B95,BV_Data_An_Cour!$AQ:$AQ,$C95,BV_Data_An_Cour!$AY:$AY,J$2) -> 130 | K95: =IF(J95=0,0,L95/J95) -> 408.36854 | L95: =-SUMIFS(BV_Data_An_Cour!$AN:$AN,BV_Data_An_Cour!$AP:$AP,$B95,BV_Data_An_Cour!$AQ:$AQ,$C95,BV_Data_An_Cour!$AR:$AR,$L2) -> 53087.91 | M95: =J95-D95 -> 130 | N95: =L95-F95 -> 53087.91 | O95: =SUMIFS(BV_Data_An_Prec!$AX:$AX,BV_Data_An_Prec!$AP:$AP,$B95,BV_Data_An_Prec!$AQ:$AQ,$C95,BV_Data_An_Prec!$AY:$AY,O$2) -> 0 | P95: =IF(O95=0,0,Q95/O95) -> 0 | Q95: =-SUMIFS(BV_Data_An_Prec!$AN:$AN,BV_Data_An_Prec!$AP:$AP,$B95,BV_Data_An_Prec!$AQ:$AQ,$C95,BV_Data_An_Prec!$AR:$AR,$L2) -> 0 | R95: =J95-O95 -> 130 | S95: =L95-Q95 -> 53087.91
A96: =+B96&C96 -> Véhicules usagésAutres marques | B96: Véhicules usagés | C96: Autres marques | D96: {=+SUMPRODUCT(('Budget original'!$A$8:$A$501=$A96)*('Budget original'!$C$3:$AO$3=D$2),'Budget original'!$C$8:$AO$501)} -> 0 | E96: =IF(D96=0,0,F96/D96) -> 0 | F96: {=+SUMPRODUCT(('Budget original'!$A$8:$A$501=$A96)*('Budget original'!$C$3:$AO$3=F$2),'Budget original'!$C$8:$AO$501)} -> 0 | J96: =SUMIFS(BV_Data_An_Cour!$AX:$AX,BV_Data_An_Cour!$AP:$AP,$B96,BV_Data_An_Cour!$AQ:$AQ,$C96,BV_Data_An_Cour!$AY:$AY,J$2) -> 0 | K96: =IF(J96=0,0,L96/J96) -> 0 | L96: =-SUMIFS(BV_Data_An_Cour!$AN:$AN,BV_Data_An_Cour!$AP:$AP,$B96,BV_Data_An_Cour!$AQ:$AQ,$C96,BV_Data_An_Cour!$AR:$AR,$L2) -> 0 | M96: =J96-D96 -> 0 | N96: =L96-F96 -> 0 | O96: =SUMIFS(BV_Data_An_Prec!$AX:$AX,BV_Data_An_Prec!$AP:$AP,$B96,BV_Data_An_Prec!$AQ:$AQ,$C96,BV_Data_An_Prec!$AY:$AY,O$2) -> 0 | P96: =IF(O96=0,0,Q96/O96) -> 0 | Q96: =-SUMIFS(BV_Data_An_Prec!$AN:$AN,BV_Data_An_Prec!$AP:$AP,$B96,BV_Data_An_Prec!$AQ:$AQ,$C96,BV_Data_An_Prec!$AR:$AR,$L2) -> 0 | R96: =J96-O96 -> 0 | S96: =L96-Q96 -> 0
A97: =+B97&C97 -> Véhicules usagésTotal Usagés | B97: Véhicules usagés | C97: Total Usagés | D97: =+D95+D94+D96 -> 0 | E97: =IF(D97=0,0,F97/D97) -> 0 | F97: =+F94+F95+F96 -> 0 | J97: =+J94+J95+J96 -> 130 | K97: =IF(J97<=0,0,L97/J97) -> 408.36854 | L97: =+L94+L95+L96 -> 53087.91 | M97: =J97-D97 -> 130 | N97: =L97-F97 -> 53087.91 | O97: =+O94+O95+O96 -> 0 | P97: =IF(O97<=0,0,Q97/O97) -> 0 | Q97: =+Q94+Q95+Q96 -> 0 | R97: =R94+R95 -> 130 | S97: =S94+S95 -> 53087.91
A98: =+B98&C98 -> Véhicules usagés | B98: Véhicules usagés | E98: =IF(D98=0,0,F98/D98) -> 0 | R98: =R97/O97 -> #DIV/0! | S98: =IF(Q97=0,0,(S97/Q97)) -> 0
A99: =+B99&C99 -> Véhicules usagésRachat bail | B99: Véhicules usagés | C99: Rachat bail | D99: {=+SUMPRODUCT(('Budget original'!$A$8:$A$501=$A99)*('Budget original'!$C$3:$AO$3=D$2),'Budget original'!$C$8:$AO$501)} -> 0 | E99: =IF(D99=0,0,F99/D99) -> 0 | F99: {=+SUMPRODUCT(('Budget original'!$A$8:$A$501=$A99)*('Budget original'!$C$3:$AO$3=F$2),'Budget original'!$C$8:$AO$501)} -> 0 | J99: =SUMIFS(BV_Data_An_Cour!$AX:$AX,BV_Data_An_Cour!$AP:$AP,$B99,BV_Data_An_Cour!$AQ:$AQ,$C99,BV_Data_An_Cour!$AY:$AY,J$2) -> 0 | K99: =IF(J99=0,0,L99/J99) -> 0 | L99: =-SUMIFS(BV_Data_An_Cour!$AN:$AN,BV_Data_An_Cour!$AP:$AP,$B99,BV_Data_An_Cour!$AQ:$AQ,$C99,BV_Data_An_Cour!$AR:$AR,$L2) -> 0 | M99: =J99-D99 -> 0 | N99: =L99-F99 -> 0 | O99: =SUMIFS(BV_Data_An_Prec!$AX:$AX,BV_Data_An_Prec!$AP:$AP,$B99,BV_Data_An_Prec!$AQ:$AQ,$C99,BV_Data_An_Prec!$AY:$AY,O$2) -> 0 | P99: =IF(O99=0,0,Q99/O99) -> 0 | Q99: =-SUMIFS(BV_Data_An_Prec!$AN:$AN,BV_Data_An_Prec!$AP:$AP,$B99,BV_Data_An_Prec!$AQ:$AQ,$C99,BV_Data_An_Prec!$AR:$AR,$L2) -> 0 | R99: =J99-O99 -> 0 | S99: =L99-Q99 -> 0
A101: =+B101&C101 -> Véhicules usagésVentes au Gros | B101: Véhicules usagés | C101: Ventes au Gros | D101: {=+SUMPRODUCT(('Budget original'!$A$8:$A$501=$A101)*('Budget original'!$C$3:$AO$3=D$2),'Budget original'!$C$8:$AO$501)} -> 0 | E101: =IF(D101=0,0,F101/D101) -> 0 | F101: {=+SUMPRODUCT(('Budget original'!$A$8:$A$501=$A101)*('Budget original'!$C$3:$AO$3=F$2),'Budget original'!$C$8:$AO$501)} -> 0 | J101: =SUMIFS(BV_Data_An_Cour!$AX:$AX,BV_Data_An_Cour!$AP:$AP,$B101,BV_Data_An_Cour!$AQ:$AQ,$C101,BV_Data_An_Cour!$AY:$AY,J$2) -> 654 | K101: =IF(J101=0,0,L101/J101) -> 801.70237 | L101: =-SUMIFS(BV_Data_An_Cour!$AN:$AN,BV_Data_An_Cour!$AP:$AP,$B101,BV_Data_An_Cour!$AQ:$AQ,$C101,BV_Data_An_Cour!$AR:$AR,L$2) -> 524313.35 | M101: =J101-D101 -> 654 | N101: =L101-F101 -> 524313.35 | O101: =SUMIFS(BV_Data_An_Prec!$AX:$AX,BV_Data_An_Prec!$AP:$AP,$B101,BV_Data_An_Prec!$AQ:$AQ,$C101,BV_Data_An_Prec!$AY:$AY,O$2) -> 0 | P101: =IF(O101=0,0,Q101/O101) -> 0 | Q101: =-SUMIFS(BV_Data_An_Prec!$AN:$AN,BV_Data_An_Prec!$AP:$AP,$B101,BV_Data_An_Prec!$AQ:$AQ,$C101,BV_Data_An_Prec!$AR:$AR,Q$2) -> 0 | R101: =J101-O101 -> 654 | S101: =L101-Q101 -> 524313.35
A102: =+B102&C102 -> Véhicules usagés | B102: Véhicules usagés
A103: =+B103&C103 -> Véhicules usagésRev. Finances | B103: Véhicules usagés | C103: Rev. Finances | D103: {=+SUMPRODUCT(('Budget original'!$A$8:$A$501=$A103)*('Budget original'!$C$3:$AO$3=D$2),'Budget original'!$C$8:$AO$501)} -> 0 | E103: =IF(D103=0,0,F103/D103) -> 0 | F103: {=+SUMPRODUCT(('Budget original'!$A$8:$A$501=$A103)*('Budget original'!$C$3:$AO$3=F$2),'Budget original'!$C$8:$AO$501)} -> 0 | K103: =IF(J97=0,0,L103/J97) -> 280.35938 | L103: =-SUMIFS(BV_Data_An_Cour!$AN:$AN,BV_Data_An_Cour!$AP:$AP,$B103,BV_Data_An_Cour!$AQ:$AQ,$C103,BV_Data_An_Cour!$AR:$AR,$L2) -> 36446.72 | N103: =L103-F103 -> 36446.72 | P103: =IF(O97=0,0,Q103/O97) -> 0 | Q103: =-SUMIFS(BV_Data_An_Prec!$AN:$AN,BV_Data_An_Prec!$AP:$AP,$B103,BV_Data_An_Prec!$AQ:$AQ,$C103,BV_Data_An_Prec!$AR:$AR,$L2) -> 0 | R103: =P103-K103 -> -280.35938 | S103: =L103-Q103 -> 36446.72
A104: =+B104&C104 -> Véhicules usagésRev. Protections | B104: Véhicules usagés | C104: Rev. Protections | D104: {=+SUMPRODUCT(('Budget original'!$A$8:$A$501=$A104)*('Budget original'!$C$3:$AO$3=D$2),'Budget original'!$C$8:$AO$501)} -> 0 | E104: =IF(D104=0,0,F104/D104) -> 0 | F104: {=+SUMPRODUCT(('Budget original'!$A$8:$A$501=$A104)*('Budget original'!$C$3:$AO$3=F$2),'Budget original'!$C$8:$AO$501)} -> 0 | K104: =IF(J97=0,0,L104/J97) -> 733.96662 | L104: =-SUMIFS(BV_Data_An_Cour!$AN:$AN,BV_Data_An_Cour!$AP:$AP,$B104,BV_Data_An_Cour!$AQ:$AQ,$C104,BV_Data_An_Cour!$AR:$AR,$L2) -> 95415.66 | N104: =L104-F104 -> 95415.66 | P104: =IF(O97=0,0,Q104/O97) -> 0 | Q104: =-SUMIFS(BV_Data_An_Prec!$AN:$AN,BV_Data_An_Prec!$AP:$AP,$B104,BV_Data_An_Prec!$AQ:$AQ,$C104,BV_Data_An_Prec!$AR:$AR,$L2) -> 0 | R104: =P104-K104 -> -733.96662 | S104: =L104-Q104 -> 95415.66
A105: =+B105&C105 -> Véhicules usagésRev. Autres | B105: Véhicules usagés | C105: Rev. Autres | D105: {=+SUMPRODUCT(('Budget original'!$A$8:$A$501=$A105)*('Budget original'!$C$3:$AO$3=D$2),'Budget original'!$C$8:$AO$501)} -> 0 | E105: =IF(D105=0,0,F105/D105) -> 0 | F105: {=+SUMPRODUCT(('Budget original'!$A$8:$A$501=$A105)*('Budget original'!$C$3:$AO$3=F$2),'Budget original'!$C$8:$AO$501)} -> 0 | K105: =IF(J97=0,0,L105/J97) -> 0 | L105: =-SUMIFS(BV_Data_An_Cour!$AN:$AN,BV_Data_An_Cour!$AP:$AP,$B105,BV_Data_An_Cour!$AQ:$AQ,$C105,BV_Data_An_Cour!$AR:$AR,$L$2) -> 0 | N105: =L105-F105 -> 0 | P105: =IF(O97=0,0,Q105/O97) -> 0 | Q105: =-SUMIFS(BV_Data_An_Prec!$AN:$AN,BV_Data_An_Prec!$AP:$AP,$B105,BV_Data_An_Prec!$AQ:$AQ,$C105,BV_Data_An_Prec!$AR:$AR,$L$2) -> 0 | R105: =P105-K105 -> 0 | S105: =L105-Q105 -> 0
A106: =+B106&C106 -> Véhicules usagésTotal F&I | B106: Véhicules usagés | C106: Total F&I | D106: =D97 -> 0 | E106: =IF(D106=0,0,F106/D106) -> 0 | F106: =F103+F104+F105 -> 0 | J106: =J97 -> 130 | K106: =IF(J106<=0,0,L106/J106) -> 1014.326 | L106: =L103+L104+L105 -> 131862.38 | M106: =J106-D106 -> 130 | N106: =L106-F106 -> 131862.38 | O106: =O97 -> 0 | P106: =IF(O106<=0,0,Q106/O106) -> 0 | Q106: =Q103+Q104+Q105 -> 0 | R106: =P106-K106 -> -1014.326 | S106: =L106-Q106 -> 131862.38
...

Sheet Carrosserie_Mois
C1: =Print_Mois!C1 -> Ste-Marie Auto | M1: Carrosserie | W1: =Print_Mois!S1 -> Réalisé, Décembre 2025
D3: BUDGET ORIGINAL | L3: RÉALISATION | P3: ÉCART réel / Budget | R3: ANNÉE PRÉCÉDENTE | V3: ECART (réel/ Ann.Préc.)
B4: Carrosserie | D4: # | E4: $VENTES | F4: % P. BRUT | G4: $PROFITS | L4: # | M4: $VENTES | N4: % P. BRUT | O4: $PROFITS | P4: # | Q4: $PROFFTS | R4: # | S4: $VENTES | T4: % P. BRUT | U4: $PROFITS | V4: % VOL | W4: $PROFITS
B5: Carrosserie
B6: Carrosserie | C6: M-O Carrosserie Client | L6: =SUMIFS(BV_Data_An_Cour!$AW:$AW,BV_Data_An_Cour!$AO:$AO,$Y6) -> 38 | M6: =-SUMIFS(BV_Data_An_Cour!$AM:$AM,BV_Data_An_Cour!$AO:$AO,$Y6) -> 41501.96 | N6: =IFERROR(O6/M6,0) -> 0.55033569 | O6: =-SUMIFS(BV_Data_An_Cour!$AM:$AM,BV_Data_An_Cour!$AO:$AO,$Y6)-SUMIFS(BV_Data_An_Cour!$AM:$AM,BV_Data_An_Cour!$AO:$AO,$Z6) -> 22840.01 | P6: =IFERROR((M6-E6)/E6,0) -> 0 | Q6: =O6-G6 -> 22840.01 | R6: =SUMIFS(BV_Data_An_Prec!$AW:$AW,BV_Data_An_Prec!$AO:$AO,$Y6) -> 0 | S6: =-SUMIFS(BV_Data_An_Prec!$AM:$AM,BV_Data_An_Prec!$AO:$AO,$Y6) -> 0 | T6: =IFERROR(U6/S6,0) -> 0 | U6: =-SUMIFS(BV_Data_An_Prec!$AM:$AM,BV_Data_An_Prec!$AO:$AO,$Y6)-SUMIFS(BV_Data_An_Prec!$AM:$AM,BV_Data_An_Prec!$AO:$AO,$Z6) -> 0 | V6: =IF(R6=0,0,L6/R6) -> 0 | W6: =O6-U6 -> 22840.01 | Y6: G47100 | Z6: G67100
B7: Carrosserie | C7: M-O Peinture Client | L7: =SUMIFS(BV_Data_An_Cour!$AW:$AW,BV_Data_An_Cour!$AO:$AO,$Y7) -> 0 | M7: =-SUMIFS(BV_Data_An_Cour!$AM:$AM,BV_Data_An_Cour!$AO:$AO,$Y7) -> 0 | N7: =IFERROR(O7/M7,0) -> 0 | O7: =-SUMIFS(BV_Data_An_Cour!$AM:$AM,BV_Data_An_Cour!$AO:$AO,$Y7)-SUMIFS(BV_Data_An_Cour!$AM:$AM,BV_Data_An_Cour!$AO:$AO,$Z7) -> 0 | P7: =IFERROR((M7-E7)/E7,0) -> 0 | Q7: =O7-G7 -> 0 | R7: =SUMIFS(BV_Data_An_Prec!$AW:$AW,BV_Data_An_Prec!$AO:$AO,$Y7) -> 0 | S7: =-SUMIFS(BV_Data_An_Prec!$AM:$AM,BV_Data_An_Prec!$AO:$AO,$Y7) -> 0 | T7: =IFERROR(U7/S7,0) -> 0 | U7: =-SUMIFS(BV_Data_An_Prec!$AM:$AM,BV_Data_An_Prec!$AO:$AO,$Y7)-SUMIFS(BV_Data_An_Prec!$AM:$AM,BV_Data_An_Prec!$AO:$AO,$Z7) -> 0 | V7: =IF(R7=0,0,L7/R7) -> 0 | W7: =O7-U7 -> 0 | Y7: G47000 | Z7: G67000
B8: Carrosserie | C8: M-O Mécanique Client | L8: =SUMIFS(BV_Data_An_Cour!$AW:$AW,BV_Data_An_Cour!$AO:$AO,$Y8) -> 0 | M8: =-SUMIFS(BV_Data_An_Cour!$AM:$AM,BV_Data_An_Cour!$AO:$AO,$Y8) -> 0 | N8: =IFERROR(O8/M8,0) -> 0 | O8: =-SUMIFS(BV_Data_An_Cour!$AM:$AM,BV_Data_An_Cour!$AO:$AO,$Y8)-SUMIFS(BV_Data_An_Cour!$AM:$AM,BV_Data_An_Cour!$AO:$AO,$Z8) -> 0 | P8: =IFERROR((M8-E8)/E8,0) -> 0 | Q8: =O8-G8 -> 0 | R8: =SUMIFS(BV_Data_An_Prec!$AW:$AW,BV_Data_An_Prec!$AO:$AO,$Y8) -> 0 | S8: =-SUMIFS(BV_Data_An_Prec!$AM:$AM,BV_Data_An_Prec!$AO:$AO,$Y8) -> 0 | T8: =IFERROR(U8/S8,0) -> 0 | U8: =-SUMIFS(BV_Data_An_Prec!$AM:$AM,BV_Data_An_Prec!$AO:$AO,$Y8)-SUMIFS(BV_Data_An_Prec!$AM:$AM,BV_Data_An_Prec!$AO:$AO,$Z8) -> 0 | V8: =IF(R8=0,0,L8/R8) -> 0 | W8: =O8-U8 -> 0 | Y8: G47110 | Z8: G67110
B9: Carrosserie | C9: Pièces ST Client | L9: =SUMIFS(BV_Data_An_Cour!$AW:$AW,BV_Data_An_Cour!$AO:$AO,$Y9) -> 0 | M9: =-SUMIFS(BV_Data_An_Cour!$AM:$AM,BV_Data_An_Cour!$AO:$AO,$Y9) -> 0 | N9: =IFERROR(O9/M9,0) -> 0 | O9: =-SUMIFS(BV_Data_An_Cour!$AM:$AM,BV_Data_An_Cour!$AO:$AO,$Y9)-SUMIFS(BV_Data_An_Cour!$AM:$AM,BV_Data_An_Cour!$AO:$AO,$Z9) -> 0 | P9: =IFERROR((M9-E9)/E9,0) -> 0 | Q9: =O9-G9 -> 0 | R9: =SUMIFS(BV_Data_An_Prec!$AW:$AW,BV_Data_An_Prec!$AO:$AO,$Y9) -> 0 | S9: =-SUMIFS(BV_Data_An_Prec!$AM:$AM,BV_Data_An_Prec!$AO:$AO,$Y9) -> 0 | T9: =IFERROR(U9/S9,0) -> 0 | U9: =-SUMIFS(BV_Data_An_Prec!$AM:$AM,BV_Data_An_Prec!$AO:$AO,$Y9)-SUMIFS(BV_Data_An_Prec!$AM:$AM,BV_Data_An_Prec!$AO:$AO,$Z9) -> 0 | V9: =IF(R9=0,0,L9/R9) -> 0 | W9: =O9-U9 -> 0 | Y9: G47610 | Z9: G67610
B10: Carrosserie | C10: Peinture Client | L10: =SUMIFS(BV_Data_An_Cour!$AW:$AW,BV_Data_An_Cour!$AO:$AO,$Y10) -> 41 | M10: =-SUMIFS(BV_Data_An_Cour!$AM:$AM,BV_Data_An_Cour!$AO:$AO,$Y10) -> 14988.55 | N10: =IFERROR(O10/M10,0) -> -1.9399562 | O10: =-SUMIFS(BV_Data_An_Cour!$AM:$AM,BV_Data_An_Cour!$AO:$AO,$Y10)-SUMIFS(BV_Data_An_Cour!$AM:$AM,BV_Data_An_Cour!$AO:$AO,$Z10) -> -29077.13 | P10: =IFERROR((M10-E10)/E10,0) -> 0 | Q10: =O10-G10 -> -29077.13 | R10: =SUMIFS(BV_Data_An_Prec!$AW:$AW,BV_Data_An_Prec!$AO:$AO,$Y10) -> 0 | S10: =-SUMIFS(BV_Data_An_Prec!$AM:$AM,BV_Data_An_Prec!$AO:$AO,$Y10) -> 0 | T10: =IFERROR(U10/S10,0) -> 0 | U10: =-SUMIFS(BV_Data_An_Prec!$AM:$AM,BV_Data_An_Prec!$AO:$AO,$Y10)-SUMIFS(BV_Data_An_Prec!$AM:$AM,BV_Data_An_Prec!$AO:$AO,$Z10) -> 0 | V10: =IF(R10=0,0,L10/R10) -> 0 | W10: =O10-U10 -> -29077.13 | Y10: G47900 | Z10: G67900
B11: Carrosserie | C11: Matériel Atelier Client | L11: =SUMIFS(BV_Data_An_Cour!$AW:$AW,BV_Data_An_Cour!$AO:$AO,$Y11) -> 0 | M11: =-SUMIFS(BV_Data_An_Cour!$AM:$AM,BV_Data_An_Cour!$AO:$AO,$Y11) -> 0 | N11: =IFERROR(O11/M11,0) -> 0 | O11: =-SUMIFS(BV_Data_An_Cour!$AM:$AM,BV_Data_An_Cour!$AO:$AO,$Y11)-SUMIFS(BV_Data_An_Cour!$AM:$AM,BV_Data_An_Cour!$AO:$AO,$Z11) -> 0 | P11: =IFERROR((M11-E11)/E11,0) -> 0 | Q11: =O11-G11 -> 0 | R11: =SUMIFS(BV_Data_An_Prec!$AW:$AW,BV_Data_An_Prec!$AO:$AO,$Y11) -> 0 | S11: =-SUMIFS(BV_Data_An_Prec!$AM:$AM,BV_Data_An_Prec!$AO:$AO,$Y11) -> 0 | T11: =IFERROR(U11/S11,0) -> 0 | U11: =-SUMIFS(BV_Data_An_Prec!$AM:$AM,BV_Data_An_Prec!$AO:$AO,$Y11)-SUMIFS(BV_Data_An_Prec!$AM:$AM,BV_Data_An_Prec!$AO:$AO,$Z11) -> 0 | V11: =IF(R11=0,0,L11/R11) -> 0 | W11: =O11-U11 -> 0 | Y11: G47910 | Z11: G67910
B12: Carrosserie | C12: Sous-Traitance Client | L12: =SUMIFS(BV_Data_An_Cour!$AW:$AW,BV_Data_An_Cour!$AO:$AO,$Y12) -> 38 | M12: =-SUMIFS(BV_Data_An_Cour!$AM:$AM,BV_Data_An_Cour!$AO:$AO,$Y12) -> 81100.96 | N12: =IFERROR(O12/M12,0) -> 0.20793367 | O12: =-SUMIFS(BV_Data_An_Cour!$AM:$AM,BV_Data_An_Cour!$AO:$AO,$Y12)-SUMIFS(BV_Data_An_Cour!$AM:$AM,BV_Data_An_Cour!$AO:$AO,$Z12) -> 16863.62 | P12: =IFERROR((M12-E12)/E12,0) -> 0 | Q12: =O12-G12 -> 16863.62 | R12: =SUMIFS(BV_Data_An_Prec!$AW:$AW,BV_Data_An_Prec!$AO:$AO,$Y12) -> 0 | S12: =-SUMIFS(BV_Data_An_Prec!$AM:$AM,BV_Data_An_Prec!$AO:$AO,$Y12) -> 0 | T12: =IFERROR(U12/S12,0) -> 0 | U12: =-SUMIFS(BV_Data_An_Prec!$AM:$AM,BV_Data_An_Prec!$AO:$AO,$Y12)-SUMIFS(BV_Data_An_Prec!$AM:$AM,BV_Data_An_Prec!$AO:$AO,$Z12) -> 0 | V12: =IF(R12=0,0,L12/R12) -> 0 | W12: =O12-U12 -> 16863.62 | Y12: G47600 | Z12: G67600
B13: Carrosserie | C13: Carrosserie Clients | E13: =SUM(E6:E12) -> 0 | F13: =G13/E13 -> #DIV/0! | G13: =SUM(G6:G12) -> 0 | M13: =SUM(M6:M12) -> 137591.47 | N13: =IFERROR(O13/M13,0) -> 0.077232259 | O13: =SUM(O6:O12) -> 10626.5 | P13: =IFERROR((M13-E13)/E13,0) -> 0 | Q13: =O13-G13 -> 10626.5 | S13: =SUM(S6:S12) -> 0 | T13: =IFERROR(U13/S13,0) -> 0 | U13: =SUM(U6:U12) -> 0 | V13: =IF(R13=0,0,L13/R13) -> 0 | W13: =O13-U13 -> 10626.5
B14: Carrosserie
B15: Carrosserie | C15: M-O Carrosserie Interne | L15: =SUMIFS(BV_Data_An_Cour!$AW:$AW,BV_Data_An_Cour!$AO:$AO,$Y15) -> 3 | M15: =-SUMIFS(BV_Data_An_Cour!$AM:$AM,BV_Data_An_Cour!$AO:$AO,$Y15) -> 3975.63 | N15: =IFERROR(O15/M15,0) -> -1.3208523 | O15: =-SUMIFS(BV_Data_An_Cour!$AM:$AM,BV_Data_An_Cour!$AO:$AO,$Y15)-SUMIFS(BV_Data_An_Cour!$AM:$AM,BV_Data_An_Cour!$AO:$AO,$Z15) -> -5251.22 | P15: =IFERROR((M15-E15)/E15,0) -> 0 | Q15: =O15-G15 -> -5251.22 | R15: =SUMIFS(BV_Data_An_Prec!$AW:$AW,BV_Data_An_Prec!$AO:$AO,$Y15) -> 0 | S15: =-SUMIFS(BV_Data_An_Prec!$AM:$AM,BV_Data_An_Prec!$AO:$AO,$Y15) -> 0 | T15: =IFERROR(U15/S15,0) -> 0 | U15: =-SUMIFS(BV_Data_An_Prec!$AM:$AM,BV_Data_An_Prec!$AO:$AO,$Y15)-SUMIFS(BV_Data_An_Prec!$AM:$AM,BV_Data_An_Prec!$AO:$AO,$Z15) -> 0 | V15: =IF(R15=0,0,L15/R15) -> 0 | W15: =O15-U15 -> -5251.22 | Y15: G47300 | Z15: G67300
B16: Carrosserie | C16: M-O Peinture Interne | L16: =SUMIFS(BV_Data_An_Cour!$AW:$AW,BV_Data_An_Cour!$AO:$AO,$Y16) -> 0 | M16: =-SUMIFS(BV_Data_An_Cour!$AM:$AM,BV_Data_An_Cour!$AO:$AO,$Y16) -> 0 | N16: =IFERROR(O16/M16,0) -> 0 | O16: =-SUMIFS(BV_Data_An_Cour!$AM:$AM,BV_Data_An_Cour!$AO:$AO,$Y16)-SUMIFS(BV_Data_An_Cour!$AM:$AM,BV_Data_An_Cour!$AO:$AO,$Z16) -> 0 | P16: =IFERROR((M16-E16)/E16,0) -> 0 | Q16: =O16-G16 -> 0 | R16: =SUMIFS(BV_Data_An_Prec!$AW:$AW,BV_Data_An_Prec!$AO:$AO,$Y16) -> 0 | S16: =-SUMIFS(BV_Data_An_Prec!$AM:$AM,BV_Data_An_Prec!$AO:$AO,$Y16) -> 0 | T16: =IFERROR(U16/S16,0) -> 0 | U16: =-SUMIFS(BV_Data_An_Prec!$AM:$AM,BV_Data_An_Prec!$AO:$AO,$Y16)-SUMIFS(BV_Data_An_Prec!$AM:$AM,BV_Data_An_Prec!$AO:$AO,$Z16) -> 0 | V16: =IF(R16=0,0,L16/R16) -> 0 | W16: =O16-U16 -> 0 | Y16: G47303 | Z16: G67303
B17: Carrosserie | C17: M-O Mécanique Interne | L17: =SUMIFS(BV_Data_An_Cour!$AW:$AW,BV_Data_An_Cour!$AO:$AO,$Y17) -> 0 | M17: =-SUMIFS(BV_Data_An_Cour!$AM:$AM,BV_Data_An_Cour!$AO:$AO,$Y17) -> 0 | N17: =IFERROR(O17/M17,0) -> 0 | O17: =-SUMIFS(BV_Data_An_Cour!$AM:$AM,BV_Data_An_Cour!$AO:$AO,$Y17)-SUMIFS(BV_Data_An_Cour!$AM:$AM,BV_Data_An_Cour!$AO:$AO,$Z17) -> 0 | P17: =IFERROR((M17-E17)/E17,0) -> 0 | Q17: =O17-G17 -> 0 | R17: =SUMIFS(BV_Data_An_Prec!$AW:$AW,BV_Data_An_Prec!$AO:$AO,$Y17) -> 0 | S17: =-SUMIFS(BV_Data_An_Prec!$AM:$AM,BV_Data_An_Prec!$AO:$AO,$Y17) -> 0 | T17: =IFERROR(U17/S17,0) -> 0 | U17: =-SUMIFS(BV_Data_An_Prec!$AM:$AM,BV_Data_An_Prec!$AO:$AO,$Y17)-SUMIFS(BV_Data_An_Prec!$AM:$AM,BV_Data_An_Prec!$AO:$AO,$Z17) -> 0 | V17: =IF(R17=0,0,L17/R17) -> 0 | W17: =O17-U17 -> 0 | Y17: G47313 | Z17: G67313
B18: Carrosserie | C18: Pièces ST Interne | L18: =SUMIFS(BV_Data_An_Cour!$AW:$AW,BV_Data_An_Cour!$AO:$AO,$Y18) -> 0 | M18: =-SUMIFS(BV_Data_An_Cour!$AM:$AM,BV_Data_An_Cour!$AO:$AO,$Y18) -> 0 | N18: =IFERROR(O18/M18,0) -> 0 | O18: =-SUMIFS(BV_Data_An_Cour!$AM:$AM,BV_Data_An_Cour!$AO:$AO,$Y18)-SUMIFS(BV_Data_An_Cour!$AM:$AM,BV_Data_An_Cour!$AO:$AO,$Z18) -> 0 | P18: =IFERROR((M18-E18)/E18,0) -> 0 | Q18: =O18-G18 -> 0 | R18: =SUMIFS(BV_Data_An_Prec!$AW:$AW,BV_Data_An_Prec!$AO:$AO,$Y18) -> 0 | S18: =-SUMIFS(BV_Data_An_Prec!$AM:$AM,BV_Data_An_Prec!$AO:$AO,$Y18) -> 0 | T18: =IFERROR(U18/S18,0) -> 0 | U18: =-SUMIFS(BV_Data_An_Prec!$AM:$AM,BV_Data_An_Prec!$AO:$AO,$Y18)-SUMIFS(BV_Data_An_Prec!$AM:$AM,BV_Data_An_Prec!$AO:$AO,$Z18) -> 0 | V18: =IF(R18=0,0,L18/R18) -> 0 | W18: =O18-U18 -> 0 | Y18: G47613 | Z18: G67613
B19: Carrosserie | C19: Peinture Interne | L19: =SUMIFS(BV_Data_An_Cour!$AW:$AW,BV_Data_An_Cour!$AO:$AO,$Y19) -> 0 | M19: =-SUMIFS(BV_Data_An_Cour!$AM:$AM,BV_Data_An_Cour!$AO:$AO,$Y19) -> 0 | N19: =IFERROR(O19/M19,0) -> 0 | O19: =-SUMIFS(BV_Data_An_Cour!$AM:$AM,BV_Data_An_Cour!$AO:$AO,$Y19)-SUMIFS(BV_Data_An_Cour!$AM:$AM,BV_Data_An_Cour!$AO:$AO,$Z19) -> 0 | P19: =IFERROR((M19-E19)/E19,0) -> 0 | Q19: =O19-G19 -> 0 | R19: =SUMIFS(BV_Data_An_Prec!$AW:$AW,BV_Data_An_Prec!$AO:$AO,$Y19) -> 0 | S19: =-SUMIFS(BV_Data_An_Prec!$AM:$AM,BV_Data_An_Prec!$AO:$AO,$Y19) -> 0 | T19: =IFERROR(U19/S19,0) -> 0 | U19: =-SUMIFS(BV_Data_An_Prec!$AM:$AM,BV_Data_An_Prec!$AO:$AO,$Y19)-SUMIFS(BV_Data_An_Prec!$AM:$AM,BV_Data_An_Prec!$AO:$AO,$Z19) -> 0 | V19: =IF(R19=0,0,L19/R19) -> 0 | W19: =O19-U19 -> 0 | Y19: G47903 | Z19: G67903
B20: Carrosserie | C20: Matériel Atelier Interne | L20: =SUMIFS(BV_Data_An_Cour!$AW:$AW,BV_Data_An_Cour!$AO:$AO,$Y20) -> 0 | M20: =-SUMIFS(BV_Data_An_Cour!$AM:$AM,BV_Data_An_Cour!$AO:$AO,$Y20) -> 0 | N20: =IFERROR(O20/M20,0) -> 0 | O20: =-SUMIFS(BV_Data_An_Cour!$AM:$AM,BV_Data_An_Cour!$AO:$AO,$Y20)-SUMIFS(BV_Data_An_Cour!$AM:$AM,BV_Data_An_Cour!$AO:$AO,$Z20) -> 0 | P20: =IFERROR((M20-E20)/E20,0) -> 0 | Q20: =O20-G20 -> 0 | R20: =SUMIFS(BV_Data_An_Prec!$AW:$AW,BV_Data_An_Prec!$AO:$AO,$Y20) -> 0 | S20: =-SUMIFS(BV_Data_An_Prec!$AM:$AM,BV_Data_An_Prec!$AO:$AO,$Y20) -> 0 | T20: =IFERROR(U20/S20,0) -> 0 | U20: =-SUMIFS(BV_Data_An_Prec!$AM:$AM,BV_Data_An_Prec!$AO:$AO,$Y20)-SUMIFS(BV_Data_An_Prec!$AM:$AM,BV_Data_An_Prec!$AO:$AO,$Z20) -> 0 | V20: =IF(R20=0,0,L20/R20) -> 0 | W20: =O20-U20 -> 0 | Y20: G47913 | Z20: G67913
B21: Carrosserie | C21: Sous-Traitance Interne | L21: =SUMIFS(BV_Data_An_Cour!$AW:$AW,BV_Data_An_Cour!$AO:$AO,$Y21) -> 0 | M21: =-SUMIFS(BV_Data_An_Cour!$AM:$AM,BV_Data_An_Cour!$AO:$AO,$Y21) -> 0 | N21: =IFERROR(O21/M21,0) -> 0 | O21: =-SUMIFS(BV_Data_An_Cour!$AM:$AM,BV_Data_An_Cour!$AO:$AO,$Y21)-SUMIFS(BV_Data_An_Cour!$AM:$AM,BV_Data_An_Cour!$AO:$AO,$Z21) -> 0 | P21: =IFERROR((M21-E21)/E21,0) -> 0 | Q21: =O21-G21 -> 0 | R21: =SUMIFS(BV_Data_An_Prec!$AW:$AW,BV_Data_An_Prec!$AO:$AO,$Y21) -> 0 | S21: =-SUMIFS(BV_Data_An_Prec!$AM:$AM,BV_Data_An_Prec!$AO:$AO,$Y21) -> 0 | T21: =IFERROR(U21/S21,0) -> 0 | U21: =-SUMIFS(BV_Data_An_Prec!$AM:$AM,BV_Data_An_Prec!$AO:$AO,$Y21)-SUMIFS(BV_Data_An_Prec!$AM:$AM,BV_Data_An_Prec!$AO:$AO,$Z21) -> 0 | V21: =IF(R21=0,0,L21/R21) -> 0 | W21: =O21-U21 -> 0 | Y21: G47603 | Z21: G67603
C22: M-O Garantie | L22: =SUMIFS(BV_Data_An_Cour!$AW:$AW,BV_Data_An_Cour!$AO:$AO,$Y22) -> 2 | M22: =-SUMIFS(BV_Data_An_Cour!$AM:$AM,BV_Data_An_Cour!$AO:$AO,$Y22) -> 1267.65 | N22: =IFERROR(O22/M22,0) -> 0.70603873 | O22: =-SUMIFS(BV_Data_An_Cour!$AM:$AM,BV_Data_An_Cour!$AO:$AO,$Y22)-SUMIFS(BV_Data_An_Cour!$AM:$AM,BV_Data_An_Cour!$AO:$AO,$Z22) -> 895.01 | P22: =IFERROR((M22-E22)/E22,0) -> 0 | Q22: =O22-G22 -> 895.01 | R22: =SUMIFS(BV_Data_An_Prec!$AW:$AW,BV_Data_An_Prec!$AO:$AO,$Y22) -> 0 | S22: =-SUMIFS(BV_Data_An_Prec!$AM:$AM,BV_Data_An_Prec!$AO:$AO,$Y22) -> 0 | T22: =IFERROR(U22/S22,0) -> 0 | U22: =-SUMIFS(BV_Data_An_Prec!$AM:$AM,BV_Data_An_Prec!$AO:$AO,$Y22)-SUMIFS(BV_Data_An_Prec!$AM:$AM,BV_Data_An_Prec!$AO:$AO,$Z22) -> 0 | V22: =IF(R22=0,0,L22/R22) -> 0 | W22: =O22-U22 -> 895.01 | Y22: G47200 | Z22: G67200
B23: Carrosserie | C23: Carrosserie Interne | E23: =SUM(E15:E21) -> 0 | F23: =G23/E23 -> #DIV/0! | G23: =SUM(G15:G21) -> 0 | M23: =SUM(M15:M22) -> 5243.28 | N23: =IFERROR(O23/M23,0) -> -0.83081773 | O23: =SUM(O15:O22) -> -4356.21 | P23: =IFERROR((M23-E23)/E23,0) -> 0 | Q23: =O23-G23 -> -4356.21 | S23: =SUM(S15:S22) -> 0 | T23: =IFERROR(U23/S23,0) -> 0 | U23: =SUM(U15:U22) -> 0 | V23: =IF(R23=0,0,L23/R23) -> 0 | W23: =SUM(W15:W22) -> -4356.21
B24: Carrosserie
B25: Carrosserie | C25: M-O Carrosserie Concession | L25: =SUMIFS(BV_Data_An_Cour!$AW:$AW,BV_Data_An_Cour!$AO:$AO,$Y25) -> 0 | M25: =-SUMIFS(BV_Data_An_Cour!$AM:$AM,BV_Data_An_Cour!$AO:$AO,$Y25) -> 0 | N25: =IFERROR(O25/M25,0) -> 0 | O25: =-SUMIFS(BV_Data_An_Cour!$AM:$AM,BV_Data_An_Cour!$AO:$AO,$Y25)-SUMIFS(BV_Data_An_Cour!$AM:$AM,BV_Data_An_Cour!$AO:$AO,$Z25) -> 0 | P25: =IFERROR((M25-E25)/E25,0) -> 0 | Q25: =O25-G25 -> 0 | R25: =SUMIFS(BV_Data_An_Prec!$AW:$AW,BV_Data_An_Prec!$AO:$AO,$Y25) -> 0 | S25: =-SUMIFS(BV_Data_An_Prec!$AM:$AM,BV_Data_An_Prec!$AO:$AO,$Y25) -> 0 | T25: =IFERROR(U25/S25,0) -> 0 | U25: =-SUMIFS(BV_Data_An_Prec!$AM:$AM,BV_Data_An_Prec!$AO:$AO,$Y25)-SUMIFS(BV_Data_An_Prec!$AM:$AM,BV_Data_An_Prec!$AO:$AO,$Z25) -> 0 | V25: =IF(R25=0,0,L25/R25) -> 0 | W25: =O25-U25 -> 0 | Y25: G47105 | Z25: G67105
B26: Carrosserie | C26: M-O Peinture Concession | L26: =SUMIFS(BV_Data_An_Cour!$AW:$AW,BV_Data_An_Cour!$AO:$AO,$Y26) -> 0 | M26: =-SUMIFS(BV_Data_An_Cour!$AM:$AM,BV_Data_An_Cour!$AO:$AO,$Y26) -> 0 | N26: =IFERROR(O26/M26,0) -> 0 | O26: =-SUMIFS(BV_Data_An_Cour!$AM:$AM,BV_Data_An_Cour!$AO:$AO,$Y26)-SUMIFS(BV_Data_An_Cour!$AM:$AM,BV_Data_An_Cour!$AO:$AO,$Z26) -> 0 | P26: =IFERROR((M26-E26)/E26,0) -> 0 | Q26: =O26-G26 -> 0 | R26: =SUMIFS(BV_Data_An_Prec!$AW:$AW,BV_Data_An_Prec!$AO:$AO,$Y26) -> 0 | S26: =-SUMIFS(BV_Data_An_Prec!$AM:$AM,BV_Data_An_Prec!$AO:$AO,$Y26) -> 0 | T26: =IFERROR(U26/S26,0) -> 0 | U26: =-SUMIFS(BV_Data_An_Prec!$AM:$AM,BV_Data_An_Prec!$AO:$AO,$Y26)-SUMIFS(BV_Data_An_Prec!$AM:$AM,BV_Data_An_Prec!$AO:$AO,$Z26) -> 0 | V26: =IF(R26=0,0,L26/R26) -> 0 | W26: =O26-U26 -> 0 | Y26: G47005 | Z26: G67005
B27: Carrosserie | C27: M-O Mécanique Concession | L27: =SUMIFS(BV_Data_An_Cour!$AW:$AW,BV_Data_An_Cour!$AO:$AO,$Y27) -> 0 | M27: =-SUMIFS(BV_Data_An_Cour!$AM:$AM,BV_Data_An_Cour!$AO:$AO,$Y27) -> 0 | N27: =IFERROR(O27/M27,0) -> 0 | O27: =-SUMIFS(BV_Data_An_Cour!$AM:$AM,BV_Data_An_Cour!$AO:$AO,$Y27)-SUMIFS(BV_Data_An_Cour!$AM:$AM,BV_Data_An_Cour!$AO:$AO,$Z27) -> 0 | P27: =IFERROR((M27-E27)/E27,0) -> 0 | Q27: =O27-G27 -> 0 | R27: =SUMIFS(BV_Data_An_Prec!$AW:$AW,BV_Data_An_Prec!$AO:$AO,$Y27) -> 0 | S27: =-SUMIFS(BV_Data_An_Prec!$AM:$AM,BV_Data_An_Prec!$AO:$AO,$Y27) -> 0 | T27: =IFERROR(U27/S27,0) -> 0 | U27: =-SUMIFS(BV_Data_An_Prec!$AM:$AM,BV_Data_An_Prec!$AO:$AO,$Y27)-SUMIFS(BV_Data_An_Prec!$AM:$AM,BV_Data_An_Prec!$AO:$AO,$Z27) -> 0 | V27: =IF(R27=0,0,L27/R27) -> 0 | W27: =O27-U27 -> 0 | Y27: G47115 | Z27: G67115
B28: Carrosserie | C28: Pièces ST Concession | L28: =SUMIFS(BV_Data_An_Cour!$AW:$AW,BV_Data_An_Cour!$AO:$AO,$Y28) -> 0 | M28: =-SUMIFS(BV_Data_An_Cour!$AM:$AM,BV_Data_An_Cour!$AO:$AO,$Y28) -> 0 | N28: =IFERROR(O28/M28,0) -> 0 | O28: =-SUMIFS(BV_Data_An_Cour!$AM:$AM,BV_Data_An_Cour!$AO:$AO,$Y28)-SUMIFS(BV_Data_An_Cour!$AM:$AM,BV_Data_An_Cour!$AO:$AO,$Z28) -> 0 | P28: =IFERROR((M28-E28)/E28,0) -> 0 | Q28: =O28-G28 -> 0 | R28: =SUMIFS(BV_Data_An_Prec!$AW:$AW,BV_Data_An_Prec!$AO:$AO,$Y28) -> 0 | S28: =-SUMIFS(BV_Data_An_Prec!$AM:$AM,BV_Data_An_Prec!$AO:$AO,$Y28) -> 0 | T28: =IFERROR(U28/S28,0) -> 0 | U28: =-SUMIFS(BV_Data_An_Prec!$AM:$AM,BV_Data_An_Prec!$AO:$AO,$Y28)-SUMIFS(BV_Data_An_Prec!$AM:$AM,BV_Data_An_Prec!$AO:$AO,$Z28) -> 0 | V28: =IF(R28=0,0,L28/R28) -> 0 | W28: =O28-U28 -> 0 | Y28: G47615 | Z28: G67615
