Workbook
Name Ticker: #REF!

Sheet Parametres
A1: Compagnie | B1: Volks
G2: 1-Mémo | M2: Mois | N2: YTD
A3: Mois Courant | B3: Novembre | C3: =+VLOOKUP(B3,$K$3:$L$14,2,0) -> 11 | G3: 10-Compte compteur | K3: Janvier | L3: 1 | M3: =+IF($K3=$B$3,"X","") | N3: =+IF(K3=B3,"X",IF(L3<=$C$3,"X","")) -> X
A4: Année | B4: 2023 | K4: Février | L4: 2 | M4: =+IF($K4=$B$3,"X","") | N4: =+IF(K4=B4,"X",IF(L4<=$C$3,"X","")) -> X
K5: Mars | L5: 3 | M5: =+IF($K5=$B$3,"X","") | N5: =+IF(K5=B5,"X",IF(L5<=$C$3,"X","")) -> X
K6: Avril | L6: 4 | M6: =+IF($K6=$B$3,"X","") | N6: =+IF(K6=B6,"X",IF(L6<=$C$3,"X","")) -> X
K7: Mai | L7: 5 | M7: =+IF($K7=$B$3,"X","") | N7: =+IF(K7=B7,"X",IF(L7<=$C$3,"X","")) -> X
K8: Juin | L8: 6 | M8: =+IF($K8=$B$3,"X","") | N8: =+IF(K8=B8,"X",IF(L8<=$C$3,"X","")) -> X
A9: Sélectionner le mois en B3 | K9: Juillet | L9: 7 | M9: =+IF($K9=$B$3,"X","") | N9: =+IF(K9=B9,"X",IF(L9<=$C$3,"X","")) -> X
A10: Coller les balances de vérification respectives en cellule A1 dans les onglets BV_Data_An_Cour et BV_Data_An_Prec | K10: Août | L10: 8 | M10: =+IF($K10=$B$3,"X","") | N10: =+IF(K10=B10,"X",IF(L10<=$C$3,"X","")) -> X
A11: Vérifier s'il y a des #N/A dans les colonnes T à X des onlgets de BV | K11: Septembre | L11: 9 | M11: =+IF($K11=$B$3,"X","") | N11: =+IF(K11=B11,"X",IF(L11<=$C$3,"X","")) -> X
A12: Vérifier les chiffres avec l'état financier et les réalisés an passé pour les résultat net mois et aad | K12: Octobre | L12: 10 | M12: =+IF($K12=$B$3,"X","") | N12: =+IF(K12=B12,"X",IF(L12<=$C$3,"X","")) -> X
K13: Novembre | L13: 11 | M13: =+IF($K13=$B$3,"X","") -> X | N13: =+IF(K13=B13,"X",IF(L13<=$C$3,"X","")) -> X
K14: Décembre | L14: 12 | M14: =+IF($K14=$B$3,"X","") | N14: =+IF(K14=B14,"X",IF(L14<=$C$3,"X",""))

Sheet Bilan
A1: BILAN
A2: =+Parametres!B1 -> Volks
A3: =CONCATENATE("",,Parametres!B3," ",Parametres!B4) -> Novembre 2023
A5: Encaisse | B5: =SUMIFS(BV_Data_An_Cour!$P:$P,BV_Data_An_Cour!$U:$U,$A$1,BV_Data_An_Cour!$V:$V,$A5) -> -200594.14 | D5: Marge de crédit | E5: =-SUMIFS(BV_Data_An_Cour!$P:$P,BV_Data_An_Cour!$U:$U,$A$1,BV_Data_An_Cour!$V:$V,$D5) -> 0
A6: Total Trésorerie et équivalent de Trésorerie | B6: =SUM(B5) -> -200594.14
D7: Portion Court Terme de la Dette Long Terme | E7: =-SUMIFS(BV_Data_An_Cour!$P:$P,BV_Data_An_Cour!$U:$U,$A$1,BV_Data_An_Cour!$V:$V,$D7) -> 0
A8: Recevables Contrats en Transit | B8: =SUMIFS(BV_Data_An_Cour!$P:$P,BV_Data_An_Cour!$U:$U,$A$1,BV_Data_An_Cour!$V:$V,$A8) -> 2274657.7
A9: Recevables Véhicules | B9: =SUMIFS(BV_Data_An_Cour!$P:$P,BV_Data_An_Cour!$U:$U,$A$1,BV_Data_An_Cour!$V:$V,$A9) -> 369958.83 | D9: Avances à payer | E9: =-SUMIFS(BV_Data_An_Cour!$P:$P,BV_Data_An_Cour!$U:$U,$A$1,BV_Data_An_Cour!$V:$V,$D9) -> 0
A10: Recevables Manufacturier | B10: =SUMIFS(BV_Data_An_Cour!$P:$P,BV_Data_An_Cour!$U:$U,$A$1,BV_Data_An_Cour!$V:$V,$A10) -> 130525.34 | D10: Comptes à Payer Fournisseurs | E10: =-SUMIFS(BV_Data_An_Cour!$P:$P,BV_Data_An_Cour!$U:$U,$A$1,BV_Data_An_Cour!$V:$V,$D10) -> 890962.02
A11: Recevables Pièces et Service | B11: =SUMIFS(BV_Data_An_Cour!$P:$P,BV_Data_An_Cour!$U:$U,$A$1,BV_Data_An_Cour!$V:$V,$A11) -> 161189.93 | D11: Taxes de Vente à Payer | E11: =-SUMIFS(BV_Data_An_Cour!$P:$P,BV_Data_An_Cour!$U:$U,$A$1,BV_Data_An_Cour!$V:$V,$D11) -> -60578.39
A12: Recevables Garantie Manufacturier | B12: =SUMIFS(BV_Data_An_Cour!$P:$P,BV_Data_An_Cour!$U:$U,$A$1,BV_Data_An_Cour!$V:$V,$A12) -> 31356.42 | D12: Impôts à payer | E12: =-SUMIFS(BV_Data_An_Cour!$P:$P,BV_Data_An_Cour!$U:$U,$A$1,BV_Data_An_Cour!$V:$V,$D12) -> 0
A13: Recevables Carrosserie | B13: =SUMIFS(BV_Data_An_Cour!$P:$P,BV_Data_An_Cour!$U:$U,$A$1,BV_Data_An_Cour!$V:$V,$A13) -> 37776.63 | D13: Dépôts de Client | E13: =-SUMIFS(BV_Data_An_Cour!$P:$P,BV_Data_An_Cour!$U:$U,$A$1,BV_Data_An_Cour!$V:$V,$D13) -> 24850
A14: Recevables Intercos | B14: =SUMIFS(BV_Data_An_Cour!$P:$P,BV_Data_An_Cour!$U:$U,$A$1,BV_Data_An_Cour!$V:$V,$A14) -> 42752.14 | D14: Payables Intercos | E14: =-SUMIFS(BV_Data_An_Cour!$P:$P,BV_Data_An_Cour!$U:$U,$A$1,BV_Data_An_Cour!$V:$V,$D14) -> 84906.93
A15: Recevables Autres | B15: =SUMIFS(BV_Data_An_Cour!$P:$P,BV_Data_An_Cour!$U:$U,$A$1,BV_Data_An_Cour!$V:$V,$A15) -> 49133 | D15: Autres Comptes à Payer | E15: =-SUMIFS(BV_Data_An_Cour!$P:$P,BV_Data_An_Cour!$U:$U,$A$1,BV_Data_An_Cour!$V:$V,$D15) -> 414000.94
A16: Total Comptes à Recevoir | B16: =+SUM(B8:B15) -> 3097350 | D16: Total Comptes à Payer | E16: =+SUM(E10:E15) -> 1354141.5
A18: Inventaire Véhicules Neufs | B18: =SUMIFS(BV_Data_An_Cour!$P:$P,BV_Data_An_Cour!$U:$U,$A$1,BV_Data_An_Cour!$V:$V,$A18) -> 3242138.3 | D18: Effet à Payer Véhicules Neufs | E18: =-SUMIFS(BV_Data_An_Cour!$P:$P,BV_Data_An_Cour!$U:$U,$A$1,BV_Data_An_Cour!$V:$V,$D18) -> 4472488.5
A19: Inventaire Véhicules Usagés | B19: =SUMIFS(BV_Data_An_Cour!$P:$P,BV_Data_An_Cour!$U:$U,$A$1,BV_Data_An_Cour!$V:$V,$A19) -> 2176291.1 | D19: Effet à Payer Véhicules Usagés | E19: =-SUMIFS(BV_Data_An_Cour!$P:$P,BV_Data_An_Cour!$U:$U,$A$1,BV_Data_An_Cour!$V:$V,$D19) -> 362813.1
A20: Inventaire Pièces, Pneus, Huile | B20: =SUMIFS(BV_Data_An_Cour!$P:$P,BV_Data_An_Cour!$U:$U,$A$1,BV_Data_An_Cour!$V:$V,$A20) -> 518591.98 | D20: Total Effets à Payer | E20: =+SUM(E18:E19) -> 4835301.6
A21: Total Inventaires | B21: =SUM(B18:B20) -> 5937021.4
D22: Salaires à Payer | E22: =-SUMIFS(BV_Data_An_Cour!$P:$P,BV_Data_An_Cour!$U:$U,$A$1,BV_Data_An_Cour!$V:$V,$D22) -> 404245.67
A23: Avances à recevoir | B23: =SUMIFS(BV_Data_An_Cour!$P:$P,BV_Data_An_Cour!$U:$U,$A$1,BV_Data_An_Cour!$V:$V,$A23) -> 0 | D23: DAS à Payer | E23: =-SUMIFS(BV_Data_An_Cour!$P:$P,BV_Data_An_Cour!$U:$U,$A$1,BV_Data_An_Cour!$V:$V,$D23) -> 5096.64
A24: Travaux en Cours | B24: =SUMIFS(BV_Data_An_Cour!$P:$P,BV_Data_An_Cour!$U:$U,$A$1,BV_Data_An_Cour!$V:$V,$A24) -> 9673.17 | D24: Autres Courus | E24: =-SUMIFS(BV_Data_An_Cour!$P:$P,BV_Data_An_Cour!$U:$U,$A$1,BV_Data_An_Cour!$V:$V,$D24) -> 360677.37
A25: Sous-Traitance | B25: =SUMIFS(BV_Data_An_Cour!$P:$P,BV_Data_An_Cour!$U:$U,$A$1,BV_Data_An_Cour!$V:$V,$A25) -> -21051.46 | D25: [...] | E25: =-SUMIFS(BV_Data_An_Cour!$P:$P,BV_Data_An_Cour!$U:$U,$A$1,BV_Data_An_Cour!$V:$V,$D25) -> 0
A26: Frais Payés d'Avance | B26: =SUMIFS(BV_Data_An_Cour!$P:$P,BV_Data_An_Cour!$U:$U,$A$1,BV_Data_An_Cour!$V:$V,$A26) -> 84938.62 | D26: [...] | E26: =-SUMIFS(BV_Data_An_Cour!$P:$P,BV_Data_An_Cour!$U:$U,$A$1,BV_Data_An_Cour!$V:$V,$D26) -> 0
A27: [...] | B27: =SUMIFS(BV_Data_An_Cour!$P:$P,BV_Data_An_Cour!$U:$U,$A$1,BV_Data_An_Cour!$V:$V,$A27) -> 0 | D27: [...] | E27: =-SUMIFS(BV_Data_An_Cour!$P:$P,BV_Data_An_Cour!$U:$U,$A$1,BV_Data_An_Cour!$V:$V,$D27) -> 0
A28: [...] | B28: =SUMIFS(BV_Data_An_Cour!$P:$P,BV_Data_An_Cour!$U:$U,$A$1,BV_Data_An_Cour!$V:$V,$A28) -> 0 | D28: Total Frais Courus | E28: =SUM(E22:E24) -> 770019.68
A29: [...] | B29: =SUMIFS(BV_Data_An_Cour!$P:$P,BV_Data_An_Cour!$U:$U,$A$1,BV_Data_An_Cour!$V:$V,$A29) -> 0
A30: Total Autres | B30: =SUM(B23:B29) -> 73560.33 | D30: Total Passif Court Terme | E30: =+E5+E7+E16+E20+E28 -> 6959462.8
A32: Total Actif Court Terme | B32: =+B6+B16+B21+B30 -> 8907337.6
D33: Impôts Futurs à payer | E33: =-SUMIFS(BV_Data_An_Cour!$P:$P,BV_Data_An_Cour!$U:$U,$A$1,BV_Data_An_Cour!$V:$V,$D33) -> 0
A35: Terrain | B35: =SUMIFS(BV_Data_An_Cour!$P:$P,BV_Data_An_Cour!$U:$U,$A$1,BV_Data_An_Cour!$V:$V,$A35) -> 0 | D35: Avances Long Terme à Payer | E35: =-SUMIFS(BV_Data_An_Cour!$P:$P,BV_Data_An_Cour!$U:$U,$A$1,BV_Data_An_Cour!$V:$V,$D35) -> 0
A36: Bâtisse | B36: =SUMIFS(BV_Data_An_Cour!$P:$P,BV_Data_An_Cour!$U:$U,$A$1,BV_Data_An_Cour!$V:$V,$A36) -> 0 | D36: Hypothèque à Payer | E36: =-SUMIFS(BV_Data_An_Cour!$P:$P,BV_Data_An_Cour!$U:$U,$A$1,BV_Data_An_Cour!$V:$V,$D36) -> 0
A37: Améliorations Locatives | B37: =SUMIFS(BV_Data_An_Cour!$P:$P,BV_Data_An_Cour!$U:$U,$A$1,BV_Data_An_Cour!$V:$V,$A37) -> 609212.17 | D37: Dette à Long Terme | E37: =-SUMIFS(BV_Data_An_Cour!$P:$P,BV_Data_An_Cour!$U:$U,$A$1,BV_Data_An_Cour!$V:$V,$D37) -> 0
A38: Améliorations Locatives Permanentes | B38: =SUMIFS(BV_Data_An_Cour!$P:$P,BV_Data_An_Cour!$U:$U,$A$1,BV_Data_An_Cour!$V:$V,$A38) -> 0 | D38: Autres Dettes à Long Terme | E38: =-SUMIFS(BV_Data_An_Cour!$P:$P,BV_Data_An_Cour!$U:$U,$A$1,BV_Data_An_Cour!$V:$V,$D38) -> 0
A39: Équipements Service | B39: =SUMIFS(BV_Data_An_Cour!$P:$P,BV_Data_An_Cour!$U:$U,$A$1,BV_Data_An_Cour!$V:$V,$A39) -> 272626.94 | D39: [...] | E39: =-SUMIFS(BV_Data_An_Cour!$P:$P,BV_Data_An_Cour!$U:$U,$A$1,BV_Data_An_Cour!$V:$V,$D39) -> 0
A40: Mobilier | B40: =SUMIFS(BV_Data_An_Cour!$P:$P,BV_Data_An_Cour!$U:$U,$A$1,BV_Data_An_Cour!$V:$V,$A40) -> 26298.79 | D40: [...] | E40: =-SUMIFS(BV_Data_An_Cour!$P:$P,BV_Data_An_Cour!$U:$U,$A$1,BV_Data_An_Cour!$V:$V,$D40) -> 0
A41: Équipements Informatique | B41: =SUMIFS(BV_Data_An_Cour!$P:$P,BV_Data_An_Cour!$U:$U,$A$1,BV_Data_An_Cour!$V:$V,$A41) -> 17785.24 | D41: [...] | E41: =-SUMIFS(BV_Data_An_Cour!$P:$P,BV_Data_An_Cour!$U:$U,$A$1,BV_Data_An_Cour!$V:$V,$D41) -> 0
A42: Équipements Téléphonique | B42: =SUMIFS(BV_Data_An_Cour!$P:$P,BV_Data_An_Cour!$U:$U,$A$1,BV_Data_An_Cour!$V:$V,$A42) -> 0 | D42: Total Passif long terme | E42: =+SUM(E33:E38) -> 0
A43: Enseigne | B43: =SUMIFS(BV_Data_An_Cour!$P:$P,BV_Data_An_Cour!$U:$U,$A$1,BV_Data_An_Cour!$V:$V,$A43) -> 0.01
A44: Total Immobilisations Nettes | B44: =SUM(B35:B43) -> 925923.15
D45: Total Passifs | E45: =+E42+E30 -> 6959462.8
A46: Avances à Recevoir Long Terme | B46: =SUMIFS(BV_Data_An_Cour!$P:$P,BV_Data_An_Cour!$U:$U,$A$1,BV_Data_An_Cour!$V:$V,$A46) -> 8473600
A48: Achalandage | B48: =SUMIFS(BV_Data_An_Cour!$P:$P,BV_Data_An_Cour!$U:$U,$A$1,BV_Data_An_Cour!$V:$V,$A48) -> 0 | D48: Capital Actions | E48: =-SUMIFS(BV_Data_An_Cour!$P:$P,BV_Data_An_Cour!$U:$U,$A$1,BV_Data_An_Cour!$V:$V,$D48) -> 2697547.5
D49: Apport | E49: =-SUMIFS(BV_Data_An_Cour!$P:$P,BV_Data_An_Cour!$U:$U,$A$1,BV_Data_An_Cour!$V:$V,$D49) -> 1723617
A50: [...] | B50: =SUMIFS(BV_Data_An_Cour!$P:$P,BV_Data_An_Cour!$U:$U,$A$1,BV_Data_An_Cour!$V:$V,$A50) -> 0 | D50: Bénéfices non répartis | E50: =-SUMIFS(BV_Data_An_Cour!$P:$P,BV_Data_An_Cour!$U:$U,$A$1,BV_Data_An_Cour!$V:$V,$D50)+Print_AAD!AF497 -> 6926233.4
A51: [...] | B51: =SUMIFS(BV_Data_An_Cour!$P:$P,BV_Data_An_Cour!$U:$U,$A$1,BV_Data_An_Cour!$V:$V,$A51) -> 0 | D51: Dividendes | E51: =-SUMIFS(BV_Data_An_Cour!$P:$P,BV_Data_An_Cour!$U:$U,$A$1,BV_Data_An_Cour!$V:$V,$D51) -> 0
A52: [...] | B52: =SUMIFS(BV_Data_An_Cour!$P:$P,BV_Data_An_Cour!$U:$U,$A$1,BV_Data_An_Cour!$V:$V,$A52) -> 0
A53: Total Actif Long Terme | B53: =+B44+B48+B46 -> 9399523.2 | D53: Total Capitaux Propres / Avoir | E53: =SUM(E48:E51) -> 11347398
A56: Total Actif | B56: =+B32+B53 -> 18306861 | D56: Total Passif et Capitaux Propres / Avoir | E56: =+E53+E45 -> 18306861
E65: =+B56-E56 -> 0

Sheet Budget original
B1: ="Budget 2023 Mensuel Révisé"&" "&Parametres!$B$1 -> Budget 2023 Mensuel Révisé Volks
B2: Mois | F2: =+IF(Parametres!$B$3=F$6,"X","") | G2: =+IF(Parametres!$B$3=F$6,"O","") | H2: =+IF(Parametres!$B$3=F$6,"U","") | I2: =+IF(Parametres!$B$3=I$6,"X","") | J2: =+IF(Parametres!$B$3=I$6,"O","") | K2: =+IF(Parametres!$B$3=I$6,"U","") | L2: =+IF(Parametres!$B$3=L$6,"X","") | M2: =+IF(Parametres!$B$3=L$6,"O","") | N2: =+IF(Parametres!$B$3=L$6,"U","") | O2: =+IF(Parametres!$B$3=O$6,"X","") | P2: =+IF(Parametres!$B$3=O$6,"O","") | Q2: =+IF(Parametres!$B$3=O$6,"U","") | R2: =+IF(Parametres!$B$3=R$6,"X","") | S2: =+IF(Parametres!$B$3=R$6,"O","") | T2: =+IF(Parametres!$B$3=R$6,"U","") | U2: =+IF(Parametres!$B$3=U$6,"X","") | V2: =+IF(Parametres!$B$3=U$6,"O","") | W2: =+IF(Parametres!$B$3=U$6,"U","") | X2: =+IF(Parametres!$B$3=X$6,"X","") | Y2: =+IF(Parametres!$B$3=X$6,"O","") | Z2: =+IF(Parametres!$B$3=X$6,"U","") | AA2: =+IF(Parametres!$B$3=AA$6,"X","") | AB2: =+IF(Parametres!$B$3=AA$6,"O","") | AC2: =+IF(Parametres!$B$3=AA$6,"U","") | AD2: =+IF(Parametres!$B$3=AD$6,"X","") | AE2: =+IF(Parametres!$B$3=AD$6,"O","") | AF2: =+IF(Parametres!$B$3=AD$6,"U","") | AG2: =+IF(Parametres!$B$3=AG$6,"X","") | AH2: =+IF(Parametres!$B$3=AG$6,"O","") | AI2: =+IF(Parametres!$B$3=AG$6,"U","") | AJ2: =+IF(Parametres!$B$3=AJ$6,"X","") -> X | AK2: =+IF(Parametres!$B$3=AJ$6,"O","") -> O | AL2: =+IF(Parametres!$B$3=AJ$6,"U","") -> U | AM2: =+IF(Parametres!$B$3=AM$6,"X","") | AN2: =+IF(Parametres!$B$3=AM$6,"O","") | AO2: =+IF(Parametres!$B$3=AM$6,"U","")
B3: YTD | F3: =+IF(VLOOKUP(F$6,Parametres!$K$3:$N$14,4,0)="X","X","") -> X | G3: =+IF(VLOOKUP(F$6,Parametres!$K$3:$N$14,4,0)="X","O","") -> O | H3: =+IF(VLOOKUP(F$6,Parametres!$K$3:$N$14,4,0)="X","U","") -> U | I3: =+IF(VLOOKUP(I$6,Parametres!$K$3:$N$14,4,0)="X","X","") -> X | J3: =+IF(VLOOKUP(I$6,Parametres!$K$3:$N$14,4,0)="X","O","") -> O | K3: =+IF(VLOOKUP(I$6,Parametres!$K$3:$N$14,4,0)="X","U","") -> U | L3: =+IF(VLOOKUP(L$6,Parametres!$K$3:$N$14,4,0)="X","X","") -> X | M3: =+IF(VLOOKUP(L$6,Parametres!$K$3:$N$14,4,0)="X","O","") -> O | N3: =+IF(VLOOKUP(L$6,Parametres!$K$3:$N$14,4,0)="X","U","") -> U | O3: =+IF(VLOOKUP(O$6,Parametres!$K$3:$N$14,4,0)="X","X","") -> X | P3: =+IF(VLOOKUP(O$6,Parametres!$K$3:$N$14,4,0)="X","O","") -> O | Q3: =+IF(VLOOKUP(O$6,Parametres!$K$3:$N$14,4,0)="X","U","") -> U | R3: =+IF(VLOOKUP(R$6,Parametres!$K$3:$N$14,4,0)="X","X","") -> X | S3: =+IF(VLOOKUP(R$6,Parametres!$K$3:$N$14,4,0)="X","O","") -> O | T3: =+IF(VLOOKUP(R$6,Parametres!$K$3:$N$14,4,0)="X","U","") -> U | U3: =+IF(VLOOKUP(U$6,Parametres!$K$3:$N$14,4,0)="X","X","") -> X | V3: =+IF(VLOOKUP(U$6,Parametres!$K$3:$N$14,4,0)="X","O","") -> O | W3: =+IF(VLOOKUP(U$6,Parametres!$K$3:$N$14,4,0)="X","U","") -> U | X3: =+IF(VLOOKUP(X$6,Parametres!$K$3:$N$14,4,0)="X","X","") -> X | Y3: =+IF(VLOOKUP(X$6,Parametres!$K$3:$N$14,4,0)="X","O","") -> O | Z3: =+IF(VLOOKUP(X$6,Parametres!$K$3:$N$14,4,0)="X","U","") -> U | AA3: =+IF(VLOOKUP(AA$6,Parametres!$K$3:$N$14,4,0)="X","X","") -> X | AB3: =+IF(VLOOKUP(AA$6,Parametres!$K$3:$N$14,4,0)="X","O","") -> O | AC3: =+IF(VLOOKUP(AA$6,Parametres!$K$3:$N$14,4,0)="X","U","") -> U | AD3: =+IF(VLOOKUP(AD$6,Parametres!$K$3:$N$14,4,0)="X","X","") -> X | AE3: =+IF(VLOOKUP(AD$6,Parametres!$K$3:$N$14,4,0)="X","O","") -> O | AF3: =+IF(VLOOKUP(AD$6,Parametres!$K$3:$N$14,4,0)="X","U","") -> U | AG3: =+IF(VLOOKUP(AG$6,Parametres!$K$3:$N$14,4,0)="X","X","") -> X | AH3: =+IF(VLOOKUP(AG$6,Parametres!$K$3:$N$14,4,0)="X","O","") -> O | AI3: =+IF(VLOOKUP(AG$6,Parametres!$K$3:$N$14,4,0)="X","U","") -> U | AJ3: =+IF(VLOOKUP(AJ$6,Parametres!$K$3:$N$14,4,0)="X","X","") -> X | AK3: =+IF(VLOOKUP(AJ$6,Parametres!$K$3:$N$14,4,0)="X","O","") -> O | AL3: =+IF(VLOOKUP(AJ$6,Parametres!$K$3:$N$14,4,0)="X","U","") -> U | AM3: =+IF(VLOOKUP(AM$6,Parametres!$K$3:$N$14,4,0)="X","X","") | AN3: =+IF(VLOOKUP(AM$6,Parametres!$K$3:$N$14,4,0)="X","O","") | AO3: =+IF(VLOOKUP(AM$6,Parametres!$K$3:$N$14,4,0)="X","U","")
B4: Budget 2023 | C4: Véhicules neufs
B6: Mois | C6: TOTAL | F6: Janvier | I6: Février | L6: Mars | O6: Avril | R6: Mai | U6: Juin | X6: Juillet | AA6: Août | AD6: Septembre | AG6: Octobre | AJ6: Novembre | AM6: Décembre
C7: UNITE | D7: $P/UNITE | E7: $PROFITS | F7: UNITE | G7: $P/UNITE | H7: $PROFITS | I7: UNITE | J7: $P/UNITE | K7: $PROFITS | L7: UNITE | M7: $P/UNITE | N7: $PROFITS | O7: UNITE | P7: $P/UNITE | Q7: $PROFITS | R7: UNITE | S7: $P/UNITE | T7: $PROFITS | U7: UNITE | V7: $P/UNITE | W7: $PROFITS | X7: UNITE | Y7: $P/UNITE | Z7: $PROFITS | AA7: UNITE | AB7: $P/UNITE | AC7: $PROFITS | AD7: UNITE | AE7: $P/UNITE | AF7: $PROFITS | AG7: UNITE | AH7: $P/UNITE | AI7: $PROFITS | AJ7: UNITE | AK7: $P/UNITE | AL7: $PROFITS | AM7: UNITE | AN7: $P/UNITE | AO7: $PROFITS
A8: =+$C$4&B8 -> Véhicules neufsVentes nettes | B8: Ventes nettes | E8: 29441341 | H8: 2058973.9 | K8: 1513989 | N8: 2694522.6 | Q8: 2946054.1 | T8: 3239507.5 | W8: 2275303.5 | Z8: 2357227.3 | AC8: 2438191.1 | AF8: 2522034.9 | AI8: 2898372.2 | AL8: 3024137.9 | AO8: 1473027.1
A9: =+$C$4&B9 -> Véhicules neufsAutos détail | B9: Autos détail | C9: 125.6 | D9: 1988.434 | E9: 249747.31 | F9: 8.792 | G9: 1988.434 | H9: 17482.312 | I9: 6.4594286 | J9: 1988.434 | K9: 12844.147 | L9: 11.483429 | M9: 1988.434 | N9: 22834.04 | O9: 12.56 | P9: 1988.434 | Q9: 24974.731 | R9: 13.816 | S9: 1988.434 | T9: 27472.204 | U9: 9.6891429 | V9: 1988.434 | W9: 19266.221 | X9: 10.048 | Y9: 1988.434 | Z9: 19979.785 | AA9: 10.406857 | AB9: 1988.434 | AC9: 20693.349 | AD9: 10.765714 | AE9: 1988.434 | AF9: 21406.912 | AG9: 12.380571 | AH9: 1988.434 | AI9: 24617.949 | AJ9: 12.918857 | AK9: 1988.434 | AL9: 25688.295 | AM9: 6.28 | AN9: 1988.434 | AO9: 12487.366
A10: =+$C$4&B10 -> Véhicules neufsCamions détail | B10: Camions détail | C10: 502.34976 | D10: 2556.3336 | E10: 1284173.6 | F10: 35.164483 | G10: 2556.3336 | H10: 89892.151 | I10: 25.835131 | J10: 2556.3336 | K10: 66043.213 | L10: 45.929121 | M10: 2556.3336 | N10: 117410.16 | O10: 50.234976 | P10: 2556.3336 | Q10: 128417.36 | R10: 55.258474 | S10: 2556.3336 | T10: 141259.09 | U10: 38.752696 | V10: 2556.3336 | W10: 99064.82 | X10: 40.187981 | Y10: 2556.3336 | Z10: 102733.89 | AA10: 41.623266 | AB10: 2556.3336 | AC10: 106402.95 | AD10: 43.058551 | AE10: 2556.3336 | AF10: 110072.02 | AG10: 49.517333 | AH10: 2556.3336 | AI10: 126582.83 | AJ10: 51.670261 | AK10: 2556.3336 | AL10: 132086.43 | AM10: 25.117488 | AN10: 2556.3336 | AO10: 64208.679
A11: =+$C$4&B11 -> Véhicules neufsSprinter | B11: Sprinter | C11: 0 | D11: 0 | E11: 0 | G11: 0 | J11: 0 | M11: 0 | P11: 0 | S11: 0 | V11: 0 | Y11: 0 | AB11: 0 | AE11: 0 | AH11: 0 | AK11: 0 | AN11: 0
A12: =+$C$4&B12 -> Véhicules neufsMoto détail | B12: Moto détail | C12: 0 | D12: 0 | E12: 0 | G12: 0 | J12: 0 | M12: 0 | P12: 0 | S12: 0 | V12: 0 | Y12: 0 | AB12: 0 | AE12: 0 | AH12: 0 | AK12: 0 | AN12: 0
A13: =+$C$4&B13 -> Véhicules neufs[...] | B13: [...] | C13: 0 | D13: 0 | E13: 0 | G13: 0 | J13: 0 | M13: 0 | P13: 0 | S13: 0 | V13: 0 | Y13: 0 | AB13: 0 | AE13: 0 | AH13: 0 | AK13: 0 | AN13: 0
A14: =+$C$4&B14 -> Véhicules neufs[...] | B14: [...] | C14: 0 | D14: 0 | E14: 0 | G14: 0 | J14: 0 | M14: 0 | P14: 0 | S14: 0 | V14: 0 | Y14: 0 | AB14: 0 | AE14: 0 | AH14: 0 | AK14: 0 | AN14: 0
A15: =+$C$4&B15 -> Véhicules neufs[...] | B15: [...] | C15: 0 | D15: 0 | E15: 0 | G15: 0 | J15: 0 | M15: 0 | P15: 0 | S15: 0 | V15: 0 | Y15: 0 | AB15: 0 | AE15: 0 | AH15: 0 | AK15: 0 | AN15: 0
A16: =+$C$4&B16 -> Véhicules neufsTotal Neufs | B16: Total Neufs | C16: 627.94976 | D16: 2442.7446 | E16: 1533920.9 | F16: 43.956483 | G16: 2442.7446 | H16: 107374.46 | I16: 32.294559 | J16: 2442.7446 | K16: 78887.36 | L16: 57.412549 | M16: 2442.7446 | N16: 140244.2 | O16: 62.794976 | P16: 2442.7446 | Q16: 153392.09 | R16: 69.074474 | S16: 2442.7446 | T16: 168731.3 | U16: 48.441839 | V16: 2442.7446 | W16: 118331.04 | X16: 50.235981 | Y16: 2442.7446 | Z16: 122713.67 | AA16: 52.030123 | AB16: 2442.7446 | AC16: 127096.3 | AD16: 53.824265 | AE16: 2442.7446 | AF16: 131478.93 | AG16: 61.897905 | AH16: 2442.7446 | AI16: 151200.77 | AJ16: 64.589118 | AK16: 2442.7446 | AL16: 157774.72 | AM16: 31.397488 | AN16: 2442.7446 | AO16: 76696.045
A17: =+$C$4&B17 -> Véhicules neufs
A18: =+$C$4&B18 -> Véhicules neufsEx-Démos et courtoisies | B18: Ex-Démos et courtoisies | C18: 30 | D18: 2442.5492 | E18: 73276.476 | F18: 2.1 | G18: 2442.5492 | H18: 5129.3533 | I18: 1.5428571 | J18: 2442.5492 | K18: 3768.5045 | L18: 2.7428571 | M18: 2442.5492 | N18: 6699.5635 | O18: 3 | P18: 2442.5492 | Q18: 7327.6476 | R18: 3.3 | S18: 2442.5492 | T18: 8060.4124 | U18: 2.3142857 | V18: 2442.5492 | W18: 5652.7567 | X18: 2.4 | Y18: 2442.5492 | Z18: 5862.1181 | AA18: 2.4857143 | AB18: 2442.5492 | AC18: 6071.4794 | AD18: 2.5714286 | AE18: 2442.5492 | AF18: 6280.8408 | AG18: 2.9571429 | AH18: 2442.5492 | AI18: 7222.9669 | AJ18: 3.0857143 | AK18: 2442.5492 | AL18: 7537.009 | AM18: 1.5 | AN18: 2442.5492 | AO18: 3663.8238
A19: =+$C$4&B19 -> Véhicules neufs
A20: =+$C$4&B20 -> Véhicules neufsFlottes | B20: Flottes | C20: 24 | D20: 2442.5492 | E20: 58621.181 | F20: 1.68 | G20: 2442.5492 | H20: 4103.4827 | I20: 1.2342857 | J20: 2442.5492 | K20: 3014.8036 | L20: 2.1942857 | M20: 2442.5492 | N20: 5359.6508 | O20: 2.4 | P20: 2442.5492 | Q20: 5862.1181 | R20: 2.64 | S20: 2442.5492 | T20: 6448.3299 | U20: 1.8514286 | V20: 2442.5492 | W20: 4522.2054 | X20: 1.92 | Y20: 2442.5492 | Z20: 4689.6945 | AA20: 1.9885714 | AB20: 2442.5492 | AC20: 4857.1836 | AD20: 2.0571429 | AE20: 2442.5492 | AF20: 5024.6726 | AG20: 2.3657143 | AH20: 2442.5492 | AI20: 5778.3735 | AJ20: 2.4685714 | AK20: 2442.5492 | AL20: 6029.6072 | AM20: 1.2 | AN20: 2442.5492 | AO20: 2931.059
A21: =+$C$4&B21 -> Véhicules neufs
A22: =+$C$4&B22 -> Véhicules neufsRachat bail | B22: Rachat bail | E22: 96000 | H22: 4800 | K22: 4800 | N22: 11520 | Q22: 11520 | T22: 11520 | W22: 11520 | Z22: 9600 | AC22: 6720 | AF22: 6720 | AI22: 5760 | AL22: 5760 | AO22: 5760
A23: =+$C$4&B23 -> Véhicules neufs
A24: =+$C$4&B24 -> Véhicules neufsRev. Finances | B24: Rev. Finances | D24: 172 | E24: 113167.36 | G24: 172 | H24: 7921.7151 | J24: 172 | K24: 5820.0356 | M24: 172 | N24: 10346.73 | P24: 172 | Q24: 11316.736 | S24: 172 | T24: 12448.409 | V24: 172 | W24: 8730.0534 | Y24: 172 | Z24: 9053.3887 | AB24: 172 | AC24: 9376.724 | AE24: 172 | AF24: 9700.0593 | AH24: 172 | AI24: 11155.068 | AK24: 172 | AL24: 11640.071 | AN24: 172 | AO24: 5658.3679
A25: =+$C$4&B25 -> Véhicules neufsRev. Protections | B25: Rev. Protections | D25: 946 | E25: 622420.47 | G25: 946 | H25: 43569.433 | J25: 946 | K25: 32010.196 | M25: 946 | N25: 56907.015 | P25: 946 | Q25: 62242.047 | S25: 946 | T25: 68466.252 | V25: 946 | W25: 48015.294 | Y25: 946 | Z25: 49793.638 | AB25: 946 | AC25: 51571.982 | AE25: 946 | AF25: 53350.326 | AH25: 946 | AI25: 61352.875 | AK25: 946 | AL25: 64020.392 | AN25: 946 | AO25: 31121.024
A26: =+$C$4&B26 -> Véhicules neufsRev. Autres | B26: Rev. Autres | D26: 29 | E26: 19080.543 | G26: 29 | H26: 1335.638 | J26: 29 | K26: 981.28507 | M26: 29 | N26: 1744.5068 | P26: 29 | Q26: 1908.0543 | S26: 29 | T26: 2098.8597 | V26: 29 | W26: 1471.9276 | Y26: 29 | Z26: 1526.4434 | AB26: 29 | AC26: 1580.9593 | AE26: 29 | AF26: 1635.4751 | AH26: 29 | AI26: 1880.7964 | AK26: 29 | AL26: 1962.5701 | AN26: 29 | AO26: 954.02715
A27: =+$C$4&B27 -> Véhicules neufsTotal F&I | B27: Total F&I | C27: 657.94976 | D27: 1147 | E27: 754668.37 | F27: 46.056483 | G27: 1147 | H27: 52826.786 | I27: 33.837416 | J27: 1147 | K27: 38811.516 | L27: 60.155407 | M27: 1147 | N27: 68998.251 | O27: 65.794976 | P27: 1147 | Q27: 75466.837 | R27: 72.374474 | S27: 1147 | T27: 83013.521 | U27: 50.756124 | V27: 1147 | W27: 58217.275 | X27: 52.635981 | Y27: 1147 | Z27: 60373.47 | AA27: 54.515837 | AB27: 1147 | AC27: 62529.665 | AD27: 56.395694 | AE27: 1147 | AF27: 64685.861 | AG27: 64.855048 | AH27: 1147 | AI27: 74388.74 | AJ27: 67.674832 | AK27: 1147 | AL27: 77623.033 | AM27: 32.897488 | AN27: 1147 | AO27: 37733.419
A28: =+$C$4&B28 -> Véhicules neufs
A29: =+$C$4&B29 -> Véhicules neufs
A30: =+$C$4&B30 -> Véhicules neufsTotal Dépt. Neufs | B30: Total Dépt. Neufs | C30: 681.94976 | D30: 3690.1354 | E30: 2516486.9 | F30: 47.736483 | G30: 3649.9146 | H30: 174234.09 | I30: 35.071702 | J30: 3686.225 | K30: 129282.18 | L30: 62.349692 | M30: 3734.1269 | N30: 232821.66 | O30: 68.194976 | P30: 3718.2899 | Q30: 253568.69 | R30: 75.014474 | S30: 3702.9329 | T30: 277773.56 | U30: 52.607553 | V30: 3768.3425 | W30: 198243.28 | X30: 54.555981 | Y30: 3725.3286 | Z30: 203238.95 | AA30: 56.504409 | AB30: 3668.2913 | AC30: 207274.63 | AD30: 58.452837 | AE30: 3664.327 | AF30: 214190.31 | AG30: 67.220762 | AH30: 3635.0503 | AI30: 244350.85 | AJ30: 70.143404 | AK30: 3631.48 | AL30: 254724.37 | AM30: 34.097488 | AN30: 3718.2899 | AO30: 126784.35
A31: =+$C$4&B31 -> Véhicules neufs
A32: =+$C$4&B32 -> Véhicules neufs
A33: =+$C$4&B33 -> Véhicules neufsDEPENSES | B33: DEPENSES
A34: =+$C$4&B34 -> Véhicules neufsComm. vendeurs | B34: Comm. vendeurs | C34: 0.3141475 | D34: 767.37931 | E34: 504897.03 | F34: 0.32509824 | G34: 794.12907 | H34: 36574.792 | I34: 0.34960605 | J34: 853.99518 | K34: 28896.99 | L34: 0.31057373 | M34: 758.64954 | N34: 45636.872 | O34: 0.30232568 | P34: 738.50173 | Q34: 48589.703 | R34: 0.29885266 | S34: 730.01807 | T34: 52834.674 | U34: 0.32000541 | V34: 781.68863 | W34: 39675.485 | X34: 0.31560967 | Y34: 770.95101 | Z34: 40579.763 | AA34: 0.3169238 | AB34: 774.16109 | AC34: 42204.04 | AD34: 0.31292384 | AE34: 764.39023 | AF34: 43108.317 | AG34: 0.30309576 | AH34: 740.38284 | AI34: 48017.565 | AJ34: 0.30230148 | AK34: 738.44262 | AL34: 49973.981 | AM34: 0.35844822 | AN34: 875.59426 | AO34: 28804.852
A35: =+$C$4&B35 -> Véhicules neufsComm. F&I | B35: Comm. F&I | C35: 0.3 | D35: 344.1 | E35: 226400.51 | F35: 0.3 | G35: 344.1 | H35: 15848.036 | I35: 0.3 | J35: 344.1 | K35: 11643.455 | L35: 0.3 | M35: 344.1 | N35: 20699.475 | O35: 0.3 | P35: 344.1 | Q35: 22640.051 | R35: 0.3 | S35: 344.1 | T35: 24904.056 | U35: 0.3 | V35: 344.1 | W35: 17465.182 | X35: 0.3 | Y35: 344.1 | Z35: 18112.041 | AA35: 0.3 | AB35: 344.1 | AC35: 18758.9 | AD35: 0.3 | AE35: 344.1 | AF35: 19405.758 | AG35: 0.3 | AH35: 344.1 | AI35: 22316.622 | AJ35: 0.3 | AK35: 344.1 | AL35: 23286.91 | AM35: 0.3 | AN35: 344.1 | AO35: 11320.026
A36: =+$C$4&B36 -> Véhicules neufsFrais de livraison | B36: Frais de livraison | D36: 113.25898 | E36: 74518.717 | G36: 113.25898 | H36: 5216.3102 | J36: 113.25898 | K36: 3832.3911 | M36: 113.25898 | N36: 6813.1398 | P36: 113.25898 | Q36: 7451.8717 | S36: 113.25898 | T36: 8197.0588 | V36: 113.25898 | W36: 5748.5867 | Y36: 113.25898 | Z36: 5961.4973 | AB36: 113.25898 | AC36: 6174.4079 | AE36: 113.25898 | AF36: 6387.3186 | AH36: 113.25898 | AI36: 7345.4163 | AK36: 113.25898 | AL36: 7664.7823 | AN36: 113.25898 | AO36: 3725.9358
A37: =+$C$4&B37 -> Véhicules neufsService gratuit 1 | B37: Service gratuit 1 | D37: 5.1177856 | E37: 3367.2458 | G37: 5.1177856 | H37: 235.70721 | J37: 5.1177856 | K37: 173.17264 | M37: 5.1177856 | N37: 307.86248 | P37: 5.1177856 | Q37: 336.72458 | S37: 5.1177856 | T37: 370.39704 | V37: 5.1177856 | W37: 259.75896 | Y37: 5.1177856 | Z37: 269.37967 | AB37: 5.1177856 | AC37: 279.00037 | AE37: 5.1177856 | AF37: 288.62107 | AH37: 5.1177856 | AI37: 331.91423 | AK37: 5.1177856 | AL37: 346.34529 | AN37: 5.1177856 | AO37: 168.36229
A38: =+$C$4&B38 -> Véhicules neufsEntretien stock | B38: Entretien stock | D38: 105.01044 | E38: 69091.596 | G38: 105.01044 | H38: 4836.4117 | J38: 105.01044 | K38: 3553.2821 | M38: 105.01044 | N38: 6316.9459 | P38: 105.01044 | Q38: 6909.1596 | S38: 105.01044 | T38: 7600.0756 | V38: 105.01044 | W38: 5329.9231 | Y38: 105.01044 | Z38: 5527.3277 | AB38: 105.01044 | AC38: 5724.7322 | AE38: 105.01044 | AF38: 5922.1368 | AH38: 105.01044 | AI38: 6810.4573 | AK38: 105.01044 | AL38: 7106.5642 | AN38: 105.01044 | AO38: 3454.5798
A39: =+$C$4&B39 -> Véhicules neufsPublicité 1 | B39: Publicité 1 | D39: 300.75552 | E39: 197882.02 | G39: 300.75552 | H39: 13851.742 | J39: 300.75552 | K39: 10176.79 | M39: 300.75552 | N39: 18092.071 | P39: 300.75552 | Q39: 19788.202 | S39: 300.75552 | T39: 21767.023 | V39: 300.75552 | W39: 15265.185 | Y39: 300.75552 | Z39: 15830.562 | AB39: 300.75552 | AC39: 16395.939 | AE39: 300.75552 | AF39: 16961.316 | AH39: 300.75552 | AI39: 19505.514 | AK39: 300.75552 | AL39: 20353.58 | AN39: 300.75552 | AO39: 9894.1012
A40: =+$C$4&B40 -> Véhicules neufsIntérêt de gros | B40: Intérêt de gros | D40: 52.641607 | E40: 34635.533 | G40: 37.116022 | H40: 1709.4334 | J40: 45.756141 | K40: 1548.2696 | M40: 67.038107 | N40: 4032.7046 | P40: 72.303115 | Q40: 4757.1817 | S40: 52.849132 | T40: 3824.9281 | V40: 45.737234 | W40: 2321.4447 | Y40: 50.687592 | Z40: 2667.9911 | AB40: 53.963736 | AC40: 2941.8783 | AE40: 63.366313 | AF40: 3573.5872 | AH40: 69.534232 | AI40: 4509.6459 | AK40: 31.332422 | AL40: 2120.4164 | AN40: 19.091169 | AO40: 628.05151
A41: =+$C$4&B41 -> Véhicules neufs[...] | B41: [...] | D41: 0 | E41: 0 | G41: 0 | J41: 0 | M41: 0 | P41: 0 | S41: 0 | V41: 0 | Y41: 0 | AB41: 0 | AE41: 0 | AH41: 0 | AK41: 0 | AN41: 0
A42: =+$C$4&B42 -> Véhicules neufs[...] | B42: [...] | D42: 0 | E42: 0 | G42: 0 | J42: 0 | M42: 0 | P42: 0 | S42: 0 | V42: 0 | Y42: 0 | AB42: 0 | AE42: 0 | AH42: 0 | AK42: 0 | AN42: 0
A43: =+$C$4&B43 -> Véhicules neufs[...] | B43: [...] | D43: 0 | E43: 0 | G43: 0 | J43: 0 | M43: 0 | P43: 0 | S43: 0 | V43: 0 | Y43: 0 | AB43: 0 | AE43: 0 | AH43: 0 | AK43: 0 | AN43: 0
A44: =+$C$4&B44 -> Véhicules neufsTOTAL VARIABLES | B44: TOTAL VARIABLES | C44: % brut | D44: 0.44140609 | E44: 1110792.7 | F44: % brut | G44: 0.4492372 | H44: 78272.432 | I44: % brut | J44: 0.46274241 | K44: 59824.35 | L44: % brut | M44: 0.43767006 | N44: 101899.07 | O44: % brut | P44: 0.43567245 | Q44: 110472.89 | R44: % brut | S44: 0.43020009 | T44: 119498.21 | U44: % brut | V44: 0.43414116 | W44: 86065.566 | X44: % brut | Y44: 0.43765508 | Z44: 88948.561 | AA44: % brut | AB44: 0.44616602 | AC44: 92478.897 | AD44: % brut | AE44: 0.44655174 | AF44: 95647.055 | AG44: % brut | AH44: 0.44541336 | AI44: 108837.13 | AJ44: % brut | AK44: 0.43518639 | AL44: 110852.58 | AM44: % brut | AN44: 0.45743745 | AO44: 57995.908
A45: =+$C$4&B45 -> Véhicules neufsSalaires cadres | B45: Salaires cadres | E45: 205874.05 | H45: 16747.194 | K45: 16201.891 | N45: 17837.799 | Q45: 16747.194 | T45: 17292.497 | W45: 17292.497 | Z45: 17292.497 | AC45: 17292.497 | AF45: 17292.497 | AI45: 16747.194 | AL45: 17292.497 | AO45: 17837.799
A46: =+$C$4&B46 -> Véhicules neufsSalaires commis | B46: Salaires commis | E46: 121332.06 | H46: 9770.1083 | K46: 9315.5793 | N46: 10679.166 | Q46: 9770.1083 | T46: 10224.637 | W46: 10224.637 | Z46: 10224.637 | AC46: 10224.637 | AF46: 10224.637 | AI46: 9770.1083 | AL46: 10224.637 | AO46: 10679.166
A47: =+$C$4&B47 -> Véhicules neufsSalaires autres | B47: Salaires autres | E47: 97388.4 | H47: 7835.8483 | K47: 7462.7126 | N47: 8582.1195 | Q47: 7835.8483 | T47: 8208.9839 | W47: 8208.9839 | Z47: 8208.9839 | AC47: 8208.9839 | AF47: 8208.9839 | AI47: 7835.8483 | AL47: 8208.9839 | AO47: 8582.1195
A48: =+$C$4&B48 -> Véhicules neufsSalaires spécialistes | B48: Salaires spécialistes | E48: 0
A49: =+$C$4&B49 -> Véhicules neufs[...] | B49: [...] | E49: 0
A50: =+$C$4&B50 -> Véhicules neufs[...] | B50: [...] | E50: 0
A51: =+$C$4&B51 -> Véhicules neufs[...] | B51: [...] | E51: 0
A52: =+$C$4&B52 -> Véhicules neufsSalaires en absences | B52: Salaires en absences | E52: 139965.49 | H52: 10568.729 | K52: 9049.4864 | N52: 12495.424 | Q52: 12691.239 | T52: 13604.051 | W52: 11279.397 | Z52: 11454.455 | AC52: 11710.77 | AF52: 11885.828 | AI52: 12590.167 | AL52: 13098.691 | AO52: 9537.2531
A53: =+$C$4&B53 -> Véhicules neufsDéduction à la source | B53: Déduction à la source | E53: 139139.48 | H53: 10506.357 | K53: 8996.0805 | N53: 12421.682 | Q53: 12616.341 | T53: 13523.766 | W53: 11212.831 | Z53: 11386.856 | AC53: 11641.659 | AF53: 11815.684 | AI53: 12515.866 | AL53: 13021.389 | AO53: 9480.9686
A54: =+$C$4&B54 -> Véhicules neufsBénéfices marginaux | B54: Bénéfices marginaux | E54: 97433.538 | H54: 7357.1612 | K54: 6299.5776 | N54: 8698.3825 | Q54: 8834.6943 | T54: 9470.1256 | W54: 7851.8751 | Z54: 7973.7373 | AC54: 8152.1651 | AF54: 8274.0274 | AI54: 8764.3356 | AL54: 9118.332 | AO54: 6639.1244
A55: =+$C$4&B55 -> Véhicules neufsCsst | B55: Csst | E55: 46546.81 | H55: 3514.728 | K55: 3009.4898 | N55: 4155.468 | Q55: 4220.5881 | T55: 4524.152 | W55: 3751.067 | Z55: 3809.2842 | AC55: 3894.5243 | AF55: 3952.7414 | AI55: 4186.9757 | AL55: 4356.09 | AO55: 3171.7011
A56: =+$C$4&B56 -> Véhicules neufs[...] | B56: [...] | E56: 0
A57: =+$C$4&B57 -> Véhicules neufsTOTAL PERSONNEL | B57: TOTAL PERSONNEL | C57: % brut | D57: 0.33685048 | E57: 847679.83 | F57: % brut | G57: 0.38052328 | H57: 66300.126 | I57: % brut | J57: 0.46669088 | K57: 60334.817 | L57: % brut | M57: 0.32157679 | N57: 74870.042 | O57: % brut | P57: 0.28677047 | Q57: 72716.013 | R57: % brut | S57: 0.27665776 | T57: 76848.212 | U57: % brut | V57: 0.35220003 | W57: 69821.288 | X57: % brut | Y57: 0.34614649 | Z57: 70350.45 | AA57: % brut | AB57: 0.34314492 | AC57: 71125.236 | AD57: % brut | AE57: 0.33453614 | AF57: 71654.398 | AG57: % brut | AH57: 0.29633821 | AI57: 72410.495 | AJ57: % brut | AK57: 0.2956946 | AL57: 75320.62 | AM57: % brut | AN57: 0.52000215 | AO57: 65928.132
A58: =+$C$4&B58 -> Véhicules neufsPublicité 2 | B58: Publicité 2 | E58: 0 | H58: 0 | K58: 0 | N58: 0 | Q58: 0 | T58: 0 | W58: 0 | Z58: 0 | AC58: 0 | AF58: 0 | AI58: 0 | AL58: 0 | AO58: 0
A59: =+$C$4&B59 -> Véhicules neufsService gratuit 2 | B59: Service gratuit 2 | E59: 0 | H59: 0 | K59: 0 | N59: 0 | Q59: 0 | T59: 0 | W59: 0 | Z59: 0 | AC59: 0 | AF59: 0 | AI59: 0 | AL59: 0 | AO59: 0
A60: =+$C$4&B60 -> Véhicules neufsFrais véhicules de cie | B60: Frais véhicules de cie | E60: 95350 | H60: 7945.8333 | K60: 7945.8333 | N60: 7945.8333 | Q60: 7945.8333 | T60: 7945.8333 | W60: 7945.8333 | Z60: 7945.8333 | AC60: 7945.8333 | AF60: 7945.8333 | AI60: 7945.8333 | AL60: 7945.8333 | AO60: 7945.8333
A61: =+$C$4&B61 -> Véhicules neufsInformatique | B61: Informatique | E61: 75130.356 | H61: 6260.8561 | K61: 6260.8561 | N61: 6260.8561 | Q61: 6260.8561 | T61: 6260.8664 | W61: 6260.8664 | Z61: 6260.8664 | AC61: 6260.8664 | AF61: 6260.8664 | AI61: 6260.8664 | AL61: 6260.8664 | AO61: 6260.8664
A62: =+$C$4&B62 -> Véhicules neufsFrais de déplacement | B62: Frais de déplacement | E62: 12001.057 | H62: 1000.088 | K62: 1000.088 | N62: 1000.088 | Q62: 1000.088 | T62: 1000.088 | W62: 1000.088 | Z62: 1000.088 | AC62: 1000.088 | AF62: 1000.088 | AI62: 1000.088 | AL62: 1000.088 | AO62: 1000.088
A63: =+$C$4&B63 -> Véhicules neufsServices extérieurs | B63: Services extérieurs | E63: 81031.465 | H63: 6832.0763 | K63: 6989.7569 | N63: 6667.7278 | Q63: 6691.3008 | T63: 6579.7114 | W63: 6901.1637 | Z63: 6796.8453 | AC63: 6506.5765 | AF63: 6527.9741 | AI63: 6690.5328 | AL63: 7157.2662 | AO63: 6690.5328
A64: =+$C$4&B64 -> Véhicules neufsFournitures autres | B64: Fournitures autres | E64: 1487.4892 | H64: 104.43469 | K64: 88.052473 | N64: 129.80487 | Q64: 155.47525 | T64: 161.70939 | W64: 119.79022 | Z64: 117.13646 | AC64: 124.8309 | AF64: 124.76419 | AI64: 139.9863 | AL64: 141.17976 | AO64: 80.324675
A65: =+$C$4&B65 -> Véhicules neufsUniformes | B65: Uniformes | E65: 768.12245 | H65: 53.928882 | K65: 45.469293 | N65: 67.029756 | Q65: 80.285646 | T65: 83.504886 | W65: 61.858303 | Z65: 60.487931 | AC65: 64.461253 | AF65: 64.426805 | AI65: 72.287329 | AL65: 72.903619 | AO65: 41.478747
A66: =+$C$4&B66 -> Véhicules neufsPapeterie | B66: Papeterie | E66: 9161.4124 | H66: 763.45104 | K66: 763.45104 | N66: 763.45104 | Q66: 763.45104 | T66: 763.45104 | W66: 763.45104 | Z66: 763.45104 | AC66: 763.45104 | AF66: 763.45104 | AI66: 763.45104 | AL66: 763.45104 | AO66: 763.45104
A67: =+$C$4&B67 -> Véhicules neufsTéléphone | B67: Téléphone | E67: 3104.643 | H67: 258.72025 | K67: 258.72025 | N67: 258.72025 | Q67: 258.72025 | T67: 258.72025 | W67: 258.72025 | Z67: 258.72025 | AC67: 258.72025 | AF67: 258.72025 | AI67: 258.72025 | AL67: 258.72025 | AO67: 258.72025
A68: =+$C$4&B68 -> Véhicules neufsFrais postaux | B68: Frais postaux | E68: 1484.9315 | H68: 123.74429 | K68: 123.74429 | N68: 123.74429 | Q68: 123.74429 | T68: 123.74429 | W68: 123.74429 | Z68: 123.74429 | AC68: 123.74429 | AF68: 123.74429 | AI68: 123.74429 | AL68: 123.74429 | AO68: 123.74429
A69: =+$C$4&B69 -> Véhicules neufsDivers | B69: Divers | E69: 5642.1884 | H69: 470.18236 | K69: 470.18236 | N69: 470.18236 | Q69: 470.18236 | T69: 470.18236 | W69: 470.18236 | Z69: 470.18236 | AC69: 470.18236 | AF69: 470.18236 | AI69: 470.18236 | AL69: 470.18236 | AO69: 470.18236
... A71: =+$C$4&B71 -> Véhicules neufsFrais bancaires | B71: Frais bancaires | E71: 17027.814 | H71: 1024.759 | K71: 872.07989 | N71: 1022.4391 | Q71: 2044.9976 | T71: 1867.0949 | W71: 1204.8888 | Z71: 1131.0254 | AC71: 1255.436 | AF71: 929.83857 | AI71: 1818.3448 | AL71: 2685.2134 | AO71: 1171.6969
A72: =+$C$4&B72 -> Véhicules neufs[...] | B72: [...] | E72: 0
A73: =+$C$4&B73 -> Véhicules neufs[...] | B73: [...] | E73: 0
A74: =+$C$4&B74 -> Véhicules neufs[...] | B74: [...] | E74: 0
A75: =+$C$4&B75 -> Véhicules neufsTOTAL SEMI-FIXES | B75: TOTAL SEMI-FIXES | C75: % brut | D75: 0.12300575 | E75: 309542.36 | F75: % brut | G75: 0.14607254 | H75: 25450.815 | I75: % brut | J75: 0.19670904 | K75: 25430.974 | L75: % brut | M75: 0.10876401 | N75: 25322.617 | O75: % brut | P75: 0.10414407 | Q75: 26407.675 | R75: % brut | S75: 0.094060955 | T75: 26127.647 | U75: % brut | V75: 0.12975637 | W75: 25723.327 | X75: % brut | Y75: 0.1256704 | Z75: 25541.121 | AA75: % brut | AB75: 0.12247968 | AC75: 25386.931 | AD75: % brut | AE75: 0.11710441 | AF75: 25082.63 | AG75: % brut | AH75: 0.10704598 | AI75: 26156.777 | AJ75: % brut | AK75: 0.10792917 | AL75: 27492.189 | AM75: % brut | AN75: 0.20049525 | AO75: 25419.659
A76: =+$C$4&B76 -> Véhicules neufs
A77: =+$C$4&B77 -> Véhicules neufsTOTAL DES DÉPENSES | B77: TOTAL DES DÉPENSES | C77: % brut | D77: 0.90126232 | E77: 2268014.9 | F77: % brut | G77: 0.97583302 | H77: 170023.37 | I77: % brut | J77: 1.1261423 | K77: 145590.14 | L77: % brut | M77: 0.86801085 | N77: 202091.73 | O77: % brut | P77: 0.82658699 | Q77: 209596.58 | R77: % brut | S77: 0.80091881 | T77: 222474.07 | U77: % brut | V77: 0.91609755 | W77: 181610.18 | X77: % brut | Y77: 0.90947197 | Z77: 184840.13 | AA77: % brut | AB77: 0.91179062 | AC77: 188991.06 | AD77: % brut | AE77: 0.89819229 | AF77: 192384.08 | AG77: % brut | AH77: 0.84879755 | AI77: 207404.41 | AJ77: % brut | AK77: 0.83881015 | AL77: 213665.39 | AM77: % brut | AN77: 1.1779348 | AO77: 149343.7
A78: =+$C$4&B78 -> Véhicules neufsProgramme neuf 1 | B78: Programme neuf 1 | E78: 54624.176 | H78: 0 | K78: 0 | N78: 10069.276 | Q78: 0 | T78: 0 | W78: 16584.69 | Z78: 0 | AC78: 0 | AF78: 15729.13 | AI78: 0 | AL78: 0 | AO78: 12241.08
A79: =+$C$4&B79 -> Véhicules neufsProgramme neuf 2 | B79: Programme neuf 2 | E79: 0
A80: =+$C$4&B80 -> Véhicules neufsProgramme neuf 3 | B80: Programme neuf 3 | E80: 0
A81: =+$C$4&B81 -> Véhicules neufsHoldbacks | B81: Holdbacks | E81: 777263.5 | H81: 54408.445 | K81: 39973.551 | N81: 71064.091 | Q81: 77726.35 | T81: 85498.985 | W81: 59960.327 | Z81: 62181.08 | AC81: 64401.833 | AF81: 66622.586 | AI81: 76615.973 | AL81: 79947.103 | AO81: 38863.175
A82: =+$C$4&B82 -> Véhicules neufs[...] | B82: [...] | E82: 0
A83: =+$C$4&B83 -> Véhicules neufs[...] | B83: [...] | E83: 0
A84: =+$C$4&B84 -> Véhicules neufs[...] | B84: [...] | E84: 0
A85: =+$C$4&B85 -> Véhicules neufsFrais administration | B85: Frais administration | E85: 244888.16 | H85: 17142.171 | K85: 12594.248 | N85: 22389.775 | Q85: 24488.816 | T85: 26937.697 | W85: 18891.372 | Z85: 19591.053 | AC85: 20290.733 | AF85: 20990.414 | AI85: 24138.976 | AL85: 25188.496 | AO85: 12244.408
A86: =+$C$4&B86 -> Véhicules neufsAUTRES REVENUS | B86: AUTRES REVENUS | E86: 1076775.8 | H86: 71550.616 | K86: 52567.8 | N86: 103523.14 | Q86: 102215.17 | T86: 112436.68 | W86: 95436.389 | Z86: 81772.133 | AC86: 84692.566 | AF86: 103342.13 | AI86: 100754.95 | AL86: 105135.6 | AO86: 63348.663
A87: =+$C$4&B87 -> Véhicules neufs
A88: =+$C$4&B88 -> Véhicules neufsPROFIT DÉPARTEMENTAL | B88: PROFIT DÉPARTEMENTAL | E88: 1325247.9 | H88: 75761.328 | K88: 36259.843 | N88: 134253.07 | Q88: 146187.28 | T88: 167736.17 | W88: 112069.49 | Z88: 100170.95 | AC88: 102976.13 | AF88: 125148.35 | AI88: 137701.4 | AL88: 146194.58 | AO88: 40789.31
B92: Budget 2023 | C92: Véhicules usagés
B94: Mois | C94: 2021 | F94: Janvier | I94: Février | L94: Mars | O94: Avril | R94: Mai | U94: Juin | X94: Juillet | AA94: Août | AD94: Septembre | AG94: Octobre | AJ94: Novembre | AM94: Décembre
C95: UNITE | D95: $P/UNITE | E95: $PROFITS | F95: UNITE | G95: $P/UNITE | H95: $PROFITS | I95: UNITE | J95: $P/UNITE | K95: $PROFITS | L95: UNITE | M95: $P/UNITE | N95: $PROFITS | O95: UNITE | P95: $P/UNITE | Q95: $PROFITS | R95: UNITE | S95: $P/UNITE | T95: $PROFITS | U95: UNITE | V95: $P/UNITE | W95: $PROFITS | X95: UNITE | Y95: $P/UNITE | Z95: $PROFITS | AA95: UNITE | AB95: $P/UNITE | AC95: $PROFITS | AD95: UNITE | AE95: $P/UNITE | AF95: $PROFITS | AG95: UNITE | AH95: $P/UNITE | AI95: $PROFITS | AJ95: UNITE | AK95: $P/UNITE | AL95: $PROFITS | AM95: UNITE | AN95: $P/UNITE | AO95: $PROFITS
A96: =+$C$92&B96 -> Véhicules usagésVentes nettes | B96: Ventes nettes | E96: 19554921 | H96: 1378872.6 | K96: 1378872.6 | N96: 1587792.7 | Q96: 2172769 | T96: 2089200.9 | W96: 1671360.8 | Z96: 1504224.7 | AC96: 1671360.8 | AF96: 1587792.7 | AI96: 1713144.8 | AL96: 1629576.7 | AO96: 1169952.5
A97: =+$C$92&B97 -> Véhicules usagésCertifié | B97: Certifié | C97: 468 | D97: 1858 | E97: 869544 | F97: 33 | G97: 1858 | H97: 61314 | I97: 33 | J97: 1858 | K97: 61314 | L97: 38 | M97: 1858 | N97: 70604 | O97: 52 | P97: 1858 | Q97: 96616 | R97: 50 | S97: 1858 | T97: 92900 | U97: 40 | V97: 1858 | W97: 74320 | X97: 36 | Y97: 1858 | Z97: 66888 | AA97: 40 | AB97: 1858 | AC97: 74320 | AD97: 38 | AE97: 1858 | AF97: 70604 | AG97: 41 | AH97: 1858 | AI97: 76178 | AJ97: 39 | AK97: 1858 | AL97: 72462 | AM97: 28 | AN97: 1858 | AO97: 52024
A98: =+$C$92&B98 -> Véhicules usagésNon Certifié | B98: Non Certifié | C98: 0 | D98: 0 | E98: 0 | F98: 0 | G98: 0 | H98: 0 | I98: 0 | J98: 0 | K98: 0 | L98: 0 | M98: 0 | N98: 0 | O98: 0 | P98: 0 | Q98: 0 | R98: 0 | S98: 0 | T98: 0 | U98: 0 | V98: 0 | W98: 0 | X98: 0 | Y98: 0 | Z98: 0 | AA98: 0 | AB98: 0 | AC98: 0 | AD98: 0 | AE98: 0 | AF98: 0 | AG98: 0 | AH98: 0 | AI98: 0 | AJ98: 0 | AK98: 0 | AL98: 0 | AM98: 0 | AN98: 0 | AO98: 0
A99: =+$C$92&B99 -> Véhicules usagésTotal Usagés | B99: Total Usagés | C99: 468 | D99: 1858 | E99: 869544 | F99: 33 | G99: 1858 | H99: 61314 | I99: 33 | J99: 1858 | K99: 61314 | L99: 38 | M99: 1858 | N99: 70604 | O99: 52 | P99: 1858 | Q99: 96616 | R99: 50 | S99: 1858 | T99: 92900 | U99: 40 | V99: 1858 | W99: 74320 | X99: 36 | Y99: 1858 | Z99: 66888 | AA99: 40 | AB99: 1858 | AC99: 74320 | AD99: 38 | AE99: 1858 | AF99: 70604 | AG99: 41 | AH99: 1858 | AI99: 76178 | AJ99: 39 | AK99: 1858 | AL99: 72462 | AM99: 28 | AN99: 1858 | AO99: 52024
A100: =+$C$92&B100 -> Véhicules usagés
A101: =+$C$92&B101 -> Véhicules usagés
A102: =+$C$92&B102 -> Véhicules usagésVentes au Gros | B102: Ventes au Gros | C102: 396 | D102: 399 | E102: 158004 | F102: 27.923077 | G102: 399 | H102: 11141.308 | I102: 27.923077 | J102: 399 | K102: 11141.308 | L102: 32.153846 | M102: 399 | N102: 12829.385 | O102: 44 | P102: 399 | Q102: 17556 | R102: 42.307692 | S102: 399 | T102: 16880.769 | U102: 33.846154 | V102: 399 | W102: 13504.615 | X102: 30.461538 | Y102: 399 | Z102: 12154.154 | AA102: 33.846154 | AB102: 399 | AC102: 13504.615 | AD102: 32.153846 | AE102: 399 | AF102: 12829.385 | AG102: 34.692308 | AH102: 399 | AI102: 13842.231 | AJ102: 33 | AK102: 399 | AL102: 13167 | AM102: 23.692308 | AN102: 399 | AO102: 9453.2308
A103: =+$C$92&B103 -> Véhicules usagés
A104: =+$C$92&B104 -> Véhicules usagésRev. Finances | B104: Rev. Finances | D104: 500 | E104: 234000 | G104: 500 | H104: 16500 | J104: 500 | K104: 16500 | M104: 500 | N104: 19000 | P104: 500 | Q104: 26000 | S104: 500 | T104: 25000 | V104: 500 | W104: 20000 | Y104: 500 | Z104: 18000 | AB104: 500 | AC104: 20000 | AE104: 500 | AF104: 19000 | AH104: 500 | AI104: 20500 | AK104: 500 | AL104: 19500 | AN104: 500 | AO104: 14000
A105: =+$C$92&B105 -> Véhicules usagésRev. Protections | B105: Rev. Protections | D105: 1250 | E105: 585000 | G105: 1250 | H105: 41250 | J105: 1250 | K105: 41250 | M105: 1250 | N105: 47500 | P105: 1250 | Q105: 65000 | S105: 1250 | T105: 62500 | V105: 1250 | W105: 50000 | Y105: 1250 | Z105: 45000 | AB105: 1250 | AC105: 50000 | AE105: 1250 | AF105: 47500 | AH105: 1250 | AI105: 51250 | AK105: 1250 | AL105: 48750 | AN105: 1250 | AO105: 35000
A106: =+$C$92&B106 -> Véhicules usagésRev. Autres | B106: Rev. Autres | D106: 350 | E106: 163800 | G106: 350 | H106: 11550 | J106: 350 | K106: 11550 | M106: 350 | N106: 13300 | P106: 350 | Q106: 18200 | S106: 350 | T106: 17500 | V106: 350 | W106: 14000 | Y106: 350 | Z106: 12600 | AB106: 350 | AC106: 14000 | AE106: 350 | AF106: 13300 | AH106: 350 | AI106: 14350 | AK106: 350 | AL106: 13650 | AN106: 350 | AO106: 9800
...

Sheet Capex
A1: PARK AVENUE VOLKSWAGEN | B1: PARK AVENUE VOLKSWAGEN
A2: Forecast Immobilisation 2022 | B2: Forecast Immobilisation 2023 | H2: 1 | I2: 2 | J2: 3 | K2: 4 | L2: 5 | M2: 6 | N2: 7 | O2: 8 | P2: 9 | Q2: 10 | R2: 11 | S2: 12
H3: =+IF(VLOOKUP(H2,Parametres!$L$3:$N$14,3,0)="X","REEL","FORECAST") -> REEL | I3: =+IF(VLOOKUP(I2,Parametres!$L$3:$N$14,3,0)="X","REEL","FORECAST") -> REEL | J3: =+IF(VLOOKUP(J2,Parametres!$L$3:$N$14,3,0)="X","REEL","FORECAST") -> REEL | K3: =+IF(VLOOKUP(K2,Parametres!$L$3:$N$14,3,0)="X","REEL","FORECAST") -> REEL | L3: =+IF(VLOOKUP(L2,Parametres!$L$3:$N$14,3,0)="X","REEL","FORECAST") -> REEL | M3: =+IF(VLOOKUP(M2,Parametres!$L$3:$N$14,3,0)="X","REEL","FORECAST") -> REEL | N3: =+IF(VLOOKUP(N2,Parametres!$L$3:$N$14,3,0)="X","REEL","FORECAST") -> REEL | O3: =+IF(VLOOKUP(O2,Parametres!$L$3:$N$14,3,0)="X","REEL","FORECAST") -> REEL | ... S3: =+IF(VLOOKUP(S2,Parametres!$L$3:$N$14,3,0)="X","REEL","FORECAST") -> FORECAST
A4: Concession | B4: Budgété / Non budgété | C4: Projet | D4: Catégorie Immo | E4: Total forecast | F4: Budget Annuel | G4: Écart vs budget | H4: January | I4: February | J4: March | K4: April | L4: May | M4: June | N4: July | O4: August | P4: September | Q4: October | R4: November | S4: December | T4: Raison / Description
C5: Total | E5: =+SUM(E6:E20) -> 178764.31 | F5: =+SUM(F6:F20) -> 10000 | G5: =+SUM(G6:G20) -> 168764.31 | H5: =+SUM(H6:H20) -> 759.98 | I5: =+SUM(I6:I20) -> 0 | J5: =+SUM(J6:J20) -> 30333.84 | K5: =+SUM(K6:K20) -> 4403.25 | L5: =+SUM(L6:L20) -> 2714.93 | ... S5: =+SUM(S6:S20) -> 0 | X5: Terrain
A6: =+Parametres!$B$1 -> Volks | B6: oui | C6: Outils Spécialisés Volks | D6: Mobilier | E6: =+SUM(H6:S6) -> 48837.92 | F6: 10000 | G6: =+E6-F6 -> 38837.92 | J6: 19223.83 | P6: 3049.1 | R6: 26564.99 | X6: Bâtisse
A7: =+Parametres!$B$1 -> Volks | B7: non | C7: Reparation immeuble | D7: Améliorations Locatives | E7: =+SUM(H7:S7) -> 10527.65 | G7: =+E7-F7 -> 10527.65 | J7: 8802.13 | K7: 1725.52 | X7: Améliorations Locatives
A8: =+Parametres!$B$1 -> Volks | B8: non | C8: Equipement informatique | D8: Équipements Informatique | E8: =+SUM(H8:S8) -> 12960.52 | G8: =+E8-F8 -> 12960.52 | H8: 759.98 | J8: 2307.88 | K8: 2677.73 | L8: 2714.93 | O8: 4500 | X8: Mobilier
A9: =+Parametres!$B$1 -> Volks | B9: non | C9: Machine a pneus et balanceur | D9: Équipements Service | E9: =+SUM(H9:S9) -> 106438.22 | G9: =+E9-F9 -> 106438.22 | Q9: 106438.22 | X9: Équipements Informatique
A10: =+Parametres!$B$1 -> Volks | B10: non | E10: =+SUM(H10:S10) -> 0 | G10: =+E10-F10 -> 0 | X10: Équipements Téléphonique
A11: =+Parametres!$B$1 -> Volks | B11: non | E11: =+SUM(H11:S11) -> 0 | G11: =+E11-F11 -> 0 | X11: Enseigne
A12: =+Parametres!$B$1 -> Volks | B12: non | E12: =+SUM(H12:S12) -> 0 | G12: =+E12-F12 -> 0
A13: =+Parametres!$B$1 -> Volks | B13: non | E13: =+SUM(H13:S13) -> 0 | G13: =+E13-F13 -> 0
A14: =+Parametres!$B$1 -> Volks | B14: non | E14: =+SUM(H14:S14) -> 0 | G14: =+E14-F14 -> 0
A15: =+Parametres!$B$1 -> Volks | B15: non | E15: =+SUM(H15:S15) -> 0 | G15: =+E15-F15 -> 0
A16: =+Parametres!$B$1 -> Volks | B16: non | E16: =+SUM(H16:S16) -> 0 | G16: =+E16-F16 -> 0
A17: =+Parametres!$B$1 -> Volks | B17: non | E17: =+SUM(H17:S17) -> 0 | G17: =+E17-F17 -> 0 | X17: non
A18: =+Parametres!$B$1 -> Volks | B18: non | E18: =+SUM(H18:S18) -> 0 | G18: =+E18-F18 -> 0
A19: =+Parametres!$B$1 -> Volks | B19: non | E19: =+SUM(H19:S19) -> 0 | G19: =+E19-F19 -> 0
A20: =+Parametres!$B$1 -> Volks | B20: non | E20: =+SUM(H20:S20) -> 0 | G20: =+E20-F20 -> 0

Sheet Inventaire_Used
A1: #Contrôle | B1: Année | C1: Marque | D1: Modèle | E1: 1416 | F1: 2103 | G1: NIV | H1: Jours en stock | M1: 45169 | N1: $ Inventaire | O1: $ Financé
A2: 5291P | B2: 2020 | C2: VOLKSWAGEN | D2: E-GOLF | E2: 32409.56 | F2: -22494.36 | G2: WVWPR7AU2LW903993 | H2: 392 | M2: CTRL | N2: =+SUM(E:E) -> 2199909.3 | O2: =+SUM(F:F) -> -296870.95
A3: 230251A | B3: 2020 | C3: VOLKSWAGEN | D3: E-GOLF | E3: 24845.21 | G3: WVWPR7AU0LW907198 | H3: 275 | M3: Unités | N3: =COUNT(E:E) -> 93 | O3: =-O2/N2 -> 0.1349469
A4: 230425A | B4: 2021 | C4: VOLKSWAGEN | D4: ATLAS CROSS SPO | E4: 37735.15 | G4: 1V2LC2CAXMC211536 | H4: 157
A5: 230365A | B5: 2018 | C5: VOLKSWAGEN | D5: BEETLE CONVERTI | E5: 29929.55 | G5: 3VW5DAAT2JM518129 | H5: 156 | M5: Moyenne | N5: =+N2/N3 -> 23654.939
A6: 5449PA | B6: 2018 | C6: VOLKSWAGEN | D6: GOLF | E6: 19715.63 | G6: 3VWB17AU0JM271989 | H6: 111
A7: 230544A | B7: 2019 | C7: VOLKSWAGEN | D7: JETTA | E7: 22879.9 | F7: -12635 | G7: 3VWG57BUXKM094345 | H7: 100 | M7: Plus de 90 Jours | N7: =SUM(E2:E10) -> 241858.49 | O7: =+N7/N2 -> 0.10994021
A8: 5485P | B8: 2018 | C8: VOLKSWAGEN | D8: ATLAS | E8: 31306.12 | G8: 1V2NR2CA5JC509107 | H8: 100 | N8: =COUNT(H2:H10) -> 9 | O8: =+N8/(N3) -> 0.096774194
A9: 5487P | B9: 2018 | C9: VOLKSWAGEN | D9: GOLF GTI | E9: 25356.95 | F9: -21600 | G9: 3VW547AU8JM271761 | H9: 97
A10: 230554A | B10: 2014 | C10: SUBARU | D10: WRX | E10: 17680.42 | G10: JF1GR8H60EL238082 | H10: 90
A11: 5496P | B11: 2019 | C11: VOLKSWAGEN | D11: GOLF | E11: 19201.82 | F11: -11233 | G11: 3VWG57AU0KM026959 | H11: 85
A12: 5500P | B12: 2019 | C12: VOLKSWAGEN | D12: JETTA | E12: 20375.85 | F12: -10707 | G12: 3VWE57BU6KM024333 | H12: 79
A13: 240008A | B13: 2020 | C13: MAZDA | D13: CX-5 | E13: 25169.95 | G13: JM3KFBCM9L0736240 | H13: 77
A14: 230567A | B14: 2021 | C14: VOLKSWAGEN | D14: TIGUAN | E14: 28635.15 | F14: -31332.8 | G14: 3VV2B7AX6MM155874 | H14: 73
A15: 5503P | B15: 2022 | C15: VOLKSWAGEN | D15: JETTA | E15: 26374.85 | G15: 3VWGM7BU3NM007957 | H15: 70
A16: 5505P | B16: 2023 | C16: VOLKSWAGEN | D16: JETTA GLI | E16: 34475.25 | F16: -32366.59 | G16: 3VW2T7BU0PM002098 | H16: 69
A17: 240013A | B17: 2022 | C17: VOLKSWAGEN | D17: TIGUAN | E17: 38815.25 | G17: 3VV4B7AX3NM051496 | H17: 63
A18: 230392A | B18: 2020 | C18: VOLKSWAGEN | D18: TIGUAN | E18: 31315.25 | F18: -24944.54 | G18: 3VV4B7AX2LM114164 | H18: 63
A19: 230599A | B19: 2019 | C19: VOLKSWAGEN | D19: JETTA | E19: 21280.25 | F19: -10962 | G19: 3VWE57BU6KM254342 | H19: 63
A20: 230606A | B20: 2018 | C20: CHEVROLET | D20: VOLT | E20: 17550 | G20: 1G1RA6S50JU104989 | H20: 62
A21: 240015A | B21: 2019 | C21: VOLKSWAGEN | D21: GOLF GTI | E21: 27280.25 | F21: -17480.23 | G21: 3VW6T7AU5KM024755 | H21: 59
A22: 5511P | B22: 2022 | C22: VOLKSWAGEN | D22: ATLAS CROSS SPO | E22: 44105.05 | F22: -38250 | G22: 1V2BE2CA6NC212111 | H22: 57
A23: 230619A | B23: 2020 | C23: NISSAN | D23: QASHQAI | E23: 26890.95 | G23: JN1BJ1CWXLW362448 | H23: 56
A24: 230622A | B24: 2020 | C24: VOLKSWAGEN | D24: JETTA | E24: 24417.5 | G24: 3VWEB7BU2LM004638 | H24: 51
A25: 240019A | B25: 2020 | C25: VOLKSWAGEN | D25: ATLAS CROSS SPO | E25: 36415.13 | F25: -26892 | G25: 1V2TE2CA8LC219420 | H25: 51
A26: 230628A | B26: 2019 | C26: VOLKSWAGEN | D26: JETTA | E26: 18251.25 | F26: -12123.43 | G26: 3VWC57BU8KM150071 | H26: 48
A27: 230596A | B27: 2020 | C27: VOLKSWAGEN | D27: TIGUAN | E27: 27935.05 | G27: 3VV2B7AX4LM005048 | H27: 45
A28: 5509PA | B28: 2017 | C28: AUDI | D28: A3 E-TRON | E28: 20050 | G28: WAUSPBFF5HA099610 | H28: 43
A29: 230626A | B29: 2018 | C29: VOLKSWAGEN | D29: TIGUAN | E29: 20497.05 | G29: 3VV4B7AX2JM130250 | H29: 41
A30: 5518P | B30: 2020 | C30: VOLKSWAGEN | D30: TIGUAN | E30: 28075.78 | F30: -23850 | G30: 3VV4B7AX0LM106225 | H30: 38
A31: 230593A | B31: 2019 | C31: VOLKSWAGEN | D31: TIGUAN | E31: 26815.25 | G31: 3VV4B7AX3KM183332 | H31: 38
A32: 5519P | B32: 2021 | C32: VOLKSWAGEN | D32: TIGUAN | E32: 28447.25 | G32: 3VV2B7AX4MM068281 | H32: 37
A33: 240044A | B33: 2019 | C33: VOLKSWAGEN | D33: ATLAS | E33: 29352 | G33: 1V2MR2CA6KC587280 | H33: 35
A34: 240041A | B34: 2018 | C34: VOLKSWAGEN | D34: GOLF | E34: 18787.5 | G34: 3VWG17AU2JM291103 | H34: 35
A35: 230625B | B35: 2015 | C35: TOYOTA | D35: RAV4 | E35: 14735.77 | G35: 2T3DFREV2FW373974 | H35: 35
A36: 240056A | B36: 2020 | C36: VOLKSWAGEN | D36: JETTA | E36: 18043.82 | G36: 3VWN57BU2LM040420 | H36: 34
A37: 240036A | B37: 2021 | C37: VOLKSWAGEN | D37: ATLAS | E37: 40209.65 | G37: 1V2FR2CA8MC595926 | H37: 31
A38: 240079A | B38: 2020 | C38: VOLKSWAGEN | D38: TIGUAN | E38: 30620.3 | G38: 3VV4B7AX5LM110786 | H38: 31
A39: 230564B | B39: 2020 | C39: JEEP | D39: COMPASS | E39: 27550 | G39: 3C4NJDDBXLT155667 | H39: 31
A40: 230649A | B40: 2020 | C40: NISSAN | D40: ROGUE | E40: 23550 | G40: 5N1AT2MT7LC775762 | H40: 30
A41: 240086A | B41: 2022 | C41: VOLKSWAGEN | D41: TIGUAN | E41: 36524.6 | G41: 3VV4B7AX9NM096457 | H41: 29
A42: 5522P | B42: 2020 | C42: VOLKSWAGEN | D42: TIGUAN | E42: 24306.21 | G42: 3VV2B7AX7LM099068 | H42: 29
... A94: 5488P | B94: 2010 | C94: VOLKSWAGEN | D94: ROUTAN | E94: 12009.67 | G94: 2V4RW3DX0AR228009 | H94: 94

Sheet Inventaire_Neuf
A1: #Contrôle | B1: Année | C1: Marque | D1: Modèle | E1: 1402 | F1: 2101 | G1: NIV | H1: Jours en stock | K1: 45230 | L1: $ Inventaire | M1: $ Financé
A2: 240187 | B2: 2024 | C2: VOLKSWAGEN | D2: ATLAS | E2: 56440.18 | F2: -57628.2 | G2: 1V2BR2CA6RC502911 | H2: 111 | K2: CTRL | L2: =+SUM(E2:E9974) -> 3304520.1 | M2: =+SUM(F2:F9974) -> -2708634.5
A3: 230650 | B3: 2023 | C3: VOLKSWAGEN | D3: JETTA SEDAN | E3: 34174.44 | F3: -32404.99 | G3: 3VW2T7BU7PM053775 | H3: 111 | K3: Unités | L3: =COUNT(E:E) -> 74 | M3: =-M2/L2 -> 0.8196756
A4: 240060 | B4: 2023 | C4: VOLKSWAGEN | D4: JETTA SEDAN | E4: 31533.26 | F4: -32628.75 | G4: 3VWGM7BU3PM060824 | H4: 85
A5: 240150 | B5: 2023 | C5: VOLKSWAGEN | D5: TAOS | E5: 38553.25 | F5: -39936.75 | G5: 3VV4X7B27PM374246 | H5: 80
A6: 240083 | B6: 2024 | C6: VOLKSWAGEN | D6: ATLAS | E6: 50422.03 | F6: -51427.95 | G6: 1V2LR2CA2RC511786 | H6: 77 | K6: Plus de 90 jrs | L6: =SUM(E2:E3) -> 90614.62 | M6: =SUM(F2:F3) -> -90033.19
A7: 240191 | B7: 2024 | C7: VOLKSWAGEN | D7: ATLAS CROSS SPT | E7: 55153.85 | F7: -57051.75 | G7: 1V2BE2CA7RC206484 | H7: 73 | L7: 2
A8: 230643 | B8: 2024 | C8: VOLKSWAGEN | D8: ATLAS | E8: 58887.12 | F8: -60546.15 | G8: 1V2FR2CA6RC509911 | H8: 73
A9: 240182 | B9: 2024 | C9: VOLKSWAGEN | D9: ATLAS CROSS SPT | E9: 49045.79 | F9: -51136.05 | G9: 1V2LE2CA3RC208611 | H9: 66 | K9: Plus de 180 jrs | L9: 0 | M9: 0
A10: 240197 | B10: 2024 | C10: VOLKSWAGEN | D10: ATLAS CROSS SPT | E10: 57630.1 | G10: 1V2BE2CA1RC206996 | H10: 62 | L10: 0
A11: 240204 | B11: 2024 | C11: VOLKSWAGEN | D11: ATLAS CROSS SPT | E11: 56202.06 | F11: -57051.75 | G11: 1V2BE2CA5RC210341 | H11: 59
A12: 240026 | B12: 2024 | C12: VOLKSWAGEN | D12: ATLAS | E12: 58051.06 | G12: 1V2BR2CA4RC506228 | H12: 59
A13: 240125 | B13: 2024 | C13: VOLKSWAGEN | D13: ATLAS | E13: 48902.32 | G13: 1V2LR2CA8RC516197 | H13: 59
A14: 240035 | B14: 2024 | C14: VOLKSWAGEN | D14: GOLF GTI | E14: 37397 | F14: -39440.1 | G14: WVWGA7CD7RW121198 | H14: 55
A15: 240102 | B15: 2024 | C15: VOLKSWAGEN | D15: ATLAS | E15: 55983.97 | F15: -58869.3 | G15: 1V2BR2CA1RC517137 | H15: 55
A16: 240168 | B16: 2024 | C16: VOLKSWAGEN | D16: ATLAS CROSS SPT | E16: 56815.09 | F16: -58834.65 | G16: 1V2FE2CAXRC211373 | H16: 51
A17: 240172 | B17: 2024 | C17: VOLKSWAGEN | D17: ATLAS CROSS SPT | E17: 56057.95 | F17: -58834.65 | G17: 1V2FE2CAXRC210840 | H17: 51
A18: 240210 | B18: 2024 | C18: VOLKSWAGEN | D18: ATLAS CROSS SPT | E18: 55948 | F18: -58834.65 | G18: 1V2FE2CA7RC210827 | H18: 49
A19: 230574 | B19: 2024 | C19: VOLKSWAGEN | D19: ATLAS | E19: 48889 | F19: -51427.95 | G19: 1V2LR2CAXRC520316 | H19: 49
A20: 240050 | B20: 2023 | C20: VOLKSWAGEN | D20: TAOS | E20: 32613.32 | F20: -34034.7 | G20: 3VVEX7B23PM379190 | H20: 49
A21: 240045 | B21: 2023 | C21: VOLKSWAGEN | D21: JETTA GLI | E21: 34545.5 | G21: 3VW2T7BU5PM062118 | H21: 49
A22: 240070 | B22: 2024 | C22: VOLKSWAGEN | D22: JETTA SEDAN | E22: 26927 | F22: -28367.85 | G22: 3VWWM7BU5RM010702 | H22: 43
A23: 240203 | B23: 2024 | C23: VOLKSWAGEN | D23: ATLAS CROSS SPT | E23: 55950.97 | F23: -58834.65 | G23: 1V2FE2CA4RC210672 | H23: 43
A24: 240192 | B24: 2024 | C24: VOLKSWAGEN | D24: ATLAS CROSS SPT | E24: 55950.97 | F24: -58834.65 | G24: 1V2FE2CA0RC211429 | H24: 43
A25: 240173 | B25: 2024 | C25: VOLKSWAGEN | D25: JETTA SEDAN | E25: 29531 | F25: -31102.05 | G25: 3VWSM7BU4RM014707 | H25: 42
A26: 240188 | B26: 2024 | C26: VOLKSWAGEN | D26: ATLAS CROSS SPT | E26: 55950.97 | F26: -58834.65 | G26: 1V2FE2CAXRC211504 | H26: 42
A27: 240176 | B27: 2023 | C27: VOLKSWAGEN | D27: TAOS | E27: 37610 | F27: -39461.1 | G27: 3VV4X7B2XPM382549 | H27: 42
A28: 240156 | B28: 2024 | C28: VOLKSWAGEN | D28: JETTA GLI | E28: 34477 | F28: -36295.35 | G28: 3VW2T7BU5RM004870 | H28: 38
A29: 240132 | B29: 2024 | C29: VOLKSWAGEN | D29: JETTA SEDAN | E29: 28309 | F29: -29734.95 | G29: 3VWFM7BU8RM015148 | H29: 37
A30: 240003 | B30: 2024 | C30: VOLKSWAGEN | D30: JETTA GLI | E30: 32637 | F30: -34363.35 | G30: 3VW9T7BUXRM015328 | H30: 37
A31: 240021 | B31: 2024 | C31: VOLKSWAGEN | D31: GOLF GTI | E31: 38101 | F31: -40179.3 | G31: WVWRA7CD3RW124950 | H31: 37
A32: 240137 | B32: 2024 | C32: VOLKSWAGEN | D32: GOLF GTI | E32: 37506.9 | F32: -39440.1 | G32: WVWGA7CD1RW121181 | H32: 37
A33: 240206 | B33: 2024 | C33: VOLKSWAGEN | D33: ATLAS CROSS SPT | E33: 54250 | F33: -57051.75 | G33: 1V2BE2CA9RC212335 | H33: 37
... A37: 240052 | B37: 2024 | C37: VOLKSWAGEN | D37: TAOS | E37: 32679.42 | F37: -33257.7 | G37: 3VVSX7B29RM011974 | H37: 28
A38: 240178 | B38: 2024 | C38: VOLKSWAGEN | D38: JETTA GLI | E38: 31816.52 | G38: 3VW8T7BU7RM014696 | H38: 21
A39: 240030 | B39: 2024 | C39: VOLKSWAGEN | D39: TIGUAN | E39: 39108 | G39: 3VVMB7AX2RM018480 | H39: 20
A40: 230581 | B40: 2024 | C40: VOLKSWAGEN | D40: ATLAS CROSS SPT | E40: 54516 | F40: -57331.05 | G40: 1V2BE2CA7RC216397 | H40: 20
A41: 240067 | B41: 2024 | C41: VOLKSWAGEN | D41: ATLAS | E41: 58735.8 | G41: 1V2FR2CA3RC523474 | H41: 20
A42: 240042 | B42: 2024 | C42: VOLKSWAGEN | D42: TAOS | E42: 32864 | F42: -34706.7 | G42: 3VVEX7B22RM012347 | H42: 17
A43: 240160 | B43: 2024 | C43: VOLKSWAGEN | D43: ATLAS CROSS SPT | E43: 55948 | F43: -58834.65 | G43: 1V2FE2CA6RC216828 | H43: 17
A44: 240186 | B44: 2024 | C44: VOLKSWAGEN | D44: ATLAS | E44: 48894 | F44: -51427.95 | G44: 1V2LR2CA9RC529461 | H44: 17
A45: 240147 | B45: 2024 | C45: VOLKSWAGEN | D45: TAOS | E45: 31399 | F45: -33257.7 | G45: 3VVSX7B28RM012310 | H45: 16
A46: 230640 | B46: 2024 | C46: VOLKSWAGEN | D46: ATLAS | E46: 57790.97 | F46: -60546.15 | G46: 1V2FR2CA6RC526367 | H46: 16
A47: 240058 | B47: 2024 | C47: VOLKSWAGEN | D47: ATLAS | E47: 57668 | F47: -60640.65 | G47: 1V2FR2CA4RC527467 | H47: 16
A48: 240061 | B48: 2024 | C48: VOLKSWAGEN | D48: ATLAS | E48: 55259.97 | F48: -58109.1 | G48: 1V2BR2CAXRC525513 | H48: 16
A49: 240135 | B49: 2024 | C49: VOLKSWAGEN | D49: TIGUAN | E49: 44816 | F49: -47242.65 | G49: 3VV4B7AX3RM024093 | H49: 14
A50: 240152 | B50: 2024 | C50: VOLKSWAGEN | D50: TIGUAN | E50: 40184 | F50: -42379.05 | G50: 3VVMB7AX6RM022810 | H50: 14
A51: 240037 | B51: 2024 | C51: VOLKSWAGEN | D51: TAOS | E51: 32594 | F51: -34423.2 | G51: 3VVEX7B27RM012375 | H51: 14
A52: 240128 | B52: 2024 | C52: VOLKSWAGEN | D52: ATLAS CROSS SPT | E52: 54976.97 | F52: -57811.95 | G52: 1V2BE2CA8RC217171 | H52: 14
A53: 240068 | B53: 2024 | C53: VOLKSWAGEN | D53: ATLAS CROSS SPT | E53: 53794.97 | F53: -56570.85 | G53: 1V2BE2CA8RC216649 | H53: 14
A54: 240193 | B54: 2024 | C54: VOLKSWAGEN | D54: ATLAS | E54: 56946.97 | F54: -59880.45 | G54: 1V2FR2CA7RC527561 | H54: 14
A55: 240207 | B55: 2024 | C55: VOLKSWAGEN | D55: JETTA SEDAN | E55: 28539 | G55: 3VWEM7BU2RM001760 | H55: 13
A56: 240190 | B56: 2024 | C56: VOLKSWAGEN | D56: TIGUAN | E56: 44354 | F56: -46757.55 | G56: 3VV4B7AX8RM008326 | H56: 10
A57: 240020 | B57: 2024 | C57: VOLKSWAGEN | D57: TAOS | E57: 37662 | F57: -39744.6 | G57: 3VV4X7B2XRM012298 | H57: 10
A58: 240154 | B58: 2024 | C58: VOLKSWAGEN | D58: JETTA SEDAN | E58: 31261 | F58: -32918.55 | G58: 3VWGM7BUXRM014734 | H58: 10
A59: 240011 | B59: 2024 | C59: VOLKSWAGEN | D59: GOLF R | E59: 49211 | F59: -51857.4 | G59: WVWFB7CD4RW129946 | H59: 10
A60: 230639 | B60: 2024 | C60: VOLKSWAGEN | D60: ATLAS | E60: 54801.97 | F60: -57628.2 | G60: 1V2BR2CA7RC532368 | H60: 10
A61: 240016 | B61: 2024 | C61: VOLKSWAGEN | D61: TIGUAN | E61: 41134 | G61: 3VV8B7AX4RM026713 | H61: 8
A62: 240034 | B62: 2024 | C62: VOLKSWAGEN | D62: TAOS | E62: 37370 | G62: 3VV4X7B23RM014233 | H62: 8
A63: 240047 | B63: 2024 | C63: VOLKSWAGEN | D63: TAOS | E63: 32714 | G63: 3VVEX7B28RM011851 | H63: 8
A64: 240141 | B64: 2024 | C64: VOLKSWAGEN | D64: TAOS | E64: 31604 | G64: 3VVSX7B24RM012045 | H64: 8
A65: 240149 | B65: 2024 | C65: VOLKSWAGEN | D65: TIGUAN | E65: 41535 | G65: 3VV8B7AX7RM036166 | H65: 7
A66: 240202 | B66: 2024 | C66: VOLKSWAGEN | D66: TIGUAN | E66: 39600 | G66: 3VVMB7AX2RM023288 | H66: 7
A67: 240184 | B67: 2024 | C67: VOLKSWAGEN | D67: ATLAS | E67: 57913 | G67: 1V2FR2CA7RC531156 | H67: 7
A68: 240007 | B68: 2024 | C68: VOLKSWAGEN | D68: TIGUAN | E68: 45175.95 | F68: -47526.15 | G68: 3VV4B7AX2RM023873 | H68: 6
A69: 240027 | B69: 2024 | C69: VOLKSWAGEN | D69: TAOS | E69: 34009 | G69: 3VVUX7B2XRM011216 | H69: 6
A70: 240022 | B70: 2024 | C70: VOLKSWAGEN | D70: TIGUAN | E70: 44464 | F70: -46949.7 | G70: 3VV4B7AX7RM024873 | H70: 3
A71: 240148 | B71: 2024 | C71: VOLKSWAGEN | D71: TIGUAN | E71: 44011 | F71: -46474.05 | G71: 3VV4B7AX6RM025190 | H71: 3
A72: 240138 | B72: 2024 | C72: VOLKSWAGEN | D72: ATLAS | E72: 56861.97 | F72: -59880.45 | G72: 1V2FR2CA1RC537230 | H72: 3
A73: 240001 | B73: 2024 | C73: VOLKSWAGEN | D73: TAOS | E73: 38195 | F73: -40225.5 | G73: 3VV4X7B25RM012063 | H73: 2
A74: 240165 | B74: 2024 | C74: VOLKSWAGEN | D74: ATLAS | E74: 54716.97 | F74: -57628.2 | G74: 1V2BR2CA4RC531890 | H74: 2
A75: 240095 | B75: 2024 | C75: VOLKSWAGEN | D75: TIGUAN | E75: 41134 | G75: 3VV8B7AX2RM018979 | H75: 0

Sheet 2pager
B1: =Parametres!$B$1&" "&"2 pager"&" "&Parametres!$B$3&" "&Parametres!$B$4 -> Volks 2 pager Novembre 2023
B3: New | C3: Actual | D3: Budget | E3: 2022 | F3: ▲ Budget | G3: ▲2022 | H3: % ▲ Budget | I3: % ▲ 2022 | J3: Commentaires
B4: Units | C4: =+Print_Mois!$J$13+Print_Mois!$J$15 -> 90 | D4: =+Print_Mois!$D$13+Print_Mois!$D$15 -> 67.674832 | E4: =+Print_Mois!$O$13+Print_Mois!$O$15 -> 38 | F4: =+IFERROR($C4-D4,"") -> 22.325168 | G4: =+IFERROR($C4-E4,"") -> 52 | H4: =+IFERROR(F4/ABS($D4),"") -> 0.32988877 | I4: =+IFERROR(G4/ABS($E4),"") -> 1.3684211 | J4: Les volumes sont maintenant en ligne avec nos budgets. Les inventaires restent bas et le pipeline prévendu monte maintenant autour de 77%. Il faut améliorer le profit par unité tant front que back. Les holdabcks suivent, les frais d'admin sont là.
B5: Front Margin | C5: =+Print_Mois!$L$13+Print_Mois!$L$15 -> 204399.78 | D5: =+Print_Mois!$F$13+Print_Mois!$F$15 -> 165311.73 | E5: =+Print_Mois!$Q$13+Print_Mois!$Q$15 -> 92855.84 | F5: =+IFERROR($C5-D5,"") -> 39088.05 | G5: =+IFERROR($C5-E5,"") -> 111543.94 | H5: =+IFERROR(F5/ABS($D5),"") -> 0.23645055 | I5: =+IFERROR(G5/ABS($E5),"") -> 1.2012593
B6: Front margin / unit | C6: =+C5/C4 -> 2271.1087 | D6: =+D5/D4 -> 2442.7357 | E6: =+E5/E4 -> 2443.5747 | F6: =+IFERROR($C6-D6,"") -> -171.62704 | G6: =+IFERROR($C6-E6,"") -> -172.46607 | H6: =+IFERROR(F6/ABS($D6),"") -> -0.070260177 | I6: =+IFERROR(G6/ABS($E6),"") -> -0.070579413
B7: $ Salaires et commission | C7: =+Print_Mois!$L$31 -> 45012.79 | D7: =+Print_Mois!$F$31 -> 49973.981 | E7: =+Print_Mois!$Q$31 -> 27121.04 | F7: =+IFERROR($C7-D7,"") -> -4961.1905 | G7: =+IFERROR($C7-E7,"") -> 17891.75 | H7: =+IFERROR(F7/ABS($D7),"") -> -0.099275472 | I7: =+IFERROR(G7/ABS($E7),"") -> 0.6597
B8: % Salaires et commission | C8: =+C7/C5 -> 0.22021937 | D8: =+D7/D5 -> 0.30230148 | E8: =+E7/E5 -> 0.29207684 | F8: =+IFERROR($C8-D8,"") -> -0.082082113 | G8: =+IFERROR($C8-E8,"") -> -0.07185747 | H8: =+IFERROR(F8/ABS($D8),"") -> -0.27152402 | I8: =+IFERROR(G8/ABS($E8),"") -> -0.24602249
B9: Back Margin | C9: =+Print_Mois!$L$24 -> 95059.78 | D9: =+Print_Mois!$F$24 -> 77623.033 | E9: =+Print_Mois!$Q$24 -> 51064.45 | F9: =+IFERROR($C9-D9,"") -> 17436.747 | G9: =+IFERROR($C9-E9,"") -> 43995.33 | H9: =+IFERROR(F9/ABS($D9),"") -> 0.22463368 | I9: =+IFERROR(G9/ABS($E9),"") -> 0.86156475
B10: Back Margin / unit | C10: =+C9/C4 -> 1056.2198 | D10: =+D9/D4 -> 1147 | E10: =+E9/E4 -> 1343.8013 | F10: =+IFERROR($C10-D10,"") -> -90.780222 | G10: =+IFERROR($C10-E10,"") -> -287.58154 | H10: =+IFERROR(F10/ABS($D10),"") -> -0.079145791 | I10: =+IFERROR(G10/ABS($E10),"") -> -0.214006
B11: $ commission FI | C11: =+Print_Mois!$L$32 -> 28480.86 | D11: =+Print_Mois!$F$32 -> 23286.91 | E11: =+Print_Mois!$Q$32 -> 17558.83 | F11: =+IFERROR($C11-D11,"") -> 5193.9502 | G11: =+IFERROR($C11-E11,"") -> 10922.03 | H11: =+IFERROR(F11/ABS($D11),"") -> 0.22304162 | I11: =+IFERROR(G11/ABS($E11),"") -> 0.62202493
B12: % commission FI | C12: =+C11/C9 -> 0.29960999 | D12: =+D11/D9 -> 0.3 | E12: =+E11/E9 -> 0.34385624 | F12: =+IFERROR($C12-D12,"") -> -0.00039000721 | G12: =+IFERROR($C12-E12,"") -> -0.044246252 | H12: =+IFERROR(F12/ABS($D12),"") -> -0.001300024 | I12: =+IFERROR(G12/ABS($E12),"") -> -0.1286766
B13: Variable fees | C13: =+Print_Mois!$L$41-C7-C11 -> 48777.8 | D13: =+Print_Mois!$F$41-D7-D11 -> 37591.688 | E13: =+Print_Mois!$Q$41-E7-E11 -> 11808.58 | F13: =+IFERROR($C13-D13,"") -> 11186.112 | G13: =+IFERROR($C13-E13,"") -> 36969.22 | H13: =+IFERROR(F13/ABS($D13),"") -> 0.29756877 | I13: =+IFERROR(G13/ABS($E13),"") -> 3.1307083
B14: Variable fees / units | C14: =+C13/C4 -> 541.97556 | D14: =+D13/D4 -> 555.47515 | E14: =+E13/E4 -> 310.75211 | F14: =+IFERROR($C14-D14,"") -> -13.499595 | G14: =+IFERROR($C14-E14,"") -> 231.22345 | H14: =+IFERROR(F14/ABS($D14),"") -> -0.024302789 | I14: =+IFERROR(G14/ABS($E14),"") -> 0.74407686
B15: Other Revenues | C15: =+Print_Mois!$L$83 -> 142300.9 | D15: =+Print_Mois!$F$83 -> 105135.6 | E15: =+Print_Mois!$Q$83 -> 102324 | F15: =+IFERROR($C15-D15,"") -> 37165.301 | G15: =+IFERROR($C15-E15,"") -> 39976.9 | H15: =+IFERROR(F15/ABS($D15),"") -> 0.35349873 | I15: =+IFERROR(G15/ABS($E15),"") -> 0.39068938
B16: Inventory
B17: Units | C17: =Inventaire_Neuf!L3 -> 74 | D17: 61 | E17: 164 | F17: =+IFERROR($C17-D17,"") -> 13 | G17: =+IFERROR($C17-E17,"") -> -90 | H17: =+IFERROR(F17/ABS($D17),"") -> 0.21311475 | I17: =+IFERROR(G17/ABS($E17),"") -> -0.54878049
B18: $ | C18: =Inventaire_Neuf!L2 -> 3304520.1 | D18: 2233570 | E18: 5689693.2 | F18: =+IFERROR($C18-D18,"") -> 1070950.1 | G18: =+IFERROR($C18-E18,"") -> -2385173.1 | H18: =+IFERROR(F18/ABS($D18),"") -> 0.47947909 | I18: =+IFERROR(G18/ABS($E18),"") -> -0.41920944
C19: =C18/C17 -> 44655.677 | D19: =D18/D17 -> 36615.902 | E19: =E18/E17 -> 34693.251
B20: Used | C20: Actual | D20: Budget | E20: =$E$3 -> 2022 | F20: ▲ Budget | G20: =$G$3 -> ▲2022 | H20: % ▲ Budget | I20: =$I$3 -> % ▲ 2022 | J20: Commentaires
B21: Units | C21: =+Print_Mois!$J$96 -> 20 | D21: =+Print_Mois!$D$96 -> 39 | E21: =+Print_Mois!$O$96 -> 27 | F21: =+IFERROR($C21-D21,"") -> -19 | G21: =+IFERROR($C21-E21,"") -> -7 | H21: =+IFERROR(F21/ABS($D21),"") -> -0.48717949 | I21: =+IFERROR(G21/ABS($E21),"") -> -0.25925926 | J21: Les volumes sont la clé. Notre profit unitaire rejoint et dépasse même notre cible. Le F&i subit encore la contre performance du changement récent d'employé Nous visons être à niveau fin octobre. L'inventaire est absolument sous contrôle et notre marchandisage comme notre niveau de réponse web est dans les top 3 du groupe. On peut encore améliorer ça avec la mise en place du 2ème agent BDC mixte entre Audi et VW pour couvrir les heures de fin de semaine, accélérer les réponses et augmenter nos ventes.
B22: Front Margin | C22: =+Print_Mois!$L$96 -> 25020.67 | D22: =+Print_Mois!$F$96 -> 72462 | E22: =+Print_Mois!$Q$96 -> 23423.91 | F22: =+IFERROR($C22-D22,"") -> -47441.33 | G22: =+IFERROR($C22-E22,"") -> 1596.76 | H22: =+IFERROR(F22/ABS($D22),"") -> -0.65470633 | I22: =+IFERROR(G22/ABS($E22),"") -> 0.068167953
B23: Front margin / unit | C23: =+C22/C21 -> 1251.0335 | D23: =+D22/D21 -> 1858 | E23: =+E22/E21 -> 867.55222 | F23: =+IFERROR($C23-D23,"") -> -606.9665 | G23: =+IFERROR($C23-E23,"") -> 383.48128 | H23: =+IFERROR(F23/ABS($D23),"") -> -0.32667734 | I23: =+IFERROR(G23/ABS($E23),"") -> 0.44202674
B24: $ Salaires et commission | C24: =+Print_Mois!$L$111 -> 8239.93 | D24: =+Print_Mois!$F$111 -> 22726.5 | E24: =+Print_Mois!$Q$111 -> 14976.51 | F24: =+IFERROR($C24-D24,"") -> -14486.57 | G24: =+IFERROR($C24-E24,"") -> -6736.58 | H24: =+IFERROR(F24/ABS($D24),"") -> -0.63743075 | I24: =+IFERROR(G24/ABS($E24),"") -> -0.44980974
B25: % Salaires et commission | C25: =+C24/C22 -> 0.32932491 | D25: =+D24/D22 -> 0.31363335 | E25: =+E24/E22 -> 0.63936849 | F25: =+IFERROR($C25-D25,"") -> 0.015691562 | G25: =+IFERROR($C25-E25,"") -> -0.31004358 | H25: =+IFERROR(F25/ABS($D25),"") -> 0.050031546 | I25: =+IFERROR(G25/ABS($E25),"") -> -0.48492158
B26: Back Margin | C26: =+Print_Mois!$L$104 -> 26546.7 | D26: =+Print_Mois!$F$104 -> 81900 | E26: =+Print_Mois!$Q$104 -> 51221.51 | F26: =+IFERROR($C26-D26,"") -> -55353.3 | G26: =+IFERROR($C26-E26,"") -> -24674.81 | H26: =+IFERROR(F26/ABS($D26),"") -> -0.67586447 | I26: =+IFERROR(G26/ABS($E26),"") -> -0.4817275
B27: Back Margin / unit | C27: =+C26/C21 -> 1327.335 | D27: =+D26/D21 -> 2100 | E27: =+E26/E21 -> 1897.093 | F27: =+IFERROR($C27-D27,"") -> -772.665 | G27: =+IFERROR($C27-E27,"") -> -569.75796 | H27: =+IFERROR(F27/ABS($D27),"") -> -0.36793571 | I27: =+IFERROR(G27/ABS($E27),"") -> -0.30033213
B28: $ commission FI | C28: =+Print_Mois!$L$112 -> 7995.8 | D28: =+Print_Mois!$F$112 -> 24570 | E28: =+Print_Mois!$Q$112 -> 15310.99 | F28: =+IFERROR($C28-D28,"") -> -16574.2 | G28: =+IFERROR($C28-E28,"") -> -7315.19 | H28: =+IFERROR(F28/ABS($D28),"") -> -0.67457061 | I28: =+IFERROR(G28/ABS($E28),"") -> -0.47777381
B29: % commission FI | C29: =+C28/C26 -> 0.30119751 | D29: =+D28/D26 -> 0.3 | E29: =+E28/E26 -> 0.29891719 | F29: =+IFERROR($C29-D29,"") -> 0.0011975123 | G29: =+IFERROR($C29-E29,"") -> 0.0022803191 | H29: =+IFERROR(F29/ABS($D29),"") -> 0.0039917077 | I29: =+IFERROR(G29/ABS($E29),"") -> 0.0076285981
B30: Variable fees | C30: =+Print_Mois!$L$121-C24-C28 -> 19821.35 | D30: =+Print_Mois!$F$121-D24-D28 -> 16049.265 | E30: =+Print_Mois!$Q$121-E24-E28 -> 21441.66 | F30: =+IFERROR($C30-D30,"") -> 3772.0846 | G30: =+IFERROR($C30-E30,"") -> -1620.31 | H30: =+IFERROR(F30/ABS($D30),"") -> 0.23503161 | I30: =+IFERROR(G30/ABS($E30),"") -> -0.07556831
B31: Variable fees / units | C31: =+C30/C21 -> 991.0675 | D31: =+D30/D21 -> 411.51962 | E31: =+E30/E21 -> 794.13556 | F31: =+IFERROR($C31-D31,"") -> 579.54788 | G31: =+IFERROR($C31-E31,"") -> 196.93194 | H31: =+IFERROR(F31/ABS($D31),"") -> 1.4083116 | I31: =+IFERROR(G31/ABS($E31),"") -> 0.24798278
B32: Other Revenues | C32: =+Print_Mois!$L$162 -> 7749 | D32: =+Print_Mois!$F$162 -> 14004.9 | E32: =+Print_Mois!$Q$162 -> 10323 | F32: =+IFERROR($C32-D32,"") -> -6255.9 | G32: =+IFERROR($C32-E32,"") -> -2574 | H32: =+IFERROR(F32/ABS($D32),"") -> -0.44669366 | I32: =+IFERROR(G32/ABS($E32),"") -> -0.24934612
B33: Inventory
B34: Units | C34: =Inventaire_Used!N3 -> 93 | D34: 68 | E34: 92 | F34: =+IFERROR($C34-D34,"") -> 25 | G34: =+IFERROR($C34-E34,"") -> 1 | H34: =+IFERROR(F34/ABS($D34),"") -> 0.36764706 | I34: =+IFERROR(G34/ABS($E34),"") -> 0.010869565
B35: $ | C35: =Inventaire_Used!N2 -> 2199909.3 | D35: 1072231 | E35: 1510979 | F35: =+IFERROR($C35-D35,"") -> 1127678.3 | G35: =+IFERROR($C35-E35,"") -> 688930.3 | H35: =+IFERROR(F35/ABS($D35),"") -> 1.0517121 | I35: =+IFERROR(G35/ABS($E35),"") -> 0.45594962
C36: =C35/C34 -> 23654.939 | D36: =D35/D34 -> 15768.103 | E36: =E35/E34 -> 16423.685
B37: Service | C37: Actual | D37: Budget | E37: =$E$3 -> 2022 | F37: ▲ Budget | G37: =$G$3 -> ▲2022 | H37: % ▲ Budget | I37: =$I$3 -> % ▲ 2022 | J37: Commentaires
B38: Revenus | C38: =+Print_Mois!$K$193 -> 408560.41 | D38: =+Print_Mois!$E$193 -> 431214.32 | E38: =+Print_Mois!$P$193 -> 391200.46 | F38: =+IFERROR($C38-D38,"") -> -22653.915 | G38: =+IFERROR($C38-E38,"") -> 17359.95 | H38: =+IFERROR(F38/ABS($D38),"") -> -0.052535163 | I38: =+IFERROR(G38/ABS($E38),"") -> 0.044376098 | J38: Nous atteignons pour la première fois les chiffres au brut que nous visions avec notre augmentation de capacité. Dépenses sous contrôle malgré le déménagement et un lost time légèrement plus haut que le budget. Les économies sur les véhicules de compagnie ont été faites et les chiffres parlent. Notre nouveau directeur des opérations fixes démarre le 6 novembre prochain.
B39: Gross margin | C39: =+Print_Mois!$L$193 -> 290276.32 | D39: =+Print_Mois!$F$193 -> 308610.32 | E39: =+Print_Mois!$Q$193 -> 277195.32 | F39: =+IFERROR($C39-D39,"") -> -18334.002 | G39: =+IFERROR($C39-E39,"") -> 13081 | H39: =+IFERROR(F39/ABS($D39),"") -> -0.059408259 | I39: =+IFERROR(G39/ABS($E39),"") -> 0.047190551
B40: $ Revenus / #WO client | C40: =+Print_Mois!$K$171/Print_Mois!$J$171 -> 245.00563 | D40: =+IFERROR(Print_Mois!$E$171/Print_Mois!$D$171,"") -> 295 | E40: =+Print_Mois!$P$171/Print_Mois!$O$171 -> 265.65314 | F40: =+IFERROR($C40-D40,"") -> -49.994367 | G40: =+IFERROR($C40-E40,"") -> -20.647505 | H40: =+IFERROR(F40/ABS($D40),"") -> -0.16947243 | I40: =+IFERROR(G40/ABS($E40),"") -> -0.077723552
B41: $ Revenus / #WO garantie | C41: =+Print_Mois!$K$174/Print_Mois!$J$174 -> 196.97871 | D41: =+IFERROR(Print_Mois!$E$174/Print_Mois!$D$174,"") -> 170 | E41: =+Print_Mois!$P$174/Print_Mois!$O$174 -> 188.81694 | F41: =+IFERROR($C41-D41,"") -> 26.978707 | G41: =+IFERROR($C41-E41,"") -> 8.1617714 | H41: =+IFERROR(F41/ABS($D41),"") -> 0.15869828 | I41: =+IFERROR(G41/ABS($E41),"") -> 0.043225844
B42: Lost time | C42: =+Print_Mois!$L$183 -> -1433.5 | D42: =+Print_Mois!$F$183 -> -4926.8858 | E42: =+Print_Mois!$Q$183 -> -272.5 | F42: =+IFERROR($C42-D42,"") -> 3493.3858 | G42: =+IFERROR($C42-E42,"") -> -1161 | H42: =+IFERROR(F42/ABS($D42),"") -> 0.70904542 | I42: =+IFERROR(G42/ABS($E42),"") -> -4.2605505
B43: Total salaries | C43: =+Print_Mois!$L$209 -> 147660.68 | D43: =+Print_Mois!$F$209 -> 151992.79 | E43: =+Print_Mois!$Q$209 -> 131464.65 | F43: =+IFERROR($C43-D43,"") -> -4332.1085 | G43: =+IFERROR($C43-E43,"") -> 16196.03 | H43: =+IFERROR(F43/ABS($D43),"") -> -0.028502066 | I43: =+IFERROR(G43/ABS($E43),"") -> 0.12319684
B44: Salaries | C44: =+SUM(Print_Mois!$L$197:$L$203) -> 98709.7 | D44: =+SUM(Print_Mois!$F$197:$F$203) -> 84859.994 | E44: =+SUM(Print_Mois!$Q$197:$Q$203) -> 93387.11 | F44: =+IFERROR($C44-D44,"") -> 13849.706 | G44: =+IFERROR($C44-E44,"") -> 5322.59 | H44: =+IFERROR(F44/ABS($D44),"") -> 0.16320654 | I44: =+IFERROR(G44/ABS($E44),"") -> 0.056994911
B45: Fringes | C45: =+SUM(Print_Mois!$L$204:$L$208) -> 48950.98 | D45: =+SUM(Print_Mois!$F$204:$F$208) -> 67132.795 | E45: =+SUM(Print_Mois!$Q$204:$Q$208) -> 38077.54 | F45: =+IFERROR($C45-D45,"") -> -18181.815 | G45: =+IFERROR($C45-E45,"") -> 10873.44 | H45: =+IFERROR(F45/ABS($D45),"") -> -0.27083357 | I45: =+IFERROR(G45/ABS($E45),"") -> 0.28556046
B46: Total salaries / Revenus | C46: =+C43/C38 -> 0.36141701 | D46: =+D43/D38 -> 0.3524762 | E46: =+E43/E38 -> 0.33605444 | F46: =+IFERROR($C46-D46,"") -> 0.0089408011 | G46: =+IFERROR($C46-E46,"") -> 0.025362569 | H46: =+IFERROR(F46/ABS($D46),"") -> 0.025365687 | I46: =+IFERROR(G46/ABS($E46),"") -> 0.07547161
B47: Frais véhicules de cie | C47: =+Print_Mois!$L$212 -> 16921.98 | D47: =+Print_Mois!$F$212 -> 13231.667 | E47: =+Print_Mois!$Q$212 -> 16526.36 | F47: =+IFERROR($C47-D47,"") -> 3690.3133 | G47: =+IFERROR($C47-E47,"") -> 395.62 | H47: =+IFERROR(F47/ABS($D47),"") -> 0.27890011 | I47: =+IFERROR(G47/ABS($E47),"") -> 0.023938726
B49: Pieces | C49: Actual | D49: Budget | E49: =$E$3 -> 2022 | F49: ▲ Budget | G49: =$G$3 -> ▲2022 | H49: % ▲ Budget | I49: =$I$3 -> % ▲ 2022 | J49: Commentaires
B50: Revenus | C50: =+Print_Mois!$J$313 -> 597143.61 | D50: =+Print_Mois!$D$313 -> 591584.6 | E50: =+Print_Mois!$O$313 -> 554056.52 | F50: =+IFERROR($C50-D50,"") -> 5559.0104 | G50: =+IFERROR($C50-E50,"") -> 43087.09 | H50: =+IFERROR(F50/ABS($D50),"") -> 0.0093968139 | I50: =+IFERROR(G50/ABS($E50),"") -> 0.077766597 | J50: Net en bas des attentes. Nous voulons remonter ce chiffre et cela passera par plus de pneus notamment. Léger handicap sur l'huile et graisse car nous sommes temporairement revenus aux barils et bouteilles de 1L sans tank à huile pour le vrac dans le building Volvo. Pas un gros enjeu mais un léger impact dans le brut. Les chiffres au client et à la garantie continue de rejoindre de nouveaux sommets.
B51: Clients | C51: =+Print_Mois!$J$294 -> 133780.1 | D51: =+Print_Mois!$D$294 -> 164420.45 | E51: =+Print_Mois!$O$294 -> 127630.7 | F51: =+IFERROR($C51-D51,"") -> -30640.354 | G51: =+IFERROR($C51-E51,"") -> 6149.4 | H51: =+IFERROR(F51/ABS($D51),"") -> -0.18635366 | I51: =+IFERROR(G51/ABS($E51),"") -> 0.048181198
B52: Garantie | C52: =+Print_Mois!$J$296 -> 27809.93 | D52: =+Print_Mois!$D$296 -> 36893.793 | E52: =+Print_Mois!$O$296 -> 48352.21 | F52: =+IFERROR($C52-D52,"") -> -9083.8627 | G52: =+IFERROR($C52-E52,"") -> -20542.28 | H52: =+IFERROR(F52/ABS($D52),"") -> -0.24621656 | I52: =+IFERROR(G52/ABS($E52),"") -> -0.42484677
B53: Wholesale | C53: =+Print_Mois!$J$299 -> 123520.37 | D53: =+Print_Mois!$D$299 -> 85355.833 | E53: =+Print_Mois!$O$299 -> 125380.11 | F53: =+IFERROR($C53-D53,"") -> 38164.537 | G53: =+IFERROR($C53-E53,"") -> -1859.74 | H53: =+IFERROR(F53/ABS($D53),"") -> 0.44712277 | I53: =+IFERROR(G53/ABS($E53),"") -> -0.014832815
B54: Tires | C54: =+Print_Mois!$J$306 -> 150650.59 | D54: =+Print_Mois!$D$306 -> 109688.01 | E54: =+Print_Mois!$O$306 -> 102054 | F54: =+IFERROR($C54-D54,"") -> 40962.58 | G54: =+IFERROR($C54-E54,"") -> 48596.59 | H54: =+IFERROR(F54/ABS($D54),"") -> 0.37344629 | I54: =+IFERROR(G54/ABS($E54),"") -> 0.47618506
B55: All others | C55: =+C50-SUM(C51:C54) -> 161382.62 | D55: =+D50-SUM(D51:D54) -> 195226.51 | E55: =+E50-SUM(E51:E54) -> 150639.5 | F55: =+IFERROR($C55-D55,"") -> -33843.89 | G55: =+IFERROR($C55-E55,"") -> 10743.12 | H55: =+IFERROR(F55/ABS($D55),"") -> -0.17335704 | I55: =+IFERROR(G55/ABS($E55),"") -> 0.071316753
B56: Gross margin | C56: =+Print_Mois!$L$313 -> 159170.27 | D56: =+Print_Mois!$F$313 -> 166658.78 | E56: =+Print_Mois!$Q$313 -> 147774 | F56: =+IFERROR($C56-D56,"") -> -7488.5061 | G56: =+IFERROR($C56-E56,"") -> 11396.27 | H56: =+IFERROR(F56/ABS($D56),"") -> -0.044933164 | I56: =+IFERROR(G56/ABS($E56),"") -> 0.077119588
B57: $ Revenus / #WO client | C57: =+Print_Mois!$J$294/Print_Mois!$J$171 -> 133.37996 | D57: =+IFERROR(Print_Mois!$D$294/Print_Mois!$D$171,"") -> 151.56165 | E57: =+Print_Mois!$O$294/Print_Mois!$O$171 -> 120.29284 | F57: =+IFERROR($C57-D57,"") -> -18.181689 | G57: =+IFERROR($C57-E57,"") -> 13.087123 | H57: =+IFERROR(F57/ABS($D57),"") -> -0.11996233 | I57: =+IFERROR(G57/ABS($E57),"") -> 0.10879387
B58: $ Revenus / #WO garantie | C58: =+Print_Mois!$J$296/Print_Mois!$J$174 -> 239.74078 | D58: =+IFERROR(Print_Mois!$D$296/Print_Mois!$D$174,"") -> 157.02257 | E58: =+Print_Mois!$O$296/Print_Mois!$O$174 -> 259.95812 | F58: =+IFERROR($C58-D58,"") -> 82.718207 | G58: =+IFERROR($C58-E58,"") -> -20.217342 | H58: =+IFERROR(F58/ABS($D58),"") -> 0.52679183 | I58: =+IFERROR(G58/ABS($E58),"") -> -0.077771537
B59: Salaires autres | C59: =+Print_Mois!$L$319 -> 113.92 | D59: =+Print_Mois!$F$319 -> 2296.092 | E59: =+Print_Mois!$Q$319 -> 26877.98 | F59: =+IFERROR($C59-D59,"") -> -2182.172 | G59: =+IFERROR($C59-E59,"") -> -26764.06 | H59: =+IFERROR(F59/ABS($D59),"") -> -0.95038526 | I59: =+IFERROR(G59/ABS($E59),"") -> -0.99576159
B61: Others | C61: Actual | D61: Budget | E61: =$E$3 -> 2022 | F61: ▲ Budget | G61: =$G$3 -> ▲2022 | H61: % ▲ Budget | I61: =$I$3 -> % ▲ 2022 | J61: Commentaires
B62: Total salaries / Gross profits | C62: =+Print_Mois!$AF$432/Print_Mois!$AF$406 -> 0.3723268 | D62: =+Print_Mois!$Z$432/Print_Mois!$Z$406 -> 0.36820404 | E62: =+Print_Mois!$AL$432/Print_Mois!$AL$406 -> 0.42070803 | F62: =+IFERROR($C62-D62,"") -> 0.0041227664 | G62: =+IFERROR($C62-E62,"") -> -0.048381221 | H62: =+IFERROR(F62/ABS($D62),"") -> 0.011196961 | I62: =+IFERROR(G62/ABS($E62),"") -> -0.11499952
B63: Headcounts | C63: 45 | D63: 52.75 | E63: 36 | F63: =+IFERROR($C63-D63,"") -> -7.75 | G63: =+IFERROR($C63-E63,"") -> 9 | H63: =+IFERROR(F63/ABS($D63),"") -> -0.14691943 | I63: =+IFERROR(G63/ABS($E63),"") -> 0.25
B64: Marketing | C64: =N17+Print_Mois!$AF$413+Print_Mois!$AF$433 -> 32873.58 | D64: =+Print_Mois!$Z$413+Print_Mois!$Z$433 -> 36013.435 | E64: =+Print_Mois!$AL$413+Print_Mois!$AL$433 -> 44016.38 | F64: =+IFERROR($C64-D64,"") -> -3139.8552 | G64: =+IFERROR($C64-E64,"") -> -11142.8 | H64: =+IFERROR(F64/ABS($D64),"") -> -0.087185661 | I64: =+IFERROR(G64/ABS($E64),"") -> -0.25315121
B65: Other semi-fixed expenses | C65: =+Print_Mois!$AF$451-Print_Mois!$AF$433 -> 149811.61 | D65: =+Print_Mois!$Z$451-Print_Mois!$Z$433 -> 109321.61 | E65: =+Print_Mois!$AL$451-Print_Mois!$AL$433 -> 123688.41 | F65: =+IFERROR($C65-D65,"") -> 40489.998 | G65: =+IFERROR($C65-E65,"") -> 26123.2 | H65: =+IFERROR(F65/ABS($D65),"") -> 0.37037506 | I65: =+IFERROR(G65/ABS($E65),"") -> 0.21120168
B66: Floor plan interest | C66: =+Print_Mois!$AF$414 -> 20041.3 | D66: =+Print_Mois!$Z$414 -> 8271.4521 | E66: =+Print_Mois!$AL$414 -> 0 | F66: =+IFERROR($C66-D66,"") -> 11769.848 | G66: =+IFERROR($C66-E66,"") -> 20041.3 | H66: =+IFERROR(F66/ABS($D66),"") -> 1.4229482 | I66: =+IFERROR(G66/ABS($E66),"")
B67: Others Revenues | C67: =+Print_Mois!$AF$480-C32-C15 -> 780.32 | D67: =+Print_Mois!$Z$480-D32-D15 -> 26110 | E67: =+Print_Mois!$AL$480-E32-E15 -> 20103.06 | F67: =+IFERROR($C67-D67,"") -> -25329.68 | G67: =+IFERROR($C67-E67,"") -> -19322.74 | H67: =+IFERROR(F67/ABS($D67),"") -> -0.97011413 | I67: =+IFERROR(G67/ABS($E67),"") -> -0.96118402
B69: P&L | C69: Actual | D69: Budget | E69: =$E$3 -> 2022 | F69: ▲ Budget | G69: =$G$3 -> ▲2022 | H69: % ▲ Budget | I69: =$I$3 -> % ▲ 2022 | J69: Commentaires
B70: Selling and Marketing | C70: =+Print_Mois!$AF$418-Print_Mois!$AF$414+Print_Mois!$AF$433+Print_Mois!$AF$434+Print_Mois!$AF$435 -> 194756.8 | D70: =+Print_Mois!$Z$418-Print_Mois!$Z$414+Print_Mois!$Z$433+Print_Mois!$Z$434+Print_Mois!$Z$435 -> 210090.81 | E70: =+Print_Mois!$AL$418-Print_Mois!$AL$414+Print_Mois!$AL$433+Print_Mois!$AL$434+Print_Mois!$AL$435 -> 162338.29 | F70: =+IFERROR($C70-D70,"") -> -15334.009 | G70: =+IFERROR($C70-E70,"") -> 32418.51 | H70: =+IFERROR(F70/ABS($D70),"") -> -0.072987528 | I70: =+IFERROR(G70/ABS($E70),"") -> 0.19969725 | J70: On revient plus proche des 4% qui est notre objectif. Il reste des actions à mener et des résultats à atteindre. Les actions portent leurs premiers résultats.
B71: S&M / Brut | C71: =+C70/Print_Mois!$AF$406 -> 0.23664916 | D71: =+D70/Print_Mois!$Z$406 -> 0.22760613 | E71: =+E70/Print_Mois!$AL$406 -> 0.23550577 | F71: =+IFERROR($C71-D71,"") -> 0.0090430316 | G71: =+IFERROR($C71-E71,"") -> 0.0011433924 | H71: =+IFERROR(F71/ABS($D71),"") -> 0.039731055 | I71: =+IFERROR(G71/ABS($E71),"") -> 0.0048550507
B72: General & administrative | C72: =+Print_Mois!$AF$465+Print_Mois!$AF$432+Print_Mois!$AF$436+Print_Mois!$AF$438+SUM(Print_Mois!$AF$439:$AF$447)+Print_Mois!$AF$437 -> 463538.6 | D72: =+Print_Mois!$Z$465+Print_Mois!$Z$432+Print_Mois!$Z$436+Print_Mois!$Z$438+SUM(Print_Mois!$Z$439:$Z$447)+Print_Mois!$Z$437 -> 467563.4 | E72: =+Print_Mois!$AL$465+Print_Mois!$AL$432+Print_Mois!$AL$436+Print_Mois!$AL$438+SUM(Print_Mois!$AL$439:$AL$447)+Print_Mois!$AL$437 -> 432101.02 | F72: =+IFERROR($C72-D72,"") -> -4024.8039 | G72: =+IFERROR($C72-E72,"") -> 31437.58 | H72: =+IFERROR(F72/ABS($D72),"") -> -0.0086080387 | I72: =+IFERROR(G72/ABS($E72),"") -> 0.072755163
B73: G&A / Brut | C73: =+C72/Print_Mois!$AF$406 -> 0.56324617 | D73: =+D72/Print_Mois!$Z$406 -> 0.50654428 | E73: =+E72/Print_Mois!$AL$406 -> 0.62685324 | F73: =+IFERROR($C73-D73,"") -> 0.05670189 | G73: =+IFERROR($C73-E73,"") -> -0.063607073 | H73: =+IFERROR(F73/ABS($D73),"") -> 0.11193866 | I73: =+IFERROR(G73/ABS($E73),"") -> -0.10147044
B74: EBITDA | C74: =+Print_Mois!$AF$482+Print_Mois!$AF$414 -> 315511.75 | D74: =+Print_Mois!$Z$482+Print_Mois!$Z$414 -> 390641.77 | E74: =+Print_Mois!$AL$482+Print_Mois!$AL$414 -> 227628.43 | F74: =+IFERROR($C74-D74,"") -> -75130.016 | G74: =+IFERROR($C74-E74,"") -> 87883.32 | H74: =+IFERROR(F74/ABS($D74),"") -> -0.19232459 | I74: =+IFERROR(G74/ABS($E74),"") -> 0.38608235
B75: EBITDA % | C75: =+C74/Print_Mois!$AF$405 -> 0.050109175 | D75: =+D74/Print_Mois!$Z$405 -> 0.067525748 | E75: =+E74/Print_Mois!$AL$405 -> 0.051913597 | F75: =+IFERROR($C75-D75,"") -> -0.017416573 | G75: =+IFERROR($C75-E75,"") -> -0.0018044227 | H75: =+IFERROR(F75/ABS($D75),"") -> -0.25792492 | I75: =+IFERROR(G75/ABS($E75),"") -> -0.034758191
B76: EBIT | C76: =N9+Print_Mois!$AF$497 -> 291155.95 | D76: =+Print_Mois!$Z$497 -> 377297.94 | E76: =+Print_Mois!$AL$497 -> 222887.14 | F76: =+IFERROR($C76-D76,"") -> -86141.986 | G76: =+IFERROR($C76-E76,"") -> 68268.81 | H76: =+IFERROR(F76/ABS($D76),"") -> -0.2283129 | I76: =+IFERROR(G76/ABS($E76),"") -> 0.30629318
B77: EBIT % | C77: =+C76/Print_Mois!$AF$405 -> 0.046241017 | D77: =+D76/Print_Mois!$Z$405 -> 0.065219153 | E77: =+E76/Print_Mois!$AL$405 -> 0.050832285 | F77: =+IFERROR($C77-D77,"") -> -0.018978136 | G77: =+IFERROR($C77-E77,"") -> -0.0045912676 | H77: =+IFERROR(F77/ABS($D77),"") -> -0.29099022 | I77: =+IFERROR(G77/ABS($E77),"") -> -0.090321881
B79: "Pacing" du 30
B80: EBITDA | C80: 332778 | D80: 0.054
B81: Écart Fav / (Défav) | C81: =+C74-C80 -> -17266.25
B83: EBIT | C83: 318565 | D83: 0.052
B84: Écart Fav / (Défav) | C84: =+C76-C83 -> -27409.05
B86: Reforecast
B87: EBIT | C87: 508928
B88: Écart Fav / (Défav) | C88: =+C76-C87 -> -217772.05
B90: =+Parametres!B1 -> Volks | C90: =Parametres!$B$3&" "&Parametres!$B$4 -> Novembre 2023 | D90: AAJ 2023
B91: =CONCATENATE("Réalisé ",Parametres!$B$3," ",Parametres!$B$4) -> Réalisé Novembre 2023 | C91: =+C76 -> 291155.95 | D91: =+Print_AAD!AF497 -> 1745917.6
B92: =CONCATENATE("Budget ",Parametres!$B$3," ",Parametres!$B$4) -> Budget Novembre 2023 | C92: =+D76 -> 377297.94 | D92: =+Print_AAD!Z497 -> 2284748.9
B93: =CONCATENATE("Réalisé ",Parametres!$B$3," ",Parametres!$B$4-1) -> Réalisé Novembre 2022 | C93: =+E76 -> 222887.14 | D93: =+Print_AAD!AL497 -> 2103568

Sheet Print_Mois
C1: =Parametres!B1 -> Volks | K1: Véhicules neufs | S1: =CONCATENATE("Réalisé,"," ",Parametres!B3," ",Parametres!B4) -> Réalisé, Novembre 2023
D2: X | E2: O | F2: U | J2: NB | L2: $ | O2: NB | Q2: $ | V2: *** NE PAS EFFACER / Pour An Précédente ***
D3: BUDGET ORIGINAL | J3: RÉALISATION | M3: ÉCART réel / Budget | O3: ANNÉE PRÉCÉDENTE | R3: ECART (réel/ Ann.Préc.) | V3: NEUF | W3: 0.45
D4: UNITÉS | E4: $P/UNITÉ | F4: $PROFITS | J4: UNITÉS | K4: $P/UNITE | L4: $PROFITS | M4: UNITÉS | N4: $PROFITS | O4: UNITÉS | P4: $P/UNITE | Q4: $PROFITS | R4: UNITÉS | S4: $PROFITS | V4: USAGE | W4: 0.1
A5: Véhicules neufsVentes nettes | B5: Véhicules neufs | C5: Ventes nettes | F5: {=+INDEX('Budget original'!$A$2:$AO$500,MATCH($A5,'Budget original'!$A$2:$A$500,0),MATCH(F$2,'Budget original'!$A$2:$AO$2,0))} -> 3024137.9 | L5: =-SUMIFS(BV_Data_An_Cour!$O:$O,BV_Data_An_Cour!$X:$X,"Oui",BV_Data_An_Cour!$U:$U,$B5) -> 4112838.4 | Q5: =-SUMIFS(BV_Data_An_Prec!$O:$O,BV_Data_An_Prec!$X:$X,"Oui",BV_Data_An_Prec!$U:$U,$B5) -> 2056128.2 | V5: SERVICE | W5: 0.225
A6: Véhicules neufsAutos détail | B6: Véhicules neufs | C6: Autos détail | D6: {=+INDEX('Budget original'!$A$2:$AO$500,MATCH($A6,'Budget original'!$A$2:$A$500,0),MATCH(D$2,'Budget original'!$A$2:$AO$2,0))} -> 12.918857 | E6: =IF(D6=0,0,F6/D6) -> 1988.434 | F6: {=+INDEX('Budget original'!$A$2:$AO$500,MATCH($A6,'Budget original'!$A$2:$A$500,0),MATCH(F$2,'Budget original'!$A$2:$AO$2,0))} -> 25688.295 | J6: =-SUMIFS(BV_Data_An_Cour!$O:$O,BV_Data_An_Cour!$U:$U,$B6,BV_Data_An_Cour!$V:$V,$C6,BV_Data_An_Cour!$W:$W,J$2) -> 18 | K6: =IF(J6=0,0,L6/J6) -> 2139.7994 | L6: =-SUMIFS(BV_Data_An_Cour!$O:$O,BV_Data_An_Cour!$U:$U,$B6,BV_Data_An_Cour!$V:$V,$C6,BV_Data_An_Cour!$W:$W,L$2) -> 38516.39 | M6: =J6-D6 -> 5.0811429 | N6: =L6-F6 -> 12828.095 | O6: =-SUMIFS(BV_Data_An_Prec!$O:$O,BV_Data_An_Prec!$U:$U,$B6,BV_Data_An_Prec!$V:$V,$C6,BV_Data_An_Prec!$W:$W,O$2) -> 2 | P6: =IF(O6=0,0,Q6/O6) -> 1595.39 | Q6: =-SUMIFS(BV_Data_An_Prec!$O:$O,BV_Data_An_Prec!$U:$U,$B6,BV_Data_An_Prec!$V:$V,$C6,BV_Data_An_Prec!$W:$W,Q$2) -> 3190.78 | R6: =J6-O6 -> 16 | S6: =L6-Q6 -> 35325.61 | V6: CARROSSERIE | W6: 0.025
A7: Véhicules neufsCamions détail | B7: Véhicules neufs | C7: Camions détail | D7: {=+INDEX('Budget original'!$A$2:$AO$500,MATCH($A7,'Budget original'!$A$2:$A$500,0),MATCH(D$2,'Budget original'!$A$2:$AO$2,0))} -> 51.670261 | E7: =IF(D7=0,0,F7/D7) -> 2556.3336 | F7: {=+INDEX('Budget original'!$A$2:$AO$500,MATCH($A7,'Budget original'!$A$2:$A$500,0),MATCH(F$2,'Budget original'!$A$2:$AO$2,0))} -> 132086.43 | J7: =-SUMIFS(BV_Data_An_Cour!$O:$O,BV_Data_An_Cour!$U:$U,$B7,BV_Data_An_Cour!$V:$V,$C7,BV_Data_An_Cour!$W:$W,J$2) -> 71 | K7: =IF(J7=0,0,L7/J7) -> 2320.119 | L7: =-SUMIFS(BV_Data_An_Cour!$O:$O,BV_Data_An_Cour!$U:$U,$B7,BV_Data_An_Cour!$V:$V,$C7,BV_Data_An_Cour!$W:$W,L$2) -> 164728.45 | M7: =J7-D7 -> 19.329739 | N7: =L7-F7 -> 32642.024 | O7: =-SUMIFS(BV_Data_An_Prec!$O:$O,BV_Data_An_Prec!$U:$U,$B7,BV_Data_An_Prec!$V:$V,$C7,BV_Data_An_Prec!$W:$W,O$2) -> 32 | P7: =IF(O7=0,0,Q7/O7) -> 2121.0544 | Q7: =-SUMIFS(BV_Data_An_Prec!$O:$O,BV_Data_An_Prec!$U:$U,$B7,BV_Data_An_Prec!$V:$V,$C7,BV_Data_An_Prec!$W:$W,Q$2) -> 67873.74 | R7: =J7-O7 -> 39 | S7: =L7-Q7 -> 96854.71 | V7: PIECES | W7: 0.2
A8: Véhicules neufsSprinter | B8: Véhicules neufs | C8: Sprinter | D8: {=+INDEX('Budget original'!$A$2:$AO$500,MATCH($A8,'Budget original'!$A$2:$A$500,0),MATCH(D$2,'Budget original'!$A$2:$AO$2,0))} -> 0 | E8: =IF(D8=0,0,F8/D8) -> 0 | F8: {=+INDEX('Budget original'!$A$2:$AO$500,MATCH($A8,'Budget original'!$A$2:$A$500,0),MATCH(F$2,'Budget original'!$A$2:$AO$2,0))} -> 0 | J8: =-SUMIFS(BV_Data_An_Cour!$O:$O,BV_Data_An_Cour!$U:$U,$B8,BV_Data_An_Cour!$V:$V,$C8,BV_Data_An_Cour!$W:$W,J$2) -> 0 | K8: =IF(J8=0,0,L8/J8) -> 0 | L8: =-SUMIFS(BV_Data_An_Cour!$O:$O,BV_Data_An_Cour!$U:$U,$B8,BV_Data_An_Cour!$V:$V,$C8,BV_Data_An_Cour!$W:$W,L$2) -> 0 | M8: =J8-D8 -> 0 | N8: =L8-F8 -> 0 | O8: =-SUMIFS(BV_Data_An_Prec!$O:$O,BV_Data_An_Prec!$U:$U,$B8,BV_Data_An_Prec!$V:$V,$C8,BV_Data_An_Prec!$W:$W,O$2) -> 0 | P8: =IF(O8=0,0,Q8/O8) -> 0 | Q8: =-SUMIFS(BV_Data_An_Prec!$O:$O,BV_Data_An_Prec!$U:$U,$B8,BV_Data_An_Prec!$V:$V,$C8,BV_Data_An_Prec!$W:$W,Q$2) -> 0 | R8: =J8-O8 -> 0 | S8: =L8-Q8 -> 0 | W8: =SUM(W3:W7) -> 1
A9: Véhicules neufsMoto détail | B9: Véhicules neufs | C9: Moto détail | D9: {=+INDEX('Budget original'!$A$2:$AO$500,MATCH($A9,'Budget original'!$A$2:$A$500,0),MATCH(D$2,'Budget original'!$A$2:$AO$2,0))} -> 0 | E9: =IF(D9=0,0,F9/D9) -> 0 | F9: {=+INDEX('Budget original'!$A$2:$AO$500,MATCH($A9,'Budget original'!$A$2:$A$500,0),MATCH(F$2,'Budget original'!$A$2:$AO$2,0))} -> 0 | J9: =-SUMIFS(BV_Data_An_Cour!$O:$O,BV_Data_An_Cour!$U:$U,$B9,BV_Data_An_Cour!$V:$V,$C9,BV_Data_An_Cour!$W:$W,J$2) -> 0 | K9: =IF(J9=0,0,L9/J9) -> 0 | L9: =-SUMIFS(BV_Data_An_Cour!$O:$O,BV_Data_An_Cour!$U:$U,$B9,BV_Data_An_Cour!$V:$V,$C9,BV_Data_An_Cour!$W:$W,L$2) -> 0 | M9: =J9-D9 -> 0 | N9: =L9-F9 -> 0 | O9: =-SUMIFS(BV_Data_An_Prec!$O:$O,BV_Data_An_Prec!$U:$U,$B9,BV_Data_An_Prec!$V:$V,$C9,BV_Data_An_Prec!$W:$W,O$2) -> 0 | P9: =IF(O9=0,0,Q9/O9) -> 0 | Q9: =-SUMIFS(BV_Data_An_Prec!$O:$O,BV_Data_An_Prec!$U:$U,$B9,BV_Data_An_Prec!$V:$V,$C9,BV_Data_An_Prec!$W:$W,Q$2) -> 0 | R9: =J9-O9 -> 0 | S9: =L9-Q9 -> 0
A10: Véhicules neufs[...] | B10: Véhicules neufs | C10: [...] | D10: 0 | E10: =IF(D10=0,0,F10/D10) -> 0 | F10: {=+INDEX('Budget original'!$A$2:$AO$500,MATCH($A10,'Budget original'!$A$2:$A$500,0),MATCH(F$2,'Budget original'!$A$2:$AO$2,0))} -> 0 | J10: =-SUMIFS(BV_Data_An_Cour!$O:$O,BV_Data_An_Cour!$U:$U,$B10,BV_Data_An_Cour!$V:$V,$C10,BV_Data_An_Cour!$W:$W,J$2) -> 0 | K10: =IF(J10=0,0,L10/J10) -> 0 | L10: =-SUMIFS(BV_Data_An_Cour!$O:$O,BV_Data_An_Cour!$U:$U,$B10,BV_Data_An_Cour!$V:$V,$C10,BV_Data_An_Cour!$W:$W,L$2) -> 0 | M10: =J10-D10 -> 0 | N10: =L10-F10 -> 0 | O10: =-SUMIFS(BV_Data_An_Prec!$O:$O,BV_Data_An_Prec!$U:$U,$B10,BV_Data_An_Prec!$V:$V,$C10,BV_Data_An_Prec!$W:$W,O$2) -> 0 | P10: =IF(O10=0,0,Q10/O10) -> 0 | Q10: =-SUMIFS(BV_Data_An_Prec!$O:$O,BV_Data_An_Prec!$U:$U,$B10,BV_Data_An_Prec!$V:$V,$C10,BV_Data_An_Prec!$W:$W,Q$2) -> 0 | R10: =J10-O10 -> 0 | S10: =L10-Q10 -> 0
A11: Véhicules neufs[...] | B11: Véhicules neufs | C11: [...] | D11: 0 | E11: =IF(D11=0,0,F11/D11) -> 0 | F11: {=+INDEX('Budget original'!$A$2:$AO$500,MATCH($A11,'Budget original'!$A$2:$A$500,0),MATCH(F$2,'Budget original'!$A$2:$AO$2,0))} -> 0 | J11: =-SUMIFS(BV_Data_An_Cour!$O:$O,BV_Data_An_Cour!$U:$U,$B11,BV_Data_An_Cour!$V:$V,$C11,BV_Data_An_Cour!$W:$W,J$2) -> 0 | K11: =IF(J11=0,0,L11/J11) -> 0 | L11: =-SUMIFS(BV_Data_An_Cour!$O:$O,BV_Data_An_Cour!$U:$U,$B11,BV_Data_An_Cour!$V:$V,$C11,BV_Data_An_Cour!$W:$W,L$2) -> 0 | M11: =J11-D11 -> 0 | N11: =L11-F11 -> 0 | O11: =-SUMIFS(BV_Data_An_Prec!$O:$O,BV_Data_An_Prec!$U:$U,$B11,BV_Data_An_Prec!$V:$V,$C11,BV_Data_An_Prec!$W:$W,O$2) -> 0 | P11: =IF(O11=0,0,Q11/O11) -> 0 | Q11: =-SUMIFS(BV_Data_An_Prec!$O:$O,BV_Data_An_Prec!$U:$U,$B11,BV_Data_An_Prec!$V:$V,$C11,BV_Data_An_Prec!$W:$W,Q$2) -> 0 | R11: =J11-O11 -> 0 | S11: =L11-Q11 -> 0
A12: Véhicules neufs[...] | B12: Véhicules neufs | C12: [...] | D12: 0 | E12: =IF(D12=0,0,F12/D12) -> 0 | F12: {=+INDEX('Budget original'!$A$2:$AO$500,MATCH($A12,'Budget original'!$A$2:$A$500,0),MATCH(F$2,'Budget original'!$A$2:$AO$2,0))} -> 0 | J12: =-SUMIFS(BV_Data_An_Cour!$O:$O,BV_Data_An_Cour!$U:$U,$B12,BV_Data_An_Cour!$V:$V,$C12,BV_Data_An_Cour!$W:$W,J$2) -> 0 | K12: =IF(J12=0,0,L12/J12) -> 0 | L12: =-SUMIFS(BV_Data_An_Cour!$O:$O,BV_Data_An_Cour!$U:$U,$B12,BV_Data_An_Cour!$V:$V,$C12,BV_Data_An_Cour!$W:$W,L$2) -> 0 | M12: =J12-D12 -> 0 | N12: =L12-F12 -> 0 | O12: =-SUMIFS(BV_Data_An_Prec!$O:$O,BV_Data_An_Prec!$U:$U,$B12,BV_Data_An_Prec!$V:$V,$C12,BV_Data_An_Prec!$W:$W,O$2) -> 0 | P12: =IF(O12=0,0,Q12/O12) -> 0 | Q12: =-SUMIFS(BV_Data_An_Prec!$O:$O,BV_Data_An_Prec!$U:$U,$B12,BV_Data_An_Prec!$V:$V,$C12,BV_Data_An_Prec!$W:$W,Q$2) -> 0 | R12: =J12-O12 -> 0 | S12: =L12-Q12 -> 0
A13: Véhicules neufsTotal Neufs | B13: Véhicules neufs | C13: Total Neufs | D13: =+SUM(D6:D12) -> 64.589118 | E13: =IF(D13<=0,0,F13/D13) -> 2442.7446 | F13: =+SUM(F6:F12) -> 157774.72 | J13: =+SUM(J6:J12) -> 89 | K13: =IF(J13<=0,0,L13/J13) -> 2283.6499 | L13: =+SUM(L6:L12) -> 203244.84 | M13: =+SUM(M6:M12) -> 24.410882 | N13: =+SUM(N6:N12) -> 45470.119 | O13: =+SUM(O6:O12) -> 34 | P13: =IF(O13<=0,0,Q13/O13) -> 2090.1329 | Q13: =+SUM(Q6:Q12) -> 71064.52 | R13: =+SUM(R6:R12) -> 55 | S13: =+SUM(S6:S12) -> 132180.32
A14: Véhicules neufs | B14: Véhicules neufs | M14: =IF(D13=0,0,M13/D13) -> 0.37794109 | N14: =IF(F13=0,0,N13/F13) -> 0.28819648 | R14: =R13/O13 -> 1.6176471 | S14: =IF(Q13=0,0,(S13/Q13)) -> 1.8600044 | AD14: 20 | AE14: 1000 | AF14: =AD14*AE14 -> 20000
A15: Véhicules neufsEx-Démos et courtoisies | B15: Véhicules neufs | C15: Ex-Démos et courtoisies | D15: {=+INDEX('Budget original'!$A$2:$AO$500,MATCH($A15,'Budget original'!$A$2:$A$500,0),MATCH(D$2,'Budget original'!$A$2:$AO$2,0))} -> 3.0857143 | E15: =IF(D15=0,0,F15/D15) -> 2442.5492 | F15: {=+INDEX('Budget original'!$A$2:$AO$500,MATCH($A15,'Budget original'!$A$2:$A$500,0),MATCH(F$2,'Budget original'!$A$2:$AO$2,0))} -> 7537.009 | J15: =-SUMIFS(BV_Data_An_Cour!$O:$O,BV_Data_An_Cour!$U:$U,$B15,BV_Data_An_Cour!$V:$V,$C15,BV_Data_An_Cour!$W:$W,J$2) -> 1 | K15: =IF(J15=0,0,L15/J15) -> 1154.94 | L15: =-SUMIFS(BV_Data_An_Cour!$O:$O,BV_Data_An_Cour!$U:$U,$B15,BV_Data_An_Cour!$V:$V,$C15,BV_Data_An_Cour!$W:$W,L$2) -> 1154.94 | M15: =J15-D15 -> -2.0857143 | N15: =L15-F15 -> -6382.069 | O15: =-SUMIFS(BV_Data_An_Prec!$O:$O,BV_Data_An_Prec!$U:$U,$B15,BV_Data_An_Prec!$V:$V,$C15,BV_Data_An_Prec!$W:$W,O$2) -> 4 | P15: =IF(O15=0,0,Q15/O15) -> 5447.83 | Q15: =-SUMIFS(BV_Data_An_Prec!$O:$O,BV_Data_An_Prec!$U:$U,$B15,BV_Data_An_Prec!$V:$V,$C15,BV_Data_An_Prec!$W:$W,Q$2) -> 21791.32 | R15: =J15-O15 -> -3 | S15: =L15-Q15 -> -20636.38 | AD15: 25 | AE15: =AF15/AD15 -> 800 | AF15: =AF14 -> 20000
A16: Véhicules neufs | B16: Véhicules neufs
A17: Véhicules neufsFlottes | B17: Véhicules neufs | C17: Flottes | D17: {=+INDEX('Budget original'!$A$2:$AO$500,MATCH($A17,'Budget original'!$A$2:$A$500,0),MATCH(D$2,'Budget original'!$A$2:$AO$2,0))} -> 2.4685714 | E17: =IF(D17=0,0,F17/D17) -> 2442.5492 | F17: {=+INDEX('Budget original'!$A$2:$AO$500,MATCH($A17,'Budget original'!$A$2:$A$500,0),MATCH(F$2,'Budget original'!$A$2:$AO$2,0))} -> 6029.6072 | J17: =-SUMIFS(BV_Data_An_Cour!$O:$O,BV_Data_An_Cour!$U:$U,$B17,BV_Data_An_Cour!$V:$V,$C17,BV_Data_An_Cour!$W:$W,J$2) -> 2 | K17: =IF(J17=0,0,L17/J17) -> 3324.41 | L17: =-SUMIFS(BV_Data_An_Cour!$O:$O,BV_Data_An_Cour!$U:$U,$B17,BV_Data_An_Cour!$V:$V,$C17,BV_Data_An_Cour!$W:$W,L$2) -> 6648.82 | M17: =J17-D17 -> -0.46857143 | N17: =L17-F17 -> 619.21283 | O17: =-SUMIFS(BV_Data_An_Prec!$O:$O,BV_Data_An_Prec!$U:$U,$B17,BV_Data_An_Prec!$V:$V,$C17,BV_Data_An_Prec!$W:$W,O$2) -> 4 | P17: =IF(O17=0,0,Q17/O17) -> 2248.6875 | Q17: =-SUMIFS(BV_Data_An_Prec!$O:$O,BV_Data_An_Prec!$U:$U,$B17,BV_Data_An_Prec!$V:$V,$C17,BV_Data_An_Prec!$W:$W,Q$2) -> 8994.75 | R17: =J17-O17 -> -2 | S17: =L17-Q17 -> -2345.93
A18: Véhicules neufs | B18: Véhicules neufs
A19: Véhicules neufsRachat bail | B19: Véhicules neufs | C19: Rachat bail | D19: {=+INDEX('Budget original'!$A$2:$AO$500,MATCH($A19,'Budget original'!$A$2:$A$500,0),MATCH(D$2,'Budget original'!$A$2:$AO$2,0))} -> 0 | E19: =IF(D19=0,0,F19/D19) -> 0 | F19: {=+INDEX('Budget original'!$A$2:$AO$500,MATCH($A19,'Budget original'!$A$2:$A$500,0),MATCH(F$2,'Budget original'!$A$2:$AO$2,0))} -> 5760 | L19: =-SUMIFS(BV_Data_An_Cour!$O:$O,BV_Data_An_Cour!$U:$U,$B19,BV_Data_An_Cour!$V:$V,$C19,BV_Data_An_Cour!$W:$W,L$2) -> 3732.16 | N19: =L19-F19 -> -2027.84 | Q19: =-SUMIFS(BV_Data_An_Prec!$O:$O,BV_Data_An_Prec!$U:$U,$B19,BV_Data_An_Prec!$V:$V,$C19,BV_Data_An_Prec!$W:$W,Q$2) -> 12188.81 | R19: =O19-K19 -> 0 | S19: =L19-Q19 -> -8456.65
A20: Véhicules neufs | B20: Véhicules neufs
A21: Véhicules neufsRev. Finances | B21: Véhicules neufs | C21: Rev. Finances | D21: {=+INDEX('Budget original'!$A$2:$AO$500,MATCH($A21,'Budget original'!$A$2:$A$500,0),MATCH(D$2,'Budget original'!$A$2:$AO$2,0))} -> 0 | E21: =IF(D21=0,0,F21/D21) -> 0 | F21: {=+INDEX('Budget original'!$A$2:$AO$500,MATCH($A21,'Budget original'!$A$2:$A$500,0),MATCH(F$2,'Budget original'!$A$2:$AO$2,0))} -> 11640.071 | K21: =IF(J13=0,0,L21/(J13+J15)) -> 48.026889 | L21: =-SUMIFS(BV_Data_An_Cour!$O:$O,BV_Data_An_Cour!$U:$U,$B21,BV_Data_An_Cour!$V:$V,$C21,BV_Data_An_Cour!$W:$W,L$2) -> 4322.42 | N21: =L21-F21 -> -7317.6512 | P21: =IF(O13=0,0,Q21/(O13+O15)) -> 297.46316 | Q21: =-SUMIFS(BV_Data_An_Prec!$O:$O,BV_Data_An_Prec!$U:$U,$B21,BV_Data_An_Prec!$V:$V,$C21,BV_Data_An_Prec!$W:$W,Q$2) -> 11303.6 | R21: =O21-K21 -> -48.026889 | S21: =L21-Q21 -> -6981.18
A22: Véhicules neufsRev. Protections | B22: Véhicules neufs | C22: Rev. Protections | D22: {=+INDEX('Budget original'!$A$2:$AO$500,MATCH($A22,'Budget original'!$A$2:$A$500,0),MATCH(D$2,'Budget original'!$A$2:$AO$2,0))} -> 0 | E22: =IF(D22=0,0,F22/D22) -> 0 | F22: {=+INDEX('Budget original'!$A$2:$AO$500,MATCH($A22,'Budget original'!$A$2:$A$500,0),MATCH(F$2,'Budget original'!$A$2:$AO$2,0))} -> 64020.392 | K22: =IF(J13=0,0,L22/(J13+J15)) -> 993.18356 | L22: =-SUMIFS(BV_Data_An_Cour!$O:$O,BV_Data_An_Cour!$U:$U,$B22,BV_Data_An_Cour!$V:$V,$C22,BV_Data_An_Cour!$W:$W,L$2) -> 89386.52 | N22: =L22-F22 -> 25366.128 | P22: =IF(O13=0,0,Q22/(O13+O15)) -> 1040.0232 | Q22: =-SUMIFS(BV_Data_An_Prec!$O:$O,BV_Data_An_Prec!$U:$U,$B22,BV_Data_An_Prec!$V:$V,$C22,BV_Data_An_Prec!$W:$W,Q$2) -> 39520.88 | R22: =O22-K22 -> -993.18356 | S22: =L22-Q22 -> 49865.64
A23: Véhicules neufsRev. Autres | B23: Véhicules neufs | C23: Rev. Autres | D23: {=+INDEX('Budget original'!$A$2:$AO$500,MATCH($A23,'Budget original'!$A$2:$A$500,0),MATCH(D$2,'Budget original'!$A$2:$AO$2,0))} -> 0 | E23: =IF(D23=0,0,F23/D23) -> 0 | F23: {=+INDEX('Budget original'!$A$2:$AO$500,MATCH($A23,'Budget original'!$A$2:$A$500,0),MATCH(F$2,'Budget original'!$A$2:$AO$2,0))} -> 1962.5701 | K23: =IF(J13=0,0,L23/(J13+J15)) -> 15.009333 | L23: =-SUMIFS(BV_Data_An_Cour!$O:$O,BV_Data_An_Cour!$U:$U,$B23,BV_Data_An_Cour!$V:$V,$C23,BV_Data_An_Cour!$W:$W,L$2) -> 1350.84 | N23: =L23-F23 -> -611.73014 | P23: =IF(O13=0,0,Q23/(O13+O15)) -> 6.315 | Q23: =-SUMIFS(BV_Data_An_Prec!$O:$O,BV_Data_An_Prec!$U:$U,$B23,BV_Data_An_Prec!$V:$V,$C23,BV_Data_An_Prec!$W:$W,Q$2) -> 239.97 | R23: =O23-K23 -> -15.009333 | S23: =L23-Q23 -> 1110.87
A24: Véhicules neufsTotal F&I | B24: Véhicules neufs | C24: Total F&I | D24: =+D15+D13 -> 67.674832 | E24: =IF(D24<=0,0,F24/D24) -> 1147 | F24: =F21+F22+F23 -> 77623.033 | J24: =+J15+J13 -> 90 | K24: =IF(J24<=0,0,L24/J24) -> 1056.2198 | L24: =L21+L22+L23 -> 95059.78 | M24: =J24-D24 -> 22.325168 | N24: =L24-F24 -> 17436.747 | O24: =+O15+O13 -> 38 | P24: =IF(O24<=0,0,Q24/O24) -> 1343.8013 | Q24: =Q21+Q22+Q23 -> 51064.45 | S24: =L24-Q24 -> 43995.33
A25: Véhicules neufs | B25: Véhicules neufs | N25: =IF(N24=0,0,N24/F24) -> 0.22463368 | S25: =IF(Q24=0,0,(S24/Q24)) -> 0.86156475
A26: Véhicules neufs | B26: Véhicules neufs
A27: Véhicules neufsTotal Dépt. Neufs | B27: Véhicules neufs | C27: Total Dépt. Neufs | D27: =+D13+D15+D17 -> 70.143404 | E27: =IF(D27<=0,0,F27/D27) -> 3631.48 | F27: =F13+F17+F24+F19+F15 -> 254724.37 | J27: =+J13+J15+J17 -> 92 | K27: =IF(J27<=0,0,L27/J27) -> 3367.832 | L27: =L13+L17+L24+L19+L15 -> 309840.54 | M27: =J27-D27 -> 21.856596 | N27: =L27-F27 -> 55116.17 | O27: =+O13+O15+O17 -> 42 | P27: =IF(O27<=0,0,Q27/O27) -> 3931.044 | Q27: =Q13+Q17+Q24+Q19+Q15 -> 165103.85 | R27: =J27-O27 -> 50 | S27: =L27-Q27 -> 144736.69
A28: Véhicules neufs | B28: Véhicules neufs | L28: =L27/F27 -> 1.2163757 | M28: =M27/D27 -> 0.31159874 | N28: =N27/F27 -> 0.21637572 | R28: =R27/O27 -> 1.1904762 | S28: =IF(Q27=0,0,S27/Q27) -> 0.87664031
A29: Véhicules neufs | B29: Véhicules neufs
A30: Véhicules neufsDEPENSES | B30: Véhicules neufs | C30: DEPENSES
A31: Véhicules neufsComm. vendeurs | B31: Véhicules neufs | C31: Comm. vendeurs | D31: =F31/(F15+F13+F17) -> 0.2916633 | E31: =F31/D$24 -> 738.44262 | F31: {=+INDEX('Budget original'!$A$2:$AO$500,MATCH($A31,'Budget original'!$A$2:$A$500,0),MATCH(F$2,'Budget original'!$A$2:$AO$2,0))} -> 49973.981 | J31: =L31/(L15+L13+L17) -> 0.21328163 | K31: =IF(L31=0,0,L31/J$24) -> 500.14211 | L31: =SUMIFS(BV_Data_An_Cour!$O:$O,BV_Data_An_Cour!$U:$U,$B31,BV_Data_An_Cour!$V:$V,$C31,BV_Data_An_Cour!$W:$W,L$2) -> 45012.79 | N31: =L31-F31 -> -4961.1905 | P31: =IF(Q31=0,0,Q31/O$24) -> 713.71158 | Q31: =SUMIFS(BV_Data_An_Prec!$O:$O,BV_Data_An_Prec!$U:$U,$B31,BV_Data_An_Prec!$V:$V,$C31,BV_Data_An_Prec!$W:$W,Q$2) -> 27121.04 | S31: =L31-Q31 -> 17891.75
A32: Véhicules neufsComm. F&I | B32: Véhicules neufs | C32: Comm. F&I | D32: =F32/F24 -> 0.3 | E32: =F32/D$24 -> 344.1 | F32: {=+INDEX('Budget original'!$A$2:$AO$500,MATCH($A32,'Budget original'!$A$2:$A$500,0),MATCH(F$2,'Budget original'!$A$2:$AO$2,0))} -> 23286.91 | J32: =L32/L24 -> 0.29960999 | K32: =IF(L32=0,0,L32/J$24) -> 316.454 | L32: =SUMIFS(BV_Data_An_Cour!$O:$O,BV_Data_An_Cour!$U:$U,$B32,BV_Data_An_Cour!$V:$V,$C32,BV_Data_An_Cour!$W:$W,L$2) -> 28480.86 | N32: =L32-F32 -> 5193.9502 | P32: =IF(Q32=0,0,Q32/O$24) -> 462.07447 | Q32: =SUMIFS(BV_Data_An_Prec!$O:$O,BV_Data_An_Prec!$U:$U,$B32,BV_Data_An_Prec!$V:$V,$C32,BV_Data_An_Prec!$W:$W,Q$2) -> 17558.83 | S32: =L32-Q32 -> 10922.03 | U32: =(L32+L112)/(L104+L24+L19) -> 0.29102486 | V32: <<- F&A total Neuf Usagé Rachat | X32: =L24*U32 -> 27664.759 | Y32: =+L32-X32 -> 816.10095
A33: Véhicules neufsFrais de livraison | B33: Véhicules neufs | C33: Frais de livraison | E33: =F33/D$24 -> 113.25898 | F33: {=+INDEX('Budget original'!$A$2:$AO$500,MATCH($A33,'Budget original'!$A$2:$A$500,0),MATCH(F$2,'Budget original'!$A$2:$AO$2,0))} -> 7664.7823 | K33: =IF(L33=0,0,L33/J$24) -> 138.78767 | L33: =SUMIFS(BV_Data_An_Cour!$O:$O,BV_Data_An_Cour!$U:$U,$B33,BV_Data_An_Cour!$V:$V,$C33,BV_Data_An_Cour!$W:$W,L$2) -> 12490.89 | N33: =L33-F33 -> 4826.1077 | P33: =IF(Q33=0,0,Q33/O$24) -> 11.985 | Q33: =SUMIFS(BV_Data_An_Prec!$O:$O,BV_Data_An_Prec!$U:$U,$B33,BV_Data_An_Prec!$V:$V,$C33,BV_Data_An_Prec!$W:$W,Q$2) -> 455.43 | S33: =L33-Q33 -> 12035.46
A34: Véhicules neufsService gratuit 1 | B34: Véhicules neufs | C34: Service gratuit 1 | E34: =F34/D$24 -> 5.1177856 | F34: {=+INDEX('Budget original'!$A$2:$AO$500,MATCH($A34,'Budget original'!$A$2:$A$500,0),MATCH(F$2,'Budget original'!$A$2:$AO$2,0))} -> 346.34529 | K34: =IF(L34=0,0,L34/J$24) -> 63.110222 | L34: =SUMIFS(BV_Data_An_Cour!$O:$O,BV_Data_An_Cour!$U:$U,$B34,BV_Data_An_Cour!$V:$V,$C34,BV_Data_An_Cour!$W:$W,L$2) -> 5679.92 | N34: =L34-F34 -> 5333.5747 | P34: =IF(Q34=0,0,Q34/O$24) -> 0 | Q34: =SUMIFS(BV_Data_An_Prec!$O:$O,BV_Data_An_Prec!$U:$U,$B34,BV_Data_An_Prec!$V:$V,$C34,BV_Data_An_Prec!$W:$W,Q$2) -> 0 | S34: =L34-Q34 -> 5679.92
A35: Véhicules neufsEntretien stock | B35: Véhicules neufs | C35: Entretien stock | E35: =F35/D$24 -> 105.01044 | F35: {=+INDEX('Budget original'!$A$2:$AO$500,MATCH($A35,'Budget original'!$A$2:$A$500,0),MATCH(F$2,'Budget original'!$A$2:$AO$2,0))} -> 7106.5642 | K35: =IF(L35=0,0,L35/J$24) -> 83.834222 | L35: =SUMIFS(BV_Data_An_Cour!$O:$O,BV_Data_An_Cour!$U:$U,$B35,BV_Data_An_Cour!$V:$V,$C35,BV_Data_An_Cour!$W:$W,L$2) -> 7545.08 | N35: =L35-F35 -> 438.51584 | P35: =IF(Q35=0,0,Q35/O$24) -> 124.58947 | Q35: =SUMIFS(BV_Data_An_Prec!$O:$O,BV_Data_An_Prec!$U:$U,$B35,BV_Data_An_Prec!$V:$V,$C35,BV_Data_An_Prec!$W:$W,Q$2) -> 4734.4 | S35: =L35-Q35 -> 2810.68
A36: Véhicules neufsPublicité 1 | B36: Véhicules neufs | C36: Publicité 1 | E36: =F36/D$24 -> 300.75552 | F36: {=+INDEX('Budget original'!$A$2:$AO$500,MATCH($A36,'Budget original'!$A$2:$A$500,0),MATCH(F$2,'Budget original'!$A$2:$AO$2,0))} -> 20353.58 | K36: =IF(L36=0,0,L36/J$24) -> 38.481889 | L36: =SUMIFS(BV_Data_An_Cour!$O:$O,BV_Data_An_Cour!$U:$U,$B36,BV_Data_An_Cour!$V:$V,$C36,BV_Data_An_Cour!$W:$W,L$2) -> 3463.37 | N36: =L36-F36 -> -16890.21 | P36: =IF(Q36=0,0,Q36/O$24) -> 174.17763 | Q36: =SUMIFS(BV_Data_An_Prec!$O:$O,BV_Data_An_Prec!$U:$U,$B36,BV_Data_An_Prec!$V:$V,$C36,BV_Data_An_Prec!$W:$W,Q$2) -> 6618.75 | S36: =L36-Q36 -> -3155.38
A37: Véhicules neufsIntérêt de gros | B37: Véhicules neufs | C37: Intérêt de gros | E37: =F37/D$24 -> 31.332422 | F37: {=+INDEX('Budget original'!$A$2:$AO$500,MATCH($A37,'Budget original'!$A$2:$A$500,0),MATCH(F$2,'Budget original'!$A$2:$AO$2,0))} -> 2120.4164 | K37: =IF(L37=0,0,L37/J$24) -> 217.76156 | L37: =SUMIFS(BV_Data_An_Cour!$O:$O,BV_Data_An_Cour!$U:$U,$B37,BV_Data_An_Cour!$V:$V,$C37,BV_Data_An_Cour!$W:$W,L$2) -> 19598.54 | N37: =L37-F37 -> 17478.124 | P37: =IF(Q37=0,0,Q37/O$24) -> 0 | Q37: =SUMIFS(BV_Data_An_Prec!$O:$O,BV_Data_An_Prec!$U:$U,$B37,BV_Data_An_Prec!$V:$V,$C37,BV_Data_An_Prec!$W:$W,Q$2) -> 0 | S37: =L37-Q37 -> 19598.54
A38: Véhicules neufs[...] | B38: Véhicules neufs | C38: [...] | E38: =F38/D$24 -> 0 | F38: {=+INDEX('Budget original'!$A$2:$AO$500,MATCH($A38,'Budget original'!$A$2:$A$500,0),MATCH(F$2,'Budget original'!$A$2:$AO$2,0))} -> 0 | K38: =IF(L38=0,0,L38/J$24) -> 0 | L38: =SUMIFS(BV_Data_An_Cour!$O:$O,BV_Data_An_Cour!$U:$U,$B38,BV_Data_An_Cour!$V:$V,$C38,BV_Data_An_Cour!$W:$W,L$2) -> 0 | N38: =L38-F38 -> 0 | P38: =IF(Q38=0,0,Q38/O$24) -> 0 | Q38: =SUMIFS(BV_Data_An_Prec!$O:$O,BV_Data_An_Prec!$U:$U,$B38,BV_Data_An_Prec!$V:$V,$C38,BV_Data_An_Prec!$W:$W,Q$2) -> 0 | S38: =L38-Q38 -> 0
A39: Véhicules neufs[...] | B39: Véhicules neufs | C39: [...] | E39: =F39/D$24 -> 0 | F39: {=+INDEX('Budget original'!$A$2:$AO$500,MATCH($A39,'Budget original'!$A$2:$A$500,0),MATCH(F$2,'Budget original'!$A$2:$AO$2,0))} -> 0 | K39: =IF(L39=0,0,L39/J$24) -> 0 | L39: =SUMIFS(BV_Data_An_Cour!$O:$O,BV_Data_An_Cour!$U:$U,$B39,BV_Data_An_Cour!$V:$V,$C39,BV_Data_An_Cour!$W:$W,L$2) -> 0 | N39: =L39-F39 -> 0 | P39: =IF(Q39=0,0,Q39/O$24) -> 0 | Q39: =SUMIFS(BV_Data_An_Prec!$O:$O,BV_Data_An_Prec!$U:$U,$B39,BV_Data_An_Prec!$V:$V,$C39,BV_Data_An_Prec!$W:$W,Q$2) -> 0 | S39: =L39-Q39 -> 0
A40: Véhicules neufs[...] | B40: Véhicules neufs | C40: [...] | E40: =F40/D$24 -> 0 | F40: {=+INDEX('Budget original'!$A$2:$AO$500,MATCH($A40,'Budget original'!$A$2:$A$500,0),MATCH(F$2,'Budget original'!$A$2:$AO$2,0))} -> 0 | K40: =IF(L40=0,0,L40/J$24) -> 0 | L40: =SUMIFS(BV_Data_An_Cour!$O:$O,BV_Data_An_Cour!$U:$U,$B40,BV_Data_An_Cour!$V:$V,$C40,BV_Data_An_Cour!$W:$W,L$2) -> 0 | N40: =L40-F40 -> 0 | P40: =IF(Q40=0,0,Q40/O$24) -> 0 | Q40: =SUMIFS(BV_Data_An_Prec!$O:$O,BV_Data_An_Prec!$U:$U,$B40,BV_Data_An_Prec!$V:$V,$C40,BV_Data_An_Prec!$W:$W,Q$2) -> 0 | S40: =L40-Q40 -> 0
A41: Véhicules neufsTOTAL VARIABLES | B41: Véhicules neufs | C41: TOTAL VARIABLES | D41: % brut | E41: =F41/F$27 -> 0.43518639 | F41: =SUM(F31:F40) -> 110852.58 | J41: % brut | K41: =L41/L$27 -> 0.39462702 | L41: =SUM(L31:L40) -> 122271.45 | N41: =L41-F41 -> 11418.872 | O41: % brut | P41: =Q41/Q$27 -> 0.3421389 | Q41: =SUM(Q31:Q40) -> 56488.45 | S41: =L41-Q41 -> 65783
A42: Véhicules neufsSalaires cadres | B42: Véhicules neufs | C42: Salaires cadres | F42: {=+INDEX('Budget original'!$A$2:$AO$500,MATCH($A42,'Budget original'!$A$2:$A$500,0),MATCH(F$2,'Budget original'!$A$2:$AO$2,0))} -> 17292.497 | L42: =SUMIFS(BV_Data_An_Cour!$O:$O,BV_Data_An_Cour!$U:$U,$B42,BV_Data_An_Cour!$V:$V,$C42,BV_Data_An_Cour!$W:$W,L$2) -> 14903.64 | N42: =L42-F42 -> -2388.8566 | Q42: =SUMIFS(BV_Data_An_Prec!$O:$O,BV_Data_An_Prec!$U:$U,$B42,BV_Data_An_Prec!$V:$V,$C42,BV_Data_An_Prec!$W:$W,Q$2) -> 10683.15 | S42: =L42-Q42 -> 4220.49
A43: Véhicules neufsSalaires commis | B43: Véhicules neufs | C43: Salaires commis | F43: {=+INDEX('Budget original'!$A$2:$AO$500,MATCH($A43,'Budget original'!$A$2:$A$500,0),MATCH(F$2,'Budget original'!$A$2:$AO$2,0))} -> 10224.637 | L43: =SUMIFS(BV_Data_An_Cour!$O:$O,BV_Data_An_Cour!$U:$U,$B43,BV_Data_An_Cour!$V:$V,$C43,BV_Data_An_Cour!$W:$W,L$2) -> 8776.47 | N43: =L43-F43 -> -1448.1672 | Q43: =SUMIFS(BV_Data_An_Prec!$O:$O,BV_Data_An_Prec!$U:$U,$B43,BV_Data_An_Prec!$V:$V,$C43,BV_Data_An_Prec!$W:$W,Q$2) -> 7810.83 | S43: =L43-Q43 -> 965.64
A44: Véhicules neufsSalaires autres | B44: Véhicules neufs | C44: Salaires autres | F44: {=+INDEX('Budget original'!$A$2:$AO$500,MATCH($A44,'Budget original'!$A$2:$A$500,0),MATCH(F$2,'Budget original'!$A$2:$AO$2,0))} -> 8208.9839 | L44: =SUMIFS(BV_Data_An_Cour!$O:$O,BV_Data_An_Cour!$U:$U,$B44,BV_Data_An_Cour!$V:$V,$C44,BV_Data_An_Cour!$W:$W,L$2) -> 2988 | N44: =L44-F44 -> -5220.9839 | Q44: =SUMIFS(BV_Data_An_Prec!$O:$O,BV_Data_An_Prec!$U:$U,$B44,BV_Data_An_Prec!$V:$V,$C44,BV_Data_An_Prec!$W:$W,Q$2) -> 6360.3 | S44: =L44-Q44 -> -3372.3
A45: Véhicules neufsSalaires spécialistes | B45: Véhicules neufs | C45: Salaires spécialistes | F45: {=+INDEX('Budget original'!$A$2:$AO$500,MATCH($A45,'Budget original'!$A$2:$A$500,0),MATCH(F$2,'Budget original'!$A$2:$AO$2,0))} -> 0 | L45: =SUMIFS(BV_Data_An_Cour!$O:$O,BV_Data_An_Cour!$U:$U,$B45,BV_Data_An_Cour!$V:$V,$C45,BV_Data_An_Cour!$W:$W,L$2) -> 0 | N45: =L45-F45 -> 0 | Q45: =SUMIFS(BV_Data_An_Prec!$O:$O,BV_Data_An_Prec!$U:$U,$B45,BV_Data_An_Prec!$V:$V,$C45,BV_Data_An_Prec!$W:$W,Q$2) -> 0 | S45: =L45-Q45 -> 0
A46: Véhicules neufs[...] | B46: Véhicules neufs | C46: [...] | F46: {=+INDEX('Budget original'!$A$2:$AO$500,MATCH($A46,'Budget original'!$A$2:$A$500,0),MATCH(F$2,'Budget original'!$A$2:$AO$2,0))} -> 0 | L46: =SUMIFS(BV_Data_An_Cour!$O:$O,BV_Data_An_Cour!$U:$U,$B46,BV_Data_An_Cour!$V:$V,$C46,BV_Data_An_Cour!$W:$W,L$2) -> 0 | N46: =L46-F46 -> 0 | Q46: =SUMIFS(BV_Data_An_Prec!$O:$O,BV_Data_An_Prec!$U:$U,$B46,BV_Data_An_Prec!$V:$V,$C46,BV_Data_An_Prec!$W:$W,Q$2) -> 0 | S46: =L46-Q46 -> 0
A47: Véhicules neufs[...] | B47: Véhicules neufs | C47: [...] | F47: {=+INDEX('Budget original'!$A$2:$AO$500,MATCH($A47,'Budget original'!$A$2:$A$500,0),MATCH(F$2,'Budget original'!$A$2:$AO$2,0))} -> 0 | L47: =SUMIFS(BV_Data_An_Cour!$O:$O,BV_Data_An_Cour!$U:$U,$B47,BV_Data_An_Cour!$V:$V,$C47,BV_Data_An_Cour!$W:$W,L$2) -> 0 | N47: =L47-F47 -> 0 | Q47: =SUMIFS(BV_Data_An_Prec!$O:$O,BV_Data_An_Prec!$U:$U,$B47,BV_Data_An_Prec!$V:$V,$C47,BV_Data_An_Prec!$W:$W,Q$2) -> 0 | S47: =L47-Q47 -> 0
A48: Véhicules neufs[...] | B48: Véhicules neufs | C48: [...] | F48: {=+INDEX('Budget original'!$A$2:$AO$500,MATCH($A48,'Budget original'!$A$2:$A$500,0),MATCH(F$2,'Budget original'!$A$2:$AO$2,0))} -> 0 | L48: =SUMIFS(BV_Data_An_Cour!$O:$O,BV_Data_An_Cour!$U:$U,$B48,BV_Data_An_Cour!$V:$V,$C48,BV_Data_An_Cour!$W:$W,L$2) -> 0 | N48: =L48-F48 -> 0 | Q48: =SUMIFS(BV_Data_An_Prec!$O:$O,BV_Data_An_Prec!$U:$U,$B48,BV_Data_An_Prec!$V:$V,$C48,BV_Data_An_Prec!$W:$W,Q$2) -> 0 | S48: =L48-Q48 -> 0
A49: Véhicules neufsSalaires en absences | B49: Véhicules neufs | C49: Salaires en absences | F49: {=+INDEX('Budget original'!$A$2:$AO$500,MATCH($A49,'Budget original'!$A$2:$A$500,0),MATCH(F$2,'Budget original'!$A$2:$AO$2,0))} -> 13098.691 | L49: =SUMIFS(BV_Data_An_Cour!$O:$O,BV_Data_An_Cour!$U:$U,$B49,BV_Data_An_Cour!$V:$V,$C49,BV_Data_An_Cour!$W:$W,L$2) -> 8803.83 | N49: =L49-F49 -> -4294.8611 | Q49: =SUMIFS(BV_Data_An_Prec!$O:$O,BV_Data_An_Prec!$U:$U,$B49,BV_Data_An_Prec!$V:$V,$C49,BV_Data_An_Prec!$W:$W,Q$2) -> 10292.12 | S49: =L49-Q49 -> -1488.29
A50: Véhicules neufsDéduction à la source | B50: Véhicules neufs | C50: Déduction à la source | F50: {=+INDEX('Budget original'!$A$2:$AO$500,MATCH($A50,'Budget original'!$A$2:$A$500,0),MATCH(F$2,'Budget original'!$A$2:$AO$2,0))} -> 13021.389 | L50: =SUMIFS(BV_Data_An_Cour!$O:$O,BV_Data_An_Cour!$U:$U,$B50,BV_Data_An_Cour!$V:$V,$C50,BV_Data_An_Cour!$W:$W,L$2) -> 11365.4 | N50: =L50-F50 -> -1655.9887 | Q50: =SUMIFS(BV_Data_An_Prec!$O:$O,BV_Data_An_Prec!$U:$U,$B50,BV_Data_An_Prec!$V:$V,$C50,BV_Data_An_Prec!$W:$W,Q$2) -> 14137.17 | S50: =L50-Q50 -> -2771.77
A51: Véhicules neufsBénéfices marginaux | B51: Véhicules neufs | C51: Bénéfices marginaux | F51: {=+INDEX('Budget original'!$A$2:$AO$500,MATCH($A51,'Budget original'!$A$2:$A$500,0),MATCH(F$2,'Budget original'!$A$2:$AO$2,0))} -> 9118.332 | L51: =SUMIFS(BV_Data_An_Cour!$O:$O,BV_Data_An_Cour!$U:$U,$B51,BV_Data_An_Cour!$V:$V,$C51,BV_Data_An_Cour!$W:$W,L$2) -> 6383.81 | N51: =L51-F51 -> -2734.522 | Q51: =SUMIFS(BV_Data_An_Prec!$O:$O,BV_Data_An_Prec!$U:$U,$B51,BV_Data_An_Prec!$V:$V,$C51,BV_Data_An_Prec!$W:$W,Q$2) -> 6475.93 | S51: =L51-Q51 -> -92.12
A52: Véhicules neufsCsst | B52: Véhicules neufs | C52: Csst | F52: {=+INDEX('Budget original'!$A$2:$AO$500,MATCH($A52,'Budget original'!$A$2:$A$500,0),MATCH(F$2,'Budget original'!$A$2:$AO$2,0))} -> 4356.09 | L52: =SUMIFS(BV_Data_An_Cour!$O:$O,BV_Data_An_Cour!$U:$U,$B52,BV_Data_An_Cour!$V:$V,$C52,BV_Data_An_Cour!$W:$W,L$2) -> 1164.96 | N52: =L52-F52 -> -3191.13 | Q52: =SUMIFS(BV_Data_An_Prec!$O:$O,BV_Data_An_Prec!$U:$U,$B52,BV_Data_An_Prec!$V:$V,$C52,BV_Data_An_Prec!$W:$W,Q$2) -> 1332 | S52: =L52-Q52 -> -167.04
A53: Véhicules neufs[...] | B53: Véhicules neufs | C53: [...] | F53: {=+INDEX('Budget original'!$A$2:$AO$500,MATCH($A53,'Budget original'!$A$2:$A$500,0),MATCH(F$2,'Budget original'!$A$2:$AO$2,0))} -> 0 | L53: =SUMIFS(BV_Data_An_Cour!$O:$O,BV_Data_An_Cour!$U:$U,$B53,BV_Data_An_Cour!$V:$V,$C53,BV_Data_An_Cour!$W:$W,L$2) -> 0 | N53: =L53-F53 -> 0 | Q53: =SUMIFS(BV_Data_An_Prec!$O:$O,BV_Data_An_Prec!$U:$U,$B53,BV_Data_An_Prec!$V:$V,$C53,BV_Data_An_Prec!$W:$W,Q$2) -> 0 | S53: =L53-Q53 -> 0
A54: Véhicules neufsTOTAL PERSONNEL | B54: Véhicules neufs | C54: TOTAL PERSONNEL | D54: % brut | E54: =F54/F$27 -> 0.2956946 | F54: =+SUM(F42:F53) -> 75320.62 | J54: % brut | K54: =L54/L$27 -> 0.17552935 | L54: =+SUM(L42:L53) -> 54386.11 | N54: =+SUM(N42:N53) -> -20934.51 | O54: % brut | P54: =Q54/Q$27 -> 0.34579145 | Q54: =+SUM(Q42:Q53) -> 57091.5 | S54: =+SUM(S42:S53) -> -2705.39
A55: Véhicules neufsPublicité 2 | B55: Véhicules neufs | C55: Publicité 2 | F55: {=+INDEX('Budget original'!$A$2:$AO$500,MATCH($A55,'Budget original'!$A$2:$A$500,0),MATCH(F$2,'Budget original'!$A$2:$AO$2,0))} -> 0 | L55: =SUMIFS(BV_Data_An_Cour!$O:$O,BV_Data_An_Cour!$U:$U,$B55,BV_Data_An_Cour!$V:$V,$C55,BV_Data_An_Cour!$W:$W,L$2) -> 0 | N55: =L55-F55 -> 0 | Q55: =SUMIFS(BV_Data_An_Prec!$O:$O,BV_Data_An_Prec!$U:$U,$B55,BV_Data_An_Prec!$V:$V,$C55,BV_Data_An_Prec!$W:$W,Q$2) -> 0 | S55: =L55-Q55 -> 0
A56: Véhicules neufsService gratuit 2 | B56: Véhicules neufs | C56: Service gratuit 2 | F56: {=+INDEX('Budget original'!$A$2:$AO$500,MATCH($A56,'Budget original'!$A$2:$A$500,0),MATCH(F$2,'Budget original'!$A$2:$AO$2,0))} -> 0 | L56: =SUMIFS(BV_Data_An_Cour!$O:$O,BV_Data_An_Cour!$U:$U,$B56,BV_Data_An_Cour!$V:$V,$C56,BV_Data_An_Cour!$W:$W,L$2) -> 0 | N56: =L56-F56 -> 0 | Q56: =SUMIFS(BV_Data_An_Prec!$O:$O,BV_Data_An_Prec!$U:$U,$B56,BV_Data_An_Prec!$V:$V,$C56,BV_Data_An_Prec!$W:$W,Q$2) -> 0 | S56: =L56-Q56 -> 0
A57: Véhicules neufsFrais véhicules de cie | B57: Véhicules neufs | C57: Frais véhicules de cie | F57: {=+INDEX('Budget original'!$A$2:$AO$500,MATCH($A57,'Budget original'!$A$2:$A$500,0),MATCH(F$2,'Budget original'!$A$2:$AO$2,0))} -> 7945.8333 | L57: =SUMIFS(BV_Data_An_Cour!$O:$O,BV_Data_An_Cour!$U:$U,$B57,BV_Data_An_Cour!$V:$V,$C57,BV_Data_An_Cour!$W:$W,L$2) -> 7119.66 | N57: =L57-F57 -> -826.17333 | Q57: =SUMIFS(BV_Data_An_Prec!$O:$O,BV_Data_An_Prec!$U:$U,$B57,BV_Data_An_Prec!$V:$V,$C57,BV_Data_An_Prec!$W:$W,Q$2) -> 7727.22 | S57: =L57-Q57 -> -607.56
A58: Véhicules neufsInformatique | B58: Véhicules neufs | C58: Informatique | F58: {=+INDEX('Budget original'!$A$2:$AO$500,MATCH($A58,'Budget original'!$A$2:$A$500,0),MATCH(F$2,'Budget original'!$A$2:$AO$2,0))} -> 6260.8664 | L58: =SUMIFS(BV_Data_An_Cour!$O:$O,BV_Data_An_Cour!$U:$U,$B58,BV_Data_An_Cour!$V:$V,$C58,BV_Data_An_Cour!$W:$W,L$2) -> 6760.11 | N58: =L58-F58 -> 499.2436 | Q58: =SUMIFS(BV_Data_An_Prec!$O:$O,BV_Data_An_Prec!$U:$U,$B58,BV_Data_An_Prec!$V:$V,$C58,BV_Data_An_Prec!$W:$W,Q$2) -> 6535.42 | S58: =L58-Q58 -> 224.69
A59: Véhicules neufsFrais de déplacement | B59: Véhicules neufs | C59: Frais de déplacement | F59: {=+INDEX('Budget original'!$A$2:$AO$500,MATCH($A59,'Budget original'!$A$2:$A$500,0),MATCH(F$2,'Budget original'!$A$2:$AO$2,0))} -> 1000.088 | L59: =SUMIFS(BV_Data_An_Cour!$O:$O,BV_Data_An_Cour!$U:$U,$B59,BV_Data_An_Cour!$V:$V,$C59,BV_Data_An_Cour!$W:$W,L$2) -> 1646.26 | N59: =L59-F59 -> 646.17196 | Q59: =SUMIFS(BV_Data_An_Prec!$O:$O,BV_Data_An_Prec!$U:$U,$B59,BV_Data_An_Prec!$V:$V,$C59,BV_Data_An_Prec!$W:$W,Q$2) -> 1005.63 | S59: =L59-Q59 -> 640.63
A60: Véhicules neufsServices extérieurs | B60: Véhicules neufs | C60: Services extérieurs | F60: {=+INDEX('Budget original'!$A$2:$AO$500,MATCH($A60,'Budget original'!$A$2:$A$500,0),MATCH(F$2,'Budget original'!$A$2:$AO$2,0))} -> 7157.2662 | L60: =SUMIFS(BV_Data_An_Cour!$O:$O,BV_Data_An_Cour!$U:$U,$B60,BV_Data_An_Cour!$V:$V,$C60,BV_Data_An_Cour!$W:$W,L$2) -> 8387.93 | N60: =L60-F60 -> 1230.6638 | Q60: =SUMIFS(BV_Data_An_Prec!$O:$O,BV_Data_An_Prec!$U:$U,$B60,BV_Data_An_Prec!$V:$V,$C60,BV_Data_An_Prec!$W:$W,Q$2) -> 7466.13 | S60: =L60-Q60 -> 921.8
A61: Véhicules neufsFournitures autres | B61: Véhicules neufs | C61: Fournitures autres | F61: {=+INDEX('Budget original'!$A$2:$AO$500,MATCH($A61,'Budget original'!$A$2:$A$500,0),MATCH(F$2,'Budget original'!$A$2:$AO$2,0))} -> 141.17976 | L61: =SUMIFS(BV_Data_An_Cour!$O:$O,BV_Data_An_Cour!$U:$U,$B61,BV_Data_An_Cour!$V:$V,$C61,BV_Data_An_Cour!$W:$W,L$2) -> 250.25 | N61: =L61-F61 -> 109.07024 | Q61: =SUMIFS(BV_Data_An_Prec!$O:$O,BV_Data_An_Prec!$U:$U,$B61,BV_Data_An_Prec!$V:$V,$C61,BV_Data_An_Prec!$W:$W,Q$2) -> 0 | S61: =L61-Q61 -> 250.25
A62: Véhicules neufsUniformes | B62: Véhicules neufs | C62: Uniformes | F62: {=+INDEX('Budget original'!$A$2:$AO$500,MATCH($A62,'Budget original'!$A$2:$A$500,0),MATCH(F$2,'Budget original'!$A$2:$AO$2,0))} -> 72.903619 | L62: =SUMIFS(BV_Data_An_Cour!$O:$O,BV_Data_An_Cour!$U:$U,$B62,BV_Data_An_Cour!$V:$V,$C62,BV_Data_An_Cour!$W:$W,L$2) -> 0 | N62: =L62-F62 -> -72.903619 | Q62: =SUMIFS(BV_Data_An_Prec!$O:$O,BV_Data_An_Prec!$U:$U,$B62,BV_Data_An_Prec!$V:$V,$C62,BV_Data_An_Prec!$W:$W,Q$2) -> 0 | S62: =L62-Q62 -> 0
A63: Véhicules neufsPapeterie | B63: Véhicules neufs | C63: Papeterie | F63: {=+INDEX('Budget original'!$A$2:$AO$500,MATCH($A63,'Budget original'!$A$2:$A$500,0),MATCH(F$2,'Budget original'!$A$2:$AO$2,0))} -> 763.45104 | L63: =SUMIFS(BV_Data_An_Cour!$O:$O,BV_Data_An_Cour!$U:$U,$B63,BV_Data_An_Cour!$V:$V,$C63,BV_Data_An_Cour!$W:$W,L$2) -> 2065.76 | N63: =L63-F63 -> 1302.309 | Q63: =SUMIFS(BV_Data_An_Prec!$O:$O,BV_Data_An_Prec!$U:$U,$B63,BV_Data_An_Prec!$V:$V,$C63,BV_Data_An_Prec!$W:$W,Q$2) -> 951.98 | S63: =L63-Q63 -> 1113.78
A64: Véhicules neufsTéléphone | B64: Véhicules neufs | C64: Téléphone | F64: {=+INDEX('Budget original'!$A$2:$AO$500,MATCH($A64,'Budget original'!$A$2:$A$500,0),MATCH(F$2,'Budget original'!$A$2:$AO$2,0))} -> 258.72025 | L64: =SUMIFS(BV_Data_An_Cour!$O:$O,BV_Data_An_Cour!$U:$U,$B64,BV_Data_An_Cour!$V:$V,$C64,BV_Data_An_Cour!$W:$W,L$2) -> 280.55 | N64: =L64-F64 -> 21.82975 | Q64: =SUMIFS(BV_Data_An_Prec!$O:$O,BV_Data_An_Prec!$U:$U,$B64,BV_Data_An_Prec!$V:$V,$C64,BV_Data_An_Prec!$W:$W,Q$2) -> 262.09 | S64: =L64-Q64 -> 18.46
A65: Véhicules neufsFrais postaux | B65: Véhicules neufs | C65: Frais postaux | F65: {=+INDEX('Budget original'!$A$2:$AO$500,MATCH($A65,'Budget original'!$A$2:$A$500,0),MATCH(F$2,'Budget original'!$A$2:$AO$2,0))} -> 123.74429 | L65: =SUMIFS(BV_Data_An_Cour!$O:$O,BV_Data_An_Cour!$U:$U,$B65,BV_Data_An_Cour!$V:$V,$C65,BV_Data_An_Cour!$W:$W,L$2) -> 169.87 | N65: =L65-F65 -> 46.125706 | Q65: =SUMIFS(BV_Data_An_Prec!$O:$O,BV_Data_An_Prec!$U:$U,$B65,BV_Data_An_Prec!$V:$V,$C65,BV_Data_An_Prec!$W:$W,Q$2) -> 231.51 | S65: =L65-Q65 -> -61.64
A66: Véhicules neufsDivers | B66: Véhicules neufs | C66: Divers | F66: {=+INDEX('Budget original'!$A$2:$AO$500,MATCH($A66,'Budget original'!$A$2:$A$500,0),MATCH(F$2,'Budget original'!$A$2:$AO$2,0))} -> 470.18236 | L66: =SUMIFS(BV_Data_An_Cour!$O:$O,BV_Data_An_Cour!$U:$U,$B66,BV_Data_An_Cour!$V:$V,$C66,BV_Data_An_Cour!$W:$W,L$2) -> 102.8 | N66: =L66-F66 -> -367.38236 | Q66: =SUMIFS(BV_Data_An_Prec!$O:$O,BV_Data_An_Prec!$U:$U,$B66,BV_Data_An_Prec!$V:$V,$C66,BV_Data_An_Prec!$W:$W,Q$2) -> 312.12 | S66: =L66-Q66 -> -209.32
A67: Véhicules neufsFormation | B67: Véhicules neufs | C67: Formation | F67: {=+INDEX('Budget original'!$A$2:$AO$500,MATCH($A67,'Budget original'!$A$2:$A$500,0),MATCH(F$2,'Budget original'!$A$2:$AO$2,0))} -> 612.7403 | L67: =SUMIFS(BV_Data_An_Cour!$O:$O,BV_Data_An_Cour!$U:$U,$B67,BV_Data_An_Cour!$V:$V,$C67,BV_Data_An_Cour!$W:$W,L$2) -> 2190.54 | N67: =L67-F67 -> 1577.7997 | Q67: =SUMIFS(BV_Data_An_Prec!$O:$O,BV_Data_An_Prec!$U:$U,$B67,BV_Data_An_Prec!$V:$V,$C67,BV_Data_An_Prec!$W:$W,Q$2) -> 2017.82 | S67: =L67-Q67 -> 172.72
A68: Véhicules neufsFrais bancaires | B68: Véhicules neufs | C68: Frais bancaires | F68: {=+INDEX('Budget original'!$A$2:$AO$500,MATCH($A68,'Budget original'!$A$2:$A$500,0),MATCH(F$2,'Budget original'!$A$2:$AO$2,0))} -> 2685.2134 | L68: =SUMIFS(BV_Data_An_Cour!$O:$O,BV_Data_An_Cour!$U:$U,$B68,BV_Data_An_Cour!$V:$V,$C68,BV_Data_An_Cour!$W:$W,L$2) -> 5124.82 | N68: =L68-F68 -> 2439.6066 | Q68: =AL447*W3 -> 11242.134 | S68: =L68-Q68 -> -6117.314
A69: Véhicules neufs[...] | B69: Véhicules neufs | C69: [...] | F69: {=+INDEX('Budget original'!$A$2:$AO$500,MATCH($A69,'Budget original'!$A$2:$A$500,0),MATCH(F$2,'Budget original'!$A$2:$AO$2,0))} -> 0 | N69: =L69-F69 -> 0 | Q69: =SUMIFS(BV_Data_An_Prec!$O:$O,BV_Data_An_Prec!$U:$U,$B69,BV_Data_An_Prec!$V:$V,$C69,BV_Data_An_Prec!$W:$W,Q$2) -> 0 | S69: =L69-Q69 -> 0
A70: Véhicules neufs[...] | B70: Véhicules neufs | C70: [...] | F70: {=+INDEX('Budget original'!$A$2:$AO$500,MATCH($A70,'Budget original'!$A$2:$A$500,0),MATCH(F$2,'Budget original'!$A$2:$AO$2,0))} -> 0 | L70: =SUMIFS(BV_Data_An_Cour!$O:$O,BV_Data_An_Cour!$U:$U,$B70,BV_Data_An_Cour!$V:$V,$C70,BV_Data_An_Cour!$W:$W,L$2) -> 0 | N70: =L70-F70 -> 0 | Q70: =SUMIFS(BV_Data_An_Prec!$O:$O,BV_Data_An_Prec!$U:$U,$B70,BV_Data_An_Prec!$V:$V,$C70,BV_Data_An_Prec!$W:$W,Q$2) -> 0 | S70: =L70-Q70 -> 0
A71: Véhicules neufs[...] | B71: Véhicules neufs | C71: [...] | F71: {=+INDEX('Budget original'!$A$2:$AO$500,MATCH($A71,'Budget original'!$A$2:$A$500,0),MATCH(F$2,'Budget original'!$A$2:$AO$2,0))} -> 0 | L71: =SUMIFS(BV_Data_An_Cour!$O:$O,BV_Data_An_Cour!$U:$U,$B71,BV_Data_An_Cour!$V:$V,$C71,BV_Data_An_Cour!$W:$W,L$2)*0.32 -> 0 | N71: =L71-F71 -> 0 | Q71: =SUMIFS(BV_Data_An_Prec!$O:$O,BV_Data_An_Prec!$U:$U,$B71,BV_Data_An_Prec!$V:$V,$C71,BV_Data_An_Prec!$W:$W,Q$2)*0.32 -> 0 | S71: =L71-Q71 -> 0
A72: Véhicules neufsTOTAL SEMI-FIXES | B72: Véhicules neufs | C72: TOTAL SEMI-FIXES | D72: % brut | E72: =F72/F$27 -> 0.10792917 | F72: =+SUM(F55:F71) -> 27492.189 | J72: % brut | K72: =L72/L$27 -> 0.11005193 | L72: =+SUM(L55:L71) -> 34098.55 | N72: =+SUM(N55:N71) -> 6606.3609 | O72: % brut | P72: =Q72/Q$27 -> 0.22865641 | Q72: =+SUM(Q55:Q71) -> 37752.054 | S72: =+SUM(S55:S71) -> -3653.504
A73: Véhicules neufs | B73: Véhicules neufs
A74: Véhicules neufsTOTAL DES DÉPENSES | B74: Véhicules neufs | C74: TOTAL DES DÉPENSES | D74: % brut | E74: =F74/F$27 -> 0.83881015 | F74: =F41+F54+F72 -> 213665.39 | J74: % brut | K74: =L74/L$27 -> 0.68020831 | L74: =L41+L54+L72 -> 210756.11 | N74: =L74-F74 -> -2909.2768 | O74: % brut | P74: =Q74/Q$27 -> 0.91658677 | Q74: =Q41+Q54+Q72 -> 151332 | S74: =L74-Q74 -> 59424.106
A75: Véhicules neufsProgramme neuf 1 | B75: Véhicules neufs | C75: Programme neuf 1 | F75: {=+INDEX('Budget original'!$A$2:$AO$500,MATCH($A75,'Budget original'!$A$2:$A$500,0),MATCH(F$2,'Budget original'!$A$2:$AO$2,0))} -> 0 | L75: =-SUMIFS(BV_Data_An_Cour!$O:$O,BV_Data_An_Cour!$U:$U,$B75,BV_Data_An_Cour!$V:$V,$C75,BV_Data_An_Cour!$W:$W,L$2)-L155 -> 0 | N75: =L75-F75 -> 0 | Q75: =-SUMIFS(BV_Data_An_Prec!$O:$O,BV_Data_An_Prec!$U:$U,$B75,BV_Data_An_Prec!$V:$V,$C75,BV_Data_An_Prec!$W:$W,Q$2) -> 0
A76: Véhicules neufsProgramme neuf 2 | B76: Véhicules neufs | C76: Programme neuf 2 | F76: {=+INDEX('Budget original'!$A$2:$AO$500,MATCH($A76,'Budget original'!$A$2:$A$500,0),MATCH(F$2,'Budget original'!$A$2:$AO$2,0))} -> 0 | L76: =-SUMIFS(BV_Data_An_Cour!$O:$O,BV_Data_An_Cour!$U:$U,$B76,BV_Data_An_Cour!$V:$V,$C76,BV_Data_An_Cour!$W:$W,L$2) -> 0 | N76: =L76-F76 -> 0 | Q76: =-SUMIFS(BV_Data_An_Prec!$O:$O,BV_Data_An_Prec!$U:$U,$B76,BV_Data_An_Prec!$V:$V,$C76,BV_Data_An_Prec!$W:$W,Q$2) -> 0 | S76: =L76-Q76 -> 0
A77: Véhicules neufsProgramme neuf 3 | B77: Véhicules neufs | C77: Programme neuf 3 | F77: {=+INDEX('Budget original'!$A$2:$AO$500,MATCH($A77,'Budget original'!$A$2:$A$500,0),MATCH(F$2,'Budget original'!$A$2:$AO$2,0))} -> 0 | L77: =-SUMIFS(BV_Data_An_Cour!$O:$O,BV_Data_An_Cour!$U:$U,$B77,BV_Data_An_Cour!$V:$V,$C77,BV_Data_An_Cour!$W:$W,L$2) -> 0 | N77: =L77-F77 -> 0 | Q77: =-SUMIFS(BV_Data_An_Prec!$O:$O,BV_Data_An_Prec!$U:$U,$B77,BV_Data_An_Prec!$V:$V,$C77,BV_Data_An_Prec!$W:$W,Q$2) -> 0 | S77: =L77-Q77 -> 0
A78: Véhicules neufsHoldbacks | B78: Véhicules neufs | C78: Holdbacks | E78: =+F78/D24 -> 1181.3417 | F78: {=+INDEX('Budget original'!$A$2:$AO$500,MATCH($A78,'Budget original'!$A$2:$A$500,0),MATCH(F$2,'Budget original'!$A$2:$AO$2,0))} -> 79947.103 | K78: =+L78/J24 -> 1115.8667 | L78: =-SUMIFS(BV_Data_An_Cour!$O:$O,BV_Data_An_Cour!$U:$U,$B78,BV_Data_An_Cour!$V:$V,$C78,BV_Data_An_Cour!$W:$W,L$2) -> 100428 | N78: =L78-F78 -> 20480.897 | Q78: =-SUMIFS(BV_Data_An_Prec!$O:$O,BV_Data_An_Prec!$U:$U,$B78,BV_Data_An_Prec!$V:$V,$C78,BV_Data_An_Prec!$W:$W,Q$2) -> 86672 | S78: =L78-Q78 -> 13756
A79: Véhicules neufs[...] | B79: Véhicules neufs | C79: [...] | F79: {=+INDEX('Budget original'!$A$2:$AO$500,MATCH($A79,'Budget original'!$A$2:$A$500,0),MATCH(F$2,'Budget original'!$A$2:$AO$2,0))} -> 0 | L79: =-SUMIFS(BV_Data_An_Cour!$O:$O,BV_Data_An_Cour!$U:$U,$B79,BV_Data_An_Cour!$V:$V,$C79,BV_Data_An_Cour!$W:$W,L$2) -> 0 | N79: =L79-F79 -> 0 | Q79: =-SUMIFS(BV_Data_An_Prec!$O:$O,BV_Data_An_Prec!$U:$U,$B79,BV_Data_An_Prec!$V:$V,$C79,BV_Data_An_Prec!$W:$W,Q$2) -> 0 | S79: =L79-Q79 -> 0
A80: Véhicules neufs[...] | B80: Véhicules neufs | C80: [...] | F80: {=+INDEX('Budget original'!$A$2:$AO$500,MATCH($A80,'Budget original'!$A$2:$A$500,0),MATCH(F$2,'Budget original'!$A$2:$AO$2,0))} -> 0 | L80: =-SUMIFS(BV_Data_An_Cour!$O:$O,BV_Data_An_Cour!$U:$U,$B80,BV_Data_An_Cour!$V:$V,$C80,BV_Data_An_Cour!$W:$W,L$2) -> 0 | N80: =L80-F80 -> 0 | Q80: =-SUMIFS(BV_Data_An_Prec!$O:$O,BV_Data_An_Prec!$U:$U,$B80,BV_Data_An_Prec!$V:$V,$C80,BV_Data_An_Prec!$W:$W,Q$2) -> 0 | S80: =L80-Q80 -> 0
A81: Véhicules neufs[...] | B81: Véhicules neufs | C81: [...] | F81: {=+INDEX('Budget original'!$A$2:$AO$500,MATCH($A81,'Budget original'!$A$2:$A$500,0),MATCH(F$2,'Budget original'!$A$2:$AO$2,0))} -> 0 | L81: =-SUMIFS(BV_Data_An_Cour!$O:$O,BV_Data_An_Cour!$U:$U,$B81,BV_Data_An_Cour!$V:$V,$C81,BV_Data_An_Cour!$W:$W,L$2) -> 0 | N81: =L81-F81 -> 0 | Q81: =-SUMIFS(BV_Data_An_Prec!$O:$O,BV_Data_An_Prec!$U:$U,$B81,BV_Data_An_Prec!$V:$V,$C81,BV_Data_An_Prec!$W:$W,Q$2) -> 0 | S81: =L81-Q81 -> 0
A82: Véhicules neufsFrais administration | B82: Véhicules neufs | C82: Frais administration | F82: {=+INDEX('Budget original'!$A$2:$AO$500,MATCH($A82,'Budget original'!$A$2:$A$500,0),MATCH(F$2,'Budget original'!$A$2:$AO$2,0))} -> 25188.496 | J82: =+L82/K82 -> 92 | K82: =+L82/J27 -> 455.14022 | L82: =-SUMIFS(BV_Data_An_Cour!$O:$O,BV_Data_An_Cour!$U:$U,$B82,BV_Data_An_Cour!$V:$V,$C82,BV_Data_An_Cour!$W:$W,L$2) -> 41872.9 | N82: =L82-F82 -> 16684.404 | Q82: =-SUMIFS(BV_Data_An_Prec!$O:$O,BV_Data_An_Prec!$U:$U,$B82,BV_Data_An_Prec!$V:$V,$C82,BV_Data_An_Prec!$W:$W,Q$2) -> 15652 | S82: =L82-Q82 -> 26220.9
A83: Véhicules neufsAUTRES REVENUS | B83: Véhicules neufs | C83: AUTRES REVENUS | F83: =+SUM(F75:F82) -> 105135.6 | L83: =+SUM(L75:L82) -> 142300.9 | N83: =+SUM(N75:N82) -> 37165.301 | Q83: =+SUM(Q75:Q82) -> 102324 | S83: =+SUM(S75:S82) -> 39976.9
A84: Véhicules neufs | B84: Véhicules neufs
A85: Véhicules neufsPROFIT DÉPARTEMENTAL | B85: Véhicules neufs | C85: PROFIT DÉPARTEMENTAL | F85: =F27-F74+F83 -> 146194.58 | L85: =L27-L74+L83 -> 241385.33 | N85: =N27-N41-N54-N72+N83 -> 95190.748 | Q85: =Q27-Q74+Q83 -> 116095.85 | S85: =S27-S41-S54-S72+S83 -> 125289.48
C89: =C1 -> Volks | K89: Véhicules usagés | S89: =$S$1 -> Réalisé, Novembre 2023
D91: BUDGET ORIGINAL | J91: RÉALISATION | M91: ÉCART réel / Budget | O91: ANNÉE PRÉCÉDENTE | R91: ECART (réel/ Ann.Préc.)
D92: UNITÉS | E92: $P/UNITÉ | F92: $PROFITS | J92: UNITÉS | K92: $P/UNITE | L92: $PROFITS | M92: UNITÉS | N92: $PROFITS | O92: UNITÉS | P92: $P/UNITE | Q92: $PROFITS | R92: UNITÉS | S92: $PROFITS
A93: Véhicules usagésVentes nettes | B93: Véhicules usagés | C93: Ventes nettes | F93: {=+INDEX('Budget original'!$A$2:$AO$500,MATCH($A93,'Budget original'!$A$2:$A$500,0),MATCH(F$2,'Budget original'!$A$2:$AO$2,0))} -> 1629576.7 | L93: =-SUMIFS(BV_Data_An_Cour!$O:$O,BV_Data_An_Cour!$X:$X,"Oui",BV_Data_An_Cour!$U:$U,$B93) -> 1111062.8 | Q93: =-SUMIFS(BV_Data_An_Prec!$O:$O,BV_Data_An_Prec!$X:$X,"Oui",BV_Data_An_Prec!$U:$U,$B93) -> 1278836.6
A94: Véhicules usagésCertifié | B94: Véhicules usagés | C94: Certifié | D94: {=+INDEX('Budget original'!$A$2:$AO$500,MATCH($A94,'Budget original'!$A$2:$A$500,0),MATCH(D$2,'Budget original'!$A$2:$AO$2,0))} -> 39 | E94: =IF(D94=0,0,F94/D94) -> 1858 | F94: {=+INDEX('Budget original'!$A$2:$AO$500,MATCH($A94,'Budget original'!$A$2:$A$500,0),MATCH(F$2,'Budget original'!$A$2:$AO$2,0))} -> 72462 | J94: =-SUMIFS(BV_Data_An_Cour!$O:$O,BV_Data_An_Cour!$U:$U,$B94,BV_Data_An_Cour!$V:$V,$C94,BV_Data_An_Cour!$W:$W,J$2) -> 16 | K94: =IF(J94=0,0,L94/J94) -> 1359.5375 | L94: =-SUMIFS(BV_Data_An_Cour!$O:$O,BV_Data_An_Cour!$U:$U,$B94,BV_Data_An_Cour!$V:$V,$C94,BV_Data_An_Cour!$W:$W,$L2) -> 21752.6 | M94: =J94-D94 -> -23 | N94: =L94-F94 -> -50709.4 | O94: =-SUMIFS(BV_Data_An_Prec!$O:$O,BV_Data_An_Prec!$U:$U,$B94,BV_Data_An_Prec!$V:$V,$C94,BV_Data_An_Prec!$W:$W,O$2) -> 27 | P94: =IF(O94=0,0,Q94/O94) -> 867.55222 | Q94: =-SUMIFS(BV_Data_An_Prec!$O:$O,BV_Data_An_Prec!$U:$U,$B94,BV_Data_An_Prec!$V:$V,$C94,BV_Data_An_Prec!$W:$W,$L2) -> 23423.91 | R94: =J94-O94 -> -11 | S94: =L94-Q94 -> -1671.31
A95: Véhicules usagésNon Certifié | B95: Véhicules usagés | C95: Non Certifié | D95: {=+INDEX('Budget original'!$A$2:$AO$500,MATCH($A95,'Budget original'!$A$2:$A$500,0),MATCH(D$2,'Budget original'!$A$2:$AO$2,0))} -> 0 | E95: =IF(D95=0,0,F95/D95) -> 0 | F95: {=+INDEX('Budget original'!$A$2:$AO$500,MATCH($A95,'Budget original'!$A$2:$A$500,0),MATCH(F$2,'Budget original'!$A$2:$AO$2,0))} -> 0 | J95: =-SUMIFS(BV_Data_An_Cour!$O:$O,BV_Data_An_Cour!$U:$U,$B95,BV_Data_An_Cour!$V:$V,$C95,BV_Data_An_Cour!$W:$W,J$2) -> 4 | K95: =IF(J95=0,0,L95/J95) -> 817.0175 | L95: =-SUMIFS(BV_Data_An_Cour!$O:$O,BV_Data_An_Cour!$U:$U,$B95,BV_Data_An_Cour!$V:$V,$C95,BV_Data_An_Cour!$W:$W,$L2) -> 3268.07 | M95: =J95-D95 -> 4 | N95: =L95-F95 -> 3268.07 | O95: =-SUMIFS(BV_Data_An_Prec!$O:$O,BV_Data_An_Prec!$U:$U,$B95,BV_Data_An_Prec!$V:$V,$C95,BV_Data_An_Prec!$W:$W,O$2) -> 0 | P95: =IF(O95=0,0,Q95/O95) -> 0 | Q95: =-SUMIFS(BV_Data_An_Prec!$O:$O,BV_Data_An_Prec!$U:$U,$B95,BV_Data_An_Prec!$V:$V,$C95,BV_Data_An_Prec!$W:$W,$L2) -> 0 | R95: =J95-O95 -> 4 | S95: =L95-Q95 -> 3268.07
A96: Véhicules usagésTotal Usagés | B96: Véhicules usagés | C96: Total Usagés | D96: =+D95+D94 -> 39 | E96: =IF(D96=0,0,F96/D96) -> 1858 | F96: =+F94+F95 -> 72462 | J96: =+J94+J95 -> 20 | K96: =IF(J96<=0,0,L96/J96) -> 1251.0335 | L96: =+L94+L95 -> 25020.67 | M96: =J96-D96 -> -19 | N96: =L96-F96 -> -47441.33 | O96: =+O94+O95 -> 27 | P96: =IF(O96<=0,0,Q96/O96) -> 867.55222 | Q96: =+Q94+Q95 -> 23423.91 | R96: =R94+R95 -> -7 | S96: =S94+S95 -> 1596.76
A97: Véhicules usagés | B97: Véhicules usagés | E97: =IF(D97=0,0,F97/D97) -> 0 | M97: =M96/D96 -> -0.48717949 | N97: =N96/F96 -> -0.65470633 | R97: =R96/O96 -> -0.25925926 | S97: =IF(Q96=0,0,(S96/Q96)) -> 0.068167953
A98: Véhicules usagésUS | B98: Véhicules usagés | C98: US
A99: Véhicules usagésVentes au Gros | B99: Véhicules usagés | C99: Ventes au Gros | D99: {=+INDEX('Budget original'!$A$2:$AO$500,MATCH($A99,'Budget original'!$A$2:$A$500,0),MATCH(D$2,'Budget original'!$A$2:$AO$2,0))} -> 33 | E99: =IF(D99=0,0,F99/D99) -> 399 | F99: {=+INDEX('Budget original'!$A$2:$AO$500,MATCH($A99,'Budget original'!$A$2:$A$500,0),MATCH(F$2,'Budget original'!$A$2:$AO$2,0))} -> 13167 | J99: =-SUMIFS(BV_Data_An_Cour!$O:$O,BV_Data_An_Cour!$U:$U,$B99,BV_Data_An_Cour!$V:$V,$C99,BV_Data_An_Cour!$W:$W,J$2) -> 31 | K99: =IF(J99=0,0,L99/J99) -> 15.867742 | L99: =-SUMIFS(BV_Data_An_Cour!$O:$O,BV_Data_An_Cour!$U:$U,$B99,BV_Data_An_Cour!$V:$V,$C99,BV_Data_An_Cour!$W:$W,L$2) -> 491.9 | M99: =J99-D99 -> -2 | N99: =L99-F99 -> -12675.1 | O99: =-SUMIFS(BV_Data_An_Prec!$O:$O,BV_Data_An_Prec!$U:$U,$B99,BV_Data_An_Prec!$V:$V,$C99,BV_Data_An_Prec!$W:$W,O$2) -> 23 | P99: =IF(O99=0,0,Q99/O99) -> 141.49783 | Q99: =-SUMIFS(BV_Data_An_Prec!$O:$O,BV_Data_An_Prec!$U:$U,$B99,BV_Data_An_Prec!$V:$V,$C99,BV_Data_An_Prec!$W:$W,Q$2) -> 3254.45 | R99: =J99-O99 -> 8 | S99: =L99-Q99 -> -2762.55
A100: Véhicules usagés | B100: Véhicules usagés
A101: Véhicules usagésRev. Finances | B101: Véhicules usagés | C101: Rev. Finances | D101: {=+INDEX('Budget original'!$A$2:$AO$500,MATCH($A101,'Budget original'!$A$2:$A$500,0),MATCH(D$2,'Budget original'!$A$2:$AO$2,0))} -> 0 | E101: =IF(D101=0,0,F101/D101) -> 0 | F101: {=+INDEX('Budget original'!$A$2:$AO$500,MATCH($A101,'Budget original'!$A$2:$A$500,0),MATCH(F$2,'Budget original'!$A$2:$AO$2,0))} -> 19500 | K101: =IF(J96=0,0,L101/J96) -> 370.491 | L101: =-SUMIFS(BV_Data_An_Cour!$O:$O,BV_Data_An_Cour!$U:$U,$B101,BV_Data_An_Cour!$V:$V,$C101,BV_Data_An_Cour!$W:$W,$L2) -> 7409.82 | N101: =L101-F101 -> -12090.18 | P101: =IF(O96=0,0,Q101/O96) -> 812.94556 | Q101: =-SUMIFS(BV_Data_An_Prec!$O:$O,BV_Data_An_Prec!$U:$U,$B101,BV_Data_An_Prec!$V:$V,$C101,BV_Data_An_Prec!$W:$W,$L2) -> 21949.53 | R101: =O101-K101 -> -370.491 | S101: =L101-Q101 -> -14539.71
A102: Véhicules usagésRev. Protections | B102: Véhicules usagés | C102: Rev. Protections | D102: {=+INDEX('Budget original'!$A$2:$AO$500,MATCH($A102,'Budget original'!$A$2:$A$500,0),MATCH(D$2,'Budget original'!$A$2:$AO$2,0))} -> 0 | E102: =IF(D102=0,0,F102/D102) -> 0 | F102: {=+INDEX('Budget original'!$A$2:$AO$500,MATCH($A102,'Budget original'!$A$2:$A$500,0),MATCH(F$2,'Budget original'!$A$2:$AO$2,0))} -> 48750 | K102: =IF(J96=0,0,L102/J96) -> 937.1465 | L102: =-SUMIFS(BV_Data_An_Cour!$O:$O,BV_Data_An_Cour!$U:$U,$B102,BV_Data_An_Cour!$V:$V,$C102,BV_Data_An_Cour!$W:$W,$L2) -> 18742.93 | N102: =L102-F102 -> -30007.07 | P102: =IF(O96=0,0,Q102/O96) -> 1070.6704 | Q102: =-SUMIFS(BV_Data_An_Prec!$O:$O,BV_Data_An_Prec!$U:$U,$B102,BV_Data_An_Prec!$V:$V,$C102,BV_Data_An_Prec!$W:$W,$L2) -> 28908.1 | R102: =O102-K102 -> -937.1465 | S102: =L102-Q102 -> -10165.17
A103: Véhicules usagésRev. Autres | B103: Véhicules usagés | C103: Rev. Autres | D103: {=+INDEX('Budget original'!$A$2:$AO$500,MATCH($A103,'Budget original'!$A$2:$A$500,0),MATCH(D$2,'Budget original'!$A$2:$AO$2,0))} -> 0 | E103: =IF(D103=0,0,F103/D103) -> 0 | F103: {=+INDEX('Budget original'!$A$2:$AO$500,MATCH($A103,'Budget original'!$A$2:$A$500,0),MATCH(F$2,'Budget original'!$A$2:$AO$2,0))} -> 13650 | K103: =IF(J96=0,0,L103/J96) -> 19.6975 | L103: =-SUMIFS(BV_Data_An_Cour!$O:$O,BV_Data_An_Cour!$U:$U,$B103,BV_Data_An_Cour!$V:$V,$C103,BV_Data_An_Cour!$W:$W,$L$2) -> 393.95 | N103: =L103-F103 -> -13256.05 | P103: =IF(O96=0,0,Q103/O96) -> 13.477037 | Q103: =-SUMIFS(BV_Data_An_Prec!$O:$O,BV_Data_An_Prec!$U:$U,$B103,BV_Data_An_Prec!$V:$V,$C103,BV_Data_An_Prec!$W:$W,$L$2) -> 363.88 | R103: =O103-K103 -> -19.6975 | S103: =L103-Q103 -> 30.07
A104: Véhicules usagésTotal F&I | B104: Véhicules usagés | C104: Total F&I | D104: =D96 -> 39 | E104: =IF(D104=0,0,F104/D104) -> 2100 | F104: =F101+F102+F103 -> 81900 | J104: =J96 -> 20 | K104: =IF(J104<=0,0,L104/J104) -> 1327.335 | L104: =L101+L102+L103 -> 26546.7 | M104: =J104-D104 -> -19 | N104: =L104-F104 -> -55353.3 | O104: =O96 -> 27 | P104: =IF(O104<=0,0,Q104/O104) -> 1897.093 | Q104: =Q101+Q102+Q103 -> 51221.51 | S104: =L104-Q104 -> -24674.81
...

Sheet Vol & Taux MOIS
B1: Park Avenue Volkswagen - Analyse des écarts "Volume & Taux - Mois courant"
B3: Neufs | C3: Volume # | D3: Marge $ | E3: Brut | G3: Usagés | H3: Volume # | I3: Marge $ | J3: Brut | L3: Service | M3: Volume $ | N3: Marge % | O3: Brut | Q3: Service #B.T. | R3: Volume # | S3: $/B.T. | T3: Ventes
B4: Écart Total | G4: Écart Total | L4: Écart Total | Q4: Écart Total
B5: Réel | C5: =Print_Mois!J27 -> 92 | D5: =Print_Mois!L27/Print_Mois!J27 -> 3367.832 | E5: =+C5*D5 -> 309840.54 | G5: Réel | H5: =Print_Mois!J107 -> 51 | I5: =Print_Mois!L107/Print_Mois!J107 -> 1020.77 | J5: =+H5*I5 -> 52059.27 | L5: Réel | M5: =Print_Mois!K193 -> 408560.41 | N5: =O5/M5 -> 0.71048568 | O5: =Print_Mois!L193 -> 290276.32 | Q5: Réel | R5: =Print_Mois!J184 -> 1458 | S5: =Print_Mois!K184/Print_Mois!J184 -> 261.057 | T5: =+R5*S5 -> 380621.1
B6: Budget | C6: =Print_Mois!G27 -> 0 | D6: =Print_Mois!I27/Print_Mois!G27 -> #DIV/0! | E6: =+C6*D6 -> #DIV/0! | G6: Budget | H6: =Print_Mois!G107 -> 0 | I6: =Print_Mois!I107/Print_Mois!G107 -> #DIV/0! | J6: =+H6*I6 -> #DIV/0! | L6: Budget | M6: =Print_Mois!H193 -> 0 | N6: =O6/M6 -> #DIV/0! | O6: =Print_Mois!I193 -> 0 | Q6: Budget | R6: =Print_Mois!G184 -> 0 | S6: =Print_Mois!H184/Print_Mois!G184 -> #DIV/0! | T6: =+R6*S6 -> #DIV/0!
B7: Écart Total | C7: =+C5-C6 -> 92 | D7: =+D5-D6 -> #DIV/0! | E7: =+E5-E6 -> #DIV/0! | G7: Écart Total | H7: =+H5-H6 -> 51 | I7: =+I5-I6 -> #DIV/0! | J7: =+J5-J6 -> #DIV/0! | L7: Écart Total | M7: =+M5-M6 -> 408560.41 | N7: =+N5-N6 -> #DIV/0! | O7: =+O5-O6 -> 290276.32 | Q7: Écart Total | R7: =+R5-R6 -> 1458 | S7: =+S5-S6 -> #DIV/0! | T7: =+T5-T6 -> #DIV/0!
C8: =+C7/C6 -> #DIV/0! | D8: =+D7/D6 -> #DIV/0! | H8: =+H7/H6 -> #DIV/0! | I8: =+I7/I6 -> #DIV/0! | M8: =+M7/M6 -> #DIV/0! | N8: =+N7/N6 -> #DIV/0! | R8: =+R7/R6 -> #DIV/0! | S8: =+S7/S6 -> #DIV/0!
B9: Écart Marge | G9: Écart Marge | L9: Écart Marge | Q9: Écart $/B.T.
B10: Marge Réelle | C10: =+C5 -> 92 | D10: =+D5 -> 3367.832 | E10: =+C10*D10 -> 309840.54 | G10: Marge Réelle | H10: =+H5 -> 51 | I10: =+I5 -> 1020.77 | J10: =+H10*I10 -> 52059.27 | L10: Marge Réelle | M10: =+M5 -> 408560.41 | N10: =+N5 -> 0.71048568 | O10: =+M10*N10 -> 290276.32 | Q10: $/B.T. Réel | R10: =+R5 -> 1458 | S10: =+S5 -> 261.057 | T10: =+R10*S10 -> 380621.1
B11: Marge Budget | C11: =+C5 -> 92 | D11: =+D6 -> #DIV/0! | E11: =C11*D11 -> #DIV/0! | G11: Marge Budget | H11: =+H5 -> 51 | I11: =+I6 -> #DIV/0! | J11: =H11*I11 -> #DIV/0! | L11: Marge Budget | M11: =+M5 -> 408560.41 | N11: =+N6 -> #DIV/0! | O11: =M11*N11 -> #DIV/0! | Q11: $/B.T. Budget | R11: =+R5 -> 1458 | S11: =+S6 -> #DIV/0! | T11: =R11*S11 -> #DIV/0!
B12: Écart Marge | C12: =+C10-C11 -> 0 | D12: =+D10-D11 -> #DIV/0! | E12: =+E10-E11 -> #DIV/0! | G12: Écart Marge | H12: =+H10-H11 -> 0 | I12: =+I10-I11 -> #DIV/0! | J12: =+J10-J11 -> #DIV/0! | L12: Écart Marge | M12: =+M10-M11 -> 0 | N12: =+N10-N11 -> #DIV/0! | O12: =+O10-O11 -> #DIV/0! | Q12: Écart $/B.T. | R12: =+R10-R11 -> 0 | S12: =+S10-S11 -> #DIV/0! | T12: =+T10-T11 -> #DIV/0!
B14: Écart Volume | G14: Écart Volume | L14: Écart Volume | Q14: Écart Volume
B15: Volume Réel | C15: =+C5 -> 92 | D15: =+D6 -> #DIV/0! | E15: =+C15*D15 -> #DIV/0! | G15: Volume Réel | H15: =+H5 -> 51 | I15: =+I6 -> #DIV/0! | J15: =+H15*I15 -> #DIV/0! | L15: Volume Réel | M15: =+M5 -> 408560.41 | N15: =+N6 -> #DIV/0! | O15: =+M15*N15 -> #DIV/0! | Q15: Volume Réel | R15: =+R5 -> 1458 | S15: =+S6 -> #DIV/0! | T15: =+R15*S15 -> #DIV/0!
B16: Volume Budget | C16: =+C6 -> 0 | D16: =+D6 -> #DIV/0! | E16: =C16*D16 -> #DIV/0! | G16: Volume Budget | H16: =+H6 -> 0 | I16: =+I6 -> #DIV/0! | J16: =H16*I16 -> #DIV/0! | L16: Volume Budget | M16: =+M6 -> 0 | N16: =+N6 -> #DIV/0! | O16: =M16*N16 -> #DIV/0! | Q16: Volume Budget | R16: =+R6 -> 0 | S16: =+S6 -> #DIV/0! | T16: =R16*S16 -> #DIV/0!
B17: Écart Volume | C17: =+C15-C16 -> 92 | D17: =+D15-D16 -> #DIV/0! | E17: =+E15-E16 -> #DIV/0! | G17: Écart Volume | H17: =+H15-H16 -> 51 | I17: =+I15-I16 -> #DIV/0! | J17: =+J15-J16 -> #DIV/0! | L17: Écart Volume | M17: =+M15-M16 -> 408560.41 | N17: =+N15-N16 -> #DIV/0! | O17: =+O15-O16 -> #DIV/0! | Q17: Écart Volume | R17: =+R15-R16 -> 1458 | S17: =+S15-S16 -> #DIV/0! | T17: =+T15-T16 -> #DIV/0!
E18: =+E7-E12-E17 -> #DIV/0! | J18: =+J7-J12-J17 -> #DIV/0! | O18: =+O7-O12-O17 -> #DIV/0! | T18: =+T7-T12-T17 -> #DIV/0!
B19: Variabilité Max-Min | G19: Variabilité Max-Min | L19: Variabilité Max-Min | Q19: Variabilité Max-Min
B20: Max Vol & Marge | C20: =MAX(C5:C6) -> 92 | D20: =MAX(D5:D6) -> #DIV/0! | E20: =+C20*D20 -> #DIV/0! | G20: Max Vol & Marge | H20: =MAX(H5:H6) -> 51 | I20: =MAX(I5:I6) -> #DIV/0! | J20: =+H20*I20 -> #DIV/0! | L20: Max Vol & Marge | M20: =MAX(M5:M6) -> 408560.41 | N20: =MAX(N5:N6) -> #DIV/0! | O20: =+M20*N20 -> #DIV/0! | Q20: Max Vol & Marge | R20: =MAX(R5:R6) -> 1458 | S20: =MAX(S5:S6) -> #DIV/0! | T20: =+R20*S20 -> #DIV/0!
B21: Moyenne | E21: =AVERAGE(E20,E22) -> #DIV/0! | G21: Moyenne | J21: =AVERAGE(J20,J22) -> #DIV/0! | L21: Moyenne | O21: =AVERAGE(O20,O22) -> #DIV/0! | Q21: Moyenne | T21: =AVERAGE(T20,T22) -> #DIV/0!
B22: Min Vol & Marge | C22: =MIN(C5:C6) -> 0 | D22: =MIN(D5:D6) -> #DIV/0! | E22: =+C22*D22 -> #DIV/0! | G22: Min Vol & Marge | H22: =MIN(H5:H6) -> 0 | I22: =MIN(I5:I6) -> #DIV/0! | J22: =+H22*I22 -> #DIV/0! | L22: Min Vol & Marge | M22: =MIN(M5:M6) -> 0 | N22: =MIN(N5:N6) -> #DIV/0! | O22: =+M22*N22 -> #DIV/0! | Q22: Min Vol & Marge | R22: =MIN(R5:R6) -> 0 | S22: =MIN(S5:S6) -> #DIV/0! | T22: =+R22*S22 -> #DIV/0!
B23: Fourchette | C23: =+C20-C22 -> 92 | D23: =+D20-D22 -> #DIV/0! | E23: =+E20-E22 -> #DIV/0! | G23: Fourchette | H23: =+H20-H22 -> 51 | I23: =+I20-I22 -> #DIV/0! | J23: =+J20-J22 -> #DIV/0! | L23: Fourchette | M23: =+M20-M22 -> 408560.41 | N23: =+N20-N22 -> #DIV/0! | O23: =+O20-O22 -> #DIV/0! | Q23: Fourchette | R23: =+R20-R22 -> 1458 | S23: =+S20-S22 -> #DIV/0! | T23: =+T20-T22 -> #DIV/0!
C25: Réel VS Max | E25: =+E5/E20 -> #DIV/0! | H25: Réel VS Max | J25: =+J5/J20 -> #DIV/0! | M25: Réel VS Max | O25: =+O5/O20 -> #DIV/0! | R25: Réel VS Max | T25: =+T5/T20 -> #DIV/0!
C26: Réel VS Moyenne | E26: =+E5/E21 -> #DIV/0! | H26: Réel VS Moyenne | J26: =+J5/J21 -> #DIV/0! | M26: Réel VS Moyenne | O26: =+O5/O21 -> #DIV/0! | R26: Réel VS Moyenne | T26: =+T5/T21 -> #DIV/0!
C27: Réel VS Min | E27: =+E5/E22 -> #DIV/0! | H27: Réel VS Min | J27: =+J5/J22 -> #DIV/0! | M27: Réel VS Min | O27: =+O5/O22 -> #DIV/0! | R27: Réel VS Min | T27: =+T5/T22 -> #DIV/0!
C29: Fourchette Variabilité | E29: =+E27-E25 -> #DIV/0! | H29: Fourchette Variabilité | J29: =+J27-J25 -> #DIV/0! | M29: Fourchette Variabilité | O29: =+O27-O25 -> #DIV/0! | R29: Fourchette Variabilité | T29: =+T27-T25 -> #DIV/0!
B31: Autres Revenus Budgétés non-réalisé | G31: Autres Revenus Budgétés non-réalisé
B32: Holdback | C32: =+C17 -> 92 | D32: =+E32/C32 -> 222.61845 | E32: =+Print_Mois!N78 -> 20480.897
B33: Frais d'Admin. | C33: =+C17 -> 92 | D33: =+E33/C33 -> 181.35221 | E33: =+Print_Mois!N82 -> 16684.404 | G33: Frais d'Admin. | H33: =+H17 -> 51 | I33: =+J33/H33 -> -122.66471 | J33: =+Print_Mois!N158 -> -6255.9
E34: =SUM(E32:E33) -> 37165.301 | J34: =SUM(J32:J33) -> -6255.9

Sheet Print_AAD
C1: =Parametres!B1 -> Volks | K1: Véhicules neufs | S1: =CONCATENATE("Réalisé AAJ,"," ",Parametres!B3," ",Parametres!B4) -> Réalisé AAJ, Novembre 2023
D2: X | E2: O | F2: U | J2: NB | L2: $ | O2: NB | Q2: $ | Z2: U
D3: BUDGET ORIGINAL | J3: RÉALISATION | M3: ÉCART réel / Budget | O3: ANNÉE PRÉCÉDENTE | R3: ECART (réel/ Ann.Préc.) | V3: NEUF | W3: 0.45
D4: UNITÉS | E4: $P/UNITÉ | F4: $PROFITS | J4: UNITÉS | K4: $P/UNITE | L4: $PROFITS | M4: UNITÉS | N4: $PROFITS | O4: UNITÉS | P4: $P/UNITE | Q4: $PROFITS | R4: UNITÉS | S4: $PROFITS | V4: USAGE | W4: 0.1
A5: =+B5&C5 -> Véhicules neufsVentes nettes | B5: =+$K$1 -> Véhicules neufs | C5: Ventes nettes | F5: =+SUMPRODUCT(('Budget original'!$A$8:$A$500=$A5)*('Budget original'!$C$3:$AO$3=F$2),'Budget original'!$C$8:$AO$500) -> 27968314 | L5: =-SUMIFS(BV_Data_An_Cour!$P:$P,BV_Data_An_Cour!$X:$X,"Oui",BV_Data_An_Cour!$U:$U,$B5) -> 27491096 | Q5: =-SUMIFS(BV_Data_An_Prec!$P:$P,BV_Data_An_Prec!$X:$X,"Oui",BV_Data_An_Prec!$U:$U,$B5) -> 25755120 | V5: SERVICE | W5: 0.225
A6: =+B6&C6 -> Véhicules neufsAutos détail | B6: =+$K$1 -> Véhicules neufs | C6: Autos détail | D6: =+SUMPRODUCT(('Budget original'!$A$8:$A$500=$A6)*('Budget original'!$C$3:$AO$3=D$2),'Budget original'!$C$8:$AO$500) -> 119.32 | E6: =IF(D6=0,0,F6/D6) -> 1988.434 | F6: =+SUMPRODUCT(('Budget original'!$A$8:$A$500=$A6)*('Budget original'!$C$3:$AO$3=F$2),'Budget original'!$C$8:$AO$500) -> 237259.94 | J6: =-SUMIFS(BV_Data_An_Cour!$P:$P,BV_Data_An_Cour!$U:$U,$B6,BV_Data_An_Cour!$V:$V,$C6,BV_Data_An_Cour!$W:$W,J$2) -> 148 | K6: =IF(J6=0,0,L6/J6) -> 2090.8759 | L6: =-SUMIFS(BV_Data_An_Cour!$P:$P,BV_Data_An_Cour!$U:$U,$B6,BV_Data_An_Cour!$V:$V,$C6,BV_Data_An_Cour!$W:$W,L$2) -> 309449.63 | M6: =J6-D6 -> 28.68 | N6: =L6-F6 -> 72189.685 | O6: =-SUMIFS(BV_Data_An_Prec!$P:$P,BV_Data_An_Prec!$U:$U,$B6,BV_Data_An_Prec!$V:$V,$C6,BV_Data_An_Prec!$W:$W,O$2) -> 99 | P6: =IF(O6=0,0,Q6/O6) -> 2541.2637 | Q6: =-SUMIFS(BV_Data_An_Prec!$P:$P,BV_Data_An_Prec!$U:$U,$B6,BV_Data_An_Prec!$V:$V,$C6,BV_Data_An_Prec!$W:$W,Q$2) -> 251585.11 | R6: =J6-O6 -> 49 | S6: =L6-Q6 -> 57864.52 | V6: CARROSSERIE | W6: 0.025
A7: =+B7&C7 -> Véhicules neufsCamions détail | B7: =+$K$1 -> Véhicules neufs | C7: Camions détail | D7: =+SUMPRODUCT(('Budget original'!$A$8:$A$500=$A7)*('Budget original'!$C$3:$AO$3=D$2),'Budget original'!$C$8:$AO$500) -> 477.23227 | E7: =IF(D7=0,0,F7/D7) -> 2556.3336 | F7: =+SUMPRODUCT(('Budget original'!$A$8:$A$500=$A7)*('Budget original'!$C$3:$AO$3=F$2),'Budget original'!$C$8:$AO$500) -> 1219964.9 | J7: =-SUMIFS(BV_Data_An_Cour!$P:$P,BV_Data_An_Cour!$U:$U,$B7,BV_Data_An_Cour!$V:$V,$C7,BV_Data_An_Cour!$W:$W,J$2) -> 363 | K7: =IF(J7=0,0,L7/J7) -> 2490.7304 | L7: =-SUMIFS(BV_Data_An_Cour!$P:$P,BV_Data_An_Cour!$U:$U,$B7,BV_Data_An_Cour!$V:$V,$C7,BV_Data_An_Cour!$W:$W,L$2) -> 904135.15 | M7: =J7-D7 -> -114.23227 | N7: =L7-F7 -> -315829.76 | O7: =-SUMIFS(BV_Data_An_Prec!$P:$P,BV_Data_An_Prec!$U:$U,$B7,BV_Data_An_Prec!$V:$V,$C7,BV_Data_An_Prec!$W:$W,O$2) -> 361 | P7: =IF(O7=0,0,Q7/O7) -> 3078.8362 | Q7: =-SUMIFS(BV_Data_An_Prec!$P:$P,BV_Data_An_Prec!$U:$U,$B7,BV_Data_An_Prec!$V:$V,$C7,BV_Data_An_Prec!$W:$W,Q$2) -> 1111459.9 | R7: =J7-O7 -> 2 | S7: =L7-Q7 -> -207324.73 | V7: PIECES | W7: 0.2
A8: =+B8&C8 -> Véhicules neufsSprinter | B8: =+$K$1 -> Véhicules neufs | C8: Sprinter | D8: =+SUMPRODUCT(('Budget original'!$A$8:$A$500=$A8)*('Budget original'!$C$3:$AO$3=D$2),'Budget original'!$C$8:$AO$500) -> 0 | E8: =IF(D8=0,0,F8/D8) -> 0 | F8: =+SUMPRODUCT(('Budget original'!$A$8:$A$500=$A8)*('Budget original'!$C$3:$AO$3=F$2),'Budget original'!$C$8:$AO$500) -> 0 | J8: =-SUMIFS(BV_Data_An_Cour!$P:$P,BV_Data_An_Cour!$U:$U,$B8,BV_Data_An_Cour!$V:$V,$C8,BV_Data_An_Cour!$W:$W,J$2) -> 0 | K8: =IF(J8=0,0,L8/J8) -> 0 | L8: =-SUMIFS(BV_Data_An_Cour!$P:$P,BV_Data_An_Cour!$U:$U,$B8,BV_Data_An_Cour!$V:$V,$C8,BV_Data_An_Cour!$W:$W,L$2) -> 0 | M8: =J8-D8 -> 0 | N8: =L8-F8 -> 0 | O8: =-SUMIFS(BV_Data_An_Prec!$P:$P,BV_Data_An_Prec!$U:$U,$B8,BV_Data_An_Prec!$V:$V,$C8,BV_Data_An_Prec!$W:$W,O$2) -> 0 | P8: =IF(O8=0,0,Q8/O8) -> 0 | Q8: =-SUMIFS(BV_Data_An_Prec!$P:$P,BV_Data_An_Prec!$U:$U,$B8,BV_Data_An_Prec!$V:$V,$C8,BV_Data_An_Prec!$W:$W,Q$2) -> 0 | R8: =J8-O8 -> 0 | S8: =L8-Q8 -> 0 | W8: =SUM(W3:W7) -> 1
A9: =+B9&C9 -> Véhicules neufsMoto détail | B9: =+$K$1 -> Véhicules neufs | C9: Moto détail | D9: =+SUMPRODUCT(('Budget original'!$A$8:$A$500=$A9)*('Budget original'!$C$3:$AO$3=D$2),'Budget original'!$C$8:$AO$500) -> 0 | E9: =IF(D9=0,0,F9/D9) -> 0 | F9: =+SUMPRODUCT(('Budget original'!$A$8:$A$500=$A9)*('Budget original'!$C$3:$AO$3=F$2),'Budget original'!$C$8:$AO$500) -> 0 | J9: =-SUMIFS(BV_Data_An_Cour!$P:$P,BV_Data_An_Cour!$U:$U,$B9,BV_Data_An_Cour!$V:$V,$C9,BV_Data_An_Cour!$W:$W,J$2) -> 0 | K9: =IF(J9=0,0,L9/J9) -> 0 | L9: =-SUMIFS(BV_Data_An_Cour!$P:$P,BV_Data_An_Cour!$U:$U,$B9,BV_Data_An_Cour!$V:$V,$C9,BV_Data_An_Cour!$W:$W,L$2) -> 0 | M9: =J9-D9 -> 0 | N9: =L9-F9 -> 0 | O9: =-SUMIFS(BV_Data_An_Prec!$P:$P,BV_Data_An_Prec!$U:$U,$B9,BV_Data_An_Prec!$V:$V,$C9,BV_Data_An_Prec!$W:$W,O$2) -> 0 | P9: =IF(O9=0,0,Q9/O9) -> 0 | Q9: =-SUMIFS(BV_Data_An_Prec!$P:$P,BV_Data_An_Prec!$U:$U,$B9,BV_Data_An_Prec!$V:$V,$C9,BV_Data_An_Prec!$W:$W,Q$2) -> 0 | R9: =J9-O9 -> 0 | S9: =L9-Q9 -> 0
A10: =+B10&C10 -> Véhicules neufs[...] | B10: =+$K$1 -> Véhicules neufs | C10: [...] | D10: =+SUMPRODUCT(('Budget original'!$A$8:$A$500=$A10)*('Budget original'!$C$3:$AO$3=D$2),'Budget original'!$C$8:$AO$500) -> 0 | E10: =IF(D10=0,0,F10/D10) -> 0 | F10: =+SUMPRODUCT(('Budget original'!$A$8:$A$500=$A10)*('Budget original'!$C$3:$AO$3=F$2),'Budget original'!$C$8:$AO$500) -> 0 | J10: =-SUMIFS(BV_Data_An_Cour!$P:$P,BV_Data_An_Cour!$U:$U,$B10,BV_Data_An_Cour!$V:$V,$C10,BV_Data_An_Cour!$W:$W,J$2) -> 0 | K10: =IF(J10=0,0,L10/J10) -> 0 | L10: =-SUMIFS(BV_Data_An_Cour!$P:$P,BV_Data_An_Cour!$U:$U,$B10,BV_Data_An_Cour!$V:$V,$C10,BV_Data_An_Cour!$W:$W,L$2) -> 0 | M10: =J10-D10 -> 0 | N10: =L10-F10 -> 0 | O10: =-SUMIFS(BV_Data_An_Prec!$P:$P,BV_Data_An_Prec!$U:$U,$B10,BV_Data_An_Prec!$V:$V,$C10,BV_Data_An_Prec!$W:$W,O$2) -> 0 | P10: =IF(O10=0,0,Q10/O10) -> 0 | Q10: =-SUMIFS(BV_Data_An_Prec!$P:$P,BV_Data_An_Prec!$U:$U,$B10,BV_Data_An_Prec!$V:$V,$C10,BV_Data_An_Prec!$W:$W,Q$2) -> 0 | R10: =J10-O10 -> 0 | S10: =L10-Q10 -> 0
A11: =+B11&C11 -> Véhicules neufs[...] | B11: =+$K$1 -> Véhicules neufs | C11: [...] | D11: =+SUMPRODUCT(('Budget original'!$A$8:$A$500=$A11)*('Budget original'!$C$3:$AO$3=D$2),'Budget original'!$C$8:$AO$500) -> 0 | E11: =IF(D11=0,0,F11/D11) -> 0 | F11: =+SUMPRODUCT(('Budget original'!$A$8:$A$500=$A11)*('Budget original'!$C$3:$AO$3=F$2),'Budget original'!$C$8:$AO$500) -> 0 | J11: =-SUMIFS(BV_Data_An_Cour!$P:$P,BV_Data_An_Cour!$U:$U,$B11,BV_Data_An_Cour!$V:$V,$C11,BV_Data_An_Cour!$W:$W,J$2) -> 0 | K11: =IF(J11=0,0,L11/J11) -> 0 | L11: =-SUMIFS(BV_Data_An_Cour!$P:$P,BV_Data_An_Cour!$U:$U,$B11,BV_Data_An_Cour!$V:$V,$C11,BV_Data_An_Cour!$W:$W,L$2) -> 0 | M11: =J11-D11 -> 0 | N11: =L11-F11 -> 0 | O11: =-SUMIFS(BV_Data_An_Prec!$P:$P,BV_Data_An_Prec!$U:$U,$B11,BV_Data_An_Prec!$V:$V,$C11,BV_Data_An_Prec!$W:$W,O$2) -> 0 | P11: =IF(O11=0,0,Q11/O11) -> 0 | Q11: =-SUMIFS(BV_Data_An_Prec!$P:$P,BV_Data_An_Prec!$U:$U,$B11,BV_Data_An_Prec!$V:$V,$C11,BV_Data_An_Prec!$W:$W,Q$2) -> 0 | R11: =J11-O11 -> 0 | S11: =L11-Q11 -> 0
A12: =+B12&C12 -> Véhicules neufs[...] | B12: =+$K$1 -> Véhicules neufs | C12: [...] | D12: =+SUMPRODUCT(('Budget original'!$A$8:$A$500=$A12)*('Budget original'!$C$3:$AO$3=D$2),'Budget original'!$C$8:$AO$500) -> 0 | E12: =IF(D12=0,0,F12/D12) -> 0 | F12: =+SUMPRODUCT(('Budget original'!$A$8:$A$500=$A12)*('Budget original'!$C$3:$AO$3=F$2),'Budget original'!$C$8:$AO$500) -> 0 | J12: =-SUMIFS(BV_Data_An_Cour!$P:$P,BV_Data_An_Cour!$U:$U,$B12,BV_Data_An_Cour!$V:$V,$C12,BV_Data_An_Cour!$W:$W,J$2) -> 0 | K12: =IF(J12=0,0,L12/J12) -> 0 | L12: =-SUMIFS(BV_Data_An_Cour!$P:$P,BV_Data_An_Cour!$U:$U,$B12,BV_Data_An_Cour!$V:$V,$C12,BV_Data_An_Cour!$W:$W,L$2) -> 0 | M12: =J12-D12 -> 0 | N12: =L12-F12 -> 0 | O12: =-SUMIFS(BV_Data_An_Prec!$P:$P,BV_Data_An_Prec!$U:$U,$B12,BV_Data_An_Prec!$V:$V,$C12,BV_Data_An_Prec!$W:$W,O$2) -> 0 | P12: =IF(O12=0,0,Q12/O12) -> 0 | Q12: =-SUMIFS(BV_Data_An_Prec!$P:$P,BV_Data_An_Prec!$U:$U,$B12,BV_Data_An_Prec!$V:$V,$C12,BV_Data_An_Prec!$W:$W,Q$2) -> 0 | R12: =J12-O12 -> 0 | S12: =L12-Q12 -> 0
A13: =+B13&C13 -> Véhicules neufsTotal Neufs | B13: =+$K$1 -> Véhicules neufs | C13: Total Neufs | D13: =+SUM(D6:D12) -> 596.55227 | E13: =IF(D13<=0,0,F13/D13) -> 2442.7446 | F13: =+SUM(F6:F12) -> 1457224.9 | J13: =+SUM(J6:J12) -> 511 | K13: =IF(J13<=0,0,L13/J13) -> 2374.9213 | L13: =+SUM(L6:L12) -> 1213584.8 | M13: =+SUM(M6:M12) -> -85.552272 | N13: =+SUM(N6:N12) -> -243640.07 | O13: =+SUM(O6:O12) -> 460 | P13: =IF(O13<=0,0,Q13/O13) -> 2963.1413 | Q13: =+SUM(Q6:Q12) -> 1363045 | R13: =+SUM(R6:R12) -> 51 | S13: =+SUM(S6:S12) -> -149460.21
A14: =+B14&C14 -> Véhicules neufs | B14: =+$K$1 -> Véhicules neufs | M14: =IF(D13=0,0,M13/D13) -> -0.14341119 | N14: =IF(F13=0,0,N13/F13) -> -0.16719456 | R14: =R13/O13 -> 0.11086957 | S14: =IF(Q13=0,0,(S13/Q13)) -> -0.10965171
A15: =+B15&C15 -> Véhicules neufsEx-Démos et courtoisies | B15: =+$K$1 -> Véhicules neufs | C15: Ex-Démos et courtoisies | D15: =+SUMPRODUCT(('Budget original'!$A$8:$A$500=$A15)*('Budget original'!$C$3:$AO$3=D$2),'Budget original'!$C$8:$AO$500) -> 28.5 | E15: =IF(D15=0,0,F15/D15) -> 2442.5492 | F15: =+SUMPRODUCT(('Budget original'!$A$8:$A$500=$A15)*('Budget original'!$C$3:$AO$3=F$2),'Budget original'!$C$8:$AO$500) -> 69612.652 | J15: =-SUMIFS(BV_Data_An_Cour!$P:$P,BV_Data_An_Cour!$U:$U,$B15,BV_Data_An_Cour!$V:$V,$C15,BV_Data_An_Cour!$W:$W,J$2) -> 41 | K15: =IF(J15=0,0,L15/J15) -> 2426.4859 | L15: =-SUMIFS(BV_Data_An_Cour!$P:$P,BV_Data_An_Cour!$U:$U,$B15,BV_Data_An_Cour!$V:$V,$C15,BV_Data_An_Cour!$W:$W,L$2) -> 99485.92 | M15: =J15-D15 -> 12.5 | N15: =L15-F15 -> 29873.268 | O15: =-SUMIFS(BV_Data_An_Prec!$P:$P,BV_Data_An_Prec!$U:$U,$B15,BV_Data_An_Prec!$V:$V,$C15,BV_Data_An_Prec!$W:$W,O$2) -> 40 | P15: =IF(O15=0,0,Q15/O15) -> 3471.9982 | Q15: =-SUMIFS(BV_Data_An_Prec!$P:$P,BV_Data_An_Prec!$U:$U,$B15,BV_Data_An_Prec!$V:$V,$C15,BV_Data_An_Prec!$W:$W,Q$2) -> 138879.93 | R15: =J15-O15 -> 1 | S15: =L15-Q15 -> -39394.01
A16: =+B16&C16 -> Véhicules neufs | B16: =+$K$1 -> Véhicules neufs
A17: =+B17&C17 -> Véhicules neufsFlottes | B17: =+$K$1 -> Véhicules neufs | C17: Flottes | D17: =+SUMPRODUCT(('Budget original'!$A$8:$A$500=$A17)*('Budget original'!$C$3:$AO$3=D$2),'Budget original'!$C$8:$AO$500) -> 22.8 | E17: =IF(D17=0,0,F17/D17) -> 2442.5492 | F17: =+SUMPRODUCT(('Budget original'!$A$8:$A$500=$A17)*('Budget original'!$C$3:$AO$3=F$2),'Budget original'!$C$8:$AO$500) -> 55690.122 | J17: =-SUMIFS(BV_Data_An_Cour!$P:$P,BV_Data_An_Cour!$U:$U,$B17,BV_Data_An_Cour!$V:$V,$C17,BV_Data_An_Cour!$W:$W,J$2) -> 26 | K17: =IF(J17=0,0,L17/J17) -> 3133.2135 | L17: =-SUMIFS(BV_Data_An_Cour!$P:$P,BV_Data_An_Cour!$U:$U,$B17,BV_Data_An_Cour!$V:$V,$C17,BV_Data_An_Cour!$W:$W,L$2) -> 81463.55 | M17: =J17-D17 -> 3.2 | N17: =L17-F17 -> 25773.428 | O17: =-SUMIFS(BV_Data_An_Prec!$P:$P,BV_Data_An_Prec!$U:$U,$B17,BV_Data_An_Prec!$V:$V,$C17,BV_Data_An_Prec!$W:$W,O$2) -> 17 | P17: =IF(O17=0,0,Q17/O17) -> 2149.7347 | Q17: =-SUMIFS(BV_Data_An_Prec!$P:$P,BV_Data_An_Prec!$U:$U,$B17,BV_Data_An_Prec!$V:$V,$C17,BV_Data_An_Prec!$W:$W,Q$2) -> 36545.49 | R17: =J17-O17 -> 9 | S17: =L17-Q17 -> 44918.06 | V17: Pour Rapport T1 | W17: Budget | X17: Réalisé T1 | Y17: Écart
A18: =+B18&C18 -> Véhicules neufs | B18: =+$K$1 -> Véhicules neufs | V18: Profit Brut Ventes | W18: =+I27+I107 -> 0 | X18: =+L27+L107 -> 3415813.4 | Y18: =+X18-W18 -> 3415813.4
A19: =+B19&C19 -> Véhicules neufsRachat bail | B19: =+$K$1 -> Véhicules neufs | C19: Rachat bail | D19: =+SUMPRODUCT(('Budget original'!$A$8:$A$500=$A19)*('Budget original'!$C$3:$AO$3=D$2),'Budget original'!$C$8:$AO$500) -> 0 | E19: =IF(D19=0,0,F19/D19) -> 0 | F19: =+SUMPRODUCT(('Budget original'!$A$8:$A$500=$A19)*('Budget original'!$C$3:$AO$3=F$2),'Budget original'!$C$8:$AO$500) -> 90240 | L19: =-SUMIFS(BV_Data_An_Cour!$P:$P,BV_Data_An_Cour!$U:$U,$B19,BV_Data_An_Cour!$V:$V,$C19,BV_Data_An_Cour!$W:$W,L$2) -> 93721.46 | N19: =L19-F19 -> 3481.46 | Q19: =-SUMIFS(BV_Data_An_Prec!$P:$P,BV_Data_An_Prec!$U:$U,$B19,BV_Data_An_Prec!$V:$V,$C19,BV_Data_An_Prec!$W:$W,Q$2) -> 136406.62 | R19: =O19-K19 -> 0 | S19: =L19-Q19 -> -42685.16 | V19: Profit Brut Op. Fixes | W19: =+I193+I249+I313 -> 0 | X19: =+L193+L249+L313 -> 3521749.3 | Y19: =+X19-W19 -> 3521749.3
A20: =+B20&C20 -> Véhicules neufs | B20: =+$K$1 -> Véhicules neufs
A21: =+B21&C21 -> Véhicules neufsRev. Finances | B21: =+$K$1 -> Véhicules neufs | C21: Rev. Finances | D21: =+SUMPRODUCT(('Budget original'!$A$8:$A$500=$A21)*('Budget original'!$C$3:$AO$3=D$2),'Budget original'!$C$8:$AO$500) -> 0 | E21: =IF(D21=0,0,F21/D21) -> 0 | F21: =+SUMPRODUCT(('Budget original'!$A$8:$A$500=$A21)*('Budget original'!$C$3:$AO$3=F$2),'Budget original'!$C$8:$AO$500) -> 107508.99 | K21: =IF(J13=0,0,L21/(J13+J15)) -> 144.94266 | L21: =-SUMIFS(BV_Data_An_Cour!$P:$P,BV_Data_An_Cour!$U:$U,$B21,BV_Data_An_Cour!$V:$V,$C21,BV_Data_An_Cour!$W:$W,L$2) -> 80008.35 | N21: =L21-F21 -> -27500.641 | P21: =IF(O13=0,0,Q21/(O13+O15)) -> 215.29744 | Q21: =-SUMIFS(BV_Data_An_Prec!$P:$P,BV_Data_An_Prec!$U:$U,$B21,BV_Data_An_Prec!$V:$V,$C21,BV_Data_An_Prec!$W:$W,Q$2) -> 107648.72 | R21: =O21-K21 -> -144.94266 | S21: =L21-Q21 -> -27640.37
A22: =+B22&C22 -> Véhicules neufsRev. Protections | B22: =+$K$1 -> Véhicules neufs | C22: Rev. Protections | D22: =+SUMPRODUCT(('Budget original'!$A$8:$A$500=$A22)*('Budget original'!$C$3:$AO$3=D$2),'Budget original'!$C$8:$AO$500) -> 0 | E22: =IF(D22=0,0,F22/D22) -> 0 | F22: =+SUMPRODUCT(('Budget original'!$A$8:$A$500=$A22)*('Budget original'!$C$3:$AO$3=F$2),'Budget original'!$C$8:$AO$500) -> 591299.45 | K22: =IF(J13=0,0,L22/(J13+J15)) -> 966.63701 | L22: =-SUMIFS(BV_Data_An_Cour!$P:$P,BV_Data_An_Cour!$U:$U,$B22,BV_Data_An_Cour!$V:$V,$C22,BV_Data_An_Cour!$W:$W,L$2) -> 533583.63 | N22: =L22-F22 -> -57715.819 | P22: =IF(O13=0,0,Q22/(O13+O15)) -> 915.13834 | Q22: =-SUMIFS(BV_Data_An_Prec!$P:$P,BV_Data_An_Prec!$U:$U,$B22,BV_Data_An_Prec!$V:$V,$C22,BV_Data_An_Prec!$W:$W,Q$2) -> 457569.17 | R22: =O22-K22 -> -966.63701 | S22: =L22-Q22 -> 76014.46
A23: =+B23&C23 -> Véhicules neufsRev. Autres | B23: =+$K$1 -> Véhicules neufs | C23: Rev. Autres | D23: =+SUMPRODUCT(('Budget original'!$A$8:$A$500=$A23)*('Budget original'!$C$3:$AO$3=D$2),'Budget original'!$C$8:$AO$500) -> 0 | E23: =IF(D23=0,0,F23/D23) -> 0 | F23: =+SUMPRODUCT(('Budget original'!$A$8:$A$500=$A23)*('Budget original'!$C$3:$AO$3=F$2),'Budget original'!$C$8:$AO$500) -> 18126.516 | K23: =IF(J13=0,0,L23/(J13+J15)) -> 9.5721558 | L23: =-SUMIFS(BV_Data_An_Cour!$P:$P,BV_Data_An_Cour!$U:$U,$B23,BV_Data_An_Cour!$V:$V,$C23,BV_Data_An_Cour!$W:$W,L$2) -> 5283.83 | N23: =L23-F23 -> -12842.686 | P23: =IF(O13=0,0,Q23/(O13+O15)) -> 16.7804 | Q23: =-SUMIFS(BV_Data_An_Prec!$P:$P,BV_Data_An_Prec!$U:$U,$B23,BV_Data_An_Prec!$V:$V,$C23,BV_Data_An_Prec!$W:$W,Q$2) -> 8390.2 | R23: =O23-K23 -> -9.5721558 | S23: =L23-Q23 -> -3106.37
A24: =+B24&C24 -> Véhicules neufsTotal F&I | B24: =+$K$1 -> Véhicules neufs | C24: Total F&I | D24: =+D15+D13 -> 625.05227 | E24: =IF(D24<=0,0,F24/D24) -> 1147 | F24: =F21+F22+F23 -> 716934.96 | J24: =+J15+J13 -> 552 | K24: =IF(J24<=0,0,L24/J24) -> 1121.1518 | L24: =L21+L22+L23 -> 618875.81 | M24: =J24-D24 -> -73.052272 | N24: =L24-F24 -> -98059.146 | O24: =+O15+O13 -> 500 | P24: =IF(O24<=0,0,Q24/O24) -> 1147.2162 | Q24: =Q21+Q22+Q23 -> 573608.09 | S24: =L24-Q24 -> 45267.72
A25: =+B25&C25 -> Véhicules neufs | B25: =+$K$1 -> Véhicules neufs | N25: =IF(N24=0,0,N24/F24) -> -0.13677551 | S25: =IF(Q24=0,0,(S24/Q24)) -> 0.078917506
A26: =+B26&C26 -> Véhicules neufs | B26: =+$K$1 -> Véhicules neufs
A27: =+B27&C27 -> Véhicules neufsTotal Dépt. Neufs | B27: =+$K$1 -> Véhicules neufs | C27: Total Dépt. Neufs | D27: =+D13+D15+D17 -> 647.85227 | E27: =IF(D27<=0,0,F27/D27) -> 3688.6535 | F27: =F13+F17+F24+F19+F15 -> 2389702.6 | J27: =+J13+J15+J17 -> 578 | K27: =IF(J27<=0,0,L27/J27) -> 3645.5563 | L27: =L13+L17+L24+L19+L15 -> 2107131.5 | M27: =J27-D27 -> -69.852272 | N27: =L27-F27 -> -282571.06 | O27: =+O13+O15+O17 -> 517 | P27: =IF(O27<=0,0,Q27/O27) -> 4349.1008 | Q27: =Q13+Q17+Q24+Q19+Q15 -> 2248485.1 | R27: =J27-O27 -> 61 | S27: =L27-Q27 -> -141353.6 | U27: =+S27/R27 -> -2317.2721
A28: =+B28&C28 -> Véhicules neufs | B28: =+$K$1 -> Véhicules neufs | L28: =+L27/F27 -> 0.88175472 | M28: =M27/D27 -> -0.1078213 | N28: =N27/F27 -> -0.11824528 | R28: =R27/O27 -> 0.11798839 | S28: =IF(Q27=0,0,S27/Q27) -> -0.062866149
A29: =+B29&C29 -> Véhicules neufs | B29: =+$K$1 -> Véhicules neufs
A30: =+B30&C30 -> Véhicules neufsDEPENSES | B30: =+$K$1 -> Véhicules neufs | C30: DEPENSES
A31: =+B31&C31 -> Véhicules neufsComm. vendeurs | B31: =+$K$1 -> Véhicules neufs | C31: Comm. vendeurs | D31: =F31/(F13+F15+F17) -> 0.30084289 | E31: =F31/D$24 -> 761.68379 | F31: =+SUMPRODUCT(('Budget original'!$A$8:$A$500=$A31)*('Budget original'!$C$3:$AO$3=F$2),'Budget original'!$C$8:$AO$500) -> 476092.18 | J31: =L31/(L13+L15+L17) -> 0.28289999 | K31: =IF(L31=0,0,L31/J$24) -> 714.69877 | L31: =SUMIFS(BV_Data_An_Cour!$P:$P,BV_Data_An_Cour!$U:$U,$B31,BV_Data_An_Cour!$V:$V,$C31,BV_Data_An_Cour!$W:$W,L$2) -> 394513.72 | N31: =L31-F31 -> -81578.461 | P31: =IF(Q31=0,0,Q31/O$24) -> 921.38408 | Q31: =SUMIFS(BV_Data_An_Prec!$P:$P,BV_Data_An_Prec!$U:$U,$B31,BV_Data_An_Prec!$V:$V,$C31,BV_Data_An_Prec!$W:$W,Q$2) -> 460692.04 | S31: =L31-Q31 -> -66178.32
A32: =+B32&C32 -> Véhicules neufsComm. F&I | B32: =+$K$1 -> Véhicules neufs | C32: Comm. F&I | D32: =F32/F24 -> 0.3 | E32: =F32/D$24 -> 344.1 | F32: =+SUMPRODUCT(('Budget original'!$A$8:$A$500=$A32)*('Budget original'!$C$3:$AO$3=F$2),'Budget original'!$C$8:$AO$500) -> 215080.49 | J32: =L32/L24 -> 0.30657815 | K32: =IF(L32=0,0,L32/J$24) -> 343.72065 | L32: =SUMIFS(BV_Data_An_Cour!$P:$P,BV_Data_An_Cour!$U:$U,$B32,BV_Data_An_Cour!$V:$V,$C32,BV_Data_An_Cour!$W:$W,L$2) -> 189733.8 | N32: =L32-F32 -> -25346.687 | P32: =IF(Q32=0,0,Q32/O$24) -> 393.92868 | Q32: =SUMIFS(BV_Data_An_Prec!$P:$P,BV_Data_An_Prec!$U:$U,$B32,BV_Data_An_Prec!$V:$V,$C32,BV_Data_An_Prec!$W:$W,Q$2) -> 196964.34 | S32: =L32-Q32 -> -7230.54
A33: =+B33&C33 -> Véhicules neufsFrais de livraison | B33: =+$K$1 -> Véhicules neufs | C33: Frais de livraison | E33: =F33/D$24 -> 113.25898 | F33: =+SUMPRODUCT(('Budget original'!$A$8:$A$500=$A33)*('Budget original'!$C$3:$AO$3=F$2),'Budget original'!$C$8:$AO$500) -> 70792.781 | K33: =IF(L33=0,0,L33/J$24) -> 116.19699 | L33: =SUMIFS(BV_Data_An_Cour!$P:$P,BV_Data_An_Cour!$U:$U,$B33,BV_Data_An_Cour!$V:$V,$C33,BV_Data_An_Cour!$W:$W,L$2) -> 64140.74 | N33: =L33-F33 -> -6652.0407 | P33: =IF(Q33=0,0,Q33/O$24) -> 80.32456 | Q33: =SUMIFS(BV_Data_An_Prec!$P:$P,BV_Data_An_Prec!$U:$U,$B33,BV_Data_An_Prec!$V:$V,$C33,BV_Data_An_Prec!$W:$W,Q$2) -> 40162.28 | S33: =L33-Q33 -> 23978.46
A34: =+B34&C34 -> Véhicules neufsService gratuit 1 | B34: =+$K$1 -> Véhicules neufs | C34: Service gratuit 1 | E34: =F34/D$24 -> 5.1177856 | F34: =+SUMPRODUCT(('Budget original'!$A$8:$A$500=$A34)*('Budget original'!$C$3:$AO$3=F$2),'Budget original'!$C$8:$AO$500) -> 3198.8835 | K34: =IF(L34=0,0,L34/J$24) -> 12.45067 | L34: =SUMIFS(BV_Data_An_Cour!$P:$P,BV_Data_An_Cour!$U:$U,$B34,BV_Data_An_Cour!$V:$V,$C34,BV_Data_An_Cour!$W:$W,L$2) -> 6872.77 | N34: =L34-F34 -> 3673.8865 | P34: =IF(Q34=0,0,Q34/O$24) -> 2.11132 | Q34: =SUMIFS(BV_Data_An_Prec!$P:$P,BV_Data_An_Prec!$U:$U,$B34,BV_Data_An_Prec!$V:$V,$C34,BV_Data_An_Prec!$W:$W,Q$2) -> 1055.66 | S34: =L34-Q34 -> 5817.11
A35: =+B35&C35 -> Véhicules neufsEntretien stock | B35: =+$K$1 -> Véhicules neufs | C35: Entretien stock | E35: =F35/D$24 -> 105.01044 | F35: =+SUMPRODUCT(('Budget original'!$A$8:$A$500=$A35)*('Budget original'!$C$3:$AO$3=F$2),'Budget original'!$C$8:$AO$500) -> 65637.016 | K35: =IF(L35=0,0,L35/J$24) -> 80.430906 | L35: =SUMIFS(BV_Data_An_Cour!$P:$P,BV_Data_An_Cour!$U:$U,$B35,BV_Data_An_Cour!$V:$V,$C35,BV_Data_An_Cour!$W:$W,L$2) -> 44397.86 | N35: =L35-F35 -> -21239.156 | P35: =IF(Q35=0,0,Q35/O$24) -> 105.57516 | Q35: =SUMIFS(BV_Data_An_Prec!$P:$P,BV_Data_An_Prec!$U:$U,$B35,BV_Data_An_Prec!$V:$V,$C35,BV_Data_An_Prec!$W:$W,Q$2) -> 52787.58 | S35: =L35-Q35 -> -8389.72
A36: =+B36&C36 -> Véhicules neufsPublicité 1 | B36: =+$K$1 -> Véhicules neufs | C36: Publicité 1 | E36: =F36/D$24 -> 300.75552 | F36: =+SUMPRODUCT(('Budget original'!$A$8:$A$500=$A36)*('Budget original'!$C$3:$AO$3=F$2),'Budget original'!$C$8:$AO$500) -> 187987.92 | K36: =IF(L36=0,0,L36/J$24) -> 96.415 | L36: =SUMIFS(BV_Data_An_Cour!$P:$P,BV_Data_An_Cour!$U:$U,$B36,BV_Data_An_Cour!$V:$V,$C36,BV_Data_An_Cour!$W:$W,L$2) -> 53221.08 | N36: =L36-F36 -> -134766.84 | P36: =IF(Q36=0,0,Q36/O$24) -> 206.12992 | Q36: =SUMIFS(BV_Data_An_Prec!$P:$P,BV_Data_An_Prec!$U:$U,$B36,BV_Data_An_Prec!$V:$V,$C36,BV_Data_An_Prec!$W:$W,Q$2) -> 103064.96 | S36: =L36-Q36 -> -49843.88
A37: =+B37&C37 -> Véhicules neufsIntérêt de gros | B37: =+$K$1 -> Véhicules neufs | C37: Intérêt de gros | E37: =F37/D$24 -> 54.407419 | F37: =+SUMPRODUCT(('Budget original'!$A$8:$A$500=$A37)*('Budget original'!$C$3:$AO$3=F$2),'Budget original'!$C$8:$AO$500) -> 34007.481 | K37: =IF(L37=0,0,L37/J$24) -> 101.60375 | L37: =SUMIFS(BV_Data_An_Cour!$P:$P,BV_Data_An_Cour!$U:$U,$B37,BV_Data_An_Cour!$V:$V,$C37,BV_Data_An_Cour!$W:$W,L$2) -> 56085.27 | N37: =L37-F37 -> 22077.789 | P37: =IF(Q37=0,0,Q37/O$24) -> 40.63 | Q37: =SUMIFS(BV_Data_An_Prec!$P:$P,BV_Data_An_Prec!$U:$U,$B37,BV_Data_An_Prec!$V:$V,$C37,BV_Data_An_Prec!$W:$W,Q$2) -> 20315 | S37: =L37-Q37 -> 35770.27
A38: =+B38&C38 -> Véhicules neufs[...] | B38: =+$K$1 -> Véhicules neufs | C38: [...] | E38: =F38/D$24 -> 0 | F38: =+SUMPRODUCT(('Budget original'!$A$8:$A$500=$A38)*('Budget original'!$C$3:$AO$3=F$2),'Budget original'!$C$8:$AO$500) -> 0 | K38: =IF(L38=0,0,L38/J$24) -> 0 | L38: =SUMIFS(BV_Data_An_Cour!$P:$P,BV_Data_An_Cour!$U:$U,$B38,BV_Data_An_Cour!$V:$V,$C38,BV_Data_An_Cour!$W:$W,L$2) -> 0 | N38: =L38-F38 -> 0 | P38: =IF(Q38=0,0,Q38/O$24) -> 0 | Q38: =SUMIFS(BV_Data_An_Prec!$P:$P,BV_Data_An_Prec!$U:$U,$B38,BV_Data_An_Prec!$V:$V,$C38,BV_Data_An_Prec!$W:$W,Q$2) -> 0 | S38: =L38-Q38 -> 0
A39: =+B39&C39 -> Véhicules neufs[...] | B39: =+$K$1 -> Véhicules neufs | C39: [...] | E39: =F39/D$24 -> 0 | F39: =+SUMPRODUCT(('Budget original'!$A$8:$A$500=$A39)*('Budget original'!$C$3:$AO$3=F$2),'Budget original'!$C$8:$AO$500) -> 0 | K39: =IF(L39=0,0,L39/J$24) -> 0 | L39: =SUMIFS(BV_Data_An_Cour!$P:$P,BV_Data_An_Cour!$U:$U,$B39,BV_Data_An_Cour!$V:$V,$C39,BV_Data_An_Cour!$W:$W,L$2) -> 0 | N39: =L39-F39 -> 0 | P39: =IF(Q39=0,0,Q39/O$24) -> 0 | Q39: =SUMIFS(BV_Data_An_Prec!$P:$P,BV_Data_An_Prec!$U:$U,$B39,BV_Data_An_Prec!$V:$V,$C39,BV_Data_An_Prec!$W:$W,Q$2) -> 0 | S39: =L39-Q39 -> 0
A40: =+B40&C40 -> Véhicules neufs[...] | B40: =+$K$1 -> Véhicules neufs | C40: [...] | E40: =F40/D$24 -> 0 | F40: =+SUMPRODUCT(('Budget original'!$A$8:$A$500=$A40)*('Budget original'!$C$3:$AO$3=F$2),'Budget original'!$C$8:$AO$500) -> 0 | K40: =IF(L40=0,0,L40/J$24) -> 0 | L40: =SUMIFS(BV_Data_An_Cour!$P:$P,BV_Data_An_Cour!$U:$U,$B40,BV_Data_An_Cour!$V:$V,$C40,BV_Data_An_Cour!$W:$W,L$2) -> 0 | N40: =L40-F40 -> 0 | P40: =IF(Q40=0,0,Q40/O$24) -> 0 | Q40: =SUMIFS(BV_Data_An_Prec!$P:$P,BV_Data_An_Prec!$U:$U,$B40,BV_Data_An_Prec!$V:$V,$C40,BV_Data_An_Prec!$W:$W,Q$2) -> 0 | S40: =L40-Q40 -> 0
A41: =+B41&C41 -> Véhicules neufsTOTAL VARIABLES | B41: =+$K$1 -> Véhicules neufs | C41: TOTAL VARIABLES | D41: % brut | E41: =F41/F$27 -> 0.44055556 | F41: =SUM(F31:F40) -> 1052796.8 | J41: % brut | K41: =L41/L$27 -> 0.38391777 | L41: =SUM(L31:L40) -> 808965.24 | N41: =L41-F41 -> -243831.51 | O41: % brut | P41: =Q41/Q$27 -> 0.38916951 | Q41: =SUM(Q31:Q40) -> 875041.86 | S41: =L41-Q41 -> -66076.62 | U41: =H41/K41 -> 0
A42: =+B42&C42 -> Véhicules neufsSalaires cadres | B42: =+$K$1 -> Véhicules neufs | C42: Salaires cadres | F42: =+SUMPRODUCT(('Budget original'!$A$8:$A$500=$A42)*('Budget original'!$C$3:$AO$3=F$2),'Budget original'!$C$8:$AO$500) -> 188036.25 | L42: =SUMIFS(BV_Data_An_Cour!$P:$P,BV_Data_An_Cour!$U:$U,$B42,BV_Data_An_Cour!$V:$V,$C42,BV_Data_An_Cour!$W:$W,L$2) -> 149801.61 | N42: =L42-F42 -> -38234.641 | Q42: =SUMIFS(BV_Data_An_Prec!$P:$P,BV_Data_An_Prec!$U:$U,$B42,BV_Data_An_Prec!$V:$V,$C42,BV_Data_An_Prec!$W:$W,Q$2) -> 165503.77
A43: =+B43&C43 -> Véhicules neufsSalaires commis | B43: =+$K$1 -> Véhicules neufs | C43: Salaires commis | F43: =+SUMPRODUCT(('Budget original'!$A$8:$A$500=$A43)*('Budget original'!$C$3:$AO$3=F$2),'Budget original'!$C$8:$AO$500) -> 110652.89 | L43: =SUMIFS(BV_Data_An_Cour!$P:$P,BV_Data_An_Cour!$U:$U,$B43,BV_Data_An_Cour!$V:$V,$C43,BV_Data_An_Cour!$W:$W,L$2) -> 133044.91 | N43: =L43-F43 -> 22392.016 | Q43: =SUMIFS(BV_Data_An_Prec!$P:$P,BV_Data_An_Prec!$U:$U,$B43,BV_Data_An_Prec!$V:$V,$C43,BV_Data_An_Prec!$W:$W,Q$2) -> 85532.85 | S43: =L43-Q43 -> 47512.06
A44: =+B44&C44 -> Véhicules neufsSalaires autres | B44: =+$K$1 -> Véhicules neufs | C44: Salaires autres | F44: =+SUMPRODUCT(('Budget original'!$A$8:$A$500=$A44)*('Budget original'!$C$3:$AO$3=F$2),'Budget original'!$C$8:$AO$500) -> 88806.28 | L44: =SUMIFS(BV_Data_An_Cour!$P:$P,BV_Data_An_Cour!$U:$U,$B44,BV_Data_An_Cour!$V:$V,$C44,BV_Data_An_Cour!$W:$W,L$2) -> 110641.16 | N44: =L44-F44 -> 21834.88 | Q44: =SUMIFS(BV_Data_An_Prec!$P:$P,BV_Data_An_Prec!$U:$U,$B44,BV_Data_An_Prec!$V:$V,$C44,BV_Data_An_Prec!$W:$W,Q$2) -> 45852.26 | S44: =L44-Q44 -> 64788.9
A45: =+B45&C45 -> Véhicules neufsSalaires spécialistes | B45: =+$K$1 -> Véhicules neufs | C45: Salaires spécialistes | F45: =+SUMPRODUCT(('Budget original'!$A$8:$A$500=$A45)*('Budget original'!$C$3:$AO$3=F$2),'Budget original'!$C$8:$AO$500) -> 0 | L45: =SUMIFS(BV_Data_An_Cour!$P:$P,BV_Data_An_Cour!$U:$U,$B45,BV_Data_An_Cour!$V:$V,$C45,BV_Data_An_Cour!$W:$W,L$2) -> 0 | N45: =L45-F45 -> 0 | Q45: =SUMIFS(BV_Data_An_Prec!$P:$P,BV_Data_An_Prec!$U:$U,$B45,BV_Data_An_Prec!$V:$V,$C45,BV_Data_An_Prec!$W:$W,Q$2) -> 0 | S45: =L45-Q45 -> 0
A46: =+B46&C46 -> Véhicules neufs[...] | B46: =+$K$1 -> Véhicules neufs | C46: [...] | F46: =+SUMPRODUCT(('Budget original'!$A$8:$A$500=$A46)*('Budget original'!$C$3:$AO$3=F$2),'Budget original'!$C$8:$AO$500) -> 0 | L46: =SUMIFS(BV_Data_An_Cour!$P:$P,BV_Data_An_Cour!$U:$U,$B46,BV_Data_An_Cour!$V:$V,$C46,BV_Data_An_Cour!$W:$W,L$2) -> 0 | N46: =L46-F46 -> 0 | Q46: =SUMIFS(BV_Data_An_Prec!$P:$P,BV_Data_An_Prec!$U:$U,$B46,BV_Data_An_Prec!$V:$V,$C46,BV_Data_An_Prec!$W:$W,Q$2) -> 0 | S46: =L46-Q46 -> 0
A47: =+B47&C47 -> Véhicules neufs[...] | B47: =+$K$1 -> Véhicules neufs | C47: [...] | F47: =+SUMPRODUCT(('Budget original'!$A$8:$A$500=$A47)*('Budget original'!$C$3:$AO$3=F$2),'Budget original'!$C$8:$AO$500) -> 0 | L47: =SUMIFS(BV_Data_An_Cour!$P:$P,BV_Data_An_Cour!$U:$U,$B47,BV_Data_An_Cour!$V:$V,$C47,BV_Data_An_Cour!$W:$W,L$2) -> 0 | N47: =L47-F47 -> 0 | Q47: =SUMIFS(BV_Data_An_Prec!$P:$P,BV_Data_An_Prec!$U:$U,$B47,BV_Data_An_Prec!$V:$V,$C47,BV_Data_An_Prec!$W:$W,Q$2) -> 0 | S47: =L47-Q47 -> 0
A48: =+B48&C48 -> Véhicules neufs[...] | B48: =+$K$1 -> Véhicules neufs | C48: [...] | F48: =+SUMPRODUCT(('Budget original'!$A$8:$A$500=$A48)*('Budget original'!$C$3:$AO$3=F$2),'Budget original'!$C$8:$AO$500) -> 0 | L48: =SUMIFS(BV_Data_An_Cour!$P:$P,BV_Data_An_Cour!$U:$U,$B48,BV_Data_An_Cour!$V:$V,$C48,BV_Data_An_Cour!$W:$W,L$2) -> 0 | N48: =L48-F48 -> 0 | Q48: =SUMIFS(BV_Data_An_Prec!$P:$P,BV_Data_An_Prec!$U:$U,$B48,BV_Data_An_Prec!$V:$V,$C48,BV_Data_An_Prec!$W:$W,Q$2) -> 0 | S48: =L48-Q48 -> 0
A49: =+B49&C49 -> Véhicules neufsSalaires en absences | B49: =+$K$1 -> Véhicules neufs | C49: Salaires en absences | F49: =+SUMPRODUCT(('Budget original'!$A$8:$A$500=$A49)*('Budget original'!$C$3:$AO$3=F$2),'Budget original'!$C$8:$AO$500) -> 130428.24 | L49: =SUMIFS(BV_Data_An_Cour!$P:$P,BV_Data_An_Cour!$U:$U,$B49,BV_Data_An_Cour!$V:$V,$C49,BV_Data_An_Cour!$W:$W,L$2) -> 116902.09 | N49: =L49-F49 -> -13526.149 | Q49: =SUMIFS(BV_Data_An_Prec!$P:$P,BV_Data_An_Prec!$U:$U,$B49,BV_Data_An_Prec!$V:$V,$C49,BV_Data_An_Prec!$W:$W,Q$2) -> 152615.57 | S49: =L49-Q49 -> -35713.48
A50: =+B50&C50 -> Véhicules neufsDéduction à la source | B50: =+$K$1 -> Véhicules neufs | C50: Déduction à la source | F50: =+SUMPRODUCT(('Budget original'!$A$8:$A$500=$A50)*('Budget original'!$C$3:$AO$3=F$2),'Budget original'!$C$8:$AO$500) -> 129658.51 | L50: =SUMIFS(BV_Data_An_Cour!$P:$P,BV_Data_An_Cour!$U:$U,$B50,BV_Data_An_Cour!$V:$V,$C50,BV_Data_An_Cour!$W:$W,L$2) -> 144637.35 | N50: =L50-F50 -> 14978.839 | Q50: =SUMIFS(BV_Data_An_Prec!$P:$P,BV_Data_An_Prec!$U:$U,$B50,BV_Data_An_Prec!$V:$V,$C50,BV_Data_An_Prec!$W:$W,Q$2) -> 175165.9 | S50: =L50-Q50 -> -30528.55 | U50: =L50-Print_Mois!L50 -> 133271.95
A51: =+B51&C51 -> Véhicules neufsBénéfices marginaux | B51: =+$K$1 -> Véhicules neufs | C51: Bénéfices marginaux | F51: =+SUMPRODUCT(('Budget original'!$A$8:$A$500=$A51)*('Budget original'!$C$3:$AO$3=F$2),'Budget original'!$C$8:$AO$500) -> 90794.414 | L51: =SUMIFS(BV_Data_An_Cour!$P:$P,BV_Data_An_Cour!$U:$U,$B51,BV_Data_An_Cour!$V:$V,$C51,BV_Data_An_Cour!$W:$W,L$2) -> 70564.22 | N51: =L51-F51 -> -20230.194 | Q51: =SUMIFS(BV_Data_An_Prec!$P:$P,BV_Data_An_Prec!$U:$U,$B51,BV_Data_An_Prec!$V:$V,$C51,BV_Data_An_Prec!$W:$W,Q$2) -> 69862.69 | S51: =L51-Q51 -> 701.53 | U51: =L51-Print_Mois!L51 -> 64180.41
A52: =+B52&C52 -> Véhicules neufsCsst | B52: =+$K$1 -> Véhicules neufs | C52: Csst | F52: =+SUMPRODUCT(('Budget original'!$A$8:$A$500=$A52)*('Budget original'!$C$3:$AO$3=F$2),'Budget original'!$C$8:$AO$500) -> 43375.109 | L52: =SUMIFS(BV_Data_An_Cour!$P:$P,BV_Data_An_Cour!$U:$U,$B52,BV_Data_An_Cour!$V:$V,$C52,BV_Data_An_Cour!$W:$W,L$2) -> 23379.41 | N52: =L52-F52 -> -19995.699 | Q52: =SUMIFS(BV_Data_An_Prec!$P:$P,BV_Data_An_Prec!$U:$U,$B52,BV_Data_An_Prec!$V:$V,$C52,BV_Data_An_Prec!$W:$W,Q$2) -> 33970.05 | S52: =L52-Q52 -> -10590.64 | U52: =L52-Print_Mois!L52 -> 22214.45
A53: =+B53&C53 -> Véhicules neufs[...] | B53: =+$K$1 -> Véhicules neufs | C53: [...] | F53: =+SUMPRODUCT(('Budget original'!$A$8:$A$500=$A53)*('Budget original'!$C$3:$AO$3=F$2),'Budget original'!$C$8:$AO$500) -> 0 | L53: =SUMIFS(BV_Data_An_Cour!$P:$P,BV_Data_An_Cour!$U:$U,$B53,BV_Data_An_Cour!$V:$V,$C53,BV_Data_An_Cour!$W:$W,L$2) -> 0 | N53: =L53-F53 -> 0 | Q53: =SUMIFS(BV_Data_An_Prec!$P:$P,BV_Data_An_Prec!$U:$U,$B53,BV_Data_An_Prec!$V:$V,$C53,BV_Data_An_Prec!$W:$W,Q$2) -> 0 | S53: =L53-Q53 -> 0
A54: =+B54&C54 -> Véhicules neufsTOTAL PERSONNEL | B54: =+$K$1 -> Véhicules neufs | C54: TOTAL PERSONNEL | D54: % brut | E54: =F54/F$27 -> 0.32713347 | F54: =+SUM(F42:F53) -> 781751.7 | J54: % brut | K54: =L54/L$27 -> 0.35544566 | L54: =+SUM(L42:L53) -> 748970.75 | N54: =+SUM(N42:N53) -> -32780.947 | O54: % brut | P54: =Q54/Q$27 -> 0.32399729 | Q54: =+SUM(Q42:Q53) -> 728503.09 | S54: =+SUM(S42:S53) -> 36169.82
A55: =+B55&C55 -> Véhicules neufsPublicité 2 | B55: =+$K$1 -> Véhicules neufs | C55: Publicité 2 | F55: =+SUMPRODUCT(('Budget original'!$A$8:$A$500=$A55)*('Budget original'!$C$3:$AO$3=F$2),'Budget original'!$C$8:$AO$500) -> 0 | L55: =SUMIFS(BV_Data_An_Cour!$P:$P,BV_Data_An_Cour!$U:$U,$B55,BV_Data_An_Cour!$V:$V,$C55,BV_Data_An_Cour!$W:$W,L$2) -> 0 | N55: =L55-F55 -> 0 | Q55: =SUMIFS(BV_Data_An_Prec!$P:$P,BV_Data_An_Prec!$U:$U,$B55,BV_Data_An_Prec!$V:$V,$C55,BV_Data_An_Prec!$W:$W,Q$2) -> 0 | S55: =L55-Q55 -> 0
A56: =+B56&C56 -> Véhicules neufsService gratuit 2 | B56: =+$K$1 -> Véhicules neufs | C56: Service gratuit 2 | F56: =+SUMPRODUCT(('Budget original'!$A$8:$A$500=$A56)*('Budget original'!$C$3:$AO$3=F$2),'Budget original'!$C$8:$AO$500) -> 0 | L56: =SUMIFS(BV_Data_An_Cour!$P:$P,BV_Data_An_Cour!$U:$U,$B56,BV_Data_An_Cour!$V:$V,$C56,BV_Data_An_Cour!$W:$W,L$2) -> 0 | N56: =L56-F56 -> 0 | Q56: =SUMIFS(BV_Data_An_Prec!$P:$P,BV_Data_An_Prec!$U:$U,$B56,BV_Data_An_Prec!$V:$V,$C56,BV_Data_An_Prec!$W:$W,Q$2) -> 0 | S56: =L56-Q56 -> 0
A57: =+B57&C57 -> Véhicules neufsFrais véhicules de cie | B57: =+$K$1 -> Véhicules neufs | C57: Frais véhicules de cie | F57: =+SUMPRODUCT(('Budget original'!$A$8:$A$500=$A57)*('Budget original'!$C$3:$AO$3=F$2),'Budget original'!$C$8:$AO$500) -> 87404.167 | L57: =SUMIFS(BV_Data_An_Cour!$P:$P,BV_Data_An_Cour!$U:$U,$B57,BV_Data_An_Cour!$V:$V,$C57,BV_Data_An_Cour!$W:$W,L$2) -> 74217.68 | N57: =L57-F57 -> -13186.487 | Q57: =SUMIFS(BV_Data_An_Prec!$P:$P,BV_Data_An_Prec!$U:$U,$B57,BV_Data_An_Prec!$V:$V,$C57,BV_Data_An_Prec!$W:$W,Q$2) -> 91428.6 | S57: =L57-Q57 -> -17210.92
A58: =+B58&C58 -> Véhicules neufsInformatique | B58: =+$K$1 -> Véhicules neufs | C58: Informatique | F58: =+SUMPRODUCT(('Budget original'!$A$8:$A$500=$A58)*('Budget original'!$C$3:$AO$3=F$2),'Budget original'!$C$8:$AO$500) -> 68869.489 | L58: =SUMIFS(BV_Data_An_Cour!$P:$P,BV_Data_An_Cour!$U:$U,$B58,BV_Data_An_Cour!$V:$V,$C58,BV_Data_An_Cour!$W:$W,L$2) -> 78409.06 | N58: =L58-F58 -> 9539.5708 | Q58: =SUMIFS(BV_Data_An_Prec!$P:$P,BV_Data_An_Prec!$U:$U,$B58,BV_Data_An_Prec!$V:$V,$C58,BV_Data_An_Prec!$W:$W,Q$2) -> 83241.56 | S58: =L58-Q58 -> -4832.5
A59: =+B59&C59 -> Véhicules neufsFrais de déplacement | B59: =+$K$1 -> Véhicules neufs | C59: Frais de déplacement | F59: =+SUMPRODUCT(('Budget original'!$A$8:$A$500=$A59)*('Budget original'!$C$3:$AO$3=F$2),'Budget original'!$C$8:$AO$500) -> 11000.968 | L59: =SUMIFS(BV_Data_An_Cour!$P:$P,BV_Data_An_Cour!$U:$U,$B59,BV_Data_An_Cour!$V:$V,$C59,BV_Data_An_Cour!$W:$W,L$2) -> 16914.63 | N59: =L59-F59 -> 5913.6615 | Q59: =SUMIFS(BV_Data_An_Prec!$P:$P,BV_Data_An_Prec!$U:$U,$B59,BV_Data_An_Prec!$V:$V,$C59,BV_Data_An_Prec!$W:$W,Q$2) -> 12492.64 | S59: =L59-Q59 -> 4421.99
A60: =+B60&C60 -> Véhicules neufsServices extérieurs | B60: =+$K$1 -> Véhicules neufs | C60: Services extérieurs | F60: =+SUMPRODUCT(('Budget original'!$A$8:$A$500=$A60)*('Budget original'!$C$3:$AO$3=F$2),'Budget original'!$C$8:$AO$500) -> 74340.932 | L60: =SUMIFS(BV_Data_An_Cour!$P:$P,BV_Data_An_Cour!$U:$U,$B60,BV_Data_An_Cour!$V:$V,$C60,BV_Data_An_Cour!$W:$W,L$2) -> 74286.16 | N60: =L60-F60 -> -54.772036 | Q60: =SUMIFS(BV_Data_An_Prec!$P:$P,BV_Data_An_Prec!$U:$U,$B60,BV_Data_An_Prec!$V:$V,$C60,BV_Data_An_Prec!$W:$W,Q$2) -> 74595.07 | S60: =L60-Q60 -> -308.91
A61: =+B61&C61 -> Véhicules neufsFournitures autres | B61: =+$K$1 -> Véhicules neufs | C61: Fournitures autres | F61: =+SUMPRODUCT(('Budget original'!$A$8:$A$500=$A61)*('Budget original'!$C$3:$AO$3=F$2),'Budget original'!$C$8:$AO$500) -> 1407.1645 | L61: =SUMIFS(BV_Data_An_Cour!$P:$P,BV_Data_An_Cour!$U:$U,$B61,BV_Data_An_Cour!$V:$V,$C61,BV_Data_An_Cour!$W:$W,L$2) -> 399.66 | N61: =L61-F61 -> -1007.5045 | Q61: =SUMIFS(BV_Data_An_Prec!$P:$P,BV_Data_An_Prec!$U:$U,$B61,BV_Data_An_Prec!$V:$V,$C61,BV_Data_An_Prec!$W:$W,Q$2) -> 339.81 | S61: =L61-Q61 -> 59.85
A62: =+B62&C62 -> Véhicules neufsUniformes | B62: =+$K$1 -> Véhicules neufs | C62: Uniformes | F62: =+SUMPRODUCT(('Budget original'!$A$8:$A$500=$A62)*('Budget original'!$C$3:$AO$3=F$2),'Budget original'!$C$8:$AO$500) -> 726.6437 | L62: =SUMIFS(BV_Data_An_Cour!$P:$P,BV_Data_An_Cour!$U:$U,$B62,BV_Data_An_Cour!$V:$V,$C62,BV_Data_An_Cour!$W:$W,L$2) -> 0 | N62: =L62-F62 -> -726.6437 | Q62: =SUMIFS(BV_Data_An_Prec!$P:$P,BV_Data_An_Prec!$U:$U,$B62,BV_Data_An_Prec!$V:$V,$C62,BV_Data_An_Prec!$W:$W,Q$2) -> 113.99 | S62: =L62-Q62 -> -113.99
A63: =+B63&C63 -> Véhicules neufsPapeterie | B63: =+$K$1 -> Véhicules neufs | C63: Papeterie | F63: =+SUMPRODUCT(('Budget original'!$A$8:$A$500=$A63)*('Budget original'!$C$3:$AO$3=F$2),'Budget original'!$C$8:$AO$500) -> 8397.9614 | L63: =SUMIFS(BV_Data_An_Cour!$P:$P,BV_Data_An_Cour!$U:$U,$B63,BV_Data_An_Cour!$V:$V,$C63,BV_Data_An_Cour!$W:$W,L$2) -> 8950.8 | N63: =L63-F63 -> 552.83861 | Q63: =SUMIFS(BV_Data_An_Prec!$P:$P,BV_Data_An_Prec!$U:$U,$B63,BV_Data_An_Prec!$V:$V,$C63,BV_Data_An_Prec!$W:$W,Q$2) -> 7650.15 | S63: =L63-Q63 -> 1300.65
A64: =+B64&C64 -> Véhicules neufsTéléphone | B64: =+$K$1 -> Véhicules neufs | C64: Téléphone | F64: =+SUMPRODUCT(('Budget original'!$A$8:$A$500=$A64)*('Budget original'!$C$3:$AO$3=F$2),'Budget original'!$C$8:$AO$500) -> 2845.9228 | L64: =SUMIFS(BV_Data_An_Cour!$P:$P,BV_Data_An_Cour!$U:$U,$B64,BV_Data_An_Cour!$V:$V,$C64,BV_Data_An_Cour!$W:$W,L$2) -> 3483.73 | N64: =L64-F64 -> 637.80725 | Q64: =SUMIFS(BV_Data_An_Prec!$P:$P,BV_Data_An_Prec!$U:$U,$B64,BV_Data_An_Prec!$V:$V,$C64,BV_Data_An_Prec!$W:$W,Q$2) -> 2959.06 | S64: =L64-Q64 -> 524.67
A65: =+B65&C65 -> Véhicules neufsFrais postaux | B65: =+$K$1 -> Véhicules neufs | C65: Frais postaux | F65: =+SUMPRODUCT(('Budget original'!$A$8:$A$500=$A65)*('Budget original'!$C$3:$AO$3=F$2),'Budget original'!$C$8:$AO$500) -> 1361.1872 | L65: =SUMIFS(BV_Data_An_Cour!$P:$P,BV_Data_An_Cour!$U:$U,$B65,BV_Data_An_Cour!$V:$V,$C65,BV_Data_An_Cour!$W:$W,L$2) -> 1392.24 | N65: =L65-F65 -> 31.052768 | Q65: =SUMIFS(BV_Data_An_Prec!$P:$P,BV_Data_An_Prec!$U:$U,$B65,BV_Data_An_Prec!$V:$V,$C65,BV_Data_An_Prec!$W:$W,Q$2) -> 1572.14 | S65: =L65-Q65 -> -179.9
A66: =+B66&C66 -> Véhicules neufsDivers | B66: =+$K$1 -> Véhicules neufs | C66: Divers | F66: =+SUMPRODUCT(('Budget original'!$A$8:$A$500=$A66)*('Budget original'!$C$3:$AO$3=F$2),'Budget original'!$C$8:$AO$500) -> 5172.006 | L66: =SUMIFS(BV_Data_An_Cour!$P:$P,BV_Data_An_Cour!$U:$U,$B66,BV_Data_An_Cour!$V:$V,$C66,BV_Data_An_Cour!$W:$W,L$2) -> 1865.04 | N66: =L66-F66 -> -3306.966 | Q66: =SUMIFS(BV_Data_An_Prec!$P:$P,BV_Data_An_Prec!$U:$U,$B66,BV_Data_An_Prec!$V:$V,$C66,BV_Data_An_Prec!$W:$W,Q$2) -> 2931.35 | S66: =L66-Q66 -> -1066.31
A67: =+B67&C67 -> Véhicules neufsFormation | B67: =+$K$1 -> Véhicules neufs | C67: Formation | F67: =+SUMPRODUCT(('Budget original'!$A$8:$A$500=$A67)*('Budget original'!$C$3:$AO$3=F$2),'Budget original'!$C$8:$AO$500) -> 6740.1433 | L67: =SUMIFS(BV_Data_An_Cour!$P:$P,BV_Data_An_Cour!$U:$U,$B67,BV_Data_An_Cour!$V:$V,$C67,BV_Data_An_Cour!$W:$W,L$2) -> 21134.26 | N67: =L67-F67 -> 14394.117 | Q67: =SUMIFS(BV_Data_An_Prec!$P:$P,BV_Data_An_Prec!$U:$U,$B67,BV_Data_An_Prec!$V:$V,$C67,BV_Data_An_Prec!$W:$W,Q$2) -> 13726.62 | S67: =L67-Q67 -> 7407.64
A68: =+B68&C68 -> Véhicules neufsFrais bancaires | B68: =+$K$1 -> Véhicules neufs | C68: Frais bancaires | F68: =+SUMPRODUCT(('Budget original'!$A$8:$A$500=$A68)*('Budget original'!$C$3:$AO$3=F$2),'Budget original'!$C$8:$AO$500) -> 15856.117 | L68: =SUMIFS(BV_Data_An_Cour!$P:$P,BV_Data_An_Cour!$U:$U,$B68,BV_Data_An_Cour!$V:$V,$C68,BV_Data_An_Cour!$W:$W,L$2) -> 39092.96 | N68: =L68-F68 -> 23236.843 | Q68: =AL447*W3 -> 46007.595 | S68: =L68-Q68 -> -6914.635
A69: =+B69&C69 -> Véhicules neufs[...] | B69: =+$K$1 -> Véhicules neufs | C69: [...] | F69: =+SUMPRODUCT(('Budget original'!$A$8:$A$500=$A69)*('Budget original'!$C$3:$AO$3=F$2),'Budget original'!$C$8:$AO$500) -> 0 | N69: =L69-F69 -> 0 | Q69: =SUMIFS(BV_Data_An_Prec!$P:$P,BV_Data_An_Prec!$U:$U,$B69,BV_Data_An_Prec!$V:$V,$C69,BV_Data_An_Prec!$W:$W,Q$2) -> 0 | S69: =L69-Q69 -> 0
A70: =+B70&C70 -> Véhicules neufs[...] | B70: =+$K$1 -> Véhicules neufs | C70: [...] | F70: =+SUMPRODUCT(('Budget original'!$A$8:$A$500=$A70)*('Budget original'!$C$3:$AO$3=F$2),'Budget original'!$C$8:$AO$500) -> 0 | L70: =SUMIFS(BV_Data_An_Cour!$P:$P,BV_Data_An_Cour!$U:$U,$B70,BV_Data_An_Cour!$V:$V,$C70,BV_Data_An_Cour!$W:$W,L$2) -> 0 | N70: =L70-F70 -> 0 | Q70: =SUMIFS(BV_Data_An_Prec!$P:$P,BV_Data_An_Prec!$U:$U,$B70,BV_Data_An_Prec!$V:$V,$C70,BV_Data_An_Prec!$W:$W,Q$2) -> 0 | S70: =L70-Q70 -> 0
A71: =+B71&C71 -> Véhicules neufs[...] | B71: =+$K$1 -> Véhicules neufs | C71: [...] | F71: =+SUMPRODUCT(('Budget original'!$A$8:$A$500=$A71)*('Budget original'!$C$3:$AO$3=F$2),'Budget original'!$C$8:$AO$500) -> 0 | L71: =SUMIFS(BV_Data_An_Cour!$P:$P,BV_Data_An_Cour!$U:$U,$B71,BV_Data_An_Cour!$V:$V,$C71,BV_Data_An_Cour!$W:$W,L$2)*0.32 -> 0 | N71: =L71-F71 -> 0 | Q71: =SUMIFS(BV_Data_An_Prec!$P:$P,BV_Data_An_Prec!$U:$U,$B71,BV_Data_An_Prec!$V:$V,$C71,BV_Data_An_Prec!$W:$W,Q$2)*0.32 -> 0 | S71: =L71-Q71 -> 0
A72: =+B72&C72 -> Véhicules neufsTOTAL SEMI-FIXES | B72: =+$K$1 -> Véhicules neufs | C72: TOTAL SEMI-FIXES | D72: % brut | E72: =F72/F$27 -> 0.11889459 | F72: =+SUM(F55:F71) -> 284122.7 | J72: % brut | K72: =L72/L$27 -> 0.15193462 | L72: =+SUM(L55:L71) -> 320146.22 | N72: =+SUM(N55:N71) -> 36023.517 | O72: % brut | P72: =Q72/Q$27 -> 0.14990474 | Q72: =+SUM(Q55:Q71) -> 337058.58 | S72: =+SUM(S55:S71) -> -16912.365
A73: =+B73&C73 -> Véhicules neufs | B73: =+$K$1 -> Véhicules neufs
A74: =+B74&C74 -> Véhicules neufsTOTAL DES DÉPENSES | B74: =+$K$1 -> Véhicules neufs | C74: TOTAL DES DÉPENSES | D74: % brut | E74: =F74/F$27 -> 0.88658361 | F74: =F41+F54+F72 -> 2118671.2 | J74: % brut | K74: =L74/L$27 -> 0.89129805 | L74: =L41+L54+L72 -> 1878082.2 | N74: =L74-F74 -> -240588.94 | O74: % brut | P74: =Q74/Q$27 -> 0.86307155 | Q74: =Q41+Q54+Q72 -> 1940603.5 | S74: =L74-Q74 -> -62521.325
A75: =+B75&C75 -> Véhicules neufsProgramme neuf 1 | B75: =+$K$1 -> Véhicules neufs | C75: Programme neuf 1 | F75: =+SUMPRODUCT(('Budget original'!$A$8:$A$500=$A75)*('Budget original'!$C$3:$AO$3=F$2),'Budget original'!$C$8:$AO$500) -> 42383.095 | L75: =-SUMIFS(BV_Data_An_Cour!$P:$P,BV_Data_An_Cour!$U:$U,$B75,BV_Data_An_Cour!$V:$V,$C75,BV_Data_An_Cour!$W:$W,L$2) -> 0 | N75: =L75-F75 -> -42383.095 | Q75: =-SUMIFS(BV_Data_An_Prec!$P:$P,BV_Data_An_Prec!$U:$U,$B75,BV_Data_An_Prec!$V:$V,$C75,BV_Data_An_Prec!$W:$W,Q$2)-Q155 -> 22000
A76: =+B76&C76 -> Véhicules neufsProgramme neuf 2 | B76: =+$K$1 -> Véhicules neufs | C76: Programme neuf 2 | F76: =+SUMPRODUCT(('Budget original'!$A$8:$A$500=$A76)*('Budget original'!$C$3:$AO$3=F$2),'Budget original'!$C$8:$AO$500) -> 0 | L76: =-SUMIFS(BV_Data_An_Cour!$P:$P,BV_Data_An_Cour!$U:$U,$B76,BV_Data_An_Cour!$V:$V,$C76,BV_Data_An_Cour!$W:$W,L$2) -> 0 | N76: =L76-F76 -> 0 | Q76: =-SUMIFS(BV_Data_An_Prec!$P:$P,BV_Data_An_Prec!$U:$U,$B76,BV_Data_An_Prec!$V:$V,$C76,BV_Data_An_Prec!$W:$W,Q$2) -> 0 | S76: =L76-Q76 -> 0
A77: =+B77&C77 -> Véhicules neufsProgramme neuf 3 | B77: =+$K$1 -> Véhicules neufs | C77: Programme neuf 3 | F77: =+SUMPRODUCT(('Budget original'!$A$8:$A$500=$A77)*('Budget original'!$C$3:$AO$3=F$2),'Budget original'!$C$8:$AO$500) -> 0 | L77: =-SUMIFS(BV_Data_An_Cour!$P:$P,BV_Data_An_Cour!$U:$U,$B77,BV_Data_An_Cour!$V:$V,$C77,BV_Data_An_Cour!$W:$W,L$2) -> 0 | N77: =L77-F77 -> 0 | Q77: =-SUMIFS(BV_Data_An_Prec!$P:$P,BV_Data_An_Prec!$U:$U,$B77,BV_Data_An_Prec!$V:$V,$C77,BV_Data_An_Prec!$W:$W,Q$2) -> 0 | S77: =L77-Q77 -> 0
A78: =+B78&C78 -> Véhicules neufsHoldbacks | B78: =+$K$1 -> Véhicules neufs | C78: Holdbacks | F78: =+SUMPRODUCT(('Budget original'!$A$8:$A$500=$A78)*('Budget original'!$C$3:$AO$3=F$2),'Budget original'!$C$8:$AO$500) -> 738400.32 | L78: =-SUMIFS(BV_Data_An_Cour!$P:$P,BV_Data_An_Cour!$U:$U,$B78,BV_Data_An_Cour!$V:$V,$C78,BV_Data_An_Cour!$W:$W,L$2) -> 624355.22 | N78: =L78-F78 -> -114045.1 | Q78: =-SUMIFS(BV_Data_An_Prec!$P:$P,BV_Data_An_Prec!$U:$U,$B78,BV_Data_An_Prec!$V:$V,$C78,BV_Data_An_Prec!$W:$W,Q$2) -> 648421.92 | S78: =L78-Q78 -> -24066.7
A79: =+B79&C79 -> Véhicules neufs[...] | B79: =+$K$1 -> Véhicules neufs | C79: [...] | F79: =+SUMPRODUCT(('Budget original'!$A$8:$A$500=$A79)*('Budget original'!$C$3:$AO$3=F$2),'Budget original'!$C$8:$AO$500) -> 0 | L79: =-SUMIFS(BV_Data_An_Cour!$P:$P,BV_Data_An_Cour!$U:$U,$B79,BV_Data_An_Cour!$V:$V,$C79,BV_Data_An_Cour!$W:$W,L$2) -> 0 | N79: =L79-F79 -> 0 | Q79: =-SUMIFS(BV_Data_An_Prec!$P:$P,BV_Data_An_Prec!$U:$U,$B79,BV_Data_An_Prec!$V:$V,$C79,BV_Data_An_Prec!$W:$W,Q$2) -> 0 | S79: =L79-Q79 -> 0
A80: =+B80&C80 -> Véhicules neufs[...] | B80: =+$K$1 -> Véhicules neufs | C80: [...] | F80: =+SUMPRODUCT(('Budget original'!$A$8:$A$500=$A80)*('Budget original'!$C$3:$AO$3=F$2),'Budget original'!$C$8:$AO$500) -> 0 | L80: =-SUMIFS(BV_Data_An_Cour!$P:$P,BV_Data_An_Cour!$U:$U,$B80,BV_Data_An_Cour!$V:$V,$C80,BV_Data_An_Cour!$W:$W,L$2) -> 0 | N80: =L80-F80 -> 0 | Q80: =-SUMIFS(BV_Data_An_Prec!$P:$P,BV_Data_An_Prec!$U:$U,$B80,BV_Data_An_Prec!$V:$V,$C80,BV_Data_An_Prec!$W:$W,Q$2) -> 0 | S80: =L80-Q80 -> 0
A81: =+B81&C81 -> Véhicules neufs[...] | B81: =+$K$1 -> Véhicules neufs | C81: [...] | F81: =+SUMPRODUCT(('Budget original'!$A$8:$A$500=$A81)*('Budget original'!$C$3:$AO$3=F$2),'Budget original'!$C$8:$AO$500) -> 0 | L81: =-SUMIFS(BV_Data_An_Cour!$P:$P,BV_Data_An_Cour!$U:$U,$B81,BV_Data_An_Cour!$V:$V,$C81,BV_Data_An_Cour!$W:$W,L$2) -> 0 | N81: =L81-F81 -> 0 | Q81: =-SUMIFS(BV_Data_An_Prec!$P:$P,BV_Data_An_Prec!$U:$U,$B81,BV_Data_An_Prec!$V:$V,$C81,BV_Data_An_Prec!$W:$W,Q$2) -> 0 | S81: =L81-Q81 -> 0
A82: =+B82&C82 -> Véhicules neufsFrais administration | B82: =+$K$1 -> Véhicules neufs | C82: Frais administration | F82: =+SUMPRODUCT(('Budget original'!$A$8:$A$500=$A82)*('Budget original'!$C$3:$AO$3=F$2),'Budget original'!$C$8:$AO$500) -> 232643.75 | L82: =-SUMIFS(BV_Data_An_Cour!$P:$P,BV_Data_An_Cour!$U:$U,$B82,BV_Data_An_Cour!$V:$V,$C82,BV_Data_An_Cour!$W:$W,L$2) -> 248583.9 | N82: =L82-F82 -> 15940.149 | Q82: =-SUMIFS(BV_Data_An_Prec!$P:$P,BV_Data_An_Prec!$U:$U,$B82,BV_Data_An_Prec!$V:$V,$C82,BV_Data_An_Prec!$W:$W,Q$2)-Q158 -> 63937 | S82: =L82-Q82 -> 184646.9
A83: =+B83&C83 -> Véhicules neufsAUTRES REVENUS | B83: =+$K$1 -> Véhicules neufs | C83: AUTRES REVENUS | F83: =+SUM(F75:F82) -> 1013427.2 | L83: =+SUM(L75:L82) -> 872939.12 | N83: =+SUM(N75:N82) -> -140488.05 | Q83: =+SUM(Q75:Q82) -> 734358.92 | S83: =+SUM(S75:S82) -> 160580.2
A84: =+B84&C84 -> Véhicules neufs | B84: =+$K$1 -> Véhicules neufs
A85: =+B85&C85 -> Véhicules neufsPROFIT DÉPARTEMENTAL | B85: =+$K$1 -> Véhicules neufs | C85: PROFIT DÉPARTEMENTAL | F85: =F27-F74+F83 -> 1284458.6 | L85: =L27-L74+L83 -> 1101988.4 | N85: =N27-N41-N54-N72+N83 -> -182470.17 | Q85: =Q27-Q74+Q83 -> 1042240.5 | S85: =L85-Q85 -> 59747.925
C89: =C1 -> Volks | K89: Véhicules usagés | S89: =$S$1 -> Réalisé AAJ, Novembre 2023
D91: BUDGET ORIGINAL | J91: RÉALISATION | M91: ÉCART réel / Budget | O91: ANNÉE PRÉCÉDENTE | R91: ECART (réel/ Ann.Préc.)
D92: UNITÉS | E92: $P/UNITÉ | F92: $PROFITS | J92: UNITÉS | K92: $P/UNITE | L92: $PROFITS | M92: UNITÉS | N92: $PROFITS | O92: UNITÉS | P92: $P/UNITE | Q92: $PROFITS | R92: UNITÉS | S92: $PROFITS
A93: =+B93&C93 -> Véhicules usagésVentes nettes | B93: Véhicules usagés | C93: Ventes nettes | F93: =+SUMPRODUCT(('Budget original'!$A$8:$A$500=$A93)*('Budget original'!$C$3:$AO$3=F$2),'Budget original'!$C$8:$AO$500) -> 18384968 | L93: =-SUMIFS(BV_Data_An_Cour!$P:$P,BV_Data_An_Cour!$X:$X,"Oui",BV_Data_An_Cour!$U:$U,$B93) -> 16075073 | Q93: =-SUMIFS(BV_Data_An_Prec!$P:$P,BV_Data_An_Prec!$X:$X,"Oui",BV_Data_An_Prec!$U:$U,$B93) -> 16412297
A94: =+B94&C94 -> Véhicules usagésCertifié | B94: Véhicules usagés | C94: Certifié | D94: =+SUMPRODUCT(('Budget original'!$A$8:$A$500=$A94)*('Budget original'!$C$3:$AO$3=D$2),'Budget original'!$C$8:$AO$500) -> 440 | E94: =IF(D94=0,0,F94/D94) -> 1858 | F94: =+SUMPRODUCT(('Budget original'!$A$8:$A$500=$A94)*('Budget original'!$C$3:$AO$3=F$2),'Budget original'!$C$8:$AO$500) -> 817520 | J94: =-SUMIFS(BV_Data_An_Cour!$P:$P,BV_Data_An_Cour!$U:$U,$B94,BV_Data_An_Cour!$V:$V,$C94,BV_Data_An_Cour!$W:$W,J$2) -> 264 | K94: =IF(J94=0,0,L94/J94) -> 1624.0647 | L94: =-SUMIFS(BV_Data_An_Cour!$P:$P,BV_Data_An_Cour!$U:$U,$B94,BV_Data_An_Cour!$V:$V,$C94,BV_Data_An_Cour!$W:$W,$L2) -> 428753.07 | M94: =J94-D94 -> -176 | N94: =L94-F94 -> -388766.93 | O94: =-SUMIFS(BV_Data_An_Prec!$P:$P,BV_Data_An_Prec!$U:$U,$B94,BV_Data_An_Prec!$V:$V,$C94,BV_Data_An_Prec!$W:$W,O$2) -> 346 | P94: =IF(O94=0,0,Q94/O94) -> 2035.0493 | Q94: =-SUMIFS(BV_Data_An_Prec!$P:$P,BV_Data_An_Prec!$U:$U,$B94,BV_Data_An_Prec!$V:$V,$C94,BV_Data_An_Prec!$W:$W,$L2) -> 704127.05 | R94: =J94-O94 -> -82 | S94: =L94-Q94 -> -275373.98
A95: =+B95&C95 -> Véhicules usagésNon Certifié | B95: Véhicules usagés | C95: Non Certifié | D95: =+SUMPRODUCT(('Budget original'!$A$8:$A$500=$A95)*('Budget original'!$C$3:$AO$3=D$2),'Budget original'!$C$8:$AO$500) -> 0 | E95: =IF(D95=0,0,F95/D95) -> 0 | F95: =+SUMPRODUCT(('Budget original'!$A$8:$A$500=$A95)*('Budget original'!$C$3:$AO$3=F$2),'Budget original'!$C$8:$AO$500) -> 0 | J95: =-SUMIFS(BV_Data_An_Cour!$P:$P,BV_Data_An_Cour!$U:$U,$B95,BV_Data_An_Cour!$V:$V,$C95,BV_Data_An_Cour!$W:$W,J$2) -> 44 | K95: =IF(J95=0,0,L95/J95) -> 1839.4793 | L95: =-SUMIFS(BV_Data_An_Cour!$P:$P,BV_Data_An_Cour!$U:$U,$B95,BV_Data_An_Cour!$V:$V,$C95,BV_Data_An_Cour!$W:$W,$L2) -> 80937.09 | M95: =J95-D95 -> 44 | N95: =L95-F95 -> 80937.09 | O95: =-SUMIFS(BV_Data_An_Prec!$P:$P,BV_Data_An_Prec!$U:$U,$B95,BV_Data_An_Prec!$V:$V,$C95,BV_Data_An_Prec!$W:$W,O$2) -> 10 | P95: =IF(O95=0,0,Q95/O95) -> 1663.876 | Q95: =-SUMIFS(BV_Data_An_Prec!$P:$P,BV_Data_An_Prec!$U:$U,$B95,BV_Data_An_Prec!$V:$V,$C95,BV_Data_An_Prec!$W:$W,$L2) -> 16638.76 | R95: =J95-O95 -> 34 | S95: =L95-Q95 -> 64298.33
A96: =+B96&C96 -> Véhicules usagésTotal Usagés | B96: Véhicules usagés | C96: Total Usagés | D96: =+D95+D94 -> 440 | E96: =IF(D96=0,0,F96/D96) -> 1858 | F96: =+F94+F95 -> 817520 | J96: =+J94+J95 -> 308 | K96: =IF(J96<=0,0,L96/J96) -> 1654.8382 | L96: =+L94+L95 -> 509690.16 | M96: =J96-D96 -> -132 | N96: =L96-F96 -> -307829.84 | O96: =+O94+O95 -> 356 | P96: =IF(O96<=0,0,Q96/O96) -> 2024.6231 | Q96: =+Q94+Q95 -> 720765.81 | R96: =R94+R95 -> -48 | S96: =S94+S95 -> -211075.65
A97: =+B97&C97 -> Véhicules usagés | B97: Véhicules usagés | E97: =IF(D97=0,0,F97/D97) -> 0 | M97: =M96/D96 -> -0.3 | N97: =N96/F96 -> -0.37654105 | R97: =R96/O96 -> -0.13483146 | S97: =IF(Q96=0,0,(S96/Q96)) -> -0.29284914
A98: =+B98&C98 -> Véhicules usagésUS | B98: Véhicules usagés | C98: US | D98: =+SUMPRODUCT(('Budget original'!$A$8:$A$500=$A98)*('Budget original'!$C$3:$AO$3=D$2),'Budget original'!$C$8:$AO$500) -> 0 | E98: =IF(D98=0,0,F98/D98) -> 0 | F98: =+SUMPRODUCT(('Budget original'!$A$8:$A$500=$A98)*('Budget original'!$C$3:$AO$3=F$2),'Budget original'!$C$8:$AO$500) -> 0 | J98: =-SUMIFS(BV_Data_An_Cour!$P:$P,BV_Data_An_Cour!$U:$U,$B98,BV_Data_An_Cour!$V:$V,$C98,BV_Data_An_Cour!$W:$W,J$2) -> 0 | K98: =IF(J98=0,0,L98/J98) -> 0 | L98: =-SUMIFS(BV_Data_An_Cour!$P:$P,BV_Data_An_Cour!$U:$U,$B98,BV_Data_An_Cour!$V:$V,$C98,BV_Data_An_Cour!$W:$W,$L2) -> 0 | O98: =-SUMIFS(BV_Data_An_Prec!$P:$P,BV_Data_An_Prec!$U:$U,$B98,BV_Data_An_Prec!$V:$V,$C98,BV_Data_An_Prec!$W:$W,O$2) -> 0 | P98: =IF(O98=0,0,Q98/O98) -> 0 | Q98: =-SUMIFS(BV_Data_An_Prec!$P:$P,BV_Data_An_Prec!$U:$U,$B98,BV_Data_An_Prec!$V:$V,$C98,BV_Data_An_Prec!$W:$W,$L2) -> 0 | R98: =J98-O98 -> 0 | S98: =L98-Q98 -> 0
A99: =+B99&C99 -> Véhicules usagésVentes au Gros | B99: Véhicules usagés | C99: Ventes au Gros | D99: =+SUMPRODUCT(('Budget original'!$A$8:$A$500=$A99)*('Budget original'!$C$3:$AO$3=D$2),'Budget original'!$C$8:$AO$500) -> 372.30769 | E99: =IF(D99=0,0,F99/D99) -> 399 | F99: =+SUMPRODUCT(('Budget original'!$A$8:$A$500=$A99)*('Budget original'!$C$3:$AO$3=F$2),'Budget original'!$C$8:$AO$500) -> 148550.77 | J99: =-SUMIFS(BV_Data_An_Cour!$P:$P,BV_Data_An_Cour!$U:$U,$B99,BV_Data_An_Cour!$V:$V,$C99,BV_Data_An_Cour!$W:$W,J$2) -> 367 | K99: =IF(J99=0,0,L99/J99) -> 452.65616 | L99: =-SUMIFS(BV_Data_An_Cour!$P:$P,BV_Data_An_Cour!$U:$U,$B99,BV_Data_An_Cour!$V:$V,$C99,BV_Data_An_Cour!$W:$W,L$2) -> 166124.81 | M99: =J99-D99 -> -5.3076923 | N99: =L99-F99 -> 17574.041 | O99: =-SUMIFS(BV_Data_An_Prec!$P:$P,BV_Data_An_Prec!$U:$U,$B99,BV_Data_An_Prec!$V:$V,$C99,BV_Data_An_Prec!$W:$W,O$2) -> 324 | P99: =IF(O99=0,0,Q99/O99) -> 399.32315 | Q99: =-SUMIFS(BV_Data_An_Prec!$P:$P,BV_Data_An_Prec!$U:$U,$B99,BV_Data_An_Prec!$V:$V,$C99,BV_Data_An_Prec!$W:$W,Q$2) -> 129380.7 | R99: =J99-O99 -> 43 | S99: =L99-Q99 -> 36744.11
A100: =+B100&C100 -> Véhicules usagés | B100: Véhicules usagés
A101: =+B101&C101 -> Véhicules usagésRev. Finances | B101: Véhicules usagés | C101: Rev. Finances | D101: =+SUMPRODUCT(('Budget original'!$A$8:$A$500=$A101)*('Budget original'!$C$3:$AO$3=D$2),'Budget original'!$C$8:$AO$500) -> 0 | E101: =IF(D101=0,0,F101/D101) -> 0 | F101: =+SUMPRODUCT(('Budget original'!$A$8:$A$500=$A101)*('Budget original'!$C$3:$AO$3=F$2),'Budget original'!$C$8:$AO$500) -> 220000 | K101: =IF(J96=0,0,L101/J96) -> 673.16581 | L101: =-SUMIFS(BV_Data_An_Cour!$P:$P,BV_Data_An_Cour!$U:$U,$B101,BV_Data_An_Cour!$V:$V,$C101,BV_Data_An_Cour!$W:$W,$L2) -> 207335.07 | N101: =L101-F101 -> -12664.93 | P101: =IF(O96=0,0,Q101/O96) -> 1034.8839 | Q101: =-SUMIFS(BV_Data_An_Prec!$P:$P,BV_Data_An_Prec!$U:$U,$B101,BV_Data_An_Prec!$V:$V,$C101,BV_Data_An_Prec!$W:$W,$L2) -> 368418.67 | R101: =O101-K101 -> -673.16581 | S101: =L101-Q101 -> -161083.6
A102: =+B102&C102 -> Véhicules usagésRev. Protections | B102: Véhicules usagés | C102: Rev. Protections | D102: =+SUMPRODUCT(('Budget original'!$A$8:$A$500=$A102)*('Budget original'!$C$3:$AO$3=D$2),'Budget original'!$C$8:$AO$500) -> 0 | E102: =IF(D102=0,0,F102/D102) -> 0 | F102: =+SUMPRODUCT(('Budget original'!$A$8:$A$500=$A102)*('Budget original'!$C$3:$AO$3=F$2),'Budget original'!$C$8:$AO$500) -> 550000 | K102: =IF(J96=0,0,L102/J96) -> 1349.9905 | L102: =-SUMIFS(BV_Data_An_Cour!$P:$P,BV_Data_An_Cour!$U:$U,$B102,BV_Data_An_Cour!$V:$V,$C102,BV_Data_An_Cour!$W:$W,$L2) -> 415797.07 | N102: =L102-F102 -> -134202.93 | P102: =IF(O96=0,0,Q102/O96) -> 1246.0956 | Q102: =-SUMIFS(BV_Data_An_Prec!$P:$P,BV_Data_An_Prec!$U:$U,$B102,BV_Data_An_Prec!$V:$V,$C102,BV_Data_An_Prec!$W:$W,$L2) -> 443610.05 | R102: =O102-K102 -> -1349.9905 | S102: =L102-Q102 -> -27812.98
A103: =+B103&C103 -> Véhicules usagésRev. Autres | B103: Véhicules usagés | C103: Rev. Autres | D103: =+SUMPRODUCT(('Budget original'!$A$8:$A$500=$A103)*('Budget original'!$C$3:$AO$3=D$2),'Budget original'!$C$8:$AO$500) -> 0 | E103: =IF(D103=0,0,F103/D103) -> 0 | F103: =+SUMPRODUCT(('Budget original'!$A$8:$A$500=$A103)*('Budget original'!$C$3:$AO$3=F$2),'Budget original'!$C$8:$AO$500) -> 154000 | K103: =IF(J96=0,0,L103/J96) -> 31.606299 | L103: =-SUMIFS(BV_Data_An_Cour!$P:$P,BV_Data_An_Cour!$U:$U,$B103,BV_Data_An_Cour!$V:$V,$C103,BV_Data_An_Cour!$W:$W,$L$2) -> 9734.74 | N103: =L103-F103 -> -144265.26 | P103: =IF(O96=0,0,Q103/O96) -> 52.25191 | Q103: =-SUMIFS(BV_Data_An_Prec!$P:$P,BV_Data_An_Prec!$U:$U,$B103,BV_Data_An_Prec!$V:$V,$C103,BV_Data_An_Prec!$W:$W,$L$2) -> 18601.68 | R103: =O103-K103 -> -31.606299 | S103: =L103-Q103 -> -8866.94
A104: =+B104&C104 -> Véhicules usagésTotal F&I | B104: Véhicules usagés | C104: Total F&I | D104: =D96 -> 440 | E104: =IF(D104=0,0,F104/D104) -> 2100 | F104: =F101+F102+F103 -> 924000 | J104: =J96 -> 308 | K104: =IF(J104<=0,0,L104/J104) -> 2054.7626 | L104: =L101+L102+L103 -> 632866.88 | M104: =J104-D104 -> -132 | N104: =L104-F104 -> -291133.12 | O104: =O96 -> 356 | P104: =IF(O104<=0,0,Q104/O104) -> 2333.2315 | Q104: =Q101+Q102+Q103 -> 830630.4 | S104: =L104-Q104 -> -197763.52
...

Sheet Mix Produits Volks Mois
A2: Pièces | B2: Mix Réalisé | F2: Mix Budget | J2: Écart Total | L2: Écart Mix | N2: Écart Taux | P2: Atteinte Cible
B3: $VENTES | C3: % P. BRUT | D3: $PROFITS | F3: $VENTES | G3: % P. BRUT | H3: $PROFITS | P3: $Ventes | Q3: $Profits
A4: Pièces Ro Clients | B4: =+Print_Mois!J294 -> 133780.1 | C4: =D4/B4 -> 0.36223407 | D4: =+Print_Mois!L294 -> 48459.71 | F4: =+Print_Mois!G294 -> 0 | G4: =H4/F4 -> #DIV/0! | H4: =+Print_Mois!I294 -> 0 | J4: =+D4-H4 -> 48459.71 | L4: =(B4-F4)*G4 -> #DIV/0! | N4: =B4*(C4-G4) -> #DIV/0! | P4: =+B4/F4 -> #DIV/0! | Q4: =+D4/H4 -> #DIV/0!
A5: Pièces Ro Carrosserie | B5: =+Print_Mois!J295 -> 36556.91 | C5: =D5/B5 -> 0.24894774 | D5: =+Print_Mois!L295 -> 9100.76 | F5: =+Print_Mois!G295 -> 0 | G5: =H5/F5 -> #DIV/0! | H5: =+Print_Mois!I295 -> 0 | J5: =+D5-H5 -> 9100.76 | L5: =(B5-F5)*G5 -> #DIV/0! | N5: =B5*(C5-G5) -> #DIV/0! | P5: =+B5/F5 -> #DIV/0! | Q5: =+D5/H5 -> #DIV/0!
