Workbook
Name Ticker: #REF!
Name Ticker: #REF!

Sheet Parametres
A1: Compagnie | B1: Volks
G2: 1-Mémo | M2: Mois | N2: YTD
A3: Mois Courant | B3: Avril | C3: =+VLOOKUP(B3,$K$3:$L$14,2,0) -> 4 | G3: 10-Compte compteur | K3: Janvier | L3: 1 | M3: =+IF($K3=$B$3,"X","") | N3: =+IF(K3=B3,"X",IF(L3<=$C$3,"X","")) -> X
A4: Année | B4: 2024 | K4: Février | L4: 2 | M4: =+IF($K4=$B$3,"X","") | N4: =+IF(K4=B4,"X",IF(L4<=$C$3,"X","")) -> X
K5: Mars | L5: 3 | M5: =+IF($K5=$B$3,"X","") | N5: =+IF(K5=B5,"X",IF(L5<=$C$3,"X","")) -> X
K6: Avril | L6: 4 | M6: =+IF($K6=$B$3,"X","") -> X | N6: =+IF(K6=B6,"X",IF(L6<=$C$3,"X","")) -> X
K7: Mai | L7: 5 | M7: =+IF($K7=$B$3,"X","") | N7: =+IF(K7=B7,"X",IF(L7<=$C$3,"X",""))
K8: Juin | L8: 6 | M8: =+IF($K8=$B$3,"X","") | N8: =+IF(K8=B8,"X",IF(L8<=$C$3,"X",""))
A9: Sélectionner le mois en B3 | K9: Juillet | L9: 7 | M9: =+IF($K9=$B$3,"X","") | N9: =+IF(K9=B9,"X",IF(L9<=$C$3,"X",""))
A10: Coller les balances de vérification respectives en cellule A1 dans les onglets BV_Data_An_Cour et BV_Data_An_Prec | K10: Août | L10: 8 | M10: =+IF($K10=$B$3,"X","") | N10: =+IF(K10=B10,"X",IF(L10<=$C$3,"X",""))
A11: Vérifier s'il y a des #N/A dans les colonnes T à X des onlgets de BV | K11: Septembre | L11: 9 | M11: =+IF($K11=$B$3,"X","") | N11: =+IF(K11=B11,"X",IF(L11<=$C$3,"X",""))
A12: Vérifier les chiffres avec l'état financier et les réalisés an passé pour les résultat net mois et aad | K12: Octobre | L12: 10 | M12: =+IF($K12=$B$3,"X","") | N12: =+IF(K12=B12,"X",IF(L12<=$C$3,"X",""))
K13: Novembre | L13: 11 | M13: =+IF($K13=$B$3,"X","") | N13: =+IF(K13=B13,"X",IF(L13<=$C$3,"X",""))
K14: Décembre | L14: 12 | M14: =+IF($K14=$B$3,"X","") | N14: =+IF(K14=B14,"X",IF(L14<=$C$3,"X",""))

Sheet Bilan
A1: BILAN
A2: =+Parametres!B1 -> Volks
A3: =CONCATENATE("",,Parametres!B3," ",Parametres!B4) -> Avril 2024
A5: Encaisse | B5: =SUMIFS(BV_Data_An_Cour!$P:$P,BV_Data_An_Cour!$U:$U,$A$1,BV_Data_An_Cour!$V:$V,$A5) -> 1570613.7 | D5: Marge de crédit | E5: =-SUMIFS(BV_Data_An_Cour!$P:$P,BV_Data_An_Cour!$U:$U,$A$1,BV_Data_An_Cour!$V:$V,$D5) -> 0
A6: Total Trésorerie et équivalent de Trésorerie | B6: =SUM(B5) -> 1570613.7
D7: Portion Court Terme de la Dette Long Terme | E7: =-SUMIFS(BV_Data_An_Cour!$P:$P,BV_Data_An_Cour!$U:$U,$A$1,BV_Data_An_Cour!$V:$V,$D7) -> 0
A8: Recevables Contrats en Transit | B8: =SUMIFS(BV_Data_An_Cour!$P:$P,BV_Data_An_Cour!$U:$U,$A$1,BV_Data_An_Cour!$V:$V,$A8) -> 1903267.8
A9: Recevables Véhicules | B9: =SUMIFS(BV_Data_An_Cour!$P:$P,BV_Data_An_Cour!$U:$U,$A$1,BV_Data_An_Cour!$V:$V,$A9) -> 386143.73 | D9: Avances à payer | E9: =-SUMIFS(BV_Data_An_Cour!$P:$P,BV_Data_An_Cour!$U:$U,$A$1,BV_Data_An_Cour!$V:$V,$D9) -> 0
A10: Recevables Manufacturier | B10: =SUMIFS(BV_Data_An_Cour!$P:$P,BV_Data_An_Cour!$U:$U,$A$1,BV_Data_An_Cour!$V:$V,$A10) -> 601016 | D10: Comptes à Payer Fournisseurs | E10: =-SUMIFS(BV_Data_An_Cour!$P:$P,BV_Data_An_Cour!$U:$U,$A$1,BV_Data_An_Cour!$V:$V,$D10) -> 225405.73
A11: Recevables Pièces et Service | B11: =SUMIFS(BV_Data_An_Cour!$P:$P,BV_Data_An_Cour!$U:$U,$A$1,BV_Data_An_Cour!$V:$V,$A11) -> 244017.37 | D11: Taxes de Vente à Payer | E11: =-SUMIFS(BV_Data_An_Cour!$P:$P,BV_Data_An_Cour!$U:$U,$A$1,BV_Data_An_Cour!$V:$V,$D11) -> -230223.21
A12: Recevables Garantie Manufacturier | B12: =SUMIFS(BV_Data_An_Cour!$P:$P,BV_Data_An_Cour!$U:$U,$A$1,BV_Data_An_Cour!$V:$V,$A12) -> 38141.16 | D12: Impôts à payer | E12: =-SUMIFS(BV_Data_An_Cour!$P:$P,BV_Data_An_Cour!$U:$U,$A$1,BV_Data_An_Cour!$V:$V,$D12) -> 0
A13: Recevables Carrosserie | B13: =SUMIFS(BV_Data_An_Cour!$P:$P,BV_Data_An_Cour!$U:$U,$A$1,BV_Data_An_Cour!$V:$V,$A13) -> 29228.72 | D13: Dépôts de Client | E13: =-SUMIFS(BV_Data_An_Cour!$P:$P,BV_Data_An_Cour!$U:$U,$A$1,BV_Data_An_Cour!$V:$V,$D13) -> 33050
A14: Recevables Intercos | B14: =SUMIFS(BV_Data_An_Cour!$P:$P,BV_Data_An_Cour!$U:$U,$A$1,BV_Data_An_Cour!$V:$V,$A14) -> 46289.36 | D14: Payables Intercos | E14: =-SUMIFS(BV_Data_An_Cour!$P:$P,BV_Data_An_Cour!$U:$U,$A$1,BV_Data_An_Cour!$V:$V,$D14) -> 104241.45
A15: Recevables Autres | B15: =SUMIFS(BV_Data_An_Cour!$P:$P,BV_Data_An_Cour!$U:$U,$A$1,BV_Data_An_Cour!$V:$V,$A15) -> 5547.23 | D15: Autres Comptes à Payer | E15: =-SUMIFS(BV_Data_An_Cour!$P:$P,BV_Data_An_Cour!$U:$U,$A$1,BV_Data_An_Cour!$V:$V,$D15) -> 604967.78
A16: Total Comptes à Recevoir | B16: =+SUM(B8:B15) -> 3253651.4 | D16: Total Comptes à Payer | E16: =+SUM(E10:E15) -> 737441.75
A18: Inventaire Véhicules Neufs | B18: =SUMIFS(BV_Data_An_Cour!$P:$P,BV_Data_An_Cour!$U:$U,$A$1,BV_Data_An_Cour!$V:$V,$A18) -> 6603791.7 | D18: Effet à Payer Véhicules Neufs | E18: =-SUMIFS(BV_Data_An_Cour!$P:$P,BV_Data_An_Cour!$U:$U,$A$1,BV_Data_An_Cour!$V:$V,$D18) -> 9510585.8
A19: Inventaire Véhicules Usagés | B19: =SUMIFS(BV_Data_An_Cour!$P:$P,BV_Data_An_Cour!$U:$U,$A$1,BV_Data_An_Cour!$V:$V,$A19) -> 2675437.9 | D19: Effet à Payer Véhicules Usagés | E19: =-SUMIFS(BV_Data_An_Cour!$P:$P,BV_Data_An_Cour!$U:$U,$A$1,BV_Data_An_Cour!$V:$V,$D19) -> 1161904
A20: Inventaire Pièces, Pneus, Huile | B20: =SUMIFS(BV_Data_An_Cour!$P:$P,BV_Data_An_Cour!$U:$U,$A$1,BV_Data_An_Cour!$V:$V,$A20) -> 686479 | D20: Total Effets à Payer | E20: =+SUM(E18:E19) -> 10672490
A21: Total Inventaires | B21: =SUM(B18:B20) -> 9965708.6
D22: Salaires à Payer | E22: =-SUMIFS(BV_Data_An_Cour!$P:$P,BV_Data_An_Cour!$U:$U,$A$1,BV_Data_An_Cour!$V:$V,$D22) -> 437444.62
A23: Avances à recevoir | B23: =SUMIFS(BV_Data_An_Cour!$P:$P,BV_Data_An_Cour!$U:$U,$A$1,BV_Data_An_Cour!$V:$V,$A23) -> 0 | D23: DAS à Payer | E23: =-SUMIFS(BV_Data_An_Cour!$P:$P,BV_Data_An_Cour!$U:$U,$A$1,BV_Data_An_Cour!$V:$V,$D23) -> -319.2
A24: Travaux en Cours | B24: =SUMIFS(BV_Data_An_Cour!$P:$P,BV_Data_An_Cour!$U:$U,$A$1,BV_Data_An_Cour!$V:$V,$A24) -> 11951.17 | D24: Autres Courus | E24: =-SUMIFS(BV_Data_An_Cour!$P:$P,BV_Data_An_Cour!$U:$U,$A$1,BV_Data_An_Cour!$V:$V,$D24) -> 487103.16
A25: Sous-Traitance | B25: =SUMIFS(BV_Data_An_Cour!$P:$P,BV_Data_An_Cour!$U:$U,$A$1,BV_Data_An_Cour!$V:$V,$A25) -> -22753.58 | D25: [...] | E25: =-SUMIFS(BV_Data_An_Cour!$P:$P,BV_Data_An_Cour!$U:$U,$A$1,BV_Data_An_Cour!$V:$V,$D25) -> 0
A26: Frais Payés d'Avance | B26: =SUMIFS(BV_Data_An_Cour!$P:$P,BV_Data_An_Cour!$U:$U,$A$1,BV_Data_An_Cour!$V:$V,$A26) -> 126296.98 | D26: [...] | E26: =-SUMIFS(BV_Data_An_Cour!$P:$P,BV_Data_An_Cour!$U:$U,$A$1,BV_Data_An_Cour!$V:$V,$D26) -> 0
A27: [...] | B27: =SUMIFS(BV_Data_An_Cour!$P:$P,BV_Data_An_Cour!$U:$U,$A$1,BV_Data_An_Cour!$V:$V,$A27) -> 0 | D27: [...] | E27: =-SUMIFS(BV_Data_An_Cour!$P:$P,BV_Data_An_Cour!$U:$U,$A$1,BV_Data_An_Cour!$V:$V,$D27) -> 0
A28: [...] | B28: =SUMIFS(BV_Data_An_Cour!$P:$P,BV_Data_An_Cour!$U:$U,$A$1,BV_Data_An_Cour!$V:$V,$A28) -> 0 | D28: Total Frais Courus | E28: =SUM(E22:E24) -> 924228.58
A29: [...] | B29: =SUMIFS(BV_Data_An_Cour!$P:$P,BV_Data_An_Cour!$U:$U,$A$1,BV_Data_An_Cour!$V:$V,$A29) -> 0
A30: Total Autres | B30: =SUM(B23:B29) -> 115494.57 | D30: Total Passif Court Terme | E30: =+E5+E7+E16+E20+E28 -> 12334160
A32: Total Actif Court Terme | B32: =+B6+B16+B21+B30 -> 14905468
D33: Impôts Futurs à payer | E33: =-SUMIFS(BV_Data_An_Cour!$P:$P,BV_Data_An_Cour!$U:$U,$A$1,BV_Data_An_Cour!$V:$V,$D33) -> 0
A35: Terrain | B35: =SUMIFS(BV_Data_An_Cour!$P:$P,BV_Data_An_Cour!$U:$U,$A$1,BV_Data_An_Cour!$V:$V,$A35) -> 0 | D35: Avances Long Terme à Payer | E35: =-SUMIFS(BV_Data_An_Cour!$P:$P,BV_Data_An_Cour!$U:$U,$A$1,BV_Data_An_Cour!$V:$V,$D35) -> 0
A36: Bâtisse | B36: =SUMIFS(BV_Data_An_Cour!$P:$P,BV_Data_An_Cour!$U:$U,$A$1,BV_Data_An_Cour!$V:$V,$A36) -> 0 | D36: Hypothèque à Payer | E36: =-SUMIFS(BV_Data_An_Cour!$P:$P,BV_Data_An_Cour!$U:$U,$A$1,BV_Data_An_Cour!$V:$V,$D36) -> 0
A37: Améliorations Locatives | B37: =SUMIFS(BV_Data_An_Cour!$P:$P,BV_Data_An_Cour!$U:$U,$A$1,BV_Data_An_Cour!$V:$V,$A37) -> 4334085.7 | D37: Dette à Long Terme | E37: =-SUMIFS(BV_Data_An_Cour!$P:$P,BV_Data_An_Cour!$U:$U,$A$1,BV_Data_An_Cour!$V:$V,$D37) -> 0
A38: Améliorations Locatives Permanentes | B38: =SUMIFS(BV_Data_An_Cour!$P:$P,BV_Data_An_Cour!$U:$U,$A$1,BV_Data_An_Cour!$V:$V,$A38) -> 0 | D38: Autres Dettes à Long Terme | E38: =-SUMIFS(BV_Data_An_Cour!$P:$P,BV_Data_An_Cour!$U:$U,$A$1,BV_Data_An_Cour!$V:$V,$D38) -> 0
A39: Équipements Service | B39: =SUMIFS(BV_Data_An_Cour!$P:$P,BV_Data_An_Cour!$U:$U,$A$1,BV_Data_An_Cour!$V:$V,$A39) -> 378067.54 | D39: [...] | E39: =-SUMIFS(BV_Data_An_Cour!$P:$P,BV_Data_An_Cour!$U:$U,$A$1,BV_Data_An_Cour!$V:$V,$D39) -> 0
A40: Mobilier | B40: =SUMIFS(BV_Data_An_Cour!$P:$P,BV_Data_An_Cour!$U:$U,$A$1,BV_Data_An_Cour!$V:$V,$A40) -> 23119.27 | D40: [...] | E40: =-SUMIFS(BV_Data_An_Cour!$P:$P,BV_Data_An_Cour!$U:$U,$A$1,BV_Data_An_Cour!$V:$V,$D40) -> 0
A41: Équipements Informatique | B41: =SUMIFS(BV_Data_An_Cour!$P:$P,BV_Data_An_Cour!$U:$U,$A$1,BV_Data_An_Cour!$V:$V,$A41) -> 19665.21 | D41: [...] | E41: =-SUMIFS(BV_Data_An_Cour!$P:$P,BV_Data_An_Cour!$U:$U,$A$1,BV_Data_An_Cour!$V:$V,$D41) -> 0
A42: Équipements Téléphonique | B42: =SUMIFS(BV_Data_An_Cour!$P:$P,BV_Data_An_Cour!$U:$U,$A$1,BV_Data_An_Cour!$V:$V,$A42) -> 0 | D42: Total Passif long terme | E42: =+SUM(E33:E38) -> 0
A43: Enseigne | B43: =SUMIFS(BV_Data_An_Cour!$P:$P,BV_Data_An_Cour!$U:$U,$A$1,BV_Data_An_Cour!$V:$V,$A43) -> 0.01
A44: Total Immobilisations Nettes | B44: =SUM(B35:B43) -> 4754937.7
D45: Total Passifs | E45: =+E42+E30 -> 12334160
A46: Avances à Recevoir Long Terme | B46: =SUMIFS(BV_Data_An_Cour!$P:$P,BV_Data_An_Cour!$U:$U,$A$1,BV_Data_An_Cour!$V:$V,$A46) -> 4473600
A48: Achalandage | B48: =SUMIFS(BV_Data_An_Cour!$P:$P,BV_Data_An_Cour!$U:$U,$A$1,BV_Data_An_Cour!$V:$V,$A48) -> 0 | D48: Capital Actions | E48: =-SUMIFS(BV_Data_An_Cour!$P:$P,BV_Data_An_Cour!$U:$U,$A$1,BV_Data_An_Cour!$V:$V,$D48) -> 2697547.5
D49: Apport | E49: =-SUMIFS(BV_Data_An_Cour!$P:$P,BV_Data_An_Cour!$U:$U,$A$1,BV_Data_An_Cour!$V:$V,$D49) -> 1723617
A50: [...] | B50: =SUMIFS(BV_Data_An_Cour!$P:$P,BV_Data_An_Cour!$U:$U,$A$1,BV_Data_An_Cour!$V:$V,$A50) -> 0 | D50: Bénéfices non répartis | E50: =-SUMIFS(BV_Data_An_Cour!$P:$P,BV_Data_An_Cour!$U:$U,$A$1,BV_Data_An_Cour!$V:$V,$D50)+Print_AAD!AF498 -> 7378681.2
A51: [...] | B51: =SUMIFS(BV_Data_An_Cour!$P:$P,BV_Data_An_Cour!$U:$U,$A$1,BV_Data_An_Cour!$V:$V,$A51) -> 0 | D51: Dividendes | E51: =-SUMIFS(BV_Data_An_Cour!$P:$P,BV_Data_An_Cour!$U:$U,$A$1,BV_Data_An_Cour!$V:$V,$D51) -> 0
A52: [...] | B52: =SUMIFS(BV_Data_An_Cour!$P:$P,BV_Data_An_Cour!$U:$U,$A$1,BV_Data_An_Cour!$V:$V,$A52) -> 0
A53: Total Actif Long Terme | B53: =+B44+B48+B46 -> 9228537.7 | D53: Total Capitaux Propres / Avoir | E53: =SUM(E48:E51) -> 11799846
A56: Total Actif | B56: =+B32+B53 -> 24134006 | D56: Total Passif et Capitaux Propres / Avoir | E56: =+E53+E45 -> 24134006
E65: =+B56-E56 -> 0

Sheet Budget original
B1: ="Budget 2024 Mensuel Révisé"&" "&Parametres!$B$1 -> Budget 2024 Mensuel Révisé Volks
B2: Mois | F2: =+IF(Parametres!$B$3=F$6,"X","") | G2: =+IF(Parametres!$B$3=F$6,"O","") | H2: =+IF(Parametres!$B$3=F$6,"U","") | I2: =+IF(Parametres!$B$3=I$6,"X","") | J2: =+IF(Parametres!$B$3=I$6,"O","") | K2: =+IF(Parametres!$B$3=I$6,"U","") | L2: =+IF(Parametres!$B$3=L$6,"X","") | M2: =+IF(Parametres!$B$3=L$6,"O","") | N2: =+IF(Parametres!$B$3=L$6,"U","") | O2: =+IF(Parametres!$B$3=O$6,"X","") -> X | P2: =+IF(Parametres!$B$3=O$6,"O","") -> O | Q2: =+IF(Parametres!$B$3=O$6,"U","") -> U | R2: =+IF(Parametres!$B$3=R$6,"X","") | S2: =+IF(Parametres!$B$3=R$6,"O","") | T2: =+IF(Parametres!$B$3=R$6,"U","") | U2: =+IF(Parametres!$B$3=U$6,"X","") | V2: =+IF(Parametres!$B$3=U$6,"O","") | W2: =+IF(Parametres!$B$3=U$6,"U","") | X2: =+IF(Parametres!$B$3=X$6,"X","") | Y2: =+IF(Parametres!$B$3=X$6,"O","") | Z2: =+IF(Parametres!$B$3=X$6,"U","") | AA2: =+IF(Parametres!$B$3=AA$6,"X","") | AB2: =+IF(Parametres!$B$3=AA$6,"O","") | AC2: =+IF(Parametres!$B$3=AA$6,"U","") | AD2: =+IF(Parametres!$B$3=AD$6,"X","") | AE2: =+IF(Parametres!$B$3=AD$6,"O","") | AF2: =+IF(Parametres!$B$3=AD$6,"U","") | AG2: =+IF(Parametres!$B$3=AG$6,"X","") | AH2: =+IF(Parametres!$B$3=AG$6,"O","") | AI2: =+IF(Parametres!$B$3=AG$6,"U","") | AJ2: =+IF(Parametres!$B$3=AJ$6,"X","") | AK2: =+IF(Parametres!$B$3=AJ$6,"O","") | AL2: =+IF(Parametres!$B$3=AJ$6,"U","") | AM2: =+IF(Parametres!$B$3=AM$6,"X","") | AN2: =+IF(Parametres!$B$3=AM$6,"O","") | AO2: =+IF(Parametres!$B$3=AM$6,"U","")
B3: YTD | F3: =+IF(VLOOKUP(F$6,Parametres!$K$3:$N$14,4,0)="X","X","") -> X | G3: =+IF(VLOOKUP(F$6,Parametres!$K$3:$N$14,4,0)="X","O","") -> O | H3: =+IF(VLOOKUP(F$6,Parametres!$K$3:$N$14,4,0)="X","U","") -> U | I3: =+IF(VLOOKUP(I$6,Parametres!$K$3:$N$14,4,0)="X","X","") -> X | J3: =+IF(VLOOKUP(I$6,Parametres!$K$3:$N$14,4,0)="X","O","") -> O | K3: =+IF(VLOOKUP(I$6,Parametres!$K$3:$N$14,4,0)="X","U","") -> U | L3: =+IF(VLOOKUP(L$6,Parametres!$K$3:$N$14,4,0)="X","X","") -> X | M3: =+IF(VLOOKUP(L$6,Parametres!$K$3:$N$14,4,0)="X","O","") -> O | N3: =+IF(VLOOKUP(L$6,Parametres!$K$3:$N$14,4,0)="X","U","") -> U | O3: =+IF(VLOOKUP(O$6,Parametres!$K$3:$N$14,4,0)="X","X","") -> X | P3: =+IF(VLOOKUP(O$6,Parametres!$K$3:$N$14,4,0)="X","O","") -> O | Q3: =+IF(VLOOKUP(O$6,Parametres!$K$3:$N$14,4,0)="X","U","") -> U | R3: =+IF(VLOOKUP(R$6,Parametres!$K$3:$N$14,4,0)="X","X","") | S3: =+IF(VLOOKUP(R$6,Parametres!$K$3:$N$14,4,0)="X","O","") | T3: =+IF(VLOOKUP(R$6,Parametres!$K$3:$N$14,4,0)="X","U","") | U3: =+IF(VLOOKUP(U$6,Parametres!$K$3:$N$14,4,0)="X","X","") | V3: =+IF(VLOOKUP(U$6,Parametres!$K$3:$N$14,4,0)="X","O","") | W3: =+IF(VLOOKUP(U$6,Parametres!$K$3:$N$14,4,0)="X","U","") | X3: =+IF(VLOOKUP(X$6,Parametres!$K$3:$N$14,4,0)="X","X","") | Y3: =+IF(VLOOKUP(X$6,Parametres!$K$3:$N$14,4,0)="X","O","") | Z3: =+IF(VLOOKUP(X$6,Parametres!$K$3:$N$14,4,0)="X","U","") | AA3: =+IF(VLOOKUP(AA$6,Parametres!$K$3:$N$14,4,0)="X","X","") | AB3: =+IF(VLOOKUP(AA$6,Parametres!$K$3:$N$14,4,0)="X","O","") | AC3: =+IF(VLOOKUP(AA$6,Parametres!$K$3:$N$14,4,0)="X","U","") | AD3: =+IF(VLOOKUP(AD$6,Parametres!$K$3:$N$14,4,0)="X","X","") | AE3: =+IF(VLOOKUP(AD$6,Parametres!$K$3:$N$14,4,0)="X","O","") | AF3: =+IF(VLOOKUP(AD$6,Parametres!$K$3:$N$14,4,0)="X","U","") | AG3: =+IF(VLOOKUP(AG$6,Parametres!$K$3:$N$14,4,0)="X","X","") | AH3: =+IF(VLOOKUP(AG$6,Parametres!$K$3:$N$14,4,0)="X","O","") | AI3: =+IF(VLOOKUP(AG$6,Parametres!$K$3:$N$14,4,0)="X","U","") | AJ3: =+IF(VLOOKUP(AJ$6,Parametres!$K$3:$N$14,4,0)="X","X","") | AK3: =+IF(VLOOKUP(AJ$6,Parametres!$K$3:$N$14,4,0)="X","O","") | AL3: =+IF(VLOOKUP(AJ$6,Parametres!$K$3:$N$14,4,0)="X","U","") | AM3: =+IF(VLOOKUP(AM$6,Parametres!$K$3:$N$14,4,0)="X","X","") | AN3: =+IF(VLOOKUP(AM$6,Parametres!$K$3:$N$14,4,0)="X","O","") | AO3: =+IF(VLOOKUP(AM$6,Parametres!$K$3:$N$14,4,0)="X","U","")
B4: Budget 2024 | C4: Véhicules neufs
B6: Mois | C6: 2024 | F6: Janvier | I6: Février | L6: Mars | O6: Avril | R6: Mai | U6: Juin | X6: Juillet | AA6: Août | AD6: Septembre | AG6: Octobre | AJ6: Novembre | AM6: Décembre
C7: UNITE | D7: $P/UNITE | E7: $PROFITS | F7: UNITE | G7: $P/UNITE | H7: $PROFITS | I7: UNITE | J7: $P/UNITE | K7: $PROFITS | L7: UNITE | M7: $P/UNITE | N7: $PROFITS | O7: UNITE | P7: $P/UNITE | Q7: $PROFITS | R7: UNITE | S7: $P/UNITE | T7: $PROFITS | U7: UNITE | V7: $P/UNITE | W7: $PROFITS | X7: UNITE | Y7: $P/UNITE | Z7: $PROFITS | AA7: UNITE | AB7: $P/UNITE | AC7: $PROFITS | AD7: UNITE | AE7: $P/UNITE | AF7: $PROFITS | AG7: UNITE | AH7: $P/UNITE | AI7: $PROFITS | AJ7: UNITE | AK7: $P/UNITE | AL7: $PROFITS | AM7: UNITE | AN7: $P/UNITE | AO7: $PROFITS
A8: =+$C$4&B8 -> Véhicules neufsVentes nettes | B8: Ventes nettes | E8: 32266637 | H8: 1621482.2 | K8: 1621482.2 | N8: 2270075 | Q8: 3243094.3 | T8: 3729071 | W8: 2918459.9 | Z8: 2594371.5 | AC8: 2918927.9 | AF8: 2594475.5 | AI8: 3890933.2 | AL8: 3242782.3 | AO8: 1621482.2
A9: =+$C$4&B9 -> Véhicules neufsAutos détail | B9: Autos détail | C9: 120 | D9: 2187.1313 | E9: 262455.76 | F9: 6 | G9: 2198.1219 | H9: 13188.732 | I9: 6 | J9: 2198.1219 | K9: 13188.732 | L9: 8.4 | M9: 2198.1219 | N9: 18464.224 | O9: 12 | P9: 2198.1219 | Q9: 26377.463 | R9: 14 | S9: 2166.7202 | T9: 30334.083 | U9: 11 | V9: 2158.1561 | W9: 23739.717 | X9: 9.6 | Y9: 2198.1219 | Z9: 21101.971 | AA9: 11 | AB9: 2158.1561 | AC9: 23739.717 | AD9: 9.6 | AE9: 2198.1219 | AF9: 21101.971 | AG9: 14.4 | AH9: 2198.1219 | AI9: 31652.956 | AJ9: 12 | AK9: 2198.1219 | AL9: 26377.463 | AM9: 6 | AN9: 2198.1219 | AO9: 13188.732
A10: =+$C$4&B10 -> Véhicules neufsCamions détail | B10: Camions détail | C10: 496 | D10: 2858.8784 | E10: 1418003.7 | F10: 25 | G10: 2850.2587 | H10: 71256.467 | I10: 25 | J10: 2850.2587 | K10: 71256.467 | L10: 35 | M10: 2850.2587 | N10: 99759.054 | O10: 50 | P10: 2850.2587 | Q10: 142512.93 | R10: 57.04 | S10: 2873.2447 | T10: 163889.88 | U10: 44.64 | V10: 2873.2447 | W10: 128261.64 | X10: 40 | Y10: 2850.2587 | Z10: 114010.35 | AA10: 45 | AB10: 2850.2587 | AC10: 128261.64 | AD10: 40 | AE10: 2850.2587 | AF10: 114010.35 | AG10: 59.52 | AH10: 2873.2447 | AI10: 171015.52 | AJ10: 49.8 | AK10: 2861.7055 | AL10: 142512.93 | AM10: 25 | AN10: 2850.2587 | AO10: 71256.467
A11: =+$C$4&B11 -> Véhicules neufsSprinter | B11: Sprinter | C11: 0 | D11: 0 | E11: 0 | F11: 0 | G11: 0 | H11: 0 | I11: 0 | J11: 0 | K11: 0 | L11: 0 | M11: 0 | N11: 0 | O11: 0 | P11: 0 | Q11: 0 | R11: 0 | S11: 0 | T11: 0 | U11: 0 | V11: 0 | W11: 0 | X11: 0 | Y11: 0 | Z11: 0 | AA11: 0 | AB11: 0 | AC11: 0 | AD11: 0 | AE11: 0 | AF11: 0 | AG11: 0 | AH11: 0 | AI11: 0 | AJ11: 0 | AK11: 0 | AL11: 0 | AM11: 0 | AN11: 0 | AO11: 0
A12: =+$C$4&B12 -> Véhicules neufsMoto détail | B12: Moto détail | C12: 0 | D12: 0 | E12: 0 | F12: 0 | G12: 0 | H12: 0 | I12: 0 | J12: 0 | K12: 0 | L12: 0 | M12: 0 | N12: 0 | O12: 0 | P12: 0 | Q12: 0 | R12: 0 | S12: 0 | T12: 0 | U12: 0 | V12: 0 | W12: 0 | X12: 0 | Y12: 0 | Z12: 0 | AA12: 0 | AB12: 0 | AC12: 0 | AD12: 0 | AE12: 0 | AF12: 0 | AG12: 0 | AH12: 0 | AI12: 0 | AJ12: 0 | AK12: 0 | AL12: 0 | AM12: 0 | AN12: 0 | AO12: 0
A13: =+$C$4&B13 -> Véhicules neufs[...] | B13: [...] | C13: 0 | D13: 0 | E13: 0 | G13: 0 | J13: 0 | M13: 0 | P13: 0 | S13: 0 | V13: 0 | Y13: 0 | AB13: 0 | AE13: 0 | AH13: 0 | AK13: 0 | AN13: 0
A14: =+$C$4&B14 -> Véhicules neufs[...] | B14: [...] | C14: 0 | D14: 0 | E14: 0 | G14: 0 | J14: 0 | M14: 0 | P14: 0 | S14: 0 | V14: 0 | Y14: 0 | AB14: 0 | AE14: 0 | AH14: 0 | AK14: 0 | AN14: 0
A15: =+$C$4&B15 -> Véhicules neufs[...] | B15: [...] | C15: 0 | D15: 0 | E15: 0 | G15: 0 | J15: 0 | M15: 0 | P15: 0 | S15: 0 | V15: 0 | Y15: 0 | AB15: 0 | AE15: 0 | AH15: 0 | AK15: 0 | AN15: 0
A16: =+$C$4&B16 -> Véhicules neufsTotal Neufs | B16: Total Neufs | C16: 616 | D16: 2728.0186 | E16: 1680459.5 | F16: 31 | G16: 2724.0387 | H16: 84445.199 | I16: 31 | J16: 2724.0387 | K16: 84445.199 | L16: 43.4 | M16: 2724.0387 | N16: 118223.28 | O16: 62 | P16: 2724.0387 | Q16: 168890.4 | R16: 71.04 | S16: 2734.0084 | T16: 194223.96 | U16: 55.64 | V16: 2731.872 | W16: 152001.36 | X16: 49.6 | Y16: 2724.0387 | Z16: 135112.32 | AA16: 56 | AB16: 2714.31 | AC16: 152001.36 | AD16: 49.6 | AE16: 2724.0387 | AF16: 135112.32 | AG16: 73.92 | AH16: 2741.7272 | AI16: 202668.48 | AJ16: 61.8 | AK16: 2732.8543 | AL16: 168890.4 | AM16: 31 | AN16: 2724.0387 | AO16: 84445.199
A17: =+$C$4&B17 -> Véhicules neufs
A18: =+$C$4&B18 -> Véhicules neufsEx-Démos et courtoisies | B18: Ex-Démos et courtoisies | C18: 48.995 | D18: 2522.7034 | E18: 123599.85 | F18: 2.45 | G18: 2535.1216 | H18: 6211.0479 | I18: 2.45 | J18: 2535.1216 | K18: 6211.0479 | L18: 3.43 | M18: 2535.1216 | N18: 8695.467 | O18: 5 | P18: 2484.4192 | Q18: 12422.096 | R18: 5.635 | S18: 2535.1216 | T18: 14285.41 | U18: 4.41 | V18: 2535.1216 | W18: 11179.886 | X18: 3.92 | Y18: 2535.1216 | Z18: 9937.6766 | AA18: 4.41 | AB18: 2535.1216 | AC18: 11179.886 | AD18: 4 | AE18: 2484.4192 | AF18: 9937.6766 | AG18: 5.88 | AH18: 2535.1216 | AI18: 14906.515 | AJ18: 4.96 | AK18: 2504.4548 | AL18: 12422.096 | AM18: 2.45 | AN18: 2535.1216 | AO18: 6211.0479
A19: =+$C$4&B19 -> Véhicules neufs
A20: =+$C$4&B20 -> Véhicules neufsFlottes | B20: Flottes | C20: 44.775 | D20: 2664.4641 | E20: 119301.38 | F20: 2.25 | G20: 2664.4641 | H20: 5995.0442 | I20: 2.25 | J20: 2664.4641 | K20: 5995.0442 | L20: 3.15 | M20: 2664.4641 | N20: 8393.0618 | O20: 4.5 | P20: 2664.4641 | Q20: 11990.088 | R20: 5.175 | S20: 2664.4641 | T20: 13788.602 | U20: 4.05 | V20: 2664.4641 | W20: 10791.079 | X20: 3.6 | Y20: 2664.4641 | Z20: 9592.0706 | AA20: 4.05 | AB20: 2664.4641 | AC20: 10791.079 | AD20: 3.6 | AE20: 2664.4641 | AF20: 9592.0706 | AG20: 5.4 | AH20: 2664.4641 | AI20: 14388.106 | AJ20: 4.5 | AK20: 2664.4641 | AL20: 11990.088 | AM20: 2.25 | AN20: 2664.4641 | AO20: 5995.0442
A21: =+$C$4&B21 -> Véhicules neufs
A22: =+$C$4&B22 -> Véhicules neufsRachat bail | B22: Rachat bail | E22: 84575 | H22: 4250 | K22: 4250 | N22: 5950 | Q22: 8500 | T22: 9775 | W22: 7650 | Z22: 6800 | AC22: 7650 | AF22: 6800 | AI22: 10200 | AL22: 8500 | AO22: 4250
A23: =+$C$4&B23 -> Véhicules neufs
A24: =+$C$4&B24 -> Véhicules neufsRev. Finances | B24: Rev. Finances | D24: 200 | E24: 132999 | G24: 200 | H24: 6690 | J24: 200 | K24: 6690 | M24: 200 | N24: 9366 | P24: 200 | Q24: 13400 | S24: 200 | T24: 15335 | V24: 200 | W24: 12010 | Y24: 200 | Z24: 10704 | AB24: 200 | AC24: 12082 | AE24: 200 | AF24: 10720 | AH24: 200 | AI24: 15960 | AK24: 200 | AL24: 13352 | AN24: 200 | AO24: 6690
A25: =+$C$4&B25 -> Véhicules neufsRev. Protections | B25: Rev. Protections | D25: 1080 | E25: 718194.6 | G25: 1080 | H25: 36126 | J25: 1080 | K25: 36126 | M25: 1080 | N25: 50576.4 | P25: 1080 | Q25: 72360 | S25: 1080 | T25: 82809 | V25: 1080 | W25: 64854 | Y25: 1080 | Z25: 57801.6 | AB25: 1080 | AC25: 65242.8 | AE25: 1080 | AF25: 57888 | AH25: 1080 | AI25: 86184 | AK25: 1080 | AL25: 72100.8 | AN25: 1080 | AO25: 36126
A26: =+$C$4&B26 -> Véhicules neufsRev. Autres | B26: Rev. Autres | D26: 20 | E26: 13299.9 | G26: 20 | H26: 669 | J26: 20 | K26: 669 | M26: 20 | N26: 936.6 | P26: 20 | Q26: 1340 | S26: 20 | T26: 1533.5 | V26: 20 | W26: 1201 | Y26: 20 | Z26: 1070.4 | AB26: 20 | AC26: 1208.2 | AE26: 20 | AF26: 1072 | AH26: 20 | AI26: 1596 | AK26: 20 | AL26: 1335.2 | AN26: 20 | AO26: 669
A27: =+$C$4&B27 -> Véhicules neufsTotal F&I | B27: Total F&I | C27: 664.995 | D27: 1300 | E27: 864493.5 | F27: 33.45 | G27: 1300 | H27: 43485 | I27: 33.45 | J27: 1300 | K27: 43485 | L27: 46.83 | M27: 1300 | N27: 60879 | O27: 67 | P27: 1300 | Q27: 87100 | R27: 76.675 | S27: 1300 | T27: 99677.5 | U27: 60.05 | V27: 1300 | W27: 78065 | X27: 53.52 | Y27: 1300 | Z27: 69576 | AA27: 60.41 | AB27: 1300 | AC27: 78533 | AD27: 53.6 | AE27: 1300 | AF27: 69680 | AG27: 79.8 | AH27: 1300 | AI27: 103740 | AJ27: 66.76 | AK27: 1300 | AL27: 86788 | AM27: 33.45 | AN27: 1300 | AO27: 43485
A28: =+$C$4&B28 -> Véhicules neufs
A29: =+$C$4&B29 -> Véhicules neufs
A30: =+$C$4&B30 -> Véhicules neufsTotal Dépt. Neufs | B30: Total Dépt. Neufs | C30: 709.77 | D30: 4046.9859 | E30: 2872429.2 | F30: 35.7 | G30: 4044.4339 | H30: 144386.29 | I30: 35.7 | J30: 4044.4339 | K30: 144386.29 | L30: 49.98 | M30: 4044.4339 | N30: 202140.81 | O30: 71.5 | P30: 4040.5956 | Q30: 288902.58 | R30: 81.85 | S30: 4053.1517 | T30: 331750.47 | U30: 64.1 | V30: 4051.2843 | W30: 259687.32 | X30: 57.12 | Y30: 4044.4339 | Z30: 231018.07 | AA30: 64.46 | AB30: 4035.9188 | AC30: 260155.32 | AD30: 57.2 | AE30: 4040.5956 | AF30: 231122.07 | AG30: 85.2 | AH30: 4059.8955 | AI30: 345903.1 | AJ30: 71.26 | AK30: 4049.8257 | AL30: 288590.58 | AM30: 35.7 | AN30: 4044.4339 | AO30: 144386.29
A31: =+$C$4&B31 -> Véhicules neufs
A32: =+$C$4&B32 -> Véhicules neufs
A33: =+$C$4&B33 -> Véhicules neufsDEPENSES | B33: DEPENSES
A34: =+$C$4&B34 -> Véhicules neufsComm. vendeurs | B34: Comm. vendeurs | C34: 0.34 | D34: 922.38313 | E34: 613380.17 | F34: 0.34 | G34: 921.46858 | H34: 30823.124 | I34: 0.34 | J34: 921.46858 | K34: 30823.124 | L34: 0.34 | M34: 921.46858 | N34: 43152.374 | O34: 0.34 | P34: 920.09325 | Q34: 61646.248 | R34: 0.34 | S34: 924.59322 | T34: 70893.185 | U34: 0.34 | V34: 923.92378 | W34: 55481.623 | X34: 0.34 | Y34: 921.46858 | Z34: 49316.998 | AA34: 0.34 | AB34: 918.41786 | AC34: 55481.623 | AD34: 0.34 | AE34: 920.09325 | AF34: 49316.998 | AG34: 0.34 | AH34: 927.01125 | AI34: 73975.497 | AJ34: 0.34 | AK34: 923.40096 | AL34: 61646.248 | AM34: 0.34 | AN34: 921.46858 | AO34: 30823.124
A35: =+$C$4&B35 -> Véhicules neufsComm. F&I | B35: Comm. F&I | C35: 0.3 | D35: 390 | E35: 259348.05 | F35: 0.3 | G35: 390 | H35: 13045.5 | I35: 0.3 | J35: 390 | K35: 13045.5 | L35: 0.3 | M35: 390 | N35: 18263.7 | O35: 0.3 | P35: 390 | Q35: 26130 | R35: 0.3 | S35: 390 | T35: 29903.25 | U35: 0.3 | V35: 390 | W35: 23419.5 | X35: 0.3 | Y35: 390 | Z35: 20872.8 | AA35: 0.3 | AB35: 390 | AC35: 23559.9 | AD35: 0.3 | AE35: 390 | AF35: 20904 | AG35: 0.3 | AH35: 390 | AI35: 31122 | AJ35: 0.3 | AK35: 390 | AL35: 26036.4 | AM35: 0.3 | AN35: 390 | AO35: 13045.5
A36: =+$C$4&B36 -> Véhicules neufsFrais de livraison | B36: Frais de livraison | D36: 115 | E36: 76474.425 | G36: 115 | H36: 3846.75 | J36: 115 | K36: 3846.75 | M36: 115 | N36: 5385.45 | P36: 115 | Q36: 7705 | S36: 115 | T36: 8817.625 | V36: 115 | W36: 6905.75 | Y36: 115 | Z36: 6154.8 | AB36: 115 | AC36: 6947.15 | AE36: 115 | AF36: 6164 | AH36: 115 | AI36: 9177 | AK36: 115 | AL36: 7677.4 | AN36: 115 | AO36: 3846.75
A37: =+$C$4&B37 -> Véhicules neufsService gratuit 1 | B37: Service gratuit 1 | D37: 3 | E37: 1994.985 | G37: 3 | H37: 100.35 | J37: 3 | K37: 100.35 | M37: 3 | N37: 140.49 | P37: 3 | Q37: 201 | S37: 3 | T37: 230.025 | V37: 3 | W37: 180.15 | Y37: 3 | Z37: 160.56 | AB37: 3 | AC37: 181.23 | AE37: 3 | AF37: 160.8 | AH37: 3 | AI37: 239.4 | AK37: 3 | AL37: 200.28 | AN37: 3 | AO37: 100.35
A38: =+$C$4&B38 -> Véhicules neufsEntretien stock | B38: Entretien stock | D38: 85.05 | E38: 56557.825 | G38: 85.05 | H38: 2844.9225 | J38: 85.05 | K38: 2844.9225 | M38: 85.05 | N38: 3982.8915 | P38: 85.05 | Q38: 5698.35 | S38: 85.05 | T38: 6521.2087 | V38: 85.05 | W38: 5107.2525 | Y38: 85.05 | Z38: 4551.876 | AB38: 85.05 | AC38: 5137.8705 | AE38: 85.05 | AF38: 4558.68 | AH38: 85.05 | AI38: 6786.99 | AK38: 85.05 | AL38: 5677.938 | AN38: 85.05 | AO38: 2844.9225
A39: =+$C$4&B39 -> Véhicules neufsPublicité 1 | B39: Publicité 1 | D39: 116.29035 | E39: 77332.5 | G39: 191.06129 | H39: 6391 | J39: 191.06129 | K39: 6391 | M39: 203.99317 | N39: 9553 | P39: 112.47761 | Q39: 7536 | S39: 26.977502 | T39: 2068.5 | V39: 137.06911 | W39: 8231 | Y39: 165.99402 | Z39: 8884 | AB39: 61.16537 | AC39: 3695 | AE39: 81.641791 | AF39: 4376 | AH39: 78.39599 | AI39: 6256 | AK39: 113.24146 | AL39: 7560 | AN39: 191.06129 | AO39: 6391
A40: =+$C$4&B40 -> Véhicules neufsIntérêt de gros | B40: Intérêt de gros | D40: 306.72127 | E40: 203968.11 | G40: 376.75365 | H40: 12602.41 | J40: 457.45429 | K40: 15301.846 | M40: 413.62169 | N40: 19369.904 | P40: 318.30489 | Q40: 21326.428 | S40: 234.37935 | T40: 17971.036 | V40: 277.29499 | W40: 16651.564 | Y40: 337.05324 | Z40: 18039.089 | AB40: 275.89285 | AC40: 16666.687 | AE40: 409.69588 | AF40: 21959.699 | AH40: 242.16209 | AI40: 19324.535 | AK40: 188.77187 | AL40: 12602.41 | AN40: 363.30355 | AO40: 12152.504
A41: =+$C$4&B41 -> Véhicules neufs[...] | B41: [...] | D41: 0 | E41: 0 | G41: 0 | J41: 0 | M41: 0 | P41: 0 | S41: 0 | V41: 0 | Y41: 0 | AB41: 0 | AE41: 0 | AH41: 0 | AK41: 0 | AN41: 0
A42: =+$C$4&B42 -> Véhicules neufs[...] | B42: [...] | D42: 0 | E42: 0 | G42: 0 | J42: 0 | M42: 0 | P42: 0 | S42: 0 | V42: 0 | Y42: 0 | AB42: 0 | AE42: 0 | AH42: 0 | AK42: 0 | AN42: 0
A43: =+$C$4&B43 -> Véhicules neufs[...] | B43: [...] | D43: 0 | E43: 0 | G43: 0 | J43: 0 | M43: 0 | P43: 0 | S43: 0 | V43: 0 | Y43: 0 | AB43: 0 | AE43: 0 | AH43: 0 | AK43: 0 | AN43: 0
A44: =+$C$4&B44 -> Véhicules neufsTOTAL VARIABLES | B44: TOTAL VARIABLES | C44: % brut | D44: 0.44876861 | E44: 1289056.1 | F44: % brut | G44: 0.48241461 | H44: 69654.056 | I44: % brut | J44: 0.50111054 | K44: 72353.492 | L44: % brut | M44: 0.49395177 | N44: 99847.809 | O44: % brut | P44: 0.45081987 | Q44: 130243.03 | R44: % brut | S44: 0.41116695 | T44: 136404.83 | U44: % brut | V44: 0.44660185 | W44: 115976.84 | X44: % brut | Y44: 0.46740987 | Z44: 107980.12 | AA44: % brut | AB44: 0.4292415 | AC44: 111669.46 | AD44: % brut | AE44: 0.46486335 | AF44: 107440.18 | AG44: % brut | AH44: 0.42463171 | AI44: 146881.42 | AJ44: % brut | AK44: 0.42066749 | AL44: 121400.68 | AM44: % brut | AN44: 0.47929862 | AO44: 69204.15
A45: =+$C$4&B45 -> Véhicules neufsSalaires cadres | B45: Salaires cadres | E45: 230110.85 | H45: 18197.117 | K45: 18197.117 | N45: 21133.479 | Q45: 18197.117 | T45: 21133.479 | W45: 18197.117 | Z45: 18197.117 | AC45: 21133.479 | AF45: 18197.117 | AI45: 18197.117 | AL45: 21133.479 | AO45: 18197.117
A46: =+$C$4&B46 -> Véhicules neufsSalaires commis | B46: Salaires commis | E46: 145957.64 | H46: 11267.511 | K46: 11267.511 | N46: 13954.389 | Q46: 11267.511 | T46: 13954.389 | W46: 11267.511 | Z46: 11267.511 | AC46: 13954.389 | AF46: 11267.511 | AI46: 11267.511 | AL46: 13954.389 | AO46: 11267.511
A47: =+$C$4&B47 -> Véhicules neufsSalaires autres | B47: Salaires autres | E47: 34636.6 | H47: 2664.3538 | K47: 2664.3538 | N47: 3330.4423 | Q47: 2664.3538 | T47: 3330.4423 | W47: 2664.3538 | Z47: 2664.3538 | AC47: 3330.4423 | AF47: 2664.3538 | AI47: 2664.3538 | AL47: 3330.4423 | AO47: 2664.3538
A48: =+$C$4&B48 -> Véhicules neufsSalaires spécialistes | B48: Salaires spécialistes | E48: 0 | H48: 0 | K48: 0 | N48: 0 | Q48: 0 | T48: 0 | W48: 0 | Z48: 0 | AC48: 0 | AF48: 0 | AI48: 0 | AL48: 0 | AO48: 0
A49: =+$C$4&B49 -> Véhicules neufs[...] | B49: [...] | E49: 0 | H49: 0 | K49: 0 | N49: 0 | Q49: 0 | T49: 0 | W49: 0 | Z49: 0 | AC49: 0 | AF49: 0 | AI49: 0 | AL49: 0 | AO49: 0
A50: =+$C$4&B50 -> Véhicules neufs[...] | B50: [...] | E50: 0 | H50: 0 | K50: 0 | N50: 0 | Q50: 0 | T50: 0 | W50: 0 | Z50: 0 | AC50: 0 | AF50: 0 | AI50: 0 | AL50: 0 | AO50: 0
A51: =+$C$4&B51 -> Véhicules neufs[...] | B51: [...] | E51: 0 | H51: 0 | K51: 0 | N51: 0 | Q51: 0 | T51: 0 | W51: 0 | Z51: 0 | AC51: 0 | AF51: 0 | AI51: 0 | AL51: 0 | AO51: 0
A52: =+$C$4&B52 -> Véhicules neufsSalaires en absences | B52: Salaires en absences | E52: 138466.76 | H52: 10293.566 | K52: 8944.9153 | N52: 12708.148 | Q52: 12428.152 | T52: 14002.318 | W52: 10829.041 | Z52: 11005.095 | AC52: 12098.266 | AF52: 11438.922 | AI52: 12326.505 | AL52: 13494.083 | AO52: 8897.7484
A53: =+$C$4&B53 -> Véhicules neufsDéduction à la source | B53: Déduction à la source | E53: 168356.06 | H53: 12515.525 | K53: 10875.756 | N53: 15451.316 | Q53: 15110.881 | T53: 17024.845 | W53: 13166.587 | Z53: 13380.644 | AC53: 14709.786 | AF53: 13908.117 | AI53: 14987.292 | AL53: 16406.903 | AO53: 10818.408
A54: =+$C$4&B54 -> Véhicules neufsBénéfices marginaux | B54: Bénéfices marginaux | E54: 86739.969 | H54: 6448.2161 | K54: 5603.3787 | N54: 7960.7867 | Q54: 7785.3886 | T54: 8771.4961 | W54: 6783.6545 | Z54: 6893.9403 | AC54: 7578.7374 | AF54: 7165.7038 | AI54: 7721.7137 | AL54: 8453.1217 | AO54: 5573.8318
A55: =+$C$4&B55 -> Véhicules neufsCsst | B55: Csst | E55: 37819.115 | H55: 2811.4585 | K55: 2443.1046 | N55: 3470.9478 | Q55: 3394.4732 | T55: 3824.4216 | W55: 2957.7115 | Z55: 3005.7967 | AC55: 3304.3721 | AF55: 3124.2872 | AI55: 3366.7106 | AL55: 3685.6086 | AO55: 2430.222
A56: =+$C$4&B56 -> Véhicules neufs[...] | B56: [...] | E56: 0
A57: =+$C$4&B57 -> Véhicules neufsTOTAL PERSONNEL | B57: TOTAL PERSONNEL | C57: % brut | D57: 0.29316197 | E57: 842086.99 | F57: % brut | G57: 0.44462495 | H57: 64197.747 | I57: % brut | J57: 0.41552516 | K57: 59996.136 | L57: % brut | M57: 0.38591667 | N57: 78009.508 | O57: % brut | P57: 0.24523102 | Q57: 70847.876 | R57: % brut | S57: 0.24729849 | T57: 82041.391 | U57: % brut | V57: 0.2536357 | W57: 65865.975 | X57: % brut | Y57: 0.28748599 | Z57: 66414.457 | AA57: % brut | AB57: 0.29255396 | AC57: 76109.471 | AD57: % brut | AE57: 0.29320442 | AF57: 67766.012 | AG57: % brut | AH57: 0.20390451 | AI57: 70531.203 | AJ57: % brut | AK57: 0.27879644 | AL57: 80458.027 | AM57: % brut | AN57: 0.41450744 | AO57: 59849.192
A58: =+$C$4&B58 -> Véhicules neufsPublicité 2 | B58: Publicité 2 | E58: 0 | H58: 0 | K58: 0 | N58: 0 | Q58: 0 | T58: 0 | W58: 0 | Z58: 0 | AC58: 0 | AF58: 0 | AI58: 0 | AL58: 0 | AO58: 0
A59: =+$C$4&B59 -> Véhicules neufsService gratuit 2 | B59: Service gratuit 2 | E59: 0 | H59: 0 | K59: 0 | N59: 0 | Q59: 0 | T59: 0 | W59: 0 | Z59: 0 | AC59: 0 | AF59: 0 | AI59: 0 | AL59: 0 | AO59: 0
A60: =+$C$4&B60 -> Véhicules neufsFrais véhicules de cie | B60: Frais véhicules de cie | E60: 110400 | H60: 9200 | K60: 9200 | N60: 9200 | Q60: 9200 | T60: 9200 | W60: 9200 | Z60: 9200 | AC60: 9200 | AF60: 9200 | AI60: 9200 | AL60: 9200 | AO60: 9200
A61: =+$C$4&B61 -> Véhicules neufsInformatique | B61: Informatique | E61: 108476.35 | H61: 9039.6955 | K61: 9039.6955 | N61: 9039.6955 | Q61: 9039.6955 | T61: 9039.6955 | W61: 9039.6955 | Z61: 9039.6955 | AC61: 9039.6955 | AF61: 9039.6955 | AI61: 9039.6955 | AL61: 9039.6955 | AO61: 9039.6955
A62: =+$C$4&B62 -> Véhicules neufsFrais de déplacement | B62: Frais de déplacement | E62: 13262.711 | H62: 1105.2259 | K62: 1105.2259 | N62: 1105.2259 | Q62: 1105.2259 | T62: 1105.2259 | W62: 1105.2259 | Z62: 1105.2259 | AC62: 1105.2259 | AF62: 1105.2259 | AI62: 1105.2259 | AL62: 1105.2259 | AO62: 1105.2259
A63: =+$C$4&B63 -> Véhicules neufsServices extérieurs | B63: Services extérieurs | E63: 80537.024 | H63: 6711.4186 | K63: 6711.4186 | N63: 6711.4186 | Q63: 6711.4186 | T63: 6711.4186 | W63: 6711.4186 | Z63: 6711.4186 | AC63: 6711.4186 | AF63: 6711.4186 | AI63: 6711.4186 | AL63: 6711.4186 | AO63: 6711.4186
A64: =+$C$4&B64 -> Véhicules neufsFournitures autres | B64: Fournitures autres | E64: 1500 | H64: 125 | K64: 125 | N64: 125 | Q64: 125 | T64: 125 | W64: 125 | Z64: 125 | AC64: 125 | AF64: 125 | AI64: 125 | AL64: 125 | AO64: 125
A65: =+$C$4&B65 -> Véhicules neufsUniformes | B65: Uniformes | E65: 1000 | H65: 83.333333 | K65: 83.333333 | N65: 83.333333 | Q65: 83.333333 | T65: 83.333333 | W65: 83.333333 | Z65: 83.333333 | AC65: 83.333333 | AF65: 83.333333 | AI65: 83.333333 | AL65: 83.333333 | AO65: 83.333333
A66: =+$C$4&B66 -> Véhicules neufsPapeterie | B66: Papeterie | E66: 9083.3592 | H66: 756.9466 | K66: 756.9466 | N66: 756.9466 | Q66: 756.9466 | T66: 756.9466 | W66: 756.9466 | Z66: 756.9466 | AC66: 756.9466 | AF66: 756.9466 | AI66: 756.9466 | AL66: 756.9466 | AO66: 756.9466
A67: =+$C$4&B67 -> Véhicules neufsTéléphone | B67: Téléphone | E67: 3712.8418 | H67: 309.40349 | K67: 309.40349 | N67: 309.40349 | Q67: 309.40349 | T67: 309.40349 | W67: 309.40349 | Z67: 309.40349 | AC67: 309.40349 | AF67: 309.40349 | AI67: 309.40349 | AL67: 309.40349 | AO67: 309.40349
A68: =+$C$4&B68 -> Véhicules neufsFrais postaux | B68: Frais postaux | E68: 1357.5457 | H68: 113.12881 | K68: 113.12881 | N68: 113.12881 | Q68: 113.12881 | T68: 113.12881 | W68: 113.12881 | Z68: 113.12881 | AC68: 113.12881 | AF68: 113.12881 | AI68: 113.12881 | AL68: 113.12881 | AO68: 113.12881
A69: =+$C$4&B69 -> Véhicules neufsDivers | B69: Divers | E69: 3389.5512 | H69: 282.4626 | K69: 282.4626 | N69: 282.4626 | Q69: 282.4626 | T69: 282.4626 | W69: 282.4626 | Z69: 282.4626 | AC69: 282.4626 | AF69: 282.4626 | AI69: 282.4626 | AL69: 282.4626 | AO69: 282.4626
... A71: =+$C$4&B71 -> Véhicules neufsFrais bancaires | B71: Frais bancaires | E71: 40359.551 | H71: 3363.2959 | K71: 3363.2959 | N71: 3363.2959 | Q71: 3363.2959 | T71: 3363.2959 | W71: 3363.2959 | Z71: 3363.2959 | AC71: 3363.2959 | AF71: 3363.2959 | AI71: 3363.2959 | AL71: 3363.2959 | AO71: 3363.2959
A72: =+$C$4&B72 -> Véhicules neufs[...] | B72: [...] | E72: 0
A73: =+$C$4&B73 -> Véhicules neufs[...] | B73: [...] | E73: 0
A74: =+$C$4&B74 -> Véhicules neufs[...] | B74: [...] | E74: 0
A75: =+$C$4&B75 -> Véhicules neufsTOTAL SEMI-FIXES | B75: TOTAL SEMI-FIXES | C75: % brut | D75: 0.13781653 | E75: 395868.22 | F75: % brut | G75: 0.2284775 | H75: 32989.018 | I75: % brut | J75: 0.2284775 | K75: 32989.018 | L75: % brut | M75: 0.16319821 | N75: 32989.018 | O75: % brut | P75: 0.11418734 | Q75: 32989.018 | R75: % brut | S75: 0.099439251 | T75: 32989.018 | U75: % brut | V75: 0.12703361 | W75: 32989.018 | X75: % brut | Y75: 0.14279844 | Z75: 32989.018 | AA75: % brut | AB75: 0.12680509 | AC75: 32989.018 | AD75: % brut | AE75: 0.14273418 | AF75: 32989.018 | AG75: % brut | AH75: 0.095370693 | AI75: 32989.018 | AJ75: % brut | AK75: 0.11431079 | AL75: 32989.018 | AM75: % brut | AN75: 0.2284775 | AO75: 32989.018
A76: =+$C$4&B76 -> Véhicules neufs
A77: =+$C$4&B77 -> Véhicules neufsTOTAL DES DÉPENSES | B77: TOTAL DES DÉPENSES | C77: % brut | D77: 0.87974711 | E77: 2527011.3 | F77: % brut | G77: 1.1555171 | H77: 166840.82 | I77: % brut | J77: 1.1451132 | K77: 165338.65 | L77: % brut | M77: 1.0430667 | N77: 210846.34 | O77: % brut | P77: 0.81023824 | Q77: 234079.92 | R77: % brut | S77: 0.7579047 | T77: 251435.24 | U77: % brut | V77: 0.82727116 | W77: 214831.83 | X77: % brut | Y77: 0.89769429 | Z77: 207383.6 | AA77: % brut | AB77: 0.84860055 | AC77: 220767.95 | AD77: % brut | AE77: 0.90080195 | AF77: 208195.21 | AG77: % brut | AH77: 0.72390691 | AI77: 250401.64 | AJ77: % brut | AK77: 0.81377472 | AL77: 234847.72 | AM77: % brut | AN77: 1.1222836 | AO77: 162042.36
A78: =+$C$4&B78 -> Véhicules neufsProgramme neuf 1 | B78: Programme neuf 1 | E78: 80000 | H78: 0 | K78: 0 | N78: 20000 | Q78: 0 | T78: 0 | W78: 20000 | Z78: 0 | AC78: 0 | AF78: 20000 | AI78: 0 | AL78: 0 | AO78: 20000
A79: =+$C$4&B79 -> Véhicules neufsProgramme neuf 2 | B79: Programme neuf 2 | E79: 0 | H79: 0 | K79: 0 | N79: 0 | Q79: 0 | T79: 0 | W79: 0 | Z79: 0 | AC79: 0 | AF79: 0 | AI79: 0 | AL79: 0 | AO79: 0
A80: =+$C$4&B80 -> Véhicules neufsProgramme neuf 3 | B80: Programme neuf 3 | E80: 0 | H80: 0 | K80: 0 | N80: 0 | Q80: 0 | T80: 0 | W80: 0 | Z80: 0 | AC80: 0 | AF80: 0 | AI80: 0 | AL80: 0 | AO80: 0
A81: =+$C$4&B81 -> Véhicules neufsHoldbacks | B81: Holdbacks | E81: 911504.31 | H81: 43066.289 | K81: 43066.289 | N81: 63098.426 | Q81: 93286.912 | T81: 107806 | W81: 82906.113 | Z81: 73114.494 | AC81: 83411.125 | AF81: 73226.719 | AI81: 112505.42 | AL81: 92950.237 | AO81: 43066.289
A82: =+$C$4&B82 -> Véhicules neufs[...] | B82: [...] | E82: 0 | H82: 0 | K82: 0 | N82: 0 | Q82: 0 | T82: 0 | W82: 0 | Z82: 0 | AC82: 0 | AF82: 0 | AI82: 0 | AL82: 0 | AO82: 0
A83: =+$C$4&B83 -> Véhicules neufs[...] | B83: [...] | E83: 0 | H83: 0 | K83: 0 | N83: 0 | Q83: 0 | T83: 0 | W83: 0 | Z83: 0 | AC83: 0 | AF83: 0 | AI83: 0 | AL83: 0 | AO83: 0
A84: =+$C$4&B84 -> Véhicules neufs[...] | B84: [...] | E84: 0 | H84: 0 | K84: 0 | N84: 0 | Q84: 0 | T84: 0 | W84: 0 | Z84: 0 | AC84: 0 | AF84: 0 | AI84: 0 | AL84: 0 | AO84: 0
A85: =+$C$4&B85 -> Véhicules neufsFrais administration | B85: Frais administration | E85: 315240.88 | H85: 15856.972 | K85: 15856.972 | N85: 22199.762 | Q85: 31761.35 | T85: 36347.784 | W85: 28466.702 | Z85: 25371.156 | AC85: 28637.36 | AF85: 25409.08 | AI85: 37829.19 | AL85: 31647.578 | AO85: 15856.972
A86: =+$C$4&B86 -> Véhicules neufsAUTRES REVENUS | B86: AUTRES REVENUS | E86: 1306745.2 | H86: 58923.261 | K86: 58923.261 | N86: 105298.19 | Q86: 125048.26 | T86: 144153.79 | W86: 131372.82 | Z86: 98485.65 | AC86: 112048.49 | AF86: 118635.8 | AI86: 150334.61 | AL86: 124597.82 | AO86: 78923.261
A87: =+$C$4&B87 -> Véhicules neufs
A88: =+$C$4&B88 -> Véhicules neufsPROFIT DÉPARTEMENTAL | B88: PROFIT DÉPARTEMENTAL | E88: 1652163.1 | H88: 36468.731 | K88: 37970.905 | N88: 96592.659 | Q88: 179870.92 | T88: 224469.02 | W88: 176228.31 | Z88: 122120.12 | AC88: 151435.86 | AF88: 141562.66 | AI88: 245836.06 | AL88: 178340.68 | AO88: 61267.192
B92: Budget 2024 | C92: Véhicules usagés
B94: Mois | C94: 2024 | F94: Janvier | I94: Février | L94: Mars | O94: Avril | R94: Mai | U94: Juin | X94: Juillet | AA94: Août | AD94: Septembre | AG94: Octobre | AJ94: Novembre | AM94: Décembre
C95: UNITE | D95: $P/UNITE | E95: $PROFITS | F95: UNITE | G95: $P/UNITE | H95: $PROFITS | I95: UNITE | J95: $P/UNITE | K95: $PROFITS | L95: UNITE | M95: $P/UNITE | N95: $PROFITS | O95: UNITE | P95: $P/UNITE | Q95: $PROFITS | R95: UNITE | S95: $P/UNITE | T95: $PROFITS | U95: UNITE | V95: $P/UNITE | W95: $PROFITS | X95: UNITE | Y95: $P/UNITE | Z95: $PROFITS | AA95: UNITE | AB95: $P/UNITE | AC95: $PROFITS | AD95: UNITE | AE95: $P/UNITE | AF95: $PROFITS | AG95: UNITE | AH95: $P/UNITE | AI95: $PROFITS | AJ95: UNITE | AK95: $P/UNITE | AL95: $PROFITS | AM95: UNITE | AN95: $P/UNITE | AO95: $PROFITS
A96: =+$C$92&B96 -> Véhicules usagésVentes nettes | B96: Ventes nettes | E96: 21136590 | H96: 1209133.8 | K96: 1249297.4 | N96: 1879230.7 | Q96: 2101187.1 | T96: 2139236.8 | W96: 1934191.4 | Z96: 1801017.5 | AC96: 1919394.3 | AF96: 1896141.7 | AI96: 1872889.1 | AL96: 1824270.1 | AO96: 1310599.6
A97: =+$C$92&B97 -> Véhicules usagésCertifié | B97: Certifié | C97: 389.961 | D97: 1800 | E97: 701929.8 | F97: 22.308 | G97: 1800 | H97: 40154.4 | I97: 23.049 | J97: 1800 | K97: 41488.2 | L97: 34.671 | M97: 1800 | N97: 62407.8 | O97: 38.766 | P97: 1800 | Q97: 69778.8 | R97: 39.468 | S97: 1800 | T97: 71042.4 | U97: 35.685 | V97: 1800 | W97: 64233 | X97: 33.228 | Y97: 1800 | Z97: 59810.4 | AA97: 35.412 | AB97: 1800 | AC97: 63741.6 | AD97: 34.983 | AE97: 1800 | AF97: 62969.4 | AG97: 34.554 | AH97: 1800 | AI97: 62197.2 | AJ97: 33.657 | AK97: 1800 | AL97: 60582.6 | AM97: 24.18 | AN97: 1800 | AO97: 43524
A98: =+$C$92&B98 -> Véhicules usagésNon Certifié | B98: Non Certifié | C98: 21.9978 | D98: 1800 | E98: 39596.04 | F98: 1.2584 | G98: 1800 | H98: 2265.12 | I98: 1.3002 | J98: 1800 | K98: 2340.36 | L98: 1.9558 | M98: 1800 | N98: 3520.44 | O98: 2.1868 | P98: 1800 | Q98: 3936.24 | R98: 2.2264 | S98: 1800 | T98: 4007.52 | U98: 2.013 | V98: 1800 | W98: 3623.4 | X98: 1.8744 | Y98: 1800 | Z98: 3373.92 | AA98: 1.9976 | AB98: 1800 | AC98: 3595.68 | AD98: 1.9734 | AE98: 1800 | AF98: 3552.12 | AG98: 1.9492 | AH98: 1800 | AI98: 3508.56 | AJ98: 1.8986 | AK98: 1800 | AL98: 3417.48 | AM98: 1.364 | AN98: 1800 | AO98: 2455.2
A99: =+$C$92&B99 -> Véhicules usagésAutres Marques | B99: Autres Marques | C99: 12.9987 | D99: 1800 | E99: 23397.66 | F99: 0.7436 | G99: 1800 | H99: 1338.48 | I99: 0.7683 | J99: 1800 | K99: 1382.94 | L99: 1.1557 | M99: 1800 | N99: 2080.26 | O99: 1.2922 | P99: 1800 | Q99: 2325.96 | R99: 1.3156 | S99: 1800 | T99: 2368.08 | U99: 1.1895 | V99: 1800 | W99: 2141.1 | X99: 1.1076 | Y99: 1800 | Z99: 1993.68 | AA99: 1.1804 | AB99: 1800 | AC99: 2124.72 | AD99: 1.1661 | AE99: 1800 | AF99: 2098.98 | AG99: 1.1518 | AH99: 1800 | AI99: 2073.24 | AJ99: 1.1219 | AK99: 1800 | AL99: 2019.42 | AM99: 0.806 | AN99: 1800 | AO99: 1450.8
A100: =+$C$92&B100 -> Véhicules usagésTotal Usagés | B100: Total Usagés | C100: 424.9575 | D100: 1800 | E100: 764923.5 | F100: 24.31 | G100: 1800 | H100: 43758 | I100: 25.1175 | J100: 1800 | K100: 45211.5 | L100: 37.7825 | M100: 1800 | N100: 68008.5 | O100: 42.245 | P100: 1800 | Q100: 76041 | R100: 43.01 | S100: 1800 | T100: 77418 | U100: 38.8875 | V100: 1800 | W100: 69997.5 | X100: 36.21 | Y100: 1800 | Z100: 65178 | AA100: 38.59 | AB100: 1800 | AC100: 69462 | AD100: 38.1225 | AE100: 1800 | AF100: 68620.5 | AG100: 37.655 | AH100: 1800 | AI100: 67779 | AJ100: 36.6775 | AK100: 1800 | AL100: 66019.5 | AM100: 26.35 | AN100: 1800 | AO100: 47430
A101: =+$C$92&B101 -> Véhicules usagés
A102: =+$C$92&B102 -> Véhicules usagés | F102: 0 | H102: 0
A103: =+$C$92&B103 -> Véhicules usagésVentes au Gros | B103: Ventes au Gros | C103: 434.9565 | D103: 400 | E103: 173982.6 | F103: 24.882 | G103: 400 | H103: 9952.8 | I103: 25.7085 | J103: 400 | K103: 10283.4 | L103: 38.6715 | M103: 400 | N103: 15468.6 | O103: 43.239 | P103: 400 | Q103: 17295.6 | R103: 44.022 | S103: 400 | T103: 17608.8 | U103: 39.8025 | V103: 400 | W103: 15921 | X103: 37.062 | Y103: 400 | Z103: 14824.8 | AA103: 39.498 | AB103: 400 | AC103: 15799.2 | AD103: 39.0195 | AE103: 400 | AF103: 15607.8 | AG103: 38.541 | AH103: 400 | AI103: 15416.4 | AJ103: 37.5405 | AK103: 400 | AL103: 15016.2 | AM103: 26.97 | AN103: 400 | AO103: 10788
A104: =+$C$92&B104 -> Véhicules usagés
A105: =+$C$92&B105 -> Véhicules usagésRev. Finances | B105: Rev. Finances | D105: 700 | E105: 297470.25 | G105: 700 | H105: 17017 | J105: 700 | K105: 17582.25 | M105: 700 | N105: 26447.75 | P105: 700 | Q105: 29571.5 | S105: 700 | T105: 30107 | V105: 700 | W105: 27221.25 | Y105: 700 | Z105: 25347 | AB105: 700 | AC105: 27013 | AE105: 700 | AF105: 26685.75 | AH105: 700 | AI105: 26358.5 | AK105: 700 | AL105: 25674.25 | AN105: 700 | AO105: 18445
A106: =+$C$92&B106 -> Véhicules usagésRev. Protections | B106: Rev. Protections | D106: 1450 | E106: 616188.38 | G106: 1450 | H106: 35249.5 | J106: 1450 | K106: 36420.375 | M106: 1450 | N106: 54784.625 | P106: 1450 | Q106: 61255.25 | S106: 1450 | T106: 62364.5 | V106: 1450 | W106: 56386.875 | Y106: 1450 | Z106: 52504.5 | AB106: 1450 | AC106: 55955.5 | AE106: 1450 | AF106: 55277.625 | AH106: 1450 | AI106: 54599.75 | AK106: 1450 | AL106: 53182.375 | AN106: 1450 | AO106: 38207.5
...

Sheet Réel 2023
B1: ="Réel 2023 Mensuel Révisé"&" "&Parametres!$B$1 -> Réel 2023 Mensuel Révisé Volks
B2: Mois | F2: =+IF(Parametres!$B$3=F$6,"X","") | G2: =+IF(Parametres!$B$3=F$6,"O","") | H2: =+IF(Parametres!$B$3=F$6,"U","") | I2: =+IF(Parametres!$B$3=I$6,"X","") | J2: =+IF(Parametres!$B$3=I$6,"O","") | K2: =+IF(Parametres!$B$3=I$6,"U","") | L2: =+IF(Parametres!$B$3=L$6,"X","") | M2: =+IF(Parametres!$B$3=L$6,"O","") | N2: =+IF(Parametres!$B$3=L$6,"U","") | O2: =+IF(Parametres!$B$3=O$6,"X","") -> X | P2: =+IF(Parametres!$B$3=O$6,"O","") -> O | Q2: =+IF(Parametres!$B$3=O$6,"U","") -> U | R2: =+IF(Parametres!$B$3=R$6,"X","") | S2: =+IF(Parametres!$B$3=R$6,"O","") | T2: =+IF(Parametres!$B$3=R$6,"U","") | U2: =+IF(Parametres!$B$3=U$6,"X","") | V2: =+IF(Parametres!$B$3=U$6,"O","") | W2: =+IF(Parametres!$B$3=U$6,"U","") | X2: =+IF(Parametres!$B$3=X$6,"X","") | Y2: =+IF(Parametres!$B$3=X$6,"O","") | Z2: =+IF(Parametres!$B$3=X$6,"U","") | AA2: =+IF(Parametres!$B$3=AA$6,"X","") | AB2: =+IF(Parametres!$B$3=AA$6,"O","") | AC2: =+IF(Parametres!$B$3=AA$6,"U","") | AD2: =+IF(Parametres!$B$3=AD$6,"X","") | AE2: =+IF(Parametres!$B$3=AD$6,"O","") | AF2: =+IF(Parametres!$B$3=AD$6,"U","") | AG2: =+IF(Parametres!$B$3=AG$6,"X","") | AH2: =+IF(Parametres!$B$3=AG$6,"O","") | AI2: =+IF(Parametres!$B$3=AG$6,"U","") | AJ2: =+IF(Parametres!$B$3=AJ$6,"X","") | AK2: =+IF(Parametres!$B$3=AJ$6,"O","") | AL2: =+IF(Parametres!$B$3=AJ$6,"U","") | AM2: =+IF(Parametres!$B$3=AM$6,"X","") | AN2: =+IF(Parametres!$B$3=AM$6,"O","") | AO2: =+IF(Parametres!$B$3=AM$6,"U","")
B3: YTD | F3: =+IF(VLOOKUP(F$6,Parametres!$K$3:$N$14,4,0)="X","X","") -> X | G3: =+IF(VLOOKUP(F$6,Parametres!$K$3:$N$14,4,0)="X","O","") -> O | H3: =+IF(VLOOKUP(F$6,Parametres!$K$3:$N$14,4,0)="X","U","") -> U | I3: =+IF(VLOOKUP(I$6,Parametres!$K$3:$N$14,4,0)="X","X","") -> X | J3: =+IF(VLOOKUP(I$6,Parametres!$K$3:$N$14,4,0)="X","O","") -> O | K3: =+IF(VLOOKUP(I$6,Parametres!$K$3:$N$14,4,0)="X","U","") -> U | L3: =+IF(VLOOKUP(L$6,Parametres!$K$3:$N$14,4,0)="X","X","") -> X | M3: =+IF(VLOOKUP(L$6,Parametres!$K$3:$N$14,4,0)="X","O","") -> O | N3: =+IF(VLOOKUP(L$6,Parametres!$K$3:$N$14,4,0)="X","U","") -> U | O3: =+IF(VLOOKUP(O$6,Parametres!$K$3:$N$14,4,0)="X","X","") -> X | P3: =+IF(VLOOKUP(O$6,Parametres!$K$3:$N$14,4,0)="X","O","") -> O | Q3: =+IF(VLOOKUP(O$6,Parametres!$K$3:$N$14,4,0)="X","U","") -> U | R3: =+IF(VLOOKUP(R$6,Parametres!$K$3:$N$14,4,0)="X","X","") | S3: =+IF(VLOOKUP(R$6,Parametres!$K$3:$N$14,4,0)="X","O","") | T3: =+IF(VLOOKUP(R$6,Parametres!$K$3:$N$14,4,0)="X","U","") | U3: =+IF(VLOOKUP(U$6,Parametres!$K$3:$N$14,4,0)="X","X","") | V3: =+IF(VLOOKUP(U$6,Parametres!$K$3:$N$14,4,0)="X","O","") | W3: =+IF(VLOOKUP(U$6,Parametres!$K$3:$N$14,4,0)="X","U","") | X3: =+IF(VLOOKUP(X$6,Parametres!$K$3:$N$14,4,0)="X","X","") | Y3: =+IF(VLOOKUP(X$6,Parametres!$K$3:$N$14,4,0)="X","O","") | Z3: =+IF(VLOOKUP(X$6,Parametres!$K$3:$N$14,4,0)="X","U","") | AA3: =+IF(VLOOKUP(AA$6,Parametres!$K$3:$N$14,4,0)="X","X","") | AB3: =+IF(VLOOKUP(AA$6,Parametres!$K$3:$N$14,4,0)="X","O","") | AC3: =+IF(VLOOKUP(AA$6,Parametres!$K$3:$N$14,4,0)="X","U","") | AD3: =+IF(VLOOKUP(AD$6,Parametres!$K$3:$N$14,4,0)="X","X","") | AE3: =+IF(VLOOKUP(AD$6,Parametres!$K$3:$N$14,4,0)="X","O","") | AF3: =+IF(VLOOKUP(AD$6,Parametres!$K$3:$N$14,4,0)="X","U","") | AG3: =+IF(VLOOKUP(AG$6,Parametres!$K$3:$N$14,4,0)="X","X","") | AH3: =+IF(VLOOKUP(AG$6,Parametres!$K$3:$N$14,4,0)="X","O","") | AI3: =+IF(VLOOKUP(AG$6,Parametres!$K$3:$N$14,4,0)="X","U","") | AJ3: =+IF(VLOOKUP(AJ$6,Parametres!$K$3:$N$14,4,0)="X","X","") | AK3: =+IF(VLOOKUP(AJ$6,Parametres!$K$3:$N$14,4,0)="X","O","") | AL3: =+IF(VLOOKUP(AJ$6,Parametres!$K$3:$N$14,4,0)="X","U","") | AM3: =+IF(VLOOKUP(AM$6,Parametres!$K$3:$N$14,4,0)="X","X","") | AN3: =+IF(VLOOKUP(AM$6,Parametres!$K$3:$N$14,4,0)="X","O","") | AO3: =+IF(VLOOKUP(AM$6,Parametres!$K$3:$N$14,4,0)="X","U","")
B4: Réel 2023 | C4: Véhicules neufs
B6: Mois | C6: 2023 | F6: Janvier | I6: Février | L6: Mars | O6: Avril | R6: Mai | U6: Juin | X6: Juillet | AA6: Août | AD6: Septembre | AG6: Octobre | AJ6: Novembre | AM6: Décembre
C7: UNITE | D7: $P/UNITE | E7: $PROFITS | F7: UNITE | G7: $P/UNITE | H7: $PROFITS | I7: UNITE | J7: $P/UNITE | K7: $PROFITS | L7: UNITE | M7: $P/UNITE | N7: $PROFITS | O7: UNITE | P7: $P/UNITE | Q7: $PROFITS | R7: UNITE | S7: $P/UNITE | T7: $PROFITS | U7: UNITE | V7: $P/UNITE | W7: $PROFITS | X7: UNITE | Y7: $P/UNITE | Z7: $PROFITS | AA7: UNITE | AB7: $P/UNITE | AC7: $PROFITS | AD7: UNITE | AE7: $P/UNITE | AF7: $PROFITS | AG7: UNITE | AH7: $P/UNITE | AI7: $PROFITS | AJ7: UNITE | AK7: $P/UNITE | AL7: $PROFITS | AM7: UNITE | AN7: $P/UNITE | AO7: $PROFITS
A8: =+$C$4&B8 -> Véhicules neufsVentes nettes | B8: Ventes nettes | E8: 46883614 | H8: 2000310.4 | K8: 1303139.6 | N8: 2316528.3 | Q8: 1765867 | T8: 2808157.7 | W8: 2851329.3 | Z8: 2122186.9 | AC8: 2567524.5 | AF8: 2612584.6 | AI8: 8285274.9 | AL8: 10151414 | AO8: 8099296.2
A9: =+$C$4&B9 -> Véhicules neufsAutos détail | B9: Autos détail | C9: 160 | D9: 2077.4209 | E9: 332387.34 | F9: 14 | G9: 1585.0143 | H9: 22190.2 | I9: 3 | J9: 908.03333 | K9: 2724.1 | L9: 9 | M9: 2223.0811 | N9: 20007.73 | O9: 12 | P9: 2975.6025 | Q9: 35707.23 | R9: 12 | S9: 2048.03 | T9: 24576.36 | U9: 16 | V9: 2103.4488 | W9: 33655.18 | X9: 12 | Y9: 1882.1942 | Z9: 22586.33 | AA9: 21 | AB9: 2336.3824 | AC9: 49064.03 | AD9: 17 | AE9: 1804.1035 | AF9: 30669.76 | AG9: 14 | AH9: 2125.1657 | AI9: 29752.32 | AJ9: 18 | AK9: 2139.7994 | AL9: 38516.39 | AM9: 12 | AN9: 1911.4758 | AO9: 22937.71
A10: =+$C$4&B10 -> Véhicules neufsCamions détail | B10: Camions détail | C10: 402 | D10: 2485.11 | E10: 999014.21 | F10: 28 | G10: 2112.1561 | H10: 59140.37 | I10: 19 | J10: 2501.8716 | K10: 47535.56 | L10: 29 | M10: 2831.0634 | N10: 82100.84 | O10: 16 | P10: 2481.2725 | Q10: 39700.36 | R10: 34 | S10: 2504.1768 | T10: 85142.01 | U10: 39 | V10: 2445.2556 | W10: 95364.97 | X10: 24 | Y10: 2577.0196 | Z10: 61848.47 | AA10: 22 | AB10: 2712.29 | AC10: 59670.38 | AD10: 36 | AE10: 2493.9233 | AF10: 89781.24 | AG10: 45 | AH10: 2647.1667 | AI10: 119122.5 | AJ10: 71 | AK10: 2320.119 | AL10: 164728.45 | AM10: 39 | AN10: 2432.7964 | AO10: 94879.06
A11: =+$C$4&B11 -> Véhicules neufsSprinter | B11: Sprinter | C11: 0 | D11: 0 | E11: 0 | F11: 0 | G11: 0 | H11: 0 | I11: 0 | J11: 0 | K11: 0 | L11: 0 | M11: 0 | N11: 0 | O11: 0 | P11: 0 | Q11: 0 | R11: 0 | S11: 0 | T11: 0 | U11: 0 | V11: 0 | W11: 0 | X11: 0 | Y11: 0 | Z11: 0 | AA11: 0 | AB11: 0 | AC11: 0 | AD11: 0 | AE11: 0 | AF11: 0 | AG11: 0 | AH11: 0 | AI11: 0 | AJ11: 0 | AK11: 0 | AL11: 0 | AM11: 0 | AN11: 0 | AO11: 0
A12: =+$C$4&B12 -> Véhicules neufsMoto détail | B12: Moto détail | C12: 0 | D12: 0 | E12: 0 | F12: 0 | G12: 0 | H12: 0 | I12: 0 | J12: 0 | K12: 0 | L12: 0 | M12: 0 | N12: 0 | O12: 0 | P12: 0 | Q12: 0 | R12: 0 | S12: 0 | T12: 0 | U12: 0 | V12: 0 | W12: 0 | X12: 0 | Y12: 0 | Z12: 0 | AA12: 0 | AB12: 0 | AC12: 0 | AD12: 0 | AE12: 0 | AF12: 0 | AG12: 0 | AH12: 0 | AI12: 0 | AJ12: 0 | AK12: 0 | AL12: 0 | AM12: 0 | AN12: 0 | AO12: 0
A13: =+$C$4&B13 -> Véhicules neufs[...] | B13: [...] | C13: 0 | D13: 0 | E13: 0 | G13: 0 | J13: 0 | M13: 0 | P13: 0 | S13: 0 | V13: 0 | Y13: 0 | AB13: 0 | AE13: 0 | AH13: 0 | AK13: 0 | AN13: 0
A14: =+$C$4&B14 -> Véhicules neufs[...] | B14: [...] | C14: 0 | D14: 0 | E14: 0 | G14: 0 | J14: 0 | M14: 0 | P14: 0 | S14: 0 | V14: 0 | Y14: 0 | AB14: 0 | AE14: 0 | AH14: 0 | AK14: 0 | AN14: 0
A15: =+$C$4&B15 -> Véhicules neufs[...] | B15: [...] | C15: 0 | D15: 0 | E15: 0 | G15: 0 | J15: 0 | M15: 0 | P15: 0 | S15: 0 | V15: 0 | Y15: 0 | AB15: 0 | AE15: 0 | AH15: 0 | AK15: 0 | AN15: 0
A16: =+$C$4&B16 -> Véhicules neufsTotal Neufs | B16: Total Neufs | C16: 562 | D16: 2369.0419 | E16: 1331401.5 | F16: 42 | G16: 1936.4421 | H16: 81330.57 | I16: 22 | J16: 2284.53 | K16: 50259.66 | L16: 38 | M16: 2687.0676 | N16: 102108.57 | O16: 28 | P16: 2693.1282 | Q16: 75407.59 | R16: 46 | S16: 2385.182 | T16: 109718.37 | U16: 55 | V16: 2345.8209 | W16: 129020.15 | X16: 36 | Y16: 2345.4111 | Z16: 84434.8 | AA16: 43 | AB16: 2528.7072 | AC16: 108734.41 | AD16: 53 | AE16: 2272.6604 | AF16: 120451 | AG16: 59 | AH16: 2523.302 | AI16: 148874.82 | AJ16: 89 | AK16: 2283.6499 | AL16: 203244.84 | AM16: 51 | AN16: 2310.1327 | AO16: 117816.77
A17: =+$C$4&B17 -> Véhicules neufs
A18: =+$C$4&B18 -> Véhicules neufsEx-Démos et courtoisies | B18: Ex-Démos et courtoisies | C18: 42 | D18: 2481.1169 | E18: 104206.91 | F18: 3 | G18: 6274.7467 | H18: 18824.24 | I18: 2 | J18: 5044.27 | K18: 10088.54 | L18: 8 | M18: 3142.5462 | N18: 25140.37 | O18: 6 | P18: 1717.8083 | Q18: 10306.85 | R18: 7 | S18: 2567.5443 | T18: 17972.81 | U18: 2 | V18: 1486.73 | W18: 2973.46 | X18: 3 | Y18: 851.18 | Z18: 2553.54 | AA18: 8 | AB18: 1186.9175 | AC18: 9495.34 | AD18: 1 | AE18: 975.83 | AF18: 975.83 | AG18: 0 | AH18: 0 | AI18: 3550 | AJ18: 1 | AK18: 1154.94 | AL18: 1154.94 | AM18: 1 | AN18: 1170.99 | AO18: 1170.99
A19: =+$C$4&B19 -> Véhicules neufs
A20: =+$C$4&B20 -> Véhicules neufsFlottes | B20: Flottes | C20: 26 | D20: 2968.9 | E20: 77191.4 | F20: 1 | G20: 2144.83 | H20: 2144.83 | I20: 1 | J20: 2919.37 | K20: 2919.37 | L20: 0 | M20: 0 | N20: 0 | O20: 3 | P20: 3228.9067 | Q20: 9686.72 | R20: 3 | S20: 1222.9133 | T20: 3668.74 | U20: 2 | V20: 2962.945 | W20: 5925.89 | X20: 1 | Y20: 4279.05 | Z20: 4279.05 | AA20: 4 | AB20: 3473.7725 | AC20: 13895.09 | AD20: 1 | AE20: 3198 | AF20: 3198 | AG20: 8 | AH20: 3193.38 | AI20: 25547.04 | AJ20: 2 | AK20: 3324.41 | AL20: 6648.82 | AM20: 0 | AN20: 0 | AO20: -722.15
A21: =+$C$4&B21 -> Véhicules neufs
A22: =+$C$4&B22 -> Véhicules neufsRachat bail | B22: Rachat bail | E22: 99141.1 | H22: 5000.4 | K22: 6807.17 | N22: 11489.37 | Q22: 7229.27 | T22: 12671.61 | W22: 12900.75 | Z22: 9971 | AC22: 7757.94 | AF22: 7932.08 | AI22: 8229.71 | AL22: 3732.16 | AO22: 5419.64
A23: =+$C$4&B23 -> Véhicules neufs
A24: =+$C$4&B24 -> Véhicules neufsRev. Finances | B24: Rev. Finances | D24: 138.28978 | E24: 83527.03 | G24: 214.11533 | H24: 9635.19 | J24: 516.52875 | K24: 12396.69 | M24: 256.81543 | N24: 11813.51 | P24: 71.606765 | Q24: 2434.63 | S24: 136.53245 | T24: 7236.22 | V24: 89.401579 | W24: 5095.89 | Y24: 247.8859 | Z24: 9667.55 | AB24: 175.29412 | AC24: 8940 | AE24: 92.308148 | AF24: 4984.64 | AH24: 59.010339 | AI24: 3481.61 | AK24: 48.026889 | AL24: 4322.42 | AN24: 67.666923 | AO24: 3518.68
A25: =+$C$4&B25 -> Véhicules neufsRev. Protections | B25: Rev. Protections | D25: 972.14964 | E25: 587178.38 | G25: 653.30889 | H25: 29398.9 | J25: 943.50875 | K25: 22644.21 | M25: 1021.8824 | N25: 47006.59 | P25: 913.24941 | Q25: 31050.48 | S25: 1002.9296 | T25: 53155.27 | V25: 868.40772 | W25: 49499.24 | Y25: 1110.4236 | Z25: 43306.52 | AB25: 1030.0339 | AC25: 52531.73 | AE25: 1111.505 | AF25: 60021.27 | AH25: 942.08305 | AI25: 55582.9 | AK25: 993.18356 | AL25: 89386.52 | AN25: 1030.6683 | AO25: 53594.75
A26: =+$C$4&B26 -> Véhicules neufsRev. Autres | B26: Rev. Autres | D26: 12.821325 | E26: 7744.08 | G26: 0 | H26: 0 | J26: 0 | K26: 0 | M26: 13.392826 | N26: 616.07 | P26: 0 | Q26: 0 | S26: 32.927736 | T26: 1745.17 | V26: 0 | W26: 0 | Y26: 0 | Z26: 0 | AB26: 12.943529 | AC26: 660.12 | AE26: 9.5077778 | AF26: 513.42 | AH26: 6.749322 | AI26: 398.21 | AK26: 15.009333 | AL26: 1350.84 | AN26: 47.3125 | AO26: 2460.25
A27: =+$C$4&B27 -> Véhicules neufsTotal F&I | B27: Total F&I | C27: 604 | D27: 1123.2607 | E27: 678449.49 | F27: 45 | G27: 867.42422 | H27: 39034.09 | I27: 24 | J27: 1460.0375 | K27: 35040.9 | L27: 46 | M27: 1292.0907 | N27: 59436.17 | O27: 34 | P27: 984.85618 | Q27: 33485.11 | R27: 53 | S27: 1172.3898 | T27: 62136.66 | U27: 57 | V27: 957.8093 | W27: 54595.13 | X27: 39 | Y27: 1358.3095 | Z27: 52974.07 | AA27: 51 | AB27: 1218.2716 | AC27: 62131.85 | AD27: 54 | AE27: 1213.3209 | AF27: 65519.33 | AG27: 59 | AH27: 1007.8427 | AI27: 59462.72 | AJ27: 90 | AK27: 1056.2198 | AL27: 95059.78 | AM27: 52 | AN27: 1145.6477 | AO27: 59573.68
A28: =+$C$4&B28 -> Véhicules neufs
A29: =+$C$4&B29 -> Véhicules neufs
A30: =+$C$4&B30 -> Véhicules neufsTotal Dépt. Neufs | B30: Total Dépt. Neufs | C30: 630 | D30: 3635.5404 | E30: 2290390.4 | F30: 46 | G30: 3181.1767 | H30: 146334.13 | I30: 25 | J30: 4204.6256 | K30: 105115.64 | L30: 46 | M30: 4308.1409 | N30: 198174.48 | O30: 37 | P30: 3678.7984 | Q30: 136115.54 | R30: 56 | S30: 3681.5748 | T30: 206168.19 | U30: 59 | V30: 3481.6166 | W30: 205415.38 | X30: 40 | Y30: 3855.3115 | Z30: 154212.46 | AA30: 55 | AB30: 3672.9933 | AC30: 202014.63 | AD30: 55 | AE30: 3601.3862 | AF30: 198076.24 | AG30: 67 | AH30: 3666.6312 | AI30: 245664.29 | AJ30: 92 | AK30: 3367.832 | AL30: 309840.54 | AM30: 52 | AN30: 3524.2102 | AO30: 183258.93
A31: =+$C$4&B31 -> Véhicules neufs
A32: =+$C$4&B32 -> Véhicules neufs
A33: =+$C$4&B33 -> Véhicules neufsDEPENSES | B33: DEPENSES
A34: =+$C$4&B34 -> Véhicules neufsComm. vendeurs | B34: Comm. vendeurs | C34: 0.29849572 | D34: 709.47513 | E34: 428522.98 | F34: 0.20080094 | G34: 446.91511 | H34: 20111.18 | I34: 0.37480389 | J34: 942.4475 | K34: 22618.74 | L34: 0.34224819 | M34: 946.75478 | N34: 43550.72 | O34: 0.43277959 | P34: 1091.0429 | Q34: 37095.46 | R34: 0.32730601 | S34: 788.56774 | T34: 41794.09 | U34: 0.33310605 | V34: 771.36614 | W34: 43967.87 | X34: 0.37701685 | Y34: 840.92487 | Z34: 32796.07 | AA34: 0.35356676 | AB34: 819.64922 | AC34: 41802.11 | AD34: 0.19647832 | AE34: 441.81 | AF34: 23857.74 | AG34: 0.27493521 | AH34: 710.28729 | AI34: 41906.95 | AJ34: 0.22021937 | AK34: 500.14211 | AL34: 45012.79 | AM34: 0.2858215 | AN34: 654.02423 | AO34: 34009.26
A35: =+$C$4&B35 -> Véhicules neufsComm. F&I | B35: Comm. F&I | C35: 0.30598639 | D35: 343.7025 | E35: 207596.31 | F35: 0.42056546 | G35: 364.80867 | H35: 16416.39 | I35: 0.28643557 | J35: 418.20667 | K35: 10036.96 | L35: 0.29836781 | M35: 385.51826 | N35: 17733.84 | O35: 0.2997816 | P35: 295.24176 | Q35: 10038.22 | R35: 0.29997187 | S35: 351.68396 | T35: 18639.25 | U35: 0.30010864 | V35: 287.44684 | W35: 16384.47 | X35: 0.30073846 | Y35: 408.4959 | Z35: 15931.34 | AA35: 0.2998974 | AB35: 365.35647 | AC35: 18633.18 | AD35: 0.30030542 | AE35: 364.36685 | AF35: 19675.81 | AG35: 0.29873305 | AH35: 301.07593 | AI35: 17763.48 | AJ35: 0.29960999 | AK35: 316.454 | AL35: 28480.86 | AM35: 0.29983896 | AN35: 343.50981 | AO35: 17862.51
A36: =+$C$4&B36 -> Véhicules neufsFrais de livraison | B36: Frais de livraison | D36: 122.55435 | E36: 74022.83 | G36: 58.516222 | H36: 2633.23 | J36: 245.49917 | K36: 5891.98 | M36: 64.906087 | N36: 2985.68 | P36: 99.448824 | Q36: 3381.26 | S36: 112.82151 | T36: 5979.54 | V36: 98.259649 | W36: 5600.8 | Y36: 168.41974 | Z36: 6568.37 | AB36: 121.67235 | AC36: 6205.29 | AE36: 85.562222 | AF36: 4620.36 | AH36: 131.92102 | AI36: 7783.34 | AK36: 138.78767 | AL36: 12490.89 | AN36: 190.04019 | AO36: 9882.09
A37: =+$C$4&B37 -> Véhicules neufsService gratuit 1 | B37: Service gratuit 1 | D37: 13.843328 | E37: 8361.37 | G37: 0 | H37: 0 | J37: 0 | K37: 0 | M37: 4.5619565 | N37: 209.85 | P37: 2.3529412 | Q37: 80 | S37: 0 | T37: 0 | V37: 0 | W37: 0 | Y37: 1.025641 | Z37: 40 | AB37: 1.8039216 | AC37: 92 | AE37: 3.9803704 | AF37: 214.94 | AH37: 9.4247458 | AI37: 556.06 | AK37: 63.110222 | AL37: 5679.92 | AN37: 28.626923 | AO37: 1488.6
A38: =+$C$4&B38 -> Véhicules neufsEntretien stock | B38: Entretien stock | D38: 79.81144 | E38: 48206.11 | G38: 59.264222 | H38: 2666.89 | J38: 125.22542 | K38: 3005.41 | M38: 48.714348 | N38: 2240.86 | P38: 88.82 | Q38: 3019.88 | S38: 66.649057 | T38: 3532.4 | V38: 70.210526 | W38: 4002 | Y38: 118.07769 | Z38: 4605.03 | AB38: 78.708235 | AC38: 4014.12 | AE38: 80.216481 | AF38: 4331.69 | AH38: 92.110169 | AI38: 5434.5 | AK38: 83.834222 | AL38: 7545.08 | AN38: 73.235577 | AO38: 3808.25
A39: =+$C$4&B39 -> Véhicules neufsPublicité 1 | B39: Publicité 1 | D39: 100.76803 | E39: 60863.89 | G39: 7.4604444 | H39: 335.72 | J39: 300.07 | K39: 7201.68 | M39: 87.100652 | N39: 4006.63 | P39: 159.71529 | Q39: 5430.32 | S39: 56.458679 | T39: 2992.31 | V39: 122.48649 | W39: 6981.73 | Y39: 154.58692 | Z39: 6028.89 | AB39: 40.121961 | AC39: 2046.22 | AE39: 102.55352 | AF39: 5537.89 | AH39: 155.86983 | AI39: 9196.32 | AK39: 38.481889 | AL39: 3463.37 | AN39: 146.97712 | AO39: 7642.81
A40: =+$C$4&B40 -> Véhicules neufsIntérêt de gros | B40: Intérêt de gros | D40: 121.38026 | E40: 73313.68 | G40: 153.29867 | H40: 6898.44 | J40: 187.08333 | K40: 4490 | M40: 86.143043 | N40: 3962.58 | P40: 54.914412 | Q40: 1867.09 | S40: 110.78396 | T40: 5871.55 | V40: 83.072632 | W40: 4735.14 | Y40: 90.482564 | Z40: 3528.82 | AB40: 0 | AC40: 0 | AE40: 95.057593 | AF40: 5133.11 | AH40: 0 | AI40: 0 | AK40: 217.76156 | AL40: 19598.54 | AN40: 331.31558 | AO40: 17228.41
A41: =+$C$4&B41 -> Véhicules neufs[...] | B41: [...] | D41: 0 | E41: 0 | G41: 0 | J41: 0 | M41: 0 | P41: 0 | S41: 0 | V41: 0 | Y41: 0 | AB41: 0 | AE41: 0 | AH41: 0 | AK41: 0 | AN41: 0
A42: =+$C$4&B42 -> Véhicules neufs[...] | B42: [...] | D42: 0 | E42: 0 | G42: 0 | J42: 0 | M42: 0 | P42: 0 | S42: 0 | V42: 0 | Y42: 0 | AB42: 0 | AE42: 0 | AH42: 0 | AK42: 0 | AN42: 0
A43: =+$C$4&B43 -> Véhicules neufs[...] | B43: [...] | D43: 0 | E43: 0 | G43: 0 | J43: 0 | M43: 0 | P43: 0 | S43: 0 | V43: 0 | Y43: 0 | AB43: 0 | AE43: 0 | AH43: 0 | AK43: 0 | AN43: 0
A44: =+$C$4&B44 -> Véhicules neufsTOTAL VARIABLES | B44: TOTAL VARIABLES | C44: % brut | D44: 0.39333345 | E44: 900887.17 | F44: % brut | G44: 0.33527278 | H44: 49061.85 | I44: % brut | J44: 0.50653518 | K44: 53244.77 | L44: % brut | M44: 0.37689091 | N44: 74690.16 | O44: % brut | P44: 0.44750386 | Q44: 60912.23 | R44: % brut | S44: 0.38225655 | T44: 78809.14 | U44: % brut | V44: 0.39759443 | W44: 81672.01 | X44: % brut | Y44: 0.45066735 | Z44: 69498.52 | AA44: % brut | AB44: 0.36033489 | AC44: 72792.92 | AD44: % brut | AE44: 0.31993509 | AF44: 63371.54 | AG44: % brut | AH44: 0.33639667 | AI44: 82640.65 | AJ44: % brut | AK44: 0.39462702 | AL44: 122271.45 | AM44: % brut | AN44: 0.50159591 | AO44: 91921.93
A45: =+$C$4&B45 -> Véhicules neufsSalaires cadres | B45: Salaires cadres | E45: 161101.4 | H45: 13320.96 | K45: 9312.96 | N45: 13684.73 | Q45: 13295.96 | T45: 13546.32 | W45: 13776.33 | Z45: 17842.1 | AC45: 14353.64 | AF45: 14161.33 | AI45: 11603.64 | AL45: 14903.64 | AO45: 11299.79
A46: =+$C$4&B46 -> Véhicules neufsSalaires commis | B46: Salaires commis | E46: 144740.67 | H46: 11974.81 | K46: 12588.32 | N46: 13439.44 | Q46: 10544.06 | T46: 12202.83 | W46: 14509.06 | Z46: 9643.58 | AC46: 12006.55 | AF46: 16026.9 | AI46: 11332.89 | AL46: 8776.47 | AO46: 11695.76
A47: =+$C$4&B47 -> Véhicules neufsSalaires autres | B47: Salaires autres | E47: 115434.12 | H47: 11519.26 | K47: 10464.68 | N47: 11841.01 | Q47: 12250.19 | T47: 14212.21 | W47: 13387.76 | Z47: 12343.13 | AC47: 11151.24 | AF47: 6488.86 | AI47: 3994.82 | AL47: 2988 | AO47: 4792.96
A48: =+$C$4&B48 -> Véhicules neufsSalaires spécialistes | B48: Salaires spécialistes | E48: 0 | H48: 0 | K48: 0 | N48: 0 | Q48: 0 | T48: 0 | W48: 0 | Z48: 0 | AC48: 0 | AF48: 0 | AI48: 0 | AL48: 0 | AO48: 0
A49: =+$C$4&B49 -> Véhicules neufs[...] | B49: [...] | E49: 0 | H49: 0 | K49: 0 | N49: 0 | Q49: 0 | T49: 0 | W49: 0 | Z49: 0 | AC49: 0 | AF49: 0 | AI49: 0 | AL49: 0 | AO49: 0
A50: =+$C$4&B50 -> Véhicules neufs[...] | B50: [...] | E50: 0 | H50: 0 | K50: 0 | N50: 0 | Q50: 0 | T50: 0 | W50: 0 | Z50: 0 | AC50: 0 | AF50: 0 | AI50: 0 | AL50: 0 | AO50: 0
A51: =+$C$4&B51 -> Véhicules neufs[...] | B51: [...] | E51: 0 | H51: 0 | K51: 0 | N51: 0 | Q51: 0 | T51: 0 | W51: 0 | Z51: 0 | AC51: 0 | AF51: 0 | AI51: 0 | AL51: 0 | AO51: 0
A52: =+$C$4&B52 -> Véhicules neufsSalaires en absences | B52: Salaires en absences | E52: 126459.04 | H52: 18179.34 | K52: 9804.34 | N52: 6896.42 | Q52: 11060.27 | T52: 12615.57 | W52: 12929.12 | Z52: 10139.23 | AC52: 6780.38 | AF52: 10273.68 | AI52: 9419.91 | AL52: 8803.83 | AO52: 9556.95
A53: =+$C$4&B53 -> Véhicules neufsDéduction à la source | B53: Déduction à la source | E53: 156049.85 | H53: 16049.06 | K53: 16298.39 | N53: 15375.15 | Q53: 16153.21 | T53: 12626.31 | W53: 12404.94 | Z53: 14378.55 | AC53: 10620.12 | AF53: 10461.01 | AI53: 8905.21 | AL53: 11365.4 | AO53: 11412.5
A54: =+$C$4&B54 -> Véhicules neufsBénéfices marginaux | B54: Bénéfices marginaux | E54: 74708.68 | H54: 6493.21 | K54: 5878.89 | N54: 5879.65 | Q54: 9403.86 | T54: 6414.78 | W54: 5591.61 | Z54: 7088.75 | AC54: 5958.04 | AF54: 6088.21 | AI54: 5383.41 | AL54: 6383.81 | AO54: 4144.46
A55: =+$C$4&B55 -> Véhicules neufsCsst | B55: Csst | E55: 24570.02 | H55: 2475.74 | K55: 2534.25 | N55: 2462.53 | Q55: 2775.98 | T55: 2337.24 | W55: 3273.76 | Z55: 2311.3 | AC55: 1830.69 | AF55: 1526.89 | AI55: 686.07 | AL55: 1164.96 | AO55: 1190.61
A56: =+$C$4&B56 -> Véhicules neufs[...] | B56: [...] | E56: 0
A57: =+$C$4&B57 -> Véhicules neufsTOTAL PERSONNEL | B57: TOTAL PERSONNEL | C57: % brut | D57: 0.35062309 | E57: 803063.78 | F57: % brut | G57: 0.54677866 | H57: 80012.38 | I57: % brut | J57: 0.63626907 | K57: 66881.83 | L57: % brut | M57: 0.35109934 | N57: 69578.93 | O57: % brut | P57: 0.55455483 | Q57: 75483.53 | R57: % brut | S57: 0.35871324 | T57: 73955.26 | U57: % brut | V57: 0.36936173 | W57: 75872.58 | X57: % brut | Y57: 0.47821454 | Z57: 73746.64 | AA57: % brut | AB57: 0.31037683 | AC57: 62700.66 | AD57: % brut | AE57: 0.32829218 | AF57: 65026.88 | AG57: % brut | AH57: 0.20892719 | AI57: 51325.95 | AJ57: % brut | AK57: 0.17552935 | AL57: 54386.11 | AM57: % brut | AN57: 0.29517268 | AO57: 54093.03
A58: =+$C$4&B58 -> Véhicules neufsPublicité 2 | B58: Publicité 2 | E58: 0 | H58: 0 | K58: 0 | N58: 0 | Q58: 0 | T58: 0 | W58: 0 | Z58: 0 | AC58: 0 | AF58: 0 | AI58: 0 | AL58: 0 | AO58: 0
A59: =+$C$4&B59 -> Véhicules neufsService gratuit 2 | B59: Service gratuit 2 | E59: 0 | H59: 0 | K59: 0 | N59: 0 | Q59: 0 | T59: 0 | W59: 0 | Z59: 0 | AC59: 0 | AF59: 0 | AI59: 0 | AL59: 0 | AO59: 0
A60: =+$C$4&B60 -> Véhicules neufsFrais véhicules de cie | B60: Frais véhicules de cie | E60: 81122.09 | H60: 9342.87 | K60: 7178.73 | N60: 5765.85 | Q60: 6050.54 | T60: 7607.19 | W60: 5916.23 | Z60: 7279.84 | AC60: 2665.34 | AF60: 5210.85 | AI60: 10080.58 | AL60: 7119.66 | AO60: 6904.41
A61: =+$C$4&B61 -> Véhicules neufsInformatique | B61: Informatique | E61: 84970.74 | H61: 5818.91 | K61: 8139.24 | N61: 7063.11 | Q61: 6422.17 | T61: 9434.75 | W61: 7019.75 | Z61: 7196.92 | AC61: 6738.03 | AF61: 7114.48 | AI61: 6701.59 | AL61: 6760.11 | AO61: 6561.68
A62: =+$C$4&B62 -> Véhicules neufsFrais de déplacement | B62: Frais de déplacement | E62: 17989.31 | H62: 738.56 | K62: 2412.6 | N62: 2012.95 | Q62: 925.52 | T62: 3463.39 | W62: 504.08 | Z62: 818.1 | AC62: 1465.98 | AF62: 1420.02 | AI62: 1507.17 | AL62: 1646.26 | AO62: 1074.68
A63: =+$C$4&B63 -> Véhicules neufsServices extérieurs | B63: Services extérieurs | E63: 81747.97 | H63: 7190.38 | K63: 8043.06 | N63: 5970.74 | Q63: 5703.27 | T63: 6186.31 | W63: 6175.67 | Z63: 5967.65 | AC63: 6269.32 | AF63: 6350.63 | AI63: 8041.2 | AL63: 8387.93 | AO63: 7461.81
A64: =+$C$4&B64 -> Véhicules neufsFournitures autres | B64: Fournitures autres | E64: 471.48 | H64: 0 | K64: 0 | N64: 8.23 | Q64: 0 | T64: 0 | W64: 0 | Z64: 0 | AC64: 0 | AF64: 141.18 | AI64: 0 | AL64: 250.25 | AO64: 71.82
A65: =+$C$4&B65 -> Véhicules neufsUniformes | B65: Uniformes | E65: 0 | H65: 0 | K65: 0 | N65: 0 | Q65: 0 | T65: 0 | W65: 0 | Z65: 0 | AC65: 0 | AF65: 0 | AI65: 0 | AL65: 0 | AO65: 0
A66: =+$C$4&B66 -> Véhicules neufsPapeterie | B66: Papeterie | E66: 10026.72 | H66: 387.75 | K66: 522.87 | N66: 1420.85 | Q66: 783.41 | T66: 536.74 | W66: 605.81 | Z66: 479.83 | AC66: 1114.19 | AF66: 751.79 | AI66: 281.8 | AL66: 2065.76 | AO66: 1075.92
A67: =+$C$4&B67 -> Véhicules neufsTéléphone | B67: Téléphone | E67: 3799.73 | H67: 346.5 | K67: 354.25 | N67: 268.57 | Q67: 233.07 | T67: 338.47 | W67: 232.9 | Z67: 233.9 | AC67: 597.5 | AF67: 294.13 | AI67: 303.89 | AL67: 280.55 | AO67: 316
A68: =+$C$4&B68 -> Véhicules neufsFrais postaux | B68: Frais postaux | E68: 1622.44 | H68: 102.26 | K68: 88.51 | N68: 84.98 | Q68: 129.09 | T68: 115.6 | W68: 81.84 | Z68: 130.12 | AC68: 103.55 | AF68: 133.46 | AI68: 252.96 | AL68: 169.87 | AO68: 230.2
A69: =+$C$4&B69 -> Véhicules neufsDivers | B69: Divers | E69: 1959.26 | H69: 567.02 | K69: 283.39 | N69: 66.3 | Q69: 116.88 | T69: 78.52 | W69: 111.34 | Z69: 106.21 | AC69: 112.7 | AF69: 199.88 | AI69: 120 | AL69: 102.8 | AO69: 94.22
... A71: =+$C$4&B71 -> Véhicules neufsFrais bancaires | B71: Frais bancaires | E71: 42299.27 | H71: 3141.73 | K71: 2483.42 | N71: 357.08 | Q71: 3025.62 | T71: 7746.73 | W71: 3537.15 | Z71: 3406.43 | AC71: 2659.84 | AF71: 3603.56 | AI71: 4006.58 | AL71: 5124.82 | AO71: 3206.31
A72: =+$C$4&B72 -> Véhicules neufs[...] | B72: [...] | E72: 0
A73: =+$C$4&B73 -> Véhicules neufs[...] | B73: [...] | E73: 0
A74: =+$C$4&B74 -> Véhicules neufs[...] | B74: [...] | E74: 0
A75: =+$C$4&B75 -> Véhicules neufsTOTAL SEMI-FIXES | B75: TOTAL SEMI-FIXES | C75: % brut | D75: 0.15179956 | E75: 347680.26 | F75: % brut | G75: 0.19364061 | H75: 28336.23 | I75: % brut | J75: 0.30792858 | K75: 32368.11 | L75: % brut | M75: 0.14977519 | N75: 29681.62 | O75: % brut | P75: 0.1915804 | Q75: 26077.07 | R75: % brut | S75: 0.17602701 | T75: 36291.17 | U75: % brut | V75: 0.12011126 | W75: 24672.7 | X75: % brut | Y75: 0.16727624 | Z75: 25796.08 | AA75: % brut | AB75: 0.1116677 | AC75: 22558.51 | AD75: % brut | AE75: 0.13562455 | AF75: 26864 | AG75: % brut | AH75: 0.13596677 | AI75: 33402.18 | AJ75: % brut | AK75: 0.11005193 | AL75: 34098.55 | AM75: % brut | AN75: 0.15024665 | AO75: 27534.04
A76: =+$C$4&B76 -> Véhicules neufs
A77: =+$C$4&B77 -> Véhicules neufsTOTAL DES DÉPENSES | B77: TOTAL DES DÉPENSES | C77: % brut | D77: 0.8957561 | E77: 2051631.2 | F77: % brut | G77: 1.075692 | H77: 157410.46 | I77: % brut | J77: 1.4507328 | K77: 152494.71 | L77: % brut | M77: 0.87776544 | N77: 173950.71 | O77: % brut | P77: 1.1936391 | Q77: 162472.83 | R77: % brut | S77: 0.9169968 | T77: 189055.57 | U77: % brut | V77: 0.88706741 | W77: 182217.29 | X77: % brut | Y77: 1.0961581 | Z77: 169041.24 | AA77: % brut | AB77: 0.78237942 | AC77: 158052.09 | AD77: % brut | AE77: 0.78385181 | AF77: 155262.42 | AG77: % brut | AH77: 0.68129063 | AI77: 167368.78 | AJ77: % brut | AK77: 0.68020831 | AL77: 210756.11 | AM77: % brut | AN77: 0.94701524 | AO77: 173549
A78: =+$C$4&B78 -> Véhicules neufsProgramme neuf 1 | B78: Programme neuf 1 | E78: 31556 | H78: 0 | K78: 0 | N78: 0 | Q78: 0 | T78: 0 | W78: 0 | Z78: 0 | AC78: 0 | AF78: 0 | AI78: 0 | AL78: 0 | AO78: 31556
A79: =+$C$4&B79 -> Véhicules neufsProgramme neuf 2 | B79: Programme neuf 2 | E79: 0 | H79: 0 | K79: 0 | N79: 0 | Q79: 0 | T79: 0 | W79: 0 | Z79: 0 | AC79: 0 | AF79: 0 | AI79: 0 | AL79: 0 | AO79: 0
A80: =+$C$4&B80 -> Véhicules neufsProgramme neuf 3 | B80: Programme neuf 3 | E80: 0 | H80: 0 | K80: 0 | N80: 0 | Q80: 0 | T80: 0 | W80: 0 | Z80: 0 | AC80: 0 | AF80: 0 | AI80: 0 | AL80: 0 | AO80: 0
A81: =+$C$4&B81 -> Véhicules neufsHoldbacks | B81: Holdbacks | E81: 679516.07 | H81: 49875 | K81: 15765 | N81: 49529.35 | Q81: 39086.08 | T81: 67424.75 | W81: 63469.55 | Z81: 42698.55 | AC81: 59882.85 | AF81: 58938 | AI81: 77258.09 | AL81: 100428 | AO81: 55160.85
A82: =+$C$4&B82 -> Véhicules neufs[...] | B82: [...] | E82: 0 | H82: 0 | K82: 0 | N82: 0 | Q82: 0 | T82: 0 | W82: 0 | Z82: 0 | AC82: 0 | AF82: 0 | AI82: 0 | AL82: 0 | AO82: 0
A83: =+$C$4&B83 -> Véhicules neufs[...] | B83: [...] | E83: 0 | H83: 0 | K83: 0 | N83: 0 | Q83: 0 | T83: 0 | W83: 0 | Z83: 0 | AC83: 0 | AF83: 0 | AI83: 0 | AL83: 0 | AO83: 0
A84: =+$C$4&B84 -> Véhicules neufs[...] | B84: [...] | E84: 0 | H84: 0 | K84: 0 | N84: 0 | Q84: 0 | T84: 0 | W84: 0 | Z84: 0 | AC84: 0 | AF84: 0 | AI84: 0 | AL84: 0 | AO84: 0
A85: =+$C$4&B85 -> Véhicules neufsFrais administration | B85: Frais administration | E85: 271044.9 | H85: 17432 | K85: 9307 | N85: 16474 | Q85: 12599 | T85: 23301 | W85: 26386 | Z85: 19446 | AC85: 26922 | AF85: 25665 | AI85: 29179 | AL85: 41872.9 | AO85: 22461
A86: =+$C$4&B86 -> Véhicules neufsAUTRES REVENUS | B86: AUTRES REVENUS | E86: 982116.97 | H86: 67307 | K86: 25072 | N86: 66003.35 | Q86: 51685.08 | T86: 90725.75 | W86: 89855.55 | Z86: 62144.55 | AC86: 86804.85 | AF86: 84603 | AI86: 106437.09 | AL86: 142300.9 | AO86: 109177.85
A87: =+$C$4&B87 -> Véhicules neufs
A88: =+$C$4&B88 -> Véhicules neufsPROFIT DÉPARTEMENTAL | B88: PROFIT DÉPARTEMENTAL | E88: 1220876.2 | H88: 56230.67 | K88: -22307.07 | N88: 90227.12 | Q88: 25327.79 | T88: 107838.37 | W88: 113053.64 | Z88: 47315.77 | AC88: 130767.39 | AF88: 127416.82 | AI88: 184732.6 | AL88: 241385.33 | AO88: 118887.78
B92: Réel 2023 | C92: Véhicules usagés
B94: Mois | C94: 2023 | F94: Janvier | I94: Février | L94: Mars | O94: Avril | R94: Mai | U94: Juin | X94: Juillet | AA94: Août | AD94: Septembre | AG94: Octobre | AJ94: Novembre | AM94: Décembre
C95: UNITE | D95: $P/UNITE | E95: $PROFITS | F95: UNITE | G95: $P/UNITE | H95: $PROFITS | I95: UNITE | J95: $P/UNITE | K95: $PROFITS | L95: UNITE | M95: $P/UNITE | N95: $PROFITS | O95: UNITE | P95: $P/UNITE | Q95: $PROFITS | R95: UNITE | S95: $P/UNITE | T95: $PROFITS | U95: UNITE | V95: $P/UNITE | W95: $PROFITS | X95: UNITE | Y95: $P/UNITE | Z95: $PROFITS | AA95: UNITE | AB95: $P/UNITE | AC95: $PROFITS | AD95: UNITE | AE95: $P/UNITE | AF95: $PROFITS | AG95: UNITE | AH95: $P/UNITE | AI95: $PROFITS | AJ95: UNITE | AK95: $P/UNITE | AL95: $PROFITS | AM95: UNITE | AN95: $P/UNITE | AO95: $PROFITS
A96: =+$C$92&B96 -> Véhicules usagésVentes nettes | B96: Ventes nettes | E96: 16855455 | H96: 1296133.1 | K96: 1497630.2 | N96: 1620696.6 | Q96: 738971.18 | T96: 1554686.6 | W96: 1977586.1 | Z96: 1727866.7 | AC96: 1894182.2 | AF96: 1244144.3 | AI96: 1412113.8 | AL96: 1111062.8 | AO96: 780381.81
A97: =+$C$92&B97 -> Véhicules usagésCertifié | B97: Certifié | C97: 277 | D97: 1593.4981 | E97: 441398.98 | F97: 24 | G97: 1385.6671 | H97: 33256.01 | I97: 25 | J97: 1372.0904 | K97: 34302.26 | L97: 34 | M97: 1614.0462 | N97: 54877.57 | O97: 15 | P97: 1983.744 | Q97: 29756.16 | R97: 15 | S97: 1755.5307 | T97: 26332.96 | U97: 18 | V97: 2437.2944 | W97: 43871.3 | X97: 32 | Y97: 1795.72 | Z97: 57463.04 | AA97: 35 | AB97: 878.82857 | AC97: 30759 | AD97: 29 | AE97: 1929.9779 | AF97: 55969.36 | AG97: 21 | AH97: 1924.4195 | AI97: 40412.81 | AJ97: 16 | AK97: 1359.5375 | AL97: 21752.6 | AM97: 13 | AN97: 972.76231 | AO97: 12645.91
A98: =+$C$92&B98 -> Véhicules usagésNon Certifié | B98: Non Certifié | C98: 49 | D98: 1832.4292 | E98: 89789.03 | F98: 2 | G98: -934.865 | H98: -1869.73 | I98: 1 | J98: -2595.5 | K98: -2595.5 | L98: 1 | M98: 951 | N98: 951 | O98: 5 | P98: 2587.164 | Q98: 12935.82 | R98: 10 | S98: 2407.581 | T98: 24075.81 | U98: 7 | V98: 1925.8071 | W98: 13480.65 | X98: 4 | Y98: 1612.4725 | Z98: 6449.89 | AA98: 1 | AB98: 3601.1 | AC98: 3601.1 | AD98: 4 | AE98: 2172.4675 | AF98: 8689.87 | AG98: 5 | AH98: 2390.022 | AI98: 11950.11 | AJ98: 4 | AK98: 817.0175 | AL98: 3268.07 | AM98: 5 | AN98: 1770.388 | AO98: 8851.94
A99: =+$C$92&B99 -> Véhicules usagésAutres Marques | B99: Autres Marques
A100: =+$C$92&B100 -> Véhicules usagésTotal Usagés | B100: Total Usagés | C100: 326 | D100: 1629.4111 | E100: 531188.01 | F100: 26 | G100: 1207.1646 | H100: 31386.28 | I100: 26 | J100: 1219.4908 | K100: 31706.76 | L100: 35 | M100: 1595.102 | N100: 55828.57 | O100: 20 | P100: 2134.599 | Q100: 42691.98 | R100: 25 | S100: 2016.3508 | T100: 50408.77 | U100: 25 | V100: 2294.078 | W100: 57351.95 | X100: 36 | Y100: 1775.3592 | Z100: 63912.93 | AA100: 36 | AB100: 954.44722 | AC100: 34360.1 | AD100: 33 | AE100: 1959.3706 | AF100: 64659.23 | AG100: 26 | AH100: 2013.9585 | AI100: 52362.92 | AJ100: 20 | AK100: 1251.0335 | AL100: 25020.67 | AM100: 18 | AN100: 1194.325 | AO100: 21497.85
A101: =+$C$92&B101 -> Véhicules usagés
A102: =+$C$92&B102 -> Véhicules usagés | F102: 0 | H102: 0 | I102: 0 | K102: 0 | L102: 0 | N102: 0 | O102: 0 | Q102: 0 | R102: 0 | T102: 0 | U102: 0 | W102: 0 | X102: 0 | Z102: 0 | AA102: 0 | AC102: 0 | AD102: 0 | AF102: 0 | AG102: 0 | AI102: 0 | AJ102: 0 | AL102: 0 | AM102: 0 | AO102: 0
A103: =+$C$92&B103 -> Véhicules usagésVentes au Gros | B103: Ventes au Gros | C103: 388 | D103: 407.72474 | E103: 158197.2 | F103: 34 | G103: 996.86471 | H103: 33893.4 | I103: 30 | J103: 494.245 | K103: 14827.35 | L103: 32 | M103: 198.24875 | N103: 6343.96 | O103: 10 | P103: 1818 | Q103: 18180 | R103: 43 | S103: 409.93326 | T103: 17627.13 | U103: 57 | V103: 568.81632 | W103: 32422.53 | X103: 28 | Y103: 616.26179 | Z103: 17255.33 | AA103: 38 | AB103: -4.6778947 | AC103: -177.76 | AD103: 26 | AE103: 442.14423 | AF103: 11495.75 | AG103: 38 | AH103: 362.24263 | AI103: 13765.22 | AJ103: 31 | AK103: 15.867742 | AL103: 491.9 | AM103: 21 | AN103: -377.50524 | AO103: -7927.61
A104: =+$C$92&B104 -> Véhicules usagés
A105: =+$C$92&B105 -> Véhicules usagésRev. Finances | B105: Rev. Finances | D105: 652.2084 | E105: 212619.94 | G105: 952.25192 | H105: 24758.55 | J105: 654.84538 | K105: 17025.98 | M105: 617.24286 | N105: 21603.5 | P105: 948.6025 | Q105: 18972.05 | S105: 829.9944 | T105: 20749.86 | V105: 734.9668 | W105: 18374.17 | Y105: 517.39306 | Z105: 18626.15 | AB105: 707.17361 | AC105: 25458.25 | AE105: 444.83667 | AF105: 14679.61 | AH105: 756.81269 | AI105: 19677.13 | AK105: 370.491 | AL105: 7409.82 | AN105: 293.60389 | AO105: 5284.87
A106: =+$C$92&B106 -> Véhicules usagésRev. Protections | B106: Rev. Protections | D106: 1332.3468 | E106: 434345.06 | G106: 1098.0212 | H106: 28548.55 | J106: 905.16 | K106: 23534.16 | M106: 1357.6009 | N106: 47516.03 | P106: 2016.661 | Q106: 40333.22 | S106: 1483.5696 | T106: 37089.24 | V106: 1754.646 | W106: 43866.15 | Y106: 997.11056 | Z106: 35895.98 | AB106: 1507.8911 | AC106: 54284.08 | AE106: 1292.9415 | AF106: 42667.07 | AH106: 1666.1408 | AI106: 43319.66 | AK106: 937.1465 | AL106: 18742.93 | AN106: 1030.4439 | AO106: 18547.99
...

Sheet Capex
A1: PARK AVENUE VOLKSWAGEN | B1: PARK AVENUE VOLKSWAGEN
A2: Forecast Immobilisation 2022 | B2: Forecast Immobilisation 2024 | H2: 1 | I2: 2 | J2: 3 | K2: 4 | L2: 5 | M2: 6 | N2: 7 | O2: 8 | P2: 9 | Q2: 10 | R2: 11 | S2: 12
H3: =+IF(VLOOKUP(H2,Parametres!$L$3:$N$14,3,0)="X","REEL","FORECAST") -> REEL | I3: =+IF(VLOOKUP(I2,Parametres!$L$3:$N$14,3,0)="X","REEL","FORECAST") -> REEL | J3: =+IF(VLOOKUP(J2,Parametres!$L$3:$N$14,3,0)="X","REEL","FORECAST") -> REEL | K3: =+IF(VLOOKUP(K2,Parametres!$L$3:$N$14,3,0)="X","REEL","FORECAST") -> REEL | L3: =+IF(VLOOKUP(L2,Parametres!$L$3:$N$14,3,0)="X","REEL","FORECAST") -> FORECAST | M3: =+IF(VLOOKUP(M2,Parametres!$L$3:$N$14,3,0)="X","REEL","FORECAST") -> FORECAST | N3: =+IF(VLOOKUP(N2,Parametres!$L$3:$N$14,3,0)="X","REEL","FORECAST") -> FORECAST | O3: =+IF(VLOOKUP(O2,Parametres!$L$3:$N$14,3,0)="X","REEL","FORECAST") -> FORECAST | ... S3: =+IF(VLOOKUP(S2,Parametres!$L$3:$N$14,3,0)="X","REEL","FORECAST") -> FORECAST
A4: Concession | B4: Budgété / Non budgété | C4: Projet | D4: Catégorie Immo | E4: Total forecast | F4: Budget Annuel | G4: Écart vs budget | H4: January | I4: February | J4: March | K4: April | L4: May | M4: June | N4: July | O4: August | P4: September | Q4: October | R4: November | S4: December | T4: Raison / Description
C5: Total | E5: =+SUM(E6:E20) -> 96462.09 | F5: =+SUM(F6:F20) -> 83000 | G5: =+SUM(G6:G20) -> 13462.09 | H5: =+SUM(H6:H20) -> 4849.87 | I5: =+SUM(I6:I20) -> 11606.23 | J5: =+SUM(J6:J20) -> 10913 | K5: =+SUM(K6:K20) -> 12548.99 | L5: =+SUM(L6:L20) -> 16097 | ... S5: =+SUM(S6:S20) -> 5000 | X5: Terrain
A6: =+Parametres!$B$1 -> Volks | B6: oui | C6: Outillage ID4 | E6: =+SUM(H6:S6) -> 51000.09 | F6: 51000 | G6: =+E6-F6 -> 0.09 | I6: 9903.09 | L6: 16097 | N6: 25000 | X6: Bâtisse
A7: =+Parametres!$B$1 -> Volks | B7: non | C7: Outils Spécialisés Volks | E7: =+SUM(H7:S7) -> 22000.01 | F7: 22000 | G7: =+E7-F7 -> 0.01 | H7: 4849.87 | I7: 1703.14 | M7: 5447 | P7: 5000 | S7: 5000 | X7: Améliorations Locatives
A8: =+Parametres!$B$1 -> Volks | B8: non | C8: Porte de garage CPO | E8: =+SUM(H8:S8) -> 10000 | F8: 10000 | G8: =+E8-F8 -> 0 | K8: 10000 | X8: Mobilier
A9: =+Parametres!$B$1 -> Volks | B9: non | C9: Lift (ex-Volvo) | E9: =+SUM(H9:S9) -> 10415 | G9: =+E9-F9 -> 10415 | J9: 10415 | X9: Équipements Informatique
A10: =+Parametres!$B$1 -> Volks | B10: non | C10: Equipement informatiques | E10: =+SUM(H10:S10) -> 3046.99 | G10: =+E10-F10 -> 3046.99 | J10: 498 | K10: 2548.99 | X10: Équipements Téléphonique
A11: =+Parametres!$B$1 -> Volks | B11: non | E11: =+SUM(H11:S11) -> 0 | G11: =+E11-F11 -> 0 | X11: Enseigne
A12: =+Parametres!$B$1 -> Volks | B12: non | E12: =+SUM(H12:S12) -> 0 | G12: =+E12-F12 -> 0
A13: =+Parametres!$B$1 -> Volks | B13: non | E13: =+SUM(H13:S13) -> 0 | G13: =+E13-F13 -> 0
A14: =+Parametres!$B$1 -> Volks | B14: non | E14: =+SUM(H14:S14) -> 0 | G14: =+E14-F14 -> 0
A15: =+Parametres!$B$1 -> Volks | B15: non | E15: =+SUM(H15:S15) -> 0 | G15: =+E15-F15 -> 0
A16: =+Parametres!$B$1 -> Volks | B16: non | E16: =+SUM(H16:S16) -> 0 | G16: =+E16-F16 -> 0
A17: =+Parametres!$B$1 -> Volks | B17: non | E17: =+SUM(H17:S17) -> 0 | G17: =+E17-F17 -> 0 | X17: non
A18: =+Parametres!$B$1 -> Volks | B18: non | E18: =+SUM(H18:S18) -> 0 | G18: =+E18-F18 -> 0
A19: =+Parametres!$B$1 -> Volks | B19: non | E19: =+SUM(H19:S19) -> 0 | G19: =+E19-F19 -> 0
A20: =+Parametres!$B$1 -> Volks | B20: non | E20: =+SUM(H20:S20) -> 0 | G20: =+E20-F20 -> 0

Sheet Inventaire_Used
A1: #Contrôle | B1: Année | C1: Marque | D1: Modèle | E1: 1416 | F1: 2103 | G1: NIV | H1: Jours en stock | M1: 45169 | N1: $ Inventaire | O1: $ Financé
A2: 5291P | B2: 2020 | C2: VOLKSWAGEN | D2: E-GOLF | E2: 32007.51 | F2: -22494.36 | G2: WVWPR7AU2LW903993 | H2: 423 | M2: CTRL | N2: =+SUM(E:E) -> 2779322.1 | O2: =+SUM(F:F) -> -640715.53
A3: 230251A | B3: 2020 | C3: VOLKSWAGEN | D3: E-GOLF | E3: 24454.46 | G3: WVWPR7AU0LW907198 | H3: 306 | M3: Unités | N3: =COUNT(E:E) -> 111 | O3: =-O2/N2 -> 0.23052943
A4: 230425A | B4: 2021 | C4: VOLKSWAGEN | D4: ATLAS CROSS SPO | E4: 37735.15 | G4: 1V2LC2CAXMC211536 | H4: 188
A5: 230365A | B5: 2018 | C5: VOLKSWAGEN | D5: BEETLE CONVERTI | E5: 29929.55 | G5: 3VW5DAAT2JM518129 | H5: 187 | M5: Moyenne | N5: =+N2/N3 -> 25038.938
A6: 5485P | B6: 2018 | C6: VOLKSWAGEN | D6: ATLAS | E6: 31306.12 | G6: 1V2NR2CA5JC509107 | H6: 131
A7: 230554A | B7: 2014 | C7: SUBARU | D7: WRX | E7: 17680.42 | G7: JF1GR8H60EL238082 | H7: 121 | M7: Plus de 90 Jours | N7: =SUM(E2:E13) -> 337989.36 | O7: =+N7/N2 -> 0.12160856
A8: 230567A | B8: 2021 | C8: VOLKSWAGEN | D8: TIGUAN | E8: 28635.15 | F8: -31332.8 | G8: 3VV2B7AX6MM155874 | H8: 104 | N8: =COUNT(H2:H13) -> 12 | O8: =+N8/(N3) -> 0.10810811
A9: 240013A | B9: 2022 | C9: VOLKSWAGEN | D9: TIGUAN | E9: 38815.25 | G9: 3VV4B7AX3NM051496 | H9: 94
A10: 230392A | B10: 2020 | C10: VOLKSWAGEN | D10: TIGUAN | E10: 31315.25 | F10: -24944.54 | G10: 3VV4B7AX2LM114164 | H10: 94
A11: 230599A | B11: 2019 | C11: VOLKSWAGEN | D11: JETTA | E11: 21280.25 | F11: -10962 | G11: 3VWE57BU6KM254342 | H11: 94
A12: 230606A | B12: 2018 | C12: CHEVROLET | D12: VOLT | E12: 17550 | G12: 1G1RA6S50JU104989 | H12: 93
A13: 240015A | B13: 2019 | C13: VOLKSWAGEN | D13: GOLF GTI | E13: 27280.25 | F13: -17480.23 | G13: 3VW6T7AU5KM024755 | H13: 90
A14: 5511P | B14: 2022 | C14: VOLKSWAGEN | D14: ATLAS CROSS SPO | E14: 44105.05 | F14: -38250 | G14: 1V2BE2CA6NC212111 | H14: 88
A15: 240019A | B15: 2020 | C15: VOLKSWAGEN | D15: ATLAS CROSS SPO | E15: 36415.13 | F15: -26892 | G15: 1V2TE2CA8LC219420 | H15: 82
A16: 230596A | B16: 2020 | C16: VOLKSWAGEN | D16: TIGUAN | E16: 27935.05 | G16: 3VV2B7AX4LM005048 | H16: 76
A17: 5509PA | B17: 2017 | C17: AUDI | D17: A3 E-TRON | E17: 20050 | G17: WAUSPBFF5HA099610 | H17: 74
A18: 230626A | B18: 2018 | C18: VOLKSWAGEN | D18: TIGUAN | E18: 20497.05 | G18: 3VV4B7AX2JM130250 | H18: 72
A19: 5518P | B19: 2020 | C19: VOLKSWAGEN | D19: TIGUAN | E19: 28075.78 | F19: -23850 | G19: 3VV4B7AX0LM106225 | H19: 69
A20: 230593A | B20: 2019 | C20: VOLKSWAGEN | D20: TIGUAN | E20: 26815.25 | G20: 3VV4B7AX3KM183332 | H20: 69
A21: 5519P | B21: 2021 | C21: VOLKSWAGEN | D21: TIGUAN | E21: 28447.25 | F21: -24418.8 | G21: 3VV2B7AX4MM068281 | H21: 68
A22: 240044A | B22: 2019 | C22: VOLKSWAGEN | D22: ATLAS | E22: 29352 | G22: 1V2MR2CA6KC587280 | H22: 66
A23: 240041A | B23: 2018 | C23: VOLKSWAGEN | D23: GOLF | E23: 18787.5 | G23: 3VWG17AU2JM291103 | H23: 66
A24: 240056A | B24: 2020 | C24: VOLKSWAGEN | D24: JETTA | E24: 18043.82 | G24: 3VWN57BU2LM040420 | H24: 65
A25: 240036A | B25: 2021 | C25: VOLKSWAGEN | D25: ATLAS | E25: 40209.65 | G25: 1V2FR2CA8MC595926 | H25: 62
A26: 240079A | B26: 2020 | C26: VOLKSWAGEN | D26: TIGUAN | E26: 30620.3 | G26: 3VV4B7AX5LM110786 | H26: 62
A27: 230564B | B27: 2020 | C27: JEEP | D27: COMPASS | E27: 28211.38 | G27: 3C4NJDDBXLT155667 | H27: 62
A28: 230649A | B28: 2020 | C28: NISSAN | D28: ROGUE | E28: 23550 | G28: 5N1AT2MT7LC775762 | H28: 61
A29: 240086A | B29: 2022 | C29: VOLKSWAGEN | D29: TIGUAN | E29: 36524.6 | G29: 3VV4B7AX9NM096457 | H29: 60
A30: 5522P | B30: 2020 | C30: VOLKSWAGEN | D30: TIGUAN | E30: 24346.21 | F30: -16047.88 | G30: 3VV2B7AX7LM099068 | H30: 60
A31: 5521P | B31: 2019 | C31: VOLKSWAGEN | D31: GOLF | E31: 18530.25 | G31: 3VWG57AU3KM018998 | H31: 60
A32: 5523P | B32: 2021 | C32: VOLKSWAGEN | D32: TIGUAN | E32: 29670.31 | F32: -25505.1 | G32: 3VV2B7AX2MM078047 | H32: 59
A33: 240089A | B33: 2020 | C33: VOLKSWAGEN | D33: JETTA | E33: 22965.2 | G33: 3VWW57BU9LM006236 | H33: 55
A34: 5525P | B34: 2021 | C34: VOLKSWAGEN | D34: TIGUAN | E34: 31666.8 | F34: -33046.59 | G34: 3VV4B7AX1MM155614 | H34: 54
A35: 240059A | B35: 2019 | C35: VOLKSWAGEN | D35: TIGUAN | E35: 24846.26 | G35: 3VV2B7AX7KM049091 | H35: 53
A36: 240099A | B36: 2020 | C36: VOLKSWAGEN | D36: JETTA | E36: 19323.74 | G36: 3VWN57BU9LM077965 | H36: 51
A37: 240098A | B37: 2019 | C37: VOLKSWAGEN | D37: GOLF | E37: 18294.75 | G37: 3VWG57AU0KM034477 | H37: 48
A38: 240038B | B38: 2018 | C38: VOLKSWAGEN | D38: GOLF | E38: 16745.3 | G38: 3VWG17AU9JM275867 | H38: 48
A39: 240091A | B39: 2022 | C39: VOLKSWAGEN | D39: ATLAS | E39: 49927.29 | G39: 1V2FR2CA7NC504226 | H39: 47
A40: 5526P | B40: 2020 | C40: VOLKSWAGEN | D40: TIGUAN | E40: 24483.1 | F40: -18876 | G40: 3VV2B7AX9LM002520 | H40: 47
A41: 240109A | B41: 2019 | C41: VOLKSWAGEN | D41: GOLF | E41: 21779.6 | G41: 3VWG57AU6KM028375 | H41: 47
A42: 240111A | B42: 2021 | C42: VOLKSWAGEN | D42: GOLF | E42: 21350 | G42: 3VWW57AU1MM000790 | H42: 45
A43: 240108A | B43: 2019 | C43: VOLKSWAGEN | D43: JETTA | E43: 17488.18 | G43: 3VWG57BU3KM143398 | H43: 45
A44: 240100A | B44: 2020 | C44: VOLKSWAGEN | D44: JETTA | E44: 18370.25 | G44: 3VWCB7BU1LM050033 | H44: 44
A45: 5527P | B45: 2018 | C45: VOLKSWAGEN | D45: TIGUAN | E45: 20165.3 | G45: 3VV2B7AX0JM078401 | H45: 44
A46: 240121A | B46: 2015 | C46: JEEP | D46: CHEROKEE | E46: 15050 | G46: 1C4PJMBBXFW775848 | H46: 44
A47: 240062A | B47: 2020 | C47: VOLKSWAGEN | D47: JETTA | E47: 21360.2 | G47: 3VWEB7BU9LM051228 | H47: 41
A48: 5528P | B48: 2021 | C48: VOLKSWAGEN | D48: JETTA | E48: 25003.85 | F48: -21330 | G48: 3VWE57BU8MM046465 | H48: 40
A49: 240153A | B49: 2020 | C49: VOLKSWAGEN | D49: TIGUAN | E49: 24894.97 | G49: 3VV0B7AX5LM117185 | H49: 40
A50: 240127A | B50: 2019 | C50: VOLKSWAGEN | D50: TIGUAN | E50: 27870.3 | G50: 3VV4B7AX2KM185248 | H50: 40
A51: 240169A | B51: 2021 | C51: VOLKSWAGEN | D51: JETTA | E51: 24530.4 | G51: 3VWE57BU7MM077268 | H51: 37
A52: 240143A | B52: 2008 | C52: VOLKSWAGEN | D52: GTI | E52: 4314.03 | G52: WVWHV91K48W093414 | H52: 37
A53: 240183A | B53: 2021 | C53: VOLKSWAGEN | D53: JETTA | E53: 24447.5 | G53: 3VWE57BU5MM022575 | H53: 33
A54: 5530P | B54: 2019 | C54: VOLKSWAGEN | D54: GOLF | E54: 20373.45 | F54: -12553.38 | G54: 3VWG57AU5KM019568 | H54: 33
A55: 240105A | B55: 2021 | C55: VOLKSWAGEN | D55: GOLF GTI | E55: 32388.2 | G55: 3VW5T7AU9MM015944 | H55: 32
A56: 240151A | B56: 2020 | C56: VOLKSWAGEN | D56: PASSAT | E56: 23491.6 | G56: 1VWBA7A31LC005280 | H56: 32
A57: 240123A | B57: 2021 | C57: VOLKSWAGEN | D57: TIGUAN | E57: 29343.25 | G57: 3VV2B7AX9MM038886 | H57: 31
A58: 240198A | B58: 2020 | C58: VOLKSWAGEN | D58: TIGUAN | E58: 29950 | G58: 3VV4B7AX7LM138623 | H58: 31
A59: 5531P | B59: 2019 | C59: VOLKSWAGEN | D59: TIGUAN | E59: 21448.99 | F59: -18000 | G59: 3VV2B7AX5KM174266 | H59: 31
A60: 240195A | B60: 2019 | C60: VOLKSWAGEN | D60: GOLF ALLTRACK | E60: 23680.2 | G60: 3VWH17AU4KM517860 | H60: 31
A61: 240031A | B61: 2019 | C61: VOLKSWAGEN | D61: GOLF | E61: 19433.85 | G61: 3VWG57AU6KM019319 | H61: 31
A62: 240208A | B62: 2019 | C62: NISSAN | D62: ROGUE | E62: 17516.85 | G62: 5N1AT2MT2KC789311 | H62: 31
A63: 240200A | B63: 2021 | C63: VOLKSWAGEN | D63: TIGUAN | E63: 28418.09 | G63: 3VV2B7AX7MM017972 | H63: 30
A64: 240120A | B64: 2020 | C64: VOLKSWAGEN | D64: TIGUAN | E64: 26650 | G64: 3VV2B7AX5LM134416 | H64: 30
A65: 5532P | B65: 2019 | C65: VOLKSWAGEN | D65: TIGUAN | E65: 22943.2 | F65: -14910 | G65: 3VV2B7AXXKM175526 | H65: 27
A66: 5536P | B66: 2024 | C66: VOLKSWAGEN | D66: GOLF R | E66: 56282.9 | F66: -53444.44 | G66: WVWEB7CD1RW113067 | H66: 26
A67: 5535P | B67: 2023 | C67: VOLKSWAGEN | D67: TIGUAN | E67: 37343.25 | F67: -31500 | G67: 3VVMB7AX1PM006494 | H67: 26
A68: 5534P | B68: 2021 | C68: VOLKSWAGEN | D68: TIGUAN | E68: 27555.44 | F68: -26142.19 | G68: 3VV2B7AX0MM070822 | H68: 26
A69: 240090A | B69: 2019 | C69: VOLKSWAGEN | D69: JETTA | E69: 15050 | G69: 3VWW57BU7KM135400 | H69: 26
A70: 5539P | B70: 2020 | C70: VOLKSWAGEN | D70: E-GOLF | E70: 24148.3 | F70: -13011 | G70: WVWPR7AUXLW900758 | H70: 25
A71: 5537P | B71: 2017 | C71: VOLKSWAGEN | D71: TIGUAN | E71: 17323.25 | F71: -14400 | G71: WVGNV7AX9HW500724 | H71: 25
A72: 5540P | B72: 2020 | C72: VOLKSWAGEN | D72: TIGUAN | E72: 24729.89 | F72: -21121.07 | G72: 3VV2B7AX5LM104042 | H72: 24
A73: 240154A | B73: 2023 | C73: HYUNDAY | D73: SANTA CRUZ | E73: 39801.28 | G73: 5NTJEDAF3PH073751 | H73: 17
A74: 5542P | B74: 2020 | C74: VOLKSWAGEN | D74: TIGUAN | E74: 27897 | F74: -21259.15 | G74: 3VV2B7AX9LM116727 | H74: 17
A75: 5543P | B75: 2021 | C75: VOLKSWAGEN | D75: TIGUAN | E75: 29849.7 | F75: -25650 | G75: 3VV4B7AX3MM043848 | H75: 16
A76: 240222A | B76: 2021 | C76: VOLKSWAGEN | D76: JETTA | E76: 22734.85 | G76: 3VWE57BU8MM023008 | H76: 16
A77: 5544P | B77: 2020 | C77: VOLKSWAGEN | D77: TIGUAN | E77: 23937.85 | G77: 3VV2B7AX7LM009577 | H77: 16
A78: 240210A | B78: 2020 | C78: DODGE | D78: RAM 1500 | E78: 37860.38 | G78: 1C6SRFFT2LN407190 | H78: 16
A79: 240226A | B79: 2019 | C79: VOLKSWAGEN | D79: GOLF | E79: 17250 | F79: -10994 | G79: 3VWG57AU7KM033052 | H79: 16
A80: 240172A | B80: 2015 | C80: VOLKSWAGEN | D80: JETTA SEDAN | E80: 9050 | G80: 3VWG07AJ8FM218642 | H80: 13
A81: 5529PA | B81: 2014 | C81: NISSAN | D81: TRUCK PATHFINDER | E81: 10550 | G81: 5N1AR2MM1EC693147 | H81: 12
A82: 5545P | B82: 2022 | C82: VOLKSWAGEN | D82: GOLF R | E82: 48197.8 | F82: -42300 | G82: WVWEB7CD8NW157948 | H82: 11
A83: 240231A | B83: 2019 | C83: VOLKSWAGEN | D83: JETTA | E83: 21402.85 | G83: 3VWE57BU8KM269358 | H83: 11
A84: 240215A | B84: 2019 | C84: VOLKSWAGEN | D84: GOLF | E84: 18179.95 | G84: 3VWW57AU6KM035788 | H84: 11
A85: 5546P | B85: 2016 | C85: BMW | D85: SAV X5 | E85: 22550 | G85: 5UXKR0C55G0S87415 | H85: 11
A86: 0925RA | B86: 2010 | C86: TOYOTA | D86: COROLLA | E86: 5450 | G86: 2T1BU4EE1AC231280 | H86: 11
A87: 240191A | B87: 2019 | C87: VOLKSWAGEN | D87: TIGUAN | E87: 20650 | G87: 3VV2B7AX1KM022551 | H87: 10
A88: 240194A | B88: 2015 | C88: VOLKSWAGEN | D88: TIGUAN | E88: 8550 | G88: WVGJV7AX1FW576563 | H88: 10
A89: 240261A | B89: 2020 | C89: VOLKSWAGEN | D89: TIGUAN | E89: 25550 | G89: 3VV2B7AXXLM100701 | H89: 9
A90: 240035A | B90: 2020 | C90: HONDA | D90: PILOT | E90: 28550 | G90: 5FNYF6H72LB500902 | H90: 9
A91: 240229A | B91: 2019 | C91: VOLKSWAGEN | D91: GOLF | E91: 17050 | G91: 3VWW57AU0KM035463 | H91: 9
A92: 240178A | B92: 2022 | C92: VOLKSWAGEN | D92: TIGUAN | E92: 31300 | G92: 3VV8B7AX7NM005591 | H92: 8
A93: 5548P | B93: 2023 | C93: VOLKSWAGEN | D93: ATLAS | E93: 47388.75 | G93: 1V2SR2CA7PC517706 | H93: 4
A94: 240058A | B94: 2021 | C94: VOLKSWAGEN | D94: JETTA | E94: 24050 | G94: 3VW6T7BU9MM023626 | H94: 4
... A114: 5488P | B114: 2010 | C114: VOLKSWAGEN | D114: ROUTAN | E114: 11948.62 | G114: 2V4RW3DX0AR228009 | H114: 94

Sheet Inventaire_Neuf
A1: #Contrôle | B1: Année | C1: Marque | D1: Modèle | E1: 1402 | F1: 2101 | G1: NIV | H1: Jours en stock | K1: 45230 | L1: $ Inventaire | M1: $ Financé
A2: 230536 | B2: 2023 | C2: VOLKSWAGEN | D2: JETTA SEDAN | E2: 33666.97 | F2: -31504.85 | G2: 3VW2T7BU7PM053775 | H2: 142 | K2: CTRL | L2: =+SUM(E2:E9963) -> 3059537.1 | M2: =+SUM(F2:F9963) -> -2668372
A3: 240001 | B3: 2024 | C3: VOLKSWAGEN | D3: ATLAS | E3: 56706.1 | F3: -57628.2 | G3: 1V2BR2CA6RC502911 | H3: 142 | K3: Unités | L3: =COUNT(E:E) -> 71 | M3: =-M2/L2 -> 0.8721489
A4: 230574 | B4: 2023 | C4: VOLKSWAGEN | D4: JETTA SEDAN | E4: 31163.98 | F4: -32628.75 | G4: 3VWGM7BU3PM060824 | H4: 116
A5: 230581 | B5: 2023 | C5: VOLKSWAGEN | D5: TAOS | E5: 38081.07 | F5: -39936.75 | G5: 3VV4X7B27PM374246 | H5: 111
A6: 240003 | B6: 2024 | C6: VOLKSWAGEN | D6: ATLAS | E6: 50511.98 | F6: -51427.95 | G6: 1V2LR2CA2RC511786 | H6: 108 | K6: Plus de 90 jrs | L6: =SUM(E2:E12) -> 532950.79 | M6: =SUM(F2:F12) -> -378366.05
A7: 240009 | B7: 2024 | C7: VOLKSWAGEN | D7: ATLAS CROSS SPT | E7: 54659.17 | F7: -57051.75 | G7: 1V2BE2CA7RC206484 | H7: 104 | L7: 2
A8: 240011 | B8: 2024 | C8: VOLKSWAGEN | D8: ATLAS CROSS SPT | E8: 48328.17 | F8: -51136.05 | G8: 1V2LE2CA3RC208611 | H8: 97
A9: 240016 | B9: 2024 | C9: VOLKSWAGEN | D9: ATLAS CROSS SPT | E9: 57229.1 | G9: 1V2BE2CA1RC206996 | H9: 93 | K9: Plus de 180 jrs | L9: 0 | M9: 0
A10: 240022 | B10: 2024 | C10: VOLKSWAGEN | D10: ATLAS | E10: 58141.01 | G10: 1V2BR2CA4RC506228 | H10: 90 | L10: 0
A11: 240021 | B11: 2024 | C11: VOLKSWAGEN | D11: ATLAS | E11: 48171.23 | G11: 1V2LR2CA8RC516197 | H11: 90
A12: 240020 | B12: 2024 | C12: VOLKSWAGEN | D12: ATLAS CROSS SPT | E12: 56292.01 | F12: -57051.75 | G12: 1V2BE2CA5RC210341 | H12: 90
A13: 240027 | B13: 2024 | C13: VOLKSWAGEN | D13: ATLAS | E13: 56073.92 | F13: -58869.3 | G13: 1V2BR2CA1RC517137 | H13: 86
A14: 240026 | B14: 2024 | C14: VOLKSWAGEN | D14: GOLF GTI | E14: 37397 | F14: -39440.1 | G14: WVWGA7CD7RW121198 | H14: 86
A15: 240030 | B15: 2024 | C15: VOLKSWAGEN | D15: ATLAS CROSS SPT | E15: 56197.99 | F15: -58834.65 | G15: 1V2FE2CAXRC211373 | H15: 82
A16: 230639 | B16: 2023 | C16: VOLKSWAGEN | D16: TAOS | E16: 32135.51 | F16: -34034.7 | G16: 3VVEX7B23PM379190 | H16: 80
A17: 240042 | B17: 2024 | C17: VOLKSWAGEN | D17: ATLAS CROSS SPT | E17: 55950.97 | F17: -58834.65 | G17: 1V2FE2CA4RC210672 | H17: 74
A18: 240047 | B18: 2024 | C18: VOLKSWAGEN | D18: ATLAS CROSS SPT | E18: 55950.97 | F18: -58834.65 | G18: 1V2FE2CA0RC211429 | H18: 74
A19: 240045 | B19: 2024 | C19: VOLKSWAGEN | D19: JETTA SEDAN | E19: 26927 | F19: -28367.85 | G19: 3VWWM7BU5RM010702 | H19: 74
A20: 230643 | B20: 2023 | C20: VOLKSWAGEN | D20: TAOS | E20: 37610 | F20: -39461.1 | G20: 3VV4X7B2XPM382549 | H20: 73
A21: 240052 | B21: 2024 | C21: VOLKSWAGEN | D21: ATLAS CROSS SPT | E21: 55950.97 | F21: -58834.65 | G21: 1V2FE2CAXRC211504 | H21: 73
A22: 240050 | B22: 2024 | C22: VOLKSWAGEN | D22: JETTA SEDAN | E22: 29531 | F22: -31102.05 | G22: 3VWSM7BU4RM014707 | H22: 73
A23: 240070 | B23: 2024 | C23: VOLKSWAGEN | D23: ATLAS CROSS SPT | E23: 54250 | F23: -57051.75 | G23: 1V2BE2CA9RC212335 | H23: 68
... A27: 240083 | B27: 2024 | C27: VOLKSWAGEN | D27: JETTA SEDAN | E27: 32017.87 | F27: -33204.15 | G27: 3VWGM7BU7RM015582 | H27: 62
A28: 240125 | B28: 2024 | C28: VOLKSWAGEN | D28: JETTA GLI | E28: 31816.52 | G28: 3VW8T7BU7RM014696 | H28: 52
A29: 240129 | B29: 2024 | C29: VOLKSWAGEN | D29: JETTA GLI | E29: 31513 | G29: 3VW8T7BU8RM016912 | H29: 51
A30: 240137 | B30: 2024 | C30: VOLKSWAGEN | D30: ATLAS | E30: 48894 | F30: -51427.95 | G30: 1V2LR2CA9RC529461 | H30: 48
A31: 240141 | B31: 2024 | C31: VOLKSWAGEN | D31: ATLAS CROSS SPT | E31: 55948 | F31: -58834.65 | G31: 1V2FE2CA6RC216828 | H31: 48
A32: 240139 | B32: 2024 | C32: VOLKSWAGEN | D32: ATLAS CROSS SPT | E32: 54236.5 | G32: 1V2BE2CAXRC212764 | H32: 48
A33: 240138 | B33: 2024 | C33: VOLKSWAGEN | D33: TAOS | E33: 32864 | F33: -34706.7 | G33: 3VVEX7B22RM012347 | H33: 48
A34: 240147 | B34: 2024 | C34: VOLKSWAGEN | D34: ATLAS | E34: 55259.97 | F34: -58109.1 | G34: 1V2BR2CAXRC525513 | H34: 47
A35: 240156 | B35: 2024 | C35: VOLKSWAGEN | D35: ATLAS CROSS SPT | E35: 53794.97 | F35: -56570.85 | G35: 1V2BE2CA8RC216649 | H35: 45
A36: 240171 | B36: 2024 | C36: VOLKSWAGEN | D36: JETTA SEDAN | E36: 28629 | G36: 3VWEM7BU2RM001760 | H36: 44
A37: 240173 | B37: 2024 | C37: VOLKSWAGEN | D37: ATLAS | E37: 54801.97 | F37: -57628.2 | G37: 1V2BR2CA7RC532368 | H37: 41
A38: 240190 | B38: 2024 | C38: VOLKSWAGEN | D38: ATLAS | E38: 58249.97 | G38: 1V2FR2CA7RC531156 | H38: 38
A39: 240197 | B39: 2024 | C39: VOLKSWAGEN | D39: TIGUAN | E39: 45175.95 | F39: -47526.15 | G39: 3VV4B7AX2RM023873 | H39: 37
A40: 240203 | B40: 2024 | C40: VOLKSWAGEN | D40: TIGUAN | E40: 44101 | F40: -46474.05 | G40: 3VV4B7AX6RM025190 | H40: 34
A41: 240207 | B41: 2024 | C41: VOLKSWAGEN | D41: ATLAS | E41: 54806.97 | F41: -57628.2 | G41: 1V2BR2CA4RC531890 | H41: 33
A42: 240206 | B42: 2024 | C42: VOLKSWAGEN | D42: TAOS | E42: 38195 | F42: -40225.5 | G42: 3VV4X7B25RM012063 | H42: 33
A43: 240212 | B43: 2024 | C43: VOLKSWAGEN | D43: ATLAS CROSS SPT | E43: 56348.1 | F43: -58834.65 | G43: 1V2FE2CA5RC219798 | H43: 30
A44: 240213 | B44: 2024 | C44: VOLKSWAGEN | D44: TIGUAN | E44: 45762.95 | G44: 3VV4B7AX1RM023721 | H44: 30
A45: 240221 | B45: 2024 | C45: VOLKSWAGEN | D45: TAOS | E45: 37908 | F45: -39749.85 | G45: 3VV4X7B20RM013248 | H45: 25
A46: 240220 | B46: 2024 | C46: VOLKSWAGEN | D46: TAOS | E46: 32705 | F46: -34423.2 | G46: 3VVEX7B2XRM013066 | H46: 25
A47: 240223 | B47: 2024 | C47: VOLKSWAGEN | D47: TAOS | E47: 32705 | F47: -34423.2 | G47: 3VVEX7B25RM012259 | H47: 25
A48: 240219 | B48: 2024 | C48: VOLKSWAGEN | D48: TAOS | E48: 32700 | F48: -34423.2 | G48: 3VVEX7B20RM012928 | H48: 25
A49: 240232 | B49: 2024 | C49: VOLKSWAGEN | D49: TAOS | E49: 35661.95 | G49: 3VVVX7B23RM011742 | H49: 20
A50: 240230 | B50: 2024 | C50: VOLKSWAGEN | D50: TIGUAN | E50: 44107 | F50: -46474.05 | G50: 3VV4B7AX4RM047169 | H50: 20
A51: 240238 | B51: 2024 | C51: VOLKSWAGEN | D51: TAOS | E51: 37441.5 | G51: 3VV4X7B26RM014615 | H51: 16
A52: 240248 | B52: 2024 | C52: VOLKSWAGEN | D52: GOLF GTI | E52: 38207 | F52: -40179.3 | G52: WVWRA7CD4RW133320 | H52: 13
A53: 240241 | B53: 2024 | C53: VOLKSWAGEN | D53: TAOS | E53: 37773 | F53: -39749.85 | G53: 3VV4X7B2XRM023463 | H53: 13
A54: 240243 | B54: 2024 | C54: VOLKSWAGEN | D54: TAOS | E54: 37109 | F54: -39552.45 | G54: 3VV4X7B23RM025278 | H54: 13
A55: 240242 | B55: 2024 | C55: VOLKSWAGEN | D55: TAOS | E55: 34270 | F55: -36066.45 | G55: 3VVUX7B20RM026050 | H55: 13
A56: 240259 | B56: 2024 | C56: VOLKSWAGEN | D56: GOLF GTI | E56: 39384 | F56: -41836.2 | G56: WVWWA7CD4RW139864 | H56: 12
A57: 240256 | B57: 2024 | C57: VOLKSWAGEN | D57: GOLF R | E57: 49697 | F57: -52243.8 | G57: WVWEB7CD9RW139691 | H57: 12
A58: 240257 | B58: 2024 | C58: VOLKSWAGEN | D58: GOLF R | E58: 49697 | F58: -52243.8 | G58: WVWEB7CD9RW140162 | H58: 12
A59: 240255 | B59: 2024 | C59: VOLKSWAGEN | D59: TAOS | E59: 35568 | F59: -37434.6 | G59: 3VVVX7B24RM026699 | H59: 12
A60: 240254 | B60: 2024 | C60: VOLKSWAGEN | D60: TAOS | E60: 34265 | F60: -36066.45 | G60: 3VVUX7B25RM026254 | H60: 12
A61: 240250 | B61: 2024 | C61: VOLKSWAGEN | D61: TAOS | E61: 28211 | G61: 3VVCX7B23RM011327 | H61: 12
A62: 240253 | B62: 2024 | C62: VOLKSWAGEN | D62: TIGUAN | E62: 47482.92 | F62: -47526.15 | G62: 3VV4B7AX0RM043880 | H62: 12
A63: 240262 | B63: 2024 | C63: VOLKSWAGEN | D63: TIGUAN | E63: 40734 | F63: -43358.7 | G63: 3VV8B7AX4RM058738 | H63: 9
A64: 240266 | B64: 2024 | C64: VOLKSWAGEN | D64: GOLF GTI | E64: 37806 | F64: -40179.3 | G64: WVWRA7CD7RW142545 | H64: 3
A65: 240270 | B65: 2024 | C65: VOLKSWAGEN | D65: TIGUAN | E65: 44886 | F65: -47718.3 | G65: 3VV4B7AXXRM065708 | H65: 3
A66: 240263 | B66: 2024 | C66: VOLKSWAGEN | D66: TIGUAN | E66: 44154 | F66: -46949.7 | G66: 3VV4B7AXXRM047399 | H66: 3
A67: 240268 | B67: 2024 | C67: VOLKSWAGEN | D67: TIGUAN | E67: 44154 | F67: -46949.7 | G67: 3VV4B7AX3RM061712 | H67: 3
A68: 240264 | B68: 2024 | C68: VOLKSWAGEN | D68: TIGUAN | E68: 43701 | F68: -46474.05 | G68: 3VV4B7AX7RM058599 | H68: 3
A69: 240267 | B69: 2024 | C69: VOLKSWAGEN | D69: TIGUAN | E69: 43701 | F69: -46474.05 | G69: 3VV4B7AX9RM059415 | H69: 3
A70: 240269 | B70: 2024 | C70: VOLKSWAGEN | D70: TIGUAN | E70: 40734 | F70: -43358.7 | G70: 3VV8B7AX7RM066865 | H70: 3
A71: 240265 | B71: 2024 | C71: VOLKSWAGEN | D71: TIGUAN | E71: 39069 | F71: -41610.45 | G71: 3VVMB7AX2RM024991 | H71: 3
A72: 240273 | B72: 2024 | C72: VOLKSWAGEN | D72: TIGUAN | E72: 44154 | F72: -46949.7 | G72: 3VV4B7AX9RM059835 | H72: 2

Sheet 2pager
B1: =Parametres!$B$1&" "&"2 pager"&" "&Parametres!$B$3&" "&Parametres!$B$4 -> Volks 2 pager Avril 2024
B3: New | C3: Actual | D3: Budget | E3: 2023 | F3: ▲ Budget | G3: ▲2023 | H3: % ▲ Budget | I3: % ▲ 2023 | J3: Commentaires
B4: Units | C4: =+Print_Mois!$J$13+Print_Mois!$J$15 -> 73 | D4: =+Print_Mois!$D$13+Print_Mois!$D$15 -> 67 | E4: =+Print_Mois!$O$13+Print_Mois!$O$15 -> 34 | F4: =+IFERROR($C4-D4,"") -> 6 | G4: =+IFERROR($C4-E4,"") -> 39 | H4: =+IFERROR(F4/ABS($D4),"") -> 0.089552239 | I4: =+IFERROR(G4/ABS($E4),"") -> 1.1470588 | J4: Volume over budget mais moyennes front & back plus difficiles, F&i en transition avec les nouvelles embauches. Des frais de livraisons en hausse avec le nombre de locates et un impact aussi sur le hodback. Dépenses sous contrôle mais on doit être plus vigilants sur la rotation de l'inventaire de neuf et privilégier absolument le stock. Le plan de paye à effet au 1er février aura un impact sur ce point.
B5: Front Margin | C5: =+Print_Mois!$L$13+Print_Mois!$L$15 -> 196303.82 | D5: =+Print_Mois!$F$13+Print_Mois!$F$15 -> 181312.49 | E5: =+Print_Mois!$Q$13+Print_Mois!$Q$15 -> 85714.44 | F5: =+IFERROR($C5-D5,"") -> 14991.326 | G5: =+IFERROR($C5-E5,"") -> 110589.38 | H5: =+IFERROR(F5/ABS($D5),"") -> 0.082682257 | I5: =+IFERROR(G5/ABS($E5),"") -> 1.2902071
B6: Front margin / unit | C6: =+C5/C4 -> 2689.0934 | D6: =+D5/D4 -> 2706.1566 | E6: =+E5/E4 -> 2521.0129 | F6: =+IFERROR($C6-D6,"") -> -17.063198 | G6: =+IFERROR($C6-E6,"") -> 168.08048 | H6: =+IFERROR(F6/ABS($D6),"") -> -0.0063053255 | I6: =+IFERROR(G6/ABS($E6),"") -> 0.066671805
B7: $ Salaires et commission | C7: =+Print_Mois!$L$31 -> 48723.01 | D7: =+Print_Mois!$F$31 -> 61646.248 | E7: =+Print_Mois!$Q$31 -> 37095.46 | F7: =+IFERROR($C7-D7,"") -> -12923.238 | G7: =+IFERROR($C7-E7,"") -> 11627.55 | H7: =+IFERROR(F7/ABS($D7),"") -> -0.20963543 | I7: =+IFERROR(G7/ABS($E7),"") -> 0.31344941
B8: % Salaires et commission | C8: =+C7/C5 -> 0.24820205 | D8: =+D7/D5 -> 0.34 | E8: =+E7/E5 -> 0.43277959 | F8: =+IFERROR($C8-D8,"") -> -0.091797953 | G8: =+IFERROR($C8-E8,"") -> -0.18457754 | H8: =+IFERROR(F8/ABS($D8),"") -> -0.26999398 | I8: =+IFERROR(G8/ABS($E8),"") -> -0.42649318
B9: Back Margin | C9: =+Print_Mois!$L$24 -> 57270.55 | D9: =+Print_Mois!$F$24 -> 87100 | E9: =+Print_Mois!$Q$24 -> 33485.11 | F9: =+IFERROR($C9-D9,"") -> -29829.45 | G9: =+IFERROR($C9-E9,"") -> 23785.44 | H9: =+IFERROR(F9/ABS($D9),"") -> -0.34247359 | I9: =+IFERROR(G9/ABS($E9),"") -> 0.71032886
B10: Back Margin / unit | C10: =+C9/C4 -> 784.52808 | D10: =+D9/D4 -> 1300 | E10: =+E9/E4 -> 984.85618 | F10: =+IFERROR($C10-D10,"") -> -515.47192 | G10: =+IFERROR($C10-E10,"") -> -200.32809 | H10: =+IFERROR(F10/ABS($D10),"") -> -0.39651686 | I10: =+IFERROR(G10/ABS($E10),"") -> -0.20340848
B11: $ commission FI | C11: =+Print_Mois!$L$32 -> 17016.15 | D11: =+Print_Mois!$F$32 -> 26130 | E11: =+Print_Mois!$Q$32 -> 10038.22 | F11: =+IFERROR($C11-D11,"") -> -9113.85 | G11: =+IFERROR($C11-E11,"") -> 6977.93 | H11: =+IFERROR(F11/ABS($D11),"") -> -0.34878875 | I11: =+IFERROR(G11/ABS($E11),"") -> 0.69513619
B12: % commission FI | C12: =+C11/C9 -> 0.29711868 | D12: =+D11/D9 -> 0.3 | E12: =+E11/E9 -> 0.2997816 | F12: =+IFERROR($C12-D12,"") -> -0.0028813238 | G12: =+IFERROR($C12-E12,"") -> -0.0026629282 | H12: =+IFERROR(F12/ABS($D12),"") -> -0.0096044127 | I12: =+IFERROR(G12/ABS($E12),"") -> -0.0088828941
B13: Variable fees | C13: =+Print_Mois!$L$41-C7-C11 -> 60127.18 | D13: =+Print_Mois!$F$41-D7-D11 -> 42466.778 | E13: =+Print_Mois!$Q$41-E7-E11 -> 13778.55 | F13: =+IFERROR($C13-D13,"") -> 17660.402 | G13: =+IFERROR($C13-E13,"") -> 46348.63 | H13: =+IFERROR(F13/ABS($D13),"") -> 0.41586395 | I13: =+IFERROR(G13/ABS($E13),"") -> 3.3638249
B14: Variable fees / units | C14: =+C13/C4 -> 823.66 | D14: =+D13/D4 -> 633.83251 | E14: =+E13/E4 -> 405.25147 | F14: =+IFERROR($C14-D14,"") -> 189.82749 | G14: =+IFERROR($C14-E14,"") -> 418.40853 | H14: =+IFERROR(F14/ABS($D14),"") -> 0.29949157 | I14: =+IFERROR(G14/ABS($E14),"") -> 1.0324664
B15: Other Revenues | C15: =+Print_Mois!$L$83 -> 142811.85 | D15: =+Print_Mois!$F$83 -> 125048.26 | E15: =+Print_Mois!$Q$83 -> 51685.08 | F15: =+IFERROR($C15-D15,"") -> 17763.588 | G15: =+IFERROR($C15-E15,"") -> 91126.77 | H15: =+IFERROR(F15/ABS($D15),"") -> 0.14205386 | I15: =+IFERROR(G15/ABS($E15),"") -> 1.7631156
B16: Inventory
B17: Units | C17: =Inventaire_Neuf!L3 -> 71 | D17: 61 | E17: 164 | F17: =+IFERROR($C17-D17,"") -> 10 | G17: =+IFERROR($C17-E17,"") -> -93 | H17: =+IFERROR(F17/ABS($D17),"") -> 0.16393443 | I17: =+IFERROR(G17/ABS($E17),"") -> -0.56707317
B18: $ | C18: =Inventaire_Neuf!L2 -> 3059537.1 | D18: 2233570 | E18: 5689693.2 | F18: =+IFERROR($C18-D18,"") -> 825967.15 | G18: =+IFERROR($C18-E18,"") -> -2630156 | H18: =+IFERROR(F18/ABS($D18),"") -> 0.36979685 | I18: =+IFERROR(G18/ABS($E18),"") -> -0.46226676
B20: Used | C20: Actual | D20: Budget | E20: =$E$3 -> 2023 | F20: ▲ Budget | G20: =$G$3 -> ▲2023 | H20: % ▲ Budget | I20: =$I$3 -> % ▲ 2023 | J20: Commentaires
B21: Units | C21: =+Print_Mois!$J$97 -> 23 | D21: =+Print_Mois!$D$97 -> 42.245 | E21: =+Print_Mois!$O$97 -> 20 | F21: =+IFERROR($C21-D21,"") -> -19.245 | G21: =+IFERROR($C21-E21,"") -> 3 | H21: =+IFERROR(F21/ABS($D21),"") -> -0.45555687 | I21: =+IFERROR(G21/ABS($E21),"") -> 0.15 | J21: Le mois le plus catastrophique de notre histoire. Pas de volume, pas de profits ni au détail ni au wholesale. Même si nos dépenses ont toutes été minimisées, nous ne sauvons pas la situation. L'écart de janvier a été ajouté aux objectifs de Février et Mars pour avoir un Q1 à niveau.
B22: Front Margin | C22: =+Print_Mois!$L$97 -> 37976.47 | D22: =+Print_Mois!$F$97 -> 76041 | E22: =+Print_Mois!$Q$97 -> 42691.98 | F22: =+IFERROR($C22-D22,"") -> -38064.53 | G22: =+IFERROR($C22-E22,"") -> -4715.51 | H22: =+IFERROR(F22/ABS($D22),"") -> -0.50057903 | I22: =+IFERROR(G22/ABS($E22),"") -> -0.11045424
B23: Front margin / unit | C23: =+C22/C21 -> 1651.1509 | D23: =+D22/D21 -> 1800 | E23: =+E22/E21 -> 2134.599 | F23: =+IFERROR($C23-D23,"") -> -148.84913 | G23: =+IFERROR($C23-E23,"") -> -483.44813 | H23: =+IFERROR(F23/ABS($D23),"") -> -0.082693961 | I23: =+IFERROR(G23/ABS($E23),"") -> -0.22648194
B24: $ Salaires et commission | C24: =+Print_Mois!$L$112 -> 12859.07 | D24: =+Print_Mois!$F$112 -> 25093.53 | E24: =+Print_Mois!$Q$112 -> 18663.87 | F24: =+IFERROR($C24-D24,"") -> -12234.46 | G24: =+IFERROR($C24-E24,"") -> -5804.8 | H24: =+IFERROR(F24/ABS($D24),"") -> -0.48755436 | I24: =+IFERROR(G24/ABS($E24),"") -> -0.31101803
B25: % Salaires et commission | C25: =+C24/C22 -> 0.33860625 | D25: =+D24/D22 -> 0.33 | E25: =+E24/E22 -> 0.43717509 | F25: =+IFERROR($C25-D25,"") -> 0.0086062475 | G25: =+IFERROR($C25-E25,"") -> -0.098568838 | H25: =+IFERROR(F25/ABS($D25),"") -> 0.026079538 | I25: =+IFERROR(G25/ABS($E25),"") -> -0.22546765
B26: Back Margin | C26: =+Print_Mois!$L$105 -> 35925.98 | D26: =+Print_Mois!$F$105 -> 92939 | E26: =+Print_Mois!$Q$105 -> 59305.27 | F26: =+IFERROR($C26-D26,"") -> -57013.02 | G26: =+IFERROR($C26-E26,"") -> -23379.29 | H26: =+IFERROR(F26/ABS($D26),"") -> -0.61344559 | I26: =+IFERROR(G26/ABS($E26),"") -> -0.39421943
B27: Back Margin / unit | C27: =+C26/C21 -> 1561.9991 | D27: =+D26/D21 -> 2200 | E27: =+E26/E21 -> 2965.2635 | F27: =+IFERROR($C27-D27,"") -> -638.00087 | G27: =+IFERROR($C27-E27,"") -> -1403.2644 | H27: =+IFERROR(F27/ABS($D27),"") -> -0.2900004 | I27: =+IFERROR(G27/ABS($E27),"") -> -0.47323429
B28: $ commission FI | C28: =+Print_Mois!$L$113 -> 10777.44 | D28: =+Print_Mois!$F$113 -> 27881.7 | E28: =+Print_Mois!$Q$113 -> 17747.59 | F28: =+IFERROR($C28-D28,"") -> -17104.26 | G28: =+IFERROR($C28-E28,"") -> -6970.15 | H28: =+IFERROR(F28/ABS($D28),"") -> -0.61345829 | I28: =+IFERROR(G28/ABS($E28),"") -> -0.39273783
B29: % commission FI | C29: =+C28/C26 -> 0.29999015 | D29: =+D28/D26 -> 0.3 | E29: =+E28/E26 -> 0.29925823 | F29: =+IFERROR($C29-D29,"") -> -9.8535934e-06 | G29: =+IFERROR($C29-E29,"") -> 0.0007319186 | H29: =+IFERROR(F29/ABS($D29),"") -> -3.2845311e-05 | I29: =+IFERROR(G29/ABS($E29),"") -> 0.002445776
B30: Variable fees | C30: =+Print_Mois!$L$122-C24-C28 -> 29102.88 | D30: =+Print_Mois!$F$122-D24-D28 -> 27155.59 | E30: =+Print_Mois!$Q$122-E24-E28 -> 17995.13 | F30: =+IFERROR($C30-D30,"") -> 1947.2905 | G30: =+IFERROR($C30-E30,"") -> 11107.75 | H30: =+IFERROR(F30/ABS($D30),"") -> 0.071708642 | I30: =+IFERROR(G30/ABS($E30),"") -> 0.61726423
B31: Variable fees / units | C31: =+C30/C21 -> 1265.3426 | D31: =+D30/D21 -> 642.81192 | E31: =+E30/E21 -> 899.7565 | F31: =+IFERROR($C31-D31,"") -> 622.53069 | G31: =+IFERROR($C31-E31,"") -> 365.58611 | H31: =+IFERROR(F31/ABS($D31),"") -> 0.9684492 | I31: =+IFERROR(G31/ABS($E31),"") -> 0.40631672
B32: Other Revenues | C32: =+Print_Mois!$L$163 -> 6428 | D32: =+Print_Mois!$F$163 -> 20026.242 | E32: =+Print_Mois!$Q$163 -> 7645 | F32: =+IFERROR($C32-D32,"") -> -13598.242 | G32: =+IFERROR($C32-E32,"") -> -1217 | H32: =+IFERROR(F32/ABS($D32),"") -> -0.67902116 | I32: =+IFERROR(G32/ABS($E32),"") -> -0.15918901
B33: Inventory
B34: Units | C34: =Inventaire_Used!N3 -> 111 | D34: 68 | E34: 92 | F34: =+IFERROR($C34-D34,"") -> 43 | G34: =+IFERROR($C34-E34,"") -> 19 | H34: =+IFERROR(F34/ABS($D34),"") -> 0.63235294 | I34: =+IFERROR(G34/ABS($E34),"") -> 0.20652174
B35: $ | C35: =Inventaire_Used!N2 -> 2779322.1 | D35: 1072231 | E35: 1510979 | F35: =+IFERROR($C35-D35,"") -> 1707091.1 | G35: =+IFERROR($C35-E35,"") -> 1268343.1 | H35: =+IFERROR(F35/ABS($D35),"") -> 1.5920927 | I35: =+IFERROR(G35/ABS($E35),"") -> 0.83941809
B37: Service | C37: Actual | D37: Budget | E37: =$E$3 -> 2023 | F37: ▲ Budget | G37: =$G$3 -> ▲2023 | H37: % ▲ Budget | I37: =$I$3 -> % ▲ 2023 | J37: Commentaires
B38: Revenus | C38: =+Print_Mois!$K$194 -> 367237.81 | D38: =+Print_Mois!$E$194 -> 427783.68 | E38: =+Print_Mois!$P$194 -> 280679.91 | F38: =+IFERROR($C38-D38,"") -> -60545.867 | G38: =+IFERROR($C38-E38,"") -> 86557.9 | H38: =+IFERROR(F38/ABS($D38),"") -> -0.14153384 | I38: =+IFERROR(G38/ABS($E38),"") -> 0.30838652 | J38: Un très beau mois de brut, le niveau de contrôle et d'organisation de Tommy Martel-Diotte semble assez avancé. Autant le % de profit brut client est au-dessus du budget que nous devons être plus forts sur la garantie et l'esthétique. Toutes les dépenses sont maitrisées. Le choix des coûts variables sur les véhicules de compagnie semble un bon choix pour ce 1er mois d'essai. Département possiblement très fort en 2024 à suivre de près.
B39: Gross margin | C39: =+Print_Mois!$L$194 -> 260372.18 | D39: =+Print_Mois!$F$194 -> 302728.48 | E39: =+Print_Mois!$Q$194 -> 200133.83 | F39: =+IFERROR($C39-D39,"") -> -42356.299 | G39: =+IFERROR($C39-E39,"") -> 60238.35 | H39: =+IFERROR(F39/ABS($D39),"") -> -0.13991515 | I39: =+IFERROR(G39/ABS($E39),"") -> 0.30099034
B40: $ Revenus / #WO client | C40: =+Print_Mois!$K$172/Print_Mois!$J$172 -> 294.83778 | D40: =+IFERROR(Print_Mois!$E$172/Print_Mois!$D$172,"") -> 330 | E40: =+Print_Mois!$P$172/Print_Mois!$O$172 -> 318.36427 | F40: =+IFERROR($C40-D40,"") -> -35.162224 | G40: =+IFERROR($C40-E40,"") -> -23.526492 | H40: =+IFERROR(F40/ABS($D40),"") -> -0.10655219 | I40: =+IFERROR(G40/ABS($E40),"") -> -0.073898029
B41: $ Revenus / #WO garantie | C41: =+Print_Mois!$K$175/Print_Mois!$J$175 -> 237.80848 | D41: =+IFERROR(Print_Mois!$E$175/Print_Mois!$D$175,"") -> 270 | E41: =+Print_Mois!$P$175/Print_Mois!$O$175 -> 257.06947 | F41: =+IFERROR($C41-D41,"") -> -32.191515 | G41: =+IFERROR($C41-E41,"") -> -19.260989 | H41: =+IFERROR(F41/ABS($D41),"") -> -0.11922783 | I41: =+IFERROR(G41/ABS($E41),"") -> -0.074925228
B42: Lost time | C42: =+Print_Mois!$L$184 -> -3446.54 | D42: =+Print_Mois!$F$184 -> -4558.5904 | E42: =+Print_Mois!$Q$184 -> -3057.78 | F42: =+IFERROR($C42-D42,"") -> 1112.0504 | G42: =+IFERROR($C42-E42,"") -> -388.76 | H42: =+IFERROR(F42/ABS($D42),"") -> 0.24394611 | I42: =+IFERROR(G42/ABS($E42),"") -> -0.12713799
B43: Total salaries | C43: =+Print_Mois!$L$210 -> 140404.3 | D43: =+Print_Mois!$F$210 -> 145383.85 | E43: =+Print_Mois!$Q$210 -> 102297.56 | F43: =+IFERROR($C43-D43,"") -> -4979.5502 | G43: =+IFERROR($C43-E43,"") -> 38106.74 | H43: =+IFERROR(F43/ABS($D43),"") -> -0.034251055 | I43: =+IFERROR(G43/ABS($E43),"") -> 0.37250879
B44: Salaries | C44: =+SUM(Print_Mois!$L$198:$L$204) -> 81957.81 | D44: =+SUM(Print_Mois!$F$198:$F$204) -> 78908.138 | E44: =+SUM(Print_Mois!$Q$198:$Q$204) -> 53530.48 | F44: =+IFERROR($C44-D44,"") -> 3049.6722 | G44: =+IFERROR($C44-E44,"") -> 28427.33 | H44: =+IFERROR(F44/ABS($D44),"") -> 0.038648387 | I44: =+IFERROR(G44/ABS($E44),"") -> 0.53104941
B45: Fringes | C45: =+SUM(Print_Mois!$L$205:$L$209) -> 58446.49 | D45: =+SUM(Print_Mois!$F$205:$F$209) -> 66475.712 | E45: =+SUM(Print_Mois!$Q$205:$Q$209) -> 48767.08 | F45: =+IFERROR($C45-D45,"") -> -8029.2225 | G45: =+IFERROR($C45-E45,"") -> 9679.41 | H45: =+IFERROR(F45/ABS($D45),"") -> -0.1207843 | I45: =+IFERROR(G45/ABS($E45),"") -> 0.19848246
B46: Total salaries / Revenus | C46: =+C43/C38 -> 0.38232528 | D46: =+D43/D38 -> 0.33985366 | E46: =+E43/E38 -> 0.36446342 | F46: =+IFERROR($C46-D46,"") -> 0.04247162 | G46: =+IFERROR($C46-E46,"") -> 0.017861864 | H46: =+IFERROR(F46/ABS($D46),"") -> 0.12497032 | I46: =+IFERROR(G46/ABS($E46),"") -> 0.04900866
B47: Frais véhicules de cie | C47: =+Print_Mois!$L$213 -> 13105.98 | D47: =+Print_Mois!$F$213 -> 13333.333 | E47: =+Print_Mois!$Q$213 -> 12465.7 | F47: =+IFERROR($C47-D47,"") -> -227.35333 | G47: =+IFERROR($C47-E47,"") -> 640.28 | H47: =+IFERROR(F47/ABS($D47),"") -> -0.0170515 | I47: =+IFERROR(G47/ABS($E47),"") -> 0.051363341
B49: Pieces | C49: Actual | D49: Budget | E49: =$E$3 -> 2023 | F49: ▲ Budget | G49: =$G$3 -> ▲2023 | H49: % ▲ Budget | I49: =$I$3 -> % ▲ 2023 | J49: Commentaires
B50: Revenus | C50: =+Print_Mois!$J$314 -> 459022.42 | D50: =+Print_Mois!$D$314 -> 592051.32 | E50: =+Print_Mois!$O$314 -> 373126.6 | F50: =+IFERROR($C50-D50,"") -> -133028.9 | G50: =+IFERROR($C50-E50,"") -> 85895.82 | H50: =+IFERROR(F50/ABS($D50),"") -> -0.2246915 | I50: =+IFERROR(G50/ABS($E50),"") -> 0.23020557 | J50: Très gros mois de janvier qui finit over budget. Le volume de livraison de véhicules neufs aide grandement sur la vente de pneus, le wholale a aussi été fort et va continuer de l'être avec les actions menées dès ce premier mois. L'équipe est complète depuis le 12 février.
B51: Clients | C51: =+Print_Mois!$J$295 -> 94158.54 | D51: =+Print_Mois!$D$295 -> 179994.55 | E51: =+Print_Mois!$O$295 -> 103800.09 | F51: =+IFERROR($C51-D51,"") -> -85836.013 | G51: =+IFERROR($C51-E51,"") -> -9641.55 | H51: =+IFERROR(F51/ABS($D51),"") -> -0.47688117 | I51: =+IFERROR(G51/ABS($E51),"") -> -0.092885758
B52: Garantie | C52: =+Print_Mois!$J$297 -> 30357.78 | D52: =+Print_Mois!$D$297 -> 66852 | E52: =+Print_Mois!$O$297 -> 50247.84 | F52: =+IFERROR($C52-D52,"") -> -36494.22 | G52: =+IFERROR($C52-E52,"") -> -19890.06 | H52: =+IFERROR(F52/ABS($D52),"") -> -0.54589571 | I52: =+IFERROR(G52/ABS($E52),"") -> -0.3958391
B53: Wholesale | C53: =+Print_Mois!$J$300 -> 169839.65 | D53: =+Print_Mois!$D$300 -> 114574.82 | E53: =+Print_Mois!$O$300 -> 110639.22 | F53: =+IFERROR($C53-D53,"") -> 55264.829 | G53: =+IFERROR($C53-E53,"") -> 59200.43 | H53: =+IFERROR(F53/ABS($D53),"") -> 0.48234707 | I53: =+IFERROR(G53/ABS($E53),"") -> 0.53507635
B54: Tires | C54: =+Print_Mois!$J$307 -> 33810.45 | D54: =+Print_Mois!$D$307 -> 56512.9 | E54: =+Print_Mois!$O$307 -> 30345.22 | F54: =+IFERROR($C54-D54,"") -> -22702.45 | G54: =+IFERROR($C54-E54,"") -> 3465.23 | H54: =+IFERROR(F54/ABS($D54),"") -> -0.40172155 | I54: =+IFERROR(G54/ABS($E54),"") -> 0.1141936
B55: All others | C55: =+C50-SUM(C51:C54) -> 130856 | D55: =+D50-SUM(D51:D54) -> 174117.05 | E55: =+E50-SUM(E51:E54) -> 78094.23 | F55: =+IFERROR($C55-D55,"") -> -43261.046 | G55: =+IFERROR($C55-E55,"") -> 52761.77 | H55: =+IFERROR(F55/ABS($D55),"") -> -0.24845957 | I55: =+IFERROR(G55/ABS($E55),"") -> 0.67561675
B56: Gross margin | C56: =+Print_Mois!$L$314 -> 126155.98 | D56: =+Print_Mois!$F$314 -> 160924.24 | E56: =+Print_Mois!$Q$314 -> 106002.2 | F56: =+IFERROR($C56-D56,"") -> -34768.264 | G56: =+IFERROR($C56-E56,"") -> 20153.78 | H56: =+IFERROR(F56/ABS($D56),"") -> -0.21605361 | I56: =+IFERROR(G56/ABS($E56),"") -> 0.19012605
B57: $ Revenus / #WO client | C57: =+Print_Mois!$J$295/Print_Mois!$J$172 -> 130.05323 | D57: =+IFERROR(Print_Mois!$D$295/Print_Mois!$D$172,"") -> 231 | E57: =+Print_Mois!$O$295/Print_Mois!$O$172 -> 159.93851 | F57: =+IFERROR($C57-D57,"") -> -100.94677 | G57: =+IFERROR($C57-E57,"") -> -29.885273 | H57: =+IFERROR(F57/ABS($D57),"") -> -0.436999 | I57: =+IFERROR(G57/ABS($E57),"") -> -0.18685477
B58: $ Revenus / #WO garantie | C58: =+Print_Mois!$J$297/Print_Mois!$J$175 -> 306.64424 | D58: =+IFERROR(Print_Mois!$D$297/Print_Mois!$D$175,"") -> 405.10128 | E58: =+Print_Mois!$O$297/Print_Mois!$O$175 -> 661.15579 | F58: =+IFERROR($C58-D58,"") -> -98.457033 | G58: =+IFERROR($C58-E58,"") -> -354.51155 | H58: =+IFERROR(F58/ABS($D58),"") -> -0.24304301 | I58: =+IFERROR(G58/ABS($E58),"") -> -0.53619972
B59: Salaires autres | C59: =+Print_Mois!$L$320 -> 190.37 | D59: =+Print_Mois!$F$320 -> 140.24615 | E59: =+Print_Mois!$Q$320 -> 2573.29 | F59: =+IFERROR($C59-D59,"") -> 50.123846 | G59: =+IFERROR($C59-E59,"") -> -2382.92 | H59: =+IFERROR(F59/ABS($D59),"") -> 0.35739908 | I59: =+IFERROR(G59/ABS($E59),"") -> -0.92602077
B61: Others | C61: Actual | D61: Budget | E61: =$E$3 -> 2023 | F61: ▲ Budget | G61: =$G$3 -> ▲2023 | H61: % ▲ Budget | I61: =$I$3 -> % ▲ 2023 | J61: Commentaires
B62: Total salaries / Gross profits | C62: =+Print_Mois!$AF$433/Print_Mois!$AF$407 -> 0.42116725 | D62: =+Print_Mois!$Z$433/Print_Mois!$Z$407 -> 0.35087401 | E62: =+Print_Mois!$AL$433/Print_Mois!$AL$407 -> 0.49939754 | F62: =+IFERROR($C62-D62,"") -> 0.070293238 | G62: =+IFERROR($C62-E62,"") -> -0.078230286 | H62: =+IFERROR(F62/ABS($D62),"") -> 0.20033755 | I62: =+IFERROR(G62/ABS($E62),"") -> -0.15664932 | J62: Le floor plan sera, entre autres, un point d'ultra vigilance cette année. Nos véhicules sont plus chers et les inventaires pourraient être plus élevés que prévus. Le rôle du DGV va sans doute être essentiellement sur cet axe comme convenu dans le plan d'affaires.
B63: Headcounts | C63: 57 | D63: 59 | E63: 56 | F63: =+IFERROR($C63-D63,"") -> -2 | G63: =+IFERROR($C63-E63,"") -> 1 | H63: =+IFERROR(F63/ABS($D63),"") -> -0.033898305 | I63: =+IFERROR(G63/ABS($E63),"") -> 0.017857143
B64: Marketing | C64: =N17+Print_Mois!$AF$414+Print_Mois!$AF$434 -> 36612.71 | D64: =+Print_Mois!$Z$414+Print_Mois!$Z$434 -> 33302.06 | E64: =+Print_Mois!$AL$414+Print_Mois!$AL$434 -> 32807.78 | F64: =+IFERROR($C64-D64,"") -> 3310.6495 | G64: =+IFERROR($C64-E64,"") -> 3804.93 | H64: =+IFERROR(F64/ABS($D64),"") -> 0.099412754 | I64: =+IFERROR(G64/ABS($E64),"") -> 0.11597645
B65: Other semi-fixed expenses | C65: =+Print_Mois!$AF$452-Print_Mois!$AF$434 -> 112807.46 | D65: =+Print_Mois!$Z$452-Print_Mois!$Z$434 -> 112354.26 | E65: =+Print_Mois!$AL$452-Print_Mois!$AL$434 -> 110723.24 | F65: =+IFERROR($C65-D65,"") -> 453.19508 | G65: =+IFERROR($C65-E65,"") -> 2084.22 | H65: =+IFERROR(F65/ABS($D65),"") -> 0.004033626 | I65: =+IFERROR(G65/ABS($E65),"") -> 0.01882369
B66: Floor plan interest | C66: =+Print_Mois!$AF$415 -> 43374.68 | D66: =+Print_Mois!$Z$415 -> 29992.662 | E66: =+Print_Mois!$AL$415 -> 3889.41 | F66: =+IFERROR($C66-D66,"") -> 13382.018 | G66: =+IFERROR($C66-E66,"") -> 39485.27 | H66: =+IFERROR(F66/ABS($D66),"") -> 0.44617638 | I66: =+IFERROR(G66/ABS($E66),"") -> 10.151995
B67: Others Revenues | C67: =+Print_Mois!$AF$481-C32-C15 -> 39288.01 | D67: =+Print_Mois!$Z$481-D32-D15 -> 0 | E67: =+Print_Mois!$AL$481-E32-E15 -> 130416.22 | F67: =+IFERROR($C67-D67,"") -> 39288.01 | G67: =+IFERROR($C67-E67,"") -> -91128.21 | H67: =+IFERROR(F67/ABS($D67),"") | I67: =+IFERROR(G67/ABS($E67),"") -> -0.69874905
B69: P&L | C69: Actual | D69: Budget | E69: =$E$3 -> 2023 | F69: ▲ Budget | G69: =$G$3 -> ▲2023 | H69: % ▲ Budget | I69: =$I$3 -> % ▲ 2023 | J69: Commentaires
B70: Selling and Marketing | C70: =+Print_Mois!$AF$419-Print_Mois!$AF$415+Print_Mois!$AF$434+Print_Mois!$AF$435+Print_Mois!$AF$436 -> 181526.48 | D70: =+Print_Mois!$Z$419-Print_Mois!$Z$415+Print_Mois!$Z$434+Print_Mois!$Z$435+Print_Mois!$Z$436 -> 227233.81 | E70: =+Print_Mois!$AL$419-Print_Mois!$AL$415+Print_Mois!$AL$434+Print_Mois!$AL$435+Print_Mois!$AL$436 -> 155241.7 | F70: =+IFERROR($C70-D70,"") -> -45707.329 | G70: =+IFERROR($C70-E70,"") -> 26284.78 | H70: =+IFERROR(F70/ABS($D70),"") -> -0.20114669 | I70: =+IFERROR(G70/ABS($E70),"") -> 0.1693152 | J70: Un écart VS le budget pour commencer l'année. On travaillera Q1 dans sa globalité.
B71: S&M / Brut | C71: =+C70/Print_Mois!$AF$407 -> 0.25007622 | D71: =+D70/Print_Mois!$Z$407 -> 0.23778639 | E71: =+E70/Print_Mois!$AL$407 -> 0.27265945 | F71: =+IFERROR($C71-D71,"") -> 0.012289837 | G71: =+IFERROR($C71-E71,"") -> -0.022583224 | H71: =+IFERROR(F71/ABS($D71),"") -> 0.051684358 | I71: =+IFERROR(G71/ABS($E71),"") -> -0.082825754
B72: General & administrative | C72: =+Print_Mois!$AF$466+Print_Mois!$AF$433+Print_Mois!$AF$437+Print_Mois!$AF$439+SUM(Print_Mois!$AF$440:$AF$448)+Print_Mois!$AF$438 -> 452447.46 | D72: =+Print_Mois!$Z$466+Print_Mois!$Z$433+Print_Mois!$Z$437+Print_Mois!$Z$439+SUM(Print_Mois!$Z$440:$Z$448)+Print_Mois!$Z$438 -> 477340.05 | E72: =+Print_Mois!$AL$466+Print_Mois!$AL$433+Print_Mois!$AL$437+Print_Mois!$AL$439+SUM(Print_Mois!$AL$440:$AL$448)+Print_Mois!$AL$438 -> 415362.68 | F72: =+IFERROR($C72-D72,"") -> -24892.588 | G72: =+IFERROR($C72-E72,"") -> 37084.78 | H72: =+IFERROR(F72/ABS($D72),"") -> -0.052148544 | I72: =+IFERROR(G72/ABS($E72),"") -> 0.089282889
B73: G&A / Brut | C73: =+C72/Print_Mois!$AF$407 -> 0.62330494 | D73: =+D72/Print_Mois!$Z$407 -> 0.49950739 | E73: =+E72/Print_Mois!$AL$407 -> 0.72952409 | F73: =+IFERROR($C73-D73,"") -> 0.12379756 | G73: =+IFERROR($C73-E73,"") -> -0.10621914 | H73: =+IFERROR(F73/ABS($D73),"") -> 0.2478393 | I73: =+IFERROR(G73/ABS($E73),"") -> -0.1456006
B74: EBITDA | C74: =+Print_Mois!$AF$483+Print_Mois!$AF$415 -> 280438.52 | D74: =+Print_Mois!$Z$483+Print_Mois!$Z$415 -> 396122.25 | E74: =+Print_Mois!$AL$483+Print_Mois!$AL$415 -> 188503.08 | F74: =+IFERROR($C74-D74,"") -> -115683.73 | G74: =+IFERROR($C74-E74,"") -> 91935.44 | H74: =+IFERROR(F74/ABS($D74),"") -> -0.29204048 | I74: =+IFERROR(G74/ABS($E74),"") -> 0.4877132
B75: EBITDA % | C75: =+C74/Print_Mois!$AF$406 -> 0.047619244 | D75: =+D74/Print_Mois!$Z$406 -> 0.061167221 | E75: =+E74/Print_Mois!$AL$406 -> 0.059301689 | F75: =+IFERROR($C75-D75,"") -> -0.013547977 | G75: =+IFERROR($C75-E75,"") -> -0.011682445 | H75: =+IFERROR(F75/ABS($D75),"") -> -0.2214908 | I75: =+IFERROR(G75/ABS($E75),"") -> -0.19700021
B76: EBIT | C76: =N9+Print_Mois!$AF$498 -> 236019.96 | D76: =+Print_Mois!$Z$498 -> 364481.25 | E76: =+Print_Mois!$AL$498 -> 180299.17 | F76: =+IFERROR($C76-D76,"") -> -128461.29 | G76: =+IFERROR($C76-E76,"") -> 55720.79 | H76: =+IFERROR(F76/ABS($D76),"") -> -0.35244966 | I76: =+IFERROR(G76/ABS($E76),"") -> 0.30904629
B77: EBIT % | C77: =+C76/Print_Mois!$AF$406 -> 0.040076848 | D77: =+D76/Print_Mois!$Z$406 -> 0.056281376 | E77: =+E76/Print_Mois!$AL$406 -> 0.056720799 | F77: =+IFERROR($C77-D77,"") -> -0.016204527 | G77: =+IFERROR($C77-E77,"") -> -0.016643951 | H77: =+IFERROR(F77/ABS($D77),"") -> -0.28791989 | I77: =+IFERROR(G77/ABS($E77),"") -> -0.29343647
B79: "Pacing" du 30
B80: EBITDA | C80: 192027 | D80: 0.039
B81: Écart Fav / (Défav) | C81: =+C74-C80 -> 88411.52
B83: EBIT | C83: 160386 | D83: 0.033
B84: Écart Fav / (Défav) | C84: =+C76-C83 -> 75633.96
B86: =+Parametres!B1 -> Volks | C86: =Parametres!$B$3&" "&Parametres!$B$4 -> Avril 2024 | D86: AAJ 2023
B87: =CONCATENATE("Réalisé ",Parametres!$B$3," ",Parametres!$B$4) -> Réalisé Avril 2024 | C87: =+C76 -> 236019.96 | D87: =+Print_AAD!AF498 -> 332417.28
B88: =CONCATENATE("Budget ",Parametres!$B$3," ",Parametres!$B$4) -> Budget Avril 2024 | C88: =+D76 -> 364481.25 | D88: =+Print_AAD!Z498 -> 413234.43
B89: =CONCATENATE("Réalisé ",Parametres!$B$3," ",Parametres!$B$4-1) -> Réalisé Avril 2023 | C89: =+E76 -> 180299.17 | D89: =+Print_AAD!AL498 -> 328789.9

Sheet Print_Mois
C1: =Parametres!B1 -> Volks | K1: Véhicules neufs | S1: =CONCATENATE("Réalisé,"," ",Parametres!B3," ",Parametres!B4) -> Réalisé, Avril 2024
D2: X | E2: O | F2: U | J2: NB | L2: $ | O2: X | P2: O | Q2: U | V2: *** NE PAS EFFACER / Pour An Précédente ***
D3: BUDGET ORIGINAL | J3: RÉALISATION | M3: ÉCART réel / Budget | O3: ANNÉE PRÉCÉDENTE | R3: ECART (réel/ Ann.Préc.) | V3: NEUF | W3: 0.45
D4: UNITE | E4: $P/UNITÉ | F4: $PROFITS | J4: UNITÉS | K4: $P/UNITE | L4: $PROFITS | M4: UNITÉS | N4: $PROFITS | O4: UNITE | P4: $P/UNITÉ | Q4: $PROFITS | R4: UNITÉS | S4: $PROFITS | V4: USAGE | W4: 0.1
A5: Véhicules neufsVentes nettes | B5: Véhicules neufs | C5: Ventes nettes | F5: =+INDEX('Budget original'!$A$2:$AO$501,MATCH($A5,'Budget original'!$A$2:$A$501,0),MATCH(F$2,'Budget original'!$A$2:$AO$2,0)) -> 3243094.3 | L5: =-SUMIFS(BV_Data_An_Cour!$O:$O,BV_Data_An_Cour!$X:$X,"Oui",BV_Data_An_Cour!$U:$U,$B5) -> 3890022.9 | Q5: {=+INDEX('Réel 2023'!$A$2:$AO$501,MATCH($A5,'Réel 2023'!$A$2:$A$501,0),MATCH(Q$2,'Réel 2023'!$A$2:$AO$2,0))} -> 1765867 | V5: SERVICE | W5: 0.225
A6: Véhicules neufsAutos détail | B6: Véhicules neufs | C6: Autos détail | D6: =+INDEX('Budget original'!$A$2:$AO$501,MATCH($A6,'Budget original'!$A$2:$A$501,0),MATCH(D$2,'Budget original'!$A$2:$AO$2,0)) -> 12 | E6: =IF(D6=0,0,F6/D6) -> 2198.1219 | F6: =+INDEX('Budget original'!$A$2:$AO$501,MATCH($A6,'Budget original'!$A$2:$A$501,0),MATCH(F$2,'Budget original'!$A$2:$AO$2,0)) -> 26377.463 | J6: =-SUMIFS(BV_Data_An_Cour!$O:$O,BV_Data_An_Cour!$U:$U,$B6,BV_Data_An_Cour!$V:$V,$C6,BV_Data_An_Cour!$W:$W,J$2) -> 18 | K6: =IF(J6=0,0,L6/J6) -> 2168.0939 | L6: =-SUMIFS(BV_Data_An_Cour!$O:$O,BV_Data_An_Cour!$U:$U,$B6,BV_Data_An_Cour!$V:$V,$C6,BV_Data_An_Cour!$W:$W,L$2) -> 39025.69 | M6: =J6-D6 -> 6 | N6: =L6-F6 -> 12648.227 | O6: =+INDEX('Réel 2023'!$A$2:$AO$501,MATCH($A6,'Réel 2023'!$A$2:$A$501,0),MATCH(O$2,'Réel 2023'!$A$2:$AO$2,0)) -> 12 | P6: =IF(O6=0,0,Q6/O6) -> 2975.6025 | Q6: {=+INDEX('Réel 2023'!$A$2:$AO$501,MATCH($A6,'Réel 2023'!$A$2:$A$501,0),MATCH(Q$2,'Réel 2023'!$A$2:$AO$2,0))} -> 35707.23 | R6: =J6-O6 -> 6 | S6: =L6-Q6 -> 3318.46 | V6: CARROSSERIE | W6: 0.025
A7: Véhicules neufsCamions détail | B7: Véhicules neufs | C7: Camions détail | D7: =+INDEX('Budget original'!$A$2:$AO$501,MATCH($A7,'Budget original'!$A$2:$A$501,0),MATCH(D$2,'Budget original'!$A$2:$AO$2,0)) -> 50 | E7: =IF(D7=0,0,F7/D7) -> 2850.2587 | F7: =+INDEX('Budget original'!$A$2:$AO$501,MATCH($A7,'Budget original'!$A$2:$A$501,0),MATCH(F$2,'Budget original'!$A$2:$AO$2,0)) -> 142512.93 | J7: =-SUMIFS(BV_Data_An_Cour!$O:$O,BV_Data_An_Cour!$U:$U,$B7,BV_Data_An_Cour!$V:$V,$C7,BV_Data_An_Cour!$W:$W,J$2) -> 51 | K7: =IF(J7=0,0,L7/J7) -> 2906.2869 | L7: =-SUMIFS(BV_Data_An_Cour!$O:$O,BV_Data_An_Cour!$U:$U,$B7,BV_Data_An_Cour!$V:$V,$C7,BV_Data_An_Cour!$W:$W,L$2) -> 148220.63 | M7: =J7-D7 -> 1 | N7: =L7-F7 -> 5707.6952 | O7: {=+INDEX('Réel 2023'!$A$2:$AO$501,MATCH($A7,'Réel 2023'!$A$2:$A$501,0),MATCH(O$2,'Réel 2023'!$A$2:$AO$2,0))} -> 16 | P7: =IF(O7=0,0,Q7/O7) -> 2481.2725 | Q7: {=+INDEX('Réel 2023'!$A$2:$AO$501,MATCH($A7,'Réel 2023'!$A$2:$A$501,0),MATCH(Q$2,'Réel 2023'!$A$2:$AO$2,0))} -> 39700.36 | R7: =J7-O7 -> 35 | S7: =L7-Q7 -> 108520.27 | V7: PIECES | W7: 0.2
A8: Véhicules neufsSprinter | B8: Véhicules neufs | C8: Sprinter | D8: =+INDEX('Budget original'!$A$2:$AO$501,MATCH($A8,'Budget original'!$A$2:$A$501,0),MATCH(D$2,'Budget original'!$A$2:$AO$2,0)) -> 0 | E8: =IF(D8=0,0,F8/D8) -> 0 | F8: =+INDEX('Budget original'!$A$2:$AO$501,MATCH($A8,'Budget original'!$A$2:$A$501,0),MATCH(F$2,'Budget original'!$A$2:$AO$2,0)) -> 0 | J8: =-SUMIFS(BV_Data_An_Cour!$O:$O,BV_Data_An_Cour!$U:$U,$B8,BV_Data_An_Cour!$V:$V,$C8,BV_Data_An_Cour!$W:$W,J$2) -> 0 | K8: =IF(J8=0,0,L8/J8) -> 0 | L8: =-SUMIFS(BV_Data_An_Cour!$O:$O,BV_Data_An_Cour!$U:$U,$B8,BV_Data_An_Cour!$V:$V,$C8,BV_Data_An_Cour!$W:$W,L$2) -> 0 | M8: =J8-D8 -> 0 | N8: =L8-F8 -> 0 | O8: {=+INDEX('Réel 2023'!$A$2:$AO$501,MATCH($A8,'Réel 2023'!$A$2:$A$501,0),MATCH(O$2,'Réel 2023'!$A$2:$AO$2,0))} -> 0 | P8: =IF(O8=0,0,Q8/O8) -> 0 | Q8: {=+INDEX('Réel 2023'!$A$2:$AO$501,MATCH($A8,'Réel 2023'!$A$2:$A$501,0),MATCH(Q$2,'Réel 2023'!$A$2:$AO$2,0))} -> 0 | R8: =J8-O8 -> 0 | S8: =L8-Q8 -> 0 | W8: =SUM(W3:W7) -> 1
A9: Véhicules neufsMoto détail | B9: Véhicules neufs | C9: Moto détail | D9: =+INDEX('Budget original'!$A$2:$AO$501,MATCH($A9,'Budget original'!$A$2:$A$501,0),MATCH(D$2,'Budget original'!$A$2:$AO$2,0)) -> 0 | E9: =IF(D9=0,0,F9/D9) -> 0 | F9: =+INDEX('Budget original'!$A$2:$AO$501,MATCH($A9,'Budget original'!$A$2:$A$501,0),MATCH(F$2,'Budget original'!$A$2:$AO$2,0)) -> 0 | J9: =-SUMIFS(BV_Data_An_Cour!$O:$O,BV_Data_An_Cour!$U:$U,$B9,BV_Data_An_Cour!$V:$V,$C9,BV_Data_An_Cour!$W:$W,J$2) -> 0 | K9: =IF(J9=0,0,L9/J9) -> 0 | L9: =-SUMIFS(BV_Data_An_Cour!$O:$O,BV_Data_An_Cour!$U:$U,$B9,BV_Data_An_Cour!$V:$V,$C9,BV_Data_An_Cour!$W:$W,L$2) -> 0 | M9: =J9-D9 -> 0 | N9: =L9-F9 -> 0 | O9: {=+INDEX('Réel 2023'!$A$2:$AO$501,MATCH($A9,'Réel 2023'!$A$2:$A$501,0),MATCH(O$2,'Réel 2023'!$A$2:$AO$2,0))} -> 0 | P9: =IF(O9=0,0,Q9/O9) -> 0 | Q9: {=+INDEX('Réel 2023'!$A$2:$AO$501,MATCH($A9,'Réel 2023'!$A$2:$A$501,0),MATCH(Q$2,'Réel 2023'!$A$2:$AO$2,0))} -> 0 | R9: =J9-O9 -> 0 | S9: =L9-Q9 -> 0
A10: Véhicules neufs[...] | B10: Véhicules neufs | C10: [...] | D10: =+INDEX('Budget original'!$A$2:$AO$501,MATCH($A10,'Budget original'!$A$2:$A$501,0),MATCH(D$2,'Budget original'!$A$2:$AO$2,0)) -> 0 | E10: =IF(D10=0,0,F10/D10) -> 0 | F10: =+INDEX('Budget original'!$A$2:$AO$501,MATCH($A10,'Budget original'!$A$2:$A$501,0),MATCH(F$2,'Budget original'!$A$2:$AO$2,0)) -> 0 | J10: =-SUMIFS(BV_Data_An_Cour!$O:$O,BV_Data_An_Cour!$U:$U,$B10,BV_Data_An_Cour!$V:$V,$C10,BV_Data_An_Cour!$W:$W,J$2) -> 0 | K10: =IF(J10=0,0,L10/J10) -> 0 | L10: =-SUMIFS(BV_Data_An_Cour!$O:$O,BV_Data_An_Cour!$U:$U,$B10,BV_Data_An_Cour!$V:$V,$C10,BV_Data_An_Cour!$W:$W,L$2) -> 0 | M10: =J10-D10 -> 0 | N10: =L10-F10 -> 0 | O10: {=+INDEX('Réel 2023'!$A$2:$AO$501,MATCH($A10,'Réel 2023'!$A$2:$A$501,0),MATCH(O$2,'Réel 2023'!$A$2:$AO$2,0))} -> 0 | P10: =IF(O10=0,0,Q10/O10) -> 0 | Q10: {=+INDEX('Réel 2023'!$A$2:$AO$501,MATCH($A10,'Réel 2023'!$A$2:$A$501,0),MATCH(Q$2,'Réel 2023'!$A$2:$AO$2,0))} -> 0 | R10: =J10-O10 -> 0 | S10: =L10-Q10 -> 0
A11: Véhicules neufs[...] | B11: Véhicules neufs | C11: [...] | D11: =+INDEX('Budget original'!$A$2:$AO$501,MATCH($A11,'Budget original'!$A$2:$A$501,0),MATCH(D$2,'Budget original'!$A$2:$AO$2,0)) -> 0 | E11: =IF(D11=0,0,F11/D11) -> 0 | F11: =+INDEX('Budget original'!$A$2:$AO$501,MATCH($A11,'Budget original'!$A$2:$A$501,0),MATCH(F$2,'Budget original'!$A$2:$AO$2,0)) -> 0 | J11: =-SUMIFS(BV_Data_An_Cour!$O:$O,BV_Data_An_Cour!$U:$U,$B11,BV_Data_An_Cour!$V:$V,$C11,BV_Data_An_Cour!$W:$W,J$2) -> 0 | K11: =IF(J11=0,0,L11/J11) -> 0 | L11: =-SUMIFS(BV_Data_An_Cour!$O:$O,BV_Data_An_Cour!$U:$U,$B11,BV_Data_An_Cour!$V:$V,$C11,BV_Data_An_Cour!$W:$W,L$2) -> 0 | M11: =J11-D11 -> 0 | N11: =L11-F11 -> 0 | O11: {=+INDEX('Réel 2023'!$A$2:$AO$501,MATCH($A11,'Réel 2023'!$A$2:$A$501,0),MATCH(O$2,'Réel 2023'!$A$2:$AO$2,0))} -> 0 | P11: =IF(O11=0,0,Q11/O11) -> 0 | Q11: {=+INDEX('Réel 2023'!$A$2:$AO$501,MATCH($A11,'Réel 2023'!$A$2:$A$501,0),MATCH(Q$2,'Réel 2023'!$A$2:$AO$2,0))} -> 0 | R11: =J11-O11 -> 0 | S11: =L11-Q11 -> 0
A12: Véhicules neufs[...] | B12: Véhicules neufs | C12: [...] | D12: =+INDEX('Budget original'!$A$2:$AO$501,MATCH($A12,'Budget original'!$A$2:$A$501,0),MATCH(D$2,'Budget original'!$A$2:$AO$2,0)) -> 0 | E12: =IF(D12=0,0,F12/D12) -> 0 | F12: =+INDEX('Budget original'!$A$2:$AO$501,MATCH($A12,'Budget original'!$A$2:$A$501,0),MATCH(F$2,'Budget original'!$A$2:$AO$2,0)) -> 0 | J12: =-SUMIFS(BV_Data_An_Cour!$O:$O,BV_Data_An_Cour!$U:$U,$B12,BV_Data_An_Cour!$V:$V,$C12,BV_Data_An_Cour!$W:$W,J$2) -> 0 | K12: =IF(J12=0,0,L12/J12) -> 0 | L12: =-SUMIFS(BV_Data_An_Cour!$O:$O,BV_Data_An_Cour!$U:$U,$B12,BV_Data_An_Cour!$V:$V,$C12,BV_Data_An_Cour!$W:$W,L$2) -> 0 | M12: =J12-D12 -> 0 | N12: =L12-F12 -> 0 | O12: {=+INDEX('Réel 2023'!$A$2:$AO$501,MATCH($A12,'Réel 2023'!$A$2:$A$501,0),MATCH(O$2,'Réel 2023'!$A$2:$AO$2,0))} -> 0 | P12: =IF(O12=0,0,Q12/O12) -> 0 | Q12: {=+INDEX('Réel 2023'!$A$2:$AO$501,MATCH($A12,'Réel 2023'!$A$2:$A$501,0),MATCH(Q$2,'Réel 2023'!$A$2:$AO$2,0))} -> 0 | R12: =J12-O12 -> 0 | S12: =L12-Q12 -> 0
A13: Véhicules neufsTotal Neufs | B13: Véhicules neufs | C13: Total Neufs | D13: =+SUM(D6:D12) -> 62 | E13: =IF(D13<=0,0,F13/D13) -> 2724.0387 | F13: =+SUM(F6:F12) -> 168890.4 | J13: =+SUM(J6:J12) -> 69 | K13: =IF(J13<=0,0,L13/J13) -> 2713.7148 | L13: =+SUM(L6:L12) -> 187246.32 | M13: =+SUM(M6:M12) -> 7 | N13: =+SUM(N6:N12) -> 18355.922 | O13: =+SUM(O6:O12) -> 28 | P13: =IF(O13<=0,0,Q13/O13) -> 2693.1282 | Q13: =+SUM(Q6:Q12) -> 75407.59 | R13: =+SUM(R6:R12) -> 41 | S13: =+SUM(S6:S12) -> 111838.73
A14: Véhicules neufs | B14: Véhicules neufs | M14: =IF(D13=0,0,M13/D13) -> 0.11290323 | N14: =IF(F13=0,0,N13/F13) -> 0.10868541 | R14: =R13/O13 -> 1.4642857 | S14: =IF(Q13=0,0,(S13/Q13)) -> 1.483123 | AD14: 20 | AE14: 1000 | AF14: =AD14*AE14 -> 20000
A15: Véhicules neufsEx-Démos et courtoisies | B15: Véhicules neufs | C15: Ex-Démos et courtoisies | D15: =+INDEX('Budget original'!$A$2:$AO$501,MATCH($A15,'Budget original'!$A$2:$A$501,0),MATCH(D$2,'Budget original'!$A$2:$AO$2,0)) -> 5 | E15: =IF(D15=0,0,F15/D15) -> 2484.4192 | F15: =+INDEX('Budget original'!$A$2:$AO$501,MATCH($A15,'Budget original'!$A$2:$A$501,0),MATCH(F$2,'Budget original'!$A$2:$AO$2,0)) -> 12422.096 | J15: =-SUMIFS(BV_Data_An_Cour!$O:$O,BV_Data_An_Cour!$U:$U,$B15,BV_Data_An_Cour!$V:$V,$C15,BV_Data_An_Cour!$W:$W,J$2) -> 4 | K15: =IF(J15=0,0,L15/J15) -> 2264.375 | L15: =-SUMIFS(BV_Data_An_Cour!$O:$O,BV_Data_An_Cour!$U:$U,$B15,BV_Data_An_Cour!$V:$V,$C15,BV_Data_An_Cour!$W:$W,L$2) -> 9057.5 | M15: =J15-D15 -> -1 | N15: =L15-F15 -> -3364.5958 | O15: {=+INDEX('Réel 2023'!$A$2:$AO$501,MATCH($A15,'Réel 2023'!$A$2:$A$501,0),MATCH(O$2,'Réel 2023'!$A$2:$AO$2,0))} -> 6 | P15: =IF(O15=0,0,Q15/O15) -> 1717.8083 | Q15: {=+INDEX('Réel 2023'!$A$2:$AO$501,MATCH($A15,'Réel 2023'!$A$2:$A$501,0),MATCH(Q$2,'Réel 2023'!$A$2:$AO$2,0))} -> 10306.85 | R15: =J15-O15 -> -2 | S15: =L15-Q15 -> -1249.35 | AD15: 25 | AE15: =AF15/AD15 -> 800 | AF15: =AF14 -> 20000
A16: Véhicules neufs | B16: Véhicules neufs
A17: Véhicules neufsFlottes | B17: Véhicules neufs | C17: Flottes | D17: =+INDEX('Budget original'!$A$2:$AO$501,MATCH($A17,'Budget original'!$A$2:$A$501,0),MATCH(D$2,'Budget original'!$A$2:$AO$2,0)) -> 4.5 | E17: =IF(D17=0,0,F17/D17) -> 2664.4641 | F17: =+INDEX('Budget original'!$A$2:$AO$501,MATCH($A17,'Budget original'!$A$2:$A$501,0),MATCH(F$2,'Budget original'!$A$2:$AO$2,0)) -> 11990.088 | J17: =-SUMIFS(BV_Data_An_Cour!$O:$O,BV_Data_An_Cour!$U:$U,$B17,BV_Data_An_Cour!$V:$V,$C17,BV_Data_An_Cour!$W:$W,J$2) -> 0 | K17: =IF(J17=0,0,L17/J17) -> 0 | L17: =-SUMIFS(BV_Data_An_Cour!$O:$O,BV_Data_An_Cour!$U:$U,$B17,BV_Data_An_Cour!$V:$V,$C17,BV_Data_An_Cour!$W:$W,L$2) -> 0 | M17: =J17-D17 -> -4.5 | N17: =L17-F17 -> -11990.088 | O17: {=+INDEX('Réel 2023'!$A$2:$AO$501,MATCH($A17,'Réel 2023'!$A$2:$A$501,0),MATCH(O$2,'Réel 2023'!$A$2:$AO$2,0))} -> 3 | P17: =IF(O17=0,0,Q17/O17) -> 3228.9067 | Q17: {=+INDEX('Réel 2023'!$A$2:$AO$501,MATCH($A17,'Réel 2023'!$A$2:$A$501,0),MATCH(Q$2,'Réel 2023'!$A$2:$AO$2,0))} -> 9686.72 | R17: =J17-O17 -> -3 | S17: =L17-Q17 -> -9686.72
A18: Véhicules neufs | B18: Véhicules neufs
A19: Véhicules neufsRachat bail | B19: Véhicules neufs | C19: Rachat bail | D19: =+INDEX('Budget original'!$A$2:$AO$501,MATCH($A19,'Budget original'!$A$2:$A$501,0),MATCH(D$2,'Budget original'!$A$2:$AO$2,0)) -> 0 | E19: =IF(D19=0,0,F19/D19) -> 0 | F19: =+INDEX('Budget original'!$A$2:$AO$501,MATCH($A19,'Budget original'!$A$2:$A$501,0),MATCH(F$2,'Budget original'!$A$2:$AO$2,0)) -> 8500 | L19: =-SUMIFS(BV_Data_An_Cour!$O:$O,BV_Data_An_Cour!$U:$U,$B19,BV_Data_An_Cour!$V:$V,$C19,BV_Data_An_Cour!$W:$W,L$2) -> 6030.37 | N19: =L19-F19 -> -2469.63 | Q19: {=+INDEX('Réel 2023'!$A$2:$AO$501,MATCH($A19,'Réel 2023'!$A$2:$A$501,0),MATCH(Q$2,'Réel 2023'!$A$2:$AO$2,0))} -> 7229.27 | R19: =O19-K19 -> 0 | S19: =L19-Q19 -> -1198.9
A20: Véhicules neufs | B20: Véhicules neufs
A21: Véhicules neufsRev. Finances | B21: Véhicules neufs | C21: Rev. Finances | D21: =+INDEX('Budget original'!$A$2:$AO$501,MATCH($A21,'Budget original'!$A$2:$A$501,0),MATCH(D$2,'Budget original'!$A$2:$AO$2,0)) -> 0 | E21: =IF(D21=0,0,F21/D21) -> 0 | F21: =+INDEX('Budget original'!$A$2:$AO$501,MATCH($A21,'Budget original'!$A$2:$A$501,0),MATCH(F$2,'Budget original'!$A$2:$AO$2,0)) -> 13400 | K21: =IF(J13=0,0,L21/(J13+J15)) -> 0 | L21: =-SUMIFS(BV_Data_An_Cour!$O:$O,BV_Data_An_Cour!$U:$U,$B21,BV_Data_An_Cour!$V:$V,$C21,BV_Data_An_Cour!$W:$W,L$2) -> 0 | N21: =L21-F21 -> -13400 | Q21: {=+INDEX('Réel 2023'!$A$2:$AO$501,MATCH($A21,'Réel 2023'!$A$2:$A$501,0),MATCH(Q$2,'Réel 2023'!$A$2:$AO$2,0))} -> 2434.63 | R21: =O21-K21 -> 0 | S21: =L21-Q21 -> -2434.63
A22: Véhicules neufsRev. Protections | B22: Véhicules neufs | C22: Rev. Protections | D22: =+INDEX('Budget original'!$A$2:$AO$501,MATCH($A22,'Budget original'!$A$2:$A$501,0),MATCH(D$2,'Budget original'!$A$2:$AO$2,0)) -> 0 | E22: =IF(D22=0,0,F22/D22) -> 0 | F22: =+INDEX('Budget original'!$A$2:$AO$501,MATCH($A22,'Budget original'!$A$2:$A$501,0),MATCH(F$2,'Budget original'!$A$2:$AO$2,0)) -> 72360 | K22: =IF(J13=0,0,L22/(J13+J15)) -> 765.92219 | L22: =-SUMIFS(BV_Data_An_Cour!$O:$O,BV_Data_An_Cour!$U:$U,$B22,BV_Data_An_Cour!$V:$V,$C22,BV_Data_An_Cour!$W:$W,L$2) -> 55912.32 | N22: =L22-F22 -> -16447.68 | Q22: {=+INDEX('Réel 2023'!$A$2:$AO$501,MATCH($A22,'Réel 2023'!$A$2:$A$501,0),MATCH(Q$2,'Réel 2023'!$A$2:$AO$2,0))} -> 31050.48 | R22: =O22-K22 -> -765.92219 | S22: =L22-Q22 -> 24861.84
A23: Véhicules neufsRev. Autres | B23: Véhicules neufs | C23: Rev. Autres | D23: =+INDEX('Budget original'!$A$2:$AO$501,MATCH($A23,'Budget original'!$A$2:$A$501,0),MATCH(D$2,'Budget original'!$A$2:$AO$2,0)) -> 0 | E23: =IF(D23=0,0,F23/D23) -> 0 | F23: =+INDEX('Budget original'!$A$2:$AO$501,MATCH($A23,'Budget original'!$A$2:$A$501,0),MATCH(F$2,'Budget original'!$A$2:$AO$2,0)) -> 1340 | K23: =IF(J13=0,0,L23/(J13+J15)) -> 18.60589 | L23: =-SUMIFS(BV_Data_An_Cour!$O:$O,BV_Data_An_Cour!$U:$U,$B23,BV_Data_An_Cour!$V:$V,$C23,BV_Data_An_Cour!$W:$W,L$2) -> 1358.23 | N23: =L23-F23 -> 18.23 | Q23: {=+INDEX('Réel 2023'!$A$2:$AO$501,MATCH($A23,'Réel 2023'!$A$2:$A$501,0),MATCH(Q$2,'Réel 2023'!$A$2:$AO$2,0))} -> 0 | R23: =O23-K23 -> -18.60589 | S23: =L23-Q23 -> 1358.23
A24: Véhicules neufsTotal F&I | B24: Véhicules neufs | C24: Total F&I | D24: =+D15+D13 -> 67 | E24: =IF(D24<=0,0,F24/D24) -> 1300 | F24: =F21+F22+F23 -> 87100 | J24: =+J15+J13 -> 73 | K24: =IF(J24<=0,0,L24/J24) -> 784.52808 | L24: =L21+L22+L23 -> 57270.55 | M24: =J24-D24 -> 6 | N24: =L24-F24 -> -29829.45 | O24: =+O15+O13 -> 34 | P24: =IF(O24<=0,0,Q24/O24) -> 984.85618 | Q24: =Q21+Q22+Q23 -> 33485.11 | S24: =L24-Q24 -> 23785.44
A25: Véhicules neufs | B25: Véhicules neufs | N25: =IF(N24=0,0,N24/F24) -> -0.34247359 | S25: =IF(Q24=0,0,(S24/Q24)) -> 0.71032886
A26: Véhicules neufs | B26: Véhicules neufs
A27: Véhicules neufsTotal Dépt. Neufs | B27: Véhicules neufs | C27: Total Dépt. Neufs | D27: =+D13+D15+D17 -> 71.5 | E27: =IF(D27<=0,0,F27/D27) -> 4040.5956 | F27: =F13+F17+F24+F19+F15 -> 288902.58 | J27: =+J13+J15+J17 -> 73 | K27: =IF(J27<=0,0,L27/J27) -> 3556.2293 | L27: =L13+L17+L24+L19+L15 -> 259604.74 | M27: =J27-D27 -> 1.5 | N27: =L27-F27 -> -29297.842 | O27: =+O13+O15+O17 -> 37 | P27: =IF(O27<=0,0,Q27/O27) -> 3678.7984 | Q27: =Q13+Q17+Q24+Q19+Q15 -> 136115.54 | R27: =J27-O27 -> 36 | S27: =L27-Q27 -> 123489.2
A28: Véhicules neufs | B28: Véhicules neufs | L28: =L27/F27 -> 0.8985892 | M28: =M27/D27 -> 0.020979021 | N28: =N27/F27 -> -0.1014108 | R28: =R27/O27 -> 0.97297297 | S28: =IF(Q27=0,0,S27/Q27) -> 0.90723807
A29: Véhicules neufs | B29: Véhicules neufs
A30: Véhicules neufsDEPENSES | B30: Véhicules neufs | C30: DEPENSES
A31: Véhicules neufsComm. vendeurs | B31: Véhicules neufs | C31: Comm. vendeurs | D31: =F31/(F13+F15) -> 0.34 | E31: =F31/D$24 -> 920.09325 | F31: =+INDEX('Budget original'!$A$2:$AO$501,MATCH($A31,'Budget original'!$A$2:$A$501,0),MATCH(F$2,'Budget original'!$A$2:$AO$2,0)) -> 61646.248 | J31: =L31/(L15+L13+L17) -> 0.24820205 | K31: =IF(L31=0,0,L31/J$24) -> 667.43849 | L31: =SUMIFS(BV_Data_An_Cour!$O:$O,BV_Data_An_Cour!$U:$U,$B31,BV_Data_An_Cour!$V:$V,$C31,BV_Data_An_Cour!$W:$W,L$2) -> 48723.01 | N31: =L31-F31 -> -12923.238 | O31: =Q31/(Q13+Q15+Q17) -> 0.38883657 | P31: =Q31/O$24 -> 1091.0429 | Q31: {=+INDEX('Réel 2023'!$A$2:$AO$501,MATCH($A31,'Réel 2023'!$A$2:$A$501,0),MATCH(Q$2,'Réel 2023'!$A$2:$AO$2,0))} -> 37095.46 | S31: =L31-Q31 -> 11627.55
A32: Véhicules neufsComm. F&I | B32: Véhicules neufs | C32: Comm. F&I | D32: =F32/F24 -> 0.3 | E32: =F32/D$24 -> 390 | F32: =+INDEX('Budget original'!$A$2:$AO$501,MATCH($A32,'Budget original'!$A$2:$A$501,0),MATCH(F$2,'Budget original'!$A$2:$AO$2,0)) -> 26130 | J32: =L32/L24 -> 0.29711868 | K32: =IF(L32=0,0,L32/J$24) -> 233.09795 | L32: =SUMIFS(BV_Data_An_Cour!$O:$O,BV_Data_An_Cour!$U:$U,$B32,BV_Data_An_Cour!$V:$V,$C32,BV_Data_An_Cour!$W:$W,L$2) -> 17016.15 | N32: =L32-F32 -> -9113.85 | O32: =Q32/Q24 -> 0.2997816 | P32: =Q32/O$24 -> 295.24176 | Q32: {=+INDEX('Réel 2023'!$A$2:$AO$501,MATCH($A32,'Réel 2023'!$A$2:$A$501,0),MATCH(Q$2,'Réel 2023'!$A$2:$AO$2,0))} -> 10038.22 | S32: =L32-Q32 -> 6977.93
A33: Véhicules neufsFrais de livraison | B33: Véhicules neufs | C33: Frais de livraison | E33: =F33/D$24 -> 115 | F33: =+INDEX('Budget original'!$A$2:$AO$501,MATCH($A33,'Budget original'!$A$2:$A$501,0),MATCH(F$2,'Budget original'!$A$2:$AO$2,0)) -> 7705 | K33: =IF(L33=0,0,L33/J$24) -> 51.42137 | L33: =SUMIFS(BV_Data_An_Cour!$O:$O,BV_Data_An_Cour!$U:$U,$B33,BV_Data_An_Cour!$V:$V,$C33,BV_Data_An_Cour!$W:$W,L$2) -> 3753.76 | N33: =L33-F33 -> -3951.24 | P33: =Q33/O$24 -> 99.448824 | Q33: {=+INDEX('Réel 2023'!$A$2:$AO$501,MATCH($A33,'Réel 2023'!$A$2:$A$501,0),MATCH(Q$2,'Réel 2023'!$A$2:$AO$2,0))} -> 3381.26 | S33: =L33-Q33 -> 372.5
A34: Véhicules neufsService gratuit 1 | B34: Véhicules neufs | C34: Service gratuit 1 | E34: =F34/D$24 -> 3 | F34: =+INDEX('Budget original'!$A$2:$AO$501,MATCH($A34,'Budget original'!$A$2:$A$501,0),MATCH(F$2,'Budget original'!$A$2:$AO$2,0)) -> 201 | K34: =IF(L34=0,0,L34/J$24) -> 1.5160274 | L34: =SUMIFS(BV_Data_An_Cour!$O:$O,BV_Data_An_Cour!$U:$U,$B34,BV_Data_An_Cour!$V:$V,$C34,BV_Data_An_Cour!$W:$W,L$2) -> 110.67 | N34: =L34-F34 -> -90.33 | P34: =Q34/O$24 -> 2.3529412 | Q34: {=+INDEX('Réel 2023'!$A$2:$AO$501,MATCH($A34,'Réel 2023'!$A$2:$A$501,0),MATCH(Q$2,'Réel 2023'!$A$2:$AO$2,0))} -> 80 | S34: =L34-Q34 -> 30.67
A35: Véhicules neufsEntretien stock | B35: Véhicules neufs | C35: Entretien stock | E35: =F35/D$24 -> 85.05 | F35: =+INDEX('Budget original'!$A$2:$AO$501,MATCH($A35,'Budget original'!$A$2:$A$501,0),MATCH(F$2,'Budget original'!$A$2:$AO$2,0)) -> 5698.35 | K35: =IF(L35=0,0,L35/J$24) -> 164.94 | L35: =SUMIFS(BV_Data_An_Cour!$O:$O,BV_Data_An_Cour!$U:$U,$B35,BV_Data_An_Cour!$V:$V,$C35,BV_Data_An_Cour!$W:$W,L$2) -> 12040.62 | N35: =L35-F35 -> 6342.27 | P35: =Q35/O$24 -> 88.82 | Q35: {=+INDEX('Réel 2023'!$A$2:$AO$501,MATCH($A35,'Réel 2023'!$A$2:$A$501,0),MATCH(Q$2,'Réel 2023'!$A$2:$AO$2,0))} -> 3019.88 | S35: =L35-Q35 -> 9020.74
A36: Véhicules neufsPublicité 1 | B36: Véhicules neufs | C36: Publicité 1 | E36: =F36/D$24 -> 112.47761 | F36: =+INDEX('Budget original'!$A$2:$AO$501,MATCH($A36,'Budget original'!$A$2:$A$501,0),MATCH(F$2,'Budget original'!$A$2:$AO$2,0)) -> 7536 | K36: =IF(L36=0,0,L36/J$24) -> 131.05397 | L36: =SUMIFS(BV_Data_An_Cour!$O:$O,BV_Data_An_Cour!$U:$U,$B36,BV_Data_An_Cour!$V:$V,$C36,BV_Data_An_Cour!$W:$W,L$2) -> 9566.94 | N36: =L36-F36 -> 2030.94 | P36: =Q36/O$24 -> 159.71529 | Q36: {=+INDEX('Réel 2023'!$A$2:$AO$501,MATCH($A36,'Réel 2023'!$A$2:$A$501,0),MATCH(Q$2,'Réel 2023'!$A$2:$AO$2,0))} -> 5430.32 | S36: =L36-Q36 -> 4136.62
A37: Véhicules neufsIntérêt de gros | B37: Véhicules neufs | C37: Intérêt de gros | E37: =F37/D$24 -> 318.30489 | F37: =+INDEX('Budget original'!$A$2:$AO$501,MATCH($A37,'Budget original'!$A$2:$A$501,0),MATCH(F$2,'Budget original'!$A$2:$AO$2,0)) -> 21326.428 | K37: =IF(L37=0,0,L37/J$24) -> 474.72863 | L37: =SUMIFS(BV_Data_An_Cour!$O:$O,BV_Data_An_Cour!$U:$U,$B37,BV_Data_An_Cour!$V:$V,$C37,BV_Data_An_Cour!$W:$W,L$2) -> 34655.19 | N37: =L37-F37 -> 13328.762 | P37: =Q37/O$24 -> 54.914412 | Q37: {=+INDEX('Réel 2023'!$A$2:$AO$501,MATCH($A37,'Réel 2023'!$A$2:$A$501,0),MATCH(Q$2,'Réel 2023'!$A$2:$AO$2,0))} -> 1867.09 | S37: =L37-Q37 -> 32788.1
A38: Véhicules neufs[...] | B38: Véhicules neufs | C38: [...] | E38: =F38/D$24 -> 0 | F38: =+INDEX('Budget original'!$A$2:$AO$501,MATCH($A38,'Budget original'!$A$2:$A$501,0),MATCH(F$2,'Budget original'!$A$2:$AO$2,0)) -> 0 | K38: =IF(L38=0,0,L38/J$24) -> 0 | L38: =SUMIFS(BV_Data_An_Cour!$O:$O,BV_Data_An_Cour!$U:$U,$B38,BV_Data_An_Cour!$V:$V,$C38,BV_Data_An_Cour!$W:$W,L$2) -> 0 | N38: =L38-F38 -> 0 | P38: =Q38/O$24 -> 0 | Q38: {=+INDEX('Réel 2023'!$A$2:$AO$501,MATCH($A38,'Réel 2023'!$A$2:$A$501,0),MATCH(Q$2,'Réel 2023'!$A$2:$AO$2,0))} -> 0 | S38: =L38-Q38 -> 0
A39: Véhicules neufs[...] | B39: Véhicules neufs | C39: [...] | E39: =F39/D$24 -> 0 | F39: =+INDEX('Budget original'!$A$2:$AO$501,MATCH($A39,'Budget original'!$A$2:$A$501,0),MATCH(F$2,'Budget original'!$A$2:$AO$2,0)) -> 0 | K39: =IF(L39=0,0,L39/J$24) -> 0 | L39: =SUMIFS(BV_Data_An_Cour!$O:$O,BV_Data_An_Cour!$U:$U,$B39,BV_Data_An_Cour!$V:$V,$C39,BV_Data_An_Cour!$W:$W,L$2) -> 0 | N39: =L39-F39 -> 0 | P39: =Q39/O$24 -> 0 | Q39: {=+INDEX('Réel 2023'!$A$2:$AO$501,MATCH($A39,'Réel 2023'!$A$2:$A$501,0),MATCH(Q$2,'Réel 2023'!$A$2:$AO$2,0))} -> 0 | S39: =L39-Q39 -> 0
A40: Véhicules neufs[...] | B40: Véhicules neufs | C40: [...] | E40: =F40/D$24 -> 0 | F40: =+INDEX('Budget original'!$A$2:$AO$501,MATCH($A40,'Budget original'!$A$2:$A$501,0),MATCH(F$2,'Budget original'!$A$2:$AO$2,0)) -> 0 | K40: =IF(L40=0,0,L40/J$24) -> 0 | L40: =SUMIFS(BV_Data_An_Cour!$O:$O,BV_Data_An_Cour!$U:$U,$B40,BV_Data_An_Cour!$V:$V,$C40,BV_Data_An_Cour!$W:$W,L$2) -> 0 | N40: =L40-F40 -> 0 | P40: =Q40/O$24 -> 0 | Q40: {=+INDEX('Réel 2023'!$A$2:$AO$501,MATCH($A40,'Réel 2023'!$A$2:$A$501,0),MATCH(Q$2,'Réel 2023'!$A$2:$AO$2,0))} -> 0 | S40: =L40-Q40 -> 0
A41: Véhicules neufsTOTAL VARIABLES | B41: Véhicules neufs | C41: TOTAL VARIABLES | D41: % brut | E41: =F41/F$27 -> 0.45081987 | F41: =SUM(F31:F40) -> 130243.03 | J41: % brut | K41: =L41/L$27 -> 0.48483837 | L41: =SUM(L31:L40) -> 125866.34 | N41: =L41-F41 -> -4376.6858 | O41: % brut | P41: =Q41/Q$27 -> 0.44750386 | Q41: =SUM(Q31:Q40) -> 60912.23 | S41: =L41-Q41 -> 64954.11
A42: Véhicules neufsSalaires cadres | B42: Véhicules neufs | C42: Salaires cadres | F42: =+INDEX('Budget original'!$A$2:$AO$501,MATCH($A42,'Budget original'!$A$2:$A$501,0),MATCH(F$2,'Budget original'!$A$2:$AO$2,0)) -> 18197.117 | L42: =SUMIFS(BV_Data_An_Cour!$O:$O,BV_Data_An_Cour!$U:$U,$B42,BV_Data_An_Cour!$V:$V,$C42,BV_Data_An_Cour!$W:$W,L$2) -> 13149.05 | N42: =L42-F42 -> -5048.0667 | P42: =Q42/Q27 -> 0.097681426 | Q42: {=+INDEX('Réel 2023'!$A$2:$AO$501,MATCH($A42,'Réel 2023'!$A$2:$A$501,0),MATCH(Q$2,'Réel 2023'!$A$2:$AO$2,0))} -> 13295.96 | S42: =L42-Q42 -> -146.91
A43: Véhicules neufsSalaires commis | B43: Véhicules neufs | C43: Salaires commis | F43: =+INDEX('Budget original'!$A$2:$AO$501,MATCH($A43,'Budget original'!$A$2:$A$501,0),MATCH(F$2,'Budget original'!$A$2:$AO$2,0)) -> 11267.511 | L43: =SUMIFS(BV_Data_An_Cour!$O:$O,BV_Data_An_Cour!$U:$U,$B43,BV_Data_An_Cour!$V:$V,$C43,BV_Data_An_Cour!$W:$W,L$2) -> 9365.85 | N43: =L43-F43 -> -1901.6611 | Q43: {=+INDEX('Réel 2023'!$A$2:$AO$501,MATCH($A43,'Réel 2023'!$A$2:$A$501,0),MATCH(Q$2,'Réel 2023'!$A$2:$AO$2,0))} -> 10544.06 | S43: =L43-Q43 -> -1178.21
A44: Véhicules neufsSalaires autres | B44: Véhicules neufs | C44: Salaires autres | F44: =+INDEX('Budget original'!$A$2:$AO$501,MATCH($A44,'Budget original'!$A$2:$A$501,0),MATCH(F$2,'Budget original'!$A$2:$AO$2,0)) -> 2664.3538 | L44: =SUMIFS(BV_Data_An_Cour!$O:$O,BV_Data_An_Cour!$U:$U,$B44,BV_Data_An_Cour!$V:$V,$C44,BV_Data_An_Cour!$W:$W,L$2) -> 4575.36 | N44: =L44-F44 -> 1911.0062 | Q44: {=+INDEX('Réel 2023'!$A$2:$AO$501,MATCH($A44,'Réel 2023'!$A$2:$A$501,0),MATCH(Q$2,'Réel 2023'!$A$2:$AO$2,0))} -> 12250.19 | S44: =L44-Q44 -> -7674.83
A45: Véhicules neufsSalaires spécialistes | B45: Véhicules neufs | C45: Salaires spécialistes | F45: =+INDEX('Budget original'!$A$2:$AO$501,MATCH($A45,'Budget original'!$A$2:$A$501,0),MATCH(F$2,'Budget original'!$A$2:$AO$2,0)) -> 0 | L45: =SUMIFS(BV_Data_An_Cour!$O:$O,BV_Data_An_Cour!$U:$U,$B45,BV_Data_An_Cour!$V:$V,$C45,BV_Data_An_Cour!$W:$W,L$2) -> 0 | N45: =L45-F45 -> 0 | Q45: {=+INDEX('Réel 2023'!$A$2:$AO$501,MATCH($A45,'Réel 2023'!$A$2:$A$501,0),MATCH(Q$2,'Réel 2023'!$A$2:$AO$2,0))} -> 0 | S45: =L45-Q45 -> 0
A46: Véhicules neufs[...] | B46: Véhicules neufs | C46: [...] | F46: =+INDEX('Budget original'!$A$2:$AO$501,MATCH($A46,'Budget original'!$A$2:$A$501,0),MATCH(F$2,'Budget original'!$A$2:$AO$2,0)) -> 0 | L46: =SUMIFS(BV_Data_An_Cour!$O:$O,BV_Data_An_Cour!$U:$U,$B46,BV_Data_An_Cour!$V:$V,$C46,BV_Data_An_Cour!$W:$W,L$2) -> 0 | N46: =L46-F46 -> 0 | Q46: {=+INDEX('Réel 2023'!$A$2:$AO$501,MATCH($A46,'Réel 2023'!$A$2:$A$501,0),MATCH(Q$2,'Réel 2023'!$A$2:$AO$2,0))} -> 0 | S46: =L46-Q46 -> 0
A47: Véhicules neufs[...] | B47: Véhicules neufs | C47: [...] | F47: =+INDEX('Budget original'!$A$2:$AO$501,MATCH($A47,'Budget original'!$A$2:$A$501,0),MATCH(F$2,'Budget original'!$A$2:$AO$2,0)) -> 0 | L47: =SUMIFS(BV_Data_An_Cour!$O:$O,BV_Data_An_Cour!$U:$U,$B47,BV_Data_An_Cour!$V:$V,$C47,BV_Data_An_Cour!$W:$W,L$2) -> 0 | N47: =L47-F47 -> 0 | Q47: {=+INDEX('Réel 2023'!$A$2:$AO$501,MATCH($A47,'Réel 2023'!$A$2:$A$501,0),MATCH(Q$2,'Réel 2023'!$A$2:$AO$2,0))} -> 0 | S47: =L47-Q47 -> 0
A48: Véhicules neufs[...] | B48: Véhicules neufs | C48: [...] | F48: =+INDEX('Budget original'!$A$2:$AO$501,MATCH($A48,'Budget original'!$A$2:$A$501,0),MATCH(F$2,'Budget original'!$A$2:$AO$2,0)) -> 0 | L48: =SUMIFS(BV_Data_An_Cour!$O:$O,BV_Data_An_Cour!$U:$U,$B48,BV_Data_An_Cour!$V:$V,$C48,BV_Data_An_Cour!$W:$W,L$2) -> 0 | N48: =L48-F48 -> 0 | Q48: {=+INDEX('Réel 2023'!$A$2:$AO$501,MATCH($A48,'Réel 2023'!$A$2:$A$501,0),MATCH(Q$2,'Réel 2023'!$A$2:$AO$2,0))} -> 0 | S48: =L48-Q48 -> 0
A49: Véhicules neufsSalaires en absences | B49: Véhicules neufs | C49: Salaires en absences | F49: =+INDEX('Budget original'!$A$2:$AO$501,MATCH($A49,'Budget original'!$A$2:$A$501,0),MATCH(F$2,'Budget original'!$A$2:$AO$2,0)) -> 12428.152 | L49: =SUMIFS(BV_Data_An_Cour!$O:$O,BV_Data_An_Cour!$U:$U,$B49,BV_Data_An_Cour!$V:$V,$C49,BV_Data_An_Cour!$W:$W,L$2) -> 11763.15 | N49: =L49-F49 -> -665.00195 | Q49: {=+INDEX('Réel 2023'!$A$2:$AO$501,MATCH($A49,'Réel 2023'!$A$2:$A$501,0),MATCH(Q$2,'Réel 2023'!$A$2:$AO$2,0))} -> 11060.27 | S49: =L49-Q49 -> 702.88
A50: Véhicules neufsDéduction à la source | B50: Véhicules neufs | C50: Déduction à la source | F50: =+INDEX('Budget original'!$A$2:$AO$501,MATCH($A50,'Budget original'!$A$2:$A$501,0),MATCH(F$2,'Budget original'!$A$2:$AO$2,0)) -> 15110.881 | L50: =SUMIFS(BV_Data_An_Cour!$O:$O,BV_Data_An_Cour!$U:$U,$B50,BV_Data_An_Cour!$V:$V,$C50,BV_Data_An_Cour!$W:$W,L$2) -> 18598.07 | N50: =L50-F50 -> 3487.1892 | Q50: {=+INDEX('Réel 2023'!$A$2:$AO$501,MATCH($A50,'Réel 2023'!$A$2:$A$501,0),MATCH(Q$2,'Réel 2023'!$A$2:$AO$2,0))} -> 16153.21 | S50: =L50-Q50 -> 2444.86
A51: Véhicules neufsBénéfices marginaux | B51: Véhicules neufs | C51: Bénéfices marginaux | F51: =+INDEX('Budget original'!$A$2:$AO$501,MATCH($A51,'Budget original'!$A$2:$A$501,0),MATCH(F$2,'Budget original'!$A$2:$AO$2,0)) -> 7785.3886 | L51: =SUMIFS(BV_Data_An_Cour!$O:$O,BV_Data_An_Cour!$U:$U,$B51,BV_Data_An_Cour!$V:$V,$C51,BV_Data_An_Cour!$W:$W,L$2) -> 7275.41 | N51: =L51-F51 -> -509.97858 | Q51: {=+INDEX('Réel 2023'!$A$2:$AO$501,MATCH($A51,'Réel 2023'!$A$2:$A$501,0),MATCH(Q$2,'Réel 2023'!$A$2:$AO$2,0))} -> 9403.86 | S51: =L51-Q51 -> -2128.45
A52: Véhicules neufsCsst | B52: Véhicules neufs | C52: Csst | F52: =+INDEX('Budget original'!$A$2:$AO$501,MATCH($A52,'Budget original'!$A$2:$A$501,0),MATCH(F$2,'Budget original'!$A$2:$AO$2,0)) -> 3394.4732 | L52: =SUMIFS(BV_Data_An_Cour!$O:$O,BV_Data_An_Cour!$U:$U,$B52,BV_Data_An_Cour!$V:$V,$C52,BV_Data_An_Cour!$W:$W,L$2) -> 3705.07 | N52: =L52-F52 -> 310.59678 | Q52: {=+INDEX('Réel 2023'!$A$2:$AO$501,MATCH($A52,'Réel 2023'!$A$2:$A$501,0),MATCH(Q$2,'Réel 2023'!$A$2:$AO$2,0))} -> 2775.98 | S52: =L52-Q52 -> 929.09
A53: Véhicules neufs[...] | B53: Véhicules neufs | C53: [...] | D53: =VLOOKUP(C53,$B$2:$B$46,1,FALSE) -> #N/A | F53: =+INDEX('Budget original'!$A$2:$AO$501,MATCH($A53,'Budget original'!$A$2:$A$501,0),MATCH(F$2,'Budget original'!$A$2:$AO$2,0)) -> 0 | L53: =SUMIFS(BV_Data_An_Cour!$O:$O,BV_Data_An_Cour!$U:$U,$B53,BV_Data_An_Cour!$V:$V,$C53,BV_Data_An_Cour!$W:$W,L$2) -> 0 | N53: =L53-F53 -> 0 | Q53: {=+INDEX('Réel 2023'!$A$2:$AO$501,MATCH($A53,'Réel 2023'!$A$2:$A$501,0),MATCH(Q$2,'Réel 2023'!$A$2:$AO$2,0))} -> 0 | S53: =L53-Q53 -> 0
A54: Véhicules neufsTOTAL PERSONNEL | B54: Véhicules neufs | C54: TOTAL PERSONNEL | D54: % brut | E54: =F54/F$27 -> 0.24523102 | F54: =+SUM(F42:F53) -> 70847.876 | J54: % brut | K54: =L54/L$27 -> 0.26360058 | L54: =+SUM(L42:L53) -> 68431.96 | N54: =+SUM(N42:N53) -> -2415.9161 | O54: % brut | P54: =Q54/Q$27 -> 0.55455483 | Q54: =+SUM(Q42:Q53) -> 75483.53 | S54: =+SUM(S42:S53) -> -7051.57
A55: Véhicules neufsPublicité 2 | B55: Véhicules neufs | C55: Publicité 2 | F55: =+INDEX('Budget original'!$A$2:$AO$501,MATCH($A55,'Budget original'!$A$2:$A$501,0),MATCH(F$2,'Budget original'!$A$2:$AO$2,0)) -> 0 | L55: =SUMIFS(BV_Data_An_Cour!$O:$O,BV_Data_An_Cour!$U:$U,$B55,BV_Data_An_Cour!$V:$V,$C55,BV_Data_An_Cour!$W:$W,L$2) -> 0 | N55: =L55-F55 -> 0 | Q55: {=+INDEX('Réel 2023'!$A$2:$AO$501,MATCH($A55,'Réel 2023'!$A$2:$A$501,0),MATCH(Q$2,'Réel 2023'!$A$2:$AO$2,0))} -> 0 | S55: =L55-Q55 -> 0
A56: Véhicules neufsService gratuit 2 | B56: Véhicules neufs | C56: Service gratuit 2 | F56: =+INDEX('Budget original'!$A$2:$AO$501,MATCH($A56,'Budget original'!$A$2:$A$501,0),MATCH(F$2,'Budget original'!$A$2:$AO$2,0)) -> 0 | L56: =SUMIFS(BV_Data_An_Cour!$O:$O,BV_Data_An_Cour!$U:$U,$B56,BV_Data_An_Cour!$V:$V,$C56,BV_Data_An_Cour!$W:$W,L$2) -> 0 | N56: =L56-F56 -> 0 | Q56: {=+INDEX('Réel 2023'!$A$2:$AO$501,MATCH($A56,'Réel 2023'!$A$2:$A$501,0),MATCH(Q$2,'Réel 2023'!$A$2:$AO$2,0))} -> 0 | S56: =L56-Q56 -> 0
A57: Véhicules neufsFrais véhicules de cie | B57: Véhicules neufs | C57: Frais véhicules de cie | F57: =+INDEX('Budget original'!$A$2:$AO$501,MATCH($A57,'Budget original'!$A$2:$A$501,0),MATCH(F$2,'Budget original'!$A$2:$AO$2,0)) -> 9200 | L57: =SUMIFS(BV_Data_An_Cour!$O:$O,BV_Data_An_Cour!$U:$U,$B57,BV_Data_An_Cour!$V:$V,$C57,BV_Data_An_Cour!$W:$W,L$2) -> 11626.31 | N57: =L57-F57 -> 2426.31 | Q57: {=+INDEX('Réel 2023'!$A$2:$AO$501,MATCH($A57,'Réel 2023'!$A$2:$A$501,0),MATCH(Q$2,'Réel 2023'!$A$2:$AO$2,0))} -> 6050.54 | S57: =L57-Q57 -> 5575.77
A58: Véhicules neufsInformatique | B58: Véhicules neufs | C58: Informatique | F58: =+INDEX('Budget original'!$A$2:$AO$501,MATCH($A58,'Budget original'!$A$2:$A$501,0),MATCH(F$2,'Budget original'!$A$2:$AO$2,0)) -> 9039.6955 | L58: =SUMIFS(BV_Data_An_Cour!$O:$O,BV_Data_An_Cour!$U:$U,$B58,BV_Data_An_Cour!$V:$V,$C58,BV_Data_An_Cour!$W:$W,L$2) -> 7516.3 | N58: =L58-F58 -> -1523.3955 | Q58: {=+INDEX('Réel 2023'!$A$2:$AO$501,MATCH($A58,'Réel 2023'!$A$2:$A$501,0),MATCH(Q$2,'Réel 2023'!$A$2:$AO$2,0))} -> 6422.17 | S58: =L58-Q58 -> 1094.13
A59: Véhicules neufsFrais de déplacement | B59: Véhicules neufs | C59: Frais de déplacement | F59: =+INDEX('Budget original'!$A$2:$AO$501,MATCH($A59,'Budget original'!$A$2:$A$501,0),MATCH(F$2,'Budget original'!$A$2:$AO$2,0)) -> 1105.2259 | L59: =SUMIFS(BV_Data_An_Cour!$O:$O,BV_Data_An_Cour!$U:$U,$B59,BV_Data_An_Cour!$V:$V,$C59,BV_Data_An_Cour!$W:$W,L$2) -> 2705.19 | N59: =L59-F59 -> 1599.9641 | Q59: {=+INDEX('Réel 2023'!$A$2:$AO$501,MATCH($A59,'Réel 2023'!$A$2:$A$501,0),MATCH(Q$2,'Réel 2023'!$A$2:$AO$2,0))} -> 925.52 | S59: =L59-Q59 -> 1779.67
A60: Véhicules neufsServices extérieurs | B60: Véhicules neufs | C60: Services extérieurs | F60: =+INDEX('Budget original'!$A$2:$AO$501,MATCH($A60,'Budget original'!$A$2:$A$501,0),MATCH(F$2,'Budget original'!$A$2:$AO$2,0)) -> 6711.4186 | L60: =SUMIFS(BV_Data_An_Cour!$O:$O,BV_Data_An_Cour!$U:$U,$B60,BV_Data_An_Cour!$V:$V,$C60,BV_Data_An_Cour!$W:$W,L$2) -> 6746.26 | N60: =L60-F60 -> 34.841358 | Q60: {=+INDEX('Réel 2023'!$A$2:$AO$501,MATCH($A60,'Réel 2023'!$A$2:$A$501,0),MATCH(Q$2,'Réel 2023'!$A$2:$AO$2,0))} -> 5703.27 | S60: =L60-Q60 -> 1042.99
A61: Véhicules neufsFournitures autres | B61: Véhicules neufs | C61: Fournitures autres | F61: =+INDEX('Budget original'!$A$2:$AO$501,MATCH($A61,'Budget original'!$A$2:$A$501,0),MATCH(F$2,'Budget original'!$A$2:$AO$2,0)) -> 125 | L61: =SUMIFS(BV_Data_An_Cour!$O:$O,BV_Data_An_Cour!$U:$U,$B61,BV_Data_An_Cour!$V:$V,$C61,BV_Data_An_Cour!$W:$W,L$2) -> 36.28 | N61: =L61-F61 -> -88.72 | Q61: {=+INDEX('Réel 2023'!$A$2:$AO$501,MATCH($A61,'Réel 2023'!$A$2:$A$501,0),MATCH(Q$2,'Réel 2023'!$A$2:$AO$2,0))} -> 0 | S61: =L61-Q61 -> 36.28
A62: Véhicules neufsUniformes | B62: Véhicules neufs | C62: Uniformes | F62: =+INDEX('Budget original'!$A$2:$AO$501,MATCH($A62,'Budget original'!$A$2:$A$501,0),MATCH(F$2,'Budget original'!$A$2:$AO$2,0)) -> 83.333333 | L62: =SUMIFS(BV_Data_An_Cour!$O:$O,BV_Data_An_Cour!$U:$U,$B62,BV_Data_An_Cour!$V:$V,$C62,BV_Data_An_Cour!$W:$W,L$2) -> 0 | N62: =L62-F62 -> -83.333333 | Q62: {=+INDEX('Réel 2023'!$A$2:$AO$501,MATCH($A62,'Réel 2023'!$A$2:$A$501,0),MATCH(Q$2,'Réel 2023'!$A$2:$AO$2,0))} -> 0 | S62: =L62-Q62 -> 0
A63: Véhicules neufsPapeterie | B63: Véhicules neufs | C63: Papeterie | F63: =+INDEX('Budget original'!$A$2:$AO$501,MATCH($A63,'Budget original'!$A$2:$A$501,0),MATCH(F$2,'Budget original'!$A$2:$AO$2,0)) -> 756.9466 | L63: =SUMIFS(BV_Data_An_Cour!$O:$O,BV_Data_An_Cour!$U:$U,$B63,BV_Data_An_Cour!$V:$V,$C63,BV_Data_An_Cour!$W:$W,L$2) -> 381.04 | N63: =L63-F63 -> -375.9066 | Q63: {=+INDEX('Réel 2023'!$A$2:$AO$501,MATCH($A63,'Réel 2023'!$A$2:$A$501,0),MATCH(Q$2,'Réel 2023'!$A$2:$AO$2,0))} -> 783.41 | S63: =L63-Q63 -> -402.37
A64: Véhicules neufsTéléphone | B64: Véhicules neufs | C64: Téléphone | F64: =+INDEX('Budget original'!$A$2:$AO$501,MATCH($A64,'Budget original'!$A$2:$A$501,0),MATCH(F$2,'Budget original'!$A$2:$AO$2,0)) -> 309.40349 | L64: =SUMIFS(BV_Data_An_Cour!$O:$O,BV_Data_An_Cour!$U:$U,$B64,BV_Data_An_Cour!$V:$V,$C64,BV_Data_An_Cour!$W:$W,L$2) -> 318.9 | N64: =L64-F64 -> 9.4965149 | Q64: {=+INDEX('Réel 2023'!$A$2:$AO$501,MATCH($A64,'Réel 2023'!$A$2:$A$501,0),MATCH(Q$2,'Réel 2023'!$A$2:$AO$2,0))} -> 233.07 | S64: =L64-Q64 -> 85.83
A65: Véhicules neufsFrais postaux | B65: Véhicules neufs | C65: Frais postaux | F65: =+INDEX('Budget original'!$A$2:$AO$501,MATCH($A65,'Budget original'!$A$2:$A$501,0),MATCH(F$2,'Budget original'!$A$2:$AO$2,0)) -> 113.12881 | L65: =SUMIFS(BV_Data_An_Cour!$O:$O,BV_Data_An_Cour!$U:$U,$B65,BV_Data_An_Cour!$V:$V,$C65,BV_Data_An_Cour!$W:$W,L$2) -> 10.56 | N65: =L65-F65 -> -102.56881 | Q65: {=+INDEX('Réel 2023'!$A$2:$AO$501,MATCH($A65,'Réel 2023'!$A$2:$A$501,0),MATCH(Q$2,'Réel 2023'!$A$2:$AO$2,0))} -> 129.09 | S65: =L65-Q65 -> -118.53
A66: Véhicules neufsDivers | B66: Véhicules neufs | C66: Divers | F66: =+INDEX('Budget original'!$A$2:$AO$501,MATCH($A66,'Budget original'!$A$2:$A$501,0),MATCH(F$2,'Budget original'!$A$2:$AO$2,0)) -> 282.4626 | L66: =SUMIFS(BV_Data_An_Cour!$O:$O,BV_Data_An_Cour!$U:$U,$B66,BV_Data_An_Cour!$V:$V,$C66,BV_Data_An_Cour!$W:$W,L$2) -> 201.95 | N66: =L66-F66 -> -80.512603 | Q66: {=+INDEX('Réel 2023'!$A$2:$AO$501,MATCH($A66,'Réel 2023'!$A$2:$A$501,0),MATCH(Q$2,'Réel 2023'!$A$2:$AO$2,0))} -> 116.88 | S66: =L66-Q66 -> 85.07
... A68: Véhicules neufsFrais bancaires | B68: Véhicules neufs | C68: Frais bancaires | F68: =+INDEX('Budget original'!$A$2:$AO$501,MATCH($A68,'Budget original'!$A$2:$A$501,0),MATCH(F$2,'Budget original'!$A$2:$AO$2,0)) -> 3363.2959 | L68: =SUMIFS(BV_Data_An_Cour!$O:$O,BV_Data_An_Cour!$U:$U,$B68,BV_Data_An_Cour!$V:$V,$C68,BV_Data_An_Cour!$W:$W,L$2) -> 4277.07 | N68: =L68-F68 -> 913.77407 | Q68: {=+INDEX('Réel 2023'!$A$2:$AO$501,MATCH($A68,'Réel 2023'!$A$2:$A$501,0),MATCH(Q$2,'Réel 2023'!$A$2:$AO$2,0))} -> 3025.62 | S68: =L68-Q68 -> 1251.45
A69: Véhicules neufs[...] | B69: Véhicules neufs | C69: [...] | F69: =+INDEX('Budget original'!$A$2:$AO$501,MATCH($A69,'Budget original'!$A$2:$A$501,0),MATCH(F$2,'Budget original'!$A$2:$AO$2,0)) -> 0 | N69: =L69-F69 -> 0 | Q69: {=+INDEX('Réel 2023'!$A$2:$AO$501,MATCH($A69,'Réel 2023'!$A$2:$A$501,0),MATCH(Q$2,'Réel 2023'!$A$2:$AO$2,0))} -> 0 | S69: =L69-Q69 -> 0
A70: Véhicules neufs[...] | B70: Véhicules neufs | C70: [...] | F70: =+INDEX('Budget original'!$A$2:$AO$501,MATCH($A70,'Budget original'!$A$2:$A$501,0),MATCH(F$2,'Budget original'!$A$2:$AO$2,0)) -> 0 | L70: =SUMIFS(BV_Data_An_Cour!$O:$O,BV_Data_An_Cour!$U:$U,$B70,BV_Data_An_Cour!$V:$V,$C70,BV_Data_An_Cour!$W:$W,L$2) -> 0 | N70: =L70-F70 -> 0 | Q70: {=+INDEX('Réel 2023'!$A$2:$AO$501,MATCH($A70,'Réel 2023'!$A$2:$A$501,0),MATCH(Q$2,'Réel 2023'!$A$2:$AO$2,0))} -> 0 | S70: =L70-Q70 -> 0
A71: Véhicules neufs[...] | B71: Véhicules neufs | C71: [...] | F71: =+INDEX('Budget original'!$A$2:$AO$501,MATCH($A71,'Budget original'!$A$2:$A$501,0),MATCH(F$2,'Budget original'!$A$2:$AO$2,0)) -> 0 | L71: =SUMIFS(BV_Data_An_Cour!$O:$O,BV_Data_An_Cour!$U:$U,$B71,BV_Data_An_Cour!$V:$V,$C71,BV_Data_An_Cour!$W:$W,L$2)*0.32 -> 0 | N71: =L71-F71 -> 0 | Q71: {=+INDEX('Réel 2023'!$A$2:$AO$501,MATCH($A71,'Réel 2023'!$A$2:$A$501,0),MATCH(Q$2,'Réel 2023'!$A$2:$AO$2,0))} -> 0 | S71: =L71-Q71 -> 0
A72: Véhicules neufsTOTAL SEMI-FIXES | B72: Véhicules neufs | C72: TOTAL SEMI-FIXES | D72: % brut | E72: =F72/F$27 -> 0.11418734 | F72: =+SUM(F55:F71) -> 32989.018 | J72: % brut | K72: =L72/L$27 -> 0.13469404 | L72: =+SUM(L55:L71) -> 34967.21 | N72: =+SUM(N55:N71) -> 1978.1917 | O72: % brut | P72: =Q72/Q$27 -> 0.1915804 | Q72: =+SUM(Q55:Q71) -> 26077.07 | S72: =+SUM(S55:S71) -> 8890.14
A73: Véhicules neufs | B73: Véhicules neufs
A74: Véhicules neufsTOTAL DES DÉPENSES | B74: Véhicules neufs | C74: TOTAL DES DÉPENSES | D74: % brut | E74: =F74/F$27 -> 0.81023824 | F74: =F41+F54+F72 -> 234079.92 | J74: % brut | K74: =L74/L$27 -> 0.88313299 | L74: =L41+L54+L72 -> 229265.51 | N74: =L74-F74 -> -4814.4101 | O74: % brut | P74: =Q74/Q$27 -> 1.1936391 | Q74: =Q41+Q54+Q72 -> 162472.83 | S74: =L74-Q74 -> 66792.68
A75: Véhicules neufsProgramme neuf 1 | B75: Véhicules neufs | C75: Programme neuf 1 | F75: =+INDEX('Budget original'!$A$2:$AO$501,MATCH($A75,'Budget original'!$A$2:$A$501,0),MATCH(F$2,'Budget original'!$A$2:$AO$2,0)) -> 0 | L75: =-SUMIFS(BV_Data_An_Cour!$O:$O,BV_Data_An_Cour!$U:$U,$B75,BV_Data_An_Cour!$V:$V,$C75,BV_Data_An_Cour!$W:$W,L$2)-L156 -> 695 | N75: =L75-F75 -> 695 | Q75: =+INDEX('Réel 2023'!$A$2:$AO$501,MATCH($A75,'Réel 2023'!$A$2:$A$501,0),MATCH(Q$2,'Réel 2023'!$A$2:$AO$2,0)) -> 0
A76: Véhicules neufsProgramme neuf 2 | B76: Véhicules neufs | C76: Programme neuf 2 | F76: =+INDEX('Budget original'!$A$2:$AO$501,MATCH($A76,'Budget original'!$A$2:$A$501,0),MATCH(F$2,'Budget original'!$A$2:$AO$2,0)) -> 0 | L76: =-SUMIFS(BV_Data_An_Cour!$O:$O,BV_Data_An_Cour!$U:$U,$B76,BV_Data_An_Cour!$V:$V,$C76,BV_Data_An_Cour!$W:$W,L$2) -> 0 | N76: =L76-F76 -> 0 | Q76: {=+INDEX('Réel 2023'!$A$2:$AO$501,MATCH($A76,'Réel 2023'!$A$2:$A$501,0),MATCH(Q$2,'Réel 2023'!$A$2:$AO$2,0))} -> 0 | S76: =L76-Q76 -> 0
A77: Véhicules neufsProgramme neuf 3 | B77: Véhicules neufs | C77: Programme neuf 3 | F77: =+INDEX('Budget original'!$A$2:$AO$501,MATCH($A77,'Budget original'!$A$2:$A$501,0),MATCH(F$2,'Budget original'!$A$2:$AO$2,0)) -> 0 | L77: =-SUMIFS(BV_Data_An_Cour!$O:$O,BV_Data_An_Cour!$U:$U,$B77,BV_Data_An_Cour!$V:$V,$C77,BV_Data_An_Cour!$W:$W,L$2) -> 0 | N77: =L77-F77 -> 0 | Q77: {=+INDEX('Réel 2023'!$A$2:$AO$501,MATCH($A77,'Réel 2023'!$A$2:$A$501,0),MATCH(Q$2,'Réel 2023'!$A$2:$AO$2,0))} -> 0 | S77: =L77-Q77 -> 0
A78: Véhicules neufsHoldbacks | B78: Véhicules neufs | C78: Holdbacks | E78: =+F78/D27 -> 1304.7121 | F78: =+INDEX('Budget original'!$A$2:$AO$501,MATCH($A78,'Budget original'!$A$2:$A$501,0),MATCH(F$2,'Budget original'!$A$2:$AO$2,0)) -> 93286.912 | K78: =+L78/J27 -> 1453.1349 | L78: =-SUMIFS(BV_Data_An_Cour!$O:$O,BV_Data_An_Cour!$U:$U,$B78,BV_Data_An_Cour!$V:$V,$C78,BV_Data_An_Cour!$W:$W,L$2) -> 106078.85 | N78: =L78-F78 -> 12791.938 | Q78: {=+INDEX('Réel 2023'!$A$2:$AO$501,MATCH($A78,'Réel 2023'!$A$2:$A$501,0),MATCH(Q$2,'Réel 2023'!$A$2:$AO$2,0))} -> 39086.08 | S78: =L78-Q78 -> 66992.77
A79: Véhicules neufs[...] | B79: Véhicules neufs | C79: [...] | F79: =+INDEX('Budget original'!$A$2:$AO$501,MATCH($A79,'Budget original'!$A$2:$A$501,0),MATCH(F$2,'Budget original'!$A$2:$AO$2,0)) -> 0 | L79: =-SUMIFS(BV_Data_An_Cour!$O:$O,BV_Data_An_Cour!$U:$U,$B79,BV_Data_An_Cour!$V:$V,$C79,BV_Data_An_Cour!$W:$W,L$2) -> 0 | N79: =L79-F79 -> 0 | Q79: {=+INDEX('Réel 2023'!$A$2:$AO$501,MATCH($A79,'Réel 2023'!$A$2:$A$501,0),MATCH(Q$2,'Réel 2023'!$A$2:$AO$2,0))} -> 0 | S79: =L79-Q79 -> 0
A80: Véhicules neufs[...] | B80: Véhicules neufs | C80: [...] | F80: =+INDEX('Budget original'!$A$2:$AO$501,MATCH($A80,'Budget original'!$A$2:$A$501,0),MATCH(F$2,'Budget original'!$A$2:$AO$2,0)) -> 0 | L80: =-SUMIFS(BV_Data_An_Cour!$O:$O,BV_Data_An_Cour!$U:$U,$B80,BV_Data_An_Cour!$V:$V,$C80,BV_Data_An_Cour!$W:$W,L$2) -> 0 | N80: =L80-F80 -> 0 | Q80: {=+INDEX('Réel 2023'!$A$2:$AO$501,MATCH($A80,'Réel 2023'!$A$2:$A$501,0),MATCH(Q$2,'Réel 2023'!$A$2:$AO$2,0))} -> 0 | S80: =L80-Q80 -> 0
A81: Véhicules neufs[...] | B81: Véhicules neufs | C81: [...] | F81: =+INDEX('Budget original'!$A$2:$AO$501,MATCH($A81,'Budget original'!$A$2:$A$501,0),MATCH(F$2,'Budget original'!$A$2:$AO$2,0)) -> 0 | L81: =-SUMIFS(BV_Data_An_Cour!$O:$O,BV_Data_An_Cour!$U:$U,$B81,BV_Data_An_Cour!$V:$V,$C81,BV_Data_An_Cour!$W:$W,L$2) -> 0 | N81: =L81-F81 -> 0 | Q81: {=+INDEX('Réel 2023'!$A$2:$AO$501,MATCH($A81,'Réel 2023'!$A$2:$A$501,0),MATCH(Q$2,'Réel 2023'!$A$2:$AO$2,0))} -> 0 | S81: =L81-Q81 -> 0
A82: Véhicules neufsFrais administration | B82: Véhicules neufs | C82: Frais administration | D82: =E82/499 -> 0.95 | E82: =+F82/D24 -> 474.05 | F82: =+INDEX('Budget original'!$A$2:$AO$501,MATCH($A82,'Budget original'!$A$2:$A$501,0),MATCH(F$2,'Budget original'!$A$2:$AO$2,0)) -> 31761.35 | J82: =K82/499 -> 0.98932111 | K82: =+L82/J24 -> 493.67123 | L82: =-SUMIFS(BV_Data_An_Cour!$O:$O,BV_Data_An_Cour!$U:$U,$B82,BV_Data_An_Cour!$V:$V,$C82,BV_Data_An_Cour!$W:$W,L$2) -> 36038 | N82: =L82-F82 -> 4276.65 | Q82: {=+INDEX('Réel 2023'!$A$2:$AO$501,MATCH($A82,'Réel 2023'!$A$2:$A$501,0),MATCH(Q$2,'Réel 2023'!$A$2:$AO$2,0))} -> 12599 | S82: =L82-Q82 -> 23439
A83: Véhicules neufsAUTRES REVENUS | B83: Véhicules neufs | C83: AUTRES REVENUS | F83: =+SUM(F75:F82) -> 125048.26 | L83: =+SUM(L75:L82) -> 142811.85 | N83: =+SUM(N75:N82) -> 17763.588 | Q83: =+SUM(Q75:Q82) -> 51685.08 | S83: =+SUM(S75:S82) -> 90431.77
A84: Véhicules neufs | B84: Véhicules neufs
A85: Véhicules neufsPROFIT DÉPARTEMENTAL | B85: Véhicules neufs | C85: PROFIT DÉPARTEMENTAL | F85: =F27-F74+F83 -> 179870.92 | L85: =L27-L74+L83 -> 173151.08 | N85: =N27-N41-N54-N72+N83 -> -6719.8439 | P85: =Q85/Q5 -> 0.014342977 | Q85: =Q27-Q74+Q83 -> 25327.79 | S85: =S27-S41-S54-S72+S83 -> 147128.29
C89: =C1 -> Volks | K89: Véhicules usagés | S89: =$S$1 -> Réalisé, Avril 2024
D91: BUDGET ORIGINAL | J91: RÉALISATION | M91: ÉCART réel / Budget | O91: ANNÉE PRÉCÉDENTE | R91: ECART (réel/ Ann.Préc.)
D92: UNITE | E92: $P/UNITÉ | F92: $PROFITS | J92: UNITÉS | K92: $P/UNITE | L92: $PROFITS | M92: UNITÉS | N92: $PROFITS | O92: UNITE | P92: $P/UNITÉ | Q92: $PROFITS | R92: UNITÉS | S92: $PROFITS
A93: Véhicules usagésVentes nettes | B93: Véhicules usagés | C93: Ventes nettes | F93: =+INDEX('Budget original'!$A$2:$AO$501,MATCH($A93,'Budget original'!$A$2:$A$501,0),MATCH(F$2,'Budget original'!$A$2:$AO$2,0)) -> 2101187.1 | L93: =-SUMIFS(BV_Data_An_Cour!$O:$O,BV_Data_An_Cour!$X:$X,"Oui",BV_Data_An_Cour!$U:$U,$B93) -> 1101235.5 | Q93: {=+INDEX('Réel 2023'!$A$2:$AO$501,MATCH($A93,'Réel 2023'!$A$2:$A$501,0),MATCH(Q$2,'Réel 2023'!$A$2:$AO$2,0))} -> 738971.18
A94: Véhicules usagésCertifié | B94: Véhicules usagés | C94: Certifié | D94: =+INDEX('Budget original'!$A$2:$AO$501,MATCH($A94,'Budget original'!$A$2:$A$501,0),MATCH(D$2,'Budget original'!$A$2:$AO$2,0)) -> 38.766 | E94: =IF(D94=0,0,F94/D94) -> 1800 | F94: =+INDEX('Budget original'!$A$2:$AO$501,MATCH($A94,'Budget original'!$A$2:$A$501,0),MATCH(F$2,'Budget original'!$A$2:$AO$2,0)) -> 69778.8 | J94: =-SUMIFS(BV_Data_An_Cour!$O:$O,BV_Data_An_Cour!$U:$U,$B94,BV_Data_An_Cour!$V:$V,$C94,BV_Data_An_Cour!$W:$W,J$2) -> 22 | K94: =IF(J94=0,0,L94/J94) -> 1680.7486 | L94: =-SUMIFS(BV_Data_An_Cour!$O:$O,BV_Data_An_Cour!$U:$U,$B94,BV_Data_An_Cour!$V:$V,$C94,BV_Data_An_Cour!$W:$W,$L2) -> 36976.47 | M94: =J94-D94 -> -16.766 | N94: =L94-F94 -> -32802.33 | O94: {=+INDEX('Réel 2023'!$A$2:$AO$501,MATCH($A94,'Réel 2023'!$A$2:$A$501,0),MATCH(O$2,'Réel 2023'!$A$2:$AO$2,0))} -> 15 | P94: =IF(O94=0,0,Q94/O94) -> 1983.744 | Q94: {=+INDEX('Réel 2023'!$A$2:$AO$501,MATCH($A94,'Réel 2023'!$A$2:$A$501,0),MATCH(Q$2,'Réel 2023'!$A$2:$AO$2,0))} -> 29756.16 | R94: =J94-O94 -> 7 | S94: =L94-Q94 -> 7220.31
A95: Véhicules usagésNon Certifié | B95: Véhicules usagés | C95: Non Certifié | D95: =+INDEX('Budget original'!$A$2:$AO$501,MATCH($A95,'Budget original'!$A$2:$A$501,0),MATCH(D$2,'Budget original'!$A$2:$AO$2,0)) -> 2.1868 | E95: =IF(D95=0,0,F95/D95) -> 1800 | F95: =+INDEX('Budget original'!$A$2:$AO$501,MATCH($A95,'Budget original'!$A$2:$A$501,0),MATCH(F$2,'Budget original'!$A$2:$AO$2,0)) -> 3936.24 | J95: =-SUMIFS(BV_Data_An_Cour!$O:$O,BV_Data_An_Cour!$U:$U,$B95,BV_Data_An_Cour!$V:$V,$C95,BV_Data_An_Cour!$W:$W,J$2) -> 1 | K95: =IF(J95=0,0,L95/J95) -> 1000 | L95: =-SUMIFS(BV_Data_An_Cour!$O:$O,BV_Data_An_Cour!$U:$U,$B95,BV_Data_An_Cour!$V:$V,$C95,BV_Data_An_Cour!$W:$W,$L2) -> 1000 | M95: =J95-D95 -> -1.1868 | N95: =L95-F95 -> -2936.24 | O95: {=+INDEX('Réel 2023'!$A$2:$AO$501,MATCH($A95,'Réel 2023'!$A$2:$A$501,0),MATCH(O$2,'Réel 2023'!$A$2:$AO$2,0))} -> 5 | P95: =IF(O95=0,0,Q95/O95) -> 2587.164 | Q95: {=+INDEX('Réel 2023'!$A$2:$AO$501,MATCH($A95,'Réel 2023'!$A$2:$A$501,0),MATCH(Q$2,'Réel 2023'!$A$2:$AO$2,0))} -> 12935.82 | R95: =J95-O95 -> -4 | S95: =L95-Q95 -> -11935.82
A96: =B96&C96 -> Véhicules usagésAutres Marques | B96: Véhicules usagés | C96: Autres Marques | D96: =+INDEX('Budget original'!$A$2:$AO$501,MATCH($A96,'Budget original'!$A$2:$A$501,0),MATCH(D$2,'Budget original'!$A$2:$AO$2,0)) -> 1.2922 | E96: =IF(D96=0,0,F96/D96) -> 1800 | F96: =+INDEX('Budget original'!$A$2:$AO$501,MATCH($A96,'Budget original'!$A$2:$A$501,0),MATCH(F$2,'Budget original'!$A$2:$AO$2,0)) -> 2325.96 | J96: =-SUMIFS(BV_Data_An_Cour!$O:$O,BV_Data_An_Cour!$U:$U,$B96,BV_Data_An_Cour!$V:$V,$C96,BV_Data_An_Cour!$W:$W,J$2) -> 0 | K96: =IF(J96=0,0,L96/J96) -> 0 | L96: =-SUMIFS(BV_Data_An_Cour!$O:$O,BV_Data_An_Cour!$U:$U,$B96,BV_Data_An_Cour!$V:$V,$C96,BV_Data_An_Cour!$W:$W,$L2) -> 0 | M96: =J96-D96 -> -1.2922 | N96: =L96-F96 -> -2325.96 | O96: =+INDEX('Réel 2023'!$A$2:$AO$501,MATCH($A96,'Réel 2023'!$A$2:$A$501,0),MATCH(O$2,'Réel 2023'!$A$2:$AO$2,0)) -> 0 | P96: =IF(O96=0,0,Q96/O96) -> 0 | Q96: =+INDEX('Réel 2023'!$A$2:$AO$501,MATCH($A96,'Réel 2023'!$A$2:$A$501,0),MATCH(Q$2,'Réel 2023'!$A$2:$AO$2,0)) -> 0 | R96: =J96-O96 -> 0 | S96: =L96-Q96 -> 0
A97: =B97&C97 -> Véhicules usagésTotal Usagés | B97: Véhicules usagés | C97: Total Usagés | D97: =+D95+D94+D96 -> 42.245 | E97: =IF(D97=0,0,F97/D97) -> 1800 | F97: =+F94+F95+F96 -> 76041 | J97: =+J94+J95+J96 -> 23 | K97: =IF(J97<=0,0,L97/J97) -> 1651.1509 | L97: =+L94+L95+L96 -> 37976.47 | M97: =J97-D97 -> -19.245 | N97: =L97-F97 -> -38064.53 | O97: =+O95+O94+O96 -> 20 | P97: =IF(O97=0,0,Q97/O97) -> 2134.599 | Q97: =+Q94+Q95+Q96 -> 42691.98 | R97: =R94+R95 -> 3 | S97: =S94+S95 -> -4715.51
A98: =B98&C98 -> Véhicules usagés | B98: Véhicules usagés | E98: =IF(D98=0,0,F98/D98) -> 0 | M98: =M97/D97 -> -0.45555687 | N98: =N97/F97 -> -0.50057903 | P98: =IF(O98=0,0,Q98/O98) -> 0 | R98: =R97/O97 -> 0.15 | S98: =IF(Q97=0,0,(S97/Q97)) -> -0.11045424
A99: =B99&C99 -> Véhicules usagés | B99: Véhicules usagés | D99: =+INDEX('Budget original'!$A$2:$AO$501,MATCH($A99,'Budget original'!$A$2:$A$501,0),MATCH(D$2,'Budget original'!$A$2:$AO$2,0)) -> 0 | E99: =IF(D99=0,0,F99/D99) -> 0 | F99: =+INDEX('Budget original'!$A$2:$AO$501,MATCH($A99,'Budget original'!$A$2:$A$501,0),MATCH(F$2,'Budget original'!$A$2:$AO$2,0)) -> 0
A100: Véhicules usagésVentes au Gros | B100: Véhicules usagés | C100: Ventes au Gros | D100: =+INDEX('Budget original'!$A$2:$AO$501,MATCH($A100,'Budget original'!$A$2:$A$501,0),MATCH(D$2,'Budget original'!$A$2:$AO$2,0)) -> 43.239 | E100: =IF(D100=0,0,F100/D100) -> 400 | F100: =+INDEX('Budget original'!$A$2:$AO$501,MATCH($A100,'Budget original'!$A$2:$A$501,0),MATCH(F$2,'Budget original'!$A$2:$AO$2,0)) -> 17295.6 | J100: =-SUMIFS(BV_Data_An_Cour!$O:$O,BV_Data_An_Cour!$U:$U,$B100,BV_Data_An_Cour!$V:$V,$C100,BV_Data_An_Cour!$W:$W,J$2) -> 31 | K100: =IF(J100=0,0,L100/J100) -> -367.3229 | L100: =-SUMIFS(BV_Data_An_Cour!$O:$O,BV_Data_An_Cour!$U:$U,$B100,BV_Data_An_Cour!$V:$V,$C100,BV_Data_An_Cour!$W:$W,L$2) -> -11387.01 | M100: =J100-D100 -> -12.239 | N100: =L100-F100 -> -28682.61 | O100: {=+INDEX('Réel 2023'!$A$2:$AO$501,MATCH($A100,'Réel 2023'!$A$2:$A$501,0),MATCH(O$2,'Réel 2023'!$A$2:$AO$2,0))} -> 10 | P100: =IF(O100=0,0,Q100/O100) -> 1818 | Q100: {=+INDEX('Réel 2023'!$A$2:$AO$501,MATCH($A100,'Réel 2023'!$A$2:$A$501,0),MATCH(Q$2,'Réel 2023'!$A$2:$AO$2,0))} -> 18180 | R100: =J100-O100 -> 21 | S100: =L100-Q100 -> -29567.01
A101: Véhicules usagés | B101: Véhicules usagés
A102: Véhicules usagésRev. Finances | B102: Véhicules usagés | C102: Rev. Finances | D102: =+INDEX('Budget original'!$A$2:$AO$501,MATCH($A102,'Budget original'!$A$2:$A$501,0),MATCH(D$2,'Budget original'!$A$2:$AO$2,0)) -> 0 | E102: =IF(D102=0,0,F102/D102) -> 0 | F102: =+INDEX('Budget original'!$A$2:$AO$501,MATCH($A102,'Budget original'!$A$2:$A$501,0),MATCH(F$2,'Budget original'!$A$2:$AO$2,0)) -> 29571.5 | K102: =IF(J97=0,0,L102/J97) -> 360.09913 | L102: =-SUMIFS(BV_Data_An_Cour!$O:$O,BV_Data_An_Cour!$U:$U,$B102,BV_Data_An_Cour!$V:$V,$C102,BV_Data_An_Cour!$W:$W,$L2) -> 8282.28 | N102: =L102-F102 -> -21289.22 | Q102: {=+INDEX('Réel 2023'!$A$2:$AO$501,MATCH($A102,'Réel 2023'!$A$2:$A$501,0),MATCH(Q$2,'Réel 2023'!$A$2:$AO$2,0))} -> 18972.05 | R102: =O102-K102 -> -360.09913 | S102: =L102-Q102 -> -10689.77
A103: Véhicules usagésRev. Protections | B103: Véhicules usagés | C103: Rev. Protections | D103: =+INDEX('Budget original'!$A$2:$AO$501,MATCH($A103,'Budget original'!$A$2:$A$501,0),MATCH(D$2,'Budget original'!$A$2:$AO$2,0)) -> 0 | E103: =IF(D103=0,0,F103/D103) -> 0 | F103: =+INDEX('Budget original'!$A$2:$AO$501,MATCH($A103,'Budget original'!$A$2:$A$501,0),MATCH(F$2,'Budget original'!$A$2:$AO$2,0)) -> 61255.25 | K103: =IF(J97=0,0,L103/J97) -> 1173.4048 | L103: =-SUMIFS(BV_Data_An_Cour!$O:$O,BV_Data_An_Cour!$U:$U,$B103,BV_Data_An_Cour!$V:$V,$C103,BV_Data_An_Cour!$W:$W,$L2) -> 26988.31 | N103: =L103-F103 -> -34266.94 | Q103: {=+INDEX('Réel 2023'!$A$2:$AO$501,MATCH($A103,'Réel 2023'!$A$2:$A$501,0),MATCH(Q$2,'Réel 2023'!$A$2:$AO$2,0))} -> 40333.22 | R103: =O103-K103 -> -1173.4048 | S103: =L103-Q103 -> -13344.91
A104: Véhicules usagésRev. Autres | B104: Véhicules usagés | C104: Rev. Autres | D104: =+INDEX('Budget original'!$A$2:$AO$501,MATCH($A104,'Budget original'!$A$2:$A$501,0),MATCH(D$2,'Budget original'!$A$2:$AO$2,0)) -> 0 | E104: =IF(D104=0,0,F104/D104) -> 0 | F104: =+INDEX('Budget original'!$A$2:$AO$501,MATCH($A104,'Budget original'!$A$2:$A$501,0),MATCH(F$2,'Budget original'!$A$2:$AO$2,0)) -> 2112.25 | K104: =IF(J97=0,0,L104/J97) -> 28.495217 | L104: =-SUMIFS(BV_Data_An_Cour!$O:$O,BV_Data_An_Cour!$U:$U,$B104,BV_Data_An_Cour!$V:$V,$C104,BV_Data_An_Cour!$W:$W,$L$2) -> 655.39 | N104: =L104-F104 -> -1456.86 | Q104: {=+INDEX('Réel 2023'!$A$2:$AO$501,MATCH($A104,'Réel 2023'!$A$2:$A$501,0),MATCH(Q$2,'Réel 2023'!$A$2:$AO$2,0))} -> 0 | R104: =O104-K104 -> -28.495217 | S104: =L104-Q104 -> 655.39
A105: Véhicules usagésTotal F&I | B105: Véhicules usagés | C105: Total F&I | D105: =D97 -> 42.245 | E105: =IF(D105=0,0,F105/D105) -> 2200 | F105: =F102+F103+F104 -> 92939 | J105: =J97 -> 23 | K105: =IF(J105<=0,0,L105/J105) -> 1561.9991 | L105: =L102+L103+L104 -> 35925.98 | M105: =J105-D105 -> -19.245 | N105: =L105-F105 -> -57013.02 | O105: =O97 -> 20 | P105: =IF(O105=0,0,Q105/O105) -> 2965.2635 | Q105: =Q102+Q103+Q104 -> 59305.27 | S105: =L105-Q105 -> -23379.29
...

Sheet Démo
B1: Suivi de Démo
B2: # Stock | C2: NIV | D2: Année | E2: Marque | F2: Modèle | G2: $ Valeur | H2: Nom | I2: Prénom | J2: Titre / Fonction
B3: 240253 | C3: 3VV4B7AX0RM043880 | D3: 2024 | E3: VOLKSWAGEN | F3: TIGUAN | G3: 44703 | H3: CABALLERO | I3: JUAN ANDRES | J3: CONSEILLER VENTE
B4: 240268 | C4: 3VV4B7AX3RM061712 | D4: 2024 | E4: VOLKSWAGEN | F4: TIGUAN | G4: 44786 | H4: BRIN | I4: FELIX-ANTOINE | J4: CONSEILLER VENTE
B5: 240418 | C5: 1V2FR2CA2RC555218 | D5: 2024 | E5: VOLKSWAGEN | F5: ATLAS | G5: 57745 | H5: BEAUVAIS | I5: FREDERIC | J5: DG
B6: 240052 | C6: 1V2FE2CAXRC211504 | D6: 2024 | E6: VOLKSWAGEN | F6: ATLAS CROSS SPT | G6: 55473 | H6: GRAVEL | I6: PHILIPPE | J6: DIRECTEUR RENOUVL.
B7: 240042 | C7: 1V2FE2CA4RC210672 | D7: 2024 | E7: VOLKSWAGEN | F7: ATLAS CROSS SPT | G7: 57912.25 | H7: BONNEAU | I7: KAVEN | J7: DIRECTEUR VENTES

Sheet Wholesale
C1: ="Analyse Wholesale "&Parametres!B1 -> Analyse Wholesale Volks
D2: $ | F2: X | G2: U | L2: $ | N2: X | O2: U
E4: =CONCATENATE("Pièces Wholesale ",Parametres!B3," ",Parametres!B4) -> Pièces Wholesale Avril 2024 | J4: =CONCATENATE("Pièces Wholesale AAD ",Parametres!B4) -> Pièces Wholesale AAD 2024
E5: Réel | F5: Budget | G5: ▲ $ | H5: ▲ % | J5: Réel | K5: Budget | L5: ▲ $ | M5: ▲ %
C6: NB de livraisons | E6: =SUMIF(A37:A48,"X",E37:E48) -> 469 | F6: =SUMIF(A37:A48,"X",F37:F48) -> 365.36471 | G6: =E6-F6 -> 103.63529 | H6: =G6/F6 -> 0.28364887 | J6: =SUMIF($B$37:$B$48,"X",$E$37:$E$48) -> 1864 | K6: =SUMIF($B$37:$B$48,"X",$F$37:$F$48) -> 1514.9105 | L6: =J6-K6 -> 349.08947 | M6: =L6/K6 -> 0.2304357
A7: =B7&C7 -> piècesVentes de Gros | B7: pièces | C7: Ventes de Gros | E7: =-SUMIFS(BV_Data_An_Cour!$O:$O,BV_Data_An_Cour!$X:$X,"Oui",BV_Data_An_Cour!$U:$U,$B7,BV_Data_An_Cour!$V:$V,$C7) -> 169839.65 | F7: =+INDEX('Budget original'!$A$2:$AO$501,MATCH($A7,'Budget original'!$A$2:$A$501,0),MATCH(F$2,'Budget original'!$A$2:$AO$2,0)) -> 114574.82 | G7: =E7-F7 -> 55264.829 | H7: =G7/F7 -> 0.48234707 | J7: =-SUMIFS(BV_Data_An_Cour!$P:$P,BV_Data_An_Cour!$X:$X,"Oui",BV_Data_An_Cour!$U:$U,$B7,BV_Data_An_Cour!$V:$V,$C7) -> 604610.61 | K7: {=+SUMPRODUCT(('Budget original'!$A$8:$A$501=$A7)*('Budget original'!$C$3:$AO$3=N$2),'Budget original'!$C$8:$AO$501)} -> 475061.21 | L7: =J7-K7 -> 129549.4 | M7: =L7/K7 -> 0.27270043
C8: Coûts | E8: =E7-E9 -> 141859.39 | F8: =F7-F9 -> 94782.242 | G8: =E8-F8 -> 47077.148 | H8: =G8/F8 -> 0.49668742 | J8: =J7-J9 -> 499164.38 | K8: =K7-K9 -> 391162.91 | L8: =J8-K8 -> 108001.47 | M8: =L8/K8 -> 0.27610356
C9: Profit brut | E9: =E12+E11 -> 27980.26 | F9: =F12+F11 -> 19792.579 | G9: =E9-F9 -> 8187.6812 | H9: =G9/F9 -> 0.4136743 | J9: =J12+J11 -> 105446.23 | K9: =K12+K11 -> 83898.307 | L9: =J9-K9 -> 21547.923 | M9: =L9/K9 -> 0.25683382
C10: % avant redevances | E10: =E9/E7 -> 0.16474516 | F10: =F9/F7 -> 0.17274807 | G10: =E10-F10 -> -0.0080029082 | J10: =J9/J7 -> 0.17440354 | K10: =K9/K7 -> 0.17660526 | L10: =J10-K10 -> -0.0022017167
C11: Coûts de redevance | E11: =SUMIFS(BV_Data_An_Cour!$O:$O,BV_Data_An_Cour!$W:$W,$D$2,BV_Data_An_Cour!L:L,C31) -> 4602.76 | F11: =SUMIF($A$37:$A$48,"X",$G$37:$G$48) -> 3179.2297 | G11: =E11-F11 -> 1423.5303 | H11: =G11/F11 -> 0.44775948 | J11: =SUMIFS(BV_Data_An_Cour!$P:$P,BV_Data_An_Cour!$W:$W,$L$2,BV_Data_An_Cour!T:T,C31) -> 18277.86 | K11: =SUMIF($B$37:$B$48,"X",$G$37:$G$48) -> 15014.431 | L11: =J11-K11 -> 3263.4289 | M11: =L11/K11 -> 0.21735282
A12: Ventes de Gros | B12: pièces | C12: Profit | E12: =-SUMIFS(BV_Data_An_Cour!$O:$O,BV_Data_An_Cour!$U:$U,$B12,BV_Data_An_Cour!$V:$V,$A12,BV_Data_An_Cour!$W:$W,$D$2) -> 23377.5 | F12: =+INDEX('Budget original'!$A$2:$AO$501,MATCH(B12&$A12,'Budget original'!$A$2:$A$501,0),MATCH(G$2,'Budget original'!$A$2:$AO$2,0)) -> 16613.349 | G12: =E12-F12 -> 6764.1509 | H12: =G12/F12 -> 0.40715156 | J12: =-SUMIFS(BV_Data_An_Cour!$P:$P,BV_Data_An_Cour!$U:$U,$B12,BV_Data_An_Cour!$V:$V,$A12,BV_Data_An_Cour!$W:$W,$D$2) -> 87168.37 | K12: {=+SUMPRODUCT(('Budget original'!$A$8:$A$501=B12&$A12)*('Budget original'!$C$3:$AO$3=O$2),'Budget original'!$C$8:$AO$501)} -> 68883.876 | L12: =J12-K12 -> 18284.494 | M12: =L12/K12 -> 0.26543939
C13: % brut | E13: =(E12)/E7 -> 0.13764454 | F13: =(F12)/F7 -> 0.145 | G13: =E13-F13 -> -0.0073554629 | J13: =(J12)/J7 -> 0.14417274 | K13: =(K12)/K7 -> 0.145 | L13: =J13-K13 -> -0.00082725715
C14: Coûts de livraison | E14: =SUMIFS(BV_Data_An_Cour!$O:$O,BV_Data_An_Cour!$W:$W,$D$2,BV_Data_An_Cour!L:L,C33) -> 9380 | F14: =SUMIF(A37:A48,"X",F37:F48)*$G$33 -> 9134.1178 | G14: =E14-F14 -> 245.88223 | H14: =G14/F14 -> 0.0269191 | J14: =SUMIFS(BV_Data_An_Cour!$P:$P,BV_Data_An_Cour!$W:$W,$L$2,BV_Data_An_Cour!T:T,C33) -> 42760 | K14: =SUMIF(B37:B48,"X",F37:F48)*$G$33 -> 37872.763 | L14: =J14-K14 -> 4887.2367 | M14: =L14/K14 -> 0.12904357
C15: Profit net | E15: =E12-E14 -> 13997.5 | F15: =F12-F14 -> 7479.2313 | G15: =E15-F15 -> 6518.2687 | H15: =G15/F15 -> 0.87151586 | J15: =J12-J14 -> 44408.37 | K15: =K12-K14 -> 31011.113 | L15: =J15-K15 -> 13397.257 | M15: =L15/K15 -> 0.43201472
C16: % net | E16: =E15/E7 -> 0.082415973 | F16: =F15/F7 -> 0.065278141 | G16: =E16-F16 -> 0.017137832 | J16: =J15/J7 -> 0.073449538 | K16: =K15/K7 -> 0.065278141 | L16: =J16-K16 -> 0.0081713973
E18: =CONCATENATE("Pièces Wholesale $ / livraison ",Parametres!B3," ",Parametres!B4) -> Pièces Wholesale $ / livraison Avril 2024 | J18: =CONCATENATE("Pièces Wholesale AAD $ / livraison ",Parametres!B4) -> Pièces Wholesale AAD $ / livraison 2024
E19: Réel | F19: Budget | G19: ▲ $ | H19: ▲ % | J19: Réel | K19: Budget | L19: ▲ $ | M19: ▲ %
C20: Ventes de Gros | E20: =E7/E$6 -> 362.13145 | F20: =F7/F$6 -> 313.59028 | G20: =E20-F20 -> 48.541172 | H20: =G20/F20 -> 0.1547917 | J20: =J7/J$6 -> 324.36192 | K20: =K7/K$6 -> 313.59028 | L20: =J20-K20 -> 10.771637 | M20: =L20/K20 -> 0.034349399
C21: Coûts | E21: =E8/E$6 -> 302.47205 | F21: =F8/F$6 -> 259.41816 | G21: =E21-F21 -> 43.053883 | H21: =G21/F21 -> 0.16596326 | J21: =J8/J$6 -> 267.79205 | K21: =K8/K$6 -> 258.20859 | L21: =J21-K21 -> 9.5834627 | M21: =L21/K21 -> 0.037115198
C22: Profit brut | E22: =E9/E$6 -> 59.659403 | F22: =F9/F$6 -> 54.172114 | G22: =E22-F22 -> 5.4872889 | H22: =G22/F22 -> 0.10129361 | J22: =J9/J$6 -> 56.569866 | K22: =K9/K$6 -> 55.381691 | L22: =J22-K22 -> 1.1881747 | M22: =L22/K22 -> 0.021454288
C23: Coûts de redevance | E23: =E11/E$6 -> 9.8139872 | F23: =F11/F$6 -> 8.7015238 | G23: =E23-F23 -> 1.1124634 | H23: =G23/F23 -> 0.12784696 | J23: =J11/J$6 -> 9.8057189 | K23: =K11/K$6 -> 9.9111009 | L23: =J23-K23 -> -0.10538199 | M23: =L23/K23 -> -0.010632723
C24: Profit | E24: =E12/E$6 -> 49.845416 | F24: =F12/F$6 -> 45.47059 | G24: =E24-F24 -> 4.3748255 | H24: =G24/F24 -> 0.096212199 | J24: =J12/J$6 -> 46.764147 | K24: =K12/K$6 -> 45.47059 | L24: =J24-K24 -> 1.2935567 | M24: =L24/K24 -> 0.028448206
C25: Coûts de livraison | E25: =E14/E$6 -> 20 | F25: =F14/F$6 -> 25 | G25: =E25-F25 -> -5 | H25: =G25/F25 -> -0.2 | J25: =J14/J$6 -> 22.939914 | K25: =K14/K$6 -> 25 | L25: =J25-K25 -> -2.0600858 | M25: =L25/K25 -> -0.082403433
C26: Profit net | E26: =E15/E$6 -> 29.845416 | F26: =F15/F$6 -> 20.47059 | G26: =E26-F26 -> 9.3748255 | H26: =G26/F26 -> 0.45796557 | J26: =J15/J$6 -> 23.824233 | K26: =K15/K$6 -> 20.47059 | L26: =J26-K26 -> 3.3536426 | M26: =L26/K26 -> 0.16382735
C29: Inscrire les GL
C30: Couts de redevance | E30: Contrôle mois | G30: =SUMIF(A37:A48,"X",E37:E48)*$G$33-E14 -> 2345 | H30: frais de livraison doit être de 25$ / livraison
C31: 5773 | E31: Contrôle YTD | G31: =SUMIF(B37:B48,"X",E37:E48)*$G$33-J14 -> 3840 | H31: frais de livraison doit être de 25$ / livraison
C32: GL livraison
C33: 6758 | E33: Coût / livraison | G33: 25
E35: NB de livraison
A36: Mois | B36: YTD | C36: Mois | E36: Réel | F36: Budgeté | G36: Coûts de redevance budgeté | H36: =+IF(Parametres!$B$3=H$38,"X","") | I36: =+IF(Parametres!$B$3=I$38,"X","") | J36: =+IF(Parametres!$B$3=J$38,"X","") | K36: =+IF(Parametres!$B$3=K$38,"X","") | L36: =+IF(Parametres!$B$3=L$38,"X","") | M36: =+IF(Parametres!$B$3=M$38,"X","") | N36: =+IF(Parametres!$B$3=N$38,"X","") | O36: =+IF(Parametres!$B$3=O$38,"X","") | ... S36: =+IF(Parametres!$B$3=S$38,"X","") | U36: =+IF(Parametres!$B$3=N$7,"X","") | V36: =+IF(Parametres!$B$3=N$7,"O","") | W36: =+IF(Parametres!$B$3=N$7,"U","") | X36: =+IF(Parametres!$B$3=Q$7,"X","") | Y36: =+IF(Parametres!$B$3=Q$7,"O","") | Z36: =+IF(Parametres!$B$3=Q$7,"U","") | AA36: =+IF(Parametres!$B$3=T$7,"X","") | AB36: =+IF(Parametres!$B$3=T$7,"O","") | AC36: =+IF(Parametres!$B$3=T$7,"U","") | AD36: =+IF(Parametres!$B$3=W$7,"X","") | AE36: =+IF(Parametres!$B$3=W$7,"O","") | AF36: =+IF(Parametres!$B$3=W$7,"U","") | AG36: =+IF(Parametres!$B$3=Z$7,"X","") | AH36: =+IF(Parametres!$B$3=Z$7,"O","") | AI36: =+IF(Parametres!$B$3=Z$7,"U","") | AJ36: =+IF(Parametres!$B$3=AC$7,"X","") | AK36: =+IF(Parametres!$B$3=AC$7,"O","") | AL36: =+IF(Parametres!$B$3=AC$7,"U","") | AM36: =+IF(Parametres!$B$3=AF$7,"X","") | AN36: =+IF(Parametres!$B$3=AF$7,"O","") | AO36: =+IF(Parametres!$B$3=AF$7,"U","")
A37: =+IF(Parametres!$B$3=$C37,"X","") | B37: =+IF(VLOOKUP($C37,Parametres!$K$3:$N$14,4,0)="X","X","") -> X | C37: Janvier | E37: 533 | F37: 418.92207 | G37: 4014.4
A38: =+IF(Parametres!$B$3=$C38,"X","") | B38: =+IF(VLOOKUP($C38,Parametres!$K$3:$N$14,4,0)="X","X","") -> X | C38: Février | E38: 433 | F38: 311.94352 | G38: 3551.28
A39: =+IF(Parametres!$B$3=$C39,"X","") | B39: =+IF(VLOOKUP($C39,Parametres!$K$3:$N$14,4,0)="X","X","") -> X | C39: Mars | E39: 429 | F39: 418.68024 | G39: 4269.5214
A40: =+IF(Parametres!$B$3=$C40,"X","") -> X | B40: =+IF(VLOOKUP($C40,Parametres!$K$3:$N$14,4,0)="X","X","") -> X | C40: Avril | E40: 469 | F40: 365.36471 | G40: 3179.2297
A41: =+IF(Parametres!$B$3=$C41,"X","") | B41: =+IF(VLOOKUP($C41,Parametres!$K$3:$N$14,4,0)="X","X","") | C41: Mai | F41: 375.87932 | G41: 4267.0567
A42: =+IF(Parametres!$B$3=$C42,"X","") | B42: =+IF(VLOOKUP($C42,Parametres!$K$3:$N$14,4,0)="X","X","") | C42: Juin | F42: 427.89427 | G42: 3723.6817
A43: =+IF(Parametres!$B$3=$C43,"X","") | B43: =+IF(VLOOKUP($C43,Parametres!$K$3:$N$14,4,0)="X","X","") | C43: Juillet | F43: 456.46099 | G43: 3830.8433
A44: =+IF(Parametres!$B$3=$C44,"X","") | B44: =+IF(VLOOKUP($C44,Parametres!$K$3:$N$14,4,0)="X","X","") | C44: Août | F44: 398.12416 | G44: 4360.9632
A45: =+IF(Parametres!$B$3=$C45,"X","") | B45: =+IF(VLOOKUP($C45,Parametres!$K$3:$N$14,4,0)="X","X","") | C45: Septembre | F45: 476.56079 | G45: 4652.1062
A46: =+IF(Parametres!$B$3=$C46,"X","") | B46: =+IF(VLOOKUP($C46,Parametres!$K$3:$N$14,4,0)="X","X","") | C46: Octobre | F46: 479.32101 | G46: 4057.5556
A47: =+IF(Parametres!$B$3=$C47,"X","") | B47: =+IF(VLOOKUP($C47,Parametres!$K$3:$N$14,4,0)="X","X","") | C47: Novembre | F47: 449.11178 | G47: 4856.957
A48: =+IF(Parametres!$B$3=$C48,"X","") | B48: =+IF(VLOOKUP($C48,Parametres!$K$3:$N$14,4,0)="X","X","") | C48: Décembre | F48: 461.73714 | G48: 4885.0883

Sheet Vol & Taux MOIS
B1: Park Avenue Volkswagen - Analyse des écarts "Volume & Taux - Mois courant"
B3: Neufs | C3: Volume # | D3: Marge $ | E3: Brut | G3: Usagés | H3: Volume # | I3: Marge $ | J3: Brut | L3: Service | M3: Volume $ | N3: Marge % | O3: Brut | Q3: Service #B.T. | R3: Volume # | S3: $/B.T. | T3: Ventes
B4: Écart Total | G4: Écart Total | L4: Écart Total | Q4: Écart Total
B5: Réel | C5: =Print_Mois!J27 -> 73 | D5: =Print_Mois!L27/Print_Mois!J27 -> 3556.2293 | E5: =+C5*D5 -> 259604.74 | G5: Réel | H5: =Print_Mois!J108 -> 54 | I5: =Print_Mois!L108/Print_Mois!J108 -> 1157.6933 | J5: =+H5*I5 -> 62515.44 | L5: Réel | M5: =Print_Mois!K194 -> 367237.81 | N5: =O5/M5 -> 0.70900156 | O5: =Print_Mois!L194 -> 260372.18 | Q5: Réel | R5: =Print_Mois!J185 -> 1055 | S5: =Print_Mois!K185/Print_Mois!J185 -> 319.10622 | T5: =+R5*S5 -> 336657.06
B6: Budget | C6: =Print_Mois!G27 -> 0 | D6: =Print_Mois!I27/Print_Mois!G27 -> #DIV/0! | E6: =+C6*D6 -> #DIV/0! | G6: Budget | H6: =Print_Mois!G108 -> 0 | I6: =Print_Mois!I108/Print_Mois!G108 -> #DIV/0! | J6: =+H6*I6 -> #DIV/0! | L6: Budget | M6: =Print_Mois!H194 -> 0 | N6: =O6/M6 -> #DIV/0! | O6: =Print_Mois!I194 -> 0 | Q6: Budget | R6: =Print_Mois!G185 -> 0 | S6: =Print_Mois!H185/Print_Mois!G185 -> #DIV/0! | T6: =+R6*S6 -> #DIV/0!
B7: Écart Total | C7: =+C5-C6 -> 73 | D7: =+D5-D6 -> #DIV/0! | E7: =+E5-E6 -> #DIV/0! | G7: Écart Total | H7: =+H5-H6 -> 54 | I7: =+I5-I6 -> #DIV/0! | J7: =+J5-J6 -> #DIV/0! | L7: Écart Total | M7: =+M5-M6 -> 367237.81 | N7: =+N5-N6 -> #DIV/0! | O7: =+O5-O6 -> 260372.18 | Q7: Écart Total | R7: =+R5-R6 -> 1055 | S7: =+S5-S6 -> #DIV/0! | T7: =+T5-T6 -> #DIV/0!
C8: =+C7/C6 -> #DIV/0! | D8: =+D7/D6 -> #DIV/0! | H8: =+H7/H6 -> #DIV/0! | I8: =+I7/I6 -> #DIV/0! | M8: =+M7/M6 -> #DIV/0! | N8: =+N7/N6 -> #DIV/0! | R8: =+R7/R6 -> #DIV/0! | S8: =+S7/S6 -> #DIV/0!
B9: Écart Marge | G9: Écart Marge | L9: Écart Marge | Q9: Écart $/B.T.
B10: Marge Réelle | C10: =+C5 -> 73 | D10: =+D5 -> 3556.2293 | E10: =+C10*D10 -> 259604.74 | G10: Marge Réelle | H10: =+H5 -> 54 | I10: =+I5 -> 1157.6933 | J10: =+H10*I10 -> 62515.44 | L10: Marge Réelle | M10: =+M5 -> 367237.81 | N10: =+N5 -> 0.70900156 | O10: =+M10*N10 -> 260372.18 | Q10: $/B.T. Réel | R10: =+R5 -> 1055 | S10: =+S5 -> 319.10622 | T10: =+R10*S10 -> 336657.06
B11: Marge Budget | C11: =+C5 -> 73 | D11: =+D6 -> #DIV/0! | E11: =C11*D11 -> #DIV/0! | G11: Marge Budget | H11: =+H5 -> 54 | I11: =+I6 -> #DIV/0! | J11: =H11*I11 -> #DIV/0! | L11: Marge Budget | M11: =+M5 -> 367237.81 | N11: =+N6 -> #DIV/0! | O11: =M11*N11 -> #DIV/0! | Q11: $/B.T. Budget | R11: =+R5 -> 1055 | S11: =+S6 -> #DIV/0! | T11: =R11*S11 -> #DIV/0!
B12: Écart Marge | C12: =+C10-C11 -> 0 | D12: =+D10-D11 -> #DIV/0! | E12: =+E10-E11 -> #DIV/0! | G12: Écart Marge | H12: =+H10-H11 -> 0 | I12: =+I10-I11 -> #DIV/0! | J12: =+J10-J11 -> #DIV/0! | L12: Écart Marge | M12: =+M10-M11 -> 0 | N12: =+N10-N11 -> #DIV/0! | O12: =+O10-O11 -> #DIV/0! | Q12: Écart $/B.T. | R12: =+R10-R11 -> 0 | S12: =+S10-S11 -> #DIV/0! | T12: =+T10-T11 -> #DIV/0!
B14: Écart Volume | G14: Écart Volume | L14: Écart Volume | Q14: Écart Volume
B15: Volume Réel | C15: =+C5 -> 73 | D15: =+D6 -> #DIV/0! | E15: =+C15*D15 -> #DIV/0! | G15: Volume Réel | H15: =+H5 -> 54 | I15: =+I6 -> #DIV/0! | J15: =+H15*I15 -> #DIV/0! | L15: Volume Réel | M15: =+M5 -> 367237.81 | N15: =+N6 -> #DIV/0! | O15: =+M15*N15 -> #DIV/0! | Q15: Volume Réel | R15: =+R5 -> 1055 | S15: =+S6 -> #DIV/0! | T15: =+R15*S15 -> #DIV/0!
B16: Volume Budget | C16: =+C6 -> 0 | D16: =+D6 -> #DIV/0! | E16: =C16*D16 -> #DIV/0! | G16: Volume Budget | H16: =+H6 -> 0 | I16: =+I6 -> #DIV/0! | J16: =H16*I16 -> #DIV/0! | L16: Volume Budget | M16: =+M6 -> 0 | N16: =+N6 -> #DIV/0! | O16: =M16*N16 -> #DIV/0! | Q16: Volume Budget | R16: =+R6 -> 0 | S16: =+S6 -> #DIV/0! | T16: =R16*S16 -> #DIV/0!
B17: Écart Volume | C17: =+C15-C16 -> 73 | D17: =+D15-D16 -> #DIV/0! | E17: =+E15-E16 -> #DIV/0! | G17: Écart Volume | H17: =+H15-H16 -> 54 | I17: =+I15-I16 -> #DIV/0! | J17: =+J15-J16 -> #DIV/0! | L17: Écart Volume | M17: =+M15-M16 -> 367237.81 | N17: =+N15-N16 -> #DIV/0! | O17: =+O15-O16 -> #DIV/0! | Q17: Écart Volume | R17: =+R15-R16 -> 1055 | S17: =+S15-S16 -> #DIV/0! | T17: =+T15-T16 -> #DIV/0!
E18: =+E7-E12-E17 -> #DIV/0! | J18: =+J7-J12-J17 -> #DIV/0! | O18: =+O7-O12-O17 -> #DIV/0! | T18: =+T7-T12-T17 -> #DIV/0!
B19: Variabilité Max-Min | G19: Variabilité Max-Min | L19: Variabilité Max-Min | Q19: Variabilité Max-Min
B20: Max Vol & Marge | C20: =MAX(C5:C6) -> 73 | D20: =MAX(D5:D6) -> #DIV/0! | E20: =+C20*D20 -> #DIV/0! | G20: Max Vol & Marge | H20: =MAX(H5:H6) -> 54 | I20: =MAX(I5:I6) -> #DIV/0! | J20: =+H20*I20 -> #DIV/0! | L20: Max Vol & Marge | M20: =MAX(M5:M6) -> 367237.81 | N20: =MAX(N5:N6) -> #DIV/0! | O20: =+M20*N20 -> #DIV/0! | Q20: Max Vol & Marge | R20: =MAX(R5:R6) -> 1055 | S20: =MAX(S5:S6) -> #DIV/0! | T20: =+R20*S20 -> #DIV/0!
B21: Moyenne | E21: =AVERAGE(E20,E22) -> #DIV/0! | G21: Moyenne | J21: =AVERAGE(J20,J22) -> #DIV/0! | L21: Moyenne | O21: =AVERAGE(O20,O22) -> #DIV/0! | Q21: Moyenne | T21: =AVERAGE(T20,T22) -> #DIV/0!
B22: Min Vol & Marge | C22: =MIN(C5:C6) -> 0 | D22: =MIN(D5:D6) -> #DIV/0! | E22: =+C22*D22 -> #DIV/0! | G22: Min Vol & Marge | H22: =MIN(H5:H6) -> 0 | I22: =MIN(I5:I6) -> #DIV/0! | J22: =+H22*I22 -> #DIV/0! | L22: Min Vol & Marge | M22: =MIN(M5:M6) -> 0 | N22: =MIN(N5:N6) -> #DIV/0! | O22: =+M22*N22 -> #DIV/0! | Q22: Min Vol & Marge | R22: =MIN(R5:R6) -> 0 | S22: =MIN(S5:S6) -> #DIV/0! | T22: =+R22*S22 -> #DIV/0!
B23: Fourchette | C23: =+C20-C22 -> 73 | D23: =+D20-D22 -> #DIV/0! | E23: =+E20-E22 -> #DIV/0! | G23: Fourchette | H23: =+H20-H22 -> 54 | I23: =+I20-I22 -> #DIV/0! | J23: =+J20-J22 -> #DIV/0! | L23: Fourchette | M23: =+M20-M22 -> 367237.81 | N23: =+N20-N22 -> #DIV/0! | O23: =+O20-O22 -> #DIV/0! | Q23: Fourchette | R23: =+R20-R22 -> 1055 | S23: =+S20-S22 -> #DIV/0! | T23: =+T20-T22 -> #DIV/0!
C25: Réel VS Max | E25: =+E5/E20 -> #DIV/0! | H25: Réel VS Max | J25: =+J5/J20 -> #DIV/0! | M25: Réel VS Max | O25: =+O5/O20 -> #DIV/0! | R25: Réel VS Max | T25: =+T5/T20 -> #DIV/0!
C26: Réel VS Moyenne | E26: =+E5/E21 -> #DIV/0! | H26: Réel VS Moyenne | J26: =+J5/J21 -> #DIV/0! | M26: Réel VS Moyenne | O26: =+O5/O21 -> #DIV/0! | R26: Réel VS Moyenne | T26: =+T5/T21 -> #DIV/0!
C27: Réel VS Min | E27: =+E5/E22 -> #DIV/0! | H27: Réel VS Min | J27: =+J5/J22 -> #DIV/0! | M27: Réel VS Min | O27: =+O5/O22 -> #DIV/0! | R27: Réel VS Min | T27: =+T5/T22 -> #DIV/0!
C29: Fourchette Variabilité | E29: =+E27-E25 -> #DIV/0! | H29: Fourchette Variabilité | J29: =+J27-J25 -> #DIV/0! | M29: Fourchette Variabilité | O29: =+O27-O25 -> #DIV/0! | R29: Fourchette Variabilité | T29: =+T27-T25 -> #DIV/0!
B31: Autres Revenus Budgétés non-réalisé | G31: Autres Revenus Budgétés non-réalisé
B32: Holdback | C32: =+C17 -> 73 | D32: =+E32/C32 -> 175.23203 | E32: =+Print_Mois!N78 -> 12791.938
B33: Frais d'Admin. | C33: =+C17 -> 73 | D33: =+E33/C33 -> 58.584247 | E33: =+Print_Mois!N82 -> 4276.65 | G33: Frais d'Admin. | H33: =+H17 -> 54 | I33: =+J33/H33 -> -251.8193 | J33: =+Print_Mois!N159 -> -13598.242
E34: =SUM(E32:E33) -> 17068.588 | J34: =SUM(J32:J33) -> -13598.242

Sheet Print_AAD
C1: =Parametres!B1 -> Volks | K1: Véhicules neufs | S1: =CONCATENATE("Réalisé AAJ,"," ",Parametres!B3," ",Parametres!B4) -> Réalisé AAJ, Avril 2024
D2: X | E2: O | F2: U | J2: NB | L2: $ | O2: X | P2: O | Q2: U | X2: X | Y2: O | Z2: U | AJ2: X | AK2: O | AL2: U
D3: BUDGET ORIGINAL | J3: RÉALISATION | M3: ÉCART réel / Budget | O3: ANNÉE PRÉCÉDENTE | R3: ECART (réel/ Ann.Préc.) | V3: NEUF | W3: 0.45
D4: UNITE | E4: $P/UNITÉ | F4: $PROFITS | J4: UNITÉS | K4: $P/UNITE | L4: $PROFITS | M4: UNITÉS | N4: $PROFITS | O4: UNITE | P4: $P/UNITÉ | Q4: $PROFITS | R4: UNITÉS | S4: $PROFITS | V4: USAGE | W4: 0.1
A5: =+B5&C5 -> Véhicules neufsVentes nettes | B5: =+$K$1 -> Véhicules neufs | C5: Ventes nettes | F5: {=+SUMPRODUCT(('Budget original'!$A$8:$A$501=$A5)*('Budget original'!$C$3:$AO$3=F$2),'Budget original'!$C$8:$AO$501)} -> 8756133.7 | L5: =-SUMIFS(BV_Data_An_Cour!$P:$P,BV_Data_An_Cour!$X:$X,"Oui",BV_Data_An_Cour!$U:$U,$B5) -> 13868001 | Q5: {=+SUMPRODUCT(('Réel 2023'!$A$8:$A$501=$A5)*('Réel 2023'!$C$3:$AO$3=Q$2),'Réel 2023'!$C$8:$AO$501)} -> 7385845.2 | V5: SERVICE | W5: 0.225
A6: =+B6&C6 -> Véhicules neufsAutos détail | B6: =+$K$1 -> Véhicules neufs | C6: Autos détail | D6: {=+SUMPRODUCT(('Budget original'!$A$8:$A$501=$A6)*('Budget original'!$C$3:$AO$3=D$2),'Budget original'!$C$8:$AO$501)} -> 32.4 | E6: =IF(D6=0,0,F6/D6) -> 2198.1219 | F6: {=+SUMPRODUCT(('Budget original'!$A$8:$A$501=$A6)*('Budget original'!$C$3:$AO$3=F$2),'Budget original'!$C$8:$AO$501)} -> 71219.15 | J6: =-SUMIFS(BV_Data_An_Cour!$P:$P,BV_Data_An_Cour!$U:$U,$B6,BV_Data_An_Cour!$V:$V,$C6,BV_Data_An_Cour!$W:$W,J$2) -> 66 | K6: =IF(J6=0,0,L6/J6) -> 2198.3617 | L6: =-SUMIFS(BV_Data_An_Cour!$P:$P,BV_Data_An_Cour!$U:$U,$B6,BV_Data_An_Cour!$V:$V,$C6,BV_Data_An_Cour!$W:$W,L$2) -> 145091.87 | M6: =J6-D6 -> 33.6 | N6: =L6-F6 -> 73872.72 | O6: {=+SUMPRODUCT(('Réel 2023'!$A$8:$A$501=$A6)*('Réel 2023'!$C$3:$AO$3=O$2),'Réel 2023'!$C$8:$AO$501)} -> 38 | P6: =IF(O6=0,0,Q6/O6) -> 2121.8226 | Q6: {=+SUMPRODUCT(('Réel 2023'!$A$8:$A$501=$A6)*('Réel 2023'!$C$3:$AO$3=Q$2),'Réel 2023'!$C$8:$AO$501)} -> 80629.26 | R6: =J6-O6 -> 28 | S6: =L6-Q6 -> 64462.61 | V6: CARROSSERIE | W6: 0.025
A7: =+B7&C7 -> Véhicules neufsCamions détail | B7: =+$K$1 -> Véhicules neufs | C7: Camions détail | D7: {=+SUMPRODUCT(('Budget original'!$A$8:$A$501=$A7)*('Budget original'!$C$3:$AO$3=D$2),'Budget original'!$C$8:$AO$501)} -> 135 | E7: =IF(D7=0,0,F7/D7) -> 2850.2587 | F7: {=+SUMPRODUCT(('Budget original'!$A$8:$A$501=$A7)*('Budget original'!$C$3:$AO$3=F$2),'Budget original'!$C$8:$AO$501)} -> 384784.92 | J7: =-SUMIFS(BV_Data_An_Cour!$P:$P,BV_Data_An_Cour!$U:$U,$B7,BV_Data_An_Cour!$V:$V,$C7,BV_Data_An_Cour!$W:$W,J$2) -> 188 | K7: =IF(J7=0,0,L7/J7) -> 2682.0884 | L7: =-SUMIFS(BV_Data_An_Cour!$P:$P,BV_Data_An_Cour!$U:$U,$B7,BV_Data_An_Cour!$V:$V,$C7,BV_Data_An_Cour!$W:$W,L$2) -> 504232.62 | M7: =J7-D7 -> 53 | N7: =L7-F7 -> 119447.7 | O7: {=+SUMPRODUCT(('Réel 2023'!$A$8:$A$501=$A7)*('Réel 2023'!$C$3:$AO$3=O$2),'Réel 2023'!$C$8:$AO$501)} -> 92 | P7: =IF(O7=0,0,Q7/O7) -> 2483.4471 | Q7: {=+SUMPRODUCT(('Réel 2023'!$A$8:$A$501=$A7)*('Réel 2023'!$C$3:$AO$3=Q$2),'Réel 2023'!$C$8:$AO$501)} -> 228477.13 | R7: =J7-O7 -> 96 | S7: =L7-Q7 -> 275755.49 | V7: PIECES | W7: 0.2
