Workbook
Name _Dates_Conc: [1]Dealers!$BF$37:$KA$63
Name _scen: '[1]Scen & Sens'!$E$26
Name _scen1: '[1]Scen & Sens'!$E$27
Name _scen2: '[1]Scen & Sens'!$E$28
Name _SCenarios: '[1]Scen & Sens'!$J$26:$O$26
Name _Sens1: '[1]Scen & Sens'!$F$9
Name _Sens2: '[1]Scen & Sens'!$F$10
Name _sensRes1: '[1]Scen & Sens'!$E$15
Name _sensRes2: '[1]Scen & Sens'!$E$16
Name _sensRes3: '[1]Scen & Sens'!$E$17
Name _sensRes4: '[1]Scen & Sens'!$E$18
Name _sensRes5: '[1]Scen & Sens'!$E$19
Name _sensRes6: '[1]Scen & Sens'!$E$20
Name _sensRes7: '[1]Scen & Sens'!$E$21
Name DateRange: [1]Volkswagen!$BF$6:$DY$6
Name Monetary_Unit: [1]Parameters!$B$15
Name Months: [1]Parameters!$E$9:$E$20
Name Rng_Dealers_Names: [1]!Tbl_Dealers[Dealer Name]
Name Rng_Dlr_Dates: [1]!Tbl_V_Dlr_Dates[Date]
Name Titre: [1]Front!$A$9

Sheet Parametres
A1: Compagnie | B1: Volks
G2: 1-Mémo | M2: Mois | N2: YTD
A3: Mois Courant | B3: Mai | C3: =+VLOOKUP(B3,$K$3:$L$14,2,0) -> 5 | G3: 10-Compte compteur | K3: Janvier | L3: 1 | M3: =+IF($K3=$B$3,"X","") | N3: =+IF(K3=B3,"X",IF(L3<=$C$3,"X","")) -> X
A4: Année | B4: 2022 | K4: Février | L4: 2 | M4: =+IF($K4=$B$3,"X","") | N4: =+IF(K4=B4,"X",IF(L4<=$C$3,"X","")) -> X
K5: Mars | L5: 3 | M5: =+IF($K5=$B$3,"X","") | N5: =+IF(K5=B5,"X",IF(L5<=$C$3,"X","")) -> X
K6: Avril | L6: 4 | M6: =+IF($K6=$B$3,"X","") | N6: =+IF(K6=B6,"X",IF(L6<=$C$3,"X","")) -> X
K7: Mai | L7: 5 | M7: =+IF($K7=$B$3,"X","") -> X | N7: =+IF(K7=B7,"X",IF(L7<=$C$3,"X","")) -> X
K8: Juin | L8: 6 | M8: =+IF($K8=$B$3,"X","") | N8: =+IF(K8=B8,"X",IF(L8<=$C$3,"X",""))
A9: Sélectionner le mois en B3 | K9: Juillet | L9: 7 | M9: =+IF($K9=$B$3,"X","") | N9: =+IF(K9=B9,"X",IF(L9<=$C$3,"X",""))
A10: Coller les balances de vérification respectives en cellule A1 dans les onglets BV_Data_An_Cour et BV_Data_An_Prec | K10: Août | L10: 8 | M10: =+IF($K10=$B$3,"X","") | N10: =+IF(K10=B10,"X",IF(L10<=$C$3,"X",""))
A11: Vérifier s'il y a des #N/A dans les colonnes T à X des onlgets de BV | K11: Septembre | L11: 9 | M11: =+IF($K11=$B$3,"X","") | N11: =+IF(K11=B11,"X",IF(L11<=$C$3,"X",""))
A12: Vérifier les chiffres avec l'état financier et les réalisés an passé pour les résultat net mois et aad | K12: Octobre | L12: 10 | M12: =+IF($K12=$B$3,"X","") | N12: =+IF(K12=B12,"X",IF(L12<=$C$3,"X",""))
K13: Novembre | L13: 11 | M13: =+IF($K13=$B$3,"X","") | N13: =+IF(K13=B13,"X",IF(L13<=$C$3,"X",""))
K14: Décembre | L14: 12 | M14: =+IF($K14=$B$3,"X","") | N14: =+IF(K14=B14,"X",IF(L14<=$C$3,"X",""))

Sheet Bilan
A1: BILAN
A2: =+Parametres!B1 -> Volks
A3: =CONCATENATE("",,Parametres!B3," ",Parametres!B4) -> Mai 2022
A5: Encaisse | B5: =SUMIFS(BV_Data_An_Cour!$P:$P,BV_Data_An_Cour!$U:$U,$A$1,BV_Data_An_Cour!$V:$V,$A5) -> 1128193.2 | D5: Marge de crédit | E5: =-SUMIFS(BV_Data_An_Cour!$P:$P,BV_Data_An_Cour!$U:$U,$A$1,BV_Data_An_Cour!$V:$V,$D5) -> 0
A6: Total Trésorerie et équivalent de Trésorerie | B6: =SUM(B5) -> 1128193.2
D7: Portion Court Terme de la Dette Long Terme | E7: =-SUMIFS(BV_Data_An_Cour!$P:$P,BV_Data_An_Cour!$U:$U,$A$1,BV_Data_An_Cour!$V:$V,$D7) -> 15810
A8: Recevables Contrats en Transit | B8: =SUMIFS(BV_Data_An_Cour!$P:$P,BV_Data_An_Cour!$U:$U,$A$1,BV_Data_An_Cour!$V:$V,$A8) -> 1272589.9
A9: Recevables Véhicules | B9: =SUMIFS(BV_Data_An_Cour!$P:$P,BV_Data_An_Cour!$U:$U,$A$1,BV_Data_An_Cour!$V:$V,$A9) -> -9939.22 | D9: Avances à payer | E9: =-SUMIFS(BV_Data_An_Cour!$P:$P,BV_Data_An_Cour!$U:$U,$A$1,BV_Data_An_Cour!$V:$V,$D9) -> 0
A10: Recevables Manufacturier | B10: =SUMIFS(BV_Data_An_Cour!$P:$P,BV_Data_An_Cour!$U:$U,$A$1,BV_Data_An_Cour!$V:$V,$A10) -> 71227.74 | D10: Comptes à Payer Fournisseurs | E10: =-SUMIFS(BV_Data_An_Cour!$P:$P,BV_Data_An_Cour!$U:$U,$A$1,BV_Data_An_Cour!$V:$V,$D10) -> 201419.27
A11: Recevables Pièces et Service | B11: =SUMIFS(BV_Data_An_Cour!$P:$P,BV_Data_An_Cour!$U:$U,$A$1,BV_Data_An_Cour!$V:$V,$A11) -> 97183.22 | D11: Taxes de Vente à Payer | E11: =-SUMIFS(BV_Data_An_Cour!$P:$P,BV_Data_An_Cour!$U:$U,$A$1,BV_Data_An_Cour!$V:$V,$D11) -> 47849.57
A12: Recevables Garantie Manufacturier | B12: =SUMIFS(BV_Data_An_Cour!$P:$P,BV_Data_An_Cour!$U:$U,$A$1,BV_Data_An_Cour!$V:$V,$A12) -> 82327.58 | D12: Impôts à payer | E12: =-SUMIFS(BV_Data_An_Cour!$P:$P,BV_Data_An_Cour!$U:$U,$A$1,BV_Data_An_Cour!$V:$V,$D12) -> 0
A13: Recevables Carrosserie | B13: =SUMIFS(BV_Data_An_Cour!$P:$P,BV_Data_An_Cour!$U:$U,$A$1,BV_Data_An_Cour!$V:$V,$A13) -> 53373 | D13: Dépôts de Client | E13: =-SUMIFS(BV_Data_An_Cour!$P:$P,BV_Data_An_Cour!$U:$U,$A$1,BV_Data_An_Cour!$V:$V,$D13) -> 20470
A14: Recevables Intercos | B14: =SUMIFS(BV_Data_An_Cour!$P:$P,BV_Data_An_Cour!$U:$U,$A$1,BV_Data_An_Cour!$V:$V,$A14) -> 228096.94 | D14: Payables Intercos | E14: =-SUMIFS(BV_Data_An_Cour!$P:$P,BV_Data_An_Cour!$U:$U,$A$1,BV_Data_An_Cour!$V:$V,$D14) -> 94718.57
A15: Recevables Autres | B15: =SUMIFS(BV_Data_An_Cour!$P:$P,BV_Data_An_Cour!$U:$U,$A$1,BV_Data_An_Cour!$V:$V,$A15) -> 10367.38 | D15: Autres Comptes à Payer | E15: =-SUMIFS(BV_Data_An_Cour!$P:$P,BV_Data_An_Cour!$U:$U,$A$1,BV_Data_An_Cour!$V:$V,$D15) -> 223407.58
A16: Total Comptes à Recevoir | B16: =+SUM(B8:B15) -> 1805226.6 | D16: Total Comptes à Payer | E16: =+SUM(E10:E15) -> 587864.99
A18: Inventaire Véhicules Neufs | B18: =SUMIFS(BV_Data_An_Cour!$P:$P,BV_Data_An_Cour!$U:$U,$A$1,BV_Data_An_Cour!$V:$V,$A18) -> 1089551.7 | D18: Effet à Payer Véhicules Neufs | E18: =-SUMIFS(BV_Data_An_Cour!$P:$P,BV_Data_An_Cour!$U:$U,$A$1,BV_Data_An_Cour!$V:$V,$D18) -> 2111279.5
A19: Inventaire Véhicules Usagés | B19: =SUMIFS(BV_Data_An_Cour!$P:$P,BV_Data_An_Cour!$U:$U,$A$1,BV_Data_An_Cour!$V:$V,$A19) -> 2662651.3 | D19: Effet à Payer Véhicules Usagés | E19: =-SUMIFS(BV_Data_An_Cour!$P:$P,BV_Data_An_Cour!$U:$U,$A$1,BV_Data_An_Cour!$V:$V,$D19) -> 1384167.9
A20: Inventaire Pièces, Pneus, Huile | B20: =SUMIFS(BV_Data_An_Cour!$P:$P,BV_Data_An_Cour!$U:$U,$A$1,BV_Data_An_Cour!$V:$V,$A20) -> 357968 | D20: Total Effets à Payer | E20: =+SUM(E18:E19) -> 3495447.4
A21: Total Inventaires | B21: =SUM(B18:B20) -> 4110171
D22: Salaires à Payer | E22: =-SUMIFS(BV_Data_An_Cour!$P:$P,BV_Data_An_Cour!$U:$U,$A$1,BV_Data_An_Cour!$V:$V,$D22) -> 505504.43
A23: Avances à recevoir | B23: =SUMIFS(BV_Data_An_Cour!$P:$P,BV_Data_An_Cour!$U:$U,$A$1,BV_Data_An_Cour!$V:$V,$A23) -> 0 | D23: DAS à Payer | E23: =-SUMIFS(BV_Data_An_Cour!$P:$P,BV_Data_An_Cour!$U:$U,$A$1,BV_Data_An_Cour!$V:$V,$D23) -> 19224.22
A24: Travaux en Cours | B24: =SUMIFS(BV_Data_An_Cour!$P:$P,BV_Data_An_Cour!$U:$U,$A$1,BV_Data_An_Cour!$V:$V,$A24) -> 8206.25 | D24: Autres Courus | E24: =-SUMIFS(BV_Data_An_Cour!$P:$P,BV_Data_An_Cour!$U:$U,$A$1,BV_Data_An_Cour!$V:$V,$D24) -> 308308.02
A25: Sous-Traitance | B25: =SUMIFS(BV_Data_An_Cour!$P:$P,BV_Data_An_Cour!$U:$U,$A$1,BV_Data_An_Cour!$V:$V,$A25) -> 26265.17 | D25: [...] | E25: =-SUMIFS(BV_Data_An_Cour!$P:$P,BV_Data_An_Cour!$U:$U,$A$1,BV_Data_An_Cour!$V:$V,$D25) -> 0
A26: Frais Payés d'Avance | B26: =SUMIFS(BV_Data_An_Cour!$P:$P,BV_Data_An_Cour!$U:$U,$A$1,BV_Data_An_Cour!$V:$V,$A26) -> -13170.37 | D26: [...] | E26: =-SUMIFS(BV_Data_An_Cour!$P:$P,BV_Data_An_Cour!$U:$U,$A$1,BV_Data_An_Cour!$V:$V,$D26) -> 0
A27: [...] | B27: =SUMIFS(BV_Data_An_Cour!$P:$P,BV_Data_An_Cour!$U:$U,$A$1,BV_Data_An_Cour!$V:$V,$A27) -> 0 | D27: [...] | E27: =-SUMIFS(BV_Data_An_Cour!$P:$P,BV_Data_An_Cour!$U:$U,$A$1,BV_Data_An_Cour!$V:$V,$D27) -> 0
A28: [...] | B28: =SUMIFS(BV_Data_An_Cour!$P:$P,BV_Data_An_Cour!$U:$U,$A$1,BV_Data_An_Cour!$V:$V,$A28) -> 0 | D28: Total Frais Courus | E28: =SUM(E22:E24) -> 833036.67
A29: [...] | B29: =SUMIFS(BV_Data_An_Cour!$P:$P,BV_Data_An_Cour!$U:$U,$A$1,BV_Data_An_Cour!$V:$V,$A29) -> 0
A30: Total Autres | B30: =SUM(B23:B29) -> 21301.05 | D30: Total Passif Court Terme | E30: =+E5+E7+E16+E20+E28 -> 4932159.1
A32: Total Actif Court Terme | B32: =+B6+B16+B21+B30 -> 7064891.8
D33: Impôts Futurs à payer | E33: =-SUMIFS(BV_Data_An_Cour!$P:$P,BV_Data_An_Cour!$U:$U,$A$1,BV_Data_An_Cour!$V:$V,$D33) -> 0
A35: Terrain | B35: =SUMIFS(BV_Data_An_Cour!$P:$P,BV_Data_An_Cour!$U:$U,$A$1,BV_Data_An_Cour!$V:$V,$A35) -> 0 | D35: Avances Long Terme à Payer | E35: =-SUMIFS(BV_Data_An_Cour!$P:$P,BV_Data_An_Cour!$U:$U,$A$1,BV_Data_An_Cour!$V:$V,$D35) -> 0
A36: Bâtisse | B36: =SUMIFS(BV_Data_An_Cour!$P:$P,BV_Data_An_Cour!$U:$U,$A$1,BV_Data_An_Cour!$V:$V,$A36) -> 0 | D36: Hypothèque à Payer | E36: =-SUMIFS(BV_Data_An_Cour!$P:$P,BV_Data_An_Cour!$U:$U,$A$1,BV_Data_An_Cour!$V:$V,$D36) -> 0
A37: Améliorations Locatives | B37: =SUMIFS(BV_Data_An_Cour!$P:$P,BV_Data_An_Cour!$U:$U,$A$1,BV_Data_An_Cour!$V:$V,$A37) -> 44145.26 | D37: Dette à Long Terme | E37: =-SUMIFS(BV_Data_An_Cour!$P:$P,BV_Data_An_Cour!$U:$U,$A$1,BV_Data_An_Cour!$V:$V,$D37) -> 5761.25
A38: Améliorations Locatives Permanentes | B38: =SUMIFS(BV_Data_An_Cour!$P:$P,BV_Data_An_Cour!$U:$U,$A$1,BV_Data_An_Cour!$V:$V,$A38) -> 0 | D38: Autres Dettes à Long Terme | E38: =-SUMIFS(BV_Data_An_Cour!$P:$P,BV_Data_An_Cour!$U:$U,$A$1,BV_Data_An_Cour!$V:$V,$D38) -> 0
A39: Équipements Service | B39: =SUMIFS(BV_Data_An_Cour!$P:$P,BV_Data_An_Cour!$U:$U,$A$1,BV_Data_An_Cour!$V:$V,$A39) -> 156025.21 | D39: [...] | E39: =-SUMIFS(BV_Data_An_Cour!$P:$P,BV_Data_An_Cour!$U:$U,$A$1,BV_Data_An_Cour!$V:$V,$D39) -> 0
A40: Mobilier | B40: =SUMIFS(BV_Data_An_Cour!$P:$P,BV_Data_An_Cour!$U:$U,$A$1,BV_Data_An_Cour!$V:$V,$A40) -> 30519.79 | D40: [...] | E40: =-SUMIFS(BV_Data_An_Cour!$P:$P,BV_Data_An_Cour!$U:$U,$A$1,BV_Data_An_Cour!$V:$V,$D40) -> 0
A41: Équipements Informatique | B41: =SUMIFS(BV_Data_An_Cour!$P:$P,BV_Data_An_Cour!$U:$U,$A$1,BV_Data_An_Cour!$V:$V,$A41) -> 16217.06 | D41: [...] | E41: =-SUMIFS(BV_Data_An_Cour!$P:$P,BV_Data_An_Cour!$U:$U,$A$1,BV_Data_An_Cour!$V:$V,$D41) -> 0
A42: Équipements Téléphonique | B42: =SUMIFS(BV_Data_An_Cour!$P:$P,BV_Data_An_Cour!$U:$U,$A$1,BV_Data_An_Cour!$V:$V,$A42) -> 0 | D42: Total Passif long terme | E42: =+SUM(E33:E38) -> 5761.25
A43: Enseigne | B43: =SUMIFS(BV_Data_An_Cour!$P:$P,BV_Data_An_Cour!$U:$U,$A$1,BV_Data_An_Cour!$V:$V,$A43) -> 0.01
A44: Total Immobilisations Nettes | B44: =SUM(B35:B43) -> 246907.33
D45: Total Passifs | E45: =+E42+E30 -> 4937920.3
A46: Avances à Recevoir Long Terme | B46: =SUMIFS(BV_Data_An_Cour!$P:$P,BV_Data_An_Cour!$U:$U,$A$1,BV_Data_An_Cour!$V:$V,$A46) -> 5873600
A48: Achalandage | B48: =SUMIFS(BV_Data_An_Cour!$P:$P,BV_Data_An_Cour!$U:$U,$A$1,BV_Data_An_Cour!$V:$V,$A48) -> 0 | D48: Capital Actions | E48: =-SUMIFS(BV_Data_An_Cour!$P:$P,BV_Data_An_Cour!$U:$U,$A$1,BV_Data_An_Cour!$V:$V,$D48) -> 2697547.5
D49: Apport | E49: =-SUMIFS(BV_Data_An_Cour!$P:$P,BV_Data_An_Cour!$U:$U,$A$1,BV_Data_An_Cour!$V:$V,$D49) -> 1723617
A50: [...] | B50: =SUMIFS(BV_Data_An_Cour!$P:$P,BV_Data_An_Cour!$U:$U,$A$1,BV_Data_An_Cour!$V:$V,$A50) -> 0 | D50: Bénéfices non répartis | E50: =-SUMIFS(BV_Data_An_Cour!$P:$P,BV_Data_An_Cour!$U:$U,$A$1,BV_Data_An_Cour!$V:$V,$D50)+Print_AAD!AF497 -> 3826314.3
A51: [...] | B51: =SUMIFS(BV_Data_An_Cour!$P:$P,BV_Data_An_Cour!$U:$U,$A$1,BV_Data_An_Cour!$V:$V,$A51) -> 0 | D51: Dividendes | E51: =-SUMIFS(BV_Data_An_Cour!$P:$P,BV_Data_An_Cour!$U:$U,$A$1,BV_Data_An_Cour!$V:$V,$D51) -> 0
A52: [...] | B52: =SUMIFS(BV_Data_An_Cour!$P:$P,BV_Data_An_Cour!$U:$U,$A$1,BV_Data_An_Cour!$V:$V,$A52) -> 0
A53: Total Actif Long Terme | B53: =+B44+B48+B46 -> 6120507.3 | D53: Total Capitaux Propres / Avoir | E53: =SUM(E48:E51) -> 8247478.8
A56: Total Actif | B56: =+B32+B53 -> 13185399 | D56: Total Passif et Capitaux Propres / Avoir | E56: =+E53+E45 -> 13185399
E65: =+B56-E56 -> 0

Sheet Budget original
B1: ="Budget 2022 Mensuel Révisé"&" "&Parametres!$B$1 -> Budget 2022 Mensuel Révisé Volks
B2: Mois | F2: =+IF(Parametres!$B$3=F$6,"X","") | G2: =+IF(Parametres!$B$3=F$6,"O","") | H2: =+IF(Parametres!$B$3=F$6,"U","") | I2: =+IF(Parametres!$B$3=I$6,"X","") | J2: =+IF(Parametres!$B$3=I$6,"O","") | K2: =+IF(Parametres!$B$3=I$6,"U","") | L2: =+IF(Parametres!$B$3=L$6,"X","") | M2: =+IF(Parametres!$B$3=L$6,"O","") | N2: =+IF(Parametres!$B$3=L$6,"U","") | O2: =+IF(Parametres!$B$3=O$6,"X","") | P2: =+IF(Parametres!$B$3=O$6,"O","") | Q2: =+IF(Parametres!$B$3=O$6,"U","") | R2: =+IF(Parametres!$B$3=R$6,"X","") -> X | S2: =+IF(Parametres!$B$3=R$6,"O","") -> O | T2: =+IF(Parametres!$B$3=R$6,"U","") -> U | U2: =+IF(Parametres!$B$3=U$6,"X","") | V2: =+IF(Parametres!$B$3=U$6,"O","") | W2: =+IF(Parametres!$B$3=U$6,"U","") | X2: =+IF(Parametres!$B$3=X$6,"X","") | Y2: =+IF(Parametres!$B$3=X$6,"O","") | Z2: =+IF(Parametres!$B$3=X$6,"U","") | AA2: =+IF(Parametres!$B$3=AA$6,"X","") | AB2: =+IF(Parametres!$B$3=AA$6,"O","") | AC2: =+IF(Parametres!$B$3=AA$6,"U","") | AD2: =+IF(Parametres!$B$3=AD$6,"X","") | AE2: =+IF(Parametres!$B$3=AD$6,"O","") | AF2: =+IF(Parametres!$B$3=AD$6,"U","") | AG2: =+IF(Parametres!$B$3=AG$6,"X","") | AH2: =+IF(Parametres!$B$3=AG$6,"O","") | AI2: =+IF(Parametres!$B$3=AG$6,"U","") | AJ2: =+IF(Parametres!$B$3=AJ$6,"X","") | AK2: =+IF(Parametres!$B$3=AJ$6,"O","") | AL2: =+IF(Parametres!$B$3=AJ$6,"U","") | AM2: =+IF(Parametres!$B$3=AM$6,"X","") | AN2: =+IF(Parametres!$B$3=AM$6,"O","") | AO2: =+IF(Parametres!$B$3=AM$6,"U","")
B3: YTD | F3: =+IF(VLOOKUP(F$6,Parametres!$K$3:$N$14,4,0)="X","X","") -> X | G3: =+IF(VLOOKUP(F$6,Parametres!$K$3:$N$14,4,0)="X","O","") -> O | H3: =+IF(VLOOKUP(F$6,Parametres!$K$3:$N$14,4,0)="X","U","") -> U | I3: =+IF(VLOOKUP(I$6,Parametres!$K$3:$N$14,4,0)="X","X","") -> X | J3: =+IF(VLOOKUP(I$6,Parametres!$K$3:$N$14,4,0)="X","O","") -> O | K3: =+IF(VLOOKUP(I$6,Parametres!$K$3:$N$14,4,0)="X","U","") -> U | L3: =+IF(VLOOKUP(L$6,Parametres!$K$3:$N$14,4,0)="X","X","") -> X | M3: =+IF(VLOOKUP(L$6,Parametres!$K$3:$N$14,4,0)="X","O","") -> O | N3: =+IF(VLOOKUP(L$6,Parametres!$K$3:$N$14,4,0)="X","U","") -> U | O3: =+IF(VLOOKUP(O$6,Parametres!$K$3:$N$14,4,0)="X","X","") -> X | P3: =+IF(VLOOKUP(O$6,Parametres!$K$3:$N$14,4,0)="X","O","") -> O | Q3: =+IF(VLOOKUP(O$6,Parametres!$K$3:$N$14,4,0)="X","U","") -> U | R3: =+IF(VLOOKUP(R$6,Parametres!$K$3:$N$14,4,0)="X","X","") -> X | S3: =+IF(VLOOKUP(R$6,Parametres!$K$3:$N$14,4,0)="X","O","") -> O | T3: =+IF(VLOOKUP(R$6,Parametres!$K$3:$N$14,4,0)="X","U","") -> U | U3: =+IF(VLOOKUP(U$6,Parametres!$K$3:$N$14,4,0)="X","X","") | V3: =+IF(VLOOKUP(U$6,Parametres!$K$3:$N$14,4,0)="X","O","") | W3: =+IF(VLOOKUP(U$6,Parametres!$K$3:$N$14,4,0)="X","U","") | X3: =+IF(VLOOKUP(X$6,Parametres!$K$3:$N$14,4,0)="X","X","") | Y3: =+IF(VLOOKUP(X$6,Parametres!$K$3:$N$14,4,0)="X","O","") | Z3: =+IF(VLOOKUP(X$6,Parametres!$K$3:$N$14,4,0)="X","U","") | AA3: =+IF(VLOOKUP(AA$6,Parametres!$K$3:$N$14,4,0)="X","X","") | AB3: =+IF(VLOOKUP(AA$6,Parametres!$K$3:$N$14,4,0)="X","O","") | AC3: =+IF(VLOOKUP(AA$6,Parametres!$K$3:$N$14,4,0)="X","U","") | AD3: =+IF(VLOOKUP(AD$6,Parametres!$K$3:$N$14,4,0)="X","X","") | AE3: =+IF(VLOOKUP(AD$6,Parametres!$K$3:$N$14,4,0)="X","O","") | AF3: =+IF(VLOOKUP(AD$6,Parametres!$K$3:$N$14,4,0)="X","U","") | AG3: =+IF(VLOOKUP(AG$6,Parametres!$K$3:$N$14,4,0)="X","X","") | AH3: =+IF(VLOOKUP(AG$6,Parametres!$K$3:$N$14,4,0)="X","O","") | AI3: =+IF(VLOOKUP(AG$6,Parametres!$K$3:$N$14,4,0)="X","U","") | AJ3: =+IF(VLOOKUP(AJ$6,Parametres!$K$3:$N$14,4,0)="X","X","") | AK3: =+IF(VLOOKUP(AJ$6,Parametres!$K$3:$N$14,4,0)="X","O","") | AL3: =+IF(VLOOKUP(AJ$6,Parametres!$K$3:$N$14,4,0)="X","U","") | AM3: =+IF(VLOOKUP(AM$6,Parametres!$K$3:$N$14,4,0)="X","X","") | AN3: =+IF(VLOOKUP(AM$6,Parametres!$K$3:$N$14,4,0)="X","O","") | AO3: =+IF(VLOOKUP(AM$6,Parametres!$K$3:$N$14,4,0)="X","U","")
B4: Budget 2022 | C4: Véhicules neufs
B6: Mois | C6: 2022 | F6: Janvier | I6: Février | L6: Mars | O6: Avril | R6: Mai | U6: Juin | X6: Juillet | AA6: Août | AD6: Septembre | AG6: Octobre | AJ6: Novembre | AM6: Décembre
C7: UNITE | D7: $P/UNITE | E7: $PROFITS | F7: UNITE | G7: $P/UNITE | H7: $PROFITS | I7: UNITE | J7: $P/UNITE | K7: $PROFITS | L7: UNITE | M7: $P/UNITE | N7: $PROFITS | O7: UNITE | P7: $P/UNITE | Q7: $PROFITS | R7: UNITE | S7: $P/UNITE | T7: $PROFITS | U7: UNITE | V7: $P/UNITE | W7: $PROFITS | X7: UNITE | Y7: $P/UNITE | Z7: $PROFITS | AA7: UNITE | AB7: $P/UNITE | AC7: $PROFITS | AD7: UNITE | AE7: $P/UNITE | AF7: $PROFITS | AG7: UNITE | AH7: $P/UNITE | AI7: $PROFITS | AJ7: UNITE | AK7: $P/UNITE | AL7: $PROFITS | AM7: UNITE | AN7: $P/UNITE | AO7: $PROFITS
A8: =+$C$4&B8 -> Véhicules neufsVentes nettes | B8: Ventes nettes | E8: =+SUM(H8,K8,N8,Q8,T8,W8,Z8,AC8,AF8,AI8,AL8,AO8) -> 32920311 | H8: 1528310.4 | K8: 1587458.9 | N8: 2936799 | Q8: 3254290.8 | T8: 3809901.5 | W8: 2936799 | Z8: 3373350.3 | AC8: 3254290.8 | AF8: 2857426.1 | AI8: 3055858.5 | AL8: 2738366.7 | AO8: 1587458.9
A9: =+$C$4&B9 -> Véhicules neufsAutos détail | B9: Autos détail | C9: =+SUM(F9,I9,L9,O9,R9,U9,X9,AA9,AD9,AG9,AJ9,AM9) -> 168 | D9: =IF(C9=0,0,E9/C9) -> 1450.6298 | E9: =+SUM(H9,K9,N9,Q9,T9,W9,Z9,AC9,AF9,AI9,AL9,AO9) -> 243705.8 | F9: 7.8939759 | G9: =IF(F9=0,0,H9/F9) -> 1450.6298 | H9: 11451.236 | I9: 8.0963855 | J9: =IF(I9=0,0,K9/I9) -> 1450.6298 | K9: 11744.858 | L9: 14.978313 | M9: =IF(L9=0,0,N9/L9) -> 1450.6298 | N9: 21727.987 | O9: 16.59759 | P9: =IF(O9=0,0,Q9/O9) -> 1450.6298 | Q9: 24076.959 | R9: 19.431325 | S9: =IF(R9=0,0,T9/R9) -> 1450.6298 | T9: 28187.659 | U9: 14.978313 | V9: =IF(U9=0,0,W9/U9) -> 1450.6298 | W9: 21727.987 | X9: 17.204819 | Y9: =IF(X9=0,0,Z9/X9) -> 1450.6298 | Z9: 24957.823 | AA9: 16.59759 | AB9: =IF(AA9=0,0,AC9/AA9) -> 1450.6298 | AC9: 24076.959 | AD9: 14.573494 | AE9: =IF(AD9=0,0,AF9/AD9) -> 1450.6298 | AF9: 21140.744 | AG9: 15.585542 | AH9: =IF(AG9=0,0,AI9/AG9) -> 1450.6298 | AI9: 22608.851 | AJ9: 13.966265 | AK9: =IF(AJ9=0,0,AL9/AJ9) -> 1450.6298 | AL9: 20259.88 | AM9: 8.0963855 | AN9: =IF(AM9=0,0,AO9/AM9) -> 1450.6298 | AO9: 11744.858
A10: =+$C$4&B10 -> Véhicules neufsCamions détail | B10: Camions détail | C10: =+SUM(F10,I10,L10,O10,R10,U10,X10,AA10,AD10,AG10,AJ10,AM10) -> 580 | D10: =IF(C10=0,0,E10/C10) -> 2081.8276 | E10: =+SUM(H10,K10,N10,Q10,T10,W10,Z10,AC10,AF10,AI10,AL10,AO10) -> 1207460 | F10: 27.253012 | G10: =IF(F10=0,0,H10/F10) -> 2081.8276 | H10: 56736.072 | I10: 27.951807 | J10: =IF(I10=0,0,K10/I10) -> 2081.8276 | K10: 58190.843 | L10: 51.710843 | M10: =IF(L10=0,0,N10/L10) -> 2081.8276 | N10: 107653.06 | O10: 57.301205 | P10: =IF(O10=0,0,Q10/O10) -> 2081.8276 | Q10: 119291.23 | R10: 67.084337 | S10: =IF(R10=0,0,T10/R10) -> 2081.8276 | T10: 139658.02 | U10: 51.710843 | V10: =IF(U10=0,0,W10/U10) -> 2081.8276 | W10: 107653.06 | X10: 59.39759 | Y10: =IF(X10=0,0,Z10/X10) -> 2081.8276 | Z10: 123655.54 | AA10: 57.301205 | AB10: =IF(AA10=0,0,AC10/AA10) -> 2081.8276 | AC10: 119291.23 | AD10: 50.313253 | AE10: =IF(AD10=0,0,AF10/AD10) -> 2081.8276 | AF10: 104743.52 | AG10: 53.807229 | AH10: =IF(AG10=0,0,AI10/AG10) -> 2081.8276 | AI10: 112017.37 | AJ10: 48.216867 | AK10: =IF(AJ10=0,0,AL10/AJ10) -> 2081.8276 | AL10: 100379.2 | AM10: 27.951807 | AN10: =IF(AM10=0,0,AO10/AM10) -> 2081.8276 | AO10: 58190.843
A11: =+$C$4&B11 -> Véhicules neufsSprinter | B11: Sprinter | C11: =+SUM(F11,I11,L11,O11,R11,U11,X11,AA11,AD11,AG11,AJ11,AM11) -> 0 | D11: =IF(C11=0,0,E11/C11) -> 0 | E11: =+SUM(H11,K11,N11,Q11,T11,W11,Z11,AC11,AF11,AI11,AL11,AO11) -> 0 | F11: 0 | G11: =IF(F11=0,0,H11/F11) -> 0 | H11: 0 | I11: 0 | J11: =IF(I11=0,0,K11/I11) -> 0 | K11: 0 | L11: 0 | M11: =IF(L11=0,0,N11/L11) -> 0 | N11: 0 | O11: 0 | P11: =IF(O11=0,0,Q11/O11) -> 0 | Q11: 0 | R11: 0 | S11: =IF(R11=0,0,T11/R11) -> 0 | T11: 0 | U11: 0 | V11: =IF(U11=0,0,W11/U11) -> 0 | W11: 0 | X11: 0 | Y11: =IF(X11=0,0,Z11/X11) -> 0 | Z11: 0 | AA11: 0 | AB11: =IF(AA11=0,0,AC11/AA11) -> 0 | AC11: 0 | AD11: 0 | AE11: =IF(AD11=0,0,AF11/AD11) -> 0 | AF11: 0 | AG11: 0 | AH11: =IF(AG11=0,0,AI11/AG11) -> 0 | AI11: 0 | AJ11: 0 | AK11: =IF(AJ11=0,0,AL11/AJ11) -> 0 | AL11: 0 | AM11: 0 | AN11: =IF(AM11=0,0,AO11/AM11) -> 0 | AO11: 0
A12: =+$C$4&B12 -> Véhicules neufsMoto détail | B12: Moto détail | C12: =+SUM(F12,I12,L12,O12,R12,U12,X12,AA12,AD12,AG12,AJ12,AM12) -> 0 | D12: =IF(C12=0,0,E12/C12) -> 0 | E12: =+SUM(H12,K12,N12,Q12,T12,W12,Z12,AC12,AF12,AI12,AL12,AO12) -> 0 | F12: 0 | G12: =IF(F12=0,0,H12/F12) -> 0 | H12: 0 | I12: 0 | J12: =IF(I12=0,0,K12/I12) -> 0 | K12: 0 | L12: 0 | M12: =IF(L12=0,0,N12/L12) -> 0 | N12: 0 | O12: 0 | P12: =IF(O12=0,0,Q12/O12) -> 0 | Q12: 0 | R12: 0 | S12: =IF(R12=0,0,T12/R12) -> 0 | T12: 0 | U12: 0 | V12: =IF(U12=0,0,W12/U12) -> 0 | W12: 0 | X12: 0 | Y12: =IF(X12=0,0,Z12/X12) -> 0 | Z12: 0 | AA12: 0 | AB12: =IF(AA12=0,0,AC12/AA12) -> 0 | AC12: 0 | AD12: 0 | AE12: =IF(AD12=0,0,AF12/AD12) -> 0 | AF12: 0 | AG12: 0 | AH12: =IF(AG12=0,0,AI12/AG12) -> 0 | AI12: 0 | AJ12: 0 | AK12: =IF(AJ12=0,0,AL12/AJ12) -> 0 | AL12: 0 | AM12: 0 | AN12: =IF(AM12=0,0,AO12/AM12) -> 0 | AO12: 0
A13: =+$C$4&B13 -> Véhicules neufs[...] | B13: [...] | C13: =+SUM(F13,I13,L13,O13,R13,U13,X13,AA13,AD13,AG13,AJ13,AM13) -> 0 | D13: =IF(C13=0,0,E13/C13) -> 0 | E13: =+SUM(H13,K13,N13,Q13,T13,W13,Z13,AC13,AF13,AI13,AL13,AO13) -> 0 | G13: =IF(F13=0,0,H13/F13) -> 0 | J13: =IF(I13=0,0,K13/I13) -> 0 | M13: =IF(L13=0,0,N13/L13) -> 0 | P13: =IF(O13=0,0,Q13/O13) -> 0 | S13: =IF(R13=0,0,T13/R13) -> 0 | V13: =IF(U13=0,0,W13/U13) -> 0 | Y13: =IF(X13=0,0,Z13/X13) -> 0 | AB13: =IF(AA13=0,0,AC13/AA13) -> 0 | AE13: =IF(AD13=0,0,AF13/AD13) -> 0 | AH13: =IF(AG13=0,0,AI13/AG13) -> 0 | AK13: =IF(AJ13=0,0,AL13/AJ13) -> 0 | AN13: =IF(AM13=0,0,AO13/AM13) -> 0
A14: =+$C$4&B14 -> Véhicules neufs[...] | B14: [...] | C14: =+SUM(F14,I14,L14,O14,R14,U14,X14,AA14,AD14,AG14,AJ14,AM14) -> 0 | D14: =IF(C14=0,0,E14/C14) -> 0 | E14: =+SUM(H14,K14,N14,Q14,T14,W14,Z14,AC14,AF14,AI14,AL14,AO14) -> 0 | G14: =IF(F14=0,0,H14/F14) -> 0 | J14: =IF(I14=0,0,K14/I14) -> 0 | M14: =IF(L14=0,0,N14/L14) -> 0 | P14: =IF(O14=0,0,Q14/O14) -> 0 | S14: =IF(R14=0,0,T14/R14) -> 0 | V14: =IF(U14=0,0,W14/U14) -> 0 | Y14: =IF(X14=0,0,Z14/X14) -> 0 | AB14: =IF(AA14=0,0,AC14/AA14) -> 0 | AE14: =IF(AD14=0,0,AF14/AD14) -> 0 | AH14: =IF(AG14=0,0,AI14/AG14) -> 0 | AK14: =IF(AJ14=0,0,AL14/AJ14) -> 0 | AN14: =IF(AM14=0,0,AO14/AM14) -> 0
A15: =+$C$4&B15 -> Véhicules neufs[...] | B15: [...] | C15: =+SUM(F15,I15,L15,O15,R15,U15,X15,AA15,AD15,AG15,AJ15,AM15) -> 0 | D15: =IF(C15=0,0,E15/C15) -> 0 | E15: =+SUM(H15,K15,N15,Q15,T15,W15,Z15,AC15,AF15,AI15,AL15,AO15) -> 0 | G15: =IF(F15=0,0,H15/F15) -> 0 | J15: =IF(I15=0,0,K15/I15) -> 0 | M15: =IF(L15=0,0,N15/L15) -> 0 | P15: =IF(O15=0,0,Q15/O15) -> 0 | S15: =IF(R15=0,0,T15/R15) -> 0 | V15: =IF(U15=0,0,W15/U15) -> 0 | Y15: =IF(X15=0,0,Z15/X15) -> 0 | AB15: =IF(AA15=0,0,AC15/AA15) -> 0 | AE15: =IF(AD15=0,0,AF15/AD15) -> 0 | AH15: =IF(AG15=0,0,AI15/AG15) -> 0 | AK15: =IF(AJ15=0,0,AL15/AJ15) -> 0 | AN15: =IF(AM15=0,0,AO15/AM15) -> 0
A16: =+$C$4&B16 -> Véhicules neufsTotal Neufs | B16: Total Neufs | C16: =+SUM(C9:C15) -> 748 | D16: =IF(C16<=0,0,E16/C16) -> 1940.0612 | E16: =+SUM(E9:E15) -> 1451165.8 | F16: =+SUM(F9:F15) -> 35.146988 | G16: =IF(F16<=0,0,H16/F16) -> 1940.0612 | H16: =+SUM(H9:H15) -> 68187.309 | I16: =+SUM(I9:I15) -> 36.048193 | J16: =IF(I16<=0,0,K16/I16) -> 1940.0612 | K16: =+SUM(K9:K15) -> 69935.701 | L16: =+SUM(L9:L15) -> 66.689157 | M16: =IF(L16<=0,0,N16/L16) -> 1940.0612 | N16: =+SUM(N9:N15) -> 129381.05 | O16: =+SUM(O9:O15) -> 73.898795 | P16: =IF(O16<=0,0,Q16/O16) -> 1940.0612 | Q16: =+SUM(Q9:Q15) -> 143368.19 | R16: =+SUM(R9:R15) -> 86.515663 | S16: =IF(R16<=0,0,T16/R16) -> 1940.0612 | T16: =+SUM(T9:T15) -> 167845.68 | U16: =+SUM(U9:U15) -> 66.689157 | V16: =IF(U16<=0,0,W16/U16) -> 1940.0612 | W16: =+SUM(W9:W15) -> 129381.05 | X16: =+SUM(X9:X15) -> 76.60241 | Y16: =IF(X16<=0,0,Z16/X16) -> 1940.0612 | Z16: =+SUM(Z9:Z15) -> 148613.37 | AA16: =+SUM(AA9:AA15) -> 73.898795 | AB16: =IF(AA16<=0,0,AC16/AA16) -> 1940.0612 | AC16: =+SUM(AC9:AC15) -> 143368.19 | AD16: =+SUM(AD9:AD15) -> 64.886747 | AE16: =IF(AD16<=0,0,AF16/AD16) -> 1940.0612 | AF16: =+SUM(AF9:AF15) -> 125884.26 | AG16: =+SUM(AG9:AG15) -> 69.392771 | AH16: =IF(AG16<=0,0,AI16/AG16) -> 1940.0612 | AI16: =+SUM(AI9:AI15) -> 134626.22 | AJ16: =+SUM(AJ9:AJ15) -> 62.183133 | AK16: =IF(AJ16<=0,0,AL16/AJ16) -> 1940.0612 | AL16: =+SUM(AL9:AL15) -> 120639.08 | AM16: =+SUM(AM9:AM15) -> 36.048193 | AN16: =IF(AM16<=0,0,AO16/AM16) -> 1940.0612 | AO16: =+SUM(AO9:AO15) -> 69935.701
A17: =+$C$4&B17 -> Véhicules neufs
A18: =+$C$4&B18 -> Véhicules neufsEx-Démos et courtoisies | B18: Ex-Démos et courtoisies | C18: =+SUM(F18,I18,L18,O18,R18,U18,X18,AA18,AD18,AG18,AJ18,AM18) -> 70 | D18: =IF(C18=0,0,E18/C18) -> 1386.1016 | E18: =+SUM(H18,K18,N18,Q18,T18,W18,Z18,AC18,AF18,AI18,AL18,AO18) -> 97027.113 | F18: 3.2891566 | G18: =IF(F18=0,0,H18/F18) -> 1386.1016 | H18: 4559.1053 | I18: 3.373494 | J18: =IF(I18=0,0,K18/I18) -> 1386.1016 | K18: 4676.0055 | L18: 6.2409639 | M18: =IF(L18=0,0,N18/L18) -> 1386.1016 | N18: 8650.6101 | O18: 6.9156627 | P18: =IF(O18=0,0,Q18/O18) -> 1386.1016 | Q18: 9585.8112 | R18: 8.0963855 | S18: =IF(R18=0,0,T18/R18) -> 1386.1016 | T18: 11222.413 | U18: 6.2409639 | V18: =IF(U18=0,0,W18/U18) -> 1386.1016 | W18: 8650.6101 | X18: 7.1686747 | Y18: =IF(X18=0,0,Z18/X18) -> 1386.1016 | Z18: 9936.5116 | AA18: 6.9156627 | AB18: =IF(AA18=0,0,AC18/AA18) -> 1386.1016 | AC18: 9585.8112 | AD18: 6.0722892 | AE18: =IF(AD18=0,0,AF18/AD18) -> 1386.1016 | AF18: 8416.8098 | AG18: 6.4939759 | AH18: =IF(AG18=0,0,AI18/AG18) -> 1386.1016 | AI18: 9001.3105 | AJ18: 5.8192771 | AK18: =IF(AJ18=0,0,AL18/AJ18) -> 1386.1016 | AL18: 8066.1094 | AM18: 3.373494 | AN18: =IF(AM18=0,0,AO18/AM18) -> 1386.1016 | AO18: 4676.0055
A19: =+$C$4&B19 -> Véhicules neufs
A20: =+$C$4&B20 -> Véhicules neufsFlottes | B20: Flottes | C20: =+SUM(F20,I20,L20,O20,R20,U20,X20,AA20,AD20,AG20,AJ20,AM20) -> 12 | D20: =IF(C20=0,0,E20/C20) -> 1938.8732 | E20: =+SUM(H20,K20,N20,Q20,T20,W20,Z20,AC20,AF20,AI20,AL20,AO20) -> 23266.478 | F20: 0 | G20: =IF(F20=0,0,H20/F20) -> 0 | H20: 0 | I20: 0.6068268 | J20: =IF(I20=0,0,K20/I20) -> 1938.8732 | K20: 1176.5602 | L20: 1.1226296 | M20: =IF(L20=0,0,N20/L20) -> 1938.8732 | N20: 2176.6364 | O20: 1.2439949 | P20: =IF(O20=0,0,Q20/O20) -> 1938.8732 | Q20: 2411.9484 | R20: 1.4563843 | S20: =IF(R20=0,0,T20/R20) -> 1938.8732 | T20: 2823.7445 | U20: 1.1226296 | V20: =IF(U20=0,0,W20/U20) -> 1938.8732 | W20: 2176.6364 | X20: 1.289507 | Y20: =IF(X20=0,0,Z20/X20) -> 1938.8732 | Z20: 2500.1904 | AA20: 1.2439949 | AB20: =IF(AA20=0,0,AC20/AA20) -> 1938.8732 | AC20: 2411.9484 | AD20: 1.0922882 | AE20: =IF(AD20=0,0,AF20/AD20) -> 1938.8732 | AF20: 2117.8084 | AG20: 1.1681416 | AH20: =IF(AG20=0,0,AI20/AG20) -> 1938.8732 | AI20: 2264.8784 | AJ20: 1.0467762 | AK20: =IF(AJ20=0,0,AL20/AJ20) -> 1938.8732 | AL20: 2029.5663 | AM20: 0.6068268 | AN20: =IF(AM20=0,0,AO20/AM20) -> 1938.8732 | AO20: 1176.5602
A21: =+$C$4&B21 -> Véhicules neufs
A22: =+$C$4&B22 -> Véhicules neufsRachat bail | B22: Rachat bail | E22: =+SUM(H22,K22,N22,Q22,T22,W22,Z22,AC22,AF22,AI22,AL22,AO22) -> 70133.658 | H22: 3506.6829 | K22: 3506.6829 | N22: 8416.039 | Q22: 8416.039 | T22: 8416.039 | W22: 8416.039 | Z22: 7013.3658 | AC22: 4909.3561 | AF22: 4909.3561 | AI22: 4208.0195 | AL22: 4208.0195 | AO22: 4208.0195
A23: =+$C$4&B23 -> Véhicules neufs
A24: =+$C$4&B24 -> Véhicules neufsRev. Finances | B24: Rev. Finances | D24: =IF(C16=0,0,E24/(C16+C18)) -> 29.923763 | E24: =+SUM(H24,K24,N24,Q24,T24,W24,Z24,AC24,AF24,AI24,AL24,AO24) -> 24477.638 | G24: =IF(F16=0,0,H24/(F16+F18)) -> 29.923763 | H24: 1150.1541 | J24: =IF(I16=0,0,K24/(I16+I18)) -> 29.923763 | K24: 1179.6452 | M24: =IF(L16=0,0,N24/(L16+L18)) -> 29.923763 | N24: 2182.3436 | P24: =IF(O16=0,0,Q24/(O16+O18)) -> 29.923763 | Q24: 2418.2727 | S24: =IF(R16=0,0,T24/(R16+R18)) -> 29.923763 | T24: 2831.1485 | V24: =IF(U16=0,0,W24/(U16+U18)) -> 29.923763 | W24: 2182.3436 | Y24: =IF(X16=0,0,Z24/(X16+X18)) -> 29.923763 | Z24: 2506.7461 | AB24: =IF(AA16=0,0,AC24/(AA16+AA18)) -> 29.923763 | AC24: 2418.2727 | AE24: =IF(AD16=0,0,AF24/(AD16+AD18)) -> 29.923763 | AF24: 2123.3614 | AH24: =IF(AG16=0,0,AI24/(AG16+AG18)) -> 29.923763 | AI24: 2270.817 | AK24: =IF(AJ16=0,0,AL24/(AJ16+AJ18)) -> 29.923763 | AL24: 2034.888 | AN24: =IF(AM16=0,0,AO24/(AM16+AM18)) -> 29.923763 | AO24: 1179.6452
A25: =+$C$4&B25 -> Véhicules neufsRev. Protections | B25: Rev. Protections | D25: =IF(C16=0,0,E25/(C16+C18)) -> 800.26939 | E25: =+SUM(H25,K25,N25,Q25,T25,W25,Z25,AC25,AF25,AI25,AL25,AO25) -> 654620.36 | G25: =IF(F16=0,0,H25/(F16+F18)) -> 800.26939 | H25: 30759.27 | J25: =IF(I16=0,0,K25/(I16+I18)) -> 800.26939 | K25: 31547.969 | M25: =IF(L16=0,0,N25/(L16+L18)) -> 800.26939 | N25: 58363.743 | P25: =IF(O16=0,0,Q25/(O16+O18)) -> 800.26939 | Q25: 64673.337 | S25: =IF(R16=0,0,T25/(R16+R18)) -> 800.26939 | T25: 75715.126 | V25: =IF(U16=0,0,W25/(U16+U18)) -> 800.26939 | W25: 58363.743 | Y25: =IF(X16=0,0,Z25/(X16+X18)) -> 800.26939 | Z25: 67039.434 | AB25: =IF(AA16=0,0,AC25/(AA16+AA18)) -> 800.26939 | AC25: 64673.337 | AE25: =IF(AD16=0,0,AF25/(AD16+AD18)) -> 800.26939 | AF25: 56786.344 | AH25: =IF(AG16=0,0,AI25/(AG16+AG18)) -> 800.26939 | AI25: 60729.841 | AK25: =IF(AJ16=0,0,AL25/(AJ16+AJ18)) -> 800.26939 | AL25: 54420.247 | AN25: =IF(AM16=0,0,AO25/(AM16+AM18)) -> 800.26939 | AO25: 31547.969
A26: =+$C$4&B26 -> Véhicules neufsRev. Autres | B26: Rev. Autres | D26: =IF(C16=0,0,E26/(C16+C18)) -> 19.806849 | E26: =+SUM(H26,K26,N26,Q26,T26,W26,Z26,AC26,AF26,AI26,AL26,AO26) -> 16202.003 | G26: =IF(F16=0,0,H26/(F16+F18)) -> 19.806849 | H26: 761.29892 | J26: =IF(I16=0,0,K26/(I16+I18)) -> 19.806849 | K26: 780.8194 | M26: =IF(L16=0,0,N26/(L16+L18)) -> 19.806849 | N26: 1444.5159 | P26: =IF(O16=0,0,Q26/(O16+O18)) -> 19.806849 | Q26: 1600.6798 | S26: =IF(R16=0,0,T26/(R16+R18)) -> 19.806849 | T26: 1873.9666 | V26: =IF(U16=0,0,W26/(U16+U18)) -> 19.806849 | W26: 1444.5159 | Y26: =IF(X16=0,0,Z26/(X16+X18)) -> 19.806849 | Z26: 1659.2412 | AB26: =IF(AA16=0,0,AC26/(AA16+AA18)) -> 19.806849 | AC26: 1600.6798 | AE26: =IF(AD16=0,0,AF26/(AD16+AD18)) -> 19.806849 | AF26: 1405.4749 | AH26: =IF(AG16=0,0,AI26/(AG16+AG18)) -> 19.806849 | AI26: 1503.0774 | AK26: =IF(AJ16=0,0,AL26/(AJ16+AJ18)) -> 19.806849 | AL26: 1346.9135 | AN26: =IF(AM16=0,0,AO26/(AM16+AM18)) -> 19.806849 | AO26: 780.8194
A27: =+$C$4&B27 -> Véhicules neufsTotal F&I | B27: Total F&I | C27: =+C18+C16 -> 818 | D27: =IF(C27<=0,0,E27/C27) -> 850 | E27: =E24+E25+E26 -> 695300 | F27: =+F18+F16 -> 38.436145 | G27: =IF(F27<=0,0,H27/F27) -> 850 | H27: =H24+H25+H26 -> 32670.723 | I27: =+I18+I16 -> 39.421687 | J27: =IF(I27<=0,0,K27/I27) -> 850 | K27: =K24+K25+K26 -> 33508.434 | L27: =+L18+L16 -> 72.93012 | M27: =IF(L27<=0,0,N27/L27) -> 850 | N27: =N24+N25+N26 -> 61990.602 | O27: =+O18+O16 -> 80.814458 | P27: =IF(O27<=0,0,Q27/O27) -> 850 | Q27: =Q24+Q25+Q26 -> 68692.289 | R27: =+R18+R16 -> 94.612048 | S27: =IF(R27<=0,0,T27/R27) -> 850 | T27: =T24+T25+T26 -> 80420.241 | U27: =+U18+U16 -> 72.93012 | V27: =IF(U27<=0,0,W27/U27) -> 850 | W27: =W24+W25+W26 -> 61990.602 | X27: =+X18+X16 -> 83.771084 | Y27: =IF(X27<=0,0,Z27/X27) -> 850 | Z27: =Z24+Z25+Z26 -> 71205.422 | AA27: =+AA18+AA16 -> 80.814458 | AB27: =IF(AA27<=0,0,AC27/AA27) -> 850 | AC27: =AC24+AC25+AC26 -> 68692.289 | AD27: =+AD18+AD16 -> 70.959036 | AE27: =IF(AD27<=0,0,AF27/AD27) -> 850 | AF27: =AF24+AF25+AF26 -> 60315.181 | AG27: =+AG18+AG16 -> 75.886747 | AH27: =IF(AG27<=0,0,AI27/AG27) -> 850 | AI27: =AI24+AI25+AI26 -> 64503.735 | AJ27: =+AJ18+AJ16 -> 68.00241 | AK27: =IF(AJ27<=0,0,AL27/AJ27) -> 850 | AL27: =AL24+AL25+AL26 -> 57802.048 | AM27: =+AM18+AM16 -> 39.421687 | AN27: =IF(AM27<=0,0,AO27/AM27) -> 850 | AO27: =AO24+AO25+AO26 -> 33508.434
A28: =+$C$4&B28 -> Véhicules neufs
A29: =+$C$4&B29 -> Véhicules neufs
A30: =+$C$4&B30 -> Véhicules neufsTotal Dépt. Neufs | B30: Total Dépt. Neufs | C30: =+C16+C18+C20 -> 830 | D30: =IF(C30<=0,0,E30/C30) -> 2815.5338 | E30: =E16+E20+E27+E22+E18 -> 2336893 | F30: =+F16+F18+F20 -> 38.436145 | G30: =IF(F30<=0,0,H30/F30) -> 2833.8904 | H30: =H16+H20+H27+H22+H18 -> 108923.82 | I30: =+I16+I18+I20 -> 40.028514 | J30: =IF(I30<=0,0,K30/I30) -> 2818.0758 | K30: =K16+K20+K27+K22+K18 -> 112803.38 | L30: =+L16+L18+L20 -> 74.05275 | M30: =IF(L30<=0,0,N30/L30) -> 2844.1204 | N30: =N16+N20+N27+N22+N18 -> 210614.94 | O30: =+O16+O18+O20 -> 82.058453 | P30: =IF(O30<=0,0,Q30/O30) -> 2833.0326 | Q30: =Q16+Q20+Q27+Q22+Q18 -> 232474.28 | R30: =+R16+R18+R20 -> 96.068433 | S30: =IF(R30<=0,0,T30/R30) -> 2818.0758 | T30: =T16+T20+T27+T22+T18 -> 270728.12 | U30: =+U16+U18+U20 -> 74.05275 | V30: =IF(U30<=0,0,W30/U30) -> 2844.1204 | W30: =W16+W20+W27+W22+W18 -> 210614.94 | X30: =+X16+X18+X20 -> 85.060591 | Y30: =IF(X30<=0,0,Z30/X30) -> 2812.9225 | Z30: =Z16+Z20+Z27+Z22+Z18 -> 239268.85 | AA30: =+AA16+AA18+AA20 -> 82.058453 | AB30: =IF(AA30<=0,0,AC30/AA30) -> 2790.2987 | AC30: =AC16+AC20+AC27+AC22+AC18 -> 228967.59 | AD30: =+AD16+AD18+AD20 -> 72.051324 | AE30: =IF(AD30<=0,0,AF30/AD30) -> 2798.6081 | AF30: =AF16+AF20+AF27+AF22+AF18 -> 201643.42 | AG30: =+AG16+AG18+AG20 -> 77.054889 | AH30: =IF(AG30<=0,0,AI30/AG30) -> 2785.0818 | AI30: =AI16+AI20+AI27+AI22+AI18 -> 214604.17 | AJ30: =+AJ16+AJ18+AJ20 -> 69.049186 | AK30: =IF(AJ30<=0,0,AL30/AJ30) -> 2791.4135 | AL30: =AL16+AL20+AL27+AL22+AL18 -> 192744.83 | AM30: =+AM16+AM18+AM20 -> 40.028514 | AN30: =IF(AM30<=0,0,AO30/AM30) -> 2835.5967 | AO30: =AO16+AO20+AO27+AO22+AO18 -> 113504.72
A31: =+$C$4&B31 -> Véhicules neufs
A32: =+$C$4&B32 -> Véhicules neufs
A33: =+$C$4&B33 -> Véhicules neufsDEPENSES | B33: DEPENSES
A34: =+$C$4&B34 -> Véhicules neufsComm. vendeurs | B34: Comm. vendeurs | C34: =E34/(E16+E18) -> 0.33115355 | D34: =IF(E34=0,0,E34/C$27) -> 626.75987 | E34: =+SUM(H34,K34,N34,Q34,T34,W34,Z34,AC34,AF34,AI34,AL34,AO34) -> 512689.57 | F34: =H34/(H16+H18) -> 0.37878062 | G34: =IF(H34=0,0,H34/F$27) -> 716.90156 | H34: 27554.932 | I34: =K34/(K16+K18) -> 0.37507774 | J34: =IF(K34=0,0,K34/I$27) -> 709.89328 | K34: 27985.19 | L34: =N34/(N16+N18) -> 0.32918247 | M34: =IF(N34=0,0,N34/L$27) -> 623.02931 | N34: 45437.602 | O34: =Q34/(Q16+Q18) -> 0.31966893 | P34: =IF(Q34=0,0,Q34/O$27) -> 605.02343 | Q34: 48894.64 | R34: =T34/(T16+T18) -> 0.31286677 | S34: =IF(T34=0,0,T34/R$27) -> 592.14929 | T34: 56024.457 | U34: =W34/(W16+W18) -> 0.32744374 | V34: =IF(W34=0,0,W34/U$27) -> 619.73848 | W34: 45197.602 | X34: =Z34/(Z16+Z18) -> 0.31769832 | Y34: =IF(Z34=0,0,Z34/X$27) -> 601.29375 | Z34: 50371.03 | AA34: =AC34/(AC16+AC18) -> 0.32280712 | AB34: =IF(AC34=0,0,AC34/AA$27) -> 610.96296 | AC34: 49374.64 | AD34: =AF34/(AF16+AF18) -> 0.32921065 | AE34: =IF(AF34=0,0,AF34/AD$27) -> 623.08263 | AF34: 44213.343 | AG34: =AI34/(AI16+AI18) -> 0.3232945 | AH34: =IF(AI34=0,0,AI34/AG$27) -> 611.88539 | AI34: 46433.992 | AJ34: =AL34/(AL16+AL18) -> 0.33205306 | AK34: =IF(AL34=0,0,AL34/AJ$27) -> 628.46234 | AL34: 42736.954 | AM34: =AO34/(AO16+AO18) -> 0.38151105 | AN34: =IF(AO34=0,0,AO34/AM$27) -> 722.06932 | AO34: 28465.19
A35: =+$C$4&B35 -> Véhicules neufsComm. F&I | B35: Comm. F&I | C35: =E35/E27 -> 0.3 | D35: =IF(E35=0,0,E35/C$27) -> 255 | E35: =+SUM(H35,K35,N35,Q35,T35,W35,Z35,AC35,AF35,AI35,AL35,AO35) -> 208590 | F35: =H35/H27 -> 0.3 | G35: =IF(H35=0,0,H35/F$27) -> 255 | H35: 9801.2169 | I35: =K35/K27 -> 0.3 | J35: =IF(K35=0,0,K35/I$27) -> 255 | K35: 10052.53 | L35: =N35/N27 -> 0.3 | M35: =IF(N35=0,0,N35/L$27) -> 255 | N35: 18597.181 | O35: =Q35/Q27 -> 0.3 | P35: =IF(Q35=0,0,Q35/O$27) -> 255 | Q35: 20607.687 | R35: =T35/T27 -> 0.3 | S35: =IF(T35=0,0,T35/R$27) -> 255 | T35: 24126.072 | U35: =W35/W27 -> 0.3 | V35: =IF(W35=0,0,W35/U$27) -> 255 | W35: 18597.181 | X35: =Z35/Z27 -> 0.3 | Y35: =IF(Z35=0,0,Z35/X$27) -> 255 | Z35: 21361.627 | AA35: =AC35/AC27 -> 0.3 | AB35: =IF(AC35=0,0,AC35/AA$27) -> 255 | AC35: 20607.687 | AD35: =AF35/AF27 -> 0.3 | AE35: =IF(AF35=0,0,AF35/AD$27) -> 255 | AF35: 18094.554 | AG35: =AI35/AI27 -> 0.3 | AH35: =IF(AI35=0,0,AI35/AG$27) -> 255 | AI35: 19351.12 | AJ35: =AL35/AL27 -> 0.3 | AK35: =IF(AL35=0,0,AL35/AJ$27) -> 255 | AL35: 17340.614 | AM35: =AO35/AO27 -> 0.3 | AN35: =IF(AO35=0,0,AO35/AM$27) -> 255 | AO35: 10052.53
A36: =+$C$4&B36 -> Véhicules neufsFrais de livraison | B36: Frais de livraison | D36: =IF(E36=0,0,E36/C$27) -> 167.8493 | E36: =+SUM(H36,K36,N36,Q36,T36,W36,Z36,AC36,AF36,AI36,AL36,AO36) -> 137300.73 | G36: =IF(H36=0,0,H36/F$27) -> 167.8493 | H36: 6451.48 | J36: =IF(K36=0,0,K36/I$27) -> 167.8493 | K36: 6616.9026 | M36: =IF(N36=0,0,N36/L$27) -> 167.8493 | N36: 12241.27 | P36: =IF(Q36=0,0,Q36/O$27) -> 167.8493 | Q36: 13564.65 | S36: =IF(T36=0,0,T36/R$27) -> 167.8493 | T36: 15880.566 | V36: =IF(W36=0,0,W36/U$27) -> 167.8493 | W36: 12241.27 | Y36: =IF(Z36=0,0,Z36/X$27) -> 167.8493 | Z36: 14060.918 | AB36: =IF(AC36=0,0,AC36/AA$27) -> 167.8493 | AC36: 13564.65 | AE36: =IF(AF36=0,0,AF36/AD$27) -> 167.8493 | AF36: 11910.425 | AH36: =IF(AI36=0,0,AI36/AG$27) -> 167.8493 | AI36: 12737.538 | AK36: =IF(AL36=0,0,AL36/AJ$27) -> 167.8493 | AL36: 11414.157 | AN36: =IF(AO36=0,0,AO36/AM$27) -> 167.8493 | AO36: 6616.9026
A37: =+$C$4&B37 -> Véhicules neufsService gratuit 1 | B37: Service gratuit 1 | D37: =IF(E37=0,0,E37/C$27) -> 7.3548076 | E37: =+SUM(H37,K37,N37,Q37,T37,W37,Z37,AC37,AF37,AI37,AL37,AO37) -> 6016.2326 | G37: =IF(H37=0,0,H37/F$27) -> 7.3548076 | H37: 282.69045 | J37: =IF(K37=0,0,K37/I$27) -> 7.3548076 | K37: 289.93892 | M37: =IF(N37=0,0,N37/L$27) -> 7.3548076 | N37: 536.38701 | P37: =IF(Q37=0,0,Q37/O$27) -> 7.3548076 | Q37: 594.37479 | S37: =IF(T37=0,0,T37/R$27) -> 7.3548076 | T37: 695.85341 | V37: =IF(W37=0,0,W37/U$27) -> 7.3548076 | W37: 536.38701 | Y37: =IF(Z37=0,0,Z37/X$27) -> 7.3548076 | Z37: 616.12021 | AB37: =IF(AC37=0,0,AC37/AA$27) -> 7.3548076 | AC37: 594.37479 | AE37: =IF(AF37=0,0,AF37/AD$27) -> 7.3548076 | AF37: 521.89006 | AH37: =IF(AI37=0,0,AI37/AG$27) -> 7.3548076 | AI37: 558.13243 | AK37: =IF(AL37=0,0,AL37/AJ$27) -> 7.3548076 | AL37: 500.14464 | AN37: =IF(AO37=0,0,AO37/AM$27) -> 7.3548076 | AO37: 289.93892
A38: =+$C$4&B38 -> Véhicules neufsEntretien stock | B38: Entretien stock | D38: =IF(E38=0,0,E38/C$27) -> 17.733118 | E38: =+SUM(H38,K38,N38,Q38,T38,W38,Z38,AC38,AF38,AI38,AL38,AO38) -> 14505.691 | G38: =IF(H38=0,0,H38/F$27) -> 17.733118 | H38: 681.5927 | J38: =IF(K38=0,0,K38/I$27) -> 17.733118 | K38: 699.06943 | M38: =IF(N38=0,0,N38/L$27) -> 17.733118 | N38: 1293.2784 | P38: =IF(Q38=0,0,Q38/O$27) -> 17.733118 | Q38: 1433.0923 | S38: =IF(T38=0,0,T38/R$27) -> 17.733118 | T38: 1677.7666 | V38: =IF(W38=0,0,W38/U$27) -> 17.733118 | W38: 1293.2784 | Y38: =IF(Z38=0,0,Z38/X$27) -> 17.733118 | Z38: 1485.5225 | AB38: =IF(AC38=0,0,AC38/AA$27) -> 17.733118 | AC38: 1433.0923 | AE38: =IF(AF38=0,0,AF38/AD$27) -> 17.733118 | AF38: 1258.325 | AH38: =IF(AI38=0,0,AI38/AG$27) -> 17.733118 | AI38: 1345.7087 | AK38: =IF(AL38=0,0,AL38/AJ$27) -> 17.733118 | AL38: 1205.8948 | AN38: =IF(AO38=0,0,AO38/AM$27) -> 17.733118 | AO38: 699.06943
A39: =+$C$4&B39 -> Véhicules neufsPublicité 1 | B39: Publicité 1 | D39: =IF(E39=0,0,E39/C$27) -> 195.93765 | E39: =+SUM(H39,K39,N39,Q39,T39,W39,Z39,AC39,AF39,AI39,AL39,AO39) -> 160277 | G39: =IF(H39=0,0,H39/F$27) -> 195.93765 | H39: 7531.088 | J39: =IF(K39=0,0,K39/I$27) -> 195.93765 | K39: 7724.1928 | M39: =IF(N39=0,0,N39/L$27) -> 195.93765 | N39: 14289.757 | P39: =IF(Q39=0,0,Q39/O$27) -> 195.93765 | Q39: 15834.595 | S39: =IF(T39=0,0,T39/R$27) -> 195.93765 | T39: 18538.063 | V39: =IF(W39=0,0,W39/U$27) -> 195.93765 | W39: 14289.757 | Y39: =IF(Z39=0,0,Z39/X$27) -> 195.93765 | Z39: 16413.91 | AB39: =IF(AC39=0,0,AC39/AA$27) -> 195.93765 | AC39: 15834.595 | AE39: =IF(AF39=0,0,AF39/AD$27) -> 195.93765 | AF39: 13903.547 | AH39: =IF(AI39=0,0,AI39/AG$27) -> 195.93765 | AI39: 14869.071 | AK39: =IF(AL39=0,0,AL39/AJ$27) -> 195.93765 | AL39: 13324.233 | AN39: =IF(AO39=0,0,AO39/AM$27) -> 195.93765 | AO39: 7724.1928
A40: =+$C$4&B40 -> Véhicules neufsIntérêt de gros | B40: Intérêt de gros | D40: =IF(E40=0,0,E40/C$27) -> 102.42004 | E40: =+SUM(H40,K40,N40,Q40,T40,W40,Z40,AC40,AF40,AI40,AL40,AO40) -> 83779.589 | G40: =IF(H40=0,0,H40/F$27) -> 146.62809 | H40: 5635.8184 | J40: =IF(K40=0,0,K40/I$27) -> 162.72861 | K40: 6415.0362 | M40: =IF(N40=0,0,N40/L$27) -> 100.885 | N40: 7357.5552 | P40: =IF(Q40=0,0,Q40/O$27) -> 101.02946 | Q40: 8164.6412 | S40: =IF(T40=0,0,T40/R$27) -> 83.856314 | T40: 7933.8176 | V40: =IF(W40=0,0,W40/U$27) -> 95.743292 | W40: 6982.5698 | Y40: =IF(Z40=0,0,Z40/X$27) -> 86.224826 | Z40: 7223.1472 | AB40: =IF(AC40=0,0,AC40/AA$27) -> 96.0289 | AC40: 7760.5235 | AE40: =IF(AF40=0,0,AF40/AD$27) -> 117.38963 | AF40: 8329.8552 | AH40: =IF(AI40=0,0,AI40/AG$27) -> 97.587388 | AI40: 7405.5894 | AK40: =IF(AL40=0,0,AL40/AJ$27) -> 79.550134 | AL40: 5409.6008 | AN40: =IF(AO40=0,0,AO40/AM$27) -> 130.92881 | AO40: 5161.4344
A41: =+$C$4&B41 -> Véhicules neufs[...] | B41: [...] | D41: =IF(E41=0,0,E41/C$27) -> 0 | E41: =+SUM(H41,K41,N41,Q41,T41,W41,Z41,AC41,AF41,AI41,AL41,AO41) -> 0 | G41: =IF(H41=0,0,H41/F$27) -> 0 | J41: =IF(K41=0,0,K41/I$27) -> 0 | M41: =IF(N41=0,0,N41/L$27) -> 0 | P41: =IF(Q41=0,0,Q41/O$27) -> 0 | S41: =IF(T41=0,0,T41/R$27) -> 0 | V41: =IF(W41=0,0,W41/U$27) -> 0 | Y41: =IF(Z41=0,0,Z41/X$27) -> 0 | AB41: =IF(AC41=0,0,AC41/AA$27) -> 0 | AE41: =IF(AF41=0,0,AF41/AD$27) -> 0 | AH41: =IF(AI41=0,0,AI41/AG$27) -> 0 | AK41: =IF(AL41=0,0,AL41/AJ$27) -> 0 | AN41: =IF(AO41=0,0,AO41/AM$27) -> 0
A42: =+$C$4&B42 -> Véhicules neufs[...] | B42: [...] | D42: =IF(E42=0,0,E42/C$27) -> 0 | E42: =+SUM(H42,K42,N42,Q42,T42,W42,Z42,AC42,AF42,AI42,AL42,AO42) -> 0 | G42: =IF(H42=0,0,H42/F$27) -> 0 | J42: =IF(K42=0,0,K42/I$27) -> 0 | M42: =IF(N42=0,0,N42/L$27) -> 0 | P42: =IF(Q42=0,0,Q42/O$27) -> 0 | S42: =IF(T42=0,0,T42/R$27) -> 0 | V42: =IF(W42=0,0,W42/U$27) -> 0 | Y42: =IF(Z42=0,0,Z42/X$27) -> 0 | AB42: =IF(AC42=0,0,AC42/AA$27) -> 0 | AE42: =IF(AF42=0,0,AF42/AD$27) -> 0 | AH42: =IF(AI42=0,0,AI42/AG$27) -> 0 | AK42: =IF(AL42=0,0,AL42/AJ$27) -> 0 | AN42: =IF(AO42=0,0,AO42/AM$27) -> 0
A43: =+$C$4&B43 -> Véhicules neufs[...] | B43: [...] | D43: =IF(E43=0,0,E43/C$27) -> 0 | E43: =+SUM(H43,K43,N43,Q43,T43,W43,Z43,AC43,AF43,AI43,AL43,AO43) -> 0 | G43: =IF(H43=0,0,H43/F$27) -> 0 | J43: =IF(K43=0,0,K43/I$27) -> 0 | M43: =IF(N43=0,0,N43/L$27) -> 0 | P43: =IF(Q43=0,0,Q43/O$27) -> 0 | S43: =IF(T43=0,0,T43/R$27) -> 0 | V43: =IF(W43=0,0,W43/U$27) -> 0 | Y43: =IF(Z43=0,0,Z43/X$27) -> 0 | AB43: =IF(AC43=0,0,AC43/AA$27) -> 0 | AE43: =IF(AF43=0,0,AF43/AD$27) -> 0 | AH43: =IF(AI43=0,0,AI43/AG$27) -> 0 | AK43: =IF(AL43=0,0,AL43/AJ$27) -> 0 | AN43: =IF(AO43=0,0,AO43/AM$27) -> 0
A44: =+$C$4&B44 -> Véhicules neufsTOTAL VARIABLES | B44: TOTAL VARIABLES | C44: % brut | D44: =IFERROR(E44/E$30,0) -> 0.48062055 | E44: =SUM(E34:E43) -> 1123158.8 | F44: % brut | G44: =IFERROR(H44/H$30,0) -> 0.53192055 | H44: =SUM(H34:H43) -> 57938.819 | I44: % brut | J44: =IFERROR(K44/K$30,0) -> 0.529974 | K44: =SUM(K34:K43) -> 59782.86 | L44: % brut | M44: =IFERROR(N44/N$30,0) -> 0.47362752 | N44: =SUM(N34:N43) -> 99753.03 | O44: % brut | P44: =IFERROR(Q44/Q$30,0) -> 0.46927206 | Q44: =SUM(Q34:Q43) -> 109093.68 | R44: % brut | S44: =IFERROR(T44/T$30,0) -> 0.46126201 | T44: =SUM(T34:T43) -> 124876.6 | U44: % brut | V44: =IFERROR(W44/W$30,0) -> 0.47070757 | W44: =SUM(W34:W43) -> 99138.045 | X44: % brut | Y44: =IFERROR(Z44/Z$30,0) -> 0.46613787 | Z44: =SUM(Z34:Z43) -> 111532.27 | AA44: % brut | AB44: =IFERROR(AC44/AC$30,0) -> 0.47679046 | AC44: =SUM(AC34:AC43) -> 109169.56 | AD44: % brut | AE44: =IFERROR(AF44/AF$30,0) -> 0.48715669 | AF44: =SUM(AF34:AF43) -> 98231.939 | AG44: % brut | AH44: =IFERROR(AI44/AI$30,0) -> 0.47856084 | AI44: =SUM(AI34:AI43) -> 102701.15 | AJ44: % brut | AK44: =IFERROR(AL44/AL$30,0) -> 0.47696013 | AL44: =SUM(AL34:AL43) -> 91931.598 | AM44: % brut | AN44: =IFERROR(AO44/AO$30,0) -> 0.51988374 | AO44: =SUM(AO34:AO43) -> 59009.259
A45: =+$C$4&B45 -> Véhicules neufsSalaires cadres | B45: Salaires cadres | E45: =+SUM(H45,K45,N45,Q45,T45,W45,Z45,AC45,AF45,AI45,AL45,AO45) -> 189054.05 | H45: 15359.234 | K45: 14832.207 | N45: 16413.288 | Q45: 15359.234 | T45: 15886.261 | W45: 15886.261 | Z45: 15886.261 | AC45: 15886.261 | AF45: 15886.261 | AI45: 15359.234 | AL45: 15886.261 | AO45: 16413.288
A46: =+$C$4&B46 -> Véhicules neufsSalaires commis | B46: Salaires commis | E46: =+SUM(H46,K46,N46,Q46,T46,W46,Z46,AC46,AF46,AI46,AL46,AO46) -> 116556.57 | H46: 9386.1061 | K46: 8950.1843 | N46: 10257.949 | Q46: 9386.1061 | T46: 9822.0278 | W46: 9822.0278 | Z46: 9822.0278 | AC46: 9822.0278 | AF46: 9822.0278 | AI46: 9386.1061 | AL46: 9822.0278 | AO46: 10257.949
A47: =+$C$4&B47 -> Véhicules neufsSalaires autres | B47: Salaires autres | E47: =+SUM(H47,K47,N47,Q47,T47,W47,Z47,AC47,AF47,AI47,AL47,AO47) -> 105840.27 | H47: 8515.8839 | K47: 8110.3656 | N47: 9326.9204 | Q47: 8515.8839 | T47: 8921.4022 | W47: 8921.4022 | Z47: 8921.4022 | AC47: 8921.4022 | AF47: 8921.4022 | AI47: 8515.8839 | AL47: 8921.4022 | AO47: 9326.9204
A48: =+$C$4&B48 -> Véhicules neufsSalaires spécialistes | B48: Salaires spécialistes | E48: =+SUM(H48,K48,N48,Q48,T48,W48,Z48,AC48,AF48,AI48,AL48,AO48) -> 0 | H48: 0 | K48: 0 | N48: 0 | Q48: 0 | T48: 0 | W48: 0 | Z48: 0 | AC48: 0 | AF48: 0 | AI48: 0 | AL48: 0 | AO48: 0
A49: =+$C$4&B49 -> Véhicules neufs[...] | B49: [...] | E49: =+SUM(H49,K49,N49,Q49,T49,W49,Z49,AC49,AF49,AI49,AL49,AO49) -> 0 | H49: 0 | K49: 0 | N49: 0 | Q49: 0 | T49: 0 | W49: 0 | Z49: 0 | AC49: 0 | AF49: 0 | AI49: 0 | AL49: 0 | AO49: 0
A50: =+$C$4&B50 -> Véhicules neufs[...] | B50: [...] | E50: =+SUM(H50,K50,N50,Q50,T50,W50,Z50,AC50,AF50,AI50,AL50,AO50) -> 0 | H50: 0 | K50: 0 | N50: 0 | Q50: 0 | T50: 0 | W50: 0 | Z50: 0 | AC50: 0 | AF50: 0 | AI50: 0 | AL50: 0 | AO50: 0
A51: =+$C$4&B51 -> Véhicules neufs[...] | B51: [...] | E51: =+SUM(H51,K51,N51,Q51,T51,W51,Z51,AC51,AF51,AI51,AL51,AO51) -> 0 | H51: 0 | K51: 0 | N51: 0 | Q51: 0 | T51: 0 | W51: 0 | Z51: 0 | AC51: 0 | AF51: 0 | AI51: 0 | AL51: 0 | AO51: 0
A52: =+$C$4&B52 -> Véhicules neufsSalaires en absences | B52: Salaires en absences | E52: =+SUM(H52,K52,N52,Q52,T52,W52,Z52,AC52,AF52,AI52,AL52,AO52) -> 138467.75 | H52: 8813.5959 | K52: 8712.1065 | N52: 12210.248 | Q52: 12474.718 | T52: 13866.553 | W52: 12003.8 | Z52: 12907.843 | AC52: 12708.499 | AF52: 11834.459 | AI52: 12051.365 | AL52: 11580.448 | AO52: 9304.1141
A53: =+$C$4&B53 -> Véhicules neufsDéduction à la source | B53: Déduction à la source | E53: =+SUM(H53,K53,N53,Q53,T53,W53,Z53,AC53,AF53,AI53,AL53,AO53) -> 124012.06 | H53: 7893.4786 | K53: 7802.5844 | N53: 10935.528 | Q53: 11172.389 | T53: 12418.92 | W53: 10750.634 | Z53: 11560.297 | AC53: 11381.763 | AF53: 10598.971 | AI53: 10793.233 | AL53: 10371.478 | AO53: 8332.7879
A54: =+$C$4&B54 -> Véhicules neufsBénéfices marginaux | B54: Bénéfices marginaux | E54: =+SUM(H54,K54,N54,Q54,T54,W54,Z54,AC54,AF54,AI54,AL54,AO54) -> 98480.168 | H54: 6268.3506 | K54: 6196.1699 | N54: 8684.096 | Q54: 8872.1911 | T54: 9862.0834 | W54: 8537.268 | Z54: 9180.2357 | AC54: 9038.4591 | AF54: 8416.8302 | AI54: 8571.0967 | AL54: 8236.1736 | AO54: 6617.2139
A55: =+$C$4&B55 -> Véhicules neufsCsst | B55: Csst | E55: =+SUM(H55,K55,N55,Q55,T55,W55,Z55,AC55,AF55,AI55,AL55,AO55) -> 40121.55 | H55: 2553.7725 | K55: 2524.3655 | N55: 3537.965 | Q55: 3614.5964 | T55: 4017.8858 | W55: 3478.1462 | Z55: 3740.096 | AC55: 3682.3352 | AF55: 3429.079 | AI55: 3491.9283 | AL55: 3355.4781 | AO55: 2695.902
A56: =+$C$4&B56 -> Véhicules neufs[...] | B56: [...] | E56: =+SUM(H56,K56,N56,Q56,T56,W56,Z56,AC56,AF56,AI56,AL56,AO56) -> 0
A57: =+$C$4&B57 -> Véhicules neufsTOTAL PERSONNEL | B57: TOTAL PERSONNEL | C57: % brut | D57: =IFERROR(E57/E$30,0) -> 0.34769774 | E57: =+SUM(E45:E56) -> 812532.42 | F57: % brut | G57: =IFERROR(H57/H$30,0) -> 0.53973889 | H57: =+SUM(H45:H56) -> 58790.421 | I57: % brut | J57: =IFERROR(K57/K$30,0) -> 0.50643856 | K57: =+SUM(K45:K56) -> 57127.983 | L57: % brut | M57: =IFERROR(N57/N$30,0) -> 0.33884584 | N57: =+SUM(N45:N56) -> 71365.995 | O57: % brut | P57: =IFERROR(Q57/Q$30,0) -> 0.29850665 | Q57: =+SUM(Q45:Q56) -> 69395.118 | R57: % brut | S57: =IFERROR(T57/T$30,0) -> 0.27627397 | T57: =+SUM(T45:T56) -> 74795.133 | U57: % brut | V57: =IFERROR(W57/W$30,0) -> 0.32950911 | W57: =+SUM(W45:W56) -> 69399.539 | X57: % brut | Y57: =IFERROR(Z57/Z$30,0) -> 0.30099263 | Z57: =+SUM(Z45:Z56) -> 72018.163 | AA57: % brut | AB57: =IFERROR(AC57/AC$30,0) -> 0.31201248 | AC57: =+SUM(AC45:AC56) -> 71440.747 | AD57: % brut | AE57: =IFERROR(AF57/AF$30,0) -> 0.34173707 | AF57: =+SUM(AF45:AF56) -> 68909.031 | AG57: % brut | AH57: =IFERROR(AI57/AI$30,0) -> 0.31764922 | AI57: =+SUM(AI45:AI56) -> 68168.847 | AJ57: % brut | AK57: =IFERROR(AL57/AL$30,0) -> 0.353697 | AL57: =+SUM(AL45:AL56) -> 68173.268 | AM57: % brut | AN57: =IFERROR(AO57/AO$30,0) -> 0.55458642 | AO57: =+SUM(AO45:AO56) -> 62948.176
A58: =+$C$4&B58 -> Véhicules neufsPublicité 2 | B58: Publicité 2 | E58: =+SUM(H58,K58,N58,Q58,T58,W58,Z58,AC58,AF58,AI58,AL58,AO58) -> 0 | H58: 0 | K58: 0 | N58: 0 | Q58: 0 | T58: 0 | W58: 0 | Z58: 0 | AC58: 0 | AF58: 0 | AI58: 0 | AL58: 0 | AO58: 0
A59: =+$C$4&B59 -> Véhicules neufsService gratuit 2 | B59: Service gratuit 2 | E59: =+SUM(H59,K59,N59,Q59,T59,W59,Z59,AC59,AF59,AI59,AL59,AO59) -> 0 | H59: 0 | K59: 0 | N59: 0 | Q59: 0 | T59: 0 | W59: 0 | Z59: 0 | AC59: 0 | AF59: 0 | AI59: 0 | AL59: 0 | AO59: 0
A60: =+$C$4&B60 -> Véhicules neufsFrais véhicules de cie | B60: Frais véhicules de cie | E60: =+SUM(H60,K60,N60,Q60,T60,W60,Z60,AC60,AF60,AI60,AL60,AO60) -> 87875.28 | H60: 7322.94 | K60: 7322.94 | N60: 7322.94 | Q60: 7322.94 | T60: 7322.94 | W60: 7322.94 | Z60: 7322.94 | AC60: 7322.94 | AF60: 7322.94 | AI60: 7322.94 | AL60: 7322.94 | AO60: 7322.94
A61: =+$C$4&B61 -> Véhicules neufsInformatique | B61: Informatique | E61: =+SUM(H61,K61,N61,Q61,T61,W61,Z61,AC61,AF61,AI61,AL61,AO61) -> 82010.345 | H61: 6834.1886 | K61: 6834.1886 | N61: 6834.1886 | Q61: 6834.1886 | T61: 6834.1988 | W61: 6834.1988 | Z61: 6834.1988 | AC61: 6834.1988 | AF61: 6834.1988 | AI61: 6834.1988 | AL61: 6834.1988 | AO61: 6834.1988
A62: =+$C$4&B62 -> Véhicules neufsFrais de déplacement | B62: Frais de déplacement | E62: =+SUM(H62,K62,N62,Q62,T62,W62,Z62,AC62,AF62,AI62,AL62,AO62) -> 9505.7016 | H62: 792.1418 | K62: 792.1418 | N62: 792.1418 | Q62: 792.1418 | T62: 792.1418 | W62: 792.1418 | Z62: 792.1418 | AC62: 792.1418 | AF62: 792.1418 | AI62: 792.1418 | AL62: 792.1418 | AO62: 792.1418
A63: =+$C$4&B63 -> Véhicules neufsServices extérieurs | B63: Services extérieurs | E63: =+SUM(H63,K63,N63,Q63,T63,W63,Z63,AC63,AF63,AI63,AL63,AO63) -> 79819.781 | H63: 6763.7218 | K63: 6916.8098 | N63: 6604.1602 | Q63: 6627.0466 | T63: 6518.7074 | W63: 6830.797 | Z63: 6729.517 | AC63: 6447.7026 | AF63: 6468.477 | AI63: 6207.101 | AL63: 7079.4402 | AO63: 6626.301
A64: =+$C$4&B64 -> Véhicules neufsFournitures autres | B64: Fournitures autres | E64: =+SUM(H64,K64,N64,Q64,T64,W64,Z64,AC64,AF64,AI64,AL64,AO64) -> 989.00443 | H64: 50.536579 | K64: 52.169296 | N64: 91.038463 | Q64: 96.216577 | T64: 107.68716 | W64: 92.790378 | Z64: 99.362812 | AC64: 94.464662 | AF64: 81.641328 | AI64: 89.80491 | AL64: 79.371051 | AO64: 53.921211
A65: =+$C$4&B65 -> Véhicules neufsUniformes | B65: Uniformes | E65: =+SUM(H65,K65,N65,Q65,T65,W65,Z65,AC65,AF65,AI65,AL65,AO65) -> 525.53095 | H65: 26.85381 | K65: 27.721392 | N65: 48.375446 | Q65: 51.12696 | T65: 57.222126 | W65: 49.306367 | Z65: 52.798786 | AC65: 50.196038 | AF65: 43.382055 | AI65: 47.719968 | AL65: 42.17569 | AO65: 28.652314
A66: =+$C$4&B66 -> Véhicules neufsPapeterie | B66: Papeterie | E66: =+SUM(H66,K66,N66,Q66,T66,W66,Z66,AC66,AF66,AI66,AL66,AO66) -> 7834.3718 | H66: 652.86432 | K66: 652.86432 | N66: 652.86432 | Q66: 652.86432 | T66: 652.86432 | W66: 652.86432 | Z66: 652.86432 | AC66: 652.86432 | AF66: 652.86432 | AI66: 652.86432 | AL66: 652.86432 | AO66: 652.86432
A67: =+$C$4&B67 -> Véhicules neufsTéléphone | B67: Téléphone | E67: =+SUM(H67,K67,N67,Q67,T67,W67,Z67,AC67,AF67,AI67,AL67,AO67) -> 3617.5743 | H67: 301.46453 | K67: 301.46453 | N67: 301.46453 | Q67: 301.46453 | T67: 301.46453 | W67: 301.46453 | Z67: 301.46453 | AC67: 301.46453 | AF67: 301.46453 | AI67: 301.46453 | AL67: 301.46453 | AO67: 301.46453
A68: =+$C$4&B68 -> Véhicules neufsFrais postaux | B68: Frais postaux | E68: =+SUM(H68,K68,N68,Q68,T68,W68,Z68,AC68,AF68,AI68,AL68,AO68) -> 1931.0049 | H68: 160.91707 | K68: 160.91707 | N68: 160.91707 | Q68: 160.91707 | T68: 160.91707 | W68: 160.91707 | Z68: 160.91707 | AC68: 160.91707 | AF68: 160.91707 | AI68: 160.91707 | AL68: 160.91707 | AO68: 160.91707
A69: =+$C$4&B69 -> Véhicules neufsDivers | B69: Divers | E69: =+SUM(H69,K69,N69,Q69,T69,W69,Z69,AC69,AF69,AI69,AL69,AO69) -> 9314.8031 | H69: 776.23359 | K69: 776.23359 | N69: 776.23359 | Q69: 776.23359 | T69: 776.23359 | W69: 776.23359 | Z69: 776.23359 | AC69: 776.23359 | AF69: 776.23359 | AI69: 776.23359 | AL69: 776.23359 | AO69: 776.23359
... A71: =+$C$4&B71 -> Véhicules neufsFrais bancaires | B71: Frais bancaires | E71: =+SUM(H71,K71,N71,Q71,T71,W71,Z71,AC71,AF71,AI71,AL71,AO71) -> 27969.359 | H71: 1683.2373 | K71: 1432.4514 | N71: 1679.4267 | Q71: 3359.0496 | T71: 3066.8322 | W71: 1979.113 | Z71: 1857.7872 | AC71: 2062.1401 | AF71: 1527.324 | AI71: 2986.7567 | AL71: 4410.6483 | AO71: 1924.593
A72: =+$C$4&B72 -> Véhicules neufs[...] | B72: [...] | E72: =+SUM(H72,K72,N72,Q72,T72,W72,Z72,AC72,AF72,AI72,AL72,AO72) -> 0
A73: =+$C$4&B73 -> Véhicules neufs[...] | B73: [...] | E73: =+SUM(H73,K73,N73,Q73,T73,W73,Z73,AC73,AF73,AI73,AL73,AO73) -> 0
A74: =+$C$4&B74 -> Véhicules neufs[...] | B74: [...] | E74: =+SUM(H74,K74,N74,Q74,T74,W74,Z74,AC74,AF74,AI74,AL74,AO74) -> 0
A75: =+$C$4&B75 -> Véhicules neufsTOTAL SEMI-FIXES | B75: TOTAL SEMI-FIXES | C75: % brut | D75: =IFERROR(E75/E$30,0) -> 0.13917275 | E75: =+SUM(E58:E74) -> 325231.83 | F75: % brut | G75: =IFERROR(H75/H$30,0) -> 0.24345782 | H75: =+SUM(H58:H74) -> 26518.356 | I75: % brut | J75: =IFERROR(K75/K$30,0) -> 0.23424083 | K75: =+SUM(K58:K74) -> 26423.158 | L75: % brut | M75: =IFERROR(N75/N$30,0) -> 0.12542799 | N75: =+SUM(N58:N74) -> 26417.007 | O75: % brut | P75: =IFERROR(Q75/Q$30,0) -> 0.12099165 | Q75: =+SUM(Q58:Q74) -> 28127.446 | R75: % brut | S75: =IFERROR(T75/T$30,0) -> 0.10248091 | T75: =+SUM(T58:T74) -> 27744.465 | U75: % brut | V75: =IFERROR(W75/W$30,0) -> 0.12793975 | W75: =+SUM(W58:W74) -> 26946.023 | X75: % brut | Y75: =IFERROR(Z75/Z$30,0) -> 0.11172989 | Z75: =+SUM(Z58:Z74) -> 26733.482 | AA75: % brut | AB75: =IFERROR(AC75/AC$30,0) -> 0.11638555 | AC75: =+SUM(AC58:AC74) -> 26648.52 | AD75: % brut | AE75: =IFERROR(AF75/AF$30,0) -> 0.12951001 | AF75: =+SUM(AF58:AF74) -> 26114.841 | AG75: % brut | AH75: =IFERROR(AI75/AI$30,0) -> 0.1273293 | AI75: =+SUM(AI58:AI74) -> 27325.399 | AJ75: % brut | AK75: =IFERROR(AL75/AL$30,0) -> 0.15360024 | AL75: =+SUM(AL58:AL74) -> 29605.652 | AM75: % brut | AN75: =IFERROR(AO75/AO$30,0) -> 0.23459363 | AO75: =+SUM(AO58:AO74) -> 26627.484
A76: =+$C$4&B76 -> Véhicules neufs
A77: =+$C$4&B77 -> Véhicules neufsTOTAL DES DÉPENSES | B77: TOTAL DES DÉPENSES | C77: % brut | D77: =IFERROR(E77/E$30,0) -> 0.96749103 | E77: =E44+E57+E75 -> 2260923.1 | F77: % brut | G77: =IFERROR(H77/H$30,0) -> 1.3151173 | H77: =H44+H57+H75 -> 143247.6 | I77: % brut | J77: =IFERROR(K77/K$30,0) -> 1.2706534 | K77: =K44+K57+K75 -> 143334 | L77: % brut | M77: =IFERROR(N77/N$30,0) -> 0.93790135 | N77: =N44+N57+N75 -> 197536.03 | O77: % brut | P77: =IFERROR(Q77/Q$30,0) -> 0.88877036 | Q77: =Q44+Q57+Q75 -> 206616.24 | R77: % brut | S77: =IFERROR(T77/T$30,0) -> 0.84001689 | T77: =T44+T57+T75 -> 227416.19 | U77: % brut | V77: =IFERROR(W77/W$30,0) -> 0.92815643 | W77: =W44+W57+W75 -> 195483.61 | X77: % brut | Y77: =IFERROR(Z77/Z$30,0) -> 0.87886039 | Z77: =Z44+Z57+Z75 -> 210283.92 | AA77: % brut | AB77: =IFERROR(AC77/AC$30,0) -> 0.90518849 | AC77: =AC44+AC57+AC75 -> 207258.83 | AD77: % brut | AE77: =IFERROR(AF77/AF$30,0) -> 0.95840377 | AF77: =AF44+AF57+AF75 -> 193255.81 | AG77: % brut | AH77: =IFERROR(AI77/AI$30,0) -> 0.92353936 | AI77: =AI44+AI57+AI75 -> 198195.4 | AJ77: % brut | AK77: =IFERROR(AL77/AL$30,0) -> 0.98425737 | AL77: =AL44+AL57+AL75 -> 189710.52 | AM77: % brut | AN77: =IFERROR(AO77/AO$30,0) -> 1.3090638 | AO77: =AO44+AO57+AO75 -> 148584.92
A78: =+$C$4&B78 -> Véhicules neufsProgramme neuf 1 | B78: Programme neuf 1 | E78: =+SUM(H78,K78,N78,Q78,T78,W78,Z78,AC78,AF78,AI78,AL78,AO78) -> 66483 | H78: 0 | K78: 0 | N78: 12255.3 | Q78: 0 | T78: 0 | W78: 20185.2 | Z78: 0 | AC78: 0 | AF78: 19143.9 | AI78: 0 | AL78: 0 | AO78: 14898.6
A79: =+$C$4&B79 -> Véhicules neufsProgramme neuf 2 | B79: Programme neuf 2 | E79: =+SUM(H79,K79,N79,Q79,T79,W79,Z79,AC79,AF79,AI79,AL79,AO79) -> 0 | H79: 0 | K79: 0 | N79: 0 | Q79: 0 | T79: 0 | W79: 0 | Z79: 0 | AC79: 0 | AF79: 0 | AI79: 0 | AL79: 0 | AO79: 0
A80: =+$C$4&B80 -> Véhicules neufsProgramme neuf 3 | B80: Programme neuf 3 | E80: =+SUM(H80,K80,N80,Q80,T80,W80,Z80,AC80,AF80,AI80,AL80,AO80) -> 0 | H80: 0 | K80: 0 | N80: 0 | Q80: 0 | T80: 0 | W80: 0 | Z80: 0 | AC80: 0 | AF80: 0 | AI80: 0 | AL80: 0 | AO80: 0
A81: =+$C$4&B81 -> Véhicules neufsHoldbacks | B81: Holdbacks | E81: =+SUM(H81,K81,N81,Q81,T81,W81,Z81,AC81,AF81,AI81,AL81,AO81) -> 868219.15 | H81: 40795.84 | K81: 41841.887 | N81: 77407.491 | Q81: 85775.868 | T81: 100420.53 | W81: 77407.491 | Z81: 88914.01 | AC81: 85775.868 | AF81: 75315.397 | AI81: 80545.632 | AL81: 72177.255 | AO81: 41841.887
A82: =+$C$4&B82 -> Véhicules neufs[...] | B82: [...] | E82: =+SUM(H82,K82,N82,Q82,T82,W82,Z82,AC82,AF82,AI82,AL82,AO82) -> 0 | H82: 0 | K82: 0 | N82: 0 | Q82: 0 | T82: 0 | W82: 0 | Z82: 0 | AC82: 0 | AF82: 0 | AI82: 0 | AL82: 0 | AO82: 0
A83: =+$C$4&B83 -> Véhicules neufs[...] | B83: [...] | E83: =+SUM(H83,K83,N83,Q83,T83,W83,Z83,AC83,AF83,AI83,AL83,AO83) -> 0 | H83: 0 | K83: 0 | N83: 0 | Q83: 0 | T83: 0 | W83: 0 | Z83: 0 | AC83: 0 | AF83: 0 | AI83: 0 | AL83: 0 | AO83: 0
A84: =+$C$4&B84 -> Véhicules neufs[...] | B84: [...] | E84: =+SUM(H84,K84,N84,Q84,T84,W84,Z84,AC84,AF84,AI84,AL84,AO84) -> 0 | H84: 0 | K84: 0 | N84: 0 | Q84: 0 | T84: 0 | W84: 0 | Z84: 0 | AC84: 0 | AF84: 0 | AI84: 0 | AL84: 0 | AO84: 0
A85: =+$C$4&B85 -> Véhicules neufsFrais administration | B85: Frais administration | E85: =+SUM(H85,K85,N85,Q85,T85,W85,Z85,AC85,AF85,AI85,AL85,AO85) -> 298053 | H85: 13802.42 | K85: 14374.239 | N85: 26592.343 | Q85: 29467.19 | T85: 34498.174 | W85: 26592.343 | Z85: 30545.258 | AC85: 29467.19 | AF85: 25873.631 | AI85: 27670.41 | AL85: 24795.563 | AO85: 14374.239
A86: =+$C$4&B86 -> Véhicules neufsAUTRES REVENUS | B86: AUTRES REVENUS | E86: =+SUM(E78:E85) -> 1232755.2 | H86: =+SUM(H78:H85) -> 54598.259 | K86: =+SUM(K78:K85) -> 56216.126 | N86: =+SUM(N78:N85) -> 116255.13 | Q86: =+SUM(Q78:Q85) -> 115243.06 | T86: =+SUM(T78:T85) -> 134918.7 | W86: =+SUM(W78:W85) -> 124185.03 | Z86: =+SUM(Z78:Z85) -> 119459.27 | AC86: =+SUM(AC78:AC85) -> 115243.06 | AF86: =+SUM(AF78:AF85) -> 120332.93 | AI86: =+SUM(AI78:AI85) -> 108216.04 | AL86: =+SUM(AL78:AL85) -> 96972.818 | AO86: =+SUM(AO78:AO85) -> 71114.726
A87: =+$C$4&B87 -> Véhicules neufs
A88: =+$C$4&B88 -> Véhicules neufsPROFIT DÉPARTEMENTAL | B88: PROFIT DÉPARTEMENTAL | E88: =E30-E77+E86 -> 1308725.1 | H88: =H30-H77+H86 -> 20274.484 | K88: =K30-K77+K86 -> 25685.508 | N88: =N30-N77+N86 -> 129334.04 | Q88: =Q30-Q77+Q86 -> 141101.09 | T88: =T30-T77+T86 -> 178230.63 | W88: =W30-W77+W86 -> 139316.36 | Z88: =Z30-Z77+Z86 -> 148444.2 | AC88: =AC30-AC77+AC86 -> 136951.82 | AF88: =AF30-AF77+AF86 -> 128720.53 | AI88: =AI30-AI77+AI86 -> 124624.81 | AL88: =AL30-AL77+AL86 -> 100007.13 | AO88: =AO30-AO77+AO86 -> 36034.528
B92: =B4 -> Budget 2022 | C92: Véhicules usagés
B94: Mois | C94: 2022 | F94: Janvier | I94: Février | L94: Mars | O94: Avril | R94: Mai | U94: Juin | X94: Juillet | AA94: Août | AD94: Septembre | AG94: Octobre | AJ94: Novembre | AM94: Décembre
C95: UNITE | D95: $P/UNITE | E95: $PROFITS | F95: UNITE | G95: $P/UNITE | H95: $PROFITS | I95: UNITE | J95: $P/UNITE | K95: $PROFITS | L95: UNITE | M95: $P/UNITE | N95: $PROFITS | O95: UNITE | P95: $P/UNITE | Q95: $PROFITS | R95: UNITE | S95: $P/UNITE | T95: $PROFITS | U95: UNITE | V95: $P/UNITE | W95: $PROFITS | X95: UNITE | Y95: $P/UNITE | Z95: $PROFITS | AA95: UNITE | AB95: $P/UNITE | AC95: $PROFITS | AD95: UNITE | AE95: $P/UNITE | AF95: $PROFITS | AG95: UNITE | AH95: $P/UNITE | AI95: $PROFITS | AJ95: UNITE | AK95: $P/UNITE | AL95: $PROFITS | AM95: UNITE | AN95: $P/UNITE | AO95: $PROFITS
A96: =+$C$92&B96 -> Véhicules usagésVentes nettes | B96: Ventes nettes | E96: =+SUM(H96,K96,N96,Q96,T96,W96,Z96,AC96,AF96,AI96,AL96,AO96) -> 14579073 | H96: 849266.38 | K96: 884652.48 | N96: 1415444 | Q96: 1380057.9 | T96: 1415444 | W96: 1486216.2 | Z96: 1415444 | AC96: 1309285.7 | AF96: 1096969.1 | AI96: 1273899.6 | AL96: 1096969.1 | AO96: 955424.68
A97: =+$C$92&B97 -> Véhicules usagésCertifié | B97: Certifié | C97: =+SUM(F97,I97,L97,O97,R97,U97,X97,AA97,AD97,AG97,AJ97,AM97) -> 445 | D97: =IF(C97=0,0,E97/C97) -> 1300 | E97: =+SUM(H97,K97,N97,Q97,T97,W97,Z97,AC97,AF97,AI97,AL97,AO97) -> 578500 | F97: 25.92233 | G97: =IF(F97=0,0,H97/F97) -> 1300 | H97: 33699.029 | I97: 27.002427 | J97: =IF(I97=0,0,K97/I97) -> 1300 | K97: 35103.155 | L97: 43.203883 | M97: =IF(L97=0,0,N97/L97) -> 1300 | N97: 56165.049 | O97: 42.123786 | P97: =IF(O97=0,0,Q97/O97) -> 1300 | Q97: 54760.922 | R97: 43.203883 | S97: =IF(R97=0,0,T97/R97) -> 1300 | T97: 56165.049 | U97: 45.364078 | V97: =IF(U97=0,0,W97/U97) -> 1300 | W97: 58973.301 | X97: 43.203883 | Y97: =IF(X97=0,0,Z97/X97) -> 1300 | Z97: 56165.049 | AA97: 39.963592 | AB97: =IF(AA97=0,0,AC97/AA97) -> 1300 | AC97: 51952.67 | AD97: 33.48301 | AE97: =IF(AD97=0,0,AF97/AD97) -> 1300 | AF97: 43527.913 | AG97: 38.883495 | AH97: =IF(AG97=0,0,AI97/AG97) -> 1300 | AI97: 50548.544 | AJ97: 33.48301 | AK97: =IF(AJ97=0,0,AL97/AJ97) -> 1300 | AL97: 43527.913 | AM97: 29.162621 | AN97: =IF(AM97=0,0,AO97/AM97) -> 1300 | AO97: 37911.408
A98: =+$C$92&B98 -> Véhicules usagésNon Certifié | B98: Non Certifié | C98: =+SUM(F98,I98,L98,O98,R98,U98,X98,AA98,AD98,AG98,AJ98,AM98) -> 25 | D98: =IF(C98=0,0,E98/C98) -> 900 | E98: =+SUM(H98,K98,N98,Q98,T98,W98,Z98,AC98,AF98,AI98,AL98,AO98) -> 22500 | F98: 1.4563107 | G98: =IF(F98=0,0,H98/F98) -> 900 | H98: 1310.6796 | I98: 1.5169903 | J98: =IF(I98=0,0,K98/I98) -> 900 | K98: 1365.2913 | L98: 2.4271845 | M98: =IF(L98=0,0,N98/L98) -> 900 | N98: 2184.466 | O98: 2.3665049 | P98: =IF(O98=0,0,Q98/O98) -> 900 | Q98: 2129.8544 | R98: 2.4271845 | S98: =IF(R98=0,0,T98/R98) -> 900 | T98: 2184.466 | U98: 2.5485437 | V98: =IF(U98=0,0,W98/U98) -> 900 | W98: 2293.6893 | X98: 2.4271845 | Y98: =IF(X98=0,0,Z98/X98) -> 900 | Z98: 2184.466 | AA98: 2.2451456 | AB98: =IF(AA98=0,0,AC98/AA98) -> 900 | AC98: 2020.6311 | AD98: 1.881068 | AE98: =IF(AD98=0,0,AF98/AD98) -> 900 | AF98: 1692.9612 | AG98: 2.184466 | AH98: =IF(AG98=0,0,AI98/AG98) -> 900 | AI98: 1966.0194 | AJ98: 1.881068 | AK98: =IF(AJ98=0,0,AL98/AJ98) -> 900 | AL98: 1692.9612 | AM98: 1.6383495 | AN98: =IF(AM98=0,0,AO98/AM98) -> 900 | AO98: 1474.5146
A99: =+$C$92&B99 -> Véhicules usagésTotal Usagés | B99: Total Usagés | C99: =+C97+C98 -> 470 | D99: =IF(C99<=0,0,E99/C99) -> 1278.7234 | E99: =+E97+E98 -> 601000 | F99: =+F97+F98 -> 27.378641 | G99: =IF(F99<=0,0,H99/F99) -> 1278.7234 | H99: =+H97+H98 -> 35009.709 | I99: =+I97+I98 -> 28.519417 | J99: =IF(I99<=0,0,K99/I99) -> 1278.7234 | K99: =+K97+K98 -> 36468.447 | L99: =+L97+L98 -> 45.631068 | M99: =IF(L99<=0,0,N99/L99) -> 1278.7234 | N99: =+N97+N98 -> 58349.515 | O99: =+O97+O98 -> 44.490291 | P99: =IF(O99<=0,0,Q99/O99) -> 1278.7234 | Q99: =+Q97+Q98 -> 56890.777 | R99: =+R97+R98 -> 45.631068 | S99: =IF(R99<=0,0,T99/R99) -> 1278.7234 | T99: =+T97+T98 -> 58349.515 | U99: =+U97+U98 -> 47.912621 | V99: =IF(U99<=0,0,W99/U99) -> 1278.7234 | W99: =+W97+W98 -> 61266.99 | X99: =+X97+X98 -> 45.631068 | Y99: =IF(X99<=0,0,Z99/X99) -> 1278.7234 | Z99: =+Z97+Z98 -> 58349.515 | AA99: =+AA97+AA98 -> 42.208738 | AB99: =IF(AA99<=0,0,AC99/AA99) -> 1278.7234 | AC99: =+AC97+AC98 -> 53973.301 | AD99: =+AD97+AD98 -> 35.364078 | AE99: =IF(AD99<=0,0,AF99/AD99) -> 1278.7234 | AF99: =+AF97+AF98 -> 45220.874 | AG99: =+AG97+AG98 -> 41.067961 | AH99: =IF(AG99<=0,0,AI99/AG99) -> 1278.7234 | AI99: =+AI97+AI98 -> 52514.563 | AJ99: =+AJ97+AJ98 -> 35.364078 | AK99: =IF(AJ99<=0,0,AL99/AJ99) -> 1278.7234 | AL99: =+AL97+AL98 -> 45220.874 | AM99: =+AM97+AM98 -> 30.800971 | AN99: =IF(AM99<=0,0,AO99/AM99) -> 1278.7234 | AO99: =+AO97+AO98 -> 39385.922
A100: =+$C$92&B100 -> Véhicules usagés
A101: =+$C$92&B101 -> Véhicules usagés | F101: 0 | H101: 0
A102: =+$C$92&B102 -> Véhicules usagésVentes au Gros | B102: Ventes au Gros | C102: =+SUM(F102,I102,L102,O102,R102,U102,X102,AA102,AD102,AG102,AJ102,AM102) -> 408.99067 | D102: =IF(C102=0,0,E102/C102) -> 212 | E102: =+SUM(H102,K102,N102,Q102,T102,W102,Z102,AC102,AF102,AI102,AL102,AO102) -> 86706.022 | F102: 23.824699 | G102: =IF(F102=0,0,H102/F102) -> 212 | H102: 5050.8362 | I102: 24.817395 | J102: =IF(I102=0,0,K102/I102) -> 212 | K102: 5261.2877 | L102: 39.707832 | M102: =IF(L102=0,0,N102/L102) -> 212 | N102: 8418.0604 | O102: 38.715136 | P102: =IF(O102=0,0,Q102/O102) -> 212 | Q102: 8207.6089 | R102: 39.707832 | S102: =IF(R102=0,0,T102/R102) -> 212 | T102: 8418.0604 | U102: 41.693224 | V102: =IF(U102=0,0,W102/U102) -> 212 | W102: 8838.9634 | X102: 39.707832 | Y102: =IF(X102=0,0,Z102/X102) -> 212 | Z102: 8418.0604 | AA102: 36.729745 | AB102: =IF(AA102=0,0,AC102/AA102) -> 212 | AC102: 7786.7059 | AD102: 30.77357 | AE102: =IF(AD102=0,0,AF102/AD102) -> 212 | AF102: 6523.9968 | AG102: 35.737049 | AH102: =IF(AG102=0,0,AI102/AG102) -> 212 | AI102: 7576.2544 | AJ102: 30.77357 | AK102: =IF(AJ102=0,0,AL102/AJ102) -> 212 | AL102: 6523.9968 | AM102: 26.802787 | AN102: =IF(AM102=0,0,AO102/AM102) -> 212 | AO102: 5682.1908
A103: =+$C$92&B103 -> Véhicules usagés
A104: =+$C$92&B104 -> Véhicules usagésRev. Finances | B104: Rev. Finances | D104: =IF(C99=0,0,E104/C99) -> 658.96091 | E104: =+SUM(H104,K104,N104,Q104,T104,W104,Z104,AC104,AF104,AI104,AL104,AO104) -> 309711.63 | G104: =IF(F99=0,0,H104/F99) -> 658.96091 | H104: 18041.454 | J104: =IF(I99=0,0,K104/I99) -> 658.96091 | K104: 18793.181 | M104: =IF(L99=0,0,N104/L99) -> 658.96091 | N104: 30069.09 | P104: =IF(O99=0,0,Q104/O99) -> 658.96091 | Q104: 29317.363 | S104: =IF(R99=0,0,T104/R99) -> 658.96091 | T104: 30069.09 | V104: =IF(U99=0,0,W104/U99) -> 658.96091 | W104: 31572.545 | Y104: =IF(X99=0,0,Z104/X99) -> 658.96091 | Z104: 30069.09 | AB104: =IF(AA99=0,0,AC104/AA99) -> 658.96091 | AC104: 27813.908 | AE104: =IF(AD99=0,0,AF104/AD99) -> 658.96091 | AF104: 23303.545 | AH104: =IF(AG99=0,0,AI104/AG99) -> 658.96091 | AI104: 27062.181 | AK104: =IF(AJ99=0,0,AL104/AJ99) -> 658.96091 | AL104: 23303.545 | AN104: =IF(AM99=0,0,AO104/AM99) -> 658.96091 | AO104: 20296.636
A105: =+$C$92&B105 -> Véhicules usagésRev. Protections | B105: Rev. Protections | D105: =IF(C99=0,0,E105/C99) -> 1161.8447 | E105: =+SUM(H105,K105,N105,Q105,T105,W105,Z105,AC105,AF105,AI105,AL105,AO105) -> 546067 | G105: =IF(F99=0,0,H105/F99) -> 1161.8447 | H105: 31809.728 | J105: =IF(I99=0,0,K105/I99) -> 1161.8447 | K105: 33135.133 | M105: =IF(L99=0,0,N105/L99) -> 1161.8447 | N105: 53016.214 | P105: =IF(O99=0,0,Q105/O99) -> 1161.8447 | Q105: 51690.808 | S105: =IF(R99=0,0,T105/R99) -> 1161.8447 | T105: 53016.214 | V105: =IF(U99=0,0,W105/U99) -> 1161.8447 | W105: 55667.024 | Y105: =IF(X99=0,0,Z105/X99) -> 1161.8447 | Z105: 53016.214 | AB105: =IF(AA99=0,0,AC105/AA99) -> 1161.8447 | AC105: 49039.998 | AE105: =IF(AD99=0,0,AF105/AD99) -> 1161.8447 | AF105: 41087.566 | AH105: =IF(AG99=0,0,AI105/AG99) -> 1161.8447 | AI105: 47714.592 | AK105: =IF(AJ99=0,0,AL105/AJ99) -> 1161.8447 | AL105: 41087.566 | AN105: =IF(AM99=0,0,AO105/AM99) -> 1161.8447 | AO105: 35785.944
A106: =+$C$92&B106 -> Véhicules usagésRev. Autres | B106: Rev. Autres | D106: =IF(C99=0,0,E106/C99) -> 32.953208 | E106: =+SUM(H106,K106,N106,Q106,T106,W106,Z106,AC106,AF106,AI106,AL106,AO106) -> 15488.008 | G106: =IF(F99=0,0,H106/F99) -> 32.953208 | H106: 902.21403 | J106: =IF(I99=0,0,K106/I99) -> 32.953208 | K106: 939.80628 | M106: =IF(L99=0,0,N106/L99) -> 32.953208 | N106: 1503.6901 | P106: =IF(O99=0,0,Q106/O99) -> 32.953208 | Q106: 1466.0978 | S106: =IF(R99=0,0,T106/R99) -> 32.953208 | T106: 1503.6901 | V106: =IF(U99=0,0,W106/U99) -> 32.953208 | W106: 1578.8746 | Y106: =IF(X99=0,0,Z106/X99) -> 32.953208 | Z106: 1503.6901 | AB106: =IF(AA99=0,0,AC106/AA99) -> 32.953208 | AC106: 1390.9133 | AE106: =IF(AD99=0,0,AF106/AD99) -> 32.953208 | AF106: 1165.3598 | AH106: =IF(AG99=0,0,AI106/AG99) -> 32.953208 | AI106: 1353.321 | AK106: =IF(AJ99=0,0,AL106/AJ99) -> 32.953208 | AL106: 1165.3598 | AN106: =IF(AM99=0,0,AO106/AM99) -> 32.953208 | AO106: 1014.9908
...

Sheet Budget révisé
B1: ="Budget 2022 Mensuel Révisé"&" "&Parametres!$B$1 -> Budget 2022 Mensuel Révisé Volks
B2: Mois | F2: =+IF(Parametres!$B$3=F$6,"X","") | G2: =+IF(Parametres!$B$3=F$6,"O","") | H2: =+IF(Parametres!$B$3=F$6,"U","") | I2: =+IF(Parametres!$B$3=I$6,"X","") | J2: =+IF(Parametres!$B$3=I$6,"O","") | K2: =+IF(Parametres!$B$3=I$6,"U","") | L2: =+IF(Parametres!$B$3=L$6,"X","") | M2: =+IF(Parametres!$B$3=L$6,"O","") | N2: =+IF(Parametres!$B$3=L$6,"U","") | O2: =+IF(Parametres!$B$3=O$6,"X","") | P2: =+IF(Parametres!$B$3=O$6,"O","") | Q2: =+IF(Parametres!$B$3=O$6,"U","") | R2: =+IF(Parametres!$B$3=R$6,"X","") -> X | S2: =+IF(Parametres!$B$3=R$6,"O","") -> O | T2: =+IF(Parametres!$B$3=R$6,"U","") -> U | U2: =+IF(Parametres!$B$3=U$6,"X","") | V2: =+IF(Parametres!$B$3=U$6,"O","") | W2: =+IF(Parametres!$B$3=U$6,"U","") | X2: =+IF(Parametres!$B$3=X$6,"X","") | Y2: =+IF(Parametres!$B$3=X$6,"O","") | Z2: =+IF(Parametres!$B$3=X$6,"U","") | AA2: =+IF(Parametres!$B$3=AA$6,"X","") | AB2: =+IF(Parametres!$B$3=AA$6,"O","") | AC2: =+IF(Parametres!$B$3=AA$6,"U","") | AD2: =+IF(Parametres!$B$3=AD$6,"X","") | AE2: =+IF(Parametres!$B$3=AD$6,"O","") | AF2: =+IF(Parametres!$B$3=AD$6,"U","") | AG2: =+IF(Parametres!$B$3=AG$6,"X","") | AH2: =+IF(Parametres!$B$3=AG$6,"O","") | AI2: =+IF(Parametres!$B$3=AG$6,"U","") | AJ2: =+IF(Parametres!$B$3=AJ$6,"X","") | AK2: =+IF(Parametres!$B$3=AJ$6,"O","") | AL2: =+IF(Parametres!$B$3=AJ$6,"U","") | AM2: =+IF(Parametres!$B$3=AM$6,"X","") | AN2: =+IF(Parametres!$B$3=AM$6,"O","") | AO2: =+IF(Parametres!$B$3=AM$6,"U","")
B3: YTD | F3: =+IF(VLOOKUP(F$6,Parametres!$K$3:$N$14,4,0)="X","X","") -> X | G3: =+IF(VLOOKUP(F$6,Parametres!$K$3:$N$14,4,0)="X","O","") -> O | H3: =+IF(VLOOKUP(F$6,Parametres!$K$3:$N$14,4,0)="X","U","") -> U | I3: =+IF(VLOOKUP(I$6,Parametres!$K$3:$N$14,4,0)="X","X","") -> X | J3: =+IF(VLOOKUP(I$6,Parametres!$K$3:$N$14,4,0)="X","O","") -> O | K3: =+IF(VLOOKUP(I$6,Parametres!$K$3:$N$14,4,0)="X","U","") -> U | L3: =+IF(VLOOKUP(L$6,Parametres!$K$3:$N$14,4,0)="X","X","") -> X | M3: =+IF(VLOOKUP(L$6,Parametres!$K$3:$N$14,4,0)="X","O","") -> O | N3: =+IF(VLOOKUP(L$6,Parametres!$K$3:$N$14,4,0)="X","U","") -> U | O3: =+IF(VLOOKUP(O$6,Parametres!$K$3:$N$14,4,0)="X","X","") -> X | P3: =+IF(VLOOKUP(O$6,Parametres!$K$3:$N$14,4,0)="X","O","") -> O | Q3: =+IF(VLOOKUP(O$6,Parametres!$K$3:$N$14,4,0)="X","U","") -> U | R3: =+IF(VLOOKUP(R$6,Parametres!$K$3:$N$14,4,0)="X","X","") -> X | S3: =+IF(VLOOKUP(R$6,Parametres!$K$3:$N$14,4,0)="X","O","") -> O | T3: =+IF(VLOOKUP(R$6,Parametres!$K$3:$N$14,4,0)="X","U","") -> U | U3: =+IF(VLOOKUP(U$6,Parametres!$K$3:$N$14,4,0)="X","X","") | V3: =+IF(VLOOKUP(U$6,Parametres!$K$3:$N$14,4,0)="X","O","") | W3: =+IF(VLOOKUP(U$6,Parametres!$K$3:$N$14,4,0)="X","U","") | X3: =+IF(VLOOKUP(X$6,Parametres!$K$3:$N$14,4,0)="X","X","") | Y3: =+IF(VLOOKUP(X$6,Parametres!$K$3:$N$14,4,0)="X","O","") | Z3: =+IF(VLOOKUP(X$6,Parametres!$K$3:$N$14,4,0)="X","U","") | AA3: =+IF(VLOOKUP(AA$6,Parametres!$K$3:$N$14,4,0)="X","X","") | AB3: =+IF(VLOOKUP(AA$6,Parametres!$K$3:$N$14,4,0)="X","O","") | AC3: =+IF(VLOOKUP(AA$6,Parametres!$K$3:$N$14,4,0)="X","U","") | AD3: =+IF(VLOOKUP(AD$6,Parametres!$K$3:$N$14,4,0)="X","X","") | AE3: =+IF(VLOOKUP(AD$6,Parametres!$K$3:$N$14,4,0)="X","O","") | AF3: =+IF(VLOOKUP(AD$6,Parametres!$K$3:$N$14,4,0)="X","U","") | AG3: =+IF(VLOOKUP(AG$6,Parametres!$K$3:$N$14,4,0)="X","X","") | AH3: =+IF(VLOOKUP(AG$6,Parametres!$K$3:$N$14,4,0)="X","O","") | AI3: =+IF(VLOOKUP(AG$6,Parametres!$K$3:$N$14,4,0)="X","U","") | AJ3: =+IF(VLOOKUP(AJ$6,Parametres!$K$3:$N$14,4,0)="X","X","") | AK3: =+IF(VLOOKUP(AJ$6,Parametres!$K$3:$N$14,4,0)="X","O","") | AL3: =+IF(VLOOKUP(AJ$6,Parametres!$K$3:$N$14,4,0)="X","U","") | AM3: =+IF(VLOOKUP(AM$6,Parametres!$K$3:$N$14,4,0)="X","X","") | AN3: =+IF(VLOOKUP(AM$6,Parametres!$K$3:$N$14,4,0)="X","O","") | AO3: =+IF(VLOOKUP(AM$6,Parametres!$K$3:$N$14,4,0)="X","U","")
B4: Budget 2022 | C4: Véhicules neufs
B6: Mois | C6: 2022 | F6: Janvier | I6: Février | L6: Mars | O6: Avril | R6: Mai | U6: Juin | X6: Juillet | AA6: Août | AD6: Septembre | AG6: Octobre | AJ6: Novembre | AM6: Décembre
C7: UNITE | D7: $P/UNITE | E7: $PROFITS | F7: UNITE | G7: $P/UNITE | H7: $PROFITS | I7: UNITE | J7: $P/UNITE | K7: $PROFITS | L7: UNITE | M7: $P/UNITE | N7: $PROFITS | O7: UNITE | P7: $P/UNITE | Q7: $PROFITS | R7: UNITE | S7: $P/UNITE | T7: $PROFITS | U7: UNITE | V7: $P/UNITE | W7: $PROFITS | X7: UNITE | Y7: $P/UNITE | Z7: $PROFITS | AA7: UNITE | AB7: $P/UNITE | AC7: $PROFITS | AD7: UNITE | AE7: $P/UNITE | AF7: $PROFITS | AG7: UNITE | AH7: $P/UNITE | AI7: $PROFITS | AJ7: UNITE | AK7: $P/UNITE | AL7: $PROFITS | AM7: UNITE | AN7: $P/UNITE | AO7: $PROFITS
A8: =+$C$4&B8 -> Véhicules neufsVentes nettes | B8: Ventes nettes | E8: =+SUM(H8,K8,N8,Q8,T8,W8,Z8,AC8,AF8,AI8,AL8,AO8) -> 32920311 | H8: 1528310.4 | K8: 1587458.9 | N8: 2936799 | Q8: 3254290.8 | T8: 3809901.5 | W8: 2936799 | Z8: 3373350.3 | AC8: 3254290.8 | AF8: 2857426.1 | AI8: 3055858.5 | AL8: 2738366.7 | AO8: 1587458.9
A9: =+$C$4&B9 -> Véhicules neufsAutos détail | B9: Autos détail | C9: =+SUM(F9,I9,L9,O9,R9,U9,X9,AA9,AD9,AG9,AJ9,AM9) -> 168 | D9: =IF(C9=0,0,E9/C9) -> 1450.6298 | E9: =+SUM(H9,K9,N9,Q9,T9,W9,Z9,AC9,AF9,AI9,AL9,AO9) -> 243705.8 | F9: 7.8939759 | G9: =IF(F9=0,0,H9/F9) -> 1450.6298 | H9: 11451.236 | I9: 8.0963855 | J9: =IF(I9=0,0,K9/I9) -> 1450.6298 | K9: 11744.858 | L9: 14.978313 | M9: =IF(L9=0,0,N9/L9) -> 1450.6298 | N9: 21727.987 | O9: 16.59759 | P9: =IF(O9=0,0,Q9/O9) -> 1450.6298 | Q9: 24076.959 | R9: 19.431325 | S9: =IF(R9=0,0,T9/R9) -> 1450.6298 | T9: 28187.659 | U9: 14.978313 | V9: =IF(U9=0,0,W9/U9) -> 1450.6298 | W9: 21727.987 | X9: 17.204819 | Y9: =IF(X9=0,0,Z9/X9) -> 1450.6298 | Z9: 24957.823 | AA9: 16.59759 | AB9: =IF(AA9=0,0,AC9/AA9) -> 1450.6298 | AC9: 24076.959 | AD9: 14.573494 | AE9: =IF(AD9=0,0,AF9/AD9) -> 1450.6298 | AF9: 21140.744 | AG9: 15.585542 | AH9: =IF(AG9=0,0,AI9/AG9) -> 1450.6298 | AI9: 22608.851 | AJ9: 13.966265 | AK9: =IF(AJ9=0,0,AL9/AJ9) -> 1450.6298 | AL9: 20259.88 | AM9: 8.0963855 | AN9: =IF(AM9=0,0,AO9/AM9) -> 1450.6298 | AO9: 11744.858
A10: =+$C$4&B10 -> Véhicules neufsCamions détail | B10: Camions détail | C10: =+SUM(F10,I10,L10,O10,R10,U10,X10,AA10,AD10,AG10,AJ10,AM10) -> 580 | D10: =IF(C10=0,0,E10/C10) -> 2081.8276 | E10: =+SUM(H10,K10,N10,Q10,T10,W10,Z10,AC10,AF10,AI10,AL10,AO10) -> 1207460 | F10: 27.253012 | G10: =IF(F10=0,0,H10/F10) -> 2081.8276 | H10: 56736.072 | I10: 27.951807 | J10: =IF(I10=0,0,K10/I10) -> 2081.8276 | K10: 58190.843 | L10: 51.710843 | M10: =IF(L10=0,0,N10/L10) -> 2081.8276 | N10: 107653.06 | O10: 57.301205 | P10: =IF(O10=0,0,Q10/O10) -> 2081.8276 | Q10: 119291.23 | R10: 67.084337 | S10: =IF(R10=0,0,T10/R10) -> 2081.8276 | T10: 139658.02 | U10: 51.710843 | V10: =IF(U10=0,0,W10/U10) -> 2081.8276 | W10: 107653.06 | X10: 59.39759 | Y10: =IF(X10=0,0,Z10/X10) -> 2081.8276 | Z10: 123655.54 | AA10: 57.301205 | AB10: =IF(AA10=0,0,AC10/AA10) -> 2081.8276 | AC10: 119291.23 | AD10: 50.313253 | AE10: =IF(AD10=0,0,AF10/AD10) -> 2081.8276 | AF10: 104743.52 | AG10: 53.807229 | AH10: =IF(AG10=0,0,AI10/AG10) -> 2081.8276 | AI10: 112017.37 | AJ10: 48.216867 | AK10: =IF(AJ10=0,0,AL10/AJ10) -> 2081.8276 | AL10: 100379.2 | AM10: 27.951807 | AN10: =IF(AM10=0,0,AO10/AM10) -> 2081.8276 | AO10: 58190.843
A11: =+$C$4&B11 -> Véhicules neufsSprinter | B11: Sprinter | C11: =+SUM(F11,I11,L11,O11,R11,U11,X11,AA11,AD11,AG11,AJ11,AM11) -> 0 | D11: =IF(C11=0,0,E11/C11) -> 0 | E11: =+SUM(H11,K11,N11,Q11,T11,W11,Z11,AC11,AF11,AI11,AL11,AO11) -> 0 | F11: 0 | G11: =IF(F11=0,0,H11/F11) -> 0 | H11: 0 | I11: 0 | J11: =IF(I11=0,0,K11/I11) -> 0 | K11: 0 | L11: 0 | M11: =IF(L11=0,0,N11/L11) -> 0 | N11: 0 | O11: 0 | P11: =IF(O11=0,0,Q11/O11) -> 0 | Q11: 0 | R11: 0 | S11: =IF(R11=0,0,T11/R11) -> 0 | T11: 0 | U11: 0 | V11: =IF(U11=0,0,W11/U11) -> 0 | W11: 0 | X11: 0 | Y11: =IF(X11=0,0,Z11/X11) -> 0 | Z11: 0 | AA11: 0 | AB11: =IF(AA11=0,0,AC11/AA11) -> 0 | AC11: 0 | AD11: 0 | AE11: =IF(AD11=0,0,AF11/AD11) -> 0 | AF11: 0 | AG11: 0 | AH11: =IF(AG11=0,0,AI11/AG11) -> 0 | AI11: 0 | AJ11: 0 | AK11: =IF(AJ11=0,0,AL11/AJ11) -> 0 | AL11: 0 | AM11: 0 | AN11: =IF(AM11=0,0,AO11/AM11) -> 0 | AO11: 0
A12: =+$C$4&B12 -> Véhicules neufsMoto détail | B12: Moto détail | C12: =+SUM(F12,I12,L12,O12,R12,U12,X12,AA12,AD12,AG12,AJ12,AM12) -> 0 | D12: =IF(C12=0,0,E12/C12) -> 0 | E12: =+SUM(H12,K12,N12,Q12,T12,W12,Z12,AC12,AF12,AI12,AL12,AO12) -> 0 | F12: 0 | G12: =IF(F12=0,0,H12/F12) -> 0 | H12: 0 | I12: 0 | J12: =IF(I12=0,0,K12/I12) -> 0 | K12: 0 | L12: 0 | M12: =IF(L12=0,0,N12/L12) -> 0 | N12: 0 | O12: 0 | P12: =IF(O12=0,0,Q12/O12) -> 0 | Q12: 0 | R12: 0 | S12: =IF(R12=0,0,T12/R12) -> 0 | T12: 0 | U12: 0 | V12: =IF(U12=0,0,W12/U12) -> 0 | W12: 0 | X12: 0 | Y12: =IF(X12=0,0,Z12/X12) -> 0 | Z12: 0 | AA12: 0 | AB12: =IF(AA12=0,0,AC12/AA12) -> 0 | AC12: 0 | AD12: 0 | AE12: =IF(AD12=0,0,AF12/AD12) -> 0 | AF12: 0 | AG12: 0 | AH12: =IF(AG12=0,0,AI12/AG12) -> 0 | AI12: 0 | AJ12: 0 | AK12: =IF(AJ12=0,0,AL12/AJ12) -> 0 | AL12: 0 | AM12: 0 | AN12: =IF(AM12=0,0,AO12/AM12) -> 0 | AO12: 0
A13: =+$C$4&B13 -> Véhicules neufs[...] | B13: [...] | C13: =+SUM(F13,I13,L13,O13,R13,U13,X13,AA13,AD13,AG13,AJ13,AM13) -> 0 | D13: =IF(C13=0,0,E13/C13) -> 0 | E13: =+SUM(H13,K13,N13,Q13,T13,W13,Z13,AC13,AF13,AI13,AL13,AO13) -> 0 | G13: =IF(F13=0,0,H13/F13) -> 0 | J13: =IF(I13=0,0,K13/I13) -> 0 | M13: =IF(L13=0,0,N13/L13) -> 0 | P13: =IF(O13=0,0,Q13/O13) -> 0 | S13: =IF(R13=0,0,T13/R13) -> 0 | V13: =IF(U13=0,0,W13/U13) -> 0 | Y13: =IF(X13=0,0,Z13/X13) -> 0 | AB13: =IF(AA13=0,0,AC13/AA13) -> 0 | AE13: =IF(AD13=0,0,AF13/AD13) -> 0 | AH13: =IF(AG13=0,0,AI13/AG13) -> 0 | AK13: =IF(AJ13=0,0,AL13/AJ13) -> 0 | AN13: =IF(AM13=0,0,AO13/AM13) -> 0
A14: =+$C$4&B14 -> Véhicules neufs[...] | B14: [...] | C14: =+SUM(F14,I14,L14,O14,R14,U14,X14,AA14,AD14,AG14,AJ14,AM14) -> 0 | D14: =IF(C14=0,0,E14/C14) -> 0 | E14: =+SUM(H14,K14,N14,Q14,T14,W14,Z14,AC14,AF14,AI14,AL14,AO14) -> 0 | G14: =IF(F14=0,0,H14/F14) -> 0 | J14: =IF(I14=0,0,K14/I14) -> 0 | M14: =IF(L14=0,0,N14/L14) -> 0 | P14: =IF(O14=0,0,Q14/O14) -> 0 | S14: =IF(R14=0,0,T14/R14) -> 0 | V14: =IF(U14=0,0,W14/U14) -> 0 | Y14: =IF(X14=0,0,Z14/X14) -> 0 | AB14: =IF(AA14=0,0,AC14/AA14) -> 0 | AE14: =IF(AD14=0,0,AF14/AD14) -> 0 | AH14: =IF(AG14=0,0,AI14/AG14) -> 0 | AK14: =IF(AJ14=0,0,AL14/AJ14) -> 0 | AN14: =IF(AM14=0,0,AO14/AM14) -> 0
A15: =+$C$4&B15 -> Véhicules neufs[...] | B15: [...] | C15: =+SUM(F15,I15,L15,O15,R15,U15,X15,AA15,AD15,AG15,AJ15,AM15) -> 0 | D15: =IF(C15=0,0,E15/C15) -> 0 | E15: =+SUM(H15,K15,N15,Q15,T15,W15,Z15,AC15,AF15,AI15,AL15,AO15) -> 0 | G15: =IF(F15=0,0,H15/F15) -> 0 | J15: =IF(I15=0,0,K15/I15) -> 0 | M15: =IF(L15=0,0,N15/L15) -> 0 | P15: =IF(O15=0,0,Q15/O15) -> 0 | S15: =IF(R15=0,0,T15/R15) -> 0 | V15: =IF(U15=0,0,W15/U15) -> 0 | Y15: =IF(X15=0,0,Z15/X15) -> 0 | AB15: =IF(AA15=0,0,AC15/AA15) -> 0 | AE15: =IF(AD15=0,0,AF15/AD15) -> 0 | AH15: =IF(AG15=0,0,AI15/AG15) -> 0 | AK15: =IF(AJ15=0,0,AL15/AJ15) -> 0 | AN15: =IF(AM15=0,0,AO15/AM15) -> 0
A16: =+$C$4&B16 -> Véhicules neufsTotal Neufs | B16: Total Neufs | C16: =+SUM(C9:C15) -> 748 | D16: =IF(C16<=0,0,E16/C16) -> 1940.0612 | E16: =+SUM(E9:E15) -> 1451165.8 | F16: =+SUM(F9:F15) -> 35.146988 | G16: =IF(F16<=0,0,H16/F16) -> 1940.0612 | H16: =+SUM(H9:H15) -> 68187.309 | I16: =+SUM(I9:I15) -> 36.048193 | J16: =IF(I16<=0,0,K16/I16) -> 1940.0612 | K16: =+SUM(K9:K15) -> 69935.701 | L16: =+SUM(L9:L15) -> 66.689157 | M16: =IF(L16<=0,0,N16/L16) -> 1940.0612 | N16: =+SUM(N9:N15) -> 129381.05 | O16: =+SUM(O9:O15) -> 73.898795 | P16: =IF(O16<=0,0,Q16/O16) -> 1940.0612 | Q16: =+SUM(Q9:Q15) -> 143368.19 | R16: =+SUM(R9:R15) -> 86.515663 | S16: =IF(R16<=0,0,T16/R16) -> 1940.0612 | T16: =+SUM(T9:T15) -> 167845.68 | U16: =+SUM(U9:U15) -> 66.689157 | V16: =IF(U16<=0,0,W16/U16) -> 1940.0612 | W16: =+SUM(W9:W15) -> 129381.05 | X16: =+SUM(X9:X15) -> 76.60241 | Y16: =IF(X16<=0,0,Z16/X16) -> 1940.0612 | Z16: =+SUM(Z9:Z15) -> 148613.37 | AA16: =+SUM(AA9:AA15) -> 73.898795 | AB16: =IF(AA16<=0,0,AC16/AA16) -> 1940.0612 | AC16: =+SUM(AC9:AC15) -> 143368.19 | AD16: =+SUM(AD9:AD15) -> 64.886747 | AE16: =IF(AD16<=0,0,AF16/AD16) -> 1940.0612 | AF16: =+SUM(AF9:AF15) -> 125884.26 | AG16: =+SUM(AG9:AG15) -> 69.392771 | AH16: =IF(AG16<=0,0,AI16/AG16) -> 1940.0612 | AI16: =+SUM(AI9:AI15) -> 134626.22 | AJ16: =+SUM(AJ9:AJ15) -> 62.183133 | AK16: =IF(AJ16<=0,0,AL16/AJ16) -> 1940.0612 | AL16: =+SUM(AL9:AL15) -> 120639.08 | AM16: =+SUM(AM9:AM15) -> 36.048193 | AN16: =IF(AM16<=0,0,AO16/AM16) -> 1940.0612 | AO16: =+SUM(AO9:AO15) -> 69935.701
A17: =+$C$4&B17 -> Véhicules neufs
A18: =+$C$4&B18 -> Véhicules neufsEx-Démos et courtoisies | B18: Ex-Démos et courtoisies | C18: =+SUM(F18,I18,L18,O18,R18,U18,X18,AA18,AD18,AG18,AJ18,AM18) -> 70 | D18: =IF(C18=0,0,E18/C18) -> 1386.1016 | E18: =+SUM(H18,K18,N18,Q18,T18,W18,Z18,AC18,AF18,AI18,AL18,AO18) -> 97027.113 | F18: 3.2891566 | G18: =IF(F18=0,0,H18/F18) -> 1386.1016 | H18: 4559.1053 | I18: 3.373494 | J18: =IF(I18=0,0,K18/I18) -> 1386.1016 | K18: 4676.0055 | L18: 6.2409639 | M18: =IF(L18=0,0,N18/L18) -> 1386.1016 | N18: 8650.6101 | O18: 6.9156627 | P18: =IF(O18=0,0,Q18/O18) -> 1386.1016 | Q18: 9585.8112 | R18: 8.0963855 | S18: =IF(R18=0,0,T18/R18) -> 1386.1016 | T18: 11222.413 | U18: 6.2409639 | V18: =IF(U18=0,0,W18/U18) -> 1386.1016 | W18: 8650.6101 | X18: 7.1686747 | Y18: =IF(X18=0,0,Z18/X18) -> 1386.1016 | Z18: 9936.5116 | AA18: 6.9156627 | AB18: =IF(AA18=0,0,AC18/AA18) -> 1386.1016 | AC18: 9585.8112 | AD18: 6.0722892 | AE18: =IF(AD18=0,0,AF18/AD18) -> 1386.1016 | AF18: 8416.8098 | AG18: 6.4939759 | AH18: =IF(AG18=0,0,AI18/AG18) -> 1386.1016 | AI18: 9001.3105 | AJ18: 5.8192771 | AK18: =IF(AJ18=0,0,AL18/AJ18) -> 1386.1016 | AL18: 8066.1094 | AM18: 3.373494 | AN18: =IF(AM18=0,0,AO18/AM18) -> 1386.1016 | AO18: 4676.0055
A19: =+$C$4&B19 -> Véhicules neufs
A20: =+$C$4&B20 -> Véhicules neufsFlottes | B20: Flottes | C20: =+SUM(F20,I20,L20,O20,R20,U20,X20,AA20,AD20,AG20,AJ20,AM20) -> 12 | D20: =IF(C20=0,0,E20/C20) -> 1938.8732 | E20: =+SUM(H20,K20,N20,Q20,T20,W20,Z20,AC20,AF20,AI20,AL20,AO20) -> 23266.478 | F20: 0 | G20: =IF(F20=0,0,H20/F20) -> 0 | H20: 0 | I20: 0.6068268 | J20: =IF(I20=0,0,K20/I20) -> 1938.8732 | K20: 1176.5602 | L20: 1.1226296 | M20: =IF(L20=0,0,N20/L20) -> 1938.8732 | N20: 2176.6364 | O20: 1.2439949 | P20: =IF(O20=0,0,Q20/O20) -> 1938.8732 | Q20: 2411.9484 | R20: 1.4563843 | S20: =IF(R20=0,0,T20/R20) -> 1938.8732 | T20: 2823.7445 | U20: 1.1226296 | V20: =IF(U20=0,0,W20/U20) -> 1938.8732 | W20: 2176.6364 | X20: 1.289507 | Y20: =IF(X20=0,0,Z20/X20) -> 1938.8732 | Z20: 2500.1904 | AA20: 1.2439949 | AB20: =IF(AA20=0,0,AC20/AA20) -> 1938.8732 | AC20: 2411.9484 | AD20: 1.0922882 | AE20: =IF(AD20=0,0,AF20/AD20) -> 1938.8732 | AF20: 2117.8084 | AG20: 1.1681416 | AH20: =IF(AG20=0,0,AI20/AG20) -> 1938.8732 | AI20: 2264.8784 | AJ20: 1.0467762 | AK20: =IF(AJ20=0,0,AL20/AJ20) -> 1938.8732 | AL20: 2029.5663 | AM20: 0.6068268 | AN20: =IF(AM20=0,0,AO20/AM20) -> 1938.8732 | AO20: 1176.5602
A21: =+$C$4&B21 -> Véhicules neufs
A22: =+$C$4&B22 -> Véhicules neufsRachat bail | B22: Rachat bail | E22: =+SUM(H22,K22,N22,Q22,T22,W22,Z22,AC22,AF22,AI22,AL22,AO22) -> 70133.658 | H22: 3506.6829 | K22: 3506.6829 | N22: 8416.039 | Q22: 8416.039 | T22: 8416.039 | W22: 8416.039 | Z22: 7013.3658 | AC22: 4909.3561 | AF22: 4909.3561 | AI22: 4208.0195 | AL22: 4208.0195 | AO22: 4208.0195
A23: =+$C$4&B23 -> Véhicules neufs
A24: =+$C$4&B24 -> Véhicules neufsRev. Finances | B24: Rev. Finances | D24: =IF(C16=0,0,E24/(C16+C18)) -> 29.923763 | E24: =+SUM(H24,K24,N24,Q24,T24,W24,Z24,AC24,AF24,AI24,AL24,AO24) -> 24477.638 | G24: =IF(F16=0,0,H24/(F16+F18)) -> 29.923763 | H24: 1150.1541 | J24: =IF(I16=0,0,K24/(I16+I18)) -> 29.923763 | K24: 1179.6452 | M24: =IF(L16=0,0,N24/(L16+L18)) -> 29.923763 | N24: 2182.3436 | P24: =IF(O16=0,0,Q24/(O16+O18)) -> 29.923763 | Q24: 2418.2727 | S24: =IF(R16=0,0,T24/(R16+R18)) -> 29.923763 | T24: 2831.1485 | V24: =IF(U16=0,0,W24/(U16+U18)) -> 29.923763 | W24: 2182.3436 | Y24: =IF(X16=0,0,Z24/(X16+X18)) -> 29.923763 | Z24: 2506.7461 | AB24: =IF(AA16=0,0,AC24/(AA16+AA18)) -> 29.923763 | AC24: 2418.2727 | AE24: =IF(AD16=0,0,AF24/(AD16+AD18)) -> 29.923763 | AF24: 2123.3614 | AH24: =IF(AG16=0,0,AI24/(AG16+AG18)) -> 29.923763 | AI24: 2270.817 | AK24: =IF(AJ16=0,0,AL24/(AJ16+AJ18)) -> 29.923763 | AL24: 2034.888 | AN24: =IF(AM16=0,0,AO24/(AM16+AM18)) -> 29.923763 | AO24: 1179.6452
A25: =+$C$4&B25 -> Véhicules neufsRev. Protections | B25: Rev. Protections | D25: =IF(C16=0,0,E25/(C16+C18)) -> 800.26939 | E25: =+SUM(H25,K25,N25,Q25,T25,W25,Z25,AC25,AF25,AI25,AL25,AO25) -> 654620.36 | G25: =IF(F16=0,0,H25/(F16+F18)) -> 800.26939 | H25: 30759.27 | J25: =IF(I16=0,0,K25/(I16+I18)) -> 800.26939 | K25: 31547.969 | M25: =IF(L16=0,0,N25/(L16+L18)) -> 800.26939 | N25: 58363.743 | P25: =IF(O16=0,0,Q25/(O16+O18)) -> 800.26939 | Q25: 64673.337 | S25: =IF(R16=0,0,T25/(R16+R18)) -> 800.26939 | T25: 75715.126 | V25: =IF(U16=0,0,W25/(U16+U18)) -> 800.26939 | W25: 58363.743 | Y25: =IF(X16=0,0,Z25/(X16+X18)) -> 800.26939 | Z25: 67039.434 | AB25: =IF(AA16=0,0,AC25/(AA16+AA18)) -> 800.26939 | AC25: 64673.337 | AE25: =IF(AD16=0,0,AF25/(AD16+AD18)) -> 800.26939 | AF25: 56786.344 | AH25: =IF(AG16=0,0,AI25/(AG16+AG18)) -> 800.26939 | AI25: 60729.841 | AK25: =IF(AJ16=0,0,AL25/(AJ16+AJ18)) -> 800.26939 | AL25: 54420.247 | AN25: =IF(AM16=0,0,AO25/(AM16+AM18)) -> 800.26939 | AO25: 31547.969
A26: =+$C$4&B26 -> Véhicules neufsRev. Autres | B26: Rev. Autres | D26: =IF(C16=0,0,E26/(C16+C18)) -> 19.806849 | E26: =+SUM(H26,K26,N26,Q26,T26,W26,Z26,AC26,AF26,AI26,AL26,AO26) -> 16202.003 | G26: =IF(F16=0,0,H26/(F16+F18)) -> 19.806849 | H26: 761.29892 | J26: =IF(I16=0,0,K26/(I16+I18)) -> 19.806849 | K26: 780.8194 | M26: =IF(L16=0,0,N26/(L16+L18)) -> 19.806849 | N26: 1444.5159 | P26: =IF(O16=0,0,Q26/(O16+O18)) -> 19.806849 | Q26: 1600.6798 | S26: =IF(R16=0,0,T26/(R16+R18)) -> 19.806849 | T26: 1873.9666 | V26: =IF(U16=0,0,W26/(U16+U18)) -> 19.806849 | W26: 1444.5159 | Y26: =IF(X16=0,0,Z26/(X16+X18)) -> 19.806849 | Z26: 1659.2412 | AB26: =IF(AA16=0,0,AC26/(AA16+AA18)) -> 19.806849 | AC26: 1600.6798 | AE26: =IF(AD16=0,0,AF26/(AD16+AD18)) -> 19.806849 | AF26: 1405.4749 | AH26: =IF(AG16=0,0,AI26/(AG16+AG18)) -> 19.806849 | AI26: 1503.0774 | AK26: =IF(AJ16=0,0,AL26/(AJ16+AJ18)) -> 19.806849 | AL26: 1346.9135 | AN26: =IF(AM16=0,0,AO26/(AM16+AM18)) -> 19.806849 | AO26: 780.8194
A27: =+$C$4&B27 -> Véhicules neufsTotal F&I | B27: Total F&I | C27: =+C18+C16 -> 818 | D27: =IF(C27<=0,0,E27/C27) -> 850 | E27: =E24+E25+E26 -> 695300 | F27: =+F18+F16 -> 38.436145 | G27: =IF(F27<=0,0,H27/F27) -> 850 | H27: =H24+H25+H26 -> 32670.723 | I27: =+I18+I16 -> 39.421687 | J27: =IF(I27<=0,0,K27/I27) -> 850 | K27: =K24+K25+K26 -> 33508.434 | L27: =+L18+L16 -> 72.93012 | M27: =IF(L27<=0,0,N27/L27) -> 850 | N27: =N24+N25+N26 -> 61990.602 | O27: =+O18+O16 -> 80.814458 | P27: =IF(O27<=0,0,Q27/O27) -> 850 | Q27: =Q24+Q25+Q26 -> 68692.289 | R27: =+R18+R16 -> 94.612048 | S27: =IF(R27<=0,0,T27/R27) -> 850 | T27: =T24+T25+T26 -> 80420.241 | U27: =+U18+U16 -> 72.93012 | V27: =IF(U27<=0,0,W27/U27) -> 850 | W27: =W24+W25+W26 -> 61990.602 | X27: =+X18+X16 -> 83.771084 | Y27: =IF(X27<=0,0,Z27/X27) -> 850 | Z27: =Z24+Z25+Z26 -> 71205.422 | AA27: =+AA18+AA16 -> 80.814458 | AB27: =IF(AA27<=0,0,AC27/AA27) -> 850 | AC27: =AC24+AC25+AC26 -> 68692.289 | AD27: =+AD18+AD16 -> 70.959036 | AE27: =IF(AD27<=0,0,AF27/AD27) -> 850 | AF27: =AF24+AF25+AF26 -> 60315.181 | AG27: =+AG18+AG16 -> 75.886747 | AH27: =IF(AG27<=0,0,AI27/AG27) -> 850 | AI27: =AI24+AI25+AI26 -> 64503.735 | AJ27: =+AJ18+AJ16 -> 68.00241 | AK27: =IF(AJ27<=0,0,AL27/AJ27) -> 850 | AL27: =AL24+AL25+AL26 -> 57802.048 | AM27: =+AM18+AM16 -> 39.421687 | AN27: =IF(AM27<=0,0,AO27/AM27) -> 850 | AO27: =AO24+AO25+AO26 -> 33508.434
A28: =+$C$4&B28 -> Véhicules neufs
A29: =+$C$4&B29 -> Véhicules neufs
A30: =+$C$4&B30 -> Véhicules neufsTotal Dépt. Neufs | B30: Total Dépt. Neufs | C30: =+C16+C18+C20 -> 830 | D30: =IF(C30<=0,0,E30/C30) -> 2815.5338 | E30: =E16+E20+E27+E22+E18 -> 2336893 | F30: =+F16+F18+F20 -> 38.436145 | G30: =IF(F30<=0,0,H30/F30) -> 2833.8904 | H30: =H16+H20+H27+H22+H18 -> 108923.82 | I30: =+I16+I18+I20 -> 40.028514 | J30: =IF(I30<=0,0,K30/I30) -> 2818.0758 | K30: =K16+K20+K27+K22+K18 -> 112803.38 | L30: =+L16+L18+L20 -> 74.05275 | M30: =IF(L30<=0,0,N30/L30) -> 2844.1204 | N30: =N16+N20+N27+N22+N18 -> 210614.94 | O30: =+O16+O18+O20 -> 82.058453 | P30: =IF(O30<=0,0,Q30/O30) -> 2833.0326 | Q30: =Q16+Q20+Q27+Q22+Q18 -> 232474.28 | R30: =+R16+R18+R20 -> 96.068433 | S30: =IF(R30<=0,0,T30/R30) -> 2818.0758 | T30: =T16+T20+T27+T22+T18 -> 270728.12 | U30: =+U16+U18+U20 -> 74.05275 | V30: =IF(U30<=0,0,W30/U30) -> 2844.1204 | W30: =W16+W20+W27+W22+W18 -> 210614.94 | X30: =+X16+X18+X20 -> 85.060591 | Y30: =IF(X30<=0,0,Z30/X30) -> 2812.9225 | Z30: =Z16+Z20+Z27+Z22+Z18 -> 239268.85 | AA30: =+AA16+AA18+AA20 -> 82.058453 | AB30: =IF(AA30<=0,0,AC30/AA30) -> 2790.2987 | AC30: =AC16+AC20+AC27+AC22+AC18 -> 228967.59 | AD30: =+AD16+AD18+AD20 -> 72.051324 | AE30: =IF(AD30<=0,0,AF30/AD30) -> 2798.6081 | AF30: =AF16+AF20+AF27+AF22+AF18 -> 201643.42 | AG30: =+AG16+AG18+AG20 -> 77.054889 | AH30: =IF(AG30<=0,0,AI30/AG30) -> 2785.0818 | AI30: =AI16+AI20+AI27+AI22+AI18 -> 214604.17 | AJ30: =+AJ16+AJ18+AJ20 -> 69.049186 | AK30: =IF(AJ30<=0,0,AL30/AJ30) -> 2791.4135 | AL30: =AL16+AL20+AL27+AL22+AL18 -> 192744.83 | AM30: =+AM16+AM18+AM20 -> 40.028514 | AN30: =IF(AM30<=0,0,AO30/AM30) -> 2835.5967 | AO30: =AO16+AO20+AO27+AO22+AO18 -> 113504.72
A31: =+$C$4&B31 -> Véhicules neufs
A32: =+$C$4&B32 -> Véhicules neufs
A33: =+$C$4&B33 -> Véhicules neufsDEPENSES | B33: DEPENSES
A34: =+$C$4&B34 -> Véhicules neufsComm. vendeurs | B34: Comm. vendeurs | C34: =E34/(E16+E18) -> 0.33115355 | D34: =IF(E34=0,0,E34/C$27) -> 626.75987 | E34: =+SUM(H34,K34,N34,Q34,T34,W34,Z34,AC34,AF34,AI34,AL34,AO34) -> 512689.57 | F34: =H34/(H16+H18) -> 0.37878062 | G34: =IF(H34=0,0,H34/F$27) -> 716.90156 | H34: 27554.932 | I34: =K34/(K16+K18) -> 0.37507774 | J34: =IF(K34=0,0,K34/I$27) -> 709.89328 | K34: 27985.19 | L34: =N34/(N16+N18) -> 0.32918247 | M34: =IF(N34=0,0,N34/L$27) -> 623.02931 | N34: 45437.602 | O34: =Q34/(Q16+Q18) -> 0.31966893 | P34: =IF(Q34=0,0,Q34/O$27) -> 605.02343 | Q34: 48894.64 | R34: =T34/(T16+T18) -> 0.31286677 | S34: =IF(T34=0,0,T34/R$27) -> 592.14929 | T34: 56024.457 | U34: =W34/(W16+W18) -> 0.32744374 | V34: =IF(W34=0,0,W34/U$27) -> 619.73848 | W34: 45197.602 | X34: =Z34/(Z16+Z18) -> 0.31769832 | Y34: =IF(Z34=0,0,Z34/X$27) -> 601.29375 | Z34: 50371.03 | AA34: =AC34/(AC16+AC18) -> 0.32280712 | AB34: =IF(AC34=0,0,AC34/AA$27) -> 610.96296 | AC34: 49374.64 | AD34: =AF34/(AF16+AF18) -> 0.32921065 | AE34: =IF(AF34=0,0,AF34/AD$27) -> 623.08263 | AF34: 44213.343 | AG34: =AI34/(AI16+AI18) -> 0.3232945 | AH34: =IF(AI34=0,0,AI34/AG$27) -> 611.88539 | AI34: 46433.992 | AJ34: =AL34/(AL16+AL18) -> 0.33205306 | AK34: =IF(AL34=0,0,AL34/AJ$27) -> 628.46234 | AL34: 42736.954 | AM34: =AO34/(AO16+AO18) -> 0.38151105 | AN34: =IF(AO34=0,0,AO34/AM$27) -> 722.06932 | AO34: 28465.19
A35: =+$C$4&B35 -> Véhicules neufsComm. F&I | B35: Comm. F&I | C35: =E35/E27 -> 0.3 | D35: =IF(E35=0,0,E35/C$27) -> 255 | E35: =+SUM(H35,K35,N35,Q35,T35,W35,Z35,AC35,AF35,AI35,AL35,AO35) -> 208590 | F35: =H35/H27 -> 0.3 | G35: =IF(H35=0,0,H35/F$27) -> 255 | H35: 9801.2169 | I35: =K35/K27 -> 0.3 | J35: =IF(K35=0,0,K35/I$27) -> 255 | K35: 10052.53 | L35: =N35/N27 -> 0.3 | M35: =IF(N35=0,0,N35/L$27) -> 255 | N35: 18597.181 | O35: =Q35/Q27 -> 0.3 | P35: =IF(Q35=0,0,Q35/O$27) -> 255 | Q35: 20607.687 | R35: =T35/T27 -> 0.3 | S35: =IF(T35=0,0,T35/R$27) -> 255 | T35: 24126.072 | U35: =W35/W27 -> 0.3 | V35: =IF(W35=0,0,W35/U$27) -> 255 | W35: 18597.181 | X35: =Z35/Z27 -> 0.3 | Y35: =IF(Z35=0,0,Z35/X$27) -> 255 | Z35: 21361.627 | AA35: =AC35/AC27 -> 0.3 | AB35: =IF(AC35=0,0,AC35/AA$27) -> 255 | AC35: 20607.687 | AD35: =AF35/AF27 -> 0.3 | AE35: =IF(AF35=0,0,AF35/AD$27) -> 255 | AF35: 18094.554 | AG35: =AI35/AI27 -> 0.3 | AH35: =IF(AI35=0,0,AI35/AG$27) -> 255 | AI35: 19351.12 | AJ35: =AL35/AL27 -> 0.3 | AK35: =IF(AL35=0,0,AL35/AJ$27) -> 255 | AL35: 17340.614 | AM35: =AO35/AO27 -> 0.3 | AN35: =IF(AO35=0,0,AO35/AM$27) -> 255 | AO35: 10052.53
A36: =+$C$4&B36 -> Véhicules neufsFrais de livraison | B36: Frais de livraison | D36: =IF(E36=0,0,E36/C$27) -> 167.8493 | E36: =+SUM(H36,K36,N36,Q36,T36,W36,Z36,AC36,AF36,AI36,AL36,AO36) -> 137300.73 | G36: =IF(H36=0,0,H36/F$27) -> 167.8493 | H36: 6451.48 | J36: =IF(K36=0,0,K36/I$27) -> 167.8493 | K36: 6616.9026 | M36: =IF(N36=0,0,N36/L$27) -> 167.8493 | N36: 12241.27 | P36: =IF(Q36=0,0,Q36/O$27) -> 167.8493 | Q36: 13564.65 | S36: =IF(T36=0,0,T36/R$27) -> 167.8493 | T36: 15880.566 | V36: =IF(W36=0,0,W36/U$27) -> 167.8493 | W36: 12241.27 | Y36: =IF(Z36=0,0,Z36/X$27) -> 167.8493 | Z36: 14060.918 | AB36: =IF(AC36=0,0,AC36/AA$27) -> 167.8493 | AC36: 13564.65 | AE36: =IF(AF36=0,0,AF36/AD$27) -> 167.8493 | AF36: 11910.425 | AH36: =IF(AI36=0,0,AI36/AG$27) -> 167.8493 | AI36: 12737.538 | AK36: =IF(AL36=0,0,AL36/AJ$27) -> 167.8493 | AL36: 11414.157 | AN36: =IF(AO36=0,0,AO36/AM$27) -> 167.8493 | AO36: 6616.9026
A37: =+$C$4&B37 -> Véhicules neufsService gratuit 1 | B37: Service gratuit 1 | D37: =IF(E37=0,0,E37/C$27) -> 7.3548076 | E37: =+SUM(H37,K37,N37,Q37,T37,W37,Z37,AC37,AF37,AI37,AL37,AO37) -> 6016.2326 | G37: =IF(H37=0,0,H37/F$27) -> 7.3548076 | H37: 282.69045 | J37: =IF(K37=0,0,K37/I$27) -> 7.3548076 | K37: 289.93892 | M37: =IF(N37=0,0,N37/L$27) -> 7.3548076 | N37: 536.38701 | P37: =IF(Q37=0,0,Q37/O$27) -> 7.3548076 | Q37: 594.37479 | S37: =IF(T37=0,0,T37/R$27) -> 7.3548076 | T37: 695.85341 | V37: =IF(W37=0,0,W37/U$27) -> 7.3548076 | W37: 536.38701 | Y37: =IF(Z37=0,0,Z37/X$27) -> 7.3548076 | Z37: 616.12021 | AB37: =IF(AC37=0,0,AC37/AA$27) -> 7.3548076 | AC37: 594.37479 | AE37: =IF(AF37=0,0,AF37/AD$27) -> 7.3548076 | AF37: 521.89006 | AH37: =IF(AI37=0,0,AI37/AG$27) -> 7.3548076 | AI37: 558.13243 | AK37: =IF(AL37=0,0,AL37/AJ$27) -> 7.3548076 | AL37: 500.14464 | AN37: =IF(AO37=0,0,AO37/AM$27) -> 7.3548076 | AO37: 289.93892
A38: =+$C$4&B38 -> Véhicules neufsEntretien stock | B38: Entretien stock | D38: =IF(E38=0,0,E38/C$27) -> 17.733118 | E38: =+SUM(H38,K38,N38,Q38,T38,W38,Z38,AC38,AF38,AI38,AL38,AO38) -> 14505.691 | G38: =IF(H38=0,0,H38/F$27) -> 17.733118 | H38: 681.5927 | J38: =IF(K38=0,0,K38/I$27) -> 17.733118 | K38: 699.06943 | M38: =IF(N38=0,0,N38/L$27) -> 17.733118 | N38: 1293.2784 | P38: =IF(Q38=0,0,Q38/O$27) -> 17.733118 | Q38: 1433.0923 | S38: =IF(T38=0,0,T38/R$27) -> 17.733118 | T38: 1677.7666 | V38: =IF(W38=0,0,W38/U$27) -> 17.733118 | W38: 1293.2784 | Y38: =IF(Z38=0,0,Z38/X$27) -> 17.733118 | Z38: 1485.5225 | AB38: =IF(AC38=0,0,AC38/AA$27) -> 17.733118 | AC38: 1433.0923 | AE38: =IF(AF38=0,0,AF38/AD$27) -> 17.733118 | AF38: 1258.325 | AH38: =IF(AI38=0,0,AI38/AG$27) -> 17.733118 | AI38: 1345.7087 | AK38: =IF(AL38=0,0,AL38/AJ$27) -> 17.733118 | AL38: 1205.8948 | AN38: =IF(AO38=0,0,AO38/AM$27) -> 17.733118 | AO38: 699.06943
A39: =+$C$4&B39 -> Véhicules neufsPublicité 1 | B39: Publicité 1 | D39: =IF(E39=0,0,E39/C$27) -> 195.93765 | E39: =+SUM(H39,K39,N39,Q39,T39,W39,Z39,AC39,AF39,AI39,AL39,AO39) -> 160277 | G39: =IF(H39=0,0,H39/F$27) -> 195.93765 | H39: 7531.088 | J39: =IF(K39=0,0,K39/I$27) -> 195.93765 | K39: 7724.1928 | M39: =IF(N39=0,0,N39/L$27) -> 195.93765 | N39: 14289.757 | P39: =IF(Q39=0,0,Q39/O$27) -> 195.93765 | Q39: 15834.595 | S39: =IF(T39=0,0,T39/R$27) -> 195.93765 | T39: 18538.063 | V39: =IF(W39=0,0,W39/U$27) -> 195.93765 | W39: 14289.757 | Y39: =IF(Z39=0,0,Z39/X$27) -> 195.93765 | Z39: 16413.91 | AB39: =IF(AC39=0,0,AC39/AA$27) -> 195.93765 | AC39: 15834.595 | AE39: =IF(AF39=0,0,AF39/AD$27) -> 195.93765 | AF39: 13903.547 | AH39: =IF(AI39=0,0,AI39/AG$27) -> 195.93765 | AI39: 14869.071 | AK39: =IF(AL39=0,0,AL39/AJ$27) -> 195.93765 | AL39: 13324.233 | AN39: =IF(AO39=0,0,AO39/AM$27) -> 195.93765 | AO39: 7724.1928
A40: =+$C$4&B40 -> Véhicules neufsIntérêt de gros | B40: Intérêt de gros | D40: =IF(E40=0,0,E40/C$27) -> 102.42004 | E40: =+SUM(H40,K40,N40,Q40,T40,W40,Z40,AC40,AF40,AI40,AL40,AO40) -> 83779.589 | G40: =IF(H40=0,0,H40/F$27) -> 146.62809 | H40: 5635.8184 | J40: =IF(K40=0,0,K40/I$27) -> 162.72861 | K40: 6415.0362 | M40: =IF(N40=0,0,N40/L$27) -> 100.885 | N40: 7357.5552 | P40: =IF(Q40=0,0,Q40/O$27) -> 101.02946 | Q40: 8164.6412 | S40: =IF(T40=0,0,T40/R$27) -> 83.856314 | T40: 7933.8176 | V40: =IF(W40=0,0,W40/U$27) -> 95.743292 | W40: 6982.5698 | Y40: =IF(Z40=0,0,Z40/X$27) -> 86.224826 | Z40: 7223.1472 | AB40: =IF(AC40=0,0,AC40/AA$27) -> 96.0289 | AC40: 7760.5235 | AE40: =IF(AF40=0,0,AF40/AD$27) -> 117.38963 | AF40: 8329.8552 | AH40: =IF(AI40=0,0,AI40/AG$27) -> 97.587388 | AI40: 7405.5894 | AK40: =IF(AL40=0,0,AL40/AJ$27) -> 79.550134 | AL40: 5409.6008 | AN40: =IF(AO40=0,0,AO40/AM$27) -> 130.92881 | AO40: 5161.4344
A41: =+$C$4&B41 -> Véhicules neufs[...] | B41: [...] | D41: =IF(E41=0,0,E41/C$27) -> 0 | E41: =+SUM(H41,K41,N41,Q41,T41,W41,Z41,AC41,AF41,AI41,AL41,AO41) -> 0 | G41: =IF(H41=0,0,H41/F$27) -> 0 | J41: =IF(K41=0,0,K41/I$27) -> 0 | M41: =IF(N41=0,0,N41/L$27) -> 0 | P41: =IF(Q41=0,0,Q41/O$27) -> 0 | S41: =IF(T41=0,0,T41/R$27) -> 0 | V41: =IF(W41=0,0,W41/U$27) -> 0 | Y41: =IF(Z41=0,0,Z41/X$27) -> 0 | AB41: =IF(AC41=0,0,AC41/AA$27) -> 0 | AE41: =IF(AF41=0,0,AF41/AD$27) -> 0 | AH41: =IF(AI41=0,0,AI41/AG$27) -> 0 | AK41: =IF(AL41=0,0,AL41/AJ$27) -> 0 | AN41: =IF(AO41=0,0,AO41/AM$27) -> 0
A42: =+$C$4&B42 -> Véhicules neufs[...] | B42: [...] | D42: =IF(E42=0,0,E42/C$27) -> 0 | E42: =+SUM(H42,K42,N42,Q42,T42,W42,Z42,AC42,AF42,AI42,AL42,AO42) -> 0 | G42: =IF(H42=0,0,H42/F$27) -> 0 | J42: =IF(K42=0,0,K42/I$27) -> 0 | M42: =IF(N42=0,0,N42/L$27) -> 0 | P42: =IF(Q42=0,0,Q42/O$27) -> 0 | S42: =IF(T42=0,0,T42/R$27) -> 0 | V42: =IF(W42=0,0,W42/U$27) -> 0 | Y42: =IF(Z42=0,0,Z42/X$27) -> 0 | AB42: =IF(AC42=0,0,AC42/AA$27) -> 0 | AE42: =IF(AF42=0,0,AF42/AD$27) -> 0 | AH42: =IF(AI42=0,0,AI42/AG$27) -> 0 | AK42: =IF(AL42=0,0,AL42/AJ$27) -> 0 | AN42: =IF(AO42=0,0,AO42/AM$27) -> 0
A43: =+$C$4&B43 -> Véhicules neufs[...] | B43: [...] | D43: =IF(E43=0,0,E43/C$27) -> 0 | E43: =+SUM(H43,K43,N43,Q43,T43,W43,Z43,AC43,AF43,AI43,AL43,AO43) -> 0 | G43: =IF(H43=0,0,H43/F$27) -> 0 | J43: =IF(K43=0,0,K43/I$27) -> 0 | M43: =IF(N43=0,0,N43/L$27) -> 0 | P43: =IF(Q43=0,0,Q43/O$27) -> 0 | S43: =IF(T43=0,0,T43/R$27) -> 0 | V43: =IF(W43=0,0,W43/U$27) -> 0 | Y43: =IF(Z43=0,0,Z43/X$27) -> 0 | AB43: =IF(AC43=0,0,AC43/AA$27) -> 0 | AE43: =IF(AF43=0,0,AF43/AD$27) -> 0 | AH43: =IF(AI43=0,0,AI43/AG$27) -> 0 | AK43: =IF(AL43=0,0,AL43/AJ$27) -> 0 | AN43: =IF(AO43=0,0,AO43/AM$27) -> 0
A44: =+$C$4&B44 -> Véhicules neufsTOTAL VARIABLES | B44: TOTAL VARIABLES | C44: % brut | D44: =IFERROR(E44/E$30,0) -> 0.48062055 | E44: =SUM(E34:E43) -> 1123158.8 | F44: % brut | G44: =IFERROR(H44/H$30,0) -> 0.53192055 | H44: =SUM(H34:H43) -> 57938.819 | I44: % brut | J44: =IFERROR(K44/K$30,0) -> 0.529974 | K44: =SUM(K34:K43) -> 59782.86 | L44: % brut | M44: =IFERROR(N44/N$30,0) -> 0.47362752 | N44: =SUM(N34:N43) -> 99753.03 | O44: % brut | P44: =IFERROR(Q44/Q$30,0) -> 0.46927206 | Q44: =SUM(Q34:Q43) -> 109093.68 | R44: % brut | S44: =IFERROR(T44/T$30,0) -> 0.46126201 | T44: =SUM(T34:T43) -> 124876.6 | U44: % brut | V44: =IFERROR(W44/W$30,0) -> 0.47070757 | W44: =SUM(W34:W43) -> 99138.045 | X44: % brut | Y44: =IFERROR(Z44/Z$30,0) -> 0.46613787 | Z44: =SUM(Z34:Z43) -> 111532.27 | AA44: % brut | AB44: =IFERROR(AC44/AC$30,0) -> 0.47679046 | AC44: =SUM(AC34:AC43) -> 109169.56 | AD44: % brut | AE44: =IFERROR(AF44/AF$30,0) -> 0.48715669 | AF44: =SUM(AF34:AF43) -> 98231.939 | AG44: % brut | AH44: =IFERROR(AI44/AI$30,0) -> 0.47856084 | AI44: =SUM(AI34:AI43) -> 102701.15 | AJ44: % brut | AK44: =IFERROR(AL44/AL$30,0) -> 0.47696013 | AL44: =SUM(AL34:AL43) -> 91931.598 | AM44: % brut | AN44: =IFERROR(AO44/AO$30,0) -> 0.51988374 | AO44: =SUM(AO34:AO43) -> 59009.259
A45: =+$C$4&B45 -> Véhicules neufsSalaires cadres | B45: Salaires cadres | E45: =+SUM(H45,K45,N45,Q45,T45,W45,Z45,AC45,AF45,AI45,AL45,AO45) -> 189054.05 | H45: 15359.234 | K45: 14832.207 | N45: 16413.288 | Q45: 15359.234 | T45: 15886.261 | W45: 15886.261 | Z45: 15886.261 | AC45: 15886.261 | AF45: 15886.261 | AI45: 15359.234 | AL45: 15886.261 | AO45: 16413.288
A46: =+$C$4&B46 -> Véhicules neufsSalaires commis | B46: Salaires commis | E46: =+SUM(H46,K46,N46,Q46,T46,W46,Z46,AC46,AF46,AI46,AL46,AO46) -> 116556.57 | H46: 9386.1061 | K46: 8950.1843 | N46: 10257.949 | Q46: 9386.1061 | T46: 9822.0278 | W46: 9822.0278 | Z46: 9822.0278 | AC46: 9822.0278 | AF46: 9822.0278 | AI46: 9386.1061 | AL46: 9822.0278 | AO46: 10257.949
A47: =+$C$4&B47 -> Véhicules neufsSalaires autres | B47: Salaires autres | E47: =+SUM(H47,K47,N47,Q47,T47,W47,Z47,AC47,AF47,AI47,AL47,AO47) -> 105840.27 | H47: 8515.8839 | K47: 8110.3656 | N47: 9326.9204 | Q47: 8515.8839 | T47: 8921.4022 | W47: 8921.4022 | Z47: 8921.4022 | AC47: 8921.4022 | AF47: 8921.4022 | AI47: 8515.8839 | AL47: 8921.4022 | AO47: 9326.9204
A48: =+$C$4&B48 -> Véhicules neufsSalaires spécialistes | B48: Salaires spécialistes | E48: =+SUM(H48,K48,N48,Q48,T48,W48,Z48,AC48,AF48,AI48,AL48,AO48) -> 0 | H48: 0 | K48: 0 | N48: 0 | Q48: 0 | T48: 0 | W48: 0 | Z48: 0 | AC48: 0 | AF48: 0 | AI48: 0 | AL48: 0 | AO48: 0
A49: =+$C$4&B49 -> Véhicules neufs[...] | B49: [...] | E49: =+SUM(H49,K49,N49,Q49,T49,W49,Z49,AC49,AF49,AI49,AL49,AO49) -> 0 | H49: 0 | K49: 0 | N49: 0 | Q49: 0 | T49: 0 | W49: 0 | Z49: 0 | AC49: 0 | AF49: 0 | AI49: 0 | AL49: 0 | AO49: 0
A50: =+$C$4&B50 -> Véhicules neufs[...] | B50: [...] | E50: =+SUM(H50,K50,N50,Q50,T50,W50,Z50,AC50,AF50,AI50,AL50,AO50) -> 0 | H50: 0 | K50: 0 | N50: 0 | Q50: 0 | T50: 0 | W50: 0 | Z50: 0 | AC50: 0 | AF50: 0 | AI50: 0 | AL50: 0 | AO50: 0
A51: =+$C$4&B51 -> Véhicules neufs[...] | B51: [...] | E51: =+SUM(H51,K51,N51,Q51,T51,W51,Z51,AC51,AF51,AI51,AL51,AO51) -> 0 | H51: 0 | K51: 0 | N51: 0 | Q51: 0 | T51: 0 | W51: 0 | Z51: 0 | AC51: 0 | AF51: 0 | AI51: 0 | AL51: 0 | AO51: 0
A52: =+$C$4&B52 -> Véhicules neufsSalaires en absences | B52: Salaires en absences | E52: =+SUM(H52,K52,N52,Q52,T52,W52,Z52,AC52,AF52,AI52,AL52,AO52) -> 138467.75 | H52: 8813.5959 | K52: 8712.1065 | N52: 12210.248 | Q52: 12474.718 | T52: 13866.553 | W52: 12003.8 | Z52: 12907.843 | AC52: 12708.499 | AF52: 11834.459 | AI52: 12051.365 | AL52: 11580.448 | AO52: 9304.1141
A53: =+$C$4&B53 -> Véhicules neufsDéduction à la source | B53: Déduction à la source | E53: =+SUM(H53,K53,N53,Q53,T53,W53,Z53,AC53,AF53,AI53,AL53,AO53) -> 124012.06 | H53: 7893.4786 | K53: 7802.5844 | N53: 10935.528 | Q53: 11172.389 | T53: 12418.92 | W53: 10750.634 | Z53: 11560.297 | AC53: 11381.763 | AF53: 10598.971 | AI53: 10793.233 | AL53: 10371.478 | AO53: 8332.7879
A54: =+$C$4&B54 -> Véhicules neufsBénéfices marginaux | B54: Bénéfices marginaux | E54: =+SUM(H54,K54,N54,Q54,T54,W54,Z54,AC54,AF54,AI54,AL54,AO54) -> 98480.168 | H54: 6268.3506 | K54: 6196.1699 | N54: 8684.096 | Q54: 8872.1911 | T54: 9862.0834 | W54: 8537.268 | Z54: 9180.2357 | AC54: 9038.4591 | AF54: 8416.8302 | AI54: 8571.0967 | AL54: 8236.1736 | AO54: 6617.2139
A55: =+$C$4&B55 -> Véhicules neufsCsst | B55: Csst | E55: =+SUM(H55,K55,N55,Q55,T55,W55,Z55,AC55,AF55,AI55,AL55,AO55) -> 40121.55 | H55: 2553.7725 | K55: 2524.3655 | N55: 3537.965 | Q55: 3614.5964 | T55: 4017.8858 | W55: 3478.1462 | Z55: 3740.096 | AC55: 3682.3352 | AF55: 3429.079 | AI55: 3491.9283 | AL55: 3355.4781 | AO55: 2695.902
A56: =+$C$4&B56 -> Véhicules neufs[...] | B56: [...] | E56: =+SUM(H56,K56,N56,Q56,T56,W56,Z56,AC56,AF56,AI56,AL56,AO56) -> 0
A57: =+$C$4&B57 -> Véhicules neufsTOTAL PERSONNEL | B57: TOTAL PERSONNEL | C57: % brut | D57: =IFERROR(E57/E$30,0) -> 0.34769774 | E57: =+SUM(E45:E56) -> 812532.42 | F57: % brut | G57: =IFERROR(H57/H$30,0) -> 0.53973889 | H57: =+SUM(H45:H56) -> 58790.421 | I57: % brut | J57: =IFERROR(K57/K$30,0) -> 0.50643856 | K57: =+SUM(K45:K56) -> 57127.983 | L57: % brut | M57: =IFERROR(N57/N$30,0) -> 0.33884584 | N57: =+SUM(N45:N56) -> 71365.995 | O57: % brut | P57: =IFERROR(Q57/Q$30,0) -> 0.29850665 | Q57: =+SUM(Q45:Q56) -> 69395.118 | R57: % brut | S57: =IFERROR(T57/T$30,0) -> 0.27627397 | T57: =+SUM(T45:T56) -> 74795.133 | U57: % brut | V57: =IFERROR(W57/W$30,0) -> 0.32950911 | W57: =+SUM(W45:W56) -> 69399.539 | X57: % brut | Y57: =IFERROR(Z57/Z$30,0) -> 0.30099263 | Z57: =+SUM(Z45:Z56) -> 72018.163 | AA57: % brut | AB57: =IFERROR(AC57/AC$30,0) -> 0.31201248 | AC57: =+SUM(AC45:AC56) -> 71440.747 | AD57: % brut | AE57: =IFERROR(AF57/AF$30,0) -> 0.34173707 | AF57: =+SUM(AF45:AF56) -> 68909.031 | AG57: % brut | AH57: =IFERROR(AI57/AI$30,0) -> 0.31764922 | AI57: =+SUM(AI45:AI56) -> 68168.847 | AJ57: % brut | AK57: =IFERROR(AL57/AL$30,0) -> 0.353697 | AL57: =+SUM(AL45:AL56) -> 68173.268 | AM57: % brut | AN57: =IFERROR(AO57/AO$30,0) -> 0.55458642 | AO57: =+SUM(AO45:AO56) -> 62948.176
A58: =+$C$4&B58 -> Véhicules neufsPublicité 2 | B58: Publicité 2 | E58: =+SUM(H58,K58,N58,Q58,T58,W58,Z58,AC58,AF58,AI58,AL58,AO58) -> 0 | H58: 0 | K58: 0 | N58: 0 | Q58: 0 | T58: 0 | W58: 0 | Z58: 0 | AC58: 0 | AF58: 0 | AI58: 0 | AL58: 0 | AO58: 0
A59: =+$C$4&B59 -> Véhicules neufsService gratuit 2 | B59: Service gratuit 2 | E59: =+SUM(H59,K59,N59,Q59,T59,W59,Z59,AC59,AF59,AI59,AL59,AO59) -> 0 | H59: 0 | K59: 0 | N59: 0 | Q59: 0 | T59: 0 | W59: 0 | Z59: 0 | AC59: 0 | AF59: 0 | AI59: 0 | AL59: 0 | AO59: 0
A60: =+$C$4&B60 -> Véhicules neufsFrais véhicules de cie | B60: Frais véhicules de cie | E60: =+SUM(H60,K60,N60,Q60,T60,W60,Z60,AC60,AF60,AI60,AL60,AO60) -> 87875.28 | H60: 7322.94 | K60: 7322.94 | N60: 7322.94 | Q60: 7322.94 | T60: 7322.94 | W60: 7322.94 | Z60: 7322.94 | AC60: 7322.94 | AF60: 7322.94 | AI60: 7322.94 | AL60: 7322.94 | AO60: 7322.94
A61: =+$C$4&B61 -> Véhicules neufsInformatique | B61: Informatique | E61: =+SUM(H61,K61,N61,Q61,T61,W61,Z61,AC61,AF61,AI61,AL61,AO61) -> 82010.345 | H61: 6834.1886 | K61: 6834.1886 | N61: 6834.1886 | Q61: 6834.1886 | T61: 6834.1988 | W61: 6834.1988 | Z61: 6834.1988 | AC61: 6834.1988 | AF61: 6834.1988 | AI61: 6834.1988 | AL61: 6834.1988 | AO61: 6834.1988
A62: =+$C$4&B62 -> Véhicules neufsFrais de déplacement | B62: Frais de déplacement | E62: =+SUM(H62,K62,N62,Q62,T62,W62,Z62,AC62,AF62,AI62,AL62,AO62) -> 9505.7016 | H62: 792.1418 | K62: 792.1418 | N62: 792.1418 | Q62: 792.1418 | T62: 792.1418 | W62: 792.1418 | Z62: 792.1418 | AC62: 792.1418 | AF62: 792.1418 | AI62: 792.1418 | AL62: 792.1418 | AO62: 792.1418
A63: =+$C$4&B63 -> Véhicules neufsServices extérieurs | B63: Services extérieurs | E63: =+SUM(H63,K63,N63,Q63,T63,W63,Z63,AC63,AF63,AI63,AL63,AO63) -> 79819.781 | H63: 6763.7218 | K63: 6916.8098 | N63: 6604.1602 | Q63: 6627.0466 | T63: 6518.7074 | W63: 6830.797 | Z63: 6729.517 | AC63: 6447.7026 | AF63: 6468.477 | AI63: 6207.101 | AL63: 7079.4402 | AO63: 6626.301
A64: =+$C$4&B64 -> Véhicules neufsFournitures autres | B64: Fournitures autres | E64: =+SUM(H64,K64,N64,Q64,T64,W64,Z64,AC64,AF64,AI64,AL64,AO64) -> 989.00443 | H64: 50.536579 | K64: 52.169296 | N64: 91.038463 | Q64: 96.216577 | T64: 107.68716 | W64: 92.790378 | Z64: 99.362812 | AC64: 94.464662 | AF64: 81.641328 | AI64: 89.80491 | AL64: 79.371051 | AO64: 53.921211
A65: =+$C$4&B65 -> Véhicules neufsUniformes | B65: Uniformes | E65: =+SUM(H65,K65,N65,Q65,T65,W65,Z65,AC65,AF65,AI65,AL65,AO65) -> 525.53095 | H65: 26.85381 | K65: 27.721392 | N65: 48.375446 | Q65: 51.12696 | T65: 57.222126 | W65: 49.306367 | Z65: 52.798786 | AC65: 50.196038 | AF65: 43.382055 | AI65: 47.719968 | AL65: 42.17569 | AO65: 28.652314
A66: =+$C$4&B66 -> Véhicules neufsPapeterie | B66: Papeterie | E66: =+SUM(H66,K66,N66,Q66,T66,W66,Z66,AC66,AF66,AI66,AL66,AO66) -> 7834.3718 | H66: 652.86432 | K66: 652.86432 | N66: 652.86432 | Q66: 652.86432 | T66: 652.86432 | W66: 652.86432 | Z66: 652.86432 | AC66: 652.86432 | AF66: 652.86432 | AI66: 652.86432 | AL66: 652.86432 | AO66: 652.86432
A67: =+$C$4&B67 -> Véhicules neufsTéléphone | B67: Téléphone | E67: =+SUM(H67,K67,N67,Q67,T67,W67,Z67,AC67,AF67,AI67,AL67,AO67) -> 3617.5743 | H67: 301.46453 | K67: 301.46453 | N67: 301.46453 | Q67: 301.46453 | T67: 301.46453 | W67: 301.46453 | Z67: 301.46453 | AC67: 301.46453 | AF67: 301.46453 | AI67: 301.46453 | AL67: 301.46453 | AO67: 301.46453
A68: =+$C$4&B68 -> Véhicules neufsFrais postaux | B68: Frais postaux | E68: =+SUM(H68,K68,N68,Q68,T68,W68,Z68,AC68,AF68,AI68,AL68,AO68) -> 1931.0049 | H68: 160.91707 | K68: 160.91707 | N68: 160.91707 | Q68: 160.91707 | T68: 160.91707 | W68: 160.91707 | Z68: 160.91707 | AC68: 160.91707 | AF68: 160.91707 | AI68: 160.91707 | AL68: 160.91707 | AO68: 160.91707
A69: =+$C$4&B69 -> Véhicules neufsDivers | B69: Divers | E69: =+SUM(H69,K69,N69,Q69,T69,W69,Z69,AC69,AF69,AI69,AL69,AO69) -> 9314.8031 | H69: 776.23359 | K69: 776.23359 | N69: 776.23359 | Q69: 776.23359 | T69: 776.23359 | W69: 776.23359 | Z69: 776.23359 | AC69: 776.23359 | AF69: 776.23359 | AI69: 776.23359 | AL69: 776.23359 | AO69: 776.23359
... A71: =+$C$4&B71 -> Véhicules neufsFrais bancaires | B71: Frais bancaires | E71: =+SUM(H71,K71,N71,Q71,T71,W71,Z71,AC71,AF71,AI71,AL71,AO71) -> 27969.359 | H71: 1683.2373 | K71: 1432.4514 | N71: 1679.4267 | Q71: 3359.0496 | T71: 3066.8322 | W71: 1979.113 | Z71: 1857.7872 | AC71: 2062.1401 | AF71: 1527.324 | AI71: 2986.7567 | AL71: 4410.6483 | AO71: 1924.593
A72: =+$C$4&B72 -> Véhicules neufs[...] | B72: [...] | E72: =+SUM(H72,K72,N72,Q72,T72,W72,Z72,AC72,AF72,AI72,AL72,AO72) -> 0
A73: =+$C$4&B73 -> Véhicules neufs[...] | B73: [...] | E73: =+SUM(H73,K73,N73,Q73,T73,W73,Z73,AC73,AF73,AI73,AL73,AO73) -> 0
A74: =+$C$4&B74 -> Véhicules neufs[...] | B74: [...] | E74: =+SUM(H74,K74,N74,Q74,T74,W74,Z74,AC74,AF74,AI74,AL74,AO74) -> 0
A75: =+$C$4&B75 -> Véhicules neufsTOTAL SEMI-FIXES | B75: TOTAL SEMI-FIXES | C75: % brut | D75: =IFERROR(E75/E$30,0) -> 0.13917275 | E75: =+SUM(E58:E74) -> 325231.83 | F75: % brut | G75: =IFERROR(H75/H$30,0) -> 0.24345782 | H75: =+SUM(H58:H74) -> 26518.356 | I75: % brut | J75: =IFERROR(K75/K$30,0) -> 0.23424083 | K75: =+SUM(K58:K74) -> 26423.158 | L75: % brut | M75: =IFERROR(N75/N$30,0) -> 0.12542799 | N75: =+SUM(N58:N74) -> 26417.007 | O75: % brut | P75: =IFERROR(Q75/Q$30,0) -> 0.12099165 | Q75: =+SUM(Q58:Q74) -> 28127.446 | R75: % brut | S75: =IFERROR(T75/T$30,0) -> 0.10248091 | T75: =+SUM(T58:T74) -> 27744.465 | U75: % brut | V75: =IFERROR(W75/W$30,0) -> 0.12793975 | W75: =+SUM(W58:W74) -> 26946.023 | X75: % brut | Y75: =IFERROR(Z75/Z$30,0) -> 0.11172989 | Z75: =+SUM(Z58:Z74) -> 26733.482 | AA75: % brut | AB75: =IFERROR(AC75/AC$30,0) -> 0.11638555 | AC75: =+SUM(AC58:AC74) -> 26648.52 | AD75: % brut | AE75: =IFERROR(AF75/AF$30,0) -> 0.12951001 | AF75: =+SUM(AF58:AF74) -> 26114.841 | AG75: % brut | AH75: =IFERROR(AI75/AI$30,0) -> 0.1273293 | AI75: =+SUM(AI58:AI74) -> 27325.399 | AJ75: % brut | AK75: =IFERROR(AL75/AL$30,0) -> 0.15360024 | AL75: =+SUM(AL58:AL74) -> 29605.652 | AM75: % brut | AN75: =IFERROR(AO75/AO$30,0) -> 0.23459363 | AO75: =+SUM(AO58:AO74) -> 26627.484
A76: =+$C$4&B76 -> Véhicules neufs
A77: =+$C$4&B77 -> Véhicules neufsTOTAL DES DÉPENSES | B77: TOTAL DES DÉPENSES | C77: % brut | D77: =IFERROR(E77/E$30,0) -> 0.96749103 | E77: =E44+E57+E75 -> 2260923.1 | F77: % brut | G77: =IFERROR(H77/H$30,0) -> 1.3151173 | H77: =H44+H57+H75 -> 143247.6 | I77: % brut | J77: =IFERROR(K77/K$30,0) -> 1.2706534 | K77: =K44+K57+K75 -> 143334 | L77: % brut | M77: =IFERROR(N77/N$30,0) -> 0.93790135 | N77: =N44+N57+N75 -> 197536.03 | O77: % brut | P77: =IFERROR(Q77/Q$30,0) -> 0.88877036 | Q77: =Q44+Q57+Q75 -> 206616.24 | R77: % brut | S77: =IFERROR(T77/T$30,0) -> 0.84001689 | T77: =T44+T57+T75 -> 227416.19 | U77: % brut | V77: =IFERROR(W77/W$30,0) -> 0.92815643 | W77: =W44+W57+W75 -> 195483.61 | X77: % brut | Y77: =IFERROR(Z77/Z$30,0) -> 0.87886039 | Z77: =Z44+Z57+Z75 -> 210283.92 | AA77: % brut | AB77: =IFERROR(AC77/AC$30,0) -> 0.90518849 | AC77: =AC44+AC57+AC75 -> 207258.83 | AD77: % brut | AE77: =IFERROR(AF77/AF$30,0) -> 0.95840377 | AF77: =AF44+AF57+AF75 -> 193255.81 | AG77: % brut | AH77: =IFERROR(AI77/AI$30,0) -> 0.92353936 | AI77: =AI44+AI57+AI75 -> 198195.4 | AJ77: % brut | AK77: =IFERROR(AL77/AL$30,0) -> 0.98425737 | AL77: =AL44+AL57+AL75 -> 189710.52 | AM77: % brut | AN77: =IFERROR(AO77/AO$30,0) -> 1.3090638 | AO77: =AO44+AO57+AO75 -> 148584.92
A78: =+$C$4&B78 -> Véhicules neufsProgramme neuf 1 | B78: Programme neuf 1 | E78: =+SUM(H78,K78,N78,Q78,T78,W78,Z78,AC78,AF78,AI78,AL78,AO78) -> 66483 | H78: 0 | K78: 0 | N78: 12255.3 | Q78: 0 | T78: 0 | W78: 20185.2 | Z78: 0 | AC78: 0 | AF78: 19143.9 | AI78: 0 | AL78: 0 | AO78: 14898.6
A79: =+$C$4&B79 -> Véhicules neufsProgramme neuf 2 | B79: Programme neuf 2 | E79: =+SUM(H79,K79,N79,Q79,T79,W79,Z79,AC79,AF79,AI79,AL79,AO79) -> 0 | H79: 0 | K79: 0 | N79: 0 | Q79: 0 | T79: 0 | W79: 0 | Z79: 0 | AC79: 0 | AF79: 0 | AI79: 0 | AL79: 0 | AO79: 0
A80: =+$C$4&B80 -> Véhicules neufsProgramme neuf 3 | B80: Programme neuf 3 | E80: =+SUM(H80,K80,N80,Q80,T80,W80,Z80,AC80,AF80,AI80,AL80,AO80) -> 0 | H80: 0 | K80: 0 | N80: 0 | Q80: 0 | T80: 0 | W80: 0 | Z80: 0 | AC80: 0 | AF80: 0 | AI80: 0 | AL80: 0 | AO80: 0
A81: =+$C$4&B81 -> Véhicules neufsHoldbacks | B81: Holdbacks | E81: =+SUM(H81,K81,N81,Q81,T81,W81,Z81,AC81,AF81,AI81,AL81,AO81) -> 868219.15 | H81: 40795.84 | K81: 41841.887 | N81: 77407.491 | Q81: 85775.868 | T81: 100420.53 | W81: 77407.491 | Z81: 88914.01 | AC81: 85775.868 | AF81: 75315.397 | AI81: 80545.632 | AL81: 72177.255 | AO81: 41841.887
A82: =+$C$4&B82 -> Véhicules neufs[...] | B82: [...] | E82: =+SUM(H82,K82,N82,Q82,T82,W82,Z82,AC82,AF82,AI82,AL82,AO82) -> 0 | H82: 0 | K82: 0 | N82: 0 | Q82: 0 | T82: 0 | W82: 0 | Z82: 0 | AC82: 0 | AF82: 0 | AI82: 0 | AL82: 0 | AO82: 0
A83: =+$C$4&B83 -> Véhicules neufs[...] | B83: [...] | E83: =+SUM(H83,K83,N83,Q83,T83,W83,Z83,AC83,AF83,AI83,AL83,AO83) -> 0 | H83: 0 | K83: 0 | N83: 0 | Q83: 0 | T83: 0 | W83: 0 | Z83: 0 | AC83: 0 | AF83: 0 | AI83: 0 | AL83: 0 | AO83: 0
A84: =+$C$4&B84 -> Véhicules neufs[...] | B84: [...] | E84: =+SUM(H84,K84,N84,Q84,T84,W84,Z84,AC84,AF84,AI84,AL84,AO84) -> 0 | H84: 0 | K84: 0 | N84: 0 | Q84: 0 | T84: 0 | W84: 0 | Z84: 0 | AC84: 0 | AF84: 0 | AI84: 0 | AL84: 0 | AO84: 0
A85: =+$C$4&B85 -> Véhicules neufsFrais administration | B85: Frais administration | E85: =+SUM(H85,K85,N85,Q85,T85,W85,Z85,AC85,AF85,AI85,AL85,AO85) -> 298053 | H85: 13802.42 | K85: 14374.239 | N85: 26592.343 | Q85: 29467.19 | T85: 34498.174 | W85: 26592.343 | Z85: 30545.258 | AC85: 29467.19 | AF85: 25873.631 | AI85: 27670.41 | AL85: 24795.563 | AO85: 14374.239
A86: =+$C$4&B86 -> Véhicules neufsAUTRES REVENUS | B86: AUTRES REVENUS | E86: =+SUM(E78:E85) -> 1232755.2 | H86: =+SUM(H78:H85) -> 54598.259 | K86: =+SUM(K78:K85) -> 56216.126 | N86: =+SUM(N78:N85) -> 116255.13 | Q86: =+SUM(Q78:Q85) -> 115243.06 | T86: =+SUM(T78:T85) -> 134918.7 | W86: =+SUM(W78:W85) -> 124185.03 | Z86: =+SUM(Z78:Z85) -> 119459.27 | AC86: =+SUM(AC78:AC85) -> 115243.06 | AF86: =+SUM(AF78:AF85) -> 120332.93 | AI86: =+SUM(AI78:AI85) -> 108216.04 | AL86: =+SUM(AL78:AL85) -> 96972.818 | AO86: =+SUM(AO78:AO85) -> 71114.726
A87: =+$C$4&B87 -> Véhicules neufs
A88: =+$C$4&B88 -> Véhicules neufsPROFIT DÉPARTEMENTAL | B88: PROFIT DÉPARTEMENTAL | E88: =E30-E77+E86 -> 1308725.1 | H88: =H30-H77+H86 -> 20274.484 | K88: =K30-K77+K86 -> 25685.508 | N88: =N30-N77+N86 -> 129334.04 | Q88: =Q30-Q77+Q86 -> 141101.09 | T88: =T30-T77+T86 -> 178230.63 | W88: =W30-W77+W86 -> 139316.36 | Z88: =Z30-Z77+Z86 -> 148444.2 | AC88: =AC30-AC77+AC86 -> 136951.82 | AF88: =AF30-AF77+AF86 -> 128720.53 | AI88: =AI30-AI77+AI86 -> 124624.81 | AL88: =AL30-AL77+AL86 -> 100007.13 | AO88: =AO30-AO77+AO86 -> 36034.528
B92: =B4 -> Budget 2022 | C92: Véhicules usagés
B94: Mois | C94: 2022 | F94: Janvier | I94: Février | L94: Mars | O94: Avril | R94: Mai | U94: Juin | X94: Juillet | AA94: Août | AD94: Septembre | AG94: Octobre | AJ94: Novembre | AM94: Décembre
C95: UNITE | D95: $P/UNITE | E95: $PROFITS | F95: UNITE | G95: $P/UNITE | H95: $PROFITS | I95: UNITE | J95: $P/UNITE | K95: $PROFITS | L95: UNITE | M95: $P/UNITE | N95: $PROFITS | O95: UNITE | P95: $P/UNITE | Q95: $PROFITS | R95: UNITE | S95: $P/UNITE | T95: $PROFITS | U95: UNITE | V95: $P/UNITE | W95: $PROFITS | X95: UNITE | Y95: $P/UNITE | Z95: $PROFITS | AA95: UNITE | AB95: $P/UNITE | AC95: $PROFITS | AD95: UNITE | AE95: $P/UNITE | AF95: $PROFITS | AG95: UNITE | AH95: $P/UNITE | AI95: $PROFITS | AJ95: UNITE | AK95: $P/UNITE | AL95: $PROFITS | AM95: UNITE | AN95: $P/UNITE | AO95: $PROFITS
A96: =+$C$92&B96 -> Véhicules usagésVentes nettes | B96: Ventes nettes | E96: =+SUM(H96,K96,N96,Q96,T96,W96,Z96,AC96,AF96,AI96,AL96,AO96) -> 14579073 | H96: 849266.38 | K96: 884652.48 | N96: 1415444 | Q96: 1380057.9 | T96: 1415444 | W96: 1486216.2 | Z96: 1415444 | AC96: 1309285.7 | AF96: 1096969.1 | AI96: 1273899.6 | AL96: 1096969.1 | AO96: 955424.68
A97: =+$C$92&B97 -> Véhicules usagésCertifié | B97: Certifié | C97: =+SUM(F97,I97,L97,O97,R97,U97,X97,AA97,AD97,AG97,AJ97,AM97) -> 445 | D97: =IF(C97=0,0,E97/C97) -> 1300 | E97: =+SUM(H97,K97,N97,Q97,T97,W97,Z97,AC97,AF97,AI97,AL97,AO97) -> 578500 | F97: 25.92233 | G97: =IF(F97=0,0,H97/F97) -> 1300 | H97: 33699.029 | I97: 27.002427 | J97: =IF(I97=0,0,K97/I97) -> 1300 | K97: 35103.155 | L97: 43.203883 | M97: =IF(L97=0,0,N97/L97) -> 1300 | N97: 56165.049 | O97: 42.123786 | P97: =IF(O97=0,0,Q97/O97) -> 1300 | Q97: 54760.922 | R97: 43.203883 | S97: =IF(R97=0,0,T97/R97) -> 1300 | T97: 56165.049 | U97: 45.364078 | V97: =IF(U97=0,0,W97/U97) -> 1300 | W97: 58973.301 | X97: 43.203883 | Y97: =IF(X97=0,0,Z97/X97) -> 1300 | Z97: 56165.049 | AA97: 39.963592 | AB97: =IF(AA97=0,0,AC97/AA97) -> 1300 | AC97: 51952.67 | AD97: 33.48301 | AE97: =IF(AD97=0,0,AF97/AD97) -> 1300 | AF97: 43527.913 | AG97: 38.883495 | AH97: =IF(AG97=0,0,AI97/AG97) -> 1300 | AI97: 50548.544 | AJ97: 33.48301 | AK97: =IF(AJ97=0,0,AL97/AJ97) -> 1300 | AL97: 43527.913 | AM97: 29.162621 | AN97: =IF(AM97=0,0,AO97/AM97) -> 1300 | AO97: 37911.408
A98: =+$C$92&B98 -> Véhicules usagésNon Certifié | B98: Non Certifié | C98: =+SUM(F98,I98,L98,O98,R98,U98,X98,AA98,AD98,AG98,AJ98,AM98) -> 25 | D98: =IF(C98=0,0,E98/C98) -> 900 | E98: =+SUM(H98,K98,N98,Q98,T98,W98,Z98,AC98,AF98,AI98,AL98,AO98) -> 22500 | F98: 1.4563107 | G98: =IF(F98=0,0,H98/F98) -> 900 | H98: 1310.6796 | I98: 1.5169903 | J98: =IF(I98=0,0,K98/I98) -> 900 | K98: 1365.2913 | L98: 2.4271845 | M98: =IF(L98=0,0,N98/L98) -> 900 | N98: 2184.466 | O98: 2.3665049 | P98: =IF(O98=0,0,Q98/O98) -> 900 | Q98: 2129.8544 | R98: 2.4271845 | S98: =IF(R98=0,0,T98/R98) -> 900 | T98: 2184.466 | U98: 2.5485437 | V98: =IF(U98=0,0,W98/U98) -> 900 | W98: 2293.6893 | X98: 2.4271845 | Y98: =IF(X98=0,0,Z98/X98) -> 900 | Z98: 2184.466 | AA98: 2.2451456 | AB98: =IF(AA98=0,0,AC98/AA98) -> 900 | AC98: 2020.6311 | AD98: 1.881068 | AE98: =IF(AD98=0,0,AF98/AD98) -> 900 | AF98: 1692.9612 | AG98: 2.184466 | AH98: =IF(AG98=0,0,AI98/AG98) -> 900 | AI98: 1966.0194 | AJ98: 1.881068 | AK98: =IF(AJ98=0,0,AL98/AJ98) -> 900 | AL98: 1692.9612 | AM98: 1.6383495 | AN98: =IF(AM98=0,0,AO98/AM98) -> 900 | AO98: 1474.5146
A99: =+$C$92&B99 -> Véhicules usagésTotal Usagés | B99: Total Usagés | C99: =+C97+C98 -> 470 | D99: =IF(C99<=0,0,E99/C99) -> 1278.7234 | E99: =+E97+E98 -> 601000 | F99: =+F97+F98 -> 27.378641 | G99: =IF(F99<=0,0,H99/F99) -> 1278.7234 | H99: =+H97+H98 -> 35009.709 | I99: =+I97+I98 -> 28.519417 | J99: =IF(I99<=0,0,K99/I99) -> 1278.7234 | K99: =+K97+K98 -> 36468.447 | L99: =+L97+L98 -> 45.631068 | M99: =IF(L99<=0,0,N99/L99) -> 1278.7234 | N99: =+N97+N98 -> 58349.515 | O99: =+O97+O98 -> 44.490291 | P99: =IF(O99<=0,0,Q99/O99) -> 1278.7234 | Q99: =+Q97+Q98 -> 56890.777 | R99: =+R97+R98 -> 45.631068 | S99: =IF(R99<=0,0,T99/R99) -> 1278.7234 | T99: =+T97+T98 -> 58349.515 | U99: =+U97+U98 -> 47.912621 | V99: =IF(U99<=0,0,W99/U99) -> 1278.7234 | W99: =+W97+W98 -> 61266.99 | X99: =+X97+X98 -> 45.631068 | Y99: =IF(X99<=0,0,Z99/X99) -> 1278.7234 | Z99: =+Z97+Z98 -> 58349.515 | AA99: =+AA97+AA98 -> 42.208738 | AB99: =IF(AA99<=0,0,AC99/AA99) -> 1278.7234 | AC99: =+AC97+AC98 -> 53973.301 | AD99: =+AD97+AD98 -> 35.364078 | AE99: =IF(AD99<=0,0,AF99/AD99) -> 1278.7234 | AF99: =+AF97+AF98 -> 45220.874 | AG99: =+AG97+AG98 -> 41.067961 | AH99: =IF(AG99<=0,0,AI99/AG99) -> 1278.7234 | AI99: =+AI97+AI98 -> 52514.563 | AJ99: =+AJ97+AJ98 -> 35.364078 | AK99: =IF(AJ99<=0,0,AL99/AJ99) -> 1278.7234 | AL99: =+AL97+AL98 -> 45220.874 | AM99: =+AM97+AM98 -> 30.800971 | AN99: =IF(AM99<=0,0,AO99/AM99) -> 1278.7234 | AO99: =+AO97+AO98 -> 39385.922
A100: =+$C$92&B100 -> Véhicules usagés
A101: =+$C$92&B101 -> Véhicules usagés | F101: 0 | H101: 0
A102: =+$C$92&B102 -> Véhicules usagésVentes au Gros | B102: Ventes au Gros | C102: =+SUM(F102,I102,L102,O102,R102,U102,X102,AA102,AD102,AG102,AJ102,AM102) -> 408.99067 | D102: =IF(C102=0,0,E102/C102) -> 212 | E102: =+SUM(H102,K102,N102,Q102,T102,W102,Z102,AC102,AF102,AI102,AL102,AO102) -> 86706.022 | F102: 23.824699 | G102: =IF(F102=0,0,H102/F102) -> 212 | H102: 5050.8362 | I102: 24.817395 | J102: =IF(I102=0,0,K102/I102) -> 212 | K102: 5261.2877 | L102: 39.707832 | M102: =IF(L102=0,0,N102/L102) -> 212 | N102: 8418.0604 | O102: 38.715136 | P102: =IF(O102=0,0,Q102/O102) -> 212 | Q102: 8207.6089 | R102: 39.707832 | S102: =IF(R102=0,0,T102/R102) -> 212 | T102: 8418.0604 | U102: 41.693224 | V102: =IF(U102=0,0,W102/U102) -> 212 | W102: 8838.9634 | X102: 39.707832 | Y102: =IF(X102=0,0,Z102/X102) -> 212 | Z102: 8418.0604 | AA102: 36.729745 | AB102: =IF(AA102=0,0,AC102/AA102) -> 212 | AC102: 7786.7059 | AD102: 30.77357 | AE102: =IF(AD102=0,0,AF102/AD102) -> 212 | AF102: 6523.9968 | AG102: 35.737049 | AH102: =IF(AG102=0,0,AI102/AG102) -> 212 | AI102: 7576.2544 | AJ102: 30.77357 | AK102: =IF(AJ102=0,0,AL102/AJ102) -> 212 | AL102: 6523.9968 | AM102: 26.802787 | AN102: =IF(AM102=0,0,AO102/AM102) -> 212 | AO102: 5682.1908
A103: =+$C$92&B103 -> Véhicules usagés
A104: =+$C$92&B104 -> Véhicules usagésRev. Finances | B104: Rev. Finances | D104: =IF(C99=0,0,E104/C99) -> 658.96091 | E104: =+SUM(H104,K104,N104,Q104,T104,W104,Z104,AC104,AF104,AI104,AL104,AO104) -> 309711.63 | G104: =IF(F99=0,0,H104/F99) -> 658.96091 | H104: 18041.454 | J104: =IF(I99=0,0,K104/I99) -> 658.96091 | K104: 18793.181 | M104: =IF(L99=0,0,N104/L99) -> 658.96091 | N104: 30069.09 | P104: =IF(O99=0,0,Q104/O99) -> 658.96091 | Q104: 29317.363 | S104: =IF(R99=0,0,T104/R99) -> 658.96091 | T104: 30069.09 | V104: =IF(U99=0,0,W104/U99) -> 658.96091 | W104: 31572.545 | Y104: =IF(X99=0,0,Z104/X99) -> 658.96091 | Z104: 30069.09 | AB104: =IF(AA99=0,0,AC104/AA99) -> 658.96091 | AC104: 27813.908 | AE104: =IF(AD99=0,0,AF104/AD99) -> 658.96091 | AF104: 23303.545 | AH104: =IF(AG99=0,0,AI104/AG99) -> 658.96091 | AI104: 27062.181 | AK104: =IF(AJ99=0,0,AL104/AJ99) -> 658.96091 | AL104: 23303.545 | AN104: =IF(AM99=0,0,AO104/AM99) -> 658.96091 | AO104: 20296.636
A105: =+$C$92&B105 -> Véhicules usagésRev. Protections | B105: Rev. Protections | D105: =IF(C99=0,0,E105/C99) -> 1161.8447 | E105: =+SUM(H105,K105,N105,Q105,T105,W105,Z105,AC105,AF105,AI105,AL105,AO105) -> 546067 | G105: =IF(F99=0,0,H105/F99) -> 1161.8447 | H105: 31809.728 | J105: =IF(I99=0,0,K105/I99) -> 1161.8447 | K105: 33135.133 | M105: =IF(L99=0,0,N105/L99) -> 1161.8447 | N105: 53016.214 | P105: =IF(O99=0,0,Q105/O99) -> 1161.8447 | Q105: 51690.808 | S105: =IF(R99=0,0,T105/R99) -> 1161.8447 | T105: 53016.214 | V105: =IF(U99=0,0,W105/U99) -> 1161.8447 | W105: 55667.024 | Y105: =IF(X99=0,0,Z105/X99) -> 1161.8447 | Z105: 53016.214 | AB105: =IF(AA99=0,0,AC105/AA99) -> 1161.8447 | AC105: 49039.998 | AE105: =IF(AD99=0,0,AF105/AD99) -> 1161.8447 | AF105: 41087.566 | AH105: =IF(AG99=0,0,AI105/AG99) -> 1161.8447 | AI105: 47714.592 | AK105: =IF(AJ99=0,0,AL105/AJ99) -> 1161.8447 | AL105: 41087.566 | AN105: =IF(AM99=0,0,AO105/AM99) -> 1161.8447 | AO105: 35785.944
A106: =+$C$92&B106 -> Véhicules usagésRev. Autres | B106: Rev. Autres | D106: =IF(C99=0,0,E106/C99) -> 32.953208 | E106: =+SUM(H106,K106,N106,Q106,T106,W106,Z106,AC106,AF106,AI106,AL106,AO106) -> 15488.008 | G106: =IF(F99=0,0,H106/F99) -> 32.953208 | H106: 902.21403 | J106: =IF(I99=0,0,K106/I99) -> 32.953208 | K106: 939.80628 | M106: =IF(L99=0,0,N106/L99) -> 32.953208 | N106: 1503.6901 | P106: =IF(O99=0,0,Q106/O99) -> 32.953208 | Q106: 1466.0978 | S106: =IF(R99=0,0,T106/R99) -> 32.953208 | T106: 1503.6901 | V106: =IF(U99=0,0,W106/U99) -> 32.953208 | W106: 1578.8746 | Y106: =IF(X99=0,0,Z106/X99) -> 32.953208 | Z106: 1503.6901 | AB106: =IF(AA99=0,0,AC106/AA99) -> 32.953208 | AC106: 1390.9133 | AE106: =IF(AD99=0,0,AF106/AD99) -> 32.953208 | AF106: 1165.3598 | AH106: =IF(AG99=0,0,AI106/AG99) -> 32.953208 | AI106: 1353.321 | AK106: =IF(AJ99=0,0,AL106/AJ99) -> 32.953208 | AL106: 1165.3598 | AN106: =IF(AM99=0,0,AO106/AM99) -> 32.953208 | AO106: 1014.9908
...

Sheet Capex
A1: CONCESSION
A2: Forecast Immobilisation 2022 | H2: 1 | I2: 2 | J2: 3 | K2: 4 | L2: 5 | M2: 6 | N2: 7 | O2: 8 | P2: 9 | Q2: 10 | R2: 11 | S2: 12
H3: =+IF(VLOOKUP(H2,Parametres!$L$3:$N$14,3,0)="X","REEL","FORECAST") -> REEL | I3: =+IF(VLOOKUP(I2,Parametres!$L$3:$N$14,3,0)="X","REEL","FORECAST") -> REEL | J3: =+IF(VLOOKUP(J2,Parametres!$L$3:$N$14,3,0)="X","REEL","FORECAST") -> REEL | K3: =+IF(VLOOKUP(K2,Parametres!$L$3:$N$14,3,0)="X","REEL","FORECAST") -> REEL | L3: =+IF(VLOOKUP(L2,Parametres!$L$3:$N$14,3,0)="X","REEL","FORECAST") -> REEL | M3: =+IF(VLOOKUP(M2,Parametres!$L$3:$N$14,3,0)="X","REEL","FORECAST") -> FORECAST | N3: =+IF(VLOOKUP(N2,Parametres!$L$3:$N$14,3,0)="X","REEL","FORECAST") -> FORECAST | O3: =+IF(VLOOKUP(O2,Parametres!$L$3:$N$14,3,0)="X","REEL","FORECAST") -> FORECAST | ... S3: =+IF(VLOOKUP(S2,Parametres!$L$3:$N$14,3,0)="X","REEL","FORECAST") -> FORECAST
A4: Concession | B4: Budgété / Non budgété | C4: Projet | D4: Catégorie Immo | E4: Total forecast | F4: Budget Annuel | G4: Écart vs budget | H4: January | I4: February | J4: March | K4: April | L4: May | M4: June | N4: July | O4: August | P4: September | Q4: October | R4: November | S4: December | T4: Raison / Description
C5: Total | E5: =+SUM(E6:E21) -> 56200 | F5: =+SUM(F6:F21) -> 56200 | G5: =+SUM(G6:G21) -> 0 | H5: =+SUM(H6:H21) -> 0 | I5: =+SUM(I6:I21) -> 1500 | J5: =+SUM(J6:J21) -> 0 | K5: =+SUM(K6:K21) -> 15100 | L5: =+SUM(L6:L21) -> 0 | ... S5: =+SUM(S6:S21) -> 8200 | X5: Terrain
A6: =+Parametres!$B$1 -> Volks | B6: oui | C6: Équipement Informatique | D6: Informatique | E6: =+SUM(H6:S6) -> 3000 | F6: 3000 | G6: =+E6-F6 -> 0 | K6: 1000 | M6: 1000 | P6: 1000 | T6: Directeur adjoint des ventes | X6: Bâtisse
A7: =+Parametres!$B$1 -> Volks | B7: oui | C7: Équipements Service | D7: Équipement | E7: =+SUM(H7:S7) -> 5000 | F7: 5000 | G7: =+E7-F7 -> 0 | K7: =$F$7/4 -> 1250 | M7: =$F$7/4 -> 1250 | P7: =$F$7/4 -> 1250 | S7: =$F$7/4 -> 1250 | T7: 4 ordinateurs de diagnostic | X7: Améliorations Locatives
A8: =+Parametres!$B$1 -> Volks | B8: oui | C8: Améliorations Locatives | D8: Amélioration locative | E8: =+SUM(H8:S8) -> 5000 | F8: 5000 | G8: =+E8-F8 -> 0 | K8: =$F$8/4 -> 1250 | M8: =$F$8/4 -> 1250 | P8: =$F$8/4 -> 1250 | S8: =$F$8/4 -> 1250 | T8: pour non planifié | X8: Améliorations Locatives Permanentes
A9: =+Parametres!$B$1 -> Volks | B9: oui | C9: Réparation machine à pneus | D9: Equipement | E9: =+SUM(H9:S9) -> 3000 | F9: 3000 | G9: =+E9-F9 -> 0 | M9: 3000 | T9: pour non planifié | X9: Mobilier
A10: =+Parametres!$B$1 -> Volks | B10: oui | C10: Remplacement machine de balancement | D10: Équipement | E10: =+SUM(H10:S10) -> 10000 | F10: 10000 | G10: =+E10-F10 -> 0 | M10: 10000 | T10: équipement solution (imposé par VW) et non planifié | X10: Équipements Informatique
A11: =+Parametres!$B$1 -> Volks | B11: oui | C11: Chargeur de batterie | D11: Équipement | E11: =+SUM(H11:S11) -> 900 | F11: 900 | G11: =+E11-F11 -> 0 | K11: 900 | X11: Équipements Téléphonique
A12: =+Parametres!$B$1 -> Volks | B12: oui | C12: 4 ordinateur de diagnostic | D12: Équipement | E12: =+SUM(H12:S12) -> 22800 | F12: 22800 | G12: =+E12-F12 -> 0 | K12: =$F$12/4 -> 5700 | M12: =$F$12/4 -> 5700 | P12: =$F$12/4 -> 5700 | S12: =$F$12/4 -> 5700 | X12: Enseigne
A13: =+Parametres!$B$1 -> Volks | B13: oui | C13: Testeur rapide | D13: Équipement | E13: =+SUM(H13:S13) -> 2000 | F13: 2000 | G13: =+E13-F13 -> 0 | K13: 2000
A14: =+Parametres!$B$1 -> Volks | B14: oui | C14: Testeur batterie | D14: Équipement | E14: =+SUM(H14:S14) -> 3000 | F14: 3000 | G14: =+E14-F14 -> 0 | K14: 3000
A15: =+Parametres!$B$1 -> Volks | B15: non | C15: 1 laptop Dir adj ventes | D15: Informatique | E15: =+SUM(H15:S15) -> 1500 | F15: 1500 | G15: =+E15-F15 -> 0 | I15: 1500
A16: =+Parametres!$B$1 -> Volks | B16: non | E16: =+SUM(H16:S16) -> 0 | G16: =+E16-F16 -> 0
A17: =+Parametres!$B$1 -> Volks | B17: non | E17: =+SUM(H17:S17) -> 0 | G17: =+E17-F17 -> 0
A18: =+Parametres!$B$1 -> Volks | B18: non | E18: =+SUM(H18:S18) -> 0 | G18: =+E18-F18 -> 0 | X18: non
A19: =+Parametres!$B$1 -> Volks | B19: non | E19: =+SUM(H19:S19) -> 0 | G19: =+E19-F19 -> 0
A20: =+Parametres!$B$1 -> Volks | B20: non | E20: =+SUM(H20:S20) -> 0 | G20: =+E20-F20 -> 0
A21: =+Parametres!$B$1 -> Volks | B21: non | E21: =+SUM(H21:S21) -> 0 | G21: =+E21-F21 -> 0

Sheet Inventaire_Neuf
A1: #Contrôle | B1: Année | C1: Marque | D1: Modèle | E1: $ Inventaire | F1: $ Financé | G1: NIV | H1: Jours en stock | L1: $ Inventaire | M1: $ Financé
A2: 211014 | B2: 2021 | C2: Volkwagen | D2: ATLAS | E2: 51942.11 | F2: -40263.3 | G2: 1V2BC2CAXMC221804 | H2: 250 | K2: CTRL | L2: =+SUM(E2:E10000) -> 1188579 | M2: =+SUM(F2:F10000) -> -1232044.2
A3: 220159 | B3: 2022 | C3: Volkwagen | D3: ATLAS | E3: 47746.5 | F3: -45047.55 | G3: 1V2LE2CA1NC207452 | H3: 146 | K3: Unités | L3: =COUNT(E:E) -> 29
A4: 220189 | B4: 2022 | C4: Volkwagen | D4: TAOS | E4: 31066.27 | F4: -31255.35 | G4: 3VVAX7B23NM030929 | H4: 133
A5: 220221 | B5: 2022 | C5: Volkwagen | D5: TIGUAN | E5: 40977.51 | F5: -41407.8 | G5: 3VV8B7AX1NM057041 | H5: 120
A6: 220229 | B6: 2022 | C6: Volkwagen | D6: TIGUAN | E6: 39676.65 | F6: -36187.4 | G6: 3VV2B7AX4NM056973 | H6: 113
A7: 220232 | B7: 2022 | C7: Volkwagen | D7: TIGUAN | E7: 41060.19 | F7: -41213.55 | G7: 3VV8B7AX7NM058209 | H7: 104
A8: 220249 | B8: 2022 | C8: Volkwagen | D8: JETTA | E8: 27411.8 | F8: -28653.45 | G8: 3VWEM7BU3NM002118 | H8: 70
A9: 220271 | B9: 2022 | C9: Volkwagen | D9: ATLAS | E9: 46928.48 | F9: -52835.79 | G9: 1V2BC2CA3NC201508 | H9: 63
A10: 220303 | B10: 2022 | C10: Volkwagen | D10: GTI | E10: 32826 | F10: -34950.3 | G10: WVWP87CD7NW160248 | H10: 20
A11: 220313 | B11: 2022 | C11: Volkwagen | D11: TAOS | E11: 36922 | F11: -39356.1 | G11: 3VV2X7B21NM061729 | H11: 1
A12: 220330 | B12: 2022 | C12: Volkwagen | D12: ATLAS | E12: 54287 | F12: -57589.35 | G12: 1V2FR2CA5NC529660 | H12: 20
A13: 220347 | B13: 2022 | C13: Volkwagen | D13: TAOS | E13: 33327 | F13: -35581.35 | G13: 3VVLX7B22NM065776 | H13: 6
A14: 220349 | B14: 2022 | C14: Volkwagen | D14: ATLAS | E14: 51112.5 | F14: -53295.9 | G14: 1V2BE2CA8NC220162 | H14: 8
A15: 220351 | B15: 2022 | C15: Volkwagen | D15: TIGUAN | E15: 39331 | F15: -41885.55 | G15: 3VV8B7AXXNM105054 | H15: 8
... A30: 220368 | B30: 2022 | C30: Volkwagen | D30: JETTA | E30: 24703 | F30: -26421.15 | G30: 3VWCM7BUXNM014113 | H30: 0

Sheet Inventaire_Used
A1: #Contrôle | B1: Année | C1: Marque | D1: Modèle | E1: Amount | F1: Financé | G1: NIV | H1: Jours en stock | L1: $ Inventaire | M1: $ Financé
A2: 5106PB | B2: 2006 | C2: AUDI A4 | D2: A4 | E2: 1915 | F2: 0 | G2: WAUKG78E16A003423 | H2: 17 | K2: CTRL | L2: =+SUM(E:E) -> 2677576.6 | M2: =+SUM(F:F) -> -1547651.2
A3: 4906P | B3: 2009 | C3: CADILLAC TRUCK SRX | D3: SRK | E3: 9677.43 | F3: 0 | G3: 1GYEE437690117273 | H3: 472 | K3: Unités | L3: =COUNT(E:E) -> 103
A4: 220297A | B4: 2019 | C4: FORD | D4: MUSTANG | E4: 29888.9 | F4: 0 | G4: 1FA6P8TH0K5162731 | H4: 43
A5: 5179P | B5: 2009 | C5: FORD PICK-UP | D5: RANGER | E5: 8679 | F5: 0 | G5: 1FTZR45E59PA43844 | H5: 25 | K5: Moyenne | L5: =+L2/L3 -> 25995.889
A6: 5199P | B6: 2019 | C6: JEEP GRAND CHEROKEE | D6: CHEROKEE | E6: 38915 | F6: 0 | G6: 1C4RJFAG5KC766665 | H6: 8
A7: 5109PA | B7: 2018 | C7: JEEP WRANGLER | D7: WRANGLER | E7: 33876.48 | F7: 0 | G7: 1C4GJXAN6JW212401 | H7: 74
A8: 220275A | B8: 2019 | C8: JEEP WRANGLER | D8: WRANGLER | E8: 47489.03 | F8: 0 | G8: 1C4HJXEG9KW543703 | H8: 57
A9: 5177PA | B9: 2013 | C9: JEEP WRANGLER UNLIMI | D9: WRANGLER | E9: 21415 | F9: 0 | G9: 1C4BJWEG8DL608836 | H9: 10
A10: 220067A | B10: 2010 | C10: KIA | D10: FORTE | E10: 3315 | F10: 0 | G10: KNAFT4A20A5141032 | H10: 17
A11: 5158PA | B11: 2007 | C11: KIA | D11: RONDO | E11: 1165 | F11: 0 | G11: KNAFG525977106652 | H11: 15
A12: 5134PA | B12: 2015 | C12: MERCEDES LIGHT TRUCK GLK-CLASS | D12: GLK | E12: 20703.23 | F12: 0 | G12: WDCGG0EBXFG348788 | H12: 42
A13: 220247B | B13: 2019 | C13: NISSAN | D13: MICRA | E13: 12765 | F13: 0 | G13: 3N1CK3CP6KL234797 | H13: 11
A14: 5172P | B14: 2019 | C14: VOLKSWAGEN | D14: ARTEON | E14: 36175 | F14: -31950 | G14: WVWSR7AN5KE007291 | H14: 37
A15: 5123P | B15: 2020 | C15: VOLKSWAGEN | D15: ARTEON | E15: 42444.1 | F15: -37125 | G15: WVWSR7ANXLE017011 | H15: 80
A16: 220242A | B16: 2018 | C16: VOLKSWAGEN | D16: ATLAS | E16: 31425.01 | F16: -22340 | G16: 1V2LR2CA8JC563718 | H16: 86
A17: 5197P | B17: 2018 | C17: VOLKSWAGEN | D17: ATLAS | E17: 37165 | F17: -33075 | G17: 1V2RR2CAXJC558790 | H17: 9
... A104: 5180P | B104: 2016 | C104: VOLKSWAGEN | D104: TOUAREG | E104: 36152.03 | F104: 0 | G104: WVGEP9BP3GD003909 | H104: 25

Sheet 2pager
B1: =Parametres!$B$1&" "&"2 pager"&" "&Parametres!$B$3&" "&Parametres!$B$4 -> Volks 2 pager Mai 2022
B3: New | C3: Actual | D3: Forecast | E3: Budget | F3: 2021 | G3: ▲ Forecast | H3: ▲ Budget | I3: ▲2021 | J3: % ▲ Forecast | K3: % ▲ Budget | L3: % ▲ 2021 | M3: Commentaires
B4: Units | C4: =+Print_Mois!$J$13+Print_Mois!$J$15 -> 46 | D4: =+Print_Mois!$G$13+Print_Mois!$G$15 -> 94.612048 | E4: =+Print_Mois!$D$13+Print_Mois!$D$15 -> 94.612048 | F4: =+Print_Mois!$O$13+Print_Mois!$O$15 -> 87 | G4: =+IFERROR($C4-D4,"") -> -48.612048 | H4: =+IFERROR($C4-E4,"") -> -48.612048 | I4: =+IFERROR($C4-F4,"") -> -41 | J4: =+IFERROR(G4/ABS($D4),"") -> -0.51380399 | K4: =+IFERROR(H4/ABS($E4),"") -> -0.51380399 | L4: =+IFERROR(I4/ABS($F4),"") -> -0.47126437 | M4: Des unités qui commencent disponibles toujours pour environ la moitié de nos prévisions. Les informations du manufacturier ne sont pas optimistes pour la fin de l’année. Dans un volume en dessous du budget de près de 52%, on ne manque le budget de brut que de 10%. Une moyenne front comme back plus haute que tous les autres mois confondus, un record a été atteint et au-delà des moyennes du groupe excellence. Les faibles volumes commencent à peser lourd dans le manque à gagner des autres revenus de type holdbacks, frais de documentation et expérience+. Les ratios de dépenses restent sous contrôle tout comme la vibe à la concession. Retard de 60433$ sur le budget.
B5: Front Margin | C5: =+Print_Mois!$L$13+Print_Mois!$L$15 -> 176182.09 | D5: =+Print_Mois!$I$13+Print_Mois!$I$15 -> 179068.1 | E5: =+Print_Mois!$F$13+Print_Mois!$F$15 -> 179068.1 | F5: =+Print_Mois!$Q$13+Print_Mois!$Q$15 -> 158566.14 | G5: =+IFERROR($C5-D5,"") -> -2886.006 | H5: =+IFERROR($C5-E5,"") -> -2886.006 | I5: =+IFERROR($C5-F5,"") -> 17615.95 | J5: =+IFERROR(G5/ABS($D5),"") -> -0.016116807 | K5: =+IFERROR(H5/ABS($E5),"") -> -0.016116807 | L5: =+IFERROR(I5/ABS($F5),"") -> 0.11109528
B6: Front margin / unit | C6: =+C5/C4 -> 3830.0454 | D6: =+D5/D4 -> 1892.6564 | E6: =+E5/E4 -> 1892.6564 | F6: =+F5/F4 -> 1822.5993 | G6: =+IFERROR($C6-D6,"") -> 1937.3891 | H6: =+IFERROR($C6-E6,"") -> 1937.3891 | I6: =+IFERROR($C6-F6,"") -> 2007.4461 | J6: =+IFERROR(G6/ABS($D6),"") -> 1.0236349 | K6: =+IFERROR(H6/ABS($E6),"") -> 1.0236349 | L6: =+IFERROR(I6/ABS($F6),"") -> 1.1014193
B7: $ Salaires et commission | C7: =+Print_Mois!$L$31 -> 50247.99 | D7: =+Print_Mois!$I$31 -> 56024.457 | E7: =+Print_Mois!$F$31 -> 56024.457 | F7: =+Print_Mois!$Q$31 -> 53186.03 | G7: =+IFERROR($C7-D7,"") -> -5776.4671 | H7: =+IFERROR($C7-E7,"") -> -5776.4671 | I7: =+IFERROR($C7-F7,"") -> -2938.04 | J7: =+IFERROR(G7/ABS($D7),"") -> -0.10310617 | K7: =+IFERROR(H7/ABS($E7),"") -> -0.10310617 | L7: =+IFERROR(I7/ABS($F7),"") -> -0.055240822
B8: % Salaires et commission | C8: =+C7/C5 -> 0.28520487 | D8: =+D7/D5 -> 0.31286677 | E8: =+E7/E5 -> 0.31286677 | F8: =+F7/F5 -> 0.33541858 | G8: =+IFERROR($C8-D8,"") -> -0.027661902 | H8: =+IFERROR($C8-E8,"") -> -0.027661902 | I8: =+IFERROR($C8-F8,"") -> -0.050213713 | J8: =+IFERROR(G8/ABS($D8),"") -> -0.088414317 | K8: =+IFERROR(H8/ABS($E8),"") -> -0.088414317 | L8: =+IFERROR(I8/ABS($F8),"") -> -0.14970463
B9: Back Margin | C9: =+Print_Mois!$L$24 -> 57567.54 | D9: =+Print_Mois!$I$24 -> 80420.241 | E9: =+Print_Mois!$F$24 -> 80420.241 | F9: =+Print_Mois!$Q$24 -> 68148.59 | G9: =+IFERROR($C9-D9,"") -> -22852.701 | H9: =+IFERROR($C9-E9,"") -> -22852.701 | I9: =+IFERROR($C9-F9,"") -> -10581.05 | J9: =+IFERROR(G9/ABS($D9),"") -> -0.28416603 | K9: =+IFERROR(H9/ABS($E9),"") -> -0.28416603 | L9: =+IFERROR(I9/ABS($F9),"") -> -0.1552644
B10: Back Margin / unit | C10: =+C9/C4 -> 1251.4683 | D10: =+D9/D4 -> 850 | E10: =+E9/E4 -> 850 | F10: =+F9/F4 -> 783.31713 | G10: =+IFERROR($C10-D10,"") -> 401.46826 | H10: =+IFERROR($C10-E10,"") -> 401.46826 | I10: =+IFERROR($C10-F10,"") -> 468.15113 | J10: =+IFERROR(G10/ABS($D10),"") -> 0.4723156 | K10: =+IFERROR(H10/ABS($E10),"") -> 0.4723156 | L10: =+IFERROR(I10/ABS($F10),"") -> 0.59765211
B11: $ commission FI | C11: =+Print_Mois!$L$32 -> 20885.45 | D11: =+Print_Mois!$I$32 -> 24126.072 | E11: =+Print_Mois!$F$32 -> 24126.072 | F11: =+Print_Mois!$Q$32 -> 20948.72 | G11: =+IFERROR($C11-D11,"") -> -3240.6223 | H11: =+IFERROR($C11-E11,"") -> -3240.6223 | I11: =+IFERROR($C11-F11,"") -> -63.27 | J11: =+IFERROR(G11/ABS($D11),"") -> -0.13432034 | K11: =+IFERROR(H11/ABS($E11),"") -> -0.13432034 | L11: =+IFERROR(I11/ABS($F11),"") -> -0.0030202323
B12: % commission FI | C12: =+C11/C9 -> 0.36279907 | D12: =+D11/D9 -> 0.3 | E12: =+E11/E9 -> 0.3 | F12: =+F11/F9 -> 0.3073977 | G12: =+IFERROR($C12-D12,"") -> 0.06279907 | H12: =+IFERROR($C12-E12,"") -> 0.06279907 | I12: =+IFERROR($C12-F12,"") -> 0.055401368 | J12: =+IFERROR(G12/ABS($D12),"") -> 0.20933023 | K12: =+IFERROR(H12/ABS($E12),"") -> 0.20933023 | L12: =+IFERROR(I12/ABS($F12),"") -> 0.18022701
B13: Variable fees | C13: =+Print_Mois!$L$41-C7-C11 -> 27329.76 | D13: =+Print_Mois!$I$41-D7-D11 -> 44726.067 | E13: =+Print_Mois!$F$41-E7-E11 -> 44726.067 | F13: =+Print_Mois!$Q$41-F7-F11 -> 32717.33 | G13: =+IFERROR($C13-D13,"") -> -17396.307 | H13: =+IFERROR($C13-E13,"") -> -17396.307 | I13: =+IFERROR($C13-F13,"") -> -5387.57 | J13: =+IFERROR(G13/ABS($D13),"") -> -0.3889523 | K13: =+IFERROR(H13/ABS($E13),"") -> -0.3889523 | L13: =+IFERROR(I13/ABS($F13),"") -> -0.16467022
B14: Variable fees / units | C14: =+C13/C4 -> 594.12522 | D14: =+D13/D4 -> 472.7312 | E14: =+E13/E4 -> 472.7312 | F14: =+F13/F4 -> 376.06126 | G14: =+IFERROR($C14-D14,"") -> 121.39402 | H14: =+IFERROR($C14-E14,"") -> 121.39402 | I14: =+IFERROR($C14-F14,"") -> 218.06395 | J14: =+IFERROR(G14/ABS($D14),"") -> 0.25679292 | K14: =+IFERROR(H14/ABS($E14),"") -> 0.25679292 | L14: =+IFERROR(I14/ABS($F14),"") -> 0.57986284
B15: Other Revenues | C15: =+Print_Mois!$L$83 -> 70701 | D15: =+Print_Mois!$I$83 -> 134918.7 | E15: =+Print_Mois!$F$83 -> 134918.7 | F15: =+Print_Mois!$Q$83 -> 128055 | G15: =+IFERROR($C15-D15,"") -> -64217.703 | H15: =+IFERROR($C15-E15,"") -> -64217.703 | I15: =+IFERROR($C15-F15,"") -> -57354 | J15: =+IFERROR(G15/ABS($D15),"") -> -0.47597332 | K15: =+IFERROR(H15/ABS($E15),"") -> -0.47597332 | L15: =+IFERROR(I15/ABS($F15),"") -> -0.44788567
B16: Inventory
B17: Units | C17: =Inventaire_Neuf!L3 -> 29 | D17: 61 | E17: 61 | F17: 164 | G17: =+IFERROR($C17-D17,"") -> -32 | H17: =+IFERROR($C17-E17,"") -> -32 | I17: =+IFERROR($C17-F17,"") -> -135 | J17: =+IFERROR(G17/ABS($D17),"") -> -0.52459016 | K17: =+IFERROR(H17/ABS($E17),"") -> -0.52459016 | L17: =+IFERROR(I17/ABS($F17),"") -> -0.82317073
B18: $ | C18: =Inventaire_Neuf!L2 -> 1188579 | D18: 2233570 | E18: 2233570 | F18: 5689693.2 | G18: =+IFERROR($C18-D18,"") -> -1044991 | H18: =+IFERROR($C18-E18,"") -> -1044991 | I18: =+IFERROR($C18-F18,"") -> -4501114.2 | J18: =+IFERROR(G18/ABS($D18),"") -> -0.46785683 | K18: =+IFERROR(H18/ABS($E18),"") -> -0.46785683 | L18: =+IFERROR(I18/ABS($F18),"") -> -0.79109963
C19: =C18/C17 -> 40985.483 | D19: =D18/D17 -> 36615.902 | E19: =E18/E17 -> 36615.902 | F19: =F18/F17 -> 34693.251
B20: Used | C20: Actual | D20: Forecast | E20: Budget | F20: 2021 | G20: ▲ Forecast | H20: ▲ Budget | I20: ▲2021 | J20: % ▲ Forecast | K20: % ▲ Budget | L20: % ▲ 2021 | M20: Commentaires
B21: Units | C21: =+Print_Mois!$J$96 -> 32 | D21: =+Print_Mois!$G$96 -> 45.631068 | E21: =+Print_Mois!$D$96 -> 45.631068 | F21: =+Print_Mois!$O$96 -> 39 | G21: =+IFERROR($C21-D21,"") -> -13.631068 | H21: =+IFERROR($C21-E21,"") -> -13.631068 | I21: =+IFERROR($C21-F21,"") -> -7 | J21: =+IFERROR(G21/ABS($D21),"") -> -0.2987234 | K21: =+IFERROR(H21/ABS($E21),"") -> -0.2987234 | L21: =+IFERROR(I21/ABS($F21),"") -> -0.17948718 | M21: Le marché change. Quelques gros VUS et Pick-ups partis à l’encan. Une stratégie d’affichage en ligne plus poussée avec Kijiji, trader et Otogo maintenant. On fait le point début juillet des choix finaux à faire pour garder la meilleure combinaison. L’inventaire est sain et plutôt avec une bonne variété de produit dans le contexte actuel. On doit continuer de pousser plus fort dans ce département. Mais aussi sans doute revoir les plans de paye devenus anormalement généreux. Avance de 8777$ sur le budget
B22: Front Margin | C22: =+Print_Mois!$L$96 -> 65718.06 | D22: =+Print_Mois!$I$96 -> 58349.515 | E22: =+Print_Mois!$F$96 -> 58349.515 | F22: =+Print_Mois!$Q$96 -> 49609.78 | G22: =+IFERROR($C22-D22,"") -> 7368.5454 | H22: =+IFERROR($C22-E22,"") -> 7368.5454 | I22: =+IFERROR($C22-F22,"") -> 16108.28 | J22: =+IFERROR(G22/ABS($D22),"") -> 0.12628289 | K22: =+IFERROR(H22/ABS($E22),"") -> 0.12628289 | L22: =+IFERROR(I22/ABS($F22),"") -> 0.32469969
B23: Front margin / unit | C23: =+C22/C21 -> 2053.6894 | D23: =+D22/D21 -> 1278.7234 | E23: =+E22/E21 -> 1278.7234 | F23: =+F22/F21 -> 1272.0456 | G23: =+IFERROR($C23-D23,"") -> 774.96597 | H23: =+IFERROR($C23-E23,"") -> 774.96597 | I23: =+IFERROR($C23-F23,"") -> 781.64373 | J23: =+IFERROR(G23/ABS($D23),"") -> 0.6060466 | K23: =+IFERROR(H23/ABS($E23),"") -> 0.6060466 | L23: =+IFERROR(I23/ABS($F23),"") -> 0.61447774
B24: $ Salaires et commission | C24: =+Print_Mois!$L$111 -> 27153.34 | D24: =+Print_Mois!$I$111 -> 22233.252 | E24: =+Print_Mois!$F$111 -> 22233.252 | F24: =+Print_Mois!$Q$111 -> 18860.02 | G24: =+IFERROR($C24-D24,"") -> 4920.0876 | H24: =+IFERROR($C24-E24,"") -> 4920.0876 | I24: =+IFERROR($C24-F24,"") -> 8293.32 | J24: =+IFERROR(G24/ABS($D24),"") -> 0.2212941 | K24: =+IFERROR(H24/ABS($E24),"") -> 0.2212941 | L24: =+IFERROR(I24/ABS($F24),"") -> 0.43973018
B25: % Salaires et commission | C25: =+C24/C22 -> 0.41317927 | D25: =+D24/D22 -> 0.38103577 | E25: =+E24/E22 -> 0.38103577 | F25: =+F24/F22 -> 0.38016738 | G25: =+IFERROR($C25-D25,"") -> 0.032143495 | H25: =+IFERROR($C25-E25,"") -> 0.032143495 | I25: =+IFERROR($C25-F25,"") -> 0.033011891 | J25: =+IFERROR(G25/ABS($D25),"") -> 0.084358209 | K25: =+IFERROR(H25/ABS($E25),"") -> 0.084358209 | L25: =+IFERROR(I25/ABS($F25),"") -> 0.086835149
B26: Back Margin | C26: =+Print_Mois!$L$104 -> 96011.69 | D26: =+Print_Mois!$I$104 -> 84588.994 | E26: =+Print_Mois!$F$104 -> 84588.994 | F26: =+Print_Mois!$Q$104 -> 82955.14 | G26: =+IFERROR($C26-D26,"") -> 11422.696 | H26: =+IFERROR($C26-E26,"") -> 11422.696 | I26: =+IFERROR($C26-F26,"") -> 13056.55 | J26: =+IFERROR(G26/ABS($D26),"") -> 0.13503762 | K26: =+IFERROR(H26/ABS($E26),"") -> 0.13503762 | L26: =+IFERROR(I26/ABS($F26),"") -> 0.1573929
B27: Back Margin / unit | C27: =+C26/C21 -> 3000.3653 | D27: =+D26/D21 -> 1853.7588 | E27: =+E26/E21 -> 1853.7588 | F27: =+F26/F21 -> 2127.0549 | G27: =+IFERROR($C27-D27,"") -> 1146.6065 | H27: =+IFERROR($C27-E27,"") -> 1146.6065 | I27: =+IFERROR($C27-F27,"") -> 873.31044 | J27: =+IFERROR(G27/ABS($D27),"") -> 0.61853058 | K27: =+IFERROR(H27/ABS($E27),"") -> 0.61853058 | L27: =+IFERROR(I27/ABS($F27),"") -> 0.4105726
B28: $ commission FI | C28: =+Print_Mois!$L$112 -> 27749.38 | D28: =+Print_Mois!$I$112 -> 25376.698 | E28: =+Print_Mois!$F$112 -> 25376.698 | F28: =+Print_Mois!$Q$112 -> 24245.08 | G28: =+IFERROR($C28-D28,"") -> 2372.6819 | H28: =+IFERROR($C28-E28,"") -> 2372.6819 | I28: =+IFERROR($C28-F28,"") -> 3504.3 | J28: =+IFERROR(G28/ABS($D28),"") -> 0.093498447 | K28: =+IFERROR(H28/ABS($E28),"") -> 0.093498447 | L28: =+IFERROR(I28/ABS($F28),"") -> 0.14453654
B29: % commission FI | C29: =+C28/C26 -> 0.28902085 | D29: =+D28/D26 -> 0.3 | E29: =+E28/E26 -> 0.3 | F29: =+F28/F26 -> 0.29226736 | G29: =+IFERROR($C29-D29,"") -> -0.010979153 | H29: =+IFERROR($C29-E29,"") -> -0.010979153 | I29: =+IFERROR($C29-F29,"") -> -0.0032465155 | J29: =+IFERROR(G29/ABS($D29),"") -> -0.036597175 | K29: =+IFERROR(H29/ABS($E29),"") -> -0.036597175 | L29: =+IFERROR(I29/ABS($F29),"") -> -0.011108033
B30: Variable fees | C30: =+Print_Mois!$L$121-C24-C28 -> 18745.97 | D30: =+Print_Mois!$I$121-D24-D28 -> 11638.554 | E30: =+Print_Mois!$F$121-E24-E28 -> 11638.554 | F30: =+Print_Mois!$Q$121-F24-F28 -> 8282.87 | G30: =+IFERROR($C30-D30,"") -> 7107.4158 | H30: =+IFERROR($C30-E30,"") -> 7107.4158 | I30: =+IFERROR($C30-F30,"") -> 10463.1 | J30: =+IFERROR(G30/ABS($D30),"") -> 0.61067858 | K30: =+IFERROR(H30/ABS($E30),"") -> 0.61067858 | L30: =+IFERROR(I30/ABS($F30),"") -> 1.2632216
B31: Variable fees / units | C31: =+C30/C21 -> 585.81156 | D31: =+D30/D21 -> 255.05768 | E31: =+E30/E21 -> 255.05768 | F31: =+F30/F21 -> 212.38128 | G31: =+IFERROR($C31-D31,"") -> 330.75389 | H31: =+IFERROR($C31-E31,"") -> 330.75389 | I31: =+IFERROR($C31-F31,"") -> 373.43028 | J31: =+IFERROR(G31/ABS($D31),"") -> 1.2967807 | K31: =+IFERROR(H31/ABS($E31),"") -> 1.2967807 | L31: =+IFERROR(I31/ABS($F31),"") -> 1.7583013
B32: Other Revenues | C32: =+Print_Mois!$L$162 -> 11168 | D32: =+Print_Mois!$I$162 -> 16386.117 | E32: =+Print_Mois!$F$162 -> 16386.117 | F32: =+Print_Mois!$Q$162 -> 13611 | G32: =+IFERROR($C32-D32,"") -> -5218.1165 | H32: =+IFERROR($C32-E32,"") -> -5218.1165 | I32: =+IFERROR($C32-F32,"") -> -2443 | J32: =+IFERROR(G32/ABS($D32),"") -> -0.31844742 | K32: =+IFERROR(H32/ABS($E32),"") -> -0.31844742 | L32: =+IFERROR(I32/ABS($F32),"") -> -0.17948718
B33: Inventory
B34: Units | C34: =Inventaire_Used!L3 -> 103 | D34: 68 | E34: 68 | F34: 92 | G34: =+IFERROR($C34-D34,"") -> 35 | H34: =+IFERROR($C34-E34,"") -> 35 | I34: =+IFERROR($C34-F34,"") -> 11 | J34: =+IFERROR(G34/ABS($D34),"") -> 0.51470588 | K34: =+IFERROR(H34/ABS($E34),"") -> 0.51470588 | L34: =+IFERROR(I34/ABS($F34),"") -> 0.11956522
B35: $ | C35: =Inventaire_Used!L2 -> 2677576.6 | D35: 1072231 | E35: 1072231 | F35: 1510979 | G35: =+IFERROR($C35-D35,"") -> 1605345.6 | H35: =+IFERROR($C35-E35,"") -> 1605345.6 | I35: =+IFERROR($C35-F35,"") -> 1166597.6 | J35: =+IFERROR(G35/ABS($D35),"") -> 1.4972013 | K35: =+IFERROR(H35/ABS($E35),"") -> 1.4972013 | L35: =+IFERROR(I35/ABS($F35),"") -> 0.77208062
C36: =C35/C34 -> 25995.889 | D36: =D35/D34 -> 15768.103 | E36: =E35/E34 -> 15768.103 | F36: =F35/F34 -> 16423.685
B37: Service | C37: Actual | D37: Forecast | E37: Budget | F37: 2021 | G37: ▲ Forecast | H37: ▲ Budget | I37: ▲2021 | J37: % ▲ Forecast | K37: % ▲ Budget | L37: % ▲ 2021 | M37: Commentaires
B38: Revenus | C38: =+Print_Mois!$K$193 -> 285908.71 | D38: =+Print_Mois!$H$193 -> 321390.32 | E38: =+Print_Mois!$E$193 -> 321390.32 | F38: =+Print_Mois!$P$193 -> 262627.93 | G38: =+IFERROR($C38-D38,"") -> -35481.607 | H38: =+IFERROR($C38-E38,"") -> -35481.607 | I38: =+IFERROR($C38-F38,"") -> 23280.78 | J38: =+IFERROR(G38/ABS($D38),"") -> -0.11040036 | K38: =+IFERROR(H38/ABS($E38),"") -> -0.11040036 | L38: =+IFERROR(I38/ABS($F38),"") -> 0.088645484 | M38: Les ventes clients ont plus que compensé le manque de $ à l’interne. La garantie reste en retard pour des raisons très explicables. Les véhicules qui brisaient « après-pandémie » du fait de l’Absence d’usage se sont tous mis à rouler à nouveau et ne brisent plus. Des dépenses qui dépassent un peu le budget compte tenu d’une relocalisation d’employés en travaux légers vers l’improduction et tombent dans les salaires autres. C’est un choix versus les laisser sur la CNESST. Un point aussi dans la portion uniformes, papeterie et autres avec un changement de facturation de LAR qui ramène dans le même mois le mois actuel et le suivant. Cela se compensera dans les prochains. Carrosserie qui va bien avec une avance sur le budget et un gros soutien sur le département des pièces. Retard de 14363$ sur le budget
B39: Gross margin | C39: =+Print_Mois!$L$193 -> 199493.81 | D39: =+Print_Mois!$I$193 -> 213845.1 | E39: =+Print_Mois!$F$193 -> 213845.1 | F39: =+Print_Mois!$Q$193 -> 174867.03 | G39: =+IFERROR($C39-D39,"") -> -14351.294 | H39: =+IFERROR($C39-E39,"") -> -14351.294 | I39: =+IFERROR($C39-F39,"") -> 24626.78 | J39: =+IFERROR(G39/ABS($D39),"") -> -0.067110696 | K39: =+IFERROR(H39/ABS($E39),"") -> -0.067110696 | L39: =+IFERROR(I39/ABS($F39),"") -> 0.14083146
B40: $ Revenus / #WO client | C40: =+Print_Mois!$K$171/Print_Mois!$J$171 -> 276.61797 | D40: =+IFERROR(Print_Mois!$H$171/Print_Mois!$G$171,"") -> 248 | E40: =+IFERROR(Print_Mois!$E$171/Print_Mois!$D$171,"") -> 248 | F40: =+Print_Mois!$P$171/Print_Mois!$O$171 -> 216.75473 | G40: =+IFERROR($C40-D40,"") -> 28.617974 | H40: =+IFERROR($C40-E40,"") -> 28.617974 | I40: =+IFERROR($C40-F40,"") -> 59.863245 | J40: =+IFERROR(G40/ABS($D40),"") -> 0.11539506 | K40: =+IFERROR(H40/ABS($E40),"") -> 0.11539506 | L40: =+IFERROR(I40/ABS($F40),"") -> 0.27617965
B41: $ Revenus / #WO garantie | C41: =+Print_Mois!$K$174/Print_Mois!$J$174 -> 114.73158 | D41: =+IFERROR(Print_Mois!$H$174/Print_Mois!$G$174,"") -> 198.09763 | E41: =+IFERROR(Print_Mois!$E$174/Print_Mois!$D$174,"") -> 198.09763 | F41: =+Print_Mois!$P$174/Print_Mois!$O$174 -> 242.70427 | G41: =+IFERROR($C41-D41,"") -> -83.366047 | H41: =+IFERROR($C41-E41,"") -> -83.366047 | I41: =+IFERROR($C41-F41,"") -> -127.97269 | J41: =+IFERROR(G41/ABS($D41),"") -> -0.42083314 | K41: =+IFERROR(H41/ABS($E41),"") -> -0.42083314 | L41: =+IFERROR(I41/ABS($F41),"") -> -0.52727827
B42: Lost time | C42: =+Print_Mois!$L$183 -> -2987.28 | D42: =+Print_Mois!$I$183 -> -4411.4934 | E42: =+Print_Mois!$F$183 -> -4411.4934 | F42: =+Print_Mois!$Q$183 -> -4646.71 | G42: =+IFERROR($C42-D42,"") -> 1424.2134 | H42: =+IFERROR($C42-E42,"") -> 1424.2134 | I42: =+IFERROR($C42-F42,"") -> 1659.43 | J42: =+IFERROR(G42/ABS($D42),"") -> 0.32284156 | K42: =+IFERROR(H42/ABS($E42),"") -> 0.32284156 | L42: =+IFERROR(I42/ABS($F42),"") -> 0.35711934
B43: Total salaries | C43: =+Print_Mois!$L$209 -> 109073.29 | D43: =+Print_Mois!$I$209 -> 116122.88 | E43: =+Print_Mois!$F$209 -> 116122.88 | F43: =+Print_Mois!$Q$209 -> 94324.18 | G43: =+IFERROR($C43-D43,"") -> -7049.5854 | H43: =+IFERROR($C43-E43,"") -> -7049.5854 | I43: =+IFERROR($C43-F43,"") -> 14749.11 | J43: =+IFERROR(G43/ABS($D43),"") -> -0.060707982 | K43: =+IFERROR(H43/ABS($E43),"") -> -0.060707982 | L43: =+IFERROR(I43/ABS($F43),"") -> 0.15636616
B44: Salaries | C44: =+SUM(Print_Mois!$L$197:$L$203) -> 64949.32 | D44: =+SUM(Print_Mois!$I$197:$I$203) -> 68744.694 | E44: =+SUM(Print_Mois!$F$197:$F$203) -> 68744.694 | F44: =+SUM(Print_Mois!$Q$197:$Q$203) -> 51361.44 | G44: =+IFERROR($C44-D44,"") -> -3795.3739 | H44: =+IFERROR($C44-E44,"") -> -3795.3739 | I44: =+IFERROR($C44-F44,"") -> 13587.88 | J44: =+IFERROR(G44/ABS($D44),"") -> -0.0552097 | K44: =+IFERROR(H44/ABS($E44),"") -> -0.0552097 | L44: =+IFERROR(I44/ABS($F44),"") -> 0.26455411
B45: Fringes | C45: =+SUM(Print_Mois!$L$204:$L$208) -> 44123.97 | D45: =+SUM(Print_Mois!$I$204:$I$208) -> 47378.182 | E45: =+SUM(Print_Mois!$F$204:$F$208) -> 47378.182 | F45: =+SUM(Print_Mois!$Q$204:$Q$208) -> 42962.74 | G45: =+IFERROR($C45-D45,"") -> -3254.2115 | H45: =+IFERROR($C45-E45,"") -> -3254.2115 | I45: =+IFERROR($C45-F45,"") -> 1161.23 | J45: =+IFERROR(G45/ABS($D45),"") -> -0.068685868 | K45: =+IFERROR(H45/ABS($E45),"") -> -0.068685868 | L45: =+IFERROR(I45/ABS($F45),"") -> 0.02702877
B46: Total salaries / Revenus | C46: =+C43/C38 -> 0.38149691 | D46: =+D43/D38 -> 0.36131417 | E46: =+E43/E38 -> 0.36131417 | F46: =+F43/F38 -> 0.35915517 | G46: =+IFERROR($C46-D46,"") -> 0.020182742 | H46: =+IFERROR($C46-E46,"") -> 0.020182742 | I46: =+IFERROR($C46-F46,"") -> 0.022341738 | J46: =+IFERROR(G46/ABS($D46),"") -> 0.05585926 | K46: =+IFERROR(H46/ABS($E46),"") -> 0.05585926 | L46: =+IFERROR(I46/ABS($F46),"") -> 0.062206364
B47: Frais véhicules de cie | C47: =+Print_Mois!$L$212 -> 11752.87 | D47: =+Print_Mois!$I$212 -> 15977.574 | E47: =+Print_Mois!$F$212 -> 15977.574 | F47: =+Print_Mois!$Q$212 -> 18069.37 | G47: =+IFERROR($C47-D47,"") -> -4224.7044 | H47: =+IFERROR($C47-E47,"") -> -4224.7044 | I47: =+IFERROR($C47-F47,"") -> -6316.5 | J47: =+IFERROR(G47/ABS($D47),"") -> -0.26441463 | K47: =+IFERROR(H47/ABS($E47),"") -> -0.26441463 | L47: =+IFERROR(I47/ABS($F47),"") -> -0.34956946
B49: Pieces | C49: Actual | D49: Forecast | E49: Budget | F49: 2021 | G49: ▲ Forecast | H49: ▲ Budget | I49: ▲2021 | J49: % ▲ Forecast | K49: % ▲ Budget | L49: % ▲ 2021 | M49: Commentaires
B50: Revenus | C50: =+Print_Mois!$J$313 -> 395972.59 | D50: =+Print_Mois!$G$313 -> 395738.32 | E50: =+Print_Mois!$D$313 -> 395738.32 | F50: =+Print_Mois!$O$313 -> 334619.39 | G50: =+IFERROR($C50-D50,"") -> 234.26786 | H50: =+IFERROR($C50-E50,"") -> 234.26786 | I50: =+IFERROR($C50-F50,"") -> 61353.2 | J50: =+IFERROR(G50/ABS($D50),"") -> 0.0005919767 | K50: =+IFERROR(H50/ABS($E50),"") -> 0.0005919767 | L50: =+IFERROR(I50/ABS($F50),"") -> 0.1833522 | M50: Un beau niveau de profitabilité dans les ventes aux clients et globalement tous canaux confondus. Belle performance dans la vente de gros. Le brut global est dépassé de 3697$ De dépenses de fonctionnement à la hausse avec la mise à jour du calcul de la CNESST qui n’avait pas été budgété ainsi que la portion publicité qui englobe plusieurs paramètres dont le détail sera disponible au monthly. Retard de 7202$ sur le budget
B51: Clients | C51: =+Print_Mois!$J$294 -> 83928.41 | D51: =+Print_Mois!$G$294 -> 79638.512 | E51: =+Print_Mois!$D$294 -> 79638.512 | F51: =+Print_Mois!$O$294 -> 68074.17 | G51: =+IFERROR($C51-D51,"") -> 4289.8978 | H51: =+IFERROR($C51-E51,"") -> 4289.8978 | I51: =+IFERROR($C51-F51,"") -> 15854.24 | J51: =+IFERROR(G51/ABS($D51),"") -> 0.053867127 | K51: =+IFERROR(H51/ABS($E51),"") -> 0.053867127 | L51: =+IFERROR(I51/ABS($F51),"") -> 0.23289656
B52: Garantie | C52: =+Print_Mois!$J$296 -> 33824.31 | D52: =+Print_Mois!$G$296 -> 92243.894 | E52: =+Print_Mois!$D$296 -> 92243.894 | F52: =+Print_Mois!$O$296 -> 79594.67 | G52: =+IFERROR($C52-D52,"") -> -58419.584 | H52: =+IFERROR($C52-E52,"") -> -58419.584 | I52: =+IFERROR($C52-F52,"") -> -45770.36 | J52: =+IFERROR(G52/ABS($D52),"") -> -0.63331654 | K52: =+IFERROR(H52/ABS($E52),"") -> -0.63331654 | L52: =+IFERROR(I52/ABS($F52),"") -> -0.57504303
B53: Wholesale | C53: =+Print_Mois!$J$299 -> 77684.11 | D53: =+Print_Mois!$G$299 -> 47625.131 | E53: =+Print_Mois!$D$299 -> 47625.131 | F53: =+Print_Mois!$O$299 -> 33246.97 | G53: =+IFERROR($C53-D53,"") -> 30058.979 | H53: =+IFERROR($C53-E53,"") -> 30058.979 | I53: =+IFERROR($C53-F53,"") -> 44437.14 | J53: =+IFERROR(G53/ABS($D53),"") -> 0.63115791 | K53: =+IFERROR(H53/ABS($E53),"") -> 0.63115791 | L53: =+IFERROR(I53/ABS($F53),"") -> 1.3365771
B54: Tires | C54: =+Print_Mois!$J$306 -> 38052.43 | D54: =+Print_Mois!$G$306 -> 40235.746 | E54: =+Print_Mois!$D$306 -> 40235.746 | F54: =+Print_Mois!$O$306 -> 41678.73 | G54: =+IFERROR($C54-D54,"") -> -2183.3157 | H54: =+IFERROR($C54-E54,"") -> -2183.3157 | I54: =+IFERROR($C54-F54,"") -> -3626.3 | J54: =+IFERROR(G54/ABS($D54),"") -> -0.054263086 | K54: =+IFERROR(H54/ABS($E54),"") -> -0.054263086 | L54: =+IFERROR(I54/ABS($F54),"") -> -0.08700601
B55: All others | C55: =+C50-SUM(C51:C54) -> 162483.33 | D55: =+D50-SUM(D51:D54) -> 135995.04 | E55: =+E50-SUM(E51:E54) -> 135995.04 | F55: =+F50-SUM(F51:F54) -> 112024.85 | G55: =+IFERROR($C55-D55,"") -> 26488.291 | H55: =+IFERROR($C55-E55,"") -> 26488.291 | I55: =+IFERROR($C55-F55,"") -> 50458.48 | J55: =+IFERROR(G55/ABS($D55),"") -> 0.19477395 | K55: =+IFERROR(H55/ABS($E55),"") -> 0.19477395 | L55: =+IFERROR(I55/ABS($F55),"") -> 0.45042221
B56: Gross margin | C56: =+Print_Mois!$L$313 -> 116031.79 | D56: =+Print_Mois!$I$313 -> 112335.11 | E56: =+Print_Mois!$F$313 -> 112335.11 | F56: =+Print_Mois!$Q$313 -> 98600.08 | G56: =+IFERROR($C56-D56,"") -> 3696.6806 | H56: =+IFERROR($C56-E56,"") -> 3696.6806 | I56: =+IFERROR($C56-F56,"") -> 17431.71 | J56: =+IFERROR(G56/ABS($D56),"") -> 0.032907616 | K56: =+IFERROR(H56/ABS($E56),"") -> 0.032907616 | L56: =+IFERROR(I56/ABS($F56),"") -> 0.17679205
B57: $ Revenus / #WO client | C57: =+Print_Mois!$J$294/Print_Mois!$J$171 -> 136.0266 | D57: =+IFERROR(Print_Mois!$G$294/Print_Mois!$G$171,"") -> 131.53564 | E57: =+IFERROR(Print_Mois!$D$294/Print_Mois!$D$171,"") -> 131.53564 | F57: =+Print_Mois!$O$294/Print_Mois!$O$171 -> 122.87756 | G57: =+IFERROR($C57-D57,"") -> 4.490958 | H57: =+IFERROR($C57-E57,"") -> 4.490958 | I57: =+IFERROR($C57-F57,"") -> 13.149033 | J57: =+IFERROR(G57/ABS($D57),"") -> 0.034142519 | K57: =+IFERROR(H57/ABS($E57),"") -> 0.034142519 | L57: =+IFERROR(I57/ABS($F57),"") -> 0.10700923
B58: $ Revenus / #WO garantie | C58: =+Print_Mois!$J$296/Print_Mois!$J$174 -> 97.196293 | D58: =+IFERROR(Print_Mois!$G$296/Print_Mois!$G$174,"") -> 249.52281 | E58: =+IFERROR(Print_Mois!$D$296/Print_Mois!$D$174,"") -> 249.52281 | F58: =+Print_Mois!$O$296/Print_Mois!$O$174 -> 323.55557 | G58: =+IFERROR($C58-D58,"") -> -152.32652 | H58: =+IFERROR($C58-E58,"") -> -152.32652 | I58: =+IFERROR($C58-F58,"") -> -226.35928 | J58: =+IFERROR(G58/ABS($D58),"") -> -0.61047131 | K58: =+IFERROR(H58/ABS($E58),"") -> -0.61047131 | L58: =+IFERROR(I58/ABS($F58),"") -> -0.69959938
B59: Salaires autres | C59: =+Print_Mois!$L$319 -> 24682.35 | D59: =+Print_Mois!$I$319 -> 24550.485 | E59: =+Print_Mois!$F$319 -> 24550.485 | F59: =+Print_Mois!$Q$319 -> 23595.43 | G59: =+IFERROR($C59-D59,"") -> 131.86543 | H59: =+IFERROR($C59-E59,"") -> 131.86543 | I59: =+IFERROR($C59-F59,"") -> 1086.92 | J59: =+IFERROR(G59/ABS($D59),"") -> 0.0053711946 | K59: =+IFERROR(H59/ABS($E59),"") -> 0.0053711946 | L59: =+IFERROR(I59/ABS($F59),"") -> 0.046064852
B61: Others | C61: Actual | D61: Forecast | E61: Budget | F61: 2021 | G61: ▲ Forecast | H61: ▲ Budget | I61: ▲2021 | J61: % ▲ Forecast | K61: % ▲ Budget | L61: % ▲ 2021 | M61: Commentaires
B62: Total salaries / Gross profits | C62: =+Print_Mois!$AF$432/Print_Mois!$AF$406 -> 0.38217949 | D62: =+Print_Mois!$AC$432/Print_Mois!$AC$406 -> 0.38857533 | E62: =+Print_Mois!$Z$432/Print_Mois!$Z$406 -> 0.38857533 | F62: =+Print_Mois!$AL$432/Print_Mois!$AL$406 -> 0.38078328 | G62: =+IFERROR($C62-D62,"") -> -0.0063958447 | H62: =+IFERROR($C62-E62,"") -> -0.0063958447 | I62: =+IFERROR($C62-F62,"") -> 0.0013962093 | J62: =+IFERROR(G62/ABS($D62),"") -> -0.016459729 | K62: =+IFERROR(H62/ABS($E62),"") -> -0.016459729 | L62: =+IFERROR(I62/ABS($F62),"") -> 0.0036666769 | M62: Toujours un nombre d’employés en dessous du budget en ligne avec le niveau d’activité. La portion marketing reste le point sur lequel nous devons augmenter notre niveau de vigilance.
B63: Headcounts | C63: 45 | D63: 52.75 | E63: 52.75 | F63: 36 | G63: =+IFERROR($C63-D63,"") -> -7.75 | H63: =+IFERROR($C63-E63,"") -> -7.75 | I63: =+IFERROR($C63-F63,"") -> 9 | J63: =+IFERROR(G63/ABS($D63),"") -> -0.14691943 | K63: =+IFERROR(H63/ABS($E63),"") -> -0.14691943 | L63: =+IFERROR(I63/ABS($F63),"") -> 0.25
B64: Marketing | C64: =Q17+Print_Mois!$AF$413+Print_Mois!$AF$433 -> 53987.53 | D64: =+Print_Mois!$AC$413+Print_Mois!$AC$433 -> 31133.284 | E64: =+Print_Mois!$Z$413+Print_Mois!$Z$433 -> 31133.284 | F64: =+Print_Mois!$AL$413+Print_Mois!$AL$433 -> 21937.58 | G64: =+IFERROR($C64-D64,"") -> 22854.246 | H64: =+IFERROR($C64-E64,"") -> 22854.246 | I64: =+IFERROR($C64-F64,"") -> 32049.95 | J64: =+IFERROR(G64/ABS($D64),"") -> 0.73407761 | K64: =+IFERROR(H64/ABS($E64),"") -> 0.73407761 | L64: =+IFERROR(I64/ABS($F64),"") -> 1.4609611
B65: Other semi-fixed expenses | C65: =+Print_Mois!$AF$451-Print_Mois!$AF$433 -> 95042.01 | D65: =+Print_Mois!$AC$451-Print_Mois!$AC$433 -> 100018.63 | E65: =+Print_Mois!$Z$451-Print_Mois!$Z$433 -> 100018.63 | F65: =+Print_Mois!$AL$451-Print_Mois!$AL$433 -> 86465.45 | G65: =+IFERROR($C65-D65,"") -> -4976.623 | H65: =+IFERROR($C65-E65,"") -> -4976.623 | I65: =+IFERROR($C65-F65,"") -> 8576.56 | J65: =+IFERROR(G65/ABS($D65),"") -> -0.049756959 | K65: =+IFERROR(H65/ABS($E65),"") -> -0.049756959 | L65: =+IFERROR(I65/ABS($F65),"") -> 0.099190602
B66: Floor plan interest | C66: =+Print_Mois!$AF$414 -> 2152.67 | D66: =+Print_Mois!$AC$414 -> 8866.1533 | E66: =+Print_Mois!$Z$414 -> 8866.1533 | F66: =+Print_Mois!$AL$414 -> 14570.89 | G66: =+IFERROR($C66-D66,"") -> -6713.4833 | H66: =+IFERROR($C66-E66,"") -> -6713.4833 | I66: =+IFERROR($C66-F66,"") -> -12418.22 | J66: =+IFERROR(G66/ABS($D66),"") -> -0.75720361 | K66: =+IFERROR(H66/ABS($E66),"") -> -0.75720361 | L66: =+IFERROR(I66/ABS($F66),"") -> -0.85226228
B67: Others Revenues | C67: =+Print_Mois!$AF$480-C32-C15 -> 16441.59 | D67: =+Print_Mois!$AC$480-D32-D15 -> 14968.87 | E67: =+Print_Mois!$Z$480-E32-E15 -> 14968.87 | F67: =+Print_Mois!$AL$480-F32-F15 -> 6192.67 | G67: =+IFERROR($C67-D67,"") -> 1472.72 | H67: =+IFERROR($C67-E67,"") -> 1472.72 | I67: =+IFERROR($C67-F67,"") -> 10248.92 | J67: =+IFERROR(G67/ABS($D67),"") -> 0.098385516 | K67: =+IFERROR(H67/ABS($E67),"") -> 0.098385516 | L67: =+IFERROR(I67/ABS($F67),"") -> 1.6550083
B69: P&L | C69: Actual | D69: Forecast | E69: Budget | F69: 2021 | G69: ▲ Forecast | H69: ▲ Budget | I69: ▲2021 | J69: % ▲ Forecast | K69: % ▲ Budget | L69: % ▲ 2021 | M69: Commentaires
B70: Selling and Marketing | C70: =+Print_Mois!$AF$418-Print_Mois!$AF$414+Print_Mois!$AF$433+Print_Mois!$AF$434+Print_Mois!$AF$435 -> 222990.44 | D70: =+Print_Mois!$AC$418-Print_Mois!$AC$414+Print_Mois!$AC$433+Print_Mois!$AC$434+Print_Mois!$AC$435 -> 214835.66 | E70: =+Print_Mois!$Z$418-Print_Mois!$Z$414+Print_Mois!$Z$433+Print_Mois!$Z$434+Print_Mois!$Z$435 -> 214835.66 | F70: =+Print_Mois!$AL$418-Print_Mois!$AL$414+Print_Mois!$AL$433+Print_Mois!$AL$434+Print_Mois!$AL$435 -> 184412.32 | G70: =+IFERROR($C70-D70,"") -> 8154.7765 | H70: =+IFERROR($C70-E70,"") -> 8154.7765 | I70: =+IFERROR($C70-F70,"") -> 38578.12 | J70: =+IFERROR(G70/ABS($D70),"") -> 0.037958206 | K70: =+IFERROR(H70/ABS($E70),"") -> 0.037958206 | L70: =+IFERROR(I70/ABS($F70),"") -> 0.20919492 | M70: Un mois difficile versus le budget car parmi les plus hauts de l’année. Cela ne doit pas occulter de bons résultats sur les éléments contrôlables. Année à jour on reste avec une légère avance sur le budget
B71: S&M / Brut | C71: =+C70/Print_Mois!$AF$406 -> 0.29735013 | D71: =+D70/Print_Mois!$AC$406 -> 0.28038777 | E71: =+E70/Print_Mois!$Z$406 -> 0.28038777 | F71: =+F70/Print_Mois!$AL$406 -> 0.26892892 | G71: =+IFERROR($C71-D71,"") -> 0.016962356 | H71: =+IFERROR($C71-E71,"") -> 0.016962356 | I71: =+IFERROR($C71-F71,"") -> 0.028421206 | J71: =+IFERROR(G71/ABS($D71),"") -> 0.060496063 | K71: =+IFERROR(H71/ABS($E71),"") -> 0.060496063 | L71: =+IFERROR(I71/ABS($F71),"") -> 0.10568297
B72: General & administrative | C72: =+Print_Mois!$AF$465+Print_Mois!$AF$432+Print_Mois!$AF$436+Print_Mois!$AF$438+SUM(Print_Mois!$AF$439:$AF$447)+Print_Mois!$AF$437 -> 404654.78 | D72: =+Print_Mois!$AC$465+Print_Mois!$AC$432+Print_Mois!$AC$436+Print_Mois!$AC$438+SUM(Print_Mois!$AC$439:$AC$447)+Print_Mois!$AC$437 -> 417677.76 | E72: =+Print_Mois!$Z$465+Print_Mois!$Z$432+Print_Mois!$Z$436+Print_Mois!$Z$438+SUM(Print_Mois!$Z$439:$Z$447)+Print_Mois!$Z$437 -> 417677.76 | F72: =+Print_Mois!$AL$465+Print_Mois!$AL$432+Print_Mois!$AL$436+Print_Mois!$AL$438+SUM(Print_Mois!$AL$439:$AL$447)+Print_Mois!$AL$437 -> 366767.99 | G72: =+IFERROR($C72-D72,"") -> -13022.983 | H72: =+IFERROR($C72-E72,"") -> -13022.983 | I72: =+IFERROR($C72-F72,"") -> 37886.79 | J72: =+IFERROR(G72/ABS($D72),"") -> -0.031179499 | K72: =+IFERROR(H72/ABS($E72),"") -> -0.031179499 | L72: =+IFERROR(I72/ABS($F72),"") -> 0.10329906
B73: G&A / Brut | C73: =+C72/Print_Mois!$AF$406 -> 0.53959331 | D73: =+D72/Print_Mois!$AC$406 -> 0.54512242 | E73: =+E72/Print_Mois!$Z$406 -> 0.54512242 | F73: =+F72/Print_Mois!$AL$406 -> 0.53485863 | G73: =+IFERROR($C73-D73,"") -> -0.0055291082 | H73: =+IFERROR($C73-E73,"") -> -0.0055291082 | I73: =+IFERROR($C73-F73,"") -> 0.0047346882 | J73: =+IFERROR(G73/ABS($D73),"") -> -0.010142874 | K73: =+IFERROR(H73/ABS($E73),"") -> -0.010142874 | L73: =+IFERROR(I73/ABS($F73),"") -> 0.0088522237
B74: EBITDA | C74: =+Print_Mois!$AF$482+Print_Mois!$AF$414 -> 220590.86 | D74: =+Print_Mois!$AC$482+Print_Mois!$AC$414 -> 299969.37 | E74: =+Print_Mois!$Z$482+Print_Mois!$Z$414 -> 299969.37 | F74: =+Print_Mois!$AL$482+Print_Mois!$AL$414 -> 282407.21 | G74: =+IFERROR($C74-D74,"") -> -79378.508 | H74: =+IFERROR($C74-E74,"") -> -79378.508 | I74: =+IFERROR($C74-F74,"") -> -61816.35 | J74: =+IFERROR(G74/ABS($D74),"") -> -0.26462205 | K74: =+IFERROR(H74/ABS($E74),"") -> -0.26462205 | L74: =+IFERROR(I74/ABS($F74),"") -> -0.21889083
B75: EBITDA % | C75: =+C74/Print_Mois!$AF$405 -> 0.046720784 | D75: =+D74/Print_Mois!$AC$405 -> 0.049799053 | E75: =+E74/Print_Mois!$Z$405 -> 0.049799053 | F75: =+F74/Print_Mois!$AL$405 -> 0.047859345 | G75: =+IFERROR($C75-D75,"") -> -0.0030782694 | H75: =+IFERROR($C75-E75,"") -> -0.0030782694 | I75: =+IFERROR($C75-F75,"") -> -0.0011385609 | J75: =+IFERROR(G75/ABS($D75),"") -> -0.061813814 | K75: =+IFERROR(H75/ABS($E75),"") -> -0.061813814 | L75: =+IFERROR(I75/ABS($F75),"") -> -0.02378973
B76: EBIT | C76: =Q9+Print_Mois!$AF$497 -> 213696.9 | D76: =+Print_Mois!$AC$497 -> 283199.85 | E76: =+Print_Mois!$Z$497 -> 283199.85 | F76: =+Print_Mois!$AL$497 -> 281298.69 | G76: =+IFERROR($C76-D76,"") -> -69502.945 | H76: =+IFERROR($C76-E76,"") -> -69502.945 | I76: =+IFERROR($C76-F76,"") -> -67601.79 | J76: =+IFERROR(G76/ABS($D76),"") -> -0.24542014 | K76: =+IFERROR(H76/ABS($E76),"") -> -0.24542014 | L76: =+IFERROR(I76/ABS($F76),"") -> -0.24032032
B77: EBIT % | C77: =+C76/Print_Mois!$AF$405 -> 0.045260654 | D77: =+D76/Print_Mois!$AC$405 -> 0.047015081 | E77: =+E76/Print_Mois!$Z$405 -> 0.047015081 | F77: =+F76/Print_Mois!$AL$405 -> 0.047671485 | G77: =+IFERROR($C77-D77,"") -> -0.0017544267 | H77: =+IFERROR($C77-E77,"") -> -0.0017544267 | I77: =+IFERROR($C77-F77,"") -> -0.0024108303 | J77: =+IFERROR(G77/ABS($D77),"") -> -0.037316253 | K77: =+IFERROR(H77/ABS($E77),"") -> -0.037316253 | L77: =+IFERROR(I77/ABS($F77),"") -> -0.050571747

Sheet Print_Mois
C1: =Parametres!B1 -> Volks | K1: Véhicules neufs | S1: =CONCATENATE("Réalisé,"," ",Parametres!B3," ",Parametres!B4) -> Réalisé, Mai 2022
D2: X | E2: O | F2: U | G2: X | H2: O | I2: U | J2: NB | L2: $ | O2: NB | Q2: $ | V2: *** *** NE PAS EFFACER *** ***
D3: BUDGET ORIGINAL | G3: BUDGET REVISE | J3: RÉALISATION | M3: ÉCART réel / révisé | O3: ANNÉE PRÉCÉDENTE | R3: ÉCART réel / original | V3: NEUF | W3: 0.45
D4: UNITE | E4: $P/UNITÉ | F4: $PROFITS | G4: UNITE | H4: $P/UNITÉ | I4: $PROFITS | J4: UNITE | K4: $P/UNITE | L4: $PROFITS | M4: UNITÉ | N4: $PROFITS | O4: UNITE | P4: $P/UNITE | Q4: $PROFITS | R4: UNITE | S4: $PROFITS | V4: USAGE | W4: 0.1
A5: Véhicules neufsVentes nettes | B5: Véhicules neufs | C5: Ventes nettes | F5: =+INDEX('Budget original'!$A$2:$AO$500,MATCH($A5,'Budget original'!$A$2:$A$500,0),MATCH(F$2,'Budget original'!$A$2:$AO$2,0)) -> 3809901.5 | I5: =+INDEX('Budget révisé'!$A$2:$AO$500,MATCH($A5,'Budget révisé'!$A$2:$A$500,0),MATCH(I$2,'Budget révisé'!$A$2:$AO$2,0)) -> 3809901.5 | L5: =-SUMIFS(BV_Data_An_Cour!$O:$O,BV_Data_An_Cour!$X:$X,"Oui",BV_Data_An_Cour!$U:$U,$B5) -> 2400932.7 | Q5: =-SUMIFS(BV_Data_An_Prec!$O:$O,BV_Data_An_Prec!$X:$X,"Oui",BV_Data_An_Prec!$U:$U,$B5) -> 3829078.6 | V5: SERVICE | W5: 0.225
A6: Véhicules neufsAutos détail | B6: Véhicules neufs | C6: Autos détail | D6: =+INDEX('Budget original'!$A$2:$AO$500,MATCH($A6,'Budget original'!$A$2:$A$500,0),MATCH(D$2,'Budget original'!$A$2:$AO$2,0)) -> 19.431325 | E6: =IF(D6=0,0,F6/D6) -> 1450.6298 | F6: =+INDEX('Budget original'!$A$2:$AO$500,MATCH($A6,'Budget original'!$A$2:$A$500,0),MATCH(F$2,'Budget original'!$A$2:$AO$2,0)) -> 28187.659 | G6: =+INDEX('Budget original'!$A$2:$AO$500,MATCH($A6,'Budget original'!$A$2:$A$500,0),MATCH(G$2,'Budget original'!$A$2:$AO$2,0)) -> 19.431325 | H6: =IF(G6=0,0,I6/G6) -> 1450.6298 | I6: =+INDEX('Budget révisé'!$A$2:$AO$500,MATCH($A6,'Budget révisé'!$A$2:$A$500,0),MATCH(I$2,'Budget révisé'!$A$2:$AO$2,0)) -> 28187.659 | J6: =-SUMIFS(BV_Data_An_Cour!$O:$O,BV_Data_An_Cour!$U:$U,$B6,BV_Data_An_Cour!$V:$V,$C6,BV_Data_An_Cour!$W:$W,J$2) -> 7 | K6: =IF(J6=0,0,L6/J6) -> 3196.7429 | L6: =-SUMIFS(BV_Data_An_Cour!$O:$O,BV_Data_An_Cour!$U:$U,$B6,BV_Data_An_Cour!$V:$V,$C6,BV_Data_An_Cour!$W:$W,L$2) -> 22377.2 | M6: =J6-G6 -> -12.431325 | N6: =L6-I6 -> -5810.4588 | O6: =-SUMIFS(BV_Data_An_Prec!$O:$O,BV_Data_An_Prec!$U:$U,$B6,BV_Data_An_Prec!$V:$V,$C6,BV_Data_An_Prec!$W:$W,O$2) -> 25 | P6: =IF(O6=0,0,Q6/O6) -> 1020.836 | Q6: =-SUMIFS(BV_Data_An_Prec!$O:$O,BV_Data_An_Prec!$U:$U,$B6,BV_Data_An_Prec!$V:$V,$C6,BV_Data_An_Prec!$W:$W,Q$2) -> 25520.9 | R6: =J6-O6 -> -18 | S6: =L6-Q6 -> -3143.7 | V6: CARROSSERIE | W6: 0.025
A7: Véhicules neufsCamions détail | B7: Véhicules neufs | C7: Camions détail | D7: =+INDEX('Budget original'!$A$2:$AO$500,MATCH($A7,'Budget original'!$A$2:$A$500,0),MATCH(D$2,'Budget original'!$A$2:$AO$2,0)) -> 67.084337 | E7: =IF(D7=0,0,F7/D7) -> 2081.8276 | F7: =+INDEX('Budget original'!$A$2:$AO$500,MATCH($A7,'Budget original'!$A$2:$A$500,0),MATCH(F$2,'Budget original'!$A$2:$AO$2,0)) -> 139658.02 | G7: =+INDEX('Budget original'!$A$2:$AO$500,MATCH($A7,'Budget original'!$A$2:$A$500,0),MATCH(G$2,'Budget original'!$A$2:$AO$2,0)) -> 67.084337 | H7: =IF(G7=0,0,I7/G7) -> 2081.8276 | I7: =+INDEX('Budget révisé'!$A$2:$AO$500,MATCH($A7,'Budget révisé'!$A$2:$A$500,0),MATCH(I$2,'Budget révisé'!$A$2:$AO$2,0)) -> 139658.02 | J7: =-SUMIFS(BV_Data_An_Cour!$O:$O,BV_Data_An_Cour!$U:$U,$B7,BV_Data_An_Cour!$V:$V,$C7,BV_Data_An_Cour!$W:$W,J$2) -> 36 | K7: =IF(J7=0,0,L7/J7) -> 3783.5983 | L7: =-SUMIFS(BV_Data_An_Cour!$O:$O,BV_Data_An_Cour!$U:$U,$B7,BV_Data_An_Cour!$V:$V,$C7,BV_Data_An_Cour!$W:$W,L$2) -> 136209.54 | M7: =J7-G7 -> -31.084337 | N7: =L7-I7 -> -3448.4841 | O7: =-SUMIFS(BV_Data_An_Prec!$O:$O,BV_Data_An_Prec!$U:$U,$B7,BV_Data_An_Prec!$V:$V,$C7,BV_Data_An_Prec!$W:$W,O$2) -> 58 | P7: =IF(O7=0,0,Q7/O7) -> 2126.4852 | Q7: =-SUMIFS(BV_Data_An_Prec!$O:$O,BV_Data_An_Prec!$U:$U,$B7,BV_Data_An_Prec!$V:$V,$C7,BV_Data_An_Prec!$W:$W,Q$2) -> 123336.14 | R7: =J7-O7 -> -22 | S7: =L7-Q7 -> 12873.4 | V7: PIECES | W7: 0.2
A8: Véhicules neufsSprinter | B8: Véhicules neufs | C8: Sprinter | D8: =+INDEX('Budget original'!$A$2:$AO$500,MATCH($A8,'Budget original'!$A$2:$A$500,0),MATCH(D$2,'Budget original'!$A$2:$AO$2,0)) -> 0 | E8: =IF(D8=0,0,F8/D8) -> 0 | F8: =+INDEX('Budget original'!$A$2:$AO$500,MATCH($A8,'Budget original'!$A$2:$A$500,0),MATCH(F$2,'Budget original'!$A$2:$AO$2,0)) -> 0 | G8: =+INDEX('Budget original'!$A$2:$AO$500,MATCH($A8,'Budget original'!$A$2:$A$500,0),MATCH(G$2,'Budget original'!$A$2:$AO$2,0)) -> 0 | H8: =IF(G8=0,0,I8/G8) -> 0 | I8: =+INDEX('Budget révisé'!$A$2:$AO$500,MATCH($A8,'Budget révisé'!$A$2:$A$500,0),MATCH(I$2,'Budget révisé'!$A$2:$AO$2,0)) -> 0 | J8: =-SUMIFS(BV_Data_An_Cour!$O:$O,BV_Data_An_Cour!$U:$U,$B8,BV_Data_An_Cour!$V:$V,$C8,BV_Data_An_Cour!$W:$W,J$2) -> 0 | K8: =IF(J8=0,0,L8/J8) -> 0 | L8: =-SUMIFS(BV_Data_An_Cour!$O:$O,BV_Data_An_Cour!$U:$U,$B8,BV_Data_An_Cour!$V:$V,$C8,BV_Data_An_Cour!$W:$W,L$2) -> 0 | M8: =J8-G8 -> 0 | N8: =L8-I8 -> 0 | O8: =-SUMIFS(BV_Data_An_Prec!$O:$O,BV_Data_An_Prec!$U:$U,$B8,BV_Data_An_Prec!$V:$V,$C8,BV_Data_An_Prec!$W:$W,O$2) -> 0 | P8: =IF(O8=0,0,Q8/O8) -> 0 | Q8: =-SUMIFS(BV_Data_An_Prec!$O:$O,BV_Data_An_Prec!$U:$U,$B8,BV_Data_An_Prec!$V:$V,$C8,BV_Data_An_Prec!$W:$W,Q$2) -> 0 | R8: =J8-O8 -> 0 | S8: =L8-Q8 -> 0 | W8: =SUM(W3:W7) -> 1
A9: Véhicules neufsMoto détail | B9: Véhicules neufs | C9: Moto détail | D9: =+INDEX('Budget original'!$A$2:$AO$500,MATCH($A9,'Budget original'!$A$2:$A$500,0),MATCH(D$2,'Budget original'!$A$2:$AO$2,0)) -> 0 | E9: =IF(D9=0,0,F9/D9) -> 0 | F9: =+INDEX('Budget original'!$A$2:$AO$500,MATCH($A9,'Budget original'!$A$2:$A$500,0),MATCH(F$2,'Budget original'!$A$2:$AO$2,0)) -> 0 | G9: =+INDEX('Budget original'!$A$2:$AO$500,MATCH($A9,'Budget original'!$A$2:$A$500,0),MATCH(G$2,'Budget original'!$A$2:$AO$2,0)) -> 0 | H9: =IF(G9=0,0,I9/G9) -> 0 | I9: =+INDEX('Budget révisé'!$A$2:$AO$500,MATCH($A9,'Budget révisé'!$A$2:$A$500,0),MATCH(I$2,'Budget révisé'!$A$2:$AO$2,0)) -> 0 | J9: =-SUMIFS(BV_Data_An_Cour!$O:$O,BV_Data_An_Cour!$U:$U,$B9,BV_Data_An_Cour!$V:$V,$C9,BV_Data_An_Cour!$W:$W,J$2) -> 0 | K9: =IF(J9=0,0,L9/J9) -> 0 | L9: =-SUMIFS(BV_Data_An_Cour!$O:$O,BV_Data_An_Cour!$U:$U,$B9,BV_Data_An_Cour!$V:$V,$C9,BV_Data_An_Cour!$W:$W,L$2) -> 0 | M9: =J9-G9 -> 0 | N9: =L9-I9 -> 0 | O9: =-SUMIFS(BV_Data_An_Prec!$O:$O,BV_Data_An_Prec!$U:$U,$B9,BV_Data_An_Prec!$V:$V,$C9,BV_Data_An_Prec!$W:$W,O$2) -> 0 | P9: =IF(O9=0,0,Q9/O9) -> 0 | Q9: =-SUMIFS(BV_Data_An_Prec!$O:$O,BV_Data_An_Prec!$U:$U,$B9,BV_Data_An_Prec!$V:$V,$C9,BV_Data_An_Prec!$W:$W,Q$2) -> 0 | R9: =J9-O9 -> 0 | S9: =L9-Q9 -> 0
A10: Véhicules neufs[...] | B10: Véhicules neufs | C10: [...] | D10: 0 | E10: =IF(D10=0,0,F10/D10) -> 0 | F10: =+INDEX('Budget original'!$A$2:$AO$500,MATCH($A10,'Budget original'!$A$2:$A$500,0),MATCH(F$2,'Budget original'!$A$2:$AO$2,0)) -> 0 | G10: 0 | H10: =IF(G10=0,0,I10/G10) -> 0 | I10: =+INDEX('Budget révisé'!$A$2:$AO$500,MATCH($A10,'Budget révisé'!$A$2:$A$500,0),MATCH(I$2,'Budget révisé'!$A$2:$AO$2,0)) -> 0 | J10: =-SUMIFS(BV_Data_An_Cour!$O:$O,BV_Data_An_Cour!$U:$U,$B10,BV_Data_An_Cour!$V:$V,$C10,BV_Data_An_Cour!$W:$W,J$2) -> 0 | K10: =IF(J10=0,0,L10/J10) -> 0 | L10: =-SUMIFS(BV_Data_An_Cour!$O:$O,BV_Data_An_Cour!$U:$U,$B10,BV_Data_An_Cour!$V:$V,$C10,BV_Data_An_Cour!$W:$W,L$2) -> 0 | M10: =J10-G10 -> 0 | N10: =L10-I10 -> 0 | O10: =-SUMIFS(BV_Data_An_Prec!$O:$O,BV_Data_An_Prec!$U:$U,$B10,BV_Data_An_Prec!$V:$V,$C10,BV_Data_An_Prec!$W:$W,O$2) -> 0 | P10: =IF(O10=0,0,Q10/O10) -> 0 | Q10: =-SUMIFS(BV_Data_An_Prec!$O:$O,BV_Data_An_Prec!$U:$U,$B10,BV_Data_An_Prec!$V:$V,$C10,BV_Data_An_Prec!$W:$W,Q$2) -> 0 | R10: =J10-O10 -> 0 | S10: =L10-Q10 -> 0
A11: Véhicules neufs[...] | B11: Véhicules neufs | C11: [...] | D11: 0 | E11: =IF(D11=0,0,F11/D11) -> 0 | F11: =+INDEX('Budget original'!$A$2:$AO$500,MATCH($A11,'Budget original'!$A$2:$A$500,0),MATCH(F$2,'Budget original'!$A$2:$AO$2,0)) -> 0 | G11: 0 | H11: =IF(G11=0,0,I11/G11) -> 0 | I11: =+INDEX('Budget révisé'!$A$2:$AO$500,MATCH($A11,'Budget révisé'!$A$2:$A$500,0),MATCH(I$2,'Budget révisé'!$A$2:$AO$2,0)) -> 0 | J11: =-SUMIFS(BV_Data_An_Cour!$O:$O,BV_Data_An_Cour!$U:$U,$B11,BV_Data_An_Cour!$V:$V,$C11,BV_Data_An_Cour!$W:$W,J$2) -> 0 | K11: =IF(J11=0,0,L11/J11) -> 0 | L11: =-SUMIFS(BV_Data_An_Cour!$O:$O,BV_Data_An_Cour!$U:$U,$B11,BV_Data_An_Cour!$V:$V,$C11,BV_Data_An_Cour!$W:$W,L$2) -> 0 | M11: =J11-G11 -> 0 | N11: =L11-I11 -> 0 | O11: =-SUMIFS(BV_Data_An_Prec!$O:$O,BV_Data_An_Prec!$U:$U,$B11,BV_Data_An_Prec!$V:$V,$C11,BV_Data_An_Prec!$W:$W,O$2) -> 0 | P11: =IF(O11=0,0,Q11/O11) -> 0 | Q11: =-SUMIFS(BV_Data_An_Prec!$O:$O,BV_Data_An_Prec!$U:$U,$B11,BV_Data_An_Prec!$V:$V,$C11,BV_Data_An_Prec!$W:$W,Q$2) -> 0 | R11: =J11-O11 -> 0 | S11: =L11-Q11 -> 0
A12: Véhicules neufs[...] | B12: Véhicules neufs | C12: [...] | D12: 0 | E12: =IF(D12=0,0,F12/D12) -> 0 | F12: =+INDEX('Budget original'!$A$2:$AO$500,MATCH($A12,'Budget original'!$A$2:$A$500,0),MATCH(F$2,'Budget original'!$A$2:$AO$2,0)) -> 0 | G12: 0 | H12: =IF(G12=0,0,I12/G12) -> 0 | I12: =+INDEX('Budget révisé'!$A$2:$AO$500,MATCH($A12,'Budget révisé'!$A$2:$A$500,0),MATCH(I$2,'Budget révisé'!$A$2:$AO$2,0)) -> 0 | J12: =-SUMIFS(BV_Data_An_Cour!$O:$O,BV_Data_An_Cour!$U:$U,$B12,BV_Data_An_Cour!$V:$V,$C12,BV_Data_An_Cour!$W:$W,J$2) -> 0 | K12: =IF(J12=0,0,L12/J12) -> 0 | L12: =-SUMIFS(BV_Data_An_Cour!$O:$O,BV_Data_An_Cour!$U:$U,$B12,BV_Data_An_Cour!$V:$V,$C12,BV_Data_An_Cour!$W:$W,L$2) -> 0 | M12: =J12-G12 -> 0 | N12: =L12-I12 -> 0 | O12: =-SUMIFS(BV_Data_An_Prec!$O:$O,BV_Data_An_Prec!$U:$U,$B12,BV_Data_An_Prec!$V:$V,$C12,BV_Data_An_Prec!$W:$W,O$2) -> 0 | P12: =IF(O12=0,0,Q12/O12) -> 0 | Q12: =-SUMIFS(BV_Data_An_Prec!$O:$O,BV_Data_An_Prec!$U:$U,$B12,BV_Data_An_Prec!$V:$V,$C12,BV_Data_An_Prec!$W:$W,Q$2) -> 0 | R12: =J12-O12 -> 0 | S12: =L12-Q12 -> 0
A13: Véhicules neufsTotal Neufs | B13: Véhicules neufs | C13: Total Neufs | D13: =+SUM(D6:D12) -> 86.515663 | E13: =IF(D13<=0,0,F13/D13) -> 1940.0612 | F13: =+SUM(F6:F12) -> 167845.68 | G13: =+SUM(G6:G12) -> 86.515663 | H13: =IF(G13<=0,0,I13/G13) -> 1940.0612 | I13: =+SUM(I6:I12) -> 167845.68 | J13: =+SUM(J6:J12) -> 43 | K13: =IF(J13<=0,0,L13/J13) -> 3688.0637 | L13: =+SUM(L6:L12) -> 158586.74 | M13: =+SUM(M6:M12) -> -43.515663 | N13: =+SUM(N6:N12) -> -9258.9429 | O13: =+SUM(O6:O12) -> 83 | P13: =IF(O13<=0,0,Q13/O13) -> 1793.4583 | Q13: =+SUM(Q6:Q12) -> 148857.04 | R13: =+SUM(R6:R12) -> -40 | S13: =+SUM(S6:S12) -> 9729.7
A14: Véhicules neufs | B14: Véhicules neufs | R14: =R13/O13 -> -0.48192771 | S14: =IF(Q13=0,0,(S13/Q13)) -> 0.065362713
A15: Véhicules neufsEx-Démos et courtoisies | B15: Véhicules neufs | C15: Ex-Démos et courtoisies | D15: =+INDEX('Budget original'!$A$2:$AO$500,MATCH($A15,'Budget original'!$A$2:$A$500,0),MATCH(D$2,'Budget original'!$A$2:$AO$2,0)) -> 8.0963855 | E15: =IF(D15=0,0,F15/D15) -> 1386.1016 | F15: =+INDEX('Budget original'!$A$2:$AO$500,MATCH($A15,'Budget original'!$A$2:$A$500,0),MATCH(F$2,'Budget original'!$A$2:$AO$2,0)) -> 11222.413 | G15: =+INDEX('Budget original'!$A$2:$AO$500,MATCH($A15,'Budget original'!$A$2:$A$500,0),MATCH(G$2,'Budget original'!$A$2:$AO$2,0)) -> 8.0963855 | H15: =IF(G15=0,0,I15/G15) -> 1386.1016 | I15: =+INDEX('Budget révisé'!$A$2:$AO$500,MATCH($A15,'Budget révisé'!$A$2:$A$500,0),MATCH(I$2,'Budget révisé'!$A$2:$AO$2,0)) -> 11222.413 | J15: =-SUMIFS(BV_Data_An_Cour!$O:$O,BV_Data_An_Cour!$U:$U,$B15,BV_Data_An_Cour!$V:$V,$C15,BV_Data_An_Cour!$W:$W,J$2) -> 3 | K15: =IF(J15=0,0,L15/J15) -> 5865.1167 | L15: =-SUMIFS(BV_Data_An_Cour!$O:$O,BV_Data_An_Cour!$U:$U,$B15,BV_Data_An_Cour!$V:$V,$C15,BV_Data_An_Cour!$W:$W,L$2) -> 17595.35 | M15: =J15-G15 -> -5.0963855 | N15: =L15-I15 -> 6372.9369 | O15: =-SUMIFS(BV_Data_An_Prec!$O:$O,BV_Data_An_Prec!$U:$U,$B15,BV_Data_An_Prec!$V:$V,$C15,BV_Data_An_Prec!$W:$W,O$2) -> 4 | P15: =IF(O15=0,0,Q15/O15) -> 2427.275 | Q15: =-SUMIFS(BV_Data_An_Prec!$O:$O,BV_Data_An_Prec!$U:$U,$B15,BV_Data_An_Prec!$V:$V,$C15,BV_Data_An_Prec!$W:$W,Q$2) -> 9709.1 | R15: =J15-O15 -> -1 | S15: =L15-Q15 -> 7886.25
A16: Véhicules neufs | B16: Véhicules neufs
A17: Véhicules neufsFlottes | B17: Véhicules neufs | C17: Flottes | D17: =+INDEX('Budget original'!$A$2:$AO$500,MATCH($A17,'Budget original'!$A$2:$A$500,0),MATCH(D$2,'Budget original'!$A$2:$AO$2,0)) -> 1.4563843 | E17: =IF(D17=0,0,F17/D17) -> 1938.8732 | F17: =+INDEX('Budget original'!$A$2:$AO$500,MATCH($A17,'Budget original'!$A$2:$A$500,0),MATCH(F$2,'Budget original'!$A$2:$AO$2,0)) -> 2823.7445 | G17: =+INDEX('Budget original'!$A$2:$AO$500,MATCH($A17,'Budget original'!$A$2:$A$500,0),MATCH(G$2,'Budget original'!$A$2:$AO$2,0)) -> 1.4563843 | H17: =IF(G17=0,0,I17/G17) -> 1938.8732 | I17: =+INDEX('Budget révisé'!$A$2:$AO$500,MATCH($A17,'Budget révisé'!$A$2:$A$500,0),MATCH(I$2,'Budget révisé'!$A$2:$AO$2,0)) -> 2823.7445 | J17: =-SUMIFS(BV_Data_An_Cour!$O:$O,BV_Data_An_Cour!$U:$U,$B17,BV_Data_An_Cour!$V:$V,$C17,BV_Data_An_Cour!$W:$W,J$2) -> 0 | K17: =IF(J17=0,0,L17/J17) -> 0 | L17: =-SUMIFS(BV_Data_An_Cour!$O:$O,BV_Data_An_Cour!$U:$U,$B17,BV_Data_An_Cour!$V:$V,$C17,BV_Data_An_Cour!$W:$W,L$2) -> 0 | M17: =J17-G17 -> -1.4563843 | N17: =L17-I17 -> -2823.7445 | O17: =-SUMIFS(BV_Data_An_Prec!$O:$O,BV_Data_An_Prec!$U:$U,$B17,BV_Data_An_Prec!$V:$V,$C17,BV_Data_An_Prec!$W:$W,O$2) -> 4 | P17: =IF(O17=0,0,Q17/O17) -> 2789.6125 | Q17: =-SUMIFS(BV_Data_An_Prec!$O:$O,BV_Data_An_Prec!$U:$U,$B17,BV_Data_An_Prec!$V:$V,$C17,BV_Data_An_Prec!$W:$W,Q$2) -> 11158.45 | R17: =J17-O17 -> -4 | S17: =L17-Q17 -> -11158.45
A18: Véhicules neufs | B18: Véhicules neufs
A19: Véhicules neufsRachat bail | B19: Véhicules neufs | C19: Rachat bail | D19: =+INDEX('Budget original'!$A$2:$AO$500,MATCH($A19,'Budget original'!$A$2:$A$500,0),MATCH(D$2,'Budget original'!$A$2:$AO$2,0)) -> 0 | E19: =IF(D19=0,0,F19/D19) -> 0 | F19: =+INDEX('Budget original'!$A$2:$AO$500,MATCH($A19,'Budget original'!$A$2:$A$500,0),MATCH(F$2,'Budget original'!$A$2:$AO$2,0)) -> 8416.039 | G19: =+INDEX('Budget original'!$A$2:$AO$500,MATCH($A19,'Budget original'!$A$2:$A$500,0),MATCH(G$2,'Budget original'!$A$2:$AO$2,0)) -> 0 | H19: =IF(G19=0,0,I19/G19) -> 0 | I19: =+INDEX('Budget révisé'!$A$2:$AO$500,MATCH($A19,'Budget révisé'!$A$2:$A$500,0),MATCH(I$2,'Budget révisé'!$A$2:$AO$2,0)) -> 8416.039 | L19: =-SUMIFS(BV_Data_An_Cour!$O:$O,BV_Data_An_Cour!$U:$U,$B19,BV_Data_An_Cour!$V:$V,$C19,BV_Data_An_Cour!$W:$W,L$2) -> 10153.06 | N19: =L19-I19 -> 1737.021 | Q19: =-SUMIFS(BV_Data_An_Prec!$O:$O,BV_Data_An_Prec!$U:$U,$B19,BV_Data_An_Prec!$V:$V,$C19,BV_Data_An_Prec!$W:$W,Q$2) -> 6141.99 | R19: =O19-K19 -> 0 | S19: =L19-Q19 -> 4011.07
A20: Véhicules neufs | B20: Véhicules neufs
A21: Véhicules neufsRev. Finances | B21: Véhicules neufs | C21: Rev. Finances | D21: =+INDEX('Budget original'!$A$2:$AO$500,MATCH($A21,'Budget original'!$A$2:$A$500,0),MATCH(D$2,'Budget original'!$A$2:$AO$2,0)) -> 0 | E21: =IF(D21=0,0,F21/D21) -> 0 | F21: =+INDEX('Budget original'!$A$2:$AO$500,MATCH($A21,'Budget original'!$A$2:$A$500,0),MATCH(F$2,'Budget original'!$A$2:$AO$2,0)) -> 2831.1485 | G21: =+INDEX('Budget original'!$A$2:$AO$500,MATCH($A21,'Budget original'!$A$2:$A$500,0),MATCH(G$2,'Budget original'!$A$2:$AO$2,0)) -> 0 | H21: =IF(G21=0,0,I21/G21) -> 0 | I21: =+INDEX('Budget révisé'!$A$2:$AO$500,MATCH($A21,'Budget révisé'!$A$2:$A$500,0),MATCH(I$2,'Budget révisé'!$A$2:$AO$2,0)) -> 2831.1485 | K21: =IF(J13=0,0,L21/(J13+J15)) -> 235.93391 | L21: =-SUMIFS(BV_Data_An_Cour!$O:$O,BV_Data_An_Cour!$U:$U,$B21,BV_Data_An_Cour!$V:$V,$C21,BV_Data_An_Cour!$W:$W,L$2) -> 10852.96 | N21: =L21-I21 -> 8021.8115 | P21: =IF(O13=0,0,Q21/(O13+O15)) -> 0 | Q21: =-SUMIFS(BV_Data_An_Prec!$O:$O,BV_Data_An_Prec!$U:$U,$B21,BV_Data_An_Prec!$V:$V,$C21,BV_Data_An_Prec!$W:$W,Q$2) -> 0 | R21: =O21-K21 -> -235.93391 | S21: =L21-Q21 -> 10852.96
A22: Véhicules neufsRev. Protections | B22: Véhicules neufs | C22: Rev. Protections | D22: =+INDEX('Budget original'!$A$2:$AO$500,MATCH($A22,'Budget original'!$A$2:$A$500,0),MATCH(D$2,'Budget original'!$A$2:$AO$2,0)) -> 0 | E22: =IF(D22=0,0,F22/D22) -> 0 | F22: =+INDEX('Budget original'!$A$2:$AO$500,MATCH($A22,'Budget original'!$A$2:$A$500,0),MATCH(F$2,'Budget original'!$A$2:$AO$2,0)) -> 75715.126 | G22: =+INDEX('Budget original'!$A$2:$AO$500,MATCH($A22,'Budget original'!$A$2:$A$500,0),MATCH(G$2,'Budget original'!$A$2:$AO$2,0)) -> 0 | H22: =IF(G22=0,0,I22/G22) -> 0 | I22: =+INDEX('Budget révisé'!$A$2:$AO$500,MATCH($A22,'Budget révisé'!$A$2:$A$500,0),MATCH(I$2,'Budget révisé'!$A$2:$AO$2,0)) -> 75715.126 | K22: =IF(J13=0,0,L22/(J13+J15)) -> 1009.41 | L22: =-SUMIFS(BV_Data_An_Cour!$O:$O,BV_Data_An_Cour!$U:$U,$B22,BV_Data_An_Cour!$V:$V,$C22,BV_Data_An_Cour!$W:$W,L$2) -> 46432.86 | N22: =L22-I22 -> -29282.266 | P22: =IF(O13=0,0,Q22/(O13+O15)) -> 765.23471 | Q22: =-SUMIFS(BV_Data_An_Prec!$O:$O,BV_Data_An_Prec!$U:$U,$B22,BV_Data_An_Prec!$V:$V,$C22,BV_Data_An_Prec!$W:$W,Q$2) -> 66575.42 | R22: =O22-K22 -> -1009.41 | S22: =L22-Q22 -> -20142.56
A23: Véhicules neufsRev. Autres | B23: Véhicules neufs | C23: Rev. Autres | D23: =+INDEX('Budget original'!$A$2:$AO$500,MATCH($A23,'Budget original'!$A$2:$A$500,0),MATCH(D$2,'Budget original'!$A$2:$AO$2,0)) -> 0 | E23: =IF(D23=0,0,F23/D23) -> 0 | F23: =+INDEX('Budget original'!$A$2:$AO$500,MATCH($A23,'Budget original'!$A$2:$A$500,0),MATCH(F$2,'Budget original'!$A$2:$AO$2,0)) -> 1873.9666 | G23: =+INDEX('Budget original'!$A$2:$AO$500,MATCH($A23,'Budget original'!$A$2:$A$500,0),MATCH(G$2,'Budget original'!$A$2:$AO$2,0)) -> 0 | H23: =IF(G23=0,0,I23/G23) -> 0 | I23: =+INDEX('Budget révisé'!$A$2:$AO$500,MATCH($A23,'Budget révisé'!$A$2:$A$500,0),MATCH(I$2,'Budget révisé'!$A$2:$AO$2,0)) -> 1873.9666 | K23: =IF(J13=0,0,L23/(J13+J15)) -> 6.1243478 | L23: =-SUMIFS(BV_Data_An_Cour!$O:$O,BV_Data_An_Cour!$U:$U,$B23,BV_Data_An_Cour!$V:$V,$C23,BV_Data_An_Cour!$W:$W,L$2) -> 281.72 | N23: =L23-I23 -> -1592.2466 | P23: =IF(O13=0,0,Q23/(O13+O15)) -> 18.082414 | Q23: =-SUMIFS(BV_Data_An_Prec!$O:$O,BV_Data_An_Prec!$U:$U,$B23,BV_Data_An_Prec!$V:$V,$C23,BV_Data_An_Prec!$W:$W,Q$2) -> 1573.17 | R23: =O23-K23 -> -6.1243478 | S23: =L23-Q23 -> -1291.45
A24: Véhicules neufsTotal F&I | B24: Véhicules neufs | C24: Total F&I | D24: =+D15+D13 -> 94.612048 | E24: =IF(D24<=0,0,F24/D24) -> 850 | F24: =F21+F22+F23 -> 80420.241 | G24: =+G15+G13 -> 94.612048 | H24: =IF(G24<=0,0,I24/G24) -> 850 | I24: =I21+I22+I23 -> 80420.241 | J24: =+J15+J13 -> 46 | K24: =IF(J24<=0,0,L24/J24) -> 1251.4683 | L24: =L21+L22+L23 -> 57567.54 | M24: =J24-G24 -> -48.612048 | N24: =L24-I24 -> -22852.701 | O24: =+O15+O13 -> 87 | P24: =IF(O24<=0,0,Q24/O24) -> 783.31713 | Q24: =Q21+Q22+Q23 -> 68148.59 | S24: =L24-Q24 -> -10581.05
A25: Véhicules neufs | B25: Véhicules neufs | N25: =IF(N24=0,0,N24/I24) -> -0.28416603 | S25: =IF(Q24=0,0,(S24/Q24)) -> -0.1552644
A26: Véhicules neufs | B26: Véhicules neufs
A27: Véhicules neufsTotal Dépt. Neufs | B27: Véhicules neufs | C27: Total Dépt. Neufs | D27: =+D13+D15+D17 -> 96.068433 | E27: =IF(D27<=0,0,F27/D27) -> 2818.0758 | F27: =F13+F17+F24+F19+F15 -> 270728.12 | G27: =+G13+G15+G17 -> 96.068433 | H27: =IF(G27<=0,0,I27/G27) -> 2818.0758 | I27: =I13+I17+I24+I19+I15 -> 270728.12 | J27: =+J13+J15+J17 -> 46 | K27: =IF(J27<=0,0,L27/J27) -> 5302.2324 | L27: =L13+L17+L24+L19+L15 -> 243902.69 | M27: =J27-G27 -> -50.068433 | N27: =L27-I27 -> -26825.43 | O27: =+O13+O15+O17 -> 91 | P27: =IF(O27<=0,0,Q27/O27) -> 2681.4854 | Q27: =Q13+Q17+Q24+Q19+Q15 -> 244015.17 | R27: =J27-O27 -> -45 | S27: =L27-Q27 -> -112.48
A28: Véhicules neufs | B28: Véhicules neufs | M28: =M27/G27 -> -0.52117466 | N28: =N27/I27 -> -0.099086236 | R28: =R27/O27 -> -0.49450549 | S28: =IF(Q27=0,0,S27/Q27) -> -0.00046095495
A29: Véhicules neufs | B29: Véhicules neufs
A30: Véhicules neufsDEPENSES | B30: Véhicules neufs | C30: DEPENSES
A31: Véhicules neufsComm. vendeurs | B31: Véhicules neufs | C31: Comm. vendeurs | D31: =F31/(F15+F13) -> 0.31286677 | E31: =F31/D$24 -> 592.14929 | F31: =+INDEX('Budget original'!$A$2:$AO$500,MATCH($A31,'Budget original'!$A$2:$A$500,0),MATCH(F$2,'Budget original'!$A$2:$AO$2,0)) -> 56024.457 | G31: =I31/(I15+I13) -> 0.31286677 | H31: =I31/G$24 -> 592.14929 | I31: =+INDEX('Budget révisé'!$A$2:$AO$500,MATCH($A31,'Budget révisé'!$A$2:$A$500,0),MATCH(I$2,'Budget révisé'!$A$2:$AO$2,0)) -> 56024.457 | J31: =L31/(L15+L13) -> 0.28520487 | K31: =IF(L31=0,0,L31/J$24) -> 1092.3476 | L31: =SUMIFS(BV_Data_An_Cour!$O:$O,BV_Data_An_Cour!$U:$U,$B31,BV_Data_An_Cour!$V:$V,$C31,BV_Data_An_Cour!$W:$W,L$2) -> 50247.99 | N31: =L31-I31 -> -5776.4671 | P31: =IF(Q31=0,0,Q31/O$24) -> 611.33368 | Q31: =SUMIFS(BV_Data_An_Prec!$O:$O,BV_Data_An_Prec!$U:$U,$B31,BV_Data_An_Prec!$V:$V,$C31,BV_Data_An_Prec!$W:$W,Q$2) -> 53186.03 | S31: =L31-Q31 -> -2938.04
A32: Véhicules neufsComm. F&I | B32: Véhicules neufs | C32: Comm. F&I | D32: =F32/F24 -> 0.3 | E32: =F32/D$24 -> 255 | F32: =+INDEX('Budget original'!$A$2:$AO$500,MATCH($A32,'Budget original'!$A$2:$A$500,0),MATCH(F$2,'Budget original'!$A$2:$AO$2,0)) -> 24126.072 | G32: =I32/I24 -> 0.3 | H32: =I32/G$24 -> 255 | I32: =+INDEX('Budget révisé'!$A$2:$AO$500,MATCH($A32,'Budget révisé'!$A$2:$A$500,0),MATCH(I$2,'Budget révisé'!$A$2:$AO$2,0)) -> 24126.072 | J32: =L32/L24 -> 0.36279907 | K32: =IF(L32=0,0,L32/J$24) -> 454.03152 | L32: =SUMIFS(BV_Data_An_Cour!$O:$O,BV_Data_An_Cour!$U:$U,$B32,BV_Data_An_Cour!$V:$V,$C32,BV_Data_An_Cour!$W:$W,L$2) -> 20885.45 | N32: =L32-I32 -> -3240.6223 | P32: =IF(Q32=0,0,Q32/O$24) -> 240.78989 | Q32: =SUMIFS(BV_Data_An_Prec!$O:$O,BV_Data_An_Prec!$U:$U,$B32,BV_Data_An_Prec!$V:$V,$C32,BV_Data_An_Prec!$W:$W,Q$2) -> 20948.72 | S32: =L32-Q32 -> -63.27 | U32: =(L32+L112)/(L104+L24+L19) -> 0.29703872 | V32: <<- F&A total Neuf Usagé Rachat
A33: Véhicules neufsFrais de livraison | B33: Véhicules neufs | C33: Frais de livraison | E33: =F33/D$24 -> 167.8493 | F33: =+INDEX('Budget original'!$A$2:$AO$500,MATCH($A33,'Budget original'!$A$2:$A$500,0),MATCH(F$2,'Budget original'!$A$2:$AO$2,0)) -> 15880.566 | H33: =I33/G$24 -> 167.8493 | I33: =+INDEX('Budget révisé'!$A$2:$AO$500,MATCH($A33,'Budget révisé'!$A$2:$A$500,0),MATCH(I$2,'Budget révisé'!$A$2:$AO$2,0)) -> 15880.566 | K33: =IF(L33=0,0,L33/J$24) -> 104.73239 | L33: =SUMIFS(BV_Data_An_Cour!$O:$O,BV_Data_An_Cour!$U:$U,$B33,BV_Data_An_Cour!$V:$V,$C33,BV_Data_An_Cour!$W:$W,L$2) -> 4817.69 | N33: =L33-I33 -> -11062.876 | P33: =IF(Q33=0,0,Q33/O$24) -> 74.75069 | Q33: =SUMIFS(BV_Data_An_Prec!$O:$O,BV_Data_An_Prec!$U:$U,$B33,BV_Data_An_Prec!$V:$V,$C33,BV_Data_An_Prec!$W:$W,Q$2) -> 6503.31 | S33: =L33-Q33 -> -1685.62
A34: Véhicules neufsService gratuit 1 | B34: Véhicules neufs | C34: Service gratuit 1 | E34: =F34/D$24 -> 7.3548076 | F34: =+INDEX('Budget original'!$A$2:$AO$500,MATCH($A34,'Budget original'!$A$2:$A$500,0),MATCH(F$2,'Budget original'!$A$2:$AO$2,0)) -> 695.85341 | H34: =I34/G$24 -> 7.3548076 | I34: =+INDEX('Budget révisé'!$A$2:$AO$500,MATCH($A34,'Budget révisé'!$A$2:$A$500,0),MATCH(I$2,'Budget révisé'!$A$2:$AO$2,0)) -> 695.85341 | K34: =IF(L34=0,0,L34/J$24) -> 0 | L34: =SUMIFS(BV_Data_An_Cour!$O:$O,BV_Data_An_Cour!$U:$U,$B34,BV_Data_An_Cour!$V:$V,$C34,BV_Data_An_Cour!$W:$W,L$2) -> 0 | N34: =L34-I34 -> -695.85341 | P34: =IF(Q34=0,0,Q34/O$24) -> 6.8565517 | Q34: =SUMIFS(BV_Data_An_Prec!$O:$O,BV_Data_An_Prec!$U:$U,$B34,BV_Data_An_Prec!$V:$V,$C34,BV_Data_An_Prec!$W:$W,Q$2) -> 596.52 | S34: =L34-Q34 -> -596.52
A35: Véhicules neufsEntretien stock | B35: Véhicules neufs | C35: Entretien stock | E35: =F35/D$24 -> 17.733118 | F35: =+INDEX('Budget original'!$A$2:$AO$500,MATCH($A35,'Budget original'!$A$2:$A$500,0),MATCH(F$2,'Budget original'!$A$2:$AO$2,0)) -> 1677.7666 | H35: =I35/G$24 -> 17.733118 | I35: =+INDEX('Budget révisé'!$A$2:$AO$500,MATCH($A35,'Budget révisé'!$A$2:$A$500,0),MATCH(I$2,'Budget révisé'!$A$2:$AO$2,0)) -> 1677.7666 | K35: =IF(L35=0,0,L35/J$24) -> 100.76913 | L35: =SUMIFS(BV_Data_An_Cour!$O:$O,BV_Data_An_Cour!$U:$U,$B35,BV_Data_An_Cour!$V:$V,$C35,BV_Data_An_Cour!$W:$W,L$2) -> 4635.38 | N35: =L35-I35 -> 2957.6134 | P35: =IF(Q35=0,0,Q35/O$24) -> 13.448276 | Q35: =SUMIFS(BV_Data_An_Prec!$O:$O,BV_Data_An_Prec!$U:$U,$B35,BV_Data_An_Prec!$V:$V,$C35,BV_Data_An_Prec!$W:$W,Q$2) -> 1170 | S35: =L35-Q35 -> 3465.38
A36: Véhicules neufsPublicité 1 | B36: Véhicules neufs | C36: Publicité 1 | E36: =F36/D$24 -> 195.93765 | F36: =+INDEX('Budget original'!$A$2:$AO$500,MATCH($A36,'Budget original'!$A$2:$A$500,0),MATCH(F$2,'Budget original'!$A$2:$AO$2,0)) -> 18538.063 | H36: =I36/G$24 -> 195.93765 | I36: =+INDEX('Budget révisé'!$A$2:$AO$500,MATCH($A36,'Budget révisé'!$A$2:$A$500,0),MATCH(I$2,'Budget révisé'!$A$2:$AO$2,0)) -> 18538.063 | K36: =IF(L36=0,0,L36/J$24) -> 382.71152 | L36: =SUMIFS(BV_Data_An_Cour!$O:$O,BV_Data_An_Cour!$U:$U,$B36,BV_Data_An_Cour!$V:$V,$C36,BV_Data_An_Cour!$W:$W,L$2) -> 17604.73 | N36: =L36-I36 -> -933.33265 | P36: =IF(Q36=0,0,Q36/O$24) -> 119.94092 | Q36: =SUMIFS(BV_Data_An_Prec!$O:$O,BV_Data_An_Prec!$U:$U,$B36,BV_Data_An_Prec!$V:$V,$C36,BV_Data_An_Prec!$W:$W,Q$2) -> 10434.86 | S36: =L36-Q36 -> 7169.87
A37: Véhicules neufsIntérêt de gros | B37: Véhicules neufs | C37: Intérêt de gros | E37: =F37/D$24 -> 83.856314 | F37: =+INDEX('Budget original'!$A$2:$AO$500,MATCH($A37,'Budget original'!$A$2:$A$500,0),MATCH(F$2,'Budget original'!$A$2:$AO$2,0)) -> 7933.8176 | H37: =I37/G$24 -> 83.856314 | I37: =+INDEX('Budget révisé'!$A$2:$AO$500,MATCH($A37,'Budget révisé'!$A$2:$A$500,0),MATCH(I$2,'Budget révisé'!$A$2:$AO$2,0)) -> 7933.8176 | K37: =IF(L37=0,0,L37/J$24) -> 5.9121739 | L37: =SUMIFS(BV_Data_An_Cour!$O:$O,BV_Data_An_Cour!$U:$U,$B37,BV_Data_An_Cour!$V:$V,$C37,BV_Data_An_Cour!$W:$W,L$2) -> 271.96 | N37: =L37-I37 -> -7661.8576 | P37: =IF(Q37=0,0,Q37/O$24) -> 161.06483 | Q37: =SUMIFS(BV_Data_An_Prec!$O:$O,BV_Data_An_Prec!$U:$U,$B37,BV_Data_An_Prec!$V:$V,$C37,BV_Data_An_Prec!$W:$W,Q$2) -> 14012.64 | S37: =L37-Q37 -> -13740.68
A38: Véhicules neufs[...] | B38: Véhicules neufs | C38: [...] | E38: =F38/D$24 -> 0 | F38: =+INDEX('Budget original'!$A$2:$AO$500,MATCH($A38,'Budget original'!$A$2:$A$500,0),MATCH(F$2,'Budget original'!$A$2:$AO$2,0)) -> 0 | H38: =I38/G$24 -> 0 | I38: =+INDEX('Budget révisé'!$A$2:$AO$500,MATCH($A38,'Budget révisé'!$A$2:$A$500,0),MATCH(I$2,'Budget révisé'!$A$2:$AO$2,0)) -> 0 | K38: =IF(L38=0,0,L38/J$24) -> 0 | L38: =SUMIFS(BV_Data_An_Cour!$O:$O,BV_Data_An_Cour!$U:$U,$B38,BV_Data_An_Cour!$V:$V,$C38,BV_Data_An_Cour!$W:$W,L$2) -> 0 | N38: =L38-I38 -> 0 | P38: =IF(Q38=0,0,Q38/O$24) -> 0 | Q38: =SUMIFS(BV_Data_An_Prec!$O:$O,BV_Data_An_Prec!$U:$U,$B38,BV_Data_An_Prec!$V:$V,$C38,BV_Data_An_Prec!$W:$W,Q$2) -> 0 | S38: =L38-Q38 -> 0
A39: Véhicules neufs[...] | B39: Véhicules neufs | C39: [...] | E39: =F39/D$24 -> 0 | F39: =+INDEX('Budget original'!$A$2:$AO$500,MATCH($A39,'Budget original'!$A$2:$A$500,0),MATCH(F$2,'Budget original'!$A$2:$AO$2,0)) -> 0 | H39: =I39/G$24 -> 0 | I39: =+INDEX('Budget révisé'!$A$2:$AO$500,MATCH($A39,'Budget révisé'!$A$2:$A$500,0),MATCH(I$2,'Budget révisé'!$A$2:$AO$2,0)) -> 0 | K39: =IF(L39=0,0,L39/J$24) -> 0 | L39: =SUMIFS(BV_Data_An_Cour!$O:$O,BV_Data_An_Cour!$U:$U,$B39,BV_Data_An_Cour!$V:$V,$C39,BV_Data_An_Cour!$W:$W,L$2) -> 0 | N39: =L39-I39 -> 0 | P39: =IF(Q39=0,0,Q39/O$24) -> 0 | Q39: =SUMIFS(BV_Data_An_Prec!$O:$O,BV_Data_An_Prec!$U:$U,$B39,BV_Data_An_Prec!$V:$V,$C39,BV_Data_An_Prec!$W:$W,Q$2) -> 0 | S39: =L39-Q39 -> 0
A40: Véhicules neufs[...] | B40: Véhicules neufs | C40: [...] | E40: =F40/D$24 -> 0 | F40: =+INDEX('Budget original'!$A$2:$AO$500,MATCH($A40,'Budget original'!$A$2:$A$500,0),MATCH(F$2,'Budget original'!$A$2:$AO$2,0)) -> 0 | H40: =I40/G$24 -> 0 | I40: =+INDEX('Budget révisé'!$A$2:$AO$500,MATCH($A40,'Budget révisé'!$A$2:$A$500,0),MATCH(I$2,'Budget révisé'!$A$2:$AO$2,0)) -> 0 | K40: =IF(L40=0,0,L40/J$24) -> 0 | L40: =SUMIFS(BV_Data_An_Cour!$O:$O,BV_Data_An_Cour!$U:$U,$B40,BV_Data_An_Cour!$V:$V,$C40,BV_Data_An_Cour!$W:$W,L$2) -> 0 | N40: =L40-I40 -> 0 | P40: =IF(Q40=0,0,Q40/O$24) -> 0 | Q40: =SUMIFS(BV_Data_An_Prec!$O:$O,BV_Data_An_Prec!$U:$U,$B40,BV_Data_An_Prec!$V:$V,$C40,BV_Data_An_Prec!$W:$W,Q$2) -> 0 | S40: =L40-Q40 -> 0
A41: Véhicules neufsTOTAL VARIABLES | B41: Véhicules neufs | C41: TOTAL VARIABLES | D41: % brut | E41: =F41/F$27 -> 0.46126201 | F41: =SUM(F31:F40) -> 124876.6 | G41: % brut | H41: =I41/I$27 -> 0.46126201 | I41: =SUM(I31:I40) -> 124876.6 | J41: % brut | K41: =L41/L$27 -> 0.4036987 | L41: =SUM(L31:L40) -> 98463.2 | N41: =L41-I41 -> -26413.396 | O41: % brut | P41: =Q41/Q$27 -> 0.43789114 | Q41: =SUM(Q31:Q40) -> 106852.08 | S41: =L41-Q41 -> -8388.88
A42: Véhicules neufsSalaires cadres | B42: Véhicules neufs | C42: Salaires cadres | F42: =+INDEX('Budget original'!$A$2:$AO$500,MATCH($A42,'Budget original'!$A$2:$A$500,0),MATCH(F$2,'Budget original'!$A$2:$AO$2,0)) -> 15886.261 | I42: =+INDEX('Budget révisé'!$A$2:$AO$500,MATCH($A42,'Budget révisé'!$A$2:$A$500,0),MATCH(I$2,'Budget révisé'!$A$2:$AO$2,0)) -> 15886.261 | L42: =SUMIFS(BV_Data_An_Cour!$O:$O,BV_Data_An_Cour!$U:$U,$B42,BV_Data_An_Cour!$V:$V,$C42,BV_Data_An_Cour!$W:$W,L$2) -> 14110.59 | N42: =L42-I42 -> -1775.6709 | Q42: =SUMIFS(BV_Data_An_Prec!$O:$O,BV_Data_An_Prec!$U:$U,$B42,BV_Data_An_Prec!$V:$V,$C42,BV_Data_An_Prec!$W:$W,Q$2) -> 21334.91 | S42: =L42-Q42 -> -7224.32
A43: Véhicules neufsSalaires commis | B43: Véhicules neufs | C43: Salaires commis | F43: =+INDEX('Budget original'!$A$2:$AO$500,MATCH($A43,'Budget original'!$A$2:$A$500,0),MATCH(F$2,'Budget original'!$A$2:$AO$2,0)) -> 9822.0278 | I43: =+INDEX('Budget révisé'!$A$2:$AO$500,MATCH($A43,'Budget révisé'!$A$2:$A$500,0),MATCH(I$2,'Budget révisé'!$A$2:$AO$2,0)) -> 9822.0278 | L43: =SUMIFS(BV_Data_An_Cour!$O:$O,BV_Data_An_Cour!$U:$U,$B43,BV_Data_An_Cour!$V:$V,$C43,BV_Data_An_Cour!$W:$W,L$2) -> 7742.61 | N43: =L43-I43 -> -2079.4178 | Q43: =SUMIFS(BV_Data_An_Prec!$O:$O,BV_Data_An_Prec!$U:$U,$B43,BV_Data_An_Prec!$V:$V,$C43,BV_Data_An_Prec!$W:$W,Q$2) -> 9816.59 | S43: =L43-Q43 -> -2073.98
A44: Véhicules neufsSalaires autres | B44: Véhicules neufs | C44: Salaires autres | F44: =+INDEX('Budget original'!$A$2:$AO$500,MATCH($A44,'Budget original'!$A$2:$A$500,0),MATCH(F$2,'Budget original'!$A$2:$AO$2,0)) -> 8921.4022 | I44: =+INDEX('Budget révisé'!$A$2:$AO$500,MATCH($A44,'Budget révisé'!$A$2:$A$500,0),MATCH(I$2,'Budget révisé'!$A$2:$AO$2,0)) -> 8921.4022 | L44: =SUMIFS(BV_Data_An_Cour!$O:$O,BV_Data_An_Cour!$U:$U,$B44,BV_Data_An_Cour!$V:$V,$C44,BV_Data_An_Cour!$W:$W,L$2) -> 4148.58 | N44: =L44-I44 -> -4772.8222 | Q44: =SUMIFS(BV_Data_An_Prec!$O:$O,BV_Data_An_Prec!$U:$U,$B44,BV_Data_An_Prec!$V:$V,$C44,BV_Data_An_Prec!$W:$W,Q$2) -> 8653.41 | S44: =L44-Q44 -> -4504.83
A45: Véhicules neufsSalaires spécialistes | B45: Véhicules neufs | C45: Salaires spécialistes | F45: =+INDEX('Budget original'!$A$2:$AO$500,MATCH($A45,'Budget original'!$A$2:$A$500,0),MATCH(F$2,'Budget original'!$A$2:$AO$2,0)) -> 0 | I45: =+INDEX('Budget révisé'!$A$2:$AO$500,MATCH($A45,'Budget révisé'!$A$2:$A$500,0),MATCH(I$2,'Budget révisé'!$A$2:$AO$2,0)) -> 0 | L45: =SUMIFS(BV_Data_An_Cour!$O:$O,BV_Data_An_Cour!$U:$U,$B45,BV_Data_An_Cour!$V:$V,$C45,BV_Data_An_Cour!$W:$W,L$2) -> 0 | N45: =L45-I45 -> 0 | Q45: =SUMIFS(BV_Data_An_Prec!$O:$O,BV_Data_An_Prec!$U:$U,$B45,BV_Data_An_Prec!$V:$V,$C45,BV_Data_An_Prec!$W:$W,Q$2) -> 0 | S45: =L45-Q45 -> 0
A46: Véhicules neufs[...] | B46: Véhicules neufs | C46: [...] | F46: =+INDEX('Budget original'!$A$2:$AO$500,MATCH($A46,'Budget original'!$A$2:$A$500,0),MATCH(F$2,'Budget original'!$A$2:$AO$2,0)) -> 0 | I46: =+INDEX('Budget révisé'!$A$2:$AO$500,MATCH($A46,'Budget révisé'!$A$2:$A$500,0),MATCH(I$2,'Budget révisé'!$A$2:$AO$2,0)) -> 0 | L46: =SUMIFS(BV_Data_An_Cour!$O:$O,BV_Data_An_Cour!$U:$U,$B46,BV_Data_An_Cour!$V:$V,$C46,BV_Data_An_Cour!$W:$W,L$2) -> 0 | N46: =L46-I46 -> 0 | Q46: =SUMIFS(BV_Data_An_Prec!$O:$O,BV_Data_An_Prec!$U:$U,$B46,BV_Data_An_Prec!$V:$V,$C46,BV_Data_An_Prec!$W:$W,Q$2) -> 0 | S46: =L46-Q46 -> 0
A47: Véhicules neufs[...] | B47: Véhicules neufs | C47: [...] | F47: =+INDEX('Budget original'!$A$2:$AO$500,MATCH($A47,'Budget original'!$A$2:$A$500,0),MATCH(F$2,'Budget original'!$A$2:$AO$2,0)) -> 0 | I47: =+INDEX('Budget révisé'!$A$2:$AO$500,MATCH($A47,'Budget révisé'!$A$2:$A$500,0),MATCH(I$2,'Budget révisé'!$A$2:$AO$2,0)) -> 0 | L47: =SUMIFS(BV_Data_An_Cour!$O:$O,BV_Data_An_Cour!$U:$U,$B47,BV_Data_An_Cour!$V:$V,$C47,BV_Data_An_Cour!$W:$W,L$2) -> 0 | N47: =L47-I47 -> 0 | Q47: =SUMIFS(BV_Data_An_Prec!$O:$O,BV_Data_An_Prec!$U:$U,$B47,BV_Data_An_Prec!$V:$V,$C47,BV_Data_An_Prec!$W:$W,Q$2) -> 0 | S47: =L47-Q47 -> 0
A48: Véhicules neufs[...] | B48: Véhicules neufs | C48: [...] | F48: =+INDEX('Budget original'!$A$2:$AO$500,MATCH($A48,'Budget original'!$A$2:$A$500,0),MATCH(F$2,'Budget original'!$A$2:$AO$2,0)) -> 0 | I48: =+INDEX('Budget révisé'!$A$2:$AO$500,MATCH($A48,'Budget révisé'!$A$2:$A$500,0),MATCH(I$2,'Budget révisé'!$A$2:$AO$2,0)) -> 0 | L48: =SUMIFS(BV_Data_An_Cour!$O:$O,BV_Data_An_Cour!$U:$U,$B48,BV_Data_An_Cour!$V:$V,$C48,BV_Data_An_Cour!$W:$W,L$2) -> 0 | N48: =L48-I48 -> 0 | Q48: =SUMIFS(BV_Data_An_Prec!$O:$O,BV_Data_An_Prec!$U:$U,$B48,BV_Data_An_Prec!$V:$V,$C48,BV_Data_An_Prec!$W:$W,Q$2) -> 0 | S48: =L48-Q48 -> 0
