Workbook
Name Ticker: #REF!
Name Ticker: #REF!

Sheet Parametres
A1: Compagnie | B1: Volks
G2: 1-Mémo | M2: Mois | N2: YTD
A3: Mois Courant | B3: Mars | C3: =+VLOOKUP(B3,$K$3:$L$14,2,0) -> 3 | G3: 10-Compte compteur | K3: Janvier | L3: 1 | M3: =+IF($K3=$B$3,"X","") | N3: =+IF(K3=B3,"X",IF(L3<=$C$3,"X","")) -> X
A4: Année | B4: 2026 | K4: Février | L4: 2 | M4: =+IF($K4=$B$3,"X","") | N4: =+IF(K4=B4,"X",IF(L4<=$C$3,"X","")) -> X
K5: Mars | L5: 3 | M5: =+IF($K5=$B$3,"X","") -> X | N5: =+IF(K5=B5,"X",IF(L5<=$C$3,"X","")) -> X
K6: Avril | L6: 4 | M6: =+IF($K6=$B$3,"X","") | N6: =+IF(K6=B6,"X",IF(L6<=$C$3,"X",""))
K7: Mai | L7: 5 | M7: =+IF($K7=$B$3,"X","") | N7: =+IF(K7=B7,"X",IF(L7<=$C$3,"X",""))
K8: Juin | L8: 6 | M8: =+IF($K8=$B$3,"X","") | N8: =+IF(K8=B8,"X",IF(L8<=$C$3,"X",""))
A9: Sélectionner le mois en B3 | K9: Juillet | L9: 7 | M9: =+IF($K9=$B$3,"X","") | N9: =+IF(K9=B9,"X",IF(L9<=$C$3,"X",""))
A10: Coller les balances de vérification respectives en cellule A1 dans les onglets BV_Data_An_Cour et BV_Data_An_Prec | K10: Août | L10: 8 | M10: =+IF($K10=$B$3,"X","") | N10: =+IF(K10=B10,"X",IF(L10<=$C$3,"X",""))
A11: Vérifier s'il y a des #N/A dans les colonnes T à X des onlgets de BV | K11: Septembre | L11: 9 | M11: =+IF($K11=$B$3,"X","") | N11: =+IF(K11=B11,"X",IF(L11<=$C$3,"X",""))
A12: Vérifier les chiffres avec l'état financier et les réalisés an passé pour les résultat net mois et aad | K12: Octobre | L12: 10 | M12: =+IF($K12=$B$3,"X","") | N12: =+IF(K12=B12,"X",IF(L12<=$C$3,"X",""))
K13: Novembre | L13: 11 | M13: =+IF($K13=$B$3,"X","") | N13: =+IF(K13=B13,"X",IF(L13<=$C$3,"X",""))
K14: Décembre | L14: 12 | M14: =+IF($K14=$B$3,"X","") | N14: =+IF(K14=B14,"X",IF(L14<=$C$3,"X",""))

Sheet Bilan
A1: BILAN
A2: =+Parametres!B1 -> Volks
A3: =CONCATENATE("",,Parametres!B3," ",Parametres!B4) -> Mars 2026
A5: Encaisse | B5: =SUMIFS(BV_Data_An_Cour!$P:$P,BV_Data_An_Cour!$U:$U,$A$1,BV_Data_An_Cour!$V:$V,$A5) -> 869083.65 | D5: Marge de crédit | E5: =-SUMIFS(BV_Data_An_Cour!$P:$P,BV_Data_An_Cour!$U:$U,$A$1,BV_Data_An_Cour!$V:$V,$D5) -> 0
A6: Total Trésorerie et équivalent de Trésorerie | B6: =SUM(B5) -> 869083.65
D7: Portion Court Terme de la Dette Long Terme | E7: =-SUMIFS(BV_Data_An_Cour!$P:$P,BV_Data_An_Cour!$U:$U,$A$1,BV_Data_An_Cour!$V:$V,$D7) -> 0
A8: Recevables Contrats en Transit | B8: =SUMIFS(BV_Data_An_Cour!$P:$P,BV_Data_An_Cour!$U:$U,$A$1,BV_Data_An_Cour!$V:$V,$A8) -> 1061257.6
A9: Recevables Véhicules | B9: =SUMIFS(BV_Data_An_Cour!$P:$P,BV_Data_An_Cour!$U:$U,$A$1,BV_Data_An_Cour!$V:$V,$A9) -> 432464.05 | D9: Avances à payer | E9: =-SUMIFS(BV_Data_An_Cour!$P:$P,BV_Data_An_Cour!$U:$U,$A$1,BV_Data_An_Cour!$V:$V,$D9) -> 0
A10: Recevables Manufacturier | B10: =SUMIFS(BV_Data_An_Cour!$P:$P,BV_Data_An_Cour!$U:$U,$A$1,BV_Data_An_Cour!$V:$V,$A10) -> 329144 | D10: Comptes à Payer Fournisseurs | E10: =-SUMIFS(BV_Data_An_Cour!$P:$P,BV_Data_An_Cour!$U:$U,$A$1,BV_Data_An_Cour!$V:$V,$D10) -> 500058.86
A11: Recevables Pièces et Service | B11: =SUMIFS(BV_Data_An_Cour!$P:$P,BV_Data_An_Cour!$U:$U,$A$1,BV_Data_An_Cour!$V:$V,$A11) -> 364961.84 | D11: Taxes de Vente à Payer | E11: =-SUMIFS(BV_Data_An_Cour!$P:$P,BV_Data_An_Cour!$U:$U,$A$1,BV_Data_An_Cour!$V:$V,$D11) -> 37029.2
A12: Recevables Garantie Manufacturier | B12: =SUMIFS(BV_Data_An_Cour!$P:$P,BV_Data_An_Cour!$U:$U,$A$1,BV_Data_An_Cour!$V:$V,$A12) -> 103776.48 | D12: Impôts à payer | E12: =-SUMIFS(BV_Data_An_Cour!$P:$P,BV_Data_An_Cour!$U:$U,$A$1,BV_Data_An_Cour!$V:$V,$D12) -> 0
A13: Recevables Carrosserie | B13: =SUMIFS(BV_Data_An_Cour!$P:$P,BV_Data_An_Cour!$U:$U,$A$1,BV_Data_An_Cour!$V:$V,$A13) -> 5239.04 | D13: Dépôts de Client | E13: =-SUMIFS(BV_Data_An_Cour!$P:$P,BV_Data_An_Cour!$U:$U,$A$1,BV_Data_An_Cour!$V:$V,$D13) -> 16400
A14: Recevables Intercos | B14: =SUMIFS(BV_Data_An_Cour!$P:$P,BV_Data_An_Cour!$U:$U,$A$1,BV_Data_An_Cour!$V:$V,$A14) -> 0 | D14: Payables Intercos | E14: =-SUMIFS(BV_Data_An_Cour!$P:$P,BV_Data_An_Cour!$U:$U,$A$1,BV_Data_An_Cour!$V:$V,$D14) -> 0
A15: Recevables Autres | B15: =SUMIFS(BV_Data_An_Cour!$P:$P,BV_Data_An_Cour!$U:$U,$A$1,BV_Data_An_Cour!$V:$V,$A15) -> -6439.35 | D15: Autres Comptes à Payer | E15: =-SUMIFS(BV_Data_An_Cour!$P:$P,BV_Data_An_Cour!$U:$U,$A$1,BV_Data_An_Cour!$V:$V,$D15) -> 237844.44
A16: Total Comptes à Recevoir | B16: =+SUM(B8:B15) -> 2290403.7 | D16: Total Comptes à Payer | E16: =+SUM(E10:E15) -> 791332.5
A18: Inventaire Véhicules Neufs | B18: =SUMIFS(BV_Data_An_Cour!$P:$P,BV_Data_An_Cour!$U:$U,$A$1,BV_Data_An_Cour!$V:$V,$A18) -> 8136066 | D18: Effet à Payer Véhicules Neufs | E18: =-SUMIFS(BV_Data_An_Cour!$P:$P,BV_Data_An_Cour!$U:$U,$A$1,BV_Data_An_Cour!$V:$V,$D18) -> 9868523.7
A19: Inventaire Véhicules Usagés | B19: =SUMIFS(BV_Data_An_Cour!$P:$P,BV_Data_An_Cour!$U:$U,$A$1,BV_Data_An_Cour!$V:$V,$A19) -> 1075639.2 | D19: Effet à Payer Véhicules Usagés | E19: =-SUMIFS(BV_Data_An_Cour!$P:$P,BV_Data_An_Cour!$U:$U,$A$1,BV_Data_An_Cour!$V:$V,$D19) -> 696409.97
A20: Inventaire Pièces, Pneus, Huile | B20: =SUMIFS(BV_Data_An_Cour!$P:$P,BV_Data_An_Cour!$U:$U,$A$1,BV_Data_An_Cour!$V:$V,$A20) -> 475121.15 | D20: Total Effets à Payer | E20: =+SUM(E18:E19) -> 10564934
A21: Total Inventaires | B21: =SUM(B18:B20) -> 9686826.3
D22: Salaires à Payer | E22: =-SUMIFS(BV_Data_An_Cour!$P:$P,BV_Data_An_Cour!$U:$U,$A$1,BV_Data_An_Cour!$V:$V,$D22) -> 380802.04
A23: Avances à recevoir | B23: =SUMIFS(BV_Data_An_Cour!$P:$P,BV_Data_An_Cour!$U:$U,$A$1,BV_Data_An_Cour!$V:$V,$A23) -> 0 | D23: DAS à Payer | E23: =-SUMIFS(BV_Data_An_Cour!$P:$P,BV_Data_An_Cour!$U:$U,$A$1,BV_Data_An_Cour!$V:$V,$D23) -> 64799.3
A24: Travaux en Cours | B24: =SUMIFS(BV_Data_An_Cour!$P:$P,BV_Data_An_Cour!$U:$U,$A$1,BV_Data_An_Cour!$V:$V,$A24) -> 16506.02 | D24: Autres Courus | E24: =-SUMIFS(BV_Data_An_Cour!$P:$P,BV_Data_An_Cour!$U:$U,$A$1,BV_Data_An_Cour!$V:$V,$D24) -> 244368.4
A25: Sous-Traitance | B25: =SUMIFS(BV_Data_An_Cour!$P:$P,BV_Data_An_Cour!$U:$U,$A$1,BV_Data_An_Cour!$V:$V,$A25) -> 5797.26 | D25: [...] | E25: =-SUMIFS(BV_Data_An_Cour!$P:$P,BV_Data_An_Cour!$U:$U,$A$1,BV_Data_An_Cour!$V:$V,$D25) -> 0
A26: Frais Payés d'Avance | B26: =SUMIFS(BV_Data_An_Cour!$P:$P,BV_Data_An_Cour!$U:$U,$A$1,BV_Data_An_Cour!$V:$V,$A26) -> 139299.12 | D26: [...] | E26: =-SUMIFS(BV_Data_An_Cour!$P:$P,BV_Data_An_Cour!$U:$U,$A$1,BV_Data_An_Cour!$V:$V,$D26) -> 0
A27: [...] | B27: =SUMIFS(BV_Data_An_Cour!$P:$P,BV_Data_An_Cour!$U:$U,$A$1,BV_Data_An_Cour!$V:$V,$A27) -> 0 | D27: [...] | E27: =-SUMIFS(BV_Data_An_Cour!$P:$P,BV_Data_An_Cour!$U:$U,$A$1,BV_Data_An_Cour!$V:$V,$D27) -> 0
A28: [...] | B28: =SUMIFS(BV_Data_An_Cour!$P:$P,BV_Data_An_Cour!$U:$U,$A$1,BV_Data_An_Cour!$V:$V,$A28) -> 0 | D28: Total Frais Courus | E28: =SUM(E22:E24) -> 689969.74
A29: [...] | B29: =SUMIFS(BV_Data_An_Cour!$P:$P,BV_Data_An_Cour!$U:$U,$A$1,BV_Data_An_Cour!$V:$V,$A29) -> 0
A30: Total Autres | B30: =SUM(B23:B29) -> 161602.4 | D30: Total Passif Court Terme | E30: =+E5+E7+E16+E20+E28 -> 12046236
A32: Total Actif Court Terme | B32: =+B6+B16+B21+B30 -> 13007916
D33: Impôts Futurs à payer | E33: =-SUMIFS(BV_Data_An_Cour!$P:$P,BV_Data_An_Cour!$U:$U,$A$1,BV_Data_An_Cour!$V:$V,$D33) -> 0
A35: Terrain | B35: =SUMIFS(BV_Data_An_Cour!$P:$P,BV_Data_An_Cour!$U:$U,$A$1,BV_Data_An_Cour!$V:$V,$A35) -> 0 | D35: Avances Long Terme à Payer | E35: =-SUMIFS(BV_Data_An_Cour!$P:$P,BV_Data_An_Cour!$U:$U,$A$1,BV_Data_An_Cour!$V:$V,$D35) -> 0
A36: Bâtisse | B36: =SUMIFS(BV_Data_An_Cour!$P:$P,BV_Data_An_Cour!$U:$U,$A$1,BV_Data_An_Cour!$V:$V,$A36) -> 0 | D36: Hypothèque à Payer | E36: =-SUMIFS(BV_Data_An_Cour!$P:$P,BV_Data_An_Cour!$U:$U,$A$1,BV_Data_An_Cour!$V:$V,$D36) -> 0
A37: Améliorations Locatives | B37: =SUMIFS(BV_Data_An_Cour!$P:$P,BV_Data_An_Cour!$U:$U,$A$1,BV_Data_An_Cour!$V:$V,$A37) -> 21438.95 | D37: Dette à Long Terme | E37: =-SUMIFS(BV_Data_An_Cour!$P:$P,BV_Data_An_Cour!$U:$U,$A$1,BV_Data_An_Cour!$V:$V,$D37) -> 5824656
A38: Améliorations Locatives Permanentes | B38: =SUMIFS(BV_Data_An_Cour!$P:$P,BV_Data_An_Cour!$U:$U,$A$1,BV_Data_An_Cour!$V:$V,$A38) -> 0 | D38: Autres Dettes à Long Terme | E38: =-SUMIFS(BV_Data_An_Cour!$P:$P,BV_Data_An_Cour!$U:$U,$A$1,BV_Data_An_Cour!$V:$V,$D38) -> 0
A39: Équipements Service | B39: =SUMIFS(BV_Data_An_Cour!$P:$P,BV_Data_An_Cour!$U:$U,$A$1,BV_Data_An_Cour!$V:$V,$A39) -> 302379.39 | D39: [...] | E39: =-SUMIFS(BV_Data_An_Cour!$P:$P,BV_Data_An_Cour!$U:$U,$A$1,BV_Data_An_Cour!$V:$V,$D39) -> 0
A40: Mobilier | B40: =SUMIFS(BV_Data_An_Cour!$P:$P,BV_Data_An_Cour!$U:$U,$A$1,BV_Data_An_Cour!$V:$V,$A40) -> 28814.22 | D40: [...] | E40: =-SUMIFS(BV_Data_An_Cour!$P:$P,BV_Data_An_Cour!$U:$U,$A$1,BV_Data_An_Cour!$V:$V,$D40) -> 0
A41: Équipements Informatique | B41: =SUMIFS(BV_Data_An_Cour!$P:$P,BV_Data_An_Cour!$U:$U,$A$1,BV_Data_An_Cour!$V:$V,$A41) -> 23338.26 | D41: [...] | E41: =-SUMIFS(BV_Data_An_Cour!$P:$P,BV_Data_An_Cour!$U:$U,$A$1,BV_Data_An_Cour!$V:$V,$D41) -> 0
A42: Équipements Téléphonique | B42: =SUMIFS(BV_Data_An_Cour!$P:$P,BV_Data_An_Cour!$U:$U,$A$1,BV_Data_An_Cour!$V:$V,$A42) -> 0 | D42: Total Passif long terme | E42: =+SUM(E33:E38) -> 5824656
A43: Enseigne | B43: =SUMIFS(BV_Data_An_Cour!$P:$P,BV_Data_An_Cour!$U:$U,$A$1,BV_Data_An_Cour!$V:$V,$A43) -> 17419.71
A44: Total Immobilisations Nettes | B44: =SUM(B35:B43) -> 393390.53
D45: Total Passifs | E45: =+E42+E30 -> 17870892
A46: Avances à Recevoir Long Terme | B46: =SUMIFS(BV_Data_An_Cour!$P:$P,BV_Data_An_Cour!$U:$U,$A$1,BV_Data_An_Cour!$V:$V,$A46) -> 8677814.1
A48: Achalandage | B48: =SUMIFS(BV_Data_An_Cour!$P:$P,BV_Data_An_Cour!$U:$U,$A$1,BV_Data_An_Cour!$V:$V,$A48) -> 0 | D48: Capital Actions | E48: =-SUMIFS(BV_Data_An_Cour!$P:$P,BV_Data_An_Cour!$U:$U,$A$1,BV_Data_An_Cour!$V:$V,$D48) -> 2697547.5
D49: Apport | E49: =-SUMIFS(BV_Data_An_Cour!$P:$P,BV_Data_An_Cour!$U:$U,$A$1,BV_Data_An_Cour!$V:$V,$D49) -> 1723617
A50: [...] | B50: =SUMIFS(BV_Data_An_Cour!$P:$P,BV_Data_An_Cour!$U:$U,$A$1,BV_Data_An_Cour!$V:$V,$A50) -> 0 | D50: Bénéfices non répartis | E50: =-SUMIFS(BV_Data_An_Cour!$P:$P,BV_Data_An_Cour!$U:$U,$A$1,BV_Data_An_Cour!$V:$V,$D50)+Print_AAD!AF498 -> -212935.81
A51: [...] | B51: =SUMIFS(BV_Data_An_Cour!$P:$P,BV_Data_An_Cour!$U:$U,$A$1,BV_Data_An_Cour!$V:$V,$A51) -> 0 | D51: Dividendes | E51: =-SUMIFS(BV_Data_An_Cour!$P:$P,BV_Data_An_Cour!$U:$U,$A$1,BV_Data_An_Cour!$V:$V,$D51) -> 0
A52: [...] | B52: =SUMIFS(BV_Data_An_Cour!$P:$P,BV_Data_An_Cour!$U:$U,$A$1,BV_Data_An_Cour!$V:$V,$A52) -> 0
A53: Total Actif Long Terme | B53: =+B44+B48+B46 -> 9071204.6 | D53: Total Capitaux Propres / Avoir | E53: =SUM(E48:E51) -> 4208228.7
A56: Total Actif | B56: =+B32+B53 -> 22079121 | D56: Total Passif et Capitaux Propres / Avoir | E56: =+E53+E45 -> 22079121
E65: =+B56-E56 -> 0

Sheet Budget original
B1: ="Budget 2024 Mensuel Révisé"&" "&Parametres!$B$1 -> Budget 2024 Mensuel Révisé Volks
B2: Mois | F2: =+IF(Parametres!$B$3=F$6,"X","") | G2: =+IF(Parametres!$B$3=F$6,"O","") | H2: =+IF(Parametres!$B$3=F$6,"U","") | I2: =+IF(Parametres!$B$3=I$6,"X","") | J2: =+IF(Parametres!$B$3=I$6,"O","") | K2: =+IF(Parametres!$B$3=I$6,"U","") | L2: =+IF(Parametres!$B$3=L$6,"X","") -> X | M2: =+IF(Parametres!$B$3=L$6,"O","") -> O | N2: =+IF(Parametres!$B$3=L$6,"U","") -> U | O2: =+IF(Parametres!$B$3=O$6,"X","") | P2: =+IF(Parametres!$B$3=O$6,"O","") | Q2: =+IF(Parametres!$B$3=O$6,"U","") | R2: =+IF(Parametres!$B$3=R$6,"X","") | S2: =+IF(Parametres!$B$3=R$6,"O","") | T2: =+IF(Parametres!$B$3=R$6,"U","") | U2: =+IF(Parametres!$B$3=U$6,"X","") | V2: =+IF(Parametres!$B$3=U$6,"O","") | W2: =+IF(Parametres!$B$3=U$6,"U","") | X2: =+IF(Parametres!$B$3=X$6,"X","") | Y2: =+IF(Parametres!$B$3=X$6,"O","") | Z2: =+IF(Parametres!$B$3=X$6,"U","") | AA2: =+IF(Parametres!$B$3=AA$6,"X","") | AB2: =+IF(Parametres!$B$3=AA$6,"O","") | AC2: =+IF(Parametres!$B$3=AA$6,"U","") | AD2: =+IF(Parametres!$B$3=AD$6,"X","") | AE2: =+IF(Parametres!$B$3=AD$6,"O","") | AF2: =+IF(Parametres!$B$3=AD$6,"U","") | AG2: =+IF(Parametres!$B$3=AG$6,"X","") | AH2: =+IF(Parametres!$B$3=AG$6,"O","") | AI2: =+IF(Parametres!$B$3=AG$6,"U","") | AJ2: =+IF(Parametres!$B$3=AJ$6,"X","") | AK2: =+IF(Parametres!$B$3=AJ$6,"O","") | AL2: =+IF(Parametres!$B$3=AJ$6,"U","") | AM2: =+IF(Parametres!$B$3=AM$6,"X","") | AN2: =+IF(Parametres!$B$3=AM$6,"O","") | AO2: =+IF(Parametres!$B$3=AM$6,"U","")
B3: YTD | F3: =+IF(VLOOKUP(F$6,Parametres!$K$3:$N$14,4,0)="X","X","") -> X | G3: =+IF(VLOOKUP(F$6,Parametres!$K$3:$N$14,4,0)="X","O","") -> O | H3: =+IF(VLOOKUP(F$6,Parametres!$K$3:$N$14,4,0)="X","U","") -> U | I3: =+IF(VLOOKUP(I$6,Parametres!$K$3:$N$14,4,0)="X","X","") -> X | J3: =+IF(VLOOKUP(I$6,Parametres!$K$3:$N$14,4,0)="X","O","") -> O | K3: =+IF(VLOOKUP(I$6,Parametres!$K$3:$N$14,4,0)="X","U","") -> U | L3: =+IF(VLOOKUP(L$6,Parametres!$K$3:$N$14,4,0)="X","X","") -> X | M3: =+IF(VLOOKUP(L$6,Parametres!$K$3:$N$14,4,0)="X","O","") -> O | N3: =+IF(VLOOKUP(L$6,Parametres!$K$3:$N$14,4,0)="X","U","") -> U | O3: =+IF(VLOOKUP(O$6,Parametres!$K$3:$N$14,4,0)="X","X","") | P3: =+IF(VLOOKUP(O$6,Parametres!$K$3:$N$14,4,0)="X","O","") | Q3: =+IF(VLOOKUP(O$6,Parametres!$K$3:$N$14,4,0)="X","U","") | R3: =+IF(VLOOKUP(R$6,Parametres!$K$3:$N$14,4,0)="X","X","") | S3: =+IF(VLOOKUP(R$6,Parametres!$K$3:$N$14,4,0)="X","O","") | T3: =+IF(VLOOKUP(R$6,Parametres!$K$3:$N$14,4,0)="X","U","") | U3: =+IF(VLOOKUP(U$6,Parametres!$K$3:$N$14,4,0)="X","X","") | V3: =+IF(VLOOKUP(U$6,Parametres!$K$3:$N$14,4,0)="X","O","") | W3: =+IF(VLOOKUP(U$6,Parametres!$K$3:$N$14,4,0)="X","U","") | X3: =+IF(VLOOKUP(X$6,Parametres!$K$3:$N$14,4,0)="X","X","") | Y3: =+IF(VLOOKUP(X$6,Parametres!$K$3:$N$14,4,0)="X","O","") | Z3: =+IF(VLOOKUP(X$6,Parametres!$K$3:$N$14,4,0)="X","U","") | AA3: =+IF(VLOOKUP(AA$6,Parametres!$K$3:$N$14,4,0)="X","X","") | AB3: =+IF(VLOOKUP(AA$6,Parametres!$K$3:$N$14,4,0)="X","O","") | AC3: =+IF(VLOOKUP(AA$6,Parametres!$K$3:$N$14,4,0)="X","U","") | AD3: =+IF(VLOOKUP(AD$6,Parametres!$K$3:$N$14,4,0)="X","X","") | AE3: =+IF(VLOOKUP(AD$6,Parametres!$K$3:$N$14,4,0)="X","O","") | AF3: =+IF(VLOOKUP(AD$6,Parametres!$K$3:$N$14,4,0)="X","U","") | AG3: =+IF(VLOOKUP(AG$6,Parametres!$K$3:$N$14,4,0)="X","X","") | AH3: =+IF(VLOOKUP(AG$6,Parametres!$K$3:$N$14,4,0)="X","O","") | AI3: =+IF(VLOOKUP(AG$6,Parametres!$K$3:$N$14,4,0)="X","U","") | AJ3: =+IF(VLOOKUP(AJ$6,Parametres!$K$3:$N$14,4,0)="X","X","") | AK3: =+IF(VLOOKUP(AJ$6,Parametres!$K$3:$N$14,4,0)="X","O","") | AL3: =+IF(VLOOKUP(AJ$6,Parametres!$K$3:$N$14,4,0)="X","U","") | AM3: =+IF(VLOOKUP(AM$6,Parametres!$K$3:$N$14,4,0)="X","X","") | AN3: =+IF(VLOOKUP(AM$6,Parametres!$K$3:$N$14,4,0)="X","O","") | AO3: =+IF(VLOOKUP(AM$6,Parametres!$K$3:$N$14,4,0)="X","U","")
B4: Budget 2025 | C4: Véhicules neufs
B6: Mois | C6: TOTAL | F6: Janvier | I6: Février | L6: Mars | O6: Avril | R6: Mai | U6: Juin | X6: Juillet | AA6: Août | AD6: Septembre | AG6: Octobre | AJ6: Novembre | AM6: Décembre
C7: UNITE | D7: $P/UNITE | E7: $PROFITS | F7: UNITE | G7: $P/UNITE | H7: $PROFITS | I7: UNITE | J7: $P/UNITE | K7: $PROFITS | L7: UNITE | M7: $P/UNITE | N7: $PROFITS | O7: UNITE | P7: $P/UNITE | Q7: $PROFITS | R7: UNITE | S7: $P/UNITE | T7: $PROFITS | U7: UNITE | V7: $P/UNITE | W7: $PROFITS | X7: UNITE | Y7: $P/UNITE | Z7: $PROFITS | AA7: UNITE | AB7: $P/UNITE | AC7: $PROFITS | AD7: UNITE | AE7: $P/UNITE | AF7: $PROFITS | AG7: UNITE | AH7: $P/UNITE | AI7: $PROFITS | AJ7: UNITE | AK7: $P/UNITE | AL7: $PROFITS | AM7: UNITE | AN7: $P/UNITE | AO7: $PROFITS
A8: =+$C$4&B8 -> Véhicules neufsVentes nettes | B8: Ventes nettes | E8: =+SUM(H8,K8,N8,Q8,T8,W8,Z8,AC8,AF8,AI8,AL8,AO8) -> 35986167 | H8: ='[1]Vehicules neuf 2026'!E60 -> 2377394.8 | K8: ='[1]Vehicules neuf 2026'!F60 -> 2560324.4 | N8: ='[1]Vehicules neuf 2026'!G60 -> 3684432.8 | Q8: ='[1]Vehicules neuf 2026'!H60 -> 3774495.5 | T8: ='[1]Vehicules neuf 2026'!I60 -> 3914068.9 | W8: ='[1]Vehicules neuf 2026'!J60 -> 3544859.4 | Z8: ='[1]Vehicules neuf 2026'!K60 -> 3172845.9 | AC8: ='[1]Vehicules neuf 2026'!L60 -> 2888981.7 | AF8: ='[1]Vehicules neuf 2026'!M60 -> 2798918.9 | AI8: ='[1]Vehicules neuf 2026'!N60 -> 2749408.3 | AL8: ='[1]Vehicules neuf 2026'!O60 -> 2426905.4 | AO8: ='[1]Vehicules neuf 2026'!P60 -> 2093530.6
A9: =+$C$4&B9 -> Véhicules neufsAutos détail | B9: Autos détail | C9: =+SUM(F9,I9,L9,O9,R9,U9,X9,AA9,AD9,AG9,AJ9,AM9) -> 197 | D9: =IF(C9=0,0,E9/C9) -> 1839.3979 | E9: =+SUM(H9,K9,N9,Q9,T9,W9,Z9,AC9,AF9,AI9,AL9,AO9) -> 362361.39 | F9: ='[1]Vehicules neuf 2026'!E35 -> 13 | G9: =IF(F9=0,0,H9/F9) -> 1839.3979 | H9: ='[1]Vehicules neuf 2026'!E53 -> 23912.173 | I9: ='[1]Vehicules neuf 2026'!F35 -> 14 | J9: =IF(I9=0,0,K9/I9) -> 1839.3979 | K9: ='[1]Vehicules neuf 2026'!F53 -> 25751.571 | L9: ='[1]Vehicules neuf 2026'!G35 -> 20 | M9: =IF(L9=0,0,N9/L9) -> 1839.3979 | N9: ='[1]Vehicules neuf 2026'!G53 -> 36787.958 | O9: ='[1]Vehicules neuf 2026'!H35 -> 21 | P9: =IF(O9=0,0,Q9/O9) -> 1839.3979 | Q9: ='[1]Vehicules neuf 2026'!H53 -> 38627.356 | R9: ='[1]Vehicules neuf 2026'!I35 -> 22 | S9: =IF(R9=0,0,T9/R9) -> 1839.3979 | T9: ='[1]Vehicules neuf 2026'!I53 -> 40466.754 | U9: ='[1]Vehicules neuf 2026'!J35 -> 19 | V9: =IF(U9=0,0,W9/U9) -> 1839.3979 | W9: ='[1]Vehicules neuf 2026'!J53 -> 34948.56 | X9: ='[1]Vehicules neuf 2026'!K35 -> 17 | Y9: =IF(X9=0,0,Z9/X9) -> 1839.3979 | Z9: ='[1]Vehicules neuf 2026'!K53 -> 31269.764 | AA9: ='[1]Vehicules neuf 2026'!L35 -> 16 | AB9: =IF(AA9=0,0,AC9/AA9) -> 1839.3979 | AC9: ='[1]Vehicules neuf 2026'!L53 -> 29430.366 | AD9: ='[1]Vehicules neuf 2026'!M35 -> 15 | AE9: =IF(AD9=0,0,AF9/AD9) -> 1839.3979 | AF9: ='[1]Vehicules neuf 2026'!M53 -> 27590.968 | AG9: ='[1]Vehicules neuf 2026'!N35 -> 15 | AH9: =IF(AG9=0,0,AI9/AG9) -> 1839.3979 | AI9: ='[1]Vehicules neuf 2026'!N53 -> 27590.968 | AJ9: ='[1]Vehicules neuf 2026'!O35 -> 13 | AK9: =IF(AJ9=0,0,AL9/AJ9) -> 1839.3979 | AL9: ='[1]Vehicules neuf 2026'!O53 -> 23912.173 | AM9: ='[1]Vehicules neuf 2026'!P35 -> 12 | AN9: =IF(AM9=0,0,AO9/AM9) -> 1839.3979 | AO9: ='[1]Vehicules neuf 2026'!P53 -> 22072.775
A10: =+$C$4&B10 -> Véhicules neufsCamions détail | B10: Camions détail | C10: =+SUM(F10,I10,L10,O10,R10,U10,X10,AA10,AD10,AG10,AJ10,AM10) -> 486 | D10: =IF(C10=0,0,E10/C10) -> 2490.3911 | E10: =+SUM(H10,K10,N10,Q10,T10,W10,Z10,AC10,AF10,AI10,AL10,AO10) -> 1210330.1 | F10: ='[1]Vehicules neuf 2026'!E36 -> 32 | G10: =IF(F10=0,0,H10/F10) -> 2490.3911 | H10: ='[1]Vehicules neuf 2026'!E54 -> 79692.514 | I10: ='[1]Vehicules neuf 2026'!F36 -> 34 | J10: =IF(I10=0,0,K10/I10) -> 2490.3911 | K10: ='[1]Vehicules neuf 2026'!F54 -> 84673.296 | L10: ='[1]Vehicules neuf 2026'!G36 -> 50 | M10: =IF(L10=0,0,N10/L10) -> 2490.3911 | N10: ='[1]Vehicules neuf 2026'!G54 -> 124519.55 | O10: ='[1]Vehicules neuf 2026'!H36 -> 51 | P10: =IF(O10=0,0,Q10/O10) -> 2490.3911 | Q10: ='[1]Vehicules neuf 2026'!H54 -> 127009.94 | R10: ='[1]Vehicules neuf 2026'!I36 -> 53 | S10: =IF(R10=0,0,T10/R10) -> 2490.3911 | T10: ='[1]Vehicules neuf 2026'!I54 -> 131990.73 | U10: ='[1]Vehicules neuf 2026'!J36 -> 48 | V10: =IF(U10=0,0,W10/U10) -> 2490.3911 | W10: ='[1]Vehicules neuf 2026'!J54 -> 119538.77 | X10: ='[1]Vehicules neuf 2026'!K36 -> 43 | Y10: =IF(X10=0,0,Z10/X10) -> 2490.3911 | Z10: ='[1]Vehicules neuf 2026'!K54 -> 107086.82 | AA10: ='[1]Vehicules neuf 2026'!L36 -> 39 | AB10: =IF(AA10=0,0,AC10/AA10) -> 2490.3911 | AC10: ='[1]Vehicules neuf 2026'!L54 -> 97125.251 | AD10: ='[1]Vehicules neuf 2026'!M36 -> 38 | AE10: =IF(AD10=0,0,AF10/AD10) -> 2490.3911 | AF10: ='[1]Vehicules neuf 2026'!M54 -> 94634.86 | AG10: ='[1]Vehicules neuf 2026'!N36 -> 37 | AH10: =IF(AG10=0,0,AI10/AG10) -> 2490.3911 | AI10: ='[1]Vehicules neuf 2026'!N54 -> 92144.469 | AJ10: ='[1]Vehicules neuf 2026'!O36 -> 33 | AK10: =IF(AJ10=0,0,AL10/AJ10) -> 2490.3911 | AL10: ='[1]Vehicules neuf 2026'!O54 -> 82182.905 | AM10: ='[1]Vehicules neuf 2026'!P36 -> 28 | AN10: =IF(AM10=0,0,AO10/AM10) -> 2490.3911 | AO10: ='[1]Vehicules neuf 2026'!P54 -> 69730.95
A11: =+$C$4&B11 -> Véhicules neufsSprinter | B11: Sprinter | C11: =+SUM(F11,I11,L11,O11,R11,U11,X11,AA11,AD11,AG11,AJ11,AM11) -> 0 | D11: =IF(C11=0,0,E11/C11) -> 0 | E11: =+SUM(H11,K11,N11,Q11,T11,W11,Z11,AC11,AF11,AI11,AL11,AO11) -> 0 | G11: =IF(F11=0,0,H11/F11) -> 0 | J11: =IF(I11=0,0,K11/I11) -> 0 | M11: =IF(L11=0,0,N11/L11) -> 0 | P11: =IF(O11=0,0,Q11/O11) -> 0 | S11: =IF(R11=0,0,T11/R11) -> 0 | V11: =IF(U11=0,0,W11/U11) -> 0 | Y11: =IF(X11=0,0,Z11/X11) -> 0 | AB11: =IF(AA11=0,0,AC11/AA11) -> 0 | AE11: =IF(AD11=0,0,AF11/AD11) -> 0 | AH11: =IF(AG11=0,0,AI11/AG11) -> 0 | AK11: =IF(AJ11=0,0,AL11/AJ11) -> 0 | AN11: =IF(AM11=0,0,AO11/AM11) -> 0
A12: =+$C$4&B12 -> Véhicules neufsMoto détail | B12: Moto détail | C12: =+SUM(F12,I12,L12,O12,R12,U12,X12,AA12,AD12,AG12,AJ12,AM12) -> 0 | D12: =IF(C12=0,0,E12/C12) -> 0 | E12: =+SUM(H12,K12,N12,Q12,T12,W12,Z12,AC12,AF12,AI12,AL12,AO12) -> 0 | G12: =IF(F12=0,0,H12/F12) -> 0 | J12: =IF(I12=0,0,K12/I12) -> 0 | M12: =IF(L12=0,0,N12/L12) -> 0 | P12: =IF(O12=0,0,Q12/O12) -> 0 | S12: =IF(R12=0,0,T12/R12) -> 0 | V12: =IF(U12=0,0,W12/U12) -> 0 | Y12: =IF(X12=0,0,Z12/X12) -> 0 | AB12: =IF(AA12=0,0,AC12/AA12) -> 0 | AE12: =IF(AD12=0,0,AF12/AD12) -> 0 | AH12: =IF(AG12=0,0,AI12/AG12) -> 0 | AK12: =IF(AJ12=0,0,AL12/AJ12) -> 0 | AN12: =IF(AM12=0,0,AO12/AM12) -> 0
A13: =+$C$4&B13 -> Véhicules neufs[...] | B13: [...] | C13: =+SUM(F13,I13,L13,O13,R13,U13,X13,AA13,AD13,AG13,AJ13,AM13) -> 0 | D13: =IF(C13=0,0,E13/C13) -> 0 | E13: =+SUM(H13,K13,N13,Q13,T13,W13,Z13,AC13,AF13,AI13,AL13,AO13) -> 0 | G13: =IF(F13=0,0,H13/F13) -> 0 | J13: =IF(I13=0,0,K13/I13) -> 0 | M13: =IF(L13=0,0,N13/L13) -> 0 | P13: =IF(O13=0,0,Q13/O13) -> 0 | S13: =IF(R13=0,0,T13/R13) -> 0 | V13: =IF(U13=0,0,W13/U13) -> 0 | Y13: =IF(X13=0,0,Z13/X13) -> 0 | AB13: =IF(AA13=0,0,AC13/AA13) -> 0 | AE13: =IF(AD13=0,0,AF13/AD13) -> 0 | AH13: =IF(AG13=0,0,AI13/AG13) -> 0 | AK13: =IF(AJ13=0,0,AL13/AJ13) -> 0 | AN13: =IF(AM13=0,0,AO13/AM13) -> 0
A14: =+$C$4&B14 -> Véhicules neufs[...] | B14: [...] | C14: =+SUM(F14,I14,L14,O14,R14,U14,X14,AA14,AD14,AG14,AJ14,AM14) -> 0 | D14: =IF(C14=0,0,E14/C14) -> 0 | E14: =+SUM(H14,K14,N14,Q14,T14,W14,Z14,AC14,AF14,AI14,AL14,AO14) -> 0 | G14: =IF(F14=0,0,H14/F14) -> 0 | J14: =IF(I14=0,0,K14/I14) -> 0 | M14: =IF(L14=0,0,N14/L14) -> 0 | P14: =IF(O14=0,0,Q14/O14) -> 0 | S14: =IF(R14=0,0,T14/R14) -> 0 | V14: =IF(U14=0,0,W14/U14) -> 0 | Y14: =IF(X14=0,0,Z14/X14) -> 0 | AB14: =IF(AA14=0,0,AC14/AA14) -> 0 | AE14: =IF(AD14=0,0,AF14/AD14) -> 0 | AH14: =IF(AG14=0,0,AI14/AG14) -> 0 | AK14: =IF(AJ14=0,0,AL14/AJ14) -> 0 | AN14: =IF(AM14=0,0,AO14/AM14) -> 0
A15: =+$C$4&B15 -> Véhicules neufs[...] | B15: [...] | C15: =+SUM(F15,I15,L15,O15,R15,U15,X15,AA15,AD15,AG15,AJ15,AM15) -> 0 | D15: =IF(C15=0,0,E15/C15) -> 0 | E15: =+SUM(H15,K15,N15,Q15,T15,W15,Z15,AC15,AF15,AI15,AL15,AO15) -> 0 | G15: =IF(F15=0,0,H15/F15) -> 0 | J15: =IF(I15=0,0,K15/I15) -> 0 | M15: =IF(L15=0,0,N15/L15) -> 0 | P15: =IF(O15=0,0,Q15/O15) -> 0 | S15: =IF(R15=0,0,T15/R15) -> 0 | V15: =IF(U15=0,0,W15/U15) -> 0 | Y15: =IF(X15=0,0,Z15/X15) -> 0 | AB15: =IF(AA15=0,0,AC15/AA15) -> 0 | AE15: =IF(AD15=0,0,AF15/AD15) -> 0 | AH15: =IF(AG15=0,0,AI15/AG15) -> 0 | AK15: =IF(AJ15=0,0,AL15/AJ15) -> 0 | AN15: =IF(AM15=0,0,AO15/AM15) -> 0
A16: =+$C$4&B16 -> Véhicules neufsTotal Neufs | B16: Total Neufs | C16: =+SUM(C9:C15) -> 683 | D16: =IF(C16<=0,0,E16/C16) -> 2302.6229 | E16: =+SUM(E9:E15) -> 1572691.4 | F16: =+SUM(F9:F15) -> 45 | G16: =IF(F16<=0,0,H16/F16) -> 2302.3264 | H16: =+SUM(H9:H15) -> 103604.69 | I16: =+SUM(I9:I15) -> 48 | J16: =IF(I16<=0,0,K16/I16) -> 2300.5181 | K16: =+SUM(K9:K15) -> 110424.87 | L16: =+SUM(L9:L15) -> 70 | M16: =IF(L16<=0,0,N16/L16) -> 2304.393 | N16: =+SUM(N9:N15) -> 161307.51 | O16: =+SUM(O9:O15) -> 72 | P16: =IF(O16<=0,0,Q16/O16) -> 2300.5181 | Q16: =+SUM(Q9:Q15) -> 165637.3 | R16: =+SUM(R9:R15) -> 75 | S16: =IF(R16<=0,0,T16/R16) -> 2299.4331 | T16: =+SUM(T9:T15) -> 172457.48 | U16: =+SUM(U9:U15) -> 67 | V16: =IF(U16<=0,0,W16/U16) -> 2305.7811 | W16: =+SUM(W9:W15) -> 154487.33 | X16: =+SUM(X9:X15) -> 60 | Y16: =IF(X16<=0,0,Z16/X16) -> 2305.943 | Z16: =+SUM(Z9:Z15) -> 138356.58 | AA16: =+SUM(AA9:AA15) -> 55 | AB16: =IF(AA16<=0,0,AC16/AA16) -> 2301.0112 | AC16: =+SUM(AC9:AC15) -> 126555.62 | AD16: =+SUM(AD9:AD15) -> 53 | AE16: =IF(AD16<=0,0,AF16/AD16) -> 2306.1477 | AF16: =+SUM(AF9:AF15) -> 122225.83 | AG16: =+SUM(AG9:AG15) -> 52 | AH16: =IF(AG16<=0,0,AI16/AG16) -> 2302.6046 | AI16: =+SUM(AI9:AI15) -> 119735.44 | AJ16: =+SUM(AJ9:AJ15) -> 46 | AK16: =IF(AJ16<=0,0,AL16/AJ16) -> 2306.4147 | AL16: =+SUM(AL9:AL15) -> 106095.08 | AM16: =+SUM(AM9:AM15) -> 40 | AN16: =IF(AM16<=0,0,AO16/AM16) -> 2295.0931 | AO16: =+SUM(AO9:AO15) -> 91803.725
A17: =+$C$4&B17 -> Véhicules neufs
A18: =+$C$4&B18 -> Véhicules neufsEx-Démos et courtoisies | B18: Ex-Démos et courtoisies | C18: =+SUM(F18,I18,L18,O18,R18,U18,X18,AA18,AD18,AG18,AJ18,AM18) -> 40 | D18: =IF(C18=0,0,E18/C18) -> 1524.8245 | E18: =+SUM(H18,K18,N18,Q18,T18,W18,Z18,AC18,AF18,AI18,AL18,AO18) -> 60992.981 | F18: ='[1]Vehicules neuf 2026'!E37 -> 3 | G18: =IF(F18=0,0,H18/F18) -> 1524.8245 | H18: ='[1]Vehicules neuf 2026'!E55 -> 4574.4736 | I18: ='[1]Vehicules neuf 2026'!F37 -> 3 | J18: =IF(I18=0,0,K18/I18) -> 1524.8245 | K18: ='[1]Vehicules neuf 2026'!F55 -> 4574.4736 | L18: ='[1]Vehicules neuf 2026'!G37 -> 4 | M18: =IF(L18=0,0,N18/L18) -> 1524.8245 | N18: ='[1]Vehicules neuf 2026'!G55 -> 6099.2981 | O18: ='[1]Vehicules neuf 2026'!H37 -> 4 | P18: =IF(O18=0,0,Q18/O18) -> 1524.8245 | Q18: ='[1]Vehicules neuf 2026'!H55 -> 6099.2981 | R18: ='[1]Vehicules neuf 2026'!I37 -> 4 | S18: =IF(R18=0,0,T18/R18) -> 1524.8245 | T18: ='[1]Vehicules neuf 2026'!I55 -> 6099.2981 | U18: ='[1]Vehicules neuf 2026'!J37 -> 4 | V18: =IF(U18=0,0,W18/U18) -> 1524.8245 | W18: ='[1]Vehicules neuf 2026'!J55 -> 6099.2981 | X18: ='[1]Vehicules neuf 2026'!K37 -> 4 | Y18: =IF(X18=0,0,Z18/X18) -> 1524.8245 | Z18: ='[1]Vehicules neuf 2026'!K55 -> 6099.2981 | AA18: ='[1]Vehicules neuf 2026'!L37 -> 3 | AB18: =IF(AA18=0,0,AC18/AA18) -> 1524.8245 | AC18: ='[1]Vehicules neuf 2026'!L55 -> 4574.4736 | AD18: ='[1]Vehicules neuf 2026'!M37 -> 3 | AE18: =IF(AD18=0,0,AF18/AD18) -> 1524.8245 | AF18: ='[1]Vehicules neuf 2026'!M55 -> 4574.4736 | AG18: ='[1]Vehicules neuf 2026'!N37 -> 3 | AH18: =IF(AG18=0,0,AI18/AG18) -> 1524.8245 | AI18: ='[1]Vehicules neuf 2026'!N55 -> 4574.4736 | AJ18: ='[1]Vehicules neuf 2026'!O37 -> 3 | AK18: =IF(AJ18=0,0,AL18/AJ18) -> 1524.8245 | AL18: ='[1]Vehicules neuf 2026'!O55 -> 4574.4736 | AM18: ='[1]Vehicules neuf 2026'!P37 -> 2 | AN18: =IF(AM18=0,0,AO18/AM18) -> 1524.8245 | AO18: ='[1]Vehicules neuf 2026'!P55 -> 3049.6491
A19: =+$C$4&B19 -> Véhicules neufs
A20: =+$C$4&B20 -> Véhicules neufsFlottes | B20: Flottes | C20: =+SUM(F20,I20,L20,O20,R20,U20,X20,AA20,AD20,AG20,AJ20,AM20) -> 49 | D20: =IF(C20=0,0,E20/C20) -> 1300.6851 | E20: =+SUM(H20,K20,N20,Q20,T20,W20,Z20,AC20,AF20,AI20,AL20,AO20) -> 63733.571 | F20: ='[1]Vehicules neuf 2026'!E38 -> 3 | G20: =IF(F20=0,0,H20/F20) -> 1300.6851 | H20: ='[1]Vehicules neuf 2026'!E56 -> 3902.0554 | I20: ='[1]Vehicules neuf 2026'!F38 -> 4 | J20: =IF(I20=0,0,K20/I20) -> 1300.6851 | K20: ='[1]Vehicules neuf 2026'!F56 -> 5202.7405 | L20: ='[1]Vehicules neuf 2026'!G38 -> 5 | M20: =IF(L20=0,0,N20/L20) -> 1300.6851 | N20: ='[1]Vehicules neuf 2026'!G56 -> 6503.4257 | O20: ='[1]Vehicules neuf 2026'!H38 -> 5 | P20: =IF(O20=0,0,Q20/O20) -> 1300.6851 | Q20: ='[1]Vehicules neuf 2026'!H56 -> 6503.4257 | R20: ='[1]Vehicules neuf 2026'!I38 -> 5 | S20: =IF(R20=0,0,T20/R20) -> 1300.6851 | T20: ='[1]Vehicules neuf 2026'!I56 -> 6503.4257 | U20: ='[1]Vehicules neuf 2026'!J38 -> 5 | V20: =IF(U20=0,0,W20/U20) -> 1300.6851 | W20: ='[1]Vehicules neuf 2026'!J56 -> 6503.4257 | X20: ='[1]Vehicules neuf 2026'!K38 -> 4 | Y20: =IF(X20=0,0,Z20/X20) -> 1300.6851 | Z20: ='[1]Vehicules neuf 2026'!K56 -> 5202.7405 | AA20: ='[1]Vehicules neuf 2026'!L38 -> 4 | AB20: =IF(AA20=0,0,AC20/AA20) -> 1300.6851 | AC20: ='[1]Vehicules neuf 2026'!L56 -> 5202.7405 | AD20: ='[1]Vehicules neuf 2026'!M38 -> 4 | AE20: =IF(AD20=0,0,AF20/AD20) -> 1300.6851 | AF20: ='[1]Vehicules neuf 2026'!M56 -> 5202.7405 | AG20: ='[1]Vehicules neuf 2026'!N38 -> 4 | AH20: =IF(AG20=0,0,AI20/AG20) -> 1300.6851 | AI20: ='[1]Vehicules neuf 2026'!N56 -> 5202.7405 | AJ20: ='[1]Vehicules neuf 2026'!O38 -> 3 | AK20: =IF(AJ20=0,0,AL20/AJ20) -> 1300.6851 | AL20: ='[1]Vehicules neuf 2026'!O56 -> 3902.0554 | AM20: ='[1]Vehicules neuf 2026'!P38 -> 3 | AN20: =IF(AM20=0,0,AO20/AM20) -> 1300.6851 | AO20: ='[1]Vehicules neuf 2026'!P56 -> 3902.0554
A21: =+$C$4&B21 -> Véhicules neufs
A22: =+$C$4&B22 -> Véhicules neufsRachat bail | B22: Rachat bail | E22: =+SUM(H22,K22,N22,Q22,T22,W22,Z22,AC22,AF22,AI22,AL22,AO22) -> 100000 | H22: ='[1]Vehicules neuf 2026'!E57 -> 6607.9295 | K22: ='[1]Vehicules neuf 2026'!F57 -> 7048.4581 | N22: ='[1]Vehicules neuf 2026'!G57 -> 10279.001 | Q22: ='[1]Vehicules neuf 2026'!H57 -> 10425.844 | T22: ='[1]Vehicules neuf 2026'!I57 -> 10866.373 | W22: ='[1]Vehicules neuf 2026'!J57 -> 9838.4728 | Z22: ='[1]Vehicules neuf 2026'!K57 -> 8810.5727 | AC22: ='[1]Vehicules neuf 2026'!L57 -> 8076.3583 | AF22: ='[1]Vehicules neuf 2026'!M57 -> 7782.6725 | AI22: ='[1]Vehicules neuf 2026'!N57 -> 7635.8297 | AL22: ='[1]Vehicules neuf 2026'!O57 -> 6754.7724 | AO22: ='[1]Vehicules neuf 2026'!P57 -> 5873.7151
A23: =+$C$4&B23 -> Véhicules neufs
A24: =+$C$4&B24 -> Véhicules neufsRev. Finances | B24: Rev. Finances | D24: =IF(C16=0,0,E24/(C16+C18)) -> 50 | E24: =+SUM(H24,K24,N24,Q24,T24,W24,Z24,AC24,AF24,AI24,AL24,AO24) -> 36150 | G24: =IF(F16=0,0,H24/(F16+F18)) -> 50 | H24: ='[1]Vehicules neuf 2026'!E79 -> 2400 | J24: =IF(I16=0,0,K24/(I16+I18)) -> 50 | K24: ='[1]Vehicules neuf 2026'!F79 -> 2550 | M24: =IF(L16=0,0,N24/(L16+L18)) -> 50 | N24: ='[1]Vehicules neuf 2026'!G79 -> 3700 | P24: =IF(O16=0,0,Q24/(O16+O18)) -> 50 | Q24: ='[1]Vehicules neuf 2026'!H79 -> 3800 | S24: =IF(R16=0,0,T24/(R16+R18)) -> 50 | T24: ='[1]Vehicules neuf 2026'!I79 -> 3950 | V24: =IF(U16=0,0,W24/(U16+U18)) -> 50 | W24: ='[1]Vehicules neuf 2026'!J79 -> 3550 | Y24: =IF(X16=0,0,Z24/(X16+X18)) -> 50 | Z24: ='[1]Vehicules neuf 2026'!K79 -> 3200 | AB24: =IF(AA16=0,0,AC24/(AA16+AA18)) -> 50 | AC24: ='[1]Vehicules neuf 2026'!L79 -> 2900 | AE24: =IF(AD16=0,0,AF24/(AD16+AD18)) -> 50 | AF24: ='[1]Vehicules neuf 2026'!M79 -> 2800 | AH24: =IF(AG16=0,0,AI24/(AG16+AG18)) -> 50 | AI24: ='[1]Vehicules neuf 2026'!N79 -> 2750 | AK24: =IF(AJ16=0,0,AL24/(AJ16+AJ18)) -> 50 | AL24: ='[1]Vehicules neuf 2026'!O79 -> 2450 | AN24: =IF(AM16=0,0,AO24/(AM16+AM18)) -> 50 | AO24: ='[1]Vehicules neuf 2026'!P79 -> 2100
A25: =+$C$4&B25 -> Véhicules neufsRev. Protections | B25: Rev. Protections | D25: =IF(C16=0,0,E25/(C16+C18)) -> 1130 | E25: =+SUM(H25,K25,N25,Q25,T25,W25,Z25,AC25,AF25,AI25,AL25,AO25) -> 816990 | G25: =IF(F16=0,0,H25/(F16+F18)) -> 1130 | H25: ='[1]Vehicules neuf 2026'!E80 -> 54240 | J25: =IF(I16=0,0,K25/(I16+I18)) -> 1130 | K25: ='[1]Vehicules neuf 2026'!F80 -> 57630 | M25: =IF(L16=0,0,N25/(L16+L18)) -> 1130 | N25: ='[1]Vehicules neuf 2026'!G80 -> 83620 | P25: =IF(O16=0,0,Q25/(O16+O18)) -> 1130 | Q25: ='[1]Vehicules neuf 2026'!H80 -> 85880 | S25: =IF(R16=0,0,T25/(R16+R18)) -> 1130 | T25: ='[1]Vehicules neuf 2026'!I80 -> 89270 | V25: =IF(U16=0,0,W25/(U16+U18)) -> 1130 | W25: ='[1]Vehicules neuf 2026'!J80 -> 80230 | Y25: =IF(X16=0,0,Z25/(X16+X18)) -> 1130 | Z25: ='[1]Vehicules neuf 2026'!K80 -> 72320 | AB25: =IF(AA16=0,0,AC25/(AA16+AA18)) -> 1130 | AC25: ='[1]Vehicules neuf 2026'!L80 -> 65540 | AE25: =IF(AD16=0,0,AF25/(AD16+AD18)) -> 1130 | AF25: ='[1]Vehicules neuf 2026'!M80 -> 63280 | AH25: =IF(AG16=0,0,AI25/(AG16+AG18)) -> 1130 | AI25: ='[1]Vehicules neuf 2026'!N80 -> 62150 | AK25: =IF(AJ16=0,0,AL25/(AJ16+AJ18)) -> 1130 | AL25: ='[1]Vehicules neuf 2026'!O80 -> 55370 | AN25: =IF(AM16=0,0,AO25/(AM16+AM18)) -> 1130 | AO25: ='[1]Vehicules neuf 2026'!P80 -> 47460
A26: =+$C$4&B26 -> Véhicules neufsRev. Autres | B26: Rev. Autres | D26: =IF(C16=0,0,E26/(C16+C18)) -> 20 | E26: =+SUM(H26,K26,N26,Q26,T26,W26,Z26,AC26,AF26,AI26,AL26,AO26) -> 14460 | G26: =IF(F16=0,0,H26/(F16+F18)) -> 20 | H26: ='[1]Vehicules neuf 2026'!E81 -> 960 | J26: =IF(I16=0,0,K26/(I16+I18)) -> 20 | K26: ='[1]Vehicules neuf 2026'!F81 -> 1020 | M26: =IF(L16=0,0,N26/(L16+L18)) -> 20 | N26: ='[1]Vehicules neuf 2026'!G81 -> 1480 | P26: =IF(O16=0,0,Q26/(O16+O18)) -> 20 | Q26: ='[1]Vehicules neuf 2026'!H81 -> 1520 | S26: =IF(R16=0,0,T26/(R16+R18)) -> 20 | T26: ='[1]Vehicules neuf 2026'!I81 -> 1580 | V26: =IF(U16=0,0,W26/(U16+U18)) -> 20 | W26: ='[1]Vehicules neuf 2026'!J81 -> 1420 | Y26: =IF(X16=0,0,Z26/(X16+X18)) -> 20 | Z26: ='[1]Vehicules neuf 2026'!K81 -> 1280 | AB26: =IF(AA16=0,0,AC26/(AA16+AA18)) -> 20 | AC26: ='[1]Vehicules neuf 2026'!L81 -> 1160 | AE26: =IF(AD16=0,0,AF26/(AD16+AD18)) -> 20 | AF26: ='[1]Vehicules neuf 2026'!M81 -> 1120 | AH26: =IF(AG16=0,0,AI26/(AG16+AG18)) -> 20 | AI26: ='[1]Vehicules neuf 2026'!N81 -> 1100 | AK26: =IF(AJ16=0,0,AL26/(AJ16+AJ18)) -> 20 | AL26: ='[1]Vehicules neuf 2026'!O81 -> 980 | AN26: =IF(AM16=0,0,AO26/(AM16+AM18)) -> 20 | AO26: ='[1]Vehicules neuf 2026'!P81 -> 840
A27: =+$C$4&B27 -> Véhicules neufsTotal F&I | B27: Total F&I | C27: =+C18+C16 -> 723 | D27: =IF(C27<=0,0,E27/C27) -> 1200 | E27: =E24+E25+E26 -> 867600 | F27: =+F18+F16 -> 48 | G27: =IF(F27<=0,0,H27/F27) -> 1200 | H27: =H24+H25+H26 -> 57600 | I27: =+I18+I16 -> 51 | J27: =IF(I27<=0,0,K27/I27) -> 1200 | K27: =K24+K25+K26 -> 61200 | L27: =+L18+L16 -> 74 | M27: =IF(L27<=0,0,N27/L27) -> 1200 | N27: =N24+N25+N26 -> 88800 | O27: =+O18+O16 -> 76 | P27: =IF(O27<=0,0,Q27/O27) -> 1200 | Q27: =Q24+Q25+Q26 -> 91200 | R27: =+R18+R16 -> 79 | S27: =IF(R27<=0,0,T27/R27) -> 1200 | T27: =T24+T25+T26 -> 94800 | U27: =+U18+U16 -> 71 | V27: =IF(U27<=0,0,W27/U27) -> 1200 | W27: =W24+W25+W26 -> 85200 | X27: =+X18+X16 -> 64 | Y27: =IF(X27<=0,0,Z27/X27) -> 1200 | Z27: =Z24+Z25+Z26 -> 76800 | AA27: =+AA18+AA16 -> 58 | AB27: =IF(AA27<=0,0,AC27/AA27) -> 1200 | AC27: =AC24+AC25+AC26 -> 69600 | AD27: =+AD18+AD16 -> 56 | AE27: =IF(AD27<=0,0,AF27/AD27) -> 1200 | AF27: =AF24+AF25+AF26 -> 67200 | AG27: =+AG18+AG16 -> 55 | AH27: =IF(AG27<=0,0,AI27/AG27) -> 1200 | AI27: =AI24+AI25+AI26 -> 66000 | AJ27: =+AJ18+AJ16 -> 49 | AK27: =IF(AJ27<=0,0,AL27/AJ27) -> 1200 | AL27: =AL24+AL25+AL26 -> 58800 | AM27: =+AM18+AM16 -> 42 | AN27: =IF(AM27<=0,0,AO27/AM27) -> 1200 | AO27: =AO24+AO25+AO26 -> 50400
A28: =+$C$4&B28 -> Véhicules neufs
A29: =+$C$4&B29 -> Véhicules neufs
A30: =+$C$4&B30 -> Véhicules neufsTotal Dépt. Neufs | B30: Total Dépt. Neufs | C30: =+C16+C18+C20 -> 772 | D30: =IF(C30<=0,0,E30/C30) -> 3452.0958 | E30: =E16+E20+E27+E22+E18 -> 2665018 | F30: =+F16+F18+F20 -> 51 | G30: =IF(F30<=0,0,H30/F30) -> 3456.6499 | H30: =H16+H20+H27+H22+H18 -> 176289.15 | I30: =+I16+I18+I20 -> 55 | J30: =IF(I30<=0,0,K30/I30) -> 3426.3734 | K30: =K16+K20+K27+K22+K18 -> 188450.54 | L30: =+L16+L18+L20 -> 79 | M30: =IF(L30<=0,0,N30/L30) -> 3455.56 | N30: =N16+N20+N27+N22+N18 -> 272989.24 | O30: =+O16+O18+O20 -> 81 | P30: =IF(O30<=0,0,Q30/O30) -> 3455.1342 | Q30: =Q16+Q20+Q27+Q22+Q18 -> 279865.87 | R30: =+R16+R18+R20 -> 84 | S30: =IF(R30<=0,0,T30/R30) -> 3461.0307 | T30: =T16+T20+T27+T22+T18 -> 290726.58 | U30: =+U16+U18+U20 -> 76 | V30: =IF(U30<=0,0,W30/U30) -> 3449.0596 | W30: =W16+W20+W27+W22+W18 -> 262128.53 | X30: =+X16+X18+X20 -> 68 | Y30: =IF(X30<=0,0,Z30/X30) -> 3459.841 | Z30: =Z16+Z20+Z27+Z22+Z18 -> 235269.19 | AA30: =+AA16+AA18+AA20 -> 62 | AB30: =IF(AA30<=0,0,AC30/AA30) -> 3451.7611 | AC30: =AC16+AC20+AC27+AC22+AC18 -> 214009.19 | AD30: =+AD16+AD18+AD20 -> 60 | AE30: =IF(AD30<=0,0,AF30/AD30) -> 3449.7619 | AF30: =AF16+AF20+AF27+AF22+AF18 -> 206985.72 | AG30: =+AG16+AG18+AG20 -> 59 | AH30: =IF(AG30<=0,0,AI30/AG30) -> 3443.1946 | AI30: =AI16+AI20+AI27+AI22+AI18 -> 203148.48 | AJ30: =+AJ16+AJ18+AJ20 -> 52 | AK30: =IF(AJ30<=0,0,AL30/AJ30) -> 3463.9688 | AL30: =AL16+AL20+AL27+AL22+AL18 -> 180126.38 | AM30: =+AM16+AM18+AM20 -> 45 | AN30: =IF(AM30<=0,0,AO30/AM30) -> 3445.0921 | AO30: =AO16+AO20+AO27+AO22+AO18 -> 155029.14
A31: =+$C$4&B31 -> Véhicules neufs
A32: =+$C$4&B32 -> Véhicules neufs
A33: =+$C$4&B33 -> Véhicules neufsDEPENSES | B33: DEPENSES
A34: =+$C$4&B34 -> Véhicules neufsComm. vendeurs | B34: Comm. vendeurs | C34: =E34/(E16+E18) -> 0.32350364 | D34: =IF(E34=0,0,E34/C$27) -> 730.98597 | E34: =+SUM(H34,K34,N34,Q34,T34,W34,Z34,AC34,AF34,AI34,AL34,AO34) -> 528502.86 | F34: =H34/(H16+H18) -> 0.32965618 | G34: =IF(H34=0,0,H34/F$27) -> 742.95684 | H34: ='[1]Vehicules neuf 2026'!E74 -> 35661.928 | I34: =K34/(K16+K18) -> 0.32917199 | J34: =IF(K34=0,0,K34/I$27) -> 742.24631 | K34: ='[1]Vehicules neuf 2026'!F74 -> 37854.562 | L34: =N34/(N16+N18) -> 0.31274572 | M34: =IF(N34=0,0,N34/L$27) -> 707.51032 | N34: ='[1]Vehicules neuf 2026'!G74 -> 52355.763 | O34: =Q34/(Q16+Q18) -> 0.31166803 | P34: =IF(Q34=0,0,Q34/O$27) -> 704.27377 | Q34: ='[1]Vehicules neuf 2026'!H74 -> 53524.806 | R34: =T34/(T16+T18) -> 0.31763709 | S34: =IF(T34=0,0,T34/R$27) -> 717.92728 | T34: ='[1]Vehicules neuf 2026'!I74 -> 56716.255 | U34: =W34/(W16+W18) -> 0.31456115 | V34: =IF(W34=0,0,W34/U$27) -> 711.46922 | W34: ='[1]Vehicules neuf 2026'!J74 -> 50514.315 | X34: =Z34/(Z16+Z18) -> 0.32645142 | Y34: =IF(Z34=0,0,Z34/X$27) -> 736.84105 | Z34: ='[1]Vehicules neuf 2026'!K74 -> 47157.827 | AA34: =AC34/(AC16+AC18) -> 0.32189305 | AB34: =IF(AC34=0,0,AC34/AA$27) -> 727.75629 | AC34: ='[1]Vehicules neuf 2026'!L74 -> 42209.865 | AD34: =AF34/(AF16+AF18) -> 0.32366501 | AE34: =IF(AF34=0,0,AF34/AD$27) -> 732.87181 | AF34: ='[1]Vehicules neuf 2026'!M74 -> 41040.822 | AG34: =AI34/(AI16+AI18) -> 0.33560008 | AH34: =IF(AI34=0,0,AI34/AG$27) -> 758.51665 | AI34: ='[1]Vehicules neuf 2026'!N74 -> 41718.416 | AJ34: =AL34/(AL16+AL18) -> 0.32831374 | AK34: =IF(AL34=0,0,AL34/AJ$27) -> 741.51702 | AL34: ='[1]Vehicules neuf 2026'!O74 -> 36334.334 | AM34: =AO34/(AO16+AO18) -> 0.35226966 | AN34: =IF(AO34=0,0,AO34/AM$27) -> 795.57061 | AO34: ='[1]Vehicules neuf 2026'!P74 -> 33413.966
A35: =+$C$4&B35 -> Véhicules neufsComm. F&I | B35: Comm. F&I | C35: =E35/E27 -> 0.2 | D35: =IF(E35=0,0,E35/C$27) -> 240 | E35: =+SUM(H35,K35,N35,Q35,T35,W35,Z35,AC35,AF35,AI35,AL35,AO35) -> 173520 | F35: =H35/H27 -> 0.2 | G35: =IF(H35=0,0,H35/F$27) -> 240 | H35: ='[1]Vehicules neuf 2026'!E85 -> 11520 | I35: =K35/K27 -> 0.2 | J35: =IF(K35=0,0,K35/I$27) -> 240 | K35: ='[1]Vehicules neuf 2026'!F85 -> 12240 | L35: =N35/N27 -> 0.2 | M35: =IF(N35=0,0,N35/L$27) -> 240 | N35: ='[1]Vehicules neuf 2026'!G85 -> 17760 | O35: =Q35/Q27 -> 0.2 | P35: =IF(Q35=0,0,Q35/O$27) -> 240 | Q35: ='[1]Vehicules neuf 2026'!H85 -> 18240 | R35: =T35/T27 -> 0.2 | S35: =IF(T35=0,0,T35/R$27) -> 240 | T35: ='[1]Vehicules neuf 2026'!I85 -> 18960 | U35: =W35/W27 -> 0.2 | V35: =IF(W35=0,0,W35/U$27) -> 240 | W35: ='[1]Vehicules neuf 2026'!J85 -> 17040 | X35: =Z35/Z27 -> 0.2 | Y35: =IF(Z35=0,0,Z35/X$27) -> 240 | Z35: ='[1]Vehicules neuf 2026'!K85 -> 15360 | AA35: =AC35/AC27 -> 0.2 | AB35: =IF(AC35=0,0,AC35/AA$27) -> 240 | AC35: ='[1]Vehicules neuf 2026'!L85 -> 13920 | AD35: =AF35/AF27 -> 0.2 | AE35: =IF(AF35=0,0,AF35/AD$27) -> 240 | AF35: ='[1]Vehicules neuf 2026'!M85 -> 13440 | AG35: =AI35/AI27 -> 0.2 | AH35: =IF(AI35=0,0,AI35/AG$27) -> 240 | AI35: ='[1]Vehicules neuf 2026'!N85 -> 13200 | AJ35: =AL35/AL27 -> 0.2 | AK35: =IF(AL35=0,0,AL35/AJ$27) -> 240 | AL35: ='[1]Vehicules neuf 2026'!O85 -> 11760 | AM35: =AO35/AO27 -> 0.2 | AN35: =IF(AO35=0,0,AO35/AM$27) -> 240 | AO35: ='[1]Vehicules neuf 2026'!P85 -> 10080
A36: =+$C$4&B36 -> Véhicules neufsFrais de livraison | B36: Frais de livraison | D36: =IF(E36=0,0,E36/C$27) -> 115 | E36: =+SUM(H36,K36,N36,Q36,T36,W36,Z36,AC36,AF36,AI36,AL36,AO36) -> 83145 | G36: =IF(H36=0,0,H36/F$27) -> 115 | H36: ='[1]Vehicules neuf 2026'!E91 -> 5520 | J36: =IF(K36=0,0,K36/I$27) -> 115 | K36: ='[1]Vehicules neuf 2026'!F91 -> 5865 | M36: =IF(N36=0,0,N36/L$27) -> 115 | N36: ='[1]Vehicules neuf 2026'!G91 -> 8510 | P36: =IF(Q36=0,0,Q36/O$27) -> 115 | Q36: ='[1]Vehicules neuf 2026'!H91 -> 8740 | S36: =IF(T36=0,0,T36/R$27) -> 115 | T36: ='[1]Vehicules neuf 2026'!I91 -> 9085 | V36: =IF(W36=0,0,W36/U$27) -> 115 | W36: ='[1]Vehicules neuf 2026'!J91 -> 8165 | Y36: =IF(Z36=0,0,Z36/X$27) -> 115 | Z36: ='[1]Vehicules neuf 2026'!K91 -> 7360 | AB36: =IF(AC36=0,0,AC36/AA$27) -> 115 | AC36: ='[1]Vehicules neuf 2026'!L91 -> 6670 | AE36: =IF(AF36=0,0,AF36/AD$27) -> 115 | AF36: ='[1]Vehicules neuf 2026'!M91 -> 6440 | AH36: =IF(AI36=0,0,AI36/AG$27) -> 115 | AI36: ='[1]Vehicules neuf 2026'!N91 -> 6325 | AK36: =IF(AL36=0,0,AL36/AJ$27) -> 115 | AL36: ='[1]Vehicules neuf 2026'!O91 -> 5635 | AN36: =IF(AO36=0,0,AO36/AM$27) -> 115 | AO36: ='[1]Vehicules neuf 2026'!P91 -> 4830
A37: =+$C$4&B37 -> Véhicules neufsService gratuit 1 | B37: Service gratuit 1 | D37: =IF(E37=0,0,E37/C$27) -> 10 | E37: =+SUM(H37,K37,N37,Q37,T37,W37,Z37,AC37,AF37,AI37,AL37,AO37) -> 7230 | G37: =IF(H37=0,0,H37/F$27) -> 10 | H37: ='[1]Vehicules neuf 2026'!E97 -> 480 | J37: =IF(K37=0,0,K37/I$27) -> 10 | K37: ='[1]Vehicules neuf 2026'!F97 -> 510 | M37: =IF(N37=0,0,N37/L$27) -> 10 | N37: ='[1]Vehicules neuf 2026'!G97 -> 740 | P37: =IF(Q37=0,0,Q37/O$27) -> 10 | Q37: ='[1]Vehicules neuf 2026'!H97 -> 760 | S37: =IF(T37=0,0,T37/R$27) -> 10 | T37: ='[1]Vehicules neuf 2026'!I97 -> 790 | V37: =IF(W37=0,0,W37/U$27) -> 10 | W37: ='[1]Vehicules neuf 2026'!J97 -> 710 | Y37: =IF(Z37=0,0,Z37/X$27) -> 10 | Z37: ='[1]Vehicules neuf 2026'!K97 -> 640 | AB37: =IF(AC37=0,0,AC37/AA$27) -> 10 | AC37: ='[1]Vehicules neuf 2026'!L97 -> 580 | AE37: =IF(AF37=0,0,AF37/AD$27) -> 10 | AF37: ='[1]Vehicules neuf 2026'!M97 -> 560 | AH37: =IF(AI37=0,0,AI37/AG$27) -> 10 | AI37: ='[1]Vehicules neuf 2026'!N97 -> 550 | AK37: =IF(AL37=0,0,AL37/AJ$27) -> 10 | AL37: ='[1]Vehicules neuf 2026'!O97 -> 490 | AN37: =IF(AO37=0,0,AO37/AM$27) -> 10 | AO37: ='[1]Vehicules neuf 2026'!P97 -> 420
A38: =+$C$4&B38 -> Véhicules neufsEntretien stock | B38: Entretien stock | D38: =IF(E38=0,0,E38/C$27) -> 120 | E38: =+SUM(H38,K38,N38,Q38,T38,W38,Z38,AC38,AF38,AI38,AL38,AO38) -> 86760 | G38: =IF(H38=0,0,H38/F$27) -> 120 | H38: ='[1]Vehicules neuf 2026'!E103 -> 5760 | J38: =IF(K38=0,0,K38/I$27) -> 120 | K38: ='[1]Vehicules neuf 2026'!F103 -> 6120 | M38: =IF(N38=0,0,N38/L$27) -> 120 | N38: ='[1]Vehicules neuf 2026'!G103 -> 8880 | P38: =IF(Q38=0,0,Q38/O$27) -> 120 | Q38: ='[1]Vehicules neuf 2026'!H103 -> 9120 | S38: =IF(T38=0,0,T38/R$27) -> 120 | T38: ='[1]Vehicules neuf 2026'!I103 -> 9480 | V38: =IF(W38=0,0,W38/U$27) -> 120 | W38: ='[1]Vehicules neuf 2026'!J103 -> 8520 | Y38: =IF(Z38=0,0,Z38/X$27) -> 120 | Z38: ='[1]Vehicules neuf 2026'!K103 -> 7680 | AB38: =IF(AC38=0,0,AC38/AA$27) -> 120 | AC38: ='[1]Vehicules neuf 2026'!L103 -> 6960 | AE38: =IF(AF38=0,0,AF38/AD$27) -> 120 | AF38: ='[1]Vehicules neuf 2026'!M103 -> 6720 | AH38: =IF(AI38=0,0,AI38/AG$27) -> 120 | AI38: ='[1]Vehicules neuf 2026'!N103 -> 6600 | AK38: =IF(AL38=0,0,AL38/AJ$27) -> 120 | AL38: ='[1]Vehicules neuf 2026'!O103 -> 5880 | AN38: =IF(AO38=0,0,AO38/AM$27) -> 120 | AO38: ='[1]Vehicules neuf 2026'!P103 -> 5040
A39: =+$C$4&B39 -> Véhicules neufsPublicité 1 | B39: Publicité 1 | D39: =IF(E39=0,0,E39/C$27) -> 68.48686 | E39: =+SUM(H39,K39,N39,Q39,T39,W39,Z39,AC39,AF39,AI39,AL39,AO39) -> 49516 | G39: =IF(H39=0,0,H39/F$27) -> 169.96875 | H39: ='[1]Vehicules neuf 2026'!E111 -> 8158.5 | J39: =IF(K39=0,0,K39/I$27) -> 61.421569 | K39: ='[1]Vehicules neuf 2026'!F111 -> 3132.5 | M39: =IF(N39=0,0,N39/L$27) -> -4.2905405 | N39: ='[1]Vehicules neuf 2026'!G111 -> -317.5 | P39: =IF(Q39=0,0,Q39/O$27) -> 149.76974 | Q39: ='[1]Vehicules neuf 2026'!H111 -> 11382.5 | S39: =IF(T39=0,0,T39/R$27) -> -13.512658 | T39: ='[1]Vehicules neuf 2026'!I111 -> -1067.5 | V39: =IF(W39=0,0,W39/U$27) -> 1.8661972 | W39: ='[1]Vehicules neuf 2026'!J111 -> 132.5 | Y39: =IF(Z39=0,0,Z39/X$27) -> 18.476562 | Z39: ='[1]Vehicules neuf 2026'!K111 -> 1182.5 | AB39: =IF(AC39=0,0,AC39/AA$27) -> 35.905172 | AC39: ='[1]Vehicules neuf 2026'!L111 -> 2082.5 | AE39: =IF(AF39=0,0,AF39/AD$27) -> 42.544643 | AF39: ='[1]Vehicules neuf 2026'!M111 -> 2382.5 | AH39: =IF(AI39=0,0,AI39/AG$27) -> 46.045455 | AI39: ='[1]Vehicules neuf 2026'!N111 -> 2532.5 | AK39: =IF(AL39=0,0,AL39/AJ$27) -> 314.94898 | AL39: ='[1]Vehicules neuf 2026'!O111 -> 15432.5 | AN39: =IF(AO39=0,0,AO39/AM$27) -> 106.72619 | AO39: ='[1]Vehicules neuf 2026'!P111 -> 4482.5
A40: =+$C$4&B40 -> Véhicules neufsIntérêt de gros | B40: Intérêt de gros | D40: =IF(E40=0,0,E40/C$27) -> 352.41067 | E40: =+SUM(H40,K40,N40,Q40,T40,W40,Z40,AC40,AF40,AI40,AL40,AO40) -> 254792.91 | G40: =IF(H40=0,0,H40/F$27) -> 402.63618 | H40: ='[1]Vehicules neuf 2026'!E49 -> 19326.537 | J40: =IF(K40=0,0,K40/I$27) -> 419.81904 | K40: ='[1]Vehicules neuf 2026'!F49 -> 21410.771 | M40: =IF(N40=0,0,N40/L$27) -> 321.98092 | N40: ='[1]Vehicules neuf 2026'!G49 -> 23826.588 | P40: =IF(Q40=0,0,Q40/O$27) -> 318.80558 | Q40: ='[1]Vehicules neuf 2026'!H49 -> 24229.224 | S40: =IF(T40=0,0,T40/R$27) -> 303.1014 | T40: ='[1]Vehicules neuf 2026'!I49 -> 23945.011 | V40: =IF(W40=0,0,W40/U$27) -> 318.57295 | W40: ='[1]Vehicules neuf 2026'!J49 -> 22618.68 | Y40: =IF(Z40=0,0,Z40/X$27) -> 334.91337 | Z40: ='[1]Vehicules neuf 2026'!K49 -> 21434.456 | AB40: =IF(AC40=0,0,AC40/AA$27) -> 357.30899 | AC40: ='[1]Vehicules neuf 2026'!L49 -> 20723.921 | AE40: =IF(AF40=0,0,AF40/AD$27) -> 365.41771 | AF40: ='[1]Vehicules neuf 2026'!M49 -> 20463.392 | AH40: =IF(AI40=0,0,AI40/AG$27) -> 361.296 | AI40: ='[1]Vehicules neuf 2026'!N49 -> 19871.28 | AK40: =IF(AL40=0,0,AL40/AJ$27) -> 381.85184 | AL40: ='[1]Vehicules neuf 2026'!O49 -> 18710.74 | AN40: =IF(AO40=0,0,AO40/AM$27) -> 434.10271 | AO40: ='[1]Vehicules neuf 2026'!P49 -> 18232.314
A41: =+$C$4&B41 -> Véhicules neufs[...] | B41: [...] | D41: =IF(E41=0,0,E41/C$27) -> 0 | E41: =+SUM(H41,K41,N41,Q41,T41,W41,Z41,AC41,AF41,AI41,AL41,AO41) -> 0 | G41: =IF(H41=0,0,H41/F$27) -> 0 | J41: =IF(K41=0,0,K41/I$27) -> 0 | M41: =IF(N41=0,0,N41/L$27) -> 0 | P41: =IF(Q41=0,0,Q41/O$27) -> 0 | S41: =IF(T41=0,0,T41/R$27) -> 0 | V41: =IF(W41=0,0,W41/U$27) -> 0 | Y41: =IF(Z41=0,0,Z41/X$27) -> 0 | AB41: =IF(AC41=0,0,AC41/AA$27) -> 0 | AE41: =IF(AF41=0,0,AF41/AD$27) -> 0 | AH41: =IF(AI41=0,0,AI41/AG$27) -> 0 | AK41: =IF(AL41=0,0,AL41/AJ$27) -> 0 | AN41: =IF(AO41=0,0,AO41/AM$27) -> 0
A42: =+$C$4&B42 -> Véhicules neufs[...] | B42: [...] | D42: =IF(E42=0,0,E42/C$27) -> 0 | E42: =+SUM(H42,K42,N42,Q42,T42,W42,Z42,AC42,AF42,AI42,AL42,AO42) -> 0 | G42: =IF(H42=0,0,H42/F$27) -> 0 | J42: =IF(K42=0,0,K42/I$27) -> 0 | M42: =IF(N42=0,0,N42/L$27) -> 0 | P42: =IF(Q42=0,0,Q42/O$27) -> 0 | S42: =IF(T42=0,0,T42/R$27) -> 0 | V42: =IF(W42=0,0,W42/U$27) -> 0 | Y42: =IF(Z42=0,0,Z42/X$27) -> 0 | AB42: =IF(AC42=0,0,AC42/AA$27) -> 0 | AE42: =IF(AF42=0,0,AF42/AD$27) -> 0 | AH42: =IF(AI42=0,0,AI42/AG$27) -> 0 | AK42: =IF(AL42=0,0,AL42/AJ$27) -> 0 | AN42: =IF(AO42=0,0,AO42/AM$27) -> 0
A43: =+$C$4&B43 -> Véhicules neufs[...] | B43: [...] | D43: =IF(E43=0,0,E43/C$27) -> 0 | E43: =+SUM(H43,K43,N43,Q43,T43,W43,Z43,AC43,AF43,AI43,AL43,AO43) -> 0 | G43: =IF(H43=0,0,H43/F$27) -> 0 | J43: =IF(K43=0,0,K43/I$27) -> 0 | M43: =IF(N43=0,0,N43/L$27) -> 0 | P43: =IF(Q43=0,0,Q43/O$27) -> 0 | S43: =IF(T43=0,0,T43/R$27) -> 0 | V43: =IF(W43=0,0,W43/U$27) -> 0 | Y43: =IF(Z43=0,0,Z43/X$27) -> 0 | AB43: =IF(AC43=0,0,AC43/AA$27) -> 0 | AE43: =IF(AF43=0,0,AF43/AD$27) -> 0 | AH43: =IF(AI43=0,0,AI43/AG$27) -> 0 | AK43: =IF(AL43=0,0,AL43/AJ$27) -> 0 | AN43: =IF(AO43=0,0,AO43/AM$27) -> 0
A44: =+$C$4&B44 -> Véhicules neufsTOTAL VARIABLES | B44: TOTAL VARIABLES | C44: % brut | D44: =IFERROR(E44/E$30,0) -> 0.44407459 | E44: =SUM(E34:E43) -> 1183466.8 | F44: % brut | G44: =IFERROR(H44/H$30,0) -> 0.49025687 | H44: =SUM(H34:H43) -> 86426.965 | I44: % brut | J44: =IFERROR(K44/K$30,0) -> 0.46236447 | K44: =SUM(K34:K43) -> 87132.833 | L44: % brut | M44: =IFERROR(N44/N$30,0) -> 0.40937457 | N44: =SUM(N34:N43) -> 111754.85 | O44: % brut | P44: =IFERROR(Q44/Q$30,0) -> 0.45020328 | Q44: =SUM(Q34:Q43) -> 125996.53 | R44: % brut | S44: =IFERROR(T44/T$30,0) -> 0.40556583 | T44: =SUM(T34:T43) -> 117908.77 | U44: % brut | V44: =IFERROR(W44/W$30,0) -> 0.41086903 | W44: =SUM(W34:W43) -> 107700.49 | X44: % brut | Y44: =IFERROR(Z44/Z$30,0) -> 0.42850822 | Z44: =SUM(Z34:Z43) -> 100814.78 | AA44: % brut | AB44: =IFERROR(AC44/AC$30,0) -> 0.43524433 | AC44: =SUM(AC34:AC43) -> 93146.286 | AD44: % brut | AE44: =IFERROR(AF44/AF$30,0) -> 0.43986955 | AF44: =SUM(AF34:AF43) -> 91046.714 | AG44: % brut | AH44: =IFERROR(AI44/AI$30,0) -> 0.44694991 | AI44: =SUM(AI34:AI43) -> 90797.196 | AJ44: % brut | AK44: =IFERROR(AL44/AL$30,0) -> 0.52320251 | AL44: =SUM(AL34:AL43) -> 94242.574 | AM44: % brut | AN44: =IFERROR(AO44/AO$30,0) -> 0.49344773 | AO44: =SUM(AO34:AO43) -> 76498.78
A45: =+$C$4&B45 -> Véhicules neufsSalaires cadres | B45: Salaires cadres | E45: =+SUM(H45,K45,N45,Q45,T45,W45,Z45,AC45,AF45,AI45,AL45,AO45) -> 263797.84 | H45: =[1]Salaire!$E$33 -> 26496.555 | K45: =[1]Salaire!$F$33 -> 20698.718 | N45: =[1]Salaire!$G$33 -> 20698.718 | Q45: =[1]Salaire!$H$33 -> 20698.718 | T45: =[1]Salaire!$I$33 -> 23102.564 | W45: =[1]Salaire!$J$33 -> 20698.718 | Z45: =[1]Salaire!$K$33 -> 23102.564 | AC45: =[1]Salaire!$L$33 -> 20698.718 | AF45: =[1]Salaire!$M$33 -> 20698.718 | AI45: =[1]Salaire!$N$33 -> 23102.564 | AL45: =[1]Salaire!$O$33 -> 20698.718 | AO45: =[1]Salaire!$P$33 -> 23102.564
A46: =+$C$4&B46 -> Véhicules neufsSalaires commis | B46: Salaires commis | E46: =+SUM(H46,K46,N46,Q46,T46,W46,Z46,AC46,AF46,AI46,AL46,AO46) -> 235724.66 | H46: =[1]Salaire!$E$90 -> 15088.421 | K46: =[1]Salaire!$F$90 -> 18491.133 | N46: =[1]Salaire!$G$90 -> 18491.133 | Q46: =[1]Salaire!$H$90 -> 18491.133 | T46: =[1]Salaire!$I$90 -> 22799.577 | W46: =[1]Salaire!$J$90 -> 18491.133 | Z46: =[1]Salaire!$K$90 -> 22799.577 | AC46: =[1]Salaire!$L$90 -> 18491.133 | AF46: =[1]Salaire!$M$90 -> 18491.133 | AI46: =[1]Salaire!$N$90 -> 22799.577 | AL46: =[1]Salaire!$O$90 -> 18491.133 | AO46: =[1]Salaire!$P$90 -> 22799.577
A47: =+$C$4&B47 -> Véhicules neufsSalaires autres | B47: Salaires autres | E47: =+SUM(H47,K47,N47,Q47,T47,W47,Z47,AC47,AF47,AI47,AL47,AO47) -> 341.85 | H47: =[1]Salaire!$E$161 -> 341.85 | K47: =[1]Salaire!$F$161 -> 0 | N47: =[1]Salaire!$G$161 -> 0 | Q47: =[1]Salaire!$H$161 -> 0 | T47: =[1]Salaire!$I$161 -> 0 | W47: =[1]Salaire!$J$161 -> 0 | Z47: =[1]Salaire!$K$161 -> 0 | AC47: =[1]Salaire!$L$161 -> 0 | AF47: =[1]Salaire!$M$161 -> 0 | AI47: =[1]Salaire!$N$161 -> 0 | AL47: =[1]Salaire!$O$161 -> 0 | AO47: =[1]Salaire!$P$161 -> 0
A48: =+$C$4&B48 -> Véhicules neufsSalaires spécialistes | B48: Salaires spécialistes | E48: =+SUM(H48,K48,N48,Q48,T48,W48,Z48,AC48,AF48,AI48,AL48,AO48) -> 0
A49: =+$C$4&B49 -> Véhicules neufs[...] | B49: [...] | E49: =+SUM(H49,K49,N49,Q49,T49,W49,Z49,AC49,AF49,AI49,AL49,AO49) -> 0
A50: =+$C$4&B50 -> Véhicules neufs[...] | B50: [...] | E50: =+SUM(H50,K50,N50,Q50,T50,W50,Z50,AC50,AF50,AI50,AL50,AO50) -> 0
A51: =+$C$4&B51 -> Véhicules neufs[...] | B51: [...] | E51: =+SUM(H51,K51,N51,Q51,T51,W51,Z51,AC51,AF51,AI51,AL51,AO51) -> 0
A52: =+$C$4&B52 -> Véhicules neufsSalaires en absences | B52: Salaires en absences | E52: =+SUM(H52,K52,N52,Q52,T52,W52,Z52,AC52,AF52,AI52,AL52,AO52) -> 148403.91 | H52: ='[1]DAS-VAC'!$F$43 -> 11375.381 | K52: ='[1]DAS-VAC'!$G$43 -> 9716.0835 | N52: ='[1]DAS-VAC'!$H$43 -> 12643.918 | Q52: ='[1]DAS-VAC'!$I$43 -> 13199.32 | T52: ='[1]DAS-VAC'!$J$43 -> 14866.607 | W52: ='[1]DAS-VAC'!$K$43 -> 11600.209 | Z52: ='[1]DAS-VAC'!$L$43 -> 12704.781 | AC52: ='[1]DAS-VAC'!$M$43 -> 12034.037 | AF52: ='[1]DAS-VAC'!$N$43 -> 12210.091 | AI52: ='[1]DAS-VAC'!$O$43 -> 14026.192 | AL52: ='[1]DAS-VAC'!$P$43 -> 13429.854 | AO52: ='[1]DAS-VAC'!$Q$43 -> 10597.435
A53: =+$C$4&B53 -> Véhicules neufsDéduction à la source | B53: Déduction à la source | E53: =+SUM(H53,K53,N53,Q53,T53,W53,Z53,AC53,AF53,AI53,AL53,AO53) -> 180438.23 | H53: ='[1]DAS-VAC'!$F$51 -> 13830.859 | K53: ='[1]DAS-VAC'!$G$51 -> 11813.388 | N53: ='[1]DAS-VAC'!$H$51 -> 15373.222 | Q53: ='[1]DAS-VAC'!$I$51 -> 16048.513 | T53: ='[1]DAS-VAC'!$J$51 -> 18075.699 | W53: ='[1]DAS-VAC'!$K$51 -> 14104.219 | Z53: ='[1]DAS-VAC'!$L$51 -> 15447.223 | AC53: ='[1]DAS-VAC'!$M$51 -> 14631.692 | AF53: ='[1]DAS-VAC'!$N$51 -> 14845.749 | AI53: ='[1]DAS-VAC'!$O$51 -> 17053.872 | AL53: ='[1]DAS-VAC'!$P$51 -> 16328.809 | AO53: ='[1]DAS-VAC'!$Q$51 -> 12884.987
A54: =+$C$4&B54 -> Véhicules neufsBénéfices marginaux | B54: Bénéfices marginaux | E54: =+SUM(H54,K54,N54,Q54,T54,W54,Z54,AC54,AF54,AI54,AL54,AO54) -> 92964.915 | H54: ='[1]DAS-VAC'!$F$59 -> 7125.8992 | K54: ='[1]DAS-VAC'!$G$59 -> 6086.4629 | N54: ='[1]DAS-VAC'!$H$59 -> 7920.5515 | Q54: ='[1]DAS-VAC'!$I$59 -> 8268.4728 | T54: ='[1]DAS-VAC'!$J$59 -> 9312.9145 | W54: ='[1]DAS-VAC'!$K$59 -> 7266.7387 | Z54: ='[1]DAS-VAC'!$L$59 -> 7958.678 | AC54: ='[1]DAS-VAC'!$M$59 -> 7538.5022 | AF54: ='[1]DAS-VAC'!$N$59 -> 7648.788 | AI54: ='[1]DAS-VAC'!$O$59 -> 8786.4514 | AL54: ='[1]DAS-VAC'!$P$59 -> 8412.8865 | AO54: ='[1]DAS-VAC'!$Q$59 -> 6638.5695
A55: =+$C$4&B55 -> Véhicules neufsCsst | B55: Csst | E55: =+SUM(H55,K55,N55,Q55,T55,W55,Z55,AC55,AF55,AI55,AL55,AO55) -> 40533.226 | H55: ='[1]DAS-VAC'!$F$67 -> 3106.9322 | K55: ='[1]DAS-VAC'!$G$67 -> 2653.7321 | N55: ='[1]DAS-VAC'!$H$67 -> 3453.405 | Q55: ='[1]DAS-VAC'!$I$67 -> 3605.1007 | T55: ='[1]DAS-VAC'!$J$67 -> 4060.4831 | W55: ='[1]DAS-VAC'!$K$67 -> 3168.339 | Z55: ='[1]DAS-VAC'!$L$67 -> 3470.0284 | AC55: ='[1]DAS-VAC'!$M$67 -> 3286.8294 | AF55: ='[1]DAS-VAC'!$N$67 -> 3334.9146 | AI55: ='[1]DAS-VAC'!$O$67 -> 3830.9423 | AL55: ='[1]DAS-VAC'!$P$67 -> 3668.0659 | AO55: ='[1]DAS-VAC'!$Q$67 -> 2894.4537
A56: =+$C$4&B56 -> Véhicules neufs[...] | B56: [...] | E56: =+SUM(H56,K56,N56,Q56,T56,W56,Z56,AC56,AF56,AI56,AL56,AO56) -> 0
A57: =+$C$4&B57 -> Véhicules neufsTOTAL PERSONNEL | B57: TOTAL PERSONNEL | C57: % brut | D57: =IFERROR(E57/E$30,0) -> 0.36104996 | E57: =+SUM(E45:E56) -> 962204.63 | F57: % brut | G57: =IFERROR(H57/H$30,0) -> 0.43885798 | H57: =+SUM(H45:H56) -> 77365.897 | I57: % brut | J57: =IFERROR(K57/K$30,0) -> 0.36858222 | K57: =+SUM(K45:K56) -> 69459.517 | L57: % brut | M57: =IFERROR(N57/N$30,0) -> 0.28785365 | N57: =+SUM(N45:N56) -> 78580.948 | O57: % brut | P57: =IFERROR(Q57/Q$30,0) -> 0.28696339 | Q57: =+SUM(Q45:Q56) -> 80311.257 | R57: % brut | S57: =IFERROR(T57/T$30,0) -> 0.31719785 | T57: =+SUM(T45:T56) -> 92217.845 | U57: % brut | V57: =IFERROR(W57/W$30,0) -> 0.28737565 | W57: =+SUM(W45:W56) -> 75329.356 | X57: % brut | Y57: =IFERROR(Z57/Z$30,0) -> 0.36334061 | Z57: =+SUM(Z45:Z56) -> 85482.852 | AA57: % brut | AB57: =IFERROR(AC57/AC$30,0) -> 0.35830663 | AC57: =+SUM(AC45:AC56) -> 76680.911 | AD57: % brut | AE57: =IFERROR(AF57/AF$30,0) -> 0.3731146 | AF57: =+SUM(AF45:AF56) -> 77229.393 | AG57: % brut | AH57: =IFERROR(AI57/AI$30,0) -> 0.44105473 | AI57: =+SUM(AI45:AI56) -> 89599.598 | AJ57: % brut | AK57: =IFERROR(AL57/AL$30,0) -> 0.44984786 | AL57: =+SUM(AL45:AL56) -> 81029.467 | AM57: % brut | AN57: =IFERROR(AO57/AO$30,0) -> 0.50905 | AO57: =+SUM(AO45:AO56) -> 78917.587
A58: =+$C$4&B58 -> Véhicules neufsPublicité 2 | B58: Publicité 2 | E58: =+SUM(H58,K58,N58,Q58,T58,W58,Z58,AC58,AF58,AI58,AL58,AO58) -> 0 | H58: =[1]DEPA!$C$6 -> 0 | K58: =[1]DEPA!$D$6 -> 0 | N58: =[1]DEPA!$E$6 -> 0 | Q58: =[1]DEPA!$F$6 -> 0 | T58: =[1]DEPA!$G$6 -> 0 | W58: =[1]DEPA!$H$6 -> 0 | Z58: =[1]DEPA!$I$6 -> 0 | AC58: =[1]DEPA!$J$6 -> 0 | AF58: =[1]DEPA!$K$6 -> 0 | AI58: =[1]DEPA!$L$6 -> 0 | AL58: =[1]DEPA!$M$6 -> 0 | AO58: =[1]DEPA!$N$6 -> 0
A59: =+$C$4&B59 -> Véhicules neufsService gratuit 2 | B59: Service gratuit 2 | E59: =+SUM(H59,K59,N59,Q59,T59,W59,Z59,AC59,AF59,AI59,AL59,AO59) -> 0 | H59: =[1]DEPA!$C$32 -> 0 | K59: =[1]DEPA!$D$32 -> 0 | N59: =[1]DEPA!$E$32 -> 0 | Q59: =[1]DEPA!$F$32 -> 0 | T59: =[1]DEPA!$G$32 -> 0 | W59: =[1]DEPA!$H$32 -> 0 | Z59: =[1]DEPA!$I$32 -> 0 | AC59: =[1]DEPA!$J$32 -> 0 | AF59: =[1]DEPA!$K$32 -> 0 | AI59: =[1]DEPA!$L$32 -> 0 | AL59: =[1]DEPA!$M$32 -> 0 | AO59: =[1]DEPA!$N$32 -> 0
A60: =+$C$4&B60 -> Véhicules neufsFrais véhicules de cie | B60: Frais véhicules de cie | E60: =+SUM(H60,K60,N60,Q60,T60,W60,Z60,AC60,AF60,AI60,AL60,AO60) -> 107430.58 | H60: =[1]DEPA!$C$41 -> 8952.5479 | K60: =[1]DEPA!$D$41 -> 8952.5479 | N60: =[1]DEPA!$E$41 -> 8952.5479 | Q60: =[1]DEPA!$F$41 -> 8952.5479 | T60: =[1]DEPA!$G$41 -> 8952.5479 | W60: =[1]DEPA!$H$41 -> 8952.5479 | Z60: =[1]DEPA!$I$41 -> 8952.5479 | AC60: =[1]DEPA!$J$41 -> 8952.5479 | AF60: =[1]DEPA!$K$41 -> 8952.5479 | AI60: =[1]DEPA!$L$41 -> 8952.5479 | AL60: =[1]DEPA!$M$41 -> 8952.5479 | AO60: =[1]DEPA!$N$41 -> 8952.5479
A61: =+$C$4&B61 -> Véhicules neufsInformatique | B61: Informatique | E61: =+SUM(H61,K61,N61,Q61,T61,W61,Z61,AC61,AF61,AI61,AL61,AO61) -> 83784 | H61: =[1]DEPA!$C$55 -> 10194 | K61: =[1]DEPA!$D$55 -> 6690 | N61: =[1]DEPA!$E$55 -> 6690 | Q61: =[1]DEPA!$F$55 -> 6690 | T61: =[1]DEPA!$G$55 -> 6690 | W61: =[1]DEPA!$H$55 -> 6690 | Z61: =[1]DEPA!$I$55 -> 6690 | AC61: =[1]DEPA!$J$55 -> 6690 | AF61: =[1]DEPA!$K$55 -> 6690 | AI61: =[1]DEPA!$L$55 -> 6690 | AL61: =[1]DEPA!$M$55 -> 6690 | AO61: =[1]DEPA!$N$55 -> 6690
A62: =+$C$4&B62 -> Véhicules neufsFrais de déplacement | B62: Frais de déplacement | E62: =+SUM(H62,K62,N62,Q62,T62,W62,Z62,AC62,AF62,AI62,AL62,AO62) -> 18000 | H62: =[1]DEPA!$C$75 -> 1500 | K62: =[1]DEPA!$D$75 -> 1500 | N62: =[1]DEPA!$E$75 -> 1500 | Q62: =[1]DEPA!$F$75 -> 1500 | T62: =[1]DEPA!$G$75 -> 1500 | W62: =[1]DEPA!$H$75 -> 1500 | Z62: =[1]DEPA!$I$75 -> 1500 | AC62: =[1]DEPA!$J$75 -> 1500 | AF62: =[1]DEPA!$K$75 -> 1500 | AI62: =[1]DEPA!$L$75 -> 1500 | AL62: =[1]DEPA!$M$75 -> 1500 | AO62: =[1]DEPA!$N$75 -> 1500
A63: =+$C$4&B63 -> Véhicules neufsServices extérieurs | B63: Services extérieurs | E63: =+SUM(H63,K63,N63,Q63,T63,W63,Z63,AC63,AF63,AI63,AL63,AO63) -> 55389.44 | H63: =[1]DEPA!$C$84 -> 5549.12 | K63: =[1]DEPA!$D$84 -> 4109.12 | N63: =[1]DEPA!$E$84 -> 3629.12 | Q63: =[1]DEPA!$F$84 -> 3629.12 | T63: =[1]DEPA!$G$84 -> 3629.12 | W63: =[1]DEPA!$H$84 -> 4909.12 | Z63: =[1]DEPA!$I$84 -> 3629.12 | AC63: =[1]DEPA!$J$84 -> 3629.12 | AF63: =[1]DEPA!$K$84 -> 3629.12 | AI63: =[1]DEPA!$L$84 -> 4589.12 | AL63: =[1]DEPA!$M$84 -> 5549.12 | AO63: =[1]DEPA!$N$84 -> 8909.12
A64: =+$C$4&B64 -> Véhicules neufsFournitures autres | B64: Fournitures autres | E64: =+SUM(H64,K64,N64,Q64,T64,W64,Z64,AC64,AF64,AI64,AL64,AO64) -> 840 | H64: =[1]DEPA!$C$113 -> 70 | K64: =[1]DEPA!$D$113 -> 70 | N64: =[1]DEPA!$E$113 -> 70 | Q64: =[1]DEPA!$F$113 -> 70 | T64: =[1]DEPA!$G$113 -> 70 | W64: =[1]DEPA!$H$113 -> 70 | Z64: =[1]DEPA!$I$113 -> 70 | AC64: =[1]DEPA!$J$113 -> 70 | AF64: =[1]DEPA!$K$113 -> 70 | AI64: =[1]DEPA!$L$113 -> 70 | AL64: =[1]DEPA!$M$113 -> 70 | AO64: =[1]DEPA!$N$113 -> 70
A65: =+$C$4&B65 -> Véhicules neufsUniformes | B65: Uniformes | E65: =+SUM(H65,K65,N65,Q65,T65,W65,Z65,AC65,AF65,AI65,AL65,AO65) -> 0 | H65: =[1]DEPA!$C$122 -> 0 | K65: =[1]DEPA!$D$122 -> 0 | N65: =[1]DEPA!$E$122 -> 0 | Q65: =[1]DEPA!$F$122 -> 0 | T65: =[1]DEPA!$G$122 -> 0 | W65: =[1]DEPA!$H$122 -> 0 | Z65: =[1]DEPA!$I$122 -> 0 | AC65: =[1]DEPA!$J$122 -> 0 | AF65: =[1]DEPA!$K$122 -> 0 | AI65: =[1]DEPA!$L$122 -> 0 | AL65: =[1]DEPA!$M$122 -> 0 | AO65: =[1]DEPA!$N$122 -> 0
A66: =+$C$4&B66 -> Véhicules neufsPapeterie | B66: Papeterie | E66: =+SUM(H66,K66,N66,Q66,T66,W66,Z66,AC66,AF66,AI66,AL66,AO66) -> 7140 | H66: =[1]DEPA!$C$131 -> 595 | K66: =[1]DEPA!$D$131 -> 595 | N66: =[1]DEPA!$E$131 -> 595 | Q66: =[1]DEPA!$F$131 -> 595 | T66: =[1]DEPA!$G$131 -> 595 | W66: =[1]DEPA!$H$131 -> 595 | Z66: =[1]DEPA!$I$131 -> 595 | AC66: =[1]DEPA!$J$131 -> 595 | AF66: =[1]DEPA!$K$131 -> 595 | AI66: =[1]DEPA!$L$131 -> 595 | AL66: =[1]DEPA!$M$131 -> 595 | AO66: =[1]DEPA!$N$131 -> 595
A67: =+$C$4&B67 -> Véhicules neufsTéléphone | B67: Téléphone | E67: =+SUM(H67,K67,N67,Q67,T67,W67,Z67,AC67,AF67,AI67,AL67,AO67) -> 5250 | H67: =[1]DEPA!$C$140 -> 437.5 | K67: =[1]DEPA!$D$140 -> 437.5 | N67: =[1]DEPA!$E$140 -> 437.5 | Q67: =[1]DEPA!$F$140 -> 437.5 | T67: =[1]DEPA!$G$140 -> 437.5 | W67: =[1]DEPA!$H$140 -> 437.5 | Z67: =[1]DEPA!$I$140 -> 437.5 | AC67: =[1]DEPA!$J$140 -> 437.5 | AF67: =[1]DEPA!$K$140 -> 437.5 | AI67: =[1]DEPA!$L$140 -> 437.5 | AL67: =[1]DEPA!$M$140 -> 437.5 | AO67: =[1]DEPA!$N$140 -> 437.5
A68: =+$C$4&B68 -> Véhicules neufsFrais postaux | B68: Frais postaux | E68: =+SUM(H68,K68,N68,Q68,T68,W68,Z68,AC68,AF68,AI68,AL68,AO68) -> 2735.04 | H68: =[1]DEPA!$C$149 -> 227.92 | K68: =[1]DEPA!$D$149 -> 227.92 | N68: =[1]DEPA!$E$149 -> 227.92 | Q68: =[1]DEPA!$F$149 -> 227.92 | T68: =[1]DEPA!$G$149 -> 227.92 | W68: =[1]DEPA!$H$149 -> 227.92 | Z68: =[1]DEPA!$I$149 -> 227.92 | AC68: =[1]DEPA!$J$149 -> 227.92 | AF68: =[1]DEPA!$K$149 -> 227.92 | AI68: =[1]DEPA!$L$149 -> 227.92 | AL68: =[1]DEPA!$M$149 -> 227.92 | AO68: =[1]DEPA!$N$149 -> 227.92
A69: =+$C$4&B69 -> Véhicules neufsDivers | B69: Divers | E69: =+SUM(H69,K69,N69,Q69,T69,W69,Z69,AC69,AF69,AI69,AL69,AO69) -> 1440 | H69: =[1]DEPA!$C$158 -> 120 | K69: =[1]DEPA!$D$158 -> 120 | N69: =[1]DEPA!$E$158 -> 120 | Q69: =[1]DEPA!$F$158 -> 120 | T69: =[1]DEPA!$G$158 -> 120 | W69: =[1]DEPA!$H$158 -> 120 | Z69: =[1]DEPA!$I$158 -> 120 | AC69: =[1]DEPA!$J$158 -> 120 | AF69: =[1]DEPA!$K$158 -> 120 | AI69: =[1]DEPA!$L$158 -> 120 | AL69: =[1]DEPA!$M$158 -> 120 | AO69: =[1]DEPA!$N$158 -> 120
A70: =+$C$4&B70 -> Véhicules neufsFormation | B70: Formation | E70: =+SUM(H70,K70,N70,Q70,T70,W70,Z70,AC70,AF70,AI70,AL70,AO70) -> 23000 | H70: =[1]DEPA!$C$169 -> 1916.6667 | K70: =[1]DEPA!$D$169 -> 1916.6667 | N70: =[1]DEPA!$E$169 -> 1916.6667 | Q70: =[1]DEPA!$F$169 -> 1916.6667 | T70: =[1]DEPA!$G$169 -> 1916.6667 | W70: =[1]DEPA!$H$169 -> 1916.6667 | Z70: =[1]DEPA!$I$169 -> 1916.6667 | AC70: =[1]DEPA!$J$169 -> 1916.6667 | AF70: =[1]DEPA!$K$169 -> 1916.6667 | AI70: =[1]DEPA!$L$169 -> 1916.6667 | AL70: =[1]DEPA!$M$169 -> 1916.6667 | AO70: =[1]DEPA!$N$169 -> 1916.6667
A71: =+$C$4&B71 -> Véhicules neufsFrais bancaires | B71: Frais bancaires | E71: =+SUM(H71,K71,N71,Q71,T71,W71,Z71,AC71,AF71,AI71,AL71,AO71) -> 43967.389 | H71: =[1]DEPA!$C$181 -> 2814.8933 | K71: =[1]DEPA!$D$181 -> 2848.5113 | N71: =[1]DEPA!$E$181 -> 3886.426 | Q71: =[1]DEPA!$F$181 -> 4126.9454 | T71: =[1]DEPA!$G$181 -> 4393.2605 | W71: =[1]DEPA!$H$181 -> 3970.1321 | Z71: =[1]DEPA!$I$181 -> 3764.2586 | AC71: =[1]DEPA!$J$181 -> 3649.3022 | AF71: =[1]DEPA!$K$181 -> 3805.8496 | AI71: =[1]DEPA!$L$181 -> 3815.2392 | AL71: =[1]DEPA!$M$181 -> 3943.546 | AO71: =[1]DEPA!$N$181 -> 2949.0246
A72: =+$C$4&B72 -> Véhicules neufs[...] | B72: [...] | E72: =+SUM(H72,K72,N72,Q72,T72,W72,Z72,AC72,AF72,AI72,AL72,AO72) -> 0
A73: =+$C$4&B73 -> Véhicules neufs[...] | B73: [...] | E73: =+SUM(H73,K73,N73,Q73,T73,W73,Z73,AC73,AF73,AI73,AL73,AO73) -> 0
A74: =+$C$4&B74 -> Véhicules neufs[...] | B74: [...] | E74: =+SUM(H74,K74,N74,Q74,T74,W74,Z74,AC74,AF74,AI74,AL74,AO74) -> 0
A75: =+$C$4&B75 -> Véhicules neufsTOTAL SEMI-FIXES | B75: TOTAL SEMI-FIXES | C75: % brut | D75: =IFERROR(E75/E$30,0) -> 0.13094712 | E75: =+SUM(E58:E74) -> 348976.44 | F75: % brut | G75: =IFERROR(H75/H$30,0) -> 0.18366218 | H75: =+SUM(H58:H74) -> 32377.648 | I75: % brut | J75: =IFERROR(K75/K$30,0) -> 0.14575318 | K75: =+SUM(K58:K74) -> 27467.266 | L75: % brut | M75: =IFERROR(N75/N$30,0) -> 0.10266039 | N75: =+SUM(N58:N74) -> 28025.181 | O75: % brut | P75: =IFERROR(Q75/Q$30,0) -> 0.10099731 | Q75: =+SUM(Q58:Q74) -> 28265.7 | R75: % brut | S75: =IFERROR(T75/T$30,0) -> 0.098140374 | T75: =+SUM(T58:T74) -> 28532.015 | U75: % brut | V75: =IFERROR(W75/W$30,0) -> 0.11211632 | W75: =+SUM(W58:W74) -> 29388.887 | X75: % brut | Y75: =IFERROR(Z75/Z$30,0) -> 0.11860037 | Z75: =+SUM(Z58:Z74) -> 27903.013 | AA75: % brut | AB75: =IFERROR(AC75/AC$30,0) -> 0.12984516 | AC75: =+SUM(AC58:AC74) -> 27788.057 | AD75: % brut | AE75: =IFERROR(AF75/AF$30,0) -> 0.1350074 | AF75: =+SUM(AF58:AF74) -> 27944.604 | AG75: % brut | AH75: =IFERROR(AI75/AI$30,0) -> 0.14232936 | AI75: =+SUM(AI58:AI74) -> 28913.994 | AJ75: % brut | AK75: =IFERROR(AL75/AL$30,0) -> 0.1665625 | AL75: =+SUM(AL58:AL74) -> 30002.301 | AM75: % brut | AN75: =IFERROR(AO75/AO$30,0) -> 0.20878512 | AO75: =+SUM(AO58:AO74) -> 32367.779
A76: =+$C$4&B76 -> Véhicules neufs
A77: =+$C$4&B77 -> Véhicules neufsTOTAL DES DÉPENSES | B77: TOTAL DES DÉPENSES | C77: % brut | D77: =IFERROR(E77/E$30,0) -> 0.93607167 | E77: =E44+E57+E75 -> 2494647.8 | F77: % brut | G77: =IFERROR(H77/H$30,0) -> 1.112777 | H77: =H44+H57+H75 -> 196170.51 | I77: % brut | J77: =IFERROR(K77/K$30,0) -> 0.97669987 | K77: =K44+K57+K75 -> 184059.62 | L77: % brut | M77: =IFERROR(N77/N$30,0) -> 0.79988861 | N77: =N44+N57+N75 -> 218360.98 | O77: % brut | P77: =IFERROR(Q77/Q$30,0) -> 0.83816397 | Q77: =Q44+Q57+Q75 -> 234573.49 | R77: % brut | S77: =IFERROR(T77/T$30,0) -> 0.82090405 | T77: =T44+T57+T75 -> 238658.63 | U77: % brut | V77: =IFERROR(W77/W$30,0) -> 0.81036101 | W77: =W44+W57+W75 -> 212418.74 | X77: % brut | Y77: =IFERROR(Z77/Z$30,0) -> 0.9104492 | Z77: =Z44+Z57+Z75 -> 214200.65 | AA77: % brut | AB77: =IFERROR(AC77/AC$30,0) -> 0.92339611 | AC77: =AC44+AC57+AC75 -> 197615.25 | AD77: % brut | AE77: =IFERROR(AF77/AF$30,0) -> 0.94799156 | AF77: =AF44+AF57+AF75 -> 196220.71 | AG77: % brut | AH77: =IFERROR(AI77/AI$30,0) -> 1.030334 | AI77: =AI44+AI57+AI75 -> 209310.79 | AJ77: % brut | AK77: =IFERROR(AL77/AL$30,0) -> 1.1396129 | AL77: =AL44+AL57+AL75 -> 205274.34 | AM77: % brut | AN77: =IFERROR(AO77/AO$30,0) -> 1.2112829 | AO77: =AO44+AO57+AO75 -> 187784.15
A78: =+$C$4&B78 -> Véhicules neufsProgramme neuf 1 | B78: Programme neuf 1 | E78: =+SUM(H78,K78,N78,Q78,T78,W78,Z78,AC78,AF78,AI78,AL78,AO78) -> 140000 | H78: ='[1]Vehicules neuf 2026'!E67 -> 0 | K78: ='[1]Vehicules neuf 2026'!F67 -> 0 | N78: ='[1]Vehicules neuf 2026'!G67 -> 35000 | Q78: ='[1]Vehicules neuf 2026'!H67 -> 0 | T78: ='[1]Vehicules neuf 2026'!I67 -> 0 | W78: ='[1]Vehicules neuf 2026'!J67 -> 35000 | Z78: ='[1]Vehicules neuf 2026'!K67 -> 0 | AC78: ='[1]Vehicules neuf 2026'!L67 -> 0 | AF78: ='[1]Vehicules neuf 2026'!M67 -> 35000 | AI78: ='[1]Vehicules neuf 2026'!N67 -> 0 | AL78: ='[1]Vehicules neuf 2026'!O67 -> 0 | AO78: ='[1]Vehicules neuf 2026'!P67 -> 35000
A79: =+$C$4&B79 -> Véhicules neufsProgramme neuf 2 | B79: Programme neuf 2 | E79: =+SUM(H79,K79,N79,Q79,T79,W79,Z79,AC79,AF79,AI79,AL79,AO79) -> 0
A80: =+$C$4&B80 -> Véhicules neufsProgramme neuf 3 | B80: Programme neuf 3 | E80: =+SUM(H80,K80,N80,Q80,T80,W80,Z80,AC80,AF80,AI80,AL80,AO80) -> 0
A81: =+$C$4&B81 -> Véhicules neufsHoldbacks | B81: Holdbacks | E81: =+SUM(H81,K81,N81,Q81,T81,W81,Z81,AC81,AF81,AI81,AL81,AO81) -> 971329 | H81: ='[1]Vehicules neuf 2026'!E65 -> 62754.402 | K81: ='[1]Vehicules neuf 2026'!F65 -> 68211.306 | N81: ='[1]Vehicules neuf 2026'!G65 -> 100952.73 | Q81: ='[1]Vehicules neuf 2026'!H65 -> 103681.19 | T81: ='[1]Vehicules neuf 2026'!I65 -> 107773.86 | W81: ='[1]Vehicules neuf 2026'!J65 -> 96860.055 | Z81: ='[1]Vehicules neuf 2026'!K65 -> 85946.246 | AC81: ='[1]Vehicules neuf 2026'!L65 -> 77760.889 | AF81: ='[1]Vehicules neuf 2026'!M65 -> 75032.437 | AI81: ='[1]Vehicules neuf 2026'!N65 -> 73668.211 | AL81: ='[1]Vehicules neuf 2026'!O65 -> 64118.628 | AO81: ='[1]Vehicules neuf 2026'!P65 -> 54569.045
A82: =+$C$4&B82 -> Véhicules neufs[...] | B82: [...] | E82: =+SUM(H82,K82,N82,Q82,T82,W82,Z82,AC82,AF82,AI82,AL82,AO82) -> 0
A83: =+$C$4&B83 -> Véhicules neufs[...] | B83: [...] | E83: =+SUM(H83,K83,N83,Q83,T83,W83,Z83,AC83,AF83,AI83,AL83,AO83) -> 0
A84: =+$C$4&B84 -> Véhicules neufs[...] | B84: [...] | E84: =+SUM(H84,K84,N84,Q84,T84,W84,Z84,AC84,AF84,AI84,AL84,AO84) -> 0
A85: =+$C$4&B85 -> Véhicules neufsFrais administration | B85: Frais administration | E85: =+SUM(H85,K85,N85,Q85,T85,W85,Z85,AC85,AF85,AI85,AL85,AO85) -> 329001.15 | H85: ='[1]Vehicules neuf 2026'!E64 -> 21842.4 | K85: ='[1]Vehicules neuf 2026'!F64 -> 23207.55 | N85: ='[1]Vehicules neuf 2026'!G64 -> 33673.7 | Q85: ='[1]Vehicules neuf 2026'!H64 -> 34583.8 | T85: ='[1]Vehicules neuf 2026'!I64 -> 35948.95 | W85: ='[1]Vehicules neuf 2026'!J64 -> 32308.55 | Z85: ='[1]Vehicules neuf 2026'!K64 -> 29123.2 | AC85: ='[1]Vehicules neuf 2026'!L64 -> 26392.9 | AF85: ='[1]Vehicules neuf 2026'!M64 -> 25482.8 | AI85: ='[1]Vehicules neuf 2026'!N64 -> 25027.75 | AL85: ='[1]Vehicules neuf 2026'!O64 -> 22297.45 | AO85: ='[1]Vehicules neuf 2026'!P64 -> 19112.1
A86: =+$C$4&B86 -> Véhicules neufsAUTRES REVENUS | B86: AUTRES REVENUS | E86: =+SUM(E78:E85) -> 1440330.2 | H86: =+SUM(H78:H85) -> 84596.802 | K86: =+SUM(K78:K85) -> 91418.856 | N86: =+SUM(N78:N85) -> 169626.43 | Q86: =+SUM(Q78:Q85) -> 138264.99 | T86: =+SUM(T78:T85) -> 143722.81 | W86: =+SUM(W78:W85) -> 164168.61 | Z86: =+SUM(Z78:Z85) -> 115069.45 | AC86: =+SUM(AC78:AC85) -> 104153.79 | AF86: =+SUM(AF78:AF85) -> 135515.24 | AI86: =+SUM(AI78:AI85) -> 98695.961 | AL86: =+SUM(AL78:AL85) -> 86416.078 | AO86: =+SUM(AO78:AO85) -> 108681.15
A87: =+$C$4&B87 -> Véhicules neufs
A88: =+$C$4&B88 -> Véhicules neufsPROFIT DÉPARTEMENTAL | B88: PROFIT DÉPARTEMENTAL | D88: =E88/E8 -> 0.044758874 | E88: =E30-E77+E86 -> 1610700.3 | H88: =H30-H77+H86 -> 64715.437 | K88: =K30-K77+K86 -> 95809.779 | N88: =N30-N77+N86 -> 224254.69 | Q88: =Q30-Q77+Q86 -> 183557.37 | T88: =T30-T77+T86 -> 195790.77 | W88: =W30-W77+W86 -> 213878.4 | Z88: =Z30-Z77+Z86 -> 136137.99 | AC88: =AC30-AC77+AC86 -> 120547.73 | AF88: =AF30-AF77+AF86 -> 146280.24 | AI88: =AI30-AI77+AI86 -> 92533.654 | AL88: =AL30-AL77+AL86 -> 61268.116 | AO88: =AO30-AO77+AO86 -> 75926.144
B92: =B4 -> Budget 2025 | C92: Véhicules usagés
B94: Mois | C94: 2021 | F94: Janvier | I94: Février | L94: Mars | O94: Avril | R94: Mai | U94: Juin | X94: Juillet | AA94: Août | AD94: Septembre | AG94: Octobre | AJ94: Novembre | AM94: Décembre
C95: UNITE | D95: $P/UNITE | E95: $PROFITS | F95: UNITE | G95: $P/UNITE | H95: $PROFITS | I95: UNITE | J95: $P/UNITE | K95: $PROFITS | L95: UNITE | M95: $P/UNITE | N95: $PROFITS | O95: UNITE | P95: $P/UNITE | Q95: $PROFITS | R95: UNITE | S95: $P/UNITE | T95: $PROFITS | U95: UNITE | V95: $P/UNITE | W95: $PROFITS | X95: UNITE | Y95: $P/UNITE | Z95: $PROFITS | AA95: UNITE | AB95: $P/UNITE | AC95: $PROFITS | AD95: UNITE | AE95: $P/UNITE | AF95: $PROFITS | AG95: UNITE | AH95: $P/UNITE | AI95: $PROFITS | AJ95: UNITE | AK95: $P/UNITE | AL95: $PROFITS | AM95: UNITE | AN95: $P/UNITE | AO95: $PROFITS
A96: =+$C$92&B96 -> Véhicules usagésVentes nettes | B96: Ventes nettes | E96: =+SUM(H96,K96,N96,Q96,T96,W96,Z96,AC96,AF96,AI96,AL96,AO96) -> 18503608 | H96: ='[1]Vehicules usages 2026'!E49 -> 1039006.6 | K96: ='[1]Vehicules usages 2026'!F49 -> 948717.2 | N96: ='[1]Vehicules usages 2026'!G49 -> 1332498.5 | Q96: ='[1]Vehicules usages 2026'!H49 -> 1484291.2 | T96: ='[1]Vehicules usages 2026'!I49 -> 1643017.4 | W96: ='[1]Vehicules usages 2026'!J49 -> 1874492 | Z96: ='[1]Vehicules usages 2026'!K49 -> 1897814.9 | AC96: ='[1]Vehicules usages 2026'!L49 -> 1852382.3 | AF96: ='[1]Vehicules usages 2026'!M49 -> 1682729.8 | AI96: ='[1]Vehicules usages 2026'!N49 -> 1857845.5 | AL96: ='[1]Vehicules usages 2026'!O49 -> 1552789.7 | AO96: ='[1]Vehicules usages 2026'!P49 -> 1338023.4
A97: =+$C$92&B97 -> Véhicules usagésCertifié | B97: Certifié | C97: =+SUM(F97,I97,L97,O97,R97,U97,X97,AA97,AD97,AG97,AJ97,AM97) -> 329 | D97: =IF(C97=0,0,E97/C97) -> 1500 | E97: =+SUM(H97,K97,N97,Q97,T97,W97,Z97,AC97,AF97,AI97,AL97,AO97) -> 493500 | F97: ='[1]Vehicules usages 2026'!E18 -> 20 | G97: =IF(F97=0,0,H97/F97) -> 1500 | H97: ='[1]Vehicules usages 2026'!E40 -> 30000 | I97: ='[1]Vehicules usages 2026'!F18 -> 21 | J97: =IF(I97=0,0,K97/I97) -> 1500 | K97: ='[1]Vehicules usages 2026'!F40 -> 31500 | L97: ='[1]Vehicules usages 2026'!G18 -> 31 | M97: =IF(L97=0,0,N97/L97) -> 1500 | N97: ='[1]Vehicules usages 2026'!G40 -> 46500 | O97: ='[1]Vehicules usages 2026'!H18 -> 31 | P97: =IF(O97=0,0,Q97/O97) -> 1500 | Q97: ='[1]Vehicules usages 2026'!H40 -> 46500 | R97: ='[1]Vehicules usages 2026'!I18 -> 33 | S97: =IF(R97=0,0,T97/R97) -> 1500 | T97: ='[1]Vehicules usages 2026'!I40 -> 49500 | U97: ='[1]Vehicules usages 2026'!J18 -> 31 | V97: =IF(U97=0,0,W97/U97) -> 1500 | W97: ='[1]Vehicules usages 2026'!J40 -> 46500 | X97: ='[1]Vehicules usages 2026'!K18 -> 30 | Y97: =IF(X97=0,0,Z97/X97) -> 1500 | Z97: ='[1]Vehicules usages 2026'!K40 -> 45000 | AA97: ='[1]Vehicules usages 2026'!L18 -> 29 | AB97: =IF(AA97=0,0,AC97/AA97) -> 1500 | AC97: ='[1]Vehicules usages 2026'!L40 -> 43500 | AD97: ='[1]Vehicules usages 2026'!M18 -> 29 | AE97: =IF(AD97=0,0,AF97/AD97) -> 1500 | AF97: ='[1]Vehicules usages 2026'!M40 -> 43500 | AG97: ='[1]Vehicules usages 2026'!N18 -> 28 | AH97: =IF(AG97=0,0,AI97/AG97) -> 1500 | AI97: ='[1]Vehicules usages 2026'!N40 -> 42000 | AJ97: ='[1]Vehicules usages 2026'!O18 -> 25 | AK97: =IF(AJ97=0,0,AL97/AJ97) -> 1500 | AL97: ='[1]Vehicules usages 2026'!O40 -> 37500 | AM97: ='[1]Vehicules usages 2026'!P18 -> 21 | AN97: =IF(AM97=0,0,AO97/AM97) -> 1500 | AO97: ='[1]Vehicules usages 2026'!P40 -> 31500
A98: =+$C$92&B98 -> Véhicules usagésNon Certifié | B98: Non Certifié | C98: =+SUM(F98,I98,L98,O98,R98,U98,X98,AA98,AD98,AG98,AJ98,AM98) -> 102 | D98: =IF(C98=0,0,E98/C98) -> 1500 | E98: =+SUM(H98,K98,N98,Q98,T98,W98,Z98,AC98,AF98,AI98,AL98,AO98) -> 153000 | F98: ='[1]Vehicules usages 2026'!E19 -> 6 | G98: =IF(F98=0,0,H98/F98) -> 1500 | H98: ='[1]Vehicules usages 2026'!E42 -> 9000 | I98: ='[1]Vehicules usages 2026'!F19 -> 6 | J98: =IF(I98=0,0,K98/I98) -> 1500 | K98: ='[1]Vehicules usages 2026'!F42 -> 9000 | L98: ='[1]Vehicules usages 2026'!G19 -> 9 | M98: =IF(L98=0,0,N98/L98) -> 1500 | N98: ='[1]Vehicules usages 2026'!G42 -> 13500 | O98: ='[1]Vehicules usages 2026'!H19 -> 10 | P98: =IF(O98=0,0,Q98/O98) -> 1500 | Q98: ='[1]Vehicules usages 2026'!H42 -> 15000 | R98: ='[1]Vehicules usages 2026'!I19 -> 10 | S98: =IF(R98=0,0,T98/R98) -> 1500 | T98: ='[1]Vehicules usages 2026'!I42 -> 15000 | U98: ='[1]Vehicules usages 2026'!J19 -> 10 | V98: =IF(U98=0,0,W98/U98) -> 1500 | W98: ='[1]Vehicules usages 2026'!J42 -> 15000 | X98: ='[1]Vehicules usages 2026'!K19 -> 9 | Y98: =IF(X98=0,0,Z98/X98) -> 1500 | Z98: ='[1]Vehicules usages 2026'!K42 -> 13500 | AA98: ='[1]Vehicules usages 2026'!L19 -> 9 | AB98: =IF(AA98=0,0,AC98/AA98) -> 1500 | AC98: ='[1]Vehicules usages 2026'!L42 -> 13500 | AD98: ='[1]Vehicules usages 2026'!M19 -> 9 | AE98: =IF(AD98=0,0,AF98/AD98) -> 1500 | AF98: ='[1]Vehicules usages 2026'!M42 -> 13500 | AG98: ='[1]Vehicules usages 2026'!N19 -> 9 | AH98: =IF(AG98=0,0,AI98/AG98) -> 1500 | AI98: ='[1]Vehicules usages 2026'!N42 -> 13500 | AJ98: ='[1]Vehicules usages 2026'!O19 -> 8 | AK98: =IF(AJ98=0,0,AL98/AJ98) -> 1500 | AL98: ='[1]Vehicules usages 2026'!O42 -> 12000 | AM98: ='[1]Vehicules usages 2026'!P19 -> 7 | AN98: =IF(AM98=0,0,AO98/AM98) -> 1500 | AO98: ='[1]Vehicules usages 2026'!P42 -> 10500
A99: =+$C$92&B99 -> Véhicules usagésAutres Marques | B99: Autres Marques | C99: =+SUM(F99,I99,L99,O99,R99,U99,X99,AA99,AD99,AG99,AJ99,AM99) -> 102 | D99: =IF(C99=0,0,E99/C99) -> 1500 | E99: =+SUM(H99,K99,N99,Q99,T99,W99,Z99,AC99,AF99,AI99,AL99,AO99) -> 153000 | F99: ='[1]Vehicules usages 2026'!E20 -> 6 | G99: =IF(F99=0,0,H99/F99) -> 1500 | H99: ='[1]Vehicules usages 2026'!E44 -> 9000 | I99: ='[1]Vehicules usages 2026'!F20 -> 6 | J99: =IF(I99=0,0,K99/I99) -> 1500 | K99: ='[1]Vehicules usages 2026'!F44 -> 9000 | L99: ='[1]Vehicules usages 2026'!G20 -> 9 | M99: =IF(L99=0,0,N99/L99) -> 1500 | N99: ='[1]Vehicules usages 2026'!G44 -> 13500 | O99: ='[1]Vehicules usages 2026'!H20 -> 10 | P99: =IF(O99=0,0,Q99/O99) -> 1500 | Q99: ='[1]Vehicules usages 2026'!H44 -> 15000 | R99: ='[1]Vehicules usages 2026'!I20 -> 10 | S99: =IF(R99=0,0,T99/R99) -> 1500 | T99: ='[1]Vehicules usages 2026'!I44 -> 15000 | U99: ='[1]Vehicules usages 2026'!J20 -> 10 | V99: =IF(U99=0,0,W99/U99) -> 1500 | W99: ='[1]Vehicules usages 2026'!J44 -> 15000 | X99: ='[1]Vehicules usages 2026'!K20 -> 9 | Y99: =IF(X99=0,0,Z99/X99) -> 1500 | Z99: ='[1]Vehicules usages 2026'!K44 -> 13500 | AA99: ='[1]Vehicules usages 2026'!L20 -> 9 | AB99: =IF(AA99=0,0,AC99/AA99) -> 1500 | AC99: ='[1]Vehicules usages 2026'!L44 -> 13500 | AD99: ='[1]Vehicules usages 2026'!M20 -> 9 | AE99: =IF(AD99=0,0,AF99/AD99) -> 1500 | AF99: ='[1]Vehicules usages 2026'!M44 -> 13500 | AG99: ='[1]Vehicules usages 2026'!N20 -> 9 | AH99: =IF(AG99=0,0,AI99/AG99) -> 1500 | AI99: ='[1]Vehicules usages 2026'!N44 -> 13500 | AJ99: ='[1]Vehicules usages 2026'!O20 -> 8 | AK99: =IF(AJ99=0,0,AL99/AJ99) -> 1500 | AL99: ='[1]Vehicules usages 2026'!O44 -> 12000 | AM99: ='[1]Vehicules usages 2026'!P20 -> 7 | AN99: =IF(AM99=0,0,AO99/AM99) -> 1500 | AO99: ='[1]Vehicules usages 2026'!P44 -> 10500
A100: =+$C$92&B100 -> Véhicules usagésTotal Usagés | B100: Total Usagés | C100: =+C97+C98+C99 -> 533 | D100: =IF(C100<=0,0,E100/C100) -> 1500 | E100: =+E97+E98+E99 -> 799500 | F100: =+F97+F98+F99 -> 32 | G100: =IF(F100<=0,0,H100/F100) -> 1500 | H100: =+H97+H98+H99 -> 48000 | I100: =+I97+I98+I99 -> 33 | J100: =IF(I100<=0,0,K100/I100) -> 1500 | K100: =+K97+K98+K99 -> 49500 | L100: =+L97+L98+L99 -> 49 | M100: =IF(L100<=0,0,N100/L100) -> 1500 | N100: =+N97+N98+N99 -> 73500 | O100: =+O97+O98+O99 -> 51 | P100: =IF(O100<=0,0,Q100/O100) -> 1500 | Q100: =+Q97+Q98+Q99 -> 76500 | R100: =+R97+R98+R99 -> 53 | S100: =IF(R100<=0,0,T100/R100) -> 1500 | T100: =+T97+T98+T99 -> 79500 | U100: =+U97+U98+U99 -> 51 | V100: =IF(U100<=0,0,W100/U100) -> 1500 | W100: =+W97+W98+W99 -> 76500 | X100: =+X97+X98+X99 -> 48 | Y100: =IF(X100<=0,0,Z100/X100) -> 1500 | Z100: =+Z97+Z98+Z99 -> 72000 | AA100: =+AA97+AA98+AA99 -> 47 | AB100: =IF(AA100<=0,0,AC100/AA100) -> 1500 | AC100: =+AC97+AC98+AC99 -> 70500 | AD100: =+AD97+AD98+AD99 -> 47 | AE100: =IF(AD100<=0,0,AF100/AD100) -> 1500 | AF100: =+AF97+AF98+AF99 -> 70500 | AG100: =+AG97+AG98+AG99 -> 46 | AH100: =IF(AG100<=0,0,AI100/AG100) -> 1500 | AI100: =+AI97+AI98+AI99 -> 69000 | AJ100: =+AJ97+AJ98+AJ99 -> 41 | AK100: =IF(AJ100<=0,0,AL100/AJ100) -> 1500 | AL100: =+AL97+AL98+AL99 -> 61500 | AM100: =+AM97+AM98+AM99 -> 35 | AN100: =IF(AM100<=0,0,AO100/AM100) -> 1500 | AO100: =+AO97+AO98+AO99 -> 52500
A101: =+$C$92&B101 -> Véhicules usagés
A102: =+$C$92&B102 -> Véhicules usagés
A103: =+$C$92&B103 -> Véhicules usagésVentes au Gros | B103: Ventes au Gros | C103: =+SUM(F103,I103,L103,O103,R103,U103,X103,AA103,AD103,AG103,AJ103,AM103) -> 340 | D103: =IF(C103=0,0,E103/C103) -> 500 | E103: =+SUM(H103,K103,N103,Q103,T103,W103,Z103,AC103,AF103,AI103,AL103,AO103) -> 170000 | F103: ='[1]Vehicules usages 2026'!E21 -> 16 | G103: =IF(F103=0,0,H103/F103) -> 500 | H103: ='[1]Vehicules usages 2026'!E46 -> 8000 | I103: ='[1]Vehicules usages 2026'!F21 -> 9 | J103: =IF(I103=0,0,K103/I103) -> 500 | K103: ='[1]Vehicules usages 2026'!F46 -> 4500 | L103: ='[1]Vehicules usages 2026'!G21 -> 9 | M103: =IF(L103=0,0,N103/L103) -> 500 | N103: ='[1]Vehicules usages 2026'!G46 -> 4500 | O103: ='[1]Vehicules usages 2026'!H21 -> 16 | P103: =IF(O103=0,0,Q103/O103) -> 500 | Q103: ='[1]Vehicules usages 2026'!H46 -> 8000 | R103: ='[1]Vehicules usages 2026'!I21 -> 22 | S103: =IF(R103=0,0,T103/R103) -> 500 | T103: ='[1]Vehicules usages 2026'!I46 -> 11000 | U103: ='[1]Vehicules usages 2026'!J21 -> 39 | V103: =IF(U103=0,0,W103/U103) -> 500 | W103: ='[1]Vehicules usages 2026'!J46 -> 19500 | X103: ='[1]Vehicules usages 2026'!K21 -> 44 | Y103: =IF(X103=0,0,Z103/X103) -> 500 | Z103: ='[1]Vehicules usages 2026'!K46 -> 22000 | AA103: ='[1]Vehicules usages 2026'!L21 -> 43 | AB103: =IF(AA103=0,0,AC103/AA103) -> 500 | AC103: ='[1]Vehicules usages 2026'!L46 -> 21500 | AD103: ='[1]Vehicules usages 2026'!M21 -> 33 | AE103: =IF(AD103=0,0,AF103/AD103) -> 500 | AF103: ='[1]Vehicules usages 2026'!M46 -> 16500 | AG103: ='[1]Vehicules usages 2026'!N21 -> 45 | AH103: =IF(AG103=0,0,AI103/AG103) -> 500 | AI103: ='[1]Vehicules usages 2026'!N46 -> 22500 | AJ103: ='[1]Vehicules usages 2026'!O21 -> 34 | AK103: =IF(AJ103=0,0,AL103/AJ103) -> 500 | AL103: ='[1]Vehicules usages 2026'!O46 -> 17000 | AM103: ='[1]Vehicules usages 2026'!P21 -> 30 | AN103: =IF(AM103=0,0,AO103/AM103) -> 500 | AO103: ='[1]Vehicules usages 2026'!P46 -> 15000
A104: =+$C$92&B104 -> Véhicules usagés
A105: =+$C$92&B105 -> Véhicules usagésRev. Finances | B105: Rev. Finances | D105: =IF(C100=0,0,E105/C100) -> 350 | E105: =+SUM(H105,K105,N105,Q105,T105,W105,Z105,AC105,AF105,AI105,AL105,AO105) -> 186550 | G105: =IF(F100=0,0,H105/F100) -> 350 | H105: ='[1]Vehicules usages 2026'!E68 -> 11200 | J105: =IF(I100=0,0,K105/I100) -> 350 | K105: ='[1]Vehicules usages 2026'!F68 -> 11550 | M105: =IF(L100=0,0,N105/L100) -> 350 | N105: ='[1]Vehicules usages 2026'!G68 -> 17150 | P105: =IF(O100=0,0,Q105/O100) -> 350 | Q105: ='[1]Vehicules usages 2026'!H68 -> 17850 | S105: =IF(R100=0,0,T105/R100) -> 350 | T105: ='[1]Vehicules usages 2026'!I68 -> 18550 | V105: =IF(U100=0,0,W105/U100) -> 350 | W105: ='[1]Vehicules usages 2026'!J68 -> 17850 | Y105: =IF(X100=0,0,Z105/X100) -> 350 | Z105: ='[1]Vehicules usages 2026'!K68 -> 16800 | AB105: =IF(AA100=0,0,AC105/AA100) -> 350 | AC105: ='[1]Vehicules usages 2026'!L68 -> 16450 | AE105: =IF(AD100=0,0,AF105/AD100) -> 350 | AF105: ='[1]Vehicules usages 2026'!M68 -> 16450 | AH105: =IF(AG100=0,0,AI105/AG100) -> 350 | AI105: ='[1]Vehicules usages 2026'!N68 -> 16100 | AK105: =IF(AJ100=0,0,AL105/AJ100) -> 350 | AL105: ='[1]Vehicules usages 2026'!O68 -> 14350 | AN105: =IF(AM100=0,0,AO105/AM100) -> 350 | AO105: ='[1]Vehicules usages 2026'!P68 -> 12250
...

Sheet Réel 2024
B1: ="Réel 2023 Mensuel Révisé"&" "&Parametres!$B$1 -> Réel 2023 Mensuel Révisé Volks
B2: Mois | F2: =+IF(Parametres!$B$3=F$6,"X","") | G2: =+IF(Parametres!$B$3=F$6,"O","") | H2: =+IF(Parametres!$B$3=F$6,"U","") | I2: =+IF(Parametres!$B$3=I$6,"X","") | J2: =+IF(Parametres!$B$3=I$6,"O","") | K2: =+IF(Parametres!$B$3=I$6,"U","") | L2: =+IF(Parametres!$B$3=L$6,"X","") -> X | M2: =+IF(Parametres!$B$3=L$6,"O","") -> O | N2: =+IF(Parametres!$B$3=L$6,"U","") -> U | O2: =+IF(Parametres!$B$3=O$6,"X","") | P2: =+IF(Parametres!$B$3=O$6,"O","") | Q2: =+IF(Parametres!$B$3=O$6,"U","") | R2: =+IF(Parametres!$B$3=R$6,"X","") | S2: =+IF(Parametres!$B$3=R$6,"O","") | T2: =+IF(Parametres!$B$3=R$6,"U","") | U2: =+IF(Parametres!$B$3=U$6,"X","") | V2: =+IF(Parametres!$B$3=U$6,"O","") | W2: =+IF(Parametres!$B$3=U$6,"U","") | X2: =+IF(Parametres!$B$3=X$6,"X","") | Y2: =+IF(Parametres!$B$3=X$6,"O","") | Z2: =+IF(Parametres!$B$3=X$6,"U","") | AA2: =+IF(Parametres!$B$3=AA$6,"X","") | AB2: =+IF(Parametres!$B$3=AA$6,"O","") | AC2: =+IF(Parametres!$B$3=AA$6,"U","") | AD2: =+IF(Parametres!$B$3=AD$6,"X","") | AE2: =+IF(Parametres!$B$3=AD$6,"O","") | AF2: =+IF(Parametres!$B$3=AD$6,"U","") | AG2: =+IF(Parametres!$B$3=AG$6,"X","") | AH2: =+IF(Parametres!$B$3=AG$6,"O","") | AI2: =+IF(Parametres!$B$3=AG$6,"U","") | AJ2: =+IF(Parametres!$B$3=AJ$6,"X","") | AK2: =+IF(Parametres!$B$3=AJ$6,"O","") | AL2: =+IF(Parametres!$B$3=AJ$6,"U","") | AM2: =+IF(Parametres!$B$3=AM$6,"X","") | AN2: =+IF(Parametres!$B$3=AM$6,"O","") | AO2: =+IF(Parametres!$B$3=AM$6,"U","")
B3: YTD | F3: =+IF(VLOOKUP(F$6,Parametres!$K$3:$N$14,4,0)="X","X","") -> X | G3: =+IF(VLOOKUP(F$6,Parametres!$K$3:$N$14,4,0)="X","O","") -> O | H3: =+IF(VLOOKUP(F$6,Parametres!$K$3:$N$14,4,0)="X","U","") -> U | I3: =+IF(VLOOKUP(I$6,Parametres!$K$3:$N$14,4,0)="X","X","") -> X | J3: =+IF(VLOOKUP(I$6,Parametres!$K$3:$N$14,4,0)="X","O","") -> O | K3: =+IF(VLOOKUP(I$6,Parametres!$K$3:$N$14,4,0)="X","U","") -> U | L3: =+IF(VLOOKUP(L$6,Parametres!$K$3:$N$14,4,0)="X","X","") -> X | M3: =+IF(VLOOKUP(L$6,Parametres!$K$3:$N$14,4,0)="X","O","") -> O | N3: =+IF(VLOOKUP(L$6,Parametres!$K$3:$N$14,4,0)="X","U","") -> U | O3: =+IF(VLOOKUP(O$6,Parametres!$K$3:$N$14,4,0)="X","X","") | P3: =+IF(VLOOKUP(O$6,Parametres!$K$3:$N$14,4,0)="X","O","") | Q3: =+IF(VLOOKUP(O$6,Parametres!$K$3:$N$14,4,0)="X","U","") | R3: =+IF(VLOOKUP(R$6,Parametres!$K$3:$N$14,4,0)="X","X","") | S3: =+IF(VLOOKUP(R$6,Parametres!$K$3:$N$14,4,0)="X","O","") | T3: =+IF(VLOOKUP(R$6,Parametres!$K$3:$N$14,4,0)="X","U","") | U3: =+IF(VLOOKUP(U$6,Parametres!$K$3:$N$14,4,0)="X","X","") | V3: =+IF(VLOOKUP(U$6,Parametres!$K$3:$N$14,4,0)="X","O","") | W3: =+IF(VLOOKUP(U$6,Parametres!$K$3:$N$14,4,0)="X","U","") | X3: =+IF(VLOOKUP(X$6,Parametres!$K$3:$N$14,4,0)="X","X","") | Y3: =+IF(VLOOKUP(X$6,Parametres!$K$3:$N$14,4,0)="X","O","") | Z3: =+IF(VLOOKUP(X$6,Parametres!$K$3:$N$14,4,0)="X","U","") | AA3: =+IF(VLOOKUP(AA$6,Parametres!$K$3:$N$14,4,0)="X","X","") | AB3: =+IF(VLOOKUP(AA$6,Parametres!$K$3:$N$14,4,0)="X","O","") | AC3: =+IF(VLOOKUP(AA$6,Parametres!$K$3:$N$14,4,0)="X","U","") | AD3: =+IF(VLOOKUP(AD$6,Parametres!$K$3:$N$14,4,0)="X","X","") | AE3: =+IF(VLOOKUP(AD$6,Parametres!$K$3:$N$14,4,0)="X","O","") | AF3: =+IF(VLOOKUP(AD$6,Parametres!$K$3:$N$14,4,0)="X","U","") | AG3: =+IF(VLOOKUP(AG$6,Parametres!$K$3:$N$14,4,0)="X","X","") | AH3: =+IF(VLOOKUP(AG$6,Parametres!$K$3:$N$14,4,0)="X","O","") | AI3: =+IF(VLOOKUP(AG$6,Parametres!$K$3:$N$14,4,0)="X","U","") | AJ3: =+IF(VLOOKUP(AJ$6,Parametres!$K$3:$N$14,4,0)="X","X","") | AK3: =+IF(VLOOKUP(AJ$6,Parametres!$K$3:$N$14,4,0)="X","O","") | AL3: =+IF(VLOOKUP(AJ$6,Parametres!$K$3:$N$14,4,0)="X","U","") | AM3: =+IF(VLOOKUP(AM$6,Parametres!$K$3:$N$14,4,0)="X","X","") | AN3: =+IF(VLOOKUP(AM$6,Parametres!$K$3:$N$14,4,0)="X","O","") | AO3: =+IF(VLOOKUP(AM$6,Parametres!$K$3:$N$14,4,0)="X","U","")
B4: Réel 2024 | C4: Véhicules neufs
B6: Mois | C6: 2024 | F6: Janvier | I6: Février | L6: Mars | O6: Avril | R6: Mai | U6: Juin | X6: Juillet | AA6: Août | AD6: Septembre | AG6: Octobre | AJ6: Novembre | AM6: Décembre
C7: UNITE | D7: $P/UNITE | E7: $PROFITS | F7: UNITE | G7: $P/UNITE | H7: $PROFITS | I7: UNITE | J7: $P/UNITE | K7: $PROFITS | L7: UNITE | M7: $P/UNITE | N7: $PROFITS | O7: UNITE | P7: $P/UNITE | Q7: $PROFITS | R7: UNITE | S7: $P/UNITE | T7: $PROFITS | U7: UNITE | V7: $P/UNITE | W7: $PROFITS | X7: UNITE | Y7: $P/UNITE | Z7: $PROFITS | AA7: UNITE | AB7: $P/UNITE | AC7: $PROFITS | AD7: UNITE | AE7: $P/UNITE | AF7: $PROFITS | AG7: UNITE | AH7: $P/UNITE | AI7: $PROFITS | AJ7: UNITE | AK7: $P/UNITE | AL7: $PROFITS | AM7: UNITE | AN7: $P/UNITE | AO7: $PROFITS
A8: =+$C$4&B8 -> Véhicules neufsVentes nettes | B8: Ventes nettes | E8: 36609711 | H8: 2918214.9 | K8: 2075892.1 | N8: 2855728.6 | Q8: 2860821 | T8: 3181778.8 | W8: 2263467 | Z8: 4089468.3 | AC8: 3610810.1 | AF8: 3303841.7 | AI8: 2861489.8 | AL8: 4142859.5 | AO8: 2445339.6
A9: =+$C$4&B9 -> Véhicules neufsAutos détail | B9: Autos détail | C9: 127 | D9: 1912.2985 | E9: 242861.91 | F9: 8 | G9: 1716.8587 | H9: 13734.87 | I9: 4 | J9: 1345.9625 | K9: 5383.85 | L9: 11 | M9: 1848.9036 | N9: 20337.94 | O9: 24 | P9: 1996.3658 | Q9: 47912.78 | R9: 10 | S9: 2530.125 | T9: 25301.25 | U9: 12 | V9: 2183.5042 | W9: 26202.05 | X9: 13 | Y9: 1905.2108 | Z9: 24767.74 | AA9: 15 | AB9: 2442.5653 | AC9: 36638.48 | AD9: 7 | AE9: 688.43143 | AF9: 4819.02 | AG9: 11 | AH9: 1392.1182 | AI9: 15313.3 | AJ9: 10 | AK9: 1542.296 | AL9: 15422.96 | AM9: 2 | AN9: 3513.835 | AO9: 7027.67
A10: =+$C$4&B10 -> Véhicules neufsCamions détail | B10: Camions détail | C10: 511 | D10: 2254.2629 | E10: 1151928.3 | F10: 40 | G10: 2500.5232 | H10: 100020.93 | I10: 26 | J10: 2574.7485 | K10: 66943.46 | L10: 40 | M10: 2175.1205 | N10: 87004.82 | O10: 32 | P10: 2603.3337 | Q10: 83306.68 | R10: 42 | S10: 2234.159 | T10: 93834.68 | U10: 29 | V10: 1971.4128 | W10: 57170.97 | X10: 63 | Y10: 2276.0851 | Z10: 143393.36 | AA10: 49 | AB10: 2254.3873 | AC10: 110464.98 | AD10: 56 | AE10: 2636.2429 | AF10: 147629.6 | AG10: 37 | AH10: 2420.7516 | AI10: 89567.81 | AJ10: 60 | AK10: 1856.0265 | AL10: 111361.59 | AM10: 37 | AN10: 1654.85 | AO10: 61229.45
A11: =+$C$4&B11 -> Véhicules neufsSprinter | B11: Sprinter | C11: 0 | D11: 0 | E11: 0 | F11: 0 | G11: 0 | H11: 0 | I11: 0 | J11: 0 | K11: 0 | L11: 0 | M11: 0 | N11: 0 | O11: 0 | P11: 0 | Q11: 0 | R11: 0 | S11: 0 | T11: 0 | U11: 0 | V11: 0 | W11: 0 | X11: 0 | Y11: 0 | Z11: 0 | AA11: 0 | AB11: 0 | AC11: 0 | AD11: 0 | AE11: 0 | AF11: 0 | AG11: 0 | AH11: 0 | AI11: 0 | AJ11: 0 | AK11: 0 | AL11: 0 | AM11: 0 | AN11: 0 | AO11: 0
A12: =+$C$4&B12 -> Véhicules neufsMoto détail | B12: Moto détail | C12: 0 | D12: 0 | E12: 0 | F12: 0 | G12: 0 | H12: 0 | I12: 0 | J12: 0 | K12: 0 | L12: 0 | M12: 0 | N12: 0 | O12: 0 | P12: 0 | Q12: 0 | R12: 0 | S12: 0 | T12: 0 | U12: 0 | V12: 0 | W12: 0 | X12: 0 | Y12: 0 | Z12: 0 | AA12: 0 | AB12: 0 | AC12: 0 | AD12: 0 | AE12: 0 | AF12: 0 | AG12: 0 | AH12: 0 | AI12: 0 | AJ12: 0 | AK12: 0 | AL12: 0 | AM12: 0 | AN12: 0 | AO12: 0
A13: =+$C$4&B13 -> Véhicules neufs[...] | B13: [...]
A14: =+$C$4&B14 -> Véhicules neufs[...] | B14: [...]
A15: =+$C$4&B15 -> Véhicules neufs[...] | B15: [...]
A16: =+$C$4&B16 -> Véhicules neufsTotal Neufs | B16: Total Neufs | C16: 638 | D16: 2186.1916 | E16: 1394790.2 | F16: 48 | G16: 2369.9125 | H16: 113755.8 | I16: 30 | J16: 2410.9103 | K16: 72327.31 | L16: 51 | M16: 2104.76 | N16: 107342.76 | O16: 56 | P16: 2343.2046 | Q16: 131219.46 | R16: 52 | S16: 2291.0756 | T16: 119135.93 | U16: 41 | V16: 2033.4883 | W16: 83373.02 | X16: 76 | Y16: 2212.6461 | Z16: 168161.1 | AA16: 64 | AB16: 2298.4916 | AC16: 147103.46 | AD16: 63 | AE16: 2419.8194 | AF16: 152448.62 | AG16: 48 | AH16: 2185.0231 | AI16: 104881.11 | AJ16: 70 | AK16: 1811.2079 | AL16: 126784.55 | AM16: 39 | AN16: 1750.1826 | AO16: 68257.12
A17: =+$C$4&B17 -> Véhicules neufs
A18: =+$C$4&B18 -> Véhicules neufsEx-Démos et courtoisies | B18: Ex-Démos et courtoisies | C18: 38 | D18: 1468.0958 | E18: 55787.64 | F18: 2 | G18: 2429.645 | H18: 4859.29 | I18: 2 | J18: 1540.7 | K18: 3081.4 | L18: 4 | M18: 370.87 | N18: 1483.48 | O18: 2 | P18: 495.505 | Q18: 991.01 | R18: 5 | S18: 2015.852 | T18: 10079.26 | U18: 6 | V18: 1300.1783 | W18: 7801.07 | X18: 5 | Y18: 1374.508 | Z18: 6872.54 | AA18: 3 | AB18: 942.82667 | AC18: 2828.48 | AD18: 1 | AE18: 1212.34 | AF18: 1212.34 | AG18: 3 | AH18: 1277.7867 | AI18: 3833.36 | AJ18: 2 | AK18: 2386.71 | AL18: 4773.42 | AM18: 3 | AN18: 2657.33 | AO18: 7971.99
A19: =+$C$4&B19 -> Véhicules neufs
A20: =+$C$4&B20 -> Véhicules neufsFlottes | B20: Flottes | C20: 22 | D20: 2142.7155 | E20: 47139.74 | F20: 4 | G20: 2065.4675 | H20: 8261.87 | I20: 8 | J20: 2662.095 | K20: 21296.76 | L20: 0 | M20: 0 | N20: 0 | O20: 0 | P20: 0 | Q20: 0 | R20: 0 | S20: 0 | T20: 0 | U20: 0 | V20: 0 | W20: 0 | X20: 0 | Y20: 0 | Z20: 0 | AA20: 2 | AB20: 905.915 | AC20: 1811.83 | AD20: 3 | AE20: 626.18667 | AF20: 1878.56 | AG20: 3 | AH20: 2106.1833 | AI20: 6318.55 | AJ20: 2 | AK20: 3786.085 | AL20: 7572.17 | AM20: 0 | AN20: 0 | AO20: 0
A21: =+$C$4&B21 -> Véhicules neufs
A22: =+$C$4&B22 -> Véhicules neufsRachat bail | B22: Rachat bail | E22: 109828.41 | H22: 4956 | K22: 6750.45 | N22: 13000.4 | Q22: 5903.29 | T22: 11767.32 | W22: 6139.6 | Z22: 12602.35 | AC22: 9461.73 | AF22: 11637.42 | AI22: 9560 | AL22: 10650.01 | AO22: 7399.84
A23: =+$C$4&B23 -> Véhicules neufs
A24: =+$C$4&B24 -> Véhicules neufsRev. Finances | B24: Rev. Finances | D24: 14.756686 | E24: 9975.52 | G24: 0 | H24: 0 | J24: 19.229688 | K24: 615.35 | M24: 0 | N24: 0 | P24: 0 | Q24: 0 | S24: 11.182281 | T24: 637.39 | V24: 14.402128 | W24: 676.9 | Y24: 7.4635802 | Z24: 604.55 | AB24: 25.274776 | AC24: 1693.41 | AE24: 0 | AF24: 0 | AH24: 38.216863 | AI24: 1949.06 | AK24: 0 | AL24: 0 | AN24: 90.449048 | AO24: 3798.86
A25: =+$C$4&B25 -> Véhicules neufsRev. Protections | B25: Rev. Protections | D25: 956.66136 | E25: 646703.08 | G25: 1179.3872 | H25: 58969.36 | J25: 984.25156 | K25: 31496.05 | M25: 606.02891 | N25: 33331.59 | P25: 931.86034 | Q25: 54047.9 | S25: 1090.3154 | T25: 62147.98 | V25: 1023.1253 | W25: 48086.89 | Y25: 985.36333 | Z25: 79814.43 | AB25: 940.25194 | AC25: 62996.88 | AE25: 952.71766 | AF25: 60973.93 | AH25: 968.15549 | AI25: 49375.93 | AK25: 995.15556 | AL25: 71651.2 | AN25: 805.02238 | AO25: 33810.94
A26: =+$C$4&B26 -> Véhicules neufsRev. Autres | B26: Rev. Autres | D26: 5.3130325 | E26: 3591.61 | G26: 0 | H26: 0 | J26: 13.8625 | K26: 443.6 | M26: 5.7529091 | N26: 316.41 | P26: 0 | Q26: 0 | S26: 4.6777193 | T26: 266.63 | V26: 0 | W26: 0 | Y26: 2.302963 | Z26: 186.54 | AB26: 5.9568657 | AC26: 399.11 | AE26: 0 | AF26: 0 | AH26: 0 | AI26: 0 | AK26: 13.881806 | AL26: 999.49 | AN26: 23.329286 | AO26: 979.83
A27: =+$C$4&B27 -> Véhicules neufsTotal F&I | B27: Total F&I | C27: 676 | D27: 976.73108 | E27: 660270.21 | F27: 50 | G27: 1179.3872 | H27: 58969.36 | I27: 32 | J27: 1017.3437 | K27: 32555 | L27: 55 | M27: 611.78182 | N27: 33648 | O27: 58 | P27: 931.86034 | Q27: 54047.9 | R27: 57 | S27: 1106.1754 | T27: 63052 | U27: 47 | V27: 1037.5274 | W27: 48763.79 | X27: 81 | Y27: 995.12988 | Z27: 80605.52 | AA27: 67 | AB27: 971.48358 | AC27: 65089.4 | AD27: 64 | AE27: 952.71766 | AF27: 60973.93 | AG27: 51 | AH27: 1006.3724 | AI27: 51324.99 | AJ27: 72 | AK27: 1009.0374 | AL27: 72650.69 | AM27: 42 | AN27: 918.80071 | AO27: 38589.63
A28: =+$C$4&B28 -> Véhicules neufs
A29: =+$C$4&B29 -> Véhicules neufs
A30: =+$C$4&B30 -> Véhicules neufsTotal Dépt. Neufs | B30: Total Dépt. Neufs | C30: 698 | D30: 3249.0204 | E30: 2267816.2 | F30: 54 | G30: 3533.3763 | H30: 190802.32 | I30: 40 | J30: 3400.273 | K30: 136010.92 | L30: 55 | M30: 2826.8116 | N30: 155474.64 | O30: 58 | P30: 3313.1321 | Q30: 192161.66 | R30: 57 | S30: 3579.5528 | T30: 204034.51 | U30: 47 | V30: 3108.0315 | W30: 146077.48 | X30: 81 | Y30: 3311.6236 | Z30: 268241.51 | AA30: 69 | AB30: 3279.6362 | AC30: 226294.9 | AD30: 67 | AE30: 3405.2369 | AF30: 228150.87 | AG30: 54 | AH30: 3257.7409 | AI30: 175918.01 | AJ30: 74 | AK30: 3005.8222 | AL30: 222430.84 | AM30: 42 | AN30: 2909.9662 | AO30: 122218.58
A31: =+$C$4&B31 -> Véhicules neufs
A32: =+$C$4&B32 -> Véhicules neufs
A33: =+$C$4&B33 -> Véhicules neufsDEPENSES | B33: DEPENSES
A34: =+$C$4&B34 -> Véhicules neufsComm. vendeurs | B34: Comm. vendeurs | C34: 0.32111322 | D34: 689.05286 | E34: 465799.73 | F34: 0.36865267 | G34: 874.5554 | H34: 43727.77 | I34: 0.35924126 | J34: 846.56 | K34: 27089.92 | L34: 0.28209805 | M34: 558.17582 | N34: 30699.67 | O34: 0.30815298 | P34: 702.4319 | Q34: 40741.05 | R34: 0.33936869 | S34: 769.32614 | T34: 43851.59 | U34: 0.34423486 | V34: 667.77234 | W34: 31385.3 | X34: 0.29871778 | Y34: 645.50198 | Z34: 52285.66 | AA34: 0.31853546 | AB34: 712.81552 | AC34: 47758.64 | AD34: 0.27814436 | AE34: 667.81141 | AF34: 42739.93 | AG34: 0.37945869 | AH34: 808.87549 | AI34: 41252.65 | AJ34: 0.2766924 | AK34: 505.57069 | AL34: 36401.09 | AM34: 0.36556192 | AN34: 663.48714 | AO34: 27866.46
A35: =+$C$4&B35 -> Véhicules neufsComm. F&I | B35: Comm. F&I | C35: 0.25728074 | D35: 251.2941 | E35: 169874.81 | F35: 0.30000105 | G35: 353.8174 | H35: 17690.87 | I35: 0.24998526 | J35: 254.32094 | K35: 8138.27 | L35: 0.30698942 | M35: 187.81055 | N35: 10329.58 | O35: 0.2000087 | P35: 186.38017 | Q35: 10810.05 | R35: 0.29999762 | S35: 331.85 | T35: 18915.45 | U35: 0.29928478 | V35: 310.51617 | W35: 14594.26 | X35: 0.25000198 | Y35: 248.78444 | Z35: 20151.54 | AA35: 0.24999478 | AB35: 242.86582 | AC35: 16272.01 | AD35: 0.26000358 | AE35: 247.71 | AF35: 15853.44 | AG35: 0.26999966 | AH35: 271.7202 | AI35: 13857.73 | AJ35: 0.26999661 | AK35: 272.43667 | AL35: 19615.44 | AM35: 0.094485747 | AN35: 86.813571 | AO35: 3646.17
A36: =+$C$4&B36 -> Véhicules neufsFrais de livraison | B36: Frais de livraison | D36: 105.38633 | E36: 71241.16 | G36: 88.6484 | H36: 4432.42 | J36: 98.328438 | K36: 3146.51 | M36: 35.175818 | N36: 1934.67 | P36: 166.21517 | Q36: 9640.48 | S36: 138.49439 | T36: 7894.18 | V36: 111.73617 | W36: 5251.6 | Y36: 112.60815 | Z36: 9121.26 | AB36: 78.424925 | AC36: 5254.47 | AE36: 130.02187 | AF36: 8321.4 | AH36: 127.63843 | AI36: 6509.56 | AK36: 73.22125 | AL36: 5271.93 | AN36: 106.25429 | AO36: 4462.68
A37: =+$C$4&B37 -> Véhicules neufsService gratuit 1 | B37: Service gratuit 1 | D37: 4.9730325 | E37: 3361.77 | G37: 1.8594 | H37: 92.97 | J37: 30.533125 | K37: 977.06 | M37: 10.110182 | N37: 556.06 | P37: 6.017069 | Q37: 348.99 | S37: 0.066315789 | T37: 3.78 | V37: 5.4995745 | W37: 258.48 | Y37: 0 | Z37: 0 | AB37: 8.5468657 | AC37: 572.64 | AE37: 0 | AF37: 0 | AH37: 4.0194118 | AI37: 204.99 | AK37: 3.7194444 | AL37: 267.8 | AN37: 1.8809524 | AO37: 79
A38: =+$C$4&B38 -> Véhicules neufsEntretien stock | B38: Entretien stock | D38: 119.19737 | E38: 80577.42 | G38: 115.9442 | H38: 5797.21 | J38: 268.93781 | K38: 8606.01 | M38: 117.53782 | N38: 6464.58 | P38: 133.99603 | Q38: 7771.77 | S38: 167.94544 | T38: 9572.89 | V38: 168.73936 | W38: 7930.75 | Y38: 43.995185 | Z38: 3563.61 | AB38: 50.172239 | AC38: 3361.54 | AE38: 121.18812 | AF38: 7756.04 | AH38: 94.619412 | AI38: 4825.59 | AK38: 109.28875 | AL38: 7868.79 | AN38: 168.06286 | AO38: 7058.64
A39: =+$C$4&B39 -> Véhicules neufsPublicité 1 | B39: Publicité 1 | D39: 152.67334 | E39: 103207.18 | G39: 91.2874 | H39: 4564.37 | J39: 137.47656 | K39: 4399.25 | M39: 367.98564 | N39: 20239.21 | P39: 245.72724 | Q39: 14252.18 | S39: 171.58053 | T39: 9780.09 | V39: 108.28021 | W39: 5089.17 | Y39: 45.389259 | Z39: 3676.53 | AB39: 86.991045 | AC39: 5828.4 | AE39: 124.21734 | AF39: 7949.91 | AH39: 233.87333 | AI39: 11927.54 | AK39: 53.550417 | AL39: 3855.63 | AN39: 277.25952 | AO39: 11644.9
A40: =+$C$4&B40 -> Véhicules neufsIntérêt de gros | B40: Intérêt de gros | D40: 224.57978 | E40: 151815.93 | G40: 538.3934 | H40: 26919.67 | J40: -353.66 | K40: -11317.12 | M40: 437.246 | N40: 24048.53 | P40: -85.485517 | Q40: -4958.16 | S40: 227.21439 | T40: 12951.22 | V40: 280.19213 | W40: 13169.03 | Y40: 273.39222 | Z40: 22144.77 | AB40: 22.367313 | AC40: 1498.61 | AE40: 37.670469 | AF40: 2410.91 | AH40: 425.86784 | AI40: 21719.26 | AK40: 337.88694 | AL40: 24327.86 | AN40: 450.03214 | AO40: 18901.35
A41: =+$C$4&B41 -> Véhicules neufs[...] | B41: [...]
A42: =+$C$4&B42 -> Véhicules neufs[...] | B42: [...]
A43: =+$C$4&B43 -> Véhicules neufs[...] | B43: [...]
A44: =+$C$4&B44 -> Véhicules neufsTOTAL VARIABLES | B44: TOTAL VARIABLES | C44: % brut | D44: 0.46118287 | E44: 1045878 | F44: % brut | G44: 0.54100642 | H44: 103225.28 | I44: % brut | J44: 0.30173974 | K44: 41039.9 | L44: % brut | M44: 0.60635162 | N44: 94272.3 | O44: % brut | P44: 0.4090637 | Q44: 78606.36 | R44: % brut | S44: 0.50466561 | T44: 102969.2 | U44: % brut | V44: 0.53176294 | W44: 77678.59 | X44: % brut | Y44: 0.41359508 | Z44: 110943.37 | AA44: % brut | AB44: 0.35593515 | AC44: 80546.31 | AD44: % brut | AE44: 0.37269913 | AF44: 85031.63 | AG44: % brut | AH44: 0.57013674 | AI44: 100297.32 | AJ44: % brut | AK44: 0.43882647 | AL44: 97608.54 | AM44: % brut | AN44: 0.60268414 | AO44: 73659.2
A45: =+$C$4&B45 -> Véhicules neufsSalaires cadres | B45: Salaires cadres | E45: 243304.97 | H45: 23989.06 | K45: 19757.52 | N45: 23707.52 | Q45: 22738.29 | T45: 18969.05 | W45: 17276.74 | Z45: 21170.97 | AC45: 18122.89 | AF45: 21495.49 | AI45: 20142.13 | AL45: 16358.33 | AO45: 19576.98
A46: =+$C$4&B46 -> Véhicules neufsSalaires commis | B46: Salaires commis | E46: 171218.81 | H46: 13193.79 | K46: 12111.66 | N46: 12526.87 | Q46: 12985.89 | T46: 14463.37 | W46: 12517.38 | Z46: 11846.53 | AC46: 15664.78 | AF46: 17579.27 | AI46: 20057.19 | AL46: 13068.19 | AO46: 15203.89
A47: =+$C$4&B47 -> Véhicules neufsSalaires autres | B47: Salaires autres | E47: 16771.8 | H47: 1613 | K47: 2451 | N47: -312 | Q47: 1208.75 | T47: 2903.5 | W47: 1819.6 | Z47: 1963.25 | AC47: 1579.5 | AF47: 11.25 | AI47: 930.2 | AL47: 1451.6 | AO47: 1152.15
A48: =+$C$4&B48 -> Véhicules neufsSalaires spécialistes | B48: Salaires spécialistes | E48: 0 | H48: 0 | K48: 0 | N48: 0 | Q48: 0 | T48: 0 | W48: 0 | Z48: 0 | AC48: 0 | AF48: 0 | AI48: 0 | AL48: 0 | AO48: 0
A49: =+$C$4&B49 -> Véhicules neufs[...] | B49: [...]
A50: =+$C$4&B50 -> Véhicules neufs[...] | B50: [...]
A51: =+$C$4&B51 -> Véhicules neufs[...] | B51: [...]
A52: =+$C$4&B52 -> Véhicules neufsSalaires en absences | B52: Salaires en absences | E52: 136704.35 | H52: 11297.5 | K52: 8944.73 | N52: 12291.71 | Q52: 12288.84 | T52: 14676.27 | W52: 11092.96 | Z52: 10866.84 | AC52: 11090.84 | AF52: 9162.42 | AI52: 13521.92 | AL52: 12767.3 | AO52: 8703.02
A53: =+$C$4&B53 -> Véhicules neufsDéduction à la source | B53: Déduction à la source | E53: 170955.68 | H53: 14203.83 | K53: 12821.25 | N53: 14654.31 | Q53: 15510.75 | T53: 17960 | W53: 13743.57 | Z53: 13752.02 | AC53: 13852.73 | AF53: 12339.01 | AI53: 15758.45 | AL53: 15446.59 | AO53: 10913.17
A54: =+$C$4&B54 -> Véhicules neufsBénéfices marginaux | B54: Bénéfices marginaux | E54: 84834.5 | H54: 7181.9 | K54: 4964.91 | N54: 7784.41 | Q54: 8178.51 | T54: 8486.02 | W54: 6407 | Z54: 7178.18 | AC54: 7016.94 | AF54: 4769.38 | AI54: 8227.63 | AL54: 8320.04 | AO54: 6319.58
A55: =+$C$4&B55 -> Véhicules neufsCsst | B55: Csst | E55: 32563.56 | H55: 2463.48 | K55: 3329.22 | N55: 2218.05 | Q55: 3094.69 | T55: 2876.17 | W55: 2667.67 | Z55: 3241.11 | AC55: 2868.85 | AF55: 2753.54 | AI55: 3456.94 | AL55: 1641.57 | AO55: 1952.27
A56: =+$C$4&B56 -> Véhicules neufs[...] | B56: [...]
A57: =+$C$4&B57 -> Véhicules neufsTOTAL PERSONNEL | B57: TOTAL PERSONNEL | C57: % brut | D57: 0.37761158 | E57: 856353.67 | F57: % brut | G57: 1.2636006 | H57: 73942.56 | I57: % brut | J57: 1.2636006 | K57: 64380.29 | L57: % brut | M57: 1.2636006 | N57: 72870.87 | O57: % brut | P57: 1.2636006 | Q57: 76005.72 | R57: % brut | S57: 1.2636006 | T57: 80334.38 | U57: % brut | V57: 1.2636006 | W57: 65524.92 | X57: % brut | Y57: 1.2636006 | Z57: 70018.9 | AA57: % brut | AB57: 1.2636006 | AC57: 70196.53 | AD57: % brut | AE57: 1.2636006 | AF57: 68110.36 | AG57: % brut | AH57: 1.2636006 | AI57: 82094.46 | AJ57: % brut | AK57: 1.2636006 | AL57: 69053.62 | AM57: % brut | AN57: 1.2636006 | AO57: 63821.06
A58: =+$C$4&B58 -> Véhicules neufsPublicité 2 | B58: Publicité 2 | E58: 0 | H58: 0 | K58: 0 | N58: 0 | Q58: 0 | T58: 0 | W58: 0 | Z58: 0 | AC58: 0 | AF58: 0 | AI58: 0 | AL58: 0 | AO58: 0
A59: =+$C$4&B59 -> Véhicules neufsService gratuit 2 | B59: Service gratuit 2 | E59: 0 | H59: 0 | K59: 0 | N59: 0 | Q59: 0 | T59: 0 | W59: 0 | Z59: 0 | AC59: 0 | AF59: 0 | AI59: 0 | AL59: 0 | AO59: 0
A60: =+$C$4&B60 -> Véhicules neufsFrais véhicules de cie | B60: Frais véhicules de cie | E60: 113056.32 | H60: 11043.63 | K60: 10438.73 | N60: 8585.79 | Q60: 5799.11 | T60: 13630.57 | W60: 11014.36 | Z60: 7490.62 | AC60: 9933.13 | AF60: 8541.72 | AI60: 6523.11 | AL60: 9881.78 | AO60: 10173.77
A61: =+$C$4&B61 -> Véhicules neufsInformatique | B61: Informatique | E61: 90221.78 | H61: 6207.73 | K61: 6313.34 | N61: 7256.78 | Q61: 7784.61 | T61: 9063.09 | W61: 5623.99 | Z61: 7652.37 | AC61: 6190.88 | AF61: 9523.36 | AI61: 7696.69 | AL61: 6971.19 | AO61: 9937.75
A62: =+$C$4&B62 -> Véhicules neufsFrais de déplacement | B62: Frais de déplacement | E62: 19344.94 | H62: 1811.46 | K62: 995.9 | N62: 1059.24 | Q62: 1501.77 | T62: 1778.24 | W62: 2225.94 | Z62: 1293.58 | AC62: 765.11 | AF62: 1925.24 | AI62: 2623.13 | AL62: 1668.07 | AO62: 1697.26
A63: =+$C$4&B63 -> Véhicules neufsServices extérieurs | B63: Services extérieurs | E63: 86815.53 | H63: 7697.88 | K63: 7771.09 | N63: 10430.41 | Q63: 7415.88 | T63: 7261.42 | W63: 6186.82 | Z63: 8436.09 | AC63: 6440.06 | AF63: 8397.52 | AI63: 8395.97 | AL63: 9175.12 | AO63: -792.73
A64: =+$C$4&B64 -> Véhicules neufsFournitures autres | B64: Fournitures autres | E64: 463.95 | H64: 0 | K64: 165.98 | N64: 140.41 | Q64: 0 | T64: 0 | W64: 0 | Z64: 0 | AC64: 131.91 | AF64: 25.65 | AI64: 0 | AL64: 0 | AO64: 0
A65: =+$C$4&B65 -> Véhicules neufsUniformes | B65: Uniformes | E65: 623 | H65: 623 | K65: 0 | N65: 0 | Q65: 0 | T65: 0 | W65: 0 | Z65: 0 | AC65: 0 | AF65: 0 | AI65: 0 | AL65: 0 | AO65: 0
A66: =+$C$4&B66 -> Véhicules neufsPapeterie | B66: Papeterie | E66: 6389.31 | H66: 161.73 | K66: 1041.95 | N66: 543.03 | Q66: 58.13 | T66: 1047.35 | W66: 408.53 | Z66: 218.53 | AC66: 821.13 | AF66: 299.54 | AI66: 58.95 | AL66: 1466.35 | AO66: 264.09
A67: =+$C$4&B67 -> Véhicules neufsTéléphone | B67: Téléphone | E67: 4914.14 | H67: 469.87 | K67: 439.54 | N67: 387.42 | Q67: 396.63 | T67: 471.73 | W67: 389.49 | Z67: 355.13 | AC67: 467.29 | AF67: 368.32 | AI67: 402.18 | AL67: 398.61 | AO67: 367.93
A68: =+$C$4&B68 -> Véhicules neufsFrais postaux | B68: Frais postaux | E68: 2686.24 | H68: 725.8 | K68: 447.9 | N68: 405.83 | Q68: 131.27 | T68: 211.16 | W68: 88.36 | Z68: 54.6 | AC68: 204.13 | AF68: 78.17 | AI68: 87.27 | AL68: 116.66 | AO68: 135.09
A69: =+$C$4&B69 -> Véhicules neufsDivers | B69: Divers | E69: 1996.17 | H69: 89.42 | K69: 71.21 | N69: 71.21 | Q69: 121.08 | T69: 111.68 | W69: 62.72 | Z69: 62.72 | AC69: 62.72 | AF69: 134.72 | AI69: 62.72 | AL69: 410.38 | AO69: 735.59
... A71: =+$C$4&B71 -> Véhicules neufsFrais bancaires | B71: Frais bancaires | E71: 48083.39 | H71: 2802.79 | K71: 2165.37 | N71: 3719.82 | Q71: 4608.58 | T71: 4559.64 | W71: 3513.7 | Z71: 3902.37 | AC71: 3804.86 | AF71: 4016.45 | AI71: 4645.42 | AL71: 6358.02 | AO71: 3986.37
A72: =+$C$4&B72 -> Véhicules neufs[...] | B72: [...]
A73: =+$C$4&B73 -> Véhicules neufs[...] | B73: [...]
A74: =+$C$4&B74 -> Véhicules neufs[...] | B74: [...]
A75: =+$C$4&B75 -> Véhicules neufsTOTAL SEMI-FIXES | B75: TOTAL SEMI-FIXES | C75: % brut | D75: 0.17348044 | E75: 393421.75 | F75: % brut | G75: 0.17775481 | H75: 33916.03 | I75: % brut | J75: 0.22450389 | K75: 30534.98 | L75: % brut | M75: 0.2345715 | N75: 36469.92 | O75: % brut | P75: 0.16496079 | Q75: 31699.14 | R75: % brut | S75: 0.18669008 | T75: 38091.22 | U75: % brut | V75: 0.21780216 | W75: 31815.99 | X75: % brut | Y75: 0.11927341 | Z75: 31994.08 | AA75: % brut | AB75: 0.13010258 | AC75: 29441.55 | AD75: % brut | AE75: 0.15220187 | AF75: 34724.99 | AG75: % brut | AH75: 0.17682504 | AI75: 31106.71 | AJ75: % brut | AK75: 0.16643349 | AL75: 37019.94 | AM75: % brut | AN75: 0.21770176 | AO75: 26607.2
A76: =+$C$4&B76 -> Véhicules neufs
A77: =+$C$4&B77 -> Véhicules neufsTOTAL DES DÉPENSES | B77: TOTAL DES DÉPENSES | C77: % brut | D77: 1.0122749 | E77: 2295653.4 | F77: % brut | G77: 1.1062961 | H77: 211083.87 | I77: % brut | J77: 0.99959011 | K77: 135955.17 | L77: % brut | M77: 1.3096225 | N77: 203613.09 | O77: % brut | P77: 0.96955459 | Q77: 186311.22 | R77: % brut | S77: 1.0850851 | T77: 221394.8 | U77: % brut | V77: 1.1981279 | W77: 175019.5 | X77: % brut | Y77: 0.79389782 | Z77: 212956.35 | AA77: % brut | AB77: 0.79623708 | AC77: 180184.39 | AD77: % brut | AE77: 0.82343311 | AF77: 187866.98 | AG77: % brut | AH77: 1.213625 | AI77: 213498.49 | AJ77: % brut | AK77: 0.9157098 | AL77: 203682.1 | AM77: % brut | AN77: 1.3425738 | AO77: 164087.46
A78: =+$C$4&B78 -> Véhicules neufsProgramme neuf 1 | B78: Programme neuf 1 | E78: 88064.2 | H78: 0 | K78: 0 | N78: 0 | Q78: 0 | T78: 0 | W78: 12000 | Z78: 0 | AC78: 19414.2 | AF78: 0 | AI78: 45250 | AL78: 0 | AO78: 11400
A79: =+$C$4&B79 -> Véhicules neufsProgramme neuf 2 | B79: Programme neuf 2 | E79: 0 | H79: 0 | K79: 0 | N79: 0 | Q79: 0 | T79: 0 | W79: 0 | Z79: 0 | AC79: 0 | AF79: 0 | AI79: 0 | AL79: 0 | AO79: 0
A80: =+$C$4&B80 -> Véhicules neufsProgramme neuf 3 | B80: Programme neuf 3 | E80: 0 | H80: 0 | K80: 0 | N80: 0 | Q80: 0 | T80: 0 | W80: 0 | Z80: 0 | AC80: 0 | AF80: 0 | AI80: 0 | AL80: 0 | AO80: 0
A81: =+$C$4&B81 -> Véhicules neufsHoldbacks | B81: Holdbacks | E81: 890720.4 | H81: 82565 | K81: 47635 | N81: 69794 | Q81: 77555 | T81: 69529 | W81: 61215.55 | Z81: 94826.85 | AC81: 80559 | AF81: 77496 | AI81: 76838 | AL81: 95331 | AO81: 57376
A82: =+$C$4&B82 -> Véhicules neufs[...] | B82: [...]
A83: =+$C$4&B83 -> Véhicules neufs[...] | B83: [...]
A84: =+$C$4&B84 -> Véhicules neufs[...] | B84: [...]
A85: =+$C$4&B85 -> Véhicules neufsFrais administration | B85: Frais administration | E85: 318588 | H85: 24546 | K85: 15936 | N85: 23652 | Q85: 24441 | T85: 26496 | W85: 23346 | Z85: 39648 | AC85: 33150 | AF85: 31659 | AI85: 22968 | AL85: 31746 | AO85: 21000
A86: =+$C$4&B86 -> Véhicules neufsAUTRES REVENUS | B86: AUTRES REVENUS | E86: 1297372.6 | H86: 107111 | K86: 63571 | N86: 93446 | Q86: 101996 | T86: 96025 | W86: 96561.55 | Z86: 134474.85 | AC86: 133123.2 | AF86: 109155 | AI86: 145056 | AL86: 127077 | AO86: 89776
A87: =+$C$4&B87 -> Véhicules neufs
A88: =+$C$4&B88 -> Véhicules neufsPROFIT DÉPARTEMENTAL | B88: PROFIT DÉPARTEMENTAL | E88: 1269535.4 | H88: 86829.45 | K88: 63626.75 | N88: 45307.55 | Q88: 107846.44 | T88: 78664.71 | W88: 67619.53 | Z88: 189760.01 | AC88: 179233.71 | AF88: 149438.89 | AI88: 107475.52 | AL88: 145825.74 | AO88: 47907.12
B92: Réel 2024 | C92: Véhicules usagés
B94: Mois | C94: 2025 | F94: Janvier | I94: Février | L94: Mars | O94: Avril | R94: Mai | U94: Juin | X94: Juillet | AA94: Août | AD94: Septembre | AG94: Octobre | AJ94: Novembre | AM94: Décembre
C95: UNITE | D95: $P/UNITE | E95: $PROFITS | F95: UNITE | G95: $P/UNITE | H95: $PROFITS | I95: UNITE | J95: $P/UNITE | K95: $PROFITS | L95: UNITE | M95: $P/UNITE | N95: $PROFITS | O95: UNITE | P95: $P/UNITE | Q95: $PROFITS | R95: UNITE | S95: $P/UNITE | T95: $PROFITS | U95: UNITE | V95: $P/UNITE | W95: $PROFITS | X95: UNITE | Y95: $P/UNITE | Z95: $PROFITS | AA95: UNITE | AB95: $P/UNITE | AC95: $PROFITS | AD95: UNITE | AE95: $P/UNITE | AF95: $PROFITS | AG95: UNITE | AH95: $P/UNITE | AI95: $PROFITS | AJ95: UNITE | AK95: $P/UNITE | AL95: $PROFITS | AM95: UNITE | AN95: $P/UNITE | AO95: $PROFITS
A96: =+$C$92&B96 -> Véhicules usagésVentes nettes | B96: Ventes nettes | E96: 15676831 | H96: 857558.07 | K96: 616311.44 | N96: 833663.21 | Q96: 1017681 | T96: 1290713.8 | W96: 1616914.6 | Z96: 1735831.8 | AC96: 1633303.6 | AF96: 1445195.3 | AI96: 1500069.8 | AL96: 2000604.9 | AO96: 1128983.9
A97: =+$C$92&B97 -> Véhicules usagésCertifié | B97: Certifié | C97: 290 | D97: 1381.2152 | E97: 400552.41 | F97: 18 | G97: 1713.5989 | H97: 30844.78 | I97: 13 | J97: 1495.4062 | K97: 19440.28 | L97: 28 | M97: 1195.8296 | N97: 33483.23 | O97: 28 | P97: 952.90393 | Q97: 26681.31 | R97: 29 | S97: 1404.1734 | T97: 40721.03 | U97: 30 | V97: 1968.675 | W97: 59060.25 | X97: 28 | Y97: 1004.9229 | Z97: 28137.84 | AA97: 27 | AB97: 556.5763 | AC97: 15027.56 | AD97: 25 | AE97: 2129.208 | AF97: 53230.2 | AG97: 15 | AH97: 2694.2227 | AI97: 40413.34 | AJ97: 28 | AK97: 1446.2436 | AL97: 40494.82 | AM97: 21 | AN97: 619.89381 | AO97: 13017.77
A98: =+$C$92&B98 -> Véhicules usagésNon Certifié | B98: Non Certifié | C98: 9 | D98: 560.16333 | E98: 5041.47 | F98: 4 | G98: 1079.355 | H98: 4317.42 | I98: 2 | J98: -169.795 | K98: -339.59 | L98: 1 | M98: 3949.99 | N98: 3949.99 | O98: 0 | P98: 0 | Q98: -4705.95 | R98: 1 | S98: 1376.03 | T98: 1376.03 | U98: 0 | V98: 0 | W98: 0 | X98: 0 | Y98: 0 | Z98: 0 | AA98: 0 | AB98: 0 | AC98: 0 | AD98: 1 | AE98: 1000 | AF98: 1000 | AG98: 0 | AH98: 0 | AI98: 0 | AJ98: 0 | AK98: 0 | AL98: 0 | AM98: 0 | AN98: 0 | AO98: -556.43
A99: =+$C$92&B99 -> Véhicules usagésAutres Marques | B99: Autres Marques | C99: 8 | D99: 2577.55 | E99: 20620.4 | F99: 2 | G99: 1352.425 | H99: 2704.85 | I99: 2 | J99: 1908.175 | K99: 3816.35 | L99: 1 | M99: 4152.3 | N99: 4152.3 | O99: 2 | P99: 2899.8 | Q99: 5799.6 | R99: 0 | S99: 0 | T99: 0 | U99: 0 | V99: 0 | W99: 0 | X99: 0 | Y99: 0 | Z99: 0 | AA99: 0 | AB99: 0 | AC99: 0 | AD99: 0 | AE99: 0 | AF99: 0 | AG99: 0 | AH99: 0 | AI99: 0 | AJ99: 0 | AK99: 0 | AL99: 0 | AM99: 1 | AN99: 4147.3 | AO99: 4147.3
A100: =+$C$92&B100 -> Véhicules usagésTotal Usagés | B100: Total Usagés | C100: 307 | D100: 1388.3201 | E100: 426214.28 | F100: 24 | G100: 1577.7937 | H100: 37867.05 | I100: 17 | J100: 1348.0612 | K100: 22917.04 | L100: 30 | M100: 1386.184 | N100: 41585.52 | O100: 30 | P100: 925.832 | Q100: 27774.96 | R100: 30 | S100: 1403.2353 | T100: 42097.06 | U100: 30 | V100: 1968.675 | W100: 59060.25 | X100: 28 | Y100: 1004.9229 | Z100: 28137.84 | AA100: 27 | AB100: 556.5763 | AC100: 15027.56 | AD100: 26 | AE100: 2085.7769 | AF100: 54230.2 | AG100: 15 | AH100: 2694.2227 | AI100: 40413.34 | AJ100: 28 | AK100: 1446.2436 | AL100: 40494.82 | AM100: 22 | AN100: 754.93818 | AO100: 16608.64
A101: =+$C$92&B101 -> Véhicules usagés
A102: =+$C$92&B102 -> Véhicules usagés
A103: =+$C$92&B103 -> Véhicules usagésVentes au Gros | B103: Ventes au Gros | C103: 404 | D103: 543.00832 | E103: 219375.36 | F103: 19 | G103: 343.84316 | H103: 6533.02 | I103: 10 | J103: 743.692 | K103: 7436.92 | L103: 10 | M103: 1059.873 | N103: 10598.73 | O103: 18 | P103: 1446.8283 | Q103: 26042.91 | R103: 26 | S103: 637.83154 | T103: 16583.62 | U103: 45 | V103: 996.06622 | W103: 44822.98 | X103: 51 | Y103: 737.09647 | Z103: 37591.92 | AA103: 50 | AB103: 637.0086 | AC103: 31850.43 | AD103: 38 | AE103: 366.98737 | AF103: 13945.52 | AG103: 52 | AH103: 182.21538 | AI103: 9475.2 | AJ103: 57 | AK103: -132.43754 | AL103: -7548.94 | AM103: 28 | AN103: 787.25179 | AO103: 22043.05
A104: =+$C$92&B104 -> Véhicules usagés
A105: =+$C$92&B105 -> Véhicules usagésRev. Finances | B105: Rev. Finances | D105: 330.46899 | E105: 101453.98 | G105: 357.9825 | H105: 8591.58 | J105: 230.15882 | K105: 3912.7 | M105: 393.41333 | N105: 11802.4 | P105: 305.93433 | Q105: 9178.03 | S105: 357.35967 | T105: 10720.79 | V105: 373.984 | W105: 11219.52 | Y105: 450.17429 | Z105: 12604.88 | AB105: 444.74963 | AC105: 12008.24 | AE105: 508.61423 | AF105: 13223.97 | AH105: 75.055333 | AI105: 1125.83 | AK105: 134.03429 | AL105: 3752.96 | AN105: 150.59455 | AO105: 3313.08
A106: =+$C$92&B106 -> Véhicules usagésRev. Protections | B106: Rev. Protections | D106: 1691.1939 | E106: 519196.53 | G106: 1456.1246 | H106: 34946.99 | J106: 1336.4476 | K106: 22719.61 | M106: 1414.3993 | N106: 42431.98 | P106: 1730.1367 | Q106: 51904.1 | S106: 1630.4857 | T106: 48914.57 | V106: 1465.0157 | W106: 43950.47 | Y106: 1933.1911 | Z106: 54129.35 | AB106: 1666.4493 | AC106: 44994.13 | AE106: 1907.0388 | AF106: 49583.01 | AH106: 1976.5013 | AI106: 29647.52 | AK106: 2014.1729 | AL106: 56396.84 | AN106: 1798.9982 | AO106: 39577.96
...

Sheet Capex
A1: PARK AVENUE VOLKSWAGEN | B1: PARK AVENUE VOLKSWAGEN
A2: Forecast Immobilisation 2022 | B2: Forecast Immobilisation 2025 | H2: 1 | I2: 2 | J2: 3 | K2: 4 | L2: 5 | M2: 6 | N2: 7 | O2: 8 | P2: 9 | Q2: 10 | R2: 11 | S2: 12
H3: =+IF(VLOOKUP(H2,Parametres!$L$3:$N$14,3,0)="X","REEL","FORECAST") -> REEL | I3: =+IF(VLOOKUP(I2,Parametres!$L$3:$N$14,3,0)="X","REEL","FORECAST") -> REEL | J3: =+IF(VLOOKUP(J2,Parametres!$L$3:$N$14,3,0)="X","REEL","FORECAST") -> REEL | K3: =+IF(VLOOKUP(K2,Parametres!$L$3:$N$14,3,0)="X","REEL","FORECAST") -> FORECAST | L3: =+IF(VLOOKUP(L2,Parametres!$L$3:$N$14,3,0)="X","REEL","FORECAST") -> FORECAST | M3: =+IF(VLOOKUP(M2,Parametres!$L$3:$N$14,3,0)="X","REEL","FORECAST") -> FORECAST | N3: =+IF(VLOOKUP(N2,Parametres!$L$3:$N$14,3,0)="X","REEL","FORECAST") -> FORECAST | O3: =+IF(VLOOKUP(O2,Parametres!$L$3:$N$14,3,0)="X","REEL","FORECAST") -> FORECAST | ... S3: =+IF(VLOOKUP(S2,Parametres!$L$3:$N$14,3,0)="X","REEL","FORECAST") -> FORECAST
A4: Concession | B4: Budgété / Non budgété | C4: Projet | D4: Catégorie Immo | E4: Total forecast | F4: Budget Annuel | G4: Écart vs budget | H4: January | I4: February | J4: March | K4: April | L4: May | M4: June | N4: July | O4: August | P4: September | Q4: October | R4: November | S4: December | T4: Raison / Description
C5: Total | E5: =+SUM(E6:E20) -> 30931.3 | F5: =+SUM(F6:F20) -> 40000 | G5: =+SUM(G6:G20) -> -9068.7 | H5: =+SUM(H6:H20) -> 30931.3 | I5: =+SUM(I6:I20) -> 0 | J5: =+SUM(J6:J20) -> 0 | K5: =+SUM(K6:K20) -> 0 | L5: =+SUM(L6:L20) -> 0 | ... S5: =+SUM(S6:S20) -> 0 | X5: Terrain
A6: =+Parametres!$B$1 -> Volks | B6: oui | C6: Outils Spécialisés Volks | E6: =+SUM(H6:S6) -> 0 | F6: 40000 | G6: =+E6-F6 -> -40000 | X6: Bâtisse
A7: =+Parametres!$B$1 -> Volks | B7: non | C7: Équipement informatique | E7: =+SUM(H7:S7) -> 0 | G7: =+E7-F7 -> 0 | X7: Améliorations Locatives
A8: =+Parametres!$B$1 -> Volks | C8: Nouveau building | E8: =+SUM(H8:S8) -> 30931.3 | G8: =+E8-F8 -> 30931.3 | H8: 30931.3 | X8: Mobilier
A9: =+Parametres!$B$1 -> Volks | E9: =+SUM(H9:S9) -> 0 | G9: =+E9-F9 -> 0 | X9: Équipements Informatique
A10: =+Parametres!$B$1 -> Volks | E10: =+SUM(H10:S10) -> 0 | G10: =+E10-F10 -> 0 | X10: Équipements Téléphonique
A11: =+Parametres!$B$1 -> Volks | E11: =+SUM(H11:S11) -> 0 | G11: =+E11-F11 -> 0 | X11: Enseigne
A12: =+Parametres!$B$1 -> Volks | E12: =+SUM(H12:S12) -> 0 | G12: =+E12-F12 -> 0
A13: =+Parametres!$B$1 -> Volks | E13: =+SUM(H13:S13) -> 0 | G13: =+E13-F13 -> 0
A14: =+Parametres!$B$1 -> Volks | E14: =+SUM(H14:S14) -> 0 | G14: =+E14-F14 -> 0
A15: =+Parametres!$B$1 -> Volks | E15: =+SUM(H15:S15) -> 0 | G15: =+E15-F15 -> 0
A16: =+Parametres!$B$1 -> Volks | E16: =+SUM(H16:S16) -> 0 | G16: =+E16-F16 -> 0
A17: =+Parametres!$B$1 -> Volks | E17: =+SUM(H17:S17) -> 0 | G17: =+E17-F17 -> 0 | X17: non
A18: =+Parametres!$B$1 -> Volks | E18: =+SUM(H18:S18) -> 0 | G18: =+E18-F18 -> 0
A19: =+Parametres!$B$1 -> Volks | E19: =+SUM(H19:S19) -> 0 | G19: =+E19-F19 -> 0
A20: =+Parametres!$B$1 -> Volks | E20: =+SUM(H20:S20) -> 0 | G20: =+E20-F20 -> 0

Sheet Inventaire_Used
A1: #Contrôle | B1: Année | C1: Marque | D1: Modèle | E1: 1416 | F1: 2103 | G1: NIV | H1: Jours en stock | M1: 45169 | N1: $ Inventaire | O1: $ Financé
A2: 5291P | B2: 2020 | C2: VOLKSWAGEN | D2: E-GOLF | E2: 32007.51 | F2: -22494.36 | G2: WVWPR7AU2LW903993 | H2: 423 | M2: CTRL | N2: =+SUM(E:E) -> 2779322.1 | O2: =+SUM(F:F) -> -640715.53
A3: 230251A | B3: 2020 | C3: VOLKSWAGEN | D3: E-GOLF | E3: 24454.46 | G3: WVWPR7AU0LW907198 | H3: 306 | M3: Unités | N3: =COUNT(E:E) -> 111 | O3: =-O2/N2 -> 0.23052943
A4: 230425A | B4: 2021 | C4: VOLKSWAGEN | D4: ATLAS CROSS SPO | E4: 37735.15 | G4: 1V2LC2CAXMC211536 | H4: 188
A5: 230365A | B5: 2018 | C5: VOLKSWAGEN | D5: BEETLE CONVERTI | E5: 29929.55 | G5: 3VW5DAAT2JM518129 | H5: 187 | M5: Moyenne | N5: =+N2/N3 -> 25038.938
A6: 5485P | B6: 2018 | C6: VOLKSWAGEN | D6: ATLAS | E6: 31306.12 | G6: 1V2NR2CA5JC509107 | H6: 131
A7: 230554A | B7: 2014 | C7: SUBARU | D7: WRX | E7: 17680.42 | G7: JF1GR8H60EL238082 | H7: 121 | M7: Plus de 90 Jours | N7: =SUM(E2:E13) -> 337989.36 | O7: =+N7/N2 -> 0.12160856
A8: 230567A | B8: 2021 | C8: VOLKSWAGEN | D8: TIGUAN | E8: 28635.15 | F8: -31332.8 | G8: 3VV2B7AX6MM155874 | H8: 104 | N8: =COUNT(H2:H13) -> 12 | O8: =+N8/(N3) -> 0.10810811
A9: 240013A | B9: 2022 | C9: VOLKSWAGEN | D9: TIGUAN | E9: 38815.25 | G9: 3VV4B7AX3NM051496 | H9: 94
A10: 230392A | B10: 2020 | C10: VOLKSWAGEN | D10: TIGUAN | E10: 31315.25 | F10: -24944.54 | G10: 3VV4B7AX2LM114164 | H10: 94
A11: 230599A | B11: 2019 | C11: VOLKSWAGEN | D11: JETTA | E11: 21280.25 | F11: -10962 | G11: 3VWE57BU6KM254342 | H11: 94
A12: 230606A | B12: 2018 | C12: CHEVROLET | D12: VOLT | E12: 17550 | G12: 1G1RA6S50JU104989 | H12: 93
A13: 240015A | B13: 2019 | C13: VOLKSWAGEN | D13: GOLF GTI | E13: 27280.25 | F13: -17480.23 | G13: 3VW6T7AU5KM024755 | H13: 90
A14: 5511P | B14: 2022 | C14: VOLKSWAGEN | D14: ATLAS CROSS SPO | E14: 44105.05 | F14: -38250 | G14: 1V2BE2CA6NC212111 | H14: 88
A15: 240019A | B15: 2020 | C15: VOLKSWAGEN | D15: ATLAS CROSS SPO | E15: 36415.13 | F15: -26892 | G15: 1V2TE2CA8LC219420 | H15: 82
A16: 230596A | B16: 2020 | C16: VOLKSWAGEN | D16: TIGUAN | E16: 27935.05 | G16: 3VV2B7AX4LM005048 | H16: 76
A17: 5509PA | B17: 2017 | C17: AUDI | D17: A3 E-TRON | E17: 20050 | G17: WAUSPBFF5HA099610 | H17: 74
A18: 230626A | B18: 2018 | C18: VOLKSWAGEN | D18: TIGUAN | E18: 20497.05 | G18: 3VV4B7AX2JM130250 | H18: 72
A19: 5518P | B19: 2020 | C19: VOLKSWAGEN | D19: TIGUAN | E19: 28075.78 | F19: -23850 | G19: 3VV4B7AX0LM106225 | H19: 69
A20: 230593A | B20: 2019 | C20: VOLKSWAGEN | D20: TIGUAN | E20: 26815.25 | G20: 3VV4B7AX3KM183332 | H20: 69
A21: 5519P | B21: 2021 | C21: VOLKSWAGEN | D21: TIGUAN | E21: 28447.25 | F21: -24418.8 | G21: 3VV2B7AX4MM068281 | H21: 68
A22: 240044A | B22: 2019 | C22: VOLKSWAGEN | D22: ATLAS | E22: 29352 | G22: 1V2MR2CA6KC587280 | H22: 66
A23: 240041A | B23: 2018 | C23: VOLKSWAGEN | D23: GOLF | E23: 18787.5 | G23: 3VWG17AU2JM291103 | H23: 66
A24: 240056A | B24: 2020 | C24: VOLKSWAGEN | D24: JETTA | E24: 18043.82 | G24: 3VWN57BU2LM040420 | H24: 65
A25: 240036A | B25: 2021 | C25: VOLKSWAGEN | D25: ATLAS | E25: 40209.65 | G25: 1V2FR2CA8MC595926 | H25: 62
A26: 240079A | B26: 2020 | C26: VOLKSWAGEN | D26: TIGUAN | E26: 30620.3 | G26: 3VV4B7AX5LM110786 | H26: 62
A27: 230564B | B27: 2020 | C27: JEEP | D27: COMPASS | E27: 28211.38 | G27: 3C4NJDDBXLT155667 | H27: 62
A28: 230649A | B28: 2020 | C28: NISSAN | D28: ROGUE | E28: 23550 | G28: 5N1AT2MT7LC775762 | H28: 61
A29: 240086A | B29: 2022 | C29: VOLKSWAGEN | D29: TIGUAN | E29: 36524.6 | G29: 3VV4B7AX9NM096457 | H29: 60
A30: 5522P | B30: 2020 | C30: VOLKSWAGEN | D30: TIGUAN | E30: 24346.21 | F30: -16047.88 | G30: 3VV2B7AX7LM099068 | H30: 60
A31: 5521P | B31: 2019 | C31: VOLKSWAGEN | D31: GOLF | E31: 18530.25 | G31: 3VWG57AU3KM018998 | H31: 60
A32: 5523P | B32: 2021 | C32: VOLKSWAGEN | D32: TIGUAN | E32: 29670.31 | F32: -25505.1 | G32: 3VV2B7AX2MM078047 | H32: 59
A33: 240089A | B33: 2020 | C33: VOLKSWAGEN | D33: JETTA | E33: 22965.2 | G33: 3VWW57BU9LM006236 | H33: 55
A34: 5525P | B34: 2021 | C34: VOLKSWAGEN | D34: TIGUAN | E34: 31666.8 | F34: -33046.59 | G34: 3VV4B7AX1MM155614 | H34: 54
A35: 240059A | B35: 2019 | C35: VOLKSWAGEN | D35: TIGUAN | E35: 24846.26 | G35: 3VV2B7AX7KM049091 | H35: 53
A36: 240099A | B36: 2020 | C36: VOLKSWAGEN | D36: JETTA | E36: 19323.74 | G36: 3VWN57BU9LM077965 | H36: 51
A37: 240098A | B37: 2019 | C37: VOLKSWAGEN | D37: GOLF | E37: 18294.75 | G37: 3VWG57AU0KM034477 | H37: 48
A38: 240038B | B38: 2018 | C38: VOLKSWAGEN | D38: GOLF | E38: 16745.3 | G38: 3VWG17AU9JM275867 | H38: 48
A39: 240091A | B39: 2022 | C39: VOLKSWAGEN | D39: ATLAS | E39: 49927.29 | G39: 1V2FR2CA7NC504226 | H39: 47
A40: 5526P | B40: 2020 | C40: VOLKSWAGEN | D40: TIGUAN | E40: 24483.1 | F40: -18876 | G40: 3VV2B7AX9LM002520 | H40: 47
A41: 240109A | B41: 2019 | C41: VOLKSWAGEN | D41: GOLF | E41: 21779.6 | G41: 3VWG57AU6KM028375 | H41: 47
A42: 240111A | B42: 2021 | C42: VOLKSWAGEN | D42: GOLF | E42: 21350 | G42: 3VWW57AU1MM000790 | H42: 45
A43: 240108A | B43: 2019 | C43: VOLKSWAGEN | D43: JETTA | E43: 17488.18 | G43: 3VWG57BU3KM143398 | H43: 45
A44: 240100A | B44: 2020 | C44: VOLKSWAGEN | D44: JETTA | E44: 18370.25 | G44: 3VWCB7BU1LM050033 | H44: 44
A45: 5527P | B45: 2018 | C45: VOLKSWAGEN | D45: TIGUAN | E45: 20165.3 | G45: 3VV2B7AX0JM078401 | H45: 44
A46: 240121A | B46: 2015 | C46: JEEP | D46: CHEROKEE | E46: 15050 | G46: 1C4PJMBBXFW775848 | H46: 44
A47: 240062A | B47: 2020 | C47: VOLKSWAGEN | D47: JETTA | E47: 21360.2 | G47: 3VWEB7BU9LM051228 | H47: 41
A48: 5528P | B48: 2021 | C48: VOLKSWAGEN | D48: JETTA | E48: 25003.85 | F48: -21330 | G48: 3VWE57BU8MM046465 | H48: 40
A49: 240153A | B49: 2020 | C49: VOLKSWAGEN | D49: TIGUAN | E49: 24894.97 | G49: 3VV0B7AX5LM117185 | H49: 40
A50: 240127A | B50: 2019 | C50: VOLKSWAGEN | D50: TIGUAN | E50: 27870.3 | G50: 3VV4B7AX2KM185248 | H50: 40
A51: 240169A | B51: 2021 | C51: VOLKSWAGEN | D51: JETTA | E51: 24530.4 | G51: 3VWE57BU7MM077268 | H51: 37
A52: 240143A | B52: 2008 | C52: VOLKSWAGEN | D52: GTI | E52: 4314.03 | G52: WVWHV91K48W093414 | H52: 37
A53: 240183A | B53: 2021 | C53: VOLKSWAGEN | D53: JETTA | E53: 24447.5 | G53: 3VWE57BU5MM022575 | H53: 33
A54: 5530P | B54: 2019 | C54: VOLKSWAGEN | D54: GOLF | E54: 20373.45 | F54: -12553.38 | G54: 3VWG57AU5KM019568 | H54: 33
A55: 240105A | B55: 2021 | C55: VOLKSWAGEN | D55: GOLF GTI | E55: 32388.2 | G55: 3VW5T7AU9MM015944 | H55: 32
A56: 240151A | B56: 2020 | C56: VOLKSWAGEN | D56: PASSAT | E56: 23491.6 | G56: 1VWBA7A31LC005280 | H56: 32
A57: 240123A | B57: 2021 | C57: VOLKSWAGEN | D57: TIGUAN | E57: 29343.25 | G57: 3VV2B7AX9MM038886 | H57: 31
A58: 240198A | B58: 2020 | C58: VOLKSWAGEN | D58: TIGUAN | E58: 29950 | G58: 3VV4B7AX7LM138623 | H58: 31
A59: 5531P | B59: 2019 | C59: VOLKSWAGEN | D59: TIGUAN | E59: 21448.99 | F59: -18000 | G59: 3VV2B7AX5KM174266 | H59: 31
A60: 240195A | B60: 2019 | C60: VOLKSWAGEN | D60: GOLF ALLTRACK | E60: 23680.2 | G60: 3VWH17AU4KM517860 | H60: 31
A61: 240031A | B61: 2019 | C61: VOLKSWAGEN | D61: GOLF | E61: 19433.85 | G61: 3VWG57AU6KM019319 | H61: 31
A62: 240208A | B62: 2019 | C62: NISSAN | D62: ROGUE | E62: 17516.85 | G62: 5N1AT2MT2KC789311 | H62: 31
A63: 240200A | B63: 2021 | C63: VOLKSWAGEN | D63: TIGUAN | E63: 28418.09 | G63: 3VV2B7AX7MM017972 | H63: 30
A64: 240120A | B64: 2020 | C64: VOLKSWAGEN | D64: TIGUAN | E64: 26650 | G64: 3VV2B7AX5LM134416 | H64: 30
A65: 5532P | B65: 2019 | C65: VOLKSWAGEN | D65: TIGUAN | E65: 22943.2 | F65: -14910 | G65: 3VV2B7AXXKM175526 | H65: 27
A66: 5536P | B66: 2024 | C66: VOLKSWAGEN | D66: GOLF R | E66: 56282.9 | F66: -53444.44 | G66: WVWEB7CD1RW113067 | H66: 26
A67: 5535P | B67: 2023 | C67: VOLKSWAGEN | D67: TIGUAN | E67: 37343.25 | F67: -31500 | G67: 3VVMB7AX1PM006494 | H67: 26
A68: 5534P | B68: 2021 | C68: VOLKSWAGEN | D68: TIGUAN | E68: 27555.44 | F68: -26142.19 | G68: 3VV2B7AX0MM070822 | H68: 26
A69: 240090A | B69: 2019 | C69: VOLKSWAGEN | D69: JETTA | E69: 15050 | G69: 3VWW57BU7KM135400 | H69: 26
A70: 5539P | B70: 2020 | C70: VOLKSWAGEN | D70: E-GOLF | E70: 24148.3 | F70: -13011 | G70: WVWPR7AUXLW900758 | H70: 25
A71: 5537P | B71: 2017 | C71: VOLKSWAGEN | D71: TIGUAN | E71: 17323.25 | F71: -14400 | G71: WVGNV7AX9HW500724 | H71: 25
A72: 5540P | B72: 2020 | C72: VOLKSWAGEN | D72: TIGUAN | E72: 24729.89 | F72: -21121.07 | G72: 3VV2B7AX5LM104042 | H72: 24
A73: 240154A | B73: 2023 | C73: HYUNDAY | D73: SANTA CRUZ | E73: 39801.28 | G73: 5NTJEDAF3PH073751 | H73: 17
A74: 5542P | B74: 2020 | C74: VOLKSWAGEN | D74: TIGUAN | E74: 27897 | F74: -21259.15 | G74: 3VV2B7AX9LM116727 | H74: 17
A75: 5543P | B75: 2021 | C75: VOLKSWAGEN | D75: TIGUAN | E75: 29849.7 | F75: -25650 | G75: 3VV4B7AX3MM043848 | H75: 16
A76: 240222A | B76: 2021 | C76: VOLKSWAGEN | D76: JETTA | E76: 22734.85 | G76: 3VWE57BU8MM023008 | H76: 16
A77: 5544P | B77: 2020 | C77: VOLKSWAGEN | D77: TIGUAN | E77: 23937.85 | G77: 3VV2B7AX7LM009577 | H77: 16
A78: 240210A | B78: 2020 | C78: DODGE | D78: RAM 1500 | E78: 37860.38 | G78: 1C6SRFFT2LN407190 | H78: 16
A79: 240226A | B79: 2019 | C79: VOLKSWAGEN | D79: GOLF | E79: 17250 | F79: -10994 | G79: 3VWG57AU7KM033052 | H79: 16
A80: 240172A | B80: 2015 | C80: VOLKSWAGEN | D80: JETTA SEDAN | E80: 9050 | G80: 3VWG07AJ8FM218642 | H80: 13
A81: 5529PA | B81: 2014 | C81: NISSAN | D81: TRUCK PATHFINDER | E81: 10550 | G81: 5N1AR2MM1EC693147 | H81: 12
A82: 5545P | B82: 2022 | C82: VOLKSWAGEN | D82: GOLF R | E82: 48197.8 | F82: -42300 | G82: WVWEB7CD8NW157948 | H82: 11
A83: 240231A | B83: 2019 | C83: VOLKSWAGEN | D83: JETTA | E83: 21402.85 | G83: 3VWE57BU8KM269358 | H83: 11
A84: 240215A | B84: 2019 | C84: VOLKSWAGEN | D84: GOLF | E84: 18179.95 | G84: 3VWW57AU6KM035788 | H84: 11
A85: 5546P | B85: 2016 | C85: BMW | D85: SAV X5 | E85: 22550 | G85: 5UXKR0C55G0S87415 | H85: 11
A86: 0925RA | B86: 2010 | C86: TOYOTA | D86: COROLLA | E86: 5450 | G86: 2T1BU4EE1AC231280 | H86: 11
A87: 240191A | B87: 2019 | C87: VOLKSWAGEN | D87: TIGUAN | E87: 20650 | G87: 3VV2B7AX1KM022551 | H87: 10
A88: 240194A | B88: 2015 | C88: VOLKSWAGEN | D88: TIGUAN | E88: 8550 | G88: WVGJV7AX1FW576563 | H88: 10
A89: 240261A | B89: 2020 | C89: VOLKSWAGEN | D89: TIGUAN | E89: 25550 | G89: 3VV2B7AXXLM100701 | H89: 9
A90: 240035A | B90: 2020 | C90: HONDA | D90: PILOT | E90: 28550 | G90: 5FNYF6H72LB500902 | H90: 9
A91: 240229A | B91: 2019 | C91: VOLKSWAGEN | D91: GOLF | E91: 17050 | G91: 3VWW57AU0KM035463 | H91: 9
A92: 240178A | B92: 2022 | C92: VOLKSWAGEN | D92: TIGUAN | E92: 31300 | G92: 3VV8B7AX7NM005591 | H92: 8
A93: 5548P | B93: 2023 | C93: VOLKSWAGEN | D93: ATLAS | E93: 47388.75 | G93: 1V2SR2CA7PC517706 | H93: 4
A94: 240058A | B94: 2021 | C94: VOLKSWAGEN | D94: JETTA | E94: 24050 | G94: 3VW6T7BU9MM023626 | H94: 4
... A114: 5488P | B114: 2010 | C114: VOLKSWAGEN | D114: ROUTAN | E114: 11948.62 | G114: 2V4RW3DX0AR228009 | H114: 94

Sheet Inventaire_Neuf
A1: #Contrôle | B1: Année | C1: Marque | D1: Modèle | E1: 1402 | F1: 2101 | G1: NIV | H1: Jours en stock | K1: 45230 | L1: $ Inventaire | M1: $ Financé
A2: 230536 | B2: 2023 | C2: VOLKSWAGEN | D2: JETTA SEDAN | E2: 33666.97 | F2: -31504.85 | G2: 3VW2T7BU7PM053775 | H2: 142 | K2: CTRL | L2: =+SUM(E2:E9963) -> 3059537.1 | M2: =+SUM(F2:F9963) -> -2668372
A3: 240001 | B3: 2024 | C3: VOLKSWAGEN | D3: ATLAS | E3: 56706.1 | F3: -57628.2 | G3: 1V2BR2CA6RC502911 | H3: 142 | K3: Unités | L3: =COUNT(E:E) -> 71 | M3: =-M2/L2 -> 0.8721489
A4: 230574 | B4: 2023 | C4: VOLKSWAGEN | D4: JETTA SEDAN | E4: 31163.98 | F4: -32628.75 | G4: 3VWGM7BU3PM060824 | H4: 116
A5: 230581 | B5: 2023 | C5: VOLKSWAGEN | D5: TAOS | E5: 38081.07 | F5: -39936.75 | G5: 3VV4X7B27PM374246 | H5: 111
A6: 240003 | B6: 2024 | C6: VOLKSWAGEN | D6: ATLAS | E6: 50511.98 | F6: -51427.95 | G6: 1V2LR2CA2RC511786 | H6: 108 | K6: Plus de 90 jrs | L6: =SUM(E2:E12) -> 532950.79 | M6: =SUM(F2:F12) -> -378366.05
A7: 240009 | B7: 2024 | C7: VOLKSWAGEN | D7: ATLAS CROSS SPT | E7: 54659.17 | F7: -57051.75 | G7: 1V2BE2CA7RC206484 | H7: 104 | L7: 2
A8: 240011 | B8: 2024 | C8: VOLKSWAGEN | D8: ATLAS CROSS SPT | E8: 48328.17 | F8: -51136.05 | G8: 1V2LE2CA3RC208611 | H8: 97
A9: 240016 | B9: 2024 | C9: VOLKSWAGEN | D9: ATLAS CROSS SPT | E9: 57229.1 | G9: 1V2BE2CA1RC206996 | H9: 93 | K9: Plus de 180 jrs | L9: 0 | M9: 0
A10: 240022 | B10: 2024 | C10: VOLKSWAGEN | D10: ATLAS | E10: 58141.01 | G10: 1V2BR2CA4RC506228 | H10: 90 | L10: 0
A11: 240021 | B11: 2024 | C11: VOLKSWAGEN | D11: ATLAS | E11: 48171.23 | G11: 1V2LR2CA8RC516197 | H11: 90
A12: 240020 | B12: 2024 | C12: VOLKSWAGEN | D12: ATLAS CROSS SPT | E12: 56292.01 | F12: -57051.75 | G12: 1V2BE2CA5RC210341 | H12: 90
A13: 240027 | B13: 2024 | C13: VOLKSWAGEN | D13: ATLAS | E13: 56073.92 | F13: -58869.3 | G13: 1V2BR2CA1RC517137 | H13: 86
A14: 240026 | B14: 2024 | C14: VOLKSWAGEN | D14: GOLF GTI | E14: 37397 | F14: -39440.1 | G14: WVWGA7CD7RW121198 | H14: 86
A15: 240030 | B15: 2024 | C15: VOLKSWAGEN | D15: ATLAS CROSS SPT | E15: 56197.99 | F15: -58834.65 | G15: 1V2FE2CAXRC211373 | H15: 82
A16: 230639 | B16: 2023 | C16: VOLKSWAGEN | D16: TAOS | E16: 32135.51 | F16: -34034.7 | G16: 3VVEX7B23PM379190 | H16: 80
A17: 240042 | B17: 2024 | C17: VOLKSWAGEN | D17: ATLAS CROSS SPT | E17: 55950.97 | F17: -58834.65 | G17: 1V2FE2CA4RC210672 | H17: 74
A18: 240047 | B18: 2024 | C18: VOLKSWAGEN | D18: ATLAS CROSS SPT | E18: 55950.97 | F18: -58834.65 | G18: 1V2FE2CA0RC211429 | H18: 74
A19: 240045 | B19: 2024 | C19: VOLKSWAGEN | D19: JETTA SEDAN | E19: 26927 | F19: -28367.85 | G19: 3VWWM7BU5RM010702 | H19: 74
A20: 230643 | B20: 2023 | C20: VOLKSWAGEN | D20: TAOS | E20: 37610 | F20: -39461.1 | G20: 3VV4X7B2XPM382549 | H20: 73
A21: 240052 | B21: 2024 | C21: VOLKSWAGEN | D21: ATLAS CROSS SPT | E21: 55950.97 | F21: -58834.65 | G21: 1V2FE2CAXRC211504 | H21: 73
A22: 240050 | B22: 2024 | C22: VOLKSWAGEN | D22: JETTA SEDAN | E22: 29531 | F22: -31102.05 | G22: 3VWSM7BU4RM014707 | H22: 73
A23: 240070 | B23: 2024 | C23: VOLKSWAGEN | D23: ATLAS CROSS SPT | E23: 54250 | F23: -57051.75 | G23: 1V2BE2CA9RC212335 | H23: 68
... A27: 240083 | B27: 2024 | C27: VOLKSWAGEN | D27: JETTA SEDAN | E27: 32017.87 | F27: -33204.15 | G27: 3VWGM7BU7RM015582 | H27: 62
A28: 240125 | B28: 2024 | C28: VOLKSWAGEN | D28: JETTA GLI | E28: 31816.52 | G28: 3VW8T7BU7RM014696 | H28: 52
A29: 240129 | B29: 2024 | C29: VOLKSWAGEN | D29: JETTA GLI | E29: 31513 | G29: 3VW8T7BU8RM016912 | H29: 51
A30: 240137 | B30: 2024 | C30: VOLKSWAGEN | D30: ATLAS | E30: 48894 | F30: -51427.95 | G30: 1V2LR2CA9RC529461 | H30: 48
A31: 240141 | B31: 2024 | C31: VOLKSWAGEN | D31: ATLAS CROSS SPT | E31: 55948 | F31: -58834.65 | G31: 1V2FE2CA6RC216828 | H31: 48
A32: 240139 | B32: 2024 | C32: VOLKSWAGEN | D32: ATLAS CROSS SPT | E32: 54236.5 | G32: 1V2BE2CAXRC212764 | H32: 48
A33: 240138 | B33: 2024 | C33: VOLKSWAGEN | D33: TAOS | E33: 32864 | F33: -34706.7 | G33: 3VVEX7B22RM012347 | H33: 48
A34: 240147 | B34: 2024 | C34: VOLKSWAGEN | D34: ATLAS | E34: 55259.97 | F34: -58109.1 | G34: 1V2BR2CAXRC525513 | H34: 47
A35: 240156 | B35: 2024 | C35: VOLKSWAGEN | D35: ATLAS CROSS SPT | E35: 53794.97 | F35: -56570.85 | G35: 1V2BE2CA8RC216649 | H35: 45
A36: 240171 | B36: 2024 | C36: VOLKSWAGEN | D36: JETTA SEDAN | E36: 28629 | G36: 3VWEM7BU2RM001760 | H36: 44
A37: 240173 | B37: 2024 | C37: VOLKSWAGEN | D37: ATLAS | E37: 54801.97 | F37: -57628.2 | G37: 1V2BR2CA7RC532368 | H37: 41
A38: 240190 | B38: 2024 | C38: VOLKSWAGEN | D38: ATLAS | E38: 58249.97 | G38: 1V2FR2CA7RC531156 | H38: 38
A39: 240197 | B39: 2024 | C39: VOLKSWAGEN | D39: TIGUAN | E39: 45175.95 | F39: -47526.15 | G39: 3VV4B7AX2RM023873 | H39: 37
A40: 240203 | B40: 2024 | C40: VOLKSWAGEN | D40: TIGUAN | E40: 44101 | F40: -46474.05 | G40: 3VV4B7AX6RM025190 | H40: 34
A41: 240207 | B41: 2024 | C41: VOLKSWAGEN | D41: ATLAS | E41: 54806.97 | F41: -57628.2 | G41: 1V2BR2CA4RC531890 | H41: 33
A42: 240206 | B42: 2024 | C42: VOLKSWAGEN | D42: TAOS | E42: 38195 | F42: -40225.5 | G42: 3VV4X7B25RM012063 | H42: 33
A43: 240212 | B43: 2024 | C43: VOLKSWAGEN | D43: ATLAS CROSS SPT | E43: 56348.1 | F43: -58834.65 | G43: 1V2FE2CA5RC219798 | H43: 30
A44: 240213 | B44: 2024 | C44: VOLKSWAGEN | D44: TIGUAN | E44: 45762.95 | G44: 3VV4B7AX1RM023721 | H44: 30
A45: 240221 | B45: 2024 | C45: VOLKSWAGEN | D45: TAOS | E45: 37908 | F45: -39749.85 | G45: 3VV4X7B20RM013248 | H45: 25
A46: 240220 | B46: 2024 | C46: VOLKSWAGEN | D46: TAOS | E46: 32705 | F46: -34423.2 | G46: 3VVEX7B2XRM013066 | H46: 25
A47: 240223 | B47: 2024 | C47: VOLKSWAGEN | D47: TAOS | E47: 32705 | F47: -34423.2 | G47: 3VVEX7B25RM012259 | H47: 25
A48: 240219 | B48: 2024 | C48: VOLKSWAGEN | D48: TAOS | E48: 32700 | F48: -34423.2 | G48: 3VVEX7B20RM012928 | H48: 25
A49: 240232 | B49: 2024 | C49: VOLKSWAGEN | D49: TAOS | E49: 35661.95 | G49: 3VVVX7B23RM011742 | H49: 20
A50: 240230 | B50: 2024 | C50: VOLKSWAGEN | D50: TIGUAN | E50: 44107 | F50: -46474.05 | G50: 3VV4B7AX4RM047169 | H50: 20
A51: 240238 | B51: 2024 | C51: VOLKSWAGEN | D51: TAOS | E51: 37441.5 | G51: 3VV4X7B26RM014615 | H51: 16
A52: 240248 | B52: 2024 | C52: VOLKSWAGEN | D52: GOLF GTI | E52: 38207 | F52: -40179.3 | G52: WVWRA7CD4RW133320 | H52: 13
A53: 240241 | B53: 2024 | C53: VOLKSWAGEN | D53: TAOS | E53: 37773 | F53: -39749.85 | G53: 3VV4X7B2XRM023463 | H53: 13
A54: 240243 | B54: 2024 | C54: VOLKSWAGEN | D54: TAOS | E54: 37109 | F54: -39552.45 | G54: 3VV4X7B23RM025278 | H54: 13
A55: 240242 | B55: 2024 | C55: VOLKSWAGEN | D55: TAOS | E55: 34270 | F55: -36066.45 | G55: 3VVUX7B20RM026050 | H55: 13
A56: 240259 | B56: 2024 | C56: VOLKSWAGEN | D56: GOLF GTI | E56: 39384 | F56: -41836.2 | G56: WVWWA7CD4RW139864 | H56: 12
A57: 240256 | B57: 2024 | C57: VOLKSWAGEN | D57: GOLF R | E57: 49697 | F57: -52243.8 | G57: WVWEB7CD9RW139691 | H57: 12
A58: 240257 | B58: 2024 | C58: VOLKSWAGEN | D58: GOLF R | E58: 49697 | F58: -52243.8 | G58: WVWEB7CD9RW140162 | H58: 12
A59: 240255 | B59: 2024 | C59: VOLKSWAGEN | D59: TAOS | E59: 35568 | F59: -37434.6 | G59: 3VVVX7B24RM026699 | H59: 12
A60: 240254 | B60: 2024 | C60: VOLKSWAGEN | D60: TAOS | E60: 34265 | F60: -36066.45 | G60: 3VVUX7B25RM026254 | H60: 12
A61: 240250 | B61: 2024 | C61: VOLKSWAGEN | D61: TAOS | E61: 28211 | G61: 3VVCX7B23RM011327 | H61: 12
A62: 240253 | B62: 2024 | C62: VOLKSWAGEN | D62: TIGUAN | E62: 47482.92 | F62: -47526.15 | G62: 3VV4B7AX0RM043880 | H62: 12
A63: 240262 | B63: 2024 | C63: VOLKSWAGEN | D63: TIGUAN | E63: 40734 | F63: -43358.7 | G63: 3VV8B7AX4RM058738 | H63: 9
A64: 240266 | B64: 2024 | C64: VOLKSWAGEN | D64: GOLF GTI | E64: 37806 | F64: -40179.3 | G64: WVWRA7CD7RW142545 | H64: 3
A65: 240270 | B65: 2024 | C65: VOLKSWAGEN | D65: TIGUAN | E65: 44886 | F65: -47718.3 | G65: 3VV4B7AXXRM065708 | H65: 3
A66: 240263 | B66: 2024 | C66: VOLKSWAGEN | D66: TIGUAN | E66: 44154 | F66: -46949.7 | G66: 3VV4B7AXXRM047399 | H66: 3
A67: 240268 | B67: 2024 | C67: VOLKSWAGEN | D67: TIGUAN | E67: 44154 | F67: -46949.7 | G67: 3VV4B7AX3RM061712 | H67: 3
A68: 240264 | B68: 2024 | C68: VOLKSWAGEN | D68: TIGUAN | E68: 43701 | F68: -46474.05 | G68: 3VV4B7AX7RM058599 | H68: 3
A69: 240267 | B69: 2024 | C69: VOLKSWAGEN | D69: TIGUAN | E69: 43701 | F69: -46474.05 | G69: 3VV4B7AX9RM059415 | H69: 3
A70: 240269 | B70: 2024 | C70: VOLKSWAGEN | D70: TIGUAN | E70: 40734 | F70: -43358.7 | G70: 3VV8B7AX7RM066865 | H70: 3
A71: 240265 | B71: 2024 | C71: VOLKSWAGEN | D71: TIGUAN | E71: 39069 | F71: -41610.45 | G71: 3VVMB7AX2RM024991 | H71: 3
A72: 240273 | B72: 2024 | C72: VOLKSWAGEN | D72: TIGUAN | E72: 44154 | F72: -46949.7 | G72: 3VV4B7AX9RM059835 | H72: 2

Sheet 2pager
B1: =Parametres!$B$1&" "&"2 pager"&" "&Parametres!$B$3&" "&Parametres!$B$4 -> Volks 2 pager Mars 2026
B3: New | C3: Actual | D3: Budget | E3: 2023 | F3: ▲ Budget | G3: ▲2023 | H3: % ▲ Budget | I3: % ▲ 2023 | J3: Commentaires
B4: Units | C4: =+Print_Mois!$J$13+Print_Mois!$J$15 -> 56 | D4: =+Print_Mois!$D$13+Print_Mois!$D$15 -> 74 | E4: =+Print_Mois!$O$13+Print_Mois!$O$15 -> 55 | F4: =+IFERROR($C4-D4,"") -> -18 | G4: =+IFERROR($C4-E4,"") -> 1 | H4: =+IFERROR(F4/ABS($D4),"") -> -0.24324324 | I4: =+IFERROR(G4/ABS($E4),"") -> 0.018181818 | J4: L'arrêt des livraisons ID4 a eu un impact significatif sur le mois de septembre. Les profits unitaires au budget n'en tenaient pas tant compte mais la comptétion tant inter-dealers qu'inter-marques a relancé les négociations sur les prix. Notre bureau commercial est encore sous le coup du turnover. Les autres revenus sont la conséquence directe de la baisse de volume d'unités livrées.
B5: Front Margin | C5: =+Print_Mois!$L$13+Print_Mois!$L$15 -> 94806.04 | D5: =+Print_Mois!$F$13+Print_Mois!$F$15 -> 167406.81 | E5: =+Print_Mois!$Q$13+Print_Mois!$Q$15 -> 108826.24 | F5: =+IFERROR($C5-D5,"") -> -72600.769 | G5: =+IFERROR($C5-E5,"") -> -14020.2 | H5: =+IFERROR(F5/ABS($D5),"") -> -0.43367871 | I5: =+IFERROR(G5/ABS($E5),"") -> -0.12883106
B6: Front margin / unit | C6: =+C5/C4 -> 1692.965 | D6: =+D5/D4 -> 2262.2542 | E6: =+E5/E4 -> 1978.6589 | F6: =+IFERROR($C6-D6,"") -> -569.28918 | G6: =+IFERROR($C6-E6,"") -> -285.69391 | H6: =+IFERROR(F6/ABS($D6),"") -> -0.25164687 | I6: =+IFERROR(G6/ABS($E6),"") -> -0.14438765
B7: $ Salaires et commission | C7: =+Print_Mois!$L$31 -> 40277.06 | D7: =+Print_Mois!$F$31 -> 52355.763 | E7: =+Print_Mois!$Q$31 -> 30699.67 | F7: =+IFERROR($C7-D7,"") -> -12078.703 | G7: =+IFERROR($C7-E7,"") -> 9577.39 | H7: =+IFERROR(F7/ABS($D7),"") -> -0.23070437 | I7: =+IFERROR(G7/ABS($E7),"") -> 0.31197045
B8: % Salaires et commission | C8: =+C7/C5 -> 0.42483643 | D8: =+D7/D5 -> 0.31274572 | E8: =+E7/E5 -> 0.28209805 | F8: =+IFERROR($C8-D8,"") -> 0.11209071 | G8: =+IFERROR($C8-E8,"") -> 0.14273839 | H8: =+IFERROR(F8/ABS($D8),"") -> 0.35840846 | I8: =+IFERROR(G8/ABS($E8),"") -> 0.50598856
B9: Back Margin | C9: =+Print_Mois!$L$24 -> 55577.27 | D9: =+Print_Mois!$F$24 -> 88800 | E9: =+Print_Mois!$Q$24 -> 33648 | F9: =+IFERROR($C9-D9,"") -> -33222.73 | G9: =+IFERROR($C9-E9,"") -> 21929.27 | H9: =+IFERROR(F9/ABS($D9),"") -> -0.37412984 | I9: =+IFERROR(G9/ABS($E9),"") -> 0.65172581
B10: Back Margin / unit | C10: =+C9/C4 -> 992.45125 | D10: =+D9/D4 -> 1200 | E10: =+E9/E4 -> 611.78182 | F10: =+IFERROR($C10-D10,"") -> -207.54875 | G10: =+IFERROR($C10-E10,"") -> 380.66943 | H10: =+IFERROR(F10/ABS($D10),"") -> -0.17295729 | I10: =+IFERROR(G10/ABS($E10),"") -> 0.6222307
B11: $ commission FI | C11: =+Print_Mois!$L$32 -> 11178.89 | D11: =+Print_Mois!$F$32 -> 17760 | E11: =+Print_Mois!$Q$32 -> 10329.58 | F11: =+IFERROR($C11-D11,"") -> -6581.11 | G11: =+IFERROR($C11-E11,"") -> 849.31 | H11: =+IFERROR(F11/ABS($D11),"") -> -0.370558 | I11: =+IFERROR(G11/ABS($E11),"") -> 0.082221155
B12: % commission FI | C12: =+C11/C9 -> 0.2011414 | D12: =+D11/D9 -> 0.2 | E12: =+E11/E9 -> 0.30698942 | F12: =+IFERROR($C12-D12,"") -> 0.0011414019 | G12: =+IFERROR($C12-E12,"") -> -0.10584802 | H12: =+IFERROR(F12/ABS($D12),"") -> 0.0057070094 | I12: =+IFERROR(G12/ABS($E12),"") -> -0.3447937
B13: Variable fees | C13: =+Print_Mois!$L$41-C7-C11 -> 40798.17 | D13: =+Print_Mois!$F$41-D7-D11 -> 41639.088 | E13: =+Print_Mois!$Q$41-E7-E11 -> 53243.05 | F13: =+IFERROR($C13-D13,"") -> -840.91826 | G13: =+IFERROR($C13-E13,"") -> -12444.88 | H13: =+IFERROR(F13/ABS($D13),"") -> -0.020195405 | I13: =+IFERROR(G13/ABS($E13),"") -> -0.23373717
B14: Variable fees / units | C14: =+C13/C4 -> 728.53875 | D14: =+D13/D4 -> 562.69038 | E14: =+E13/E4 -> 968.05545 | F14: =+IFERROR($C14-D14,"") -> 165.84837 | G14: =+IFERROR($C14-E14,"") -> -239.5167 | H14: =+IFERROR(F14/ABS($D14),"") -> 0.29474179 | I14: =+IFERROR(G14/ABS($E14),"") -> -0.24742044
B15: Other Revenues | C15: =+Print_Mois!$L$83 -> 192613.85 | D15: =+Print_Mois!$F$83 -> 169626.43 | E15: =+Print_Mois!$Q$83 -> 93446 | F15: =+IFERROR($C15-D15,"") -> 22987.417 | G15: =+IFERROR($C15-E15,"") -> 99167.85 | H15: =+IFERROR(F15/ABS($D15),"") -> 0.13551789 | I15: =+IFERROR(G15/ABS($E15),"") -> 1.0612316
B16: Inventory
B17: Units | C17: =Inventaire_Neuf!L3 -> 71 | D17: 61 | E17: 164 | F17: =+IFERROR($C17-D17,"") -> 10 | G17: =+IFERROR($C17-E17,"") -> -93 | H17: =+IFERROR(F17/ABS($D17),"") -> 0.16393443 | I17: =+IFERROR(G17/ABS($E17),"") -> -0.56707317
B18: $ | C18: =Inventaire_Neuf!L2 -> 3059537.1 | D18: 2233570 | E18: 5689693.2 | F18: =+IFERROR($C18-D18,"") -> 825967.15 | G18: =+IFERROR($C18-E18,"") -> -2630156 | H18: =+IFERROR(F18/ABS($D18),"") -> 0.36979685 | I18: =+IFERROR(G18/ABS($E18),"") -> -0.46226676
B20: Used | C20: Actual | D20: Budget | E20: =$E$3 -> 2023 | F20: ▲ Budget | G20: =$G$3 -> ▲2023 | H20: % ▲ Budget | I20: =$I$3 -> % ▲ 2023 | J20: Commentaires
B21: Units | C21: =+Print_Mois!$J$97 -> 18 | D21: =+Print_Mois!$D$97 -> 49 | E21: =+Print_Mois!$O$97 -> 30 | F21: =+IFERROR($C21-D21,"") -> -31 | G21: =+IFERROR($C21-E21,"") -> -12 | H21: =+IFERROR(F21/ABS($D21),"") -> -0.63265306 | I21: =+IFERROR(G21/ABS($E21),"") -> -0.4 | J21: Le volume et les résultats du bureau commercial sont maintenant en ligne avec les attentes. Le profit unitaire "front" est le dernier sujet d'ajustement côté chiffre en même temps que la prise de contrôle des leads, du temps de réponse et de ce que l'on en fait ! Invenaire sain, marchandisage optimisé. Il nous reste à être extrèmement vigilants et rigoureux dans le suivi de ces opérations.
B22: Front Margin | C22: =+Print_Mois!$L$97 -> 13303.71 | D22: =+Print_Mois!$F$97 -> 73500 | E22: =+Print_Mois!$Q$97 -> 41585.52 | F22: =+IFERROR($C22-D22,"") -> -60196.29 | G22: =+IFERROR($C22-E22,"") -> -28281.81 | H22: =+IFERROR(F22/ABS($D22),"") -> -0.81899714 | I22: =+IFERROR(G22/ABS($E22),"") -> -0.68008792
B23: Front margin / unit | C23: =+C22/C21 -> 739.095 | D23: =+D22/D21 -> 1500 | E23: =+E22/E21 -> 1386.184 | F23: =+IFERROR($C23-D23,"") -> -760.905 | G23: =+IFERROR($C23-E23,"") -> -647.089 | H23: =+IFERROR(F23/ABS($D23),"") -> -0.50727 | I23: =+IFERROR(G23/ABS($E23),"") -> -0.46681321
B24: $ Salaires et commission | C24: =+Print_Mois!$L$112 -> 10589.1 | D24: =+Print_Mois!$F$112 -> 22645 | E24: =+Print_Mois!$Q$112 -> 14256.15 | F24: =+IFERROR($C24-D24,"") -> -12055.9 | G24: =+IFERROR($C24-E24,"") -> -3667.05 | H24: =+IFERROR(F24/ABS($D24),"") -> -0.53238684 | I24: =+IFERROR(G24/ABS($E24),"") -> -0.25722583
B25: % Salaires et commission | C25: =+C24/C22 -> 0.7959509 | D25: =+D24/D22 -> 0.30809524 | E25: =+E24/E22 -> 0.34281524 | F25: =+IFERROR($C25-D25,"") -> 0.48785567 | G25: =+IFERROR($C25-E25,"") -> 0.45313566 | H25: =+IFERROR(F25/ABS($D25),"") -> 1.5834573 | I25: =+IFERROR(G25/ABS($E25),"") -> 1.3218072
B26: Back Margin | C26: =+Print_Mois!$L$105 -> 25594.91 | D26: =+Print_Mois!$F$105 -> 98000 | E26: =+Print_Mois!$Q$105 -> 56059.2 | F26: =+IFERROR($C26-D26,"") -> -72405.09 | G26: =+IFERROR($C26-E26,"") -> -30464.29 | H26: =+IFERROR(F26/ABS($D26),"") -> -0.73882745 | I26: =+IFERROR(G26/ABS($E26),"") -> -0.54343069
B27: Back Margin / unit | C27: =+C26/C21 -> 1421.9394 | D27: =+D26/D21 -> 2000 | E27: =+E26/E21 -> 1868.64 | F27: =+IFERROR($C27-D27,"") -> -578.06056 | G27: =+IFERROR($C27-E27,"") -> -446.70056 | H27: =+IFERROR(F27/ABS($D27),"") -> -0.28903028 | I27: =+IFERROR(G27/ABS($E27),"") -> -0.23905116
B28: $ commission FI | C28: =+Print_Mois!$L$113 -> 5756.98 | D28: =+Print_Mois!$F$113 -> 25575.8 | E28: =+Print_Mois!$Q$113 -> 15696.14 | F28: =+IFERROR($C28-D28,"") -> -19818.82 | G28: =+IFERROR($C28-E28,"") -> -9939.16 | H28: =+IFERROR(F28/ABS($D28),"") -> -0.77490519 | I28: =+IFERROR(G28/ABS($E28),"") -> -0.6332232
B29: % commission FI | C29: =+C28/C26 -> 0.22492675 | D29: =+D28/D26 -> 0.26097755 | E29: =+E28/E26 -> 0.27999222 | F29: =+IFERROR($C29-D29,"") -> -0.036050801 | G29: =+IFERROR($C29-E29,"") -> -0.055065469 | H29: =+IFERROR(F29/ABS($D29),"") -> -0.13813755 | I29: =+IFERROR(G29/ABS($E29),"") -> -0.19666785
B30: Variable fees | C30: =+Print_Mois!$L$122-C24-C28 -> 12509.58 | D30: =+Print_Mois!$F$122-D24-D28 -> 20374.25 | E30: =+Print_Mois!$Q$122-E24-E28 -> 17692.36 | F30: =+IFERROR($C30-D30,"") -> -7864.67 | G30: =+IFERROR($C30-E30,"") -> -5182.78 | H30: =+IFERROR(F30/ABS($D30),"") -> -0.38601028 | I30: =+IFERROR(G30/ABS($E30),"") -> -0.29293887
B31: Variable fees / units | C31: =+C30/C21 -> 694.97667 | D31: =+D30/D21 -> 415.80102 | E31: =+E30/E21 -> 589.74533 | F31: =+IFERROR($C31-D31,"") -> 279.17565 | G31: =+IFERROR($C31-E31,"") -> 105.23133 | H31: =+IFERROR(F31/ABS($D31),"") -> 0.67141645 | I31: =+IFERROR(G31/ABS($E31),"") -> 0.17843521
B32: Other Revenues | C32: =+Print_Mois!$L$163 -> 8652 | D32: =+Print_Mois!$F$163 -> 22297.45 | E32: =+Print_Mois!$Q$163 -> 14076 | F32: =+IFERROR($C32-D32,"") -> -13645.45 | G32: =+IFERROR($C32-E32,"") -> -5424 | H32: =+IFERROR(F32/ABS($D32),"") -> -0.61197357 | I32: =+IFERROR(G32/ABS($E32),"") -> -0.38533674
B33: Inventory
B34: Units | C34: =Inventaire_Used!N3 -> 111 | D34: 68 | E34: 92 | F34: =+IFERROR($C34-D34,"") -> 43 | G34: =+IFERROR($C34-E34,"") -> 19 | H34: =+IFERROR(F34/ABS($D34),"") -> 0.63235294 | I34: =+IFERROR(G34/ABS($E34),"") -> 0.20652174
B35: $ | C35: =Inventaire_Used!N2 -> 2779322.1 | D35: 1072231 | E35: 1510979 | F35: =+IFERROR($C35-D35,"") -> 1707091.1 | G35: =+IFERROR($C35-E35,"") -> 1268343.1 | H35: =+IFERROR(F35/ABS($D35),"") -> 1.5920927 | I35: =+IFERROR(G35/ABS($E35),"") -> 0.83941809
B37: Service | C37: Actual | D37: Budget | E37: =$E$3 -> 2023 | F37: ▲ Budget | G37: =$G$3 -> ▲2023 | H37: % ▲ Budget | I37: =$I$3 -> % ▲ 2023 | J37: Commentaires
B38: Revenus | C38: =+Print_Mois!$K$194 -> 309003.25 | D38: =+Print_Mois!$E$194 -> 329436.56 | E38: =+Print_Mois!$P$194 -> 311810.16 | F38: =+IFERROR($C38-D38,"") -> -20433.308 | G38: =+IFERROR($C38-E38,"") -> -2806.91 | H38: =+IFERROR(F38/ABS($D38),"") -> -0.062025017 | I38: =+IFERROR(G38/ABS($E38),"") -> -0.0090019838 | J38: Très belle progression versus 2023, autant sur le fait de voir monter le brut globalement que sur le contrôle des dépenses. Le modèle de fonctionnement de la mixité de véhicules de courtoisies, Uber Pro et chauffeurs fonctionne. Bon mois de Csi à côté de la performance financière.
B39: Gross margin | C39: =+Print_Mois!$L$194 -> 224558.39 | D39: =+Print_Mois!$F$194 -> 228107.7 | E39: =+Print_Mois!$Q$194 -> 219030.28 | F39: =+IFERROR($C39-D39,"") -> -3549.3129 | G39: =+IFERROR($C39-E39,"") -> 5528.11 | H39: =+IFERROR(F39/ABS($D39),"") -> -0.015559812 | I39: =+IFERROR(G39/ABS($E39),"") -> 0.025239022
B40: $ Revenus / #WO client | C40: =+Print_Mois!$K$172/Print_Mois!$J$172 -> 353.18657 | D40: =+IFERROR(Print_Mois!$E$172/Print_Mois!$D$172,"") -> 350 | E40: =+Print_Mois!$P$172/Print_Mois!$O$172 -> 360.50129 | F40: =+IFERROR($C40-D40,"") -> 3.1865653 | G40: =+IFERROR($C40-E40,"") -> -7.3147288 | H40: =+IFERROR(F40/ABS($D40),"") -> 0.0091044724 | I40: =+IFERROR(G40/ABS($E40),"") -> -0.020290437
B41: $ Revenus / #WO garantie | C41: =+Print_Mois!$K$175/Print_Mois!$J$175 -> 442.52294 | D41: =+IFERROR(Print_Mois!$E$175/Print_Mois!$D$175,"") -> 300 | E41: =+Print_Mois!$P$175/Print_Mois!$O$175 -> 289.85456 | F41: =+IFERROR($C41-D41,"") -> 142.52294 | G41: =+IFERROR($C41-E41,"") -> 152.66838 | H41: =+IFERROR(F41/ABS($D41),"") -> 0.47507647 | I41: =+IFERROR(G41/ABS($E41),"") -> 0.52670682
B42: Lost time | C42: =+Print_Mois!$L$184 -> -2324.03 | D42: =+Print_Mois!$F$184 -> -3337.986 | E42: =+Print_Mois!$Q$184 -> -634.37 | F42: =+IFERROR($C42-D42,"") -> 1013.956 | G42: =+IFERROR($C42-E42,"") -> -1689.66 | H42: =+IFERROR(F42/ABS($D42),"") -> 0.30376281 | I42: =+IFERROR(G42/ABS($E42),"") -> -2.6635244
B43: Total salaries | C43: =+Print_Mois!$L$210 -> 115222.41 | D43: =+Print_Mois!$F$210 -> 145403.49 | E43: =+Print_Mois!$Q$210 -> 101345.1 | F43: =+IFERROR($C43-D43,"") -> -30181.082 | G43: =+IFERROR($C43-E43,"") -> 13877.31 | H43: =+IFERROR(F43/ABS($D43),"") -> -0.20756779 | I43: =+IFERROR(G43/ABS($E43),"") -> 0.13693124
B44: Salaries | C44: =+SUM(Print_Mois!$L$198:$L$204) -> 62584.67 | D44: =+SUM(Print_Mois!$F$198:$F$204) -> 84986.959 | E44: =+SUM(Print_Mois!$Q$198:$Q$204) -> 58391.07 | F44: =+IFERROR($C44-D44,"") -> -22402.289 | G44: =+IFERROR($C44-E44,"") -> 4193.6 | H44: =+IFERROR(F44/ABS($D44),"") -> -0.26359679 | I44: =+IFERROR(G44/ABS($E44),"") -> 0.071819201
B45: Fringes | C45: =+SUM(Print_Mois!$L$205:$L$209) -> 52637.74 | D45: =+SUM(Print_Mois!$F$205:$F$209) -> 60416.532 | E45: =+SUM(Print_Mois!$Q$205:$Q$209) -> 42954.03 | F45: =+IFERROR($C45-D45,"") -> -7778.7921 | G45: =+IFERROR($C45-E45,"") -> 9683.71 | H45: =+IFERROR(F45/ABS($D45),"") -> -0.12875271 | I45: =+IFERROR(G45/ABS($E45),"") -> 0.22544357
B46: Total salaries / Revenus | C46: =+C43/C38 -> 0.37288414 | D46: =+D43/D38 -> 0.44137024 | E46: =+E43/E38 -> 0.3250218 | F46: =+IFERROR($C46-D46,"") -> -0.0684861 | G46: =+IFERROR($C46-E46,"") -> 0.047862335 | H46: =+IFERROR(F46/ABS($D46),"") -> -0.15516701 | I46: =+IFERROR(G46/ABS($E46),"") -> 0.14725884
B47: Frais véhicules de cie | C47: =+Print_Mois!$L$213 -> 9445.3 | D47: =+Print_Mois!$F$213 -> 14083.739 | E47: =+Print_Mois!$Q$213 -> 10165.46 | F47: =+IFERROR($C47-D47,"") -> -4638.4394 | G47: =+IFERROR($C47-E47,"") -> -720.16 | H47: =+IFERROR(F47/ABS($D47),"") -> -0.32934715 | I47: =+IFERROR(G47/ABS($E47),"") -> -0.070843818
B49: Pieces | C49: Actual | D49: Budget | E49: =$E$3 -> 2023 | F49: ▲ Budget | G49: =$G$3 -> ▲2023 | H49: % ▲ Budget | I49: =$I$3 -> % ▲ 2023 | J49: Commentaires
B50: Revenus | C50: =+Print_Mois!$J$314 -> 589674.65 | D50: =+Print_Mois!$D$314 -> 543337.75 | E50: =+Print_Mois!$O$314 -> 543573.3 | F50: =+IFERROR($C50-D50,"") -> 46336.904 | G50: =+IFERROR($C50-E50,"") -> 46101.35 | H50: =+IFERROR(F50/ABS($D50),"") -> 0.085281954 | I50: =+IFERROR(G50/ABS($E50),"") -> 0.084811653 | J50: Le wholesale est LA machine du département. Analyse rapide mais son point le plus avantageux est la portion de booster le volume d'achats chez l'OEM. Car en fait de $ de ventes, on mobilise quasiment 1 employé, beaucoup d'espace et la quasi-totalité de nos crédits de retour gratuits chez VW. Notre commis sénior n'a pas la maturité analytique pour faire des choix d'anticipation stratégique. Sujet à creuser avant fin q4.
B51: Clients | C51: =+Print_Mois!$J$295 -> 68042.28 | D51: =+Print_Mois!$D$295 -> 84563.813 | E51: =+Print_Mois!$O$295 -> 76633.43 | F51: =+IFERROR($C51-D51,"") -> -16521.533 | G51: =+IFERROR($C51-E51,"") -> -8591.15 | H51: =+IFERROR(F51/ABS($D51),"") -> -0.19537356 | I51: =+IFERROR(G51/ABS($E51),"") -> -0.11210708
B52: Garantie | C52: =+Print_Mois!$J$297 -> 68776.24 | D52: =+Print_Mois!$D$297 -> 99102.372 | E52: =+Print_Mois!$O$297 -> 136018.11 | F52: =+IFERROR($C52-D52,"") -> -30326.132 | G52: =+IFERROR($C52-E52,"") -> -67241.87 | H52: =+IFERROR(F52/ABS($D52),"") -> -0.30600813 | I52: =+IFERROR(G52/ABS($E52),"") -> -0.49435968
B53: Wholesale | C53: =+Print_Mois!$J$300 -> 280445.62 | D53: =+Print_Mois!$D$300 -> 186966.87 | E53: =+Print_Mois!$O$300 -> 219537.13 | F53: =+IFERROR($C53-D53,"") -> 93478.751 | G53: =+IFERROR($C53-E53,"") -> 60908.49 | H53: =+IFERROR(F53/ABS($D53),"") -> 0.49997495 | I53: =+IFERROR(G53/ABS($E53),"") -> 0.27744049
B54: Tires | C54: =+Print_Mois!$J$307 -> 39869.18 | D54: =+Print_Mois!$D$307 -> 29677.516 | E54: =+Print_Mois!$O$307 -> 28787.21 | F54: =+IFERROR($C54-D54,"") -> 10191.664 | G54: =+IFERROR($C54-E54,"") -> 11081.97 | H54: =+IFERROR(F54/ABS($D54),"") -> 0.34341364 | I54: =+IFERROR(G54/ABS($E54),"") -> 0.38496159
B55: All others | C55: =+C50-SUM(C51:C54) -> 132541.33 | D55: =+D50-SUM(D51:D54) -> 143027.18 | E55: =+E50-SUM(E51:E54) -> 82597.42 | F55: =+IFERROR($C55-D55,"") -> -10485.846 | G55: =+IFERROR($C55-E55,"") -> 49943.91 | H55: =+IFERROR(F55/ABS($D55),"") -> -0.07331366 | I55: =+IFERROR(G55/ABS($E55),"") -> 0.60466671
B56: Gross margin | C56: =+Print_Mois!$L$314 -> 155663.02 | D56: =+Print_Mois!$F$314 -> 152441.54 | E56: =+Print_Mois!$Q$314 -> 122287.43 | F56: =+IFERROR($C56-D56,"") -> 3221.4817 | G56: =+IFERROR($C56-E56,"") -> 33375.59 | H56: =+IFERROR(F56/ABS($D56),"") -> 0.021132571 | I56: =+IFERROR(G56/ABS($E56),"") -> 0.2729274
B57: $ Revenus / #WO client | C57: =+Print_Mois!$J$295/Print_Mois!$J$172 -> 206.81544 | D57: =+IFERROR(Print_Mois!$D$295/Print_Mois!$D$172,"") -> 228.31537 | E57: =+Print_Mois!$O$295/Print_Mois!$O$172 -> 225.39244 | F57: =+IFERROR($C57-D57,"") -> -21.499933 | G57: =+IFERROR($C57-E57,"") -> -18.577 | H57: =+IFERROR(F57/ABS($D57),"") -> -0.094167699 | I57: =+IFERROR(G57/ABS($E57),"") -> -0.08242069
B58: $ Revenus / #WO garantie | C58: =+Print_Mois!$J$297/Print_Mois!$J$175 -> 404.56612 | D58: =+IFERROR(Print_Mois!$D$297/Print_Mois!$D$175,"") -> 340.65471 | E58: =+Print_Mois!$O$297/Print_Mois!$O$175 -> 473.9307 | F58: =+IFERROR($C58-D58,"") -> 63.911408 | G58: =+IFERROR($C58-E58,"") -> -69.364579 | H58: =+IFERROR(F58/ABS($D58),"") -> 0.18761346 | I58: =+IFERROR(G58/ABS($E58),"") -> -0.14636017
B59: Salaires autres | C59: =+Print_Mois!$L$320 -> 6588.69 | D59: =+Print_Mois!$F$320 -> 0 | E59: =+Print_Mois!$Q$320 -> 113.92 | F59: =+IFERROR($C59-D59,"") -> 6588.69 | G59: =+IFERROR($C59-E59,"") -> 6474.77 | H59: =+IFERROR(F59/ABS($D59),"") | I59: =+IFERROR(G59/ABS($E59),"") -> 56.836113
B61: Others | C61: Actual | D61: Budget | E61: =$E$3 -> 2023 | F61: ▲ Budget | G61: =$G$3 -> ▲2023 | H61: % ▲ Budget | I61: =$I$3 -> % ▲ 2023 | J61: Commentaires
B62: Total salaries / Gross profits | C62: =+Print_Mois!$AF$433/Print_Mois!$AF$407 -> 0.45749024 | D62: =+Print_Mois!$Z$433/Print_Mois!$Z$407 -> 0.39249961 | E62: =+Print_Mois!$AL$433/Print_Mois!$AL$407 -> 0.45933094 | F62: =+IFERROR($C62-D62,"") -> 0.06499063 | G62: =+IFERROR($C62-E62,"") -> -0.001840696 | H62: =+IFERROR(F62/ABS($D62),"") -> 0.16558139 | I62: =+IFERROR(G62/ABS($E62),"") -> -0.0040073417
B63: Headcounts | C63: 57 | D63: 59 | E63: 56 | F63: =+IFERROR($C63-D63,"") -> -2 | G63: =+IFERROR($C63-E63,"") -> 1 | H63: =+IFERROR(F63/ABS($D63),"") -> -0.033898305 | I63: =+IFERROR(G63/ABS($E63),"") -> 0.017857143
B64: Marketing | C64: =N17+Print_Mois!$AF$414+Print_Mois!$AF$434 -> 8785.09 | D64: =+Print_Mois!$Z$414+Print_Mois!$Z$434 -> 18779.75 | E64: =+Print_Mois!$AL$414+Print_Mois!$AL$434 -> 50088.98 | F64: =+IFERROR($C64-D64,"") -> -9994.66 | G64: =+IFERROR($C64-E64,"") -> -41303.89 | H64: =+IFERROR(F64/ABS($D64),"") -> -0.5322041 | I64: =+IFERROR(G64/ABS($E64),"") -> -0.82461032
B65: Other semi-fixed expenses | C65: =+Print_Mois!$AF$452-Print_Mois!$AF$434 -> 108678 | D65: =+Print_Mois!$Z$452-Print_Mois!$Z$434 -> 119106.5 | E65: =+Print_Mois!$AL$452-Print_Mois!$AL$434 -> 128328.93 | F65: =+IFERROR($C65-D65,"") -> -10428.5 | G65: =+IFERROR($C65-E65,"") -> -19650.93 | H65: =+IFERROR(F65/ABS($D65),"") -> -0.087556097 | I65: =+IFERROR(G65/ABS($E65),"") -> -0.15312938
B66: Floor plan interest | C66: =+Print_Mois!$AF$415 -> 29401.98 | D66: =+Print_Mois!$Z$415 -> 23826.588 | E66: =+Print_Mois!$AL$415 -> 26082.33 | F66: =+IFERROR($C66-D66,"") -> 5575.3917 | G66: =+IFERROR($C66-E66,"") -> 3319.65 | H66: =+IFERROR(F66/ABS($D66),"") -> 0.23399874 | I66: =+IFERROR(G66/ABS($E66),"") -> 0.12727582
B67: Others Revenues | C67: =+Print_Mois!$AF$481-C32-C15 -> 50186.14 | D67: =+Print_Mois!$Z$481-D32-D15 -> 20000 | E67: =+Print_Mois!$AL$481-E32-E15 -> 42727.95 | F67: =+IFERROR($C67-D67,"") -> 30186.14 | G67: =+IFERROR($C67-E67,"") -> 7458.19 | H67: =+IFERROR(F67/ABS($D67),"") -> 1.509307 | I67: =+IFERROR(G67/ABS($E67),"") -> 0.17455062
B69: P&L | C69: Actual | D69: Budget | E69: =$E$3 -> 2023 | F69: ▲ Budget | G69: =$G$3 -> ▲2023 | H69: % ▲ Budget | I69: =$I$3 -> % ▲ 2023 | J69: Commentaires
B70: Selling and Marketing | C70: =+Print_Mois!$AF$419-Print_Mois!$AF$415+Print_Mois!$AF$434+Print_Mois!$AF$435+Print_Mois!$AF$436 -> 118986.87 | D70: =+Print_Mois!$Z$419-Print_Mois!$Z$415+Print_Mois!$Z$434+Print_Mois!$Z$435+Print_Mois!$Z$436 -> 196672.96 | E70: =+Print_Mois!$AL$419-Print_Mois!$AL$415+Print_Mois!$AL$434+Print_Mois!$AL$435+Print_Mois!$AL$436 -> 161823.91 | F70: =+IFERROR($C70-D70,"") -> -77686.09 | G70: =+IFERROR($C70-E70,"") -> -42837.04 | H70: =+IFERROR(F70/ABS($D70),"") -> -0.39500138 | I70: =+IFERROR(G70/ABS($E70),"") -> -0.26471391 | J70: Malgré une baisse des bruts aux ventes nous restons forts sur nos coût et donc cela génère une amélioration légère de notre EBITDA versus 2023, c'est notre objectif qui sera aussi celui des derniers mois de 2024.
B71: S&M / Brut | C71: =+C70/Print_Mois!$AF$407 -> 0.19438787 | D71: =+D70/Print_Mois!$Z$407 -> 0.23224925 | E71: =+E70/Print_Mois!$AL$407 -> 0.26625469 | F71: =+IFERROR($C71-D71,"") -> -0.03786138 | G71: =+IFERROR($C71-E71,"") -> -0.071866815 | H71: =+IFERROR(F71/ABS($D71),"") -> -0.16302046 | I71: =+IFERROR(G71/ABS($E71),"") -> -0.26991756
B72: General & administrative | C72: =+Print_Mois!$AF$466+Print_Mois!$AF$433+Print_Mois!$AF$437+Print_Mois!$AF$439+SUM(Print_Mois!$AF$440:$AF$448)+Print_Mois!$AF$438 -> 482512.55 | D72: =+Print_Mois!$Z$466+Print_Mois!$Z$433+Print_Mois!$Z$437+Print_Mois!$Z$439+SUM(Print_Mois!$Z$440:$Z$448)+Print_Mois!$Z$438 -> 535486.93 | E72: =+Print_Mois!$AL$466+Print_Mois!$AL$433+Print_Mois!$AL$437+Print_Mois!$AL$439+SUM(Print_Mois!$AL$440:$AL$448)+Print_Mois!$AL$438 -> 448131.57 | F72: =+IFERROR($C72-D72,"") -> -52974.376 | G72: =+IFERROR($C72-E72,"") -> 34380.98 | H72: =+IFERROR(F72/ABS($D72),"") -> -0.098927488 | I72: =+IFERROR(G72/ABS($E72),"") -> 0.076720727
B73: G&A / Brut | C73: =+C72/Print_Mois!$AF$407 -> 0.78827679 | D73: =+D72/Print_Mois!$Z$407 -> 0.63235149 | E73: =+E72/Print_Mois!$AL$407 -> 0.73732696 | F73: =+IFERROR($C73-D73,"") -> 0.1559253 | G73: =+IFERROR($C73-E73,"") -> 0.050949834 | H73: =+IFERROR(F73/ABS($D73),"") -> 0.24658012 | I73: =+IFERROR(G73/ABS($E73),"") -> 0.069100733
B74: EBITDA | C74: =+Print_Mois!$AF$483+Print_Mois!$AF$415 -> 262063.13 | D74: =+Print_Mois!$Z$483+Print_Mois!$Z$415 -> 326582.48 | E74: =+Print_Mois!$AL$483+Print_Mois!$AL$415 -> 148073.1 | F74: =+IFERROR($C74-D74,"") -> -64519.345 | G74: =+IFERROR($C74-E74,"") -> 113990.03 | H74: =+IFERROR(F74/ABS($D74),"") -> -0.19755912 | I74: =+IFERROR(G74/ABS($E74),"") -> 0.76982268
B75: EBITDA % | C75: =+C74/Print_Mois!$AF$406 -> 0.044845901 | D75: =+D74/Print_Mois!$Z$406 -> 0.054451235 | E75: =+E74/Print_Mois!$AL$406 -> 0.032458181 | F75: =+IFERROR($C75-D75,"") -> -0.0096053335 | G75: =+IFERROR($C75-E75,"") -> 0.01238772 | H75: =+IFERROR(F75/ABS($D75),"") -> -0.17640249 | I75: =+IFERROR(G75/ABS($E75),"") -> 0.3816517
B76: EBIT | C76: =N9+Print_Mois!$AF$498 -> 245121.41 | D76: =+Print_Mois!$Z$498 -> 293239.22 | E76: =+Print_Mois!$AL$498 -> 80421.77 | F76: =+IFERROR($C76-D76,"") -> -48117.81 | G76: =+IFERROR($C76-E76,"") -> 164699.64 | H76: =+IFERROR(F76/ABS($D76),"") -> -0.16409064 | I76: =+IFERROR(G76/ABS($E76),"") -> 2.0479485
B77: EBIT % | C77: =+C76/Print_Mois!$AF$406 -> 0.041946727 | D77: =+D76/Print_Mois!$Z$406 -> 0.0488919 | E77: =+E76/Print_Mois!$AL$406 -> 0.017628755 | F77: =+IFERROR($C77-D77,"") -> -0.0069451728 | G77: =+IFERROR($C77-E77,"") -> 0.024317972 | H77: =+IFERROR(F77/ABS($D77),"") -> -0.1420516 | I77: =+IFERROR(G77/ABS($E77),"") -> 1.3794492
B79: "Pacing" du 30
B80: EBITDA | C80: 59525 | D80: 0.011
B81: Écart Fav / (Défav) | C81: =+C74-C80 -> 202538.13
B83: EBIT | C83: -23522 | D83: -0.004
B84: Écart Fav / (Défav) | C84: =+C76-C83 -> 268643.41
B86: =+Parametres!B1 -> Volks | C86: =Parametres!$B$3&" "&Parametres!$B$4 -> Mars 2026 | D86: AAJ
B87: =CONCATENATE("Réalisé ",Parametres!$B$3," ",Parametres!$B$4) -> Réalisé Mars 2026 | C87: =+C76 -> 245121.41 | D87: =+Print_AAD!AF498 -> 197423.6
B88: =CONCATENATE("Budget ",Parametres!$B$3," ",Parametres!$B$4) -> Budget Mars 2026 | C88: =+D76 -> 293239.22 | D88: =+Print_AAD!Z498 -> 326676.24
B89: =CONCATENATE("Réalisé ",Parametres!$B$3," ",Parametres!$B$4-1) -> Réalisé Mars 2025 | C89: =+E76 -> 80421.77 | D89: =+Print_AAD!AL498 -> 75957.42

Sheet Print_Mois
C1: =Parametres!B1 -> Volks | K1: Véhicules neufs | S1: =CONCATENATE("Réalisé,"," ",Parametres!B3," ",Parametres!B4) -> Réalisé, Mars 2026
D2: X | E2: O | F2: U | J2: NB | L2: $ | O2: X | P2: O | Q2: U | V2: *** NE PAS EFFACER / Pour An Précédente ***
D3: BUDGET ORIGINAL | J3: RÉALISATION | M3: ÉCART réel / Budget | O3: ANNÉE PRÉCÉDENTE | R3: ECART (réel/ Ann.Préc.) | V3: NEUF | W3: 0.45
D4: UNITE | E4: $P/UNITÉ | F4: $PROFITS | J4: UNITÉS | K4: $P/UNITE | L4: $PROFITS | M4: UNITÉS | N4: $PROFITS | O4: UNITE | P4: $P/UNITÉ | Q4: $PROFITS | R4: UNITÉS | S4: $PROFITS | V4: USAGE | W4: 0.1
A5: Véhicules neufsVentes nettes | B5: Véhicules neufs | C5: Ventes nettes | F5: =+INDEX('Budget original'!$A$2:$AO$501,MATCH($A5,'Budget original'!$A$2:$A$501,0),MATCH(F$2,'Budget original'!$A$2:$AO$2,0)) -> 3684432.8 | L5: =-SUMIFS(BV_Data_An_Cour!$O:$O,BV_Data_An_Cour!$X:$X,"Oui",BV_Data_An_Cour!$U:$U,$B5) -> 3914887.7 | Q5: {=+INDEX('Réel 2024'!$A$2:$AO$501,MATCH($A5,'Réel 2024'!$A$2:$A$501,0),MATCH(Q$2,'Réel 2024'!$A$2:$AO$2,0))} -> 2855728.6 | V5: SERVICE | W5: 0.225
A6: Véhicules neufsAutos détail | B6: Véhicules neufs | C6: Autos détail | D6: =+INDEX('Budget original'!$A$2:$AO$501,MATCH($A6,'Budget original'!$A$2:$A$501,0),MATCH(D$2,'Budget original'!$A$2:$AO$2,0)) -> 20 | E6: =IF(D6=0,0,F6/D6) -> 1839.3979 | F6: =+INDEX('Budget original'!$A$2:$AO$501,MATCH($A6,'Budget original'!$A$2:$A$501,0),MATCH(F$2,'Budget original'!$A$2:$AO$2,0)) -> 36787.958 | J6: =-SUMIFS(BV_Data_An_Cour!$O:$O,BV_Data_An_Cour!$U:$U,$B6,BV_Data_An_Cour!$V:$V,$C6,BV_Data_An_Cour!$W:$W,J$2) -> 7 | K6: =IF(J6=0,0,L6/J6) -> 1717.0614 | L6: =-SUMIFS(BV_Data_An_Cour!$O:$O,BV_Data_An_Cour!$U:$U,$B6,BV_Data_An_Cour!$V:$V,$C6,BV_Data_An_Cour!$W:$W,L$2) -> 12019.43 | M6: =J6-D6 -> -13 | N6: =L6-F6 -> -24768.528 | O6: =+INDEX('Réel 2024'!$A$2:$AO$501,MATCH($A6,'Réel 2024'!$A$2:$A$501,0),MATCH(O$2,'Réel 2024'!$A$2:$AO$2,0)) -> 11 | P6: =IF(O6=0,0,Q6/O6) -> 1848.9036 | Q6: {=+INDEX('Réel 2024'!$A$2:$AO$501,MATCH($A6,'Réel 2024'!$A$2:$A$501,0),MATCH(Q$2,'Réel 2024'!$A$2:$AO$2,0))} -> 20337.94 | R6: =J6-O6 -> -4 | S6: =L6-Q6 -> -8318.51 | V6: CARROSSERIE | W6: 0.025
A7: Véhicules neufsCamions détail | B7: Véhicules neufs | C7: Camions détail | D7: =+INDEX('Budget original'!$A$2:$AO$501,MATCH($A7,'Budget original'!$A$2:$A$501,0),MATCH(D$2,'Budget original'!$A$2:$AO$2,0)) -> 50 | E7: =IF(D7=0,0,F7/D7) -> 2490.3911 | F7: =+INDEX('Budget original'!$A$2:$AO$501,MATCH($A7,'Budget original'!$A$2:$A$501,0),MATCH(F$2,'Budget original'!$A$2:$AO$2,0)) -> 124519.55 | J7: =-SUMIFS(BV_Data_An_Cour!$O:$O,BV_Data_An_Cour!$U:$U,$B7,BV_Data_An_Cour!$V:$V,$C7,BV_Data_An_Cour!$W:$W,J$2) -> 48 | K7: =IF(J7=0,0,L7/J7) -> 1724.721 | L7: =-SUMIFS(BV_Data_An_Cour!$O:$O,BV_Data_An_Cour!$U:$U,$B7,BV_Data_An_Cour!$V:$V,$C7,BV_Data_An_Cour!$W:$W,L$2) -> 82786.61 | M7: =J7-D7 -> -2 | N7: =L7-F7 -> -41732.943 | O7: {=+INDEX('Réel 2024'!$A$2:$AO$501,MATCH($A7,'Réel 2024'!$A$2:$A$501,0),MATCH(O$2,'Réel 2024'!$A$2:$AO$2,0))} -> 40 | P7: =IF(O7=0,0,Q7/O7) -> 2175.1205 | Q7: {=+INDEX('Réel 2024'!$A$2:$AO$501,MATCH($A7,'Réel 2024'!$A$2:$A$501,0),MATCH(Q$2,'Réel 2024'!$A$2:$AO$2,0))} -> 87004.82 | R7: =J7-O7 -> 8 | S7: =L7-Q7 -> -4218.21 | V7: PIECES | W7: 0.2
A8: Véhicules neufsSprinter | B8: Véhicules neufs | C8: Sprinter | D8: =+INDEX('Budget original'!$A$2:$AO$501,MATCH($A8,'Budget original'!$A$2:$A$501,0),MATCH(D$2,'Budget original'!$A$2:$AO$2,0)) -> 0 | E8: =IF(D8=0,0,F8/D8) -> 0 | F8: =+INDEX('Budget original'!$A$2:$AO$501,MATCH($A8,'Budget original'!$A$2:$A$501,0),MATCH(F$2,'Budget original'!$A$2:$AO$2,0)) -> 0 | J8: =-SUMIFS(BV_Data_An_Cour!$O:$O,BV_Data_An_Cour!$U:$U,$B8,BV_Data_An_Cour!$V:$V,$C8,BV_Data_An_Cour!$W:$W,J$2) -> 0 | K8: =IF(J8=0,0,L8/J8) -> 0 | L8: =-SUMIFS(BV_Data_An_Cour!$O:$O,BV_Data_An_Cour!$U:$U,$B8,BV_Data_An_Cour!$V:$V,$C8,BV_Data_An_Cour!$W:$W,L$2) -> 0 | M8: =J8-D8 -> 0 | N8: =L8-F8 -> 0 | O8: {=+INDEX('Réel 2024'!$A$2:$AO$501,MATCH($A8,'Réel 2024'!$A$2:$A$501,0),MATCH(O$2,'Réel 2024'!$A$2:$AO$2,0))} -> 0 | P8: =IF(O8=0,0,Q8/O8) -> 0 | Q8: {=+INDEX('Réel 2024'!$A$2:$AO$501,MATCH($A8,'Réel 2024'!$A$2:$A$501,0),MATCH(Q$2,'Réel 2024'!$A$2:$AO$2,0))} -> 0 | R8: =J8-O8 -> 0 | S8: =L8-Q8 -> 0 | W8: =SUM(W3:W7) -> 1
A9: Véhicules neufsMoto détail | B9: Véhicules neufs | C9: Moto détail | D9: =+INDEX('Budget original'!$A$2:$AO$501,MATCH($A9,'Budget original'!$A$2:$A$501,0),MATCH(D$2,'Budget original'!$A$2:$AO$2,0)) -> 0 | E9: =IF(D9=0,0,F9/D9) -> 0 | F9: =+INDEX('Budget original'!$A$2:$AO$501,MATCH($A9,'Budget original'!$A$2:$A$501,0),MATCH(F$2,'Budget original'!$A$2:$AO$2,0)) -> 0 | J9: =-SUMIFS(BV_Data_An_Cour!$O:$O,BV_Data_An_Cour!$U:$U,$B9,BV_Data_An_Cour!$V:$V,$C9,BV_Data_An_Cour!$W:$W,J$2) -> 0 | K9: =IF(J9=0,0,L9/J9) -> 0 | L9: =-SUMIFS(BV_Data_An_Cour!$O:$O,BV_Data_An_Cour!$U:$U,$B9,BV_Data_An_Cour!$V:$V,$C9,BV_Data_An_Cour!$W:$W,L$2) -> 0 | M9: =J9-D9 -> 0 | N9: =L9-F9 -> 0 | O9: {=+INDEX('Réel 2024'!$A$2:$AO$501,MATCH($A9,'Réel 2024'!$A$2:$A$501,0),MATCH(O$2,'Réel 2024'!$A$2:$AO$2,0))} -> 0 | P9: =IF(O9=0,0,Q9/O9) -> 0 | Q9: {=+INDEX('Réel 2024'!$A$2:$AO$501,MATCH($A9,'Réel 2024'!$A$2:$A$501,0),MATCH(Q$2,'Réel 2024'!$A$2:$AO$2,0))} -> 0 | R9: =J9-O9 -> 0 | S9: =L9-Q9 -> 0
A10: Véhicules neufs[...] | B10: Véhicules neufs | C10: [...] | D10: =+INDEX('Budget original'!$A$2:$AO$501,MATCH($A10,'Budget original'!$A$2:$A$501,0),MATCH(D$2,'Budget original'!$A$2:$AO$2,0)) -> 0 | E10: =IF(D10=0,0,F10/D10) -> 0 | F10: =+INDEX('Budget original'!$A$2:$AO$501,MATCH($A10,'Budget original'!$A$2:$A$501,0),MATCH(F$2,'Budget original'!$A$2:$AO$2,0)) -> 0 | J10: =-SUMIFS(BV_Data_An_Cour!$O:$O,BV_Data_An_Cour!$U:$U,$B10,BV_Data_An_Cour!$V:$V,$C10,BV_Data_An_Cour!$W:$W,J$2) -> 0 | K10: =IF(J10=0,0,L10/J10) -> 0 | L10: =-SUMIFS(BV_Data_An_Cour!$O:$O,BV_Data_An_Cour!$U:$U,$B10,BV_Data_An_Cour!$V:$V,$C10,BV_Data_An_Cour!$W:$W,L$2) -> 0 | M10: =J10-D10 -> 0 | N10: =L10-F10 -> 0 | O10: {=+INDEX('Réel 2024'!$A$2:$AO$501,MATCH($A10,'Réel 2024'!$A$2:$A$501,0),MATCH(O$2,'Réel 2024'!$A$2:$AO$2,0))} -> 0 | P10: =IF(O10=0,0,Q10/O10) -> 0 | Q10: {=+INDEX('Réel 2024'!$A$2:$AO$501,MATCH($A10,'Réel 2024'!$A$2:$A$501,0),MATCH(Q$2,'Réel 2024'!$A$2:$AO$2,0))} -> 0 | R10: =J10-O10 -> 0 | S10: =L10-Q10 -> 0
A11: Véhicules neufs[...] | B11: Véhicules neufs | C11: [...] | D11: =+INDEX('Budget original'!$A$2:$AO$501,MATCH($A11,'Budget original'!$A$2:$A$501,0),MATCH(D$2,'Budget original'!$A$2:$AO$2,0)) -> 0 | E11: =IF(D11=0,0,F11/D11) -> 0 | F11: =+INDEX('Budget original'!$A$2:$AO$501,MATCH($A11,'Budget original'!$A$2:$A$501,0),MATCH(F$2,'Budget original'!$A$2:$AO$2,0)) -> 0 | J11: =-SUMIFS(BV_Data_An_Cour!$O:$O,BV_Data_An_Cour!$U:$U,$B11,BV_Data_An_Cour!$V:$V,$C11,BV_Data_An_Cour!$W:$W,J$2) -> 0 | K11: =IF(J11=0,0,L11/J11) -> 0 | L11: =-SUMIFS(BV_Data_An_Cour!$O:$O,BV_Data_An_Cour!$U:$U,$B11,BV_Data_An_Cour!$V:$V,$C11,BV_Data_An_Cour!$W:$W,L$2) -> 0 | M11: =J11-D11 -> 0 | N11: =L11-F11 -> 0 | O11: {=+INDEX('Réel 2024'!$A$2:$AO$501,MATCH($A11,'Réel 2024'!$A$2:$A$501,0),MATCH(O$2,'Réel 2024'!$A$2:$AO$2,0))} -> 0 | P11: =IF(O11=0,0,Q11/O11) -> 0 | Q11: {=+INDEX('Réel 2024'!$A$2:$AO$501,MATCH($A11,'Réel 2024'!$A$2:$A$501,0),MATCH(Q$2,'Réel 2024'!$A$2:$AO$2,0))} -> 0 | R11: =J11-O11 -> 0 | S11: =L11-Q11 -> 0
A12: Véhicules neufs[...] | B12: Véhicules neufs | C12: [...] | D12: =+INDEX('Budget original'!$A$2:$AO$501,MATCH($A12,'Budget original'!$A$2:$A$501,0),MATCH(D$2,'Budget original'!$A$2:$AO$2,0)) -> 0 | E12: =IF(D12=0,0,F12/D12) -> 0 | F12: =+INDEX('Budget original'!$A$2:$AO$501,MATCH($A12,'Budget original'!$A$2:$A$501,0),MATCH(F$2,'Budget original'!$A$2:$AO$2,0)) -> 0 | J12: =-SUMIFS(BV_Data_An_Cour!$O:$O,BV_Data_An_Cour!$U:$U,$B12,BV_Data_An_Cour!$V:$V,$C12,BV_Data_An_Cour!$W:$W,J$2) -> 0 | K12: =IF(J12=0,0,L12/J12) -> 0 | L12: =-SUMIFS(BV_Data_An_Cour!$O:$O,BV_Data_An_Cour!$U:$U,$B12,BV_Data_An_Cour!$V:$V,$C12,BV_Data_An_Cour!$W:$W,L$2) -> 0 | M12: =J12-D12 -> 0 | N12: =L12-F12 -> 0 | O12: {=+INDEX('Réel 2024'!$A$2:$AO$501,MATCH($A12,'Réel 2024'!$A$2:$A$501,0),MATCH(O$2,'Réel 2024'!$A$2:$AO$2,0))} -> 0 | P12: =IF(O12=0,0,Q12/O12) -> 0 | Q12: {=+INDEX('Réel 2024'!$A$2:$AO$501,MATCH($A12,'Réel 2024'!$A$2:$A$501,0),MATCH(Q$2,'Réel 2024'!$A$2:$AO$2,0))} -> 0 | R12: =J12-O12 -> 0 | S12: =L12-Q12 -> 0
A13: Véhicules neufsTotal Neufs | B13: Véhicules neufs | C13: Total Neufs | D13: =+SUM(D6:D12) -> 70 | E13: =IF(D13<=0,0,F13/D13) -> 2304.393 | F13: =+SUM(F6:F12) -> 161307.51 | J13: =+SUM(J6:J12) -> 55 | K13: =IF(J13<=0,0,L13/J13) -> 1723.7462 | L13: =+SUM(L6:L12) -> 94806.04 | M13: =+SUM(M6:M12) -> -15 | N13: =+SUM(N6:N12) -> -66501.471 | O13: =+SUM(O6:O12) -> 51 | P13: =IF(O13<=0,0,Q13/O13) -> 2104.76 | Q13: =+SUM(Q6:Q12) -> 107342.76 | R13: =+SUM(R6:R12) -> 4 | S13: =+SUM(S6:S12) -> -12536.72
A14: Véhicules neufs | B14: Véhicules neufs | M14: =IF(D13=0,0,M13/D13) -> -0.21428571 | N14: =IF(F13=0,0,N13/F13) -> -0.41226519 | R14: =R13/O13 -> 0.078431373 | S14: =IF(Q13=0,0,(S13/Q13)) -> -0.11679148 | AD14: 20 | AE14: 1000 | AF14: =AD14*AE14 -> 20000
A15: Véhicules neufsEx-Démos et courtoisies | B15: Véhicules neufs | C15: Ex-Démos et courtoisies | D15: =+INDEX('Budget original'!$A$2:$AO$501,MATCH($A15,'Budget original'!$A$2:$A$501,0),MATCH(D$2,'Budget original'!$A$2:$AO$2,0)) -> 4 | E15: =IF(D15=0,0,F15/D15) -> 1524.8245 | F15: =+INDEX('Budget original'!$A$2:$AO$501,MATCH($A15,'Budget original'!$A$2:$A$501,0),MATCH(F$2,'Budget original'!$A$2:$AO$2,0)) -> 6099.2981 | J15: =-SUMIFS(BV_Data_An_Cour!$O:$O,BV_Data_An_Cour!$U:$U,$B15,BV_Data_An_Cour!$V:$V,$C15,BV_Data_An_Cour!$W:$W,J$2) -> 1 | K15: =IF(J15=0,0,L15/J15) -> 0 | L15: =-SUMIFS(BV_Data_An_Cour!$O:$O,BV_Data_An_Cour!$U:$U,$B15,BV_Data_An_Cour!$V:$V,$C15,BV_Data_An_Cour!$W:$W,L$2) -> 0 | M15: =J15-D15 -> -3 | N15: =L15-F15 -> -6099.2981 | O15: {=+INDEX('Réel 2024'!$A$2:$AO$501,MATCH($A15,'Réel 2024'!$A$2:$A$501,0),MATCH(O$2,'Réel 2024'!$A$2:$AO$2,0))} -> 4 | P15: =IF(O15=0,0,Q15/O15) -> 370.87 | Q15: {=+INDEX('Réel 2024'!$A$2:$AO$501,MATCH($A15,'Réel 2024'!$A$2:$A$501,0),MATCH(Q$2,'Réel 2024'!$A$2:$AO$2,0))} -> 1483.48 | R15: =J15-O15 -> -3 | S15: =L15-Q15 -> -1483.48 | AD15: 25 | AE15: =AF15/AD15 -> 800 | AF15: =AF14 -> 20000
A16: Véhicules neufs | B16: Véhicules neufs
A17: Véhicules neufsFlottes | B17: Véhicules neufs | C17: Flottes | D17: =+INDEX('Budget original'!$A$2:$AO$501,MATCH($A17,'Budget original'!$A$2:$A$501,0),MATCH(D$2,'Budget original'!$A$2:$AO$2,0)) -> 5 | E17: =IF(D17=0,0,F17/D17) -> 1300.6851 | F17: =+INDEX('Budget original'!$A$2:$AO$501,MATCH($A17,'Budget original'!$A$2:$A$501,0),MATCH(F$2,'Budget original'!$A$2:$AO$2,0)) -> 6503.4257 | J17: =-SUMIFS(BV_Data_An_Cour!$O:$O,BV_Data_An_Cour!$U:$U,$B17,BV_Data_An_Cour!$V:$V,$C17,BV_Data_An_Cour!$W:$W,J$2) -> 24 | K17: =IF(J17=0,0,L17/J17) -> 67.140833 | L17: =-SUMIFS(BV_Data_An_Cour!$O:$O,BV_Data_An_Cour!$U:$U,$B17,BV_Data_An_Cour!$V:$V,$C17,BV_Data_An_Cour!$W:$W,L$2) -> 1611.38 | M17: =J17-D17 -> 19 | N17: =L17-F17 -> -4892.0456 | O17: {=+INDEX('Réel 2024'!$A$2:$AO$501,MATCH($A17,'Réel 2024'!$A$2:$A$501,0),MATCH(O$2,'Réel 2024'!$A$2:$AO$2,0))} -> 0 | P17: =IF(O17=0,0,Q17/O17) -> 0 | Q17: {=+INDEX('Réel 2024'!$A$2:$AO$501,MATCH($A17,'Réel 2024'!$A$2:$A$501,0),MATCH(Q$2,'Réel 2024'!$A$2:$AO$2,0))} -> 0 | R17: =J17-O17 -> 24 | S17: =L17-Q17 -> 1611.38
A18: Véhicules neufs | B18: Véhicules neufs
A19: Véhicules neufsRachat bail | B19: Véhicules neufs | C19: Rachat bail | D19: =+INDEX('Budget original'!$A$2:$AO$501,MATCH($A19,'Budget original'!$A$2:$A$501,0),MATCH(D$2,'Budget original'!$A$2:$AO$2,0)) -> 0 | E19: =IF(D19=0,0,F19/D19) -> 0 | F19: =+INDEX('Budget original'!$A$2:$AO$501,MATCH($A19,'Budget original'!$A$2:$A$501,0),MATCH(F$2,'Budget original'!$A$2:$AO$2,0)) -> 10279.001 | L19: =-SUMIFS(BV_Data_An_Cour!$O:$O,BV_Data_An_Cour!$U:$U,$B19,BV_Data_An_Cour!$V:$V,$C19,BV_Data_An_Cour!$W:$W,L$2) -> 4617.32 | N19: =L19-F19 -> -5661.6815 | Q19: {=+INDEX('Réel 2024'!$A$2:$AO$501,MATCH($A19,'Réel 2024'!$A$2:$A$501,0),MATCH(Q$2,'Réel 2024'!$A$2:$AO$2,0))} -> 13000.4 | R19: =O19-K19 -> 0 | S19: =L19-Q19 -> -8383.08
A20: Véhicules neufs | B20: Véhicules neufs
A21: Véhicules neufsRev. Finances | B21: Véhicules neufs | C21: Rev. Finances | D21: =+INDEX('Budget original'!$A$2:$AO$501,MATCH($A21,'Budget original'!$A$2:$A$501,0),MATCH(D$2,'Budget original'!$A$2:$AO$2,0)) -> 0 | E21: =IF(D21=0,0,F21/D21) -> 0 | F21: =+INDEX('Budget original'!$A$2:$AO$501,MATCH($A21,'Budget original'!$A$2:$A$501,0),MATCH(F$2,'Budget original'!$A$2:$AO$2,0)) -> 3700 | K21: =IF(J13=0,0,L21/(J13+J15)) -> 8.0357143 | L21: =-SUMIFS(BV_Data_An_Cour!$O:$O,BV_Data_An_Cour!$U:$U,$B21,BV_Data_An_Cour!$V:$V,$C21,BV_Data_An_Cour!$W:$W,L$2) -> 450 | N21: =L21-F21 -> -3250 | Q21: {=+INDEX('Réel 2024'!$A$2:$AO$501,MATCH($A21,'Réel 2024'!$A$2:$A$501,0),MATCH(Q$2,'Réel 2024'!$A$2:$AO$2,0))} -> 0 | R21: =O21-K21 -> -8.0357143 | S21: =L21-Q21 -> 450
A22: Véhicules neufsRev. Protections | B22: Véhicules neufs | C22: Rev. Protections | D22: =+INDEX('Budget original'!$A$2:$AO$501,MATCH($A22,'Budget original'!$A$2:$A$501,0),MATCH(D$2,'Budget original'!$A$2:$AO$2,0)) -> 0 | E22: =IF(D22=0,0,F22/D22) -> 0 | F22: =+INDEX('Budget original'!$A$2:$AO$501,MATCH($A22,'Budget original'!$A$2:$A$501,0),MATCH(F$2,'Budget original'!$A$2:$AO$2,0)) -> 83620 | K22: =IF(J13=0,0,L22/(J13+J15)) -> 977.23411 | L22: =-SUMIFS(BV_Data_An_Cour!$O:$O,BV_Data_An_Cour!$U:$U,$B22,BV_Data_An_Cour!$V:$V,$C22,BV_Data_An_Cour!$W:$W,L$2) -> 54725.11 | N22: =L22-F22 -> -28894.89 | Q22: {=+INDEX('Réel 2024'!$A$2:$AO$501,MATCH($A22,'Réel 2024'!$A$2:$A$501,0),MATCH(Q$2,'Réel 2024'!$A$2:$AO$2,0))} -> 33331.59 | R22: =O22-K22 -> -977.23411 | S22: =L22-Q22 -> 21393.52
A23: Véhicules neufsRev. Autres | B23: Véhicules neufs | C23: Rev. Autres | D23: =+INDEX('Budget original'!$A$2:$AO$501,MATCH($A23,'Budget original'!$A$2:$A$501,0),MATCH(D$2,'Budget original'!$A$2:$AO$2,0)) -> 0 | E23: =IF(D23=0,0,F23/D23) -> 0 | F23: =+INDEX('Budget original'!$A$2:$AO$501,MATCH($A23,'Budget original'!$A$2:$A$501,0),MATCH(F$2,'Budget original'!$A$2:$AO$2,0)) -> 1480 | K23: =IF(J13=0,0,L23/(J13+J15)) -> 7.1814286 | L23: =-SUMIFS(BV_Data_An_Cour!$O:$O,BV_Data_An_Cour!$U:$U,$B23,BV_Data_An_Cour!$V:$V,$C23,BV_Data_An_Cour!$W:$W,L$2) -> 402.16 | N23: =L23-F23 -> -1077.84 | Q23: {=+INDEX('Réel 2024'!$A$2:$AO$501,MATCH($A23,'Réel 2024'!$A$2:$A$501,0),MATCH(Q$2,'Réel 2024'!$A$2:$AO$2,0))} -> 316.41 | R23: =O23-K23 -> -7.1814286 | S23: =L23-Q23 -> 85.75
A24: Véhicules neufsTotal F&I | B24: Véhicules neufs | C24: Total F&I | D24: =+D15+D13 -> 74 | E24: =IF(D24<=0,0,F24/D24) -> 1200 | F24: =F21+F22+F23 -> 88800 | J24: =+J15+J13 -> 56 | K24: =IF(J24<=0,0,L24/J24) -> 992.45125 | L24: =L21+L22+L23 -> 55577.27 | M24: =J24-D24 -> -18 | N24: =L24-F24 -> -33222.73 | O24: =+O15+O13 -> 55 | P24: =IF(O24<=0,0,Q24/O24) -> 611.78182 | Q24: =Q21+Q22+Q23 -> 33648 | S24: =L24-Q24 -> 21929.27
A25: Véhicules neufs | B25: Véhicules neufs | N25: =IF(N24=0,0,N24/F24) -> -0.37412984 | S25: =IF(Q24=0,0,(S24/Q24)) -> 0.65172581
A26: Véhicules neufs | B26: Véhicules neufs
A27: Véhicules neufsTotal Dépt. Neufs | B27: Véhicules neufs | C27: Total Dépt. Neufs | D27: =+D13+D15+D17 -> 79 | E27: =IF(D27<=0,0,F27/D27) -> 3455.56 | F27: =F13+F17+F24+F19+F15 -> 272989.24 | J27: =+J13+J15+J17 -> 80 | K27: =IF(J27<=0,0,L27/J27) -> 1957.6501 | L27: =L13+L17+L24+L19+L15 -> 156612.01 | M27: =J27-D27 -> 1 | N27: =L27-F27 -> -116377.23 | O27: =+O13+O15+O17 -> 55 | P27: =IF(O27<=0,0,Q27/O27) -> 2826.8116 | Q27: =Q13+Q17+Q24+Q19+Q15 -> 155474.64 | R27: =J27-O27 -> 25 | S27: =L27-Q27 -> 1137.37
A28: Véhicules neufs | B28: Véhicules neufs | L28: =L27/F27 -> 0.57369299 | M28: =M27/D27 -> 0.012658228 | N28: =N27/F27 -> -0.42630701 | R28: =R27/O27 -> 0.45454545 | S28: =IF(Q27=0,0,S27/Q27) -> 0.0073154696
A29: Véhicules neufs | B29: Véhicules neufs
A30: Véhicules neufsDEPENSES | B30: Véhicules neufs | C30: DEPENSES
A31: Véhicules neufsComm. vendeurs | B31: Véhicules neufs | C31: Comm. vendeurs | D31: =F31/(F13+F15) -> 0.31274572 | E31: =F31/D$24 -> 707.51032 | F31: =+INDEX('Budget original'!$A$2:$AO$501,MATCH($A31,'Budget original'!$A$2:$A$501,0),MATCH(F$2,'Budget original'!$A$2:$AO$2,0)) -> 52355.763 | J31: =L31/(L15+L13+L17) -> 0.41773634 | K31: =IF(L31=0,0,L31/J$24) -> 719.23321 | L31: =SUMIFS(BV_Data_An_Cour!$O:$O,BV_Data_An_Cour!$U:$U,$B31,BV_Data_An_Cour!$V:$V,$C31,BV_Data_An_Cour!$W:$W,L$2) -> 40277.06 | N31: =L31-F31 -> -12078.703 | O31: =Q31/(Q13+Q15+Q17) -> 0.28209805 | P31: =Q31/O$24 -> 558.17582 | Q31: {=+INDEX('Réel 2024'!$A$2:$AO$501,MATCH($A31,'Réel 2024'!$A$2:$A$501,0),MATCH(Q$2,'Réel 2024'!$A$2:$AO$2,0))} -> 30699.67 | S31: =L31-Q31 -> 9577.39
A32: Véhicules neufsComm. F&I | B32: Véhicules neufs | C32: Comm. F&I | D32: =F32/F24 -> 0.2 | E32: =F32/D$24 -> 240 | F32: =+INDEX('Budget original'!$A$2:$AO$501,MATCH($A32,'Budget original'!$A$2:$A$501,0),MATCH(F$2,'Budget original'!$A$2:$AO$2,0)) -> 17760 | J32: =L32/L24 -> 0.2011414 | K32: =IF(L32=0,0,L32/J$24) -> 199.62304 | L32: =SUMIFS(BV_Data_An_Cour!$O:$O,BV_Data_An_Cour!$U:$U,$B32,BV_Data_An_Cour!$V:$V,$C32,BV_Data_An_Cour!$W:$W,L$2) -> 11178.89 | N32: =L32-F32 -> -6581.11 | O32: =Q32/Q24 -> 0.30698942 | P32: =Q32/O$24 -> 187.81055 | Q32: {=+INDEX('Réel 2024'!$A$2:$AO$501,MATCH($A32,'Réel 2024'!$A$2:$A$501,0),MATCH(Q$2,'Réel 2024'!$A$2:$AO$2,0))} -> 10329.58 | S32: =L32-Q32 -> 849.31
A33: Véhicules neufsFrais de livraison | B33: Véhicules neufs | C33: Frais de livraison | E33: =F33/D$24 -> 115 | F33: =+INDEX('Budget original'!$A$2:$AO$501,MATCH($A33,'Budget original'!$A$2:$A$501,0),MATCH(F$2,'Budget original'!$A$2:$AO$2,0)) -> 8510 | K33: =IF(L33=0,0,L33/J$24) -> 141.28839 | L33: =SUMIFS(BV_Data_An_Cour!$O:$O,BV_Data_An_Cour!$U:$U,$B33,BV_Data_An_Cour!$V:$V,$C33,BV_Data_An_Cour!$W:$W,L$2) -> 7912.15 | N33: =L33-F33 -> -597.85 | P33: =Q33/O$24 -> 35.175818 | Q33: {=+INDEX('Réel 2024'!$A$2:$AO$501,MATCH($A33,'Réel 2024'!$A$2:$A$501,0),MATCH(Q$2,'Réel 2024'!$A$2:$AO$2,0))} -> 1934.67 | S33: =L33-Q33 -> 5977.48
A34: Véhicules neufsService gratuit 1 | B34: Véhicules neufs | C34: Service gratuit 1 | E34: =F34/D$24 -> 10 | F34: =+INDEX('Budget original'!$A$2:$AO$501,MATCH($A34,'Budget original'!$A$2:$A$501,0),MATCH(F$2,'Budget original'!$A$2:$AO$2,0)) -> 740 | K34: =IF(L34=0,0,L34/J$24) -> 0 | L34: =SUMIFS(BV_Data_An_Cour!$O:$O,BV_Data_An_Cour!$U:$U,$B34,BV_Data_An_Cour!$V:$V,$C34,BV_Data_An_Cour!$W:$W,L$2) -> 0 | N34: =L34-F34 -> -740 | P34: =Q34/O$24 -> 10.110182 | Q34: {=+INDEX('Réel 2024'!$A$2:$AO$501,MATCH($A34,'Réel 2024'!$A$2:$A$501,0),MATCH(Q$2,'Réel 2024'!$A$2:$AO$2,0))} -> 556.06 | S34: =L34-Q34 -> -556.06
A35: Véhicules neufsEntretien stock | B35: Véhicules neufs | C35: Entretien stock | E35: =F35/D$24 -> 120 | F35: =+INDEX('Budget original'!$A$2:$AO$501,MATCH($A35,'Budget original'!$A$2:$A$501,0),MATCH(F$2,'Budget original'!$A$2:$AO$2,0)) -> 8880 | K35: =IF(L35=0,0,L35/J$24) -> 138.72375 | L35: =SUMIFS(BV_Data_An_Cour!$O:$O,BV_Data_An_Cour!$U:$U,$B35,BV_Data_An_Cour!$V:$V,$C35,BV_Data_An_Cour!$W:$W,L$2) -> 7768.53 | N35: =L35-F35 -> -1111.47 | P35: =Q35/O$24 -> 117.53782 | Q35: {=+INDEX('Réel 2024'!$A$2:$AO$501,MATCH($A35,'Réel 2024'!$A$2:$A$501,0),MATCH(Q$2,'Réel 2024'!$A$2:$AO$2,0))} -> 6464.58 | S35: =L35-Q35 -> 1303.95
A36: Véhicules neufsPublicité 1 | B36: Véhicules neufs | C36: Publicité 1 | E36: =F36/D$24 -> -4.2905405 | F36: =+INDEX('Budget original'!$A$2:$AO$501,MATCH($A36,'Budget original'!$A$2:$A$501,0),MATCH(F$2,'Budget original'!$A$2:$AO$2,0)) -> -317.5 | K36: =IF(L36=0,0,L36/J$24) -> -51.488214 | L36: =SUMIFS(BV_Data_An_Cour!$O:$O,BV_Data_An_Cour!$U:$U,$B36,BV_Data_An_Cour!$V:$V,$C36,BV_Data_An_Cour!$W:$W,L$2) -> -2883.34 | N36: =L36-F36 -> -2565.84 | P36: =Q36/O$24 -> 367.98564 | Q36: {=+INDEX('Réel 2024'!$A$2:$AO$501,MATCH($A36,'Réel 2024'!$A$2:$A$501,0),MATCH(Q$2,'Réel 2024'!$A$2:$AO$2,0))} -> 20239.21 | S36: =L36-Q36 -> -23122.55
A37: Véhicules neufsIntérêt de gros | B37: Véhicules neufs | C37: Intérêt de gros | E37: =F37/D$24 -> 321.98092 | F37: =+INDEX('Budget original'!$A$2:$AO$501,MATCH($A37,'Budget original'!$A$2:$A$501,0),MATCH(F$2,'Budget original'!$A$2:$AO$2,0)) -> 23826.588 | K37: =IF(L37=0,0,L37/J$24) -> 500.01482 | L37: =SUMIFS(BV_Data_An_Cour!$O:$O,BV_Data_An_Cour!$U:$U,$B37,BV_Data_An_Cour!$V:$V,$C37,BV_Data_An_Cour!$W:$W,L$2) -> 28000.83 | N37: =L37-F37 -> 4174.2417 | P37: =Q37/O$24 -> 437.246 | Q37: {=+INDEX('Réel 2024'!$A$2:$AO$501,MATCH($A37,'Réel 2024'!$A$2:$A$501,0),MATCH(Q$2,'Réel 2024'!$A$2:$AO$2,0))} -> 24048.53 | S37: =L37-Q37 -> 3952.3
A38: Véhicules neufs[...] | B38: Véhicules neufs | C38: [...] | E38: =F38/D$24 -> 0 | F38: =+INDEX('Budget original'!$A$2:$AO$501,MATCH($A38,'Budget original'!$A$2:$A$501,0),MATCH(F$2,'Budget original'!$A$2:$AO$2,0)) -> 0 | K38: =IF(L38=0,0,L38/J$24) -> 0 | L38: =SUMIFS(BV_Data_An_Cour!$O:$O,BV_Data_An_Cour!$U:$U,$B38,BV_Data_An_Cour!$V:$V,$C38,BV_Data_An_Cour!$W:$W,L$2) -> 0 | N38: =L38-F38 -> 0 | P38: =Q38/O$24 -> 0 | Q38: {=+INDEX('Réel 2024'!$A$2:$AO$501,MATCH($A38,'Réel 2024'!$A$2:$A$501,0),MATCH(Q$2,'Réel 2024'!$A$2:$AO$2,0))} -> 0 | S38: =L38-Q38 -> 0
A39: Véhicules neufs[...] | B39: Véhicules neufs | C39: [...] | E39: =F39/D$24 -> 0 | F39: =+INDEX('Budget original'!$A$2:$AO$501,MATCH($A39,'Budget original'!$A$2:$A$501,0),MATCH(F$2,'Budget original'!$A$2:$AO$2,0)) -> 0 | K39: =IF(L39=0,0,L39/J$24) -> 0 | L39: =SUMIFS(BV_Data_An_Cour!$O:$O,BV_Data_An_Cour!$U:$U,$B39,BV_Data_An_Cour!$V:$V,$C39,BV_Data_An_Cour!$W:$W,L$2) -> 0 | N39: =L39-F39 -> 0 | P39: =Q39/O$24 -> 0 | Q39: {=+INDEX('Réel 2024'!$A$2:$AO$501,MATCH($A39,'Réel 2024'!$A$2:$A$501,0),MATCH(Q$2,'Réel 2024'!$A$2:$AO$2,0))} -> 0 | S39: =L39-Q39 -> 0
A40: Véhicules neufs[...] | B40: Véhicules neufs | C40: [...] | E40: =F40/D$24 -> 0 | F40: =+INDEX('Budget original'!$A$2:$AO$501,MATCH($A40,'Budget original'!$A$2:$A$501,0),MATCH(F$2,'Budget original'!$A$2:$AO$2,0)) -> 0 | K40: =IF(L40=0,0,L40/J$24) -> 0 | L40: =SUMIFS(BV_Data_An_Cour!$O:$O,BV_Data_An_Cour!$U:$U,$B40,BV_Data_An_Cour!$V:$V,$C40,BV_Data_An_Cour!$W:$W,L$2) -> 0 | N40: =L40-F40 -> 0 | P40: =Q40/O$24 -> 0 | Q40: {=+INDEX('Réel 2024'!$A$2:$AO$501,MATCH($A40,'Réel 2024'!$A$2:$A$501,0),MATCH(Q$2,'Réel 2024'!$A$2:$AO$2,0))} -> 0 | S40: =L40-Q40 -> 0
A41: Véhicules neufsTOTAL VARIABLES | B41: Véhicules neufs | C41: TOTAL VARIABLES | D41: % brut | E41: =F41/F$27 -> 0.40937457 | F41: =SUM(F31:F40) -> 111754.85 | J41: % brut | K41: =L41/L$27 -> 0.58906159 | L41: =SUM(L31:L40) -> 92254.12 | N41: =L41-F41 -> -19500.732 | O41: % brut | P41: =Q41/Q$27 -> 0.60635162 | Q41: =SUM(Q31:Q40) -> 94272.3 | S41: =L41-Q41 -> -2018.18
A42: Véhicules neufsSalaires cadres | B42: Véhicules neufs | C42: Salaires cadres | F42: =+INDEX('Budget original'!$A$2:$AO$501,MATCH($A42,'Budget original'!$A$2:$A$501,0),MATCH(F$2,'Budget original'!$A$2:$AO$2,0)) -> 20698.718 | L42: =SUMIFS(BV_Data_An_Cour!$O:$O,BV_Data_An_Cour!$U:$U,$B42,BV_Data_An_Cour!$V:$V,$C42,BV_Data_An_Cour!$W:$W,L$2) -> 8276.74 | N42: =L42-F42 -> -12421.978 | P42: =Q42/Q27 -> 0.1524848 | Q42: {=+INDEX('Réel 2024'!$A$2:$AO$501,MATCH($A42,'Réel 2024'!$A$2:$A$501,0),MATCH(Q$2,'Réel 2024'!$A$2:$AO$2,0))} -> 23707.52 | S42: =L42-Q42 -> -15430.78
A43: Véhicules neufsSalaires commis | B43: Véhicules neufs | C43: Salaires commis | F43: =+INDEX('Budget original'!$A$2:$AO$501,MATCH($A43,'Budget original'!$A$2:$A$501,0),MATCH(F$2,'Budget original'!$A$2:$AO$2,0)) -> 18491.133 | L43: =SUMIFS(BV_Data_An_Cour!$O:$O,BV_Data_An_Cour!$U:$U,$B43,BV_Data_An_Cour!$V:$V,$C43,BV_Data_An_Cour!$W:$W,L$2) -> 12360.33 | N43: =L43-F43 -> -6130.8031 | Q43: {=+INDEX('Réel 2024'!$A$2:$AO$501,MATCH($A43,'Réel 2024'!$A$2:$A$501,0),MATCH(Q$2,'Réel 2024'!$A$2:$AO$2,0))} -> 12526.87 | S43: =L43-Q43 -> -166.54
A44: Véhicules neufsSalaires autres | B44: Véhicules neufs | C44: Salaires autres | F44: =+INDEX('Budget original'!$A$2:$AO$501,MATCH($A44,'Budget original'!$A$2:$A$501,0),MATCH(F$2,'Budget original'!$A$2:$AO$2,0)) -> 0 | L44: =SUMIFS(BV_Data_An_Cour!$O:$O,BV_Data_An_Cour!$U:$U,$B44,BV_Data_An_Cour!$V:$V,$C44,BV_Data_An_Cour!$W:$W,L$2) -> 7219.67 | N44: =L44-F44 -> 7219.67 | Q44: {=+INDEX('Réel 2024'!$A$2:$AO$501,MATCH($A44,'Réel 2024'!$A$2:$A$501,0),MATCH(Q$2,'Réel 2024'!$A$2:$AO$2,0))} -> -312 | S44: =L44-Q44 -> 7531.67
A45: Véhicules neufsSalaires spécialistes | B45: Véhicules neufs | C45: Salaires spécialistes | F45: =+INDEX('Budget original'!$A$2:$AO$501,MATCH($A45,'Budget original'!$A$2:$A$501,0),MATCH(F$2,'Budget original'!$A$2:$AO$2,0)) -> 0 | L45: =SUMIFS(BV_Data_An_Cour!$O:$O,BV_Data_An_Cour!$U:$U,$B45,BV_Data_An_Cour!$V:$V,$C45,BV_Data_An_Cour!$W:$W,L$2) -> 0 | N45: =L45-F45 -> 0 | Q45: {=+INDEX('Réel 2024'!$A$2:$AO$501,MATCH($A45,'Réel 2024'!$A$2:$A$501,0),MATCH(Q$2,'Réel 2024'!$A$2:$AO$2,0))} -> 0 | S45: =L45-Q45 -> 0
A46: Véhicules neufs[...] | B46: Véhicules neufs | C46: [...] | F46: =+INDEX('Budget original'!$A$2:$AO$501,MATCH($A46,'Budget original'!$A$2:$A$501,0),MATCH(F$2,'Budget original'!$A$2:$AO$2,0)) -> 0 | L46: =SUMIFS(BV_Data_An_Cour!$O:$O,BV_Data_An_Cour!$U:$U,$B46,BV_Data_An_Cour!$V:$V,$C46,BV_Data_An_Cour!$W:$W,L$2) -> 0 | N46: =L46-F46 -> 0 | Q46: {=+INDEX('Réel 2024'!$A$2:$AO$501,MATCH($A46,'Réel 2024'!$A$2:$A$501,0),MATCH(Q$2,'Réel 2024'!$A$2:$AO$2,0))} -> 0 | S46: =L46-Q46 -> 0
A47: Véhicules neufs[...] | B47: Véhicules neufs | C47: [...] | F47: =+INDEX('Budget original'!$A$2:$AO$501,MATCH($A47,'Budget original'!$A$2:$A$501,0),MATCH(F$2,'Budget original'!$A$2:$AO$2,0)) -> 0 | L47: =SUMIFS(BV_Data_An_Cour!$O:$O,BV_Data_An_Cour!$U:$U,$B47,BV_Data_An_Cour!$V:$V,$C47,BV_Data_An_Cour!$W:$W,L$2) -> 0 | N47: =L47-F47 -> 0 | Q47: {=+INDEX('Réel 2024'!$A$2:$AO$501,MATCH($A47,'Réel 2024'!$A$2:$A$501,0),MATCH(Q$2,'Réel 2024'!$A$2:$AO$2,0))} -> 0 | S47: =L47-Q47 -> 0
A48: Véhicules neufs[...] | B48: Véhicules neufs | C48: [...] | F48: =+INDEX('Budget original'!$A$2:$AO$501,MATCH($A48,'Budget original'!$A$2:$A$501,0),MATCH(F$2,'Budget original'!$A$2:$AO$2,0)) -> 0 | L48: =SUMIFS(BV_Data_An_Cour!$O:$O,BV_Data_An_Cour!$U:$U,$B48,BV_Data_An_Cour!$V:$V,$C48,BV_Data_An_Cour!$W:$W,L$2) -> 0 | N48: =L48-F48 -> 0 | Q48: {=+INDEX('Réel 2024'!$A$2:$AO$501,MATCH($A48,'Réel 2024'!$A$2:$A$501,0),MATCH(Q$2,'Réel 2024'!$A$2:$AO$2,0))} -> 0 | S48: =L48-Q48 -> 0
A49: Véhicules neufsSalaires en absences | B49: Véhicules neufs | C49: Salaires en absences | F49: =+INDEX('Budget original'!$A$2:$AO$501,MATCH($A49,'Budget original'!$A$2:$A$501,0),MATCH(F$2,'Budget original'!$A$2:$AO$2,0)) -> 12643.918 | L49: =SUMIFS(BV_Data_An_Cour!$O:$O,BV_Data_An_Cour!$U:$U,$B49,BV_Data_An_Cour!$V:$V,$C49,BV_Data_An_Cour!$W:$W,L$2) -> 10662.01 | N49: =L49-F49 -> -1981.9084 | Q49: {=+INDEX('Réel 2024'!$A$2:$AO$501,MATCH($A49,'Réel 2024'!$A$2:$A$501,0),MATCH(Q$2,'Réel 2024'!$A$2:$AO$2,0))} -> 12291.71 | S49: =L49-Q49 -> -1629.7
A50: Véhicules neufsDéduction à la source | B50: Véhicules neufs | C50: Déduction à la source | F50: =+INDEX('Budget original'!$A$2:$AO$501,MATCH($A50,'Budget original'!$A$2:$A$501,0),MATCH(F$2,'Budget original'!$A$2:$AO$2,0)) -> 15373.222 | L50: =SUMIFS(BV_Data_An_Cour!$O:$O,BV_Data_An_Cour!$U:$U,$B50,BV_Data_An_Cour!$V:$V,$C50,BV_Data_An_Cour!$W:$W,L$2) -> 13455.59 | N50: =L50-F50 -> -1917.6323 | Q50: {=+INDEX('Réel 2024'!$A$2:$AO$501,MATCH($A50,'Réel 2024'!$A$2:$A$501,0),MATCH(Q$2,'Réel 2024'!$A$2:$AO$2,0))} -> 14654.31 | S50: =L50-Q50 -> -1198.72
A51: Véhicules neufsBénéfices marginaux | B51: Véhicules neufs | C51: Bénéfices marginaux | F51: =+INDEX('Budget original'!$A$2:$AO$501,MATCH($A51,'Budget original'!$A$2:$A$501,0),MATCH(F$2,'Budget original'!$A$2:$AO$2,0)) -> 7920.5515 | L51: =SUMIFS(BV_Data_An_Cour!$O:$O,BV_Data_An_Cour!$U:$U,$B51,BV_Data_An_Cour!$V:$V,$C51,BV_Data_An_Cour!$W:$W,L$2) -> 6062.58 | N51: =L51-F51 -> -1857.9715 | Q51: {=+INDEX('Réel 2024'!$A$2:$AO$501,MATCH($A51,'Réel 2024'!$A$2:$A$501,0),MATCH(Q$2,'Réel 2024'!$A$2:$AO$2,0))} -> 7784.41 | S51: =L51-Q51 -> -1721.83
A52: Véhicules neufsCsst | B52: Véhicules neufs | C52: Csst | F52: =+INDEX('Budget original'!$A$2:$AO$501,MATCH($A52,'Budget original'!$A$2:$A$501,0),MATCH(F$2,'Budget original'!$A$2:$AO$2,0)) -> 3453.405 | L52: =SUMIFS(BV_Data_An_Cour!$O:$O,BV_Data_An_Cour!$U:$U,$B52,BV_Data_An_Cour!$V:$V,$C52,BV_Data_An_Cour!$W:$W,L$2) -> 1876.33 | N52: =L52-F52 -> -1577.075 | Q52: {=+INDEX('Réel 2024'!$A$2:$AO$501,MATCH($A52,'Réel 2024'!$A$2:$A$501,0),MATCH(Q$2,'Réel 2024'!$A$2:$AO$2,0))} -> 2218.05 | S52: =L52-Q52 -> -341.72
A53: Véhicules neufs[...] | B53: Véhicules neufs | C53: [...] | D53: =VLOOKUP(C53,$B$2:$B$46,1,FALSE) -> #N/A | F53: =+INDEX('Budget original'!$A$2:$AO$501,MATCH($A53,'Budget original'!$A$2:$A$501,0),MATCH(F$2,'Budget original'!$A$2:$AO$2,0)) -> 0 | L53: =SUMIFS(BV_Data_An_Cour!$O:$O,BV_Data_An_Cour!$U:$U,$B53,BV_Data_An_Cour!$V:$V,$C53,BV_Data_An_Cour!$W:$W,L$2) -> 0 | N53: =L53-F53 -> 0 | Q53: {=+INDEX('Réel 2024'!$A$2:$AO$501,MATCH($A53,'Réel 2024'!$A$2:$A$501,0),MATCH(Q$2,'Réel 2024'!$A$2:$AO$2,0))} -> 0 | S53: =L53-Q53 -> 0
A54: Véhicules neufsTOTAL PERSONNEL | B54: Véhicules neufs | C54: TOTAL PERSONNEL | D54: % brut | E54: =F54/F$27 -> 0.28785365 | F54: =+SUM(F42:F53) -> 78580.948 | J54: % brut | K54: =L54/L$27 -> 0.38255846 | L54: =+SUM(L42:L53) -> 59913.25 | N54: =+SUM(N42:N53) -> -18667.698 | O54: % brut | P54: =Q54/Q$27 -> 0.4686994 | Q54: =+SUM(Q42:Q53) -> 72870.87 | S54: =+SUM(S42:S53) -> -12957.62
A55: Véhicules neufsPublicité 2 | B55: Véhicules neufs | C55: Publicité 2 | F55: =+INDEX('Budget original'!$A$2:$AO$501,MATCH($A55,'Budget original'!$A$2:$A$501,0),MATCH(F$2,'Budget original'!$A$2:$AO$2,0)) -> 0 | L55: =SUMIFS(BV_Data_An_Cour!$O:$O,BV_Data_An_Cour!$U:$U,$B55,BV_Data_An_Cour!$V:$V,$C55,BV_Data_An_Cour!$W:$W,L$2) -> 0 | N55: =L55-F55 -> 0 | Q55: {=+INDEX('Réel 2024'!$A$2:$AO$501,MATCH($A55,'Réel 2024'!$A$2:$A$501,0),MATCH(Q$2,'Réel 2024'!$A$2:$AO$2,0))} -> 0 | S55: =L55-Q55 -> 0
A56: Véhicules neufsService gratuit 2 | B56: Véhicules neufs | C56: Service gratuit 2 | F56: =+INDEX('Budget original'!$A$2:$AO$501,MATCH($A56,'Budget original'!$A$2:$A$501,0),MATCH(F$2,'Budget original'!$A$2:$AO$2,0)) -> 0 | L56: =SUMIFS(BV_Data_An_Cour!$O:$O,BV_Data_An_Cour!$U:$U,$B56,BV_Data_An_Cour!$V:$V,$C56,BV_Data_An_Cour!$W:$W,L$2) -> 0 | N56: =L56-F56 -> 0 | Q56: {=+INDEX('Réel 2024'!$A$2:$AO$501,MATCH($A56,'Réel 2024'!$A$2:$A$501,0),MATCH(Q$2,'Réel 2024'!$A$2:$AO$2,0))} -> 0 | S56: =L56-Q56 -> 0
A57: Véhicules neufsFrais véhicules de cie | B57: Véhicules neufs | C57: Frais véhicules de cie | F57: =+INDEX('Budget original'!$A$2:$AO$501,MATCH($A57,'Budget original'!$A$2:$A$501,0),MATCH(F$2,'Budget original'!$A$2:$AO$2,0)) -> 8952.5479 | L57: =SUMIFS(BV_Data_An_Cour!$O:$O,BV_Data_An_Cour!$U:$U,$B57,BV_Data_An_Cour!$V:$V,$C57,BV_Data_An_Cour!$W:$W,L$2) -> 6586.98 | N57: =L57-F57 -> -2365.5679 | Q57: {=+INDEX('Réel 2024'!$A$2:$AO$501,MATCH($A57,'Réel 2024'!$A$2:$A$501,0),MATCH(Q$2,'Réel 2024'!$A$2:$AO$2,0))} -> 8585.79 | S57: =L57-Q57 -> -1998.81
A58: Véhicules neufsInformatique | B58: Véhicules neufs | C58: Informatique | F58: =+INDEX('Budget original'!$A$2:$AO$501,MATCH($A58,'Budget original'!$A$2:$A$501,0),MATCH(F$2,'Budget original'!$A$2:$AO$2,0)) -> 6690 | L58: =SUMIFS(BV_Data_An_Cour!$O:$O,BV_Data_An_Cour!$U:$U,$B58,BV_Data_An_Cour!$V:$V,$C58,BV_Data_An_Cour!$W:$W,L$2) -> 7443.72 | N58: =L58-F58 -> 753.72 | Q58: {=+INDEX('Réel 2024'!$A$2:$AO$501,MATCH($A58,'Réel 2024'!$A$2:$A$501,0),MATCH(Q$2,'Réel 2024'!$A$2:$AO$2,0))} -> 7256.78 | S58: =L58-Q58 -> 186.94
A59: Véhicules neufsFrais de déplacement | B59: Véhicules neufs | C59: Frais de déplacement | F59: =+INDEX('Budget original'!$A$2:$AO$501,MATCH($A59,'Budget original'!$A$2:$A$501,0),MATCH(F$2,'Budget original'!$A$2:$AO$2,0)) -> 1500 | L59: =SUMIFS(BV_Data_An_Cour!$O:$O,BV_Data_An_Cour!$U:$U,$B59,BV_Data_An_Cour!$V:$V,$C59,BV_Data_An_Cour!$W:$W,L$2) -> 1992.45 | N59: =L59-F59 -> 492.45 | Q59: {=+INDEX('Réel 2024'!$A$2:$AO$501,MATCH($A59,'Réel 2024'!$A$2:$A$501,0),MATCH(Q$2,'Réel 2024'!$A$2:$AO$2,0))} -> 1059.24 | S59: =L59-Q59 -> 933.21
A60: Véhicules neufsServices extérieurs | B60: Véhicules neufs | C60: Services extérieurs | F60: =+INDEX('Budget original'!$A$2:$AO$501,MATCH($A60,'Budget original'!$A$2:$A$501,0),MATCH(F$2,'Budget original'!$A$2:$AO$2,0)) -> 3629.12 | L60: =SUMIFS(BV_Data_An_Cour!$O:$O,BV_Data_An_Cour!$U:$U,$B60,BV_Data_An_Cour!$V:$V,$C60,BV_Data_An_Cour!$W:$W,L$2) -> 2526.25 | N60: =L60-F60 -> -1102.87 | Q60: {=+INDEX('Réel 2024'!$A$2:$AO$501,MATCH($A60,'Réel 2024'!$A$2:$A$501,0),MATCH(Q$2,'Réel 2024'!$A$2:$AO$2,0))} -> 10430.41 | S60: =L60-Q60 -> -7904.16
A61: Véhicules neufsFournitures autres | B61: Véhicules neufs | C61: Fournitures autres | F61: =+INDEX('Budget original'!$A$2:$AO$501,MATCH($A61,'Budget original'!$A$2:$A$501,0),MATCH(F$2,'Budget original'!$A$2:$AO$2,0)) -> 70 | L61: =SUMIFS(BV_Data_An_Cour!$O:$O,BV_Data_An_Cour!$U:$U,$B61,BV_Data_An_Cour!$V:$V,$C61,BV_Data_An_Cour!$W:$W,L$2) -> 0 | N61: =L61-F61 -> -70 | Q61: {=+INDEX('Réel 2024'!$A$2:$AO$501,MATCH($A61,'Réel 2024'!$A$2:$A$501,0),MATCH(Q$2,'Réel 2024'!$A$2:$AO$2,0))} -> 140.41 | S61: =L61-Q61 -> -140.41
A62: Véhicules neufsUniformes | B62: Véhicules neufs | C62: Uniformes | F62: =+INDEX('Budget original'!$A$2:$AO$501,MATCH($A62,'Budget original'!$A$2:$A$501,0),MATCH(F$2,'Budget original'!$A$2:$AO$2,0)) -> 0 | L62: =SUMIFS(BV_Data_An_Cour!$O:$O,BV_Data_An_Cour!$U:$U,$B62,BV_Data_An_Cour!$V:$V,$C62,BV_Data_An_Cour!$W:$W,L$2) -> 0 | N62: =L62-F62 -> 0 | Q62: {=+INDEX('Réel 2024'!$A$2:$AO$501,MATCH($A62,'Réel 2024'!$A$2:$A$501,0),MATCH(Q$2,'Réel 2024'!$A$2:$AO$2,0))} -> 0 | S62: =L62-Q62 -> 0
A63: Véhicules neufsPapeterie | B63: Véhicules neufs | C63: Papeterie | F63: =+INDEX('Budget original'!$A$2:$AO$501,MATCH($A63,'Budget original'!$A$2:$A$501,0),MATCH(F$2,'Budget original'!$A$2:$AO$2,0)) -> 595 | L63: =SUMIFS(BV_Data_An_Cour!$O:$O,BV_Data_An_Cour!$U:$U,$B63,BV_Data_An_Cour!$V:$V,$C63,BV_Data_An_Cour!$W:$W,L$2) -> 1096.38 | N63: =L63-F63 -> 501.38 | Q63: {=+INDEX('Réel 2024'!$A$2:$AO$501,MATCH($A63,'Réel 2024'!$A$2:$A$501,0),MATCH(Q$2,'Réel 2024'!$A$2:$AO$2,0))} -> 543.03 | S63: =L63-Q63 -> 553.35
A64: Véhicules neufsTéléphone | B64: Véhicules neufs | C64: Téléphone | F64: =+INDEX('Budget original'!$A$2:$AO$501,MATCH($A64,'Budget original'!$A$2:$A$501,0),MATCH(F$2,'Budget original'!$A$2:$AO$2,0)) -> 437.5 | L64: =SUMIFS(BV_Data_An_Cour!$O:$O,BV_Data_An_Cour!$U:$U,$B64,BV_Data_An_Cour!$V:$V,$C64,BV_Data_An_Cour!$W:$W,L$2) -> 188.84 | N64: =L64-F64 -> -248.66 | Q64: {=+INDEX('Réel 2024'!$A$2:$AO$501,MATCH($A64,'Réel 2024'!$A$2:$A$501,0),MATCH(Q$2,'Réel 2024'!$A$2:$AO$2,0))} -> 387.42 | S64: =L64-Q64 -> -198.58
A65: Véhicules neufsFrais postaux | B65: Véhicules neufs | C65: Frais postaux | F65: =+INDEX('Budget original'!$A$2:$AO$501,MATCH($A65,'Budget original'!$A$2:$A$501,0),MATCH(F$2,'Budget original'!$A$2:$AO$2,0)) -> 227.92 | L65: =SUMIFS(BV_Data_An_Cour!$O:$O,BV_Data_An_Cour!$U:$U,$B65,BV_Data_An_Cour!$V:$V,$C65,BV_Data_An_Cour!$W:$W,L$2) -> 73.97 | N65: =L65-F65 -> -153.95 | Q65: {=+INDEX('Réel 2024'!$A$2:$AO$501,MATCH($A65,'Réel 2024'!$A$2:$A$501,0),MATCH(Q$2,'Réel 2024'!$A$2:$AO$2,0))} -> 405.83 | S65: =L65-Q65 -> -331.86
A66: Véhicules neufsDivers | B66: Véhicules neufs | C66: Divers | F66: =+INDEX('Budget original'!$A$2:$AO$501,MATCH($A66,'Budget original'!$A$2:$A$501,0),MATCH(F$2,'Budget original'!$A$2:$AO$2,0)) -> 120 | L66: =SUMIFS(BV_Data_An_Cour!$O:$O,BV_Data_An_Cour!$U:$U,$B66,BV_Data_An_Cour!$V:$V,$C66,BV_Data_An_Cour!$W:$W,L$2) -> 338.63 | N66: =L66-F66 -> 218.63 | Q66: {=+INDEX('Réel 2024'!$A$2:$AO$501,MATCH($A66,'Réel 2024'!$A$2:$A$501,0),MATCH(Q$2,'Réel 2024'!$A$2:$AO$2,0))} -> 71.21 | S66: =L66-Q66 -> 267.42
... A68: Véhicules neufsFrais bancaires | B68: Véhicules neufs | C68: Frais bancaires | F68: =+INDEX('Budget original'!$A$2:$AO$501,MATCH($A68,'Budget original'!$A$2:$A$501,0),MATCH(F$2,'Budget original'!$A$2:$AO$2,0)) -> 3886.426 | L68: =SUMIFS(BV_Data_An_Cour!$O:$O,BV_Data_An_Cour!$U:$U,$B68,BV_Data_An_Cour!$V:$V,$C68,BV_Data_An_Cour!$W:$W,L$2) -> 3826.7 | N68: =L68-F68 -> -59.726029 | Q68: {=+INDEX('Réel 2024'!$A$2:$AO$501,MATCH($A68,'Réel 2024'!$A$2:$A$501,0),MATCH(Q$2,'Réel 2024'!$A$2:$AO$2,0))} -> 3719.82 | S68: =L68-Q68 -> 106.88
A69: Véhicules neufs[...] | B69: Véhicules neufs | C69: [...] | F69: =+INDEX('Budget original'!$A$2:$AO$501,MATCH($A69,'Budget original'!$A$2:$A$501,0),MATCH(F$2,'Budget original'!$A$2:$AO$2,0)) -> 0 | N69: =L69-F69 -> 0 | Q69: {=+INDEX('Réel 2024'!$A$2:$AO$501,MATCH($A69,'Réel 2024'!$A$2:$A$501,0),MATCH(Q$2,'Réel 2024'!$A$2:$AO$2,0))} -> 0 | S69: =L69-Q69 -> 0
A70: Véhicules neufs[...] | B70: Véhicules neufs | C70: [...] | F70: =+INDEX('Budget original'!$A$2:$AO$501,MATCH($A70,'Budget original'!$A$2:$A$501,0),MATCH(F$2,'Budget original'!$A$2:$AO$2,0)) -> 0 | L70: =SUMIFS(BV_Data_An_Cour!$O:$O,BV_Data_An_Cour!$U:$U,$B70,BV_Data_An_Cour!$V:$V,$C70,BV_Data_An_Cour!$W:$W,L$2) -> 0 | N70: =L70-F70 -> 0 | Q70: {=+INDEX('Réel 2024'!$A$2:$AO$501,MATCH($A70,'Réel 2024'!$A$2:$A$501,0),MATCH(Q$2,'Réel 2024'!$A$2:$AO$2,0))} -> 0 | S70: =L70-Q70 -> 0
A71: Véhicules neufs[...] | B71: Véhicules neufs | C71: [...] | F71: =+INDEX('Budget original'!$A$2:$AO$501,MATCH($A71,'Budget original'!$A$2:$A$501,0),MATCH(F$2,'Budget original'!$A$2:$AO$2,0)) -> 0 | L71: =SUMIFS(BV_Data_An_Cour!$O:$O,BV_Data_An_Cour!$U:$U,$B71,BV_Data_An_Cour!$V:$V,$C71,BV_Data_An_Cour!$W:$W,L$2)*0.32 -> 0 | N71: =L71-F71 -> 0 | Q71: {=+INDEX('Réel 2024'!$A$2:$AO$501,MATCH($A71,'Réel 2024'!$A$2:$A$501,0),MATCH(Q$2,'Réel 2024'!$A$2:$AO$2,0))} -> 0 | S71: =L71-Q71 -> 0
A72: Véhicules neufsTOTAL SEMI-FIXES | B72: Véhicules neufs | C72: TOTAL SEMI-FIXES | D72: % brut | E72: =F72/F$27 -> 0.10266039 | F72: =+SUM(F55:F71) -> 28025.181 | J72: % brut | K72: =L72/L$27 -> 0.15820805 | L72: =+SUM(L55:L71) -> 24777.28 | N72: =+SUM(N55:N71) -> -3247.9006 | O72: % brut | P72: =Q72/Q$27 -> 0.2345715 | Q72: =+SUM(Q55:Q71) -> 36469.92 | S72: =+SUM(S55:S71) -> -11692.64
A73: Véhicules neufs | B73: Véhicules neufs
A74: Véhicules neufsTOTAL DES DÉPENSES | B74: Véhicules neufs | C74: TOTAL DES DÉPENSES | D74: % brut | E74: =F74/F$27 -> 0.79988861 | F74: =F41+F54+F72 -> 218360.98 | J74: % brut | K74: =L74/L$27 -> 1.1298281 | L74: =L41+L54+L72 -> 176944.65 | N74: =L74-F74 -> -41416.331 | O74: % brut | P74: =Q74/Q$27 -> 1.3096225 | Q74: =Q41+Q54+Q72 -> 203613.09 | S74: =L74-Q74 -> -26668.44
A75: Véhicules neufsProgramme neuf 1 | B75: Véhicules neufs | C75: Programme neuf 1 | F75: =+INDEX('Budget original'!$A$2:$AO$501,MATCH($A75,'Budget original'!$A$2:$A$501,0),MATCH(F$2,'Budget original'!$A$2:$AO$2,0)) -> 35000 | L75: =-SUMIFS(BV_Data_An_Cour!$O:$O,BV_Data_An_Cour!$U:$U,$B75,BV_Data_An_Cour!$V:$V,$C75,BV_Data_An_Cour!$W:$W,L$2)-L156 -> 37700 | N75: =L75-F75 -> 2700 | Q75: =+INDEX('Réel 2024'!$A$2:$AO$501,MATCH($A75,'Réel 2024'!$A$2:$A$501,0),MATCH(Q$2,'Réel 2024'!$A$2:$AO$2,0)) -> 0
A76: Véhicules neufsProgramme neuf 2 | B76: Véhicules neufs | C76: Programme neuf 2 | F76: =+INDEX('Budget original'!$A$2:$AO$501,MATCH($A76,'Budget original'!$A$2:$A$501,0),MATCH(F$2,'Budget original'!$A$2:$AO$2,0)) -> 0 | L76: =-SUMIFS(BV_Data_An_Cour!$O:$O,BV_Data_An_Cour!$U:$U,$B76,BV_Data_An_Cour!$V:$V,$C76,BV_Data_An_Cour!$W:$W,L$2) -> 0 | N76: =L76-F76 -> 0 | Q76: {=+INDEX('Réel 2024'!$A$2:$AO$501,MATCH($A76,'Réel 2024'!$A$2:$A$501,0),MATCH(Q$2,'Réel 2024'!$A$2:$AO$2,0))} -> 0 | S76: =L76-Q76 -> 0
A77: Véhicules neufsProgramme neuf 3 | B77: Véhicules neufs | C77: Programme neuf 3 | F77: =+INDEX('Budget original'!$A$2:$AO$501,MATCH($A77,'Budget original'!$A$2:$A$501,0),MATCH(F$2,'Budget original'!$A$2:$AO$2,0)) -> 0 | L77: =-SUMIFS(BV_Data_An_Cour!$O:$O,BV_Data_An_Cour!$U:$U,$B77,BV_Data_An_Cour!$V:$V,$C77,BV_Data_An_Cour!$W:$W,L$2) -> 0 | N77: =L77-F77 -> 0 | Q77: {=+INDEX('Réel 2024'!$A$2:$AO$501,MATCH($A77,'Réel 2024'!$A$2:$A$501,0),MATCH(Q$2,'Réel 2024'!$A$2:$AO$2,0))} -> 0 | S77: =L77-Q77 -> 0
A78: Véhicules neufsHoldbacks | B78: Véhicules neufs | C78: Holdbacks | E78: =+F78/D27 -> 1277.8827 | F78: =+INDEX('Budget original'!$A$2:$AO$501,MATCH($A78,'Budget original'!$A$2:$A$501,0),MATCH(F$2,'Budget original'!$A$2:$AO$2,0)) -> 100952.73 | K78: =+L78/J27 -> 1615.2856 | L78: =-SUMIFS(BV_Data_An_Cour!$O:$O,BV_Data_An_Cour!$U:$U,$B78,BV_Data_An_Cour!$V:$V,$C78,BV_Data_An_Cour!$W:$W,L$2) -> 129222.85 | N78: =L78-F78 -> 28270.117 | Q78: {=+INDEX('Réel 2024'!$A$2:$AO$501,MATCH($A78,'Réel 2024'!$A$2:$A$501,0),MATCH(Q$2,'Réel 2024'!$A$2:$AO$2,0))} -> 69794 | S78: =L78-Q78 -> 59428.85
