Workbook
Name Ticker: #REF!
Name Ticker: #REF!

Sheet Parametres
A1: Compagnie | B1: Volks
G2: 1-Mémo | M2: Mois | N2: YTD
A3: Mois Courant | B3: Juillet | C3: =+VLOOKUP(B3,$K$3:$L$14,2,0) -> 7 | G3: 10-Compte compteur | K3: Janvier | L3: 1 | M3: =+IF($K3=$B$3,"X","") | N3: =+IF(K3=B3,"X",IF(L3<=$C$3,"X","")) -> X
A4: Année | B4: 2025 | K4: Février | L4: 2 | M4: =+IF($K4=$B$3,"X","") | N4: =+IF(K4=B4,"X",IF(L4<=$C$3,"X","")) -> X
K5: Mars | L5: 3 | M5: =+IF($K5=$B$3,"X","") | N5: =+IF(K5=B5,"X",IF(L5<=$C$3,"X","")) -> X
K6: Avril | L6: 4 | M6: =+IF($K6=$B$3,"X","") | N6: =+IF(K6=B6,"X",IF(L6<=$C$3,"X","")) -> X
K7: Mai | L7: 5 | M7: =+IF($K7=$B$3,"X","") | N7: =+IF(K7=B7,"X",IF(L7<=$C$3,"X","")) -> X
K8: Juin | L8: 6 | M8: =+IF($K8=$B$3,"X","") | N8: =+IF(K8=B8,"X",IF(L8<=$C$3,"X","")) -> X
A9: Sélectionner le mois en B3 | K9: Juillet | L9: 7 | M9: =+IF($K9=$B$3,"X","") -> X | N9: =+IF(K9=B9,"X",IF(L9<=$C$3,"X","")) -> X
A10: Coller les balances de vérification respectives en cellule A1 dans les onglets BV_Data_An_Cour et BV_Data_An_Prec | K10: Août | L10: 8 | M10: =+IF($K10=$B$3,"X","") | N10: =+IF(K10=B10,"X",IF(L10<=$C$3,"X",""))
A11: Vérifier s'il y a des #N/A dans les colonnes T à X des onlgets de BV | K11: Septembre | L11: 9 | M11: =+IF($K11=$B$3,"X","") | N11: =+IF(K11=B11,"X",IF(L11<=$C$3,"X",""))
A12: Vérifier les chiffres avec l'état financier et les réalisés an passé pour les résultat net mois et aad | K12: Octobre | L12: 10 | M12: =+IF($K12=$B$3,"X","") | N12: =+IF(K12=B12,"X",IF(L12<=$C$3,"X",""))
K13: Novembre | L13: 11 | M13: =+IF($K13=$B$3,"X","") | N13: =+IF(K13=B13,"X",IF(L13<=$C$3,"X",""))
K14: Décembre | L14: 12 | M14: =+IF($K14=$B$3,"X","") | N14: =+IF(K14=B14,"X",IF(L14<=$C$3,"X",""))

Sheet Bilan
A1: BILAN
A2: =+Parametres!B1 -> Volks
A3: =CONCATENATE("",,Parametres!B3," ",Parametres!B4) -> Juillet 2025
A5: Encaisse | B5: =SUMIFS(BV_Data_An_Cour!$P:$P,BV_Data_An_Cour!$U:$U,$A$1,BV_Data_An_Cour!$V:$V,$A5) -> 104754.7 | D5: Marge de crédit | E5: =-SUMIFS(BV_Data_An_Cour!$P:$P,BV_Data_An_Cour!$U:$U,$A$1,BV_Data_An_Cour!$V:$V,$D5) -> 0
A6: Total Trésorerie et équivalent de Trésorerie | B6: =SUM(B5) -> 104754.7
D7: Portion Court Terme de la Dette Long Terme | E7: =-SUMIFS(BV_Data_An_Cour!$P:$P,BV_Data_An_Cour!$U:$U,$A$1,BV_Data_An_Cour!$V:$V,$D7) -> 0
A8: Recevables Contrats en Transit | B8: =SUMIFS(BV_Data_An_Cour!$P:$P,BV_Data_An_Cour!$U:$U,$A$1,BV_Data_An_Cour!$V:$V,$A8) -> 991942.07
A9: Recevables Véhicules | B9: =SUMIFS(BV_Data_An_Cour!$P:$P,BV_Data_An_Cour!$U:$U,$A$1,BV_Data_An_Cour!$V:$V,$A9) -> 491754.35 | D9: Avances à payer | E9: =-SUMIFS(BV_Data_An_Cour!$P:$P,BV_Data_An_Cour!$U:$U,$A$1,BV_Data_An_Cour!$V:$V,$D9) -> 0
A10: Recevables Manufacturier | B10: =SUMIFS(BV_Data_An_Cour!$P:$P,BV_Data_An_Cour!$U:$U,$A$1,BV_Data_An_Cour!$V:$V,$A10) -> 229390 | D10: Comptes à Payer Fournisseurs | E10: =-SUMIFS(BV_Data_An_Cour!$P:$P,BV_Data_An_Cour!$U:$U,$A$1,BV_Data_An_Cour!$V:$V,$D10) -> 404715.46
A11: Recevables Pièces et Service | B11: =SUMIFS(BV_Data_An_Cour!$P:$P,BV_Data_An_Cour!$U:$U,$A$1,BV_Data_An_Cour!$V:$V,$A11) -> 196011.14 | D11: Taxes de Vente à Payer | E11: =-SUMIFS(BV_Data_An_Cour!$P:$P,BV_Data_An_Cour!$U:$U,$A$1,BV_Data_An_Cour!$V:$V,$D11) -> 72856.79
A12: Recevables Garantie Manufacturier | B12: =SUMIFS(BV_Data_An_Cour!$P:$P,BV_Data_An_Cour!$U:$U,$A$1,BV_Data_An_Cour!$V:$V,$A12) -> 113753.84 | D12: Impôts à payer | E12: =-SUMIFS(BV_Data_An_Cour!$P:$P,BV_Data_An_Cour!$U:$U,$A$1,BV_Data_An_Cour!$V:$V,$D12) -> 0
A13: Recevables Carrosserie | B13: =SUMIFS(BV_Data_An_Cour!$P:$P,BV_Data_An_Cour!$U:$U,$A$1,BV_Data_An_Cour!$V:$V,$A13) -> 10686.27 | D13: Dépôts de Client | E13: =-SUMIFS(BV_Data_An_Cour!$P:$P,BV_Data_An_Cour!$U:$U,$A$1,BV_Data_An_Cour!$V:$V,$D13) -> 28850
A14: Recevables Intercos | B14: =SUMIFS(BV_Data_An_Cour!$P:$P,BV_Data_An_Cour!$U:$U,$A$1,BV_Data_An_Cour!$V:$V,$A14) -> 117631.28 | D14: Payables Intercos | E14: =-SUMIFS(BV_Data_An_Cour!$P:$P,BV_Data_An_Cour!$U:$U,$A$1,BV_Data_An_Cour!$V:$V,$D14) -> 98608.04
A15: Recevables Autres | B15: =SUMIFS(BV_Data_An_Cour!$P:$P,BV_Data_An_Cour!$U:$U,$A$1,BV_Data_An_Cour!$V:$V,$A15) -> -1665.65 | D15: Autres Comptes à Payer | E15: =-SUMIFS(BV_Data_An_Cour!$P:$P,BV_Data_An_Cour!$U:$U,$A$1,BV_Data_An_Cour!$V:$V,$D15) -> 521616
A16: Total Comptes à Recevoir | B16: =+SUM(B8:B15) -> 2149503.3 | D16: Total Comptes à Payer | E16: =+SUM(E10:E15) -> 1126646.3
A18: Inventaire Véhicules Neufs | B18: =SUMIFS(BV_Data_An_Cour!$P:$P,BV_Data_An_Cour!$U:$U,$A$1,BV_Data_An_Cour!$V:$V,$A18) -> 4980838 | D18: Effet à Payer Véhicules Neufs | E18: =-SUMIFS(BV_Data_An_Cour!$P:$P,BV_Data_An_Cour!$U:$U,$A$1,BV_Data_An_Cour!$V:$V,$D18) -> 6607400.1
A19: Inventaire Véhicules Usagés | B19: =SUMIFS(BV_Data_An_Cour!$P:$P,BV_Data_An_Cour!$U:$U,$A$1,BV_Data_An_Cour!$V:$V,$A19) -> 1775371.1 | D19: Effet à Payer Véhicules Usagés | E19: =-SUMIFS(BV_Data_An_Cour!$P:$P,BV_Data_An_Cour!$U:$U,$A$1,BV_Data_An_Cour!$V:$V,$D19) -> 614115.28
A20: Inventaire Pièces, Pneus, Huile | B20: =SUMIFS(BV_Data_An_Cour!$P:$P,BV_Data_An_Cour!$U:$U,$A$1,BV_Data_An_Cour!$V:$V,$A20) -> 573866.21 | D20: Total Effets à Payer | E20: =+SUM(E18:E19) -> 7221515.4
A21: Total Inventaires | B21: =SUM(B18:B20) -> 7330075.3
D22: Salaires à Payer | E22: =-SUMIFS(BV_Data_An_Cour!$P:$P,BV_Data_An_Cour!$U:$U,$A$1,BV_Data_An_Cour!$V:$V,$D22) -> 473403.06
A23: Avances à recevoir | B23: =SUMIFS(BV_Data_An_Cour!$P:$P,BV_Data_An_Cour!$U:$U,$A$1,BV_Data_An_Cour!$V:$V,$A23) -> 0 | D23: DAS à Payer | E23: =-SUMIFS(BV_Data_An_Cour!$P:$P,BV_Data_An_Cour!$U:$U,$A$1,BV_Data_An_Cour!$V:$V,$D23) -> -10796.08
A24: Travaux en Cours | B24: =SUMIFS(BV_Data_An_Cour!$P:$P,BV_Data_An_Cour!$U:$U,$A$1,BV_Data_An_Cour!$V:$V,$A24) -> 12303.47 | D24: Autres Courus | E24: =-SUMIFS(BV_Data_An_Cour!$P:$P,BV_Data_An_Cour!$U:$U,$A$1,BV_Data_An_Cour!$V:$V,$D24) -> 446733.66
A25: Sous-Traitance | B25: =SUMIFS(BV_Data_An_Cour!$P:$P,BV_Data_An_Cour!$U:$U,$A$1,BV_Data_An_Cour!$V:$V,$A25) -> -28170.96 | D25: [...] | E25: =-SUMIFS(BV_Data_An_Cour!$P:$P,BV_Data_An_Cour!$U:$U,$A$1,BV_Data_An_Cour!$V:$V,$D25) -> 0
A26: Frais Payés d'Avance | B26: =SUMIFS(BV_Data_An_Cour!$P:$P,BV_Data_An_Cour!$U:$U,$A$1,BV_Data_An_Cour!$V:$V,$A26) -> -7604.54 | D26: [...] | E26: =-SUMIFS(BV_Data_An_Cour!$P:$P,BV_Data_An_Cour!$U:$U,$A$1,BV_Data_An_Cour!$V:$V,$D26) -> 0
A27: [...] | B27: =SUMIFS(BV_Data_An_Cour!$P:$P,BV_Data_An_Cour!$U:$U,$A$1,BV_Data_An_Cour!$V:$V,$A27) -> 0 | D27: [...] | E27: =-SUMIFS(BV_Data_An_Cour!$P:$P,BV_Data_An_Cour!$U:$U,$A$1,BV_Data_An_Cour!$V:$V,$D27) -> 0
A28: [...] | B28: =SUMIFS(BV_Data_An_Cour!$P:$P,BV_Data_An_Cour!$U:$U,$A$1,BV_Data_An_Cour!$V:$V,$A28) -> 0 | D28: Total Frais Courus | E28: =SUM(E22:E24) -> 909340.64
A29: [...] | B29: =SUMIFS(BV_Data_An_Cour!$P:$P,BV_Data_An_Cour!$U:$U,$A$1,BV_Data_An_Cour!$V:$V,$A29) -> 0
A30: Total Autres | B30: =SUM(B23:B29) -> -23472.03 | D30: Total Passif Court Terme | E30: =+E5+E7+E16+E20+E28 -> 9257502.3
A32: Total Actif Court Terme | B32: =+B6+B16+B21+B30 -> 9560861.3
D33: Impôts Futurs à payer | E33: =-SUMIFS(BV_Data_An_Cour!$P:$P,BV_Data_An_Cour!$U:$U,$A$1,BV_Data_An_Cour!$V:$V,$D33) -> 0
A35: Terrain | B35: =SUMIFS(BV_Data_An_Cour!$P:$P,BV_Data_An_Cour!$U:$U,$A$1,BV_Data_An_Cour!$V:$V,$A35) -> 0 | D35: Avances Long Terme à Payer | E35: =-SUMIFS(BV_Data_An_Cour!$P:$P,BV_Data_An_Cour!$U:$U,$A$1,BV_Data_An_Cour!$V:$V,$D35) -> 0
A36: Bâtisse | B36: =SUMIFS(BV_Data_An_Cour!$P:$P,BV_Data_An_Cour!$U:$U,$A$1,BV_Data_An_Cour!$V:$V,$A36) -> 0 | D36: Hypothèque à Payer | E36: =-SUMIFS(BV_Data_An_Cour!$P:$P,BV_Data_An_Cour!$U:$U,$A$1,BV_Data_An_Cour!$V:$V,$D36) -> 0
A37: Améliorations Locatives | B37: =SUMIFS(BV_Data_An_Cour!$P:$P,BV_Data_An_Cour!$U:$U,$A$1,BV_Data_An_Cour!$V:$V,$A37) -> -8394.37 | D37: Dette à Long Terme | E37: =-SUMIFS(BV_Data_An_Cour!$P:$P,BV_Data_An_Cour!$U:$U,$A$1,BV_Data_An_Cour!$V:$V,$D37) -> 0
A38: Améliorations Locatives Permanentes | B38: =SUMIFS(BV_Data_An_Cour!$P:$P,BV_Data_An_Cour!$U:$U,$A$1,BV_Data_An_Cour!$V:$V,$A38) -> 0 | D38: Autres Dettes à Long Terme | E38: =-SUMIFS(BV_Data_An_Cour!$P:$P,BV_Data_An_Cour!$U:$U,$A$1,BV_Data_An_Cour!$V:$V,$D38) -> 0
A39: Équipements Service | B39: =SUMIFS(BV_Data_An_Cour!$P:$P,BV_Data_An_Cour!$U:$U,$A$1,BV_Data_An_Cour!$V:$V,$A39) -> 385618.82 | D39: [...] | E39: =-SUMIFS(BV_Data_An_Cour!$P:$P,BV_Data_An_Cour!$U:$U,$A$1,BV_Data_An_Cour!$V:$V,$D39) -> 0
A40: Mobilier | B40: =SUMIFS(BV_Data_An_Cour!$P:$P,BV_Data_An_Cour!$U:$U,$A$1,BV_Data_An_Cour!$V:$V,$A40) -> 30124.81 | D40: [...] | E40: =-SUMIFS(BV_Data_An_Cour!$P:$P,BV_Data_An_Cour!$U:$U,$A$1,BV_Data_An_Cour!$V:$V,$D40) -> 0
A41: Équipements Informatique | B41: =SUMIFS(BV_Data_An_Cour!$P:$P,BV_Data_An_Cour!$U:$U,$A$1,BV_Data_An_Cour!$V:$V,$A41) -> 60720.81 | D41: [...] | E41: =-SUMIFS(BV_Data_An_Cour!$P:$P,BV_Data_An_Cour!$U:$U,$A$1,BV_Data_An_Cour!$V:$V,$D41) -> 0
A42: Équipements Téléphonique | B42: =SUMIFS(BV_Data_An_Cour!$P:$P,BV_Data_An_Cour!$U:$U,$A$1,BV_Data_An_Cour!$V:$V,$A42) -> 0 | D42: Total Passif long terme | E42: =+SUM(E33:E38) -> 0
A43: Enseigne | B43: =SUMIFS(BV_Data_An_Cour!$P:$P,BV_Data_An_Cour!$U:$U,$A$1,BV_Data_An_Cour!$V:$V,$A43) -> 6327.01
A44: Total Immobilisations Nettes | B44: =SUM(B35:B43) -> 474397.08
D45: Total Passifs | E45: =+E42+E30 -> 9257502.3
A46: Avances à Recevoir Long Terme | B46: =SUMIFS(BV_Data_An_Cour!$P:$P,BV_Data_An_Cour!$U:$U,$A$1,BV_Data_An_Cour!$V:$V,$A46) -> 2323600
A48: Achalandage | B48: =SUMIFS(BV_Data_An_Cour!$P:$P,BV_Data_An_Cour!$U:$U,$A$1,BV_Data_An_Cour!$V:$V,$A48) -> 0 | D48: Capital Actions | E48: =-SUMIFS(BV_Data_An_Cour!$P:$P,BV_Data_An_Cour!$U:$U,$A$1,BV_Data_An_Cour!$V:$V,$D48) -> 2697547.5
D49: Apport | E49: =-SUMIFS(BV_Data_An_Cour!$P:$P,BV_Data_An_Cour!$U:$U,$A$1,BV_Data_An_Cour!$V:$V,$D49) -> 1723617
A50: [...] | B50: =SUMIFS(BV_Data_An_Cour!$P:$P,BV_Data_An_Cour!$U:$U,$A$1,BV_Data_An_Cour!$V:$V,$A50) -> 0 | D50: Bénéfices non répartis | E50: =-SUMIFS(BV_Data_An_Cour!$P:$P,BV_Data_An_Cour!$U:$U,$A$1,BV_Data_An_Cour!$V:$V,$D50)+Print_AAD!AF498 -> -1319808.4
A51: [...] | B51: =SUMIFS(BV_Data_An_Cour!$P:$P,BV_Data_An_Cour!$U:$U,$A$1,BV_Data_An_Cour!$V:$V,$A51) -> 0 | D51: Dividendes | E51: =-SUMIFS(BV_Data_An_Cour!$P:$P,BV_Data_An_Cour!$U:$U,$A$1,BV_Data_An_Cour!$V:$V,$D51) -> 0
A52: [...] | B52: =SUMIFS(BV_Data_An_Cour!$P:$P,BV_Data_An_Cour!$U:$U,$A$1,BV_Data_An_Cour!$V:$V,$A52) -> 0
A53: Total Actif Long Terme | B53: =+B44+B48+B46 -> 2797997.1 | D53: Total Capitaux Propres / Avoir | E53: =SUM(E48:E51) -> 3101356.1
A56: Total Actif | B56: =+B32+B53 -> 12358858 | D56: Total Passif et Capitaux Propres / Avoir | E56: =+E53+E45 -> 12358858
E65: =+B56-E56 -> 0

Sheet Budget original
B1: ="Budget 2024 Mensuel Révisé"&" "&Parametres!$B$1 -> Budget 2024 Mensuel Révisé Volks
B2: Mois | F2: =+IF(Parametres!$B$3=F$6,"X","") | G2: =+IF(Parametres!$B$3=F$6,"O","") | H2: =+IF(Parametres!$B$3=F$6,"U","") | I2: =+IF(Parametres!$B$3=I$6,"X","") | J2: =+IF(Parametres!$B$3=I$6,"O","") | K2: =+IF(Parametres!$B$3=I$6,"U","") | L2: =+IF(Parametres!$B$3=L$6,"X","") | M2: =+IF(Parametres!$B$3=L$6,"O","") | N2: =+IF(Parametres!$B$3=L$6,"U","") | O2: =+IF(Parametres!$B$3=O$6,"X","") | P2: =+IF(Parametres!$B$3=O$6,"O","") | Q2: =+IF(Parametres!$B$3=O$6,"U","") | R2: =+IF(Parametres!$B$3=R$6,"X","") | S2: =+IF(Parametres!$B$3=R$6,"O","") | T2: =+IF(Parametres!$B$3=R$6,"U","") | U2: =+IF(Parametres!$B$3=U$6,"X","") | V2: =+IF(Parametres!$B$3=U$6,"O","") | W2: =+IF(Parametres!$B$3=U$6,"U","") | X2: =+IF(Parametres!$B$3=X$6,"X","") -> X | Y2: =+IF(Parametres!$B$3=X$6,"O","") -> O | Z2: =+IF(Parametres!$B$3=X$6,"U","") -> U | AA2: =+IF(Parametres!$B$3=AA$6,"X","") | AB2: =+IF(Parametres!$B$3=AA$6,"O","") | AC2: =+IF(Parametres!$B$3=AA$6,"U","") | AD2: =+IF(Parametres!$B$3=AD$6,"X","") | AE2: =+IF(Parametres!$B$3=AD$6,"O","") | AF2: =+IF(Parametres!$B$3=AD$6,"U","") | AG2: =+IF(Parametres!$B$3=AG$6,"X","") | AH2: =+IF(Parametres!$B$3=AG$6,"O","") | AI2: =+IF(Parametres!$B$3=AG$6,"U","") | AJ2: =+IF(Parametres!$B$3=AJ$6,"X","") | AK2: =+IF(Parametres!$B$3=AJ$6,"O","") | AL2: =+IF(Parametres!$B$3=AJ$6,"U","") | AM2: =+IF(Parametres!$B$3=AM$6,"X","") | AN2: =+IF(Parametres!$B$3=AM$6,"O","") | AO2: =+IF(Parametres!$B$3=AM$6,"U","")
B3: YTD | F3: =+IF(VLOOKUP(F$6,Parametres!$K$3:$N$14,4,0)="X","X","") -> X | G3: =+IF(VLOOKUP(F$6,Parametres!$K$3:$N$14,4,0)="X","O","") -> O | H3: =+IF(VLOOKUP(F$6,Parametres!$K$3:$N$14,4,0)="X","U","") -> U | I3: =+IF(VLOOKUP(I$6,Parametres!$K$3:$N$14,4,0)="X","X","") -> X | J3: =+IF(VLOOKUP(I$6,Parametres!$K$3:$N$14,4,0)="X","O","") -> O | K3: =+IF(VLOOKUP(I$6,Parametres!$K$3:$N$14,4,0)="X","U","") -> U | L3: =+IF(VLOOKUP(L$6,Parametres!$K$3:$N$14,4,0)="X","X","") -> X | M3: =+IF(VLOOKUP(L$6,Parametres!$K$3:$N$14,4,0)="X","O","") -> O | N3: =+IF(VLOOKUP(L$6,Parametres!$K$3:$N$14,4,0)="X","U","") -> U | O3: =+IF(VLOOKUP(O$6,Parametres!$K$3:$N$14,4,0)="X","X","") -> X | P3: =+IF(VLOOKUP(O$6,Parametres!$K$3:$N$14,4,0)="X","O","") -> O | Q3: =+IF(VLOOKUP(O$6,Parametres!$K$3:$N$14,4,0)="X","U","") -> U | R3: =+IF(VLOOKUP(R$6,Parametres!$K$3:$N$14,4,0)="X","X","") -> X | S3: =+IF(VLOOKUP(R$6,Parametres!$K$3:$N$14,4,0)="X","O","") -> O | T3: =+IF(VLOOKUP(R$6,Parametres!$K$3:$N$14,4,0)="X","U","") -> U | U3: =+IF(VLOOKUP(U$6,Parametres!$K$3:$N$14,4,0)="X","X","") -> X | V3: =+IF(VLOOKUP(U$6,Parametres!$K$3:$N$14,4,0)="X","O","") -> O | W3: =+IF(VLOOKUP(U$6,Parametres!$K$3:$N$14,4,0)="X","U","") -> U | X3: =+IF(VLOOKUP(X$6,Parametres!$K$3:$N$14,4,0)="X","X","") -> X | Y3: =+IF(VLOOKUP(X$6,Parametres!$K$3:$N$14,4,0)="X","O","") -> O | Z3: =+IF(VLOOKUP(X$6,Parametres!$K$3:$N$14,4,0)="X","U","") -> U | AA3: =+IF(VLOOKUP(AA$6,Parametres!$K$3:$N$14,4,0)="X","X","") | AB3: =+IF(VLOOKUP(AA$6,Parametres!$K$3:$N$14,4,0)="X","O","") | AC3: =+IF(VLOOKUP(AA$6,Parametres!$K$3:$N$14,4,0)="X","U","") | AD3: =+IF(VLOOKUP(AD$6,Parametres!$K$3:$N$14,4,0)="X","X","") | AE3: =+IF(VLOOKUP(AD$6,Parametres!$K$3:$N$14,4,0)="X","O","") | AF3: =+IF(VLOOKUP(AD$6,Parametres!$K$3:$N$14,4,0)="X","U","") | AG3: =+IF(VLOOKUP(AG$6,Parametres!$K$3:$N$14,4,0)="X","X","") | AH3: =+IF(VLOOKUP(AG$6,Parametres!$K$3:$N$14,4,0)="X","O","") | AI3: =+IF(VLOOKUP(AG$6,Parametres!$K$3:$N$14,4,0)="X","U","") | AJ3: =+IF(VLOOKUP(AJ$6,Parametres!$K$3:$N$14,4,0)="X","X","") | AK3: =+IF(VLOOKUP(AJ$6,Parametres!$K$3:$N$14,4,0)="X","O","") | AL3: =+IF(VLOOKUP(AJ$6,Parametres!$K$3:$N$14,4,0)="X","U","") | AM3: =+IF(VLOOKUP(AM$6,Parametres!$K$3:$N$14,4,0)="X","X","") | AN3: =+IF(VLOOKUP(AM$6,Parametres!$K$3:$N$14,4,0)="X","O","") | AO3: =+IF(VLOOKUP(AM$6,Parametres!$K$3:$N$14,4,0)="X","U","")
B4: Budget 2025 | C4: Véhicules neufs
B6: Mois | C6: 2025 | F6: Janvier | I6: Février | L6: Mars | O6: Avril | R6: Mai | U6: Juin | X6: Juillet | AA6: Août | AD6: Septembre | AG6: Octobre | AJ6: Novembre | AM6: Décembre
C7: UNITE | D7: $P/UNITE | E7: $PROFITS | F7: UNITE | G7: $P/UNITE | H7: $PROFITS | I7: UNITE | J7: $P/UNITE | K7: $PROFITS | L7: UNITE | M7: $P/UNITE | N7: $PROFITS | O7: UNITE | P7: $P/UNITE | Q7: $PROFITS | R7: UNITE | S7: $P/UNITE | T7: $PROFITS | U7: UNITE | V7: $P/UNITE | W7: $PROFITS | X7: UNITE | Y7: $P/UNITE | Z7: $PROFITS | AA7: UNITE | AB7: $P/UNITE | AC7: $PROFITS | AD7: UNITE | AE7: $P/UNITE | AF7: $PROFITS | AG7: UNITE | AH7: $P/UNITE | AI7: $PROFITS | AJ7: UNITE | AK7: $P/UNITE | AL7: $PROFITS | AM7: UNITE | AN7: $P/UNITE | AO7: $PROFITS
A8: =+$C$4&B8 -> Véhicules neufsVentes nettes | B8: Ventes nettes | E8: 42012202 | H8: 2738793.1 | K8: 2857429.7 | N8: 3142915.1 | Q8: 3150915.1 | T8: 3234339.5 | W8: 3782098.2 | Z8: 3782098.2 | AC8: 4621342.2 | AF8: 3359976.1 | AI8: 3781098.2 | AL8: 4620342.2 | AO8: 2940854.1
A9: =+$C$4&B9 -> Véhicules neufsAutos détail | B9: Autos détail | C9: 206 | D9: 1953.6492 | E9: 402451.73 | F9: 15 | G9: 1953.6492 | H9: 29304.738 | I9: 14 | J9: 1953.6492 | K9: 27351.088 | L9: 13 | M9: 1953.6492 | N9: 25397.439 | O9: 15 | P9: 1953.6492 | Q9: 29304.738 | R9: 16 | S9: 1953.6492 | T9: 31258.387 | U9: 19 | V9: 1953.6492 | W9: 37119.334 | X9: 19 | Y9: 1953.6492 | Z9: 37119.334 | AA9: 23 | AB9: 1953.6492 | AC9: 44933.931 | AD9: 16 | AE9: 1953.6492 | AF9: 31258.387 | AG9: 19 | AH9: 1953.6492 | AI9: 37119.334 | AJ9: 23 | AK9: 1953.6492 | AL9: 44933.931 | AM9: 14 | AN9: 1953.6492 | AO9: 27351.088
A10: =+$C$4&B10 -> Véhicules neufsCamions détail | B10: Camions détail | C10: 555 | D10: 2435.9047 | E10: 1351927.1 | F10: 42 | G10: 2435.9047 | H10: 102308 | I10: 38 | J10: 2435.9047 | K10: 92564.378 | L10: 36 | M10: 2435.9047 | N10: 87692.568 | O10: 42 | P10: 2435.9047 | Q10: 102308 | R10: 43 | S10: 2435.9047 | T10: 104743.9 | U10: 50 | V10: 2435.9047 | W10: 121795.23 | X10: 50 | Y10: 2435.9047 | Z10: 121795.23 | AA10: 61 | AB10: 2435.9047 | AC10: 148590.19 | AD10: 44 | AE10: 2435.9047 | AF10: 107179.81 | AG10: 50 | AH10: 2435.9047 | AI10: 121795.23 | AJ10: 60 | AK10: 2435.9047 | AL10: 146154.28 | AM10: 39 | AN10: 2435.9047 | AO10: 95000.282
A11: =+$C$4&B11 -> Véhicules neufsSprinter | B11: Sprinter | C11: 0 | D11: 0 | E11: 0 | F11: 0 | G11: 0 | H11: 0 | I11: 0 | J11: 0 | K11: 0 | L11: 0 | M11: 0 | N11: 0 | O11: 0 | P11: 0 | Q11: 0 | R11: 0 | S11: 0 | T11: 0 | U11: 0 | V11: 0 | W11: 0 | X11: 0 | Y11: 0 | Z11: 0 | AA11: 0 | AB11: 0 | AC11: 0 | AD11: 0 | AE11: 0 | AF11: 0 | AG11: 0 | AH11: 0 | AI11: 0 | AJ11: 0 | AK11: 0 | AL11: 0 | AM11: 0 | AN11: 0 | AO11: 0
A12: =+$C$4&B12 -> Véhicules neufsMoto détail | B12: Moto détail | C12: 0 | D12: 0 | E12: 0 | F12: 0 | G12: 0 | H12: 0 | I12: 0 | J12: 0 | K12: 0 | L12: 0 | M12: 0 | N12: 0 | O12: 0 | P12: 0 | Q12: 0 | R12: 0 | S12: 0 | T12: 0 | U12: 0 | V12: 0 | W12: 0 | X12: 0 | Y12: 0 | Z12: 0 | AA12: 0 | AB12: 0 | AC12: 0 | AD12: 0 | AE12: 0 | AF12: 0 | AG12: 0 | AH12: 0 | AI12: 0 | AJ12: 0 | AK12: 0 | AL12: 0 | AM12: 0 | AN12: 0 | AO12: 0
A13: =+$C$4&B13 -> Véhicules neufs[...] | B13: [...] | C13: 0 | D13: 0 | E13: 0 | G13: 0 | J13: 0 | M13: 0 | P13: 0 | S13: 0 | V13: 0 | Y13: 0 | AB13: 0 | AE13: 0 | AH13: 0 | AK13: 0 | AN13: 0
A14: =+$C$4&B14 -> Véhicules neufs[...] | B14: [...] | C14: 0 | D14: 0 | E14: 0 | G14: 0 | J14: 0 | M14: 0 | P14: 0 | S14: 0 | V14: 0 | Y14: 0 | AB14: 0 | AE14: 0 | AH14: 0 | AK14: 0 | AN14: 0
A15: =+$C$4&B15 -> Véhicules neufs[...] | B15: [...] | C15: 0 | D15: 0 | E15: 0 | G15: 0 | J15: 0 | M15: 0 | P15: 0 | S15: 0 | V15: 0 | Y15: 0 | AB15: 0 | AE15: 0 | AH15: 0 | AK15: 0 | AN15: 0
A16: =+$C$4&B16 -> Véhicules neufsTotal Neufs | B16: Total Neufs | C16: 761 | D16: 2305.3598 | E16: 1754378.8 | F16: 57 | G16: 2308.9953 | H16: 131612.73 | I16: 52 | J16: 2306.0667 | K16: 119915.47 | L16: 49 | M16: 2307.9593 | N16: 113090.01 | O16: 57 | P16: 2308.9953 | Q16: 131612.73 | R16: 59 | S16: 2305.1235 | T16: 136002.29 | U16: 69 | V16: 2303.1097 | W16: 158914.57 | X16: 69 | Y16: 2303.1097 | Z16: 158914.57 | AA16: 84 | AB16: 2303.8585 | AC16: 193524.12 | AD16: 60 | AE16: 2307.3032 | AF16: 138438.19 | AG16: 69 | AH16: 2303.1097 | AI16: 158914.57 | AJ16: 83 | AK16: 2302.2676 | AL16: 191088.21 | AM16: 53 | AN16: 2308.5164 | AO16: 122351.37
A17: =+$C$4&B17 -> Véhicules neufs
A18: =+$C$4&B18 -> Véhicules neufsEx-Démos et courtoisies | B18: Ex-Démos et courtoisies | C18: 39 | D18: 1534.7521 | E18: 59855.334 | F18: 3 | G18: 1534.7521 | H18: 4604.2564 | I18: 3 | J18: 1534.7521 | K18: 4604.2564 | L18: 3 | M18: 1534.7521 | N18: 4604.2564 | O18: 3 | P18: 1534.7521 | Q18: 4604.2564 | R18: 2 | S18: 1534.7521 | T18: 3069.5043 | U18: 4 | V18: 1534.7521 | W18: 6139.0086 | X18: 4 | Y18: 1534.7521 | Z18: 6139.0086 | AA18: 4 | AB18: 1534.7521 | AC18: 6139.0086 | AD18: 3 | AE18: 1534.7521 | AF18: 4604.2564 | AG18: 3 | AH18: 1534.7521 | AI18: 4604.2564 | AJ18: 4 | AK18: 1534.7521 | AL18: 6139.0086 | AM18: 3 | AN18: 1534.7521 | AO18: 4604.2564
A19: =+$C$4&B19 -> Véhicules neufs
A20: =+$C$4&B20 -> Véhicules neufsFlottes | B20: Flottes | C20: 20 | D20: 2393.8521 | E20: 47877.042 | F20: 1 | G20: 2393.8521 | H20: 2393.8521 | I20: 1 | J20: 2393.8521 | K20: 2393.8521 | L20: 1 | M20: 2393.8521 | N20: 2393.8521 | O20: 2 | P20: 2393.8521 | Q20: 4787.7042 | R20: 2 | S20: 2393.8521 | T20: 4787.7042 | U20: 2 | V20: 2393.8521 | W20: 4787.7042 | X20: 2 | Y20: 2393.8521 | Z20: 4787.7042 | AA20: 2 | AB20: 2393.8521 | AC20: 4787.7042 | AD20: 2 | AE20: 2393.8521 | AF20: 4787.7042 | AG20: 2 | AH20: 2393.8521 | AI20: 4787.7042 | AJ20: 2 | AK20: 2393.8521 | AL20: 4787.7042 | AM20: 1 | AN20: 2393.8521 | AO20: 2393.8521
A21: =+$C$4&B21 -> Véhicules neufs
A22: =+$C$4&B22 -> Véhicules neufsRachat bail | B22: Rachat bail | E22: 85000 | H22: 5525 | K22: 5780 | N22: 6375 | Q22: 6375 | T22: 6545 | W22: 7650 | Z22: 7650 | AC22: 9350 | AF22: 6800 | AI22: 7650 | AL22: 9350 | AO22: 5950
A23: =+$C$4&B23 -> Véhicules neufs
A24: =+$C$4&B24 -> Véhicules neufsRev. Finances | B24: Rev. Finances | D24: 50 | E24: 40000 | G24: 50 | H24: 3000 | J24: 50 | K24: 2750 | M24: 50 | N24: 2600 | P24: 50 | Q24: 3000 | S24: 50 | T24: 3050 | V24: 50 | W24: 3650 | Y24: 50 | Z24: 3650 | AB24: 50 | AC24: 4400 | AE24: 50 | AF24: 3150 | AH24: 50 | AI24: 3600 | AK24: 50 | AL24: 4350 | AN24: 50 | AO24: 2800
A25: =+$C$4&B25 -> Véhicules neufsRev. Protections | B25: Rev. Protections | D25: 930 | E25: 744000 | G25: 930 | H25: 55800 | J25: 930 | K25: 51150 | M25: 930 | N25: 48360 | P25: 930 | Q25: 55800 | S25: 930 | T25: 56730 | V25: 930 | W25: 67890 | Y25: 930 | Z25: 67890 | AB25: 930 | AC25: 81840 | AE25: 930 | AF25: 58590 | AH25: 930 | AI25: 66960 | AK25: 930 | AL25: 80910 | AN25: 930 | AO25: 52080
A26: =+$C$4&B26 -> Véhicules neufsRev. Autres | B26: Rev. Autres | D26: 20 | E26: 16000 | G26: 20 | H26: 1200 | J26: 20 | K26: 1100 | M26: 20 | N26: 1040 | P26: 20 | Q26: 1200 | S26: 20 | T26: 1220 | V26: 20 | W26: 1460 | Y26: 20 | Z26: 1460 | AB26: 20 | AC26: 1760 | AE26: 20 | AF26: 1260 | AH26: 20 | AI26: 1440 | AK26: 20 | AL26: 1740 | AN26: 20 | AO26: 1120
A27: =+$C$4&B27 -> Véhicules neufsTotal F&I | B27: Total F&I | C27: 800 | D27: 1000 | E27: 800000 | F27: 60 | G27: 1000 | H27: 60000 | I27: 55 | J27: 1000 | K27: 55000 | L27: 52 | M27: 1000 | N27: 52000 | O27: 60 | P27: 1000 | Q27: 60000 | R27: 61 | S27: 1000 | T27: 61000 | U27: 73 | V27: 1000 | W27: 73000 | X27: 73 | Y27: 1000 | Z27: 73000 | AA27: 88 | AB27: 1000 | AC27: 88000 | AD27: 63 | AE27: 1000 | AF27: 63000 | AG27: 72 | AH27: 1000 | AI27: 72000 | AJ27: 87 | AK27: 1000 | AL27: 87000 | AM27: 56 | AN27: 1000 | AO27: 56000
A28: =+$C$4&B28 -> Véhicules neufs
A29: =+$C$4&B29 -> Véhicules neufs
A30: =+$C$4&B30 -> Véhicules neufsTotal Dépt. Neufs | B30: Total Dépt. Neufs | C30: 820 | D30: 3350.1356 | E30: 2747111.2 | F30: 61 | G30: 3346.4892 | H30: 204135.84 | I30: 56 | J30: 3351.671 | K30: 187693.57 | L30: 53 | M30: 3367.2286 | N30: 178463.12 | O30: 62 | P30: 3344.8338 | Q30: 207379.69 | R30: 63 | S30: 3355.6269 | T30: 211404.5 | U30: 75 | V30: 3339.8837 | W30: 250491.28 | X30: 75 | Y30: 3339.8837 | Z30: 250491.28 | AA30: 90 | AB30: 3353.3425 | AC30: 301800.83 | AD30: 65 | AE30: 3348.1562 | AF30: 217630.15 | AG30: 74 | AH30: 3350.7639 | AI30: 247956.53 | AJ30: 89 | AK30: 3352.4149 | AL30: 298364.92 | AM30: 57 | AN30: 3356.1312 | AO30: 191299.48
A31: =+$C$4&B31 -> Véhicules neufs
A32: =+$C$4&B32 -> Véhicules neufs
A33: =+$C$4&B33 -> Véhicules neufsDEPENSES | B33: DEPENSES
A34: =+$C$4&B34 -> Véhicules neufsComm. vendeurs | B34: Comm. vendeurs | C34: 0.33 | D34: 748.37159 | E34: 598697.27 | F34: 0.33900479 | G34: 769.63686 | H34: 46178.212 | I34: 0.33358069 | J34: 755.22499 | K34: 41537.375 | L34: 0.33665933 | M34: 761.97832 | N34: 39622.872 | O34: 0.33304494 | P34: 756.10632 | Q34: 45366.379 | R34: 0.34122338 | S34: 777.94339 | T34: 47454.547 | U34: 0.32512204 | V34: 735.1035 | W34: 53662.555 | X34: 0.32512204 | Y34: 735.1035 | Z34: 53662.555 | AA34: 0.32397102 | AB34: 735.05757 | AC34: 64685.066 | AD34: 0.33053742 | AE34: 750.49018 | AF34: 47280.881 | AG34: 0.33313833 | AH34: 756.58872 | AI34: 54474.388 | AJ34: 0.31738468 | AK34: 719.50459 | AL34: 62596.899 | AM34: 0.33220695 | AN34: 753.13468 | AO34: 42175.542
A35: =+$C$4&B35 -> Véhicules neufsComm. F&I | B35: Comm. F&I | C35: 0.28 | D35: 280 | E35: 224000 | F35: 0.28 | G35: 280 | H35: 16800 | I35: 0.28 | J35: 280 | K35: 15400 | L35: 0.28 | M35: 280 | N35: 14560 | O35: 0.28 | P35: 280 | Q35: 16800 | R35: 0.28 | S35: 280 | T35: 17080 | U35: 0.28 | V35: 280 | W35: 20440 | X35: 0.28 | Y35: 280 | Z35: 20440 | AA35: 0.28 | AB35: 280 | AC35: 24640 | AD35: 0.28 | AE35: 280 | AF35: 17640 | AG35: 0.28 | AH35: 280 | AI35: 20160 | AJ35: 0.28 | AK35: 280 | AL35: 24360 | AM35: 0.28 | AN35: 280 | AO35: 15680
A36: =+$C$4&B36 -> Véhicules neufsFrais de livraison | B36: Frais de livraison | D36: 115 | E36: 92000 | G36: 115 | H36: 6900 | J36: 115 | K36: 6325 | M36: 115 | N36: 5980 | P36: 115 | Q36: 6900 | S36: 115 | T36: 7015 | V36: 115 | W36: 8395 | Y36: 115 | Z36: 8395 | AB36: 115 | AC36: 10120 | AE36: 115 | AF36: 7245 | AH36: 115 | AI36: 8280 | AK36: 115 | AL36: 10005 | AN36: 115 | AO36: 6440
A37: =+$C$4&B37 -> Véhicules neufsService gratuit 1 | B37: Service gratuit 1 | D37: 10 | E37: 8000 | G37: 10 | H37: 600 | J37: 10 | K37: 550 | M37: 10 | N37: 520 | P37: 10 | Q37: 600 | S37: 10 | T37: 610 | V37: 10 | W37: 730 | Y37: 10 | Z37: 730 | AB37: 10 | AC37: 880 | AE37: 10 | AF37: 630 | AH37: 10 | AI37: 720 | AK37: 10 | AL37: 870 | AN37: 10 | AO37: 560
A38: =+$C$4&B38 -> Véhicules neufsEntretien stock | B38: Entretien stock | D38: 120.75 | E38: 96600 | G38: 120.75 | H38: 7245 | J38: 120.75 | K38: 6641.25 | M38: 120.75 | N38: 6279 | P38: 120.75 | Q38: 7245 | S38: 120.75 | T38: 7365.75 | V38: 120.75 | W38: 8814.75 | Y38: 120.75 | Z38: 8814.75 | AB38: 120.75 | AC38: 10626 | AE38: 120.75 | AF38: 7607.25 | AH38: 120.75 | AI38: 8694 | AK38: 120.75 | AL38: 10505.25 | AN38: 120.75 | AO38: 6762
A39: =+$C$4&B39 -> Véhicules neufsPublicité 1 | B39: Publicité 1 | D39: 101.93 | E39: 81544 | G39: 91.033333 | H39: 5462 | J39: 108.4 | K39: 5962 | M39: 351.19231 | N39: 18262 | P39: 91.033333 | Q39: 5462 | S39: 87.901639 | T39: 5362 | V39: 57.013699 | W39: 4162 | Y39: 57.013699 | Z39: 4162 | AB39: 30.25 | AC39: 2662 | AE39: 81.936508 | AF39: 5162 | AH39: 225.86111 | AI39: 16262 | AK39: 31.747126 | AL39: 2762 | AN39: 104.67857 | AO39: 5862
A40: =+$C$4&B40 -> Véhicules neufsIntérêt de gros | B40: Intérêt de gros | D40: 554.295 | E40: 443436 | G40: 580.19552 | H40: 34811.731 | J40: 623.20302 | K40: 34276.166 | M40: 690.05503 | N40: 35882.862 | P40: 601.02305 | Q40: 36061.383 | S40: 626.28924 | T40: 38203.644 | V40: 523.33758 | W40: 38203.644 | Y40: 560.02013 | Z40: 40881.469 | AB40: 413.84576 | AC40: 36418.427 | AE40: 603.57336 | AF40: 38025.122 | AH40: 565.31871 | AI40: 40702.947 | AK40: 402.18682 | AL40: 34990.253 | AN40: 624.61342 | AO40: 34978.352
A41: =+$C$4&B41 -> Véhicules neufs[...] | B41: [...] | D41: 0 | E41: 0 | G41: 0 | J41: 0 | M41: 0 | P41: 0 | S41: 0 | V41: 0 | Y41: 0 | AB41: 0 | AE41: 0 | AH41: 0 | AK41: 0 | AN41: 0
A42: =+$C$4&B42 -> Véhicules neufs[...] | B42: [...] | D42: 0 | E42: 0 | G42: 0 | J42: 0 | M42: 0 | P42: 0 | S42: 0 | V42: 0 | Y42: 0 | AB42: 0 | AE42: 0 | AH42: 0 | AK42: 0 | AN42: 0
A43: =+$C$4&B43 -> Véhicules neufs[...] | B43: [...] | D43: 0 | E43: 0 | G43: 0 | J43: 0 | M43: 0 | P43: 0 | S43: 0 | V43: 0 | Y43: 0 | AB43: 0 | AE43: 0 | AH43: 0 | AK43: 0 | AN43: 0
A44: =+$C$4&B44 -> Véhicules neufsTOTAL VARIABLES | B44: TOTAL VARIABLES | C44: % brut | D44: 0.56214589 | E44: 1544277.3 | F44: % brut | G44: 0.57803148 | H44: 117996.94 | I44: % brut | J44: 0.58974736 | K44: 110691.79 | L44: % brut | M44: 0.67860932 | N44: 121106.73 | O44: % brut | P44: 0.57110106 | Q44: 118434.76 | R44: % brut | S44: 0.58225318 | T44: 123090.94 | U44: % brut | V44: 0.53657736 | W44: 134407.95 | X44: % brut | Y44: 0.54726765 | Z44: 137085.77 | AA44: % brut | AB44: 0.49712088 | AC44: 150031.49 | AD44: % brut | AE44: 0.56789122 | AF44: 123590.25 | AG44: % brut | AH44: 0.6020948 | AI44: 149293.34 | AJ44: % brut | AK44: 0.4896333 | AL44: 146089.4 | AM44: % brut | AN44: 0.58786304 | AO44: 112457.89
A45: =+$C$4&B45 -> Véhicules neufsSalaires cadres | B45: Salaires cadres | E45: 309574.05 | H45: 28420.582 | K45: 24486.465 | N45: 24486.465 | Q45: 24486.465 | T45: 28420.582 | W45: 24486.465 | Z45: 24486.465 | AC45: 28420.582 | AF45: 24486.465 | AI45: 28420.582 | AL45: 24486.465 | AO45: 24486.465
A46: =+$C$4&B46 -> Véhicules neufsSalaires commis | B46: Salaires commis | E46: 179904.85 | H46: 17167.774 | K46: 13904.219 | N46: 13904.219 | Q46: 13904.219 | T46: 17167.774 | W46: 13904.219 | Z46: 13904.219 | AC46: 17167.774 | AF46: 13904.219 | AI46: 17167.774 | AL46: 13904.219 | AO46: 13904.219
A47: =+$C$4&B47 -> Véhicules neufsSalaires autres | B47: Salaires autres | E47: 4102.2 | H47: 394.44231 | K47: 315.55385 | N47: 315.55385 | Q47: 315.55385 | T47: 394.44231 | W47: 315.55385 | Z47: 315.55385 | AC47: 394.44231 | AF47: 315.55385 | AI47: 394.44231 | AL47: 315.55385 | AO47: 315.55385
A48: =+$C$4&B48 -> Véhicules neufsSalaires spécialistes | B48: Salaires spécialistes | E48: 0 | H48: 0 | K48: 0 | N48: 0 | Q48: 0 | T48: 0 | W48: 0 | Z48: 0 | AC48: 0 | AF48: 0 | AI48: 0 | AL48: 0 | AO48: 0
A49: =+$C$4&B49 -> Véhicules neufs[...] | B49: [...] | E49: 0 | H49: 0 | K49: 0 | N49: 0 | Q49: 0 | T49: 0 | W49: 0 | Z49: 0 | AC49: 0 | AF49: 0 | AI49: 0 | AL49: 0 | AO49: 0
A50: =+$C$4&B50 -> Véhicules neufs[...] | B50: [...] | E50: 0 | H50: 0 | K50: 0 | N50: 0 | Q50: 0 | T50: 0 | W50: 0 | Z50: 0 | AC50: 0 | AF50: 0 | AI50: 0 | AL50: 0 | AO50: 0
A51: =+$C$4&B51 -> Véhicules neufs[...] | B51: [...] | E51: 0 | H51: 0 | K51: 0 | N51: 0 | Q51: 0 | T51: 0 | W51: 0 | Z51: 0 | AC51: 0 | AF51: 0 | AI51: 0 | AL51: 0 | AO51: 0
A52: =+$C$4&B52 -> Véhicules neufsSalaires en absences | B52: Salaires en absences | E52: 148529.81 | H52: 12062.772 | K52: 9735.8915 | N52: 12663.726 | Q52: 13219.128 | T52: 14936.127 | W52: 11620.017 | Z52: 11796.071 | AC52: 13032.075 | AF52: 12229.899 | AI52: 14095.712 | AL52: 13449.662 | AO52: 9688.7245
A53: =+$C$4&B53 -> Véhicules neufsDéduction à la source | B53: Déduction à la source | E53: 180591.3 | H53: 14666.631 | K53: 11837.472 | N53: 15397.306 | Q53: 16072.596 | T53: 18160.225 | W53: 14128.302 | Z53: 14342.359 | AC53: 15845.166 | AF53: 14869.833 | AI53: 17138.398 | AL53: 16352.893 | AO53: 11780.123
A54: =+$C$4&B54 -> Véhicules neufsBénéfices marginaux | B54: Bénéfices marginaux | E54: 93043.781 | H54: 7556.5033 | K54: 6098.8712 | N54: 7932.9599 | Q54: 8280.8811 | T54: 9356.4639 | W54: 7279.1471 | Z54: 7389.4328 | AC54: 8163.7052 | AF54: 7661.1963 | AI54: 8830.0009 | AL54: 8425.2949 | AO54: 6069.3244
A55: =+$C$4&B55 -> Véhicules neufsCsst | B55: Csst | E55: 40567.612 | H55: 3294.6779 | K55: 2659.1422 | N55: 3458.8151 | Q55: 3610.5108 | T55: 4079.4709 | W55: 3173.7491 | Z55: 3221.8343 | AC55: 3559.4214 | AF55: 3340.3247 | AI55: 3849.9301 | AL55: 3673.476 | AO55: 2646.2596
A56: =+$C$4&B56 -> Véhicules neufs[...] | B56: [...] | E56: 0
A57: =+$C$4&B57 -> Véhicules neufsTOTAL PERSONNEL | B57: TOTAL PERSONNEL | C57: % brut | D57: 0.34811609 | E57: 956313.6 | F57: % brut | G57: 0.40935184 | H57: 83563.382 | I57: % brut | J57: 0.36782087 | K57: 69037.615 | L57: % brut | M57: 0.4379563 | N57: 78159.046 | O57: % brut | P57: 0.38523229 | Q57: 79889.355 | R57: % brut | S57: 0.43762118 | T57: 92515.085 | U57: % brut | V57: 0.29904216 | W57: 74907.453 | X57: % brut | Y57: 0.30123178 | Z57: 75455.935 | AA57: % brut | AB57: 0.28688843 | AC57: 86583.166 | AD57: % brut | AE57: 0.35292669 | AF57: 76807.49 | AG57: % brut | AH57: 0.3625508 | AI57: 89896.839 | AJ57: % brut | AK57: 0.27016434 | AL57: 80607.564 | AM57: % brut | AN57: 0.36011948 | AO57: 68890.67
A58: =+$C$4&B58 -> Véhicules neufsPublicité 2 | B58: Publicité 2 | E58: 0 | H58: 0 | K58: 0 | N58: 0 | Q58: 0 | T58: 0 | W58: 0 | Z58: 0 | AC58: 0 | AF58: 0 | AI58: 0 | AL58: 0 | AO58: 0
A59: =+$C$4&B59 -> Véhicules neufsService gratuit 2 | B59: Service gratuit 2 | E59: 0 | H59: 0 | K59: 0 | N59: 0 | Q59: 0 | T59: 0 | W59: 0 | Z59: 0 | AC59: 0 | AF59: 0 | AI59: 0 | AL59: 0 | AO59: 0
A60: =+$C$4&B60 -> Véhicules neufsFrais véhicules de cie | B60: Frais véhicules de cie | E60: 107430.58 | H60: 8952.5479 | K60: 8952.5479 | N60: 8952.5479 | Q60: 8952.5479 | T60: 8952.5479 | W60: 8952.5479 | Z60: 8952.5479 | AC60: 8952.5479 | AF60: 8952.5479 | AI60: 8952.5479 | AL60: 8952.5479 | AO60: 8952.5479
A61: =+$C$4&B61 -> Véhicules neufsInformatique | B61: Informatique | E61: 95531.937 | H61: 7960.9948 | K61: 7960.9948 | N61: 7960.9948 | Q61: 7960.9948 | T61: 7960.9948 | W61: 7960.9948 | Z61: 7960.9948 | AC61: 7960.9948 | AF61: 7960.9948 | AI61: 7960.9948 | AL61: 7960.9948 | AO61: 7960.9948
A62: =+$C$4&B62 -> Véhicules neufsFrais de déplacement | B62: Frais de déplacement | E62: 15200.37 | H62: 1266.6975 | K62: 1266.6975 | N62: 1266.6975 | Q62: 1266.6975 | T62: 1266.6975 | W62: 1266.6975 | Z62: 1266.6975 | AC62: 1266.6975 | AF62: 1266.6975 | AI62: 1266.6975 | AL62: 1266.6975 | AO62: 1266.6975
A63: =+$C$4&B63 -> Véhicules neufsServices extérieurs | B63: Services extérieurs | E63: 86588.889 | H63: 7215.7407 | K63: 7215.7407 | N63: 7215.7407 | Q63: 7215.7407 | T63: 7215.7407 | W63: 7215.7407 | Z63: 7215.7407 | AC63: 7215.7407 | AF63: 7215.7407 | AI63: 7215.7407 | AL63: 7215.7407 | AO63: 7215.7407
A64: =+$C$4&B64 -> Véhicules neufsFournitures autres | B64: Fournitures autres | E64: 1167.088 | H64: 97.257333 | K64: 97.257333 | N64: 97.257333 | Q64: 97.257333 | T64: 97.257333 | W64: 97.257333 | Z64: 97.257333 | AC64: 97.257333 | AF64: 97.257333 | AI64: 97.257333 | AL64: 97.257333 | AO64: 97.257333
A65: =+$C$4&B65 -> Véhicules neufsUniformes | B65: Uniformes | E65: 340 | H65: 28.333333 | K65: 28.333333 | N65: 28.333333 | Q65: 28.333333 | T65: 28.333333 | W65: 28.333333 | Z65: 28.333333 | AC65: 28.333333 | AF65: 28.333333 | AI65: 28.333333 | AL65: 28.333333 | AO65: 28.333333
A66: =+$C$4&B66 -> Véhicules neufsPapeterie | B66: Papeterie | E66: 8897.1707 | H66: 741.43089 | K66: 741.43089 | N66: 741.43089 | Q66: 741.43089 | T66: 741.43089 | W66: 741.43089 | Z66: 741.43089 | AC66: 741.43089 | AF66: 741.43089 | AI66: 741.43089 | AL66: 741.43089 | AO66: 741.43089
A67: =+$C$4&B67 -> Véhicules neufsTéléphone | B67: Téléphone | E67: 4137.6238 | H67: 344.80198 | K67: 344.80198 | N67: 344.80198 | Q67: 344.80198 | T67: 344.80198 | W67: 344.80198 | Z67: 344.80198 | AC67: 344.80198 | AF67: 344.80198 | AI67: 344.80198 | AL67: 344.80198 | AO67: 344.80198
A68: =+$C$4&B68 -> Véhicules neufsFrais postaux | B68: Frais postaux | E68: 1233.8687 | H68: 102.8224 | K68: 102.8224 | N68: 102.8224 | Q68: 102.8224 | T68: 102.8224 | W68: 102.8224 | Z68: 102.8224 | AC68: 102.8224 | AF68: 102.8224 | AI68: 102.8224 | AL68: 102.8224 | AO68: 102.8224
A69: =+$C$4&B69 -> Véhicules neufsDivers | B69: Divers | E69: 2414.0446 | H69: 201.17039 | K69: 201.17039 | N69: 201.17039 | Q69: 201.17039 | T69: 201.17039 | W69: 201.17039 | Z69: 201.17039 | AC69: 201.17039 | AF69: 201.17039 | AI69: 201.17039 | AL69: 201.17039 | AO69: 201.17039
... A71: =+$C$4&B71 -> Véhicules neufsFrais bancaires | B71: Frais bancaires | E71: 42711.178 | H71: 2786.7514 | K71: 2686.9399 | N71: 2842.795 | Q71: 3725.0158 | T71: 3960.0994 | W71: 3689.0506 | Z71: 3605.8794 | AC71: 3899.9395 | AF71: 3172.2328 | AI71: 4283.1051 | AL71: 5035.3183 | AO71: 3024.0505
A72: =+$C$4&B72 -> Véhicules neufs[...] | B72: [...] | E72: 0
A73: =+$C$4&B73 -> Véhicules neufs[...] | B73: [...] | E73: 0
A74: =+$C$4&B74 -> Véhicules neufs[...] | B74: [...] | E74: 0
A75: =+$C$4&B75 -> Véhicules neufsTOTAL SEMI-FIXES | B75: TOTAL SEMI-FIXES | C75: % brut | D75: 0.14155569 | E75: 388869.22 | F75: % brut | G75: 0.15496179 | H75: 31633.255 | I75: % brut | J75: 0.16800492 | K75: 31533.443 | L75: % brut | M75: 0.17756778 | N75: 31689.299 | O75: % brut | P75: 0.15706224 | Q75: 32571.519 | R75: % brut | S75: 0.15518404 | T75: 32806.603 | U75: % brut | V75: 0.12988697 | W75: 32535.554 | X75: % brut | Y75: 0.12955494 | Z75: 32452.383 | AA75: % brut | AB75: 0.10850349 | AC75: 32746.443 | AD75: % brut | AE75: 0.14712454 | AF75: 32018.736 | AG75: % brut | AH75: 0.13361055 | AI75: 33129.609 | AJ75: % brut | AK75: 0.11355833 | AL75: 33881.822 | AM75: % brut | AN75: 0.16660032 | AO75: 31870.554
A76: =+$C$4&B76 -> Véhicules neufs
A77: =+$C$4&B77 -> Véhicules neufsTOTAL DES DÉPENSES | B77: TOTAL DES DÉPENSES | C77: % brut | D77: 1.0518177 | E77: 2889460.1 | F77: % brut | G77: 1.1423451 | H77: 233193.58 | I77: % brut | J77: 1.1255732 | K77: 211262.85 | L77: % brut | M77: 1.2941334 | N77: 230955.08 | O77: % brut | P77: 1.1133956 | Q77: 230895.64 | R77: % brut | S77: 1.1750584 | T77: 248412.63 | U77: % brut | V77: 0.96550649 | W77: 241850.96 | X77: % brut | Y77: 0.97805437 | Z77: 244994.09 | AA77: % brut | AB77: 0.8925128 | AC77: 269361.1 | AD77: % brut | AE77: 1.0679425 | AF77: 232416.48 | AG77: % brut | AH77: 1.0982562 | AI77: 272319.78 | AJ77: % brut | AK77: 0.87335597 | AL77: 260578.79 | AM77: % brut | AN77: 1.1145828 | AO77: 213219.12
A78: =+$C$4&B78 -> Véhicules neufsProgramme neuf 1 | B78: Programme neuf 1 | E78: 100000 | H78: 0 | K78: 0 | N78: 25000 | Q78: 0 | T78: 0 | W78: 25000 | Z78: 0 | AC78: 0 | AF78: 25000 | AI78: 0 | AL78: 0 | AO78: 25000
A79: =+$C$4&B79 -> Véhicules neufsProgramme neuf 2 | B79: Programme neuf 2 | E79: 0 | H79: 0 | K79: 0 | N79: 0 | Q79: 0 | T79: 0 | W79: 0 | Z79: 0 | AC79: 0 | AF79: 0 | AI79: 0 | AL79: 0 | AO79: 0
A80: =+$C$4&B80 -> Véhicules neufsProgramme neuf 3 | B80: Programme neuf 3 | E80: 0 | H80: 0 | K80: 0 | N80: 0 | Q80: 0 | T80: 0 | W80: 0 | Z80: 0 | AC80: 0 | AF80: 0 | AI80: 0 | AL80: 0 | AO80: 0
A81: =+$C$4&B81 -> Véhicules neufsHoldbacks | B81: Holdbacks | E81: 1145900.2 | H81: 84434.755 | K81: 76895.938 | N81: 72372.647 | Q81: 85942.518 | T81: 87450.282 | W81: 105543.44 | Z81: 105543.44 | AC81: 128159.9 | AF81: 90465.809 | AI81: 104035.68 | AL81: 126652.13 | AO81: 78403.701
A82: =+$C$4&B82 -> Véhicules neufs[...] | B82: [...] | E82: 0 | H82: 0 | K82: 0 | N82: 0 | Q82: 0 | T82: 0 | W82: 0 | Z82: 0 | AC82: 0 | AF82: 0 | AI82: 0 | AL82: 0 | AO82: 0
A83: =+$C$4&B83 -> Véhicules neufs[...] | B83: [...] | E83: 0 | H83: 0 | K83: 0 | N83: 0 | Q83: 0 | T83: 0 | W83: 0 | Z83: 0 | AC83: 0 | AF83: 0 | AI83: 0 | AL83: 0 | AO83: 0
A84: =+$C$4&B84 -> Véhicules neufs[...] | B84: [...] | E84: 0 | H84: 0 | K84: 0 | N84: 0 | Q84: 0 | T84: 0 | W84: 0 | Z84: 0 | AC84: 0 | AF84: 0 | AI84: 0 | AL84: 0 | AO84: 0
A85: =+$C$4&B85 -> Véhicules neufsFrais administration | B85: Frais administration | E85: 379240 | H85: 28443 | K85: 26072.75 | N85: 24650.6 | Q85: 28443 | T85: 28917.05 | W85: 34605.65 | Z85: 34605.65 | AC85: 41716.4 | AF85: 29865.15 | AI85: 34131.6 | AL85: 41242.35 | AO85: 26546.8
A86: =+$C$4&B86 -> Véhicules neufsAUTRES REVENUS | B86: AUTRES REVENUS | E86: 1625140.2 | H86: 112877.75 | K86: 102968.69 | N86: 122023.25 | Q86: 114385.52 | T86: 116367.33 | W86: 165149.09 | Z86: 140149.09 | AC86: 169876.3 | AF86: 145330.96 | AI86: 138167.28 | AL86: 167894.48 | AO86: 129950.5
A87: =+$C$4&B87 -> Véhicules neufs
A88: =+$C$4&B88 -> Véhicules neufsPROFIT DÉPARTEMENTAL | B88: PROFIT DÉPARTEMENTAL | E88: 1482791.4 | H88: 83820.017 | K88: 79399.413 | N88: 69531.285 | Q88: 90869.577 | T88: 79359.2 | W88: 173789.42 | Z88: 145646.28 | AC88: 202316.02 | AF88: 130544.63 | AI88: 113804.03 | AL88: 205680.62 | AO88: 108030.86
B92: Budget 2025 Mensuel VOLKS | C92: Véhicules usagés
B94: Mois | C94: 2025 | F94: Janvier | I94: Février | L94: Mars | O94: Avril | R94: Mai | U94: Juin | X94: Juillet | AA94: Août | AD94: Septembre | AG94: Octobre | AJ94: Novembre | AM94: Décembre
C95: UNITE | D95: $P/UNITE | E95: $PROFITS | F95: UNITE | G95: $P/UNITE | H95: $PROFITS | I95: UNITE | J95: $P/UNITE | K95: $PROFITS | L95: UNITE | M95: $P/UNITE | N95: $PROFITS | O95: UNITE | P95: $P/UNITE | Q95: $PROFITS | R95: UNITE | S95: $P/UNITE | T95: $PROFITS | U95: UNITE | V95: $P/UNITE | W95: $PROFITS | X95: UNITE | Y95: $P/UNITE | Z95: $PROFITS | AA95: UNITE | AB95: $P/UNITE | AC95: $PROFITS | AD95: UNITE | AE95: $P/UNITE | AF95: $PROFITS | AG95: UNITE | AH95: $P/UNITE | AI95: $PROFITS | AJ95: UNITE | AK95: $P/UNITE | AL95: $PROFITS | AM95: UNITE | AN95: $P/UNITE | AO95: $PROFITS
A96: =+$C$92&B96 -> Véhicules usagésVentes nettes | B96: Ventes nettes | E96: 18869045 | H96: 1038928 | K96: 1318990.2 | N96: 1322790.2 | Q96: 1417410.9 | T96: 2037727.7 | W96: 1743301.4 | Z96: 1699373.1 | AC96: 1510131.6 | AF96: 1226269.4 | AI96: 2168676.7 | AL96: 1792093.8 | AO96: 1593352.4
A97: =+$C$92&B97 -> Véhicules usagésCertifié | B97: Certifié | C97: 287 | D97: 1400 | E97: 401800 | F97: 16 | G97: 1400 | H97: 22400 | I97: 20 | J97: 1400 | K97: 28000 | L97: 20 | M97: 1400 | N97: 28000 | O97: 22 | P97: 1400 | Q97: 30800 | R97: 31 | S97: 1400 | T97: 43400 | U97: 30 | V97: 1400 | W97: 42000 | X97: 26 | Y97: 1400 | Z97: 36400 | AA97: 23 | AB97: 1400 | AC97: 32200 | AD97: 19 | AE97: 1400 | AF97: 26600 | AG97: 33 | AH97: 1400 | AI97: 46200 | AJ97: 27 | AK97: 1400 | AL97: 37800 | AM97: 20 | AN97: 1400 | AO97: 28000
A98: =+$C$92&B98 -> Véhicules usagésNon Certifié | B98: Non Certifié | C98: 34 | D98: 1800 | E98: 61200 | F98: 2 | G98: 1800 | H98: 3600 | I98: 2 | J98: 1800 | K98: 3600 | L98: 2 | M98: 1800 | N98: 3600 | O98: 3 | P98: 1800 | Q98: 5400 | R98: 4 | S98: 1800 | T98: 7200 | U98: 3 | V98: 1800 | W98: 5400 | X98: 3 | Y98: 1800 | Z98: 5400 | AA98: 3 | AB98: 1800 | AC98: 5400 | AD98: 2 | AE98: 1800 | AF98: 3600 | AG98: 4 | AH98: 1800 | AI98: 7200 | AJ98: 3 | AK98: 1800 | AL98: 5400 | AM98: 3 | AN98: 1800 | AO98: 5400
A99: =+$C$92&B99 -> Véhicules usagésAutres Marques | B99: Autres Marques | C99: 50 | D99: 1500 | E99: 75000 | F99: 3 | G99: 1500 | H99: 4500 | I99: 3 | J99: 1500 | K99: 4500 | L99: 5 | M99: 1500 | N99: 7500 | O99: 4 | P99: 1500 | Q99: 6000 | R99: 5 | S99: 1500 | T99: 7500 | U99: 5 | V99: 1500 | W99: 7500 | X99: 5 | Y99: 1500 | Z99: 7500 | AA99: 4 | AB99: 1500 | AC99: 6000 | AD99: 3 | AE99: 1500 | AF99: 4500 | AG99: 5 | AH99: 1500 | AI99: 7500 | AJ99: 5 | AK99: 1500 | AL99: 7500 | AM99: 3 | AN99: 1500 | AO99: 4500
A100: =+$C$92&B100 -> Véhicules usagésTotal Usagés | B100: Total Usagés | C100: 371 | D100: 1450.1348 | E100: 538000 | F100: 21 | G100: 1452.381 | H100: 30500 | I100: 25 | J100: 1444 | K100: 36100 | L100: 27 | M100: 1448.1481 | N100: 39100 | O100: 29 | P100: 1455.1724 | Q100: 42200 | R100: 40 | S100: 1452.5 | T100: 58100 | U100: 38 | V100: 1444.7368 | W100: 54900 | X100: 34 | Y100: 1450 | Z100: 49300 | AA100: 30 | AB100: 1453.3333 | AC100: 43600 | AD100: 24 | AE100: 1445.8333 | AF100: 34700 | AG100: 42 | AH100: 1450 | AI100: 60900 | AJ100: 35 | AK100: 1448.5714 | AL100: 50700 | AM100: 26 | AN100: 1457.6923 | AO100: 37900
A101: =+$C$92&B101 -> Véhicules usagés
A102: =+$C$92&B102 -> Véhicules usagés | F102: 0 | H102: 0
A103: =+$C$92&B103 -> Véhicules usagésVentes au Gros | B103: Ventes au Gros | C103: 409 | D103: 400 | E103: 163600 | F103: 22 | G103: 400 | H103: 8800 | I103: 29 | J103: 400 | K103: 11600 | L103: 29 | M103: 400 | N103: 11600 | O103: 31 | P103: 400 | Q103: 12400 | R103: 44 | S103: 400 | T103: 17600 | U103: 38 | V103: 400 | W103: 15200 | X103: 37 | Y103: 400 | Z103: 14800 | AA103: 33 | AB103: 400 | AC103: 13200 | AD103: 27 | AE103: 400 | AF103: 10800 | AG103: 45 | AH103: 400 | AI103: 18000 | AJ103: 39 | AK103: 400 | AL103: 15600 | AM103: 35 | AN103: 400 | AO103: 14000
A104: =+$C$92&B104 -> Véhicules usagés
A105: =+$C$92&B105 -> Véhicules usagésRev. Finances | B105: Rev. Finances | D105: 600 | E105: 222600 | G105: 600 | H105: 12600 | J105: 600 | K105: 15000 | M105: 600 | N105: 16200 | P105: 600 | Q105: 17400 | S105: 600 | T105: 24000 | V105: 600 | W105: 22800 | Y105: 600 | Z105: 20400 | AB105: 600 | AC105: 18000 | AE105: 600 | AF105: 14400 | AH105: 600 | AI105: 25200 | AK105: 600 | AL105: 21000 | AN105: 600 | AO105: 15600
A106: =+$C$92&B106 -> Véhicules usagésRev. Protections | B106: Rev. Protections | D106: 1250 | E106: 463750 | G106: 1250 | H106: 26250 | J106: 1250 | K106: 31250 | M106: 1250 | N106: 33750 | P106: 1250 | Q106: 36250 | S106: 1250 | T106: 50000 | V106: 1250 | W106: 47500 | Y106: 1250 | Z106: 42500 | AB106: 1250 | AC106: 37500 | AE106: 1250 | AF106: 30000 | AH106: 1250 | AI106: 52500 | AK106: 1250 | AL106: 43750 | AN106: 1250 | AO106: 32500
...

Sheet Réel 2024
B1: ="Réel 2023 Mensuel Révisé"&" "&Parametres!$B$1 -> Réel 2023 Mensuel Révisé Volks
B2: Mois | F2: =+IF(Parametres!$B$3=F$6,"X","") | G2: =+IF(Parametres!$B$3=F$6,"O","") | H2: =+IF(Parametres!$B$3=F$6,"U","") | I2: =+IF(Parametres!$B$3=I$6,"X","") | J2: =+IF(Parametres!$B$3=I$6,"O","") | K2: =+IF(Parametres!$B$3=I$6,"U","") | L2: =+IF(Parametres!$B$3=L$6,"X","") | M2: =+IF(Parametres!$B$3=L$6,"O","") | N2: =+IF(Parametres!$B$3=L$6,"U","") | O2: =+IF(Parametres!$B$3=O$6,"X","") | P2: =+IF(Parametres!$B$3=O$6,"O","") | Q2: =+IF(Parametres!$B$3=O$6,"U","") | R2: =+IF(Parametres!$B$3=R$6,"X","") | S2: =+IF(Parametres!$B$3=R$6,"O","") | T2: =+IF(Parametres!$B$3=R$6,"U","") | U2: =+IF(Parametres!$B$3=U$6,"X","") | V2: =+IF(Parametres!$B$3=U$6,"O","") | W2: =+IF(Parametres!$B$3=U$6,"U","") | X2: =+IF(Parametres!$B$3=X$6,"X","") -> X | Y2: =+IF(Parametres!$B$3=X$6,"O","") -> O | Z2: =+IF(Parametres!$B$3=X$6,"U","") -> U | AA2: =+IF(Parametres!$B$3=AA$6,"X","") | AB2: =+IF(Parametres!$B$3=AA$6,"O","") | AC2: =+IF(Parametres!$B$3=AA$6,"U","") | AD2: =+IF(Parametres!$B$3=AD$6,"X","") | AE2: =+IF(Parametres!$B$3=AD$6,"O","") | AF2: =+IF(Parametres!$B$3=AD$6,"U","") | AG2: =+IF(Parametres!$B$3=AG$6,"X","") | AH2: =+IF(Parametres!$B$3=AG$6,"O","") | AI2: =+IF(Parametres!$B$3=AG$6,"U","") | AJ2: =+IF(Parametres!$B$3=AJ$6,"X","") | AK2: =+IF(Parametres!$B$3=AJ$6,"O","") | AL2: =+IF(Parametres!$B$3=AJ$6,"U","") | AM2: =+IF(Parametres!$B$3=AM$6,"X","") | AN2: =+IF(Parametres!$B$3=AM$6,"O","") | AO2: =+IF(Parametres!$B$3=AM$6,"U","")
B3: YTD | F3: =+IF(VLOOKUP(F$6,Parametres!$K$3:$N$14,4,0)="X","X","") -> X | G3: =+IF(VLOOKUP(F$6,Parametres!$K$3:$N$14,4,0)="X","O","") -> O | H3: =+IF(VLOOKUP(F$6,Parametres!$K$3:$N$14,4,0)="X","U","") -> U | I3: =+IF(VLOOKUP(I$6,Parametres!$K$3:$N$14,4,0)="X","X","") -> X | J3: =+IF(VLOOKUP(I$6,Parametres!$K$3:$N$14,4,0)="X","O","") -> O | K3: =+IF(VLOOKUP(I$6,Parametres!$K$3:$N$14,4,0)="X","U","") -> U | L3: =+IF(VLOOKUP(L$6,Parametres!$K$3:$N$14,4,0)="X","X","") -> X | M3: =+IF(VLOOKUP(L$6,Parametres!$K$3:$N$14,4,0)="X","O","") -> O | N3: =+IF(VLOOKUP(L$6,Parametres!$K$3:$N$14,4,0)="X","U","") -> U | O3: =+IF(VLOOKUP(O$6,Parametres!$K$3:$N$14,4,0)="X","X","") -> X | P3: =+IF(VLOOKUP(O$6,Parametres!$K$3:$N$14,4,0)="X","O","") -> O | Q3: =+IF(VLOOKUP(O$6,Parametres!$K$3:$N$14,4,0)="X","U","") -> U | R3: =+IF(VLOOKUP(R$6,Parametres!$K$3:$N$14,4,0)="X","X","") -> X | S3: =+IF(VLOOKUP(R$6,Parametres!$K$3:$N$14,4,0)="X","O","") -> O | T3: =+IF(VLOOKUP(R$6,Parametres!$K$3:$N$14,4,0)="X","U","") -> U | U3: =+IF(VLOOKUP(U$6,Parametres!$K$3:$N$14,4,0)="X","X","") -> X | V3: =+IF(VLOOKUP(U$6,Parametres!$K$3:$N$14,4,0)="X","O","") -> O | W3: =+IF(VLOOKUP(U$6,Parametres!$K$3:$N$14,4,0)="X","U","") -> U | X3: =+IF(VLOOKUP(X$6,Parametres!$K$3:$N$14,4,0)="X","X","") -> X | Y3: =+IF(VLOOKUP(X$6,Parametres!$K$3:$N$14,4,0)="X","O","") -> O | Z3: =+IF(VLOOKUP(X$6,Parametres!$K$3:$N$14,4,0)="X","U","") -> U | AA3: =+IF(VLOOKUP(AA$6,Parametres!$K$3:$N$14,4,0)="X","X","") | AB3: =+IF(VLOOKUP(AA$6,Parametres!$K$3:$N$14,4,0)="X","O","") | AC3: =+IF(VLOOKUP(AA$6,Parametres!$K$3:$N$14,4,0)="X","U","") | AD3: =+IF(VLOOKUP(AD$6,Parametres!$K$3:$N$14,4,0)="X","X","") | AE3: =+IF(VLOOKUP(AD$6,Parametres!$K$3:$N$14,4,0)="X","O","") | AF3: =+IF(VLOOKUP(AD$6,Parametres!$K$3:$N$14,4,0)="X","U","") | AG3: =+IF(VLOOKUP(AG$6,Parametres!$K$3:$N$14,4,0)="X","X","") | AH3: =+IF(VLOOKUP(AG$6,Parametres!$K$3:$N$14,4,0)="X","O","") | AI3: =+IF(VLOOKUP(AG$6,Parametres!$K$3:$N$14,4,0)="X","U","") | AJ3: =+IF(VLOOKUP(AJ$6,Parametres!$K$3:$N$14,4,0)="X","X","") | AK3: =+IF(VLOOKUP(AJ$6,Parametres!$K$3:$N$14,4,0)="X","O","") | AL3: =+IF(VLOOKUP(AJ$6,Parametres!$K$3:$N$14,4,0)="X","U","") | AM3: =+IF(VLOOKUP(AM$6,Parametres!$K$3:$N$14,4,0)="X","X","") | AN3: =+IF(VLOOKUP(AM$6,Parametres!$K$3:$N$14,4,0)="X","O","") | AO3: =+IF(VLOOKUP(AM$6,Parametres!$K$3:$N$14,4,0)="X","U","")
B4: Réel 2024 | C4: Véhicules neufs
B6: Mois | C6: 2024 | F6: Janvier | I6: Février | L6: Mars | O6: Avril | R6: Mai | U6: Juin | X6: Juillet | AA6: Août | AD6: Septembre | AG6: Octobre | AJ6: Novembre | AM6: Décembre
C7: UNITE | D7: $P/UNITE | E7: $PROFITS | F7: UNITE | G7: $P/UNITE | H7: $PROFITS | I7: UNITE | J7: $P/UNITE | K7: $PROFITS | L7: UNITE | M7: $P/UNITE | N7: $PROFITS | O7: UNITE | P7: $P/UNITE | Q7: $PROFITS | R7: UNITE | S7: $P/UNITE | T7: $PROFITS | U7: UNITE | V7: $P/UNITE | W7: $PROFITS | X7: UNITE | Y7: $P/UNITE | Z7: $PROFITS | AA7: UNITE | AB7: $P/UNITE | AC7: $PROFITS | AD7: UNITE | AE7: $P/UNITE | AF7: $PROFITS | AG7: UNITE | AH7: $P/UNITE | AI7: $PROFITS | AJ7: UNITE | AK7: $P/UNITE | AL7: $PROFITS | AM7: UNITE | AN7: $P/UNITE | AO7: $PROFITS
A8: =+$C$4&B8 -> Véhicules neufsVentes nettes | B8: Ventes nettes | E8: 38196011 | H8: 2179097.8 | K8: 3708952.5 | N8: 4089927.9 | Q8: 3890022.9 | T8: 3906259.8 | W8: 2093787.4 | Z8: 4524162.1 | AC8: 4621444.5 | AF8: 2442838.5 | AI8: 2470114 | AL8: 2101403.3 | AO8: 2168000.1
A9: =+$C$4&B9 -> Véhicules neufsAutos détail | B9: Autos détail | C9: 183 | D9: 1942.5738 | E9: 355491 | F9: 10 | G9: 1336.532 | H9: 13365.32 | I9: 24 | J9: 2210.4767 | K9: 53051.44 | L9: 14 | M9: 2832.1014 | N9: 39649.42 | O9: 18 | P9: 2168.0939 | Q9: 39025.69 | R9: 18 | S9: 1997.7756 | T9: 35959.96 | U9: 15 | V9: 1651.894 | W9: 24778.41 | X9: 23 | Y9: 1942.4757 | Z9: 44676.94 | AA9: 19 | AB9: 1667.12 | AC9: 31675.28 | AD9: 16 | AE9: 1640.0056 | AF9: 26240.09 | AG9: 12 | AH9: 1802.2583 | AI9: 21627.1 | AJ9: 8 | AK9: 2031.0612 | AL9: 16248.49 | AM9: 6 | AN9: 1532.1433 | AO9: 9192.86
A10: =+$C$4&B10 -> Véhicules neufsCamions détail | B10: Camions détail | C10: 489 | D10: 2368.9078 | E10: 1158395.9 | F10: 34 | G10: 2268.3159 | H10: 77122.74 | I10: 47 | J10: 2454.7581 | K10: 115373.63 | L10: 56 | M10: 2919.9218 | N10: 163515.62 | O10: 51 | P10: 2906.2869 | Q10: 148220.63 | R10: 51 | S10: 2441.8604 | T10: 124534.88 | U10: 25 | V10: 2415.8504 | W10: 60396.26 | X10: 54 | Y10: 2267.4683 | Z10: 122443.29 | AA10: 62 | AB10: 2284.2913 | AC10: 141626.06 | AD10: 26 | AE10: 2080.4762 | AF10: 54092.38 | AG10: 32 | AH10: 1508.5388 | AI10: 48273.24 | AJ10: 27 | AK10: 2114.5019 | AL10: 57091.55 | AM10: 24 | AN10: 1904.4017 | AO10: 45705.64
A11: =+$C$4&B11 -> Véhicules neufsSprinter | B11: Sprinter | C11: 0 | D11: 0 | E11: 0 | F11: 0 | G11: 0 | H11: 0 | I11: 0 | J11: 0 | K11: 0 | L11: 0 | M11: 0 | N11: 0 | O11: 0 | P11: 0 | Q11: 0 | R11: 0 | S11: 0 | T11: 0 | U11: 0 | V11: 0 | W11: 0 | X11: 0 | Y11: 0 | Z11: 0 | AA11: 0 | AB11: 0 | AC11: 0 | AD11: 0 | AE11: 0 | AF11: 0 | AG11: 0 | AH11: 0 | AI11: 0 | AJ11: 0 | AK11: 0 | AL11: 0 | AM11: 0 | AN11: 0 | AO11: 0
A12: =+$C$4&B12 -> Véhicules neufsMoto détail | B12: Moto détail | C12: 0 | D12: 0 | E12: 0 | F12: 0 | G12: 0 | H12: 0 | I12: 0 | J12: 0 | K12: 0 | L12: 0 | M12: 0 | N12: 0 | O12: 0 | P12: 0 | Q12: 0 | R12: 0 | S12: 0 | T12: 0 | U12: 0 | V12: 0 | W12: 0 | X12: 0 | Y12: 0 | Z12: 0 | AA12: 0 | AB12: 0 | AC12: 0 | AD12: 0 | AE12: 0 | AF12: 0 | AG12: 0 | AH12: 0 | AI12: 0 | AJ12: 0 | AK12: 0 | AL12: 0 | AM12: 0 | AN12: 0 | AO12: 0
A13: =+$C$4&B13 -> Véhicules neufs[...] | B13: [...] | C13: 0 | D13: 0 | E13: 0 | G13: 0 | J13: 0 | M13: 0 | P13: 0 | S13: 0 | V13: 0 | Y13: 0 | AB13: 0 | AE13: 0 | AH13: 0 | AK13: 0 | AN13: 0
A14: =+$C$4&B14 -> Véhicules neufs[...] | B14: [...] | C14: 0 | D14: 0 | E14: 0 | G14: 0 | J14: 0 | M14: 0 | P14: 0 | S14: 0 | V14: 0 | Y14: 0 | AB14: 0 | AE14: 0 | AH14: 0 | AK14: 0 | AN14: 0
A15: =+$C$4&B15 -> Véhicules neufs[...] | B15: [...] | C15: 0 | D15: 0 | E15: 0 | G15: 0 | J15: 0 | M15: 0 | P15: 0 | S15: 0 | V15: 0 | Y15: 0 | AB15: 0 | AE15: 0 | AH15: 0 | AK15: 0 | AN15: 0
A16: =+$C$4&B16 -> Véhicules neufsTotal Neufs | B16: Total Neufs | C16: 672 | D16: 2252.8079 | E16: 1513886.9 | F16: 44 | G16: 2056.5468 | H16: 90488.06 | I16: 71 | J16: 2372.1841 | K16: 168425.07 | L16: 70 | M16: 2902.3577 | N16: 203165.04 | O16: 69 | P16: 2713.7148 | Q16: 187246.32 | R16: 69 | S16: 2326.0122 | T16: 160494.84 | U16: 40 | V16: 2129.3667 | W16: 85174.67 | X16: 77 | Y16: 2170.3926 | Z16: 167120.23 | AA16: 81 | AB16: 2139.5227 | AC16: 173301.34 | AD16: 42 | AE16: 1912.6779 | AF16: 80332.47 | AG16: 44 | AH16: 1588.6441 | AI16: 69900.34 | AJ16: 35 | AK16: 2095.4297 | AL16: 73340.04 | AM16: 30 | AN16: 1829.95 | AO16: 54898.5
A17: =+$C$4&B17 -> Véhicules neufs
A18: =+$C$4&B18 -> Véhicules neufsEx-Démos et courtoisies | B18: Ex-Démos et courtoisies | C18: 41 | D18: 1567.3937 | E18: 64263.14 | F18: 2 | G18: 2875.985 | H18: 5751.97 | I18: 2 | J18: 1741.325 | K18: 3482.65 | L18: 4 | M18: 590.49 | N18: 2361.96 | O18: 4 | P18: 2264.375 | Q18: 9057.5 | R18: 5 | S18: 1165.582 | T18: 5827.91 | U18: 0 | V18: 0 | W18: 0 | X18: 3 | Y18: 913.29 | Z18: 2739.87 | AA18: 6 | AB18: 1521.5767 | AC18: 9129.46 | AD18: 3 | AE18: 2567.51 | AF18: 7702.53 | AG18: 6 | AH18: 1038.8833 | AI18: 6233.3 | AJ18: 2 | AK18: 1396.23 | AL18: 2792.46 | AM18: 4 | AN18: 2295.8825 | AO18: 9183.53
A19: =+$C$4&B19 -> Véhicules neufs
A20: =+$C$4&B20 -> Véhicules neufsFlottes | B20: Flottes | C20: 20 | D20: 1710.9615 | E20: 34219.23 | F20: 0 | G20: 0 | H20: 0 | I20: 2 | J20: 1747.28 | K20: 3494.56 | L20: 0 | M20: 0 | N20: 0 | O20: 0 | P20: 0 | Q20: 0 | R20: 0 | S20: 0 | T20: 0 | U20: 0 | V20: 0 | W20: 0 | X20: 5 | Y20: 2550.916 | Z20: 12754.58 | AA20: 1 | AB20: 1402.08 | AC20: 1402.08 | AD20: 1 | AE20: 4920.64 | AF20: 4920.64 | AG20: 2 | AH20: 383.48 | AI20: 766.96 | AJ20: 3 | AK20: 1478.8733 | AL20: 4436.62 | AM20: 6 | AN20: 1073.965 | AO20: 6443.79
A21: =+$C$4&B21 -> Véhicules neufs
A22: =+$C$4&B22 -> Véhicules neufsRachat bail | B22: Rachat bail | E22: 91424.37 | H22: 5000 | K22: 4000 | N22: 7500 | Q22: 6030.37 | T22: 9930 | W22: 6100 | Z22: 10000 | AC22: 4315 | AF22: 14800 | AI22: 10100 | AL22: 7700 | AO22: 5949
A23: =+$C$4&B23 -> Véhicules neufs
A24: =+$C$4&B24 -> Véhicules neufsRev. Finances | B24: Rev. Finances | D24: 15.171052 | E24: 10816.96 | G24: 6.5217391 | H24: 300 | J24: 115.4537 | K24: 8428.12 | M24: 0 | N24: 0 | P24: 0 | Q24: 0 | S24: 10.810811 | T24: 800 | V24: 0 | W24: 0 | Y24: 0 | Z24: 0 | AB24: 0 | AC24: 0 | AE24: 0 | AF24: 0 | AH24: 0 | AI24: 0 | AK24: 0 | AL24: 0 | AN24: 37.907059 | AO24: 1288.84
A25: =+$C$4&B25 -> Véhicules neufsRev. Protections | B25: Rev. Protections | D25: 882.44753 | E25: 629185.09 | G25: 883.63217 | H25: 40647.08 | J25: 899.34425 | K25: 65652.13 | M25: 926.11297 | N25: 68532.36 | P25: 765.92219 | Q25: 55912.32 | S25: 791.51257 | T25: 58571.93 | V25: 775.005 | W25: 31000.2 | Y25: 762.336 | Z25: 60986.88 | AB25: 880.21138 | AC25: 76578.39 | AE25: 1020.234 | AF25: 45910.53 | AH25: 844.5266 | AI25: 42226.33 | AK25: 1044.0162 | AL25: 38628.6 | AN25: 1309.9512 | AO25: 44538.34
A26: =+$C$4&B26 -> Véhicules neufsRev. Autres | B26: Rev. Autres | D26: 10.581304 | E26: 7544.47 | G26: 0 | H26: 0 | J26: 0 | K26: 0 | M26: 0 | N26: 0 | P26: 18.60589 | Q26: 1358.23 | S26: 0 | T26: 0 | V26: 67.475 | W26: 2699 | Y26: 7.12275 | Z26: 569.82 | AB26: 0 | AC26: 0 | AE26: 36.183111 | AF26: 1628.24 | AH26: 12.8804 | AI26: 644.02 | AK26: 17.436757 | AL26: 645.16 | AN26: 0 | AO26: 0
A27: =+$C$4&B27 -> Véhicules neufsTotal F&I | B27: Total F&I | C27: 713 | D27: 908.19989 | E27: 647546.52 | F27: 46 | G27: 890.15391 | H27: 40947.08 | I27: 73 | J27: 1014.7979 | K27: 74080.25 | L27: 74 | M27: 926.11297 | N27: 68532.36 | O27: 73 | P27: 784.52808 | Q27: 57270.55 | R27: 74 | S27: 802.32338 | T27: 59371.93 | U27: 40 | V27: 842.48 | W27: 33699.2 | X27: 80 | Y27: 769.45875 | Z27: 61556.7 | AA27: 87 | AB27: 880.21138 | AC27: 76578.39 | AD27: 45 | AE27: 1056.4171 | AF27: 47538.77 | AG27: 50 | AH27: 857.407 | AI27: 42870.35 | AJ27: 37 | AK27: 1061.453 | AL27: 39273.76 | AM27: 34 | AN27: 1347.8582 | AO27: 45827.18
A28: =+$C$4&B28 -> Véhicules neufs
A29: =+$C$4&B29 -> Véhicules neufs
A30: =+$C$4&B30 -> Véhicules neufsTotal Dépt. Neufs | B30: Total Dépt. Neufs | C30: 733 | D30: 3207.8311 | E30: 2351340.2 | F30: 46 | G30: 3091.0241 | H30: 142187.11 | I30: 75 | J30: 3379.7671 | K30: 253482.53 | L30: 74 | M30: 3804.8562 | N30: 281559.36 | O30: 73 | P30: 3556.2293 | Q30: 259604.74 | R30: 74 | S30: 3184.1173 | T30: 235624.68 | U30: 40 | V30: 3124.3467 | W30: 124973.87 | X30: 85 | Y30: 2990.2515 | Z30: 254171.38 | AA30: 88 | AB30: 3008.2531 | AC30: 264726.27 | AD30: 46 | AE30: 3375.9654 | AF30: 155294.41 | AG30: 52 | AH30: 2497.5183 | AI30: 129870.95 | AJ30: 40 | AK30: 3188.572 | AL30: 127542.88 | AM30: 40 | AN30: 3057.55 | AO30: 122302
A31: =+$C$4&B31 -> Véhicules neufs
A32: =+$C$4&B32 -> Véhicules neufs
A33: =+$C$4&B33 -> Véhicules neufsDEPENSES | B33: DEPENSES
A34: =+$C$4&B34 -> Véhicules neufsComm. vendeurs | B34: Comm. vendeurs | C34: 0.30428588 | D34: 673.5046 | E34: 480208.78 | F34: 0.35900508 | G34: 751.1013 | H34: 34550.66 | I34: 0.27013796 | J34: 636.14795 | K34: 46438.8 | L34: 0.3078577 | M34: 855.04149 | N34: 63273.07 | O34: 0.24820205 | P34: 667.43849 | Q34: 48723.01 | R34: 0.21053999 | S34: 473.21068 | T34: 35017.59 | U34: 0.30022752 | V34: 639.2945 | W34: 25571.78 | X34: 0.33547025 | Y34: 712.28763 | Z34: 56983.01 | AA34: 0.34952376 | AB34: 732.91839 | AC34: 63763.9 | AD34: 0.34726234 | AE34: 679.36089 | AF34: 30571.24 | AG34: 0.36906117 | AH34: 561.9594 | AI34: 28097.97 | AJ34: 0.31392099 | AK34: 645.93486 | AL34: 23899.59 | AM34: 0.36387986 | AN34: 685.82824 | AO34: 23318.16
A35: =+$C$4&B35 -> Véhicules neufsComm. F&I | B35: Comm. F&I | C35: 0.27412176 | D35: 248.95735 | E35: 177506.59 | F35: 0.29998818 | G35: 267.03565 | H35: 12283.64 | I35: 0.30043055 | J35: 304.8763 | K35: 22255.97 | L35: 0.29634424 | M35: 274.44824 | N35: 20309.17 | O35: 0.29711868 | P35: 233.09795 | Q35: 17016.15 | R35: 0.29999833 | S35: 240.69568 | T35: 17811.48 | U35: 0.0032629855 | V35: 2.749 | W35: 109.96 | X35: 0.26999709 | Y35: 207.75163 | Z35: 16620.13 | AA35: 0.26932885 | AB35: 237.06632 | AC35: 20624.77 | AD35: 0.2977738 | AE35: 314.57333 | AF35: 14155.8 | AG35: 0.26999336 | AH35: 231.4942 | AI35: 11574.71 | AJ35: 0.27998974 | AK35: 297.19595 | AL35: 10996.25 | AM35: 0.30000886 | AN35: 404.36941 | AO35: 13748.56
A36: =+$C$4&B36 -> Véhicules neufsFrais de livraison | B36: Frais de livraison | D36: 122.99884 | E36: 87698.17 | G36: 164.2663 | H36: 7556.25 | J36: 117.11219 | K36: 8549.19 | M36: 115.96514 | N36: 8581.42 | P36: 51.42137 | Q36: 3753.76 | S36: 153.52486 | T36: 11360.84 | V36: 130.5265 | W36: 5221.06 | Y36: 95.093 | Z36: 7607.44 | AB36: 120.29333 | AC36: 10465.52 | AE36: 123.12511 | AF36: 5540.63 | AH36: 156.3466 | AI36: 7817.33 | AK36: 233.92757 | AL36: 8655.32 | AN36: 76.159118 | AO36: 2589.41
A37: =+$C$4&B37 -> Véhicules neufsService gratuit 1 | B37: Service gratuit 1 | D37: 21.524348 | E37: 15346.86 | G37: 8.3769565 | H37: 385.34 | J37: 17.555205 | K37: 1281.53 | M37: 4.4041892 | N37: 325.91 | P37: 1.5160274 | Q37: 110.67 | S37: 13.206486 | T37: 977.28 | V37: 4.62375 | W37: 184.95 | Y37: 33.065625 | Z37: 2645.25 | AB37: 23.456092 | AC37: 2040.68 | AE37: 36.238889 | AF37: 1630.75 | AH37: 16.8636 | AI37: 843.18 | AK37: 108.85892 | AL37: 4027.78 | AN37: 26.280588 | AO37: 893.54
A38: =+$C$4&B38 -> Véhicules neufsEntretien stock | B38: Entretien stock | D38: 122.40062 | E38: 87271.64 | G38: 127.07739 | H38: 5845.56 | J38: 32.798493 | K38: 2394.29 | M38: 142.67541 | N38: 10557.98 | P38: 164.94 | Q38: 12040.62 | S38: 132.78284 | T38: 9825.93 | V38: 185.7815 | W38: 7431.26 | Y38: 79.675375 | Z38: 6374.03 | AB38: 65.982069 | AC38: 5740.44 | AE38: 174.15711 | AF38: 7837.07 | AH38: 159.8588 | AI38: 7992.94 | AK38: 212.08676 | AL38: 7847.21 | AN38: 99.538529 | AO38: 3384.31
A39: =+$C$4&B39 -> Véhicules neufsPublicité 1 | B39: Publicité 1 | D39: 144.03689 | E39: 102698.3 | G39: 158.61696 | H39: 7296.38 | J39: -25.284384 | K39: -1845.76 | M39: 152.39 | N39: 11276.86 | P39: 131.05397 | Q39: 9566.94 | S39: 164.58405 | T39: 12179.22 | V39: 266.85925 | W39: 10674.37 | Y39: 39.7595 | Z39: 3180.76 | AB39: 8.5896552 | AC39: 747.3 | AE39: 180.94756 | AF39: 8142.64 | AH39: 224.6836 | AI39: 11234.18 | AK39: 527.05568 | AL39: 19501.06 | AN39: 316.01029 | AO39: 10744.35
A40: =+$C$4&B40 -> Véhicules neufsIntérêt de gros | B40: Intérêt de gros | D40: 430.43816 | E40: 306902.41 | G40: 488.54978 | H40: 22473.29 | J40: 418.82699 | K40: 30574.37 | M40: 473.94432 | N40: 35071.88 | P40: 474.72863 | Q40: 34655.19 | S40: 644.70649 | T40: 47708.28 | V40: 1001.4042 | W40: 40056.17 | Y40: 565.70337 | Z40: 45256.27 | AB40: 400.05483 | AC40: 34804.77 | AE40: 678.81778 | AF40: 30546.8 | AH40: 530.407 | AI40: 26520.35 | AK40: -1003.7751 | AL40: -37139.68 | AN40: -106.62588 | AO40: -3625.28
A41: =+$C$4&B41 -> Véhicules neufs[...] | B41: [...] | D41: 0 | E41: 0 | G41: 0 | J41: 0 | M41: 0 | P41: 0 | S41: 0 | V41: 0 | Y41: 0 | AB41: 0 | AE41: 0 | AH41: 0 | AK41: 0 | AN41: 0
A42: =+$C$4&B42 -> Véhicules neufs[...] | B42: [...] | D42: 0 | E42: 0 | G42: 0 | J42: 0 | M42: 0 | P42: 0 | S42: 0 | V42: 0 | Y42: 0 | AB42: 0 | AE42: 0 | AH42: 0 | AK42: 0 | AN42: 0
A43: =+$C$4&B43 -> Véhicules neufs[...] | B43: [...] | D43: 0 | E43: 0 | G43: 0 | J43: 0 | M43: 0 | P43: 0 | S43: 0 | V43: 0 | Y43: 0 | AB43: 0 | AE43: 0 | AH43: 0 | AK43: 0 | AN43: 0
A44: =+$C$4&B44 -> Véhicules neufsTOTAL VARIABLES | B44: TOTAL VARIABLES | C44: % brut | D44: 0.53485785 | E44: 1257632.7 | F44: % brut | G44: 0.63571951 | H44: 90391.12 | I44: % brut | J44: 0.43256784 | K44: 109648.39 | L44: % brut | M44: 0.53060317 | N44: 149396.29 | O44: % brut | P44: 0.48483837 | Q44: 125866.34 | R44: % brut | S44: 0.57243842 | T44: 134880.62 | U44: % brut | V44: 0.71414569 | W44: 89249.55 | X44: % brut | Y44: 0.54556453 | Z44: 138666.89 | AA44: % brut | AB44: 0.52200101 | AC44: 138187.38 | AD44: % brut | AE44: 0.6337957 | AF44: 98424.93 | AG44: % brut | AH44: 0.72441651 | AI44: 94080.66 | AJ44: % brut | AK44: 0.29627314 | AL44: 37787.53 | AM44: % brut | AN44: 0.4174343 | AO44: 51053.05
A45: =+$C$4&B45 -> Véhicules neufsSalaires cadres | B45: Salaires cadres | E45: 192636.23 | H45: 15283.28 | K45: 18688.15 | N45: 21641.75 | Q45: 13149.05 | T45: 11905.98 | W45: 12515.2 | Z45: 15863.28 | AC45: 15861.36 | AF45: 15361.35 | AI45: 12188.2 | AL45: 24253.66 | AO45: 15924.97
A46: =+$C$4&B46 -> Véhicules neufsSalaires commis | B46: Salaires commis | E46: 119210.41 | H46: 9379.4 | K46: 8496.62 | N46: 11348.47 | Q46: 9365.85 | T46: 9609.39 | W46: 10896.4 | Z46: 8318.46 | AC46: 11048.85 | AF46: 9911.09 | AI46: 8630.72 | AL46: 13792.56 | AO46: 8412.6
A47: =+$C$4&B47 -> Véhicules neufsSalaires autres | B47: Salaires autres | E47: 41466.12 | H47: 2993.74 | K47: 3562.25 | N47: 3645.21 | Q47: 4575.36 | T47: 3925.06 | W47: 2584.64 | Z47: 2420.59 | AC47: 4682.53 | AF47: 3755.5 | AI47: 2146.12 | AL47: 4339.52 | AO47: 2835.6
A48: =+$C$4&B48 -> Véhicules neufsSalaires spécialistes | B48: Salaires spécialistes | E48: 0 | H48: 0 | K48: 0 | N48: 0 | Q48: 0 | T48: 0 | W48: 0 | Z48: 0 | AC48: 0 | AF48: 0 | AI48: 0 | AL48: 0 | AO48: 0
A49: =+$C$4&B49 -> Véhicules neufs[...] | B49: [...] | E49: 0 | H49: 0 | K49: 0 | N49: 0 | Q49: 0 | T49: 0 | W49: 0 | Z49: 0 | AC49: 0 | AF49: 0 | AI49: 0 | AL49: 0 | AO49: 0
A50: =+$C$4&B50 -> Véhicules neufs[...] | B50: [...] | E50: 0 | H50: 0 | K50: 0 | N50: 0 | Q50: 0 | T50: 0 | W50: 0 | Z50: 0 | AC50: 0 | AF50: 0 | AI50: 0 | AL50: 0 | AO50: 0
A51: =+$C$4&B51 -> Véhicules neufs[...] | B51: [...] | E51: 0 | H51: 0 | K51: 0 | N51: 0 | Q51: 0 | T51: 0 | W51: 0 | Z51: 0 | AC51: 0 | AF51: 0 | AI51: 0 | AL51: 0 | AO51: 0
A52: =+$C$4&B52 -> Véhicules neufsSalaires en absences | B52: Salaires en absences | E52: 130545.49 | H52: 10293.26 | K52: 9094.53 | N52: 10397.81 | Q52: 11763.15 | T52: 14577.13 | W52: 10189.97 | Z52: 10664.1 | AC52: 11439.02 | AF52: 11002.44 | AI52: 10528.2 | AL52: 11233.56 | AO52: 9362.32
A53: =+$C$4&B53 -> Véhicules neufsDéduction à la source | B53: Déduction à la source | E53: 175655.29 | H53: 16906.26 | K53: 14498.97 | N53: 18365.25 | Q53: 18598.07 | T53: 16512.36 | W53: 11457.24 | Z53: 12553.25 | AC53: 14840.25 | AF53: 14099.3 | AI53: 14036.34 | AL53: 12527.06 | AO53: 11260.94
A54: =+$C$4&B54 -> Véhicules neufsBénéfices marginaux | B54: Bénéfices marginaux | E54: 75545.53 | H54: 6508.32 | K54: 6952.68 | N54: 6187.38 | Q54: 7275.41 | T54: 8805.59 | W54: 6085.69 | Z54: 7041.73 | AC54: 7953.48 | AF54: 7411.59 | AI54: 6769.08 | AL54: 372.18 | AO54: 4182.4
A55: =+$C$4&B55 -> Véhicules neufsCsst | B55: Csst | E55: 30693.23 | H55: 2586.22 | K55: 2844.68 | N55: 3260.08 | Q55: 3705.07 | T55: 3234.85 | W55: 1674.44 | Z55: 1892.71 | AC55: 3473.47 | AF55: 2367.79 | AI55: 1167.34 | AL55: 1645.94 | AO55: 2840.64
A56: =+$C$4&B56 -> Véhicules neufs[...] | B56: [...] | E56: 0
A57: =+$C$4&B57 -> Véhicules neufsTOTAL PERSONNEL | B57: TOTAL PERSONNEL | C57: % brut | D57: 0.32566632 | E57: 765752.3 | F57: % brut | G57: 0.44976285 | H57: 63950.48 | I57: % brut | J57: 0.25302683 | K57: 64137.88 | L57: % brut | M57: 0.26582654 | N57: 74845.95 | O57: % brut | P57: 0.26360058 | Q57: 68431.96 | R57: % brut | S57: 0.26360058 | T57: 68570.36 | U57: % brut | V57: 1.2636006 | W57: 55403.58 | X57: % brut | Y57: 1.2636006 | Z57: 58754.12 | AA57: % brut | AB57: 1.2636006 | AC57: 69298.96 | AD57: % brut | AE57: 1.2636006 | AF57: 63909.06 | AG57: % brut | AH57: 1.2636006 | AI57: 55466 | AJ57: % brut | AK57: 1.2636006 | AL57: 68164.48 | AM57: % brut | AN57: 1.2636006 | AO57: 54819.47
A58: =+$C$4&B58 -> Véhicules neufsPublicité 2 | B58: Publicité 2 | E58: 0 | H58: 0 | K58: 0 | N58: 0 | Q58: 0 | T58: 0 | W58: 0 | Z58: 0 | AC58: 0 | AF58: 0 | AI58: 0 | AL58: 0 | AO58: 0
A59: =+$C$4&B59 -> Véhicules neufsService gratuit 2 | B59: Service gratuit 2 | E59: 0 | H59: 0 | K59: 0 | N59: 0 | Q59: 0 | T59: 0 | W59: 0 | Z59: 0 | AC59: 0 | AF59: 0 | AI59: 0 | AL59: 0 | AO59: 0
A60: =+$C$4&B60 -> Véhicules neufsFrais véhicules de cie | B60: Frais véhicules de cie | E60: 105840.31 | H60: 6677.55 | K60: 7358.99 | N60: 7788.24 | Q60: 11626.31 | T60: 7403.65 | W60: 7254.82 | Z60: 9199.43 | AC60: 9189.64 | AF60: 10497.54 | AI60: 8473.11 | AL60: 8283.33 | AO60: 12087.7
A61: =+$C$4&B61 -> Véhicules neufsInformatique | B61: Informatique | E61: 88237.24 | H61: 6687.32 | K61: 7119.2 | N61: 7015.61 | Q61: 7516.3 | T61: 7461.29 | W61: 7043.39 | Z61: 5972.42 | AC61: 8684.45 | AF61: 8853.42 | AI61: 7015.5 | AL61: 6688.36 | AO61: 8179.98
A62: =+$C$4&B62 -> Véhicules neufsFrais de déplacement | B62: Frais de déplacement | E62: 18128.02 | H62: 1076.85 | K62: 230.83 | N62: 1100.6 | Q62: 2705.19 | T62: 1278.4 | W62: 1316.83 | Z62: 1613.78 | AC62: 1158.94 | AF62: 1810.19 | AI62: 2344.34 | AL62: 2373.63 | AO62: 1118.44
A63: =+$C$4&B63 -> Véhicules neufsServices extérieurs | B63: Services extérieurs | E63: 88609.06 | H63: 7732.26 | K63: 6706.21 | N63: 6497.3 | Q63: 6746.26 | T63: 7123.34 | W63: 7463.74 | Z63: 7694.41 | AC63: 7667.77 | AF63: 8147.65 | AI63: 8179.53 | AL63: 7674.68 | AO63: 6975.91
A64: =+$C$4&B64 -> Véhicules neufsFournitures autres | B64: Fournitures autres | E64: 873.33 | H64: 104.38 | K64: 0 | N64: 220.74 | Q64: 36.28 | T64: 17.22 | W64: 4.56 | Z64: 97.12 | AC64: 141.9 | AF64: 74.69 | AI64: 0 | AL64: 0 | AO64: 176.44
A65: =+$C$4&B65 -> Véhicules neufsUniformes | B65: Uniformes | E65: 434.88 | H65: 0 | K65: 0 | N65: 0 | Q65: 0 | T65: 0 | W65: 0 | Z65: 0 | AC65: 0 | AF65: 0 | AI65: 434.88 | AL65: 0 | AO65: 0
A66: =+$C$4&B66 -> Véhicules neufsPapeterie | B66: Papeterie | E66: 9025.32 | H66: 425.21 | K66: 1331.47 | N66: 552.11 | Q66: 381.04 | T66: 885.48 | W66: 387.99 | Z66: 356.55 | AC66: 1375.08 | AF66: 628.31 | AI66: 377.56 | AL66: 1262.34 | AO66: 1062.18
A67: =+$C$4&B67 -> Véhicules neufsTéléphone | B67: Téléphone | E67: 4238.2 | H67: 381.78 | K67: 318.49 | N67: 360.77 | Q67: 318.9 | T67: 340.16 | W67: 326.92 | Z67: 330.97 | AC67: 440.89 | AF67: 345.76 | AI67: 393.48 | AL67: 351.63 | AO67: 328.45
A68: =+$C$4&B68 -> Véhicules neufsFrais postaux | B68: Frais postaux | E68: 896.29 | H68: 159.3 | K68: 222.02 | N68: 278.24 | Q68: 10.56 | T68: 10.56 | W68: 32.96 | Z68: 32.96 | AC68: 10.56 | AF68: 32.96 | AI68: 32.96 | AL68: 40.25 | AO68: 32.96
A69: =+$C$4&B69 -> Véhicules neufsDivers | B69: Divers | E69: 2165.78 | H69: 103.25 | K69: 205.65 | N69: 255.97 | Q69: 201.95 | T69: 105.31 | W69: 123.77 | Z69: 188.48 | AC69: 52.48 | AF69: 152.01 | AI69: 234.47 | AL69: 446.81 | AO69: 95.63
... A71: =+$C$4&B71 -> Véhicules neufsFrais bancaires | B71: Frais bancaires | E71: 47376.41 | H71: 3087.92 | K71: 2438.09 | N71: 3214.1 | Q71: 4277.07 | T71: 4750.5 | W71: 3357.81 | Z71: 3718.78 | AC71: 3576.25 | AF71: 3267.11 | AI71: 4782.88 | AL71: 6767.49 | AO71: 4138.41
A72: =+$C$4&B72 -> Véhicules neufs[...] | B72: [...] | E72: 0
A73: =+$C$4&B73 -> Véhicules neufs[...] | B73: [...] | E73: 0
A74: =+$C$4&B74 -> Véhicules neufs[...] | B74: [...] | E74: 0
A75: =+$C$4&B75 -> Véhicules neufsTOTAL SEMI-FIXES | B75: TOTAL SEMI-FIXES | C75: % brut | D75: 0.16497808 | E75: 387919.6 | F75: % brut | G75: 0.19889159 | H75: 28279.82 | I75: % brut | J75: 0.10677817 | K75: 27066.4 | L75: % brut | M75: 0.10190043 | N75: 28691.02 | O75: % brut | P75: 0.13469404 | Q75: 34967.21 | R75: % brut | S75: 0.12965552 | T75: 30550.04 | U75: % brut | V75: 0.22968153 | W75: 28704.19 | X75: % brut | Y75: 0.12862569 | Z75: 32692.97 | AA75: % brut | AB75: 0.13551749 | AC75: 35875.04 | AD75: % brut | AE75: 0.23494143 | AF75: 36485.09 | AG75: % brut | AH75: 0.26669297 | AI75: 34635.67 | AJ75: % brut | AK75: 0.27970178 | AL75: 35673.97 | AM75: % brut | AN75: 0.28043842 | AO75: 34298.18
A76: =+$C$4&B76 -> Véhicules neufs
A77: =+$C$4&B77 -> Véhicules neufsTOTAL DES DÉPENSES | B77: TOTAL DES DÉPENSES | C77: % brut | D77: 1.0255023 | E77: 2411304.6 | F77: % brut | G77: 1.2843739 | H77: 182621.42 | I77: % brut | J77: 0.79237283 | K77: 200852.67 | L77: % brut | M77: 0.89833014 | N77: 252933.26 | O77: % brut | P77: 0.88313299 | Q77: 229265.51 | R77: % brut | S77: 0.99310913 | T77: 234001.02 | U77: % brut | V77: 1.3871485 | W77: 173357.32 | X77: % brut | Y77: 0.90534969 | Z77: 230113.98 | AA77: % brut | AB77: 0.91929441 | AC77: 243361.38 | AD77: % brut | AE77: 1.280272 | AF77: 198819.08 | AG77: % brut | AH77: 1.418195 | AI77: 184182.33 | AJ77: % brut | AK77: 1.1104186 | AL77: 141625.98 | AM77: % brut | AN77: 1.1461031 | AO77: 140170.7
A78: =+$C$4&B78 -> Véhicules neufsProgramme neuf 1 | B78: Programme neuf 1 | E78: 87295 | H78: 0 | K78: 0 | N78: 0 | Q78: 695 | T78: 0 | W78: 20000 | Z78: 18100 | AC78: 0 | AF78: 16000 | AI78: 0 | AL78: 12500 | AO78: 20000
A79: =+$C$4&B79 -> Véhicules neufsProgramme neuf 2 | B79: Programme neuf 2 | E79: 0 | H79: 0 | K79: 0 | N79: 0 | Q79: 0 | T79: 0 | W79: 0 | Z79: 0 | AC79: 0 | AF79: 0 | AI79: 0 | AL79: 0 | AO79: 0
A80: =+$C$4&B80 -> Véhicules neufsProgramme neuf 3 | B80: Programme neuf 3 | E80: 0 | H80: 0 | K80: 0 | N80: 0 | Q80: 0 | T80: 0 | W80: 0 | Z80: 0 | AC80: 0 | AF80: 0 | AI80: 0 | AL80: 0 | AO80: 0
A81: =+$C$4&B81 -> Véhicules neufsHoldbacks | B81: Holdbacks | E81: 953913.25 | H81: 51590 | K81: 91804.85 | N81: 83565 | Q81: 106078.85 | T81: 99044.7 | W81: 55522 | Z81: 127510 | AC81: 110039 | AF81: 52835 | AI81: 66750.85 | AL81: 55120 | AO81: 54053
A82: =+$C$4&B82 -> Véhicules neufs[...] | B82: [...] | E82: 0 | H82: 0 | K82: 0 | N82: 0 | Q82: 0 | T82: 0 | W82: 0 | Z82: 0 | AC82: 0 | AF82: 0 | AI82: 0 | AL82: 0 | AO82: 0
A83: =+$C$4&B83 -> Véhicules neufs[...] | B83: [...] | E83: 0 | H83: 0 | K83: 0 | N83: 0 | Q83: 0 | T83: 0 | W83: 0 | Z83: 0 | AC83: 0 | AF83: 0 | AI83: 0 | AL83: 0 | AO83: 0
A84: =+$C$4&B84 -> Véhicules neufs[...] | B84: [...] | E84: 0 | H84: 0 | K84: 0 | N84: 0 | Q84: 0 | T84: 0 | W84: 0 | Z84: 0 | AC84: 0 | AF84: 0 | AI84: 0 | AL84: 0 | AO84: 0
A85: =+$C$4&B85 -> Véhicules neufsFrais administration | B85: Frais administration | E85: 330462.5 | H85: 24336 | K85: 30949 | N85: 34491 | Q85: 36038 | T85: 32586 | W85: 19532.5 | Z85: 35590 | AC85: 39816 | AF85: 19467 | AI85: 24378 | AL85: 16782 | AO85: 16497
A86: =+$C$4&B86 -> Véhicules neufsAUTRES REVENUS | B86: AUTRES REVENUS | E86: 1371670.8 | H86: 75926 | K86: 122753.85 | N86: 118056 | Q86: 142811.85 | T86: 131630.7 | W86: 95054.5 | Z86: 181200 | AC86: 149855 | AF86: 88302 | AI86: 91128.85 | AL86: 84402 | AO86: 90550
A87: =+$C$4&B87 -> Véhicules neufs
A88: =+$C$4&B88 -> Véhicules neufsPROFIT DÉPARTEMENTAL | B88: PROFIT DÉPARTEMENTAL | E88: 1311706.3 | H88: 35491.69 | K88: 175383.71 | N88: 146682.1 | Q88: 173151.08 | T88: 133254.36 | W88: 46671.05 | Z88: 205257.4 | AC88: 171219.89 | AF88: 44777.33 | AI88: 36817.47 | AL88: 70318.9 | AO88: 72681.3
B92: Réel 2024 | C92: Véhicules usagés
B94: Mois | C94: 2024 | F94: Janvier | I94: Février | L94: Mars | O94: Avril | R94: Mai | U94: Juin | X94: Juillet | AA94: Août | AD94: Septembre | AG94: Octobre | AJ94: Novembre | AM94: Décembre
C95: UNITE | D95: $P/UNITE | E95: $PROFITS | F95: UNITE | G95: $P/UNITE | H95: $PROFITS | I95: UNITE | J95: $P/UNITE | K95: $PROFITS | L95: UNITE | M95: $P/UNITE | N95: $PROFITS | O95: UNITE | P95: $P/UNITE | Q95: $PROFITS | R95: UNITE | S95: $P/UNITE | T95: $PROFITS | U95: UNITE | V95: $P/UNITE | W95: $PROFITS | X95: UNITE | Y95: $P/UNITE | Z95: $PROFITS | AA95: UNITE | AB95: $P/UNITE | AC95: $PROFITS | AD95: UNITE | AE95: $P/UNITE | AF95: $PROFITS | AG95: UNITE | AH95: $P/UNITE | AI95: $PROFITS | AJ95: UNITE | AK95: $P/UNITE | AL95: $PROFITS | AM95: UNITE | AN95: $P/UNITE | AO95: $PROFITS
A96: =+$C$92&B96 -> Véhicules usagésVentes nettes | B96: Ventes nettes | E96: 15217940 | H96: 1261256.2 | K96: 1454969.4 | N96: 1441390.1 | Q96: 1101235.5 | T96: 1785178.6 | W96: 1325634.6 | Z96: 1416483.6 | AC96: 1094286.6 | AF96: 1166915.5 | AI96: 1341799.5 | AL96: 1025214 | AO96: 803576.36
A97: =+$C$92&B97 -> Véhicules usagésCertifié | B97: Certifié | C97: 304 | D97: 949.22845 | E97: 288565.45 | F97: 11 | G97: 311.87273 | H97: 3430.6 | I97: 25 | J97: 127.2604 | K97: 3181.51 | L97: 22 | M97: 1225.9168 | N97: 26970.17 | O97: 22 | P97: 1680.7486 | Q97: 36976.47 | R97: 38 | S97: 23.055789 | T97: 876.12 | U97: 31 | V97: 599.35871 | W97: 18580.12 | X97: 25 | Y97: 1627.8944 | Z97: 40697.36 | AA97: 19 | AB97: 922.09053 | AC97: 17519.72 | AD97: 27 | AE97: 1293.3581 | AF97: 34920.67 | AG97: 37 | AH97: 1033.9343 | AI97: 38255.57 | AJ97: 30 | AK97: 1597.681 | AL97: 47930.43 | AM97: 17 | AN97: 1130.9829 | AO97: 19226.71
A98: =+$C$92&B98 -> Véhicules usagésNon Certifié | B98: Non Certifié | C98: 11 | D98: -2135.6709 | E98: -23492.38 | F98: 1 | G98: 450 | H98: 450 | I98: 2 | J98: -4595.21 | K98: -9190.42 | L98: 0 | M98: 0 | N98: 0 | O98: 1 | P98: 1000 | Q98: 1000 | R98: 2 | S98: -811.45 | T98: -1622.9 | U98: 2 | V98: 1491.09 | W98: 2982.18 | X98: 5 | Y98: 1346.904 | Z98: 6734.52 | AA98: 6 | AB98: 615.43667 | AC98: 3692.62 | AD98: -13 | AE98: 1650.3969 | AF98: -21455.16 | AG98: 3 | AH98: -1128.6233 | AI98: -3385.87 | AJ98: 2 | AK98: -1112.96 | AL98: -2225.92 | AM98: 0 | AN98: 0 | AO98: -471.43
A99: =+$C$92&B99 -> Véhicules usagésAutres Marques | B99: Autres Marques | C99: 7 | D99: 5686.2243 | E99: 39803.57 | F99: 0 | G99: 0 | H99: 0 | I99: 0 | J99: 0 | K99: 0 | L99: 0 | M99: 0 | N99: 0 | O99: 0 | P99: 0 | Q99: 0 | R99: 0 | S99: 0 | T99: 0 | U99: 0 | V99: 0 | W99: 0 | X99: 0 | Y99: 0 | Z99: 0 | AA99: 0 | AB99: 0 | AC99: 0 | AD99: 0 | AE99: 0 | AF99: 24564.57 | AG99: 3 | AH99: 2230.9333 | AI99: 6692.8 | AJ99: 3 | AK99: 2132.8667 | AL99: 6398.6 | AM99: 1 | AN99: 2147.6 | AO99: 2147.6
A100: =+$C$92&B100 -> Véhicules usagésTotal Usagés | B100: Total Usagés | C100: 322 | D100: 946.82186 | E100: 304876.64 | F100: 12 | G100: 323.38333 | H100: 3880.6 | I100: 27 | J100: -222.55222 | K100: -6008.91 | L100: 22 | M100: 1225.9168 | N100: 26970.17 | O100: 23 | P100: 1651.1509 | Q100: 37976.47 | R100: 40 | S100: -18.6695 | T100: -746.78 | U100: 33 | V100: 653.40303 | W100: 21562.3 | X100: 30 | Y100: 1581.0627 | Z100: 47431.88 | AA100: 25 | AB100: 848.4936 | AC100: 21212.34 | AD100: 14 | AE100: 2716.4343 | AF100: 38030.08 | AG100: 43 | AH100: 966.56977 | AI100: 41562.5 | AJ100: 35 | AK100: 1488.6603 | AL100: 52103.11 | AM100: 18 | AN100: 1161.2711 | AO100: 20902.88
A101: =+$C$92&B101 -> Véhicules usagés
A102: =+$C$92&B102 -> Véhicules usagés
A103: =+$C$92&B103 -> Véhicules usagésVentes au Gros | B103: Ventes au Gros | C103: 394 | D103: -49.915127 | E103: -19666.56 | F103: 40 | G103: 0.00575 | H103: 0.23 | I103: 37 | J103: -55.195405 | K103: -2042.23 | L103: 35 | M103: 494.95057 | N103: 17323.27 | O103: 31 | P103: -367.3229 | Q103: -11387.01 | R103: 47 | S103: -663.50468 | T103: -31184.72 | U103: 29 | V103: 144.99517 | W103: 4204.86 | X103: 37 | Y103: -125.19595 | Z103: -4632.25 | AA103: 42 | AB103: 10.700238 | AC103: 449.41 | AD103: 32 | AE103: 218.91063 | AF103: 7005.14 | AG103: 23 | AH103: 251.70435 | AI103: 5789.2 | AJ103: 19 | AK103: 279.54947 | AL103: 5311.44 | AM103: 22 | AN103: -477.45 | AO103: -10503.9
A104: =+$C$92&B104 -> Véhicules usagés
A105: =+$C$92&B105 -> Véhicules usagésRev. Finances | B105: Rev. Finances | D105: 267.29988 | E105: 86070.56 | G105: -316.30833 | H105: -3795.7 | J105: 126.87667 | K105: 3425.67 | M105: 304.22364 | N105: 6692.92 | P105: 360.09913 | Q105: 8282.28 | S105: 264.2365 | T105: 10569.46 | V105: 273.09788 | W105: 9012.23 | Y105: 275.555 | Z105: 8266.65 | AB105: 109.0996 | AC105: 2727.49 | AE105: 845.18214 | AF105: 11832.55 | AH105: 354.06837 | AI105: 15224.94 | AK105: 283.59714 | AL105: 9925.9 | AN105: 217.00944 | AO105: 3906.17
A106: =+$C$92&B106 -> Véhicules usagésRev. Protections | B106: Rev. Protections | D106: 1438.4533 | E106: 463181.95 | G106: 1480.4992 | H106: 17765.99 | J106: 636.5863 | K106: 17187.83 | M106: 1189.2841 | N106: 26164.25 | P106: 1173.4048 | Q106: 26988.31 | S106: 1738.2057 | T106: 69528.23 | V106: 1518.8015 | W106: 50120.45 | Y106: 1564.6717 | Z106: 46940.15 | AB106: 1018.2744 | AC106: 25456.86 | AE106: 3171.295 | AF106: 44398.13 | AH106: 1561.194 | AI106: 67131.34 | AK106: 1232.4863 | AL106: 43137.02 | AN106: 1575.7439 | AO106: 28363.39
...

Sheet Capex
A1: PARK AVENUE VOLKSWAGEN | B1: PARK AVENUE VOLKSWAGEN
A2: Forecast Immobilisation 2022 | B2: Forecast Immobilisation 2025 | H2: 1 | I2: 2 | J2: 3 | K2: 4 | L2: 5 | M2: 6 | N2: 7 | O2: 8 | P2: 9 | Q2: 10 | R2: 11 | S2: 12
H3: =+IF(VLOOKUP(H2,Parametres!$L$3:$N$14,3,0)="X","REEL","FORECAST") -> REEL | I3: =+IF(VLOOKUP(I2,Parametres!$L$3:$N$14,3,0)="X","REEL","FORECAST") -> REEL | J3: =+IF(VLOOKUP(J2,Parametres!$L$3:$N$14,3,0)="X","REEL","FORECAST") -> REEL | K3: =+IF(VLOOKUP(K2,Parametres!$L$3:$N$14,3,0)="X","REEL","FORECAST") -> REEL | L3: =+IF(VLOOKUP(L2,Parametres!$L$3:$N$14,3,0)="X","REEL","FORECAST") -> REEL | M3: =+IF(VLOOKUP(M2,Parametres!$L$3:$N$14,3,0)="X","REEL","FORECAST") -> REEL | N3: =+IF(VLOOKUP(N2,Parametres!$L$3:$N$14,3,0)="X","REEL","FORECAST") -> REEL | O3: =+IF(VLOOKUP(O2,Parametres!$L$3:$N$14,3,0)="X","REEL","FORECAST") -> FORECAST | ... S3: =+IF(VLOOKUP(S2,Parametres!$L$3:$N$14,3,0)="X","REEL","FORECAST") -> FORECAST
A4: Concession | B4: Budgété / Non budgété | C4: Projet | D4: Catégorie Immo | E4: Total forecast | F4: Budget Annuel | G4: Écart vs budget | H4: January | I4: February | J4: March | K4: April | L4: May | M4: June | N4: July | O4: August | P4: September | Q4: October | R4: November | S4: December | T4: Raison / Description
C5: Total | E5: =+SUM(E6:E20) -> 90029.98 | F5: =+SUM(F6:F20) -> 40000 | G5: =+SUM(G6:G20) -> 50029.98 | H5: =+SUM(H6:H20) -> 30931.3 | I5: =+SUM(I6:I20) -> 5073.24 | J5: =+SUM(J6:J20) -> 0 | K5: =+SUM(K6:K20) -> 0 | L5: =+SUM(L6:L20) -> 33385.44 | ... S5: =+SUM(S6:S20) -> 0 | X5: Terrain
A6: =+Parametres!$B$1 -> Volks | B6: oui | C6: Outils Spécialisés Volks | E6: =+SUM(H6:S6) -> 40000.46 | F6: 40000 | G6: =+E6-F6 -> 0.46 | I6: 2000 | L6: 17360.46 | P6: 10000 | R6: 10640 | X6: Bâtisse
A7: =+Parametres!$B$1 -> Volks | B7: non | C7: Équipement informatique | E7: =+SUM(H7:S7) -> 5924.22 | G7: =+E7-F7 -> 5924.22 | I7: 3073.24 | L7: 2850.98 | X7: Améliorations Locatives
A8: =+Parametres!$B$1 -> Volks | C8: Nouveau building | E8: =+SUM(H8:S8) -> 44105.3 | G8: =+E8-F8 -> 44105.3 | H8: 30931.3 | L8: =1012+1690+10472 -> 13174 | X8: Mobilier
A9: =+Parametres!$B$1 -> Volks | E9: =+SUM(H9:S9) -> 0 | G9: =+E9-F9 -> 0 | X9: Équipements Informatique
A10: =+Parametres!$B$1 -> Volks | E10: =+SUM(H10:S10) -> 0 | G10: =+E10-F10 -> 0 | X10: Équipements Téléphonique
A11: =+Parametres!$B$1 -> Volks | E11: =+SUM(H11:S11) -> 0 | G11: =+E11-F11 -> 0 | X11: Enseigne
A12: =+Parametres!$B$1 -> Volks | E12: =+SUM(H12:S12) -> 0 | G12: =+E12-F12 -> 0
A13: =+Parametres!$B$1 -> Volks | E13: =+SUM(H13:S13) -> 0 | G13: =+E13-F13 -> 0
A14: =+Parametres!$B$1 -> Volks | E14: =+SUM(H14:S14) -> 0 | G14: =+E14-F14 -> 0
A15: =+Parametres!$B$1 -> Volks | E15: =+SUM(H15:S15) -> 0 | G15: =+E15-F15 -> 0
A16: =+Parametres!$B$1 -> Volks | E16: =+SUM(H16:S16) -> 0 | G16: =+E16-F16 -> 0
A17: =+Parametres!$B$1 -> Volks | E17: =+SUM(H17:S17) -> 0 | G17: =+E17-F17 -> 0 | X17: non
A18: =+Parametres!$B$1 -> Volks | E18: =+SUM(H18:S18) -> 0 | G18: =+E18-F18 -> 0
A19: =+Parametres!$B$1 -> Volks | E19: =+SUM(H19:S19) -> 0 | G19: =+E19-F19 -> 0
A20: =+Parametres!$B$1 -> Volks | E20: =+SUM(H20:S20) -> 0 | G20: =+E20-F20 -> 0

Sheet Inventaire_Used
A1: #Contrôle | B1: Année | C1: Marque | D1: Modèle | E1: 1416 | F1: 2103 | G1: NIV | H1: Jours en stock | M1: 45169 | N1: $ Inventaire | O1: $ Financé
A2: 5291P | B2: 2020 | C2: VOLKSWAGEN | D2: E-GOLF | E2: 32007.51 | F2: -22494.36 | G2: WVWPR7AU2LW903993 | H2: 423 | M2: CTRL | N2: =+SUM(E:E) -> 2779322.1 | O2: =+SUM(F:F) -> -640715.53
A3: 230251A | B3: 2020 | C3: VOLKSWAGEN | D3: E-GOLF | E3: 24454.46 | G3: WVWPR7AU0LW907198 | H3: 306 | M3: Unités | N3: =COUNT(E:E) -> 111 | O3: =-O2/N2 -> 0.23052943
A4: 230425A | B4: 2021 | C4: VOLKSWAGEN | D4: ATLAS CROSS SPO | E4: 37735.15 | G4: 1V2LC2CAXMC211536 | H4: 188
A5: 230365A | B5: 2018 | C5: VOLKSWAGEN | D5: BEETLE CONVERTI | E5: 29929.55 | G5: 3VW5DAAT2JM518129 | H5: 187 | M5: Moyenne | N5: =+N2/N3 -> 25038.938
A6: 5485P | B6: 2018 | C6: VOLKSWAGEN | D6: ATLAS | E6: 31306.12 | G6: 1V2NR2CA5JC509107 | H6: 131
A7: 230554A | B7: 2014 | C7: SUBARU | D7: WRX | E7: 17680.42 | G7: JF1GR8H60EL238082 | H7: 121 | M7: Plus de 90 Jours | N7: =SUM(E2:E13) -> 337989.36 | O7: =+N7/N2 -> 0.12160856
A8: 230567A | B8: 2021 | C8: VOLKSWAGEN | D8: TIGUAN | E8: 28635.15 | F8: -31332.8 | G8: 3VV2B7AX6MM155874 | H8: 104 | N8: =COUNT(H2:H13) -> 12 | O8: =+N8/(N3) -> 0.10810811
A9: 240013A | B9: 2022 | C9: VOLKSWAGEN | D9: TIGUAN | E9: 38815.25 | G9: 3VV4B7AX3NM051496 | H9: 94
A10: 230392A | B10: 2020 | C10: VOLKSWAGEN | D10: TIGUAN | E10: 31315.25 | F10: -24944.54 | G10: 3VV4B7AX2LM114164 | H10: 94
A11: 230599A | B11: 2019 | C11: VOLKSWAGEN | D11: JETTA | E11: 21280.25 | F11: -10962 | G11: 3VWE57BU6KM254342 | H11: 94
A12: 230606A | B12: 2018 | C12: CHEVROLET | D12: VOLT | E12: 17550 | G12: 1G1RA6S50JU104989 | H12: 93
A13: 240015A | B13: 2019 | C13: VOLKSWAGEN | D13: GOLF GTI | E13: 27280.25 | F13: -17480.23 | G13: 3VW6T7AU5KM024755 | H13: 90
A14: 5511P | B14: 2022 | C14: VOLKSWAGEN | D14: ATLAS CROSS SPO | E14: 44105.05 | F14: -38250 | G14: 1V2BE2CA6NC212111 | H14: 88
A15: 240019A | B15: 2020 | C15: VOLKSWAGEN | D15: ATLAS CROSS SPO | E15: 36415.13 | F15: -26892 | G15: 1V2TE2CA8LC219420 | H15: 82
A16: 230596A | B16: 2020 | C16: VOLKSWAGEN | D16: TIGUAN | E16: 27935.05 | G16: 3VV2B7AX4LM005048 | H16: 76
A17: 5509PA | B17: 2017 | C17: AUDI | D17: A3 E-TRON | E17: 20050 | G17: WAUSPBFF5HA099610 | H17: 74
A18: 230626A | B18: 2018 | C18: VOLKSWAGEN | D18: TIGUAN | E18: 20497.05 | G18: 3VV4B7AX2JM130250 | H18: 72
A19: 5518P | B19: 2020 | C19: VOLKSWAGEN | D19: TIGUAN | E19: 28075.78 | F19: -23850 | G19: 3VV4B7AX0LM106225 | H19: 69
A20: 230593A | B20: 2019 | C20: VOLKSWAGEN | D20: TIGUAN | E20: 26815.25 | G20: 3VV4B7AX3KM183332 | H20: 69
A21: 5519P | B21: 2021 | C21: VOLKSWAGEN | D21: TIGUAN | E21: 28447.25 | F21: -24418.8 | G21: 3VV2B7AX4MM068281 | H21: 68
A22: 240044A | B22: 2019 | C22: VOLKSWAGEN | D22: ATLAS | E22: 29352 | G22: 1V2MR2CA6KC587280 | H22: 66
A23: 240041A | B23: 2018 | C23: VOLKSWAGEN | D23: GOLF | E23: 18787.5 | G23: 3VWG17AU2JM291103 | H23: 66
A24: 240056A | B24: 2020 | C24: VOLKSWAGEN | D24: JETTA | E24: 18043.82 | G24: 3VWN57BU2LM040420 | H24: 65
A25: 240036A | B25: 2021 | C25: VOLKSWAGEN | D25: ATLAS | E25: 40209.65 | G25: 1V2FR2CA8MC595926 | H25: 62
A26: 240079A | B26: 2020 | C26: VOLKSWAGEN | D26: TIGUAN | E26: 30620.3 | G26: 3VV4B7AX5LM110786 | H26: 62
A27: 230564B | B27: 2020 | C27: JEEP | D27: COMPASS | E27: 28211.38 | G27: 3C4NJDDBXLT155667 | H27: 62
A28: 230649A | B28: 2020 | C28: NISSAN | D28: ROGUE | E28: 23550 | G28: 5N1AT2MT7LC775762 | H28: 61
A29: 240086A | B29: 2022 | C29: VOLKSWAGEN | D29: TIGUAN | E29: 36524.6 | G29: 3VV4B7AX9NM096457 | H29: 60
A30: 5522P | B30: 2020 | C30: VOLKSWAGEN | D30: TIGUAN | E30: 24346.21 | F30: -16047.88 | G30: 3VV2B7AX7LM099068 | H30: 60
A31: 5521P | B31: 2019 | C31: VOLKSWAGEN | D31: GOLF | E31: 18530.25 | G31: 3VWG57AU3KM018998 | H31: 60
A32: 5523P | B32: 2021 | C32: VOLKSWAGEN | D32: TIGUAN | E32: 29670.31 | F32: -25505.1 | G32: 3VV2B7AX2MM078047 | H32: 59
A33: 240089A | B33: 2020 | C33: VOLKSWAGEN | D33: JETTA | E33: 22965.2 | G33: 3VWW57BU9LM006236 | H33: 55
A34: 5525P | B34: 2021 | C34: VOLKSWAGEN | D34: TIGUAN | E34: 31666.8 | F34: -33046.59 | G34: 3VV4B7AX1MM155614 | H34: 54
A35: 240059A | B35: 2019 | C35: VOLKSWAGEN | D35: TIGUAN | E35: 24846.26 | G35: 3VV2B7AX7KM049091 | H35: 53
A36: 240099A | B36: 2020 | C36: VOLKSWAGEN | D36: JETTA | E36: 19323.74 | G36: 3VWN57BU9LM077965 | H36: 51
A37: 240098A | B37: 2019 | C37: VOLKSWAGEN | D37: GOLF | E37: 18294.75 | G37: 3VWG57AU0KM034477 | H37: 48
A38: 240038B | B38: 2018 | C38: VOLKSWAGEN | D38: GOLF | E38: 16745.3 | G38: 3VWG17AU9JM275867 | H38: 48
A39: 240091A | B39: 2022 | C39: VOLKSWAGEN | D39: ATLAS | E39: 49927.29 | G39: 1V2FR2CA7NC504226 | H39: 47
A40: 5526P | B40: 2020 | C40: VOLKSWAGEN | D40: TIGUAN | E40: 24483.1 | F40: -18876 | G40: 3VV2B7AX9LM002520 | H40: 47
A41: 240109A | B41: 2019 | C41: VOLKSWAGEN | D41: GOLF | E41: 21779.6 | G41: 3VWG57AU6KM028375 | H41: 47
A42: 240111A | B42: 2021 | C42: VOLKSWAGEN | D42: GOLF | E42: 21350 | G42: 3VWW57AU1MM000790 | H42: 45
A43: 240108A | B43: 2019 | C43: VOLKSWAGEN | D43: JETTA | E43: 17488.18 | G43: 3VWG57BU3KM143398 | H43: 45
A44: 240100A | B44: 2020 | C44: VOLKSWAGEN | D44: JETTA | E44: 18370.25 | G44: 3VWCB7BU1LM050033 | H44: 44
A45: 5527P | B45: 2018 | C45: VOLKSWAGEN | D45: TIGUAN | E45: 20165.3 | G45: 3VV2B7AX0JM078401 | H45: 44
A46: 240121A | B46: 2015 | C46: JEEP | D46: CHEROKEE | E46: 15050 | G46: 1C4PJMBBXFW775848 | H46: 44
A47: 240062A | B47: 2020 | C47: VOLKSWAGEN | D47: JETTA | E47: 21360.2 | G47: 3VWEB7BU9LM051228 | H47: 41
A48: 5528P | B48: 2021 | C48: VOLKSWAGEN | D48: JETTA | E48: 25003.85 | F48: -21330 | G48: 3VWE57BU8MM046465 | H48: 40
A49: 240153A | B49: 2020 | C49: VOLKSWAGEN | D49: TIGUAN | E49: 24894.97 | G49: 3VV0B7AX5LM117185 | H49: 40
A50: 240127A | B50: 2019 | C50: VOLKSWAGEN | D50: TIGUAN | E50: 27870.3 | G50: 3VV4B7AX2KM185248 | H50: 40
A51: 240169A | B51: 2021 | C51: VOLKSWAGEN | D51: JETTA | E51: 24530.4 | G51: 3VWE57BU7MM077268 | H51: 37
A52: 240143A | B52: 2008 | C52: VOLKSWAGEN | D52: GTI | E52: 4314.03 | G52: WVWHV91K48W093414 | H52: 37
A53: 240183A | B53: 2021 | C53: VOLKSWAGEN | D53: JETTA | E53: 24447.5 | G53: 3VWE57BU5MM022575 | H53: 33
A54: 5530P | B54: 2019 | C54: VOLKSWAGEN | D54: GOLF | E54: 20373.45 | F54: -12553.38 | G54: 3VWG57AU5KM019568 | H54: 33
A55: 240105A | B55: 2021 | C55: VOLKSWAGEN | D55: GOLF GTI | E55: 32388.2 | G55: 3VW5T7AU9MM015944 | H55: 32
A56: 240151A | B56: 2020 | C56: VOLKSWAGEN | D56: PASSAT | E56: 23491.6 | G56: 1VWBA7A31LC005280 | H56: 32
A57: 240123A | B57: 2021 | C57: VOLKSWAGEN | D57: TIGUAN | E57: 29343.25 | G57: 3VV2B7AX9MM038886 | H57: 31
A58: 240198A | B58: 2020 | C58: VOLKSWAGEN | D58: TIGUAN | E58: 29950 | G58: 3VV4B7AX7LM138623 | H58: 31
A59: 5531P | B59: 2019 | C59: VOLKSWAGEN | D59: TIGUAN | E59: 21448.99 | F59: -18000 | G59: 3VV2B7AX5KM174266 | H59: 31
A60: 240195A | B60: 2019 | C60: VOLKSWAGEN | D60: GOLF ALLTRACK | E60: 23680.2 | G60: 3VWH17AU4KM517860 | H60: 31
A61: 240031A | B61: 2019 | C61: VOLKSWAGEN | D61: GOLF | E61: 19433.85 | G61: 3VWG57AU6KM019319 | H61: 31
A62: 240208A | B62: 2019 | C62: NISSAN | D62: ROGUE | E62: 17516.85 | G62: 5N1AT2MT2KC789311 | H62: 31
A63: 240200A | B63: 2021 | C63: VOLKSWAGEN | D63: TIGUAN | E63: 28418.09 | G63: 3VV2B7AX7MM017972 | H63: 30
A64: 240120A | B64: 2020 | C64: VOLKSWAGEN | D64: TIGUAN | E64: 26650 | G64: 3VV2B7AX5LM134416 | H64: 30
A65: 5532P | B65: 2019 | C65: VOLKSWAGEN | D65: TIGUAN | E65: 22943.2 | F65: -14910 | G65: 3VV2B7AXXKM175526 | H65: 27
A66: 5536P | B66: 2024 | C66: VOLKSWAGEN | D66: GOLF R | E66: 56282.9 | F66: -53444.44 | G66: WVWEB7CD1RW113067 | H66: 26
A67: 5535P | B67: 2023 | C67: VOLKSWAGEN | D67: TIGUAN | E67: 37343.25 | F67: -31500 | G67: 3VVMB7AX1PM006494 | H67: 26
A68: 5534P | B68: 2021 | C68: VOLKSWAGEN | D68: TIGUAN | E68: 27555.44 | F68: -26142.19 | G68: 3VV2B7AX0MM070822 | H68: 26
A69: 240090A | B69: 2019 | C69: VOLKSWAGEN | D69: JETTA | E69: 15050 | G69: 3VWW57BU7KM135400 | H69: 26
A70: 5539P | B70: 2020 | C70: VOLKSWAGEN | D70: E-GOLF | E70: 24148.3 | F70: -13011 | G70: WVWPR7AUXLW900758 | H70: 25
A71: 5537P | B71: 2017 | C71: VOLKSWAGEN | D71: TIGUAN | E71: 17323.25 | F71: -14400 | G71: WVGNV7AX9HW500724 | H71: 25
A72: 5540P | B72: 2020 | C72: VOLKSWAGEN | D72: TIGUAN | E72: 24729.89 | F72: -21121.07 | G72: 3VV2B7AX5LM104042 | H72: 24
A73: 240154A | B73: 2023 | C73: HYUNDAY | D73: SANTA CRUZ | E73: 39801.28 | G73: 5NTJEDAF3PH073751 | H73: 17
A74: 5542P | B74: 2020 | C74: VOLKSWAGEN | D74: TIGUAN | E74: 27897 | F74: -21259.15 | G74: 3VV2B7AX9LM116727 | H74: 17
A75: 5543P | B75: 2021 | C75: VOLKSWAGEN | D75: TIGUAN | E75: 29849.7 | F75: -25650 | G75: 3VV4B7AX3MM043848 | H75: 16
A76: 240222A | B76: 2021 | C76: VOLKSWAGEN | D76: JETTA | E76: 22734.85 | G76: 3VWE57BU8MM023008 | H76: 16
A77: 5544P | B77: 2020 | C77: VOLKSWAGEN | D77: TIGUAN | E77: 23937.85 | G77: 3VV2B7AX7LM009577 | H77: 16
A78: 240210A | B78: 2020 | C78: DODGE | D78: RAM 1500 | E78: 37860.38 | G78: 1C6SRFFT2LN407190 | H78: 16
A79: 240226A | B79: 2019 | C79: VOLKSWAGEN | D79: GOLF | E79: 17250 | F79: -10994 | G79: 3VWG57AU7KM033052 | H79: 16
A80: 240172A | B80: 2015 | C80: VOLKSWAGEN | D80: JETTA SEDAN | E80: 9050 | G80: 3VWG07AJ8FM218642 | H80: 13
A81: 5529PA | B81: 2014 | C81: NISSAN | D81: TRUCK PATHFINDER | E81: 10550 | G81: 5N1AR2MM1EC693147 | H81: 12
A82: 5545P | B82: 2022 | C82: VOLKSWAGEN | D82: GOLF R | E82: 48197.8 | F82: -42300 | G82: WVWEB7CD8NW157948 | H82: 11
A83: 240231A | B83: 2019 | C83: VOLKSWAGEN | D83: JETTA | E83: 21402.85 | G83: 3VWE57BU8KM269358 | H83: 11
A84: 240215A | B84: 2019 | C84: VOLKSWAGEN | D84: GOLF | E84: 18179.95 | G84: 3VWW57AU6KM035788 | H84: 11
A85: 5546P | B85: 2016 | C85: BMW | D85: SAV X5 | E85: 22550 | G85: 5UXKR0C55G0S87415 | H85: 11
A86: 0925RA | B86: 2010 | C86: TOYOTA | D86: COROLLA | E86: 5450 | G86: 2T1BU4EE1AC231280 | H86: 11
A87: 240191A | B87: 2019 | C87: VOLKSWAGEN | D87: TIGUAN | E87: 20650 | G87: 3VV2B7AX1KM022551 | H87: 10
A88: 240194A | B88: 2015 | C88: VOLKSWAGEN | D88: TIGUAN | E88: 8550 | G88: WVGJV7AX1FW576563 | H88: 10
A89: 240261A | B89: 2020 | C89: VOLKSWAGEN | D89: TIGUAN | E89: 25550 | G89: 3VV2B7AXXLM100701 | H89: 9
A90: 240035A | B90: 2020 | C90: HONDA | D90: PILOT | E90: 28550 | G90: 5FNYF6H72LB500902 | H90: 9
A91: 240229A | B91: 2019 | C91: VOLKSWAGEN | D91: GOLF | E91: 17050 | G91: 3VWW57AU0KM035463 | H91: 9
A92: 240178A | B92: 2022 | C92: VOLKSWAGEN | D92: TIGUAN | E92: 31300 | G92: 3VV8B7AX7NM005591 | H92: 8
A93: 5548P | B93: 2023 | C93: VOLKSWAGEN | D93: ATLAS | E93: 47388.75 | G93: 1V2SR2CA7PC517706 | H93: 4
A94: 240058A | B94: 2021 | C94: VOLKSWAGEN | D94: JETTA | E94: 24050 | G94: 3VW6T7BU9MM023626 | H94: 4
... A114: 5488P | B114: 2010 | C114: VOLKSWAGEN | D114: ROUTAN | E114: 11948.62 | G114: 2V4RW3DX0AR228009 | H114: 94

Sheet Inventaire_Neuf
A1: #Contrôle | B1: Année | C1: Marque | D1: Modèle | E1: 1402 | F1: 2101 | G1: NIV | H1: Jours en stock | K1: 45230 | L1: $ Inventaire | M1: $ Financé
A2: 230536 | B2: 2023 | C2: VOLKSWAGEN | D2: JETTA SEDAN | E2: 33666.97 | F2: -31504.85 | G2: 3VW2T7BU7PM053775 | H2: 142 | K2: CTRL | L2: =+SUM(E2:E9963) -> 3059537.1 | M2: =+SUM(F2:F9963) -> -2668372
A3: 240001 | B3: 2024 | C3: VOLKSWAGEN | D3: ATLAS | E3: 56706.1 | F3: -57628.2 | G3: 1V2BR2CA6RC502911 | H3: 142 | K3: Unités | L3: =COUNT(E:E) -> 71 | M3: =-M2/L2 -> 0.8721489
A4: 230574 | B4: 2023 | C4: VOLKSWAGEN | D4: JETTA SEDAN | E4: 31163.98 | F4: -32628.75 | G4: 3VWGM7BU3PM060824 | H4: 116
A5: 230581 | B5: 2023 | C5: VOLKSWAGEN | D5: TAOS | E5: 38081.07 | F5: -39936.75 | G5: 3VV4X7B27PM374246 | H5: 111
A6: 240003 | B6: 2024 | C6: VOLKSWAGEN | D6: ATLAS | E6: 50511.98 | F6: -51427.95 | G6: 1V2LR2CA2RC511786 | H6: 108 | K6: Plus de 90 jrs | L6: =SUM(E2:E12) -> 532950.79 | M6: =SUM(F2:F12) -> -378366.05
A7: 240009 | B7: 2024 | C7: VOLKSWAGEN | D7: ATLAS CROSS SPT | E7: 54659.17 | F7: -57051.75 | G7: 1V2BE2CA7RC206484 | H7: 104 | L7: 2
A8: 240011 | B8: 2024 | C8: VOLKSWAGEN | D8: ATLAS CROSS SPT | E8: 48328.17 | F8: -51136.05 | G8: 1V2LE2CA3RC208611 | H8: 97
A9: 240016 | B9: 2024 | C9: VOLKSWAGEN | D9: ATLAS CROSS SPT | E9: 57229.1 | G9: 1V2BE2CA1RC206996 | H9: 93 | K9: Plus de 180 jrs | L9: 0 | M9: 0
A10: 240022 | B10: 2024 | C10: VOLKSWAGEN | D10: ATLAS | E10: 58141.01 | G10: 1V2BR2CA4RC506228 | H10: 90 | L10: 0
A11: 240021 | B11: 2024 | C11: VOLKSWAGEN | D11: ATLAS | E11: 48171.23 | G11: 1V2LR2CA8RC516197 | H11: 90
A12: 240020 | B12: 2024 | C12: VOLKSWAGEN | D12: ATLAS CROSS SPT | E12: 56292.01 | F12: -57051.75 | G12: 1V2BE2CA5RC210341 | H12: 90
A13: 240027 | B13: 2024 | C13: VOLKSWAGEN | D13: ATLAS | E13: 56073.92 | F13: -58869.3 | G13: 1V2BR2CA1RC517137 | H13: 86
A14: 240026 | B14: 2024 | C14: VOLKSWAGEN | D14: GOLF GTI | E14: 37397 | F14: -39440.1 | G14: WVWGA7CD7RW121198 | H14: 86
A15: 240030 | B15: 2024 | C15: VOLKSWAGEN | D15: ATLAS CROSS SPT | E15: 56197.99 | F15: -58834.65 | G15: 1V2FE2CAXRC211373 | H15: 82
A16: 230639 | B16: 2023 | C16: VOLKSWAGEN | D16: TAOS | E16: 32135.51 | F16: -34034.7 | G16: 3VVEX7B23PM379190 | H16: 80
A17: 240042 | B17: 2024 | C17: VOLKSWAGEN | D17: ATLAS CROSS SPT | E17: 55950.97 | F17: -58834.65 | G17: 1V2FE2CA4RC210672 | H17: 74
A18: 240047 | B18: 2024 | C18: VOLKSWAGEN | D18: ATLAS CROSS SPT | E18: 55950.97 | F18: -58834.65 | G18: 1V2FE2CA0RC211429 | H18: 74
A19: 240045 | B19: 2024 | C19: VOLKSWAGEN | D19: JETTA SEDAN | E19: 26927 | F19: -28367.85 | G19: 3VWWM7BU5RM010702 | H19: 74
A20: 230643 | B20: 2023 | C20: VOLKSWAGEN | D20: TAOS | E20: 37610 | F20: -39461.1 | G20: 3VV4X7B2XPM382549 | H20: 73
A21: 240052 | B21: 2024 | C21: VOLKSWAGEN | D21: ATLAS CROSS SPT | E21: 55950.97 | F21: -58834.65 | G21: 1V2FE2CAXRC211504 | H21: 73
A22: 240050 | B22: 2024 | C22: VOLKSWAGEN | D22: JETTA SEDAN | E22: 29531 | F22: -31102.05 | G22: 3VWSM7BU4RM014707 | H22: 73
A23: 240070 | B23: 2024 | C23: VOLKSWAGEN | D23: ATLAS CROSS SPT | E23: 54250 | F23: -57051.75 | G23: 1V2BE2CA9RC212335 | H23: 68
... A27: 240083 | B27: 2024 | C27: VOLKSWAGEN | D27: JETTA SEDAN | E27: 32017.87 | F27: -33204.15 | G27: 3VWGM7BU7RM015582 | H27: 62
A28: 240125 | B28: 2024 | C28: VOLKSWAGEN | D28: JETTA GLI | E28: 31816.52 | G28: 3VW8T7BU7RM014696 | H28: 52
A29: 240129 | B29: 2024 | C29: VOLKSWAGEN | D29: JETTA GLI | E29: 31513 | G29: 3VW8T7BU8RM016912 | H29: 51
A30: 240137 | B30: 2024 | C30: VOLKSWAGEN | D30: ATLAS | E30: 48894 | F30: -51427.95 | G30: 1V2LR2CA9RC529461 | H30: 48
A31: 240141 | B31: 2024 | C31: VOLKSWAGEN | D31: ATLAS CROSS SPT | E31: 55948 | F31: -58834.65 | G31: 1V2FE2CA6RC216828 | H31: 48
A32: 240139 | B32: 2024 | C32: VOLKSWAGEN | D32: ATLAS CROSS SPT | E32: 54236.5 | G32: 1V2BE2CAXRC212764 | H32: 48
A33: 240138 | B33: 2024 | C33: VOLKSWAGEN | D33: TAOS | E33: 32864 | F33: -34706.7 | G33: 3VVEX7B22RM012347 | H33: 48
A34: 240147 | B34: 2024 | C34: VOLKSWAGEN | D34: ATLAS | E34: 55259.97 | F34: -58109.1 | G34: 1V2BR2CAXRC525513 | H34: 47
A35: 240156 | B35: 2024 | C35: VOLKSWAGEN | D35: ATLAS CROSS SPT | E35: 53794.97 | F35: -56570.85 | G35: 1V2BE2CA8RC216649 | H35: 45
A36: 240171 | B36: 2024 | C36: VOLKSWAGEN | D36: JETTA SEDAN | E36: 28629 | G36: 3VWEM7BU2RM001760 | H36: 44
A37: 240173 | B37: 2024 | C37: VOLKSWAGEN | D37: ATLAS | E37: 54801.97 | F37: -57628.2 | G37: 1V2BR2CA7RC532368 | H37: 41
A38: 240190 | B38: 2024 | C38: VOLKSWAGEN | D38: ATLAS | E38: 58249.97 | G38: 1V2FR2CA7RC531156 | H38: 38
A39: 240197 | B39: 2024 | C39: VOLKSWAGEN | D39: TIGUAN | E39: 45175.95 | F39: -47526.15 | G39: 3VV4B7AX2RM023873 | H39: 37
A40: 240203 | B40: 2024 | C40: VOLKSWAGEN | D40: TIGUAN | E40: 44101 | F40: -46474.05 | G40: 3VV4B7AX6RM025190 | H40: 34
A41: 240207 | B41: 2024 | C41: VOLKSWAGEN | D41: ATLAS | E41: 54806.97 | F41: -57628.2 | G41: 1V2BR2CA4RC531890 | H41: 33
A42: 240206 | B42: 2024 | C42: VOLKSWAGEN | D42: TAOS | E42: 38195 | F42: -40225.5 | G42: 3VV4X7B25RM012063 | H42: 33
A43: 240212 | B43: 2024 | C43: VOLKSWAGEN | D43: ATLAS CROSS SPT | E43: 56348.1 | F43: -58834.65 | G43: 1V2FE2CA5RC219798 | H43: 30
A44: 240213 | B44: 2024 | C44: VOLKSWAGEN | D44: TIGUAN | E44: 45762.95 | G44: 3VV4B7AX1RM023721 | H44: 30
A45: 240221 | B45: 2024 | C45: VOLKSWAGEN | D45: TAOS | E45: 37908 | F45: -39749.85 | G45: 3VV4X7B20RM013248 | H45: 25
A46: 240220 | B46: 2024 | C46: VOLKSWAGEN | D46: TAOS | E46: 32705 | F46: -34423.2 | G46: 3VVEX7B2XRM013066 | H46: 25
A47: 240223 | B47: 2024 | C47: VOLKSWAGEN | D47: TAOS | E47: 32705 | F47: -34423.2 | G47: 3VVEX7B25RM012259 | H47: 25
A48: 240219 | B48: 2024 | C48: VOLKSWAGEN | D48: TAOS | E48: 32700 | F48: -34423.2 | G48: 3VVEX7B20RM012928 | H48: 25
A49: 240232 | B49: 2024 | C49: VOLKSWAGEN | D49: TAOS | E49: 35661.95 | G49: 3VVVX7B23RM011742 | H49: 20
A50: 240230 | B50: 2024 | C50: VOLKSWAGEN | D50: TIGUAN | E50: 44107 | F50: -46474.05 | G50: 3VV4B7AX4RM047169 | H50: 20
A51: 240238 | B51: 2024 | C51: VOLKSWAGEN | D51: TAOS | E51: 37441.5 | G51: 3VV4X7B26RM014615 | H51: 16
A52: 240248 | B52: 2024 | C52: VOLKSWAGEN | D52: GOLF GTI | E52: 38207 | F52: -40179.3 | G52: WVWRA7CD4RW133320 | H52: 13
A53: 240241 | B53: 2024 | C53: VOLKSWAGEN | D53: TAOS | E53: 37773 | F53: -39749.85 | G53: 3VV4X7B2XRM023463 | H53: 13
A54: 240243 | B54: 2024 | C54: VOLKSWAGEN | D54: TAOS | E54: 37109 | F54: -39552.45 | G54: 3VV4X7B23RM025278 | H54: 13
A55: 240242 | B55: 2024 | C55: VOLKSWAGEN | D55: TAOS | E55: 34270 | F55: -36066.45 | G55: 3VVUX7B20RM026050 | H55: 13
A56: 240259 | B56: 2024 | C56: VOLKSWAGEN | D56: GOLF GTI | E56: 39384 | F56: -41836.2 | G56: WVWWA7CD4RW139864 | H56: 12
A57: 240256 | B57: 2024 | C57: VOLKSWAGEN | D57: GOLF R | E57: 49697 | F57: -52243.8 | G57: WVWEB7CD9RW139691 | H57: 12
A58: 240257 | B58: 2024 | C58: VOLKSWAGEN | D58: GOLF R | E58: 49697 | F58: -52243.8 | G58: WVWEB7CD9RW140162 | H58: 12
A59: 240255 | B59: 2024 | C59: VOLKSWAGEN | D59: TAOS | E59: 35568 | F59: -37434.6 | G59: 3VVVX7B24RM026699 | H59: 12
A60: 240254 | B60: 2024 | C60: VOLKSWAGEN | D60: TAOS | E60: 34265 | F60: -36066.45 | G60: 3VVUX7B25RM026254 | H60: 12
A61: 240250 | B61: 2024 | C61: VOLKSWAGEN | D61: TAOS | E61: 28211 | G61: 3VVCX7B23RM011327 | H61: 12
A62: 240253 | B62: 2024 | C62: VOLKSWAGEN | D62: TIGUAN | E62: 47482.92 | F62: -47526.15 | G62: 3VV4B7AX0RM043880 | H62: 12
A63: 240262 | B63: 2024 | C63: VOLKSWAGEN | D63: TIGUAN | E63: 40734 | F63: -43358.7 | G63: 3VV8B7AX4RM058738 | H63: 9
A64: 240266 | B64: 2024 | C64: VOLKSWAGEN | D64: GOLF GTI | E64: 37806 | F64: -40179.3 | G64: WVWRA7CD7RW142545 | H64: 3
A65: 240270 | B65: 2024 | C65: VOLKSWAGEN | D65: TIGUAN | E65: 44886 | F65: -47718.3 | G65: 3VV4B7AXXRM065708 | H65: 3
A66: 240263 | B66: 2024 | C66: VOLKSWAGEN | D66: TIGUAN | E66: 44154 | F66: -46949.7 | G66: 3VV4B7AXXRM047399 | H66: 3
A67: 240268 | B67: 2024 | C67: VOLKSWAGEN | D67: TIGUAN | E67: 44154 | F67: -46949.7 | G67: 3VV4B7AX3RM061712 | H67: 3
A68: 240264 | B68: 2024 | C68: VOLKSWAGEN | D68: TIGUAN | E68: 43701 | F68: -46474.05 | G68: 3VV4B7AX7RM058599 | H68: 3
A69: 240267 | B69: 2024 | C69: VOLKSWAGEN | D69: TIGUAN | E69: 43701 | F69: -46474.05 | G69: 3VV4B7AX9RM059415 | H69: 3
A70: 240269 | B70: 2024 | C70: VOLKSWAGEN | D70: TIGUAN | E70: 40734 | F70: -43358.7 | G70: 3VV8B7AX7RM066865 | H70: 3
A71: 240265 | B71: 2024 | C71: VOLKSWAGEN | D71: TIGUAN | E71: 39069 | F71: -41610.45 | G71: 3VVMB7AX2RM024991 | H71: 3
A72: 240273 | B72: 2024 | C72: VOLKSWAGEN | D72: TIGUAN | E72: 44154 | F72: -46949.7 | G72: 3VV4B7AX9RM059835 | H72: 2

Sheet Print_Mois
C1: =Parametres!B1 -> Volks | K1: Véhicules neufs | S1: =CONCATENATE("Réalisé,"," ",Parametres!B3," ",Parametres!B4) -> Réalisé, Juillet 2025
D2: X | E2: O | F2: U | J2: NB | L2: $ | O2: X | P2: O | Q2: U | V2: *** NE PAS EFFACER / Pour An Précédente ***
D3: BUDGET ORIGINAL | J3: RÉALISATION | M3: ÉCART réel / Budget | O3: ANNÉE PRÉCÉDENTE | R3: ECART (réel/ Ann.Préc.) | V3: NEUF | W3: 0.45
D4: UNITE | E4: $P/UNITÉ | F4: $PROFITS | J4: UNITÉS | K4: $P/UNITE | L4: $PROFITS | M4: UNITÉS | N4: $PROFITS | O4: UNITE | P4: $P/UNITÉ | Q4: $PROFITS | R4: UNITÉS | S4: $PROFITS | V4: USAGE | W4: 0.1
A5: Véhicules neufsVentes nettes | B5: Véhicules neufs | C5: Ventes nettes | F5: =+INDEX('Budget original'!$A$2:$AO$501,MATCH($A5,'Budget original'!$A$2:$A$501,0),MATCH(F$2,'Budget original'!$A$2:$AO$2,0)) -> 3782098.2 | L5: =-SUMIFS(BV_Data_An_Cour!$O:$O,BV_Data_An_Cour!$X:$X,"Oui",BV_Data_An_Cour!$U:$U,$B5) -> 4089468.3 | Q5: {=+INDEX('Réel 2024'!$A$2:$AO$501,MATCH($A5,'Réel 2024'!$A$2:$A$501,0),MATCH(Q$2,'Réel 2024'!$A$2:$AO$2,0))} -> 4524162.1 | V5: SERVICE | W5: 0.225
A6: Véhicules neufsAutos détail | B6: Véhicules neufs | C6: Autos détail | D6: =+INDEX('Budget original'!$A$2:$AO$501,MATCH($A6,'Budget original'!$A$2:$A$501,0),MATCH(D$2,'Budget original'!$A$2:$AO$2,0)) -> 19 | E6: =IF(D6=0,0,F6/D6) -> 1953.6492 | F6: =+INDEX('Budget original'!$A$2:$AO$501,MATCH($A6,'Budget original'!$A$2:$A$501,0),MATCH(F$2,'Budget original'!$A$2:$AO$2,0)) -> 37119.334 | J6: =-SUMIFS(BV_Data_An_Cour!$O:$O,BV_Data_An_Cour!$U:$U,$B6,BV_Data_An_Cour!$V:$V,$C6,BV_Data_An_Cour!$W:$W,J$2) -> 13 | K6: =IF(J6=0,0,L6/J6) -> 1905.2108 | L6: =-SUMIFS(BV_Data_An_Cour!$O:$O,BV_Data_An_Cour!$U:$U,$B6,BV_Data_An_Cour!$V:$V,$C6,BV_Data_An_Cour!$W:$W,L$2) -> 24767.74 | M6: =J6-D6 -> -6 | N6: =L6-F6 -> -12351.594 | O6: =+INDEX('Réel 2024'!$A$2:$AO$501,MATCH($A6,'Réel 2024'!$A$2:$A$501,0),MATCH(O$2,'Réel 2024'!$A$2:$AO$2,0)) -> 23 | P6: =IF(O6=0,0,Q6/O6) -> 1942.4757 | Q6: {=+INDEX('Réel 2024'!$A$2:$AO$501,MATCH($A6,'Réel 2024'!$A$2:$A$501,0),MATCH(Q$2,'Réel 2024'!$A$2:$AO$2,0))} -> 44676.94 | R6: =J6-O6 -> -10 | S6: =L6-Q6 -> -19909.2 | V6: CARROSSERIE | W6: 0.025
A7: Véhicules neufsCamions détail | B7: Véhicules neufs | C7: Camions détail | D7: =+INDEX('Budget original'!$A$2:$AO$501,MATCH($A7,'Budget original'!$A$2:$A$501,0),MATCH(D$2,'Budget original'!$A$2:$AO$2,0)) -> 50 | E7: =IF(D7=0,0,F7/D7) -> 2435.9047 | F7: =+INDEX('Budget original'!$A$2:$AO$501,MATCH($A7,'Budget original'!$A$2:$A$501,0),MATCH(F$2,'Budget original'!$A$2:$AO$2,0)) -> 121795.23 | J7: =-SUMIFS(BV_Data_An_Cour!$O:$O,BV_Data_An_Cour!$U:$U,$B7,BV_Data_An_Cour!$V:$V,$C7,BV_Data_An_Cour!$W:$W,J$2) -> 63 | K7: =IF(J7=0,0,L7/J7) -> 2276.0851 | L7: =-SUMIFS(BV_Data_An_Cour!$O:$O,BV_Data_An_Cour!$U:$U,$B7,BV_Data_An_Cour!$V:$V,$C7,BV_Data_An_Cour!$W:$W,L$2) -> 143393.36 | M7: =J7-D7 -> 13 | N7: =L7-F7 -> 21598.126 | O7: {=+INDEX('Réel 2024'!$A$2:$AO$501,MATCH($A7,'Réel 2024'!$A$2:$A$501,0),MATCH(O$2,'Réel 2024'!$A$2:$AO$2,0))} -> 54 | P7: =IF(O7=0,0,Q7/O7) -> 2267.4683 | Q7: {=+INDEX('Réel 2024'!$A$2:$AO$501,MATCH($A7,'Réel 2024'!$A$2:$A$501,0),MATCH(Q$2,'Réel 2024'!$A$2:$AO$2,0))} -> 122443.29 | R7: =J7-O7 -> 9 | S7: =L7-Q7 -> 20950.07 | V7: PIECES | W7: 0.2
A8: Véhicules neufsSprinter | B8: Véhicules neufs | C8: Sprinter | D8: =+INDEX('Budget original'!$A$2:$AO$501,MATCH($A8,'Budget original'!$A$2:$A$501,0),MATCH(D$2,'Budget original'!$A$2:$AO$2,0)) -> 0 | E8: =IF(D8=0,0,F8/D8) -> 0 | F8: =+INDEX('Budget original'!$A$2:$AO$501,MATCH($A8,'Budget original'!$A$2:$A$501,0),MATCH(F$2,'Budget original'!$A$2:$AO$2,0)) -> 0 | J8: =-SUMIFS(BV_Data_An_Cour!$O:$O,BV_Data_An_Cour!$U:$U,$B8,BV_Data_An_Cour!$V:$V,$C8,BV_Data_An_Cour!$W:$W,J$2) -> 0 | K8: =IF(J8=0,0,L8/J8) -> 0 | L8: =-SUMIFS(BV_Data_An_Cour!$O:$O,BV_Data_An_Cour!$U:$U,$B8,BV_Data_An_Cour!$V:$V,$C8,BV_Data_An_Cour!$W:$W,L$2) -> 0 | M8: =J8-D8 -> 0 | N8: =L8-F8 -> 0 | O8: {=+INDEX('Réel 2024'!$A$2:$AO$501,MATCH($A8,'Réel 2024'!$A$2:$A$501,0),MATCH(O$2,'Réel 2024'!$A$2:$AO$2,0))} -> 0 | P8: =IF(O8=0,0,Q8/O8) -> 0 | Q8: {=+INDEX('Réel 2024'!$A$2:$AO$501,MATCH($A8,'Réel 2024'!$A$2:$A$501,0),MATCH(Q$2,'Réel 2024'!$A$2:$AO$2,0))} -> 0 | R8: =J8-O8 -> 0 | S8: =L8-Q8 -> 0 | W8: =SUM(W3:W7) -> 1
A9: Véhicules neufsMoto détail | B9: Véhicules neufs | C9: Moto détail | D9: =+INDEX('Budget original'!$A$2:$AO$501,MATCH($A9,'Budget original'!$A$2:$A$501,0),MATCH(D$2,'Budget original'!$A$2:$AO$2,0)) -> 0 | E9: =IF(D9=0,0,F9/D9) -> 0 | F9: =+INDEX('Budget original'!$A$2:$AO$501,MATCH($A9,'Budget original'!$A$2:$A$501,0),MATCH(F$2,'Budget original'!$A$2:$AO$2,0)) -> 0 | J9: =-SUMIFS(BV_Data_An_Cour!$O:$O,BV_Data_An_Cour!$U:$U,$B9,BV_Data_An_Cour!$V:$V,$C9,BV_Data_An_Cour!$W:$W,J$2) -> 0 | K9: =IF(J9=0,0,L9/J9) -> 0 | L9: =-SUMIFS(BV_Data_An_Cour!$O:$O,BV_Data_An_Cour!$U:$U,$B9,BV_Data_An_Cour!$V:$V,$C9,BV_Data_An_Cour!$W:$W,L$2) -> 0 | M9: =J9-D9 -> 0 | N9: =L9-F9 -> 0 | O9: {=+INDEX('Réel 2024'!$A$2:$AO$501,MATCH($A9,'Réel 2024'!$A$2:$A$501,0),MATCH(O$2,'Réel 2024'!$A$2:$AO$2,0))} -> 0 | P9: =IF(O9=0,0,Q9/O9) -> 0 | Q9: {=+INDEX('Réel 2024'!$A$2:$AO$501,MATCH($A9,'Réel 2024'!$A$2:$A$501,0),MATCH(Q$2,'Réel 2024'!$A$2:$AO$2,0))} -> 0 | R9: =J9-O9 -> 0 | S9: =L9-Q9 -> 0
A10: Véhicules neufs[...] | B10: Véhicules neufs | C10: [...] | D10: =+INDEX('Budget original'!$A$2:$AO$501,MATCH($A10,'Budget original'!$A$2:$A$501,0),MATCH(D$2,'Budget original'!$A$2:$AO$2,0)) -> 0 | E10: =IF(D10=0,0,F10/D10) -> 0 | F10: =+INDEX('Budget original'!$A$2:$AO$501,MATCH($A10,'Budget original'!$A$2:$A$501,0),MATCH(F$2,'Budget original'!$A$2:$AO$2,0)) -> 0 | J10: =-SUMIFS(BV_Data_An_Cour!$O:$O,BV_Data_An_Cour!$U:$U,$B10,BV_Data_An_Cour!$V:$V,$C10,BV_Data_An_Cour!$W:$W,J$2) -> 0 | K10: =IF(J10=0,0,L10/J10) -> 0 | L10: =-SUMIFS(BV_Data_An_Cour!$O:$O,BV_Data_An_Cour!$U:$U,$B10,BV_Data_An_Cour!$V:$V,$C10,BV_Data_An_Cour!$W:$W,L$2) -> 0 | M10: =J10-D10 -> 0 | N10: =L10-F10 -> 0 | O10: {=+INDEX('Réel 2024'!$A$2:$AO$501,MATCH($A10,'Réel 2024'!$A$2:$A$501,0),MATCH(O$2,'Réel 2024'!$A$2:$AO$2,0))} -> 0 | P10: =IF(O10=0,0,Q10/O10) -> 0 | Q10: {=+INDEX('Réel 2024'!$A$2:$AO$501,MATCH($A10,'Réel 2024'!$A$2:$A$501,0),MATCH(Q$2,'Réel 2024'!$A$2:$AO$2,0))} -> 0 | R10: =J10-O10 -> 0 | S10: =L10-Q10 -> 0
A11: Véhicules neufs[...] | B11: Véhicules neufs | C11: [...] | D11: =+INDEX('Budget original'!$A$2:$AO$501,MATCH($A11,'Budget original'!$A$2:$A$501,0),MATCH(D$2,'Budget original'!$A$2:$AO$2,0)) -> 0 | E11: =IF(D11=0,0,F11/D11) -> 0 | F11: =+INDEX('Budget original'!$A$2:$AO$501,MATCH($A11,'Budget original'!$A$2:$A$501,0),MATCH(F$2,'Budget original'!$A$2:$AO$2,0)) -> 0 | J11: =-SUMIFS(BV_Data_An_Cour!$O:$O,BV_Data_An_Cour!$U:$U,$B11,BV_Data_An_Cour!$V:$V,$C11,BV_Data_An_Cour!$W:$W,J$2) -> 0 | K11: =IF(J11=0,0,L11/J11) -> 0 | L11: =-SUMIFS(BV_Data_An_Cour!$O:$O,BV_Data_An_Cour!$U:$U,$B11,BV_Data_An_Cour!$V:$V,$C11,BV_Data_An_Cour!$W:$W,L$2) -> 0 | M11: =J11-D11 -> 0 | N11: =L11-F11 -> 0 | O11: {=+INDEX('Réel 2024'!$A$2:$AO$501,MATCH($A11,'Réel 2024'!$A$2:$A$501,0),MATCH(O$2,'Réel 2024'!$A$2:$AO$2,0))} -> 0 | P11: =IF(O11=0,0,Q11/O11) -> 0 | Q11: {=+INDEX('Réel 2024'!$A$2:$AO$501,MATCH($A11,'Réel 2024'!$A$2:$A$501,0),MATCH(Q$2,'Réel 2024'!$A$2:$AO$2,0))} -> 0 | R11: =J11-O11 -> 0 | S11: =L11-Q11 -> 0
A12: Véhicules neufs[...] | B12: Véhicules neufs | C12: [...] | D12: =+INDEX('Budget original'!$A$2:$AO$501,MATCH($A12,'Budget original'!$A$2:$A$501,0),MATCH(D$2,'Budget original'!$A$2:$AO$2,0)) -> 0 | E12: =IF(D12=0,0,F12/D12) -> 0 | F12: =+INDEX('Budget original'!$A$2:$AO$501,MATCH($A12,'Budget original'!$A$2:$A$501,0),MATCH(F$2,'Budget original'!$A$2:$AO$2,0)) -> 0 | J12: =-SUMIFS(BV_Data_An_Cour!$O:$O,BV_Data_An_Cour!$U:$U,$B12,BV_Data_An_Cour!$V:$V,$C12,BV_Data_An_Cour!$W:$W,J$2) -> 0 | K12: =IF(J12=0,0,L12/J12) -> 0 | L12: =-SUMIFS(BV_Data_An_Cour!$O:$O,BV_Data_An_Cour!$U:$U,$B12,BV_Data_An_Cour!$V:$V,$C12,BV_Data_An_Cour!$W:$W,L$2) -> 0 | M12: =J12-D12 -> 0 | N12: =L12-F12 -> 0 | O12: {=+INDEX('Réel 2024'!$A$2:$AO$501,MATCH($A12,'Réel 2024'!$A$2:$A$501,0),MATCH(O$2,'Réel 2024'!$A$2:$AO$2,0))} -> 0 | P12: =IF(O12=0,0,Q12/O12) -> 0 | Q12: {=+INDEX('Réel 2024'!$A$2:$AO$501,MATCH($A12,'Réel 2024'!$A$2:$A$501,0),MATCH(Q$2,'Réel 2024'!$A$2:$AO$2,0))} -> 0 | R12: =J12-O12 -> 0 | S12: =L12-Q12 -> 0
A13: Véhicules neufsTotal Neufs | B13: Véhicules neufs | C13: Total Neufs | D13: =+SUM(D6:D12) -> 69 | E13: =IF(D13<=0,0,F13/D13) -> 2303.1097 | F13: =+SUM(F6:F12) -> 158914.57 | J13: =+SUM(J6:J12) -> 76 | K13: =IF(J13<=0,0,L13/J13) -> 2212.6461 | L13: =+SUM(L6:L12) -> 168161.1 | M13: =+SUM(M6:M12) -> 7 | N13: =+SUM(N6:N12) -> 9246.5319 | O13: =+SUM(O6:O12) -> 77 | P13: =IF(O13<=0,0,Q13/O13) -> 2170.3926 | Q13: =+SUM(Q6:Q12) -> 167120.23 | R13: =+SUM(R6:R12) -> -1 | S13: =+SUM(S6:S12) -> 1040.87
A14: Véhicules neufs | B14: Véhicules neufs | M14: =IF(D13=0,0,M13/D13) -> 0.10144928 | N14: =IF(F13=0,0,N13/F13) -> 0.058185552 | R14: =R13/O13 -> -0.012987013 | S14: =IF(Q13=0,0,(S13/Q13)) -> 0.0062282705 | AD14: 20 | AE14: 1000 | AF14: =AD14*AE14 -> 20000
A15: Véhicules neufsEx-Démos et courtoisies | B15: Véhicules neufs | C15: Ex-Démos et courtoisies | D15: =+INDEX('Budget original'!$A$2:$AO$501,MATCH($A15,'Budget original'!$A$2:$A$501,0),MATCH(D$2,'Budget original'!$A$2:$AO$2,0)) -> 4 | E15: =IF(D15=0,0,F15/D15) -> 1534.7521 | F15: =+INDEX('Budget original'!$A$2:$AO$501,MATCH($A15,'Budget original'!$A$2:$A$501,0),MATCH(F$2,'Budget original'!$A$2:$AO$2,0)) -> 6139.0086 | J15: =-SUMIFS(BV_Data_An_Cour!$O:$O,BV_Data_An_Cour!$U:$U,$B15,BV_Data_An_Cour!$V:$V,$C15,BV_Data_An_Cour!$W:$W,J$2) -> 5 | K15: =IF(J15=0,0,L15/J15) -> 1374.508 | L15: =-SUMIFS(BV_Data_An_Cour!$O:$O,BV_Data_An_Cour!$U:$U,$B15,BV_Data_An_Cour!$V:$V,$C15,BV_Data_An_Cour!$W:$W,L$2) -> 6872.54 | M15: =J15-D15 -> 1 | N15: =L15-F15 -> 733.53143 | O15: {=+INDEX('Réel 2024'!$A$2:$AO$501,MATCH($A15,'Réel 2024'!$A$2:$A$501,0),MATCH(O$2,'Réel 2024'!$A$2:$AO$2,0))} -> 3 | P15: =IF(O15=0,0,Q15/O15) -> 913.29 | Q15: {=+INDEX('Réel 2024'!$A$2:$AO$501,MATCH($A15,'Réel 2024'!$A$2:$A$501,0),MATCH(Q$2,'Réel 2024'!$A$2:$AO$2,0))} -> 2739.87 | R15: =J15-O15 -> 2 | S15: =L15-Q15 -> 4132.67 | AD15: 25 | AE15: =AF15/AD15 -> 800 | AF15: =AF14 -> 20000
A16: Véhicules neufs | B16: Véhicules neufs
A17: Véhicules neufsFlottes | B17: Véhicules neufs | C17: Flottes | D17: =+INDEX('Budget original'!$A$2:$AO$501,MATCH($A17,'Budget original'!$A$2:$A$501,0),MATCH(D$2,'Budget original'!$A$2:$AO$2,0)) -> 2 | E17: =IF(D17=0,0,F17/D17) -> 2393.8521 | F17: =+INDEX('Budget original'!$A$2:$AO$501,MATCH($A17,'Budget original'!$A$2:$A$501,0),MATCH(F$2,'Budget original'!$A$2:$AO$2,0)) -> 4787.7042 | J17: =-SUMIFS(BV_Data_An_Cour!$O:$O,BV_Data_An_Cour!$U:$U,$B17,BV_Data_An_Cour!$V:$V,$C17,BV_Data_An_Cour!$W:$W,J$2) -> 0 | K17: =IF(J17=0,0,L17/J17) -> 0 | L17: =-SUMIFS(BV_Data_An_Cour!$O:$O,BV_Data_An_Cour!$U:$U,$B17,BV_Data_An_Cour!$V:$V,$C17,BV_Data_An_Cour!$W:$W,L$2) -> 0 | M17: =J17-D17 -> -2 | N17: =L17-F17 -> -4787.7042 | O17: {=+INDEX('Réel 2024'!$A$2:$AO$501,MATCH($A17,'Réel 2024'!$A$2:$A$501,0),MATCH(O$2,'Réel 2024'!$A$2:$AO$2,0))} -> 5 | P17: =IF(O17=0,0,Q17/O17) -> 2550.916 | Q17: {=+INDEX('Réel 2024'!$A$2:$AO$501,MATCH($A17,'Réel 2024'!$A$2:$A$501,0),MATCH(Q$2,'Réel 2024'!$A$2:$AO$2,0))} -> 12754.58 | R17: =J17-O17 -> -5 | S17: =L17-Q17 -> -12754.58
A18: Véhicules neufs | B18: Véhicules neufs
A19: Véhicules neufsRachat bail | B19: Véhicules neufs | C19: Rachat bail | D19: =+INDEX('Budget original'!$A$2:$AO$501,MATCH($A19,'Budget original'!$A$2:$A$501,0),MATCH(D$2,'Budget original'!$A$2:$AO$2,0)) -> 0 | E19: =IF(D19=0,0,F19/D19) -> 0 | F19: =+INDEX('Budget original'!$A$2:$AO$501,MATCH($A19,'Budget original'!$A$2:$A$501,0),MATCH(F$2,'Budget original'!$A$2:$AO$2,0)) -> 7650 | L19: =-SUMIFS(BV_Data_An_Cour!$O:$O,BV_Data_An_Cour!$U:$U,$B19,BV_Data_An_Cour!$V:$V,$C19,BV_Data_An_Cour!$W:$W,L$2) -> 12602.35 | N19: =L19-F19 -> 4952.35 | Q19: {=+INDEX('Réel 2024'!$A$2:$AO$501,MATCH($A19,'Réel 2024'!$A$2:$A$501,0),MATCH(Q$2,'Réel 2024'!$A$2:$AO$2,0))} -> 10000 | R19: =O19-K19 -> 0 | S19: =L19-Q19 -> 2602.35
A20: Véhicules neufs | B20: Véhicules neufs
A21: Véhicules neufsRev. Finances | B21: Véhicules neufs | C21: Rev. Finances | D21: =+INDEX('Budget original'!$A$2:$AO$501,MATCH($A21,'Budget original'!$A$2:$A$501,0),MATCH(D$2,'Budget original'!$A$2:$AO$2,0)) -> 0 | E21: =IF(D21=0,0,F21/D21) -> 0 | F21: =+INDEX('Budget original'!$A$2:$AO$501,MATCH($A21,'Budget original'!$A$2:$A$501,0),MATCH(F$2,'Budget original'!$A$2:$AO$2,0)) -> 3650 | K21: =IF(J13=0,0,L21/(J13+J15)) -> 7.4635802 | L21: =-SUMIFS(BV_Data_An_Cour!$O:$O,BV_Data_An_Cour!$U:$U,$B21,BV_Data_An_Cour!$V:$V,$C21,BV_Data_An_Cour!$W:$W,L$2) -> 604.55 | N21: =L21-F21 -> -3045.45 | Q21: {=+INDEX('Réel 2024'!$A$2:$AO$501,MATCH($A21,'Réel 2024'!$A$2:$A$501,0),MATCH(Q$2,'Réel 2024'!$A$2:$AO$2,0))} -> 0 | R21: =O21-K21 -> -7.4635802 | S21: =L21-Q21 -> 604.55
A22: Véhicules neufsRev. Protections | B22: Véhicules neufs | C22: Rev. Protections | D22: =+INDEX('Budget original'!$A$2:$AO$501,MATCH($A22,'Budget original'!$A$2:$A$501,0),MATCH(D$2,'Budget original'!$A$2:$AO$2,0)) -> 0 | E22: =IF(D22=0,0,F22/D22) -> 0 | F22: =+INDEX('Budget original'!$A$2:$AO$501,MATCH($A22,'Budget original'!$A$2:$A$501,0),MATCH(F$2,'Budget original'!$A$2:$AO$2,0)) -> 67890 | K22: =IF(J13=0,0,L22/(J13+J15)) -> 985.36333 | L22: =-SUMIFS(BV_Data_An_Cour!$O:$O,BV_Data_An_Cour!$U:$U,$B22,BV_Data_An_Cour!$V:$V,$C22,BV_Data_An_Cour!$W:$W,L$2) -> 79814.43 | N22: =L22-F22 -> 11924.43 | Q22: {=+INDEX('Réel 2024'!$A$2:$AO$501,MATCH($A22,'Réel 2024'!$A$2:$A$501,0),MATCH(Q$2,'Réel 2024'!$A$2:$AO$2,0))} -> 60986.88 | R22: =O22-K22 -> -985.36333 | S22: =L22-Q22 -> 18827.55
A23: Véhicules neufsRev. Autres | B23: Véhicules neufs | C23: Rev. Autres | D23: =+INDEX('Budget original'!$A$2:$AO$501,MATCH($A23,'Budget original'!$A$2:$A$501,0),MATCH(D$2,'Budget original'!$A$2:$AO$2,0)) -> 0 | E23: =IF(D23=0,0,F23/D23) -> 0 | F23: =+INDEX('Budget original'!$A$2:$AO$501,MATCH($A23,'Budget original'!$A$2:$A$501,0),MATCH(F$2,'Budget original'!$A$2:$AO$2,0)) -> 1460 | K23: =IF(J13=0,0,L23/(J13+J15)) -> 2.302963 | L23: =-SUMIFS(BV_Data_An_Cour!$O:$O,BV_Data_An_Cour!$U:$U,$B23,BV_Data_An_Cour!$V:$V,$C23,BV_Data_An_Cour!$W:$W,L$2) -> 186.54 | N23: =L23-F23 -> -1273.46 | Q23: {=+INDEX('Réel 2024'!$A$2:$AO$501,MATCH($A23,'Réel 2024'!$A$2:$A$501,0),MATCH(Q$2,'Réel 2024'!$A$2:$AO$2,0))} -> 569.82 | R23: =O23-K23 -> -2.302963 | S23: =L23-Q23 -> -383.28
A24: Véhicules neufsTotal F&I | B24: Véhicules neufs | C24: Total F&I | D24: =+D15+D13 -> 73 | E24: =IF(D24<=0,0,F24/D24) -> 1000 | F24: =F21+F22+F23 -> 73000 | J24: =+J15+J13 -> 81 | K24: =IF(J24<=0,0,L24/J24) -> 995.12988 | L24: =L21+L22+L23 -> 80605.52 | M24: =J24-D24 -> 8 | N24: =L24-F24 -> 7605.52 | O24: =+O15+O13 -> 80 | P24: =IF(O24<=0,0,Q24/O24) -> 769.45875 | Q24: =Q21+Q22+Q23 -> 61556.7 | S24: =L24-Q24 -> 19048.82
A25: Véhicules neufs | B25: Véhicules neufs | N25: =IF(N24=0,0,N24/F24) -> 0.10418521 | S25: =IF(Q24=0,0,(S24/Q24)) -> 0.30945161
A26: Véhicules neufs | B26: Véhicules neufs
A27: Véhicules neufsTotal Dépt. Neufs | B27: Véhicules neufs | C27: Total Dépt. Neufs | D27: =+D13+D15+D17 -> 75 | E27: =IF(D27<=0,0,F27/D27) -> 3339.8837 | F27: =F13+F17+F24+F19+F15 -> 250491.28 | J27: =+J13+J15+J17 -> 81 | K27: =IF(J27<=0,0,L27/J27) -> 3311.6236 | L27: =L13+L17+L24+L19+L15 -> 268241.51 | M27: =J27-D27 -> 6 | N27: =L27-F27 -> 17750.229 | O27: =+O13+O15+O17 -> 85 | P27: =IF(O27<=0,0,Q27/O27) -> 2990.2515 | Q27: =Q13+Q17+Q24+Q19+Q15 -> 254171.38 | R27: =J27-O27 -> -4 | S27: =L27-Q27 -> 14070.13
A28: Véhicules neufs | B28: Véhicules neufs | L28: =L27/F27 -> 1.0708617 | M28: =M27/D27 -> 0.08 | N28: =N27/F27 -> 0.070861665 | R28: =R27/O27 -> -0.047058824 | S28: =IF(Q27=0,0,S27/Q27) -> 0.055356862
A29: Véhicules neufs | B29: Véhicules neufs
A30: Véhicules neufsDEPENSES | B30: Véhicules neufs | C30: DEPENSES
A31: Véhicules neufsComm. vendeurs | B31: Véhicules neufs | C31: Comm. vendeurs | D31: =F31/(F13+F15) -> 0.32512204 | E31: =F31/D$24 -> 735.1035 | F31: =+INDEX('Budget original'!$A$2:$AO$501,MATCH($A31,'Budget original'!$A$2:$A$501,0),MATCH(F$2,'Budget original'!$A$2:$AO$2,0)) -> 53662.555 | J31: =L31/(L15+L13+L17) -> 0.29871778 | K31: =IF(L31=0,0,L31/J$24) -> 645.50198 | L31: =SUMIFS(BV_Data_An_Cour!$O:$O,BV_Data_An_Cour!$U:$U,$B31,BV_Data_An_Cour!$V:$V,$C31,BV_Data_An_Cour!$W:$W,L$2) -> 52285.66 | N31: =L31-F31 -> -1376.8954 | O31: =Q31/(Q13+Q15+Q17) -> 0.31203959 | P31: =Q31/O$24 -> 712.28763 | Q31: {=+INDEX('Réel 2024'!$A$2:$AO$501,MATCH($A31,'Réel 2024'!$A$2:$A$501,0),MATCH(Q$2,'Réel 2024'!$A$2:$AO$2,0))} -> 56983.01 | S31: =L31-Q31 -> -4697.35
A32: Véhicules neufsComm. F&I | B32: Véhicules neufs | C32: Comm. F&I | D32: =F32/F24 -> 0.28 | E32: =F32/D$24 -> 280 | F32: =+INDEX('Budget original'!$A$2:$AO$501,MATCH($A32,'Budget original'!$A$2:$A$501,0),MATCH(F$2,'Budget original'!$A$2:$AO$2,0)) -> 20440 | J32: =L32/L24 -> 0.25000198 | K32: =IF(L32=0,0,L32/J$24) -> 248.78444 | L32: =SUMIFS(BV_Data_An_Cour!$O:$O,BV_Data_An_Cour!$U:$U,$B32,BV_Data_An_Cour!$V:$V,$C32,BV_Data_An_Cour!$W:$W,L$2) -> 20151.54 | N32: =L32-F32 -> -288.46 | O32: =Q32/Q24 -> 0.26999709 | P32: =Q32/O$24 -> 207.75163 | Q32: {=+INDEX('Réel 2024'!$A$2:$AO$501,MATCH($A32,'Réel 2024'!$A$2:$A$501,0),MATCH(Q$2,'Réel 2024'!$A$2:$AO$2,0))} -> 16620.13 | S32: =L32-Q32 -> 3531.41
A33: Véhicules neufsFrais de livraison | B33: Véhicules neufs | C33: Frais de livraison | E33: =F33/D$24 -> 115 | F33: =+INDEX('Budget original'!$A$2:$AO$501,MATCH($A33,'Budget original'!$A$2:$A$501,0),MATCH(F$2,'Budget original'!$A$2:$AO$2,0)) -> 8395 | K33: =IF(L33=0,0,L33/J$24) -> 112.60815 | L33: =SUMIFS(BV_Data_An_Cour!$O:$O,BV_Data_An_Cour!$U:$U,$B33,BV_Data_An_Cour!$V:$V,$C33,BV_Data_An_Cour!$W:$W,L$2) -> 9121.26 | N33: =L33-F33 -> 726.26 | P33: =Q33/O$24 -> 95.093 | Q33: {=+INDEX('Réel 2024'!$A$2:$AO$501,MATCH($A33,'Réel 2024'!$A$2:$A$501,0),MATCH(Q$2,'Réel 2024'!$A$2:$AO$2,0))} -> 7607.44 | S33: =L33-Q33 -> 1513.82
A34: Véhicules neufsService gratuit 1 | B34: Véhicules neufs | C34: Service gratuit 1 | E34: =F34/D$24 -> 10 | F34: =+INDEX('Budget original'!$A$2:$AO$501,MATCH($A34,'Budget original'!$A$2:$A$501,0),MATCH(F$2,'Budget original'!$A$2:$AO$2,0)) -> 730 | K34: =IF(L34=0,0,L34/J$24) -> 0 | L34: =SUMIFS(BV_Data_An_Cour!$O:$O,BV_Data_An_Cour!$U:$U,$B34,BV_Data_An_Cour!$V:$V,$C34,BV_Data_An_Cour!$W:$W,L$2) -> 0 | N34: =L34-F34 -> -730 | P34: =Q34/O$24 -> 33.065625 | Q34: {=+INDEX('Réel 2024'!$A$2:$AO$501,MATCH($A34,'Réel 2024'!$A$2:$A$501,0),MATCH(Q$2,'Réel 2024'!$A$2:$AO$2,0))} -> 2645.25 | S34: =L34-Q34 -> -2645.25
A35: Véhicules neufsEntretien stock | B35: Véhicules neufs | C35: Entretien stock | E35: =F35/D$24 -> 120.75 | F35: =+INDEX('Budget original'!$A$2:$AO$501,MATCH($A35,'Budget original'!$A$2:$A$501,0),MATCH(F$2,'Budget original'!$A$2:$AO$2,0)) -> 8814.75 | K35: =IF(L35=0,0,L35/J$24) -> 43.995185 | L35: =SUMIFS(BV_Data_An_Cour!$O:$O,BV_Data_An_Cour!$U:$U,$B35,BV_Data_An_Cour!$V:$V,$C35,BV_Data_An_Cour!$W:$W,L$2) -> 3563.61 | N35: =L35-F35 -> -5251.14 | P35: =Q35/O$24 -> 79.675375 | Q35: {=+INDEX('Réel 2024'!$A$2:$AO$501,MATCH($A35,'Réel 2024'!$A$2:$A$501,0),MATCH(Q$2,'Réel 2024'!$A$2:$AO$2,0))} -> 6374.03 | S35: =L35-Q35 -> -2810.42
A36: Véhicules neufsPublicité 1 | B36: Véhicules neufs | C36: Publicité 1 | E36: =F36/D$24 -> 57.013699 | F36: =+INDEX('Budget original'!$A$2:$AO$501,MATCH($A36,'Budget original'!$A$2:$A$501,0),MATCH(F$2,'Budget original'!$A$2:$AO$2,0)) -> 4162 | K36: =IF(L36=0,0,L36/J$24) -> 45.389259 | L36: =SUMIFS(BV_Data_An_Cour!$O:$O,BV_Data_An_Cour!$U:$U,$B36,BV_Data_An_Cour!$V:$V,$C36,BV_Data_An_Cour!$W:$W,L$2) -> 3676.53 | N36: =L36-F36 -> -485.47 | P36: =Q36/O$24 -> 39.7595 | Q36: {=+INDEX('Réel 2024'!$A$2:$AO$501,MATCH($A36,'Réel 2024'!$A$2:$A$501,0),MATCH(Q$2,'Réel 2024'!$A$2:$AO$2,0))} -> 3180.76 | S36: =L36-Q36 -> 495.77
A37: Véhicules neufsIntérêt de gros | B37: Véhicules neufs | C37: Intérêt de gros | E37: =F37/D$24 -> 560.02013 | F37: =+INDEX('Budget original'!$A$2:$AO$501,MATCH($A37,'Budget original'!$A$2:$A$501,0),MATCH(F$2,'Budget original'!$A$2:$AO$2,0)) -> 40881.469 | K37: =IF(L37=0,0,L37/J$24) -> 273.39222 | L37: =SUMIFS(BV_Data_An_Cour!$O:$O,BV_Data_An_Cour!$U:$U,$B37,BV_Data_An_Cour!$V:$V,$C37,BV_Data_An_Cour!$W:$W,L$2) -> 22144.77 | N37: =L37-F37 -> -18736.699 | P37: =Q37/O$24 -> 565.70337 | Q37: {=+INDEX('Réel 2024'!$A$2:$AO$501,MATCH($A37,'Réel 2024'!$A$2:$A$501,0),MATCH(Q$2,'Réel 2024'!$A$2:$AO$2,0))} -> 45256.27 | S37: =L37-Q37 -> -23111.5
A38: Véhicules neufs[...] | B38: Véhicules neufs | C38: [...] | E38: =F38/D$24 -> 0 | F38: =+INDEX('Budget original'!$A$2:$AO$501,MATCH($A38,'Budget original'!$A$2:$A$501,0),MATCH(F$2,'Budget original'!$A$2:$AO$2,0)) -> 0 | K38: =IF(L38=0,0,L38/J$24) -> 0 | L38: =SUMIFS(BV_Data_An_Cour!$O:$O,BV_Data_An_Cour!$U:$U,$B38,BV_Data_An_Cour!$V:$V,$C38,BV_Data_An_Cour!$W:$W,L$2) -> 0 | N38: =L38-F38 -> 0 | P38: =Q38/O$24 -> 0 | Q38: {=+INDEX('Réel 2024'!$A$2:$AO$501,MATCH($A38,'Réel 2024'!$A$2:$A$501,0),MATCH(Q$2,'Réel 2024'!$A$2:$AO$2,0))} -> 0 | S38: =L38-Q38 -> 0
A39: Véhicules neufs[...] | B39: Véhicules neufs | C39: [...] | E39: =F39/D$24 -> 0 | F39: =+INDEX('Budget original'!$A$2:$AO$501,MATCH($A39,'Budget original'!$A$2:$A$501,0),MATCH(F$2,'Budget original'!$A$2:$AO$2,0)) -> 0 | K39: =IF(L39=0,0,L39/J$24) -> 0 | L39: =SUMIFS(BV_Data_An_Cour!$O:$O,BV_Data_An_Cour!$U:$U,$B39,BV_Data_An_Cour!$V:$V,$C39,BV_Data_An_Cour!$W:$W,L$2) -> 0 | N39: =L39-F39 -> 0 | P39: =Q39/O$24 -> 0 | Q39: {=+INDEX('Réel 2024'!$A$2:$AO$501,MATCH($A39,'Réel 2024'!$A$2:$A$501,0),MATCH(Q$2,'Réel 2024'!$A$2:$AO$2,0))} -> 0 | S39: =L39-Q39 -> 0
A40: Véhicules neufs[...] | B40: Véhicules neufs | C40: [...] | E40: =F40/D$24 -> 0 | F40: =+INDEX('Budget original'!$A$2:$AO$501,MATCH($A40,'Budget original'!$A$2:$A$501,0),MATCH(F$2,'Budget original'!$A$2:$AO$2,0)) -> 0 | K40: =IF(L40=0,0,L40/J$24) -> 0 | L40: =SUMIFS(BV_Data_An_Cour!$O:$O,BV_Data_An_Cour!$U:$U,$B40,BV_Data_An_Cour!$V:$V,$C40,BV_Data_An_Cour!$W:$W,L$2) -> 0 | N40: =L40-F40 -> 0 | P40: =Q40/O$24 -> 0 | Q40: {=+INDEX('Réel 2024'!$A$2:$AO$501,MATCH($A40,'Réel 2024'!$A$2:$A$501,0),MATCH(Q$2,'Réel 2024'!$A$2:$AO$2,0))} -> 0 | S40: =L40-Q40 -> 0
A41: Véhicules neufsTOTAL VARIABLES | B41: Véhicules neufs | C41: TOTAL VARIABLES | D41: % brut | E41: =F41/F$27 -> 0.54726765 | F41: =SUM(F31:F40) -> 137085.77 | J41: % brut | K41: =L41/L$27 -> 0.41359508 | L41: =SUM(L31:L40) -> 110943.37 | N41: =L41-F41 -> -26142.405 | O41: % brut | P41: =Q41/Q$27 -> 0.54556453 | Q41: =SUM(Q31:Q40) -> 138666.89 | S41: =L41-Q41 -> -27723.52
A42: Véhicules neufsSalaires cadres | B42: Véhicules neufs | C42: Salaires cadres | F42: =+INDEX('Budget original'!$A$2:$AO$501,MATCH($A42,'Budget original'!$A$2:$A$501,0),MATCH(F$2,'Budget original'!$A$2:$AO$2,0)) -> 24486.465 | L42: =SUMIFS(BV_Data_An_Cour!$O:$O,BV_Data_An_Cour!$U:$U,$B42,BV_Data_An_Cour!$V:$V,$C42,BV_Data_An_Cour!$W:$W,L$2) -> 21170.97 | N42: =L42-F42 -> -3315.4954 | P42: =Q42/Q27 -> 0.062411748 | Q42: {=+INDEX('Réel 2024'!$A$2:$AO$501,MATCH($A42,'Réel 2024'!$A$2:$A$501,0),MATCH(Q$2,'Réel 2024'!$A$2:$AO$2,0))} -> 15863.28 | S42: =L42-Q42 -> 5307.69
A43: Véhicules neufsSalaires commis | B43: Véhicules neufs | C43: Salaires commis | F43: =+INDEX('Budget original'!$A$2:$AO$501,MATCH($A43,'Budget original'!$A$2:$A$501,0),MATCH(F$2,'Budget original'!$A$2:$AO$2,0)) -> 13904.219 | L43: =SUMIFS(BV_Data_An_Cour!$O:$O,BV_Data_An_Cour!$U:$U,$B43,BV_Data_An_Cour!$V:$V,$C43,BV_Data_An_Cour!$W:$W,L$2) -> 11846.53 | N43: =L43-F43 -> -2057.6891 | Q43: {=+INDEX('Réel 2024'!$A$2:$AO$501,MATCH($A43,'Réel 2024'!$A$2:$A$501,0),MATCH(Q$2,'Réel 2024'!$A$2:$AO$2,0))} -> 8318.46 | S43: =L43-Q43 -> 3528.07
A44: Véhicules neufsSalaires autres | B44: Véhicules neufs | C44: Salaires autres | F44: =+INDEX('Budget original'!$A$2:$AO$501,MATCH($A44,'Budget original'!$A$2:$A$501,0),MATCH(F$2,'Budget original'!$A$2:$AO$2,0)) -> 315.55385 | L44: =SUMIFS(BV_Data_An_Cour!$O:$O,BV_Data_An_Cour!$U:$U,$B44,BV_Data_An_Cour!$V:$V,$C44,BV_Data_An_Cour!$W:$W,L$2) -> 1963.25 | N44: =L44-F44 -> 1647.6962 | Q44: {=+INDEX('Réel 2024'!$A$2:$AO$501,MATCH($A44,'Réel 2024'!$A$2:$A$501,0),MATCH(Q$2,'Réel 2024'!$A$2:$AO$2,0))} -> 2420.59 | S44: =L44-Q44 -> -457.34
A45: Véhicules neufsSalaires spécialistes | B45: Véhicules neufs | C45: Salaires spécialistes | F45: =+INDEX('Budget original'!$A$2:$AO$501,MATCH($A45,'Budget original'!$A$2:$A$501,0),MATCH(F$2,'Budget original'!$A$2:$AO$2,0)) -> 0 | L45: =SUMIFS(BV_Data_An_Cour!$O:$O,BV_Data_An_Cour!$U:$U,$B45,BV_Data_An_Cour!$V:$V,$C45,BV_Data_An_Cour!$W:$W,L$2) -> 0 | N45: =L45-F45 -> 0 | Q45: {=+INDEX('Réel 2024'!$A$2:$AO$501,MATCH($A45,'Réel 2024'!$A$2:$A$501,0),MATCH(Q$2,'Réel 2024'!$A$2:$AO$2,0))} -> 0 | S45: =L45-Q45 -> 0
A46: Véhicules neufs[...] | B46: Véhicules neufs | C46: [...] | F46: =+INDEX('Budget original'!$A$2:$AO$501,MATCH($A46,'Budget original'!$A$2:$A$501,0),MATCH(F$2,'Budget original'!$A$2:$AO$2,0)) -> 0 | L46: =SUMIFS(BV_Data_An_Cour!$O:$O,BV_Data_An_Cour!$U:$U,$B46,BV_Data_An_Cour!$V:$V,$C46,BV_Data_An_Cour!$W:$W,L$2) -> 0 | N46: =L46-F46 -> 0 | Q46: {=+INDEX('Réel 2024'!$A$2:$AO$501,MATCH($A46,'Réel 2024'!$A$2:$A$501,0),MATCH(Q$2,'Réel 2024'!$A$2:$AO$2,0))} -> 0 | S46: =L46-Q46 -> 0
A47: Véhicules neufs[...] | B47: Véhicules neufs | C47: [...] | F47: =+INDEX('Budget original'!$A$2:$AO$501,MATCH($A47,'Budget original'!$A$2:$A$501,0),MATCH(F$2,'Budget original'!$A$2:$AO$2,0)) -> 0 | L47: =SUMIFS(BV_Data_An_Cour!$O:$O,BV_Data_An_Cour!$U:$U,$B47,BV_Data_An_Cour!$V:$V,$C47,BV_Data_An_Cour!$W:$W,L$2) -> 0 | N47: =L47-F47 -> 0 | Q47: {=+INDEX('Réel 2024'!$A$2:$AO$501,MATCH($A47,'Réel 2024'!$A$2:$A$501,0),MATCH(Q$2,'Réel 2024'!$A$2:$AO$2,0))} -> 0 | S47: =L47-Q47 -> 0
A48: Véhicules neufs[...] | B48: Véhicules neufs | C48: [...] | F48: =+INDEX('Budget original'!$A$2:$AO$501,MATCH($A48,'Budget original'!$A$2:$A$501,0),MATCH(F$2,'Budget original'!$A$2:$AO$2,0)) -> 0 | L48: =SUMIFS(BV_Data_An_Cour!$O:$O,BV_Data_An_Cour!$U:$U,$B48,BV_Data_An_Cour!$V:$V,$C48,BV_Data_An_Cour!$W:$W,L$2) -> 0 | N48: =L48-F48 -> 0 | Q48: {=+INDEX('Réel 2024'!$A$2:$AO$501,MATCH($A48,'Réel 2024'!$A$2:$A$501,0),MATCH(Q$2,'Réel 2024'!$A$2:$AO$2,0))} -> 0 | S48: =L48-Q48 -> 0
A49: Véhicules neufsSalaires en absences | B49: Véhicules neufs | C49: Salaires en absences | F49: =+INDEX('Budget original'!$A$2:$AO$501,MATCH($A49,'Budget original'!$A$2:$A$501,0),MATCH(F$2,'Budget original'!$A$2:$AO$2,0)) -> 11796.071 | L49: =SUMIFS(BV_Data_An_Cour!$O:$O,BV_Data_An_Cour!$U:$U,$B49,BV_Data_An_Cour!$V:$V,$C49,BV_Data_An_Cour!$W:$W,L$2) -> 10866.84 | N49: =L49-F49 -> -929.23067 | Q49: {=+INDEX('Réel 2024'!$A$2:$AO$501,MATCH($A49,'Réel 2024'!$A$2:$A$501,0),MATCH(Q$2,'Réel 2024'!$A$2:$AO$2,0))} -> 10664.1 | S49: =L49-Q49 -> 202.74
A50: Véhicules neufsDéduction à la source | B50: Véhicules neufs | C50: Déduction à la source | F50: =+INDEX('Budget original'!$A$2:$AO$501,MATCH($A50,'Budget original'!$A$2:$A$501,0),MATCH(F$2,'Budget original'!$A$2:$AO$2,0)) -> 14342.359 | L50: =SUMIFS(BV_Data_An_Cour!$O:$O,BV_Data_An_Cour!$U:$U,$B50,BV_Data_An_Cour!$V:$V,$C50,BV_Data_An_Cour!$W:$W,L$2) -> 13752.02 | N50: =L50-F50 -> -590.33905 | Q50: {=+INDEX('Réel 2024'!$A$2:$AO$501,MATCH($A50,'Réel 2024'!$A$2:$A$501,0),MATCH(Q$2,'Réel 2024'!$A$2:$AO$2,0))} -> 12553.25 | S50: =L50-Q50 -> 1198.77
A51: Véhicules neufsBénéfices marginaux | B51: Véhicules neufs | C51: Bénéfices marginaux | F51: =+INDEX('Budget original'!$A$2:$AO$501,MATCH($A51,'Budget original'!$A$2:$A$501,0),MATCH(F$2,'Budget original'!$A$2:$AO$2,0)) -> 7389.4328 | L51: =SUMIFS(BV_Data_An_Cour!$O:$O,BV_Data_An_Cour!$U:$U,$B51,BV_Data_An_Cour!$V:$V,$C51,BV_Data_An_Cour!$W:$W,L$2) -> 7178.18 | N51: =L51-F51 -> -211.25282 | Q51: {=+INDEX('Réel 2024'!$A$2:$AO$501,MATCH($A51,'Réel 2024'!$A$2:$A$501,0),MATCH(Q$2,'Réel 2024'!$A$2:$AO$2,0))} -> 7041.73 | S51: =L51-Q51 -> 136.45
A52: Véhicules neufsCsst | B52: Véhicules neufs | C52: Csst | F52: =+INDEX('Budget original'!$A$2:$AO$501,MATCH($A52,'Budget original'!$A$2:$A$501,0),MATCH(F$2,'Budget original'!$A$2:$AO$2,0)) -> 3221.8343 | L52: =SUMIFS(BV_Data_An_Cour!$O:$O,BV_Data_An_Cour!$U:$U,$B52,BV_Data_An_Cour!$V:$V,$C52,BV_Data_An_Cour!$W:$W,L$2) -> 3241.11 | N52: =L52-F52 -> 19.27572 | Q52: {=+INDEX('Réel 2024'!$A$2:$AO$501,MATCH($A52,'Réel 2024'!$A$2:$A$501,0),MATCH(Q$2,'Réel 2024'!$A$2:$AO$2,0))} -> 1892.71 | S52: =L52-Q52 -> 1348.4
A53: Véhicules neufs[...] | B53: Véhicules neufs | C53: [...] | D53: =VLOOKUP(C53,$B$2:$B$46,1,FALSE) -> #N/A | F53: =+INDEX('Budget original'!$A$2:$AO$501,MATCH($A53,'Budget original'!$A$2:$A$501,0),MATCH(F$2,'Budget original'!$A$2:$AO$2,0)) -> 0 | L53: =SUMIFS(BV_Data_An_Cour!$O:$O,BV_Data_An_Cour!$U:$U,$B53,BV_Data_An_Cour!$V:$V,$C53,BV_Data_An_Cour!$W:$W,L$2) -> 0 | N53: =L53-F53 -> 0 | Q53: {=+INDEX('Réel 2024'!$A$2:$AO$501,MATCH($A53,'Réel 2024'!$A$2:$A$501,0),MATCH(Q$2,'Réel 2024'!$A$2:$AO$2,0))} -> 0 | S53: =L53-Q53 -> 0
A54: Véhicules neufsTOTAL PERSONNEL | B54: Véhicules neufs | C54: TOTAL PERSONNEL | D54: % brut | E54: =F54/F$27 -> 0.30123178 | F54: =+SUM(F42:F53) -> 75455.935 | J54: % brut | K54: =L54/L$27 -> 0.26102932 | L54: =+SUM(L42:L53) -> 70018.9 | N54: =+SUM(N42:N53) -> -5437.0351 | O54: % brut | P54: =Q54/Q$27 -> 0.23115946 | Q54: =+SUM(Q42:Q53) -> 58754.12 | S54: =+SUM(S42:S53) -> 11264.78
A55: Véhicules neufsPublicité 2 | B55: Véhicules neufs | C55: Publicité 2 | F55: =+INDEX('Budget original'!$A$2:$AO$501,MATCH($A55,'Budget original'!$A$2:$A$501,0),MATCH(F$2,'Budget original'!$A$2:$AO$2,0)) -> 0 | L55: =SUMIFS(BV_Data_An_Cour!$O:$O,BV_Data_An_Cour!$U:$U,$B55,BV_Data_An_Cour!$V:$V,$C55,BV_Data_An_Cour!$W:$W,L$2) -> 0 | N55: =L55-F55 -> 0 | Q55: {=+INDEX('Réel 2024'!$A$2:$AO$501,MATCH($A55,'Réel 2024'!$A$2:$A$501,0),MATCH(Q$2,'Réel 2024'!$A$2:$AO$2,0))} -> 0 | S55: =L55-Q55 -> 0
A56: Véhicules neufsService gratuit 2 | B56: Véhicules neufs | C56: Service gratuit 2 | F56: =+INDEX('Budget original'!$A$2:$AO$501,MATCH($A56,'Budget original'!$A$2:$A$501,0),MATCH(F$2,'Budget original'!$A$2:$AO$2,0)) -> 0 | L56: =SUMIFS(BV_Data_An_Cour!$O:$O,BV_Data_An_Cour!$U:$U,$B56,BV_Data_An_Cour!$V:$V,$C56,BV_Data_An_Cour!$W:$W,L$2) -> 0 | N56: =L56-F56 -> 0 | Q56: {=+INDEX('Réel 2024'!$A$2:$AO$501,MATCH($A56,'Réel 2024'!$A$2:$A$501,0),MATCH(Q$2,'Réel 2024'!$A$2:$AO$2,0))} -> 0 | S56: =L56-Q56 -> 0
A57: Véhicules neufsFrais véhicules de cie | B57: Véhicules neufs | C57: Frais véhicules de cie | F57: =+INDEX('Budget original'!$A$2:$AO$501,MATCH($A57,'Budget original'!$A$2:$A$501,0),MATCH(F$2,'Budget original'!$A$2:$AO$2,0)) -> 8952.5479 | L57: =SUMIFS(BV_Data_An_Cour!$O:$O,BV_Data_An_Cour!$U:$U,$B57,BV_Data_An_Cour!$V:$V,$C57,BV_Data_An_Cour!$W:$W,L$2) -> 7490.62 | N57: =L57-F57 -> -1461.9279 | Q57: {=+INDEX('Réel 2024'!$A$2:$AO$501,MATCH($A57,'Réel 2024'!$A$2:$A$501,0),MATCH(Q$2,'Réel 2024'!$A$2:$AO$2,0))} -> 9199.43 | S57: =L57-Q57 -> -1708.81
A58: Véhicules neufsInformatique | B58: Véhicules neufs | C58: Informatique | F58: =+INDEX('Budget original'!$A$2:$AO$501,MATCH($A58,'Budget original'!$A$2:$A$501,0),MATCH(F$2,'Budget original'!$A$2:$AO$2,0)) -> 7960.9948 | L58: =SUMIFS(BV_Data_An_Cour!$O:$O,BV_Data_An_Cour!$U:$U,$B58,BV_Data_An_Cour!$V:$V,$C58,BV_Data_An_Cour!$W:$W,L$2) -> 7652.37 | N58: =L58-F58 -> -308.62476 | Q58: {=+INDEX('Réel 2024'!$A$2:$AO$501,MATCH($A58,'Réel 2024'!$A$2:$A$501,0),MATCH(Q$2,'Réel 2024'!$A$2:$AO$2,0))} -> 5972.42 | S58: =L58-Q58 -> 1679.95
A59: Véhicules neufsFrais de déplacement | B59: Véhicules neufs | C59: Frais de déplacement | F59: =+INDEX('Budget original'!$A$2:$AO$501,MATCH($A59,'Budget original'!$A$2:$A$501,0),MATCH(F$2,'Budget original'!$A$2:$AO$2,0)) -> 1266.6975 | L59: =SUMIFS(BV_Data_An_Cour!$O:$O,BV_Data_An_Cour!$U:$U,$B59,BV_Data_An_Cour!$V:$V,$C59,BV_Data_An_Cour!$W:$W,L$2) -> 1293.58 | N59: =L59-F59 -> 26.882499 | Q59: {=+INDEX('Réel 2024'!$A$2:$AO$501,MATCH($A59,'Réel 2024'!$A$2:$A$501,0),MATCH(Q$2,'Réel 2024'!$A$2:$AO$2,0))} -> 1613.78 | S59: =L59-Q59 -> -320.2
A60: Véhicules neufsServices extérieurs | B60: Véhicules neufs | C60: Services extérieurs | F60: =+INDEX('Budget original'!$A$2:$AO$501,MATCH($A60,'Budget original'!$A$2:$A$501,0),MATCH(F$2,'Budget original'!$A$2:$AO$2,0)) -> 7215.7407 | L60: =SUMIFS(BV_Data_An_Cour!$O:$O,BV_Data_An_Cour!$U:$U,$B60,BV_Data_An_Cour!$V:$V,$C60,BV_Data_An_Cour!$W:$W,L$2) -> 8436.09 | N60: =L60-F60 -> 1220.3493 | Q60: {=+INDEX('Réel 2024'!$A$2:$AO$501,MATCH($A60,'Réel 2024'!$A$2:$A$501,0),MATCH(Q$2,'Réel 2024'!$A$2:$AO$2,0))} -> 7694.41 | S60: =L60-Q60 -> 741.68
A61: Véhicules neufsFournitures autres | B61: Véhicules neufs | C61: Fournitures autres | F61: =+INDEX('Budget original'!$A$2:$AO$501,MATCH($A61,'Budget original'!$A$2:$A$501,0),MATCH(F$2,'Budget original'!$A$2:$AO$2,0)) -> 97.257333 | L61: =SUMIFS(BV_Data_An_Cour!$O:$O,BV_Data_An_Cour!$U:$U,$B61,BV_Data_An_Cour!$V:$V,$C61,BV_Data_An_Cour!$W:$W,L$2) -> 0 | N61: =L61-F61 -> -97.257333 | Q61: {=+INDEX('Réel 2024'!$A$2:$AO$501,MATCH($A61,'Réel 2024'!$A$2:$A$501,0),MATCH(Q$2,'Réel 2024'!$A$2:$AO$2,0))} -> 97.12 | S61: =L61-Q61 -> -97.12
A62: Véhicules neufsUniformes | B62: Véhicules neufs | C62: Uniformes | F62: =+INDEX('Budget original'!$A$2:$AO$501,MATCH($A62,'Budget original'!$A$2:$A$501,0),MATCH(F$2,'Budget original'!$A$2:$AO$2,0)) -> 28.333333 | L62: =SUMIFS(BV_Data_An_Cour!$O:$O,BV_Data_An_Cour!$U:$U,$B62,BV_Data_An_Cour!$V:$V,$C62,BV_Data_An_Cour!$W:$W,L$2) -> 0 | N62: =L62-F62 -> -28.333333 | Q62: {=+INDEX('Réel 2024'!$A$2:$AO$501,MATCH($A62,'Réel 2024'!$A$2:$A$501,0),MATCH(Q$2,'Réel 2024'!$A$2:$AO$2,0))} -> 0 | S62: =L62-Q62 -> 0
A63: Véhicules neufsPapeterie | B63: Véhicules neufs | C63: Papeterie | F63: =+INDEX('Budget original'!$A$2:$AO$501,MATCH($A63,'Budget original'!$A$2:$A$501,0),MATCH(F$2,'Budget original'!$A$2:$AO$2,0)) -> 741.43089 | L63: =SUMIFS(BV_Data_An_Cour!$O:$O,BV_Data_An_Cour!$U:$U,$B63,BV_Data_An_Cour!$V:$V,$C63,BV_Data_An_Cour!$W:$W,L$2) -> 218.53 | N63: =L63-F63 -> -522.90089 | Q63: {=+INDEX('Réel 2024'!$A$2:$AO$501,MATCH($A63,'Réel 2024'!$A$2:$A$501,0),MATCH(Q$2,'Réel 2024'!$A$2:$AO$2,0))} -> 356.55 | S63: =L63-Q63 -> -138.02
A64: Véhicules neufsTéléphone | B64: Véhicules neufs | C64: Téléphone | F64: =+INDEX('Budget original'!$A$2:$AO$501,MATCH($A64,'Budget original'!$A$2:$A$501,0),MATCH(F$2,'Budget original'!$A$2:$AO$2,0)) -> 344.80198 | L64: =SUMIFS(BV_Data_An_Cour!$O:$O,BV_Data_An_Cour!$U:$U,$B64,BV_Data_An_Cour!$V:$V,$C64,BV_Data_An_Cour!$W:$W,L$2) -> 355.13 | N64: =L64-F64 -> 10.328015 | Q64: {=+INDEX('Réel 2024'!$A$2:$AO$501,MATCH($A64,'Réel 2024'!$A$2:$A$501,0),MATCH(Q$2,'Réel 2024'!$A$2:$AO$2,0))} -> 330.97 | S64: =L64-Q64 -> 24.16
A65: Véhicules neufsFrais postaux | B65: Véhicules neufs | C65: Frais postaux | F65: =+INDEX('Budget original'!$A$2:$AO$501,MATCH($A65,'Budget original'!$A$2:$A$501,0),MATCH(F$2,'Budget original'!$A$2:$AO$2,0)) -> 102.8224 | L65: =SUMIFS(BV_Data_An_Cour!$O:$O,BV_Data_An_Cour!$U:$U,$B65,BV_Data_An_Cour!$V:$V,$C65,BV_Data_An_Cour!$W:$W,L$2) -> 54.6 | N65: =L65-F65 -> -48.222395 | Q65: {=+INDEX('Réel 2024'!$A$2:$AO$501,MATCH($A65,'Réel 2024'!$A$2:$A$501,0),MATCH(Q$2,'Réel 2024'!$A$2:$AO$2,0))} -> 32.96 | S65: =L65-Q65 -> 21.64
A66: Véhicules neufsDivers | B66: Véhicules neufs | C66: Divers | F66: =+INDEX('Budget original'!$A$2:$AO$501,MATCH($A66,'Budget original'!$A$2:$A$501,0),MATCH(F$2,'Budget original'!$A$2:$AO$2,0)) -> 201.17039 | L66: =SUMIFS(BV_Data_An_Cour!$O:$O,BV_Data_An_Cour!$U:$U,$B66,BV_Data_An_Cour!$V:$V,$C66,BV_Data_An_Cour!$W:$W,L$2) -> 62.72 | N66: =L66-F66 -> -138.45039 | Q66: {=+INDEX('Réel 2024'!$A$2:$AO$501,MATCH($A66,'Réel 2024'!$A$2:$A$501,0),MATCH(Q$2,'Réel 2024'!$A$2:$AO$2,0))} -> 188.48 | S66: =L66-Q66 -> -125.76
... A68: Véhicules neufsFrais bancaires | B68: Véhicules neufs | C68: Frais bancaires | F68: =+INDEX('Budget original'!$A$2:$AO$501,MATCH($A68,'Budget original'!$A$2:$A$501,0),MATCH(F$2,'Budget original'!$A$2:$AO$2,0)) -> 3605.8794 | L68: =SUMIFS(BV_Data_An_Cour!$O:$O,BV_Data_An_Cour!$U:$U,$B68,BV_Data_An_Cour!$V:$V,$C68,BV_Data_An_Cour!$W:$W,L$2) -> 3902.37 | N68: =L68-F68 -> 296.49063 | Q68: {=+INDEX('Réel 2024'!$A$2:$AO$501,MATCH($A68,'Réel 2024'!$A$2:$A$501,0),MATCH(Q$2,'Réel 2024'!$A$2:$AO$2,0))} -> 3718.78 | S68: =L68-Q68 -> 183.59
A69: Véhicules neufs[...] | B69: Véhicules neufs | C69: [...] | F69: =+INDEX('Budget original'!$A$2:$AO$501,MATCH($A69,'Budget original'!$A$2:$A$501,0),MATCH(F$2,'Budget original'!$A$2:$AO$2,0)) -> 0 | N69: =L69-F69 -> 0 | Q69: {=+INDEX('Réel 2024'!$A$2:$AO$501,MATCH($A69,'Réel 2024'!$A$2:$A$501,0),MATCH(Q$2,'Réel 2024'!$A$2:$AO$2,0))} -> 0 | S69: =L69-Q69 -> 0
A70: Véhicules neufs[...] | B70: Véhicules neufs | C70: [...] | F70: =+INDEX('Budget original'!$A$2:$AO$501,MATCH($A70,'Budget original'!$A$2:$A$501,0),MATCH(F$2,'Budget original'!$A$2:$AO$2,0)) -> 0 | L70: =SUMIFS(BV_Data_An_Cour!$O:$O,BV_Data_An_Cour!$U:$U,$B70,BV_Data_An_Cour!$V:$V,$C70,BV_Data_An_Cour!$W:$W,L$2) -> 0 | N70: =L70-F70 -> 0 | Q70: {=+INDEX('Réel 2024'!$A$2:$AO$501,MATCH($A70,'Réel 2024'!$A$2:$A$501,0),MATCH(Q$2,'Réel 2024'!$A$2:$AO$2,0))} -> 0 | S70: =L70-Q70 -> 0
A71: Véhicules neufs[...] | B71: Véhicules neufs | C71: [...] | F71: =+INDEX('Budget original'!$A$2:$AO$501,MATCH($A71,'Budget original'!$A$2:$A$501,0),MATCH(F$2,'Budget original'!$A$2:$AO$2,0)) -> 0 | L71: =SUMIFS(BV_Data_An_Cour!$O:$O,BV_Data_An_Cour!$U:$U,$B71,BV_Data_An_Cour!$V:$V,$C71,BV_Data_An_Cour!$W:$W,L$2)*0.32 -> 0 | N71: =L71-F71 -> 0 | Q71: {=+INDEX('Réel 2024'!$A$2:$AO$501,MATCH($A71,'Réel 2024'!$A$2:$A$501,0),MATCH(Q$2,'Réel 2024'!$A$2:$AO$2,0))} -> 0 | S71: =L71-Q71 -> 0
A72: Véhicules neufsTOTAL SEMI-FIXES | B72: Véhicules neufs | C72: TOTAL SEMI-FIXES | D72: % brut | E72: =F72/F$27 -> 0.12955494 | F72: =+SUM(F55:F71) -> 32452.383 | J72: % brut | K72: =L72/L$27 -> 0.11927341 | L72: =+SUM(L55:L71) -> 31994.08 | N72: =+SUM(N55:N71) -> -458.30287 | O72: % brut | P72: =Q72/Q$27 -> 0.12862569 | Q72: =+SUM(Q55:Q71) -> 32692.97 | S72: =+SUM(S55:S71) -> -698.89
A73: Véhicules neufs | B73: Véhicules neufs
A74: Véhicules neufsTOTAL DES DÉPENSES | B74: Véhicules neufs | C74: TOTAL DES DÉPENSES | D74: % brut | E74: =F74/F$27 -> 0.97805437 | F74: =F41+F54+F72 -> 244994.09 | J74: % brut | K74: =L74/L$27 -> 0.79389782 | L74: =L41+L54+L72 -> 212956.35 | N74: =L74-F74 -> -32037.743 | O74: % brut | P74: =Q74/Q$27 -> 0.90534969 | Q74: =Q41+Q54+Q72 -> 230113.98 | S74: =L74-Q74 -> -17157.63
A75: Véhicules neufsProgramme neuf 1 | B75: Véhicules neufs | C75: Programme neuf 1 | F75: =+INDEX('Budget original'!$A$2:$AO$501,MATCH($A75,'Budget original'!$A$2:$A$501,0),MATCH(F$2,'Budget original'!$A$2:$AO$2,0)) -> 0 | L75: =-SUMIFS(BV_Data_An_Cour!$O:$O,BV_Data_An_Cour!$U:$U,$B75,BV_Data_An_Cour!$V:$V,$C75,BV_Data_An_Cour!$W:$W,L$2)-L156 -> 0 | N75: =L75-F75 -> 0 | Q75: =+INDEX('Réel 2024'!$A$2:$AO$501,MATCH($A75,'Réel 2024'!$A$2:$A$501,0),MATCH(Q$2,'Réel 2024'!$A$2:$AO$2,0)) -> 18100
A76: Véhicules neufsProgramme neuf 2 | B76: Véhicules neufs | C76: Programme neuf 2 | F76: =+INDEX('Budget original'!$A$2:$AO$501,MATCH($A76,'Budget original'!$A$2:$A$501,0),MATCH(F$2,'Budget original'!$A$2:$AO$2,0)) -> 0 | L76: =-SUMIFS(BV_Data_An_Cour!$O:$O,BV_Data_An_Cour!$U:$U,$B76,BV_Data_An_Cour!$V:$V,$C76,BV_Data_An_Cour!$W:$W,L$2) -> 0 | N76: =L76-F76 -> 0 | Q76: {=+INDEX('Réel 2024'!$A$2:$AO$501,MATCH($A76,'Réel 2024'!$A$2:$A$501,0),MATCH(Q$2,'Réel 2024'!$A$2:$AO$2,0))} -> 0 | S76: =L76-Q76 -> 0
A77: Véhicules neufsProgramme neuf 3 | B77: Véhicules neufs | C77: Programme neuf 3 | F77: =+INDEX('Budget original'!$A$2:$AO$501,MATCH($A77,'Budget original'!$A$2:$A$501,0),MATCH(F$2,'Budget original'!$A$2:$AO$2,0)) -> 0 | L77: =-SUMIFS(BV_Data_An_Cour!$O:$O,BV_Data_An_Cour!$U:$U,$B77,BV_Data_An_Cour!$V:$V,$C77,BV_Data_An_Cour!$W:$W,L$2) -> 0 | N77: =L77-F77 -> 0 | Q77: {=+INDEX('Réel 2024'!$A$2:$AO$501,MATCH($A77,'Réel 2024'!$A$2:$A$501,0),MATCH(Q$2,'Réel 2024'!$A$2:$AO$2,0))} -> 0 | S77: =L77-Q77 -> 0
A78: Véhicules neufsHoldbacks | B78: Véhicules neufs | C78: Holdbacks | E78: =+F78/D27 -> 1407.2459 | F78: =+INDEX('Budget original'!$A$2:$AO$501,MATCH($A78,'Budget original'!$A$2:$A$501,0),MATCH(F$2,'Budget original'!$A$2:$AO$2,0)) -> 105543.44 | J78: =K78/E78 -> 0.83190993 | K78: =+L78/J27 -> 1170.7019 | L78: =-SUMIFS(BV_Data_An_Cour!$O:$O,BV_Data_An_Cour!$U:$U,$B78,BV_Data_An_Cour!$V:$V,$C78,BV_Data_An_Cour!$W:$W,L$2) -> 94826.85 | N78: =L78-F78 -> -10716.594 | Q78: {=+INDEX('Réel 2024'!$A$2:$AO$501,MATCH($A78,'Réel 2024'!$A$2:$A$501,0),MATCH(Q$2,'Réel 2024'!$A$2:$AO$2,0))} -> 127510 | S78: =L78-Q78 -> -32683.15
A79: Véhicules neufs[...] | B79: Véhicules neufs | C79: [...] | F79: =+INDEX('Budget original'!$A$2:$AO$501,MATCH($A79,'Budget original'!$A$2:$A$501,0),MATCH(F$2,'Budget original'!$A$2:$AO$2,0)) -> 0 | L79: =-SUMIFS(BV_Data_An_Cour!$O:$O,BV_Data_An_Cour!$U:$U,$B79,BV_Data_An_Cour!$V:$V,$C79,BV_Data_An_Cour!$W:$W,L$2) -> 0 | N79: =L79-F79 -> 0 | Q79: {=+INDEX('Réel 2024'!$A$2:$AO$501,MATCH($A79,'Réel 2024'!$A$2:$A$501,0),MATCH(Q$2,'Réel 2024'!$A$2:$AO$2,0))} -> 0 | S79: =L79-Q79 -> 0
A80: Véhicules neufs[...] | B80: Véhicules neufs | C80: [...] | F80: =+INDEX('Budget original'!$A$2:$AO$501,MATCH($A80,'Budget original'!$A$2:$A$501,0),MATCH(F$2,'Budget original'!$A$2:$AO$2,0)) -> 0 | L80: =-SUMIFS(BV_Data_An_Cour!$O:$O,BV_Data_An_Cour!$U:$U,$B80,BV_Data_An_Cour!$V:$V,$C80,BV_Data_An_Cour!$W:$W,L$2) -> 0 | N80: =L80-F80 -> 0 | Q80: {=+INDEX('Réel 2024'!$A$2:$AO$501,MATCH($A80,'Réel 2024'!$A$2:$A$501,0),MATCH(Q$2,'Réel 2024'!$A$2:$AO$2,0))} -> 0 | S80: =L80-Q80 -> 0
A81: Véhicules neufs[...] | B81: Véhicules neufs | C81: [...] | F81: =+INDEX('Budget original'!$A$2:$AO$501,MATCH($A81,'Budget original'!$A$2:$A$501,0),MATCH(F$2,'Budget original'!$A$2:$AO$2,0)) -> 0 | L81: =-SUMIFS(BV_Data_An_Cour!$O:$O,BV_Data_An_Cour!$U:$U,$B81,BV_Data_An_Cour!$V:$V,$C81,BV_Data_An_Cour!$W:$W,L$2) -> 0 | N81: =L81-F81 -> 0 | Q81: {=+INDEX('Réel 2024'!$A$2:$AO$501,MATCH($A81,'Réel 2024'!$A$2:$A$501,0),MATCH(Q$2,'Réel 2024'!$A$2:$AO$2,0))} -> 0 | S81: =L81-Q81 -> 0
A82: Véhicules neufsFrais administration | B82: Véhicules neufs | C82: Frais administration | D82: =E82/499 -> 0.95 | E82: =+F82/D24 -> 474.05 | F82: =+INDEX('Budget original'!$A$2:$AO$501,MATCH($A82,'Budget original'!$A$2:$A$501,0),MATCH(F$2,'Budget original'!$A$2:$AO$2,0)) -> 34605.65 | J82: =K82/474 -> 1.0326614 | K82: =+L82/J24 -> 489.48148 | L82: =-SUMIFS(BV_Data_An_Cour!$O:$O,BV_Data_An_Cour!$U:$U,$B82,BV_Data_An_Cour!$V:$V,$C82,BV_Data_An_Cour!$W:$W,L$2) -> 39648 | N82: =L82-F82 -> 5042.35 | Q82: {=+INDEX('Réel 2024'!$A$2:$AO$501,MATCH($A82,'Réel 2024'!$A$2:$A$501,0),MATCH(Q$2,'Réel 2024'!$A$2:$AO$2,0))} -> 35590 | S82: =L82-Q82 -> 4058
A83: Véhicules neufsAUTRES REVENUS | B83: Véhicules neufs | C83: AUTRES REVENUS | F83: =+SUM(F75:F82) -> 140149.09 | L83: =+SUM(L75:L82) -> 134474.85 | N83: =+SUM(N75:N82) -> -5674.2436 | Q83: =+SUM(Q75:Q82) -> 181200 | S83: =+SUM(S75:S82) -> -28625.15
A84: Véhicules neufs | B84: Véhicules neufs
A85: Véhicules neufsPROFIT DÉPARTEMENTAL | B85: Véhicules neufs | C85: PROFIT DÉPARTEMENTAL | F85: =F27-F74+F83 -> 145646.28 | L85: =L27-L74+L83 -> 189760.01 | N85: =N27-N41-N54-N72+N83 -> 44113.728 | P85: =Q85/Q5 -> 0.045369153 | Q85: =Q27-Q74+Q83 -> 205257.4 | S85: =S27-S41-S54-S72+S83 -> 2602.61
C89: =C1 -> Volks | K89: Véhicules usagés | S89: =$S$1 -> Réalisé, Juillet 2025
D91: BUDGET ORIGINAL | J91: RÉALISATION | M91: ÉCART réel / Budget | O91: ANNÉE PRÉCÉDENTE | R91: ECART (réel/ Ann.Préc.)
D92: UNITE | E92: $P/UNITÉ | F92: $PROFITS | J92: UNITÉS | K92: $P/UNITE | L92: $PROFITS | M92: UNITÉS | N92: $PROFITS | O92: UNITE | P92: $P/UNITÉ | Q92: $PROFITS | R92: UNITÉS | S92: $PROFITS
A93: Véhicules usagésVentes nettes | B93: Véhicules usagés | C93: Ventes nettes | F93: =+INDEX('Budget original'!$A$2:$AO$501,MATCH($A93,'Budget original'!$A$2:$A$501,0),MATCH(F$2,'Budget original'!$A$2:$AO$2,0)) -> 1699373.1 | L93: =-SUMIFS(BV_Data_An_Cour!$O:$O,BV_Data_An_Cour!$X:$X,"Oui",BV_Data_An_Cour!$U:$U,$B93) -> 1735831.8 | Q93: {=+INDEX('Réel 2024'!$A$2:$AO$501,MATCH($A93,'Réel 2024'!$A$2:$A$501,0),MATCH(Q$2,'Réel 2024'!$A$2:$AO$2,0))} -> 1416483.6
A94: Véhicules usagésCertifié | B94: Véhicules usagés | C94: Certifié | D94: =+INDEX('Budget original'!$A$2:$AO$501,MATCH($A94,'Budget original'!$A$2:$A$501,0),MATCH(D$2,'Budget original'!$A$2:$AO$2,0)) -> 26 | E94: =IF(D94=0,0,F94/D94) -> 1400 | F94: =+INDEX('Budget original'!$A$2:$AO$501,MATCH($A94,'Budget original'!$A$2:$A$501,0),MATCH(F$2,'Budget original'!$A$2:$AO$2,0)) -> 36400 | J94: =-SUMIFS(BV_Data_An_Cour!$O:$O,BV_Data_An_Cour!$U:$U,$B94,BV_Data_An_Cour!$V:$V,$C94,BV_Data_An_Cour!$W:$W,J$2) -> 28 | K94: =IF(J94=0,0,L94/J94) -> 1004.9229 | L94: =-SUMIFS(BV_Data_An_Cour!$O:$O,BV_Data_An_Cour!$U:$U,$B94,BV_Data_An_Cour!$V:$V,$C94,BV_Data_An_Cour!$W:$W,$L2) -> 28137.84 | M94: =J94-D94 -> 2 | N94: =L94-F94 -> -8262.16 | O94: {=+INDEX('Réel 2024'!$A$2:$AO$501,MATCH($A94,'Réel 2024'!$A$2:$A$501,0),MATCH(O$2,'Réel 2024'!$A$2:$AO$2,0))} -> 25 | P94: =IF(O94=0,0,Q94/O94) -> 1627.8944 | Q94: {=+INDEX('Réel 2024'!$A$2:$AO$501,MATCH($A94,'Réel 2024'!$A$2:$A$501,0),MATCH(Q$2,'Réel 2024'!$A$2:$AO$2,0))} -> 40697.36 | R94: =J94-O94 -> 3 | S94: =L94-Q94 -> -12559.52
A95: Véhicules usagésNon Certifié | B95: Véhicules usagés | C95: Non Certifié | D95: =+INDEX('Budget original'!$A$2:$AO$501,MATCH($A95,'Budget original'!$A$2:$A$501,0),MATCH(D$2,'Budget original'!$A$2:$AO$2,0)) -> 3 | E95: =IF(D95=0,0,F95/D95) -> 1800 | F95: =+INDEX('Budget original'!$A$2:$AO$501,MATCH($A95,'Budget original'!$A$2:$A$501,0),MATCH(F$2,'Budget original'!$A$2:$AO$2,0)) -> 5400 | J95: =-SUMIFS(BV_Data_An_Cour!$O:$O,BV_Data_An_Cour!$U:$U,$B95,BV_Data_An_Cour!$V:$V,$C95,BV_Data_An_Cour!$W:$W,J$2) -> 0 | K95: =IF(J95=0,0,L95/J95) -> 0 | L95: =-SUMIFS(BV_Data_An_Cour!$O:$O,BV_Data_An_Cour!$U:$U,$B95,BV_Data_An_Cour!$V:$V,$C95,BV_Data_An_Cour!$W:$W,$L2) -> 0 | M95: =J95-D95 -> -3 | N95: =L95-F95 -> -5400 | O95: {=+INDEX('Réel 2024'!$A$2:$AO$501,MATCH($A95,'Réel 2024'!$A$2:$A$501,0),MATCH(O$2,'Réel 2024'!$A$2:$AO$2,0))} -> 5 | P95: =IF(O95=0,0,Q95/O95) -> 1346.904 | Q95: {=+INDEX('Réel 2024'!$A$2:$AO$501,MATCH($A95,'Réel 2024'!$A$2:$A$501,0),MATCH(Q$2,'Réel 2024'!$A$2:$AO$2,0))} -> 6734.52 | R95: =J95-O95 -> -5 | S95: =L95-Q95 -> -6734.52
A96: =B96&C96 -> Véhicules usagésAutres Marques | B96: Véhicules usagés | C96: Autres Marques | D96: =+INDEX('Budget original'!$A$2:$AO$501,MATCH($A96,'Budget original'!$A$2:$A$501,0),MATCH(D$2,'Budget original'!$A$2:$AO$2,0)) -> 5 | E96: =IF(D96=0,0,F96/D96) -> 1500 | F96: =+INDEX('Budget original'!$A$2:$AO$501,MATCH($A96,'Budget original'!$A$2:$A$501,0),MATCH(F$2,'Budget original'!$A$2:$AO$2,0)) -> 7500 | J96: =-SUMIFS(BV_Data_An_Cour!$O:$O,BV_Data_An_Cour!$U:$U,$B96,BV_Data_An_Cour!$V:$V,$C96,BV_Data_An_Cour!$W:$W,J$2) -> 0 | K96: =IF(J96=0,0,L96/J96) -> 0 | L96: =-SUMIFS(BV_Data_An_Cour!$O:$O,BV_Data_An_Cour!$U:$U,$B96,BV_Data_An_Cour!$V:$V,$C96,BV_Data_An_Cour!$W:$W,$L2) -> 0 | M96: =J96-D96 -> -5 | N96: =L96-F96 -> -7500 | O96: =+INDEX('Réel 2024'!$A$2:$AO$501,MATCH($A96,'Réel 2024'!$A$2:$A$501,0),MATCH(O$2,'Réel 2024'!$A$2:$AO$2,0)) -> 0 | P96: =IF(O96=0,0,Q96/O96) -> 0 | Q96: =+INDEX('Réel 2024'!$A$2:$AO$501,MATCH($A96,'Réel 2024'!$A$2:$A$501,0),MATCH(Q$2,'Réel 2024'!$A$2:$AO$2,0)) -> 0 | R96: =J96-O96 -> 0 | S96: =L96-Q96 -> 0
A97: =B97&C97 -> Véhicules usagésTotal Usagés | B97: Véhicules usagés | C97: Total Usagés | D97: =+D95+D94+D96 -> 34 | E97: =IF(D97=0,0,F97/D97) -> 1450 | F97: =+F94+F95+F96 -> 49300 | J97: =+J94+J95+J96 -> 28 | K97: =IF(J97<=0,0,L97/J97) -> 1004.9229 | L97: =+L94+L95+L96 -> 28137.84 | M97: =J97-D97 -> -6 | N97: =L97-F97 -> -21162.16 | O97: =+O95+O94+O96 -> 30 | P97: =IF(O97=0,0,Q97/O97) -> 1581.0627 | Q97: =+Q94+Q95+Q96 -> 47431.88 | R97: =R94+R95 -> -2 | S97: =S94+S95 -> -19294.04
A98: =B98&C98 -> Véhicules usagés | B98: Véhicules usagés | E98: =IF(D98=0,0,F98/D98) -> 0 | M98: =M97/D97 -> -0.17647059 | N98: =N97/F97 -> -0.42925274 | P98: =IF(O98=0,0,Q98/O98) -> 0 | R98: =R97/O97 -> -0.066666667 | S98: =IF(Q97=0,0,(S97/Q97)) -> -0.40677367
A99: =B99&C99 -> Véhicules usagés | B99: Véhicules usagés | D99: =+INDEX('Budget original'!$A$2:$AO$501,MATCH($A99,'Budget original'!$A$2:$A$501,0),MATCH(D$2,'Budget original'!$A$2:$AO$2,0)) -> 0 | E99: =IF(D99=0,0,F99/D99) -> 0 | F99: =+INDEX('Budget original'!$A$2:$AO$501,MATCH($A99,'Budget original'!$A$2:$A$501,0),MATCH(F$2,'Budget original'!$A$2:$AO$2,0)) -> 0
A100: Véhicules usagésVentes au Gros | B100: Véhicules usagés | C100: Ventes au Gros | D100: =+INDEX('Budget original'!$A$2:$AO$501,MATCH($A100,'Budget original'!$A$2:$A$501,0),MATCH(D$2,'Budget original'!$A$2:$AO$2,0)) -> 37 | E100: =IF(D100=0,0,F100/D100) -> 400 | F100: =+INDEX('Budget original'!$A$2:$AO$501,MATCH($A100,'Budget original'!$A$2:$A$501,0),MATCH(F$2,'Budget original'!$A$2:$AO$2,0)) -> 14800 | J100: =-SUMIFS(BV_Data_An_Cour!$O:$O,BV_Data_An_Cour!$U:$U,$B100,BV_Data_An_Cour!$V:$V,$C100,BV_Data_An_Cour!$W:$W,J$2) -> 51 | K100: =IF(J100=0,0,L100/J100) -> 737.09647 | L100: =-SUMIFS(BV_Data_An_Cour!$O:$O,BV_Data_An_Cour!$U:$U,$B100,BV_Data_An_Cour!$V:$V,$C100,BV_Data_An_Cour!$W:$W,L$2) -> 37591.92 | M100: =J100-D100 -> 14 | N100: =L100-F100 -> 22791.92 | O100: {=+INDEX('Réel 2024'!$A$2:$AO$501,MATCH($A100,'Réel 2024'!$A$2:$A$501,0),MATCH(O$2,'Réel 2024'!$A$2:$AO$2,0))} -> 37 | P100: =IF(O100=0,0,Q100/O100) -> -125.19595 | Q100: {=+INDEX('Réel 2024'!$A$2:$AO$501,MATCH($A100,'Réel 2024'!$A$2:$A$501,0),MATCH(Q$2,'Réel 2024'!$A$2:$AO$2,0))} -> -4632.25 | R100: =J100-O100 -> 14 | S100: =L100-Q100 -> 42224.17
A101: Véhicules usagés | B101: Véhicules usagés
A102: Véhicules usagésRev. Finances | B102: Véhicules usagés | C102: Rev. Finances | D102: =+INDEX('Budget original'!$A$2:$AO$501,MATCH($A102,'Budget original'!$A$2:$A$501,0),MATCH(D$2,'Budget original'!$A$2:$AO$2,0)) -> 0 | E102: =IF(D102=0,0,F102/D102) -> 0 | F102: =+INDEX('Budget original'!$A$2:$AO$501,MATCH($A102,'Budget original'!$A$2:$A$501,0),MATCH(F$2,'Budget original'!$A$2:$AO$2,0)) -> 20400 | K102: =IF(J97=0,0,L102/J97) -> 450.17429 | L102: =-SUMIFS(BV_Data_An_Cour!$O:$O,BV_Data_An_Cour!$U:$U,$B102,BV_Data_An_Cour!$V:$V,$C102,BV_Data_An_Cour!$W:$W,$L2) -> 12604.88 | N102: =L102-F102 -> -7795.12 | Q102: {=+INDEX('Réel 2024'!$A$2:$AO$501,MATCH($A102,'Réel 2024'!$A$2:$A$501,0),MATCH(Q$2,'Réel 2024'!$A$2:$AO$2,0))} -> 8266.65 | R102: =O102-K102 -> -450.17429 | S102: =L102-Q102 -> 4338.23
A103: Véhicules usagésRev. Protections | B103: Véhicules usagés | C103: Rev. Protections | D103: =+INDEX('Budget original'!$A$2:$AO$501,MATCH($A103,'Budget original'!$A$2:$A$501,0),MATCH(D$2,'Budget original'!$A$2:$AO$2,0)) -> 0 | E103: =IF(D103=0,0,F103/D103) -> 0 | F103: =+INDEX('Budget original'!$A$2:$AO$501,MATCH($A103,'Budget original'!$A$2:$A$501,0),MATCH(F$2,'Budget original'!$A$2:$AO$2,0)) -> 42500 | K103: =IF(J97=0,0,L103/J97) -> 1933.1911 | L103: =-SUMIFS(BV_Data_An_Cour!$O:$O,BV_Data_An_Cour!$U:$U,$B103,BV_Data_An_Cour!$V:$V,$C103,BV_Data_An_Cour!$W:$W,$L2) -> 54129.35 | N103: =L103-F103 -> 11629.35 | Q103: {=+INDEX('Réel 2024'!$A$2:$AO$501,MATCH($A103,'Réel 2024'!$A$2:$A$501,0),MATCH(Q$2,'Réel 2024'!$A$2:$AO$2,0))} -> 46940.15 | R103: =O103-K103 -> -1933.1911 | S103: =L103-Q103 -> 7189.2
A104: Véhicules usagésRev. Autres | B104: Véhicules usagés | C104: Rev. Autres | D104: =+INDEX('Budget original'!$A$2:$AO$501,MATCH($A104,'Budget original'!$A$2:$A$501,0),MATCH(D$2,'Budget original'!$A$2:$AO$2,0)) -> 0 | E104: =IF(D104=0,0,F104/D104) -> 0 | F104: =+INDEX('Budget original'!$A$2:$AO$501,MATCH($A104,'Budget original'!$A$2:$A$501,0),MATCH(F$2,'Budget original'!$A$2:$AO$2,0)) -> 1700 | K104: =IF(J97=0,0,L104/J97) -> 28.672143 | L104: =-SUMIFS(BV_Data_An_Cour!$O:$O,BV_Data_An_Cour!$U:$U,$B104,BV_Data_An_Cour!$V:$V,$C104,BV_Data_An_Cour!$W:$W,$L$2) -> 802.82 | N104: =L104-F104 -> -897.18 | Q104: {=+INDEX('Réel 2024'!$A$2:$AO$501,MATCH($A104,'Réel 2024'!$A$2:$A$501,0),MATCH(Q$2,'Réel 2024'!$A$2:$AO$2,0))} -> 2036.84 | R104: =O104-K104 -> -28.672143 | S104: =L104-Q104 -> -1234.02
A105: Véhicules usagésTotal F&I | B105: Véhicules usagés | C105: Total F&I | D105: =D97 -> 34 | E105: =IF(D105=0,0,F105/D105) -> 1900 | F105: =F102+F103+F104 -> 64600 | J105: =J97 -> 28 | K105: =IF(J105<=0,0,L105/J105) -> 2412.0375 | L105: =L102+L103+L104 -> 67537.05 | M105: =J105-D105 -> -6 | N105: =L105-F105 -> 2937.05 | O105: =O97 -> 30 | P105: =IF(O105=0,0,Q105/O105) -> 1908.1213 | Q105: =Q102+Q103+Q104 -> 57243.64 | S105: =L105-Q105 -> 10293.41
...

Sheet 2pager
B1: =Parametres!$B$1&" "&"2 pager"&" "&Parametres!$B$3&" "&Parametres!$B$4 -> Volks 2 pager Juillet 2025
B3: New | C3: Actual | D3: Budget | E3: 2023 | F3: ▲ Budget | G3: ▲2023 | H3: % ▲ Budget | I3: % ▲ 2023 | J3: Commentaires
B4: Units | C4: =+Print_Mois!$J$13+Print_Mois!$J$15 -> 81 | D4: =+Print_Mois!$D$13+Print_Mois!$D$15 -> 73 | E4: =+Print_Mois!$O$13+Print_Mois!$O$15 -> 80 | F4: =+IFERROR($C4-D4,"") -> 8 | G4: =+IFERROR($C4-E4,"") -> 1 | H4: =+IFERROR(F4/ABS($D4),"") -> 0.10958904 | I4: =+IFERROR(G4/ABS($E4),"") -> 0.0125 | J4: L'arrêt des livraisons ID4 a eu un impact significatif sur le mois de septembre. Les profits unitaires au budget n'en tenaient pas tant compte mais la comptétion tant inter-dealers qu'inter-marques a relancé les négociations sur les prix. Notre bureau commercial est encore sous le coup du turnover. Les autres revenus sont la conséquence directe de la baisse de volume d'unités livrées.
B5: Front Margin | C5: =+Print_Mois!$L$13+Print_Mois!$L$15 -> 175033.64 | D5: =+Print_Mois!$F$13+Print_Mois!$F$15 -> 165053.58 | E5: =+Print_Mois!$Q$13+Print_Mois!$Q$15 -> 169860.1 | F5: =+IFERROR($C5-D5,"") -> 9980.0633 | G5: =+IFERROR($C5-E5,"") -> 5173.54 | H5: =+IFERROR(F5/ABS($D5),"") -> 0.060465599 | I5: =+IFERROR(G5/ABS($E5),"") -> 0.030457653
B6: Front margin / unit | C6: =+C5/C4 -> 2160.9091 | D6: =+D5/D4 -> 2261.0079 | E6: =+E5/E4 -> 2123.2512 | F6: =+IFERROR($C6-D6,"") -> -100.09876 | G6: =+IFERROR($C6-E6,"") -> 37.657886 | H6: =+IFERROR(F6/ABS($D6),"") -> -0.044271744 | I6: =+IFERROR(G6/ABS($E6),"") -> 0.017735954
B7: $ Salaires et commission | C7: =+Print_Mois!$L$31 -> 52285.66 | D7: =+Print_Mois!$F$31 -> 53662.555 | E7: =+Print_Mois!$Q$31 -> 56983.01 | F7: =+IFERROR($C7-D7,"") -> -1376.8954 | G7: =+IFERROR($C7-E7,"") -> -4697.35 | H7: =+IFERROR(F7/ABS($D7),"") -> -0.025658401 | I7: =+IFERROR(G7/ABS($E7),"") -> -0.08243422
B8: % Salaires et commission | C8: =+C7/C5 -> 0.29871778 | D8: =+D7/D5 -> 0.32512204 | E8: =+E7/E5 -> 0.33547025 | F8: =+IFERROR($C8-D8,"") -> -0.026404261 | G8: =+IFERROR($C8-E8,"") -> -0.036752471 | H8: =+IFERROR(F8/ABS($D8),"") -> -0.081213384 | I8: =+IFERROR(G8/ABS($E8),"") -> -0.10955508
B9: Back Margin | C9: =+Print_Mois!$L$24 -> 80605.52 | D9: =+Print_Mois!$F$24 -> 73000 | E9: =+Print_Mois!$Q$24 -> 61556.7 | F9: =+IFERROR($C9-D9,"") -> 7605.52 | G9: =+IFERROR($C9-E9,"") -> 19048.82 | H9: =+IFERROR(F9/ABS($D9),"") -> 0.10418521 | I9: =+IFERROR(G9/ABS($E9),"") -> 0.30945161
B10: Back Margin / unit | C10: =+C9/C4 -> 995.12988 | D10: =+D9/D4 -> 1000 | E10: =+E9/E4 -> 769.45875 | F10: =+IFERROR($C10-D10,"") -> -4.8701235 | G10: =+IFERROR($C10-E10,"") -> 225.67113 | H10: =+IFERROR(F10/ABS($D10),"") -> -0.0048701235 | I10: =+IFERROR(G10/ABS($E10),"") -> 0.29328554
B11: $ commission FI | C11: =+Print_Mois!$L$32 -> 20151.54 | D11: =+Print_Mois!$F$32 -> 20440 | E11: =+Print_Mois!$Q$32 -> 16620.13 | F11: =+IFERROR($C11-D11,"") -> -288.46 | G11: =+IFERROR($C11-E11,"") -> 3531.41 | H11: =+IFERROR(F11/ABS($D11),"") -> -0.014112524 | I11: =+IFERROR(G11/ABS($E11),"") -> 0.21247788
B12: % commission FI | C12: =+C11/C9 -> 0.25000198 | D12: =+D11/D9 -> 0.28 | E12: =+E11/E9 -> 0.26999709 | F12: =+IFERROR($C12-D12,"") -> -0.029998015 | G12: =+IFERROR($C12-E12,"") -> -0.019995107 | H12: =+IFERROR(F12/ABS($D12),"") -> -0.10713577 | I12: =+IFERROR(G12/ABS($E12),"") -> -0.07405675
B13: Variable fees | C13: =+Print_Mois!$L$41-C7-C11 -> 38506.17 | D13: =+Print_Mois!$F$41-D7-D11 -> 62983.219 | E13: =+Print_Mois!$Q$41-E7-E11 -> 65063.75 | F13: =+IFERROR($C13-D13,"") -> -24477.049 | G13: =+IFERROR($C13-E13,"") -> -26557.58 | H13: =+IFERROR(F13/ABS($D13),"") -> -0.38862811 | I13: =+IFERROR(G13/ABS($E13),"") -> -0.40817783
B14: Variable fees / units | C14: =+C13/C4 -> 475.38481 | D14: =+D13/D4 -> 862.78382 | E14: =+E13/E4 -> 813.29687 | F14: =+IFERROR($C14-D14,"") -> -387.39901 | G14: =+IFERROR($C14-E14,"") -> -337.91206 | H14: =+IFERROR(F14/ABS($D14),"") -> -0.44901052 | I14: =+IFERROR(G14/ABS($E14),"") -> -0.41548427
B15: Other Revenues | C15: =+Print_Mois!$L$83 -> 134474.85 | D15: =+Print_Mois!$F$83 -> 140149.09 | E15: =+Print_Mois!$Q$83 -> 181200 | F15: =+IFERROR($C15-D15,"") -> -5674.2436 | G15: =+IFERROR($C15-E15,"") -> -46725.15 | H15: =+IFERROR(F15/ABS($D15),"") -> -0.040487195 | I15: =+IFERROR(G15/ABS($E15),"") -> -0.25786507
B16: Inventory
B17: Units | C17: =Inventaire_Neuf!L3 -> 71 | D17: 61 | E17: 164 | F17: =+IFERROR($C17-D17,"") -> 10 | G17: =+IFERROR($C17-E17,"") -> -93 | H17: =+IFERROR(F17/ABS($D17),"") -> 0.16393443 | I17: =+IFERROR(G17/ABS($E17),"") -> -0.56707317
B18: $ | C18: =Inventaire_Neuf!L2 -> 3059537.1 | D18: 2233570 | E18: 5689693.2 | F18: =+IFERROR($C18-D18,"") -> 825967.15 | G18: =+IFERROR($C18-E18,"") -> -2630156 | H18: =+IFERROR(F18/ABS($D18),"") -> 0.36979685 | I18: =+IFERROR(G18/ABS($E18),"") -> -0.46226676
B20: Used | C20: Actual | D20: Budget | E20: =$E$3 -> 2023 | F20: ▲ Budget | G20: =$G$3 -> ▲2023 | H20: % ▲ Budget | I20: =$I$3 -> % ▲ 2023 | J20: Commentaires
B21: Units | C21: =+Print_Mois!$J$97 -> 28 | D21: =+Print_Mois!$D$97 -> 34 | E21: =+Print_Mois!$O$97 -> 30 | F21: =+IFERROR($C21-D21,"") -> -6 | G21: =+IFERROR($C21-E21,"") -> -2 | H21: =+IFERROR(F21/ABS($D21),"") -> -0.17647059 | I21: =+IFERROR(G21/ABS($E21),"") -> -0.066666667 | J21: Le volume et les résultats du bureau commercial sont maintenant en ligne avec les attentes. Le profit unitaire "front" est le dernier sujet d'ajustement côté chiffre en même temps que la prise de contrôle des leads, du temps de réponse et de ce que l'on en fait ! Invenaire sain, marchandisage optimisé. Il nous reste à être extrèmement vigilants et rigoureux dans le suivi de ces opérations.
B22: Front Margin | C22: =+Print_Mois!$L$97 -> 28137.84 | D22: =+Print_Mois!$F$97 -> 49300 | E22: =+Print_Mois!$Q$97 -> 47431.88 | F22: =+IFERROR($C22-D22,"") -> -21162.16 | G22: =+IFERROR($C22-E22,"") -> -19294.04 | H22: =+IFERROR(F22/ABS($D22),"") -> -0.42925274 | I22: =+IFERROR(G22/ABS($E22),"") -> -0.40677367
B23: Front margin / unit | C23: =+C22/C21 -> 1004.9229 | D23: =+D22/D21 -> 1450 | E23: =+E22/E21 -> 1581.0627 | F23: =+IFERROR($C23-D23,"") -> -445.07714 | G23: =+IFERROR($C23-E23,"") -> -576.13981 | H23: =+IFERROR(F23/ABS($D23),"") -> -0.30694975 | I23: =+IFERROR(G23/ABS($E23),"") -> -0.36440036
B24: $ Salaires et commission | C24: =+Print_Mois!$L$112 -> 12008.3 | D24: =+Print_Mois!$F$112 -> 16644.205 | E24: =+Print_Mois!$Q$112 -> 15040.14 | F24: =+IFERROR($C24-D24,"") -> -4635.9049 | G24: =+IFERROR($C24-E24,"") -> -3031.84 | H24: =+IFERROR(F24/ABS($D24),"") -> -0.27852967 | I24: =+IFERROR(G24/ABS($E24),"") -> -0.20158323
B25: % Salaires et commission | C25: =+C24/C22 -> 0.42676694 | D25: =+D24/D22 -> 0.33761065 | E25: =+E24/E22 -> 0.31708927 | F25: =+IFERROR($C25-D25,"") -> 0.089156298 | G25: =+IFERROR($C25-E25,"") -> 0.10967768 | H25: =+IFERROR(F25/ABS($D25),"") -> 0.26408023 | I25: =+IFERROR(G25/ABS($E25),"") -> 0.34588897
B26: Back Margin | C26: =+Print_Mois!$L$105 -> 67537.05 | D26: =+Print_Mois!$F$105 -> 64600 | E26: =+Print_Mois!$Q$105 -> 57243.64 | F26: =+IFERROR($C26-D26,"") -> 2937.05 | G26: =+IFERROR($C26-E26,"") -> 10293.41 | H26: =+IFERROR(F26/ABS($D26),"") -> 0.04546517 | I26: =+IFERROR(G26/ABS($E26),"") -> 0.17981753
B27: Back Margin / unit | C27: =+C26/C21 -> 2412.0375 | D27: =+D26/D21 -> 1900 | E27: =+E26/E21 -> 1908.1213 | F27: =+IFERROR($C27-D27,"") -> 512.0375 | G27: =+IFERROR($C27-E27,"") -> 503.91617 | H27: =+IFERROR(F27/ABS($D27),"") -> 0.26949342 | I27: =+IFERROR(G27/ABS($E27),"") -> 0.26409021
B28: $ commission FI | C28: =+Print_Mois!$L$113 -> 20164.34 | D28: =+Print_Mois!$F$113 -> 19380 | E28: =+Print_Mois!$Q$113 -> 17173.36 | F28: =+IFERROR($C28-D28,"") -> 784.34 | G28: =+IFERROR($C28-E28,"") -> 2990.98 | H28: =+IFERROR(F28/ABS($D28),"") -> 0.04047162 | I28: =+IFERROR(G28/ABS($E28),"") -> 0.17416394
B29: % commission FI | C29: =+C28/C26 -> 0.29856708 | D29: =+D28/D26 -> 0.3 | E29: =+E28/E26 -> 0.30000468 | F29: =+IFERROR($C29-D29,"") -> -0.0014329172 | G29: =+IFERROR($C29-E29,"") -> -0.0014375989 | H29: =+IFERROR(F29/ABS($D29),"") -> -0.0047763906 | I29: =+IFERROR(G29/ABS($E29),"") -> -0.0047919217
B30: Variable fees | C30: =+Print_Mois!$L$122-C24-C28 -> 20250.55 | D30: =+Print_Mois!$F$122-D24-D28 -> 26365.46 | E30: =+Print_Mois!$Q$122-E24-E28 -> 22458.87 | F30: =+IFERROR($C30-D30,"") -> -6114.9095 | G30: =+IFERROR($C30-E30,"") -> -2208.32 | H30: =+IFERROR(F30/ABS($D30),"") -> -0.23192881 | I30: =+IFERROR(G30/ABS($E30),"") -> -0.098327298
B31: Variable fees / units | C31: =+C30/C21 -> 723.23393 | D31: =+D30/D21 -> 775.45469 | E31: =+E30/E21 -> 748.629 | F31: =+IFERROR($C31-D31,"") -> -52.220764 | G31: =+IFERROR($C31-E31,"") -> -25.395071 | H31: =+IFERROR(F31/ABS($D31),"") -> -0.067342121 | I31: =+IFERROR(G31/ABS($E31),"") -> -0.033922105
B32: Other Revenues | C32: =+Print_Mois!$L$163 -> 12504 | D32: =+Print_Mois!$F$163 -> 12887.7 | E32: =+Print_Mois!$Q$163 -> 12594 | F32: =+IFERROR($C32-D32,"") -> -383.7 | G32: =+IFERROR($C32-E32,"") -> -90 | H32: =+IFERROR(F32/ABS($D32),"") -> -0.029772574 | I32: =+IFERROR(G32/ABS($E32),"") -> -0.0071462601
B33: Inventory
B34: Units | C34: =Inventaire_Used!N3 -> 111 | D34: 68 | E34: 92 | F34: =+IFERROR($C34-D34,"") -> 43 | G34: =+IFERROR($C34-E34,"") -> 19 | H34: =+IFERROR(F34/ABS($D34),"") -> 0.63235294 | I34: =+IFERROR(G34/ABS($E34),"") -> 0.20652174
B35: $ | C35: =Inventaire_Used!N2 -> 2779322.1 | D35: 1072231 | E35: 1510979 | F35: =+IFERROR($C35-D35,"") -> 1707091.1 | G35: =+IFERROR($C35-E35,"") -> 1268343.1 | H35: =+IFERROR(F35/ABS($D35),"") -> 1.5920927 | I35: =+IFERROR(G35/ABS($E35),"") -> 0.83941809
B37: Service | C37: Actual | D37: Budget | E37: =$E$3 -> 2023 | F37: ▲ Budget | G37: =$G$3 -> ▲2023 | H37: % ▲ Budget | I37: =$I$3 -> % ▲ 2023 | J37: Commentaires
B38: Revenus | C38: =+Print_Mois!$K$194 -> 337642.8 | D38: =+Print_Mois!$E$194 -> 304520.43 | E38: =+Print_Mois!$P$194 -> 289832.12 | F38: =+IFERROR($C38-D38,"") -> 33122.369 | G38: =+IFERROR($C38-E38,"") -> 47810.68 | H38: =+IFERROR(F38/ABS($D38),"") -> 0.10876895 | I38: =+IFERROR(G38/ABS($E38),"") -> 0.16495991 | J38: Très belle progression versus 2023, autant sur le fait de voir monter le brut globalement que sur le contrôle des dépenses. Le modèle de fonctionnement de la mixité de véhicules de courtoisies, Uber Pro et chauffeurs fonctionne. Bon mois de Csi à côté de la performance financière.
B39: Gross margin | C39: =+Print_Mois!$L$194 -> 241303.18 | D39: =+Print_Mois!$F$194 -> 212692.64 | E39: =+Print_Mois!$Q$194 -> 207116.96 | F39: =+IFERROR($C39-D39,"") -> 28610.54 | G39: =+IFERROR($C39-E39,"") -> 34186.22 | H39: =+IFERROR(F39/ABS($D39),"") -> 0.13451589 | I39: =+IFERROR(G39/ABS($E39),"") -> 0.16505756
B40: $ Revenus / #WO client | C40: =+Print_Mois!$K$172/Print_Mois!$J$172 -> 338.76512 | D40: =+IFERROR(Print_Mois!$E$172/Print_Mois!$D$172,"") -> 340 | E40: =+Print_Mois!$P$172/Print_Mois!$O$172 -> 387.01669 | F40: =+IFERROR($C40-D40,"") -> -1.2348756 | G40: =+IFERROR($C40-E40,"") -> -48.251562 | H40: =+IFERROR(F40/ABS($D40),"") -> -0.0036319871 | I40: =+IFERROR(G40/ABS($E40),"") -> -0.12467566
B41: $ Revenus / #WO garantie | C41: =+Print_Mois!$K$175/Print_Mois!$J$175 -> 324.71142 | D41: =+IFERROR(Print_Mois!$E$175/Print_Mois!$D$175,"") -> 270 | E41: =+Print_Mois!$P$175/Print_Mois!$O$175 -> 339.96528 | F41: =+IFERROR($C41-D41,"") -> 54.711422 | G41: =+IFERROR($C41-E41,"") -> -15.253854 | H41: =+IFERROR(F41/ABS($D41),"") -> 0.2026349 | I41: =+IFERROR(G41/ABS($E41),"") -> -0.044868858
B42: Lost time | C42: =+Print_Mois!$L$184 -> -1154.13 | D42: =+Print_Mois!$F$184 -> -3339.3512 | E42: =+Print_Mois!$Q$184 -> -1170.23 | F42: =+IFERROR($C42-D42,"") -> 2185.2212 | G42: =+IFERROR($C42-E42,"") -> 16.1 | H42: =+IFERROR(F42/ABS($D42),"") -> 0.65438496 | I42: =+IFERROR(G42/ABS($E42),"") -> 0.013757979
B43: Total salaries | C43: =+Print_Mois!$L$210 -> 108311.01 | D43: =+Print_Mois!$F$210 -> 117062.61 | E43: =+Print_Mois!$Q$210 -> 109232.29 | F43: =+IFERROR($C43-D43,"") -> -8751.5969 | G43: =+IFERROR($C43-E43,"") -> -921.28 | H43: =+IFERROR(F43/ABS($D43),"") -> -0.074759969 | I43: =+IFERROR(G43/ABS($E43),"") -> -0.0084341361
B44: Salaries | C44: =+SUM(Print_Mois!$L$198:$L$204) -> 59281.8 | D44: =+SUM(Print_Mois!$F$198:$F$204) -> 66392.858 | E44: =+SUM(Print_Mois!$Q$198:$Q$204) -> 58735.18 | F44: =+IFERROR($C44-D44,"") -> -7111.0579 | G44: =+IFERROR($C44-E44,"") -> 546.62 | H44: =+IFERROR(F44/ABS($D44),"") -> -0.10710577 | I44: =+IFERROR(G44/ABS($E44),"") -> 0.0093065178
B45: Fringes | C45: =+SUM(Print_Mois!$L$205:$L$209) -> 49029.21 | D45: =+SUM(Print_Mois!$F$205:$F$209) -> 50669.749 | E45: =+SUM(Print_Mois!$Q$205:$Q$209) -> 50497.11 | F45: =+IFERROR($C45-D45,"") -> -1640.539 | G45: =+IFERROR($C45-E45,"") -> -1467.9 | H45: =+IFERROR(F45/ABS($D45),"") -> -0.032377089 | I45: =+IFERROR(G45/ABS($E45),"") -> -0.02906899
B46: Total salaries / Revenus | C46: =+C43/C38 -> 0.32078578 | D46: =+D43/D38 -> 0.38441627 | E46: =+E43/E38 -> 0.37688124 | F46: =+IFERROR($C46-D46,"") -> -0.063630482 | G46: =+IFERROR($C46-E46,"") -> -0.056095461 | H46: =+IFERROR(F46/ABS($D46),"") -> -0.16552495 | I46: =+IFERROR(G46/ABS($E46),"") -> -0.14884121
B47: Frais véhicules de cie | C47: =+Print_Mois!$L$213 -> 12916.71 | D47: =+Print_Mois!$F$213 -> 11083.739 | E47: =+Print_Mois!$Q$213 -> 15457.5 | F47: =+IFERROR($C47-D47,"") -> 1832.9706 | G47: =+IFERROR($C47-E47,"") -> -2540.79 | H47: =+IFERROR(F47/ABS($D47),"") -> 0.16537475 | I47: =+IFERROR(G47/ABS($E47),"") -> -0.16437263
B49: Pieces | C49: Actual | D49: Budget | E49: =$E$3 -> 2023 | F49: ▲ Budget | G49: =$G$3 -> ▲2023 | H49: % ▲ Budget | I49: =$I$3 -> % ▲ 2023 | J49: Commentaires
B50: Revenus | C50: =+Print_Mois!$J$314 -> 535619.36 | D50: =+Print_Mois!$D$314 -> 450860.7 | E50: =+Print_Mois!$O$314 -> 420612.72 | F50: =+IFERROR($C50-D50,"") -> 84758.659 | G50: =+IFERROR($C50-E50,"") -> 115006.64 | H50: =+IFERROR(F50/ABS($D50),"") -> 0.18799301 | I50: =+IFERROR(G50/ABS($E50),"") -> 0.27342644 | J50: Le wholesale est LA machine du département. Analyse rapide mais son point le plus avantageux est la portion de booster le volume d'achats chez l'OEM. Car en fait de $ de ventes, on mobilise quasiment 1 employé, beaucoup d'espace et la quasi-totalité de nos crédits de retour gratuits chez VW. Notre commis sénior n'a pas la maturité analytique pour faire des choix d'anticipation stratégique. Sujet à creuser avant fin q4.
B51: Clients | C51: =+Print_Mois!$J$295 -> 87058.76 | D51: =+Print_Mois!$D$295 -> 81099.138 | E51: =+Print_Mois!$O$295 -> 97246.46 | F51: =+IFERROR($C51-D51,"") -> 5959.6222 | G51: =+IFERROR($C51-E51,"") -> -10187.7 | H51: =+IFERROR(F51/ABS($D51),"") -> 0.073485641 | I51: =+IFERROR(G51/ABS($E51),"") -> -0.10476165
B52: Garantie | C52: =+Print_Mois!$J$297 -> 95506.71 | D52: =+Print_Mois!$D$297 -> 60847.342 | E52: =+Print_Mois!$O$297 -> 63908.64 | F52: =+IFERROR($C52-D52,"") -> 34659.368 | G52: =+IFERROR($C52-E52,"") -> 31598.07 | H52: =+IFERROR(F52/ABS($D52),"") -> 0.56961185 | I52: =+IFERROR(G52/ABS($E52),"") -> 0.49442564
B53: Wholesale | C53: =+Print_Mois!$J$300 -> 186492.61 | D53: =+Print_Mois!$D$300 -> 153843.46 | E53: =+Print_Mois!$O$300 -> 143365.44 | F53: =+IFERROR($C53-D53,"") -> 32649.151 | G53: =+IFERROR($C53-E53,"") -> 43127.17 | H53: =+IFERROR(F53/ABS($D53),"") -> 0.2122232 | I53: =+IFERROR(G53/ABS($E53),"") -> 0.30081985
B54: Tires | C54: =+Print_Mois!$J$307 -> 32612.16 | D54: =+Print_Mois!$D$307 -> 23014.84 | E54: =+Print_Mois!$O$307 -> 17894.14 | F54: =+IFERROR($C54-D54,"") -> 9597.32 | G54: =+IFERROR($C54-E54,"") -> 14718.02 | H54: =+IFERROR(F54/ABS($D54),"") -> 0.41700572 | I54: =+IFERROR(G54/ABS($E54),"") -> 0.82250502
B55: All others | C55: =+C50-SUM(C51:C54) -> 133949.12 | D55: =+D50-SUM(D51:D54) -> 132055.92 | E55: =+E50-SUM(E51:E54) -> 98198.04 | F55: =+IFERROR($C55-D55,"") -> 1893.1987 | G55: =+IFERROR($C55-E55,"") -> 35751.08 | H55: =+IFERROR(F55/ABS($D55),"") -> 0.014336341 | I55: =+IFERROR(G55/ABS($E55),"") -> 0.36407122
B56: Gross margin | C56: =+Print_Mois!$L$314 -> 125086.84 | D56: =+Print_Mois!$F$314 -> 114969.37 | E56: =+Print_Mois!$Q$314 -> 104719.71 | F56: =+IFERROR($C56-D56,"") -> 10117.469 | G56: =+IFERROR($C56-E56,"") -> 20367.13 | H56: =+IFERROR(F56/ABS($D56),"") -> 0.088001432 | I56: =+IFERROR(G56/ABS($E56),"") -> 0.19449185
B57: $ Revenus / #WO client | C57: =+Print_Mois!$J$295/Print_Mois!$J$172 -> 216.56408 | D57: =+IFERROR(Print_Mois!$D$295/Print_Mois!$D$172,"") -> 193.222 | E57: =+Print_Mois!$O$295/Print_Mois!$O$172 -> 292.91102 | F57: =+IFERROR($C57-D57,"") -> 23.34208 | G57: =+IFERROR($C57-E57,"") -> -76.346944 | H57: =+IFERROR(F57/ABS($D57),"") -> 0.12080446 | I57: =+IFERROR(G57/ABS($E57),"") -> -0.26064893
B58: $ Revenus / #WO garantie | C58: =+Print_Mois!$J$297/Print_Mois!$J$175 -> 452.63844 | D58: =+IFERROR(Print_Mois!$D$297/Print_Mois!$D$175,"") -> 407.46898 | E58: =+Print_Mois!$O$297/Print_Mois!$O$175 -> 503.21764 | F58: =+IFERROR($C58-D58,"") -> 45.169458 | G58: =+IFERROR($C58-E58,"") -> -50.579202 | H58: =+IFERROR(F58/ABS($D58),"") -> 0.11085373 | I58: =+IFERROR(G58/ABS($E58),"") -> -0.10051158
B59: Salaires autres | C59: =+Print_Mois!$L$320 -> 113.92 | D59: =+Print_Mois!$F$320 -> 140.24615 | E59: =+Print_Mois!$Q$320 -> 113.92 | F59: =+IFERROR($C59-D59,"") -> -26.326154 | G59: =+IFERROR($C59-E59,"") -> 0 | H59: =+IFERROR(F59/ABS($D59),"") -> -0.18771391 | I59: =+IFERROR(G59/ABS($E59),"") -> 0
B61: Others | C61: Actual | D61: Budget | E61: =$E$3 -> 2023 | F61: ▲ Budget | G61: =$G$3 -> ▲2023 | H61: % ▲ Budget | I61: =$I$3 -> % ▲ 2023 | J61: Commentaires
B62: Total salaries / Gross profits | C62: =+Print_Mois!$AF$433/Print_Mois!$AF$407 -> 0.36057553 | D62: =+Print_Mois!$Z$433/Print_Mois!$Z$407 -> 0.42517969 | E62: =+Print_Mois!$AL$433/Print_Mois!$AL$407 -> 0.39968829 | F62: =+IFERROR($C62-D62,"") -> -0.064604151 | G62: =+IFERROR($C62-E62,"") -> -0.039112757 | H62: =+IFERROR(F62/ABS($D62),"") -> -0.15194553 | I62: =+IFERROR(G62/ABS($E62),"") -> -0.09785815
B63: Headcounts | C63: 57 | D63: 59 | E63: 56 | F63: =+IFERROR($C63-D63,"") -> -2 | G63: =+IFERROR($C63-E63,"") -> 1 | H63: =+IFERROR(F63/ABS($D63),"") -> -0.033898305 | I63: =+IFERROR(G63/ABS($E63),"") -> 0.017857143
B64: Marketing | C64: =N17+Print_Mois!$AF$414+Print_Mois!$AF$434 -> 26906.44 | D64: =+Print_Mois!$Z$414+Print_Mois!$Z$434 -> 28236.953 | E64: =+Print_Mois!$AL$414+Print_Mois!$AL$434 -> 29641.07 | F64: =+IFERROR($C64-D64,"") -> -1330.5131 | G64: =+IFERROR($C64-E64,"") -> -2734.63 | H64: =+IFERROR(F64/ABS($D64),"") -> -0.04711957 | I64: =+IFERROR(G64/ABS($E64),"") -> -0.09225814
B65: Other semi-fixed expenses | C65: =+Print_Mois!$AF$452-Print_Mois!$AF$434 -> 120011.21 | D65: =+Print_Mois!$Z$452-Print_Mois!$Z$434 -> 111418.21 | E65: =+Print_Mois!$AL$452-Print_Mois!$AL$434 -> 110604.75 | F65: =+IFERROR($C65-D65,"") -> 8593.0011 | G65: =+IFERROR($C65-E65,"") -> 9406.46 | H65: =+IFERROR(F65/ABS($D65),"") -> 0.077123848 | I65: =+IFERROR(G65/ABS($E65),"") -> 0.085045715
B66: Floor plan interest | C66: =+Print_Mois!$AF$415 -> 26209.15 | D66: =+Print_Mois!$Z$415 -> 48122.929 | E66: =+Print_Mois!$AL$415 -> 49031.8 | F66: =+IFERROR($C66-D66,"") -> -21913.779 | G66: =+IFERROR($C66-E66,"") -> -22822.65 | H66: =+IFERROR(F66/ABS($D66),"") -> -0.45537085 | I66: =+IFERROR(G66/ABS($E66),"") -> -0.46546629
B67: Others Revenues | C67: =+Print_Mois!$AF$481-C32-C15 -> 67.01 | D67: =+Print_Mois!$Z$481-D32-D15 -> 0 | E67: =+Print_Mois!$AL$481-E32-E15 -> 7191.32 | F67: =+IFERROR($C67-D67,"") -> 67.01 | G67: =+IFERROR($C67-E67,"") -> -7124.31 | H67: =+IFERROR(F67/ABS($D67),"") | I67: =+IFERROR(G67/ABS($E67),"") -> -0.99068182
B69: P&L | C69: Actual | D69: Budget | E69: =$E$3 -> 2023 | F69: ▲ Budget | G69: =$G$3 -> ▲2023 | H69: % ▲ Budget | I69: =$I$3 -> % ▲ 2023 | J69: Commentaires
B70: Selling and Marketing | C70: =+Print_Mois!$AF$419-Print_Mois!$AF$415+Print_Mois!$AF$434+Print_Mois!$AF$435+Print_Mois!$AF$436 -> 176094.18 | D70: =+Print_Mois!$Z$419-Print_Mois!$Z$415+Print_Mois!$Z$434+Print_Mois!$Z$435+Print_Mois!$Z$436 -> 190800.11 | E70: =+Print_Mois!$AL$419-Print_Mois!$AL$415+Print_Mois!$AL$434+Print_Mois!$AL$435+Print_Mois!$AL$436 -> 191307.8 | F70: =+IFERROR($C70-D70,"") -> -14705.929 | G70: =+IFERROR($C70-E70,"") -> -15213.62 | H70: =+IFERROR(F70/ABS($D70),"") -> -0.077075056 | I70: =+IFERROR(G70/ABS($E70),"") -> -0.079524306 | J70: Malgré une baisse des bruts aux ventes nous restons forts sur nos coût et donc cela génère une amélioration légère de notre EBITDA versus 2023, c'est notre objectif qui sera aussi celui des derniers mois de 2024.
B71: S&M / Brut | C71: =+C70/Print_Mois!$AF$407 -> 0.22647402 | D71: =+D70/Print_Mois!$Z$407 -> 0.26595564 | E71: =+E70/Print_Mois!$AL$407 -> 0.28685383 | F71: =+IFERROR($C71-D71,"") -> -0.039481616 | G71: =+IFERROR($C71-E71,"") -> -0.06037981 | H71: =+IFERROR(F71/ABS($D71),"") -> -0.14845189 | I71: =+IFERROR(G71/ABS($E71),"") -> -0.21048982
B72: General & administrative | C72: =+Print_Mois!$AF$466+Print_Mois!$AF$433+Print_Mois!$AF$437+Print_Mois!$AF$439+SUM(Print_Mois!$AF$440:$AF$448)+Print_Mois!$AF$438 -> 443067.69 | D72: =+Print_Mois!$Z$466+Print_Mois!$Z$433+Print_Mois!$Z$437+Print_Mois!$Z$439+SUM(Print_Mois!$Z$440:$Z$448)+Print_Mois!$Z$438 -> 451418.3 | E72: =+Print_Mois!$AL$466+Print_Mois!$AL$433+Print_Mois!$AL$437+Print_Mois!$AL$439+SUM(Print_Mois!$AL$440:$AL$448)+Print_Mois!$AL$438 -> 405762.54 | F72: =+IFERROR($C72-D72,"") -> -8350.6137 | G72: =+IFERROR($C72-E72,"") -> 37305.15 | H72: =+IFERROR(F72/ABS($D72),"") -> -0.018498616 | I72: =+IFERROR(G72/ABS($E72),"") -> 0.091938379
B73: G&A / Brut | C73: =+C72/Print_Mois!$AF$407 -> 0.56982759 | D73: =+D72/Print_Mois!$Z$407 -> 0.62923047 | E73: =+E72/Print_Mois!$AL$407 -> 0.60841502 | F73: =+IFERROR($C73-D73,"") -> -0.059402885 | G73: =+IFERROR($C73-E73,"") -> -0.038587436 | H73: =+IFERROR(F73/ABS($D73),"") -> -0.094405608 | I73: =+IFERROR(G73/ABS($E73),"") -> -0.063422885
B74: EBITDA | C74: =+Print_Mois!$AF$483+Print_Mois!$AF$415 -> 305430.92 | D74: =+Print_Mois!$Z$483+Print_Mois!$Z$415 -> 228231.67 | E74: =+Print_Mois!$AL$483+Print_Mois!$AL$415 -> 270832.34 | F74: =+IFERROR($C74-D74,"") -> 77199.247 | G74: =+IFERROR($C74-E74,"") -> 34598.58 | H74: =+IFERROR(F74/ABS($D74),"") -> 0.33824949 | I74: =+IFERROR(G74/ABS($E74),"") -> 0.12774907
B75: EBITDA % | C75: =+C74/Print_Mois!$AF$406 -> 0.045254528 | D75: =+D74/Print_Mois!$Z$406 -> 0.036314564 | E75: =+E74/Print_Mois!$AL$406 -> 0.040714689 | F75: =+IFERROR($C75-D75,"") -> 0.0089399639 | G75: =+IFERROR($C75-E75,"") -> 0.004539839 | H75: =+IFERROR(F75/ABS($D75),"") -> 0.24618123 | I75: =+IFERROR(G75/ABS($E75),"") -> 0.11150371
B76: EBIT | C76: =N9+Print_Mois!$AF$498 -> 237652.77 | D76: =+Print_Mois!$Z$498 -> 137539.91 | E76: =+Print_Mois!$AL$498 -> 190691.56 | F76: =+IFERROR($C76-D76,"") -> 100112.86 | G76: =+IFERROR($C76-E76,"") -> 46961.21 | H76: =+IFERROR(F76/ABS($D76),"") -> 0.72788225 | I76: =+IFERROR(G76/ABS($E76),"") -> 0.2462679
B77: EBIT % | C77: =+C76/Print_Mois!$AF$406 -> 0.035212099 | D77: =+D76/Print_Mois!$Z$406 -> 0.02188435 | E77: =+E76/Print_Mois!$AL$406 -> 0.028666988 | F77: =+IFERROR($C77-D77,"") -> 0.013327749 | G77: =+IFERROR($C77-E77,"") -> 0.006545111 | H77: =+IFERROR(F77/ABS($D77),"") -> 0.60900821 | I77: =+IFERROR(G77/ABS($E77),"") -> 0.22831526
B79: "Pacing" du 30
B80: EBITDA | C80: 262310 | D80: 0.03
B81: Écart Fav / (Défav) | C81: =+C74-C80 -> 43120.92
B83: EBIT | C83: 171618 | D83: 0.014
B84: Écart Fav / (Défav) | C84: =+C76-C83 -> 66034.77
B86: =+Parametres!B1 -> Volks | C86: =Parametres!$B$3&" "&Parametres!$B$4 -> Juillet 2025 | D86: AAJ
B87: =CONCATENATE("Réalisé ",Parametres!$B$3," ",Parametres!$B$4) -> Réalisé Juillet 2025 | C87: =+C76 -> 237652.77 | D87: =+Print_AAD!AF498 -> 671057.64
B88: =CONCATENATE("Budget ",Parametres!$B$3," ",Parametres!$B$4) -> Budget Juillet 2025 | C88: =+D76 -> 137539.91 | D88: =+Print_AAD!Z498 -> 498062.8
B89: =CONCATENATE("Réalisé ",Parametres!$B$3," ",Parametres!$B$4-1) -> Réalisé Juillet 2024 | C89: =+E76 -> 190691.56 | D89: =+Print_AAD!AL498 -> 648284.07

Sheet Démo
B1: Suivi de Démo
B2: # Stock | C2: NIV | D2: Année | E2: Marque | F2: Modèle | G2: $ Valeur | H2: Nom | I2: Prénom | J2: Titre / Fonction
H3: BEAUVAIS | I3: FREDERIC | J3: DG
H4: PARADIS | I4: ALEXANDRE | J4: DIRECTEUR ADJ VENTE
H5: CABALLERO | I5: JUAN ANDRES | J5: CONSEILLER VENTE

Sheet Wholesale
C1: ="Analyse Wholesale "&Parametres!B1 -> Analyse Wholesale Volks
D2: $ | F2: X | G2: U | L2: $ | N2: X | O2: U
E4: =CONCATENATE("Pièces Wholesale ",Parametres!B3," ",Parametres!B4) -> Pièces Wholesale Juillet 2025 | J4: =CONCATENATE("Pièces Wholesale AAD ",Parametres!B4) -> Pièces Wholesale AAD 2025
E5: Réel | F5: Budget | G5: ▲ $ | H5: ▲ % | J5: Réel | K5: Budget | L5: ▲ $ | M5: ▲ %
C6: NB de livraisons | E6: =SUMIF(A37:A48,"X",E37:E48) -> 558 | F6: =SUMIF(A37:A48,"X",F37:F48) -> 0 | G6: =E6-F6 -> 558 | H6: =G6/F6 -> #DIV/0! | J6: =SUMIF($B$37:$B$48,"X",$E$37:$E$48) -> 3784 | K6: =SUMIF($B$37:$B$48,"X",$F$37:$F$48) -> 0 | L6: =J6-K6 -> 3784 | M6: =L6/K6 -> #DIV/0!
A7: =B7&C7 -> piècesVentes de Gros | B7: pièces | C7: Ventes de Gros | E7: =-SUMIFS(BV_Data_An_Cour!$O:$O,BV_Data_An_Cour!$X:$X,"Oui",BV_Data_An_Cour!$U:$U,$B7,BV_Data_An_Cour!$V:$V,$C7) -> 186492.61 | F7: =+INDEX('Budget original'!$A$2:$AO$501,MATCH($A7,'Budget original'!$A$2:$A$501,0),MATCH(F$2,'Budget original'!$A$2:$AO$2,0)) -> 153843.46 | G7: =E7-F7 -> 32649.151 | H7: =G7/F7 -> 0.2122232 | J7: =-SUMIFS(BV_Data_An_Cour!$P:$P,BV_Data_An_Cour!$X:$X,"Oui",BV_Data_An_Cour!$U:$U,$B7,BV_Data_An_Cour!$V:$V,$C7) -> 1348594.2 | K7: {=+SUMPRODUCT(('Budget original'!$A$8:$A$501=$A7)*('Budget original'!$C$3:$AO$3=N$2),'Budget original'!$C$8:$AO$501)} -> 1096883.9 | L7: =J7-K7 -> 251710.34 | M7: =L7/K7 -> 0.22947765
C8: Coûts | E8: =E7-E9 -> 155905.34 | F8: =F7-F9 -> 129243.75 | G8: =E8-F8 -> 26661.591 | H8: =G8/F8 -> 0.20628921 | J8: =J7-J9 -> 1121550.5 | K8: =K7-K9 -> 921968.55 | L8: =J8-K8 -> 199581.92 | M8: =L8/K8 -> 0.21647368
C9: Profit brut | E9: =E12+E11 -> 30587.27 | F9: =F12+F11 -> 24599.71 | G9: =E9-F9 -> 5987.5598 | H9: =G9/F9 -> 0.24339961 | J9: =J12+J11 -> 227043.75 | K9: =K12+K11 -> 174915.34 | L9: =J9-K9 -> 52128.413 | M9: =L9/K9 -> 0.29802083
C10: % avant redevances | E10: =E9/E7 -> 0.16401331 | F10: =F9/F7 -> 0.15990092 | G10: =E10-F10 -> 0.0041123913 | J10: =J9/J7 -> 0.16835587 | K10: =K9/K7 -> 0.15946568 | L10: =J10-K10 -> 0.0088901852
C11: Coûts de redevance | E11: =SUMIFS(BV_Data_An_Cour!$O:$O,BV_Data_An_Cour!$W:$W,$D$2,BV_Data_An_Cour!L:L,C31) -> 6166.35 | F11: =SUMIF($A$37:$A$48,"X",$G$37:$G$48) -> 3830.8433 | G11: =E11-F11 -> 2335.5067 | H11: =G11/F11 -> 0.60965865 | J11: =SUMIFS(BV_Data_An_Cour!$P:$P,BV_Data_An_Cour!$W:$W,$L$2,BV_Data_An_Cour!T:T,C31) -> 44668.31 | K11: =SUMIF($B$37:$B$48,"X",$G$37:$G$48) -> 26836.013 | L11: =J11-K11 -> 17832.297 | M11: =L11/K11 -> 0.66449131
A12: Ventes de Gros | B12: pièces | C12: Profit | E12: =-SUMIFS(BV_Data_An_Cour!$O:$O,BV_Data_An_Cour!$U:$U,$B12,BV_Data_An_Cour!$V:$V,$A12,BV_Data_An_Cour!$W:$W,$D$2) -> 24420.92 | F12: =+INDEX('Budget original'!$A$2:$AO$501,MATCH(B12&$A12,'Budget original'!$A$2:$A$501,0),MATCH(G$2,'Budget original'!$A$2:$AO$2,0)) -> 20768.867 | G12: =E12-F12 -> 3652.053 | H12: =G12/F12 -> 0.17584267 | J12: =-SUMIFS(BV_Data_An_Cour!$P:$P,BV_Data_An_Cour!$U:$U,$B12,BV_Data_An_Cour!$V:$V,$A12,BV_Data_An_Cour!$W:$W,$D$2) -> 182375.44 | K12: {=+SUMPRODUCT(('Budget original'!$A$8:$A$501=B12&$A12)*('Budget original'!$C$3:$AO$3=O$2),'Budget original'!$C$8:$AO$501)} -> 148079.32 | L12: =J12-K12 -> 34296.116 | M12: =L12/K12 -> 0.23160638
C13: % brut | E13: =(E12)/E7 -> 0.13094846 | F13: =(F12)/F7 -> 0.135 | G13: =E13-F13 -> -0.0040515404 | J13: =(J12)/J7 -> 0.13523374 | K13: =(K12)/K7 -> 0.135 | L13: =J13-K13 -> 0.00023373992
C14: Coûts de livraison | E14: =SUMIFS(BV_Data_An_Cour!$O:$O,BV_Data_An_Cour!$W:$W,$D$2,BV_Data_An_Cour!L:L,C33) -> 11160 | F14: =SUMIF(A37:A48,"X",F37:F48)*$G$33 -> 0 | G14: =E14-F14 -> 11160 | H14: =G14/F14 -> #DIV/0! | J14: =SUMIFS(BV_Data_An_Cour!$P:$P,BV_Data_An_Cour!$W:$W,$L$2,BV_Data_An_Cour!T:T,C33) -> 75680 | K14: =SUMIF(B37:B48,"X",F37:F48)*$G$33 -> 0 | L14: =J14-K14 -> 75680 | M14: =L14/K14 -> #DIV/0!
C15: Profit net | E15: =E12-E14 -> 13260.92 | F15: =F12-F14 -> 20768.867 | G15: =E15-F15 -> -7507.947 | H15: =G15/F15 -> -0.36150007 | J15: =J12-J14 -> 106695.44 | K15: =K12-K14 -> 148079.32 | L15: =J15-K15 -> -41383.884 | M15: =L15/K15 -> -0.27947105
C16: % net | E16: =E15/E7 -> 0.071106946 | F16: =F15/F7 -> 0.135 | G16: =E16-F16 -> -0.063893054 | J16: =J15/J7 -> 0.079116044 | K16: =K15/K7 -> 0.135 | L16: =J16-K16 -> -0.055883956
E18: =CONCATENATE("Pièces Wholesale $ / livraison ",Parametres!B3," ",Parametres!B4) -> Pièces Wholesale $ / livraison Juillet 2025 | J18: =CONCATENATE("Pièces Wholesale AAD $ / livraison ",Parametres!B4) -> Pièces Wholesale AAD $ / livraison 2025
E19: Réel | F19: Budget | G19: ▲ $ | H19: ▲ % | J19: Réel | K19: Budget | L19: ▲ $ | M19: ▲ %
C20: Ventes de Gros | E20: =E7/E$6 -> 334.21615 | F20: =F7/F$6 -> #DIV/0! | G20: =E20-F20 -> #DIV/0! | H20: =G20/F20 -> #DIV/0! | J20: =J7/J$6 -> 356.39382 | K20: =K7/K$6 -> #DIV/0! | L20: =J20-K20 -> #DIV/0! | M20: =L20/K20 -> #DIV/0!
C21: Coûts | E21: =E8/E$6 -> 279.40025 | F21: =F8/F$6 -> #DIV/0! | G21: =E21-F21 -> #DIV/0! | H21: =G21/F21 -> #DIV/0! | J21: =J8/J$6 -> 296.39283 | K21: =K8/K$6 -> #DIV/0! | L21: =J21-K21 -> #DIV/0! | M21: =L21/K21 -> #DIV/0!
C22: Profit brut | E22: =E9/E$6 -> 54.815896 | F22: =F9/F$6 -> #DIV/0! | G22: =E22-F22 -> #DIV/0! | H22: =G22/F22 -> #DIV/0! | J22: =J9/J$6 -> 60.000991 | K22: =K9/K$6 -> #DIV/0! | L22: =J22-K22 -> #DIV/0! | M22: =L22/K22 -> #DIV/0!
C23: Coûts de redevance | E23: =E11/E$6 -> 11.050806 | F23: =F11/F$6 -> #DIV/0! | G23: =E23-F23 -> #DIV/0! | H23: =G23/F23 -> #DIV/0! | J23: =J11/J$6 -> 11.804522 | K23: =K11/K$6 -> #DIV/0! | L23: =J23-K23 -> #DIV/0! | M23: =L23/K23 -> #DIV/0!
C24: Profit | E24: =E12/E$6 -> 43.76509 | F24: =F12/F$6 -> #DIV/0! | G24: =E24-F24 -> #DIV/0! | H24: =G24/F24 -> #DIV/0! | J24: =J12/J$6 -> 48.196469 | K24: =K12/K$6 -> #DIV/0! | L24: =J24-K24 -> #DIV/0! | M24: =L24/K24 -> #DIV/0!
C25: Coûts de livraison | E25: =E14/E$6 -> 20 | F25: =F14/F$6 -> #DIV/0! | G25: =E25-F25 -> #DIV/0! | H25: =G25/F25 -> #DIV/0! | J25: =J14/J$6 -> 20 | K25: =K14/K$6 -> #DIV/0! | L25: =J25-K25 -> #DIV/0! | M25: =L25/K25 -> #DIV/0!
C26: Profit net | E26: =E15/E$6 -> 23.76509 | F26: =F15/F$6 -> #DIV/0! | G26: =E26-F26 -> #DIV/0! | H26: =G26/F26 -> #DIV/0! | J26: =J15/J$6 -> 28.196469 | K26: =K15/K$6 -> #DIV/0! | L26: =J26-K26 -> #DIV/0! | M26: =L26/K26 -> #DIV/0!
C29: Inscrire les GL
C30: Couts de redevance | E30: Contrôle mois | G30: =SUMIF(A37:A48,"X",E37:E48)*$G$33-E14 -> 0 | H30: frais de livraison doit être de 25$ / livraison
C31: 5773 | E31: Contrôle YTD | G31: =SUMIF(B37:B48,"X",E37:E48)*$G$33-J14 -> 0 | H31: frais de livraison doit être de 25$ / livraison
C32: GL livraison
C33: 6758 | E33: Coût / livraison | G33: 20
E35: NB de livraison
A36: Mois | B36: YTD | C36: Mois | E36: Réel | F36: Budgeté | G36: Coûts de redevance budgeté | H36: =+IF(Parametres!$B$3=H$38,"X","") | I36: =+IF(Parametres!$B$3=I$38,"X","") | J36: =+IF(Parametres!$B$3=J$38,"X","") | K36: =+IF(Parametres!$B$3=K$38,"X","") | L36: =+IF(Parametres!$B$3=L$38,"X","") | M36: =+IF(Parametres!$B$3=M$38,"X","") | N36: =+IF(Parametres!$B$3=N$38,"X","") | O36: =+IF(Parametres!$B$3=O$38,"X","") | ... S36: =+IF(Parametres!$B$3=S$38,"X","") | U36: =+IF(Parametres!$B$3=N$7,"X","") | V36: =+IF(Parametres!$B$3=N$7,"O","") | W36: =+IF(Parametres!$B$3=N$7,"U","") | X36: =+IF(Parametres!$B$3=Q$7,"X","") | Y36: =+IF(Parametres!$B$3=Q$7,"O","") | Z36: =+IF(Parametres!$B$3=Q$7,"U","") | AA36: =+IF(Parametres!$B$3=T$7,"X","") | AB36: =+IF(Parametres!$B$3=T$7,"O","") | AC36: =+IF(Parametres!$B$3=T$7,"U","") | AD36: =+IF(Parametres!$B$3=W$7,"X","") | AE36: =+IF(Parametres!$B$3=W$7,"O","") | AF36: =+IF(Parametres!$B$3=W$7,"U","") | AG36: =+IF(Parametres!$B$3=Z$7,"X","") | AH36: =+IF(Parametres!$B$3=Z$7,"O","") | AI36: =+IF(Parametres!$B$3=Z$7,"U","") | AJ36: =+IF(Parametres!$B$3=AC$7,"X","") | AK36: =+IF(Parametres!$B$3=AC$7,"O","") | AL36: =+IF(Parametres!$B$3=AC$7,"U","") | AM36: =+IF(Parametres!$B$3=AF$7,"X","") | AN36: =+IF(Parametres!$B$3=AF$7,"O","") | AO36: =+IF(Parametres!$B$3=AF$7,"U","")
A37: =+IF(Parametres!$B$3=$C37,"X","") | B37: =+IF(VLOOKUP($C37,Parametres!$K$3:$N$14,4,0)="X","X","") -> X | C37: Janvier | E37: 557 | G37: 4014.4 | H37: =ARRONDI -> #NAME?
A38: =+IF(Parametres!$B$3=$C38,"X","") | B38: =+IF(VLOOKUP($C38,Parametres!$K$3:$N$14,4,0)="X","X","") -> X | C38: Février | E38: 503 | G38: 3551.28
A39: =+IF(Parametres!$B$3=$C39,"X","") | B39: =+IF(VLOOKUP($C39,Parametres!$K$3:$N$14,4,0)="X","X","") -> X | C39: Mars | E39: 525 | G39: 4269.5214
A40: =+IF(Parametres!$B$3=$C40,"X","") | B40: =+IF(VLOOKUP($C40,Parametres!$K$3:$N$14,4,0)="X","X","") -> X | C40: Avril | E40: 537 | G40: 3179.2297
A41: =+IF(Parametres!$B$3=$C41,"X","") | B41: =+IF(VLOOKUP($C41,Parametres!$K$3:$N$14,4,0)="X","X","") -> X | C41: Mai | E41: 562 | G41: 4267.0567
A42: =+IF(Parametres!$B$3=$C42,"X","") | B42: =+IF(VLOOKUP($C42,Parametres!$K$3:$N$14,4,0)="X","X","") -> X | C42: Juin | E42: 542 | G42: 3723.6817
A43: =+IF(Parametres!$B$3=$C43,"X","") -> X | B43: =+IF(VLOOKUP($C43,Parametres!$K$3:$N$14,4,0)="X","X","") -> X | C43: Juillet | E43: 558 | G43: 3830.8433
A44: =+IF(Parametres!$B$3=$C44,"X","") | B44: =+IF(VLOOKUP($C44,Parametres!$K$3:$N$14,4,0)="X","X","") | C44: Août | G44: 4360.9632
A45: =+IF(Parametres!$B$3=$C45,"X","") | B45: =+IF(VLOOKUP($C45,Parametres!$K$3:$N$14,4,0)="X","X","") | C45: Septembre | G45: 4652.1062
A46: =+IF(Parametres!$B$3=$C46,"X","") | B46: =+IF(VLOOKUP($C46,Parametres!$K$3:$N$14,4,0)="X","X","") | C46: Octobre | G46: 4057.5556
A47: =+IF(Parametres!$B$3=$C47,"X","") | B47: =+IF(VLOOKUP($C47,Parametres!$K$3:$N$14,4,0)="X","X","") | C47: Novembre | G47: 4856.957
A48: =+IF(Parametres!$B$3=$C48,"X","") | B48: =+IF(VLOOKUP($C48,Parametres!$K$3:$N$14,4,0)="X","X","") | C48: Décembre | G48: 4885.0883

Sheet Vol & Taux MOIS
B1: Park Avenue Volkswagen - Analyse des écarts "Volume & Taux - Mois courant"
B3: Neufs | C3: Volume # | D3: Marge $ | E3: Brut | G3: Usagés | H3: Volume # | I3: Marge $ | J3: Brut | L3: Service | M3: Volume $ | N3: Marge % | O3: Brut | Q3: Service #B.T. | R3: Volume # | S3: $/B.T. | T3: Ventes
B4: Écart Total | G4: Écart Total | L4: Écart Total | Q4: Écart Total
B5: Réel | C5: =Print_Mois!J27 -> 81 | D5: =Print_Mois!L27/Print_Mois!J27 -> 3311.6236 | E5: =+C5*D5 -> 268241.51 | G5: Réel | H5: =Print_Mois!J108 -> 79 | I5: =Print_Mois!L108/Print_Mois!J108 -> 1686.9216 | J5: =+H5*I5 -> 133266.81 | L5: Réel | M5: =Print_Mois!K194 -> 337642.8 | N5: =O5/M5 -> 0.71467 | O5: =Print_Mois!L194 -> 241303.18 | Q5: Réel | R5: =Print_Mois!J185 -> 862 | S5: =Print_Mois!K185/Print_Mois!J185 -> 355.10094 | T5: =+R5*S5 -> 306097.01
B6: Budget | C6: =Print_Mois!G27 -> 0 | D6: =Print_Mois!I27/Print_Mois!G27 -> #DIV/0! | E6: =+C6*D6 -> #DIV/0! | G6: Budget | H6: =Print_Mois!G108 -> 0 | I6: =Print_Mois!I108/Print_Mois!G108 -> #DIV/0! | J6: =+H6*I6 -> #DIV/0! | L6: Budget | M6: =Print_Mois!H194 -> 0 | N6: =O6/M6 -> #DIV/0! | O6: =Print_Mois!I194 -> 0 | Q6: Budget | R6: =Print_Mois!G185 -> 0 | S6: =Print_Mois!H185/Print_Mois!G185 -> #DIV/0! | T6: =+R6*S6 -> #DIV/0!
B7: Écart Total | C7: =+C5-C6 -> 81 | D7: =+D5-D6 -> #DIV/0! | E7: =+E5-E6 -> #DIV/0! | G7: Écart Total | H7: =+H5-H6 -> 79 | I7: =+I5-I6 -> #DIV/0! | J7: =+J5-J6 -> #DIV/0! | L7: Écart Total | M7: =+M5-M6 -> 337642.8 | N7: =+N5-N6 -> #DIV/0! | O7: =+O5-O6 -> 241303.18 | Q7: Écart Total | R7: =+R5-R6 -> 862 | S7: =+S5-S6 -> #DIV/0! | T7: =+T5-T6 -> #DIV/0!
C8: =+C7/C6 -> #DIV/0! | D8: =+D7/D6 -> #DIV/0! | H8: =+H7/H6 -> #DIV/0! | I8: =+I7/I6 -> #DIV/0! | M8: =+M7/M6 -> #DIV/0! | N8: =+N7/N6 -> #DIV/0! | R8: =+R7/R6 -> #DIV/0! | S8: =+S7/S6 -> #DIV/0!
B9: Écart Marge | G9: Écart Marge | L9: Écart Marge | Q9: Écart $/B.T.
B10: Marge Réelle | C10: =+C5 -> 81 | D10: =+D5 -> 3311.6236 | E10: =+C10*D10 -> 268241.51 | G10: Marge Réelle | H10: =+H5 -> 79 | I10: =+I5 -> 1686.9216 | J10: =+H10*I10 -> 133266.81 | L10: Marge Réelle | M10: =+M5 -> 337642.8 | N10: =+N5 -> 0.71467 | O10: =+M10*N10 -> 241303.18 | Q10: $/B.T. Réel | R10: =+R5 -> 862 | S10: =+S5 -> 355.10094 | T10: =+R10*S10 -> 306097.01
B11: Marge Budget | C11: =+C5 -> 81 | D11: =+D6 -> #DIV/0! | E11: =C11*D11 -> #DIV/0! | G11: Marge Budget | H11: =+H5 -> 79 | I11: =+I6 -> #DIV/0! | J11: =H11*I11 -> #DIV/0! | L11: Marge Budget | M11: =+M5 -> 337642.8 | N11: =+N6 -> #DIV/0! | O11: =M11*N11 -> #DIV/0! | Q11: $/B.T. Budget | R11: =+R5 -> 862 | S11: =+S6 -> #DIV/0! | T11: =R11*S11 -> #DIV/0!
B12: Écart Marge | C12: =+C10-C11 -> 0 | D12: =+D10-D11 -> #DIV/0! | E12: =+E10-E11 -> #DIV/0! | G12: Écart Marge | H12: =+H10-H11 -> 0 | I12: =+I10-I11 -> #DIV/0! | J12: =+J10-J11 -> #DIV/0! | L12: Écart Marge | M12: =+M10-M11 -> 0 | N12: =+N10-N11 -> #DIV/0! | O12: =+O10-O11 -> #DIV/0! | Q12: Écart $/B.T. | R12: =+R10-R11 -> 0 | S12: =+S10-S11 -> #DIV/0! | T12: =+T10-T11 -> #DIV/0!
B14: Écart Volume | G14: Écart Volume | L14: Écart Volume | Q14: Écart Volume
B15: Volume Réel | C15: =+C5 -> 81 | D15: =+D6 -> #DIV/0! | E15: =+C15*D15 -> #DIV/0! | G15: Volume Réel | H15: =+H5 -> 79 | I15: =+I6 -> #DIV/0! | J15: =+H15*I15 -> #DIV/0! | L15: Volume Réel | M15: =+M5 -> 337642.8 | N15: =+N6 -> #DIV/0! | O15: =+M15*N15 -> #DIV/0! | Q15: Volume Réel | R15: =+R5 -> 862 | S15: =+S6 -> #DIV/0! | T15: =+R15*S15 -> #DIV/0!
B16: Volume Budget | C16: =+C6 -> 0 | D16: =+D6 -> #DIV/0! | E16: =C16*D16 -> #DIV/0! | G16: Volume Budget | H16: =+H6 -> 0 | I16: =+I6 -> #DIV/0! | J16: =H16*I16 -> #DIV/0! | L16: Volume Budget | M16: =+M6 -> 0 | N16: =+N6 -> #DIV/0! | O16: =M16*N16 -> #DIV/0! | Q16: Volume Budget | R16: =+R6 -> 0 | S16: =+S6 -> #DIV/0! | T16: =R16*S16 -> #DIV/0!
B17: Écart Volume | C17: =+C15-C16 -> 81 | D17: =+D15-D16 -> #DIV/0! | E17: =+E15-E16 -> #DIV/0! | G17: Écart Volume | H17: =+H15-H16 -> 79 | I17: =+I15-I16 -> #DIV/0! | J17: =+J15-J16 -> #DIV/0! | L17: Écart Volume | M17: =+M15-M16 -> 337642.8 | N17: =+N15-N16 -> #DIV/0! | O17: =+O15-O16 -> #DIV/0! | Q17: Écart Volume | R17: =+R15-R16 -> 862 | S17: =+S15-S16 -> #DIV/0! | T17: =+T15-T16 -> #DIV/0!
E18: =+E7-E12-E17 -> #DIV/0! | J18: =+J7-J12-J17 -> #DIV/0! | O18: =+O7-O12-O17 -> #DIV/0! | T18: =+T7-T12-T17 -> #DIV/0!
B19: Variabilité Max-Min | G19: Variabilité Max-Min | L19: Variabilité Max-Min | Q19: Variabilité Max-Min
B20: Max Vol & Marge | C20: =MAX(C5:C6) -> 81 | D20: =MAX(D5:D6) -> #DIV/0! | E20: =+C20*D20 -> #DIV/0! | G20: Max Vol & Marge | H20: =MAX(H5:H6) -> 79 | I20: =MAX(I5:I6) -> #DIV/0! | J20: =+H20*I20 -> #DIV/0! | L20: Max Vol & Marge | M20: =MAX(M5:M6) -> 337642.8 | N20: =MAX(N5:N6) -> #DIV/0! | O20: =+M20*N20 -> #DIV/0! | Q20: Max Vol & Marge | R20: =MAX(R5:R6) -> 862 | S20: =MAX(S5:S6) -> #DIV/0! | T20: =+R20*S20 -> #DIV/0!
B21: Moyenne | E21: =AVERAGE(E20,E22) -> #DIV/0! | G21: Moyenne | J21: =AVERAGE(J20,J22) -> #DIV/0! | L21: Moyenne | O21: =AVERAGE(O20,O22) -> #DIV/0! | Q21: Moyenne | T21: =AVERAGE(T20,T22) -> #DIV/0!
B22: Min Vol & Marge | C22: =MIN(C5:C6) -> 0 | D22: =MIN(D5:D6) -> #DIV/0! | E22: =+C22*D22 -> #DIV/0! | G22: Min Vol & Marge | H22: =MIN(H5:H6) -> 0 | I22: =MIN(I5:I6) -> #DIV/0! | J22: =+H22*I22 -> #DIV/0! | L22: Min Vol & Marge | M22: =MIN(M5:M6) -> 0 | N22: =MIN(N5:N6) -> #DIV/0! | O22: =+M22*N22 -> #DIV/0! | Q22: Min Vol & Marge | R22: =MIN(R5:R6) -> 0 | S22: =MIN(S5:S6) -> #DIV/0! | T22: =+R22*S22 -> #DIV/0!
B23: Fourchette | C23: =+C20-C22 -> 81 | D23: =+D20-D22 -> #DIV/0! | E23: =+E20-E22 -> #DIV/0! | G23: Fourchette | H23: =+H20-H22 -> 79 | I23: =+I20-I22 -> #DIV/0! | J23: =+J20-J22 -> #DIV/0! | L23: Fourchette | M23: =+M20-M22 -> 337642.8 | N23: =+N20-N22 -> #DIV/0! | O23: =+O20-O22 -> #DIV/0! | Q23: Fourchette | R23: =+R20-R22 -> 862 | S23: =+S20-S22 -> #DIV/0! | T23: =+T20-T22 -> #DIV/0!
C25: Réel VS Max | E25: =+E5/E20 -> #DIV/0! | H25: Réel VS Max | J25: =+J5/J20 -> #DIV/0! | M25: Réel VS Max | O25: =+O5/O20 -> #DIV/0! | R25: Réel VS Max | T25: =+T5/T20 -> #DIV/0!
C26: Réel VS Moyenne | E26: =+E5/E21 -> #DIV/0! | H26: Réel VS Moyenne | J26: =+J5/J21 -> #DIV/0! | M26: Réel VS Moyenne | O26: =+O5/O21 -> #DIV/0! | R26: Réel VS Moyenne | T26: =+T5/T21 -> #DIV/0!
C27: Réel VS Min | E27: =+E5/E22 -> #DIV/0! | H27: Réel VS Min | J27: =+J5/J22 -> #DIV/0! | M27: Réel VS Min | O27: =+O5/O22 -> #DIV/0! | R27: Réel VS Min | T27: =+T5/T22 -> #DIV/0!
C29: Fourchette Variabilité | E29: =+E27-E25 -> #DIV/0! | H29: Fourchette Variabilité | J29: =+J27-J25 -> #DIV/0! | M29: Fourchette Variabilité | O29: =+O27-O25 -> #DIV/0! | R29: Fourchette Variabilité | T29: =+T27-T25 -> #DIV/0!
B31: Autres Revenus Budgétés non-réalisé | G31: Autres Revenus Budgétés non-réalisé
B32: Holdback | C32: =+C17 -> 81 | D32: =+E32/C32 -> -132.30363 | E32: =+Print_Mois!N78 -> -10716.594
B33: Frais d'Admin. | C33: =+C17 -> 81 | D33: =+E33/C33 -> 62.251235 | E33: =+Print_Mois!N82 -> 5042.35 | G33: Frais d'Admin. | H33: =+H17 -> 79 | I33: =+J33/H33 -> -4.856962 | J33: =+Print_Mois!N159 -> -383.7
E34: =SUM(E32:E33) -> -5674.2436 | J34: =SUM(J32:J33) -> -383.7

Sheet Print_AAD
C1: =Parametres!B1 -> Volks | K1: Véhicules neufs | S1: =CONCATENATE("Réalisé AAJ,"," ",Parametres!B3," ",Parametres!B4) -> Réalisé AAJ, Juillet 2025
D2: X | E2: O | F2: U | J2: NB | L2: $ | O2: X | P2: O | Q2: U | X2: X | Y2: O | Z2: U | AJ2: X | AK2: O | AL2: U
D3: BUDGET ORIGINAL | J3: RÉALISATION | M3: ÉCART réel / Budget | O3: ANNÉE PRÉCÉDENTE | R3: ECART (réel/ Ann.Préc.) | V3: NEUF | W3: 0.45
D4: UNITE | E4: $P/UNITÉ | F4: $PROFITS | J4: UNITÉS | K4: $P/UNITE | L4: $PROFITS | M4: UNITÉS | N4: $PROFITS | O4: UNITE | P4: $P/UNITÉ | Q4: $PROFITS | R4: UNITÉS | S4: $PROFITS | V4: USAGE | W4: 0.1
A5: =+B5&C5 -> Véhicules neufsVentes nettes | B5: =+$K$1 -> Véhicules neufs | C5: Ventes nettes | F5: {=+SUMPRODUCT(('Budget original'!$A$8:$A$501=$A5)*('Budget original'!$C$3:$AO$3=F$2),'Budget original'!$C$8:$AO$501)} -> 22688589 | L5: =-SUMIFS(BV_Data_An_Cour!$P:$P,BV_Data_An_Cour!$X:$X,"Oui",BV_Data_An_Cour!$U:$U,$B5) -> 20245371 | Q5: {=+SUMPRODUCT(('Réel 2024'!$A$8:$A$501=$A5)*('Réel 2024'!$C$3:$AO$3=Q$2),'Réel 2024'!$C$8:$AO$501)} -> 24392210 | V5: SERVICE | W5: 0.225
A6: =+B6&C6 -> Véhicules neufsAutos détail | B6: =+$K$1 -> Véhicules neufs | C6: Autos détail | D6: {=+SUMPRODUCT(('Budget original'!$A$8:$A$501=$A6)*('Budget original'!$C$3:$AO$3=D$2),'Budget original'!$C$8:$AO$501)} -> 111 | E6: =IF(D6=0,0,F6/D6) -> 1953.6492 | F6: {=+SUMPRODUCT(('Budget original'!$A$8:$A$501=$A6)*('Budget original'!$C$3:$AO$3=F$2),'Budget original'!$C$8:$AO$501)} -> 216855.06 | J6: =-SUMIFS(BV_Data_An_Cour!$P:$P,BV_Data_An_Cour!$U:$U,$B6,BV_Data_An_Cour!$V:$V,$C6,BV_Data_An_Cour!$W:$W,J$2) -> 82 | K6: =IF(J6=0,0,L6/J6) -> 1995.6156 | L6: =-SUMIFS(BV_Data_An_Cour!$P:$P,BV_Data_An_Cour!$U:$U,$B6,BV_Data_An_Cour!$V:$V,$C6,BV_Data_An_Cour!$W:$W,L$2) -> 163640.48 | M6: =J6-D6 -> -29 | N6: =L6-F6 -> -53214.578 | O6: {=+SUMPRODUCT(('Réel 2024'!$A$8:$A$501=$A6)*('Réel 2024'!$C$3:$AO$3=O$2),'Réel 2024'!$C$8:$AO$501)} -> 122 | P6: =IF(O6=0,0,Q6/O6) -> 2053.3375 | Q6: {=+SUMPRODUCT(('Réel 2024'!$A$8:$A$501=$A6)*('Réel 2024'!$C$3:$AO$3=Q$2),'Réel 2024'!$C$8:$AO$501)} -> 250507.18 | R6: =J6-O6 -> -40 | S6: =L6-Q6 -> -86866.7 | V6: CARROSSERIE | W6: 0.025
A7: =+B7&C7 -> Véhicules neufsCamions détail | B7: =+$K$1 -> Véhicules neufs | C7: Camions détail | D7: {=+SUMPRODUCT(('Budget original'!$A$8:$A$501=$A7)*('Budget original'!$C$3:$AO$3=D$2),'Budget original'!$C$8:$AO$501)} -> 301 | E7: =IF(D7=0,0,F7/D7) -> 2435.9047 | F7: {=+SUMPRODUCT(('Budget original'!$A$8:$A$501=$A7)*('Budget original'!$C$3:$AO$3=F$2),'Budget original'!$C$8:$AO$501)} -> 733207.31 | J7: =-SUMIFS(BV_Data_An_Cour!$P:$P,BV_Data_An_Cour!$U:$U,$B7,BV_Data_An_Cour!$V:$V,$C7,BV_Data_An_Cour!$W:$W,J$2) -> 272 | K7: =IF(J7=0,0,L7/J7) -> 2322.3342 | L7: =-SUMIFS(BV_Data_An_Cour!$P:$P,BV_Data_An_Cour!$U:$U,$B7,BV_Data_An_Cour!$V:$V,$C7,BV_Data_An_Cour!$W:$W,L$2) -> 631674.9 | M7: =J7-D7 -> -29 | N7: =L7-F7 -> -101532.41 | O7: {=+SUMPRODUCT(('Réel 2024'!$A$8:$A$501=$A7)*('Réel 2024'!$C$3:$AO$3=O$2),'Réel 2024'!$C$8:$AO$501)} -> 318 | P7: =IF(O7=0,0,Q7/O7) -> 2552.2234 | Q7: {=+SUMPRODUCT(('Réel 2024'!$A$8:$A$501=$A7)*('Réel 2024'!$C$3:$AO$3=Q$2),'Réel 2024'!$C$8:$AO$501)} -> 811607.05 | R7: =J7-O7 -> -46 | S7: =L7-Q7 -> -179932.15 | V7: PIECES | W7: 0.2
A8: =+B8&C8 -> Véhicules neufsSprinter | B8: =+$K$1 -> Véhicules neufs | C8: Sprinter | D8: {=+SUMPRODUCT(('Budget original'!$A$8:$A$501=$A8)*('Budget original'!$C$3:$AO$3=D$2),'Budget original'!$C$8:$AO$501)} -> 0 | E8: =IF(D8=0,0,F8/D8) -> 0 | F8: {=+SUMPRODUCT(('Budget original'!$A$8:$A$501=$A8)*('Budget original'!$C$3:$AO$3=F$2),'Budget original'!$C$8:$AO$501)} -> 0 | J8: =-SUMIFS(BV_Data_An_Cour!$P:$P,BV_Data_An_Cour!$U:$U,$B8,BV_Data_An_Cour!$V:$V,$C8,BV_Data_An_Cour!$W:$W,J$2) -> 0 | K8: =IF(J8=0,0,L8/J8) -> 0 | L8: =-SUMIFS(BV_Data_An_Cour!$P:$P,BV_Data_An_Cour!$U:$U,$B8,BV_Data_An_Cour!$V:$V,$C8,BV_Data_An_Cour!$W:$W,L$2) -> 0 | M8: =J8-D8 -> 0 | N8: =L8-F8 -> 0 | O8: {=+SUMPRODUCT(('Réel 2024'!$A$8:$A$501=$A8)*('Réel 2024'!$C$3:$AO$3=O$2),'Réel 2024'!$C$8:$AO$501)} -> 0 | P8: =IF(O8=0,0,Q8/O8) -> 0 | Q8: {=+SUMPRODUCT(('Réel 2024'!$A$8:$A$501=$A8)*('Réel 2024'!$C$3:$AO$3=Q$2),'Réel 2024'!$C$8:$AO$501)} -> 0 | R8: =J8-O8 -> 0 | S8: =L8-Q8 -> 0 | W8: =SUM(W3:W7) -> 1
A9: =+B9&C9 -> Véhicules neufsMoto détail | B9: =+$K$1 -> Véhicules neufs | C9: Moto détail | D9: {=+SUMPRODUCT(('Budget original'!$A$8:$A$501=$A9)*('Budget original'!$C$3:$AO$3=D$2),'Budget original'!$C$8:$AO$501)} -> 0 | E9: =IF(D9=0,0,F9/D9) -> 0 | F9: {=+SUMPRODUCT(('Budget original'!$A$8:$A$501=$A9)*('Budget original'!$C$3:$AO$3=F$2),'Budget original'!$C$8:$AO$501)} -> 0 | J9: =-SUMIFS(BV_Data_An_Cour!$P:$P,BV_Data_An_Cour!$U:$U,$B9,BV_Data_An_Cour!$V:$V,$C9,BV_Data_An_Cour!$W:$W,J$2) -> 0 | K9: =IF(J9=0,0,L9/J9) -> 0 | L9: =-SUMIFS(BV_Data_An_Cour!$P:$P,BV_Data_An_Cour!$U:$U,$B9,BV_Data_An_Cour!$V:$V,$C9,BV_Data_An_Cour!$W:$W,L$2) -> 0 | M9: =J9-D9 -> 0 | N9: =L9-F9 -> 0 | O9: {=+SUMPRODUCT(('Réel 2024'!$A$8:$A$501=$A9)*('Réel 2024'!$C$3:$AO$3=O$2),'Réel 2024'!$C$8:$AO$501)} -> 0 | P9: =IF(O9=0,0,Q9/O9) -> 0 | Q9: {=+SUMPRODUCT(('Réel 2024'!$A$8:$A$501=$A9)*('Réel 2024'!$C$3:$AO$3=Q$2),'Réel 2024'!$C$8:$AO$501)} -> 0 | R9: =J9-O9 -> 0 | S9: =L9-Q9 -> 0
