Workbook
Name Ticker: #REF!

Sheet SOMMAIRE
A1: Bonis Cadre
A3: VW | B3: 45688 | C3: GL
A4: Tommy Martel | B4: ='Tommy Martel Diotte 2024'!K30 -> 3058 | D4: =B4*0.6 -> 1834.8 | E4: =B4*0.4 -> 1223.2
A5: Tommy Martel - Trim | B5: ='Tommy Martel Diotte 2024'!K47 -> 0 | D5: =B5*0.6 -> 0 | E5: =B5*0.4 -> 0
A6: Marc-Olivier Poulin | B6: ='Marc-Olivier Poulin 2025'!K34 -> 4250 | C6: 6222
A7: Sebastien Fleury | B7: ='Sebastien Fleury 2025'!K36 -> 4250
A8: Alexandre Paradis | B8: ='Alexandre Paradis 2025 v2'!K44 -> 4500 | C8: 6122
A9: Rémi Dubreuil | B9: ='Rémi Dubreuil 2025'!K36 -> 864.59221 | C9: 6722
A10: Total VW | B10: =SUM(B4:B9) -> 16922.592
B12: Final | C12: Prov. É/F | D12: Écart
A13: 6122 | B13: =B7+B8 -> 8750 | D13: =+B13-C13 -> 8750 | E13: Neuf
A14: 6222 | B14: =B6 -> 4250 | D14: =+B14-C14 -> 4250 | E14: Usagé
A15: 6422 | B15: =D4+D5 -> 1834.8 | D15: =+B15-C15 -> 1834.8 | E15: Service
A16: 6722 | B16: =E4+E5+B9 -> 2087.7922 | D16: =+B16-C16 -> 2087.7922 | E16: Pièces | J16: 6445 | K16: 100
B17: =SUM(B13:B16) -> 16922.592 | C17: =SUM(C13:C16) -> 0 | D17: =SUM(D13:D16) -> 16922.592

Sheet Kaven Bonneau v2 2024
B1: Kaven Bonneau - Directeur des Ventes
B3: Bonis Mensuels | H3: 45321 | I3: 45350 | J3: 45379 | K3: 45408 | L3: 45437 | M3: 45466 | N3: 45495 | O3: 45524 | P3: 45553 | Q3: 45582 | R3: 45611 | S3: 45640
B4: Profit brut départemental NEUF | G4: Réalisé | M4: 124974 | N4: 254171 | O4: 260155
B5: vs BUDGET 2024 | G5: Cible | M5: 259687 | N5: 231018 | O5: 260155
C6: de | D6: à | E6: Boni | G6: % | M6: =IFERROR(ROUND(M4/M5,3)," - - -") -> 0.481 | N6: =IFERROR(ROUND(N4/N5,3)," - - -") -> 1.1 | O6: =IFERROR(ROUND(O4/O5,3)," - - -") -> 1 | P6: =IFERROR(ROUND(P4/P5,3)," - - -") -> - - - | Q6: =IFERROR(ROUND(Q4/Q5,3)," - - -") -> - - - | R6: =IFERROR(ROUND(R4/R5,3)," - - -") -> - - - | S6: =IFERROR(ROUND(S4/S5,3)," - - -") -> - - -
C7: 0.9 | D7: 0.9999 | E7: 500 | M7: =IF(AND(M$6>=$C7,M$6<=$D7),$E7,0) -> 0 | N7: =IF(AND(N$6>=$C7,N$6<=$D7),$E7,0) -> 0 | O7: =IF(AND(O$6>=$C7,O$6<=$D7),$E7,0) -> 0 | P7: =IF(AND(P$6>=$C7,P$6<=$D7),$E7,0) -> 0 | Q7: =IF(AND(Q$6>=$C7,Q$6<=$D7),$E7,0) -> 0 | R7: =IF(AND(R$6>=$C7,R$6<=$D7),$E7,0) -> 0 | S7: =IF(AND(S$6>=$C7,S$6<=$D7),$E7,0) -> 0
C8: 1 | D8: 1.049 | E8: 800 | M8: =IF(AND(M$6>=$C8,M$6<=$D8),$E8,0) -> 0 | N8: =IF(AND(N$6>=$C8,N$6<=$D8),$E8,0) -> 0 | O8: =IF(AND(O$6>=$C8,O$6<=$D8),$E8,0) -> 800 | P8: =IF(AND(P$6>=$C8,P$6<=$D8),$E8,0) -> 0 | Q8: =IF(AND(Q$6>=$C8,Q$6<=$D8),$E8,0) -> 0 | R8: =IF(AND(R$6>=$C8,R$6<=$D8),$E8,0) -> 0 | S8: =IF(AND(S$6>=$C8,S$6<=$D8),$E8,0) -> 0
C9: 1.05 | D9: et plus | E9: 1250 | M9: =IF(AND(M$6>=$C9,M$6<=$D9),$E9,0) -> 0 | N9: =IF(AND(N$6>=$C9,N$6<=$D9),$E9,0) -> 1250 | O9: =IF(AND(O$6>=$C9,O$6<=$D9),$E9,0) -> 0 | P9: =IF(AND(P$6>=$C9,P$6<=$D9),$E9,0) -> 1250 | Q9: =IF(AND(Q$6>=$C9,Q$6<=$D9),$E9,0) -> 1250 | R9: =IF(AND(R$6>=$C9,R$6<=$D9),$E9,0) -> 1250 | S9: =IF(AND(S$6>=$C9,S$6<=$D9),$E9,0) -> 1250
G10: Payable | M10: =SUM(M7:M9) -> 0 | N10: =SUM(N7:N9) -> 1250 | O10: =SUM(O7:O9) -> 800 | P10: =SUM(P7:P9) -> 1250 | Q10: =SUM(Q7:Q9) -> 1250 | R10: =SUM(R7:R9) -> 1250 | S10: =SUM(S7:S9) -> 1250
B11: Objectifs de volume vehicules neufs | G11: Réalisé | M11: 40 | N11: 85 | O11: 88
B12: vs objectif mensuel du manufacturier | G12: Cible | M12: 87 | N12: 80 | O12: 81
C13: de | D13: à | E13: Boni | G13: % | M13: =IFERROR(ROUND(M11/M12,3)," - - -") -> 0.46 | N13: =IFERROR(ROUND(N11/N12,3)," - - -") -> 1.063 | O13: =IFERROR(ROUND(O11/O12,3)," - - -") -> 1.086 | P13: =IFERROR(ROUND(P11/P12,3)," - - -") -> - - - | Q13: =IFERROR(ROUND(Q11/Q12,3)," - - -") -> - - - | R13: =IFERROR(ROUND(R11/R12,3)," - - -") -> - - - | S13: =IFERROR(ROUND(S11/S12,3)," - - -") -> - - -
C14: 0.9 | D14: 0.9999 | E14: 500 | M14: =IF(AND(M$6>=$C14,M$6<=$D14),$E14,0) -> 0 | N14: =IF(AND(N$13>=$C14,N$13<=$D14),$E14,0) -> 0 | O14: =IF(AND(O$13>=$C14,O$13<=$D14),$E14,0) -> 0 | P14: =IF(AND(P$13>=$C14,P$13<=$D14),$E14,0) -> 0 | Q14: =IF(AND(Q$13>=$C14,Q$13<=$D14),$E14,0) -> 0 | R14: =IF(AND(R$13>=$C14,R$13<=$D14),$E14,0) -> 0 | S14: =IF(AND(S$13>=$C14,S$13<=$D14),$E14,0) -> 0
C15: 1 | D15: 1.049 | E15: 800 | M15: =IF(AND(M$6>=$C15,M$6<=$D15),$E15,0) -> 0 | N15: =IF(AND(N$13>=$C15,N$13<=$D15),$E15,0) -> 0 | O15: =IF(AND(O$13>=$C15,O$13<=$D15),$E15,0) -> 0 | P15: =IF(AND(P$13>=$C15,P$13<=$D15),$E15,0) -> 0 | Q15: =IF(AND(Q$13>=$C15,Q$13<=$D15),$E15,0) -> 0 | R15: =IF(AND(R$13>=$C15,R$13<=$D15),$E15,0) -> 0 | S15: =IF(AND(S$13>=$C15,S$13<=$D15),$E15,0) -> 0
C16: 1.05 | D16: et plus | E16: 1250 | M16: =IF(AND(M$6>=$C16,M$6<=$D16),$E16,0) -> 0 | N16: =IF(AND(N$13>=$C16,N$13<=$D16),$E16,0) -> 1250 | O16: =IF(AND(O$13>=$C16,O$13<=$D16),$E16,0) -> 1250 | P16: =IF(AND(P$13>=$C16,P$13<=$D16),$E16,0) -> 1250 | Q16: =IF(AND(Q$13>=$C16,Q$13<=$D16),$E16,0) -> 1250 | R16: =IF(AND(R$13>=$C16,R$13<=$D16),$E16,0) -> 1250 | S16: =IF(AND(S$13>=$C16,S$13<=$D16),$E16,0) -> 1250
G17: Payable | M17: =SUM(M14:M16) -> 0 | N17: =SUM(N14:N16) -> 1250 | O17: =SUM(O14:O16) -> 1250 | P17: =SUM(P14:P16) -> 1250 | Q17: =SUM(Q14:Q16) -> 1250 | R17: =SUM(R14:R16) -> 1250 | S17: =SUM(S14:S16) -> 1250
B18: CSI vehicules neuf, 3 indicateurs strategiques | G18: Réalisé
B19: Doit avoir 80% sur les 3 questions | C19: de | D19: à | E19: Boni | G19: % | M19: 0 | N19: 0 | O19: 1 | P19: =IFERROR(ROUND(P18/#REF!,3)," - - -") -> - - - | Q19: =IFERROR(ROUND(Q18/#REF!,3)," - - -") -> - - - | R19: =IFERROR(ROUND(R18/#REF!,3)," - - -") -> - - - | S19: =IFERROR(ROUND(S18/#REF!,3)," - - -") -> - - -
B20: 2,4,5 | C20: 0 | D20: 0.799 | E20: 0 | M20: =IF(AND(M$6>=$C20,M$6<=$D20),$E20,0) -> 0 | N20: =IF(AND(N$19>=$C20,N$19<=$D20),$E20,0) -> 0 | O20: =IF(AND(O$19>=$C20,O$19<=$D20),$E20,0) -> 0 | P20: =IF(AND(P$19>=$C20,P$19<=$D20),$E20,0) -> 0 | Q20: =IF(AND(Q$19>=$C20,Q$19<=$D20),$E20,0) -> 0 | R20: =IF(AND(R$19>=$C20,R$19<=$D20),$E20,0) -> 0 | S20: =IF(AND(S$19>=$C20,S$19<=$D20),$E20,0) -> 0
C21: 0.8 | D21: 0.83 | E21: 500 | M21: =IF(AND(M$6>=$C21,M$6<=$D21),$E21,0) -> 0 | N21: =IF(AND(N$19>=$C21,N$19<=$D21),$E21,0) -> 0 | O21: =IF(AND(O$19>=$C21,O$19<=$D21),$E21,0) -> 0 | P21: =IF(AND(P$19>=$C21,P$19<=$D21),$E21,0) -> 0 | Q21: =IF(AND(Q$19>=$C21,Q$19<=$D21),$E21,0) -> 0 | R21: =IF(AND(R$19>=$C21,R$19<=$D21),$E21,0) -> 0 | S21: =IF(AND(S$19>=$C21,S$19<=$D21),$E21,0) -> 0
C22: 0.8301 | D22: et plus | E22: 750 | M22: =IF(AND(M$6>=$C22,M$6<=$D22),$E22,0) -> 0 | N22: =IF(AND(N$19>=$C22,N$19<=$D22),$E22,0) -> 0 | O22: =IF(AND(O$19>=$C22,O$19<=$D22),$E22,0) -> 750 | P22: =IF(AND(P$19>=$C22,P$19<=$D22),$E22,0) -> 750 | Q22: =IF(AND(Q$19>=$C22,Q$19<=$D22),$E22,0) -> 750 | R22: =IF(AND(R$19>=$C22,R$19<=$D22),$E22,0) -> 750 | S22: =IF(AND(S$19>=$C22,S$19<=$D22),$E22,0) -> 750
G23: Payable | M23: =SUM(M20:M22) -> 0 | N23: =SUM(N20:N22) -> 0 | O23: =SUM(O20:O22) -> 750 | P23: =SUM(P20:P22) -> 750 | Q23: =SUM(Q20:Q22) -> 750 | R23: =SUM(R20:R22) -> 750 | S23: =SUM(S20:S22) -> 750
B24: Profit brut départemental USAGÉ | G24: Réalisé | M24: 84900 | N24: 100043 | O24: 42434
B25: vs BUDGET 2024 | G25: Cible | M25: 171471 | N25: 159665 | O25: 170159
C26: de | D26: à | E26: Boni | G26: % | M26: =IFERROR(ROUND(M24/M25,3)," - - -") -> 0.495 | N26: =IFERROR(ROUND(N24/N25,3)," - - -") -> 0.627 | O26: =IFERROR(ROUND(O24/O25,3)," - - -") -> 0.249 | P26: =IFERROR(ROUND(P24/P25,3)," - - -") -> - - - | Q26: =IFERROR(ROUND(Q24/Q25,3)," - - -") -> - - - | R26: =IFERROR(ROUND(R24/R25,3)," - - -") -> - - - | S26: =IFERROR(ROUND(S24/S25,3)," - - -") -> - - -
C27: 0.9 | D27: 0.9999 | E27: 500 | M27: =IF(AND(M$26>=$C27,M$26<=$D27),$E27,0) -> 0 | N27: =IF(AND(N$26>=$C27,N$26<=$D27),$E27,0) -> 0 | O27: =IF(AND(O$26>=$C27,O$26<=$D27),$E27,0) -> 0 | P27: =IF(AND(P$26>=$C27,P$26<=$D27),$E27,0) -> 0 | Q27: =IF(AND(Q$26>=$C27,Q$26<=$D27),$E27,0) -> 0 | R27: =IF(AND(R$26>=$C27,R$26<=$D27),$E27,0) -> 0 | S27: =IF(AND(S$26>=$C27,S$26<=$D27),$E27,0) -> 0
C28: 1 | D28: 1.0999 | E28: 800 | M28: =IF(AND(M$26>=$C28,M$26<=$D28),$E28,0) -> 0 | N28: =IF(AND(N$26>=$C28,N$26<=$D28),$E28,0) -> 0 | O28: =IF(AND(O$26>=$C28,O$26<=$D28),$E28,0) -> 0 | P28: =IF(AND(P$26>=$C28,P$26<=$D28),$E28,0) -> 0 | Q28: =IF(AND(Q$26>=$C28,Q$26<=$D28),$E28,0) -> 0 | R28: =IF(AND(R$26>=$C28,R$26<=$D28),$E28,0) -> 0 | S28: =IF(AND(S$26>=$C28,S$26<=$D28),$E28,0) -> 0
C29: 1.1 | D29: et plus | E29: 1250 | M29: =IF(AND(M$26>=$C29,M$26<=$D29),$E29,0) -> 0 | N29: =IF(AND(N$26>=$C29,N$26<=$D29),$E29,0) -> 0 | O29: =IF(AND(O$26>=$C29,O$26<=$D29),$E29,0) -> 0 | P29: =IF(AND(P$26>=$C29,P$26<=$D29),$E29,0) -> 1250 | Q29: =IF(AND(Q$26>=$C29,Q$26<=$D29),$E29,0) -> 1250 | R29: =IF(AND(R$26>=$C29,R$26<=$D29),$E29,0) -> 1250 | S29: =IF(AND(S$26>=$C29,S$26<=$D29),$E29,0) -> 1250
G30: Payable | M30: =SUM(M27:M29) -> 0 | N30: =SUM(N27:N29) -> 0 | O30: =SUM(O27:O29) -> 0 | P30: =SUM(P27:P29) -> 1250 | Q30: =SUM(Q27:Q29) -> 1250 | R30: =SUM(R27:R29) -> 1250 | S30: =SUM(S27:S29) -> 1250
B31: CSI vehicules d'occasion, 3 indicateurs strategiques | G31: Réalisé
B32: Doit avoir 80% sur les 4 questions | C32: de | D32: à | E32: Boni | G32: % | M32: 0 | N32: 0 | O32: 0 | P32: =IFERROR(ROUND(P31/#REF!,3)," - - -") -> - - - | Q32: =IFERROR(ROUND(Q31/#REF!,3)," - - -") -> - - - | R32: =IFERROR(ROUND(R31/#REF!,3)," - - -") -> - - - | S32: =IFERROR(ROUND(S31/#REF!,3)," - - -") -> - - -
B33: 2,3,4,5 | C33: 0 | D33: 0.799 | E33: 0 | M33: =IF(AND(M$32>=$C33,M$32<=$D33),$E33,0) -> 0 | N33: =IF(AND(N$32>=$C33,N$32<=$D33),$E33,0) -> 0 | O33: =IF(AND(O$32>=$C33,O$32<=$D33),$E33,0) -> 0 | P33: =IF(AND(P$32>=$C33,P$32<=$D33),$E33,0) -> 0 | Q33: =IF(AND(Q$32>=$C33,Q$32<=$D33),$E33,0) -> 0 | R33: =IF(AND(R$32>=$C33,R$32<=$D33),$E33,0) -> 0 | S33: =IF(AND(S$32>=$C33,S$32<=$D33),$E33,0) -> 0
C34: 0.8 | D34: 0.83 | E34: 500 | M34: =IF(AND(M$32>=$C34,M$32<=$D34),$E34,0) -> 0 | N34: =IF(AND(N$32>=$C34,N$32<=$D34),$E34,0) -> 0 | O34: =IF(AND(O$32>=$C34,O$32<=$D34),$E34,0) -> 0 | P34: =IF(AND(P$32>=$C34,P$32<=$D34),$E34,0) -> 0 | Q34: =IF(AND(Q$32>=$C34,Q$32<=$D34),$E34,0) -> 0 | R34: =IF(AND(R$32>=$C34,R$32<=$D34),$E34,0) -> 0 | S34: =IF(AND(S$32>=$C34,S$32<=$D34),$E34,0) -> 0
C35: 0.8301 | D35: et plus | E35: 750 | M35: =IF(AND(M$32>=$C35,M$32<=$D35),$E35,0) -> 0 | N35: =IF(AND(N$32>=$C35,N$32<=$D35),$E35,0) -> 0 | O35: =IF(AND(O$32>=$C35,O$32<=$D35),$E35,0) -> 0 | P35: =IF(AND(P$32>=$C35,P$32<=$D35),$E35,0) -> 750 | Q35: =IF(AND(Q$32>=$C35,Q$32<=$D35),$E35,0) -> 750 | R35: =IF(AND(R$32>=$C35,R$32<=$D35),$E35,0) -> 750 | S35: =IF(AND(S$32>=$C35,S$32<=$D35),$E35,0) -> 750
G36: Payable | M36: =SUM(M33:M35) -> 0 | N36: =SUM(N33:N35) -> 0 | O36: =SUM(O33:O35) -> 0 | P36: =SUM(P33:P35) -> 750 | Q36: =SUM(Q33:Q35) -> 750 | R36: =SUM(R33:R35) -> 750 | S36: =SUM(S33:S35) -> 750
G38: Ajustement | O38: 1250
G40: Total Mensuel | M40: =+M10+M30+M36+M17+M23 -> 0 | N40: =+N10+N30+N36+N17+N23 -> 2500 | O40: =+O10+O30+O36+O17+O23+O38 -> 4050 | P40: =+P10+P30+P36+P17+P23 -> 5250 | Q40: =+Q10+Q30+Q36+Q17+Q23 -> 5250 | R40: =+R10+R30+R36+R17+R23 -> 5250 | S40: =+S10+S30+S36+S17+S23 -> 5250
B41: Bonis Trimestriels
B42: Profit NET cumule des 2 departements des ventes | G42: Réalisé | M42: 268536
G43: Cible | M43: 762586
C44: de | D44: à | E44: Boni | M44: =IFERROR(ROUND(M42/M43,3)," - - -") -> 0.352 | P44: =IFERROR(ROUND(P42/P43,3)," - - -") -> - - - | S44: =IFERROR(ROUND(S42/S43,3)," - - -") -> - - -
C45: 0.9 | D45: 0.9999 | E45: 1000 | M45: =IF(AND(M$44>=$C45,M$44<=$D45),$E45,0) -> 0 | P45: =IF(AND(P$44>=$C45,P$44<=$D45),$E45,0) -> 0 | S45: =IF(AND(S$44>=$C45,S$44<=$D45),$E45,0) -> 0
C46: 1 | D46: 1.0999 | E46: 2000 | M46: =IF(AND(M$44>=$C46,M$44<=$D46),$E46,0) -> 0 | P46: =IF(AND(P$44>=$C46,P$44<=$D46),$E46,0) -> 0 | S46: =IF(AND(S$44>=$C46,S$44<=$D46),$E46,0) -> 0
C47: 1.1 | D47: et plus | E47: 3500 | M47: =IF(AND(M$44>=$C47,M$44<=$D47),$E47,0) -> 0 | P47: =IF(AND(P$44>=$C47,P$44<=$D47),$E47,0) -> 3500 | S47: =IF(AND(S$44>=$C47,S$44<=$D47),$E47,0) -> 3500
G48: Payable | M48: =SUM(M45:M47) -> 0 | P48: =SUM(P45:P47) -> 3500 | S48: =SUM(S45:S47) -> 3500
B50: Atteinte des Indicateurs Expérience + ( X de 5 ) | G50: Réalisé | M50: 4 | P50: 5 | S50: 5
C51: de | D51: à | E51: Boni
C52: 3 | D52: =C52 -> 3 | E52: 700 | M52: =IF(AND(M$50>=$C52,M$50<=$D52),$E52,0) -> 0 | P52: =IF(AND(P$50>=$C52,P$50<=$D52),$E52,0) -> 0 | S52: =IF(AND(S$50>=$C52,S$50<=$D52),$E52,0) -> 0
C53: =C52+1 -> 4 | D53: =D52+1 -> 4 | E53: 1500 | M53: =IF(AND(M$50>=$C53,M$50<=$D53),$E53,0) -> 1500 | P53: =IF(AND(P$50>=$C53,P$50<=$D53),$E53,0) -> 0 | S53: =IF(AND(S$50>=$C53,S$50<=$D53),$E53,0) -> 0
C54: =C53+1 -> 5 | D54: =D53+1 -> 5 | E54: 2500 | M54: =IF(AND(M$50>=$C54,M$50<=$D54),$E54,0) -> 0 | P54: =IF(AND(P$50>=$C54,P$50<=$D54),$E54,0) -> 2500 | S54: =IF(AND(S$50>=$C54,S$50<=$D54),$E54,0) -> 2500
G55: Payable | M55: =SUM(M52:M54) -> 1500 | P55: =SUM(P52:P54) -> 2500 | S55: =SUM(S52:S54) -> 2500
G56: Total Trimestriel | J56: =+J48+J55 -> 0 | M56: =+M48+M55 -> 1500 | P56: =+P48+P55 -> 6000 | S56: =+S48+S55 -> 6000
G58: Total Payable | J58: =J40+J56 -> 0 | M58: =M40+M56 -> 1500 | P58: =P40+P56 -> 11250 | S58: =+S40+S56 -> 11250
I61: Neuf | J61: =#REF! -> #REF!
I62: Used | J62: =#REF! -> #REF!
I63: Bonis | J63: =-(SOMMAIRE!B13+SOMMAIRE!B14) -> -13000
I64: Réel | J64: =SUM(J61:J63) -> #REF!
I66: Neuf | J66: =#REF! -> #REF!
I67: Used | J67: =#REF! -> #REF!
I68: Budget | J68: =SUM(J66:J67) -> #REF!
I70: Variance | J70: =J64-+J68 -> #REF!
J71: =J64/J68 -> #REF!

Sheet Guillaume Raymond v2 2024 
B1: Guillaume Raymond - Directeur Adjoint Ventes Usagé
B3: Bonis Mensuels | H3: 45321 | I3: 45350 | J3: 45379 | K3: 45408 | L3: 45437 | M3: 45466 | N3: 45495 | O3: 45524 | P3: 45553 | Q3: 45582 | R3: 45611 | S3: 45640
B4: Profit brut départemental USAGÉ | G4: Réalisé | M4: 84900 | N4: ='Kaven Bonneau v2 2024'!N24 -> 100043 | O4: ='Kaven Bonneau v2 2024'!O24 -> 42434 | P4: ='Kaven Bonneau v2 2024'!P24 -> 0 | Q4: ='Kaven Bonneau v2 2024'!Q24 -> 0 | R4: ='Kaven Bonneau v2 2024'!R24 -> 0 | S4: ='Kaven Bonneau v2 2024'!S24 -> 0
B5: vs le Budget 2024 | G5: Cible | M5: 171471 | N5: ='Kaven Bonneau v2 2024'!N25 -> 159665 | O5: ='Kaven Bonneau v2 2024'!O25 -> 170159 | P5: ='Kaven Bonneau v2 2024'!P25 -> 0 | Q5: ='Kaven Bonneau v2 2024'!Q25 -> 0 | R5: ='Kaven Bonneau v2 2024'!R25 -> 0 | S5: ='Kaven Bonneau v2 2024'!S25 -> 0
C6: de | D6: à | E6: Boni | G6: % | M6: =IFERROR(ROUND(M4/M5,3)," - - -") -> 0.495 | N6: =IFERROR(ROUND(N4/N5,3)," - - -") -> 0.627 | O6: =IFERROR(ROUND(O4/O5,3)," - - -") -> 0.249 | P6: =IFERROR(ROUND(P4/P5,3)," - - -") -> - - - | Q6: =IFERROR(ROUND(Q4/Q5,3)," - - -") -> - - - | R6: =IFERROR(ROUND(R4/R5,3)," - - -") -> - - - | S6: =IFERROR(ROUND(S4/S5,3)," - - -") -> - - -
C7: 0.9 | D7: 0.9999 | E7: 500 | M7: =IF(AND(M$6>=$C7,M$6<=$D7),$E7,0) -> 0 | N7: =IF(AND(N$6>=$C7,N$6<=$D7),$E7,0) -> 0 | O7: =IF(AND(O$6>=$C7,O$6<=$D7),$E7,0) -> 0 | P7: =IF(AND(P$6>=$C7,P$6<=$D7),$E7,0) -> 0 | Q7: =IF(AND(Q$6>=$C7,Q$6<=$D7),$E7,0) -> 0 | R7: =IF(AND(R$6>=$C7,R$6<=$D7),$E7,0) -> 0 | S7: =IF(AND(S$6>=$C7,S$6<=$D7),$E7,0) -> 0
C8: 1 | D8: 1.0999 | E8: 850 | M8: =IF(AND(M$6>=$C8,M$6<=$D8),$E8,0) -> 0 | N8: =IF(AND(N$6>=$C8,N$6<=$D8),$E8,0) -> 0 | O8: =IF(AND(O$6>=$C8,O$6<=$D8),$E8,0) -> 0 | P8: =IF(AND(P$6>=$C8,P$6<=$D8),$E8,0) -> 0 | Q8: =IF(AND(Q$6>=$C8,Q$6<=$D8),$E8,0) -> 0 | R8: =IF(AND(R$6>=$C8,R$6<=$D8),$E8,0) -> 0 | S8: =IF(AND(S$6>=$C8,S$6<=$D8),$E8,0) -> 0
C9: 1.1 | D9: et plus | E9: 1500 | M9: =IF(AND(M$6>=$C9,M$6<=$D9),$E9,0) -> 0 | N9: =IF(AND(N$6>=$C9,N$6<=$D9),$E9,0) -> 0 | O9: =IF(AND(O$6>=$C9,O$6<=$D9),$E9,0) -> 0 | P9: =IF(AND(P$6>=$C9,P$6<=$D9),$E9,0) -> 1500 | Q9: =IF(AND(Q$6>=$C9,Q$6<=$D9),$E9,0) -> 1500 | R9: =IF(AND(R$6>=$C9,R$6<=$D9),$E9,0) -> 1500 | S9: =IF(AND(S$6>=$C9,S$6<=$D9),$E9,0) -> 1500
G10: Payable | M10: =SUM(M7:M9) -> 0 | N10: =SUM(N7:N9) -> 0 | O10: =SUM(O7:O9) -> 0 | P10: =SUM(P7:P9) -> 1500 | Q10: =SUM(Q7:Q9) -> 1500 | R10: =SUM(R7:R9) -> 1500 | S10: =SUM(S7:S9) -> 1500
B12: Atteinte Volume Ventes Usagés - DÉTAILS | G12: Réalisé | M12: 33 | N12: 30 | O12: 25
B13: vs le Budget 2024 | G13: Cible | M13: 39 | N13: 36 | O13: 39
C14: de | D14: à | E14: Boni | G14: % | M14: =IFERROR(ROUND(M12/M13,3)," - - -") -> 0.846 | N14: =IFERROR(ROUND(N12/N13,3)," - - -") -> 0.833 | O14: =IFERROR(ROUND(O12/O13,3)," - - -") -> 0.641 | P14: =IFERROR(ROUND(P12/P13,3)," - - -") -> - - - | Q14: =IFERROR(ROUND(Q12/Q13,3)," - - -") -> - - - | R14: =IFERROR(ROUND(R12/R13,3)," - - -") -> - - - | S14: =IFERROR(ROUND(S12/S13,3)," - - -") -> - - -
C15: 0.9 | D15: 0.9999 | E15: 500 | M15: =IF(AND(M$14>=$C15,M$14<=$D15),$E15,0) -> 0 | N15: =IF(AND(N$14>=$C15,N$14<=$D15),$E15,0) -> 0 | O15: =IF(AND(O$14>=$C15,O$14<=$D15),$E15,0) -> 0 | P15: =IF(AND(P$14>=$C15,P$14<=$D15),$E15,0) -> 0 | Q15: =IF(AND(Q$14>=$C15,Q$14<=$D15),$E15,0) -> 0 | R15: =IF(AND(R$14>=$C15,R$14<=$D15),$E15,0) -> 0 | S15: =IF(AND(S$14>=$C15,S$14<=$D15),$E15,0) -> 0
C16: 1 | D16: 1.0999 | E16: 750 | M16: =IF(AND(M$14>=$C16,M$14<=$D16),$E16,0) -> 0 | N16: =IF(AND(N$14>=$C16,N$14<=$D16),$E16,0) -> 0 | O16: =IF(AND(O$14>=$C16,O$14<=$D16),$E16,0) -> 0 | P16: =IF(AND(P$14>=$C16,P$14<=$D16),$E16,0) -> 0 | Q16: =IF(AND(Q$14>=$C16,Q$14<=$D16),$E16,0) -> 0 | R16: =IF(AND(R$14>=$C16,R$14<=$D16),$E16,0) -> 0 | S16: =IF(AND(S$14>=$C16,S$14<=$D16),$E16,0) -> 0
C17: 1.1 | D17: et plus | E17: 1500 | M17: =IF(AND(M$14>=$C17,M$14<=$D17),$E17,0) -> 0 | N17: =IF(AND(N$14>=$C17,N$14<=$D17),$E17,0) -> 0 | O17: =IF(AND(O$14>=$C17,O$14<=$D17),$E17,0) -> 0 | P17: =IF(AND(P$14>=$C17,P$14<=$D17),$E17,0) -> 1500 | Q17: =IF(AND(Q$14>=$C17,Q$14<=$D17),$E17,0) -> 1500 | R17: =IF(AND(R$14>=$C17,R$14<=$D17),$E17,0) -> 1500 | S17: =IF(AND(S$14>=$C17,S$14<=$D17),$E17,0) -> 1500
G18: Payable | M18: =SUM(M15:M17) -> 0 | N18: =SUM(N15:N17) -> 0 | O18: =SUM(O15:O17) -> 0 | P18: =SUM(P15:P17) -> 1500 | Q18: =SUM(Q15:Q17) -> 1500 | R18: =SUM(R15:R17) -> 1500 | S18: =SUM(S15:S17) -> 1500
B20: Atteinte des Indicateurs de Performance ( X de 3 ) | M20: 1 | N20: 1 | O20: 1
C21: de | D21: à | E21: Boni
C22: 0 | D22: 1 | E22: 0 | M22: =IF(AND(M20>=$C22,M20<=$D22),$E22,0) -> 0 | N22: =IF(AND(N20>=$C22,N20<=$D22),$E22,0) -> 0 | O22: =IF(AND(O20>=$C22,O20<=$D22),$E22,0) -> 0 | P22: =IF(AND(P20>=$C22,P20<=$D22),$E22,0) -> 0 | Q22: =IF(AND(Q20>=$C22,Q20<=$D22),$E22,0) -> 0 | R22: =IF(AND(R20>=$C22,R20<=$D22),$E22,0) -> 0 | S22: =IF(AND(S20>=$C22,S20<=$D22),$E22,0) -> 0
C23: 2 | D23: 2 | E23: 750 | M23: =IF(AND(M20>=$C23,M20<=$D23),$E23,0) -> 0 | N23: =IF(AND(N20>=$C23,N20<=$D23),$E23,0) -> 0 | O23: =IF(AND(O20>=$C23,O20<=$D23),$E23,0) -> 0 | P23: =IF(AND(P20>=$C23,P20<=$D23),$E23,0) -> 0 | Q23: =IF(AND(Q20>=$C23,Q20<=$D23),$E23,0) -> 0 | R23: =IF(AND(R20>=$C23,R20<=$D23),$E23,0) -> 0 | S23: =IF(AND(S20>=$C23,S20<=$D23),$E23,0) -> 0
C24: 3 | D24: 3 | E24: 1250 | M24: =IF(AND(M20>=$C24,M20<=$D24),$E24,0) -> 0 | N24: =IF(AND(N20>=$C24,N20<=$D24),$E24,0) -> 0 | O24: =IF(AND(O20>=$C24,O20<=$D24),$E24,0) -> 0 | P24: =IF(AND(P20>=$C24,P20<=$D24),$E24,0) -> 0 | Q24: =IF(AND(Q20>=$C24,Q20<=$D24),$E24,0) -> 0 | R24: =IF(AND(R20>=$C24,R20<=$D24),$E24,0) -> 0 | S24: =IF(AND(S20>=$C24,S20<=$D24),$E24,0) -> 0
G25: Payable | M25: =SUM(M22:M24) -> 0 | N25: =SUM(N22:N24) -> 0 | O25: =SUM(O22:O24) -> 0 | P25: =SUM(P22:P24) -> 0 | Q25: =SUM(Q22:Q24) -> 0 | R25: =SUM(R22:R24) -> 0 | S25: =SUM(S22:S24) -> 0
B27: CSI ( X de 4 ) | M27: 1 | N27: 0 | O27: 0
C28: de | D28: à | E28: Boni
C29: 0 | D29: 0.7999 | E29: 0 | M29: =IF(AND(M27>=$C29,M27<=$D29),$E29,0) -> 0 | N29: =IF(AND(N27>=$C29,N27<=$D29),$E29,0) -> 0 | O29: =IF(AND(O27>=$C29,O27<=$D29),$E29,0) -> 0 | P29: =IF(AND(P27>=$C29,P27<=$D29),$E29,0) -> 0 | Q29: =IF(AND(Q27>=$C29,Q27<=$D29),$E29,0) -> 0 | R29: =IF(AND(R27>=$C29,R27<=$D29),$E29,0) -> 0 | S29: =IF(AND(S27>=$C29,S27<=$D29),$E29,0) -> 0
C30: 0.8 | D30: 0.85 | E30: 1000 | M30: =IF(AND(M27>=$C30,M27<=$D30),$E30,0) -> 0 | N30: =IF(AND(N27>=$C30,N27<=$D30),$E30,0) -> 0 | O30: =IF(AND(O27>=$C30,O27<=$D30),$E30,0) -> 0 | P30: =IF(AND(P27>=$C30,P27<=$D30),$E30,0) -> 0 | Q30: =IF(AND(Q27>=$C30,Q27<=$D30),$E30,0) -> 0 | R30: =IF(AND(R27>=$C30,R27<=$D30),$E30,0) -> 0 | S30: =IF(AND(S27>=$C30,S27<=$D30),$E30,0) -> 0
C31: 0.8501 | D31: et plus | E31: 2000 | M31: =IF(AND(M27>=$C31,M27<=$D31),$E31,0) -> 2000 | N31: =IF(AND(N27>=$C31,N27<=$D31),$E31,0) -> 0 | O31: =IF(AND(O27>=$C31,O27<=$D31),$E31,0) -> 0 | P31: =IF(AND(P27>=$C31,P27<=$D31),$E31,0) -> 0 | Q31: =IF(AND(Q27>=$C31,Q27<=$D31),$E31,0) -> 0 | R31: =IF(AND(R27>=$C31,R27<=$D31),$E31,0) -> 0 | S31: =IF(AND(S27>=$C31,S27<=$D31),$E31,0) -> 0
G32: Payable | M32: =SUM(M29:M31) -> 2000 | N32: =SUM(N29:N31) -> 0 | O32: =SUM(O29:O31) -> 0 | P32: =SUM(P29:P31) -> 0 | Q32: =SUM(Q29:Q31) -> 0 | R32: =SUM(R29:R31) -> 0 | S32: =SUM(S29:S31) -> 0
E34: Vente de véhicule en inventaire / Produit F&I | M34: 280 | N34: 60
G36: Total Mensuel | H36: =H10+H18+H25+H32+H34 -> 0 | I36: =I10+I18+I25+I32+I34 -> 0 | J36: =J10+J18+J25+J32+J34 -> 0 | K36: =K10+K18+K25+K32+K34 -> 0 | L36: =L10+L18+L25+L32+L34 -> 0 | M36: =M10+M18+M25+M32+M34 -> 2280 | N36: =N10+N18+N25+N32+N34 -> 60 | O36: =O10+O18+O25+O32+O34 -> 0 | ... S36: =S10+S18+S25+S32+S34 -> 3000

Sheet Guillaume Raymond 2024
B1: Guillaume Raymond - Directeur Adjoint Ventes Usagé
B3: Bonis Mensuels | H3: 45321 | I3: 45350 | J3: 45379 | K3: 45408 | L3: 45437 | M3: 45466 | N3: 45495 | O3: 45524 | P3: 45553 | Q3: 45582 | R3: 45611 | S3: 45640
B4: Profit brut départemental USAGÉ | G4: Réalisé | I4: 12562 | J4: 77150.61 | K4: ='Kaven Bonneau 2024'!K12 -> 62515 | L4: 49484 | M4: 84900
B5: vs le Budget 2024 | G5: Cible | I5: 110753 | J5: 166598.6 | K5: ='Kaven Bonneau 2024'!K13 -> 186276 | L5: 189649 | M5: 171471
C6: de | D6: à | E6: Boni | G6: % | I6: =IFERROR(ROUND(I4/I5,3)," - - -") -> 0.113 | J6: =IFERROR(ROUND(J4/J5,3)," - - -") -> 0.463 | K6: =IFERROR(ROUND(K4/K5,3)," - - -") -> 0.336 | L6: =IFERROR(ROUND(L4/L5,3)," - - -") -> 0.261 | M6: =IFERROR(ROUND(M4/M5,3)," - - -") -> 0.495 | N6: =IFERROR(ROUND(N4/N5,3)," - - -") -> - - - | O6: =IFERROR(ROUND(O4/O5,3)," - - -") -> - - - | P6: =IFERROR(ROUND(P4/P5,3)," - - -") -> - - - | ... S6: =IFERROR(ROUND(S4/S5,3)," - - -") -> - - -
C7: 0.9 | D7: 0.9999 | E7: 750 | H7: =IF(AND(H$6>=$C7,H$6<=$D7),$E7,0) -> 0 | I7: =IF(AND(I$6>=$C7,I$6<=$D7),$E7,0) -> 0 | J7: =IF(AND(J$6>=$C7,J$6<=$D7),$E7,0) -> 0 | K7: =IF(AND(K$6>=$C7,K$6<=$D7),$E7,0) -> 0 | L7: =IF(AND(L$6>=$C7,L$6<=$D7),$E7,0) -> 0 | M7: =IF(AND(M$6>=$C7,M$6<=$D7),$E7,0) -> 0 | N7: =IF(AND(N$6>=$C7,N$6<=$D7),$E7,0) -> 0 | O7: =IF(AND(O$6>=$C7,O$6<=$D7),$E7,0) -> 0 | ... S7: =IF(AND(S$6>=$C7,S$6<=$D7),$E7,0) -> 0
C8: 1 | D8: 1.0999 | E8: 1250 | H8: =IF(AND(H$6>=$C8,H$6<=$D8),$E8,0) -> 0 | I8: =IF(AND(I$6>=$C8,I$6<=$D8),$E8,0) -> 0 | J8: =IF(AND(J$6>=$C8,J$6<=$D8),$E8,0) -> 0 | K8: =IF(AND(K$6>=$C8,K$6<=$D8),$E8,0) -> 0 | L8: =IF(AND(L$6>=$C8,L$6<=$D8),$E8,0) -> 0 | M8: =IF(AND(M$6>=$C8,M$6<=$D8),$E8,0) -> 0 | N8: =IF(AND(N$6>=$C8,N$6<=$D8),$E8,0) -> 0 | O8: =IF(AND(O$6>=$C8,O$6<=$D8),$E8,0) -> 0 | ... S8: =IF(AND(S$6>=$C8,S$6<=$D8),$E8,0) -> 0
C9: 1.1 | D9: et plus | E9: 1750 | H9: =IF(AND(H$6>=$C9,H$6<=$D9),$E9,0) -> 0 | I9: =IF(AND(I$6>=$C9,I$6<=$D9),$E9,0) -> 0 | J9: =IF(AND(J$6>=$C9,J$6<=$D9),$E9,0) -> 0 | K9: =IF(AND(K$6>=$C9,K$6<=$D9),$E9,0) -> 0 | L9: =IF(AND(L$6>=$C9,L$6<=$D9),$E9,0) -> 0 | M9: =IF(AND(M$6>=$C9,M$6<=$D9),$E9,0) -> 0 | N9: =IF(AND(N$6>=$C9,N$6<=$D9),$E9,0) -> 1750 | O9: =IF(AND(O$6>=$C9,O$6<=$D9),$E9,0) -> 1750 | ... S9: =IF(AND(S$6>=$C9,S$6<=$D9),$E9,0) -> 1750
G10: Payable | H10: =SUM(H7:H9) -> 0 | I10: =SUM(I7:I9) -> 0 | J10: =SUM(J7:J9) -> 0 | K10: =SUM(K7:K9) -> 0 | L10: =SUM(L7:L9) -> 0 | M10: =SUM(M7:M9) -> 0 | N10: =SUM(N7:N9) -> 1750 | O10: =SUM(O7:O9) -> 1750 | ... S10: =SUM(S7:S9) -> 1750
B12: Atteinte Volume Ventes Usagés - DÉTAILS | G12: Réalisé | I12: 27 | J12: 22 | K12: 23 | L12: 40 | M12: 33
B13: vs le Budget 2024 | G13: Cible | I13: 25 | J13: 37.7825 | K13: 42 | L13: 43 | M13: 39
C14: de | D14: à | E14: Boni | G14: % | I14: =IFERROR(ROUND(I12/I13,3)," - - -") -> 1.08 | J14: =IFERROR(ROUND(J12/J13,3)," - - -") -> 0.582 | K14: =IFERROR(ROUND(K12/K13,3)," - - -") -> 0.548 | L14: =IFERROR(ROUND(L12/L13,3)," - - -") -> 0.93 | M14: =IFERROR(ROUND(M12/M13,3)," - - -") -> 0.846 | N14: =IFERROR(ROUND(N12/N13,3)," - - -") -> - - - | O14: =IFERROR(ROUND(O12/O13,3)," - - -") -> - - - | P14: =IFERROR(ROUND(P12/P13,3)," - - -") -> - - - | ... S14: =IFERROR(ROUND(S12/S13,3)," - - -") -> - - -
C15: 0.9 | D15: 0.9999 | E15: 750 | H15: =IF(AND(H$14>=$C15,H$14<=$D15),$E15,0) -> 0 | I15: =IF(AND(I$14>=$C15,I$14<=$D15),$E15,0) -> 0 | J15: =IF(AND(J$14>=$C15,J$14<=$D15),$E15,0) -> 0 | K15: =IF(AND(K$14>=$C15,K$14<=$D15),$E15,0) -> 0 | L15: =IF(AND(L$14>=$C15,L$14<=$D15),$E15,0) -> 750 | M15: =IF(AND(M$14>=$C15,M$14<=$D15),$E15,0) -> 0 | N15: =IF(AND(N$14>=$C15,N$14<=$D15),$E15,0) -> 0 | O15: =IF(AND(O$14>=$C15,O$14<=$D15),$E15,0) -> 0 | ... S15: =IF(AND(S$14>=$C15,S$14<=$D15),$E15,0) -> 0
C16: 1 | D16: 1.0999 | E16: 1250 | H16: =IF(AND(H$14>=$C16,H$14<=$D16),$E16,0) -> 0 | I16: =IF(AND(I$14>=$C16,I$14<=$D16),$E16,0) -> 1250 | J16: =IF(AND(J$14>=$C16,J$14<=$D16),$E16,0) -> 0 | K16: =IF(AND(K$14>=$C16,K$14<=$D16),$E16,0) -> 0 | L16: =IF(AND(L$14>=$C16,L$14<=$D16),$E16,0) -> 0 | M16: =IF(AND(M$14>=$C16,M$14<=$D16),$E16,0) -> 0 | N16: =IF(AND(N$14>=$C16,N$14<=$D16),$E16,0) -> 0 | O16: =IF(AND(O$14>=$C16,O$14<=$D16),$E16,0) -> 0 | ... S16: =IF(AND(S$14>=$C16,S$14<=$D16),$E16,0) -> 0
C17: 1.1 | D17: et plus | E17: 1750 | H17: =IF(AND(H$14>=$C17,H$14<=$D17),$E17,0) -> 0 | I17: =IF(AND(I$14>=$C17,I$14<=$D17),$E17,0) -> 0 | J17: =IF(AND(J$14>=$C17,J$14<=$D17),$E17,0) -> 0 | K17: =IF(AND(K$14>=$C17,K$14<=$D17),$E17,0) -> 0 | L17: =IF(AND(L$14>=$C17,L$14<=$D17),$E17,0) -> 0 | M17: =IF(AND(M$14>=$C17,M$14<=$D17),$E17,0) -> 0 | N17: =IF(AND(N$14>=$C17,N$14<=$D17),$E17,0) -> 1750 | O17: =IF(AND(O$14>=$C17,O$14<=$D17),$E17,0) -> 1750 | ... S17: =IF(AND(S$14>=$C17,S$14<=$D17),$E17,0) -> 1750
G18: Payable | H18: =SUM(H15:H17) -> 0 | I18: =SUM(I15:I17) -> 1250 | J18: =SUM(J15:J17) -> 0 | K18: =SUM(K15:K17) -> 0 | L18: =SUM(L15:L17) -> 750 | M18: =SUM(M15:M17) -> 0 | N18: =SUM(N15:N17) -> 1750 | O18: =SUM(O15:O17) -> 1750 | ... S18: =SUM(S15:S17) -> 1750
B20: Atteinte de la Cible CSI CPO (VOC) | G20: Réalisé | I20: 5 | J20: 5 | K20: 4 | L20: 4.04
C21: de | D21: à | E21: Boni
C22: 0 | D22: 4.8 | E22: 0 | H22: =IF(AND(H$20>=$C22,H$20<=$D22),$E22,0) -> 0 | I22: =IF(AND(I$20>=$C22,I$20<=$D22),$E22,0) -> 0 | J22: =IF(AND(J$20>=$C22,J$20<=$D22),$E22,0) -> 0 | K22: =IF(AND(K$20>=$C22,K$20<=$D22),$E22,0) -> 0 | L22: =IF(AND(L$20>=$C22,L$20<=$D22),$E22,0) -> 0 | M22: =IF(AND(M$20>=$C22,M$20<=$D22),$E22,0) -> 0 | N22: =IF(AND(N$20>=$C22,N$20<=$D22),$E22,0) -> 0 | O22: =IF(AND(O$20>=$C22,O$20<=$D22),$E22,0) -> 0 | ... S22: =IF(AND(S$20>=$C22,S$20<=$D22),$E22,0) -> 0
C23: 4.81 | D23: 4.89 | E23: 500 | H23: =IF(AND(H$20>=$C23,H$20<=$D23),$E23,0) -> 0 | I23: =IF(AND(I$20>=$C23,I$20<=$D23),$E23,0) -> 0 | J23: =IF(AND(J$20>=$C23,J$20<=$D23),$E23,0) -> 0 | K23: =IF(AND(K$20>=$C23,K$20<=$D23),$E23,0) -> 0 | L23: =IF(AND(L$20>=$C23,L$20<=$D23),$E23,0) -> 0 | M23: =IF(AND(M$20>=$C23,M$20<=$D23),$E23,0) -> 0 | N23: =IF(AND(N$20>=$C23,N$20<=$D23),$E23,0) -> 0 | O23: =IF(AND(O$20>=$C23,O$20<=$D23),$E23,0) -> 0 | ... S23: =IF(AND(S$20>=$C23,S$20<=$D23),$E23,0) -> 0
C24: 4.9 | D24: et plus | E24: 1000 | H24: =IF(AND(H$20>=$C24,H$20<=$D24),$E24,0) -> 0 | I24: =IF(AND(I$20>=$C24,I$20<=$D24),$E24,0) -> 1000 | J24: =IF(AND(J$20>=$C24,J$20<=$D24),$E24,0) -> 1000 | K24: =IF(AND(K$20>=$C24,K$20<=$D24),$E24,0) -> 0 | L24: =IF(AND(L$20>=$C24,L$20<=$D24),$E24,0) -> 0 | M24: =IF(AND(M$20>=$C24,M$20<=$D24),$E24,0) -> 0 | N24: =IF(AND(N$20>=$C24,N$20<=$D24),$E24,0) -> 0 | O24: =IF(AND(O$20>=$C24,O$20<=$D24),$E24,0) -> 0 | ... S24: =IF(AND(S$20>=$C24,S$20<=$D24),$E24,0) -> 0
G25: Payable | H25: =SUM(H22:H24) -> 0 | I25: =SUM(I22:I24) -> 1000 | J25: =SUM(J22:J24) -> 1000 | K25: =SUM(K22:K24) -> 0 | L25: =SUM(L22:L24) -> 0 | M25: =SUM(M22:M24) -> 0 | N25: =SUM(N22:N24) -> 0 | O25: =SUM(O22:O24) -> 0 | ... S25: =SUM(S22:S24) -> 0
B27: Atteinte des Indiicateurs de Performance ( X de 4 )
B28: (Inventaire > 90 jours en bas de 15% ou de Nov à février 25% / Marchandisage moyen dans le mois >95% / Taux de closing web >15% / Taux de closing Phone ups > 30% | G28: Réalisé | I28: 3 | J28: 2 | K28: 3 | L28: 2
C29: de | D29: à | E29: Boni
C30: 2 | D30: 2 | E30: 500 | H30: =IF(AND(H$28>=$C30,H$28<=$D30),$E30,0) -> 0 | I30: =IF(AND(I$28>=$C30,I$28<=$D30),$E30,0) -> 0 | J30: =IF(AND(J$28>=$C30,J$28<=$D30),$E30,0) -> 500 | K30: =IF(AND(K$28>=$C30,K$28<=$D30),$E30,0) -> 0 | L30: =IF(AND(L$28>=$C30,L$28<=$D30),$E30,0) -> 500 | M30: =IF(AND(M$28>=$C30,M$28<=$D30),$E30,0) -> 0 | N30: =IF(AND(N$28>=$C30,N$28<=$D30),$E30,0) -> 0 | O30: =IF(AND(O$28>=$C30,O$28<=$D30),$E30,0) -> 0 | ... S30: =IF(AND(S$28>=$C30,S$28<=$D30),$E30,0) -> 0
C31: 3 | D31: 3 | E31: 1000 | H31: =IF(AND(H$28>=$C31,H$28<=$D31),$E31,0) -> 0 | I31: =IF(AND(I$28>=$C31,I$28<=$D31),$E31,0) -> 1000 | J31: =IF(AND(J$28>=$C31,J$28<=$D31),$E31,0) -> 0 | K31: =IF(AND(K$28>=$C31,K$28<=$D31),$E31,0) -> 1000 | L31: =IF(AND(L$28>=$C31,L$28<=$D31),$E31,0) -> 0 | M31: =IF(AND(M$28>=$C31,M$28<=$D31),$E31,0) -> 0 | N31: =IF(AND(N$28>=$C31,N$28<=$D31),$E31,0) -> 0 | O31: =IF(AND(O$28>=$C31,O$28<=$D31),$E31,0) -> 0 | ... S31: =IF(AND(S$28>=$C31,S$28<=$D31),$E31,0) -> 0
C32: 4 | D32: 4 | E32: 1500 | H32: =IF(AND(H$28>=$C32,H$28<=$D32),$E32,0) -> 0 | I32: =IF(AND(I$28>=$C32,I$28<=$D32),$E32,0) -> 0 | J32: =IF(AND(J$28>=$C32,J$28<=$D32),$E32,0) -> 0 | K32: =IF(AND(K$28>=$C32,K$28<=$D32),$E32,0) -> 0 | L32: =IF(AND(L$28>=$C32,L$28<=$D32),$E32,0) -> 0 | M32: =IF(AND(M$28>=$C32,M$28<=$D32),$E32,0) -> 0 | N32: =IF(AND(N$28>=$C32,N$28<=$D32),$E32,0) -> 0 | O32: =IF(AND(O$28>=$C32,O$28<=$D32),$E32,0) -> 0 | ... S32: =IF(AND(S$28>=$C32,S$28<=$D32),$E32,0) -> 0
G33: Payable | H33: =SUM(H30:H32) -> 0 | I33: =SUM(I30:I32) -> 1000 | J33: =SUM(J30:J32) -> 500 | K33: =SUM(K30:K32) -> 1000 | L33: =SUM(L30:L32) -> 500 | M33: =SUM(M30:M32) -> 0 | N33: =SUM(N30:N32) -> 0 | O33: =SUM(O30:O32) -> 0 | ... S33: =SUM(S30:S32) -> 0
E35: Vente de véhicule en inventaire / Produit F&I | J35: 200 | K35: 200 | L35: 120
G37: Total Mensuel | H37: =+H10+H18+H25+H33 -> 0 | I37: =+I10+I18+I25+I33 -> 3250 | J37: =+J10+J18+J25+J33+J35 -> 1700 | K37: =+K10+K18+K25+K33+K35 -> 1200 | L37: =+L10+L18+L25+L33+L35 -> 1370 | M37: =+M10+M18+M25+M33+M35 -> 0 | N37: =+N10+N18+N25+N33+N35 -> 3500 | O37: =+O10+O18+O25+O33+O35 -> 3500 | P37: =+P10+P18+P25+P33+P35 -> 3500 | Q37: =+Q10+Q18+Q25+Q33+Q35 -> 3500 | ... S37: =+S10+S18+S25+S33+S35 -> 3500

Sheet Sebastien Fleury 2025
B1: Sebastien Fleury - Directeur General des ventes
B3: Bonis Mensuels | H3: 45688 | I3: 45716 | J3: 45747 | K3: 45777 | L3: 45808 | M3: 45838 | N3: 45869 | O3: 45900 | P3: 45930 | Q3: 45961 | R3: 45991 | S3: 46022
B4: Profit net départemental NEUF | G4: Réalisé | H4: 110350 | I4: 63627 | J4: 55508 | K4: =115596-21449.7-15600 -> 78546.3 | L4: 0 | M4: 0 | N4: 0 | O4: 0 | P4: 0 | Q4: 0 | R4: 0 | S4: 0 | U4: L27 | V4: =SUM(I4:J4) -> 119135
B5: vs le Budget 2025 | G5: Cible | H5: 83820 | I5: 79399 | J5: =69531-25000 -> 44531 | K5: 90870 | L5: 0 | M5: 0 | N5: 0 | O5: 0 | P5: 0 | Q5: 0 | R5: 0 | S5: 0 | U5: F27 | V5: =SUM(I5:J5) -> 123930
C6: de | D6: à | E6: Boni | G6: % | H6: =IFERROR(ROUND(H4/H5,3)," - - -") -> 1.317 | I6: 0.9 | J6: =IFERROR(ROUND(J4/J5,3)," - - -") -> 1.247 | K6: =IFERROR(ROUND(K4/K5,3)," - - -") -> 0.864 | L6: =IFERROR(ROUND(L4/L5,3)," - - -") -> - - - | M6: =IFERROR(ROUND(M4/M5,3)," - - -") -> - - - | N6: =IFERROR(ROUND(N4/N5,3)," - - -") -> - - - | O6: =IFERROR(ROUND(O4/O5,3)," - - -") -> - - - | P6: =IFERROR(ROUND(P4/P5,3)," - - -") -> - - - | Q6: =IFERROR(ROUND(Q4/Q5,3)," - - -") -> - - - | ... S6: =IFERROR(ROUND(S4/S5,3)," - - -") -> - - - | V6: =IFERROR(ROUND(V4/V5,3)," - - -") -> 0.961
C7: 0.9 | D7: 0.9999 | E7: 750 | H7: =IF(AND(H$6>=$C7,H$6<=$D7),$E7,0) -> 0 | I7: =IF(AND(I$6>=$C7,I$6<=$D7),$E7,0) -> 750 | J7: =IF(AND(J$6>=$C7,J$6<=$D7),$E7,0) -> 0 | K7: =IF(AND(K$6>=$C7,K$6<=$D7),$E7,0) -> 0 | L7: =IF(AND(L$6>=$C7,L$6<=$D7),$E7,0) -> 0 | M7: =IF(AND(M$6>=$C7,M$6<=$D7),$E7,0) -> 0 | N7: =IF(AND(N$6>=$C7,N$6<=$D7),$E7,0) -> 0 | O7: =IF(AND(O$6>=$C7,O$6<=$D7),$E7,0) -> 0 | ... S7: =IF(AND(S$6>=$C7,S$6<=$D7),$E7,0) -> 0
C8: 1 | D8: 1.1999 | E8: 1500 | H8: =IF(AND(H$6>=$C8,H$6<=$D8),$E8,0) -> 0 | I8: =IF(AND(I$6>=$C8,I$6<=$D8),$E8,0) -> 0 | J8: =IF(AND(J$6>=$C8,J$6<=$D8),$E8,0) -> 0 | K8: =IF(AND(K$6>=$C8,K$6<=$D8),$E8,0) -> 0 | L8: =IF(AND(L$6>=$C8,L$6<=$D8),$E8,0) -> 0 | M8: =IF(AND(M$6>=$C8,M$6<=$D8),$E8,0) -> 0 | N8: =IF(AND(N$6>=$C8,N$6<=$D8),$E8,0) -> 0 | O8: =IF(AND(O$6>=$C8,O$6<=$D8),$E8,0) -> 0 | ... S8: =IF(AND(S$6>=$C8,S$6<=$D8),$E8,0) -> 0
C9: 1.2 | D9: et plus | E9: 2500 | H9: =IF(AND(H$6>=$C9,H$6<=$D9),$E9,0) -> 2500 | I9: =IF(AND(I$6>=$C9,I$6<=$D9),$E9,0) -> 0 | J9: =IF(AND(J$6>=$C9,J$6<=$D9),$E9,0) -> 2500 | K9: =IF(AND(K$6>=$C9,K$6<=$D9),$E9,0) -> 0 | L9: =IF(AND(L$6>=$C9,L$6<=$D9),$E9,0) -> 2500 | M9: =IF(AND(M$6>=$C9,M$6<=$D9),$E9,0) -> 2500 | N9: =IF(AND(N$6>=$C9,N$6<=$D9),$E9,0) -> 2500 | O9: =IF(AND(O$6>=$C9,O$6<=$D9),$E9,0) -> 2500 | ... S9: =IF(AND(S$6>=$C9,S$6<=$D9),$E9,0) -> 2500
G10: Payable | H10: =SUM(H7:H9) -> 2500 | I10: =SUM(I7:I9) -> 750 | J10: =SUM(J7:J9) -> 2500 | K10: =SUM(K7:K9) -> 0 | L10: =SUM(L7:L9) -> 2500 | M10: =SUM(M7:M9) -> 2500 | N10: =SUM(N7:N9) -> 2500 | O10: =SUM(O7:O9) -> 2500 | ... S10: =SUM(S7:S9) -> 2500
B12: Profit net départemental USED | G12: Réalisé | H12: 1151 | I12: -9236 | J12: 27817 | K12: 30976 | L12: 0 | M12: 0 | N12: 0 | O12: 0 | P12: 0 | Q12: 0 | R12: 0 | S12: 0 | U12: L27 | V12: =SUM(I12:J12) -> 18581
B13: vs le Budget 2025 | G13: Cible | H13: -19027 | I13: 516 | J13: 3636 | K13: 2935 | L13: 0 | M13: 0 | N13: 0 | O13: 0 | P13: 0 | Q13: 0 | R13: 0 | S13: 0 | U13: F27 | V13: =SUM(I13:J13) -> 4152
C14: de | D14: à | E14: Boni | G14: % | H14: 1.2 | I14: 0.9 | J14: =IFERROR(ROUND(J12/J13,3)," - - -") -> 7.65 | K14: =IFERROR(ROUND(K12/K13,3)," - - -") -> 10.554 | L14: =IFERROR(ROUND(L12/L13,3)," - - -") -> - - - | M14: =IFERROR(ROUND(M12/M13,3)," - - -") -> - - - | N14: =IFERROR(ROUND(N12/N13,3)," - - -") -> - - - | O14: =IFERROR(ROUND(O12/O13,3)," - - -") -> - - - | P14: =IFERROR(ROUND(P12/P13,3)," - - -") -> - - - | Q14: =IFERROR(ROUND(Q12/Q13,3)," - - -") -> - - - | ... S14: =IFERROR(ROUND(S12/S13,3)," - - -") -> - - - | V14: =IFERROR(ROUND(V12/V13,3)," - - -") -> 4.475
C15: 0.9 | D15: 0.9999 | E15: 750 | H15: =IF(AND(H$14>=$C15,H$14<=$D15),$E15,0) -> 0 | I15: =IF(AND(I$14>=$C15,I$14<=$D15),$E15,0) -> 750 | J15: =IF(AND(J$14>=$C15,J$14<=$D15),$E15,0) -> 0 | K15: =IF(AND(K$14>=$C15,K$14<=$D15),$E15,0) -> 0 | L15: =IF(AND(L$14>=$C15,L$14<=$D15),$E15,0) -> 0 | M15: =IF(AND(M$14>=$C15,M$14<=$D15),$E15,0) -> 0 | N15: =IF(AND(N$14>=$C15,N$14<=$D15),$E15,0) -> 0 | O15: =IF(AND(O$14>=$C15,O$14<=$D15),$E15,0) -> 0 | ... S15: =IF(AND(S$14>=$C15,S$14<=$D15),$E15,0) -> 0
C16: 1 | D16: 1.1999 | E16: 1500 | H16: =IF(AND(H$14>=$C16,H$14<=$D16),$E16,0) -> 0 | I16: =IF(AND(I$14>=$C16,I$14<=$D16),$E16,0) -> 0 | J16: =IF(AND(J$14>=$C16,J$14<=$D16),$E16,0) -> 0 | K16: =IF(AND(K$14>=$C16,K$14<=$D16),$E16,0) -> 0 | L16: =IF(AND(L$14>=$C16,L$14<=$D16),$E16,0) -> 0 | M16: =IF(AND(M$14>=$C16,M$14<=$D16),$E16,0) -> 0 | N16: =IF(AND(N$14>=$C16,N$14<=$D16),$E16,0) -> 0 | O16: =IF(AND(O$14>=$C16,O$14<=$D16),$E16,0) -> 0 | ... S16: =IF(AND(S$14>=$C16,S$14<=$D16),$E16,0) -> 0
C17: 1.2 | D17: et plus | E17: 2500 | H17: =IF(AND(H$14>=$C17,H$14<=$D17),$E17,0) -> 2500 | I17: =IF(AND(I$14>=$C17,I$14<=$D17),$E17,0) -> 0 | J17: =IF(AND(J$14>=$C17,J$14<=$D17),$E17,0) -> 2500 | K17: =IF(AND(K$14>=$C17,K$14<=$D17),$E17,0) -> 2500 | L17: =IF(AND(L$14>=$C17,L$14<=$D17),$E17,0) -> 2500 | M17: =IF(AND(M$14>=$C17,M$14<=$D17),$E17,0) -> 2500 | N17: =IF(AND(N$14>=$C17,N$14<=$D17),$E17,0) -> 2500 | O17: =IF(AND(O$14>=$C17,O$14<=$D17),$E17,0) -> 2500 | ... S17: =IF(AND(S$14>=$C17,S$14<=$D17),$E17,0) -> 2500
G18: Payable | H18: =SUM(H15:H17) -> 2500 | I18: =SUM(I15:I17) -> 750 | J18: =SUM(J15:J17) -> 2500 | K18: =SUM(K15:K17) -> 2500 | L18: =SUM(L15:L17) -> 2500 | M18: =SUM(M15:M17) -> 2500 | N18: =SUM(N15:N17) -> 2500 | O18: =SUM(O15:O17) -> 2500 | ... S18: =SUM(S15:S17) -> 2500
B20: Objectifs de volumes vehicules neuf selon BPV | G20: Réalisé | H20: 58 | I20: 38 | J20: 53 | K20: 56 | L20: 0 | M20: 0 | N20: 0 | O20: 0 | P20: 0 | Q20: 0 | R20: 0 | S20: 0
G21: Cible | H21: 49 | I21: 53 | J21: 62 | K21: 56 | L21: 0 | M21: 0 | N21: 0 | O21: 0 | P21: 0 | Q21: 0 | R21: 0 | S21: 0
C22: de | D22: à | E22: Boni | G22: % | H22: 1.2 | I22: 0.9 | J22: =IFERROR(ROUND(J20/J21,3)," - - -") -> 0.855 | K22: =IFERROR(ROUND(K20/K21,3)," - - -") -> 1 | L22: =IFERROR(ROUND(L20/L21,3)," - - -") -> - - - | M22: =IFERROR(ROUND(M20/M21,3)," - - -") -> - - - | N22: =IFERROR(ROUND(N20/N21,3)," - - -") -> - - - | O22: =IFERROR(ROUND(O20/O21,3)," - - -") -> - - - | P22: =IFERROR(ROUND(P20/P21,3)," - - -") -> - - - | Q22: =IFERROR(ROUND(Q20/Q21,3)," - - -") -> - - - | ... S22: =IFERROR(ROUND(S20/S21,3)," - - -") -> - - -
C23: 0.9 | D23: 0.9999 | E23: 450 | H23: =IF(AND(H$22>=$C23,H$22<=$D23),$E23,0) -> 0 | I23: =IF(AND(I$22>=$C23,I$22<=$D23),$E23,0) -> 450 | J23: =IF(AND(J$22>=$C23,J$22<=$D23),$E23,0) -> 0 | K23: =IF(AND(K$22>=$C23,K$22<=$D23),$E23,0) -> 0 | L23: =IF(AND(L$22>=$C23,L$22<=$D23),$E23,0) -> 0 | M23: =IF(AND(M$22>=$C23,M$22<=$D23),$E23,0) -> 0 | N23: =IF(AND(N$22>=$C23,N$22<=$D23),$E23,0) -> 0 | O23: =IF(AND(O$22>=$C23,O$22<=$D23),$E23,0) -> 0 | ... S23: =IF(AND(S$22>=$C23,S$22<=$D23),$E23,0) -> 0
C24: 1 | D24: 1.1999 | E24: 750 | H24: =IF(AND(H$22>=$C24,H$22<=$D24),$E24,0) -> 0 | I24: =IF(AND(I$22>=$C24,I$22<=$D24),$E24,0) -> 0 | J24: =IF(AND(J$22>=$C24,J$22<=$D24),$E24,0) -> 0 | K24: =IF(AND(K$22>=$C24,K$22<=$D24),$E24,0) -> 750 | L24: =IF(AND(L$22>=$C24,L$22<=$D24),$E24,0) -> 0 | M24: =IF(AND(M$22>=$C24,M$22<=$D24),$E24,0) -> 0 | N24: =IF(AND(N$22>=$C24,N$22<=$D24),$E24,0) -> 0 | O24: =IF(AND(O$22>=$C24,O$22<=$D24),$E24,0) -> 0 | ... S24: =IF(AND(S$22>=$C24,S$22<=$D24),$E24,0) -> 0
C25: 1.2 | D25: et plus | E25: 1250 | H25: =IF(AND(H$22>=$C25,H$22<=$D25),$E25,0) -> 1250 | I25: =IF(AND(I$22>=$C25,I$22<=$D25),$E25,0) -> 0 | J25: =IF(AND(J$22>=$C25,J$22<=$D25),$E25,0) -> 0 | K25: =IF(AND(K$22>=$C25,K$22<=$D25),$E25,0) -> 0 | L25: =IF(AND(L$22>=$C25,L$22<=$D25),$E25,0) -> 1250 | M25: =IF(AND(M$22>=$C25,M$22<=$D25),$E25,0) -> 1250 | N25: =IF(AND(N$22>=$C25,N$22<=$D25),$E25,0) -> 1250 | O25: =IF(AND(O$22>=$C25,O$22<=$D25),$E25,0) -> 1250 | ... S25: =IF(AND(S$22>=$C25,S$22<=$D25),$E25,0) -> 1250
G26: Payable | H26: =SUM(H23:H25) -> 1250 | I26: =SUM(I23:I25) -> 450 | J26: =SUM(J23:J25) -> 0 | K26: =SUM(K23:K25) -> 750 | L26: =SUM(L23:L25) -> 1250 | M26: =SUM(M23:M25) -> 1250 | N26: =SUM(N23:N25) -> 1250 | O26: =SUM(O23:O25) -> 1250 | ... S26: =SUM(S23:S25) -> 1250
B28: CSI ventes: Questions D2 / D4 / D5 | C28: de | D28: à | E28: Boni | H28: 0.875 | I28: 0.85 | J28: 0.83 | K28: 0.92 | L28: 0 | M28: 0 | N28: 0 | O28: 0 | P28: 0 | Q28: 0 | R28: 0 | S28: 0
C29: 0 | D29: 0.7999 | E29: 0 | H29: =IF(AND(H28>=$C29,H28<=$D29),$E29,0) -> 0 | I29: =IF(AND(I28>=$C29,I28<=$D29),$E29,0) -> 0 | J29: =IF(AND(J28>=$C29,J28<=$D29),$E29,0) -> 0 | K29: =IF(AND(K28>=$C29,K28<=$D29),$E29,0) -> 0 | L29: =IF(AND(L28>=$C29,L28<=$D29),$E29,0) -> 0 | M29: =IF(AND(M28>=$C29,M28<=$D29),$E29,0) -> 0 | N29: =IF(AND(N28>=$C29,N28<=$D29),$E29,0) -> 0 | O29: =IF(AND(O28>=$C29,O28<=$D29),$E29,0) -> 0 | ... S29: =IF(AND(S28>=$C29,S28<=$D29),$E29,0) -> 0
C30: 0.8 | D30: 0.8999 | E30: 500 | H30: =IF(AND(H28>=$C30,H28<=$D30),$E30,0) -> 500 | I30: =IF(AND(I28>=$C30,I28<=$D30),$E30,0) -> 500 | J30: =IF(AND(J28>=$C30,J28<=$D30),$E30,0) -> 500 | K30: =IF(AND(K28>=$C30,K28<=$D30),$E30,0) -> 0 | L30: =IF(AND(L28>=$C30,L28<=$D30),$E30,0) -> 0 | M30: =IF(AND(M28>=$C30,M28<=$D30),$E30,0) -> 0 | N30: =IF(AND(N28>=$C30,N28<=$D30),$E30,0) -> 0 | O30: =IF(AND(O28>=$C30,O28<=$D30),$E30,0) -> 0 | ... S30: =IF(AND(S28>=$C30,S28<=$D30),$E30,0) -> 0
C31: 0.9 | D31: et plus | E31: 1000 | H31: =IF(AND(H28>=$C31,H28<=$D31),$E31,0) -> 0 | I31: =IF(AND(I28>=$C31,I28<=$D31),$E31,0) -> 0 | J31: =IF(AND(J28>=$C31,J28<=$D31),$E31,0) -> 0 | K31: =IF(AND(K28>=$C31,K28<=$D31),$E31,0) -> 1000 | L31: =IF(AND(L28>=$C31,L28<=$D31),$E31,0) -> 0 | M31: =IF(AND(M28>=$C31,M28<=$D31),$E31,0) -> 0 | N31: =IF(AND(N28>=$C31,N28<=$D31),$E31,0) -> 0 | O31: =IF(AND(O28>=$C31,O28<=$D31),$E31,0) -> 0 | ... S31: =IF(AND(S28>=$C31,S28<=$D31),$E31,0) -> 0
G32: Payable | H32: =SUM(H29:H31) -> 500 | I32: =SUM(I29:I31) -> 500 | J32: =SUM(J29:J31) -> 500 | K32: =SUM(K29:K31) -> 1000 | L32: =SUM(L29:L31) -> 0 | M32: =SUM(M29:M31) -> 0 | N32: =SUM(N29:N31) -> 0 | O32: =SUM(O29:O31) -> 0 | ... S32: =SUM(S29:S31) -> 0
G34: Rattrapage | J34: 1750
G36: Total Mensuel | H36: =+H10+H32+H26+H18 -> 6750 | I36: =+I10+I32+I26+I18 -> 2450 | J36: =+J10+J32+J26+J18+J34 -> 7250 | K36: =+K10+K32+K26+K18 -> 4250 | L36: =+L10+L32+L26+L18 -> 6250 | M36: =+M10+M32+M26+M18 -> 6250 | N36: =+N10+N32+N26+N18 -> 6250 | O36: =+O10+O32+O26+O18 -> 6250 | P36: =+P10+P32+P26+P18 -> 6250 | Q36: =+Q10+Q32+Q26+Q18 -> 6250 | R36: =+R10+R32+R26+R18 -> 6250 | S36: =+S10+S32+S26+S18 -> 6250
B38: Bonis Annuels
B39: Classement de la concession au Wolfsburg 2025 | G39: Réalisé
C40: de | D40: à | E40: Boni
C41: 1 | D41: 5 | E41: 10000 | S41: =IF(AND(S$39>=$C41,S$39<=$D41),$E41,0) -> 0
C42: 6 | D42: 10 | E42: 5000 | S42: =IF(AND(S$39>=$C42,S$39<=$D42),$E42,0) -> 0
C43: 11 | D43: 15 | E43: 2500 | S43: =IF(AND(S$39>=$C43,S$39<=$D43),$E43,0) -> 0
G44: Payable | S44: =SUM(S41:S43) -> 0
G46: Total Payable | S46: =+S36+S44 -> 6250

Sheet Karim Noori 2024
B1: Karim Noori - Directeur Adjoint Desk Manager
B3: Bonis Mensuels | H3: 45322 | I3: 45350 | J3: 45378 | K3: 45406 | L3: 45434 | M3: 45462 | N3: 45490 | O3: 45518 | P3: 45546 | Q3: 45574 | R3: 45602 | S3: 45630
B4: Profit brut départemental NEUF | G4: Réalisé | H4: 142187 | I4: 249483 | J4: 281559.36 | K4: ='Kaven Bonneau 2024'!K4 -> 259605 | L4: 235625 | M4: 124974 | N4: ='Kaven Bonneau v2 2024'!N4 -> 254171 | O4: 260155 | P4: =#REF! -> #REF! | Q4: =#REF! -> #REF! | R4: =#REF! -> #REF! | S4: =#REF! -> #REF! | U4: L27
B5: vs le Budget 2024 | G5: Cible | H5: 144386 | I5: 144386 | J5: 202140.81 | K5: ='Kaven Bonneau 2024'!K5 -> 288903 | L5: 331750 | M5: 259687 | N5: ='Kaven Bonneau v2 2024'!N5 -> 231018 | O5: 260155 | P5: =#REF! -> #REF! | Q5: =#REF! -> #REF! | R5: =#REF! -> #REF! | S5: =#REF! -> #REF! | U5: F27
C6: de | D6: à | E6: Boni | G6: % | H6: =IFERROR(ROUND(H4/H5,3)," - - -") -> 0.985 | I6: =IFERROR(ROUND(I4/I5,3)," - - -") -> 1.728 | J6: =IFERROR(ROUND(J4/J5,3)," - - -") -> 1.393 | K6: =IFERROR(ROUND(K4/K5,3)," - - -") -> 0.899 | L6: =IFERROR(ROUND(L4/L5,3)," - - -") -> 0.71 | M6: =IFERROR(ROUND(M4/M5,3)," - - -") -> 0.481 | N6: =IFERROR(ROUND(N4/N5,3)," - - -") -> 1.1 | O6: =IFERROR(ROUND(O4/O5,3)," - - -") -> 1 | P6: =IFERROR(ROUND(P4/P5,3)," - - -") -> - - - | Q6: 0.9 | R6: =IFERROR(ROUND(R4/R5,3)," - - -") -> - - - | S6: =IFERROR(ROUND(S4/S5,3)," - - -") -> - - -
C7: 0.85 | D7: 0.9999 | E7: 500 | H7: =IF(AND(H$6>=$C7,H$6<=$D7),$E7,0) -> 500 | I7: =IF(AND(I$6>=$C7,I$6<=$D7),$E7,0) -> 0 | J7: =IF(AND(J$6>=$C7,J$6<=$D7),$E7,0) -> 0 | K7: =IF(AND(K$6>=$C7,K$6<=$D7),$E7,0) -> 500 | L7: =IF(AND(L$6>=$C7,L$6<=$D7),$E7,0) -> 0 | M7: =IF(AND(M$6>=$C7,M$6<=$D7),$E7,0) -> 0 | N7: =IF(AND(N$6>=$C7,N$6<=$D7),$E7,0) -> 0 | O7: =IF(AND(O$6>=$C7,O$6<=$D7),$E7,0) -> 0 | ... S7: =IF(AND(S$6>=$C7,S$6<=$D7),$E7,0) -> 0
C8: 1 | D8: 1.0999 | E8: 1500 | H8: =IF(AND(H$6>=$C8,H$6<=$D8),$E8,0) -> 0 | I8: =IF(AND(I$6>=$C8,I$6<=$D8),$E8,0) -> 0 | J8: =IF(AND(J$6>=$C8,J$6<=$D8),$E8,0) -> 0 | K8: =IF(AND(K$6>=$C8,K$6<=$D8),$E8,0) -> 0 | L8: =IF(AND(L$6>=$C8,L$6<=$D8),$E8,0) -> 0 | M8: =IF(AND(M$6>=$C8,M$6<=$D8),$E8,0) -> 0 | N8: =IF(AND(N$6>=$C8,N$6<=$D8),$E8,0) -> 0 | O8: =IF(AND(O$6>=$C8,O$6<=$D8),$E8,0) -> 1500 | ... S8: =IF(AND(S$6>=$C8,S$6<=$D8),$E8,0) -> 0
C9: 1.1 | D9: et plus | E9: 2000 | H9: =IF(AND(H$6>=$C9,H$6<=$D9),$E9,0) -> 0 | I9: =IF(AND(I$6>=$C9,I$6<=$D9),$E9,0) -> 2000 | J9: =IF(AND(J$6>=$C9,J$6<=$D9),$E9,0) -> 2000 | K9: =IF(AND(K$6>=$C9,K$6<=$D9),$E9,0) -> 0 | L9: =IF(AND(L$6>=$C9,L$6<=$D9),$E9,0) -> 0 | M9: =IF(AND(M$6>=$C9,M$6<=$D9),$E9,0) -> 0 | N9: =IF(AND(N$6>=$C9,N$6<=$D9),$E9,0) -> 2000 | O9: =IF(AND(O$6>=$C9,O$6<=$D9),$E9,0) -> 0 | ... S9: =IF(AND(S$6>=$C9,S$6<=$D9),$E9,0) -> 2000
G10: Payable | H10: =SUM(H7:H9) -> 500 | I10: =SUM(I7:I9) -> 2000 | J10: =SUM(J7:J9) -> 2000 | K10: =SUM(K7:K9) -> 500 | L10: =SUM(L7:L9) -> 0 | M10: =SUM(M7:M9) -> 0 | N10: =SUM(N7:N9) -> 2000 | O10: =SUM(O7:O9) -> 1500 | ... S10: =SUM(S7:S9) -> 2000
B12: Atteinte du volume mensuel neuf au budget | G12: Réalisé | H12: 46 | I12: 75 | J12: 74 | K12: 73 | L12: 74 | M12: 40 | N12: 85 | O12: 89 | P12: =#REF! -> #REF! | Q12: =#REF! -> #REF! | R12: =#REF! -> #REF! | S12: =#REF! -> #REF! | U12: L27
B13: vs le Budget 2024 | G13: Cible | H13: 36 | I13: 36 | J13: 46.83 | K13: 72 | L13: 82 | M13: 64 | N13: 57 | O13: 64 | P13: =#REF! -> #REF! | Q13: =#REF! -> #REF! | R13: =#REF! -> #REF! | S13: =#REF! -> #REF! | U13: F27
C14: de | D14: à | E14: Boni | G14: % | H14: =IFERROR(ROUND(H12/H13,3)," - - -") -> 1.278 | I14: =IFERROR(ROUND(I12/I13,3)," - - -") -> 2.083 | J14: =IFERROR(ROUND(J12/J13,3)," - - -") -> 1.58 | K14: =IFERROR(ROUND(K12/K13,3)," - - -") -> 1.014 | L14: =IFERROR(ROUND(L12/L13,3)," - - -") -> 0.902 | M14: =IFERROR(ROUND(M12/M13,3)," - - -") -> 0.625 | N14: =IFERROR(ROUND(N12/N13,3)," - - -") -> 1.491 | O14: =IFERROR(ROUND(O12/O13,3)," - - -") -> 1.391 | P14: =IFERROR(ROUND(P12/P13,3)," - - -") -> - - - | Q14: 0.9 | R14: =IFERROR(ROUND(R12/R13,3)," - - -") -> - - - | S14: =IFERROR(ROUND(S12/S13,3)," - - -") -> - - -
C15: 0.85 | D15: 0.9999 | E15: 500 | H15: =IF(AND(H$14>=$C15,H$14<=$D15),$E15,0) -> 0 | I15: =IF(AND(I$14>=$C15,I$14<=$D15),$E15,0) -> 0 | J15: =IF(AND(J$14>=$C15,J$14<=$D15),$E15,0) -> 0 | K15: =IF(AND(K$14>=$C15,K$14<=$D15),$E15,0) -> 0 | L15: =IF(AND(L$14>=$C15,L$14<=$D15),$E15,0) -> 500 | M15: =IF(AND(M$14>=$C15,M$14<=$D15),$E15,0) -> 0 | N15: =IF(AND(N$14>=$C15,N$14<=$D15),$E15,0) -> 0 | O15: =IF(AND(O$14>=$C15,O$14<=$D15),$E15,0) -> 0 | ... S15: =IF(AND(S$14>=$C15,S$14<=$D15),$E15,0) -> 0
C16: 1 | D16: 1.0999 | E16: 1500 | H16: =IF(AND(H$14>=$C16,H$14<=$D16),$E16,0) -> 0 | I16: =IF(AND(I$14>=$C16,I$14<=$D16),$E16,0) -> 0 | J16: =IF(AND(J$14>=$C16,J$14<=$D16),$E16,0) -> 0 | K16: =IF(AND(K$14>=$C16,K$14<=$D16),$E16,0) -> 1500 | L16: =IF(AND(L$14>=$C16,L$14<=$D16),$E16,0) -> 0 | M16: =IF(AND(M$14>=$C16,M$14<=$D16),$E16,0) -> 0 | N16: =IF(AND(N$14>=$C16,N$14<=$D16),$E16,0) -> 0 | O16: =IF(AND(O$14>=$C16,O$14<=$D16),$E16,0) -> 0 | ... S16: =IF(AND(S$14>=$C16,S$14<=$D16),$E16,0) -> 0
C17: 1.1 | D17: et plus | E17: 2000 | H17: =IF(AND(H$14>=$C17,H$14<=$D17),$E17,0) -> 2000 | I17: =IF(AND(I$14>=$C17,I$14<=$D17),$E17,0) -> 2000 | J17: =IF(AND(J$14>=$C17,J$14<=$D17),$E17,0) -> 2000 | K17: =IF(AND(K$14>=$C17,K$14<=$D17),$E17,0) -> 0 | L17: =IF(AND(L$14>=$C17,L$14<=$D17),$E17,0) -> 0 | M17: =IF(AND(M$14>=$C17,M$14<=$D17),$E17,0) -> 0 | N17: =IF(AND(N$14>=$C17,N$14<=$D17),$E17,0) -> 2000 | O17: =IF(AND(O$14>=$C17,O$14<=$D17),$E17,0) -> 2000 | ... S17: =IF(AND(S$14>=$C17,S$14<=$D17),$E17,0) -> 2000
G18: Payable | H18: =SUM(H15:H17) -> 2000 | I18: =SUM(I15:I17) -> 2000 | J18: =SUM(J15:J17) -> 2000 | K18: =SUM(K15:K17) -> 1500 | L18: =SUM(L15:L17) -> 500 | M18: =SUM(M15:M17) -> 0 | N18: =SUM(N15:N17) -> 2000 | O18: =SUM(O15:O17) -> 2000 | ... S18: =SUM(S15:S17) -> 2000
B20: Atteinte des Indicateurs Expérience + ( X de 3 ) | G20: Réalisé | H20: 2 | I20: 3 | J20: 2 | K20: 3 | L20: 2 | M20: 3 | N20: 2 | O20: 2 | P20: =#REF! -> #REF! | Q20: =#REF! -> #REF! | R20: =#REF! -> #REF! | S20: 2
B21: - Closing +de 55% - Renouvellement +de 59% - Look to book neuf +de 40%. | G21: Cible | H21: 3 | I21: 3 | J21: 3 | K21: 3 | L21: 3 | M21: 3 | N21: 3 | O21: 3 | P21: =#REF! -> #REF! | Q21: =#REF! -> #REF! | R21: =#REF! -> #REF! | S21: =#REF! -> #REF!
C22: de | D22: à | E22: Boni | G22: % | H22: =IFERROR(ROUND(H20/H21,3)," - - -") -> 0.667 | I22: =IFERROR(ROUND(I20/I21,3)," - - -") -> 1 | J22: =IFERROR(ROUND(J20/J21,3)," - - -") -> 0.667 | K22: =IFERROR(ROUND(K20/K21,3)," - - -") -> 1 | L22: =IFERROR(ROUND(L20/L21,3)," - - -") -> 0.667 | M22: =IFERROR(ROUND(M20/M21,3)," - - -") -> 1 | N22: =IFERROR(ROUND(N20/N21,3)," - - -") -> 0.667 | O22: =IFERROR(ROUND(O20/O21,3)," - - -") -> 0.667 | ... S22: =IFERROR(ROUND(S20/S21,3)," - - -") -> - - -
C23: 1 | D23: 1 | E23: 100 | H23: =IF(AND(H$20>=$C23,H$20<=$D23),$E23,0) -> 0 | I23: =IF(AND(I$20>=$C23,I$20<=$D23),$E23,0) -> 0 | J23: =IF(AND(J$20>=$C23,J$20<=$D23),$E23,0) -> 0 | K23: =IF(AND(K$20>=$C23,K$20<=$D23),$E23,0) -> 0 | L23: =IF(AND(L$20>=$C23,L$20<=$D23),$E23,0) -> 0 | M23: =IF(AND(M$20>=$C23,M$20<=$D23),$E23,0) -> 0 | N23: =IF(AND(N$20>=$C23,N$20<=$D23),$E23,0) -> 0 | O23: =IF(AND(O$20>=$C23,O$20<=$D23),$E23,0) -> 0 | ... S23: =IF(AND(S$20>=$C23,S$20<=$D23),$E23,0) -> 0
C24: 2 | D24: 2 | E24: 350 | H24: =IF(AND(H$20>=$C24,H$20<=$D24),$E24,0) -> 350 | I24: =IF(AND(I$20>=$C24,I$20<=$D24),$E24,0) -> 0 | J24: =IF(AND(J$20>=$C24,J$20<=$D24),$E24,0) -> 350 | K24: =IF(AND(K$20>=$C24,K$20<=$D24),$E24,0) -> 0 | L24: =IF(AND(L$20>=$C24,L$20<=$D24),$E24,0) -> 350 | M24: =IF(AND(M$20>=$C24,M$20<=$D24),$E24,0) -> 0 | N24: =IF(AND(N$20>=$C24,N$20<=$D24),$E24,0) -> 350 | O24: =IF(AND(O$20>=$C24,O$20<=$D24),$E24,0) -> 350 | ... S24: =IF(AND(S$20>=$C24,S$20<=$D24),$E24,0) -> 350
C25: 3 | D25: 3 | E25: 1000 | H25: =IF(AND(H$20>=$C25,H$20<=$D25),$E25,0) -> 0 | I25: =IF(AND(I$20>=$C25,I$20<=$D25),$E25,0) -> 1000 | J25: =IF(AND(J$20>=$C25,J$20<=$D25),$E25,0) -> 0 | K25: =IF(AND(K$20>=$C25,K$20<=$D25),$E25,0) -> 1000 | L25: =IF(AND(L$20>=$C25,L$20<=$D25),$E25,0) -> 0 | M25: =IF(AND(M$20>=$C25,M$20<=$D25),$E25,0) -> 1000 | N25: =IF(AND(N$20>=$C25,N$20<=$D25),$E25,0) -> 0 | O25: =IF(AND(O$20>=$C25,O$20<=$D25),$E25,0) -> 0 | ... S25: =IF(AND(S$20>=$C25,S$20<=$D25),$E25,0) -> 0
G26: Payable | H26: =SUM(H23:H25) -> 350 | I26: =SUM(I23:I25) -> 1000 | J26: =SUM(J23:J25) -> 350 | K26: =SUM(K23:K25) -> 1000 | L26: =SUM(L23:L25) -> 350 | M26: =SUM(M23:M25) -> 1000 | N26: =SUM(N23:N25) -> 350 | O26: =SUM(O23:O25) -> 350 | ... S26: =SUM(S23:S25) -> 350
B28: CSI ventes | C28: de | D28: à | E28: Boni | H28: 4.87 | I28: 5 | J28: 4.63 | K28: 4.81 | L28: 4.78 | M28: 4.61 | N28: 4.48 | O28: 4.93 | P28: =#REF! -> #REF! | Q28: =#REF! -> #REF! | R28: =#REF! -> #REF! | S28: 4.89
C29: 4.6 | D29: 4.85 | E29: 0 | H29: 4.87 | I29: =IF(AND(I28>=$C29,I28<=$D29),$E29,0) -> 0 | J29: =IF(AND(J28>=$C29,J28<=$D29),$E29,0) -> 0 | K29: =IF(AND(K28>=$C29,K28<=$D29),$E29,0) -> 0 | L29: =IF(AND(L28>=$C29,L28<=$D29),$E29,0) -> 0 | M29: =IF(AND(M28>=$C29,M28<=$D29),$E29,0) -> 0 | N29: =IF(AND(N28>=$C29,N28<=$D29),$E29,0) -> 0 | O29: =IF(AND(O28>=$C29,O28<=$D29),$E29,0) -> 0 | P29: =IF(AND(P28>=$C29,P28<=$D29),$E29,0) -> #REF! | ... S29: =IF(AND(S28>=$C29,S28<=$D29),$E29,0) -> 0
C30: 4.86 | D30: 4.94 | E30: 350 | H30: =IF(AND(H28>=$C30,H28<=$D30),$E30,0) -> 350 | I30: =IF(AND(I28>=$C30,I28<=$D30),$E30,0) -> 0 | J30: =IF(AND(J28>=$C30,J28<=$D30),$E30,0) -> 0 | K30: =IF(AND(K28>=$C30,K28<=$D30),$E30,0) -> 0 | L30: =IF(AND(L28>=$C30,L28<=$D30),$E30,0) -> 0 | M30: =IF(AND(M28>=$C30,M28<=$D30),$E30,0) -> 0 | N30: =IF(AND(N28>=$C30,N28<=$D30),$E30,0) -> 0 | O30: =IF(AND(O28>=$C30,O28<=$D30),$E30,0) -> 350 | ... S30: =IF(AND(S28>=$C30,S28<=$D30),$E30,0) -> 350
C31: 4.95 | D31: et plus | E31: 750 | H31: =IF(AND(H28>=$C31,H28<=$D31),$E31,0) -> 0 | I31: =IF(AND(I28>=$C31,I28<=$D31),$E31,0) -> 750 | J31: =IF(AND(J28>=$C31,J28<=$D31),$E31,0) -> 0 | K31: =IF(AND(K28>=$C31,K28<=$D31),$E31,0) -> 0 | L31: =IF(AND(L28>=$C31,L28<=$D31),$E31,0) -> 0 | M31: =IF(AND(M28>=$C31,M28<=$D31),$E31,0) -> 0 | N31: =IF(AND(N28>=$C31,N28<=$D31),$E31,0) -> 0 | O31: =IF(AND(O28>=$C31,O28<=$D31),$E31,0) -> 0 | ... S31: =IF(AND(S28>=$C31,S28<=$D31),$E31,0) -> 0
G32: Payable | H32: =SUM(H29:H31) -> 354.87 | I32: =SUM(I29:I31) -> 750 | J32: =SUM(J29:J31) -> 0 | K32: =SUM(K29:K31) -> 0 | L32: =SUM(L29:L31) -> 0 | M32: =SUM(M29:M31) -> 0 | N32: =SUM(N29:N31) -> 0 | O32: =SUM(O29:O31) -> 350 | ... S32: =SUM(S29:S31) -> 350
J34: 520 | K34: 480 | L34: 410 | M34: 200 | N34: 1400 | R34: 773.72
G36: Total Mensuel | H36: =+H10+H32+H26+H18 -> 3204.87 | I36: =+I10+I32+I26+I18+I34 -> 5750 | J36: =+J10+J32+J26+J18+J34 -> 4870 | K36: =+K10+K32+K26+K18+K34 -> 3480 | L36: =+L10+L32+L26+L18+L34 -> 1260 | M36: =+M10+M32+M26+M18+M34 -> 1200 | N36: =+N10+N32+N26+N18+N34 -> 5750 | O36: =+O10+O32+O26+O18+O34 -> 4200 | P36: =+P10+P32+P26+P18+P34 -> #REF! | ... S36: =+S10+S32+S26+S18+S34 -> 4700
B38: Bonis Trimestriels
B39: Atteinte des Indicateurs Expérience + ( X de 3 ) | G39: Réalisé | J39: 2 | M39: 2 | P39: =#REF! -> #REF! | S39: =#REF! -> #REF!
B40: CSI + de 4,9 CarNet + de 90% Voksklick: sup 20 jours par mois | G40: Cible | J40: 3 | M40: 3 | P40: =#REF! -> #REF! | S40: =#REF! -> #REF!
C41: de | D41: à | E41: Boni
C42: 1 | D42: 1 | E42: 500 | J42: =IF(AND(J$39>=$C42,J$39<=$D42),$E42,0) -> 0 | M42: =IF(AND(M$39>=$C42,M$39<=$D42),$E42,0) -> 0 | P42: =IF(AND(P$39>=$C42,P$39<=$D42),$E42,0) -> #REF! | S42: =IF(AND(S$39>=$C42,S$39<=$D42),$E42,0) -> #REF!
C43: 2 | D43: 2 | E43: 1000 | J43: =IF(AND(J$39>=$C43,J$39<=$D43),$E43,0) -> 1000 | M43: =IF(AND(M$39>=$C43,M$39<=$D43),$E43,0) -> 1000 | P43: =IF(AND(P$39>=$C43,P$39<=$D43),$E43,0) -> #REF! | S43: =IF(AND(S$39>=$C43,S$39<=$D43),$E43,0) -> #REF!
C44: 3 | D44: 3 | E44: 2500 | J44: =IF(AND(J$39>=$C44,J$39<=$D44),$E44,0) -> 0 | M44: =IF(AND(M$39>=$C44,M$39<=$D44),$E44,0) -> 0 | P44: =IF(AND(P$39>=$C44,P$39<=$D44),$E44,0) -> #REF! | S44: =IF(AND(S$39>=$C44,S$39<=$D44),$E44,0) -> #REF!
G45: Payable | J45: =SUM(J42:J44) -> 1000 | M45: =SUM(M42:M44) -> 1000 | P45: =SUM(P42:P44) -> #REF! | S45: =SUM(S42:S44) -> #REF!
G47: Total Payable | J47: =+J36+J45 -> 5870 | M47: =+M36+M45 -> 2200 | P47: =+P36+P45 -> #REF! | S47: =+S36+S45 -> #REF!

Sheet Alexandre Paradis 2025
B1: Alexandre Paradis - Directeur Adjoint Ventes Neuf
B3: Bonis Mensuels | H3: 45688 | I3: 45716 | J3: 45747 | K3: 45777 | L3: 45808 | M3: 45838 | N3: 45869 | O3: 45900 | P3: 45930 | Q3: 45961 | R3: 45991 | S3: 46022
B4: Profit brut départemental NEUF | G4: Réalisé | H4: 190802 | I4: 136011 | J4: 155475
B5: vs le Budget 2025 | G5: Cible | H5: 204136 | I5: 187694 | J5: 178463
C6: de | D6: à | E6: Boni | G6: % | H6: =IFERROR(ROUND(H4/H5,3)," - - -") -> 0.935 | I6: =IFERROR(ROUND(I4/I5,3)," - - -") -> 0.725 | J6: =IFERROR(ROUND(J4/J5,3)," - - -") -> 0.871
C7: 0.85 | D7: 0.9999 | E7: 750 | H7: =IF(AND(H$6>=$C7,H$6<=$D7),$E7,0) -> 750 | I7: =IF(AND(I$6>=$C7,I$6<=$D7),$E7,0) -> 0 | J7: =IF(AND(J$6>=$C7,J$6<=$D7),$E7,0) -> 750
C8: 1 | D8: 1.0999 | E8: 1500 | H8: =IF(AND(H$6>=$C8,H$6<=$D8),$E8,0) -> 0 | I8: =IF(AND(I$6>=$C8,I$6<=$D8),$E8,0) -> 0 | J8: =IF(AND(J$6>=$C8,J$6<=$D8),$E8,0) -> 0
C9: 1.1 | D9: et plus | E9: 2000 | H9: =IF(AND(H$6>=$C9,H$6<=$D9),$E9,0) -> 0 | I9: =IF(AND(I$6>=$C9,I$6<=$D9),$E9,0) -> 0 | J9: =IF(AND(J$6>=$C9,J$6<=$D9),$E9,0) -> 0
G10: Payable | H10: =SUM(H7:H9) -> 750 | I10: =SUM(I7:I9) -> 0 | J10: =SUM(J7:J9) -> 750
B12: Atteinte de l'objectif mensuel de volume BPV OEM | G12: Réalisé | H12: ='Sebastien Fleury 2025'!H20 -> 58 | I12: 38 | J12: ='Sebastien Fleury 2025'!J20 -> 53
G13: Cible | H13: ='Sebastien Fleury 2025'!H21 -> 49 | I13: 53 | J13: ='Sebastien Fleury 2025'!J21 -> 62
C14: de | D14: à | E14: Boni | G14: % | H14: =IFERROR(ROUND(H12/H13,3)," - - -") -> 1.184 | I14: =IFERROR(ROUND(I12/I13,3)," - - -") -> 0.717 | J14: =IFERROR(ROUND(J12/J13,3)," - - -") -> 0.855
C15: 0.9 | D15: 0.9999 | E15: 500 | H15: =IF(AND(H14>=$C15,H14<=$D15),$E15,0) -> 0 | I15: =IF(AND(I14>=$C15,I14<=$D15),$E15,0) -> 0 | J15: =IF(AND(J14>=$C15,J14<=$D15),$E15,0) -> 0
C16: 1 | D16: 1.0999 | E16: 1000 | H16: =IF(AND(H13>=$C16,H13<=$D16),$E16,0) -> 0 | I16: =IF(AND(I13>=$C16,I13<=$D16),$E16,0) -> 0 | J16: =IF(AND(J13>=$C16,J13<=$D16),$E16,0) -> 0
C17: 1.1 | D17: et plus | E17: 1750 | H17: =IF(AND(H14>=$C17,H14<=$D17),$E17,0) -> 1750 | I17: =IF(AND(I14>=$C17,I14<=$D17),$E17,0) -> 0 | J17: =IF(AND(J14>=$C17,J14<=$D17),$E17,0) -> 0
G18: Payable | H18: =SUM(H15:H17) -> 1750 | I18: =SUM(I15:I17) -> 0 | J18: =SUM(J15:J17) -> 0
B20: Turn rate (mois d'avant) | H20: 0.45 | I20: 0.406 | J20: 0.4
C21: de | D21: à | E21: Boni
C22: 0.35 | D22: 0.39 | E22: 500 | H22: =IF(AND(H20>=$C22,H20<=$D22),$E22,0) -> 0 | I22: =IF(AND(I20>=$C22,I20<=$D22),$E22,0) -> 0 | J22: =IF(AND(J20>=$C22,J20<=$D22),$E22,0) -> 0 | U22: id4 _ tiguan stop sale
C23: 0.3901 | D23: 0.47 | E23: 1000 | H23: =IF(AND(H20>=$C23,H20<=$D23),$E23,0) -> 1000 | I23: =IF(AND(I20>=$C23,I20<=$D23),$E23,0) -> 1000 | J23: =IF(AND(J20>=$C23,J20<=$D23),$E23,0) -> 1000
C24: 0.4701 | D24: et plus | E24: 1500 | H24: =IF(AND(H20>=$C24,H20<=$D24),$E24,0) -> 0 | I24: =IF(AND(I20>=$C24,I20<=$D24),$E24,0) -> 0 | J24: =IF(AND(J20>=$C24,J20<=$D24),$E24,0) -> 0
G25: Payable | H25: =SUM(H22:H24) -> 1000 | I25: =SUM(I22:I24) -> 1000 | J25: =SUM(J22:J24) -> 1000
B27: CSI: Moyenne Questions D2 / D4 / D5 | G27: % | H27: 0.88 | I27: 0.85 | J27: 0.85
C28: de | D28: à | E28: Boni
C29: 0 | D29: 0.7999 | E29: 0 | H29: =IF(AND(H27>=$C29,H27<=$D29),$E29,0) -> 0 | I29: =IF(AND(I27>=$C29,I27<=$D29),$E29,0) -> 0 | J29: =IF(AND(J27>=$C29,J27<=$D29),$E29,0) -> 0
C30: 0.8 | D30: 0.8899 | E30: 500 | H30: =IF(AND(H27>=$C30,H27<=$D30),$E30,0) -> 500 | I30: =IF(AND(I27>=$C30,I27<=$D30),$E30,0) -> 500 | J30: =IF(AND(J27>=$C30,J27<=$D30),$E30,0) -> 500
C31: 0.89 | D31: et plus | E31: 1000 | H31: =IF(AND(H27>=$C31,H27<=$D31),$E31,0) -> 0 | I31: =IF(AND(I27>=$C31,I27<=$D31),$E31,0) -> 0 | J31: =IF(AND(J27>=$C31,J27<=$D31),$E31,0) -> 0
G32: Payable | H32: =SUM(H29:H31) -> 500 | I32: =SUM(I29:I31) -> 500 | J32: =SUM(J29:J31) -> 500
G34: Rattrapge | J34: 1000
G36: Total Mensuel | H36: =H10+H18+H25+H32 -> 4000 | I36: =I10+I18+I25+I32 -> 1500 | J36: =J10+J18+J25+J32+J34 -> 3250 | K36: =K10+K18+K25+K32 -> 0 | L36: =L10+L18+L25+L32 -> 0 | M36: =M10+M18+M25+M32 -> 0 | N36: =N10+N18+N25+N32 -> 0 | O36: =O10+O18+O25+O32 -> 0 | P36: =P10+P18+P25+P32 -> 0 | Q36: =Q10+Q18+Q25+Q32 -> 0 | R36: =R10+R18+R25+R32 -> 0 | S36: =S10+S18+S25+S32 -> 0
B39: Bonis Annuels
B40: Classement de la concession au Wolfsburg 2025 | G40: Réalisé
C41: de | D41: à | E41: Boni
C42: 1 | D42: 10 | E42: 5000 | S42: =IF(AND(S$40>=$C42,S$40<=$D42),$E42,0) -> 0
C43: 11 | D43: 15 | E43: 2500 | S43: =IF(AND(S$40>=$C43,S$40<=$D43),$E43,0) -> 0
C44: 16 | D44: 20 | E44: 500 | S44: =IF(AND(S$40>=$C44,S$40<=$D44),$E44,0) -> 0
G45: Payable | S45: =SUM(S42:S44) -> 0
G47: Total Payable | S47: =+S37+S45 -> 0

Sheet Alexandre Paradis 2025 v2
B1: Alexandre Paradis - Directeur Adjoint Ventes Neuf
B3: Bonis Mensuels | H3: 45688 | I3: 45716 | J3: 45747 | K3: 45777 | L3: 45808 | M3: 45838 | N3: 45869 | O3: 45900 | P3: 45930 | Q3: 45961 | R3: 45991 | S3: 46022
B4: Profit brut départemental NEUF | G4: Réalisé | K4: 192162 | L4: 155475 | M4: 155475 | N4: 155475 | O4: 155475 | P4: 155475 | Q4: 155475 | R4: 155475 | S4: 155475
B5: vs le Budget 2025 | G5: Cible | K5: 207380 | L5: 178463 | M5: 178463 | N5: 178463 | O5: 178463 | P5: 178463 | Q5: 178463 | R5: 178463 | S5: 178463
C6: de | D6: à | E6: Boni | G6: % | K6: =IFERROR(ROUND(K4/K5,3)," - - -") -> 0.927 | L6: =IFERROR(ROUND(L4/L5,3)," - - -") -> 0.871 | M6: =IFERROR(ROUND(M4/M5,3)," - - -") -> 0.871 | N6: =IFERROR(ROUND(N4/N5,3)," - - -") -> 0.871 | O6: =IFERROR(ROUND(O4/O5,3)," - - -") -> 0.871 | P6: =IFERROR(ROUND(P4/P5,3)," - - -") -> 0.871 | Q6: =IFERROR(ROUND(Q4/Q5,3)," - - -") -> 0.871 | R6: =IFERROR(ROUND(R4/R5,3)," - - -") -> 0.871 | S6: =IFERROR(ROUND(S4/S5,3)," - - -") -> 0.871
C7: 0.85 | D7: 0.9999 | E7: 500 | K7: =IF(AND(K$6>=$C7,K$6<=$D7),$E7,0) -> 500 | L7: =IF(AND(L$6>=$C7,L$6<=$D7),$E7,0) -> 500 | M7: =IF(AND(M$6>=$C7,M$6<=$D7),$E7,0) -> 500 | N7: =IF(AND(N$6>=$C7,N$6<=$D7),$E7,0) -> 500 | O7: =IF(AND(O$6>=$C7,O$6<=$D7),$E7,0) -> 500 | P7: =IF(AND(P$6>=$C7,P$6<=$D7),$E7,0) -> 500 | Q7: =IF(AND(Q$6>=$C7,Q$6<=$D7),$E7,0) -> 500 | R7: =IF(AND(R$6>=$C7,R$6<=$D7),$E7,0) -> 500 | S7: =IF(AND(S$6>=$C7,S$6<=$D7),$E7,0) -> 500
C8: 1 | D8: 1.0999 | E8: 1000 | K8: =IF(AND(K$6>=$C8,K$6<=$D8),$E8,0) -> 0 | L8: =IF(AND(L$6>=$C8,L$6<=$D8),$E8,0) -> 0 | M8: =IF(AND(M$6>=$C8,M$6<=$D8),$E8,0) -> 0 | N8: =IF(AND(N$6>=$C8,N$6<=$D8),$E8,0) -> 0 | O8: =IF(AND(O$6>=$C8,O$6<=$D8),$E8,0) -> 0 | P8: =IF(AND(P$6>=$C8,P$6<=$D8),$E8,0) -> 0 | Q8: =IF(AND(Q$6>=$C8,Q$6<=$D8),$E8,0) -> 0 | R8: =IF(AND(R$6>=$C8,R$6<=$D8),$E8,0) -> 0 | S8: =IF(AND(S$6>=$C8,S$6<=$D8),$E8,0) -> 0
C9: 1.1 | D9: et plus | E9: 1500 | K9: =IF(AND(K$6>=$C9,K$6<=$D9),$E9,0) -> 0 | L9: =IF(AND(L$6>=$C9,L$6<=$D9),$E9,0) -> 0 | M9: =IF(AND(M$6>=$C9,M$6<=$D9),$E9,0) -> 0 | N9: =IF(AND(N$6>=$C9,N$6<=$D9),$E9,0) -> 0 | O9: =IF(AND(O$6>=$C9,O$6<=$D9),$E9,0) -> 0 | P9: =IF(AND(P$6>=$C9,P$6<=$D9),$E9,0) -> 0 | Q9: =IF(AND(Q$6>=$C9,Q$6<=$D9),$E9,0) -> 0 | R9: =IF(AND(R$6>=$C9,R$6<=$D9),$E9,0) -> 0 | S9: =IF(AND(S$6>=$C9,S$6<=$D9),$E9,0) -> 0
G10: Payable | K10: =SUM(K7:K9) -> 500 | L10: =SUM(L7:L9) -> 500 | M10: =SUM(M7:M9) -> 500 | N10: =SUM(N7:N9) -> 500 | O10: =SUM(O7:O9) -> 500 | P10: =SUM(P7:P9) -> 500 | Q10: =SUM(Q7:Q9) -> 500 | R10: =SUM(R7:R9) -> 500 | S10: =SUM(S7:S9) -> 500
B12: Profit brut départemental USAGE | G12: Réalisé | K12: 115188 | L12: ='Sebastien Fleury 2025'!L20 -> 0 | M12: ='Sebastien Fleury 2025'!M20 -> 0 | N12: ='Sebastien Fleury 2025'!N20 -> 0 | O12: ='Sebastien Fleury 2025'!O20 -> 0 | P12: ='Sebastien Fleury 2025'!P20 -> 0 | Q12: ='Sebastien Fleury 2025'!Q20 -> 0 | R12: ='Sebastien Fleury 2025'!R20 -> 0 | S12: ='Sebastien Fleury 2025'!S20 -> 0
B13: vs le Budget 2025 | G13: Cible | K13: 109700 | L13: ='Sebastien Fleury 2025'!L21 -> 0 | M13: ='Sebastien Fleury 2025'!M21 -> 0 | N13: ='Sebastien Fleury 2025'!N21 -> 0 | O13: ='Sebastien Fleury 2025'!O21 -> 0 | P13: ='Sebastien Fleury 2025'!P21 -> 0 | Q13: ='Sebastien Fleury 2025'!Q21 -> 0 | R13: ='Sebastien Fleury 2025'!R21 -> 0 | S13: ='Sebastien Fleury 2025'!S21 -> 0
C14: de | D14: à | E14: Boni | G14: % | K14: =IFERROR(ROUND(K12/K13,3)," - - -") -> 1.05 | L14: =IFERROR(ROUND(L12/L13,3)," - - -") -> - - - | M14: =IFERROR(ROUND(M12/M13,3)," - - -") -> - - - | N14: =IFERROR(ROUND(N12/N13,3)," - - -") -> - - - | O14: =IFERROR(ROUND(O12/O13,3)," - - -") -> - - - | P14: =IFERROR(ROUND(P12/P13,3)," - - -") -> - - - | Q14: =IFERROR(ROUND(Q12/Q13,3)," - - -") -> - - - | R14: =IFERROR(ROUND(R12/R13,3)," - - -") -> - - - | S14: =IFERROR(ROUND(S12/S13,3)," - - -") -> - - -
C15: 0.85 | D15: 0.9999 | E15: 500 | K15: =IF(AND(K14>=$C15,K14<=$D15),$E15,0) -> 0 | L15: =IF(AND(L14>=$C15,L14<=$D15),$E15,0) -> 0 | M15: =IF(AND(M14>=$C15,M14<=$D15),$E15,0) -> 0 | N15: =IF(AND(N14>=$C15,N14<=$D15),$E15,0) -> 0 | O15: =IF(AND(O14>=$C15,O14<=$D15),$E15,0) -> 0 | P15: =IF(AND(P14>=$C15,P14<=$D15),$E15,0) -> 0 | Q15: =IF(AND(Q14>=$C15,Q14<=$D15),$E15,0) -> 0 | R15: =IF(AND(R14>=$C15,R14<=$D15),$E15,0) -> 0 | S15: =IF(AND(S14>=$C15,S14<=$D15),$E15,0) -> 0
C16: 1 | D16: 1.0999 | E16: 1000 | K16: =IF(AND(K14>=$C16,K14<=$D16),$E16,0) -> 1000 | L16: =IF(AND(L14>=$C16,L14<=$D16),$E16,0) -> 0 | M16: =IF(AND(M14>=$C16,M14<=$D16),$E16,0) -> 0 | N16: =IF(AND(N14>=$C16,N14<=$D16),$E16,0) -> 0 | O16: =IF(AND(O14>=$C16,O14<=$D16),$E16,0) -> 0 | P16: =IF(AND(P14>=$C16,P14<=$D16),$E16,0) -> 0 | Q16: =IF(AND(Q14>=$C16,Q14<=$D16),$E16,0) -> 0 | R16: =IF(AND(R14>=$C16,R14<=$D16),$E16,0) -> 0 | S16: =IF(AND(S14>=$C16,S14<=$D16),$E16,0) -> 0
C17: 1.1 | D17: et plus | E17: 1500 | K17: =IF(AND(K14>=$C17,K14<=$D17),$E17,0) -> 0 | L17: =IF(AND(L14>=$C17,L14<=$D17),$E17,0) -> 1500 | M17: =IF(AND(M14>=$C17,M14<=$D17),$E17,0) -> 1500 | N17: =IF(AND(N14>=$C17,N14<=$D17),$E17,0) -> 1500 | O17: =IF(AND(O14>=$C17,O14<=$D17),$E17,0) -> 1500 | P17: =IF(AND(P14>=$C17,P14<=$D17),$E17,0) -> 1500 | Q17: =IF(AND(Q14>=$C17,Q14<=$D17),$E17,0) -> 1500 | R17: =IF(AND(R14>=$C17,R14<=$D17),$E17,0) -> 1500 | S17: =IF(AND(S14>=$C17,S14<=$D17),$E17,0) -> 1500
G18: Payable | K18: =SUM(K15:K17) -> 1000 | L18: =SUM(L15:L17) -> 1500 | M18: =SUM(M15:M17) -> 1500 | N18: =SUM(N15:N17) -> 1500 | O18: =SUM(O15:O17) -> 1500 | P18: =SUM(P15:P17) -> 1500 | Q18: =SUM(Q15:Q17) -> 1500 | R18: =SUM(R15:R17) -> 1500 | S18: =SUM(S15:S17) -> 1500
B20: Objectifs de volumes vehicules neuf selon BPV | G20: Réalisé | K20: 56 | L20: 0 | M20: 0 | N20: 0 | O20: 0 | P20: 0 | Q20: 0 | R20: 0 | S20: 0
G21: Cible | K21: 56 | L21: 0 | M21: 0 | N21: 0 | O21: 0 | P21: 0 | Q21: 0 | R21: 0 | S21: 0
C22: de | D22: à | E22: Boni | G22: % | K22: =IFERROR(ROUND(K20/K21,3)," - - -") -> 1 | L22: =IFERROR(ROUND(L20/L21,3)," - - -") -> - - - | M22: =IFERROR(ROUND(M20/M21,3)," - - -") -> - - - | N22: =IFERROR(ROUND(N20/N21,3)," - - -") -> - - - | O22: =IFERROR(ROUND(O20/O21,3)," - - -") -> - - - | P22: =IFERROR(ROUND(P20/P21,3)," - - -") -> - - - | Q22: =IFERROR(ROUND(Q20/Q21,3)," - - -") -> - - - | R22: =IFERROR(ROUND(R20/R21,3)," - - -") -> - - - | S22: =IFERROR(ROUND(S20/S21,3)," - - -") -> - - -
C23: 0.9 | D23: 0.9999 | E23: 500 | K23: =IF(AND(K$22>=$C23,K$22<=$D23),$E23,0) -> 0 | L23: =IF(AND(L$22>=$C23,L$22<=$D23),$E23,0) -> 0 | M23: =IF(AND(M$22>=$C23,M$22<=$D23),$E23,0) -> 0 | N23: =IF(AND(N$22>=$C23,N$22<=$D23),$E23,0) -> 0 | O23: =IF(AND(O$22>=$C23,O$22<=$D23),$E23,0) -> 0 | P23: =IF(AND(P$22>=$C23,P$22<=$D23),$E23,0) -> 0 | Q23: =IF(AND(Q$22>=$C23,Q$22<=$D23),$E23,0) -> 0 | R23: =IF(AND(R$22>=$C23,R$22<=$D23),$E23,0) -> 0 | S23: =IF(AND(S$22>=$C23,S$22<=$D23),$E23,0) -> 0
C24: 1 | D24: 1.1999 | E24: 1000 | K24: =IF(AND(K$22>=$C24,K$22<=$D24),$E24,0) -> 1000 | L24: =IF(AND(L$22>=$C24,L$22<=$D24),$E24,0) -> 0 | M24: =IF(AND(M$22>=$C24,M$22<=$D24),$E24,0) -> 0 | N24: =IF(AND(N$22>=$C24,N$22<=$D24),$E24,0) -> 0 | O24: =IF(AND(O$22>=$C24,O$22<=$D24),$E24,0) -> 0 | P24: =IF(AND(P$22>=$C24,P$22<=$D24),$E24,0) -> 0 | Q24: =IF(AND(Q$22>=$C24,Q$22<=$D24),$E24,0) -> 0 | R24: =IF(AND(R$22>=$C24,R$22<=$D24),$E24,0) -> 0 | S24: =IF(AND(S$22>=$C24,S$22<=$D24),$E24,0) -> 0
C25: 1.2 | D25: et plus | E25: 1750 | K25: =IF(AND(K$22>=$C25,K$22<=$D25),$E25,0) -> 0 | L25: =IF(AND(L$22>=$C25,L$22<=$D25),$E25,0) -> 1750 | M25: =IF(AND(M$22>=$C25,M$22<=$D25),$E25,0) -> 1750 | N25: =IF(AND(N$22>=$C25,N$22<=$D25),$E25,0) -> 1750 | O25: =IF(AND(O$22>=$C25,O$22<=$D25),$E25,0) -> 1750 | P25: =IF(AND(P$22>=$C25,P$22<=$D25),$E25,0) -> 1750 | Q25: =IF(AND(Q$22>=$C25,Q$22<=$D25),$E25,0) -> 1750 | R25: =IF(AND(R$22>=$C25,R$22<=$D25),$E25,0) -> 1750 | S25: =IF(AND(S$22>=$C25,S$22<=$D25),$E25,0) -> 1750
G26: Payable | K26: =SUM(K23:K25) -> 1000 | L26: =SUM(L23:L25) -> 1750 | M26: =SUM(M23:M25) -> 1750 | N26: =SUM(N23:N25) -> 1750 | O26: =SUM(O23:O25) -> 1750 | P26: =SUM(P23:P25) -> 1750 | Q26: =SUM(Q23:Q25) -> 1750 | R26: =SUM(R23:R25) -> 1750 | S26: =SUM(S23:S25) -> 1750
B28: Critere d'age de l'inventaire | K28: 0.105
B29: Véhicules > 180 jours en inventaire comptable hors stop sale | C29: de | D29: à | E29: Boni
C30: 1 | D30: 0.15 | E30: 0 | K30: =IF(AND(K28<=$C30,K28>=$D30),$E30,0) -> 0 | L30: =IF(AND(L28<=$C30,L28>=$D30),$E30,0) -> 0 | M30: =IF(AND(M28<=$C30,M28>=$D30),$E30,0) -> 0 | N30: =IF(AND(N28<=$C30,N28>=$D30),$E30,0) -> 0 | O30: =IF(AND(O28<=$C30,O28>=$D30),$E30,0) -> 0 | P30: =IF(AND(P28<=$C30,P28>=$D30),$E30,0) -> 0 | Q30: =IF(AND(Q28<=$C30,Q28>=$D30),$E30,0) -> 0 | R30: =IF(AND(R28<=$C30,R28>=$D30),$E30,0) -> 0 | S30: =IF(AND(S28<=$C30,S28>=$D30),$E30,0) -> 0 | U30: id4 _ tiguan stop sale
C31: 0.149 | D31: 0.1 | E31: 1000 | K31: =IF(AND(K28<=$C31,K28>=$D31),$E31,0) -> 1000 | L31: =IF(AND(L28<=$C31,L28>=$D31),$E31,0) -> 0 | M31: =IF(AND(M28<=$C31,M28>=$D31),$E31,0) -> 0 | N31: =IF(AND(N28<=$C31,N28>=$D31),$E31,0) -> 0 | O31: =IF(AND(O28<=$C31,O28>=$D31),$E31,0) -> 0 | P31: =IF(AND(P28<=$C31,P28>=$D31),$E31,0) -> 0 | Q31: =IF(AND(Q28<=$C31,Q28>=$D31),$E31,0) -> 0 | R31: =IF(AND(R28<=$C31,R28>=$D31),$E31,0) -> 0 | S31: =IF(AND(S28<=$C31,S28>=$D31),$E31,0) -> 0
C32: 0.099 | D32: et moins | E32: 1500 | K32: =IF(AND(K28<=$C32,K28>=$D32),$E32,0) -> 0 | L32: =IF(AND(L28<=$C32,L28>=$D32),$E32,0) -> 0 | M32: =IF(AND(M28<=$C32,M28>=$D32),$E32,0) -> 0 | N32: =IF(AND(N28<=$C32,N28>=$D32),$E32,0) -> 0 | O32: =IF(AND(O28<=$C32,O28>=$D32),$E32,0) -> 0 | P32: =IF(AND(P28<=$C32,P28>=$D32),$E32,0) -> 0 | Q32: =IF(AND(Q28<=$C32,Q28>=$D32),$E32,0) -> 0 | R32: =IF(AND(R28<=$C32,R28>=$D32),$E32,0) -> 0 | S32: =IF(AND(S28<=$C32,S28>=$D32),$E32,0) -> 0
G33: Payable | K33: =SUM(K30:K32) -> 1000 | L33: =SUM(L30:L32) -> 0 | M33: =SUM(M30:M32) -> 0 | N33: =SUM(N30:N32) -> 0 | O33: =SUM(O30:O32) -> 0 | P33: =SUM(P30:P32) -> 0 | Q33: =SUM(Q30:Q32) -> 0 | R33: =SUM(R30:R32) -> 0 | S33: =SUM(S30:S32) -> 0
B35: CSI: Moyenne Questions D2 / D4 / D5 | G35: % | K35: 0.92
C36: de | D36: à | E36: Boni
C37: 0 | D37: 0.7999 | E37: 0 | K37: =IF(AND(K35>=$C37,K35<=$D37),$E37,0) -> 0 | L37: =IF(AND(L35>=$C37,L35<=$D37),$E37,0) -> 0 | M37: =IF(AND(M35>=$C37,M35<=$D37),$E37,0) -> 0 | N37: =IF(AND(N35>=$C37,N35<=$D37),$E37,0) -> 0 | O37: =IF(AND(O35>=$C37,O35<=$D37),$E37,0) -> 0 | P37: =IF(AND(P35>=$C37,P35<=$D37),$E37,0) -> 0 | Q37: =IF(AND(Q35>=$C37,Q35<=$D37),$E37,0) -> 0 | R37: =IF(AND(R35>=$C37,R35<=$D37),$E37,0) -> 0 | S37: =IF(AND(S35>=$C37,S35<=$D37),$E37,0) -> 0
C38: 0.8 | D38: 0.8899 | E38: 500 | K38: =IF(AND(K35>=$C38,K35<=$D38),$E38,0) -> 0 | L38: =IF(AND(L35>=$C38,L35<=$D38),$E38,0) -> 0 | M38: =IF(AND(M35>=$C38,M35<=$D38),$E38,0) -> 0 | N38: =IF(AND(N35>=$C38,N35<=$D38),$E38,0) -> 0 | O38: =IF(AND(O35>=$C38,O35<=$D38),$E38,0) -> 0 | P38: =IF(AND(P35>=$C38,P35<=$D38),$E38,0) -> 0 | Q38: =IF(AND(Q35>=$C38,Q35<=$D38),$E38,0) -> 0 | R38: =IF(AND(R35>=$C38,R35<=$D38),$E38,0) -> 0 | S38: =IF(AND(S35>=$C38,S35<=$D38),$E38,0) -> 0
C39: 0.89 | D39: et plus | E39: 1000 | K39: =IF(AND(K35>=$C39,K35<=$D39),$E39,0) -> 1000 | L39: =IF(AND(L35>=$C39,L35<=$D39),$E39,0) -> 0 | M39: =IF(AND(M35>=$C39,M35<=$D39),$E39,0) -> 0 | N39: =IF(AND(N35>=$C39,N35<=$D39),$E39,0) -> 0 | O39: =IF(AND(O35>=$C39,O35<=$D39),$E39,0) -> 0 | P39: =IF(AND(P35>=$C39,P35<=$D39),$E39,0) -> 0 | Q39: =IF(AND(Q35>=$C39,Q35<=$D39),$E39,0) -> 0 | R39: =IF(AND(R35>=$C39,R35<=$D39),$E39,0) -> 0 | S39: =IF(AND(S35>=$C39,S35<=$D39),$E39,0) -> 0
G40: Payable | K40: =SUM(K37:K39) -> 1000 | L40: =SUM(L37:L39) -> 0 | M40: =SUM(M37:M39) -> 0 | N40: =SUM(N37:N39) -> 0 | O40: =SUM(O37:O39) -> 0 | P40: =SUM(P37:P39) -> 0 | Q40: =SUM(Q37:Q39) -> 0 | R40: =SUM(R37:R39) -> 0 | S40: =SUM(S37:S39) -> 0
G42: Rattrapge
G44: Total Mensuel | K44: =K10+K18+K33+K40+K26 -> 4500 | L44: =L10+L18+L33+L40+L26 -> 3750 | M44: =M10+M18+M33+M40+M26 -> 3750 | N44: =N10+N18+N33+N40+N26 -> 3750 | O44: =O10+O18+O33+O40+O26 -> 3750 | P44: =P10+P18+P33+P40+P26 -> 3750 | Q44: =Q10+Q18+Q33+Q40+Q26 -> 3750 | R44: =R10+R18+R33+R40+R26 -> 3750 | S44: =S10+S18+S33+S40+S26 -> 3750
B47: Bonis Annuels
B48: Classement de la concession au Wolfsburg 2025 | G48: Réalisé
C49: de | D49: à | E49: Boni
C50: 1 | D50: 10 | E50: 5000 | S50: =IF(AND(S$48>=$C50,S$48<=$D50),$E50,0) -> 0
C51: 11 | D51: 15 | E51: 2500 | S51: =IF(AND(S$48>=$C51,S$48<=$D51),$E51,0) -> 0
C52: 16 | D52: 20 | E52: 500 | S52: =IF(AND(S$48>=$C52,S$48<=$D52),$E52,0) -> 0
G53: Payable | S53: =SUM(S50:S52) -> 0
G55: Total Payable | S55: =+S45+S53 -> 0

Sheet Karim Noori 2025
B1: Alexandre Paradis - Directeur Adjoint Ventes Neuf
B3: Bonis Mensuels | H3: 45688 | I3: 45716 | J3: 45747 | K3: 45777 | L3: 45808 | M3: 45838 | N3: 45869 | O3: 45900 | P3: 45930 | Q3: 45961 | R3: 45991 | S3: 46022
B4: Profit brut départemental NEUF | G4: Réalisé | H4: 190802 | I4: 136011 | J4: 155475
B5: vs le Budget 2025 | G5: Cible | H5: 204136 | I5: 187694 | J5: 178463
C6: de | D6: à | E6: Boni | G6: % | H6: =IFERROR(ROUND(H4/H5,3)," - - -") -> 0.935 | I6: =IFERROR(ROUND(I4/I5,3)," - - -") -> 0.725 | J6: =IFERROR(ROUND(J4/J5,3)," - - -") -> 0.871
C7: 0.85 | D7: 0.9999 | E7: 750 | H7: =IF(AND(H$6>=$C7,H$6<=$D7),$E7,0) -> 750 | I7: =IF(AND(I$6>=$C7,I$6<=$D7),$E7,0) -> 0 | J7: =IF(AND(J$6>=$C7,J$6<=$D7),$E7,0) -> 750
C8: 1 | D8: 1.0999 | E8: 1500 | H8: =IF(AND(H$6>=$C8,H$6<=$D8),$E8,0) -> 0 | I8: =IF(AND(I$6>=$C8,I$6<=$D8),$E8,0) -> 0 | J8: =IF(AND(J$6>=$C8,J$6<=$D8),$E8,0) -> 0
C9: 1.1 | D9: et plus | E9: 2000 | H9: =IF(AND(H$6>=$C9,H$6<=$D9),$E9,0) -> 0 | I9: =IF(AND(I$6>=$C9,I$6<=$D9),$E9,0) -> 0 | J9: =IF(AND(J$6>=$C9,J$6<=$D9),$E9,0) -> 0
G10: Payable | H10: =SUM(H7:H9) -> 750 | I10: =SUM(I7:I9) -> 0 | J10: =SUM(J7:J9) -> 750
B12: Atteinte de l'objectif mensuel de volume BPV OEM | G12: Réalisé | H12: ='Sebastien Fleury 2025'!H20 -> 58 | I12: 38 | J12: ='Sebastien Fleury 2025'!J20 -> 53
G13: Cible | H13: ='Sebastien Fleury 2025'!H21 -> 49 | I13: 53 | J13: ='Sebastien Fleury 2025'!J21 -> 62
C14: de | D14: à | E14: Boni | G14: % | H14: =IFERROR(ROUND(H12/H13,3)," - - -") -> 1.184 | I14: =IFERROR(ROUND(I12/I13,3)," - - -") -> 0.717 | J14: =IFERROR(ROUND(J12/J13,3)," - - -") -> 0.855
C15: 0.9 | D15: 0.9999 | E15: 500 | H15: =IF(AND(H14>=$C15,H14<=$D15),$E15,0) -> 0 | I15: =IF(AND(I14>=$C15,I14<=$D15),$E15,0) -> 0 | J15: =IF(AND(J14>=$C15,J14<=$D15),$E15,0) -> 0
C16: 1 | D16: 1.0999 | E16: 1000 | H16: =IF(AND(H13>=$C16,H13<=$D16),$E16,0) -> 0 | I16: =IF(AND(I13>=$C16,I13<=$D16),$E16,0) -> 0 | J16: =IF(AND(J13>=$C16,J13<=$D16),$E16,0) -> 0
C17: 1.1 | D17: et plus | E17: 1750 | H17: =IF(AND(H14>=$C17,H14<=$D17),$E17,0) -> 1750 | I17: =IF(AND(I14>=$C17,I14<=$D17),$E17,0) -> 0 | J17: =IF(AND(J14>=$C17,J14<=$D17),$E17,0) -> 0
G18: Payable | H18: =SUM(H15:H17) -> 1750 | I18: =SUM(I15:I17) -> 0 | J18: =SUM(J15:J17) -> 0
B20: Turn rate (mois d'avant) | H20: 0.45 | I20: 0.406 | J20: 0.4
C21: de | D21: à | E21: Boni
C22: 0.35 | D22: 0.39 | E22: 500 | H22: =IF(AND(H20>=$C22,H20<=$D22),$E22,0) -> 0 | I22: =IF(AND(I20>=$C22,I20<=$D22),$E22,0) -> 0 | J22: =IF(AND(J20>=$C22,J20<=$D22),$E22,0) -> 0 | U22: id4 _ tiguan stop sale
C23: 0.3901 | D23: 0.47 | E23: 1000 | H23: =IF(AND(H20>=$C23,H20<=$D23),$E23,0) -> 1000 | I23: =IF(AND(I20>=$C23,I20<=$D23),$E23,0) -> 1000 | J23: =IF(AND(J20>=$C23,J20<=$D23),$E23,0) -> 1000
C24: 0.4701 | D24: et plus | E24: 1500 | H24: =IF(AND(H20>=$C24,H20<=$D24),$E24,0) -> 0 | I24: =IF(AND(I20>=$C24,I20<=$D24),$E24,0) -> 0 | J24: =IF(AND(J20>=$C24,J20<=$D24),$E24,0) -> 0
G25: Payable | H25: =SUM(H22:H24) -> 1000 | I25: =SUM(I22:I24) -> 1000 | J25: =SUM(J22:J24) -> 1000
B27: CSI: Moyenne Questions D2 / D4 / D5 | G27: % | H27: 0.88 | I27: 0.85 | J27: 0.85
C28: de | D28: à | E28: Boni
C29: 0 | D29: 0.7999 | E29: 0 | H29: =IF(AND(H27>=$C29,H27<=$D29),$E29,0) -> 0 | I29: =IF(AND(I27>=$C29,I27<=$D29),$E29,0) -> 0 | J29: =IF(AND(J27>=$C29,J27<=$D29),$E29,0) -> 0
C30: 0.8 | D30: 0.8899 | E30: 500 | H30: =IF(AND(H27>=$C30,H27<=$D30),$E30,0) -> 500 | I30: =IF(AND(I27>=$C30,I27<=$D30),$E30,0) -> 500 | J30: =IF(AND(J27>=$C30,J27<=$D30),$E30,0) -> 500
C31: 0.89 | D31: et plus | E31: 1000 | H31: =IF(AND(H27>=$C31,H27<=$D31),$E31,0) -> 0 | I31: =IF(AND(I27>=$C31,I27<=$D31),$E31,0) -> 0 | J31: =IF(AND(J27>=$C31,J27<=$D31),$E31,0) -> 0
G32: Payable | H32: =SUM(H29:H31) -> 500 | I32: =SUM(I29:I31) -> 500 | J32: =SUM(J29:J31) -> 500
G34: Rattrapge | J34: 1000
G36: Total Mensuel | H36: =H10+H18+H25+H32 -> 4000 | I36: =I10+I18+I25+I32 -> 1500 | J36: =J10+J18+J25+J32+J34 -> 3250 | K36: =K10+K18+K25+K32 -> 0 | L36: =L10+L18+L25+L32 -> 0 | M36: =M10+M18+M25+M32 -> 0 | N36: =N10+N18+N25+N32 -> 0 | O36: =O10+O18+O25+O32 -> 0 | P36: =P10+P18+P25+P32 -> 0 | Q36: =Q10+Q18+Q25+Q32 -> 0 | R36: =R10+R18+R25+R32 -> 0 | S36: =S10+S18+S25+S32 -> 0
B39: Bonis Annuels
B40: Classement de la concession au Wolfsburg 2025 | G40: Réalisé
C41: de | D41: à | E41: Boni
C42: 1 | D42: 10 | E42: 5000 | S42: =IF(AND(S$40>=$C42,S$40<=$D42),$E42,0) -> 0
C43: 11 | D43: 15 | E43: 2500 | S43: =IF(AND(S$40>=$C43,S$40<=$D43),$E43,0) -> 0
C44: 16 | D44: 20 | E44: 500 | S44: =IF(AND(S$40>=$C44,S$40<=$D44),$E44,0) -> 0
G45: Payable | S45: =SUM(S42:S44) -> 0
G47: Total Payable | S47: =+S37+S45 -> 0

Sheet Marc-Olivier Poulin 2025
B1: Marc-Olivier Poulin - Directeur Adjoint Ventes Usagé
B3: Bonis Mensuels | H3: 45688 | I3: 45716 | J3: 45747 | K3: 45777 | L3: 45808 | M3: 45838 | N3: 45869 | O3: 45900 | P3: 45930 | Q3: 45961 | R3: 45991 | S3: 46022
B4: Profit brut départemental USAGÉ | G4: Réalisé | H4: 88469 | I4: 57239 | J4: 108243 | K4: 115188 | L4: 0 | M4: 0 | N4: 0 | O4: 0 | P4: 0 | Q4: 0 | R4: 0 | S4: 0
B5: vs le Budget 2025 | G5: Cible | H5: 79200 | I5: 95200 | J5: 102000 | K5: 109700 | L5: 0 | M5: 0 | N5: 0 | O5: 0 | P5: 0 | Q5: 0 | R5: 0 | S5: 0
C6: de | D6: à | E6: Boni | G6: % | H6: =IFERROR(ROUND(H4/H5,3)," - - -") -> 1.117 | I6: =IFERROR(ROUND(I4/I5,3)," - - -") -> 0.601 | J6: =IFERROR(ROUND(J4/J5,3)," - - -") -> 1.061 | K6: =IFERROR(ROUND(K4/K5,3)," - - -") -> 1.05 | L6: =IFERROR(ROUND(L4/L5,3)," - - -") -> - - - | M6: =IFERROR(ROUND(M4/M5,3)," - - -") -> - - - | N6: =IFERROR(ROUND(N4/N5,3)," - - -") -> - - - | O6: =IFERROR(ROUND(O4/O5,3)," - - -") -> - - - | ... S6: =IFERROR(ROUND(S4/S5,3)," - - -") -> - - -
C7: 0.9 | D7: 0.9999 | E7: 1000 | H7: =IF(AND(H$6>=$C7,H$6<=$D7),$E7,0) -> 0 | I7: =IF(AND(I$6>=$C7,I$6<=$D7),$E7,0) -> 0 | J7: =IF(AND(J$6>=$C7,J$6<=$D7),$E7,0) -> 0 | K7: =IF(AND(K$6>=$C7,K$6<=$D7),$E7,0) -> 0 | L7: =IF(AND(L$6>=$C7,L$6<=$D7),$E7,0) -> 0 | M7: =IF(AND(M$6>=$C7,M$6<=$D7),$E7,0) -> 0 | N7: =IF(AND(N$6>=$C7,N$6<=$D7),$E7,0) -> 0 | O7: =IF(AND(O$6>=$C7,O$6<=$D7),$E7,0) -> 0 | ... S7: =IF(AND(S$6>=$C7,S$6<=$D7),$E7,0) -> 0
C8: 1 | D8: 1.0999 | E8: 1500 | H8: =IF(AND(H$6>=$C8,H$6<=$D8),$E8,0) -> 0 | I8: =IF(AND(I$6>=$C8,I$6<=$D8),$E8,0) -> 0 | J8: =IF(AND(J$6>=$C8,J$6<=$D8),$E8,0) -> 1500 | K8: =IF(AND(K$6>=$C8,K$6<=$D8),$E8,0) -> 1500 | L8: =IF(AND(L$6>=$C8,L$6<=$D8),$E8,0) -> 0 | M8: =IF(AND(M$6>=$C8,M$6<=$D8),$E8,0) -> 0 | N8: =IF(AND(N$6>=$C8,N$6<=$D8),$E8,0) -> 0 | O8: =IF(AND(O$6>=$C8,O$6<=$D8),$E8,0) -> 0 | ... S8: =IF(AND(S$6>=$C8,S$6<=$D8),$E8,0) -> 0
C9: 1.1 | D9: et plus | E9: 2000 | H9: =IF(AND(H$6>=$C9,H$6<=$D9),$E9,0) -> 2000 | I9: =IF(AND(I$6>=$C9,I$6<=$D9),$E9,0) -> 0 | J9: =IF(AND(J$6>=$C9,J$6<=$D9),$E9,0) -> 0 | K9: =IF(AND(K$6>=$C9,K$6<=$D9),$E9,0) -> 0 | L9: =IF(AND(L$6>=$C9,L$6<=$D9),$E9,0) -> 2000 | M9: =IF(AND(M$6>=$C9,M$6<=$D9),$E9,0) -> 2000 | N9: =IF(AND(N$6>=$C9,N$6<=$D9),$E9,0) -> 2000 | O9: =IF(AND(O$6>=$C9,O$6<=$D9),$E9,0) -> 2000 | ... S9: =IF(AND(S$6>=$C9,S$6<=$D9),$E9,0) -> 2000
G10: Payable | H10: =SUM(H7:H9) -> 2000 | I10: =SUM(I7:I9) -> 0 | J10: =SUM(J7:J9) -> 1500 | K10: =SUM(K7:K9) -> 1500 | L10: =SUM(L7:L9) -> 2000 | M10: =SUM(M7:M9) -> 2000 | N10: =SUM(N7:N9) -> 2000 | O10: =SUM(O7:O9) -> 2000 | ... S10: =SUM(S7:S9) -> 2000
B12: Atteinte de l'objectif mensuel de volume BPV OEM | G12: Réalisé | H12: 16 | I12: 11 | J12: 23 | K12: 28 | L12: 0 | M12: 0 | N12: 0 | O12: 0 | P12: 0 | Q12: 0 | R12: 0 | S12: 0
G13: Cible | H13: 16 | I13: 16 | J13: 20 | K13: 20 | L13: 0 | M13: 0 | N13: 0 | O13: 0 | P13: 0 | Q13: 0 | R13: 0 | S13: 0
C14: de | D14: à | E14: Boni | G14: % | H14: 1.1 | I14: =IFERROR(ROUND(I12/I13,3)," - - -") -> 0.688 | J14: =IFERROR(ROUND(J12/J13,3)," - - -") -> 1.15 | K14: =IFERROR(ROUND(K12/K13,3)," - - -") -> 1.4 | L14: =IFERROR(ROUND(L12/L13,3)," - - -") -> - - - | M14: =IFERROR(ROUND(M12/M13,3)," - - -") -> - - - | N14: =IFERROR(ROUND(N12/N13,3)," - - -") -> - - - | O14: =IFERROR(ROUND(O12/O13,3)," - - -") -> - - - | P14: =IFERROR(ROUND(P12/P13,3)," - - -") -> - - - | ... S14: =IFERROR(ROUND(S12/S13,3)," - - -") -> - - -
C15: 0.9 | D15: 0.9999 | E15: 500 | H15: =IF(AND(H14>=$C15,H14<=$D15),$E15,0) -> 0 | I15: =IF(AND(I14>=$C15,I14<=$D15),$E15,0) -> 0 | J15: =IF(AND(J14>=$C15,J14<=$D15),$E15,0) -> 0 | K15: =IF(AND(K14>=$C15,K14<=$D15),$E15,0) -> 0 | L15: =IF(AND(L14>=$C15,L14<=$D15),$E15,0) -> 0 | M15: =IF(AND(M14>=$C15,M14<=$D15),$E15,0) -> 0 | N15: =IF(AND(N14>=$C15,N14<=$D15),$E15,0) -> 0 | O15: =IF(AND(O14>=$C15,O14<=$D15),$E15,0) -> 0 | ... S15: =IF(AND(S14>=$C15,S14<=$D15),$E15,0) -> 0
C16: 1 | D16: 1.0999 | E16: 1000 | H16: =IF(AND(H14>=$C16,H14<=$D16),$E16,0) -> 0 | I16: =IF(AND(I14>=$C16,I14<=$D16),$E16,0) -> 0 | J16: =IF(AND(J14>=$C16,J14<=$D16),$E16,0) -> 0 | K16: =IF(AND(K14>=$C16,K14<=$D16),$E16,0) -> 0 | L16: =IF(AND(L14>=$C16,L14<=$D16),$E16,0) -> 0 | M16: =IF(AND(M14>=$C16,M14<=$D16),$E16,0) -> 0 | N16: =IF(AND(N14>=$C16,N14<=$D16),$E16,0) -> 0 | O16: =IF(AND(O14>=$C16,O14<=$D16),$E16,0) -> 0 | ... S16: =IF(AND(S14>=$C16,S14<=$D16),$E16,0) -> 0
C17: 1.1 | D17: et plus | E17: 1500 | H17: =IF(AND(H14>=$C17,H14<=$D17),$E17,0) -> 1500 | I17: =IF(AND(I14>=$C17,I14<=$D17),$E17,0) -> 0 | J17: =IF(AND(J14>=$C17,J14<=$D17),$E17,0) -> 1500 | K17: =IF(AND(K14>=$C17,K14<=$D17),$E17,0) -> 1500 | L17: =IF(AND(L14>=$C17,L14<=$D17),$E17,0) -> 1500 | M17: =IF(AND(M14>=$C17,M14<=$D17),$E17,0) -> 1500 | N17: =IF(AND(N14>=$C17,N14<=$D17),$E17,0) -> 1500 | O17: =IF(AND(O14>=$C17,O14<=$D17),$E17,0) -> 1500 | ... S17: =IF(AND(S14>=$C17,S14<=$D17),$E17,0) -> 1500
G18: Payable | H18: =SUM(H15:H17) -> 1500 | I18: =SUM(I15:I17) -> 0 | J18: =SUM(J15:J17) -> 1500 | K18: =SUM(K15:K17) -> 1500 | L18: =SUM(L15:L17) -> 1500 | M18: =SUM(M15:M17) -> 1500 | N18: =SUM(N15:N17) -> 1500 | O18: =SUM(O15:O17) -> 1500 | ... S18: =SUM(S15:S17) -> 1500
B20: Indicateurs de performance | H20: 2 | I20: 3 | J20: 3 | K20: 3
C21: de | D21: à | E21: Boni
C22: 1 | D22: 1 | E22: 250 | H22: =IF(AND(H20>=$C22,H20<=$D22),$E22,0) -> 0 | I22: =IF(AND(I20>=$C22,I20<=$D22),$E22,0) -> 0 | J22: =IF(AND(J20>=$C22,J20<=$D22),$E22,0) -> 0 | K22: =IF(AND(K20>=$C22,K20<=$D22),$E22,0) -> 0 | L22: =IF(AND(L20>=$C22,L20<=$D22),$E22,0) -> 0 | M22: =IF(AND(M20>=$C22,M20<=$D22),$E22,0) -> 0 | N22: =IF(AND(N20>=$C22,N20<=$D22),$E22,0) -> 0 | O22: =IF(AND(O20>=$C22,O20<=$D22),$E22,0) -> 0 | ... S22: =IF(AND(S20>=$C22,S20<=$D22),$E22,0) -> 0
C23: 2 | D23: 2 | E23: 750 | H23: =IF(AND(H20>=$C23,H20<=$D23),$E23,0) -> 750 | I23: =IF(AND(I20>=$C23,I20<=$D23),$E23,0) -> 0 | J23: =IF(AND(J20>=$C23,J20<=$D23),$E23,0) -> 0 | K23: =IF(AND(K20>=$C23,K20<=$D23),$E23,0) -> 0 | L23: =IF(AND(L20>=$C23,L20<=$D23),$E23,0) -> 0 | M23: =IF(AND(M20>=$C23,M20<=$D23),$E23,0) -> 0 | N23: =IF(AND(N20>=$C23,N20<=$D23),$E23,0) -> 0 | O23: =IF(AND(O20>=$C23,O20<=$D23),$E23,0) -> 0 | ... S23: =IF(AND(S20>=$C23,S20<=$D23),$E23,0) -> 0
C24: 3 | D24: et plus | E24: 1250 | H24: =IF(AND(H20>=$C24,H20<=$D24),$E24,0) -> 0 | I24: =IF(AND(I20>=$C24,I20<=$D24),$E24,0) -> 1250 | J24: =IF(AND(J20>=$C24,J20<=$D24),$E24,0) -> 1250 | K24: =IF(AND(K20>=$C24,K20<=$D24),$E24,0) -> 1250 | L24: =IF(AND(L20>=$C24,L20<=$D24),$E24,0) -> 0 | M24: =IF(AND(M20>=$C24,M20<=$D24),$E24,0) -> 0 | N24: =IF(AND(N20>=$C24,N20<=$D24),$E24,0) -> 0 | O24: =IF(AND(O20>=$C24,O20<=$D24),$E24,0) -> 0 | ... S24: =IF(AND(S20>=$C24,S20<=$D24),$E24,0) -> 0
G25: Payable | H25: =SUM(H22:H24) -> 750 | I25: =SUM(I22:I24) -> 1250 | J25: =SUM(J22:J24) -> 1250 | K25: =SUM(K22:K24) -> 1250 | L25: =SUM(L22:L24) -> 0 | M25: =SUM(M22:M24) -> 0 | N25: =SUM(N22:N24) -> 0 | O25: =SUM(O22:O24) -> 0 | ... S25: =SUM(S22:S24) -> 0
B27: CSI: Moyenne Questions D2 / D3 / D4 / D5 | G27: % | H27: 0.6 | I27: 0 | J27: 0 | K27: 0 | L27: 0 | M27: 0 | N27: 0 | O27: 0 | P27: 0 | Q27: 0 | R27: 0 | S27: 0
C28: de | D28: à | E28: Boni
C29: 0 | D29: 0.7999 | E29: 0 | H29: =IF(AND(H27>=$C29,H27<=$D29),$E29,0) -> 0 | I29: =IF(AND(I27>=$C29,I27<=$D29),$E29,0) -> 0 | J29: =IF(AND(J27>=$C29,J27<=$D29),$E29,0) -> 0 | K29: =IF(AND(K27>=$C29,K27<=$D29),$E29,0) -> 0 | L29: =IF(AND(L27>=$C29,L27<=$D29),$E29,0) -> 0 | M29: =IF(AND(M27>=$C29,M27<=$D29),$E29,0) -> 0 | N29: =IF(AND(N27>=$C29,N27<=$D29),$E29,0) -> 0 | O29: =IF(AND(O27>=$C29,O27<=$D29),$E29,0) -> 0 | ... S29: =IF(AND(S27>=$C29,S27<=$D29),$E29,0) -> 0
C30: 0.8 | D30: 0.85 | E30: 750 | H30: =IF(AND(H27>=$C30,H27<=$D30),$E30,0) -> 0 | I30: =IF(AND(I27>=$C30,I27<=$D30),$E30,0) -> 0 | J30: =IF(AND(J27>=$C30,J27<=$D30),$E30,0) -> 0 | K30: =IF(AND(K27>=$C30,K27<=$D30),$E30,0) -> 0 | L30: =IF(AND(L27>=$C30,L27<=$D30),$E30,0) -> 0 | M30: =IF(AND(M27>=$C30,M27<=$D30),$E30,0) -> 0 | N30: =IF(AND(N27>=$C30,N27<=$D30),$E30,0) -> 0 | O30: =IF(AND(O27>=$C30,O27<=$D30),$E30,0) -> 0 | ... S30: =IF(AND(S27>=$C30,S27<=$D30),$E30,0) -> 0
C31: 0.8501 | D31: et plus | E31: 1000 | H31: =IF(AND(H27>=$C31,H27<=$D31),$E31,0) -> 0 | I31: =IF(AND(I27>=$C31,I27<=$D31),$E31,0) -> 0 | J31: =IF(AND(J27>=$C31,J27<=$D31),$E31,0) -> 0 | K31: =IF(AND(K27>=$C31,K27<=$D31),$E31,0) -> 0 | L31: =IF(AND(L27>=$C31,L27<=$D31),$E31,0) -> 0 | M31: =IF(AND(M27>=$C31,M27<=$D31),$E31,0) -> 0 | N31: =IF(AND(N27>=$C31,N27<=$D31),$E31,0) -> 0 | O31: =IF(AND(O27>=$C31,O27<=$D31),$E31,0) -> 0 | ... S31: =IF(AND(S27>=$C31,S27<=$D31),$E31,0) -> 0
G32: Payable | H32: =SUM(H29:H31) -> 0 | I32: =SUM(I29:I31) -> 0 | J32: =SUM(J29:J31) -> 0 | K32: =SUM(K29:K31) -> 0 | L32: =SUM(L29:L31) -> 0 | M32: =SUM(M29:M31) -> 0 | N32: =SUM(N29:N31) -> 0 | O32: =SUM(O29:O31) -> 0 | ... S32: =SUM(S29:S31) -> 0
G34: Total Mensuel | H34: =H10+H18+H25+H32 -> 4250 | I34: =I10+I18+I25 -> 1250 | J34: =J10+J18+J25 -> 4250 | K34: =K10+K18+K25 -> 4250 | L34: =L10+L18+L25 -> 3500 | M34: =M10+M18+M25 -> 3500 | N34: =N10+N18+N25 -> 3500 | O34: =O10+O18+O25 -> 3500 | P34: =P10+P18+P25 -> 3500 | ... S34: =S10+S18+S25 -> 3500
B37: Bonis Annuels
B38: Classement de la concession au Wolfsburg 2025 | G38: Réalisé
C39: de | D39: à | E39: Boni
C40: 1 | D40: 10 | E40: 5000 | S40: =IF(AND(S$38>=$C40,S$38<=$D40),$E40,0) -> 0
C41: 11 | D41: 15 | E41: 2500 | S41: =IF(AND(S$38>=$C41,S$38<=$D41),$E41,0) -> 0
C42: 16 | D42: 28 | E42: 500 | S42: =IF(AND(S$38>=$C42,S$38<=$D42),$E42,0) -> 0
G43: Payable | S43: =SUM(S40:S42) -> 0
G45: Total Payable | S45: =+S35+S43 -> 0

Sheet Tommy Martel Diotte 2024
B1: Tommy Martel Diotte - Directrice Opérations Fixes
B3: Bonis Mensuels | H3: 45688 | I3: 45716 | J3: 45747 | K3: 45777 | L3: 45808 | M3: 45838 | N3: 45869 | O3: 45900 | P3: 45930 | Q3: 45961 | R3: 45991 | S3: 46022
B4: Atteinte du Profit Net Départements Service, Pièces & Carrosserie | G4: Réalisé | H4: 30183 | I4: 54294 | J4: 106190 | K4: 105484 | L4: 0 | M4: 0 | N4: 0 | O4: 0 | P4: 0 | Q4: 0 | R4: 0 | S4: 0
B5: vs le Budget 2024 | G5: Cible | H5: 23140 | I5: 14921 | J5: 33534 | K5: 134821 | L5: 0 | M5: 0 | N5: 0 | O5: 0 | P5: 0 | Q5: 0 | R5: 0 | S5: 0
C6: de | D6: à | E6: Boni | G6: % | H6: =IFERROR(ROUND(H4/H5,3)," - - -") -> 1.304 | I6: =IFERROR(ROUND(I4/I5,3)," - - -") -> 3.639 | J6: =IFERROR(ROUND(J4/J5,3)," - - -") -> 3.167 | K6: 0.8 | L6: =IFERROR(ROUND(L4/L5,3)," - - -") -> - - - | M6: =IFERROR(ROUND(M4/M5,3)," - - -") -> - - - | N6: =IFERROR(ROUND(N4/N5,3)," - - -") -> - - - | O6: =IFERROR(ROUND(O4/O5,3)," - - -") -> - - - | P6: =IFERROR(ROUND(P4/P5,3)," - - -") -> - - - | Q6: =IFERROR(ROUND(Q4/Q5,3)," - - -") -> - - - | R6: =IFERROR(ROUND(R4/R5,3)," - - -") -> - - - | S6: =IFERROR(ROUND(S4/S5,3)," - - -") -> - - -
C7: 0.8 | D7: 0.9999 | E7: 1720 | H7: =IF(AND(H$6>=$C7,H$6<=$D7),$E7,0) -> 0 | I7: =IF(AND(I$6>=$C7,I$6<=$D7),$E7,0) -> 0 | J7: =IF(AND(J$6>=$C7,J$6<=$D7),$E7,0) -> 0 | K7: =IF(AND(K$6>=$C7,K$6<=$D7),$E7,0) -> 1720 | L7: =IF(AND(L$6>=$C7,L$6<=$D7),$E7,0) -> 0 | M7: =IF(AND(M$6>=$C7,M$6<=$D7),$E7,0) -> 0 | N7: =IF(AND(N$6>=$C7,N$6<=$D7),$E7,0) -> 0 | O7: =IF(AND(O$6>=$C7,O$6<=$D7),$E7,0) -> 0 | ... S7: =IF(AND(S$6>=$C7,S$6<=$D7),$E7,0) -> 0
C8: 1 | D8: 1.1999 | E8: 2150 | H8: =IF(AND(H$6>=$C8,H$6<=$D8),$E8,0) -> 0 | I8: =IF(AND(I$6>=$C8,I$6<=$D8),$E8,0) -> 0 | J8: =IF(AND(J$6>=$C8,J$6<=$D8),$E8,0) -> 0 | K8: =IF(AND(K$6>=$C8,K$6<=$D8),$E8,0) -> 0 | L8: =IF(AND(L$6>=$C8,L$6<=$D8),$E8,0) -> 0 | M8: =IF(AND(M$6>=$C8,M$6<=$D8),$E8,0) -> 0 | N8: =IF(AND(N$6>=$C8,N$6<=$D8),$E8,0) -> 0 | O8: =IF(AND(O$6>=$C8,O$6<=$D8),$E8,0) -> 0 | ... S8: =IF(AND(S$6>=$C8,S$6<=$D8),$E8,0) -> 0
C9: 1.2 | D9: et plus | E9: 2580 | H9: =IF(AND(H$6>=$C9,H$6<=$D9),$E9,0) -> 2580 | I9: =IF(AND(I$6>=$C9,I$6<=$D9),$E9,0) -> 2580 | J9: =IF(AND(J$6>=$C9,J$6<=$D9),$E9,0) -> 2580 | K9: =IF(AND(K$6>=$C9,K$6<=$D9),$E9,0) -> 0 | L9: =IF(AND(L$6>=$C9,L$6<=$D9),$E9,0) -> 2580 | M9: =IF(AND(M$6>=$C9,M$6<=$D9),$E9,0) -> 2580 | N9: =IF(AND(N$6>=$C9,N$6<=$D9),$E9,0) -> 2580 | O9: =IF(AND(O$6>=$C9,O$6<=$D9),$E9,0) -> 2580 | ... S9: =IF(AND(S$6>=$C9,S$6<=$D9),$E9,0) -> 2580
G10: Payable | H10: =SUM(H7:H9) -> 2580 | I10: =SUM(I7:I9) -> 2580 | J10: =SUM(J7:J9) -> 2580 | K10: =SUM(K7:K9) -> 1720 | L10: =SUM(L7:L9) -> 2580 | M10: =SUM(M7:M9) -> 2580 | N10: =SUM(N7:N9) -> 2580 | O10: =SUM(O7:O9) -> 2580 | ... S10: =SUM(S7:S9) -> 2580
B12: Atteinte du Profit Brut M/O SVC Client, Garantie & Interne | G12: Réalisé | H12: 184054 | I12: 178542 | J12: 219030 | K12: 273402 | L12: 0 | M12: 0 | N12: 0 | O12: 0 | P12: 0 | Q12: 0 | R12: 0 | S12: 0
B13: vs le Budget 2024 | G13: Cible | H13: 159257 | I13: 146481 | J13: 176957 | K13: 281294 | L13: 0 | M13: 0 | N13: 0 | O13: 0 | P13: 0 | Q13: 0 | R13: 0 | S13: 0
C14: de | D14: à | E14: Boni | G14: % | H14: =IFERROR(ROUND(H12/H13,3)," - - -") -> 1.156 | I14: =IFERROR(ROUND(I12/I13,3)," - - -") -> 1.219 | J14: =IFERROR(ROUND(J12/J13,3)," - - -") -> 1.238 | K14: =IFERROR(ROUND(K12/K13,3)," - - -") -> 0.972 | L14: =IFERROR(ROUND(L12/L13,3)," - - -") -> - - - | M14: =IFERROR(ROUND(M12/M13,3)," - - -") -> - - - | N14: =IFERROR(ROUND(N12/N13,3)," - - -") -> - - - | O14: =IFERROR(ROUND(O12/O13,3)," - - -") -> - - - | ... S14: =IFERROR(ROUND(S12/S13,3)," - - -") -> - - -
C15: 0.8 | D15: 0.9999 | E15: 669 | H15: =IF(AND(H$14>=$C15,H$14<=$D15),$E15,0) -> 0 | I15: =IF(AND(I$14>=$C15,I$14<=$D15),$E15,0) -> 0 | J15: =IF(AND(J$14>=$C15,J$14<=$D15),$E15,0) -> 0 | K15: =IF(AND(K$14>=$C15,K$14<=$D15),$E15,0) -> 669 | L15: =IF(AND(L$14>=$C15,L$14<=$D15),$E15,0) -> 0 | M15: =IF(AND(M$14>=$C15,M$14<=$D15),$E15,0) -> 0 | N15: =IF(AND(N$14>=$C15,N$14<=$D15),$E15,0) -> 0 | O15: =IF(AND(O$14>=$C15,O$14<=$D15),$E15,0) -> 0 | ... S15: =IF(AND(S$14>=$C15,S$14<=$D15),$E15,0) -> 0
C16: 1 | D16: 1.1999 | E16: 836 | H16: =IF(AND(H$14>=$C16,H$14<=$D16),$E16,0) -> 836 | I16: =IF(AND(I$14>=$C16,I$14<=$D16),$E16,0) -> 0 | J16: =IF(AND(J$14>=$C16,J$14<=$D16),$E16,0) -> 0 | K16: =IF(AND(K$14>=$C16,K$14<=$D16),$E16,0) -> 0 | L16: =IF(AND(L$14>=$C16,L$14<=$D16),$E16,0) -> 0 | M16: =IF(AND(M$14>=$C16,M$14<=$D16),$E16,0) -> 0 | N16: =IF(AND(N$14>=$C16,N$14<=$D16),$E16,0) -> 0 | O16: =IF(AND(O$14>=$C16,O$14<=$D16),$E16,0) -> 0 | ... S16: =IF(AND(S$14>=$C16,S$14<=$D16),$E16,0) -> 0
C17: 1.2 | D17: et plus | E17: 1003 | H17: =IF(AND(H$14>=$C17,H$14<=$D17),$E17,0) -> 0 | I17: =IF(AND(I$14>=$C17,I$14<=$D17),$E17,0) -> 1003 | J17: =IF(AND(J$14>=$C17,J$14<=$D17),$E17,0) -> 1003 | K17: =IF(AND(K$14>=$C17,K$14<=$D17),$E17,0) -> 0 | L17: =IF(AND(L$14>=$C17,L$14<=$D17),$E17,0) -> 1003 | M17: =IF(AND(M$14>=$C17,M$14<=$D17),$E17,0) -> 1003 | N17: =IF(AND(N$14>=$C17,N$14<=$D17),$E17,0) -> 1003 | O17: =IF(AND(O$14>=$C17,O$14<=$D17),$E17,0) -> 1003 | ... S17: =IF(AND(S$14>=$C17,S$14<=$D17),$E17,0) -> 1003
G18: Payable | H18: =SUM(H15:H17) -> 836 | I18: =SUM(I15:I17) -> 1003 | J18: =SUM(J15:J17) -> 1003 | K18: =SUM(K15:K17) -> 669 | L18: =SUM(L15:L17) -> 1003 | M18: =SUM(M15:M17) -> 1003 | N18: =SUM(N15:N17) -> 1003 | O18: =SUM(O15:O17) -> 1003 | ... S18: =SUM(S15:S17) -> 1003
B20: Atteinte du Profit Brut Pièces & Accessoires | G20: Réalisé | H20: 112029 | I20: 104069 | J20: 122287 | K20: 109680 | L20: 0 | M20: 0 | N20: 0 | O20: 0 | P20: 0 | Q20: 0 | R20: 0 | S20: 0
B21: vs le Budget 2024 | G21: Cible | H21: 106569 | I21: 95970 | J21: 94972 | K21: 129543 | L21: 0 | M21: 0 | N21: 0 | O21: 0 | P21: 0 | Q21: 0 | R21: 0 | S21: 0
C22: de | D22: à | E22: Boni | G22: % | H22: =IFERROR(ROUND(H20/H21,3)," - - -") -> 1.051 | I22: =IFERROR(ROUND(I20/I21,3)," - - -") -> 1.084 | J22: =IFERROR(ROUND(J20/J21,3)," - - -") -> 1.288 | K22: =IFERROR(ROUND(K20/K21,3)," - - -") -> 0.847 | L22: =IFERROR(ROUND(L20/L21,3)," - - -") -> - - - | M22: =IFERROR(ROUND(M20/M21,3)," - - -") -> - - - | N22: =IFERROR(ROUND(N20/N21,3)," - - -") -> - - - | O22: =IFERROR(ROUND(O20/O21,3)," - - -") -> - - - | ... S22: =IFERROR(ROUND(S20/S21,3)," - - -") -> - - -
C23: 0.8 | D23: 0.9999 | E23: 669 | H23: =IF(AND(H$22>=$C23,H$22<=$D23),$E23,0) -> 0 | I23: =IF(AND(I$22>=$C23,I$22<=$D23),$E23,0) -> 0 | J23: =IF(AND(J$22>=$C23,J$22<=$D23),$E23,0) -> 0 | K23: =IF(AND(K$22>=$C23,K$22<=$D23),$E23,0) -> 669 | L23: =IF(AND(L$22>=$C23,L$22<=$D23),$E23,0) -> 0 | M23: =IF(AND(M$22>=$C23,M$22<=$D23),$E23,0) -> 0 | N23: =IF(AND(N$22>=$C23,N$22<=$D23),$E23,0) -> 0 | O23: =IF(AND(O$22>=$C23,O$22<=$D23),$E23,0) -> 0 | ... S23: =IF(AND(S$22>=$C23,S$22<=$D23),$E23,0) -> 0
C24: 1 | D24: 1.1999 | E24: 836 | H24: =IF(AND(H$22>=$C24,H$22<=$D24),$E24,0) -> 836 | I24: =IF(AND(I$22>=$C24,I$22<=$D24),$E24,0) -> 836 | J24: =IF(AND(J$22>=$C24,J$22<=$D24),$E24,0) -> 0 | K24: =IF(AND(K$22>=$C24,K$22<=$D24),$E24,0) -> 0 | L24: =IF(AND(L$22>=$C24,L$22<=$D24),$E24,0) -> 0 | M24: =IF(AND(M$22>=$C24,M$22<=$D24),$E24,0) -> 0 | N24: =IF(AND(N$22>=$C24,N$22<=$D24),$E24,0) -> 0 | O24: =IF(AND(O$22>=$C24,O$22<=$D24),$E24,0) -> 0 | ... S24: =IF(AND(S$22>=$C24,S$22<=$D24),$E24,0) -> 0
C25: 1.2 | D25: et plus | E25: 1003 | H25: =IF(AND(H$22>=$C25,H$22<=$D25),$E25,0) -> 0 | I25: =IF(AND(I$22>=$C25,I$22<=$D25),$E25,0) -> 0 | J25: =IF(AND(J$22>=$C25,J$22<=$D25),$E25,0) -> 1003 | K25: =IF(AND(K$22>=$C25,K$22<=$D25),$E25,0) -> 0 | L25: =IF(AND(L$22>=$C25,L$22<=$D25),$E25,0) -> 1003 | M25: =IF(AND(M$22>=$C25,M$22<=$D25),$E25,0) -> 1003 | N25: =IF(AND(N$22>=$C25,N$22<=$D25),$E25,0) -> 1003 | O25: =IF(AND(O$22>=$C25,O$22<=$D25),$E25,0) -> 1003 | ... S25: =IF(AND(S$22>=$C25,S$22<=$D25),$E25,0) -> 1003
G26: Payable | H26: =SUM(H23:H25) -> 836 | I26: =SUM(I23:I25) -> 836 | J26: =SUM(J23:J25) -> 1003 | K26: =SUM(K23:K25) -> 669 | L26: =SUM(L23:L25) -> 1003 | M26: =SUM(M23:M25) -> 1003 | N26: =SUM(N23:N25) -> 1003 | O26: =SUM(O23:O25) -> 1003 | ... S26: =SUM(S23:S25) -> 1003
G28: Excedant du 100% payé en fev et mars | K28: =((I30-3511)+(J30-3511))*-1 -> -1983
G29: Boni Discr. | M29: 1000
G30: Total mensuel | H30: =+H10+H18+H26 -> 4252 | I30: =+I10+I18+I26 -> 4419 | J30: =+J10+J18+J26 -> 4586 | K30: =+K10+K18+K26 -> 3058 | L30: =+L10+L18+L26 -> 4586 | M30: =+M10+M18+M26 -> 4586 | N30: =+N10+N18+N26 -> 4586 | O30: =+O10+O18+O26 -> 4586 | ... S30: =+S10+S18+S26 -> 4586
B31: Bonis Trimestriels
B32: Atteinte des Ventes de Pneus | G32: Réalisé | J32: 131840 | M32: 0 | P32: 0 | S32: 0
B33: vs le Budget 2024 | G33: Cible | J33: 132335 | M33: 0 | P33: 0 | S33: 0
C34: de | D34: à | E34: Boni | G34: % | J34: 1 | M34: =IFERROR(ROUND(M32/M33,3)," - - -") -> - - - | P34: =IFERROR(ROUND(P32/P33,3)," - - -") -> - - - | S34: =IFERROR(ROUND(S32/S33,3)," - - -") -> - - -
C35: 0.8 | D35: 0.9999 | E35: 1147 | J35: =IF(AND(J$34>=$C35,J$34<=$D35),$E35,0) -> 0 | M35: =IF(AND(M$34>=$C35,M$34<=$D35),$E35,0) -> 0 | P35: =IF(AND(P$34>=$C35,P$34<=$D35),$E35,0) -> 0 | S35: =IF(AND(S$34>=$C35,S$34<=$D35),$E35,0) -> 0
C36: 1 | D36: 1.1999 | E36: 1433 | J36: =IF(AND(J$34>=$C36,J$34<=$D36),$E36,0) -> 1433 | M36: =IF(AND(M$34>=$C36,M$34<=$D36),$E36,0) -> 0 | P36: =IF(AND(P$34>=$C36,P$34<=$D36),$E36,0) -> 0 | S36: =IF(AND(S$34>=$C36,S$34<=$D36),$E36,0) -> 0
C37: 1.2 | D37: et plus | E37: 1720 | J37: =IF(AND(J$34>=$C37,J$34<=$D37),$E37,0) -> 0 | M37: =IF(AND(M$34>=$C37,M$34<=$D37),$E37,0) -> 1720 | P37: =IF(AND(P$34>=$C37,P$34<=$D37),$E37,0) -> 1720 | S37: =IF(AND(S$34>=$C37,S$34<=$D37),$E37,0) -> 1720
G38: Payable | J38: =SUM(J35:J37) -> 1433 | M38: =SUM(M35:M37) -> 1720 | P38: =SUM(P35:P37) -> 1720 | S38: =SUM(S35:S37) -> 1720
B40: Atteinte de la Cible CSI | J40: 0.9 | M40: 0 | P40: 0 | S40: 0
C41: de | D41: à | E41: Boni
C42: 0.8 | D42: 0.8499 | E42: 1147 | J42: =IF(AND(J40>=$C42,J40<=$D42),$E42,0) -> 0 | M42: =IF(AND(M40>=$C42,M40<=$D42),$E42,0) -> 0 | P42: =IF(AND(P40>=$C42,P40<=$D42),$E42,0) -> 0 | S42: =IF(AND(S40>=$C42,S40<=$D42),$E42,0) -> 0
C43: 0.85 | D43: 0.8999 | E43: 1433 | J43: =IF(AND(J40>=$C43,J40<=$D43),$E43,0) -> 0 | M43: =IF(AND(M40>=$C43,M40<=$D43),$E43,0) -> 0 | P43: =IF(AND(P40>=$C43,P40<=$D43),$E43,0) -> 0 | S43: =IF(AND(S40>=$C43,S40<=$D43),$E43,0) -> 0
C44: 0.9 | D44: et plus | E44: 1720 | J44: =IF(AND(J40>=$C44,J40<=$D44),$E44,0) -> 1720 | M44: =IF(AND(M40>=$C44,M40<=$D44),$E44,0) -> 0 | P44: =IF(AND(P40>=$C44,P40<=$D44),$E44,0) -> 0 | S44: =IF(AND(S40>=$C44,S40<=$D44),$E44,0) -> 0
G45: Payable | J45: =SUM(J42:J44) -> 1720 | M45: =SUM(M42:M44) -> 0 | P45: =SUM(P42:P44) -> 0 | S45: =SUM(S42:S44) -> 0
G47: Total trimestriel | J47: =+J38+J45 -> 3153 | M47: =+M38+M45 -> 1720 | P47: =+P38+P45 -> 1720 | S47: =+S38+S45 -> 1720
G49: Total Payable | J49: =+J30+J47 -> 7739 | M49: =+M30+M47 -> 6306 | P49: =+P30+P47 -> 6306 | S49: =+S30+S47 -> 6306

Sheet Rémi Dubreuil 2025
B1: Rémi Dubreuil - Commis senior
B3: Bonis Mensuels | H3: 45688 | I3: 45716 | J3: 45747 | K3: 45777 | L3: 45808 | M3: 45838 | N3: 45869 | O3: 45900 | P3: 45930 | Q3: 45961 | R3: 45991 | S3: 46022
B4: Atteinte du Profit Net Département Pièces | G4: Réalisé | H4: 30183 | I4: 22522 | J4: 46946 | K4: 29786 | L4: 0 | M4: 0 | N4: 0 | O4: 0 | P4: 0 | Q4: 0 | R4: 0 | S4: 0 | U4: L352
B5: vs le Budget 2025 | D5: Progressif/Incrémental | G5: Cible | H5: 23140 | I5: 24513 | J5: 22324 | K5: 52865 | L5: 0 | M5: 0 | N5: 0 | O5: 0 | P5: 0 | Q5: 0 | R5: 0 | S5: 0 | U5: F352
C6: de | D6: à | E6: Boni | G6: % | H6: =IFERROR(ROUND(H4/H5,3)," - - -") -> 1.304 | I6: =IFERROR(ROUND(I4/I5,3)," - - -") -> 0.919 | J6: =IFERROR(ROUND(J4/J5,3)," - - -") -> 2.103 | K6: =IFERROR(ROUND(K4/K5,3)," - - -") -> 0.563 | L6: =IFERROR(ROUND(L4/L5,3)," - - -") -> - - - | M6: =IFERROR(ROUND(M4/M5,3)," - - -") -> - - - | N6: =IFERROR(ROUND(N4/N5,3)," - - -") -> - - - | O6: =IFERROR(ROUND(O4/O5,3)," - - -") -> - - - | ... S6: =IFERROR(ROUND(S4/S5,3)," - - -") -> - - -
C7: 0.9 | D7: 0.9999 | E7: =ROUND(4000/12,2) -> 333.33 | H7: =IF(AND(H$6>=$C7,H$6<=$D7),($E7+((($E8-$E7)*(H$6-$C7))/($D7-$C7))),0) -> 0 | I7: =IF(AND(I$6>=$C7,I$6<=$D7),($E7+((($E8-$E7)*(I$6-$C7))/($D7-$C7))),0) -> 365.029 | J7: =IF(AND(J$6>=$C7,J$6<=$D7),($E7+((($E8-$E7)*(J$6-$C7))/($D7-$C7))),0) -> 0 | K7: =IF(AND(K$6>=$C7,K$6<=$D7),($E7+((($E8-$E7)*(K$6-$C7))/($D7-$C7))),0) -> 0 | L7: =IF(AND(L$6>=$C7,L$6<=$D7),($E7+((($E8-$E7)*(L$6-$C7))/($D7-$C7))),0) -> 0 | M7: =IF(AND(M$6>=$C7,M$6<=$D7),($E7+((($E8-$E7)*(M$6-$C7))/($D7-$C7))),0) -> 0 | N7: =IF(AND(N$6>=$C7,N$6<=$D7),($E7+((($E8-$E7)*(N$6-$C7))/($D7-$C7))),0) -> 0 | O7: =IF(AND(O$6>=$C7,O$6<=$D7),($E7+((($E8-$E7)*(O$6-$C7))/($D7-$C7))),0) -> 0 | ... S7: =IF(AND(S$6>=$C7,S$6<=$D7),($E7+((($E8-$E7)*(S$6-$C7))/($D7-$C7))),0) -> 0
C8: 1 | D8: 1.1999 | E8: =ROUND(6000/12,2) -> 500 | H8: =IF(AND(H$6>=$C8,H$6<=$D8),($E8+((($E9-$E8)*(H$6-$C8))/($D8-$C8))),0) -> 0 | I8: =IF(AND(I$6>=$C8,I$6<=$D8),($E8+((($E9-$E8)*(I$6-$C8))/($D8-$C8))),0) -> 0 | J8: =IF(AND(J$6>=$C8,J$6<=$D8),($E8+((($E9-$E8)*(J$6-$C8))/($D8-$C8))),0) -> 0 | K8: =IF(AND(K$6>=$C8,K$6<=$D8),($E8+((($E9-$E8)*(K$6-$C8))/($D8-$C8))),0) -> 0 | L8: =IF(AND(L$6>=$C8,L$6<=$D8),($E8+((($E9-$E8)*(L$6-$C8))/($D8-$C8))),0) -> 0 | M8: =IF(AND(M$6>=$C8,M$6<=$D8),($E8+((($E9-$E8)*(M$6-$C8))/($D8-$C8))),0) -> 0 | N8: =IF(AND(N$6>=$C8,N$6<=$D8),($E8+((($E9-$E8)*(N$6-$C8))/($D8-$C8))),0) -> 0 | O8: =IF(AND(O$6>=$C8,O$6<=$D8),($E8+((($E9-$E8)*(O$6-$C8))/($D8-$C8))),0) -> 0 | ... S8: =IF(AND(S$6>=$C8,S$6<=$D8),($E8+((($E9-$E8)*(S$6-$C8))/($D8-$C8))),0) -> 0
C9: 1.2 | D9: et plus | E9: =ROUND(8000/12,2) -> 666.67 | H9: =IF(AND(H$6>=$C9,H$6<=$D9),$E9,0) -> 666.67 | I9: =IF(AND(I$6>=$C9,I$6<=$D9),$E9,0) -> 0 | J9: =IF(AND(J$6>=$C9,J$6<=$D9),$E9,0) -> 666.67 | K9: =IF(AND(K$6>=$C9,K$6<=$D9),$E9,0) -> 0 | L9: =IF(AND(L$6>=$C9,L$6<=$D9),$E9,0) -> 666.67 | M9: =IF(AND(M$6>=$C9,M$6<=$D9),$E9,0) -> 666.67 | N9: =IF(AND(N$6>=$C9,N$6<=$D9),$E9,0) -> 666.67 | O9: =IF(AND(O$6>=$C9,O$6<=$D9),$E9,0) -> 666.67 | ... S9: =IF(AND(S$6>=$C9,S$6<=$D9),$E9,0) -> 666.67
G10: Payable | H10: =SUM(H7:H9) -> 666.67 | I10: =SUM(I7:I9) -> 365.029 | J10: =SUM(J7:J9) -> 666.67 | K10: =SUM(K7:K9) -> 0 | L10: =SUM(L7:L9) -> 666.67 | M10: =SUM(M7:M9) -> 666.67 | N10: =SUM(N7:N9) -> 666.67 | O10: =SUM(O7:O9) -> 666.67 | ... S10: =SUM(S7:S9) -> 666.67
B12: Boni mensuel sur les Ventes en gros | G12: Réalisé | H12: 197837 | I12: 198782 | J12: 219537 | K12: 185451 | L12: 0 | M12: 0 | N12: 0 | O12: 0 | P12: 0 | Q12: 0 | R12: 0 | S12: 0 | U12: J299
B13: vs le Budget 2025 | D13: Progressif/Incrémental | G13: Cible | H13: 181815 | I13: 149848 | J13: 133864 | K13: 181815 | L13: 0 | M13: 0 | N13: 0 | O13: 0 | P13: 0 | Q13: 0 | R13: 0 | S13: 0 | U13: D299
C14: de | D14: à | E14: Boni | G14: % | H14: =IFERROR(ROUND(H12/H13,3)," - - -") -> 1.088 | I14: =IFERROR(ROUND(I12/I13,3)," - - -") -> 1.327 | J14: =IFERROR(ROUND(J12/J13,3)," - - -") -> 1.64 | K14: =IFERROR(ROUND(K12/K13,3)," - - -") -> 1.02 | L14: =IFERROR(ROUND(L12/L13,3)," - - -") -> - - - | M14: =IFERROR(ROUND(M12/M13,3)," - - -") -> - - - | N14: =IFERROR(ROUND(N12/N13,3)," - - -") -> - - - | O14: =IFERROR(ROUND(O12/O13,3)," - - -") -> - - - | ... S14: =IFERROR(ROUND(S12/S13,3)," - - -") -> - - -
C15: 0.9 | D15: 0.9999 | E15: =ROUND(2500/12,2) -> 208.33 | H15: =IF(AND(H$14>=$C15,H$14<=$D15),($E15+((($E16-$E15)*(H$14-$C15))/($D15-$C15))),0) -> 0 | I15: =IF(AND(I$14>=$C15,I$14<=$D15),($E15+((($E16-$E15)*(I$14-$C15))/($D15-$C15))),0) -> 0 | J15: =IF(AND(J$14>=$C15,J$14<=$D15),($E15+((($E16-$E15)*(J$14-$C15))/($D15-$C15))),0) -> 0 | K15: =IF(AND(K$14>=$C15,K$14<=$D15),($E15+((($E16-$E15)*(K$14-$C15))/($D15-$C15))),0) -> 0 | L15: =IF(AND(L$14>=$C15,L$14<=$D15),($E15+((($E16-$E15)*(L$14-$C15))/($D15-$C15))),0) -> 0 | M15: =IF(AND(M$14>=$C15,M$14<=$D15),($E15+((($E16-$E15)*(M$14-$C15))/($D15-$C15))),0) -> 0 | N15: =IF(AND(N$14>=$C15,N$14<=$D15),($E15+((($E16-$E15)*(N$14-$C15))/($D15-$C15))),0) -> 0 | O15: =IF(AND(O$14>=$C15,O$14<=$D15),($E15+((($E16-$E15)*(O$14-$C15))/($D15-$C15))),0) -> 0 | ... S15: =IF(AND(S$14>=$C15,S$14<=$D15),($E15+((($E16-$E15)*(S$14-$C15))/($D15-$C15))),0) -> 0
C16: 1 | D16: 1.1999 | E16: =ROUND(3750/12,2) -> 312.5 | H16: =IF(AND(H$14>=$C16,H$14<=$D16),($E16+((($E17-$E16)*(H$14-$C16))/($D16-$C16))),0) -> 358.35773 | I16: =IF(AND(I$14>=$C16,I$14<=$D16),($E16+((($E17-$E16)*(I$14-$C16))/($D16-$C16))),0) -> 0 | J16: =IF(AND(J$14>=$C16,J$14<=$D16),($E16+((($E17-$E16)*(J$14-$C16))/($D16-$C16))),0) -> 0 | K16: =IF(AND(K$14>=$C16,K$14<=$D16),($E16+((($E17-$E16)*(K$14-$C16))/($D16-$C16))),0) -> 322.92221 | L16: =IF(AND(L$14>=$C16,L$14<=$D16),($E16+((($E17-$E16)*(L$14-$C16))/($D16-$C16))),0) -> 0 | M16: =IF(AND(M$14>=$C16,M$14<=$D16),($E16+((($E17-$E16)*(M$14-$C16))/($D16-$C16))),0) -> 0 | N16: =IF(AND(N$14>=$C16,N$14<=$D16),($E16+((($E17-$E16)*(N$14-$C16))/($D16-$C16))),0) -> 0 | O16: =IF(AND(O$14>=$C16,O$14<=$D16),($E16+((($E17-$E16)*(O$14-$C16))/($D16-$C16))),0) -> 0 | ... S16: =IF(AND(S$14>=$C16,S$14<=$D16),($E16+((($E17-$E16)*(S$14-$C16))/($D16-$C16))),0) -> 0
C17: 1.2 | D17: et plus | E17: =ROUND(5000/12,2) -> 416.67 | H17: =IF(AND(H$14>=$C17,H$14<=$D17),$E17,0) -> 0 | I17: =IF(AND(I$14>=$C17,I$14<=$D17),$E17,0) -> 416.67 | J17: =IF(AND(J$14>=$C17,J$14<=$D17),$E17,0) -> 416.67 | K17: =IF(AND(K$14>=$C17,K$14<=$D17),$E17,0) -> 0 | L17: =IF(AND(L$14>=$C17,L$14<=$D17),$E17,0) -> 416.67 | M17: =IF(AND(M$14>=$C17,M$14<=$D17),$E17,0) -> 416.67 | N17: =IF(AND(N$14>=$C17,N$14<=$D17),$E17,0) -> 416.67 | O17: =IF(AND(O$14>=$C17,O$14<=$D17),$E17,0) -> 416.67 | ... S17: =IF(AND(S$14>=$C17,S$14<=$D17),$E17,0) -> 416.67
G18: Payable | H18: =SUM(H15:H17) -> 358.35773 | I18: =SUM(I15:I17) -> 416.67 | J18: =SUM(J15:J17) -> 416.67 | K18: =SUM(K15:K17) -> 322.92221 | L18: =SUM(L15:L17) -> 416.67 | M18: =SUM(M15:M17) -> 416.67 | N18: =SUM(N15:N17) -> 416.67 | O18: =SUM(O15:O17) -> 416.67 | ... S18: =SUM(S15:S17) -> 416.67
B20: Boni mensuel sur les Ventes de pneus | G20: Réalisé | H20: 197837 | I20: 49339 | J20: 28787 | K20: 42082 | L20: 0 | M20: 0 | N20: 0 | O20: 0 | P20: 0 | Q20: 0 | R20: 0 | S20: 0 | U20: J306
B21: vs le Budget 2025 | D21: Progressif/Incrémental | G21: Cible | H21: 181815 | I21: 51783 | J21: 28769 | K21: 28769 | L21: 0 | M21: 0 | N21: 0 | O21: 0 | P21: 0 | Q21: 0 | R21: 0 | S21: 0 | U21: D306
C22: de | D22: à | E22: Boni | G22: % | H22: =IFERROR(ROUND(H20/H21,3)," - - -") -> 1.088 | I22: =IFERROR(ROUND(I20/I21,3)," - - -") -> 0.953 | J22: =IFERROR(ROUND(J20/J21,3)," - - -") -> 1.001 | K22: =IFERROR(ROUND(K20/K21,3)," - - -") -> 1.463 | L22: =IFERROR(ROUND(L20/L21,3)," - - -") -> - - - | M22: =IFERROR(ROUND(M20/M21,3)," - - -") -> - - - | N22: =IFERROR(ROUND(N20/N21,3)," - - -") -> - - - | O22: =IFERROR(ROUND(O20/O21,3)," - - -") -> - - - | ... S22: =IFERROR(ROUND(S20/S21,3)," - - -") -> - - -
C23: 0.9 | D23: 0.9999 | E23: =ROUND(2500/12,2) -> 208.33 | H23: =IF(AND(H$22>=$C23,H$22<=$D23),($E23+((($E24-$E23)*(H$22-$C23))/($D23-$C23))),0) -> 0 | I23: =IF(AND(I$22>=$C23,I$22<=$D23),($E23+((($E24-$E23)*(I$22-$C23))/($D23-$C23))),0) -> 263.59537 | J23: =IF(AND(J$22>=$C23,J$22<=$D23),($E23+((($E24-$E23)*(J$22-$C23))/($D23-$C23))),0) -> 0 | K23: =IF(AND(K$22>=$C23,K$22<=$D23),($E23+((($E24-$E23)*(K$22-$C23))/($D23-$C23))),0) -> 0 | L23: =IF(AND(L$22>=$C23,L$22<=$D23),($E23+((($E24-$E23)*(L$22-$C23))/($D23-$C23))),0) -> 0 | M23: =IF(AND(M$22>=$C23,M$22<=$D23),($E23+((($E24-$E23)*(M$22-$C23))/($D23-$C23))),0) -> 0 | N23: =IF(AND(N$22>=$C23,N$22<=$D23),($E23+((($E24-$E23)*(N$22-$C23))/($D23-$C23))),0) -> 0 | O23: =IF(AND(O$22>=$C23,O$22<=$D23),($E23+((($E24-$E23)*(O$22-$C23))/($D23-$C23))),0) -> 0 | ... S23: =IF(AND(S$22>=$C23,S$22<=$D23),($E23+((($E24-$E23)*(S$22-$C23))/($D23-$C23))),0) -> 0
C24: 1 | D24: 1.1999 | E24: =ROUND(3750/12,2) -> 312.5 | H24: =IF(AND(H$22>=$C24,H$22<=$D24),($E24+((($E25-$E24)*(H$22-$C24))/($D24-$C24))),0) -> 358.35773 | I24: =IF(AND(I$22>=$C24,I$22<=$D24),($E24+((($E25-$E24)*(I$22-$C24))/($D24-$C24))),0) -> 0 | J24: =IF(AND(J$22>=$C24,J$22<=$D24),($E24+((($E25-$E24)*(J$22-$C24))/($D24-$C24))),0) -> 313.02111 | K24: =IF(AND(K$22>=$C24,K$22<=$D24),($E24+((($E25-$E24)*(K$22-$C24))/($D24-$C24))),0) -> 0 | L24: =IF(AND(L$22>=$C24,L$22<=$D24),($E24+((($E25-$E24)*(L$22-$C24))/($D24-$C24))),0) -> 0 | M24: =IF(AND(M$22>=$C24,M$22<=$D24),($E24+((($E25-$E24)*(M$22-$C24))/($D24-$C24))),0) -> 0 | N24: =IF(AND(N$22>=$C24,N$22<=$D24),($E24+((($E25-$E24)*(N$22-$C24))/($D24-$C24))),0) -> 0 | O24: =IF(AND(O$22>=$C24,O$22<=$D24),($E24+((($E25-$E24)*(O$22-$C24))/($D24-$C24))),0) -> 0 | ... S24: =IF(AND(S$22>=$C24,S$22<=$D24),($E24+((($E25-$E24)*(S$22-$C24))/($D24-$C24))),0) -> 0
C25: 1.2 | D25: et plus | E25: =ROUND(5000/12,2) -> 416.67 | H25: =IF(AND(H$22>=$C25,H$22<=$D25),$E25,0) -> 0 | I25: =IF(AND(I$22>=$C25,I$22<=$D25),$E25,0) -> 0 | J25: =IF(AND(J$22>=$C25,J$22<=$D25),$E25,0) -> 0 | K25: =IF(AND(K$22>=$C25,K$22<=$D25),$E25,0) -> 416.67 | L25: =IF(AND(L$22>=$C25,L$22<=$D25),$E25,0) -> 416.67 | M25: =IF(AND(M$22>=$C25,M$22<=$D25),$E25,0) -> 416.67 | N25: =IF(AND(N$22>=$C25,N$22<=$D25),$E25,0) -> 416.67 | O25: =IF(AND(O$22>=$C25,O$22<=$D25),$E25,0) -> 416.67 | ... S25: =IF(AND(S$22>=$C25,S$22<=$D25),$E25,0) -> 416.67
G26: Payable | H26: =SUM(H23:H25) -> 358.35773 | I26: =SUM(I23:I25) -> 263.59537 | J26: =SUM(J23:J25) -> 313.02111 | K26: =SUM(K23:K25) -> 416.67 | L26: =SUM(L23:L25) -> 416.67 | M26: =SUM(M23:M25) -> 416.67 | N26: =SUM(N23:N25) -> 416.67 | O26: =SUM(O23:O25) -> 416.67 | ... S26: =SUM(S23:S25) -> 416.67
B28: Boni sur les Achats d'Accessoires par Véh. Neufs (VPN) | G28: Achats | H28: 9267 | I28: 16799.3 | J28: 13400.71 | K28: 27566.25 | L28: 0 | M28: 0 | N28: 0 | O28: 0 | P28: 0 | Q28: 0 | R28: 0 | S28: 0
B29: vs le Budget 2025 | G29: RDR | H29: ='Sebastien Fleury 2025'!H20 -> 58 | I29: ='Sebastien Fleury 2025'!I20 -> 38 | J29: ='Sebastien Fleury 2025'!J20 -> 53 | K29: ='Sebastien Fleury 2025'!K20 -> 56 | L29: ='Sebastien Fleury 2025'!L20 -> 0 | M29: ='Sebastien Fleury 2025'!M20 -> 0 | N29: ='Sebastien Fleury 2025'!N20 -> 0 | O29: ='Sebastien Fleury 2025'!O20 -> 0 | ... S29: ='Sebastien Fleury 2025'!S20 -> 0
C30: de | D30: à | E30: Boni | G30: $/Unité | H30: =IFERROR(ROUND(H28/H29,3)," - - -") -> 159.776 | I30: =IFERROR(ROUND(I28/I29,3)," - - -") -> 442.087 | J30: =IFERROR(ROUND(J28/J29,3)," - - -") -> 252.844 | K30: =IFERROR(ROUND(K28/K29,3)," - - -") -> 492.254 | L30: =IFERROR(ROUND(L28/L29,3)," - - -") -> - - - | M30: =IFERROR(ROUND(M28/M29,3)," - - -") -> - - - | N30: =IFERROR(ROUND(N28/N29,3)," - - -") -> - - - | O30: =IFERROR(ROUND(O28/O29,3)," - - -") -> - - - | ... S30: =IFERROR(ROUND(S28/S29,3)," - - -") -> - - -
C31: 300 | D31: 374.99 | E31: =ROUND(750/12,2) -> 62.5 | H31: =IF(AND(H$30>=$C31,H$30<=$D31),$E31,0) -> 0 | I31: =IF(AND(I$30>=$C31,I$30<=$D31),$E31,0) -> 0 | J31: =IF(AND(J$30>=$C31,J$30<=$D31),$E31,0) -> 0 | K31: =IF(AND(K$30>=$C31,K$30<=$D31),$E31,0) -> 0 | L31: =IF(AND(L$30>=$C31,L$30<=$D31),$E31,0) -> 0 | M31: =IF(AND(M$30>=$C31,M$30<=$D31),$E31,0) -> 0 | N31: =IF(AND(N$30>=$C31,N$30<=$D31),$E31,0) -> 0 | O31: =IF(AND(O$30>=$C31,O$30<=$D31),$E31,0) -> 0 | ... S31: =IF(AND(S$30>=$C31,S$30<=$D31),$E31,0) -> 0
C32: 375 | D32: 524.99 | E32: =ROUND(1500/12,2) -> 125 | H32: =IF(AND(H$30>=$C32,H$30<=$D32),$E32,0) -> 0 | I32: =IF(AND(I$30>=$C32,I$30<=$D32),$E32,0) -> 125 | J32: =IF(AND(J$30>=$C32,J$30<=$D32),$E32,0) -> 0 | K32: =IF(AND(K$30>=$C32,K$30<=$D32),$E32,0) -> 125 | L32: =IF(AND(L$30>=$C32,L$30<=$D32),$E32,0) -> 0 | M32: =IF(AND(M$30>=$C32,M$30<=$D32),$E32,0) -> 0 | N32: =IF(AND(N$30>=$C32,N$30<=$D32),$E32,0) -> 0 | O32: =IF(AND(O$30>=$C32,O$30<=$D32),$E32,0) -> 0 | ... S32: =IF(AND(S$30>=$C32,S$30<=$D32),$E32,0) -> 0
C33: 525 | D33: et plus | E33: =ROUND(2500/12,2) -> 208.33 | H33: =IF(AND(H$30>=$C33,H$30<=$D33),$E33,0) -> 0 | I33: =IF(AND(I$30>=$C33,I$30<=$D33),$E33,0) -> 0 | J33: =IF(AND(J$30>=$C33,J$30<=$D33),$E33,0) -> 0 | K33: =IF(AND(K$30>=$C33,K$30<=$D33),$E33,0) -> 0 | L33: =IF(AND(L$30>=$C33,L$30<=$D33),$E33,0) -> 208.33 | M33: =IF(AND(M$30>=$C33,M$30<=$D33),$E33,0) -> 208.33 | N33: =IF(AND(N$30>=$C33,N$30<=$D33),$E33,0) -> 208.33 | O33: =IF(AND(O$30>=$C33,O$30<=$D33),$E33,0) -> 208.33 | ... S33: =IF(AND(S$30>=$C33,S$30<=$D33),$E33,0) -> 208.33
G34: Payable | H34: =SUM(H31:H33) -> 0 | I34: =SUM(I31:I33) -> 125 | J34: =SUM(J31:J33) -> 0 | K34: =SUM(K31:K33) -> 125 | L34: =SUM(L31:L33) -> 208.33 | M34: =SUM(M31:M33) -> 208.33 | N34: 125 | O34: =SUM(O31:O33) -> 208.33 | P34: =SUM(P31:P33) -> 208.33 | Q34: =SUM(Q31:Q33) -> 208.33 | R34: =SUM(R31:R33) -> 208.33 | S34: =SUM(S31:S33) -> 208.33
G36: Total Payable | H36: =+H34+H26+H18+H10 -> 1383.3855 | I36: =+I34+I26+I18+I10 -> 1170.2944 | J36: =+J34+J26+J18+J10 -> 1396.3611 | K36: =+K34+K26+K18+K10 -> 864.59221 | L36: =+L34+L26+L18+L10 -> 1708.34 | M36: =+M34+M26+M18+M10 -> 1708.34 | N36: =+N34+N26+N18+N10 -> 1625.01 | O36: =+O34+O26+O18+O10 -> 1708.34 | ... S36: =+S34+S26+S18+S10 -> 1708.34

Sheet Kaven Bonneau 2024
B3: Bonis Mensuels | H3: 45321 | I3: 45350 | J3: 45379 | K3: 45408 | L3: 45437 | M3: 45466 | N3: 45495 | O3: 45524 | P3: 45553 | Q3: 45582 | R3: 45611 | S3: 45640
B4: Profit brut départemental NEUF | G4: Réalisé | H4: 142187 | I4: 249483 | J4: 281559.36 | K4: 259605 | L4: 235625 | U4: L27 | W4: =SUM(H4:J4) -> 673229.36
B5: vs BUDGET 2024 | G5: Cible | H5: 144386 | I5: 144386 | J5: 202140.81 | K5: 288903 | L5: 331750 | U5: Unite objectif manuf*E27 | W5: =SUM(H5:J5) -> 490912.81
C6: de | D6: à | E6: Boni | G6: % | H6: =IFERROR(ROUND(H4/H5,3)," - - -") -> 0.985 | I6: =IFERROR(ROUND(I4/I5,3)," - - -") -> 1.728 | J6: =IFERROR(ROUND(J4/J5,3)," - - -") -> 1.393 | K6: =IFERROR(ROUND(K4/K5,3)," - - -") -> 0.899 | L6: =IFERROR(ROUND(L4/L5,3)," - - -") -> 0.71 | M6: =IFERROR(ROUND(M4/M5,3)," - - -") -> - - - | N6: =IFERROR(ROUND(N4/N5,3)," - - -") -> - - - | O6: =IFERROR(ROUND(O4/O5,3)," - - -") -> - - - | ... S6: =IFERROR(ROUND(S4/S5,3)," - - -") -> - - - | W6: =IFERROR(ROUND(W4/W5,3)," - - -") -> 1.371
C7: 0.9 | D7: 0.9999 | E7: 700 | H7: =IF(AND(H$6>=$C7,H$6<=$D7),$E7,0) -> 700 | I7: =IF(AND(I$6>=$C7,I$6<=$D7),$E7,0) -> 0 | J7: =IF(AND(J$6>=$C7,J$6<=$D7),$E7,0) -> 0 | K7: =IF(AND(K$6>=$C7,K$6<=$D7),$E7,0) -> 0 | L7: =IF(AND(L$6>=$C7,L$6<=$D7),$E7,0) -> 0 | M7: =IF(AND(M$6>=$C7,M$6<=$D7),$E7,0) -> 0 | N7: =IF(AND(N$6>=$C7,N$6<=$D7),$E7,0) -> 0 | O7: =IF(AND(O$6>=$C7,O$6<=$D7),$E7,0) -> 0 | ... S7: =IF(AND(S$6>=$C7,S$6<=$D7),$E7,0) -> 0
C8: 1 | D8: 1.0999 | E8: 1150 | H8: =IF(AND(H$6>=$C8,H$6<=$D8),$E8,0) -> 0 | I8: =IF(AND(I$6>=$C8,I$6<=$D8),$E8,0) -> 0 | J8: =IF(AND(J$6>=$C8,J$6<=$D8),$E8,0) -> 0 | K8: =IF(AND(K$6>=$C8,K$6<=$D8),$E8,0) -> 0 | L8: =IF(AND(L$6>=$C8,L$6<=$D8),$E8,0) -> 0 | M8: =IF(AND(M$6>=$C8,M$6<=$D8),$E8,0) -> 0 | N8: =IF(AND(N$6>=$C8,N$6<=$D8),$E8,0) -> 0 | O8: =IF(AND(O$6>=$C8,O$6<=$D8),$E8,0) -> 0 | ... S8: =IF(AND(S$6>=$C8,S$6<=$D8),$E8,0) -> 0
C9: 1.1 | D9: et plus | E9: 1500 | H9: =IF(AND(H$6>=$C9,H$6<=$D9),$E9,0) -> 0 | I9: =IF(AND(I$6>=$C9,I$6<=$D9),$E9,0) -> 1500 | J9: =IF(AND(J$6>=$C9,J$6<=$D9),$E9,0) -> 1500 | K9: =IF(AND(K$6>=$C9,K$6<=$D9),$E9,0) -> 0 | L9: =IF(AND(L$6>=$C9,L$6<=$D9),$E9,0) -> 0 | M9: =IF(AND(M$6>=$C9,M$6<=$D9),$E9,0) -> 1500 | N9: =IF(AND(N$6>=$C9,N$6<=$D9),$E9,0) -> 1500 | O9: 2000 | P9: =IF(AND(P$6>=$C9,P$6<=$D9),$E9,0) -> 1500 | Q9: =IF(AND(Q$6>=$C9,Q$6<=$D9),$E9,0) -> 1500 | R9: =IF(AND(R$6>=$C9,R$6<=$D9),$E9,0) -> 1500 | S9: =IF(AND(S$6>=$C9,S$6<=$D9),$E9,0) -> 1500 | W9: =E9*3 -> 4500 | X9: =SUM(H10:J10) -> 3700 | Y9: =W9-X9 -> 800
G10: Payable | H10: =SUM(H7:H9) -> 700 | I10: =SUM(I7:I9) -> 1500 | J10: =SUM(J7:J9) -> 1500 | K10: =SUM(K7:K9) -> 0 | L10: =SUM(L7:L9) -> 0 | M10: =SUM(M7:M9) -> 1500 | N10: =SUM(N7:N9) -> 1500 | O10: =SUM(O7:O9) -> 2000 | ... S10: =SUM(S7:S9) -> 1500
B12: Profit brut départemental USAGÉ | G12: Réalisé | H12: 18396 | I12: 12562 | J12: 77150.61 | K12: 62515 | L12: 49484 | W12: =SUM(H12:L12) -> 220107.61
B13: vs BUDGET 2024 | G13: Cible | H13: 107193 | I13: 110753 | J13: 166598.6 | K13: 186276 | L13: 189649 | U13: Unite objectif manuf | W13: =SUM(H13:J13) -> 384544.6
C14: de | D14: à | E14: Boni | G14: % | H14: =IFERROR(ROUND(H12/H13,3)," - - -") -> 0.172 | I14: =IFERROR(ROUND(I12/I13,3)," - - -") -> 0.113 | J14: =IFERROR(ROUND(J12/J13,3)," - - -") -> 0.463 | K14: =IFERROR(ROUND(K12/K13,3)," - - -") -> 0.336 | L14: =IFERROR(ROUND(L12/L13,3)," - - -") -> 0.261 | M14: =IFERROR(ROUND(M12/M13,3)," - - -") -> - - - | N14: =IFERROR(ROUND(N12/N13,3)," - - -") -> - - - | O14: =IFERROR(ROUND(O12/O13,3)," - - -") -> - - - | ... S14: =IFERROR(ROUND(S12/S13,3)," - - -") -> - - - | W14: =IFERROR(ROUND(W12/W13,3)," - - -") -> 0.572
C15: 0.9 | D15: 0.9999 | E15: 700 | H15: =IF(AND(H$14>=$C15,H$14<=$D15),$E15,0) -> 0 | I15: =IF(AND(I$14>=$C15,I$14<=$D15),$E15,0) -> 0 | J15: =E15*3 -> 2100 | K15: =IF(AND(K$14>=$C15,K$14<=$D15),$E15,0) -> 0 | L15: =IF(AND(L$14>=$C15,L$14<=$D15),$E15,0) -> 0 | M15: =IF(AND(M$14>=$C15,M$14<=$D15),$E15,0) -> 0 | N15: =IF(AND(N$14>=$C15,N$14<=$D15),$E15,0) -> 0 | O15: =IF(AND(O$14>=$C15,O$14<=$D15),$E15,0) -> 0 | P15: =IF(AND(P$14>=$C15,P$14<=$D15),$E15,0) -> 0 | Q15: =IF(AND(Q$14>=$C15,Q$14<=$D15),$E15,0) -> 0 | R15: =IF(AND(R$14>=$C15,R$14<=$D15),$E15,0) -> 0 | S15: =IF(AND(S$14>=$C15,S$14<=$D15),$E15,0) -> 0
C16: 1 | D16: 1.0999 | E16: 1150 | H16: =IF(AND(H$14>=$C16,H$14<=$D16),$E16,0) -> 0 | I16: =IF(AND(I$14>=$C16,I$14<=$D16),$E16,0) -> 0 | J16: =IF(AND(J$14>=$C16,J$14<=$D16),$E16,0) -> 0 | K16: =IF(AND(K$14>=$C16,K$14<=$D16),$E16,0) -> 0 | L16: =IF(AND(L$14>=$C16,L$14<=$D16),$E16,0) -> 0 | M16: =IF(AND(M$14>=$C16,M$14<=$D16),$E16,0) -> 0 | N16: =IF(AND(N$14>=$C16,N$14<=$D16),$E16,0) -> 0 | O16: =IF(AND(O$14>=$C16,O$14<=$D16),$E16,0) -> 0 | ... S16: =IF(AND(S$14>=$C16,S$14<=$D16),$E16,0) -> 0
C17: 1.1 | D17: et plus | E17: 1500 | H17: =IF(AND(H$14>=$C17,H$14<=$D17),$E17,0) -> 0 | I17: =IF(AND(I$14>=$C17,I$14<=$D17),$E17,0) -> 0 | J17: =IF(AND(J$14>=$C17,J$14<=$D17),$E17,0) -> 0 | K17: =IF(AND(K$14>=$C17,K$14<=$D17),$E17,0) -> 0 | L17: =IF(AND(L$14>=$C17,L$14<=$D17),$E17,0) -> 0 | M17: =IF(AND(M$14>=$C17,M$14<=$D17),$E17,0) -> 1500 | N17: =IF(AND(N$14>=$C17,N$14<=$D17),$E17,0) -> 1500 | O17: 2000 | P17: =IF(AND(P$14>=$C17,P$14<=$D17),$E17,0) -> 1500 | Q17: =IF(AND(Q$14>=$C17,Q$14<=$D17),$E17,0) -> 1500 | R17: =IF(AND(R$14>=$C17,R$14<=$D17),$E17,0) -> 1500 | S17: =IF(AND(S$14>=$C17,S$14<=$D17),$E17,0) -> 1500 | W17: 0 | X17: 0 | Y17: =W17-X17 -> 0
G18: Payable | H18: =SUM(H15:H17) -> 0 | I18: =SUM(I15:I17) -> 0 | J18: =SUM(J15:J17) -> 2100 | K18: =SUM(K15:K17) -> 0 | L18: =SUM(L15:L17) -> 0 | M18: =SUM(M15:M17) -> 1500 | N18: =SUM(N15:N17) -> 1500 | O18: =SUM(O15:O17) -> 2000 | ... S18: =SUM(S15:S17) -> 1500
B20: Profit NET cucmule des 2 departements des ventes | G20: Réalisé | H20: -6512 | I20: 113128 | J20: 153986.24 | K20: 152718 | L20: 82191 | U20: L107 | W20: =SUM(H20:J20) -> 260602.24
B21: vs BUDGET 2024 | G21: Cible | H21: 45676 | I21: 48398 | J21: 143960.45 | K21: 243151 | L21: 286383 | U21: F107 | W21: =SUM(H21:J21) -> 238034.45
C22: de | D22: à | E22: Boni | G22: % | H22: =IFERROR(ROUND(H20/H21,3)," - - -") -> -0.143 | I22: =IFERROR(ROUND(I20/I21,3)," - - -") -> 2.337 | J22: =IFERROR(ROUND(J20/J21,3)," - - -") -> 1.07 | K22: =IFERROR(ROUND(K20/K21,3)," - - -") -> 0.628 | L22: =IFERROR(ROUND(L20/L21,3)," - - -") -> 0.287 | M22: =IFERROR(ROUND(M20/M21,3)," - - -") -> - - - | N22: =IFERROR(ROUND(N20/N21,3)," - - -") -> - - - | O22: =IFERROR(ROUND(O20/O21,3)," - - -") -> - - - | ... S22: =IFERROR(ROUND(S20/S21,3)," - - -") -> - - - | W22: =IFERROR(ROUND(W20/W21,3)," - - -") -> 1.095
C23: 0.9 | D23: 0.9999 | E23: 700 | H23: =IF(AND(H$22>=$C23,H$22<=$D23),$E23,0) -> 0 | I23: =IF(AND(I$22>=$C23,I$22<=$D23),$E23,0) -> 0 | J23: =IF(AND(J$22>=$C23,J$22<=$D23),$E23,0) -> 0 | K23: =IF(AND(K$22>=$C23,K$14<=$D23),$E23,0) -> 0 | L23: =IF(AND(L$22>=$C23,L$14<=$D23),$E23,0) -> 0 | M23: =IF(AND(M$22>=$C23,M$22<=$D23),$E23,0) -> 0 | N23: =IF(AND(N$22>=$C23,N$22<=$D23),$E23,0) -> 0 | O23: =IF(AND(O$22>=$C23,O$22<=$D23),$E23,0) -> 0 | P23: =IF(AND(P$22>=$C23,P$22<=$D23),$E23,0) -> 0 | Q23: =IF(AND(Q$22>=$C23,Q$22<=$D23),$E23,0) -> 0 | R23: =IF(AND(R$22>=$C23,R$22<=$D23),$E23,0) -> 0 | S23: =IF(AND(S$22>=$C23,S$22<=$D23),$E23,0) -> 0
C24: 1 | D24: 1.0999 | E24: 1150 | H24: =IF(AND(H$22>=$C24,H$22<=$D24),$E24,0) -> 0 | I24: =IF(AND(I$22>=$C24,I$22<=$D24),$E24,0) -> 0 | J24: =IF(AND(J$22>=$C24,J$22<=$D24),$E24,0) -> 1150 | K24: =IF(AND(K$22>=$C24,K$14<=$D24),$E24,0) -> 0 | L24: =IF(AND(L$22>=$C24,L$14<=$D24),$E24,0) -> 0 | M24: =IF(AND(M$22>=$C24,M$22<=$D24),$E24,0) -> 0 | N24: =IF(AND(N$22>=$C24,N$22<=$D24),$E24,0) -> 0 | O24: =IF(AND(O$22>=$C24,O$22<=$D24),$E24,0) -> 0 | P24: =IF(AND(P$22>=$C24,P$22<=$D24),$E24,0) -> 0 | Q24: =IF(AND(Q$22>=$C24,Q$22<=$D24),$E24,0) -> 0 | R24: =IF(AND(R$22>=$C24,R$22<=$D24),$E24,0) -> 0 | S24: =IF(AND(S$22>=$C24,S$22<=$D24),$E24,0) -> 0
C25: 1.1 | D25: et plus | E25: 1500 | H25: =IF(AND(H$22>=$C25,H$22<=$D25),$E25,0) -> 0 | I25: =IF(AND(I$22>=$C25,I$22<=$D25),$E25,0) -> 1500 | J25: =IF(AND(J$22>=$C25,J$22<=$D25),$E25,0) -> 0 | K25: =IF(AND(K$22>=$C25,K$14<=$D25),$E25,0) -> 0 | L25: =IF(AND(L$22>=$C25,L$14<=$D25),$E25,0) -> 0 | M25: =IF(AND(M$22>=$C25,M$22<=$D25),$E25,0) -> 1500 | N25: =IF(AND(N$22>=$C25,N$22<=$D25),$E25,0) -> 1500 | O25: =IF(AND(O$22>=$C25,O$22<=$D25),$E25,0) -> 1500 | P25: =IF(AND(P$22>=$C25,P$22<=$D25),$E25,0) -> 1500 | Q25: =IF(AND(Q$22>=$C25,Q$22<=$D25),$E25,0) -> 1500 | R25: =IF(AND(R$22>=$C25,R$22<=$D25),$E25,0) -> 1500 | S25: =IF(AND(S$22>=$C25,S$22<=$D25),$E25,0) -> 1500 | W25: =E24*3 -> 3450 | X25: =SUM(H26:J26) -> 2650 | Y25: =W25-X25 -> 800
G26: Payable | H26: =SUM(H23:H25) -> 0 | I26: =SUM(I23:I25) -> 1500 | J26: =SUM(J23:J25) -> 1150 | K26: =SUM(K23:K25) -> 0 | L26: =SUM(L23:L25) -> 0 | M26: =SUM(M23:M25) -> 1500 | N26: =SUM(N23:N25) -> 1500 | O26: =SUM(O23:O25) -> 1500 | ... S26: =SUM(S23:S25) -> 1500
G29: Total Mensuel | H29: =+H10+H18+H26 -> 700 | I29: =+I10+I18+I26 -> 3000 | J29: =+J10+J18+J26 -> 4750 | K29: =+K10+K18+K26 -> 0 | L29: =+L10+L18+L26 -> 0 | M29: =+M10+M18+M26 -> 4500 | N29: =+N10+N18+N26 -> 4500 | O29: =+O10+O18+O26 -> 5500 | ... S29: =+S10+S18+S26 -> 4500
B30: Bonis Trimestriels
B31: Objectif de volume vehicules neufs selon objectif BPV du manufacturier | G31: Réalisé | J31: 193
G32: Cible | J32: 133
C33: de | D33: à | E33: Boni | J33: =IFERROR(ROUND(J31/J32,3)," - - -") -> 1.451 | M33: =IFERROR(ROUND(M31/M32,3)," - - -") -> - - - | P33: =IFERROR(ROUND(P31/P32,3)," - - -") -> - - - | S33: =IFERROR(ROUND(S31/S32,3)," - - -") -> - - -
C34: 0.9 | D34: 0.9999 | E34: 1500 | J34: =IF(AND(J$33>=$C34,J$33<=$D34),$E34,0) -> 0 | M34: =IF(AND(M$33>=$C34,M$33<=$D34),$E34,0) -> 0 | P34: =IF(AND(P$33>=$C34,P$33<=$D34),$E34,0) -> 0 | S34: =IF(AND(S$33>=$C34,S$33<=$D34),$E34,0) -> 0
C35: 1 | D35: 1.0999 | E35: 2500 | J35: =IF(AND(J$33>=$C35,J$33<=$D35),$E35,0) -> 0 | M35: =IF(AND(M$33>=$C35,M$33<=$D35),$E35,0) -> 0 | P35: =IF(AND(P$33>=$C35,P$33<=$D35),$E35,0) -> 0 | S35: =IF(AND(S$33>=$C35,S$33<=$D35),$E35,0) -> 0
C36: 1.1 | D36: et plus | E36: 3500 | J36: =IF(AND(J$33>=$C36,J$33<=$D36),$E36,0) -> 3500 | M36: =IF(AND(M$33>=$C36,M$33<=$D36),$E36,0) -> 3500 | P36: =IF(AND(P$33>=$C36,P$33<=$D36),$E36,0) -> 3500 | S36: =IF(AND(S$33>=$C36,S$33<=$D36),$E36,0) -> 3500
G37: Payable | J37: =SUM(J34:J36) -> 3500 | M37: =SUM(M34:M36) -> 3500 | P37: =SUM(P34:P36) -> 3500 | S37: =SUM(S34:S36) -> 3500
B39: Atteinte des Indicateurs Expérience + ( X de 5 ) | G39: Réalisé | J39: 2 | M39: 5 | P39: 5 | S39: 5
C40: de | D40: à | E40: Boni
C41: 3 | D41: =C41 -> 3 | E41: 700 | J41: =IF(AND(J$39>=$C41,J$39<=$D41),$E41,0) -> 0 | M41: =IF(AND(M$39>=$C41,M$39<=$D41),$E41,0) -> 0 | P41: =IF(AND(P$39>=$C41,P$39<=$D41),$E41,0) -> 0 | S41: =IF(AND(S$39>=$C41,S$39<=$D41),$E41,0) -> 0
C42: =C41+1 -> 4 | D42: =D41+1 -> 4 | E42: 2000 | J42: =IF(AND(J$39>=$C42,J$39<=$D42),$E42,0) -> 0 | M42: =IF(AND(M$39>=$C42,M$39<=$D42),$E42,0) -> 0 | P42: =IF(AND(P$39>=$C42,P$39<=$D42),$E42,0) -> 0 | S42: =IF(AND(S$39>=$C42,S$39<=$D42),$E42,0) -> 0
C43: =C42+1 -> 5 | D43: =D42+1 -> 5 | E43: 2500 | J43: =IF(AND(J$39>=$C43,J$39<=$D43),$E43,0) -> 0 | M43: =IF(AND(M$39>=$C43,M$39<=$D43),$E43,0) -> 2500 | P43: =IF(AND(P$39>=$C43,P$39<=$D43),$E43,0) -> 2500 | S43: =IF(AND(S$39>=$C43,S$39<=$D43),$E43,0) -> 2500
G44: Payable | J44: =SUM(J41:J43) -> 0 | M44: =SUM(M41:M43) -> 2500 | P44: =SUM(P41:P43) -> 2500 | S44: =SUM(S41:S43) -> 2500
G45: Total Trimestriel | J45: =+J37+J44 -> 3500 | M45: =+M37+M44 -> 6000 | P45: =+P37+P44 -> 6000 | S45: =+S37+S44 -> 6000
G47: Total Payable | J47: =J29+J45 -> 8250 | M47: =M29+M45 -> 10500 | P47: =P29+P45 -> 10500 | S47: =+S29+S45 -> 10500
I50: Neuf | J50: =#REF! -> #REF!
I51: Used | J51: =#REF! -> #REF!
I52: Bonis | J52: =-(SOMMAIRE!B13+SOMMAIRE!B14) -> -13000
I53: Réel | J53: =SUM(J50:J52) -> #REF!
I55: Neuf | J55: =#REF! -> #REF!
I56: Used | J56: =#REF! -> #REF!
I57: Budget | J57: =SUM(J55:J56) -> #REF!
I59: Variance | J59: =J53-+J57 -> #REF!
J60: =J53/J57 -> #REF!

Sheet Vincent Metayer 2023
B1: Vincent Metayer - Directeur Adjoint du Service
B3: Bonis Mensuels | M3: 45107 | N3: 45138 | O3: 45169 | P3: 45199 | Q3: 45230 | R3: 45260 | S3: 45291
B4: Atteinte de l'objectif de vente Sur la production de l'atelierCPO selon taux effectif Mensuel | D4: Progressif/Incrémental | M4: =43557.46/350.84 -> 124.15192 | N4: 0 | O4: 0 | P4: 0 | Q4: 0 | R4: 0 | S4: 0 | U4: Fait par service
C5: de | D5: à | F5: Boni | M5: B | N5: C | O5: C | P5: B
C6: 125 | D6: 134.99 | E6: A | F6: 625 | M6: =IF(M$5=$E$6,$F$6,0) -> 0 | N6: =IF(N$5=$E$6,$F$6,0) -> 0 | O6: =IF(O$5=$E$6,$F$6,0) -> 0 | P6: =IF(P$5=$E$6,$F$6,0) -> 0 | Q6: =IF(Q$5=$E$6,$F$6,0) -> 0 | R6: =IF(R$5=$E$6,$F$6,0) -> 0 | S6: =IF(S$5=$E$6,$F$6,0) -> 0
C7: 135 | D7: 149.99 | E7: B | F7: 833.33 | M7: =IF(M$5=$E$7,$F$7,0) -> 833.33 | N7: =IF(N$5=$E$7,$F$7,0) -> 0 | O7: =IF(O$5=$E$7,$F$7,0) -> 0 | P7: =IF(P$5=$E$7,$F$7,0) -> 833.33 | Q7: =IF(Q$5=$E$7,$F$7,0) -> 0 | R7: =IF(R$5=$E$7,$F$7,0) -> 0 | S7: =IF(S$5=$E$7,$F$7,0) -> 0
C8: $150 et plus | E8: C | F8: 1250 | M8: =IF(M$5=$E$8,$F$8,0) -> 0 | N8: =IF(N$5=$E$8,$F$8,0) -> 1250 | O8: =IF(O$5=$E$8,$F$8,0) -> 1250 | P8: =IF(P$5=$E$8,$F$8,0) -> 0 | Q8: =IF(Q$5=$E$8,$F$8,0) -> 0 | R8: =IF(R$5=$E$8,$F$8,0) -> 0 | S8: =IF(S$5=$E$8,$F$8,0) -> 0
M9: =SUM(M6:M8) -> 833.33 | N9: =SUM(N6:N8) -> 1250 | O9: =SUM(O6:O8) -> 1250 | P9: =SUM(P6:P8) -> 833.33 | Q9: =SUM(Q6:Q8) -> 0 | R9: =SUM(R6:R8) -> 0 | S9: =SUM(S6:S8) -> 0
B11: Atteinte de l'objectif de vente d'esthetique sur la production de l'atelier CPO selon taux effectuf Mensuel | D11: Progressif/Incrémental | M11: =54921.15/521.35 -> 105.34411 | N11: 0 | O11: 0 | P11: 0 | Q11: 0 | R11: 0 | S11: 0
C12: de | D12: à | F12: Boni | M12: C | O12: C | P12: C
C13: 45 | D13: 54.99 | E13: A | F13: 625 | M13: =IF(M$12=$E$13,$F$13,0) -> 0 | N13: =IF(N$12=$E$13,$F$13,0) -> 0 | O13: =IF(O$12=$E$13,$F$13,0) -> 0 | P13: =IF(P$12=$E$13,$F$13,0) -> 0 | Q13: =IF(Q$12=$E$13,$F$13,0) -> 0 | R13: =IF(R$12=$E$13,$F$13,0) -> 0 | S13: =IF(S$12=$E$13,$F$13,0) -> 0
C14: 55 | D14: 64.99 | E14: B | F14: 833.33 | M14: =IF(M$12=$E$14,$F$14,0) -> 0 | N14: =IF(N$12=$E$14,$F$14,0) -> 0 | O14: =IF(O$12=$E$14,$F$14,0) -> 0 | P14: =IF(P$12=$E$14,$F$14,0) -> 0 | Q14: =IF(Q$12=$E$14,$F$14,0) -> 0 | R14: =IF(R$12=$E$14,$F$14,0) -> 0 | S14: =IF(S$12=$E$14,$F$14,0) -> 0
C15: $65 et plus | E15: C | F15: 1250 | M15: =IF(M$12=$E$15,$F$15,0) -> 1250 | N15: =IF(N$12=$E$15,$F$15,0) -> 0 | O15: =IF(O$12=$E$15,$F$15,0) -> 1250 | P15: =IF(P$12=$E$15,$F$15,0) -> 1250 | Q15: =IF(Q$12=$E$15,$F$15,0) -> 0 | R15: =IF(R$12=$E$15,$F$15,0) -> 0 | S15: =IF(S$12=$E$15,$F$15,0) -> 0
M16: =SUM(M13:M15) -> 1250 | N16: =SUM(N13:N15) -> 0 | O16: =SUM(O13:O15) -> 1250 | P16: =SUM(P13:P15) -> 1250 | Q16: =SUM(Q13:Q15) -> 0 | R16: =SUM(R13:R15) -> 0 | S16: =SUM(S13:S15) -> 0
M18: =M16+M9 -> 2083.33 | N18: =N16+N9 -> 1250 | O18: =O16+O9 -> 2500 | P18: =P16+P9 -> 2083.33 | Q18: =Q16+Q9 -> 0 | R18: =R16+R9 -> 0 | S18: =S16+S9 -> 0

Sheet Claudia Pantalena
B1: Claudia Pantalena - Directrice Opérations Fixes
B3: Bonis Mensuels | H3: 44957 | I3: 44985 | J3: 45016 | K3: 45046 | L3: 45077 | M3: 45107 | N3: 45138 | O3: 45169 | P3: 45199 | Q3: 45230 | R3: 45260 | S3: 45291
B4: Atteinte du Profit Net Départements Service, Pièces & Carrosserie | G4: Réalisé | H4: 29700 | I4: 5296 | J4: 11620 | K4: 72343.4 | L4: 117853 | M4: 66509 | N4: 78300 | O4: 113715 | P4: 1 | Q4: 1 | R4: 1 | S4: 1 | U4: L352 + L288 + L232
B5: vs le Budget 2023 | G5: Cible | H5: 20024 | I5: 17472 | J5: 47377 | K5: 133970.33 | L5: 91698 | M5: 85910 | N5: 59628 | O5: 62559 | P5: 100 | Q5: 100 | R5: 100 | S5: 100 | U5: F352 + F288 + F232
C6: de | D6: à | E6: Boni | G6: % | H6: 1.483 | I6: 0.303 | J6: 0.245 | K6: 0.54 | L6: 1.285 | M6: 0.774 | N6: 1.313 | O6: =IFERROR(ROUND(O4/O5,3)," - - -") -> 1.818 | P6: =IFERROR(ROUND(P4/P5,3)," - - -") -> 0.01 | Q6: =IFERROR(ROUND(Q4/Q5,3)," - - -") -> 0.01 | R6: =IFERROR(ROUND(R4/R5,3)," - - -") -> 0.01 | S6: =IFERROR(ROUND(S4/S5,3)," - - -") -> 0.01
C7: 0.8 | D7: 0.9999 | E7: 1556 | H7: 0 | I7: 0 | J7: 0 | K7: 0 | L7: 0 | M7: 0 | N7: 0 | O7: =IF(AND(O$6>=$C7,O$6<=$D7),$E7,0) -> 0 | P7: =IF(AND(P$6>=$C7,P$6<=$D7),$E7,0) -> 0 | Q7: =IF(AND(Q$6>=$C7,Q$6<=$D7),$E7,0) -> 0 | R7: =IF(AND(R$6>=$C7,R$6<=$D7),$E7,0) -> 0 | S7: =IF(AND(S$6>=$C7,S$6<=$D7),$E7,0) -> 0
C8: 1 | D8: 1.1999 | E8: 1944 | H8: 0 | I8: 0 | J8: 0 | K8: 0 | L8: 0 | M8: 0 | N8: 0 | O8: =IF(AND(O$6>=$C8,O$6<=$D8),$E8,0) -> 0 | P8: =IF(AND(P$6>=$C8,P$6<=$D8),$E8,0) -> 0 | Q8: =IF(AND(Q$6>=$C8,Q$6<=$D8),$E8,0) -> 0 | R8: =IF(AND(R$6>=$C8,R$6<=$D8),$E8,0) -> 0 | S8: =IF(AND(S$6>=$C8,S$6<=$D8),$E8,0) -> 0
C9: 1.2 | D9: 1.4999 | E9: 2333 | H9: 2333 | I9: 0 | J9: 0 | K9: 0 | L9: 2333 | M9: 0 | N9: 2333 | O9: =IF(AND(O$6>=$C9,O$6<=$D9),$E9,0) -> 0 | P9: =IF(AND(P$6>=$C9,P$6<=$D9),$E9,0) -> 0 | Q9: =IF(AND(Q$6>=$C9,Q$6<=$D9),$E9,0) -> 0 | R9: =IF(AND(R$6>=$C9,R$6<=$D9),$E9,0) -> 0 | S9: =IF(AND(S$6>=$C9,S$6<=$D9),$E9,0) -> 0
C10: 1.5 | D10: 1.9999 | E10: 2917 | H10: 0 | I10: 0 | J10: 0 | K10: 0 | L10: 0 | M10: 0 | N10: 0 | O10: =IF(AND(O$6>=$C10,O$6<=$D10),$E10,0) -> 2917 | P10: =IF(AND(P$6>=$C10,P$6<=$D10),$E10,0) -> 0 | Q10: =IF(AND(Q$6>=$C10,Q$6<=$D10),$E10,0) -> 0 | R10: =IF(AND(R$6>=$C10,R$6<=$D10),$E10,0) -> 0 | S10: =IF(AND(S$6>=$C10,S$6<=$D10),$E10,0) -> 0
C11: 2 | D11: et plus | E11: 3889 | H11: 0 | I11: 0 | J11: 0 | K11: 0 | L11: 0 | M11: 0 | N11: 0 | O11: =IF(AND(O$6>=$C11,O$6<=$D11),$E11,0) -> 0 | P11: =IF(AND(P$6>=$C11,P$6<=$D11),$E11,0) -> 0 | Q11: =IF(AND(Q$6>=$C11,Q$6<=$D11),$E11,0) -> 0 | R11: =IF(AND(R$6>=$C11,R$6<=$D11),$E11,0) -> 0 | S11: =IF(AND(S$6>=$C11,S$6<=$D11),$E11,0) -> 0
G12: Payable | H12: 2333 | I12: 0 | J12: 0 | K12: 0 | L12: 2333 | M12: 0 | N12: 2333 | O12: =SUM(O7:O11) -> 2917 | P12: =SUM(P7:P11) -> 0 | Q12: =SUM(Q7:Q11) -> 0 | R12: =SUM(R7:R11) -> 0 | S12: =SUM(S7:S11) -> 0
B14: Atteinte du Profit Brut M/O SVC Client, Garantie & Interne | G14: Réalisé | H14: 114469 | I14: 107834 | J14: 133607 | K14: 199787.24 | L14: 237616 | M14: 197610 | N14: 173315 | O14: 176180 | P14: 1 | Q14: 1 | R14: 1 | S14: 1 | U14: L184
B15: vs le Budget 2023 | G15: Cible | H15: 113091 | I15: 119978 | J15: 148420 | K15: 236607.95 | L15: 204165 | M15: 166054 | N15: 146718 | O15: 149686 | P15: 100 | Q15: 100 | R15: 100 | S15: 100 | U15: F184
C16: de | D16: à | E16: Boni | G16: % | H16: 1.012 | I16: 0.899 | J16: 0.9 | K16: 0.844 | L16: 1.164 | M16: 1.19 | N16: 1.181 | O16: =IFERROR(ROUND(O14/O15,3)," - - -") -> 1.177 | P16: =IFERROR(ROUND(P14/P15,3)," - - -") -> 0.01 | Q16: =IFERROR(ROUND(Q14/Q15,3)," - - -") -> 0.01 | R16: =IFERROR(ROUND(R14/R15,3)," - - -") -> 0.01 | S16: =IFERROR(ROUND(S14/S15,3)," - - -") -> 0.01
C17: 0.8 | D17: 0.9999 | E17: 544 | H17: 0 | I17: 544 | J17: 544 | K17: 544 | L17: 0 | M17: 0 | N17: 0 | O17: =IF(AND(O$16>=$C17,O$16<=$D17),$E17,0) -> 0 | P17: =IF(AND(P$16>=$C17,P$16<=$D17),$E17,0) -> 0 | Q17: =IF(AND(Q$16>=$C17,Q$16<=$D17),$E17,0) -> 0 | R17: =IF(AND(R$16>=$C17,R$16<=$D17),$E17,0) -> 0 | S17: =IF(AND(S$16>=$C17,S$16<=$D17),$E17,0) -> 0
C18: 1 | D18: 1.1999 | E18: 681 | H18: 681 | I18: 0 | J18: 0 | K18: 0 | L18: 681 | M18: 681 | N18: 681 | O18: =IF(AND(O$16>=$C18,O$16<=$D18),$E18,0) -> 681 | P18: =IF(AND(P$16>=$C18,P$16<=$D18),$E18,0) -> 0 | Q18: =IF(AND(Q$16>=$C18,Q$16<=$D18),$E18,0) -> 0 | R18: =IF(AND(R$16>=$C18,R$16<=$D18),$E18,0) -> 0 | S18: =IF(AND(S$16>=$C18,S$16<=$D18),$E18,0) -> 0
C19: 1.2 | D19: 1.4999 | E19: 817 | H19: 0 | I19: 0 | J19: 0 | K19: 0 | L19: 0 | M19: 0 | N19: 0 | O19: =IF(AND(O$16>=$C19,O$16<=$D19),$E19,0) -> 0 | P19: =IF(AND(P$16>=$C19,P$16<=$D19),$E19,0) -> 0 | Q19: =IF(AND(Q$16>=$C19,Q$16<=$D19),$E19,0) -> 0 | R19: =IF(AND(R$16>=$C19,R$16<=$D19),$E19,0) -> 0 | S19: =IF(AND(S$16>=$C19,S$16<=$D19),$E19,0) -> 0
C20: 1.5 | D20: 1.9999 | E20: 1021 | H20: 0 | I20: 0 | J20: 0 | K20: 0 | L20: 0 | M20: 0 | N20: 0 | O20: =IF(AND(O$16>=$C20,O$16<=$D20),$E20,0) -> 0 | P20: =IF(AND(P$16>=$C20,P$16<=$D20),$E20,0) -> 0 | Q20: =IF(AND(Q$16>=$C20,Q$16<=$D20),$E20,0) -> 0 | R20: =IF(AND(R$16>=$C20,R$16<=$D20),$E20,0) -> 0 | S20: =IF(AND(S$16>=$C20,S$16<=$D20),$E20,0) -> 0
C21: 2 | D21: et plus | E21: 1361 | H21: 0 | I21: 0 | J21: 0 | K21: 0 | L21: 0 | M21: 0 | N21: 0 | O21: =IF(AND(O$16>=$C21,O$16<=$D21),$E21,0) -> 0 | P21: =IF(AND(P$16>=$C21,P$16<=$D21),$E21,0) -> 0 | Q21: =IF(AND(Q$16>=$C21,Q$16<=$D21),$E21,0) -> 0 | R21: =IF(AND(R$16>=$C21,R$16<=$D21),$E21,0) -> 0 | S21: =IF(AND(S$16>=$C21,S$16<=$D21),$E21,0) -> 0
G22: Payable | H22: 681 | I22: 544 | J22: 544 | K22: 544 | L22: 681 | M22: 681 | N22: 681 | O22: =SUM(O17:O21) -> 681 | P22: =SUM(P17:P21) -> 0 | Q22: =SUM(Q17:Q21) -> 0 | R22: =SUM(R17:R21) -> 0 | S22: =SUM(S17:S21) -> 0
B24: Atteinte du Profit Brut Pièces & Accessoires | G24: Réalisé | H24: 107122 | I24: 102438 | J24: 108788 | K24: 106002.2 | L24: 120886 | M24: 104268 | N24: 118020 | O24: 121137 | P24: 1 | Q24: 1 | R24: 1 | S24: 1 | U24: L313
B25: vs le Budget 2023 | G25: Cible | H25: 99957 | I25: 93753 | J25: 100193 | K25: 120639.64 | L25: 115941 | M25: 123119 | N25: 114270 | O25: 116103 | P25: 100 | Q25: 100 | R25: 100 | S25: 100 | U25: F313
C26: de | D26: à | E26: Boni | G26: % | H26: 1.072 | I26: 1.093 | J26: 1.086 | K26: 0.879 | L26: 1.043 | M26: 0.847 | N26: 1.033 | O26: =IFERROR(ROUND(O24/O25,3)," - - -") -> 1.043 | P26: =IFERROR(ROUND(P24/P25,3)," - - -") -> 0.01 | Q26: =IFERROR(ROUND(Q24/Q25,3)," - - -") -> 0.01 | R26: =IFERROR(ROUND(R24/R25,3)," - - -") -> 0.01 | S26: =IFERROR(ROUND(S24/S25,3)," - - -") -> 0.01
C27: 0.8 | D27: 0.9999 | E27: 544 | H27: 0 | I27: 0 | J27: 0 | K27: 544 | L27: 0 | M27: 544 | N27: 0 | O27: =IF(AND(O$26>=$C27,O$26<=$D27),$E27,0) -> 0 | P27: =IF(AND(P$26>=$C27,P$26<=$D27),$E27,0) -> 0 | Q27: =IF(AND(Q$26>=$C27,Q$26<=$D27),$E27,0) -> 0 | R27: =IF(AND(R$26>=$C27,R$26<=$D27),$E27,0) -> 0 | S27: =IF(AND(S$26>=$C27,S$26<=$D27),$E27,0) -> 0
C28: 1 | D28: 1.1999 | E28: 681 | H28: 681 | I28: 681 | J28: 681 | K28: 0 | L28: 681 | M28: 0 | N28: 681 | O28: =IF(AND(O$26>=$C28,O$26<=$D28),$E28,0) -> 681 | P28: =IF(AND(P$26>=$C28,P$26<=$D28),$E28,0) -> 0 | Q28: =IF(AND(Q$26>=$C28,Q$26<=$D28),$E28,0) -> 0 | R28: =IF(AND(R$26>=$C28,R$26<=$D28),$E28,0) -> 0 | S28: =IF(AND(S$26>=$C28,S$26<=$D28),$E28,0) -> 0
C29: 1.2 | D29: 1.4999 | E29: 817 | H29: 0 | I29: 0 | J29: 0 | K29: 0 | L29: 0 | M29: 0 | N29: 0 | O29: =IF(AND(O$26>=$C29,O$26<=$D29),$E29,0) -> 0 | P29: =IF(AND(P$26>=$C29,P$26<=$D29),$E29,0) -> 0 | Q29: =IF(AND(Q$26>=$C29,Q$26<=$D29),$E29,0) -> 0 | R29: =IF(AND(R$26>=$C29,R$26<=$D29),$E29,0) -> 0 | S29: =IF(AND(S$26>=$C29,S$26<=$D29),$E29,0) -> 0
C30: 1.5 | D30: 1.9999 | E30: 1021 | H30: 0 | I30: 0 | J30: 0 | K30: 0 | L30: 0 | M30: 0 | N30: 0 | O30: =IF(AND(O$26>=$C30,O$26<=$D30),$E30,0) -> 0 | P30: =IF(AND(P$26>=$C30,P$26<=$D30),$E30,0) -> 0 | Q30: =IF(AND(Q$26>=$C30,Q$26<=$D30),$E30,0) -> 0 | R30: =IF(AND(R$26>=$C30,R$26<=$D30),$E30,0) -> 0 | S30: =IF(AND(S$26>=$C30,S$26<=$D30),$E30,0) -> 0
C31: 2 | D31: et plus | E31: 1361 | H31: 0 | I31: 0 | J31: 0 | K31: 0 | L31: 0 | M31: 0 | N31: 0 | O31: =IF(AND(O$26>=$C31,O$26<=$D31),$E31,0) -> 0 | P31: =IF(AND(P$26>=$C31,P$26<=$D31),$E31,0) -> 0 | Q31: =IF(AND(Q$26>=$C31,Q$26<=$D31),$E31,0) -> 0 | R31: =IF(AND(R$26>=$C31,R$26<=$D31),$E31,0) -> 0 | S31: =IF(AND(S$26>=$C31,S$26<=$D31),$E31,0) -> 0
G32: Payable | H32: 681 | I32: 681 | J32: 681 | K32: 544 | L32: 681 | M32: 544 | N32: 681 | O32: =SUM(O27:O31) -> 681 | P32: =SUM(P27:P31) -> 0 | Q32: =SUM(Q27:Q31) -> 0 | R32: =SUM(R27:R31) -> 0 | S32: =SUM(S27:S31) -> 0
G33: Total mensuel | H33: 3695 | I33: 1225 | J33: 1225 | K33: 1088 | L33: 3695 | M33: 1225 | N33: 3695 | O33: =+O12+O22+O32 -> 4279 | P33: =+P12+P22+P32 -> 0 | Q33: =+Q12+Q22+Q32 -> 0 | R33: =+R12+R22+R32 -> 0 | S33: =+S12+S22+S32 -> 0
B34: Bonis Trimestriels
B35: Atteinte des Ventes de Pneus | G35: Réalisé | J35: 114254 | M35: =199826-114254 -> 85572 | P35: 1 | S35: 1
B36: vs le Budget 2023 | G36: Cible | J36: 100734 | M36: =194876-100734 -> 94142 | P36: 100 | S36: 100
C37: de | D37: à | E37: Boni | G37: % | J37: =IFERROR(ROUND(J35/J36,3)," - - -") -> 1.134 | M37: =IFERROR(ROUND(M35/M36,3)," - - -") -> 0.909 | P37: =IFERROR(ROUND(P35/P36,3)," - - -") -> 0.01 | S37: =IFERROR(ROUND(S35/S36,3)," - - -") -> 0.01
C38: 0.8 | D38: 0.9999 | E38: 700 | J38: =IF(AND(J$37>=$C38,J$37<=$D38),$E38,0) -> 0 | M38: =IF(AND(M$37>=$C38,M$37<=$D38),$E38,0) -> 700 | P38: =IF(AND(P$37>=$C38,P$37<=$D38),$E38,0) -> 0 | S38: =IF(AND(S$37>=$C38,S$37<=$D38),$E38,0) -> 0
C39: 1 | D39: 1.1999 | E39: 875 | J39: =IF(AND(J$37>=$C39,J$37<=$D39),$E39,0) -> 875 | M39: =IF(AND(M$37>=$C39,M$37<=$D39),$E39,0) -> 0 | P39: =IF(AND(P$37>=$C39,P$37<=$D39),$E39,0) -> 0 | S39: =IF(AND(S$37>=$C39,S$37<=$D39),$E39,0) -> 0
C40: 1.2 | D40: 1.4999 | E40: 1050 | J40: =IF(AND(J$37>=$C40,J$37<=$D40),$E40,0) -> 0 | M40: =IF(AND(M$37>=$C40,M$37<=$D40),$E40,0) -> 0 | P40: =IF(AND(P$37>=$C40,P$37<=$D40),$E40,0) -> 0 | S40: =IF(AND(S$37>=$C40,S$37<=$D40),$E40,0) -> 0
C41: 1.5 | D41: 1.9999 | E41: 1313 | J41: =IF(AND(J$37>=$C41,J$37<=$D41),$E41,0) -> 0 | M41: =IF(AND(M$37>=$C41,M$37<=$D41),$E41,0) -> 0 | P41: =IF(AND(P$37>=$C41,P$37<=$D41),$E41,0) -> 0 | S41: =IF(AND(S$37>=$C41,S$37<=$D41),$E41,0) -> 0
C42: 2 | D42: et plus | E42: 1750 | J42: =IF(AND(J$37>=$C42,J$37<=$D42),$E42,0) -> 0 | M42: =IF(AND(M$37>=$C42,M$37<=$D42),$E42,0) -> 0 | P42: =IF(AND(P$37>=$C42,P$37<=$D42),$E42,0) -> 0 | S42: =IF(AND(S$37>=$C42,S$37<=$D42),$E42,0) -> 0
G43: Payable | J43: =SUM(J38:J42) -> 875 | M43: =SUM(M38:M42) -> 700 | P43: =SUM(P38:P42) -> 0 | S43: =SUM(S38:S42) -> 0
B45: Atteinte de la Cible CSI | G45: Réalisé | J45: 4.71 | M45: 4.67 | P45: 0 | S45: 0
B46: en référence à VW Cdn : 4,70 | G46: Cible | J46: 4.75 | M46: 4.75 | P46: 4.75 | S46: 4.75
C47: de | D47: à | E47: Boni | G47: % | J47: =IFERROR(ROUND(J45/J46,3)," - - -") -> 0.992 | M47: =IFERROR(ROUND(M45/M46,3)," - - -") -> 0.983 | P47: =IFERROR(ROUND(P45/P46,3)," - - -") -> 0 | S47: =IFERROR(ROUND(S45/S46,3)," - - -") -> 0
C48: 4.6 | D48: 4.69 | E48: 700 | J48: =IF(AND(J$45>=$C48,J$45<=$D48),$E48,0) -> 0 | M48: =IF(AND(M$45>=$C48,M$45<=$D48),$E48,0) -> 700 | P48: =IF(AND(P$45>=$C48,P$45<=$D48),$E48,0) -> 0 | S48: =IF(AND(S$45>=$C48,S$45<=$D48),$E48,0) -> 0
C49: 4.7 | D49: 4.73 | E49: 875 | J49: =IF(AND(J$45>=$C49,J$45<=$D49),$E49,0) -> 875 | M49: =IF(AND(M$45>=$C49,M$45<=$D49),$E49,0) -> 0 | P49: =IF(AND(P$45>=$C49,P$45<=$D49),$E49,0) -> 0 | S49: =IF(AND(S$45>=$C49,S$45<=$D49),$E49,0) -> 0
C50: 4.74 | D50: et plus | E50: 1050 | J50: =IF(AND(J$45>=$C50,J$45<=$D50),$E50,0) -> 0 | M50: =IF(AND(M$45>=$C50,M$45<=$D50),$E50,0) -> 0 | P50: =IF(AND(P$45>=$C50,P$45<=$D50),$E50,0) -> 0 | S50: =IF(AND(S$45>=$C50,S$45<=$D50),$E50,0) -> 0
G51: Payable | J51: =SUM(J48:J50) -> 875 | M51: =SUM(M48:M50) -> 700 | P51: =SUM(P48:P50) -> 0 | S51: =SUM(S48:S50) -> 0
G52: Total trimestriel | J52: =+J43+J51 -> 1750 | M52: =+M43+M51 -> 1400 | P52: =+P43+P51 -> 0 | S52: =+S43+S51 -> 0
G54: Total Payable | J54: =+J33+J52 -> 2975 | M54: =+M33+M52 -> 2625 | P54: =+P33+P52 -> 0 | S54: =+S33+S52 -> 0

Sheet Kaven Bonneau 2023-01 à 03
B1: Kaven Bonneau - Directeur Adjoint Ventes Neuf
B3: Bonis Mensuels | H3: 44957 | I3: 44985 | J3: 45016 | K3: 45046 | L3: 45077 | M3: 45107 | N3: 45138 | O3: 45169 | P3: 45199 | Q3: 45230 | R3: 45260 | S3: 45291
B4: Profit brut départemental NEUF | G4: Réalisé | H4: 146334 | I4: 105116 | J4: 198174 | K4: 1 | L4: 1 | M4: 1 | N4: 1 | O4: 1 | P4: 1 | Q4: 1 | R4: 1 | S4: 1
B5: vs le Budget 2023 | G5: Cible | H5: 174234 | I5: 129282 | J5: 232822 | K5: 100 | L5: 100 | M5: 100 | N5: 100 | O5: 100 | P5: 100 | Q5: 100 | R5: 100 | S5: 100
C6: de | D6: à | E6: Boni | G6: % | H6: =IFERROR(ROUND(H4/H5,3)," - - -") -> 0.84 | I6: =IFERROR(ROUND(I4/I5,3)," - - -") -> 0.813 | J6: =IFERROR(ROUND(J4/J5,3)," - - -") -> 0.851 | K6: =IFERROR(ROUND(K4/K5,3)," - - -") -> 0.01 | L6: =IFERROR(ROUND(L4/L5,3)," - - -") -> 0.01 | M6: =IFERROR(ROUND(M4/M5,3)," - - -") -> 0.01 | N6: =IFERROR(ROUND(N4/N5,3)," - - -") -> 0.01 | O6: =IFERROR(ROUND(O4/O5,3)," - - -") -> 0.01 | ... S6: =IFERROR(ROUND(S4/S5,3)," - - -") -> 0.01
C7: 0.85 | D7: 0.9999 | E7: 1000 | H7: =IF(AND(H$6>=$C7,H$6<=$D7),$E7,0) -> 0 | I7: =IF(AND(I$6>=$C7,I$6<=$D7),$E7,0) -> 0 | J7: =IF(AND(J$6>=$C7,J$6<=$D7),$E7,0) -> 1000 | K7: =IF(AND(K$6>=$C7,K$6<=$D7),$E7,0) -> 0 | L7: =IF(AND(L$6>=$C7,L$6<=$D7),$E7,0) -> 0 | M7: =IF(AND(M$6>=$C7,M$6<=$D7),$E7,0) -> 0 | N7: =IF(AND(N$6>=$C7,N$6<=$D7),$E7,0) -> 0 | O7: =IF(AND(O$6>=$C7,O$6<=$D7),$E7,0) -> 0 | ... S7: =IF(AND(S$6>=$C7,S$6<=$D7),$E7,0) -> 0
C8: 1 | D8: 1.149 | E8: 1500 | H8: =IF(AND(H$6>=$C8,H$6<=$D8),$E8,0) -> 0 | I8: =IF(AND(I$6>=$C8,I$6<=$D8),$E8,0) -> 0 | J8: =IF(AND(J$6>=$C8,J$6<=$D8),$E8,0) -> 0 | K8: =IF(AND(K$6>=$C8,K$6<=$D8),$E8,0) -> 0 | L8: =IF(AND(L$6>=$C8,L$6<=$D8),$E8,0) -> 0 | M8: =IF(AND(M$6>=$C8,M$6<=$D8),$E8,0) -> 0 | N8: =IF(AND(N$6>=$C8,N$6<=$D8),$E8,0) -> 0 | O8: =IF(AND(O$6>=$C8,O$6<=$D8),$E8,0) -> 0 | ... S8: =IF(AND(S$6>=$C8,S$6<=$D8),$E8,0) -> 0
C9: 1.15 | D9: et plus | E9: 2000 | H9: =IF(AND(H$6>=$C9,H$6<=$D9),$E9,0) -> 0 | I9: =IF(AND(I$6>=$C9,I$6<=$D9),$E9,0) -> 0 | J9: =IF(AND(J$6>=$C9,J$6<=$D9),$E9,0) -> 0 | K9: =IF(AND(K$6>=$C9,K$6<=$D9),$E9,0) -> 0 | L9: =IF(AND(L$6>=$C9,L$6<=$D9),$E9,0) -> 0 | M9: =IF(AND(M$6>=$C9,M$6<=$D9),$E9,0) -> 0 | N9: =IF(AND(N$6>=$C9,N$6<=$D9),$E9,0) -> 0 | O9: =IF(AND(O$6>=$C9,O$6<=$D9),$E9,0) -> 0 | ... S9: =IF(AND(S$6>=$C9,S$6<=$D9),$E9,0) -> 0
G10: Payable | H10: =SUM(H7:H9) -> 0 | I10: =SUM(I7:I9) -> 0 | J10: =SUM(J7:J9) -> 1000 | K10: =SUM(K7:K9) -> 0 | L10: =SUM(L7:L9) -> 0 | M10: =SUM(M7:M9) -> 0 | N10: =SUM(N7:N9) -> 0 | O10: =SUM(O7:O9) -> 0 | ... S10: =SUM(S7:S9) -> 0
B12: Atteinte Volume Ventes Neufs | G12: Réalisé | H12: 46 | I12: 25 | J12: 46 | K12: 1 | L12: 1 | M12: 1 | N12: 1 | O12: 1 | P12: 1 | Q12: 1 | R12: 1 | S12: 1
B13: vs le Budget 2023 | G13: Cible | H13: 48 | I13: 35 | J13: 62 | K13: 100 | L13: 100 | M13: 100 | N13: 100 | O13: 100 | P13: 100 | Q13: 100 | R13: 100 | S13: 100
C14: de | D14: à | E14: Boni | G14: % | H14: =IFERROR(ROUND(H12/H13,3)," - - -") -> 0.958 | I14: =IFERROR(ROUND(I12/I13,3)," - - -") -> 0.714 | J14: =IFERROR(ROUND(J12/J13,3)," - - -") -> 0.742 | K14: =IFERROR(ROUND(K12/K13,3)," - - -") -> 0.01 | L14: =IFERROR(ROUND(L12/L13,3)," - - -") -> 0.01 | M14: =IFERROR(ROUND(M12/M13,3)," - - -") -> 0.01 | N14: =IFERROR(ROUND(N12/N13,3)," - - -") -> 0.01 | O14: =IFERROR(ROUND(O12/O13,3)," - - -") -> 0.01 | ... S14: =IFERROR(ROUND(S12/S13,3)," - - -") -> 0.01
C15: 0.75 | D15: 0.959 | E15: 750 | H15: =IF(AND(H$14>=$C15,H$14<=$D15),$E15,0) -> 750 | I15: =IF(AND(I$14>=$C15,I$14<=$D15),$E15,0) -> 0 | J15: =IF(AND(J$14>=$C15,J$14<=$D15),$E15,0) -> 0 | K15: =IF(AND(K$14>=$C15,K$14<=$D15),$E15,0) -> 0 | L15: =IF(AND(L$14>=$C15,L$14<=$D15),$E15,0) -> 0 | M15: =IF(AND(M$14>=$C15,M$14<=$D15),$E15,0) -> 0 | N15: =IF(AND(N$14>=$C15,N$14<=$D15),$E15,0) -> 0 | O15: =IF(AND(O$14>=$C15,O$14<=$D15),$E15,0) -> 0 | ... S15: =IF(AND(S$14>=$C15,S$14<=$D15),$E15,0) -> 0
C16: 0.96 | D16: 1.149 | E16: 1250 | H16: =IF(AND(H$14>=$C16,H$14<=$D16),$E16,0) -> 0 | I16: =IF(AND(I$14>=$C16,I$14<=$D16),$E16,0) -> 0 | J16: =IF(AND(J$14>=$C16,J$14<=$D16),$E16,0) -> 0 | K16: =IF(AND(K$14>=$C16,K$14<=$D16),$E16,0) -> 0 | L16: =IF(AND(L$14>=$C16,L$14<=$D16),$E16,0) -> 0 | M16: =IF(AND(M$14>=$C16,M$14<=$D16),$E16,0) -> 0 | N16: =IF(AND(N$14>=$C16,N$14<=$D16),$E16,0) -> 0 | O16: =IF(AND(O$14>=$C16,O$14<=$D16),$E16,0) -> 0 | ... S16: =IF(AND(S$14>=$C16,S$14<=$D16),$E16,0) -> 0
C17: 1.15 | D17: et plus | E17: 2000 | H17: =IF(AND(H$14>=$C17,H$14<=$D17),$E17,0) -> 0 | I17: =IF(AND(I$14>=$C17,I$14<=$D17),$E17,0) -> 0 | J17: =IF(AND(J$14>=$C17,J$14<=$D17),$E17,0) -> 0 | K17: =IF(AND(K$14>=$C17,K$14<=$D17),$E17,0) -> 0 | L17: =IF(AND(L$14>=$C17,L$14<=$D17),$E17,0) -> 0 | M17: =IF(AND(M$14>=$C17,M$14<=$D17),$E17,0) -> 0 | N17: =IF(AND(N$14>=$C17,N$14<=$D17),$E17,0) -> 0 | O17: =IF(AND(O$14>=$C17,O$14<=$D17),$E17,0) -> 0 | ... S17: =IF(AND(S$14>=$C17,S$14<=$D17),$E17,0) -> 0
G18: Payable | H18: =SUM(H15:H17) -> 750 | I18: =SUM(I15:I17) -> 0 | J18: =SUM(J15:J17) -> 0 | K18: =SUM(K15:K17) -> 0 | L18: =SUM(L15:L17) -> 0 | M18: =SUM(M15:M17) -> 0 | N18: =SUM(N15:N17) -> 0 | O18: =SUM(O15:O17) -> 0 | ... S18: =SUM(S15:S17) -> 0
B20: Atteinte des Indicateurs de Performance ( X de 3 ) | G20: Réalisé | H20: 2 | I20: 2 | J20: 2 | K20: 2 | L20: 0 | M20: 0 | N20: 0 | O20: 0 | P20: 0 | Q20: 0 | R20: 0 | S20: 0
B21: (Accessoires VW +375$/RDR / Renouv +54% / Fr. Admin +de 93%) | G21: Cible | H21: 3 | I21: 3 | J21: 3 | K21: 3 | L21: 3 | M21: 3 | N21: 3 | O21: 3 | P21: 3 | Q21: 3 | R21: 3 | S21: 3
C22: de | D22: à | E22: Boni | G22: % | H22: =IFERROR(ROUND(H20/H21,3)," - - -") -> 0.667 | I22: =IFERROR(ROUND(I20/I21,3)," - - -") -> 0.667 | J22: =IFERROR(ROUND(J20/J21,3)," - - -") -> 0.667 | K22: =IFERROR(ROUND(K20/K21,3)," - - -") -> 0.667 | L22: =IFERROR(ROUND(L20/L21,3)," - - -") -> 0 | M22: =IFERROR(ROUND(M20/M21,3)," - - -") -> 0 | N22: =IFERROR(ROUND(N20/N21,3)," - - -") -> 0 | O22: =IFERROR(ROUND(O20/O21,3)," - - -") -> 0 | ... S22: =IFERROR(ROUND(S20/S21,3)," - - -") -> 0
C23: 1 | D23: 1 | E23: 0 | H23: =IF(AND(H$20>=$C23,H$20<=$D23),$E23,0) -> 0 | I23: =IF(AND(I$20>=$C23,I$20<=$D23),$E23,0) -> 0 | J23: =IF(AND(J$20>=$C23,J$20<=$D23),$E23,0) -> 0 | K23: =IF(AND(K$20>=$C23,K$20<=$D23),$E23,0) -> 0 | L23: =IF(AND(L$20>=$C23,L$20<=$D23),$E23,0) -> 0 | M23: =IF(AND(M$20>=$C23,M$20<=$D23),$E23,0) -> 0 | N23: =IF(AND(N$20>=$C23,N$20<=$D23),$E23,0) -> 0 | O23: =IF(AND(O$20>=$C23,O$20<=$D23),$E23,0) -> 0 | ... S23: =IF(AND(S$20>=$C23,S$20<=$D23),$E23,0) -> 0
C24: 2 | D24: 2 | E24: 400 | H24: =IF(AND(H$20>=$C24,H$20<=$D24),$E24,0) -> 400 | I24: =IF(AND(I$20>=$C24,I$20<=$D24),$E24,0) -> 400 | J24: =IF(AND(J$20>=$C24,J$20<=$D24),$E24,0) -> 400 | K24: =IF(AND(K$20>=$C24,K$20<=$D24),$E24,0) -> 400 | L24: =IF(AND(L$20>=$C24,L$20<=$D24),$E24,0) -> 0 | M24: =IF(AND(M$20>=$C24,M$20<=$D24),$E24,0) -> 0 | N24: =IF(AND(N$20>=$C24,N$20<=$D24),$E24,0) -> 0 | O24: =IF(AND(O$20>=$C24,O$20<=$D24),$E24,0) -> 0 | ... S24: =IF(AND(S$20>=$C24,S$20<=$D24),$E24,0) -> 0
C25: 3 | D25: 3 | E25: 750 | H25: =IF(AND(H$20>=$C25,H$20<=$D25),$E25,0) -> 0 | I25: =IF(AND(I$20>=$C25,I$20<=$D25),$E25,0) -> 0 | J25: =IF(AND(J$20>=$C25,J$20<=$D25),$E25,0) -> 0 | K25: =IF(AND(K$20>=$C25,K$20<=$D25),$E25,0) -> 0 | L25: =IF(AND(L$20>=$C25,L$20<=$D25),$E25,0) -> 0 | M25: =IF(AND(M$20>=$C25,M$20<=$D25),$E25,0) -> 0 | N25: =IF(AND(N$20>=$C25,N$20<=$D25),$E25,0) -> 0 | O25: =IF(AND(O$20>=$C25,O$20<=$D25),$E25,0) -> 0 | ... S25: =IF(AND(S$20>=$C25,S$20<=$D25),$E25,0) -> 0
G26: Payable | H26: =SUM(H23:H25) -> 400 | I26: =SUM(I23:I25) -> 400 | J26: =SUM(J23:J25) -> 400 | K26: =SUM(K23:K25) -> 400 | L26: =SUM(L23:L25) -> 0 | M26: =SUM(M23:M25) -> 0 | N26: =SUM(N23:N25) -> 0 | O26: =SUM(O23:O25) -> 0 | ... S26: =SUM(S23:S25) -> 0
G28: Total Mensuel | H28: =+H10+H18+H26 -> 1150 | I28: =+I10+I18+I26 -> 400 | J28: =+J10+J18+J26 -> 1400 | K28: =+K10+K18+K26 -> 400 | L28: =+L10+L18+L26 -> 0 | M28: =+M10+M18+M26 -> 0 | N28: =+N10+N18+N26 -> 0 | O28: =+O10+O18+O26 -> 0 | ... S28: =+S10+S18+S26 -> 0
B29: Bonis Trimestriels
B30: Atteinte des Indicateurs Expérience + ( X de 3 ) | G30: Réalisé | J30: 2 | M30: 0 | P30: 0 | S30: 0
B31: (CSI +de 4,9 / CarNet +de 95% / SalesForce selon Manuf.) | G31: Cible | J31: 2 | M31: 2 | P31: 2 | S31: 2
C32: de | D32: à | E32: Boni | G32: % | J32: =IFERROR(ROUND(J30/J31,3)," - - -") -> 1 | M32: =IFERROR(ROUND(M30/M31,3)," - - -") -> 0 | P32: =IFERROR(ROUND(P30/P31,3)," - - -") -> 0 | S32: =IFERROR(ROUND(S30/S31,3)," - - -") -> 0
C33: 1 | D33: 1 | E33: 1000 | J33: =IF(AND(J$30>=$C33,J$30<=$D33),$E33,0) -> 0 | M33: =IF(AND(M$30>=$C33,M$30<=$D33),$E33,0) -> 0 | P33: =IF(AND(P$30>=$C33,P$30<=$D33),$E33,0) -> 0 | S33: =IF(AND(S$30>=$C33,S$30<=$D33),$E33,0) -> 0
C34: 2 | D34: 2 | E34: 1500 | J34: =IF(AND(J$30>=$C34,J$30<=$D34),$E34,0) -> 1500 | M34: =IF(AND(M$30>=$C34,M$30<=$D34),$E34,0) -> 0 | P34: =IF(AND(P$30>=$C34,P$30<=$D34),$E34,0) -> 0 | S34: =IF(AND(S$30>=$C34,S$30<=$D34),$E34,0) -> 0
C35: 3 | D35: 3 | E35: 2500 | J35: =IF(AND(J$30>=$C35,J$30<=$D35),$E35,0) -> 0 | M35: =IF(AND(M$30>=$C35,M$30<=$D35),$E35,0) -> 0 | P35: =IF(AND(P$30>=$C35,P$30<=$D35),$E35,0) -> 0 | S35: =IF(AND(S$30>=$C35,S$30<=$D35),$E35,0) -> 0
G36: Payable | J36: =SUM(J33:J35) -> 1500 | M36: =SUM(M33:M35) -> 0 | P36: =SUM(P33:P35) -> 0 | S36: =SUM(S33:S35) -> 0
G37: Total Trimestriel | J37: =+J36 -> 1500 | M37: =+M36 -> 0 | P37: =+P36 -> 0 | S37: =+S36 -> 0
G39: Total Payable | H39: =+H28+H37 -> 1150 | I39: =+I28+I37 -> 400 | J39: =+J28+J37 -> 2900 | K39: =+K28+K37 -> 400 | L39: =+L28+L37 -> 0 | M39: =+M28+M37 -> 0 | N39: =+N28+N37 -> 0 | O39: =+O28+O37 -> 0 | ... S39: =+S28+S37 -> 0

Sheet Karim Noori 2023-01 seulement
B1: Karim Noori
H2: 44834 | J2: 44865 | L2: 44895 | N2: 44926 | P2: 44957
H3: Neuf | I3: Usagé | J3: Neuf | K3: Usagé | L3: Neuf | M3: Usagé | N3: Neuf | O3: Usagé | P3: Neuf | Q3: Usagé
B4: Atteinte profit brut | G4: réalisé | H4: 191478 | I4: 141059 | J4: 205157 | K4: 132109 | L4: 165104 | M4: 77900 | N4: S/O | O4: 50241 | P4: S/O | Q4: 118587
B5: non incrémental | C5: 0.85 | D5: 1 | E5: 1.15 | G5: target | H5: 201643 | I5: 117301 | J5: 214604 | K5: 136221 | L5: 192745 | M5: 117301 | N5: S/O | O5: 102166 | P5: S/O | Q5: 141755
B6: Budget 2022 | C6: 500 | D6: 1500 | E6: 2000 | G6: % | H6: =(H4+I4)/(H5+I5) -> 1.0426188 | J6: =(J4+K4)/(J5+K5) -> 0.9613511 | L6: =(L4+M4)/(L5+M5) -> 0.78376757 | N6: =+O4/O5 -> 0.49175851 | P6: =+Q4/Q5 -> 0.83656308
B7: neuf et usagé 50/50 | C7: =C6/2 -> 250 | D7: =D6/2 -> 750 | E7: =E6/2 -> 1000 | G7: payout | H7: =+D7 -> 750 | I7: =+D7 -> 750 | J7: =+C7 -> 250 | K7: =+C7 -> 250 | L7: 0 | M7: 0 | N7: 0 | O7: 0 | P7: 0 | Q7: 0
I9: Usagé | K9: Usagé | M9: Usagé | O9: Usagé | Q9: Usagé
B10: Atteinte des volumes d'unités de vente Usagés à 120% du VPA VW Cdn | G10: réalisé | I10: 34 | K10: 26 | M10: 24 | O10: 25 | Q10: 27
B11: non incrémental | C11: 0.85 | D11: 1 | E11: 1.15 | G11: target X 120% | I11: =25*1.2 -> 30 | K11: =29*1.2 -> 34.8 | M11: =25*1.2 -> 30 | O11: =22*1.2 -> 26.4 | Q11: 33
B12: Budget 2022 | C12: 750 | D12: 1500 | E12: 2000 | G12: % | I12: =I10/I11 -> 1.1333333 | K12: =K10/K11 -> 0.74712644 | M12: =M10/M11 -> 0.8 | O12: =O10/O11 -> 0.9469697 | Q12: =Q10/Q11 -> 0.81818182
G13: payout | I13: =+D12 -> 1500 | K13: 0 | M13: 0 | O13: =+C12 -> 750 | Q13: 0
B15: CSI | C15: 4.7 à 4.84 | D15: 4.85 à 4.95 | E15: 4.96 et plus | H15: réalisé | I15: 5 | J15: réalisé | K15: 3.33 | L15: réalisé | M15: 4.67 | N15: réalisé | O15: 5 | P15: réalisé | Q15: 4.5
B16: dept véhicule usagé | C16: 100 | D16: 250 | E16: 500 | H16: payout | I16: =+E16 -> 500 | J16: payout | K16: 0 | L16: payout | M16: 0 | N16: payout | O16: =+E16 -> 500 | P16: payout | Q16: 0
B18: Indicateur de Performance | C18: 2/4 | D18: 3/4 | E18: 4/4 | H18: Réalisé | I18: Score | J18: Réalisé | K18: Score | L18: Réalisé | M18: Score | N18: Réalisé | O18: Score | P18: Réalisé | Q18: Score
C19: 100 | D19: 450 | E19: 750
B20: Cible 1 : Inventaires Usagés des 90 jours ou plus | D20: Moins de 20% | G20: 0.2 | H20: 0.19 | I20: =IF(H20<$G$20,1,0) -> 1 | J20: =17/90 -> 0.18888889 | K20: =IF(J20<$G$20,1,0) -> 1 | L20: 0.1134 | M20: =IF(L20<$G$20,1,0) -> 1 | N20: 0.115 | O20: =IF(N20<$G$20,1,0) -> 1 | P20: 0.1388 | Q20: =IF(P20<$G$20,1,0) -> 1
B21: Cible 2 : Marchandisage moyen dans le mois | D21: 95% et plus | G21: 0.95 | H21: N/A | I21: =IF(H21>=$G$21,1,0) -> 1 | J21: 0.955 | K21: =IF(J21>=$G$21,1,0) -> 1 | L21: 0.97 | M21: =IF(L21>=$G$21,1,0) -> 1 | N21: 0.9 | O21: =IF(N21>=$G$21,1,0) -> 0 | P21: 0.96 | Q21: =IF(P21>=$G$21,1,0) -> 1
B22: Cible 3 : Pénétration Protections Mécaniques | D22: 60% et plus | G22: 0.6 | H22: 0.47 | I22: =IF(H22>=$G$22,1,0) -> 0 | J22: =10/26 -> 0.38461538 | K22: =IF(J22>=$G$22,1,0) -> 0 | M22: =IF(L22>=$G$22,1,0) -> 0 | O22: =IF(N22>=$G$22,1,0) -> 0 | P22: 1 | Q22: =IF(P22>=$G$22,1,0) -> 1
B23: Cible 4 : Frais Administratif supérieur à | D23: 0.93 | G23: 0.93 | H23: 0.9791 | I23: =IF(H23>$G$23,1,0) -> 1 | J23: 1 | K23: =IF(J23>$G$23,1,0) -> 1 | L23: 1 | M23: =IF(L23>$G$23,1,0) -> 1 | N23: 1 | O23: =IF(N23>$G$23,1,0) -> 1 | P23: 1 | Q23: =IF(P23>$G$23,1,0) -> 1
I24: =SUM(I20:I23) -> 3 | K24: =SUM(K20:K23) -> 3 | M24: =SUM(M20:M23) -> 3 | O24: =SUM(O20:O23) -> 2 | Q24: =SUM(Q20:Q23) -> 4
G25: payout | I25: =+D19 -> 450 | K25: =+D19 -> 450 | M25: =+D19 -> 450 | O25: =+C19 -> 100 | Q25: =+E19 -> 750
G26: Déjà Payé | Q26: -500
G27: Solde | I27: =+H7+I7+I13+I16+I25 -> 3950 | K27: =+J7+K7+K13+K16+K25 -> 950 | M27: =+L7+M7+M13+M16+M25 -> 450 | O27: =+N7+O7+O13+O16+O25 -> 1350 | Q27: =+Q25+Q26 -> 250
H30: Neuf | I30: Usagé | J30: Neuf | K30: Usagé | L30: Neuf | M30: Usagé | N30: Neuf | O30: Usagé | P30: Neuf | Q30: Usagé
B31: * objectif 1 et 2 éligible a un rattrapage trimestriel | H31: =+H7 -> 750 | I31: =+I7+I13+I16+I25 -> 3200 | J31: =+J7 -> 250 | K31: =+K7+K13+K16+K25 -> 700 | L31: =+L7 -> 0 | M31: =+M7+M13+M16+M25 -> 450 | N31: =+N7 -> 0 | O31: =+O7+O13+O16+O25 -> 1350 | P31: =+P7 -> 0 | Q31: =+Q7+Q13+Q16+Q25 -> 750
I32: =+H31+I31 -> 3950 | K32: =+J31+K31 -> 950 | M32: =+L31+M31 -> 450 | O32: =+N31+O31 -> 1350 | Q32: =+P31+Q31 -> 750
M33: Boni Nov. Corrigé et payé avec décembre | O33: =+M32+O32 -> 1800

Sheet Simon Bénard
A1: ANNEXE AU PLAN DE RÉMUNÉRATION
A2: Conseiller à la carrosserie
A3: Simon Bénard
B8: Boni Mensuel
A13: Profit net dept vs budget | B13: 90%-94.9% | C13: 95%-104.9% | D13: 105% et 109.9% | E13: 110% et plus
B14: 300 | C14: 500 | D14: 750 | E14: 1000
B16: Oct. 2022 | C16: Nov. 2022 | D16: Déc. 2022 | E16: Janv 2023 | I16: `AOUT 22 | J16: `SEPT 22 | K16: `OCT 22 | L16: `NOV 22 | M16: `DEC 22
A17: Réel | B17: 11000 | C17: 6667 | D17: -662 | E17: 17241
A18: budget | B18: 8490 | C18: 8298 | D18: -123 | E18: 9572
A19: Atteinte | B19: 1.2956419 | C19: 0.80344661 | D19: -5.3821138 | E19: =E17/E18 -> 1.801191
A20: payé | B20: 1000 | C20: 0 | D20: 0 | E20: =+E14 -> 1000
E25: =E23+E20 -> 1000

Sheet Jean-Marc Monnier 2023
B1: Jean-Marc Monnier - Directeur Adjoint Ventes Usagé
B3: Bonis Mensuels | H3: 44957 | I3: 44985 | J3: 45016 | K3: 45046 | L3: 45077 | M3: 45107 | N3: 45138 | O3: 45169 | P3: 45199 | Q3: 45230 | R3: 45260 | S3: 45291
B4: Profit brut départemental USAGÉ | G4: Réalisé | H4: 118587 | I4: 88264 | J4: 132216 | K4: 120177.25 | L4: ='Kaven Bonneau 2024'!L20 -> 82191 | M4: 1 | N4: 1 | O4: 1 | P4: 1 | Q4: 1 | R4: 1 | S4: 1 | U4: L107
B5: vs le Budget 2023 | G5: Cible | H5: 141755 | I5: 141755 | J5: 163233 | K5: 223372 | L5: ='Kaven Bonneau 2024'!L21 -> 286383 | M5: 100 | N5: 100 | O5: 100 | P5: 100 | Q5: 100 | R5: 100 | S5: 100 | U5: F107
C6: de | D6: à | E6: Boni | G6: % | H6: =IFERROR(ROUND(H4/H5,3)," - - -") -> 0.837 | I6: =IFERROR(ROUND(I4/I5,3)," - - -") -> 0.623 | J6: =IFERROR(ROUND(J4/J5,3)," - - -") -> 0.81 | K6: =IFERROR(ROUND(K4/K5,3)," - - -") -> 0.538 | L6: =IFERROR(ROUND(L4/L5,3)," - - -") -> 0.287 | M6: =IFERROR(ROUND(M4/M5,3)," - - -") -> 0.01 | N6: =IFERROR(ROUND(N4/N5,3)," - - -") -> 0.01 | O6: =IFERROR(ROUND(O4/O5,3)," - - -") -> 0.01 | ... S6: =IFERROR(ROUND(S4/S5,3)," - - -") -> 0.01
C7: 0.85 | D7: 0.9999 | E7: 500 | H7: =IF(AND(H$6>=$C7,H$6<=$D7),$E7,0) -> 0 | I7: =IF(AND(I$6>=$C7,I$6<=$D7),$E7,0) -> 0 | J7: =IF(AND(J$6>=$C7,J$6<=$D7),$E7,0) -> 0 | K7: =IF(AND(K$6>=$C7,K$6<=$D7),$E7,0) -> 0 | L7: =IF(AND(L$6>=$C7,L$6<=$D7),$E7,0) -> 0 | M7: =IF(AND(M$6>=$C7,M$6<=$D7),$E7,0) -> 0 | N7: =IF(AND(N$6>=$C7,N$6<=$D7),$E7,0) -> 0 | O7: =IF(AND(O$6>=$C7,O$6<=$D7),$E7,0) -> 0 | ... S7: =IF(AND(S$6>=$C7,S$6<=$D7),$E7,0) -> 0
C8: 1 | D8: 1.149 | E8: 1500 | H8: =IF(AND(H$6>=$C8,H$6<=$D8),$E8,0) -> 0 | I8: =IF(AND(I$6>=$C8,I$6<=$D8),$E8,0) -> 0 | J8: =IF(AND(J$6>=$C8,J$6<=$D8),$E8,0) -> 0 | K8: =IF(AND(K$6>=$C8,K$6<=$D8),$E8,0) -> 0 | L8: =IF(AND(L$6>=$C8,L$6<=$D8),$E8,0) -> 0 | M8: =IF(AND(M$6>=$C8,M$6<=$D8),$E8,0) -> 0 | N8: =IF(AND(N$6>=$C8,N$6<=$D8),$E8,0) -> 0 | O8: =IF(AND(O$6>=$C8,O$6<=$D8),$E8,0) -> 0 | ... S8: =IF(AND(S$6>=$C8,S$6<=$D8),$E8,0) -> 0
C9: 1.15 | D9: et plus | E9: 2000 | H9: =IF(AND(H$6>=$C9,H$6<=$D9),$E9,0) -> 0 | I9: =IF(AND(I$6>=$C9,I$6<=$D9),$E9,0) -> 0 | J9: =IF(AND(J$6>=$C9,J$6<=$D9),$E9,0) -> 0 | K9: =IF(AND(K$6>=$C9,K$6<=$D9),$E9,0) -> 0 | L9: =IF(AND(L$6>=$C9,L$6<=$D9),$E9,0) -> 0 | M9: =IF(AND(M$6>=$C9,M$6<=$D9),$E9,0) -> 0 | N9: =IF(AND(N$6>=$C9,N$6<=$D9),$E9,0) -> 0 | O9: =IF(AND(O$6>=$C9,O$6<=$D9),$E9,0) -> 0 | ... S9: =IF(AND(S$6>=$C9,S$6<=$D9),$E9,0) -> 0
G10: Payable | H10: =SUM(H7:H9) -> 0 | I10: =SUM(I7:I9) -> 0 | J10: =SUM(J7:J9) -> 0 | K10: =SUM(K7:K9) -> 0 | L10: =SUM(L7:L9) -> 0 | M10: =SUM(M7:M9) -> 0 | N10: =SUM(N7:N9) -> 0 | O10: =SUM(O7:O9) -> 0 | ... S10: =SUM(S7:S9) -> 0
B12: Atteinte Volume Ventes Usagés - DÉTAILS (ligne 96) | G12: Réalisé | H12: 60 | I12: 26 | J12: 35 | K12: 20 | L12: 25 | M12: 1 | N12: 1 | O12: 1 | P12: 1 | Q12: 1 | R12: 1 | S12: 1 | U12: J96
B13: vs le Budget 2023 | G13: Cible | H13: 61 | I13: 33 | J13: 38 | K13: 52 | L13: 50 | M13: 100 | N13: 100 | O13: 100 | P13: 100 | Q13: 100 | R13: 100 | S13: 100 | U13: D96
C14: de | D14: à | E14: Boni | G14: % | H14: =IFERROR(ROUND(H12/H13,3)," - - -") -> 0.984 | I14: =IFERROR(ROUND(I12/I13,3)," - - -") -> 0.788 | J14: =IFERROR(ROUND(J12/J13,3)," - - -") -> 0.921 | K14: =IFERROR(ROUND(K12/K13,3)," - - -") -> 0.385 | L14: =IFERROR(ROUND(L12/L13,3)," - - -") -> 0.5 | M14: =IFERROR(ROUND(M12/M13,3)," - - -") -> 0.01 | N14: =IFERROR(ROUND(N12/N13,3)," - - -") -> 0.01 | O14: =IFERROR(ROUND(O12/O13,3)," - - -") -> 0.01 | ... S14: =IFERROR(ROUND(S12/S13,3)," - - -") -> 0.01
C15: 0.85 | D15: 0.9999 | E15: 750 | H15: =IF(AND(H$14>=$C15,H$14<=$D15),$E15,0) -> 750 | I15: =IF(AND(I$14>=$C15,I$14<=$D15),$E15,0) -> 0 | J15: =IF(AND(J$14>=$C15,J$14<=$D15),$E15,0) -> 750 | K15: =IF(AND(K$14>=$C15,K$14<=$D15),$E15,0) -> 0 | L15: =IF(AND(L$14>=$C15,L$14<=$D15),$E15,0) -> 0 | M15: =IF(AND(M$14>=$C15,M$14<=$D15),$E15,0) -> 0 | N15: =IF(AND(N$14>=$C15,N$14<=$D15),$E15,0) -> 0 | O15: =IF(AND(O$14>=$C15,O$14<=$D15),$E15,0) -> 0 | ... S15: =IF(AND(S$14>=$C15,S$14<=$D15),$E15,0) -> 0
C16: 1 | D16: 1.149 | E16: 1500 | H16: =IF(AND(H$14>=$C16,H$14<=$D16),$E16,0) -> 0 | I16: =IF(AND(I$14>=$C16,I$14<=$D16),$E16,0) -> 0 | J16: =IF(AND(J$14>=$C16,J$14<=$D16),$E16,0) -> 0 | K16: =IF(AND(K$14>=$C16,K$14<=$D16),$E16,0) -> 0 | L16: =IF(AND(L$14>=$C16,L$14<=$D16),$E16,0) -> 0 | M16: =IF(AND(M$14>=$C16,M$14<=$D16),$E16,0) -> 0 | N16: =IF(AND(N$14>=$C16,N$14<=$D16),$E16,0) -> 0 | O16: =IF(AND(O$14>=$C16,O$14<=$D16),$E16,0) -> 0 | ... S16: =IF(AND(S$14>=$C16,S$14<=$D16),$E16,0) -> 0
C17: 1.15 | D17: et plus | E17: 2000 | H17: =IF(AND(H$14>=$C17,H$14<=$D17),$E17,0) -> 0 | I17: =IF(AND(I$14>=$C17,I$14<=$D17),$E17,0) -> 0 | J17: =IF(AND(J$14>=$C17,J$14<=$D17),$E17,0) -> 0 | K17: =IF(AND(K$14>=$C17,K$14<=$D17),$E17,0) -> 0 | L17: =IF(AND(L$14>=$C17,L$14<=$D17),$E17,0) -> 0 | M17: =IF(AND(M$14>=$C17,M$14<=$D17),$E17,0) -> 0 | N17: =IF(AND(N$14>=$C17,N$14<=$D17),$E17,0) -> 0 | O17: =IF(AND(O$14>=$C17,O$14<=$D17),$E17,0) -> 0 | ... S17: =IF(AND(S$14>=$C17,S$14<=$D17),$E17,0) -> 0
G18: Payable | H18: =SUM(H15:H17) -> 750 | I18: =SUM(I15:I17) -> 0 | J18: =SUM(J15:J17) -> 750 | K18: =SUM(K15:K17) -> 0 | L18: =SUM(L15:L17) -> 0 | M18: =SUM(M15:M17) -> 0 | N18: =SUM(N15:N17) -> 0 | O18: =SUM(O15:O17) -> 0 | ... S18: =SUM(S15:S17) -> 0
B20: Atteinte de la Cible CSI CPO (VOC) | G20: Réalisé | H20: 4.5 | I20: 5 | J20: 4.5 | K20: 4.71 | L20: 4.75 | M20: 1 | N20: 1 | O20: 1 | P20: 1 | Q20: 1 | R20: 1 | S20: 1 | U20: Courriel Frederic
G21: Cible | H21: 4.9 | I21: 4.9 | J21: 4.9 | K21: 4.9 | L21: 4.9 | M21: 4.9 | N21: 4.9 | O21: 4.9 | P21: 4.9 | Q21: 4.9 | R21: 4.9 | S21: 4.9
C22: de | D22: à | E22: Boni | G22: % | H22: =IFERROR(ROUND(H20/H21,3)," - - -") -> 0.918 | I22: =IFERROR(ROUND(I20/I21,3)," - - -") -> 1.02 | J22: =IFERROR(ROUND(J20/J21,3)," - - -") -> 0.918 | K22: =IFERROR(ROUND(K20/K21,3)," - - -") -> 0.961 | L22: =IFERROR(ROUND(L20/L21,3)," - - -") -> 0.969 | M22: =IFERROR(ROUND(M20/M21,3)," - - -") -> 0.204 | N22: =IFERROR(ROUND(N20/N21,3)," - - -") -> 0.204 | O22: =IFERROR(ROUND(O20/O21,3)," - - -") -> 0.204 | ... S22: =IFERROR(ROUND(S20/S21,3)," - - -") -> 0.204
C23: 4.7 | D23: 4.84 | E23: 100 | H23: =IF(AND(H$20>=$C23,H$20<=$D23),$E23,0) -> 0 | I23: =IF(AND(I$20>=$C23,I$20<=$D23),$E23,0) -> 0 | J23: =IF(AND(J$20>=$C23,J$20<=$D23),$E23,0) -> 0 | K23: =IF(AND(K$20>=$C23,K$20<=$D23),$E23,0) -> 100 | L23: =IF(AND(L$20>=$C23,L$20<=$D23),$E23,0) -> 100 | M23: =IF(AND(M$20>=$C23,M$20<=$D23),$E23,0) -> 0 | N23: =IF(AND(N$20>=$C23,N$20<=$D23),$E23,0) -> 0 | O23: =IF(AND(O$20>=$C23,O$20<=$D23),$E23,0) -> 0 | ... S23: =IF(AND(S$20>=$C23,S$20<=$D23),$E23,0) -> 0
C24: 4.85 | D24: 4.95 | E24: 250 | H24: =IF(AND(H$20>=$C24,H$20<=$D24),$E24,0) -> 0 | I24: =IF(AND(I$20>=$C24,I$20<=$D24),$E24,0) -> 0 | J24: =IF(AND(J$20>=$C24,J$20<=$D24),$E24,0) -> 0 | K24: =IF(AND(K$20>=$C24,K$20<=$D24),$E24,0) -> 0 | L24: =IF(AND(L$20>=$C24,L$20<=$D24),$E24,0) -> 0 | M24: =IF(AND(M$20>=$C24,M$20<=$D24),$E24,0) -> 0 | N24: =IF(AND(N$20>=$C24,N$20<=$D24),$E24,0) -> 0 | O24: =IF(AND(O$20>=$C24,O$20<=$D24),$E24,0) -> 0 | ... S24: =IF(AND(S$20>=$C24,S$20<=$D24),$E24,0) -> 0
C25: 4.96 | D25: et plus | E25: 500 | H25: =IF(AND(H$20>=$C25,H$20<=$D25),$E25,0) -> 0 | I25: =IF(AND(I$20>=$C25,I$20<=$D25),$E25,0) -> 500 | J25: =IF(AND(J$20>=$C25,J$20<=$D25),$E25,0) -> 0 | K25: =IF(AND(K$20>=$C25,K$20<=$D25),$E25,0) -> 0 | L25: =IF(AND(L$20>=$C25,L$20<=$D25),$E25,0) -> 0 | M25: =IF(AND(M$20>=$C25,M$20<=$D25),$E25,0) -> 0 | N25: =IF(AND(N$20>=$C25,N$20<=$D25),$E25,0) -> 0 | O25: =IF(AND(O$20>=$C25,O$20<=$D25),$E25,0) -> 0 | ... S25: =IF(AND(S$20>=$C25,S$20<=$D25),$E25,0) -> 0
G26: Payable | H26: =SUM(H23:H25) -> 0 | I26: =SUM(I23:I25) -> 500 | J26: =SUM(J23:J25) -> 0 | K26: =SUM(K23:K25) -> 100 | L26: =SUM(L23:L25) -> 100 | M26: =SUM(M23:M25) -> 0 | N26: =SUM(N23:N25) -> 0 | O26: =SUM(O23:O25) -> 0 | ... S26: =SUM(S23:S25) -> 0
B28: Atteinte des Indiicateurs de Performance ( X de 3 ) | G28: Réalisé | H28: 2 | I28: 2 | J28: 2 | K28: 3 | L28: 3 | M28: 0 | N28: 0 | O28: 0 | P28: 0 | Q28: 0 | R28: 0 | S28: 0
B29: (Inv. 90jrs moins de 20% / Protec. Méc. +de 60% / Fr. Admin +de 95%) | G29: Cible | H29: 2 | I29: 2 | J29: 2 | K29: 2 | L29: 2 | M29: 2 | N29: 2 | O29: 2 | P29: 2 | Q29: 2 | R29: 2 | S29: 2
C30: de | D30: à | E30: Boni | G30: % | H30: =IFERROR(ROUND(H28/H29,3)," - - -") -> 1 | I30: =IFERROR(ROUND(I28/I29,3)," - - -") -> 1 | J30: =IFERROR(ROUND(J28/J29,3)," - - -") -> 1 | K30: =IFERROR(ROUND(K28/K29,3)," - - -") -> 1.5 | L30: =IFERROR(ROUND(L28/L29,3)," - - -") -> 1.5 | M30: =IFERROR(ROUND(M28/M29,3)," - - -") -> 0 | N30: =IFERROR(ROUND(N28/N29,3)," - - -") -> 0 | O30: =IFERROR(ROUND(O28/O29,3)," - - -") -> 0 | ... S30: =IFERROR(ROUND(S28/S29,3)," - - -") -> 0
C31: 1 | D31: 1 | E31: 100 | H31: =IF(AND(H$28>=$C31,H$28<=$D31),$E31,0) -> 0 | I31: =IF(AND(I$28>=$C31,I$28<=$D31),$E31,0) -> 0 | J31: =IF(AND(J$28>=$C31,J$28<=$D31),$E31,0) -> 0 | K31: =IF(AND(K$28>=$C31,K$28<=$D31),$E31,0) -> 0 | L31: =IF(AND(L$28>=$C31,L$28<=$D31),$E31,0) -> 0 | M31: =IF(AND(M$28>=$C31,M$28<=$D31),$E31,0) -> 0 | N31: =IF(AND(N$28>=$C31,N$28<=$D31),$E31,0) -> 0 | O31: =IF(AND(O$28>=$C31,O$28<=$D31),$E31,0) -> 0 | ... S31: =IF(AND(S$28>=$C31,S$28<=$D31),$E31,0) -> 0
C32: 2 | D32: 2 | E32: 750 | H32: =IF(AND(H$28>=$C32,H$28<=$D32),$E32,0) -> 750 | I32: =IF(AND(I$28>=$C32,I$28<=$D32),$E32,0) -> 750 | J32: =IF(AND(J$28>=$C32,J$28<=$D32),$E32,0) -> 750 | K32: =IF(AND(K$28>=$C32,K$28<=$D32),$E32,0) -> 0 | L32: =IF(AND(L$28>=$C32,L$28<=$D32),$E32,0) -> 0 | M32: =IF(AND(M$28>=$C32,M$28<=$D32),$E32,0) -> 0 | N32: =IF(AND(N$28>=$C32,N$28<=$D32),$E32,0) -> 0 | O32: =IF(AND(O$28>=$C32,O$28<=$D32),$E32,0) -> 0 | ... S32: =IF(AND(S$28>=$C32,S$28<=$D32),$E32,0) -> 0
C33: 3 | D33: 3 | E33: 1250 | H33: =IF(AND(H$28>=$C33,H$28<=$D33),$E33,0) -> 0 | I33: =IF(AND(I$28>=$C33,I$28<=$D33),$E33,0) -> 0 | J33: =IF(AND(J$28>=$C33,J$28<=$D33),$E33,0) -> 0 | K33: =IF(AND(K$28>=$C33,K$28<=$D33),$E33,0) -> 1250 | L33: =IF(AND(L$28>=$C33,L$28<=$D33),$E33,0) -> 1250 | M33: =IF(AND(M$28>=$C33,M$28<=$D33),$E33,0) -> 0 | N33: =IF(AND(N$28>=$C33,N$28<=$D33),$E33,0) -> 0 | O33: =IF(AND(O$28>=$C33,O$28<=$D33),$E33,0) -> 0 | ... S33: =IF(AND(S$28>=$C33,S$28<=$D33),$E33,0) -> 0
G34: Payable | H34: =SUM(H31:H33) -> 750 | I34: =SUM(I31:I33) -> 750 | J34: =SUM(J31:J33) -> 750 | K34: =SUM(K31:K33) -> 1250 | L34: =SUM(L31:L33) -> 1250 | M34: =SUM(M31:M33) -> 0 | N34: =SUM(N31:N33) -> 0 | O34: =SUM(O31:O33) -> 0 | ... S34: =SUM(S31:S33) -> 0
G35: Total Mensuel | H35: =+H10+H18+H26+H34 -> 1500 | I35: =+I10+I18+I26+I34 -> 1250 | J35: =+J10+J18+J26+J34 -> 1500 | K35: =+K10+K18+K26+K34 -> 1350 | L35: =+L10+L18+L26+L34 -> 1350 | M35: =+M10+M18+M26+M34 -> 0 | N35: =+N10+N18+N26+N34 -> 0 | O35: =+O10+O18+O26+O34 -> 0 | ... S35: =+S10+S18+S26+S34 -> 0

Sheet H2
A1: =RIGHT(CELL("filename",A1),LEN(CELL("filename",A1))-SEARCH("]",CELL("filename",A1))) -> H2 | B1: Juillet | E1: Août | H1: Septembre | K1: Octobre | N1: Novembre | Q1: Décembre | T1: Total Q3 & Q4 2020
A2: Hypothèse forecast 2020
A3: % Basé sur le 1er budget 2020
A4: Unités neufs | B4: 0.8 | E4: 0.8 | H4: 0.8 | K4: 0.85 | N4: 0.85 | Q4: 0.85
A5: Gross neufs | B5: 0.9 | E5: 0.9 | H5: 0.9 | K5: 0.9 | N5: 0.9 | Q5: 0.9
A6: Unités usagés | B6: 0.9 | E6: 0.9 | H6: 0.9 | K6: 0.9 | N6: 0.9 | Q6: 0.9
A7: Gross usagés | B7: 0.9 | E7: 0.9 | H7: 0.9 | K7: 0.9 | N7: 0.9 | Q7: 0.9
A8: Revenus Services et Carrosserie | B8: 0.8 | E8: 0.8 | H8: 0.8 | K8: 0.8 | N8: 0.8 | Q8: 0.8
A9: Revenus Pièces | B9: 0.85 | E9: 0.85 | H9: 0.85 | K9: 0.85 | N9: 0.85 | Q9: 0.85
A10: Autres Revenus | B10: 0.7 | E10: 0.7 | H10: 0.7 | K10: 0.75 | N10: 0.75 | Q10: 0.75
A12: NEW | B12: # | C12: $P/UNITÉ | D12: $PROFITS | E12: # | F12: $P/UNITÉ | G12: $PROFITS | H12: # | I12: $P/UNITÉ | J12: $PROFITS | K12: # | L12: $P/UNITÉ | M12: $PROFITS | N12: # | O12: $P/UNITÉ | P12: $PROFITS | Q12: # | R12: $P/UNITÉ | S12: $PROFITS | T12: # | U12: $P/UNITÉ | V12: $PROFITS
A13: Total Neufs | B13: 80 | C13: =+D13/B13 -> 967.554 | D13: 77404.32 | E13: 85.6 | F13: =+G13/E13 -> 979.86449 | G13: 83876.4 | H13: 101.6 | I13: =+J13/H13 -> 949.2378 | J13: 96442.56 | K13: 96.05 | L13: =+M13/K13 -> 948.45664 | M13: 91099.26 | N13: 88.4 | O13: =+P13/N13 -> 967.73365 | P13: 85547.655 | Q13: 60.35 | R13: =+S13/Q13 -> 957.42254 | S13: 57780.45 | T13: =+SUM(B13,E13,H13,K13,N13,Q13) -> 512 | U13: =+V13/T13 -> 961.23173 | V13: =+SUM(D13,G13,J13,M13,P13,S13) -> 492150.65
A14: Ex-démos et courtoisies | B14: 20.8 | C14: =+D14/B14 -> 0 | D14: 0 | E14: 21.6 | F14: =+G14/E14 -> 0 | G14: 0 | H14: 24.8 | I14: =+J14/H14 -> 0 | J14: 0 | K14: 19.55 | L14: =+M14/K14 -> 0 | M14: 0 | N14: 19.55 | O14: =+P14/N14 -> 0 | P14: 0 | Q14: 13.6 | R14: =+S14/Q14 -> 0 | S14: 0 | T14: =+SUM(B14,E14,H14,K14,N14,Q14) -> 119.9 | U14: =+V14/T14 -> 0 | V14: =+SUM(D14,G14,J14,M14,P14,S14) -> 0
A15: Flottes | B15: 0 | C15: =+IFERROR(D15/B15,0) -> 0 | D15: 0 | E15: 0 | F15: =+IFERROR(G15/E15,0) -> 0 | G15: 0 | H15: 0 | I15: =+IFERROR(J15/H15,0) -> 0 | J15: 0 | K15: 0 | L15: =+IFERROR(M15/K15,0) -> 0 | M15: 0 | N15: 0 | O15: =+IFERROR(P15/N15,0) -> 0 | P15: 0 | Q15: 0 | R15: =+IFERROR(S15/Q15,0) -> 0 | S15: 0 | T15: =+SUM(B15,E15,H15,K15,N15,Q15) -> 0 | U15: =+IFERROR(V15/T15,0) -> 0 | V15: =+SUM(D15,G15,J15,M15,P15,S15) -> 0
A16: Rachat bail | D16: 6720 | G16: 6720 | J16: 6720 | M16: 7140 | P16: 7140 | S16: 7140 | T16: =+SUM(B16,E16,H16,K16,N16,Q16) -> 0 | V16: =+SUM(D16,G16,J16,M16,P16,S16) -> 41580
A17: Total F&I | B17: 100.8 | C17: =+IFERROR(D17/B17,0) -> 945 | D17: 95256 | E17: 107.2 | F17: =+IFERROR(G17/E17,0) -> 945 | G17: 101304 | H17: 126.4 | I17: =+IFERROR(J17/H17,0) -> 945 | J17: 119448 | K17: 115.6 | L17: =+IFERROR(M17/K17,0) -> 945 | M17: 109242 | N17: 107.95 | O17: =+IFERROR(P17/N17,0) -> 945 | P17: 102012.75 | Q17: 73.95 | R17: =+IFERROR(S17/Q17,0) -> 945 | S17: 69882.75 | T17: =+SUM(B17,E17,H17,K17,N17,Q17) -> 631.9 | U17: =+IFERROR(V17/T17,0) -> 945 | V17: =+SUM(D17,G17,J17,M17,P17,S17) -> 597145.5
A18: Total Neufs | B18: =+SUM(B13:B15) -> 100.8 | C18: =+IFERROR(D18/B18,0) -> 1779.5667 | D18: =+SUM(D13:D17) -> 179380.32 | E18: =+SUM(E13:E15) -> 107.2 | F18: =+IFERROR(G18/E18,0) -> 1790.1157 | G18: =+SUM(G13:G17) -> 191900.4 | H18: =+SUM(H13:H15) -> 126.4 | I18: =+IFERROR(J18/H18,0) -> 1761.1595 | J18: =+SUM(J13:J17) -> 222610.56 | K18: =+SUM(K13:K15) -> 115.6 | L18: =+IFERROR(M18/K18,0) -> 1794.8206 | M18: =+SUM(M13:M17) -> 207481.26 | N18: =+SUM(N13:N15) -> 107.95 | O18: =+IFERROR(P18/N18,0) -> 1803.6165 | P18: =+SUM(P13:P17) -> 194700.4 | Q18: =+SUM(Q13:Q15) -> 73.95 | R18: =+IFERROR(S18/Q18,0) -> 1822.8966 | S18: =+SUM(S13:S17) -> 134803.2 | T18: =+SUM(T13:T15) -> 631.9 | U18: =+IFERROR(V18/T18,0) -> 1789.6442 | V18: =+SUM(V13:V17) -> 1130876.1
C19: =D13/(B13+B14) -> 767.9 | F19: =G13/(E13+E14) -> 782.4291 | I19: =J13/(H13+H14) -> 762.99494 | L19: =M13/(K13+K14) -> 788.05588 | O19: =P13/(N13+N14) -> 792.4748 | R19: =S13/(Q13+Q14) -> 781.34483
A20: Usagés | B20: # | C20: $P/UNITÉ | D20: $PROFITS | E20: # | F20: $P/UNITÉ | G20: $PROFITS | H20: # | I20: $P/UNITÉ | J20: $PROFITS | K20: # | L20: $P/UNITÉ | M20: $PROFITS | N20: # | O20: $P/UNITÉ | P20: $PROFITS | Q20: # | R20: $P/UNITÉ | S20: $PROFITS | T20: # | U20: $P/UNITÉ | V20: $PROFITS
A21: Total Used | B21: 45 | C21: =+D21/B21 -> 834.3 | D21: 37543.5 | E21: 48.6 | F21: =+G21/E21 -> 840.83333 | G21: 40864.5 | H21: 48.6 | I21: =+J21/H21 -> 837.5 | J21: 40702.5 | K21: 45.9 | L21: =+M21/K21 -> 830.29412 | M21: 38110.5 | N21: 45 | O21: =+P21/N21 -> 834.3 | P21: 37543.5 | Q21: 33.3 | R21: =+S21/Q21 -> 834.32432 | S21: 27783 | T21: =+SUM(B21,E21,H21,K21,N21,Q21) -> 266.4 | U21: =+V21/T21 -> 835.38851 | V21: =+SUM(D21,G21,J21,M21,P21,S21) -> 222547.5
A22: US | T22: =+SUM(B22,E22,H22,K22,N22,Q22) -> 0 | U22: =+V22/T22 -> #DIV/0! | V22: =+SUM(D22,G22,J22,M22,P22,S22) -> 0
A23: Gros | B23: 42.3 | C23: =+D23/B23 -> 90 | D23: 3807 | E23: 41.4 | F23: =+G23/E23 -> 90 | G23: 3726 | H23: 40.5 | I23: =+J23/H23 -> 90 | J23: 3645 | K23: 41.4 | L23: =+M23/K23 -> 90 | M23: 3726 | N23: 41.4 | O23: =+P23/N23 -> 90 | P23: 3726 | Q23: 40.5 | R23: =+S23/Q23 -> 90 | S23: 3645 | T23: =+SUM(B23,E23,H23,K23,N23,Q23) -> 247.5 | U23: =+V23/T23 -> 90 | V23: =+SUM(D23,G23,J23,M23,P23,S23) -> 22275
A24: Total F&I | B24: 45 | C24: =+D24/B24 -> 1278 | D24: 57510 | E24: 48.6 | F24: =+G24/E24 -> 1278 | G24: 62110.8 | H24: 48.6 | I24: =+J24/H24 -> 1278 | J24: 62110.8 | K24: 45.9 | L24: =+M24/K24 -> 1278 | M24: 58660.2 | N24: 45 | O24: =+P24/N24 -> 1278 | P24: 57510 | Q24: 33.3 | R24: =+S24/Q24 -> 1278 | S24: 42557.4 | T24: =+SUM(B24,E24,H24,K24,N24,Q24) -> 266.4 | U24: =+V24/T24 -> 1278 | V24: =+SUM(D24,G24,J24,M24,P24,S24) -> 340459.2
A25: TOTAL Usagés | B25: =+SUM(B21:B23) -> 87.3 | C25: =+IFERROR(D25/B25,0) -> 1132.4227 | D25: =+SUM(D21:D24) -> 98860.5 | E25: =+SUM(E21:E23) -> 90 | F25: =+IFERROR(G25/E25,0) -> 1185.57 | G25: =+SUM(G21:G24) -> 106701.3 | H25: =+SUM(H21:H23) -> 89.1 | I25: =+IFERROR(J25/H25,0) -> 1194.8182 | J25: =+SUM(J21:J24) -> 106458.3 | K25: =+SUM(K21:K23) -> 87.3 | L25: =+IFERROR(M25/K25,0) -> 1151.1649 | M25: =+SUM(M21:M24) -> 100496.7 | N25: =+SUM(N21:N23) -> 86.4 | O25: =+IFERROR(P25/N25,0) -> 1143.2812 | P25: =+SUM(P21:P24) -> 98779.5 | Q25: =+SUM(Q21:Q23) -> 73.8 | R25: =+IFERROR(S25/Q25,0) -> 1002.5122 | S25: =+SUM(S21:S24) -> 73985.4 | T25: =+SUM(T21:T23) -> 513.9 | U25: =+IFERROR(V25/T25,0) -> 1138.9019 | V25: =+SUM(V21:V24) -> 585281.7
A27: Services et Carosserie | B27: Ventes | C27: Profit | D27: % | E27: Ventes | F27: Profit | G27: % | H27: Ventes | I27: Profit | J27: % | K27: Ventes | L27: Profit | M27: % | N27: Ventes | O27: Profit | P27: % | Q27: Ventes | R27: Profit | S27: % | T27: Ventes | U27: Profit | V27: %
A28: Services | B28: 425918.62 | C28: =+B28*D28 -> 280000.2 | D28: 0.65740305 | E28: 421131.51 | F28: =+E28*G28 -> 277052.88 | G28: 0.65787734 | H28: 358560.62 | I28: =+H28*J28 -> 235158.1 | J28: 0.65583917 | K28: 557240.85 | L28: =+K28*M28 -> 369320.5 | M28: 0.66276638 | N28: 629544.09 | O28: =+N28*P28 -> 419365.11 | P28: 0.66614096 | Q28: 401750.93 | R28: =+Q28*S28 -> 266281.8 | S28: 0.6628032 | T28: =+SUM(B28,E28,H28,K28,N28,Q28) -> 2794146.6 | U28: =+SUM(C28,F28,I28,L28,O28,R28) -> 1847178.6 | V28: =+U28/T28 -> 0.66108864
A29: Carosserie | B29: 80000 | C29: =+B29*D29 -> 18400 | D29: 0.23 | E29: 80000 | F29: =+E29*G29 -> 18400 | G29: 0.23 | H29: 80000 | I29: =+H29*J29 -> 18400 | J29: 0.23 | K29: 80000 | L29: =+K29*M29 -> 18400 | M29: 0.23 | N29: 80000 | O29: =+N29*P29 -> 18400 | P29: 0.23 | Q29: 80000 | R29: =+Q29*S29 -> 18400 | S29: 0.23 | T29: =+SUM(B29,E29,H29,K29,N29,Q29) -> 480000 | U29: =+SUM(C29,F29,I29,L29,O29,R29) -> 110400 | V29: =+U29/T29 -> 0.23
A30: Total | B30: =+B28+B29 -> 505918.62 | C30: =+C28+C29 -> 298400.2 | D30: =+C30/B30 -> 0.58981858 | E30: =+E28+E29 -> 501131.51 | F30: =+F28+F29 -> 295452.88 | G30: =+F30/E30 -> 0.58957154 | H30: =+H28+H29 -> 438560.62 | I30: =+I28+I29 -> 253558.1 | J30: =+I30/H30 -> 0.57815976 | K30: =+K28+K29 -> 637240.85 | L30: =+L28+L29 -> 387720.5 | M30: =+L30/K30 -> 0.60843636 | N30: =+N28+N29 -> 709544.09 | O30: =+O28+O29 -> 437765.11 | P30: =+O30/N30 -> 0.61696674 | Q30: =+Q28+Q29 -> 481750.93 | R30: =+R28+R29 -> 284681.8 | S30: =+R30/Q30 -> 0.5909315 | T30: =+T28+T29 -> 3274146.6 | U30: =+U28+U29 -> 1957578.6 | V30: =+U30/T30 -> 0.59788971
A32: Pièces | B32: Ventes | C32: Profit | D32: % | E32: Ventes | F32: Profit | G32: % | H32: Ventes | I32: Profit | J32: % | K32: Ventes | L32: Profit | M32: % | N32: Ventes | O32: Profit | P32: % | Q32: Ventes | R32: Profit | S32: % | T32: Ventes | U32: Profit | V32: %
A33: Total | B33: 749749.93 | C33: =+B33*D33 -> 215892.02 | D33: 0.28795204 | E33: 719236.7 | F33: =+E33*G33 -> 215265.66 | G33: 0.29929738 | H33: 687160.19 | I33: =+H33*J33 -> 204105.56 | J33: 0.29702762 | K33: 1083893.2 | L33: =+K33*M33 -> 314522.04 | M33: 0.29017806 | N33: 1206826 | O33: =+N33*P33 -> 342601.84 | P33: 0.28388668 | Q33: 762759.45 | R33: =+Q33*S33 -> 220263.49 | S33: 0.28877189 | T33: =+SUM(B33,E33,H33,K33,N33,Q33) -> 5209625.6 | U33: =+SUM(C33,F33,I33,L33,O33,R33) -> 1512650.6 | V33: =+U33/T33 -> 0.29035688
A35: Profit brut | B35: =+C33+C30+D25+D18 -> 792533.04 | E35: =+F33+F30+G25+G18 -> 809320.24 | H35: =+I33+I30+J25+J18 -> 786732.52 | K35: =+L33+L30+M25+M18 -> 1010220.5 | N35: =+O33+O30+P25+P18 -> 1073846.9 | Q35: =+R33+R30+S25+S18 -> 713733.89 | T35: =+U33+U30+V25+V18 -> 5186387
A37: Dépenses
A38: Comm. vendeurs | B38: 74290 | E38: 77290 | H38: 83050 | K38: 79000 | N38: 76435 | Q38: 62725 | T38: =+SUM(B38,E38,H38,K38,N38,Q38) -> 452790 | U38: =+SUM(C38,F38,I38,L38,O38,R38) -> 0 | V38: =+SUM(D38,G38,J38,M38,P38,S38) -> 0
A39: Comm. F&I | B39: 42010.65 | E39: 44939.07 | H39: 49928.67 | K39: 46173.105 | N39: 43868.756 | Q39: 30921.041 | T39: =+SUM(B39,E39,H39,K39,N39,Q39) -> 257841.29 | U39: =+SUM(C39,F39,I39,L39,O39,R39) -> 0 | V39: =+SUM(D39,G39,J39,M39,P39,S39) -> 0
A40: Frais de livraison | B40: 46992 | E40: 49392 | H40: 54000 | K40: 50760 | N40: 48708 | Q40: 37740 | T40: =+SUM(B40,E40,H40,K40,N40,Q40) -> 287592 | U40: =+SUM(C40,F40,I40,L40,O40,R40) -> 0 | V40: =+SUM(D40,G40,J40,M40,P40,S40) -> 0
A41: Goodwill | B41: 23219.857 | E41: 23330.603 | H41: 22723.51 | K41: 29572.176 | N41: 31693.127 | Q41: 21104.88 | T41: =+SUM(B41,E41,H41,K41,N41,Q41) -> 151644.15 | U41: =+SUM(C41,F41,I41,L41,O41,R41) -> 0 | V41: =+SUM(D41,G41,J41,M41,P41,S41) -> 0
A42: Publicité | B42: 44706.952 | E42: 45129.115 | H42: 46395.606 | K42: 45683.205 | N42: 45178.587 | Q42: 42935.843 | T42: =+SUM(B42,E42,H42,K42,N42,Q42) -> 270029.31 | U42: =+SUM(C42,F42,I42,L42,O42,R42) -> 0 | V42: =+SUM(D42,G42,J42,M42,P42,S42) -> 0
A43: Intérêt de gros | B43: 44000 | E43: 44000 | H43: 44000 | K43: 44000 | N43: 44000 | Q43: 44000 | T43: =+SUM(B43,E43,H43,K43,N43,Q43) -> 264000 | U43: =+SUM(C43,F43,I43,L43,O43,R43) -> 0 | V43: =+SUM(D43,G43,J43,M43,P43,S43) -> 0
A44: Total variables | B44: =+SUM(B38:D43) -> 275219.46 | E44: =+SUM(E38:G43) -> 284080.79 | H44: =+SUM(H38:J43) -> 300097.79 | K44: =+SUM(K38:M43) -> 295188.49 | N44: =+SUM(N38:P43) -> 289883.47 | Q44: =+SUM(Q38:S43) -> 239426.76 | T44: =+SUM(T38:V43) -> 1683896.8
A46: Salaires propriétaire | B46: 14759 | E46: 14759 | H46: 14759 | K46: 14759 | N46: 14759 | Q46: 14759 | T46: =+SUM(B46,E46,H46,K46,N46,Q46) -> 88554 | U46: =+SUM(C46,F46,I46,L46,O46,R46) -> 0 | V46: =+SUM(D46,G46,J46,M46,P46,S46) -> 0
A47: Salaires cadres | B47: 60293.851 | E47: 60708.498 | H47: 61249.348 | K47: 65893.274 | N47: 67106.766 | Q47: 57296.599 | T47: =+SUM(B47,E47,H47,K47,N47,Q47) -> 372548.34 | U47: =+SUM(C47,F47,I47,L47,O47,R47) -> 0 | V47: =+SUM(D47,G47,J47,M47,P47,S47) -> 0
A48: Salaires autres | B48: 165222.92 | E48: 164097.75 | H48: 159787.78 | K48: 205127.37 | N48: 219293.73 | Q48: 157781.14 | T48: =+SUM(B48,E48,H48,K48,N48,Q48) -> 1071310.7 | U48: =+SUM(C48,F48,I48,L48,O48,R48) -> 0 | V48: =+SUM(D48,G48,J48,M48,P48,S48) -> 0
A49: Salaires en absences | B49: 28204.742 | E49: 28373.648 | H49: 27688.866 | K49: 33023.655 | N49: 34662.112 | Q49: 26027.596 | T49: =+SUM(B49,E49,H49,K49,N49,Q49) -> 177980.62 | U49: =+SUM(C49,F49,I49,L49,O49,R49) -> 0 | V49: =+SUM(D49,G49,J49,M49,P49,S49) -> 0
A50: Déduction à la source | B50: 67691.38 | E50: 68096.754 | H50: 66453.278 | K50: 79256.772 | N50: 83189.069 | Q50: 62466.229 | T50: =+SUM(B50,E50,H50,K50,N50,Q50) -> 427153.48 | U50: =+SUM(C50,F50,I50,L50,O50,R50) -> 0 | V50: =+SUM(D50,G50,J50,M50,P50,S50) -> 0
A51: Bénéfices marginaux | B51: 28204.742 | E51: 28373.648 | H51: 27688.866 | K51: 33023.655 | N51: 34662.112 | Q51: 26027.596 | T51: =+SUM(B51,E51,H51,K51,N51,Q51) -> 177980.62 | U51: =+SUM(C51,F51,I51,L51,O51,R51) -> 0 | V51: =+SUM(D51,G51,J51,M51,P51,S51) -> 0
A52: Csst | B52: 16922.845 | E52: 17024.189 | H52: 16613.32 | K52: 19814.193 | N52: 20797.267 | Q52: 15616.557 | T52: =+SUM(B52,E52,H52,K52,N52,Q52) -> 106788.37 | U52: =+SUM(C52,F52,I52,L52,O52,R52) -> 0 | V52: =+SUM(D52,G52,J52,M52,P52,S52) -> 0
A53: Total personnel | B53: =+SUM(B46:D52) -> 381299.48 | E53: =+SUM(E46:G52) -> 381433.49 | H53: =+SUM(H46:J52) -> 374240.46 | K53: =+SUM(K46:M52) -> 450897.92 | N53: =+SUM(N46:P52) -> 474470.06 | Q53: =+SUM(Q46:S52) -> 359974.72 | T53: =+SUM(T46:V52) -> 2422316.1
A55: Frais de véhicules | B55: 59985.327 | E55: 59592.784 | H55: 54461.971 | K55: 70753.75 | N55: 76682.616 | Q55: 58003.576 | T55: =+SUM(B55,E55,H55,K55,N55,Q55) -> 379480.02 | U55: =+SUM(C55,F55,I55,L55,O55,R55) -> 0 | V55: =+SUM(D55,G55,J55,M55,P55,S55) -> 0
A56: Bureau | B56: 52325.885 | E56: 51355.126 | H56: 48752.322 | K56: 65126.187 | N56: 70495.179 | Q56: 52019.035 | T56: =+SUM(B56,E56,H56,K56,N56,Q56) -> 340073.73 | U56: =+SUM(C56,F56,I56,L56,O56,R56) -> 0 | V56: =+SUM(D56,G56,J56,M56,P56,S56) -> 0
A57: Loyer | B57: 95500 | E57: 95500 | H57: 95500 | K57: 95500 | N57: 95500 | Q57: 95500 | T57: =+SUM(B57,E57,H57,K57,N57,Q57) -> 573000 | U57: =+SUM(C57,F57,I57,L57,O57,R57) -> 0 | V57: =+SUM(D57,G57,J57,M57,P57,S57) -> 0
A58: Informatique | B58: 27173.635 | E58: 27089.167 | H58: 26862.689 | K58: 28287.428 | N58: 28754.6 | Q58: 27146.936 | T58: =+SUM(B58,E58,H58,K58,N58,Q58) -> 165314.45 | U58: =+SUM(C58,F58,I58,L58,O58,R58) -> 0 | V58: =+SUM(D58,G58,J58,M58,P58,S58) -> 0
A59: Services extérieurs et frais professionnels | B59: 80203.072 | E59: 79739.125 | H59: 78495.188 | K59: 86320.619 | N59: 88886.579 | Q59: 80056.422 | T59: =+SUM(B59,E59,H59,K59,N59,Q59) -> 493701.01 | U59: =+SUM(C59,F59,I59,L59,O59,R59) -> 0 | V59: =+SUM(D59,G59,J59,M59,P59,S59) -> 0
A60: Bâtisse | B60: 49055 | E60: 49055 | H60: 49055 | K60: 49055 | N60: 49055 | Q60: 49055 | T60: =+SUM(B60,E60,H60,K60,N60,Q60) -> 294330 | U60: =+SUM(C60,F60,I60,L60,O60,R60) -> 0 | V60: =+SUM(D60,G60,J60,M60,P60,S60) -> 0
A61: Total semi-fixes et fixes | B61: =+SUM(B55:D60) -> 364242.92 | E61: =+SUM(E55:G60) -> 362331.2 | H61: =+SUM(H55:J60) -> 353127.17 | K61: =+SUM(K55:M60) -> 395042.98 | N61: =+SUM(N55:P60) -> 409373.97 | Q61: =+SUM(Q55:S60) -> 361780.97 | T61: =+SUM(T55:V60) -> 2245899.2
A63: Total dépenses | B63: =+B61+B53+B44 -> 1020761.9 | E63: =+E61+E53+E44 -> 1027845.5 | H63: =+H61+H53+H44 -> 1027465.4 | K63: =+K61+K53+K44 -> 1141129.4 | N63: =+N61+N53+N44 -> 1173727.5 | Q63: =+Q61+Q53+Q44 -> 961182.45 | T63: =+T61+T53+T44 -> 6352112.1
A65: Autres revenus | B65: 374587.63 | E65: 391248.15 | H65: 341696.28 | K65: 336678.68 | N65: 334619.16 | Q65: 260756.1 | T65: =+SUM(B65,E65,H65,K65,N65,Q65) -> 2039586 | U65: =+SUM(C65,F65,I65,L65,O65,R65) -> 0 | V65: =+SUM(D65,G65,J65,M65,P65,S65) -> 0
A67: BAIIA | B67: =+B35-B63+B65 -> 146358.82 | E67: =+E35-E63+E65 -> 172722.91 | H67: =+H35-H63+H65 -> 100963.38 | K67: =+K35-K63+K65 -> 205769.79 | N67: =+N35-N63+N65 -> 234738.51 | Q67: =+Q35-Q63+Q65 -> 13307.54 | T67: =+T35-T63+T65 -> 873860.96
A69: Amortissement | B69: 51100 | E69: 51100 | H69: 51100 | K69: 51100 | N69: 51100 | Q69: 51100 | T69: =+SUM(B69,E69,H69,K69,N69,Q69) -> 306600 | U69: =+SUM(C69,F69,I69,L69,O69,R69) -> 0 | V69: =+SUM(D69,G69,J69,M69,P69,S69) -> 0
A70: Intérêt | B70: 9172 | E70: 9172 | H70: 9172 | K70: 9172 | N70: 9172 | Q70: 9172 | T70: =+SUM(B70,E70,H70,K70,N70,Q70) -> 55032 | U70: =+SUM(C70,F70,I70,L70,O70,R70) -> 0 | V70: =+SUM(D70,G70,J70,M70,P70,S70) -> 0
A72: Profit net | B72: =+B67-B69-B70 -> 86086.822 | E72: =+E67-E69-E70 -> 112450.91 | H72: =+H67-H69-H70 -> 40691.385 | K72: =+K67-K69-K70 -> 145497.79 | N72: =+N67-N69-N70 -> 174466.51 | Q72: =+Q67-Q69-Q70 -> -46964.46 | T72: =+T67-T69-T70 -> 512228.96
A76: Seasonality
C77: Profit | F77: Profit | I77: Profit | L77: Profit | O77: Profit | R77: Profit | U77: Profit
A78: Services
A79: Carosserie
A80: Pièces

Sheet Karim Noori (feb 22)
B2: 1 | C2: 1.15
B3: 1600 | C3: 2080
B4: 1600 | C4: 2080
B5: 250 | C5: 500
B6: 250 | C6: 500
B7: =SUM(B3:B6) -> 3700 | C7: =SUM(C3:C6) -> 5160
B9: 0 | C9: =C7*0.5 -> 2580
C10: =C7*0.5 -> 2580
A13: Neuf | B13: =0+B5++B6 -> 500
A14: usagé | C14: =C3+C4+B5+B6 -> 4660
B15: 0.5 | C15: 0.5
B16: =B15*B13 -> 250 | C16: =C15*C14 -> 2330 | D16: =SUM(B16:C16) -> 2580

Sheet Marie Eve Légaré
B1: ANNEXE AU PLAN DE RÉMUNÉRATION
B2: Directrice Adjointe
B6: Bonis mensuel
C8: Boni Mensuel | H8: En annuel
L9: Janvier
C10: 95%-99.9% | D10: 100%-109.9% | E10: 110% et + | H10: =C10 -> 95%-99.9% | I10: =D10 -> 100%-109.9% | J10: =E10 -> 110% et +
B11: Attreinte de vente MO en profit brut (client, interne et garantie) | C11: 250 | D11: 500 | E11: 750 | H11: =C11*12 -> 3000 | I11: =D11*12 -> 6000 | J11: =E11*12 -> 9000
D12: JANV 21 | E12: `FEB 21
B13: Janvier 2021 | C13: Réel | D13: 180311.62 | E13: 254010.75
C14: Budget | D14: 296936.9 | E14: 299317.73
C15: % | D15: =D13/D14 -> 0.60723885 | E15: =E13/E14 -> 0.84863248
C16: payé | D16: 0 | E16: 0
D18: Fait | I18: Fait
B19: Atteinte de WIP (Pool sur une moyenne de 25 RO / aviseur) | D19: 250 | I19: =D19*12 -> 3000
C20: payé | D20: 250 | E20: 250
B25: Objectifs de vente cible (Alignement, Liquide à frein, réparation PB) | D25: 250 | I25: =D25*12 -> 3000
C26: payé | D26: 0 | E26: 0
C30: 85%-99.9% | D30: 100%-109.9% | E30: 110% et + | H30: 85%-99.9% | I30: 100%-109.9% | J30: 110% et +
B31: Ventes esthétique Client (au budget) | C31: 1.8% | D31: 0.02 | E31: 2.5% | H31: =SUM((B33*0.9)*0.0018)*12 -> 3620.9138 | I31: =B33*(2%) -> 3725.22 | J31: =SUM((B33*1.1)*0.0025)*12 -> 6146.613
B33: 186261 | C33: Réel | D33: 944.5 | E33: 1775.17
C34: Budget | D34: 4337.6979 | E34: 5352.3619 | I34: =I11+I19+I25+I31 -> 15725.22
C35: % | D35: =D33/D34 -> 0.21774223 | E35: =E33/E34 -> 0.33166105
C36: payé | D36: 0 | E36: 0
C39: total | D39: =D16+D20+D26+D36 -> 250 | E39: =E16+E20+E26+E36 -> 250 | H39: =H11+I19+I25+H31 -> 12620.914 | I39: =I11+I19+I25+I31 -> 15725.22 | J39: =J11+I19+I25+J31 -> 21146.613
