Workbook
Name _Dates_Conc: [1]Dealers!$BF$37:$KA$63
Name _scen: '[1]Scen & Sens'!$E$26
Name _scen1: '[1]Scen & Sens'!$E$27
Name _scen2: '[1]Scen & Sens'!$E$28
Name _SCenarios: '[1]Scen & Sens'!$J$26:$O$26
Name _Sens1: '[1]Scen & Sens'!$F$9
Name _Sens2: '[1]Scen & Sens'!$F$10
Name _sensRes1: '[1]Scen & Sens'!$E$15
Name _sensRes2: '[1]Scen & Sens'!$E$16
Name _sensRes3: '[1]Scen & Sens'!$E$17
Name _sensRes4: '[1]Scen & Sens'!$E$18
Name _sensRes5: '[1]Scen & Sens'!$E$19
Name _sensRes6: '[1]Scen & Sens'!$E$20
Name _sensRes7: '[1]Scen & Sens'!$E$21
Name a: #REF!
Name a: #REF!
Name a: #REF!
Name a: #REF!
Name a: #REF!
Name a: #REF!
Name a: #REF!
Name a: #REF!
Name a: #REF!
Name a: #REF!
Name a: #REF!
Name a: #REF!
Name BLANK: #REF!
Name BLANK: #REF!
Name BLANK: #REF!
Name BLANK: #REF!
Name BLANK: #REF!
Name BLANK: #REF!
Name BLANK: #REF!
Name BLANK: #REF!
Name BLANK: #REF!
Name BLANK: #REF!
Name BLANK: #REF!
Name BLANK: #REF!
Name BROWN: #REF!
Name BROWN: #REF!
Name BROWN: #REF!
Name BROWN: #REF!
Name BROWN: #REF!
Name BROWN: #REF!
Name BROWN: #REF!
Name BROWN: #REF!
Name BROWN: #REF!
Name BROWN: #REF!
Name BROWN: #REF!
Name BROWN: #REF!
Name Compco1: #REF!
Name Compco1: #REF!
Name Compco1: #REF!
Name Compco1: #REF!
Name Compco1: #REF!
Name Compco1: #REF!
Name Compco1: #REF!
Name Compco1: #REF!
Name Compco1: #REF!
Name Compco1: #REF!

Sheet RECAP v2
B2: Delivery Fee NEW + USED
B3: =CONCATENATE(#REF!,F2,#REF!) -> #REF! | M3: BUDGET | X3: 2019
B4: STORE | C4: Units | D4: Margin | E4: Margin demo | F4: Front margin | G4: frais de livraison | H4: Ent. Stock | I4: Delivery fee | J4: Delivery fee / unit | K4: % Delivery fee / Front margin | M4: STORE | N4: Units | O4: M. new | P4: M. Demos | Q4: Front margin | R4: frais de livraison | S4: Ent. Stock | T4: Delivery fee | U4: Delivery fee / unit | V4: % Delivery fee / Front margin | X4: STORE | Y4: Units | Z4: M. used | AB4: Front margin | AC4: frais de livraison | AD4: Ent. Stock | AE4: Delivery fee | AF4: Delivery fee / unit | AG4: % Delivery fee / Front margin
B5: TOTAL | C5: =+SUM(C6:C23) -> #REF! | D5: =+SUM(D6:D23) -> #REF! | E5: =+SUM(E6:E23) -> #REF! | F5: =+SUM(F6:F23) -> #REF! | G5: =+SUM(G6:G23) -> #REF! | H5: =+SUM(H6:H23) -> #REF! | I5: =+SUM(I6:I23) -> #REF! | J5: =+I5/C5 -> #REF! | K5: =+I5/F5 -> #REF! | M5: TOTAL | N5: =+SUM(N6:N23) -> #REF! | O5: =+SUM(O6:O23) -> #REF! | P5: =+SUM(P6:P23) -> #REF! | Q5: =+SUM(Q6:Q23) -> #REF! | R5: =+SUM(R6:R23) -> #REF! | S5: =+SUM(S6:S23) -> #REF! | T5: =+SUM(T6:T23) -> #REF! | U5: =+T5/N5 -> #REF! | V5: =+T5/Q5 -> #REF! | X5: TOTAL | Y5: =+SUM(Y6:Y23) -> #REF! | Z5: =+SUM(Z6:Z23) -> #REF! | AA5: =+SUM(AA6:AA23) -> #REF! | AB5: =+SUM(AB6:AB23) -> #REF! | AC5: =+SUM(AC6:AC23) -> #REF! | AD5: =+SUM(AD6:AD23) -> #REF! | AE5: =+SUM(AE6:AE23) -> #REF! | AF5: =+AE5/Y5 -> #REF! | AG5: =+AE5/AB5 -> #REF!
B6: AUDI | C6: =+C29+C52 -> #REF! | D6: =+D29+D52 -> #REF! | E6: =+E29+E52 -> #REF! | F6: =+D6+E6 -> #REF! | G6: =+G29+G52 -> #REF! | H6: =+H29+H52 -> #REF! | I6: =+G6+H6 -> #REF! | J6: =+I6/C6 -> #REF! | K6: =+I6/F6 -> #REF! | M6: AUDI | N6: =+N29+N52 -> #REF! | O6: =+O29+O52 -> #REF! | P6: =+P29+P52 -> #REF! | Q6: =+O6+P6 -> #REF! | R6: =+R29+R52 -> #REF! | S6: =+S29+S52 -> #REF! | T6: =+R6+S6 -> #REF! | U6: =+T6/N6 -> #REF! | V6: =+T6/Q6 -> #REF! | X6: AUDI | Y6: =+Y29+Y52 -> #REF! | Z6: =+Z29+Z52 -> #REF! | AA6: =+AA29+AA52 -> #REF! | AB6: =+Z6+AA6 -> #REF! | AC6: =+AC29+AC52 -> #REF! | AD6: =+AD29+AD52 -> #REF! | AE6: =+AC6+AD6 -> #REF! | AF6: =+AE6/Y6 -> #REF! | AG6: =+AE6/AB6 -> #REF!
B7: INFINITI | C7: =+C30+C53 -> #REF! | D7: =+D30+D53 -> #REF! | E7: =+E30+E53 -> #REF! | F7: =+D7+E7 -> #REF! | G7: =+G30+G53 -> #REF! | H7: =+H30+H53 -> #REF! | I7: =+G7+H7 -> #REF! | J7: =+I7/C7 -> #REF! | K7: =+I7/F7 -> #REF! | M7: INFINITI | N7: =+N30+N53 -> #REF! | O7: =+O30+O53 -> #REF! | P7: =+P30+P53 -> #REF! | Q7: =+O7+P7 -> #REF! | R7: =+R30+R53 -> #REF! | S7: =+S30+S53 -> #REF! | T7: =+R7+S7 -> #REF! | U7: =+T7/N7 -> #REF! | V7: =+T7/Q7 -> #REF! | X7: INFINITI | Y7: =+Y30+Y53 -> #REF! | Z7: =+Z30+Z53 -> #REF! | AA7: =+AA30+AA53 -> #REF! | AB7: =+Z7+AA7 -> #REF! | AC7: =+AC30+AC53 -> #REF! | AD7: =+AD30+AD53 -> #REF! | AE7: =+AC7+AD7 -> #REF! | AF7: =+AE7/Y7 -> #REF! | AG7: =+AE7/AB7 -> #REF!
B8: MCPA LAP | C8: =+C31+C54 -> #REF! | D8: =+D31+D54 -> #REF! | E8: =+E31+E54 -> 0 | F8: =+D8+E8 -> #REF! | G8: =+G31+G54 -> #REF! | H8: =+H31+H54 -> #REF! | I8: =+G8+H8 -> #REF! | J8: =+I8/C8 -> #REF! | K8: =+I8/F8 -> #REF! | M8: MCPA LAP | N8: =+N31+N54 -> #REF! | O8: =+O31+O54 -> #REF! | P8: =+P31+P54 -> 0 | Q8: =+O8+P8 -> #REF! | R8: =+R31+R54 -> #REF! | S8: =+S31+S54 -> #REF! | T8: =+R8+S8 -> #REF! | U8: =+T8/N8 -> #REF! | V8: =+T8/Q8 -> #REF! | X8: MCPA LAP | Y8: =+Y31+Y54 -> #REF! | Z8: =+Z31+Z54 -> #REF! | AA8: =+AA31+AA54 -> 0 | AB8: =+Z8+AA8 -> #REF! | AC8: =+AC31+AC54 -> #REF! | AD8: =+AD31+AD54 -> #REF! | AE8: =+AC8+AD8 -> #REF! | AF8: =+AE8/Y8 -> #REF! | AG8: =+AE8/AB8 -> #REF!
B9: MCPA LAV | C9: =+C32+C55 -> #REF! | D9: =+D32+D55 -> #REF! | E9: =+E32+E55 -> 0 | F9: =+D9+E9 -> #REF! | G9: =+G32+G55 -> #REF! | H9: =+H32+H55 -> #REF! | I9: =+G9+H9 -> #REF! | J9: =+I9/C9 -> #REF! | K9: =+I9/F9 -> #REF! | M9: MCPA LAV | N9: =+N32+N55 -> #REF! | O9: =+O32+O55 -> #REF! | P9: =+P32+P55 -> 0 | Q9: =+O9+P9 -> #REF! | R9: =+R32+R55 -> #REF! | S9: =+S32+S55 -> #REF! | T9: =+R9+S9 -> #REF! | U9: =+T9/N9 -> #REF! | V9: =+T9/Q9 -> #REF! | X9: MCPA LAV | Y9: =+Y32+Y55 -> #REF! | Z9: =+Z32+Z55 -> #REF! | AA9: =+AA32+AA55 -> 0 | AB9: =+Z9+AA9 -> #REF! | AC9: =+AC32+AC55 -> #REF! | AD9: =+AD32+AD55 -> #REF! | AE9: =+AC9+AD9 -> #REF! | AF9: =+AE9/Y9 -> #REF! | AG9: =+AE9/AB9 -> #REF!
B10: MCPA SPE | C10: =+C33+C56 -> #REF! | D10: =+D33+D56 -> #REF! | E10: =+E33+E56 -> 0 | F10: =+D10+E10 -> #REF! | G10: =+G33+G56 -> #REF! | H10: =+H33+H56 -> #REF! | I10: =+G10+H10 -> #REF! | J10: =+I10/C10 -> #REF! | K10: =+I10/F10 -> #REF! | M10: MCPA SPE | N10: =+N33+N56 -> #REF! | O10: =+O33+O56 -> #REF! | P10: =+P33+P56 -> 0 | Q10: =+O10+P10 -> #REF! | R10: =+R33+R56 -> #REF! | S10: =+S33+S56 -> #REF! | T10: =+R10+S10 -> #REF! | U10: =+T10/N10 -> #REF! | V10: =+T10/Q10 -> #REF! | X10: MCPA SPE | Y10: =+Y33+Y56 -> #REF! | Z10: =+Z33+Z56 -> #REF! | AA10: =+AA33+AA56 -> 0 | AB10: =+Z10+AA10 -> #REF! | AC10: =+AC33+AC56 -> #REF! | AD10: =+AD33+AD56 -> #REF! | AE10: =+AC10+AD10 -> #REF! | AF10: =+AE10/Y10 -> #REF! | AG10: =+AE10/AB10 -> #REF!
B11: HONDA | C11: =+C34+C57 -> #REF! | D11: =+D34+D57 -> #REF! | E11: =+E34+E57 -> #REF! | F11: =+D11+E11 -> #REF! | G11: =+G34+G57 -> #REF! | H11: =+H34+H57 -> #REF! | I11: =+G11+H11 -> #REF! | J11: =+I11/C11 -> #REF! | K11: =+I11/F11 -> #REF! | M11: HONDA | N11: =+N34+N57 -> #REF! | O11: =+O34+O57 -> #REF! | P11: =+P34+P57 -> #REF! | Q11: =+O11+P11 -> #REF! | R11: =+R34+R57 -> #REF! | S11: =+S34+S57 -> #REF! | T11: =+R11+S11 -> #REF! | U11: =+T11/N11 -> #REF! | V11: =+T11/Q11 -> #REF! | X11: HONDA | Y11: =+Y34+Y57 -> #REF! | Z11: =+Z34+Z57 -> #REF! | AA11: =+AA34+AA57 -> #REF! | AB11: =+Z11+AA11 -> #REF! | AC11: =+AC34+AC57 -> #REF! | AD11: =+AD34+AD57 -> #REF! | AE11: =+AC11+AD11 -> #REF! | AF11: =+AE11/Y11 -> #REF! | AG11: =+AE11/AB11 -> #REF!
B12: TOYOTA | C12: =+C35+C58 -> #REF! | D12: =+D35+D58 -> #REF! | E12: =+E35+E58 -> #REF! | F12: =+D12+E12 -> #REF! | G12: =+G35+G58 -> #REF! | H12: =+H35+H58 -> #REF! | I12: =+G12+H12 -> #REF! | J12: =+I12/C12 -> #REF! | K12: =+I12/F12 -> #REF! | M12: TOYOTA | N12: =+N35+N58 -> #REF! | O12: =+O35+O58 -> #REF! | P12: =+P35+P58 -> #REF! | Q12: =+O12+P12 -> #REF! | R12: =+R35+R58 -> #REF! | S12: =+S35+S58 -> #REF! | T12: =+R12+S12 -> #REF! | U12: =+T12/N12 -> #REF! | V12: =+T12/Q12 -> #REF! | X12: TOYOTA | Y12: =+Y35+Y58 -> #REF! | Z12: =+Z35+Z58 -> #REF! | AA12: =+AA35+AA58 -> #REF! | AB12: =+Z12+AA12 -> #REF! | AC12: =+AC35+AC58 -> #REF! | AD12: =+AD35+AD58 -> #REF! | AE12: =+AC12+AD12 -> #REF! | AF12: =+AE12/Y12 -> #REF! | AG12: =+AE12/AB12 -> #REF!
B13: VOLKS | C13: =+C36+C59 -> #REF! | D13: =+D36+D59 -> #REF! | E13: =+E36+E59 -> #REF! | F13: =+D13+E13 -> #REF! | G13: =+G36+G59 -> #REF! | H13: =+H36+H59 -> #REF! | I13: =+G13+H13 -> #REF! | J13: =+I13/C13 -> #REF! | K13: =+I13/F13 -> #REF! | M13: VOLKS | N13: =+N36+N59 -> #REF! | O13: =+O36+O59 -> #REF! | P13: =+P36+P59 -> #REF! | Q13: =+O13+P13 -> #REF! | R13: =+R36+R59 -> #REF! | S13: =+S36+S59 -> #REF! | T13: =+R13+S13 -> #REF! | U13: =+T13/N13 -> #REF! | V13: =+T13/Q13 -> #REF! | X13: VOLKS | Y13: =+Y36+Y59 -> #REF! | Z13: =+Z36+Z59 -> #REF! | AA13: =+AA36+AA59 -> #REF! | AB13: =+Z13+AA13 -> #REF! | AC13: =+AC36+AC59 -> #REF! | AD13: =+AD36+AD59 -> #REF! | AE13: =+AC13+AD13 -> #REF! | AF13: =+AE13/Y13 -> #REF! | AG13: =+AE13/AB13 -> #REF!
B14: BMW PA | C14: =+C37+C60 -> #REF! | D14: =+D37+D60 -> #REF! | E14: =+E37+E60 -> #REF! | F14: =+D14+E14 -> #REF! | G14: =+G37+G60 -> #REF! | H14: =+H37+H60 -> #REF! | I14: =+G14+H14 -> #REF! | J14: =+I14/C14 -> #REF! | K14: =+I14/F14 -> #REF! | M14: BMW PA | N14: =+N37+N60 -> #REF! | O14: =+O37+O60 -> #REF! | P14: =+P37+P60 -> #REF! | Q14: =+O14+P14 -> #REF! | R14: =+R37+R60 -> #REF! | S14: =+S37+S60 -> #REF! | T14: =+R14+S14 -> #REF! | U14: =+T14/N14 -> #REF! | V14: =+T14/Q14 -> #REF! | X14: BMW PA | Y14: =+Y37+Y60 -> #REF! | Z14: =+Z37+Z60 -> #REF! | AA14: =+AA37+AA60 -> #REF! | AB14: =+Z14+AA14 -> #REF! | AC14: =+AC37+AC60 -> #REF! | AD14: =+AD37+AD60 -> #REF! | AE14: =+AC14+AD14 -> #REF! | AF14: =+AE14/Y14 -> #REF! | AG14: =+AE14/AB14 -> #REF!
B15: MINI | C15: =+C38+C61 -> #REF! | D15: =+D38+D61 -> #REF! | E15: =+E38+E61 -> #REF! | F15: =+D15+E15 -> #REF! | G15: =+G38+G61 -> #REF! | H15: =+H38+H61 -> #REF! | I15: =+G15+H15 -> #REF! | J15: =+I15/C15 -> #REF! | K15: =+I15/F15 -> #REF! | M15: MINI | N15: =+N38+N61 -> #REF! | O15: =+O38+O61 -> #REF! | P15: =+P38+P61 -> #REF! | Q15: =+O15+P15 -> #REF! | R15: =+R38+R61 -> #REF! | S15: =+S38+S61 -> #REF! | T15: =+R15+S15 -> #REF! | U15: =+T15/N15 -> #REF! | V15: =+T15/Q15 -> #REF! | X15: MINI | Y15: =+Y38+Y61 -> #REF! | Z15: =+Z38+Z61 -> #REF! | AA15: =+AA38+AA61 -> #REF! | AB15: =+Z15+AA15 -> #REF! | AC15: =+AC38+AC61 -> #REF! | AD15: =+AD38+AD61 -> #REF! | AE15: =+AC15+AD15 -> #REF! | AF15: =+AE15/Y15 -> #REF! | AG15: =+AE15/AB15 -> #REF!
B16: BMW STJ | C16: =+C39+C62 -> #REF! | D16: =+D39+D62 -> #REF! | E16: =+E39+E62 -> #REF! | F16: =+D16+E16 -> #REF! | G16: =+G39+G62 -> #REF! | H16: =+H39+H62 -> #REF! | I16: =+G16+H16 -> #REF! | J16: =+I16/C16 -> #REF! | K16: =+I16/F16 -> #REF! | M16: BMW STJ | N16: =+N39+N62 -> #REF! | O16: =+O39+O62 -> #REF! | P16: =+P39+P62 -> #REF! | Q16: =+O16+P16 -> #REF! | R16: =+R39+R62 -> #REF! | S16: =+S39+S62 -> #REF! | T16: =+R16+S16 -> #REF! | U16: =+T16/N16 -> #REF! | V16: =+T16/Q16 -> #REF! | X16: BMW STJ | Y16: =+Y39+Y62 -> #REF! | Z16: =+Z39+Z62 -> #REF! | AA16: =+AA39+AA62 -> #REF! | AB16: =+Z16+AA16 -> #REF! | AC16: =+AC39+AC62 -> #REF! | AD16: =+AD39+AD62 -> #REF! | AE16: =+AC16+AD16 -> #REF! | AF16: =+AE16/Y16 -> #REF! | AG16: =+AE16/AB16 -> #REF!
B17: LEXUS | C17: =+C40+C63 -> #REF! | D17: =+D40+D63 -> #REF! | E17: =+E40+E63 -> #REF! | F17: =+D17+E17 -> #REF! | G17: =+G40+G63 -> #REF! | H17: =+H40+H63 -> #REF! | I17: =+G17+H17 -> #REF! | J17: =+I17/C17 -> #REF! | K17: =+I17/F17 -> #REF! | M17: LEXUS | N17: =+N40+N63 -> #REF! | O17: =+O40+O63 -> #REF! | P17: =+P40+P63 -> #REF! | Q17: =+O17+P17 -> #REF! | R17: =+R40+R63 -> #REF! | S17: =+S40+S63 -> #REF! | T17: =+R17+S17 -> #REF! | U17: =+T17/N17 -> #REF! | V17: =+T17/Q17 -> #REF! | X17: LEXUS | Y17: =+Y40+Y63 -> #REF! | Z17: =+Z40+Z63 -> #REF! | AA17: =+AA40+AA63 -> #REF! | AB17: =+Z17+AA17 -> #REF! | AC17: =+AC40+AC63 -> #REF! | AD17: =+AD40+AD63 -> #REF! | AE17: =+AC17+AD17 -> #REF! | AF17: =+AE17/Y17 -> #REF! | AG17: =+AE17/AB17 -> #REF!
... B23: LHD | C23: =+C46+C69 -> #REF! | D23: =+D46+D69 -> #REF! | E23: =+E46+E69 -> #REF! | F23: =+D23+E23 -> #REF! | G23: =+G46+G69 -> #REF! | H23: =+H46+H69 -> #REF! | I23: =+G23+H23 -> #REF! | J23: =+I23/C23 -> #REF! | K23: =+I23/F23 -> #REF! | M23: LHD | N23: =+N46+N69 -> #REF! | O23: =+O46+O69 -> #REF! | P23: =+P46+P69 -> #REF! | Q23: =+O23+P23 -> #REF! | R23: =+R46+R69 -> #REF! | S23: =+S46+S69 -> #REF! | T23: =+R23+S23 -> #REF! | U23: =+T23/N23 -> #REF! | V23: =+T23/Q23 -> #REF! | X23: LHD | Y23: =+Y46+Y69 -> #REF! | Z23: =+Z46+Z69 -> #REF! | AA23: =+AA46+AA69 -> #REF! | AB23: =+Z23+AA23 -> #REF! | AC23: =+AC46+AC69 -> #REF! | AD23: =+AD46+AD69 -> #REF! | AE23: =+AC23+AD23 -> #REF! | AF23: =+AE23/Y23 -> #REF! | AG23: =+AE23/AB23 -> #REF!
B25: Delivery Fee New
B26: =B3 -> #REF! | M26: BUDGET | X26: 2019
B27: STORE | C27: Units | D27: Margin | E27: Margin demo | F27: Front margin | G27: frais de livraison | H27: Ent. Stock | I27: Delivery fee | J27: Delivery fee / unit | K27: % Delivery fee / Front margin | M27: STORE | N27: Units | O27: M. new | P27: M. Demos | Q27: Front margin | R27: frais de livraison | S27: Ent. Stock | T27: Delivery fee | U27: Delivery fee / unit | V27: % Delivery fee / Front margin | X27: STORE | Y27: Units | Z27: M. used | AB27: Front margin | AC27: frais de livraison | AD27: Ent. Stock | AE27: Delivery fee | AF27: Delivery fee / unit | AG27: % Delivery fee / Front margin
B28: TOTAL | C28: =+SUM(C29:C46) -> #REF! | D28: =+SUM(D29:D46) -> #REF! | E28: =+SUM(E29:E46) -> #REF! | F28: =+SUM(F29:F46) -> #REF! | G28: =+SUM(G29:G46) -> #REF! | H28: =+SUM(H29:H46) -> #REF! | I28: =+SUM(I29:I46) -> #REF! | J28: =+I28/C28 -> #REF! | K28: =+I28/F28 -> #REF! | M28: TOTAL | N28: =+SUM(N29:N46) -> #REF! | O28: =+SUM(O29:O46) -> #REF! | P28: =+SUM(P29:P46) -> #REF! | Q28: =+SUM(Q29:Q46) -> #REF! | R28: =+SUM(R29:R46) -> #REF! | S28: =+SUM(S29:S46) -> #REF! | T28: =+SUM(T29:T46) -> #REF! | U28: =+T28/N28 -> #REF! | V28: =+T28/Q28 -> #REF! | X28: TOTAL | Y28: =+SUM(Y29:Y46) -> #REF! | Z28: =+SUM(Z29:Z46) -> #REF! | AA28: =+SUM(AA29:AA46) -> #REF! | AB28: =+SUM(AB29:AB46) -> #REF! | AC28: =+SUM(AC29:AC46) -> #REF! | AD28: =+SUM(AD29:AD46) -> #REF! | AE28: =+SUM(AE29:AE46) -> #REF! | AF28: =+AE28/Y28 -> #REF! | AG28: =+AE28/AB28 -> #REF!
B29: AUDI | C29: =+#REF! -> #REF! | D29: =+#REF! -> #REF! | E29: =+#REF! -> #REF! | F29: =+D29+E29 -> #REF! | G29: =+#REF! -> #REF! | H29: =+#REF! -> #REF! | I29: =+G29+H29 -> #REF! | J29: =+I29/C29 -> #REF! | K29: =+I29/F29 -> #REF! | M29: AUDI | N29: =+#REF! -> #REF! | O29: =+#REF! -> #REF! | P29: =+#REF! -> #REF! | Q29: =+O29+P29 -> #REF! | R29: =+#REF! -> #REF! | S29: =+#REF! -> #REF! | T29: =+R29+S29 -> #REF! | U29: =+T29/N29 -> #REF! | V29: =+T29/Q29 -> #REF! | X29: AUDI | Y29: =+#REF! -> #REF! | Z29: =+#REF! -> #REF! | AA29: =+#REF! -> #REF! | AB29: =+Z29+AA29 -> #REF! | AC29: =+#REF! -> #REF! | AD29: =+#REF! -> #REF! | AE29: =+AC29+AD29 -> #REF! | AF29: =+AE29/Y29 -> #REF! | AG29: =+AE29/AB29 -> #REF!
B30: INFINITI | C30: =+#REF! -> #REF! | D30: =+#REF! -> #REF! | E30: =+#REF! -> #REF! | F30: =+D30+E30 -> #REF! | G30: =+#REF! -> #REF! | H30: =+#REF! -> #REF! | I30: =+G30+H30 -> #REF! | J30: =+I30/C30 -> #REF! | K30: =+I30/F30 -> #REF! | M30: INFINITI | N30: =+#REF! -> #REF! | O30: =+#REF! -> #REF! | P30: =+#REF! -> #REF! | Q30: =+O30+P30 -> #REF! | R30: =+#REF! -> #REF! | S30: =+#REF! -> #REF! | T30: =+R30+S30 -> #REF! | U30: =+T30/N30 -> #REF! | V30: =+T30/Q30 -> #REF! | X30: INFINITI | Y30: =+#REF! -> #REF! | Z30: =+#REF! -> #REF! | AA30: =+#REF! -> #REF! | AB30: =+Z30+AA30 -> #REF! | AC30: =+#REF! -> #REF! | AD30: =+#REF! -> #REF! | AE30: =+AC30+AD30 -> #REF! | AF30: =+AE30/Y30 -> #REF! | AG30: =+AE30/AB30 -> #REF!
B34: HONDA | C34: =+#REF! -> #REF! | D34: =+#REF! -> #REF! | E34: =+#REF! -> #REF! | F34: =+D34+E34 -> #REF! | G34: =+#REF! -> #REF! | H34: =+#REF! -> #REF! | I34: =+G34+H34 -> #REF! | J34: =+I34/C34 -> #REF! | K34: =+I34/F34 -> #REF! | M34: HONDA | N34: =+#REF! -> #REF! | O34: =+#REF! -> #REF! | P34: =+#REF! -> #REF! | Q34: =+O34+P34 -> #REF! | R34: =+#REF! -> #REF! | S34: =+#REF! -> #REF! | T34: =+R34+S34 -> #REF! | U34: =+T34/N34 -> #REF! | V34: =+T34/Q34 -> #REF! | X34: HONDA | Y34: =+#REF! -> #REF! | Z34: =+#REF! -> #REF! | AA34: =+#REF! -> #REF! | AB34: =+Z34+AA34 -> #REF! | AC34: =+#REF! -> #REF! | AD34: =+#REF! -> #REF! | AE34: =+AC34+AD34 -> #REF! | AF34: =+AE34/Y34 -> #REF! | AG34: =+AE34/AB34 -> #REF!
B35: TOYOTA | C35: =+#REF! -> #REF! | D35: =+#REF! -> #REF! | E35: =+#REF! -> #REF! | F35: =+D35+E35 -> #REF! | G35: =+#REF! -> #REF! | H35: =+#REF! -> #REF! | I35: =+G35+H35 -> #REF! | J35: =+I35/C35 -> #REF! | K35: =+I35/F35 -> #REF! | M35: TOYOTA | N35: =+#REF! -> #REF! | O35: =+#REF! -> #REF! | P35: =+#REF! -> #REF! | Q35: =+O35+P35 -> #REF! | R35: =+#REF! -> #REF! | S35: =+#REF! -> #REF! | T35: =+R35+S35 -> #REF! | U35: =+T35/N35 -> #REF! | V35: =+T35/Q35 -> #REF! | X35: TOYOTA | Y35: =+#REF! -> #REF! | Z35: =+#REF! -> #REF! | AA35: =+#REF! -> #REF! | AB35: =+Z35+AA35 -> #REF! | AC35: =+#REF! -> #REF! | AD35: =+#REF! -> #REF! | AE35: =+AC35+AD35 -> #REF! | AF35: =+AE35/Y35 -> #REF! | AG35: =+AE35/AB35 -> #REF!
B36: VOLKS | C36: =+#REF! -> #REF! | D36: =+#REF! -> #REF! | E36: =+#REF! -> #REF! | F36: =+D36+E36 -> #REF! | G36: =+#REF! -> #REF! | H36: =+#REF! -> #REF! | I36: =+G36+H36 -> #REF! | J36: =+I36/C36 -> #REF! | K36: =+I36/F36 -> #REF! | M36: VOLKS | N36: =+#REF! -> #REF! | O36: =+#REF! -> #REF! | P36: =+#REF! -> #REF! | Q36: =+O36+P36 -> #REF! | R36: =+#REF! -> #REF! | S36: =+#REF! -> #REF! | T36: =+R36+S36 -> #REF! | U36: =+T36/N36 -> #REF! | V36: =+T36/Q36 -> #REF! | X36: VOLKS | Y36: =+#REF! -> #REF! | Z36: =+#REF! -> #REF! | AA36: =+#REF! -> #REF! | AB36: =+Z36+AA36 -> #REF! | AC36: =+#REF! -> #REF! | AD36: =+#REF! -> #REF! | AE36: =+AC36+AD36 -> #REF! | AF36: =+AE36/Y36 -> #REF! | AG36: =+AE36/AB36 -> #REF!
B37: BMW PA | C37: =+#REF! -> #REF! | D37: =+#REF! -> #REF! | E37: =+#REF! -> #REF! | F37: =+D37+E37 -> #REF! | G37: =+#REF! -> #REF! | H37: =+#REF! -> #REF! | I37: =+G37+H37 -> #REF! | J37: =+I37/C37 -> #REF! | K37: =+I37/F37 -> #REF! | M37: BMW PA | N37: =+#REF! -> #REF! | O37: =+#REF! -> #REF! | P37: =+#REF! -> #REF! | Q37: =+O37+P37 -> #REF! | R37: =+#REF! -> #REF! | S37: =+#REF! -> #REF! | T37: =+R37+S37 -> #REF! | U37: =+T37/N37 -> #REF! | V37: =+T37/Q37 -> #REF! | X37: BMW PA | Y37: =+#REF! -> #REF! | Z37: =+#REF! -> #REF! | AA37: =+#REF! -> #REF! | AB37: =+Z37+AA37 -> #REF! | AC37: =+#REF! -> #REF! | AD37: =+#REF! -> #REF! | AE37: =+AC37+AD37 -> #REF! | AF37: =+AE37/Y37 -> #REF! | AG37: =+AE37/AB37 -> #REF!
B38: MINI | C38: =+#REF! -> #REF! | D38: =+#REF! -> #REF! | E38: =+#REF! -> #REF! | F38: =+D38+E38 -> #REF! | G38: =+#REF! -> #REF! | H38: =+#REF! -> #REF! | I38: =+G38+H38 -> #REF! | J38: =+I38/C38 -> #REF! | K38: =+I38/F38 -> #REF! | M38: MINI | N38: =+#REF! -> #REF! | O38: =+#REF! -> #REF! | P38: =+#REF! -> #REF! | Q38: =+O38+P38 -> #REF! | R38: =+#REF! -> #REF! | S38: =+#REF! -> #REF! | T38: =+R38+S38 -> #REF! | U38: =+T38/N38 -> #REF! | V38: =+T38/Q38 -> #REF! | X38: MINI | Y38: =+#REF! -> #REF! | Z38: =+#REF! -> #REF! | AA38: =+#REF! -> #REF! | AB38: =+Z38+AA38 -> #REF! | AC38: =+#REF! -> #REF! | AD38: =+#REF! -> #REF! | AE38: =+AC38+AD38 -> #REF! | AF38: =+AE38/Y38 -> #REF! | AG38: =+AE38/AB38 -> #REF!
B39: BMW STJ | C39: =+#REF! -> #REF! | D39: =+#REF! -> #REF! | E39: =+#REF! -> #REF! | F39: =+D39+E39 -> #REF! | G39: =+#REF! -> #REF! | H39: =+#REF! -> #REF! | I39: =+G39+H39 -> #REF! | J39: =+I39/C39 -> #REF! | K39: =+I39/F39 -> #REF! | M39: BMW STJ | N39: =+#REF! -> #REF! | O39: =+#REF! -> #REF! | P39: =+#REF! -> #REF! | Q39: =+O39+P39 -> #REF! | R39: =+#REF! -> #REF! | S39: =+#REF! -> #REF! | T39: =+R39+S39 -> #REF! | U39: =+T39/N39 -> #REF! | V39: =+T39/Q39 -> #REF! | X39: BMW STJ | Y39: =+#REF! -> #REF! | Z39: =+#REF! -> #REF! | AA39: =+#REF! -> #REF! | AB39: =+Z39+AA39 -> #REF! | AC39: =+#REF! -> #REF! | AD39: =+#REF! -> #REF! | AE39: =+AC39+AD39 -> #REF! | AF39: =+AE39/Y39 -> #REF! | AG39: =+AE39/AB39 -> #REF!
B40: LEXUS | C40: =+#REF! -> #REF! | D40: =+#REF! -> #REF! | E40: =+#REF! -> #REF! | F40: =+D40+E40 -> #REF! | G40: =+#REF! -> #REF! | H40: =+#REF! -> #REF! | I40: =+G40+H40 -> #REF! | J40: =+I40/C40 -> #REF! | K40: =+I40/F40 -> #REF! | M40: LEXUS | N40: =+#REF! -> #REF! | O40: =+#REF! -> #REF! | P40: =+#REF! -> #REF! | Q40: =+O40+P40 -> #REF! | R40: =+#REF! -> #REF! | S40: =+#REF! -> #REF! | T40: =+R40+S40 -> #REF! | U40: =+T40/N40 -> #REF! | V40: =+T40/Q40 -> #REF! | X40: LEXUS | Y40: =+#REF! -> #REF! | Z40: =+#REF! -> #REF! | AA40: =+#REF! -> #REF! | AB40: =+Z40+AA40 -> #REF! | AC40: =+#REF! -> #REF! | AD40: =+#REF! -> #REF! | AE40: =+AC40+AD40 -> #REF! | AF40: =+AE40/Y40 -> #REF! | AG40: =+AE40/AB40 -> #REF!
B41: BMW SHER | C41: =+#REF! -> #REF! | D41: =+#REF! -> #REF! | E41: =+#REF! -> #REF! | F41: =+D41+E41 -> #REF! | G41: =+#REF! -> #REF! | H41: =+#REF! -> #REF! | I41: =+G41+H41 -> #REF! | J41: =+I41/C41 -> #REF! | K41: =+I41/F41 -> #REF! | M41: BMW SHER | N41: =+#REF! -> #REF! | O41: =+#REF! -> #REF! | P41: =+#REF! -> #REF! | Q41: =+O41+P41 -> #REF! | R41: =+#REF! -> #REF! | S41: =+#REF! -> #REF! | T41: =+R41+S41 -> #REF! | U41: =+T41/N41 -> #REF! | V41: =+T41/Q41 -> #REF! | X41: BMW SHER | Y41: =+#REF! -> #REF! | Z41: =+#REF! -> #REF! | AA41: =+#REF! -> #REF! | AB41: =+Z41+AA41 -> #REF! | AC41: =+#REF! -> #REF! | AD41: =+#REF! -> #REF! | AE41: =+AC41+AD41 -> #REF! | AF41: =+AE41/Y41 -> #REF! | AG41: =+AE41/AB41 -> #REF!
B42: SSMB | C42: =+#REF! -> #REF! | D42: =+#REF! -> #REF! | E42: =+#REF! -> #REF! | F42: =+D42+E42 -> #REF! | G42: =+#REF! -> #REF! | H42: =+#REF! -> #REF! | I42: =+G42+H42 -> #REF! | J42: =+I42/C42 -> #REF! | K42: =+I42/F42 -> #REF! | M42: SSMB | N42: =+#REF! -> #REF! | O42: =+#REF! -> #REF! | P42: =+#REF! -> #REF! | Q42: =+O42+P42 -> #REF! | R42: =+#REF! -> #REF! | S42: =+#REF! -> #REF! | T42: =+R42+S42 -> #REF! | U42: =+T42/N42 -> #REF! | V42: =+T42/Q42 -> #REF! | X42: SSMB | Y42: =+#REF! -> #REF! | Z42: =+#REF! -> #REF! | AA42: =+#REF! -> #REF! | AB42: =+Z42+AA42 -> #REF! | AC42: =+#REF! -> #REF! | AD42: =+#REF! -> #REF! | AE42: =+AC42+AD42 -> #REF! | AF42: =+AE42/Y42 -> #REF! | AG42: =+AE42/AB42 -> #REF!
B43: MBQ | C43: =+#REF! -> #REF! | D43: =+#REF! -> #REF! | E43: =+#REF! -> #REF! | F43: =+D43+E43 -> #REF! | G43: =+#REF! -> #REF! | H43: =+#REF! -> #REF! | I43: =+G43+H43 -> #REF! | J43: =+I43/C43 -> #REF! | K43: =+I43/F43 -> #REF! | M43: MBQ | N43: =+#REF! -> #REF! | O43: =+#REF! -> #REF! | P43: =+#REF! -> #REF! | Q43: =+O43+P43 -> #REF! | R43: =+#REF! -> #REF! | S43: =+#REF! -> #REF! | T43: =+R43+S43 -> #REF! | U43: =+T43/N43 -> #REF! | V43: =+T43/Q43 -> #REF! | X43: MBQ | Y43: =+#REF! -> #REF! | Z43: =+#REF! -> #REF! | AA43: =+#REF! -> #REF! | AB43: =+Z43+AA43 -> #REF! | AC43: =+#REF! -> #REF! | AD43: =+#REF! -> #REF! | AE43: =+AC43+AD43 -> #REF! | AF43: =+AE43/Y43 -> #REF! | AG43: =+AE43/AB43 -> #REF!
... B46: LHD | C46: =+#REF! -> #REF! | D46: =+#REF! -> #REF! | E46: =+#REF! -> #REF! | F46: =+D46+E46 -> #REF! | G46: =+#REF! -> #REF! | H46: =+#REF! -> #REF! | I46: =+G46+H46 -> #REF! | J46: =+I46/C46 -> #REF! | K46: =+I46/F46 -> #REF! | M46: LHD | N46: =+#REF! -> #REF! | O46: =+#REF! -> #REF! | P46: =+#REF! -> #REF! | Q46: =+O46+P46 -> #REF! | R46: =+#REF! -> #REF! | S46: =+#REF! -> #REF! | T46: =+R46+S46 -> #REF! | U46: =+T46/N46 -> #REF! | V46: =+T46/Q46 -> #REF! | X46: LHD | Y46: =+#REF! -> #REF! | Z46: =+#REF! -> #REF! | AA46: =+#REF! -> #REF! | AB46: =+Z46+AA46 -> #REF! | AC46: =+#REF! -> #REF! | AD46: =+#REF! -> #REF! | AE46: =+AC46+AD46 -> #REF! | AF46: =+AE46/Y46 -> #REF! | AG46: =+AE46/AB46 -> #REF!
B48: Delivery Fee Used
B49: =B26 -> #REF! | M49: BUDGET | X49: 2019
B50: STORE | C50: Units | D50: Margin | E50: Margin demo | F50: Front margin | G50: frais de livraison | H50: Ent. Stock | I50: Delivery fee | J50: Delivery fee / unit | K50: % Delivery fee / Front margin | M50: STORE | N50: Units | O50: M. new | P50: M. Demos | Q50: Front margin | R50: frais de livraison | S50: Ent. Stock | T50: Delivery fee | U50: Delivery fee / unit | V50: % Delivery fee / Front margin | X50: STORE | Y50: Units | Z50: M. used | AB50: Front margin | AC50: frais de livraison | AD50: Ent. Stock | AE50: Delivery fee | AF50: Delivery fee / unit | AG50: % Delivery fee / Front margin
B51: TOTAL | C51: =+SUM(C52:C69) -> #REF! | D51: =+SUM(D52:D69) -> #REF! | F51: =+SUM(F52:F69) -> #REF! | G51: =+SUM(G52:G69) -> #REF! | H51: =+SUM(H52:H69) -> #REF! | I51: =+SUM(I52:I69) -> #REF! | J51: =+I51/C51 -> #REF! | K51: =+I51/F51 -> #REF! | M51: TOTAL | N51: =+SUM(N52:N69) -> #REF! | O51: =+SUM(O52:O69) -> #REF! | Q51: =+SUM(Q52:Q69) -> #REF! | R51: =+SUM(R52:R69) -> #REF! | S51: =+SUM(S52:S69) -> #REF! | T51: =+SUM(T52:T69) -> #REF! | U51: =+T51/N51 -> #REF! | V51: =+T51/Q51 -> #REF! | X51: TOTAL | Y51: =+SUM(Y52:Y69) -> #REF! | Z51: =+SUM(Z52:Z69) -> #REF! | AB51: =+SUM(AB52:AB69) -> #REF! | AC51: =+SUM(AC52:AC69) -> #REF! | AD51: =+SUM(AD52:AD69) -> #REF! | AE51: =+SUM(AE52:AE69) -> #REF! | AF51: =+AE51/Y51 -> #REF! | AG51: =+AE51/AB51 -> #REF!
B52: AUDI | C52: =+#REF! -> #REF! | D52: =+#REF! -> #REF! | F52: =+D52+E52 -> #REF! | G52: =+#REF! -> #REF! | H52: =+#REF! -> #REF! | I52: =+G52+H52 -> #REF! | J52: =+I52/C52 -> #REF! | K52: =+I52/F52 -> #REF! | M52: AUDI | N52: =+#REF! -> #REF! | O52: =+#REF! -> #REF! | Q52: =+O52+P52 -> #REF! | R52: =+#REF! -> #REF! | S52: =+#REF! -> #REF! | T52: =+R52+S52 -> #REF! | U52: =+T52/N52 -> #REF! | V52: =+T52/Q52 -> #REF! | X52: AUDI | Y52: =+#REF! -> #REF! | Z52: =+#REF! -> #REF! | AB52: =+Z52+AA52 -> #REF! | AC52: =+#REF! -> #REF! | AD52: =+#REF! -> #REF! | AE52: =+AC52+AD52 -> #REF! | AF52: =+AE52/Y52 -> #REF! | AG52: =+AE52/AB52 -> #REF!
B53: INFINITI | C53: =+#REF! -> #REF! | D53: =+#REF! -> #REF! | F53: =+D53+E53 -> #REF! | G53: =+#REF! -> #REF! | H53: =+#REF! -> #REF! | I53: =+G53+H53 -> #REF! | J53: =+I53/C53 -> #REF! | K53: =+I53/F53 -> #REF! | M53: INFINITI | N53: =+#REF! -> #REF! | O53: =+#REF! -> #REF! | Q53: =+O53+P53 -> #REF! | R53: =+#REF! -> #REF! | S53: =+#REF! -> #REF! | T53: =+R53+S53 -> #REF! | U53: =+T53/N53 -> #REF! | V53: =+T53/Q53 -> #REF! | X53: INFINITI | Y53: =+#REF! -> #REF! | Z53: =+#REF! -> #REF! | AB53: =+Z53+AA53 -> #REF! | AC53: =+#REF! -> #REF! | AD53: =+#REF! -> #REF! | AE53: =+AC53+AD53 -> #REF! | AF53: =+AE53/Y53 -> #REF! | AG53: =+AE53/AB53 -> #REF!
B54: MCPA LAP | C54: =+#REF! -> #REF! | D54: =+#REF! -> #REF! | F54: =+D54+E54 -> #REF! | G54: =+#REF! -> #REF! | H54: =+#REF! -> #REF! | I54: =+G54+H54 -> #REF! | J54: =+I54/C54 -> #REF! | K54: =+I54/F54 -> #REF! | M54: MCPA LAP | N54: =+#REF! -> #REF! | O54: =+#REF! -> #REF! | Q54: =+O54+P54 -> #REF! | R54: =+#REF! -> #REF! | S54: =+#REF! -> #REF! | T54: =+R54+S54 -> #REF! | U54: =+T54/N54 -> #REF! | V54: =+T54/Q54 -> #REF! | X54: MCPA LAP | Y54: =+#REF! -> #REF! | Z54: =+#REF! -> #REF! | AB54: =+Z54+AA54 -> #REF! | AC54: =+#REF! -> #REF! | AD54: =+#REF! -> #REF! | AE54: =+AC54+AD54 -> #REF! | AF54: =+AE54/Y54 -> #REF! | AG54: =+AE54/AB54 -> #REF!
B55: MCPA LAV | C55: =+#REF! -> #REF! | D55: =+#REF! -> #REF! | F55: =+D55+E55 -> #REF! | G55: =+#REF! -> #REF! | H55: =+#REF! -> #REF! | I55: =+G55+H55 -> #REF! | J55: =+I55/C55 -> #REF! | K55: =+I55/F55 -> #REF! | M55: MCPA LAV | N55: =+#REF! -> #REF! | O55: =+#REF! -> #REF! | Q55: =+O55+P55 -> #REF! | R55: =+#REF! -> #REF! | S55: =+#REF! -> #REF! | T55: =+R55+S55 -> #REF! | U55: =+T55/N55 -> #REF! | V55: =+T55/Q55 -> #REF! | X55: MCPA LAV | Y55: =+#REF! -> #REF! | Z55: =+#REF! -> #REF! | AB55: =+Z55+AA55 -> #REF! | AC55: =+#REF! -> #REF! | AD55: =+#REF! -> #REF! | AE55: =+AC55+AD55 -> #REF! | AF55: =+AE55/Y55 -> #REF! | AG55: =+AE55/AB55 -> #REF!
B56: MCPA SPE | C56: =+#REF! -> #REF! | D56: =+#REF! -> #REF! | F56: =+D56+E56 -> #REF! | G56: =+#REF! -> #REF! | H56: =+#REF! -> #REF! | I56: =+G56+H56 -> #REF! | J56: =+I56/C56 -> #REF! | K56: =+I56/F56 -> #REF! | M56: MCPA SPE | N56: =+#REF! -> #REF! | O56: =+#REF! -> #REF! | Q56: =+O56+P56 -> #REF! | R56: =+#REF! -> #REF! | S56: =+#REF! -> #REF! | T56: =+R56+S56 -> #REF! | U56: =+T56/N56 -> #REF! | V56: =+T56/Q56 -> #REF! | X56: MCPA SPE | Y56: =+#REF! -> #REF! | Z56: =+#REF! -> #REF! | AB56: =+Z56+AA56 -> #REF! | AC56: =+#REF! -> #REF! | AD56: =+#REF! -> #REF! | AE56: =+AC56+AD56 -> #REF! | AF56: =+AE56/Y56 -> #REF! | AG56: =+AE56/AB56 -> #REF!
B57: HONDA | C57: =+#REF! -> #REF! | D57: =+#REF! -> #REF! | F57: =+D57+E57 -> #REF! | G57: =+#REF! -> #REF! | H57: =+#REF! -> #REF! | I57: =+G57+H57 -> #REF! | J57: =+I57/C57 -> #REF! | K57: =+I57/F57 -> #REF! | M57: HONDA | N57: =+#REF! -> #REF! | O57: =+#REF! -> #REF! | Q57: =+O57+P57 -> #REF! | R57: =+#REF! -> #REF! | S57: =+#REF! -> #REF! | T57: =+R57+S57 -> #REF! | U57: =+T57/N57 -> #REF! | V57: =+T57/Q57 -> #REF! | X57: HONDA | Y57: =+#REF! -> #REF! | Z57: =+#REF! -> #REF! | AB57: =+Z57+AA57 -> #REF! | AC57: =+#REF! -> #REF! | AD57: =+#REF! -> #REF! | AE57: =+AC57+AD57 -> #REF! | AF57: =+AE57/Y57 -> #REF! | AG57: =+AE57/AB57 -> #REF!
B58: TOYOTA | C58: =+#REF! -> #REF! | D58: =+#REF! -> #REF! | F58: =+D58+E58 -> #REF! | G58: =+#REF! -> #REF! | H58: =+#REF! -> #REF! | I58: =+G58+H58 -> #REF! | J58: =+I58/C58 -> #REF! | K58: =+I58/F58 -> #REF! | M58: TOYOTA | N58: =+#REF! -> #REF! | O58: =+#REF! -> #REF! | Q58: =+O58+P58 -> #REF! | R58: =+#REF! -> #REF! | S58: =+#REF! -> #REF! | T58: =+R58+S58 -> #REF! | U58: =+T58/N58 -> #REF! | V58: =+T58/Q58 -> #REF! | X58: TOYOTA | Y58: =+#REF! -> #REF! | Z58: =+#REF! -> #REF! | AB58: =+Z58+AA58 -> #REF! | AC58: =+#REF! -> #REF! | AD58: =+#REF! -> #REF! | AE58: =+AC58+AD58 -> #REF! | AF58: =+AE58/Y58 -> #REF! | AG58: =+AE58/AB58 -> #REF!
B59: VOLKS | C59: =+#REF! -> #REF! | D59: =+#REF! -> #REF! | F59: =+D59+E59 -> #REF! | G59: =+#REF! -> #REF! | H59: =+#REF! -> #REF! | I59: =+G59+H59 -> #REF! | J59: =+I59/C59 -> #REF! | K59: =+I59/F59 -> #REF! | M59: VOLKS | N59: =+#REF! -> #REF! | O59: =+#REF! -> #REF! | Q59: =+O59+P59 -> #REF! | R59: =+#REF! -> #REF! | S59: =+#REF! -> #REF! | T59: =+R59+S59 -> #REF! | U59: =+T59/N59 -> #REF! | V59: =+T59/Q59 -> #REF! | X59: VOLKS | Y59: =+#REF! -> #REF! | Z59: =+#REF! -> #REF! | AB59: =+Z59+AA59 -> #REF! | AC59: =+#REF! -> #REF! | AD59: =+#REF! -> #REF! | AE59: =+AC59+AD59 -> #REF! | AF59: =+AE59/Y59 -> #REF! | AG59: =+AE59/AB59 -> #REF!
B60: BMW PA | C60: =+#REF! -> #REF! | D60: =+#REF! -> #REF! | F60: =+D60+E60 -> #REF! | G60: =+#REF! -> #REF! | H60: =+#REF! -> #REF! | I60: =+G60+H60 -> #REF! | J60: =+I60/C60 -> #REF! | K60: =+I60/F60 -> #REF! | M60: BMW PA | N60: =+#REF! -> #REF! | O60: =+#REF! -> #REF! | Q60: =+O60+P60 -> #REF! | R60: =+#REF! -> #REF! | S60: =+#REF! -> #REF! | T60: =+R60+S60 -> #REF! | U60: =+T60/N60 -> #REF! | V60: =+T60/Q60 -> #REF! | X60: BMW PA | Y60: =+#REF! -> #REF! | Z60: =+#REF! -> #REF! | AB60: =+Z60+AA60 -> #REF! | AC60: =+#REF! -> #REF! | AD60: =+#REF! -> #REF! | AE60: =+AC60+AD60 -> #REF! | AF60: =+AE60/Y60 -> #REF! | AG60: =+AE60/AB60 -> #REF!
B61: MINI | C61: =+#REF! -> #REF! | D61: =+#REF! -> #REF! | F61: =+D61+E61 -> #REF! | G61: =+#REF! -> #REF! | H61: =+#REF! -> #REF! | I61: =+G61+H61 -> #REF! | J61: =+I61/C61 -> #REF! | K61: =+I61/F61 -> #REF! | M61: MINI | N61: =+#REF! -> #REF! | O61: =+#REF! -> #REF! | Q61: =+O61+P61 -> #REF! | R61: =+#REF! -> #REF! | S61: =+#REF! -> #REF! | T61: =+R61+S61 -> #REF! | U61: =+T61/N61 -> #REF! | V61: =+T61/Q61 -> #REF! | X61: MINI | Y61: =+#REF! -> #REF! | Z61: =+#REF! -> #REF! | AB61: =+Z61+AA61 -> #REF! | AC61: =+#REF! -> #REF! | AD61: =+#REF! -> #REF! | AE61: =+AC61+AD61 -> #REF! | AF61: =+AE61/Y61 -> #REF! | AG61: =+AE61/AB61 -> #REF!
B62: BMW STJ | C62: =+#REF! -> #REF! | D62: =+#REF! -> #REF! | F62: =+D62+E62 -> #REF! | G62: =+#REF! -> #REF! | H62: =+#REF! -> #REF! | I62: =+G62+H62 -> #REF! | J62: =+I62/C62 -> #REF! | K62: =+I62/F62 -> #REF! | M62: BMW STJ | N62: =+#REF! -> #REF! | O62: =+#REF! -> #REF! | Q62: =+O62+P62 -> #REF! | R62: =+#REF! -> #REF! | S62: =+#REF! -> #REF! | T62: =+R62+S62 -> #REF! | U62: =+T62/N62 -> #REF! | V62: =+T62/Q62 -> #REF! | X62: BMW STJ | Y62: =+#REF! -> #REF! | Z62: =+#REF! -> #REF! | AB62: =+Z62+AA62 -> #REF! | AC62: =+#REF! -> #REF! | AD62: =+#REF! -> #REF! | AE62: =+AC62+AD62 -> #REF! | AF62: =+AE62/Y62 -> #REF! | AG62: =+AE62/AB62 -> #REF!
B63: LEXUS | C63: =+#REF! -> #REF! | D63: =+#REF! -> #REF! | F63: =+D63+E63 -> #REF! | G63: =+#REF! -> #REF! | H63: =+#REF! -> #REF! | I63: =+G63+H63 -> #REF! | J63: =+I63/C63 -> #REF! | K63: =+I63/F63 -> #REF! | M63: LEXUS | N63: =+#REF! -> #REF! | O63: =+#REF! -> #REF! | Q63: =+O63+P63 -> #REF! | R63: =+#REF! -> #REF! | S63: =+#REF! -> #REF! | T63: =+R63+S63 -> #REF! | U63: =+T63/N63 -> #REF! | V63: =+T63/Q63 -> #REF! | X63: LEXUS | Y63: =+#REF! -> #REF! | Z63: =+#REF! -> #REF! | AB63: =+Z63+AA63 -> #REF! | AC63: =+#REF! -> #REF! | AD63: =+#REF! -> #REF! | AE63: =+AC63+AD63 -> #REF! | AF63: =+AE63/Y63 -> #REF! | AG63: =+AE63/AB63 -> #REF!
... B69: LHD | C69: =+#REF! -> #REF! | D69: =+#REF! -> #REF! | F69: =+D69+E69 -> #REF! | G69: =+#REF! -> #REF! | H69: =+#REF! -> #REF! | I69: =+G69+H69 -> #REF! | J69: =+I69/C69 -> #REF! | K69: =+I69/F69 -> #REF! | M69: LHD | N69: =+#REF! -> #REF! | O69: =+#REF! -> #REF! | Q69: =+O69+P69 -> #REF! | R69: =+#REF! -> #REF! | S69: =+#REF! -> #REF! | T69: =+R69+S69 -> #REF! | U69: =+T69/N69 -> #REF! | V69: =+T69/Q69 -> #REF! | X69: LHD | Y69: =+#REF! -> #REF! | Z69: =+#REF! -> #REF! | AB69: =+Z69+AA69 -> #REF! | AC69: =+#REF! -> #REF! | AD69: =+#REF! -> #REF! | AE69: =+AC69+AD69 -> #REF! | AF69: =+AE69/Y69 -> #REF! | AG69: =+AE69/AB69 -> #REF!

Sheet RECAP v1
B1: Delivery Fee NEW + USED | M1: Delivery Fee New | X1: Delivery Fee used
B3: ='RECAP v2'!B3:K3 -> #REF! | M3: =B3 -> #REF! | X3: =M3 -> #REF!
B4: STORE | C4: Units | D4: Margin | E4: Margin demo | F4: Front margin | G4: frais de livraison | H4: Ent. Stock | I4: Delivery fee | J4: Delivery fee / unit | K4: % Delivery fee / Front margin | M4: STORE | N4: Units | O4: M. new | P4: M. Demos | Q4: Front margin | R4: frais de livraison | S4: Ent. Stock | T4: Delivery fee | U4: Delivery fee / unit | V4: % Delivery fee / Front margin | X4: STORE | Y4: Units | Z4: M. used | AB4: Front margin | AC4: frais de livraison | AD4: Ent. Stock | AE4: Delivery fee | AF4: Delivery fee / unit | AG4: % Delivery fee / Front margin
B5: TOTAL | C5: =+SUM(C6:C23) -> #REF! | D5: =+SUM(D6:D23) -> #REF! | E5: =+SUM(E6:E23) -> #REF! | F5: =+SUM(F6:F23) -> #REF! | G5: =+SUM(G6:G23) -> #REF! | H5: =+SUM(H6:H23) -> #REF! | I5: =+SUM(I6:I23) -> #REF! | J5: =+I5/C5 -> #REF! | K5: =+I5/F5 -> #REF! | M5: TOTAL | N5: =+SUM(N6:N23) -> #REF! | O5: =+SUM(O6:O23) -> #REF! | P5: =+SUM(P6:P23) -> #REF! | Q5: =+SUM(Q6:Q23) -> #REF! | R5: =+SUM(R6:R23) -> #REF! | S5: =+SUM(S6:S23) -> #REF! | T5: =+SUM(T6:T23) -> #REF! | U5: =+T5/N5 -> #REF! | V5: =+T5/Q5 -> #REF! | X5: TOTAL | Y5: =+SUM(Y6:Y23) -> #REF! | Z5: =+SUM(Z6:Z23) -> #REF! | AB5: =+SUM(AB6:AB23) -> #REF! | AC5: =+SUM(AC6:AC23) -> #REF! | AD5: =+SUM(AD6:AD23) -> #REF! | AE5: =+SUM(AE6:AE23) -> #REF! | AF5: =+AE5/Y5 -> #REF! | AG5: =+AE5/AB5 -> #REF!
B6: AUDI | C6: =+N6+Y6 -> #REF! | D6: =+O6+Z6 -> #REF! | E6: =+P6+AA6 -> #REF! | F6: =+D6+E6 -> #REF! | G6: =+R6+AC6 -> #REF! | H6: =+S6+AD6 -> #REF! | I6: =+G6+H6 -> #REF! | J6: =+I6/C6 -> #REF! | K6: =+I6/F6 -> #REF! | M6: AUDI | N6: =+#REF! -> #REF! | O6: =+#REF! -> #REF! | P6: =+#REF! -> #REF! | Q6: =+O6+P6 -> #REF! | R6: =+#REF! -> #REF! | S6: =+#REF! -> #REF! | T6: =+R6+S6 -> #REF! | U6: =+T6/N6 -> #REF! | V6: =+T6/Q6 -> #REF! | X6: AUDI | Y6: =+#REF! -> #REF! | Z6: =+#REF! -> #REF! | AB6: =+Z6+AA6 -> #REF! | AC6: =+#REF! -> #REF! | AD6: =+#REF! -> #REF! | AE6: =+AC6+AD6 -> #REF! | AF6: =+AE6/Y6 -> #REF! | AG6: =+AE6/AB6 -> #REF!
B7: INFINITI | C7: =+N7+Y7 -> #REF! | D7: =+O7+Z7 -> #REF! | E7: =+P7+AA7 -> #REF! | F7: =+D7+E7 -> #REF! | G7: =+R7+AC7 -> #REF! | H7: =+S7+AD7 -> #REF! | I7: =+G7+H7 -> #REF! | J7: =+I7/C7 -> #REF! | K7: =+I7/F7 -> #REF! | M7: INFINITI | N7: =+#REF! -> #REF! | O7: =+#REF! -> #REF! | P7: =+#REF! -> #REF! | Q7: =+O7+P7 -> #REF! | R7: =+#REF! -> #REF! | S7: =+#REF! -> #REF! | T7: =+R7+S7 -> #REF! | U7: =+T7/N7 -> #REF! | V7: =+T7/Q7 -> #REF! | X7: INFINITI | Y7: =+#REF! -> #REF! | Z7: =+#REF! -> #REF! | AB7: =+Z7+AA7 -> #REF! | AC7: =+#REF! -> #REF! | AD7: =+#REF! -> #REF! | AE7: =+AC7+AD7 -> #REF! | AF7: =+AE7/Y7 -> #REF! | AG7: =+AE7/AB7 -> #REF!
B8: MCPA LAP | C8: =+N8+Y8 -> #REF! | D8: =+O8+Z8 -> #REF! | E8: =+P8+AA8 -> 0 | F8: =+D8+E8 -> #REF! | G8: =+R8+AC8 -> #REF! | H8: =+S8+AD8 -> #REF! | I8: =+G8+H8 -> #REF! | J8: =+I8/C8 -> #REF! | K8: =+I8/F8 -> #REF! | X8: MCPA LAP | Y8: =+#REF! -> #REF! | Z8: =+#REF! -> #REF! | AB8: =+Z8+AA8 -> #REF! | AC8: =+#REF! -> #REF! | AD8: =+#REF! -> #REF! | AE8: =+AC8+AD8 -> #REF! | AF8: =+AE8/Y8 -> #REF! | AG8: =+AE8/AB8 -> #REF!
B9: MCPA LAV | C9: =+N9+Y9 -> #REF! | D9: =+O9+Z9 -> #REF! | E9: =+P9+AA9 -> 0 | F9: =+D9+E9 -> #REF! | G9: =+R9+AC9 -> #REF! | H9: =+S9+AD9 -> #REF! | I9: =+G9+H9 -> #REF! | J9: =+I9/C9 -> #REF! | K9: =+I9/F9 -> #REF! | X9: MCPA LAV | Y9: =+#REF! -> #REF! | Z9: =+#REF! -> #REF! | AB9: =+Z9+AA9 -> #REF! | AC9: =+#REF! -> #REF! | AD9: =+#REF! -> #REF! | AE9: =+AC9+AD9 -> #REF! | AF9: =+AE9/Y9 -> #REF! | AG9: =+AE9/AB9 -> #REF!
B10: MCPA SPE | C10: =+N10+Y10 -> #REF! | D10: =+O10+Z10 -> #REF! | E10: =+P10+AA10 -> 0 | F10: =+D10+E10 -> #REF! | G10: =+R10+AC10 -> #REF! | H10: =+S10+AD10 -> #REF! | I10: =+G10+H10 -> #REF! | J10: =+I10/C10 -> #REF! | K10: =+I10/F10 -> #REF! | X10: MCPA SPE | Y10: =+#REF! -> #REF! | Z10: =+#REF! -> #REF! | AB10: =+Z10+AA10 -> #REF! | AC10: =+#REF! -> #REF! | AD10: =+#REF! -> #REF! | AE10: =+AC10+AD10 -> #REF! | AF10: =+AE10/Y10 -> #REF! | AG10: =+AE10/AB10 -> #REF!
B11: HONDA | C11: =+N11+Y11 -> #REF! | D11: =+O11+Z11 -> #REF! | E11: =+P11+AA11 -> #REF! | F11: =+D11+E11 -> #REF! | G11: =+R11+AC11 -> #REF! | H11: =+S11+AD11 -> #REF! | I11: =+G11+H11 -> #REF! | J11: =+I11/C11 -> #REF! | K11: =+I11/F11 -> #REF! | M11: HONDA | N11: =+#REF! -> #REF! | O11: =+#REF! -> #REF! | P11: =+#REF! -> #REF! | Q11: =+O11+P11 -> #REF! | R11: =+#REF! -> #REF! | S11: =+#REF! -> #REF! | T11: =+R11+S11 -> #REF! | U11: =+T11/N11 -> #REF! | V11: =+T11/Q11 -> #REF! | X11: HONDA | Y11: =+#REF! -> #REF! | Z11: =+#REF! -> #REF! | AB11: =+Z11+AA11 -> #REF! | AC11: =+#REF! -> #REF! | AD11: =+#REF! -> #REF! | AE11: =+AC11+AD11 -> #REF! | AF11: =+AE11/Y11 -> #REF! | AG11: =+AE11/AB11 -> #REF!
B12: TOYOTA | C12: =+N12+Y12 -> #REF! | D12: =+O12+Z12 -> #REF! | E12: =+P12+AA12 -> #REF! | F12: =+D12+E12 -> #REF! | G12: =+R12+AC12 -> #REF! | H12: =+S12+AD12 -> #REF! | I12: =+G12+H12 -> #REF! | J12: =+I12/C12 -> #REF! | K12: =+I12/F12 -> #REF! | M12: TOYOTA | N12: =+#REF! -> #REF! | O12: =+#REF! -> #REF! | P12: =+#REF! -> #REF! | Q12: =+O12+P12 -> #REF! | R12: =+#REF! -> #REF! | S12: =+#REF! -> #REF! | T12: =+R12+S12 -> #REF! | U12: =+T12/N12 -> #REF! | V12: =+T12/Q12 -> #REF! | X12: TOYOTA | Y12: =+#REF! -> #REF! | Z12: =+#REF! -> #REF! | AB12: =+Z12+AA12 -> #REF! | AC12: =+#REF! -> #REF! | AD12: =+#REF! -> #REF! | AE12: =+AC12+AD12 -> #REF! | AF12: =+AE12/Y12 -> #REF! | AG12: =+AE12/AB12 -> #REF!
B13: VOLKS | C13: =+N13+Y13 -> #REF! | D13: =+O13+Z13 -> #REF! | E13: =+P13+AA13 -> #REF! | F13: =+D13+E13 -> #REF! | G13: =+R13+AC13 -> #REF! | H13: =+S13+AD13 -> #REF! | I13: =+G13+H13 -> #REF! | J13: =+I13/C13 -> #REF! | K13: =+I13/F13 -> #REF! | M13: VOLKS | N13: =+#REF! -> #REF! | O13: =+#REF! -> #REF! | P13: =+#REF! -> #REF! | Q13: =+O13+P13 -> #REF! | R13: =+#REF! -> #REF! | S13: =+#REF! -> #REF! | T13: =+R13+S13 -> #REF! | U13: =+T13/N13 -> #REF! | V13: =+T13/Q13 -> #REF! | X13: VOLKS | Y13: =+#REF! -> #REF! | Z13: =+#REF! -> #REF! | AB13: =+Z13+AA13 -> #REF! | AC13: =+#REF! -> #REF! | AD13: =+#REF! -> #REF! | AE13: =+AC13+AD13 -> #REF! | AF13: =+AE13/Y13 -> #REF! | AG13: =+AE13/AB13 -> #REF!
B14: BMW PA | C14: =+N14+Y14 -> #REF! | D14: =+O14+Z14 -> #REF! | E14: =+P14+AA14 -> #REF! | F14: =+D14+E14 -> #REF! | G14: =+R14+AC14 -> #REF! | H14: =+S14+AD14 -> #REF! | I14: =+G14+H14 -> #REF! | J14: =+I14/C14 -> #REF! | K14: =+I14/F14 -> #REF! | M14: BMW PA | N14: =+#REF! -> #REF! | O14: =+#REF! -> #REF! | P14: =+#REF! -> #REF! | Q14: =+O14+P14 -> #REF! | R14: =+#REF! -> #REF! | S14: =+#REF! -> #REF! | T14: =+R14+S14 -> #REF! | U14: =+T14/N14 -> #REF! | V14: =+T14/Q14 -> #REF! | X14: BMW PA | Y14: =+#REF! -> #REF! | Z14: =+#REF! -> #REF! | AB14: =+Z14+AA14 -> #REF! | AC14: =+#REF! -> #REF! | AD14: =+#REF! -> #REF! | AE14: =+AC14+AD14 -> #REF! | AF14: =+AE14/Y14 -> #REF! | AG14: =+AE14/AB14 -> #REF!
B15: MINI | C15: =+N15+Y15 -> #REF! | D15: =+O15+Z15 -> #REF! | E15: =+P15+AA15 -> #REF! | F15: =+D15+E15 -> #REF! | G15: =+R15+AC15 -> #REF! | H15: =+S15+AD15 -> #REF! | I15: =+G15+H15 -> #REF! | J15: =+I15/C15 -> #REF! | K15: =+I15/F15 -> #REF! | M15: MINI | N15: =+#REF! -> #REF! | O15: =+#REF! -> #REF! | P15: =+#REF! -> #REF! | Q15: =+O15+P15 -> #REF! | R15: =+#REF! -> #REF! | S15: =+#REF! -> #REF! | T15: =+R15+S15 -> #REF! | U15: =+T15/N15 -> #REF! | V15: =+T15/Q15 -> #REF! | X15: MINI | Y15: =+#REF! -> #REF! | Z15: =+#REF! -> #REF! | AB15: =+Z15+AA15 -> #REF! | AC15: =+#REF! -> #REF! | AD15: =+#REF! -> #REF! | AE15: =+AC15+AD15 -> #REF! | AF15: =+AE15/Y15 -> #REF! | AG15: =+AE15/AB15 -> #REF!
B16: BMW STJ | C16: =+N16+Y16 -> #REF! | D16: =+O16+Z16 -> #REF! | E16: =+P16+AA16 -> #REF! | F16: =+D16+E16 -> #REF! | G16: =+R16+AC16 -> #REF! | H16: =+S16+AD16 -> #REF! | I16: =+G16+H16 -> #REF! | J16: =+I16/C16 -> #REF! | K16: =+I16/F16 -> #REF! | M16: BMW STJ | N16: =+#REF! -> #REF! | O16: =+#REF! -> #REF! | P16: =+#REF! -> #REF! | Q16: =+O16+P16 -> #REF! | R16: =+#REF! -> #REF! | S16: =+#REF! -> #REF! | T16: =+R16+S16 -> #REF! | U16: =+T16/N16 -> #REF! | V16: =+T16/Q16 -> #REF! | X16: BMW STJ | Y16: =+#REF! -> #REF! | Z16: =+#REF! -> #REF! | AB16: =+Z16+AA16 -> #REF! | AC16: =+#REF! -> #REF! | AD16: =+#REF! -> #REF! | AE16: =+AC16+AD16 -> #REF! | AF16: =+AE16/Y16 -> #REF! | AG16: =+AE16/AB16 -> #REF!
B17: LEXUS | C17: =+N17+Y17 -> #REF! | D17: =+O17+Z17 -> #REF! | E17: =+P17+AA17 -> #REF! | F17: =+D17+E17 -> #REF! | G17: =+R17+AC17 -> #REF! | H17: =+S17+AD17 -> #REF! | I17: =+G17+H17 -> #REF! | J17: =+I17/C17 -> #REF! | K17: =+I17/F17 -> #REF! | M17: LEXUS | N17: =+#REF! -> #REF! | O17: =+#REF! -> #REF! | P17: =+#REF! -> #REF! | Q17: =+O17+P17 -> #REF! | R17: =+#REF! -> #REF! | S17: =+#REF! -> #REF! | T17: =+R17+S17 -> #REF! | U17: =+T17/N17 -> #REF! | V17: =+T17/Q17 -> #REF! | X17: LEXUS | Y17: =+#REF! -> #REF! | Z17: =+#REF! -> #REF! | AB17: =+Z17+AA17 -> #REF! | AC17: =+#REF! -> #REF! | AD17: =+#REF! -> #REF! | AE17: =+AC17+AD17 -> #REF! | AF17: =+AE17/Y17 -> #REF! | AG17: =+AE17/AB17 -> #REF!
B18: BMW SHER | C18: =+N18+Y18 -> #REF! | D18: =+O18+Z18 -> #REF! | E18: =+P18+AA18 -> #REF! | F18: =+D18+E18 -> #REF! | G18: =+R18+AC18 -> #REF! | H18: =+S18+AD18 -> #REF! | I18: =+G18+H18 -> #REF! | J18: =+I18/C18 -> #REF! | K18: =+I18/F18 -> #REF! | M18: BMW SHER | N18: =+#REF! -> #REF! | O18: =+#REF! -> #REF! | P18: =+#REF! -> #REF! | Q18: =+O18+P18 -> #REF! | R18: =+#REF! -> #REF! | S18: =+#REF! -> #REF! | T18: =+R18+S18 -> #REF! | U18: =+T18/N18 -> #REF! | V18: =+T18/Q18 -> #REF! | X18: BMW SHER | Y18: =+#REF! -> #REF! | Z18: =+#REF! -> #REF! | AB18: =+Z18+AA18 -> #REF! | AC18: =+#REF! -> #REF! | AD18: =+#REF! -> #REF! | AE18: =+AC18+AD18 -> #REF! | AF18: =+AE18/Y18 -> #REF! | AG18: =+AE18/AB18 -> #REF!
B19: SSMB | C19: =+N19+Y19 -> #REF! | D19: =+O19+Z19 -> #REF! | E19: =+P19+AA19 -> #REF! | F19: =+D19+E19 -> #REF! | G19: =+R19+AC19 -> #REF! | H19: =+S19+AD19 -> #REF! | I19: =+G19+H19 -> #REF! | J19: =+I19/C19 -> #REF! | K19: =+I19/F19 -> #REF! | M19: SSMB | N19: =+#REF! -> #REF! | O19: =+#REF! -> #REF! | P19: =+#REF! -> #REF! | Q19: =+O19+P19 -> #REF! | R19: =+#REF! -> #REF! | S19: =+#REF! -> #REF! | T19: =+R19+S19 -> #REF! | U19: =+T19/N19 -> #REF! | V19: =+T19/Q19 -> #REF! | X19: SSMB | Y19: =+#REF! -> #REF! | Z19: =+#REF! -> #REF! | AB19: =+Z19+AA19 -> #REF! | AC19: =+#REF! -> #REF! | AD19: =+#REF! -> #REF! | AE19: =+AC19+AD19 -> #REF! | AF19: =+AE19/Y19 -> #REF! | AG19: =+AE19/AB19 -> #REF!
B20: MBQ | C20: =+N20+Y20 -> #REF! | D20: =+O20+Z20 -> #REF! | E20: =+P20+AA20 -> #REF! | F20: =+D20+E20 -> #REF! | G20: =+R20+AC20 -> #REF! | H20: =+S20+AD20 -> #REF! | I20: =+G20+H20 -> #REF! | J20: =+I20/C20 -> #REF! | K20: =+I20/F20 -> #REF! | M20: MBQ | N20: =+#REF! -> #REF! | O20: =+#REF! -> #REF! | P20: =+#REF! -> #REF! | Q20: =+O20+P20 -> #REF! | R20: =+#REF! -> #REF! | S20: =+#REF! -> #REF! | T20: =+R20+S20 -> #REF! | U20: =+T20/N20 -> #REF! | V20: =+T20/Q20 -> #REF! | X20: MBQ | Y20: =+#REF! -> #REF! | Z20: =+#REF! -> #REF! | AB20: =+Z20+AA20 -> #REF! | AC20: =+#REF! -> #REF! | AD20: =+#REF! -> #REF! | AE20: =+AC20+AD20 -> #REF! | AF20: =+AE20/Y20 -> #REF! | AG20: =+AE20/AB20 -> #REF!
B21: VOLVO | C21: =+N21+Y21 -> #REF! | D21: =+O21+Z21 -> #REF! | E21: =+P21+AA21 -> #REF! | F21: =+D21+E21 -> #REF! | G21: =+R21+AC21 -> #REF! | H21: =+S21+AD21 -> #REF! | I21: =+G21+H21 -> #REF! | J21: =+I21/C21 -> #REF! | K21: =+I21/F21 -> #REF! | M21: VOLVO | N21: =+#REF! -> #REF! | O21: =+#REF! -> #REF! | P21: =+#REF! -> #REF! | Q21: =+O21+P21 -> #REF! | R21: =+#REF! -> #REF! | S21: =+#REF! -> #REF! | T21: =+R21+S21 -> #REF! | U21: =+T21/N21 -> #REF! | V21: =+T21/Q21 -> #REF! | X21: VOLVO | Y21: =+#REF! -> #REF! | Z21: =+#REF! -> #REF! | AB21: =+Z21+AA21 -> #REF! | AC21: =+#REF! -> #REF! | AD21: =+#REF! -> #REF! | AE21: =+AC21+AD21 -> #REF! | AF21: =+AE21/Y21 -> #REF! | AG21: =+AE21/AB21 -> #REF!
B22: JLR | C22: =+N22+Y22 -> #REF! | D22: =+O22+Z22 -> #REF! | E22: =+P22+AA22 -> #REF! | F22: =+D22+E22 -> #REF! | G22: =+R22+AC22 -> #REF! | H22: =+S22+AD22 -> #REF! | I22: =+G22+H22 -> #REF! | J22: =+I22/C22 -> #REF! | K22: =+I22/F22 -> #REF! | M22: JLR | N22: =+#REF! -> #REF! | O22: =+#REF! -> #REF! | P22: =+#REF! -> #REF! | Q22: =+O22+P22 -> #REF! | R22: =+#REF! -> #REF! | S22: =+#REF! -> #REF! | T22: =+R22+S22 -> #REF! | U22: =+T22/N22 -> #REF! | V22: =+T22/Q22 -> #REF! | X22: JLR | Y22: =+#REF! -> #REF! | Z22: =+#REF! -> #REF! | AB22: =+Z22+AA22 -> #REF! | AC22: =+#REF! -> #REF! | AD22: =+#REF! -> #REF! | AE22: =+AC22+AD22 -> #REF! | AF22: =+AE22/Y22 -> #REF! | AG22: =+AE22/AB22 -> #REF!
B23: LHD | C23: =+N23+Y23 -> #REF! | D23: =+O23+Z23 -> #REF! | E23: =+P23+AA23 -> #REF! | F23: =+D23+E23 -> #REF! | G23: =+R23+AC23 -> #REF! | H23: =+S23+AD23 -> #REF! | I23: =+G23+H23 -> #REF! | J23: =+I23/C23 -> #REF! | K23: =+I23/F23 -> #REF! | M23: LHD | N23: =+#REF! -> #REF! | O23: =+#REF! -> #REF! | P23: =+#REF! -> #REF! | Q23: =+O23+P23 -> #REF! | R23: =+#REF! -> #REF! | S23: =+#REF! -> #REF! | T23: =+R23+S23 -> #REF! | U23: =+T23/N23 -> #REF! | V23: =+T23/Q23 -> #REF! | X23: LHD | Y23: =+#REF! -> #REF! | Z23: =+#REF! -> #REF! | AB23: =+Z23+AA23 -> #REF! | AC23: =+#REF! -> #REF! | AD23: =+#REF! -> #REF! | AE23: =+AC23+AD23 -> #REF! | AF23: =+AE23/Y23 -> #REF! | AG23: =+AE23/AB23 -> #REF!
B25: BUDGET | M25: BUDGET | X25: BUDGET
B26: STORE | C26: Units | D26: Margin | E26: Margin demo | F26: Front margin | G26: frais de livraison | H26: Ent. Stock | I26: Delivery fee | J26: Delivery fee / unit | K26: % Delivery fee / Front margin | M26: STORE | N26: Units | O26: M. new | P26: M. Demos | Q26: Front margin | R26: frais de livraison | S26: Ent. Stock | T26: Delivery fee | U26: Delivery fee / unit | V26: % Delivery fee / Front margin | X26: STORE | Y26: Units | Z26: M. used | AB26: Front margin | AC26: frais de livraison | AD26: Ent. Stock | AE26: Delivery fee | AF26: Delivery fee / unit | AG26: % Delivery fee / Front margin
B27: TOTAL | C27: =+SUM(C28:C45) -> #REF! | D27: =+SUM(D28:D45) -> #REF! | E27: =+SUM(E28:E45) -> #REF! | F27: =+SUM(F28:F45) -> #REF! | G27: =+SUM(G28:G45) -> #REF! | H27: =+SUM(H28:H45) -> #REF! | I27: =+SUM(I28:I45) -> #REF! | J27: =+I27/C27 -> #REF! | K27: =+I27/F27 -> #REF! | M27: TOTAL | N27: =+SUM(N28:N45) -> #REF! | O27: =+SUM(O28:O45) -> #REF! | P27: =+SUM(P28:P45) -> #REF! | Q27: =+SUM(Q28:Q45) -> #REF! | R27: =+SUM(R28:R45) -> #REF! | S27: =+SUM(S28:S45) -> #REF! | T27: =+SUM(T28:T45) -> #REF! | U27: =+T27/N27 -> #REF! | V27: =+T27/Q27 -> #REF! | X27: TOTAL | Y27: =+SUM(Y28:Y45) -> #REF! | Z27: =+SUM(Z28:Z45) -> #REF! | AB27: =+SUM(AB28:AB45) -> #REF! | AC27: =+SUM(AC28:AC45) -> #REF! | AD27: =+SUM(AD28:AD45) -> #REF! | AE27: =+SUM(AE28:AE45) -> #REF! | AF27: =+AE27/Y27 -> #REF! | AG27: =+AE27/AB27 -> #REF!
B28: AUDI | C28: =+N28+Y28 -> #REF! | D28: =+O28+Z28 -> #REF! | E28: =+P28+AA28 -> #REF! | F28: =+D28+E28 -> #REF! | G28: =+R28+AC28 -> #REF! | H28: =+S28+AD28 -> #REF! | I28: =+G28+H28 -> #REF! | J28: =+I28/C28 -> #REF! | K28: =+I28/F28 -> #REF! | M28: AUDI | N28: =+#REF! -> #REF! | O28: =+#REF! -> #REF! | P28: =+#REF! -> #REF! | Q28: =+O28+P28 -> #REF! | R28: =+#REF! -> #REF! | S28: =+#REF! -> #REF! | T28: =+R28+S28 -> #REF! | U28: =+T28/N28 -> #REF! | V28: =+T28/Q28 -> #REF! | X28: AUDI | Y28: =+#REF! -> #REF! | Z28: =+#REF! -> #REF! | AB28: =+Z28+AA28 -> #REF! | AC28: =+#REF! -> #REF! | AD28: =+#REF! -> #REF! | AE28: =+AC28+AD28 -> #REF! | AF28: =+AE28/Y28 -> #REF! | AG28: =+AE28/AB28 -> #REF!
B29: INFINITI | C29: =+N29+Y29 -> #REF! | D29: =+O29+Z29 -> #REF! | E29: =+P29+AA29 -> #REF! | F29: =+D29+E29 -> #REF! | G29: =+R29+AC29 -> #REF! | H29: =+S29+AD29 -> #REF! | I29: =+G29+H29 -> #REF! | J29: =+I29/C29 -> #REF! | K29: =+I29/F29 -> #REF! | M29: INFINITI | N29: =+#REF! -> #REF! | O29: =+#REF! -> #REF! | P29: =+#REF! -> #REF! | Q29: =+O29+P29 -> #REF! | R29: =+#REF! -> #REF! | S29: =+#REF! -> #REF! | T29: =+R29+S29 -> #REF! | U29: =+T29/N29 -> #REF! | V29: =+T29/Q29 -> #REF! | X29: INFINITI | Y29: =+#REF! -> #REF! | Z29: =+#REF! -> #REF! | AB29: =+Z29+AA29 -> #REF! | AC29: =+#REF! -> #REF! | AD29: =+#REF! -> #REF! | AE29: =+AC29+AD29 -> #REF! | AF29: =+AE29/Y29 -> #REF! | AG29: =+AE29/AB29 -> #REF!
B30: MCPA LAP | C30: =+N30+Y30 -> #REF! | D30: =+O30+Z30 -> #REF! | E30: =+P30+AA30 -> 0 | F30: =+D30+E30 -> #REF! | G30: =+R30+AC30 -> #REF! | H30: =+S30+AD30 -> #REF! | I30: =+G30+H30 -> #REF! | J30: =+I30/C30 -> #REF! | K30: =+I30/F30 -> #REF! | X30: MCPA LAP | Y30: =+#REF! -> #REF! | Z30: =+#REF! -> #REF! | AB30: =+Z30+AA30 -> #REF! | AC30: =+#REF! -> #REF! | AD30: =+#REF! -> #REF! | AE30: =+AC30+AD30 -> #REF! | AF30: =+AE30/Y30 -> #REF! | AG30: =+AE30/AB30 -> #REF!
B31: MCPA LAV | C31: =+N31+Y31 -> #REF! | D31: =+O31+Z31 -> #REF! | E31: =+P31+AA31 -> 0 | F31: =+D31+E31 -> #REF! | G31: =+R31+AC31 -> #REF! | H31: =+S31+AD31 -> #REF! | I31: =+G31+H31 -> #REF! | J31: =+I31/C31 -> #REF! | K31: =+I31/F31 -> #REF! | X31: MCPA LAV | Y31: =+#REF! -> #REF! | Z31: =+#REF! -> #REF! | AB31: =+Z31+AA31 -> #REF! | AC31: =+#REF! -> #REF! | AD31: =+#REF! -> #REF! | AE31: =+AC31+AD31 -> #REF! | AF31: =+AE31/Y31 -> #REF! | AG31: =+AE31/AB31 -> #REF!
B32: MCPA SPE | C32: =+N32+Y32 -> #REF! | D32: =+O32+Z32 -> #REF! | E32: =+P32+AA32 -> 0 | F32: =+D32+E32 -> #REF! | G32: =+R32+AC32 -> #REF! | H32: =+S32+AD32 -> #REF! | I32: =+G32+H32 -> #REF! | J32: =+I32/C32 -> #REF! | K32: =+I32/F32 -> #REF! | X32: MCPA SPE | Y32: =+#REF! -> #REF! | Z32: =+#REF! -> #REF! | AB32: =+Z32+AA32 -> #REF! | AC32: =+#REF! -> #REF! | AD32: =+#REF! -> #REF! | AE32: =+AC32+AD32 -> #REF! | AF32: =+AE32/Y32 -> #REF! | AG32: =+AE32/AB32 -> #REF!
B33: HONDA | C33: =+N33+Y33 -> #REF! | D33: =+O33+Z33 -> #REF! | E33: =+P33+AA33 -> #REF! | F33: =+D33+E33 -> #REF! | G33: =+R33+AC33 -> #REF! | H33: =+S33+AD33 -> #REF! | I33: =+G33+H33 -> #REF! | J33: =+I33/C33 -> #REF! | K33: =+I33/F33 -> #REF! | M33: HONDA | N33: =+#REF! -> #REF! | O33: =+#REF! -> #REF! | P33: =+#REF! -> #REF! | Q33: =+O33+P33 -> #REF! | R33: =+#REF! -> #REF! | S33: =+#REF! -> #REF! | T33: =+R33+S33 -> #REF! | U33: =+T33/N33 -> #REF! | V33: =+T33/Q33 -> #REF! | X33: HONDA | Y33: =+#REF! -> #REF! | Z33: =+#REF! -> #REF! | AB33: =+Z33+AA33 -> #REF! | AC33: =+#REF! -> #REF! | AD33: =+#REF! -> #REF! | AE33: =+AC33+AD33 -> #REF! | AF33: =+AE33/Y33 -> #REF! | AG33: =+AE33/AB33 -> #REF!
B34: TOYOTA | C34: =+N34+Y34 -> #REF! | D34: =+O34+Z34 -> #REF! | E34: =+P34+AA34 -> #REF! | F34: =+D34+E34 -> #REF! | G34: =+R34+AC34 -> #REF! | H34: =+S34+AD34 -> #REF! | I34: =+G34+H34 -> #REF! | J34: =+I34/C34 -> #REF! | K34: =+I34/F34 -> #REF! | M34: TOYOTA | N34: =+#REF! -> #REF! | O34: =+#REF! -> #REF! | P34: =+#REF! -> #REF! | Q34: =+O34+P34 -> #REF! | R34: =+#REF! -> #REF! | S34: =+#REF! -> #REF! | T34: =+R34+S34 -> #REF! | U34: =+T34/N34 -> #REF! | V34: =+T34/Q34 -> #REF! | X34: TOYOTA | Y34: =+#REF! -> #REF! | Z34: =+#REF! -> #REF! | AB34: =+Z34+AA34 -> #REF! | AC34: =+#REF! -> #REF! | AD34: =+#REF! -> #REF! | AE34: =+AC34+AD34 -> #REF! | AF34: =+AE34/Y34 -> #REF! | AG34: =+AE34/AB34 -> #REF!
B35: VOLKS | C35: =+N35+Y35 -> #REF! | D35: =+O35+Z35 -> #REF! | E35: =+P35+AA35 -> #REF! | F35: =+D35+E35 -> #REF! | G35: =+R35+AC35 -> #REF! | H35: =+S35+AD35 -> #REF! | I35: =+G35+H35 -> #REF! | J35: =+I35/C35 -> #REF! | K35: =+I35/F35 -> #REF! | M35: VOLKS | N35: =+#REF! -> #REF! | O35: =+#REF! -> #REF! | P35: =+#REF! -> #REF! | Q35: =+O35+P35 -> #REF! | R35: =+#REF! -> #REF! | S35: =+#REF! -> #REF! | T35: =+R35+S35 -> #REF! | U35: =+T35/N35 -> #REF! | V35: =+T35/Q35 -> #REF! | X35: VOLKS | Y35: =+#REF! -> #REF! | Z35: =+#REF! -> #REF! | AB35: =+Z35+AA35 -> #REF! | AC35: =+#REF! -> #REF! | AD35: =+#REF! -> #REF! | AE35: =+AC35+AD35 -> #REF! | AF35: =+AE35/Y35 -> #REF! | AG35: =+AE35/AB35 -> #REF!
B36: BMW PA | C36: =+N36+Y36 -> #REF! | D36: =+O36+Z36 -> #REF! | E36: =+P36+AA36 -> #REF! | F36: =+D36+E36 -> #REF! | G36: =+R36+AC36 -> #REF! | H36: =+S36+AD36 -> #REF! | I36: =+G36+H36 -> #REF! | J36: =+I36/C36 -> #REF! | K36: =+I36/F36 -> #REF! | M36: BMW PA | N36: =+#REF! -> #REF! | O36: =+#REF! -> #REF! | P36: =+#REF! -> #REF! | Q36: =+O36+P36 -> #REF! | R36: =+#REF! -> #REF! | S36: =+#REF! -> #REF! | T36: =+R36+S36 -> #REF! | U36: =+T36/N36 -> #REF! | V36: =+T36/Q36 -> #REF! | X36: BMW PA | Y36: =+#REF! -> #REF! | Z36: =+#REF! -> #REF! | AB36: =+Z36+AA36 -> #REF! | AC36: =+#REF! -> #REF! | AD36: =+#REF! -> #REF! | AE36: =+AC36+AD36 -> #REF! | AF36: =+AE36/Y36 -> #REF! | AG36: =+AE36/AB36 -> #REF!
B37: MINI | C37: =+N37+Y37 -> #REF! | D37: =+O37+Z37 -> #REF! | E37: =+P37+AA37 -> #REF! | F37: =+D37+E37 -> #REF! | G37: =+R37+AC37 -> #REF! | H37: =+S37+AD37 -> #REF! | I37: =+G37+H37 -> #REF! | J37: =+I37/C37 -> #REF! | K37: =+I37/F37 -> #REF! | M37: MINI | N37: =+#REF! -> #REF! | O37: =+#REF! -> #REF! | P37: =+#REF! -> #REF! | Q37: =+O37+P37 -> #REF! | R37: =+#REF! -> #REF! | S37: =+#REF! -> #REF! | T37: =+R37+S37 -> #REF! | U37: =+T37/N37 -> #REF! | V37: =+T37/Q37 -> #REF! | X37: MINI | Y37: =+#REF! -> #REF! | Z37: =+#REF! -> #REF! | AB37: =+Z37+AA37 -> #REF! | AC37: =+#REF! -> #REF! | AD37: =+#REF! -> #REF! | AE37: =+AC37+AD37 -> #REF! | AF37: =+AE37/Y37 -> #REF! | AG37: =+AE37/AB37 -> #REF!
B38: BMW STJ | C38: =+N38+Y38 -> #REF! | D38: =+O38+Z38 -> #REF! | E38: =+P38+AA38 -> #REF! | F38: =+D38+E38 -> #REF! | G38: =+R38+AC38 -> #REF! | H38: =+S38+AD38 -> #REF! | I38: =+G38+H38 -> #REF! | J38: =+I38/C38 -> #REF! | K38: =+I38/F38 -> #REF! | M38: BMW STJ | N38: =+#REF! -> #REF! | O38: =+#REF! -> #REF! | P38: =+#REF! -> #REF! | Q38: =+O38+P38 -> #REF! | R38: =+#REF! -> #REF! | S38: =+#REF! -> #REF! | T38: =+R38+S38 -> #REF! | U38: =+T38/N38 -> #REF! | V38: =+T38/Q38 -> #REF! | X38: BMW STJ | Y38: =+#REF! -> #REF! | Z38: =+#REF! -> #REF! | AB38: =+Z38+AA38 -> #REF! | AC38: =+#REF! -> #REF! | AD38: =+#REF! -> #REF! | AE38: =+AC38+AD38 -> #REF! | AF38: =+AE38/Y38 -> #REF! | AG38: =+AE38/AB38 -> #REF!
B39: LEXUS | C39: =+N39+Y39 -> #REF! | D39: =+O39+Z39 -> #REF! | E39: =+P39+AA39 -> #REF! | F39: =+D39+E39 -> #REF! | G39: =+R39+AC39 -> #REF! | H39: =+S39+AD39 -> #REF! | I39: =+G39+H39 -> #REF! | J39: =+I39/C39 -> #REF! | K39: =+I39/F39 -> #REF! | M39: LEXUS | N39: =+#REF! -> #REF! | O39: =+#REF! -> #REF! | P39: =+#REF! -> #REF! | Q39: =+O39+P39 -> #REF! | R39: =+#REF! -> #REF! | S39: =+#REF! -> #REF! | T39: =+R39+S39 -> #REF! | U39: =+T39/N39 -> #REF! | V39: =+T39/Q39 -> #REF! | X39: LEXUS | Y39: =+#REF! -> #REF! | Z39: =+#REF! -> #REF! | AB39: =+Z39+AA39 -> #REF! | AC39: =+#REF! -> #REF! | AD39: =+#REF! -> #REF! | AE39: =+AC39+AD39 -> #REF! | AF39: =+AE39/Y39 -> #REF! | AG39: =+AE39/AB39 -> #REF!
B40: BMW SHER | C40: =+N40+Y40 -> #REF! | D40: =+O40+Z40 -> #REF! | E40: =+P40+AA40 -> #REF! | F40: =+D40+E40 -> #REF! | G40: =+R40+AC40 -> #REF! | H40: =+S40+AD40 -> #REF! | I40: =+G40+H40 -> #REF! | J40: =+I40/C40 -> #REF! | K40: =+I40/F40 -> #REF! | M40: BMW SHER | N40: =+#REF! -> #REF! | O40: =+#REF! -> #REF! | P40: =+#REF! -> #REF! | Q40: =+O40+P40 -> #REF! | R40: =+#REF! -> #REF! | S40: =+#REF! -> #REF! | T40: =+R40+S40 -> #REF! | U40: =+T40/N40 -> #REF! | V40: =+T40/Q40 -> #REF! | X40: BMW SHER | Y40: =+#REF! -> #REF! | Z40: =+#REF! -> #REF! | AB40: =+Z40+AA40 -> #REF! | AC40: =+#REF! -> #REF! | AD40: =+#REF! -> #REF! | AE40: =+AC40+AD40 -> #REF! | AF40: =+AE40/Y40 -> #REF! | AG40: =+AE40/AB40 -> #REF!
B41: SSMB | C41: =+N41+Y41 -> #REF! | D41: =+O41+Z41 -> #REF! | E41: =+P41+AA41 -> #REF! | F41: =+D41+E41 -> #REF! | G41: =+R41+AC41 -> #REF! | H41: =+S41+AD41 -> #REF! | I41: =+G41+H41 -> #REF! | J41: =+I41/C41 -> #REF! | K41: =+I41/F41 -> #REF! | M41: SSMB | N41: =+#REF! -> #REF! | O41: =+#REF! -> #REF! | P41: =+#REF! -> #REF! | Q41: =+O41+P41 -> #REF! | R41: =+#REF! -> #REF! | S41: =+#REF! -> #REF! | T41: =+R41+S41 -> #REF! | U41: =+T41/N41 -> #REF! | V41: =+T41/Q41 -> #REF! | X41: SSMB | Y41: =+#REF! -> #REF! | Z41: =+#REF! -> #REF! | AB41: =+Z41+AA41 -> #REF! | AC41: =+#REF! -> #REF! | AD41: =+#REF! -> #REF! | AE41: =+AC41+AD41 -> #REF! | AF41: =+AE41/Y41 -> #REF! | AG41: =+AE41/AB41 -> #REF!
B42: MBQ | C42: =+N42+Y42 -> #REF! | D42: =+O42+Z42 -> #REF! | E42: =+P42+AA42 -> #REF! | F42: =+D42+E42 -> #REF! | G42: =+R42+AC42 -> #REF! | H42: =+S42+AD42 -> #REF! | I42: =+G42+H42 -> #REF! | J42: =+I42/C42 -> #REF! | K42: =+I42/F42 -> #REF! | M42: MBQ | N42: =+#REF! -> #REF! | O42: =+#REF! -> #REF! | P42: =+#REF! -> #REF! | Q42: =+O42+P42 -> #REF! | R42: =+#REF! -> #REF! | S42: =+#REF! -> #REF! | T42: =+R42+S42 -> #REF! | U42: =+T42/N42 -> #REF! | V42: =+T42/Q42 -> #REF! | X42: MBQ | Y42: =+#REF! -> #REF! | Z42: =+#REF! -> #REF! | AB42: =+Z42+AA42 -> #REF! | AC42: =+#REF! -> #REF! | AD42: =+#REF! -> #REF! | AE42: =+AC42+AD42 -> #REF! | AF42: =+AE42/Y42 -> #REF! | AG42: =+AE42/AB42 -> #REF!
B43: VOLVO | C43: =+N43+Y43 -> #REF! | D43: =+O43+Z43 -> #REF! | E43: =+P43+AA43 -> #REF! | F43: =+D43+E43 -> #REF! | G43: =+R43+AC43 -> #REF! | H43: =+S43+AD43 -> #REF! | I43: =+G43+H43 -> #REF! | J43: =+I43/C43 -> #REF! | K43: =+I43/F43 -> #REF! | M43: VOLVO | N43: =+#REF! -> #REF! | O43: =+#REF! -> #REF! | P43: =+#REF! -> #REF! | Q43: =+O43+P43 -> #REF! | R43: =+#REF! -> #REF! | S43: =+#REF! -> #REF! | T43: =+R43+S43 -> #REF! | U43: =+T43/N43 -> #REF! | V43: =+T43/Q43 -> #REF! | X43: VOLVO | Y43: =+#REF! -> #REF! | Z43: =+#REF! -> #REF! | AB43: =+Z43+AA43 -> #REF! | AC43: =+#REF! -> #REF! | AD43: =+#REF! -> #REF! | AE43: =+AC43+AD43 -> #REF! | AF43: =+AE43/Y43 -> #REF! | AG43: =+AE43/AB43 -> #REF!
B44: JLR | C44: =+N44+Y44 -> #REF! | D44: =+O44+Z44 -> #REF! | E44: =+P44+AA44 -> #REF! | F44: =+D44+E44 -> #REF! | G44: =+R44+AC44 -> #REF! | H44: =+S44+AD44 -> #REF! | I44: =+G44+H44 -> #REF! | J44: =+I44/C44 -> #REF! | K44: =+I44/F44 -> #REF! | M44: JLR | N44: =+#REF! -> #REF! | O44: =+#REF! -> #REF! | P44: =+#REF! -> #REF! | Q44: =+O44+P44 -> #REF! | R44: =+#REF! -> #REF! | S44: =+#REF! -> #REF! | T44: =+R44+S44 -> #REF! | U44: =+T44/N44 -> #REF! | V44: =+T44/Q44 -> #REF! | X44: JLR | Y44: =+#REF! -> #REF! | Z44: =+#REF! -> #REF! | AB44: =+Z44+AA44 -> #REF! | AC44: =+#REF! -> #REF! | AD44: =+#REF! -> #REF! | AE44: =+AC44+AD44 -> #REF! | AF44: =+AE44/Y44 -> #REF! | AG44: =+AE44/AB44 -> #REF!
B45: LHD | C45: =+N45+Y45 -> #REF! | D45: =+O45+Z45 -> #REF! | E45: =+P45+AA45 -> #REF! | F45: =+D45+E45 -> #REF! | G45: =+R45+AC45 -> #REF! | H45: =+S45+AD45 -> #REF! | I45: =+G45+H45 -> #REF! | J45: =+I45/C45 -> #REF! | K45: =+I45/F45 -> #REF! | M45: LHD | N45: =+#REF! -> #REF! | O45: =+#REF! -> #REF! | P45: =+#REF! -> #REF! | Q45: =+O45+P45 -> #REF! | R45: =+#REF! -> #REF! | S45: =+#REF! -> #REF! | T45: =+R45+S45 -> #REF! | U45: =+T45/N45 -> #REF! | V45: =+T45/Q45 -> #REF! | X45: LHD | Y45: =+#REF! -> #REF! | Z45: =+#REF! -> #REF! | AB45: =+Z45+AA45 -> #REF! | AC45: =+#REF! -> #REF! | AD45: =+#REF! -> #REF! | AE45: =+AC45+AD45 -> #REF! | AF45: =+AE45/Y45 -> #REF! | AG45: =+AE45/AB45 -> #REF!
B47: 2019 | M47: 2019 | X47: 2019
B48: STORE | C48: Units | D48: Margin | E48: Margin demo | F48: Front margin | G48: frais de livraison | H48: Ent. Stock | I48: Delivery fee | J48: Delivery fee / unit | K48: % Delivery fee / Front margin | M48: STORE | N48: Units | O48: M. new | P48: M. Demos | Q48: Front margin | R48: frais de livraison | S48: Ent. Stock | T48: Delivery fee | U48: Delivery fee / unit | V48: % Delivery fee / Front margin | X48: STORE | Y48: Units | Z48: M. used | AB48: Front margin | AC48: frais de livraison | AD48: Ent. Stock | AE48: Delivery fee | AF48: Delivery fee / unit | AG48: % Delivery fee / Front margin
B49: TOTAL | C49: =+SUM(C50:C67) -> #REF! | D49: =+SUM(D50:D67) -> #REF! | E49: =+SUM(E50:E67) -> #REF! | F49: =+SUM(F50:F67) -> #REF! | G49: =+SUM(G50:G67) -> #REF! | H49: =+SUM(H50:H67) -> #REF! | I49: =+SUM(I50:I67) -> #REF! | J49: =+I49/C49 -> #REF! | K49: =+I49/F49 -> #REF! | M49: TOTAL | N49: =+SUM(N50:N67) -> #REF! | O49: =+SUM(O50:O67) -> #REF! | P49: =+SUM(P50:P67) -> #REF! | Q49: =+SUM(Q50:Q67) -> #REF! | R49: =+SUM(R50:R67) -> #REF! | S49: =+SUM(S50:S67) -> #REF! | T49: =+SUM(T50:T67) -> #REF! | U49: =+T49/N49 -> #REF! | V49: =+T49/Q49 -> #REF! | X49: TOTAL | Y49: =+SUM(Y50:Y67) -> #REF! | Z49: =+SUM(Z50:Z67) -> #REF! | AB49: =+SUM(AB50:AB67) -> #REF! | AC49: =+SUM(AC50:AC67) -> #REF! | AD49: =+SUM(AD50:AD67) -> #REF! | AE49: =+SUM(AE50:AE67) -> #REF! | AF49: =+AE49/Y49 -> #REF! | AG49: =+AE49/AB49 -> #REF!
B50: AUDI | C50: =+N50+Y50 -> #REF! | D50: =+O50+Z50 -> #REF! | E50: =+P50+AA50 -> #REF! | F50: =+D50+E50 -> #REF! | G50: =+R50+AC50 -> #REF! | H50: =+S50+AD50 -> #REF! | I50: =+G50+H50 -> #REF! | J50: =+I50/C50 -> #REF! | K50: =+I50/F50 -> #REF! | M50: AUDI | N50: =+#REF! -> #REF! | O50: =+#REF! -> #REF! | P50: =+#REF! -> #REF! | Q50: =+O50+P50 -> #REF! | R50: =+#REF! -> #REF! | S50: =+#REF! -> #REF! | T50: =+R50+S50 -> #REF! | U50: =+T50/N50 -> #REF! | V50: =+T50/Q50 -> #REF! | X50: AUDI | Y50: =+#REF! -> #REF! | Z50: =+#REF! -> #REF! | AB50: =+Z50+AA50 -> #REF! | AC50: =+#REF! -> #REF! | AD50: =+#REF! -> #REF! | AE50: =+AC50+AD50 -> #REF! | AF50: =+AE50/Y50 -> #REF! | AG50: =+AE50/AB50 -> #REF!
B51: INFINITI | C51: =+N51+Y51 -> #REF! | D51: =+O51+Z51 -> #REF! | E51: =+P51+AA51 -> #REF! | F51: =+D51+E51 -> #REF! | G51: =+R51+AC51 -> #REF! | H51: =+S51+AD51 -> #REF! | I51: =+G51+H51 -> #REF! | J51: =+I51/C51 -> #REF! | K51: =+I51/F51 -> #REF! | M51: INFINITI | N51: =+#REF! -> #REF! | O51: =+#REF! -> #REF! | P51: =+#REF! -> #REF! | Q51: =+O51+P51 -> #REF! | R51: =+#REF! -> #REF! | S51: =+#REF! -> #REF! | T51: =+R51+S51 -> #REF! | U51: =+T51/N51 -> #REF! | V51: =+T51/Q51 -> #REF! | X51: INFINITI | Y51: =+#REF! -> #REF! | Z51: =+#REF! -> #REF! | AB51: =+Z51+AA51 -> #REF! | AC51: =+#REF! -> #REF! | AD51: =+#REF! -> #REF! | AE51: =+AC51+AD51 -> #REF! | AF51: =+AE51/Y51 -> #REF! | AG51: =+AE51/AB51 -> #REF!
B52: MCPA LAP | C52: =+N52+Y52 -> #REF! | D52: =+O52+Z52 -> #REF! | E52: =+P52+AA52 -> 0 | F52: =+D52+E52 -> #REF! | G52: =+R52+AC52 -> #REF! | H52: =+S52+AD52 -> #REF! | I52: =+G52+H52 -> #REF! | J52: =+I52/C52 -> #REF! | K52: =+I52/F52 -> #REF! | X52: MCPA LAP | Y52: =+#REF! -> #REF! | Z52: =+#REF! -> #REF! | AB52: =+Z52+AA52 -> #REF! | AC52: =+#REF! -> #REF! | AD52: =+#REF! -> #REF! | AE52: =+AC52+AD52 -> #REF! | AF52: =+AE52/Y52 -> #REF! | AG52: =+AE52/AB52 -> #REF!
B53: MCPA LAV | C53: =+N53+Y53 -> #REF! | D53: =+O53+Z53 -> #REF! | E53: =+P53+AA53 -> 0 | F53: =+D53+E53 -> #REF! | G53: =+R53+AC53 -> #REF! | H53: =+S53+AD53 -> #REF! | I53: =+G53+H53 -> #REF! | J53: =+I53/C53 -> #REF! | K53: =+I53/F53 -> #REF! | X53: MCPA LAV | Y53: =+#REF! -> #REF! | Z53: =+#REF! -> #REF! | AB53: =+Z53+AA53 -> #REF! | AC53: =+#REF! -> #REF! | AD53: =+#REF! -> #REF! | AE53: =+AC53+AD53 -> #REF! | AF53: =+AE53/Y53 -> #REF! | AG53: =+AE53/AB53 -> #REF!
B54: MCPA SPE | C54: =+N54+Y54 -> #REF! | D54: =+O54+Z54 -> #REF! | E54: =+P54+AA54 -> 0 | F54: =+D54+E54 -> #REF! | G54: =+R54+AC54 -> #REF! | H54: =+S54+AD54 -> #REF! | I54: =+G54+H54 -> #REF! | J54: =+I54/C54 -> #REF! | K54: =+I54/F54 -> #REF! | X54: MCPA SPE | Y54: =+#REF! -> #REF! | Z54: =+#REF! -> #REF! | AB54: =+Z54+AA54 -> #REF! | AC54: =+#REF! -> #REF! | AD54: =+#REF! -> #REF! | AE54: =+AC54+AD54 -> #REF! | AF54: =+AE54/Y54 -> #REF! | AG54: =+AE54/AB54 -> #REF!
B55: HONDA | C55: =+N55+Y55 -> #REF! | D55: =+O55+Z55 -> #REF! | E55: =+P55+AA55 -> #REF! | F55: =+D55+E55 -> #REF! | G55: =+R55+AC55 -> #REF! | H55: =+S55+AD55 -> #REF! | I55: =+G55+H55 -> #REF! | J55: =+I55/C55 -> #REF! | K55: =+I55/F55 -> #REF! | M55: HONDA | N55: =+#REF! -> #REF! | O55: =+#REF! -> #REF! | P55: =+#REF! -> #REF! | Q55: =+O55+P55 -> #REF! | R55: =+#REF! -> #REF! | S55: =+#REF! -> #REF! | T55: =+R55+S55 -> #REF! | U55: =+T55/N55 -> #REF! | V55: =+T55/Q55 -> #REF! | X55: HONDA | Y55: =+#REF! -> #REF! | Z55: =+#REF! -> #REF! | AB55: =+Z55+AA55 -> #REF! | AC55: =+#REF! -> #REF! | AD55: =+#REF! -> #REF! | AE55: =+AC55+AD55 -> #REF! | AF55: =+AE55/Y55 -> #REF! | AG55: =+AE55/AB55 -> #REF!
B56: TOYOTA | C56: =+N56+Y56 -> #REF! | D56: =+O56+Z56 -> #REF! | E56: =+P56+AA56 -> #REF! | F56: =+D56+E56 -> #REF! | G56: =+R56+AC56 -> #REF! | H56: =+S56+AD56 -> #REF! | I56: =+G56+H56 -> #REF! | J56: =+I56/C56 -> #REF! | K56: =+I56/F56 -> #REF! | M56: TOYOTA | N56: =+#REF! -> #REF! | O56: =+#REF! -> #REF! | P56: =+#REF! -> #REF! | Q56: =+O56+P56 -> #REF! | R56: =+#REF! -> #REF! | S56: =+#REF! -> #REF! | T56: =+R56+S56 -> #REF! | U56: =+T56/N56 -> #REF! | V56: =+T56/Q56 -> #REF! | X56: TOYOTA | Y56: =+#REF! -> #REF! | Z56: =+#REF! -> #REF! | AB56: =+Z56+AA56 -> #REF! | AC56: =+#REF! -> #REF! | AD56: =+#REF! -> #REF! | AE56: =+AC56+AD56 -> #REF! | AF56: =+AE56/Y56 -> #REF! | AG56: =+AE56/AB56 -> #REF!
B57: VOLKS | C57: =+N57+Y57 -> #REF! | D57: =+O57+Z57 -> #REF! | E57: =+P57+AA57 -> #REF! | F57: =+D57+E57 -> #REF! | G57: =+R57+AC57 -> #REF! | H57: =+S57+AD57 -> #REF! | I57: =+G57+H57 -> #REF! | J57: =+I57/C57 -> #REF! | K57: =+I57/F57 -> #REF! | M57: VOLKS | N57: =+#REF! -> #REF! | O57: =+#REF! -> #REF! | P57: =+#REF! -> #REF! | Q57: =+O57+P57 -> #REF! | R57: =+#REF! -> #REF! | S57: =+#REF! -> #REF! | T57: =+R57+S57 -> #REF! | U57: =+T57/N57 -> #REF! | V57: =+T57/Q57 -> #REF! | X57: VOLKS | Y57: =+#REF! -> #REF! | Z57: =+#REF! -> #REF! | AB57: =+Z57+AA57 -> #REF! | AC57: =+#REF! -> #REF! | AD57: =+#REF! -> #REF! | AE57: =+AC57+AD57 -> #REF! | AF57: =+AE57/Y57 -> #REF! | AG57: =+AE57/AB57 -> #REF!
B58: BMW PA | C58: =+N58+Y58 -> #REF! | D58: =+O58+Z58 -> #REF! | E58: =+P58+AA58 -> #REF! | F58: =+D58+E58 -> #REF! | G58: =+R58+AC58 -> #REF! | H58: =+S58+AD58 -> #REF! | I58: =+G58+H58 -> #REF! | J58: =+I58/C58 -> #REF! | K58: =+I58/F58 -> #REF! | M58: BMW PA | N58: =+#REF! -> #REF! | O58: =+#REF! -> #REF! | P58: =+#REF! -> #REF! | Q58: =+O58+P58 -> #REF! | R58: =+#REF! -> #REF! | S58: =+#REF! -> #REF! | T58: =+R58+S58 -> #REF! | U58: =+T58/N58 -> #REF! | V58: =+T58/Q58 -> #REF! | X58: BMW PA | Y58: =+#REF! -> #REF! | Z58: =+#REF! -> #REF! | AB58: =+Z58+AA58 -> #REF! | AC58: =+#REF! -> #REF! | AD58: =+#REF! -> #REF! | AE58: =+AC58+AD58 -> #REF! | AF58: =+AE58/Y58 -> #REF! | AG58: =+AE58/AB58 -> #REF!
B59: MINI | C59: =+N59+Y59 -> #REF! | D59: =+O59+Z59 -> #REF! | E59: =+P59+AA59 -> #REF! | F59: =+D59+E59 -> #REF! | G59: =+R59+AC59 -> #REF! | H59: =+S59+AD59 -> #REF! | I59: =+G59+H59 -> #REF! | J59: =+I59/C59 -> #REF! | K59: =+I59/F59 -> #REF! | M59: MINI | N59: =+#REF! -> #REF! | O59: =+#REF! -> #REF! | P59: =+#REF! -> #REF! | Q59: =+O59+P59 -> #REF! | R59: =+#REF! -> #REF! | S59: =+#REF! -> #REF! | T59: =+R59+S59 -> #REF! | U59: =+T59/N59 -> #REF! | V59: =+T59/Q59 -> #REF! | X59: MINI | Y59: =+#REF! -> #REF! | Z59: =+#REF! -> #REF! | AB59: =+Z59+AA59 -> #REF! | AC59: =+#REF! -> #REF! | AD59: =+#REF! -> #REF! | AE59: =+AC59+AD59 -> #REF! | AF59: =+AE59/Y59 -> #REF! | AG59: =+AE59/AB59 -> #REF!
B60: BMW STJ | C60: =+N60+Y60 -> #REF! | D60: =+O60+Z60 -> #REF! | E60: =+P60+AA60 -> #REF! | F60: =+D60+E60 -> #REF! | G60: =+R60+AC60 -> #REF! | H60: =+S60+AD60 -> #REF! | I60: =+G60+H60 -> #REF! | J60: =+I60/C60 -> #REF! | K60: =+I60/F60 -> #REF! | M60: BMW STJ | N60: =+#REF! -> #REF! | O60: =+#REF! -> #REF! | P60: =+#REF! -> #REF! | Q60: =+O60+P60 -> #REF! | R60: =+#REF! -> #REF! | S60: =+#REF! -> #REF! | T60: =+R60+S60 -> #REF! | U60: =+T60/N60 -> #REF! | V60: =+T60/Q60 -> #REF! | X60: BMW STJ | Y60: =+#REF! -> #REF! | Z60: =+#REF! -> #REF! | AB60: =+Z60+AA60 -> #REF! | AC60: =+#REF! -> #REF! | AD60: =+#REF! -> #REF! | AE60: =+AC60+AD60 -> #REF! | AF60: =+AE60/Y60 -> #REF! | AG60: =+AE60/AB60 -> #REF!
B61: LEXUS | C61: =+N61+Y61 -> #REF! | D61: =+O61+Z61 -> #REF! | E61: =+P61+AA61 -> #REF! | F61: =+D61+E61 -> #REF! | G61: =+R61+AC61 -> #REF! | H61: =+S61+AD61 -> #REF! | I61: =+G61+H61 -> #REF! | J61: =+I61/C61 -> #REF! | K61: =+I61/F61 -> #REF! | M61: LEXUS | N61: =+#REF! -> #REF! | O61: =+#REF! -> #REF! | P61: =+#REF! -> #REF! | Q61: =+O61+P61 -> #REF! | R61: =+#REF! -> #REF! | S61: =+#REF! -> #REF! | T61: =+R61+S61 -> #REF! | U61: =+T61/N61 -> #REF! | V61: =+T61/Q61 -> #REF! | X61: LEXUS | Y61: =+#REF! -> #REF! | Z61: =+#REF! -> #REF! | AB61: =+Z61+AA61 -> #REF! | AC61: =+#REF! -> #REF! | AD61: =+#REF! -> #REF! | AE61: =+AC61+AD61 -> #REF! | AF61: =+AE61/Y61 -> #REF! | AG61: =+AE61/AB61 -> #REF!
B62: BMW SHER | C62: =+N62+Y62 -> #REF! | D62: =+O62+Z62 -> #REF! | E62: =+P62+AA62 -> #REF! | F62: =+D62+E62 -> #REF! | G62: =+R62+AC62 -> #REF! | H62: =+S62+AD62 -> #REF! | I62: =+G62+H62 -> #REF! | J62: =+I62/C62 -> #REF! | K62: =+I62/F62 -> #REF! | M62: BMW SHER | N62: =+#REF! -> #REF! | O62: =+#REF! -> #REF! | P62: =+#REF! -> #REF! | Q62: =+O62+P62 -> #REF! | R62: =+#REF! -> #REF! | S62: =+#REF! -> #REF! | T62: =+R62+S62 -> #REF! | U62: =+T62/N62 -> #REF! | V62: =+T62/Q62 -> #REF! | X62: BMW SHER | Y62: =+#REF! -> #REF! | Z62: =+#REF! -> #REF! | AB62: =+Z62+AA62 -> #REF! | AC62: =+#REF! -> #REF! | AD62: =+#REF! -> #REF! | AE62: =+AC62+AD62 -> #REF! | AF62: =+AE62/Y62 -> #REF! | AG62: =+AE62/AB62 -> #REF!
B63: SSMB | C63: =+N63+Y63 -> #REF! | D63: =+O63+Z63 -> #REF! | E63: =+P63+AA63 -> #REF! | F63: =+D63+E63 -> #REF! | G63: =+R63+AC63 -> #REF! | H63: =+S63+AD63 -> #REF! | I63: =+G63+H63 -> #REF! | J63: =+I63/C63 -> #REF! | K63: =+I63/F63 -> #REF! | M63: SSMB | N63: =+#REF! -> #REF! | O63: =+#REF! -> #REF! | P63: =+#REF! -> #REF! | Q63: =+O63+P63 -> #REF! | R63: =+#REF! -> #REF! | S63: =+#REF! -> #REF! | T63: =+R63+S63 -> #REF! | U63: =+T63/N63 -> #REF! | V63: =+T63/Q63 -> #REF! | X63: SSMB | Y63: =+#REF! -> #REF! | Z63: =+#REF! -> #REF! | AB63: =+Z63+AA63 -> #REF! | AC63: =+#REF! -> #REF! | AD63: =+#REF! -> #REF! | AE63: =+AC63+AD63 -> #REF! | AF63: =+AE63/Y63 -> #REF! | AG63: =+AE63/AB63 -> #REF!
B64: MBQ | C64: =+N64+Y64 -> #REF! | D64: =+O64+Z64 -> #REF! | E64: =+P64+AA64 -> #REF! | F64: =+D64+E64 -> #REF! | G64: =+R64+AC64 -> #REF! | H64: =+S64+AD64 -> #REF! | I64: =+G64+H64 -> #REF! | J64: =+I64/C64 -> #REF! | K64: =+I64/F64 -> #REF! | M64: MBQ | N64: =+#REF! -> #REF! | O64: =+#REF! -> #REF! | P64: =+#REF! -> #REF! | Q64: =+O64+P64 -> #REF! | R64: =+#REF! -> #REF! | S64: =+#REF! -> #REF! | T64: =+R64+S64 -> #REF! | U64: =+T64/N64 -> #REF! | V64: =+T64/Q64 -> #REF! | X64: MBQ | Y64: =+#REF! -> #REF! | Z64: =+#REF! -> #REF! | AB64: =+Z64+AA64 -> #REF! | AC64: =+#REF! -> #REF! | AD64: =+#REF! -> #REF! | AE64: =+AC64+AD64 -> #REF! | AF64: =+AE64/Y64 -> #REF! | AG64: =+AE64/AB64 -> #REF!
B65: VOLVO | C65: =+N65+Y65 -> #REF! | D65: =+O65+Z65 -> #REF! | E65: =+P65+AA65 -> #REF! | F65: =+D65+E65 -> #REF! | G65: =+R65+AC65 -> #REF! | H65: =+S65+AD65 -> #REF! | I65: =+G65+H65 -> #REF! | J65: =+I65/C65 -> #REF! | K65: =+I65/F65 -> #REF! | M65: VOLVO | N65: =+#REF! -> #REF! | O65: =+#REF! -> #REF! | P65: =+#REF! -> #REF! | Q65: =+O65+P65 -> #REF! | R65: =+#REF! -> #REF! | S65: =+#REF! -> #REF! | T65: =+R65+S65 -> #REF! | U65: =+T65/N65 -> #REF! | V65: =+T65/Q65 -> #REF! | X65: VOLVO | Y65: =+#REF! -> #REF! | Z65: =+#REF! -> #REF! | AB65: =+Z65+AA65 -> #REF! | AC65: =+#REF! -> #REF! | AD65: =+#REF! -> #REF! | AE65: =+AC65+AD65 -> #REF! | AF65: =+AE65/Y65 -> #REF! | AG65: =+AE65/AB65 -> #REF!
B66: JLR | C66: =+N66+Y66 -> #REF! | D66: =+O66+Z66 -> #REF! | E66: =+P66+AA66 -> #REF! | F66: =+D66+E66 -> #REF! | G66: =+R66+AC66 -> #REF! | H66: =+S66+AD66 -> #REF! | I66: =+G66+H66 -> #REF! | J66: =+I66/C66 -> #REF! | K66: =+I66/F66 -> #REF! | M66: JLR | N66: =+#REF! -> #REF! | O66: =+#REF! -> #REF! | P66: =+#REF! -> #REF! | Q66: =+O66+P66 -> #REF! | R66: =+#REF! -> #REF! | S66: =+#REF! -> #REF! | T66: =+R66+S66 -> #REF! | U66: =+T66/N66 -> #REF! | V66: =+T66/Q66 -> #REF! | X66: JLR | Y66: =+#REF! -> #REF! | Z66: =+#REF! -> #REF! | AB66: =+Z66+AA66 -> #REF! | AC66: =+#REF! -> #REF! | AD66: =+#REF! -> #REF! | AE66: =+AC66+AD66 -> #REF! | AF66: =+AE66/Y66 -> #REF! | AG66: =+AE66/AB66 -> #REF!
B67: LHD | C67: =+N67+Y67 -> #REF! | D67: =+O67+Z67 -> #REF! | E67: =+P67+AA67 -> #REF! | F67: =+D67+E67 -> #REF! | G67: =+R67+AC67 -> #REF! | H67: =+S67+AD67 -> #REF! | I67: =+G67+H67 -> #REF! | J67: =+I67/C67 -> #REF! | K67: =+I67/F67 -> #REF! | M67: LHD | N67: =+#REF! -> #REF! | O67: =+#REF! -> #REF! | P67: =+#REF! -> #REF! | Q67: =+O67+P67 -> #REF! | R67: =+#REF! -> #REF! | S67: =+#REF! -> #REF! | T67: =+R67+S67 -> #REF! | U67: =+T67/N67 -> #REF! | V67: =+T67/Q67 -> #REF! | X67: LHD | Y67: =+#REF! -> #REF! | Z67: =+#REF! -> #REF! | AB67: =+Z67+AA67 -> #REF! | AC67: =+#REF! -> #REF! | AD67: =+#REF! -> #REF! | AE67: =+AC67+AD67 -> #REF! | AF67: =+AE67/Y67 -> #REF! | AG67: =+AE67/AB67 -> #REF!

Sheet Mensuel
C1: Réalisé Annuel | D1: Janvier | G1: Février | J1: Mars | M1: Avril | P1: Mai | S1: Juin | V1: Juillet | Y1: Août | AB1: Septembre | AE1: Octobre | AH1: Novembre | AK1: Décembre | AN1: Total (YTD)
D2: 1 | G2: 2 | J2: 3 | M2: 4 | P2: 5 | S2: 6 | V2: 7 | Y2: 8 | AB2: 9 | AE2: 10 | AH2: 11 | AK2: 12
C3: Véhicules neufs | D3: RÉALISATION | G3: RÉALISATION | J3: RÉALISATION | M3: RÉALISATION | P3: RÉALISATION | S3: RÉALISATION | V3: RÉALISATION | Y3: RÉALISATION | AB3: RÉALISATION | AE3: RÉALISATION | AH3: RÉALISATION | AK3: RÉALISATION | AN3: RÉALISATION
D4: UNITE | E4: $P/UNITE | F4: $PROFITS | G4: UNITE | H4: $P/UNITE | I4: $PROFITS | J4: UNITE | K4: $P/UNITE | L4: $PROFITS | M4: UNITE | N4: $P/UNITE | O4: $PROFITS | P4: UNITE | Q4: $P/UNITE | R4: $PROFITS | S4: UNITE | T4: $P/UNITE | U4: $PROFITS | V4: UNITE | W4: $P/UNITE | X4: $PROFITS | Y4: UNITE | Z4: $P/UNITE | AA4: $PROFITS | AB4: UNITE | AC4: $P/UNITE | AD4: $PROFITS | AE4: UNITE | AF4: $P/UNITE | AG4: $PROFITS | AH4: UNITE | AI4: $P/UNITE | AJ4: $PROFITS | AK4: UNITE | AL4: $P/UNITE | AM4: $PROFITS | AN4: UNITE | AO4: $P/UNITE | AP4: $PROFITS
A5: =+B5&C5 -> Véhicules neufsVentes nettes | B5: Véhicules neufs | C5: Ventes nettes | F5: ='1'!$L$5 -> 1000810 | I5: ='2'!$L$5 -> 2019283.1 | L5: ='3'!$L$5 -> 3240605.2 | O5: ='4'!$L$5 -> 3185397.8 | R5: ='5'!$L$5 -> 3760930 | U5: ='6'!$L$5 -> 2741022.2 | X5: ='7'!$L$5 -> 18845742 | AA5: ='8'!$L$5 -> 22095178 | AD5: ='9'!$L$5 -> 0 | AG5: ='10'!$L$5 -> 0 | AJ5: ='11'!$L$5 -> 0 | AM5: ='12'!$L$5 -> 0 | AP5: =SUM(F5,I5,L5,O5,R5,U5,X5,AA5,AD5,AG5,AJ5,AM5) -> 56888968
A6: =+B6&C6 -> Véhicules neufsAutos détail | B6: Véhicules neufs | C6: Autos détail | D6: ='1'!$J$6 -> 7 | E6: =IF(D6=0,0,F6/D6) -> 590.46 | F6: ='1'!$L$6 -> 4133.22 | G6: ='2'!$J$6 -> 15 | H6: =IF(G6=0,0,I6/G6) -> 1396.284 | I6: ='2'!$L$6 -> 20944.26 | J6: ='3'!$J$6 -> 32 | K6: =IF(J6=0,0,L6/J6) -> 1097.7472 | L6: ='3'!$L$6 -> 35127.91 | M6: ='4'!$J$6 -> 24 | N6: =IF(M6=0,0,O6/M6) -> 474.33792 | O6: ='4'!$L$6 -> 11384.11 | P6: ='5'!$J$6 -> 25 | Q6: =IF(P6=0,0,R6/P6) -> 1020.836 | R6: ='5'!$L$6 -> 25520.9 | S6: ='6'!$J$6 -> 23 | T6: =IF(S6=0,0,U6/S6) -> 1164.0583 | U6: ='6'!$L$6 -> 26773.34 | V6: ='7'!$J$6 -> 150 | W6: =IF(V6=0,0,X6/V6) -> 1030.7103 | X6: ='7'!$L$6 -> 154606.55 | Y6: ='8'!$J$6 -> 174 | Z6: =IF(Y6=0,0,AA6/Y6) -> 1036.2561 | AA6: ='8'!$L$6 -> 180308.56 | AB6: ='9'!$J$6 -> 0 | AC6: =IF(AB6=0,0,AD6/AB6) -> 0 | AD6: ='9'!$L$6 -> 0 | AE6: ='10'!$J$6 -> 0 | AF6: =IF(AE6=0,0,AG6/AE6) -> 0 | AG6: ='10'!$L$6 -> 0 | AH6: ='11'!$J$6 -> 0 | AI6: =IF(AH6=0,0,AJ6/AH6) -> 0 | AJ6: ='11'!$L$6 -> 0 | AK6: ='12'!$J$6 -> 0 | AL6: =IF(AK6=0,0,AM6/AK6) -> 0 | AM6: ='12'!$L$6 -> 0 | AN6: =SUM(D6,G6,J6,M6,P6,S6,V6,Y6,AB6,AE6,AH6,AK6) -> 450 | AO6: =IF(AN6=0,0,AP6/AN6) -> 1019.553 | AP6: =SUM(F6,I6,L6,O6,R6,U6,X6,AA6,AD6,AG6,AJ6,AM6) -> 458798.85
A7: =+B7&C7 -> Véhicules neufsCamions détail | B7: Véhicules neufs | C7: Camions détail | D7: ='1'!$J$7 -> 13 | E7: =IF(D7=0,0,F7/D7) -> 1549.7277 | F7: ='1'!$L$7 -> 20146.46 | G7: ='2'!$J$7 -> 21 | H7: =IF(G7=0,0,I7/G7) -> 2079.4924 | I7: ='2'!$L$7 -> 43669.34 | J7: ='3'!$J$7 -> 37 | K7: =IF(J7=0,0,L7/J7) -> 2171.0773 | L7: ='3'!$L$7 -> 80329.86 | M7: ='4'!$J$7 -> 41 | N7: =IF(M7=0,0,O7/M7) -> 2167.9161 | O7: ='4'!$L$7 -> 88884.56 | P7: ='5'!$J$7 -> 58 | Q7: =IF(P7=0,0,R7/P7) -> 2126.4852 | R7: ='5'!$L$7 -> 123336.14 | S7: ='6'!$J$7 -> 32 | T7: =IF(S7=0,0,U7/S7) -> 2323.7591 | U7: ='6'!$L$7 -> 74360.29 | V7: ='7'!$J$7 -> 239 | W7: =IF(V7=0,0,X7/V7) -> 2180.0418 | X7: ='7'!$L$7 -> 521029.98 | Y7: ='8'!$J$7 -> 278 | Z7: =IF(Y7=0,0,AA7/Y7) -> 2164.2449 | AA7: ='8'!$L$7 -> 601660.08 | AB7: ='9'!$J$7 -> 0 | AC7: =IF(AB7=0,0,AD7/AB7) -> 0 | AD7: ='9'!$L$7 -> 0 | AE7: ='10'!$J$7 -> 0 | AF7: =IF(AE7=0,0,AG7/AE7) -> 0 | AG7: ='10'!$L$7 -> 0 | AH7: ='11'!$J$7 -> 0 | AI7: =IF(AH7=0,0,AJ7/AH7) -> 0 | AJ7: ='11'!$L$7 -> 0 | AK7: ='12'!$J$7 -> 0 | AL7: =IF(AK7=0,0,AM7/AK7) -> 0 | AM7: ='12'!$L$7 -> 0 | AN7: =SUM(D7,G7,J7,M7,P7,S7,V7,Y7,AB7,AE7,AH7,AK7) -> 719 | AO7: =IF(AN7=0,0,AP7/AN7) -> 2160.5239 | AP7: =SUM(F7,I7,L7,O7,R7,U7,X7,AA7,AD7,AG7,AJ7,AM7) -> 1553416.7
A8: =+B8&C8 -> Véhicules neufsSprinter | B8: Véhicules neufs | C8: Sprinter | D8: ='1'!$J$8 -> 0 | E8: =IF(D8=0,0,F8/D8) -> 0 | F8: ='1'!$L$8 -> 0 | G8: ='2'!$J$8 -> 0 | H8: =IF(G8=0,0,I8/G8) -> 0 | I8: ='2'!$L$8 -> 0 | J8: ='3'!$J$8 -> 0 | K8: =IF(J8=0,0,L8/J8) -> 0 | L8: ='3'!$L$8 -> 0 | M8: ='4'!$J$8 -> 0 | N8: =IF(M8=0,0,O8/M8) -> 0 | O8: ='4'!$L$8 -> 0 | P8: ='5'!$J$8 -> 0 | Q8: =IF(P8=0,0,R8/P8) -> 0 | R8: ='5'!$L$8 -> 0 | S8: ='6'!$J$8 -> 0 | T8: =IF(S8=0,0,U8/S8) -> 0 | U8: ='6'!$L$8 -> 0 | V8: ='7'!$J$8 -> 0 | W8: =IF(V8=0,0,X8/V8) -> 0 | X8: ='7'!$L$8 -> 0 | Y8: ='8'!$J$8 -> 0 | Z8: =IF(Y8=0,0,AA8/Y8) -> 0 | AA8: ='8'!$L$8 -> 0 | AB8: ='9'!$J$8 -> 0 | AC8: =IF(AB8=0,0,AD8/AB8) -> 0 | AD8: ='9'!$L$8 -> 0 | AE8: ='10'!$J$8 -> 0 | AF8: =IF(AE8=0,0,AG8/AE8) -> 0 | AG8: ='10'!$L$8 -> 0 | AH8: ='11'!$J$8 -> 0 | AI8: =IF(AH8=0,0,AJ8/AH8) -> 0 | AJ8: ='11'!$L$8 -> 0 | AK8: ='12'!$J$8 -> 0 | AL8: =IF(AK8=0,0,AM8/AK8) -> 0 | AM8: ='12'!$L$8 -> 0 | AN8: =SUM(D8,G8,J8,M8,P8,S8,V8,Y8,AB8,AE8,AH8,AK8) -> 0 | AO8: =IF(AN8=0,0,AP8/AN8) -> 0 | AP8: =SUM(F8,I8,L8,O8,R8,U8,X8,AA8,AD8,AG8,AJ8,AM8) -> 0
A9: =+B9&C9 -> Véhicules neufsMoto détail | B9: Véhicules neufs | C9: Moto détail | D9: ='1'!$J$9 -> 0 | E9: =IF(D9=0,0,F9/D9) -> 0 | F9: ='1'!$L$9 -> 0 | G9: ='2'!$J$9 -> 0 | H9: =IF(G9=0,0,I9/G9) -> 0 | I9: ='2'!$L$9 -> 0 | J9: ='3'!$J$9 -> 0 | K9: =IF(J9=0,0,L9/J9) -> 0 | L9: ='3'!$L$9 -> 0 | M9: ='4'!$J$9 -> 0 | N9: =IF(M9=0,0,O9/M9) -> 0 | O9: ='4'!$L$9 -> 0 | P9: ='5'!$J$9 -> 0 | Q9: =IF(P9=0,0,R9/P9) -> 0 | R9: ='5'!$L$9 -> 0 | S9: ='6'!$J$9 -> 0 | T9: =IF(S9=0,0,U9/S9) -> 0 | U9: ='6'!$L$9 -> 0 | V9: ='7'!$J$9 -> 0 | W9: =IF(V9=0,0,X9/V9) -> 0 | X9: ='7'!$L$9 -> 0 | Y9: ='8'!$J$9 -> 0 | Z9: =IF(Y9=0,0,AA9/Y9) -> 0 | AA9: ='8'!$L$9 -> 0 | AB9: ='9'!$J$9 -> 0 | AC9: =IF(AB9=0,0,AD9/AB9) -> 0 | AD9: ='9'!$L$9 -> 0 | AE9: ='10'!$J$9 -> 0 | AF9: =IF(AE9=0,0,AG9/AE9) -> 0 | AG9: ='10'!$L$9 -> 0 | AH9: ='11'!$J$9 -> 0 | AI9: =IF(AH9=0,0,AJ9/AH9) -> 0 | AJ9: ='11'!$L$9 -> 0 | AK9: ='12'!$J$9 -> 0 | AL9: =IF(AK9=0,0,AM9/AK9) -> 0 | AM9: ='12'!$L$9 -> 0 | AN9: =SUM(D9,G9,J9,M9,P9,S9,V9,Y9,AB9,AE9,AH9,AK9) -> 0 | AO9: =IF(AN9=0,0,AP9/AN9) -> 0 | AP9: =SUM(F9,I9,L9,O9,R9,U9,X9,AA9,AD9,AG9,AJ9,AM9) -> 0
A10: =+B10&C10 -> Véhicules neufs[...] | B10: Véhicules neufs | C10: [...] | D10: ='1'!G10 -> 0 | E10: =IF(D10=0,0,F10/D10) -> 0 | F10: ='1'!$L$10 -> 0 | G10: ='2'!J10 -> 0 | H10: =IF(G10=0,0,I10/G10) -> 0 | I10: ='2'!$L$10 -> 0 | J10: ='3'!M10 -> 0 | K10: =IF(J10=0,0,L10/J10) -> 0 | L10: ='3'!$L$10 -> 0 | M10: ='4'!P10 -> 0 | N10: =IF(M10=0,0,O10/M10) -> 0 | O10: ='4'!$L$10 -> 0 | P10: ='5'!S10 -> 0 | Q10: =IF(P10=0,0,R10/P10) -> 0 | R10: ='5'!$L$10 -> 0 | S10: ='6'!V10 -> 0 | T10: =IF(S10=0,0,U10/S10) -> 0 | U10: ='6'!$L$10 -> 0 | V10: ='7'!Y10 -> 0 | W10: =IF(V10=0,0,X10/V10) -> 0 | X10: ='7'!$L$10 -> 0 | Y10: ='8'!AB10 -> 0 | Z10: =IF(Y10=0,0,AA10/Y10) -> 0 | AA10: ='8'!$L$10 -> 0 | AB10: ='9'!AE10 -> 0 | AC10: =IF(AB10=0,0,AD10/AB10) -> 0 | AD10: ='9'!$L$10 -> 0 | AE10: ='10'!AH10 -> 0 | AF10: =IF(AE10=0,0,AG10/AE10) -> 0 | AG10: ='10'!$L$10 -> 0 | AH10: ='11'!AK10 -> 0 | AI10: =IF(AH10=0,0,AJ10/AH10) -> 0 | AJ10: ='11'!$L$10 -> 0 | AK10: ='12'!AN10 -> 0 | AL10: =IF(AK10=0,0,AM10/AK10) -> 0 | AM10: ='12'!$L$10 -> 0 | AN10: =SUM(D10,G10,J10,M10,P10,S10,V10,Y10,AB10,AE10,AH10,AK10) -> 0 | AO10: =IF(AN10=0,0,AP10/AN10) -> 0 | AP10: =SUM(F10,I10,L10,O10,R10,U10,X10,AA10,AD10,AG10,AJ10,AM10) -> 0
A11: =+B11&C11 -> Véhicules neufs[...] | B11: Véhicules neufs | C11: [...] | D11: ='1'!G11 -> 0 | E11: =IF(D11=0,0,F11/D11) -> 0 | F11: ='1'!$L$11 -> 0 | G11: ='2'!J11 -> 0 | H11: =IF(G11=0,0,I11/G11) -> 0 | I11: ='2'!$L$11 -> 0 | J11: ='3'!M11 -> 0 | K11: =IF(J11=0,0,L11/J11) -> 0 | L11: ='3'!$L$11 -> 0 | M11: ='4'!P11 -> 0 | N11: =IF(M11=0,0,O11/M11) -> 0 | O11: ='4'!$L$11 -> 0 | P11: ='5'!S11 -> 0 | Q11: =IF(P11=0,0,R11/P11) -> 0 | R11: ='5'!$L$11 -> 0 | S11: ='6'!V11 -> 0 | T11: =IF(S11=0,0,U11/S11) -> 0 | U11: ='6'!$L$11 -> 0 | V11: ='7'!Y11 -> 0 | W11: =IF(V11=0,0,X11/V11) -> 0 | X11: ='7'!$L$11 -> 0 | Y11: ='8'!AB11 -> 0 | Z11: =IF(Y11=0,0,AA11/Y11) -> 0 | AA11: ='8'!$L$11 -> 0 | AB11: ='9'!AE11 -> 0 | AC11: =IF(AB11=0,0,AD11/AB11) -> 0 | AD11: ='9'!$L$11 -> 0 | AE11: ='10'!AH11 -> 0 | AF11: =IF(AE11=0,0,AG11/AE11) -> 0 | AG11: ='10'!$L$11 -> 0 | AH11: ='11'!AK11 -> 0 | AI11: =IF(AH11=0,0,AJ11/AH11) -> 0 | AJ11: ='11'!$L$11 -> 0 | AK11: ='12'!AN11 -> 0 | AL11: =IF(AK11=0,0,AM11/AK11) -> 0 | AM11: ='12'!$L$11 -> 0 | AN11: =SUM(D11,G11,J11,M11,P11,S11,V11,Y11,AB11,AE11,AH11,AK11) -> 0 | AO11: =IF(AN11=0,0,AP11/AN11) -> 0 | AP11: =SUM(F11,I11,L11,O11,R11,U11,X11,AA11,AD11,AG11,AJ11,AM11) -> 0
A12: =+B12&C12 -> Véhicules neufs[...] | B12: Véhicules neufs | C12: [...] | D12: ='1'!G12 -> 0 | E12: =IF(D12=0,0,F12/D12) -> 0 | F12: ='1'!$L$12 -> 0 | G12: ='2'!J12 -> 0 | H12: =IF(G12=0,0,I12/G12) -> 0 | I12: ='2'!$L$12 -> 0 | J12: ='3'!M12 -> 0 | K12: =IF(J12=0,0,L12/J12) -> 0 | L12: ='3'!$L$12 -> 0 | M12: ='4'!P12 -> 0 | N12: =IF(M12=0,0,O12/M12) -> 0 | O12: ='4'!$L$12 -> 0 | P12: ='5'!S12 -> 0 | Q12: =IF(P12=0,0,R12/P12) -> 0 | R12: ='5'!$L$12 -> 0 | S12: ='6'!V12 -> 0 | T12: =IF(S12=0,0,U12/S12) -> 0 | U12: ='6'!$L$12 -> 0 | V12: ='7'!Y12 -> 0 | W12: =IF(V12=0,0,X12/V12) -> 0 | X12: ='7'!$L$12 -> 0 | Y12: ='8'!AB12 -> 0 | Z12: =IF(Y12=0,0,AA12/Y12) -> 0 | AA12: ='8'!$L$12 -> 0 | AB12: ='9'!AE12 -> 0 | AC12: =IF(AB12=0,0,AD12/AB12) -> 0 | AD12: ='9'!$L$12 -> 0 | AE12: ='10'!AH12 -> 0 | AF12: =IF(AE12=0,0,AG12/AE12) -> 0 | AG12: ='10'!$L$12 -> 0 | AH12: ='11'!AK12 -> 0 | AI12: =IF(AH12=0,0,AJ12/AH12) -> 0 | AJ12: ='11'!$L$12 -> 0 | AK12: ='12'!AN12 -> 0 | AL12: =IF(AK12=0,0,AM12/AK12) -> 0 | AM12: ='12'!$L$12 -> 0 | AN12: =SUM(D12,G12,J12,M12,P12,S12,V12,Y12,AB12,AE12,AH12,AK12) -> 0 | AO12: =IF(AN12=0,0,AP12/AN12) -> 0 | AP12: =SUM(F12,I12,L12,O12,R12,U12,X12,AA12,AD12,AG12,AJ12,AM12) -> 0
A13: =+B13&C13 -> Véhicules neufsTotal Neufs | B13: Véhicules neufs | C13: Total Neufs | D13: =+SUM(D6:D12) -> 20 | E13: =IF(D13<=0,0,F13/D13) -> 1213.984 | F13: =+SUM(F6:F12) -> 24279.68 | G13: =+SUM(G6:G12) -> 36 | H13: =IF(G13<=0,0,I13/G13) -> 1794.8222 | I13: =+SUM(I6:I12) -> 64613.6 | J13: =+SUM(J6:J12) -> 69 | K13: =IF(J13<=0,0,L13/J13) -> 1673.301 | L13: =+SUM(L6:L12) -> 115457.77 | M13: =+SUM(M6:M12) -> 65 | N13: =IF(M13<=0,0,O13/M13) -> 1542.5949 | O13: =+SUM(O6:O12) -> 100268.67 | P13: =+SUM(P6:P12) -> 83 | Q13: =IF(P13<=0,0,R13/P13) -> 1793.4583 | R13: =+SUM(R6:R12) -> 148857.04 | S13: =+SUM(S6:S12) -> 55 | T13: =IF(S13<=0,0,U13/S13) -> 1838.7933 | U13: =+SUM(U6:U12) -> 101133.63 | V13: =+SUM(V6:V12) -> 389 | W13: =IF(V13<=0,0,X13/V13) -> 1736.8548 | X13: =+SUM(X6:X12) -> 675636.53 | Y13: =+SUM(Y6:Y12) -> 452 | Z13: =IF(Y13<=0,0,AA13/Y13) -> 1730.0191 | AA13: =+SUM(AA6:AA12) -> 781968.64 | AB13: =+SUM(AB6:AB12) -> 0 | AC13: =IF(AB13<=0,0,AD13/AB13) -> 0 | AD13: =+SUM(AD6:AD12) -> 0 | AE13: =+SUM(AE6:AE12) -> 0 | AF13: =IF(AE13<=0,0,AG13/AE13) -> 0 | AG13: =+SUM(AG6:AG12) -> 0 | AH13: =+SUM(AH6:AH12) -> 0 | AI13: =IF(AH13<=0,0,AJ13/AH13) -> 0 | AJ13: =+SUM(AJ6:AJ12) -> 0 | AK13: =+SUM(AK6:AK12) -> 0 | AL13: =IF(AK13<=0,0,AM13/AK13) -> 0 | AM13: =+SUM(AM6:AM12) -> 0 | AN13: =+SUM(AN6:AN12) -> 1169 | AO13: =IF(AN13<=0,0,AP13/AN13) -> 1721.3136 | AP13: =+SUM(AP6:AP12) -> 2012215.6
A14: =+B14&C14 -> Véhicules neufs | B14: Véhicules neufs
A15: =+B15&C15 -> Véhicules neufsEx-Démos et courtoisies | B15: Véhicules neufs | C15: Ex-Démos et courtoisies | D15: ='1'!$J$15 -> 4 | E15: =IF(D15=0,0,F15/D15) -> 1253.6675 | F15: ='1'!$L$15 -> 5014.67 | G15: ='2'!$J$15 -> 13 | H15: =IF(G15=0,0,I15/G15) -> 654.57077 | I15: ='2'!$L$15 -> 8509.42 | J15: ='3'!$J$15 -> 9 | K15: =IF(J15=0,0,L15/J15) -> 754.36444 | L15: ='3'!$L$15 -> 6789.28 | M15: ='4'!$J$15 -> 3 | N15: =IF(M15=0,0,O15/M15) -> 1041.6767 | O15: ='4'!$L$15 -> 3125.03 | P15: ='5'!$J$15 -> 4 | Q15: =IF(P15=0,0,R15/P15) -> 2427.275 | R15: ='5'!$L$15 -> 9709.1 | S15: ='6'!$J$15 -> 9 | T15: =IF(S15=0,0,U15/S15) -> 1229.3844 | U15: ='6'!$L$15 -> 11064.46 | V15: ='7'!$J$15 -> 46 | W15: =IF(V15=0,0,X15/V15) -> 1095.7154 | X15: ='7'!$L$15 -> 50402.91 | Y15: ='8'!$J$15 -> 60 | Z15: =IF(Y15=0,0,AA15/Y15) -> 1310.5077 | AA15: ='8'!$L$15 -> 78630.46 | AB15: ='9'!$J$15 -> 0 | AC15: =IF(AB15=0,0,AD15/AB15) -> 0 | AD15: ='9'!$L$15 -> 0 | AE15: ='10'!$J$15 -> 0 | AF15: =IF(AE15=0,0,AG15/AE15) -> 0 | AG15: ='10'!$L$15 -> 0 | AH15: ='11'!$J$15 -> 0 | AI15: =IF(AH15=0,0,AJ15/AH15) -> 0 | AJ15: ='11'!$L$15 -> 0 | AK15: ='12'!$J$15 -> 0 | AL15: =IF(AK15=0,0,AM15/AK15) -> 0 | AM15: ='12'!$L$15 -> 0 | AN15: =SUM(D15,G15,J15,M15,P15,S15,V15,Y15,AB15,AE15,AH15,AK15) -> 148 | AO15: =IF(AN15=0,0,AP15/AN15) -> 1170.5766 | AP15: =SUM(F15,I15,L15,O15,R15,U15,X15,AA15,AD15,AG15,AJ15,AM15) -> 173245.33
A16: =+B16&C16 -> Véhicules neufs | B16: Véhicules neufs | F16: ='1'!$L$16 -> 0 | I16: ='2'!$L$16 -> 0 | L16: ='3'!$L$16 -> 0 | O16: ='4'!$L$16 -> 0 | R16: ='5'!$L$16 -> 0 | U16: ='6'!$L$16 -> 0 | X16: ='7'!$L$16 -> 0 | AA16: ='8'!$L$16 -> 0 | AD16: ='9'!$L$16 -> 0 | AG16: ='10'!$L$16 -> 0 | AJ16: ='11'!$L$16 -> 0 | AM16: ='12'!$L$16 -> 0 | AP16: =SUM(F16,I16,L16,O16,R16,U16,X16,AA16,AD16,AG16,AJ16,AM16) -> 0
A17: =+B17&C17 -> Véhicules neufsFlottes | B17: Véhicules neufs | C17: Flottes | D17: ='1'!$J$17 -> 0 | E17: =IF(D17=0,0,F17/D17) -> 0 | F17: ='1'!$L$17 -> 0 | G17: ='2'!$J$17 -> 3 | H17: =IF(G17=0,0,I17/G17) -> 1210.7133 | I17: ='2'!$L$17 -> 3632.14 | J17: ='3'!$J$17 -> 3 | K17: =IF(J17=0,0,L17/J17) -> 1019.75 | L17: ='3'!$L$17 -> 3059.25 | M17: ='4'!$J$17 -> 5 | N17: =IF(M17=0,0,O17/M17) -> 2400.116 | O17: ='4'!$L$17 -> 12000.58 | P17: ='5'!$J$17 -> 4 | Q17: =IF(P17=0,0,R17/P17) -> 2789.6125 | R17: ='5'!$L$17 -> 11158.45 | S17: ='6'!$J$17 -> 1 | T17: =IF(S17=0,0,U17/S17) -> 1036 | U17: ='6'!$L$17 -> 1036 | V17: ='7'!$J$17 -> 18 | W17: =IF(V17=0,0,X17/V17) -> 1776.96 | X17: ='7'!$L$17 -> 31985.28 | Y17: ='8'!$J$17 -> 19 | Z17: =IF(Y17=0,0,AA17/Y17) -> 1735.22 | AA17: ='8'!$L$17 -> 32969.18 | AB17: ='9'!$J$17 -> 0 | AC17: =IF(AB17=0,0,AD17/AB17) -> 0 | AD17: ='9'!$L$17 -> 0 | AE17: ='10'!$J$17 -> 0 | AF17: =IF(AE17=0,0,AG17/AE17) -> 0 | AG17: ='10'!$L$17 -> 0 | AH17: ='11'!$J$17 -> 0 | AI17: =IF(AH17=0,0,AJ17/AH17) -> 0 | AJ17: ='11'!$L$17 -> 0 | AK17: ='12'!$J$17 -> 0 | AL17: =IF(AK17=0,0,AM17/AK17) -> 0 | AM17: ='12'!$L$17 -> 0 | AN17: =SUM(D17,G17,J17,M17,P17,S17,V17,Y17,AB17,AE17,AH17,AK17) -> 53 | AO17: =IF(AN17=0,0,AP17/AN17) -> 1808.3185 | AP17: =SUM(F17,I17,L17,O17,R17,U17,X17,AA17,AD17,AG17,AJ17,AM17) -> 95840.88
A18: =+B18&C18 -> Véhicules neufs | B18: Véhicules neufs | F18: ='1'!$L$18 -> 0 | I18: ='2'!$L$18 -> 0 | L18: ='3'!$L$18 -> 0 | O18: ='4'!$L$18 -> 0 | R18: ='5'!$L$18 -> 0 | U18: ='6'!$L$18 -> 0 | X18: ='7'!$L$18 -> 0 | AA18: ='8'!$L$18 -> 0 | AD18: ='9'!$L$18 -> 0 | AG18: ='10'!$L$18 -> 0 | AJ18: ='11'!$L$18 -> 0 | AM18: ='12'!$L$18 -> 0 | AP18: =SUM(F18,I18,L18,O18,R18,U18,X18,AA18,AD18,AG18,AJ18,AM18) -> 0
A19: =+B19&C19 -> Véhicules neufsRachat bail | B19: Véhicules neufs | C19: Rachat bail | F19: ='1'!$L$19 -> 898.55 | I19: ='2'!$L$19 -> 987.85 | L19: ='3'!$L$19 -> 6884.37 | O19: ='4'!$L$19 -> 10386.97 | R19: ='5'!$L$19 -> 6141.99 | U19: ='6'!$L$19 -> 7884.92 | X19: ='7'!$L$19 -> 38801.77 | AA19: ='8'!$L$19 -> 46793.96 | AD19: ='9'!$L$19 -> 0 | AG19: ='10'!$L$19 -> 0 | AJ19: ='11'!$L$19 -> 0 | AM19: ='12'!$L$19 -> 0 | AP19: =SUM(F19,I19,L19,O19,R19,U19,X19,AA19,AD19,AG19,AJ19,AM19) -> 118780.38
A20: =+B20&C20 -> Véhicules neufs | B20: Véhicules neufs | F20: ='1'!$L$20 -> 0 | I20: ='2'!$L$20 -> 0 | L20: ='3'!$L$20 -> 0 | O20: ='4'!$L$20 -> 0 | R20: ='5'!$L$20 -> 0 | U20: ='6'!$L$20 -> 0 | X20: ='7'!$L$20 -> 0 | AA20: ='8'!$L$20 -> 0 | AD20: ='9'!$L$20 -> 0 | AG20: ='10'!$L$20 -> 0 | AJ20: ='11'!$L$20 -> 0 | AM20: ='12'!$L$20 -> 0 | AP20: =SUM(F20,I20,L20,O20,R20,U20,X20,AA20,AD20,AG20,AJ20,AM20) -> 0
A21: =+B21&C21 -> Véhicules neufsRev. Finances | B21: Véhicules neufs | C21: Rev. Finances | E21: =IF(D13=0,0,F21/(D13+D15)) -> 0 | F21: ='1'!$L$21 -> 0 | H21: =IF(G13=0,0,I21/(G13+G15)) -> 0 | I21: ='2'!$L$21 -> 0 | K21: =IF(J13=0,0,L21/(J13+J15)) -> -13.910513 | L21: ='3'!$L$21 -> -1085.02 | N21: =IF(M13=0,0,O21/(M13+M15)) -> 93.977941 | O21: ='4'!$L$21 -> 6390.5 | Q21: =IF(P13=0,0,R21/(P13+P15)) -> 0 | R21: ='5'!$L$21 -> 0 | T21: =IF(S13=0,0,U21/(S13+S15)) -> 21.57375 | U21: ='6'!$L$21 -> 1380.72 | W21: =IF(V13=0,0,X21/(V13+V15)) -> 15.60046 | X21: ='7'!$L$21 -> 6786.2 | Z21: =IF(Y13=0,0,AA21/(Y13+Y15)) -> 13.254297 | AA21: ='8'!$L$21 -> 6786.2 | AC21: =IF(AB13=0,0,AD21/(AB13+AB15)) -> 0 | AD21: ='9'!$L$21 -> 0 | AF21: =IF(AE13=0,0,AG21/(AE13+AE15)) -> 0 | AG21: ='10'!$L$21 -> 0 | AI21: =IF(AH13=0,0,AJ21/(AH13+AH15)) -> 0 | AJ21: ='11'!$L$21 -> 0 | AL21: =IF(AK13=0,0,AM21/(AK13+AK15)) -> 0 | AM21: ='12'!$L$21 -> 0 | AO21: =IF(AN13=0,0,AP21/(AN13+AN15)) -> 15.382384 | AP21: =SUM(F21,I21,L21,O21,R21,U21,X21,AA21,AD21,AG21,AJ21,AM21) -> 20258.6
A22: =+B22&C22 -> Véhicules neufsRev. Protections | B22: Véhicules neufs | C22: Rev. Protections | E22: =IF(D13=0,0,F22/(D13+D15)) -> 677.14833 | F22: ='1'!$L$22 -> 16251.56 | H22: =IF(G13=0,0,I22/(G13+G15)) -> 638.4802 | I22: ='2'!$L$22 -> 31285.53 | K22: =IF(J13=0,0,L22/(J13+J15)) -> 674.86 | L22: ='3'!$L$22 -> 52639.08 | N22: =IF(M13=0,0,O22/(M13+M15)) -> 763.56294 | O22: ='4'!$L$22 -> 51922.28 | Q22: =IF(P13=0,0,R22/(P13+P15)) -> 765.23471 | R22: ='5'!$L$22 -> 66575.42 | T22: =IF(S13=0,0,U22/(S13+S15)) -> 878.27656 | U22: ='6'!$L$22 -> 56209.7 | W22: =IF(V13=0,0,X22/(V13+V15)) -> 758.63241 | X22: ='7'!$L$22 -> 330005.1 | Z22: =IF(Y13=0,0,AA22/(Y13+Y15)) -> 783.95705 | AA22: ='8'!$L$22 -> 401386.01 | AC22: =IF(AB13=0,0,AD22/(AB13+AB15)) -> 0 | AD22: ='9'!$L$22 -> 0 | AF22: =IF(AE13=0,0,AG22/(AE13+AE15)) -> 0 | AG22: ='10'!$L$22 -> 0 | AI22: =IF(AH13=0,0,AJ22/(AH13+AH15)) -> 0 | AJ22: ='11'!$L$22 -> 0 | AL22: =IF(AK13=0,0,AM22/(AK13+AK15)) -> 0 | AM22: ='12'!$L$22 -> 0 | AO22: =IF(AN13=0,0,AP22/(AN13+AN15)) -> 764.06582 | AP22: =SUM(F22,I22,L22,O22,R22,U22,X22,AA22,AD22,AG22,AJ22,AM22) -> 1006274.7
A23: =+B23&C23 -> Véhicules neufsRev. Autres | B23: Véhicules neufs | C23: Rev. Autres | E23: =IF(D13=0,0,F23/(D13+D15)) -> 14.2025 | F23: ='1'!$L$23 -> 340.86 | H23: =IF(G13=0,0,I23/(G13+G15)) -> 30.002041 | I23: ='2'!$L$23 -> 1470.1 | K23: =IF(J13=0,0,L23/(J13+J15)) -> 25.959231 | L23: ='3'!$L$23 -> 2024.82 | N23: =IF(M13=0,0,O23/(M13+M15)) -> 14.451618 | O23: ='4'!$L$23 -> 982.71 | Q23: =IF(P13=0,0,R23/(P13+P15)) -> 18.082414 | R23: ='5'!$L$23 -> 1573.17 | T23: =IF(S13=0,0,U23/(S13+S15)) -> 31.760781 | U23: ='6'!$L$23 -> 2032.69 | W23: =IF(V13=0,0,X23/(V13+V15)) -> 23.460713 | X23: ='7'!$L$23 -> 10205.41 | Z23: =IF(Y13=0,0,AA23/(Y13+Y15)) -> 22.488047 | AA23: ='8'!$L$23 -> 11513.88 | AC23: =IF(AB13=0,0,AD23/(AB13+AB15)) -> 0 | AD23: ='9'!$L$23 -> 0 | AF23: =IF(AE13=0,0,AG23/(AE13+AE15)) -> 0 | AG23: ='10'!$L$23 -> 0 | AI23: =IF(AH13=0,0,AJ23/(AH13+AH15)) -> 0 | AJ23: ='11'!$L$23 -> 0 | AL23: =IF(AK13=0,0,AM23/(AK13+AK15)) -> 0 | AM23: ='12'!$L$23 -> 0 | AO23: =IF(AN13=0,0,AP23/(AN13+AN15)) -> 22.888109 | AP23: =SUM(F23,I23,L23,O23,R23,U23,X23,AA23,AD23,AG23,AJ23,AM23) -> 30143.64
A24: =+B24&C24 -> Véhicules neufsTotal F&I | B24: Véhicules neufs | C24: Total F&I | D24: =+D15+D13 -> 24 | E24: =IF(D24<=0,0,F24/D24) -> 691.35083 | F24: =F21+F22+F23 -> 16592.42 | G24: =+G15+G13 -> 49 | H24: =IF(G24<=0,0,I24/G24) -> 668.48224 | I24: =I21+I22+I23 -> 32755.63 | J24: =+J15+J13 -> 78 | K24: =IF(J24<=0,0,L24/J24) -> 686.90872 | L24: =L21+L22+L23 -> 53578.88 | M24: =+M15+M13 -> 68 | N24: =IF(M24<=0,0,O24/M24) -> 871.9925 | O24: =O21+O22+O23 -> 59295.49 | P24: =+P15+P13 -> 87 | Q24: =IF(P24<=0,0,R24/P24) -> 783.31713 | R24: =R21+R22+R23 -> 68148.59 | S24: =+S15+S13 -> 64 | T24: =IF(S24<=0,0,U24/S24) -> 931.61109 | U24: =U21+U22+U23 -> 59623.11 | V24: =+V15+V13 -> 435 | W24: =IF(V24<=0,0,X24/V24) -> 797.69359 | X24: =X21+X22+X23 -> 346996.71 | Y24: =+Y15+Y13 -> 512 | Z24: =IF(Y24<=0,0,AA24/Y24) -> 819.69939 | AA24: =AA21+AA22+AA23 -> 419686.09 | AB24: =+AB15+AB13 -> 0 | AC24: =IF(AB24<=0,0,AD24/AB24) -> 0 | AD24: =AD21+AD22+AD23 -> 0 | AE24: =+AE15+AE13 -> 0 | AF24: =IF(AE24<=0,0,AG24/AE24) -> 0 | AG24: =AG21+AG22+AG23 -> 0 | AH24: =+AH15+AH13 -> 0 | AI24: =IF(AH24<=0,0,AJ24/AH24) -> 0 | AJ24: =AJ21+AJ22+AJ23 -> 0 | AK24: =+AK15+AK13 -> 0 | AL24: =IF(AK24<=0,0,AM24/AK24) -> 0 | AM24: =AM21+AM22+AM23 -> 0 | AN24: =+AN15+AN13 -> 1317 | AO24: =IF(AN24<=0,0,AP24/AN24) -> 802.33631 | AP24: =AP21+AP22+AP23 -> 1056676.9
A25: =+B25&C25 -> Véhicules neufs | B25: Véhicules neufs
A26: =+B26&C26 -> Véhicules neufs | B26: Véhicules neufs
A27: =+B27&C27 -> Véhicules neufsTotal Dépt. Neufs | B27: Véhicules neufs | C27: Total Dépt. Neufs | D27: =+D13+D15+D17 -> 24 | E27: =IF(D27<=0,0,F27/D27) -> 1949.3883 | F27: =F13+F17+F24+F19+F15 -> 46785.32 | G27: =+G13+G15+G17 -> 52 | H27: =IF(G27<=0,0,I27/G27) -> 2124.9738 | I27: =I13+I17+I24+I19+I15 -> 110498.64 | J27: =+J13+J15+J17 -> 81 | K27: =IF(J27<=0,0,L27/J27) -> 2293.4512 | L27: =L13+L17+L24+L19+L15 -> 185769.55 | M27: =+M13+M15+M17 -> 73 | N27: =IF(M27<=0,0,O27/M27) -> 2535.2978 | O27: =O13+O17+O24+O19+O15 -> 185076.74 | P27: =+P13+P15+P17 -> 91 | Q27: =IF(P27<=0,0,R27/P27) -> 2681.4854 | R27: =R13+R17+R24+R19+R15 -> 244015.17 | S27: =+S13+S15+S17 -> 65 | T27: =IF(S27<=0,0,U27/S27) -> 2780.648 | U27: =U13+U17+U24+U19+U15 -> 180742.12 | V27: =+V13+V15+V17 -> 453 | W27: =IF(V27<=0,0,X27/V27) -> 2524.996 | X27: =X13+X17+X24+X19+X15 -> 1143823.2 | Y27: =+Y13+Y15+Y17 -> 531 | Z27: =IF(Y27<=0,0,AA27/Y27) -> 2561.2963 | AA27: =AA13+AA17+AA24+AA19+AA15 -> 1360048.3 | AB27: =+AB13+AB15+AB17 -> 0 | AC27: =IF(AB27<=0,0,AD27/AB27) -> 0 | AD27: =AD13+AD17+AD24+AD19+AD15 -> 0 | AE27: =+AE13+AE15+AE17 -> 0 | AF27: =IF(AE27<=0,0,AG27/AE27) -> 0 | AG27: =AG13+AG17+AG24+AG19+AG15 -> 0 | AH27: =+AH13+AH15+AH17 -> 0 | AI27: =IF(AH27<=0,0,AJ27/AH27) -> 0 | AJ27: =AJ13+AJ17+AJ24+AJ19+AJ15 -> 0 | AK27: =+AK13+AK15+AK17 -> 0 | AL27: =IF(AK27<=0,0,AM27/AK27) -> 0 | AM27: =AM13+AM17+AM24+AM19+AM15 -> 0 | AN27: =+AN13+AN15+AN17 -> 1370 | AO27: =IF(AN27<=0,0,AP27/AN27) -> 2523.1818 | AP27: =AP13+AP17+AP24+AP19+AP15 -> 3456759.1
A28: =+B28&C28 -> Véhicules neufs | B28: Véhicules neufs
A29: =+B29&C29 -> Véhicules neufs | B29: Véhicules neufs
A30: =+B30&C30 -> Véhicules neufsDEPENSES | B30: Véhicules neufs | C30: DEPENSES
A31: =+B31&C31 -> Véhicules neufsComm. vendeurs | B31: Véhicules neufs | C31: Comm. vendeurs | D31: =F31/F13 -> 0.80468153 | E31: =IF(F31=0,0,F31/D$24) -> 814.05875 | F31: ='1'!$L$31 -> 19537.41 | G31: =I31/I13 -> 0.43488909 | H31: =IF(I31=0,0,I31/G$24) -> 573.46429 | I31: ='2'!$L$31 -> 28099.75 | J31: =L31/L13 -> 0.36360325 | K31: =IF(L31=0,0,L31/J$24) -> 538.21564 | L31: ='3'!$L$31 -> 41980.82 | M31: =O31/O13 -> 0.41324912 | N31: =IF(O31=0,0,O31/M$24) -> 609.35206 | O31: ='4'!$L$31 -> 41435.94 | P31: =R31/R13 -> 0.35729603 | Q31: =IF(R31=0,0,R31/P$24) -> 611.33368 | R31: ='5'!$L$31 -> 53186.03 | S31: =U31/U13 -> 0.40998598 | T31: =IF(U31=0,0,U31/S$24) -> 647.86516 | U31: ='6'!$L$31 -> 41463.37 | V31: =X31/X13 -> 0.39054987 | W31: =IF(X31=0,0,X31/V$24) -> 606.59715 | X31: ='7'!$L$31 -> 263869.76 | Y31: =AA31/AA13 -> 0.39635748 | Z31: =IF(AA31=0,0,AA31/Y$24) -> 605.34984 | AA31: ='8'!$L$31 -> 309939.12 | AB31: =AD31/AD13 -> #DIV/0! | AC31: =IF(AD31=0,0,AD31/AB$24) -> 0 | AD31: ='9'!$L$31 -> 0 | AE31: =AG31/AG13 -> #DIV/0! | AF31: =IF(AG31=0,0,AG31/AE$24) -> 0 | AG31: ='10'!$L$31 -> 0 | AH31: =AJ31/AJ13 -> #DIV/0! | AI31: =IF(AJ31=0,0,AJ31/AH$24) -> 0 | AJ31: ='11'!$L$31 -> 0 | AK31: =AM31/AM13 -> #DIV/0! | AL31: =IF(AM31=0,0,AM31/AK$24) -> 0 | AM31: ='12'!$L$31 -> 0 | AN31: =AP31/AP13 -> 0.3973293 | AO31: =IF(AP31=0,0,AP31/AN$24) -> 607.07077 | AP31: =SUM(F31,I31,L31,O31,R31,U31,X31,AA31,AD31,AG31,AJ31,AM31) -> 799512.2
A32: =+B32&C32 -> Véhicules neufsComm. F&I | B32: Véhicules neufs | C32: Comm. F&I | D32: =F32/F24 -> 0.29489188 | E32: =IF(F32=0,0,F32/D$24) -> 203.87375 | F32: ='1'!$L$32 -> 4892.97 | G32: =I32/I24 -> 0.28865236 | H32: =IF(I32=0,0,I32/G$24) -> 192.95898 | I32: ='2'!$L$32 -> 9454.99 | J32: =L32/L24 -> 0.29627308 | K32: =IF(L32=0,0,L32/J$24) -> 203.51256 | L32: ='3'!$L$32 -> 15873.98 | M32: =O32/O24 -> 0.31930793 | N32: =IF(O32=0,0,O32/M$24) -> 278.43412 | O32: ='4'!$L$32 -> 18933.52 | P32: =R32/R24 -> 0.3073977 | Q32: =IF(R32=0,0,R32/P$24) -> 240.78989 | R32: ='5'!$L$32 -> 20948.72 | S32: =U32/U24 -> 0.29999576 | T32: =IF(U32=0,0,U32/S$24) -> 279.47938 | U32: ='6'!$L$32 -> 17886.68 | V32: =X32/X24 -> 0.30388677 | W32: =IF(X32=0,0,X32/V$24) -> 242.40853 | X32: ='7'!$L$32 -> 105447.71 | Y32: =AA32/AA24 -> 0.30121742 | Z32: =IF(AA32=0,0,AA32/Y$24) -> 246.90773 | AA32: ='8'!$L$32 -> 126416.76 | AB32: =AD32/AD24 -> #DIV/0! | AC32: =IF(AD32=0,0,AD32/AB$24) -> 0 | AD32: ='9'!$L$32 -> 0 | AE32: =AG32/AG24 -> #DIV/0! | AF32: =IF(AG32=0,0,AG32/AE$24) -> 0 | AG32: ='10'!$L$32 -> 0 | AH32: =AJ32/AJ24 -> #DIV/0! | AI32: =IF(AJ32=0,0,AJ32/AH$24) -> 0 | AJ32: ='11'!$L$32 -> 0 | AK32: =AM32/AM24 -> #DIV/0! | AL32: =IF(AM32=0,0,AM32/AK$24) -> 0 | AM32: ='12'!$L$32 -> 0 | AN32: =AP32/AP24 -> 0.30269927 | AO32: =IF(AP32=0,0,AP32/AN$24) -> 242.86661 | AP32: =SUM(F32,I32,L32,O32,R32,U32,X32,AA32,AD32,AG32,AJ32,AM32) -> 319855.33
A33: =+B33&C33 -> Véhicules neufsFrais de livraison | B33: Véhicules neufs | C33: Frais de livraison | E33: =IF(F33=0,0,F33/D$24) -> 199.92917 | F33: ='1'!$L$33 -> 4798.3 | H33: =IF(I33=0,0,I33/G$24) -> 139.43082 | I33: ='2'!$L$33 -> 6832.11 | K33: =IF(L33=0,0,L33/J$24) -> 135.56885 | L33: ='3'!$L$33 -> 10574.37 | N33: =IF(O33=0,0,O33/M$24) -> 186.22485 | O33: ='4'!$L$33 -> 12663.29 | Q33: =IF(R33=0,0,R33/P$24) -> 74.75069 | R33: ='5'!$L$33 -> 6503.31 | T33: =IF(U33=0,0,U33/S$24) -> 175.26109 | U33: ='6'!$L$33 -> 11216.71 | W33: =IF(X33=0,0,X33/V$24) -> 159.76255 | X33: ='7'!$L$33 -> 69496.71 | Z33: =IF(AA33=0,0,AA33/Y$24) -> 155.38496 | AA33: ='8'!$L$33 -> 79557.1 | AC33: =IF(AD33=0,0,AD33/AB$24) -> 0 | AD33: ='9'!$L$33 -> 0 | AF33: =IF(AG33=0,0,AG33/AE$24) -> 0 | AG33: ='10'!$L$33 -> 0 | AI33: =IF(AJ33=0,0,AJ33/AH$24) -> 0 | AJ33: ='11'!$L$33 -> 0 | AL33: =IF(AM33=0,0,AM33/AK$24) -> 0 | AM33: ='12'!$L$33 -> 0 | AO33: =IF(AP33=0,0,AP33/AN$24) -> 153.10699 | AP33: =SUM(F33,I33,L33,O33,R33,U33,X33,AA33,AD33,AG33,AJ33,AM33) -> 201641.9
A34: =+B34&C34 -> Véhicules neufsService gratuit 1 | B34: Véhicules neufs | C34: Service gratuit 1 | E34: =IF(F34=0,0,F34/D$24) -> 17.662917 | F34: ='1'!$L$34 -> 423.91 | H34: =IF(I34=0,0,I34/G$24) -> 1.2995918 | I34: ='2'!$L$34 -> 63.68 | K34: =IF(L34=0,0,L34/J$24) -> 0 | L34: ='3'!$L$34 -> 0 | N34: =IF(O34=0,0,O34/M$24) -> 10.717647 | O34: ='4'!$L$34 -> 728.8 | Q34: =IF(R34=0,0,R34/P$24) -> 6.8565517 | R34: ='5'!$L$34 -> 596.52 | T34: =IF(U34=0,0,U34/S$24) -> 16.853437 | U34: ='6'!$L$34 -> 1078.62 | W34: =IF(X34=0,0,X34/V$24) -> 7.6705057 | X34: ='7'!$L$34 -> 3336.67 | Z34: =IF(AA34=0,0,AA34/Y$24) -> 7.6217383 | AA34: ='8'!$L$34 -> 3902.33 | AC34: =IF(AD34=0,0,AD34/AB$24) -> 0 | AD34: ='9'!$L$34 -> 0 | AF34: =IF(AG34=0,0,AG34/AE$24) -> 0 | AG34: ='10'!$L$34 -> 0 | AI34: =IF(AJ34=0,0,AJ34/AH$24) -> 0 | AJ34: ='11'!$L$34 -> 0 | AL34: =IF(AM34=0,0,AM34/AK$24) -> 0 | AM34: ='12'!$L$34 -> 0 | AO34: =IF(AP34=0,0,AP34/AN$24) -> 7.692126 | AP34: =SUM(F34,I34,L34,O34,R34,U34,X34,AA34,AD34,AG34,AJ34,AM34) -> 10130.53
A35: =+B35&C35 -> Véhicules neufsEntretien stock | B35: Véhicules neufs | C35: Entretien stock | E35: =IF(F35=0,0,F35/D$24) -> 7.08125 | F35: ='1'!$L$35 -> 169.95 | H35: =IF(I35=0,0,I35/G$24) -> 21.868367 | I35: ='2'!$L$35 -> 1071.55 | K35: =IF(L35=0,0,L35/J$24) -> 0.51282051 | L35: ='3'!$L$35 -> 40 | N35: =IF(O35=0,0,O35/M$24) -> 13.796029 | O35: ='4'!$L$35 -> 938.13 | Q35: =IF(R35=0,0,R35/P$24) -> 13.448276 | R35: ='5'!$L$35 -> 1170 | T35: =IF(U35=0,0,U35/S$24) -> 0.625 | U35: ='6'!$L$35 -> 40 | W35: =IF(X35=0,0,X35/V$24) -> 8.2865057 | X35: ='7'!$L$35 -> 3604.63 | Z35: =IF(AA35=0,0,AA35/Y$24) -> 13.165703 | AA35: ='8'!$L$35 -> 6740.84 | AC35: =IF(AD35=0,0,AD35/AB$24) -> 0 | AD35: ='9'!$L$35 -> 0 | AF35: =IF(AG35=0,0,AG35/AE$24) -> 0 | AG35: ='10'!$L$35 -> 0 | AI35: =IF(AJ35=0,0,AJ35/AH$24) -> 0 | AJ35: ='11'!$L$35 -> 0 | AL35: =IF(AM35=0,0,AM35/AK$24) -> 0 | AM35: ='12'!$L$35 -> 0 | AO35: =IF(AP35=0,0,AP35/AN$24) -> 10.459453 | AP35: =SUM(F35,I35,L35,O35,R35,U35,X35,AA35,AD35,AG35,AJ35,AM35) -> 13775.1
A36: =+B36&C36 -> Véhicules neufsPublicité 1 | B36: Véhicules neufs | C36: Publicité 1 | E36: =IF(F36=0,0,F36/D$24) -> 307.50417 | F36: ='1'!$L$36 -> 7380.1 | H36: =IF(I36=0,0,I36/G$24) -> 185.16224 | I36: ='2'!$L$36 -> 9072.95 | K36: =IF(L36=0,0,L36/J$24) -> 97.126795 | L36: ='3'!$L$36 -> 7575.89 | N36: =IF(O36=0,0,O36/M$24) -> 179.49603 | O36: ='4'!$L$36 -> 12205.73 | Q36: =IF(R36=0,0,R36/P$24) -> 119.94092 | R36: ='5'!$L$36 -> 10434.86 | T36: =IF(U36=0,0,U36/S$24) -> 194.70016 | U36: ='6'!$L$36 -> 12460.81 | W36: =IF(X36=0,0,X36/V$24) -> 159.56648 | X36: ='7'!$L$36 -> 69411.42 | Z36: =IF(AA36=0,0,AA36/Y$24) -> 159.89959 | AA36: ='8'!$L$36 -> 81868.59 | AC36: =IF(AD36=0,0,AD36/AB$24) -> 0 | AD36: ='9'!$L$36 -> 0 | AF36: =IF(AG36=0,0,AG36/AE$24) -> 0 | AG36: ='10'!$L$36 -> 0 | AI36: =IF(AJ36=0,0,AJ36/AH$24) -> 0 | AJ36: ='11'!$L$36 -> 0 | AL36: =IF(AM36=0,0,AM36/AK$24) -> 0 | AM36: ='12'!$L$36 -> 0 | AO36: =IF(AP36=0,0,AP36/AN$24) -> 159.76488 | AP36: =SUM(F36,I36,L36,O36,R36,U36,X36,AA36,AD36,AG36,AJ36,AM36) -> 210410.35
A37: =+B37&C37 -> Véhicules neufsIntérêt de gros | B37: Véhicules neufs | C37: Intérêt de gros | E37: =IF(F37=0,0,F37/D$24) -> 480.64333 | F37: ='1'!$L$37 -> 11535.44 | H37: =IF(I37=0,0,I37/G$24) -> 239.47878 | I37: ='2'!$L$37 -> 11734.46 | K37: =IF(L37=0,0,L37/J$24) -> 172.06923 | L37: ='3'!$L$37 -> 13421.4 | N37: =IF(O37=0,0,O37/M$24) -> 226.95059 | O37: ='4'!$L$37 -> 15432.64 | Q37: =IF(R37=0,0,R37/P$24) -> 161.06483 | R37: ='5'!$L$37 -> 14012.64 | T37: =IF(U37=0,0,U37/S$24) -> 232.88 | U37: ='6'!$L$37 -> 14904.32 | W37: =IF(X37=0,0,X37/V$24) -> 210.7969 | X37: ='7'!$L$37 -> 91696.65 | Z37: =IF(AA37=0,0,AA37/Y$24) -> 202.45084 | AA37: ='8'!$L$37 -> 103654.83 | AC37: =IF(AD37=0,0,AD37/AB$24) -> 0 | AD37: ='9'!$L$37 -> 0 | AF37: =IF(AG37=0,0,AG37/AE$24) -> 0 | AG37: ='10'!$L$37 -> 0 | AI37: =IF(AJ37=0,0,AJ37/AH$24) -> 0 | AJ37: ='11'!$L$37 -> 0 | AL37: =IF(AM37=0,0,AM37/AK$24) -> 0 | AM37: ='12'!$L$37 -> 0 | AO37: =IF(AP37=0,0,AP37/AN$24) -> 209.86513 | AP37: =SUM(F37,I37,L37,O37,R37,U37,X37,AA37,AD37,AG37,AJ37,AM37) -> 276392.38
A38: =+B38&C38 -> Véhicules neufs[...] | B38: Véhicules neufs | C38: [...] | E38: =IF(F38=0,0,F38/D$24) -> 0 | F38: ='1'!$L$38 -> 0 | H38: =IF(I38=0,0,I38/G$24) -> 0 | I38: ='2'!$L$38 -> 0 | K38: =IF(L38=0,0,L38/J$24) -> 0 | L38: ='3'!$L$38 -> 0 | N38: =IF(O38=0,0,O38/M$24) -> 0 | O38: ='4'!$L$38 -> 0 | Q38: =IF(R38=0,0,R38/P$24) -> 0 | R38: ='5'!$L$38 -> 0 | T38: =IF(U38=0,0,U38/S$24) -> 0 | U38: ='6'!$L$38 -> 0 | W38: =IF(X38=0,0,X38/V$24) -> 0 | X38: ='7'!$L$38 -> 0 | Z38: =IF(AA38=0,0,AA38/Y$24) -> 0 | AA38: ='8'!$L$38 -> 0 | AC38: =IF(AD38=0,0,AD38/AB$24) -> 0 | AD38: ='9'!$L$38 -> 0 | AF38: =IF(AG38=0,0,AG38/AE$24) -> 0 | AG38: ='10'!$L$38 -> 0 | AI38: =IF(AJ38=0,0,AJ38/AH$24) -> 0 | AJ38: ='11'!$L$38 -> 0 | AL38: =IF(AM38=0,0,AM38/AK$24) -> 0 | AM38: ='12'!$L$38 -> 0 | AO38: =IF(AP38=0,0,AP38/AN$24) -> 0 | AP38: =SUM(F38,I38,L38,O38,R38,U38,X38,AA38,AD38,AG38,AJ38,AM38) -> 0
A39: =+B39&C39 -> Véhicules neufs[...] | B39: Véhicules neufs | C39: [...] | E39: =IF(F39=0,0,F39/D$24) -> 0 | F39: ='1'!$L$39 -> 0 | H39: =IF(I39=0,0,I39/G$24) -> 0 | I39: ='2'!$L$39 -> 0 | K39: =IF(L39=0,0,L39/J$24) -> 0 | L39: ='3'!$L$39 -> 0 | N39: =IF(O39=0,0,O39/M$24) -> 0 | O39: ='4'!$L$39 -> 0 | Q39: =IF(R39=0,0,R39/P$24) -> 0 | R39: ='5'!$L$39 -> 0 | T39: =IF(U39=0,0,U39/S$24) -> 0 | U39: ='6'!$L$39 -> 0 | W39: =IF(X39=0,0,X39/V$24) -> 0 | X39: ='7'!$L$39 -> 0 | Z39: =IF(AA39=0,0,AA39/Y$24) -> 0 | AA39: ='8'!$L$39 -> 0 | AC39: =IF(AD39=0,0,AD39/AB$24) -> 0 | AD39: ='9'!$L$39 -> 0 | AF39: =IF(AG39=0,0,AG39/AE$24) -> 0 | AG39: ='10'!$L$39 -> 0 | AI39: =IF(AJ39=0,0,AJ39/AH$24) -> 0 | AJ39: ='11'!$L$39 -> 0 | AL39: =IF(AM39=0,0,AM39/AK$24) -> 0 | AM39: ='12'!$L$39 -> 0 | AO39: =IF(AP39=0,0,AP39/AN$24) -> 0 | AP39: =SUM(F39,I39,L39,O39,R39,U39,X39,AA39,AD39,AG39,AJ39,AM39) -> 0
A40: =+B40&C40 -> Véhicules neufs[...] | B40: Véhicules neufs | C40: [...] | E40: =IF(F40=0,0,F40/D$24) -> 0 | F40: ='1'!$L$40 -> 0 | H40: =IF(I40=0,0,I40/G$24) -> 0 | I40: ='2'!$L$40 -> 0 | K40: =IF(L40=0,0,L40/J$24) -> 0 | L40: ='3'!$L$40 -> 0 | N40: =IF(O40=0,0,O40/M$24) -> 0 | O40: ='4'!$L$40 -> 0 | Q40: =IF(R40=0,0,R40/P$24) -> 0 | R40: ='5'!$L$40 -> 0 | T40: =IF(U40=0,0,U40/S$24) -> 0 | U40: ='6'!$L$40 -> 0 | W40: =IF(X40=0,0,X40/V$24) -> 0 | X40: ='7'!$L$40 -> 0 | Z40: =IF(AA40=0,0,AA40/Y$24) -> 0 | AA40: ='8'!$L$40 -> 0 | AC40: =IF(AD40=0,0,AD40/AB$24) -> 0 | AD40: ='9'!$L$40 -> 0 | AF40: =IF(AG40=0,0,AG40/AE$24) -> 0 | AG40: ='10'!$L$40 -> 0 | AI40: =IF(AJ40=0,0,AJ40/AH$24) -> 0 | AJ40: ='11'!$L$40 -> 0 | AL40: =IF(AM40=0,0,AM40/AK$24) -> 0 | AM40: ='12'!$L$40 -> 0 | AO40: =IF(AP40=0,0,AP40/AN$24) -> 0 | AP40: =SUM(F40,I40,L40,O40,R40,U40,X40,AA40,AD40,AG40,AJ40,AM40) -> 0
A41: =+B41&C41 -> Véhicules neufsTOTAL VARIABLES | B41: Véhicules neufs | C41: TOTAL VARIABLES | D41: % brut | E41: =F41/F$27 -> 1.0417387 | F41: =SUM(F31:F40) -> 48738.08 | G41: % brut | H41: =I41/I$27 -> 0.60027427 | I41: =SUM(I31:I40) -> 66329.49 | J41: % brut | K41: =L41/L$27 -> 0.48159916 | L41: =SUM(L31:L40) -> 89466.46 | M41: % brut | N41: =O41/O$27 -> 0.55294928 | O41: =SUM(O31:O40) -> 102338.05 | P41: % brut | Q41: =R41/R$27 -> 0.43789114 | R41: =SUM(R31:R40) -> 106852.08 | S41: % brut | T41: =U41/U$27 -> 0.54802118 | U41: =SUM(U31:U40) -> 99050.51 | V41: % brut | W41: =X41/X$27 -> 0.53055713 | X41: =SUM(X31:X40) -> 606863.55 | Y41: % brut | Z41: =AA41/AA$27 -> 0.52356931 | AA41: =SUM(AA31:AA40) -> 712079.57 | AB41: % brut | AC41: =AD41/AD$27 -> #DIV/0! | AD41: =SUM(AD31:AD40) -> 0 | AE41: % brut | AF41: =AG41/AG$27 -> #DIV/0! | AG41: =SUM(AG31:AG40) -> 0 | AH41: % brut | AI41: =AJ41/AJ$27 -> #DIV/0! | AJ41: =SUM(AJ31:AJ40) -> 0 | AK41: % brut | AL41: =AM41/AM$27 -> #DIV/0! | AM41: =SUM(AM31:AM40) -> 0 | AN41: % brut | AO41: =AP41/AP$27 -> 0.52989455 | AP41: =SUM(AP31:AP40) -> 1831717.8
A42: =+B42&C42 -> Véhicules neufsSalaires cadres | B42: Véhicules neufs | C42: Salaires cadres | F42: ='1'!$L$42 -> 6384.14 | I42: ='2'!$L$42 -> 21025.42 | L42: ='3'!$L$42 -> 33399.28 | O42: ='4'!$L$42 -> 23208.79 | R42: ='5'!$L$42 -> 21334.91 | U42: ='6'!$L$42 -> 24698.93 | X42: ='7'!$L$42 -> 143848.51 | AA42: ='8'!$L$42 -> 158918.63 | AD42: ='9'!$L$42 -> 0 | AG42: ='10'!$L$42 -> 0 | AJ42: ='11'!$L$42 -> 0 | AM42: ='12'!$L$42 -> 0 | AP42: =SUM(F42,I42,L42,O42,R42,U42,X42,AA42,AD42,AG42,AJ42,AM42) -> 432818.61
A43: =+B43&C43 -> Véhicules neufsSalaires commis | B43: Véhicules neufs | C43: Salaires commis | F43: ='1'!$L$43 -> 5390.92 | I43: ='2'!$L$43 -> 7319.23 | L43: ='3'!$L$43 -> 9351.04 | O43: ='4'!$L$43 -> 9482.66 | R43: ='5'!$L$43 -> 9816.59 | U43: ='6'!$L$43 -> 9024.66 | X43: ='7'!$L$43 -> 59358.09 | AA43: ='8'!$L$43 -> 68580.64 | AD43: ='9'!$L$43 -> 0 | AG43: ='10'!$L$43 -> 0 | AJ43: ='11'!$L$43 -> 0 | AM43: ='12'!$L$43 -> 0 | AP43: =SUM(F43,I43,L43,O43,R43,U43,X43,AA43,AD43,AG43,AJ43,AM43) -> 178323.83
A44: =+B44&C44 -> Véhicules neufsSalaires autres | B44: Véhicules neufs | C44: Salaires autres | F44: ='1'!$L$44 -> 4197.11 | I44: ='2'!$L$44 -> 6897.65 | L44: ='3'!$L$44 -> 7584.35 | O44: ='4'!$L$44 -> 9954.62 | R44: ='5'!$L$44 -> 8653.41 | U44: ='6'!$L$44 -> 10067.66 | X44: ='7'!$L$44 -> 56676.11 | AA44: ='8'!$L$44 -> 65873.35 | AD44: ='9'!$L$44 -> 0 | AG44: ='10'!$L$44 -> 0 | AJ44: ='11'!$L$44 -> 0 | AM44: ='12'!$L$44 -> 0 | AP44: =SUM(F44,I44,L44,O44,R44,U44,X44,AA44,AD44,AG44,AJ44,AM44) -> 169904.26
A45: =+B45&C45 -> Véhicules neufsSalaires spécialistes | B45: Véhicules neufs | C45: Salaires spécialistes | F45: ='1'!$L$45 -> 0 | I45: ='2'!$L$45 -> 0 | L45: ='3'!$L$45 -> 0 | O45: ='4'!$L$45 -> 0 | R45: ='5'!$L$45 -> 0 | U45: ='6'!$L$45 -> 0 | X45: ='7'!$L$45 -> 0 | AA45: ='8'!$L$45 -> 0 | AD45: ='9'!$L$45 -> 0 | AG45: ='10'!$L$45 -> 0 | AJ45: ='11'!$L$45 -> 0 | AM45: ='12'!$L$45 -> 0 | AP45: =SUM(F45,I45,L45,O45,R45,U45,X45,AA45,AD45,AG45,AJ45,AM45) -> 0
A46: =+B46&C46 -> Véhicules neufs[...] | B46: Véhicules neufs | C46: [...] | F46: ='1'!$L$46 -> 0 | I46: ='2'!$L$46 -> 0 | L46: ='3'!$L$46 -> 0 | O46: ='4'!$L$46 -> 0 | R46: ='5'!$L$46 -> 0 | U46: ='6'!$L$46 -> 0 | X46: ='7'!$L$46 -> 0 | AA46: ='8'!$L$46 -> 0 | AD46: ='9'!$L$46 -> 0 | AG46: ='10'!$L$46 -> 0 | AJ46: ='11'!$L$46 -> 0 | AM46: ='12'!$L$46 -> 0 | AP46: =SUM(F46,I46,L46,O46,R46,U46,X46,AA46,AD46,AG46,AJ46,AM46) -> 0
A47: =+B47&C47 -> Véhicules neufs[...] | B47: Véhicules neufs | C47: [...] | F47: ='1'!$L$47 -> 0 | I47: ='2'!$L$47 -> 0 | L47: ='3'!$L$47 -> 0 | O47: ='4'!$L$47 -> 0 | R47: ='5'!$L$47 -> 0 | U47: ='6'!$L$47 -> 0 | X47: ='7'!$L$47 -> 0 | AA47: ='8'!$L$47 -> 0 | AD47: ='9'!$L$47 -> 0 | AG47: ='10'!$L$47 -> 0 | AJ47: ='11'!$L$47 -> 0 | AM47: ='12'!$L$47 -> 0 | AP47: =SUM(F47,I47,L47,O47,R47,U47,X47,AA47,AD47,AG47,AJ47,AM47) -> 0
A48: =+B48&C48 -> Véhicules neufs[...] | B48: Véhicules neufs | C48: [...] | F48: ='1'!$L$48 -> 0 | I48: ='2'!$L$48 -> 0 | L48: ='3'!$L$48 -> 0 | O48: ='4'!$L$48 -> 0 | R48: ='5'!$L$48 -> 0 | U48: ='6'!$L$48 -> 0 | X48: ='7'!$L$48 -> 0 | AA48: ='8'!$L$48 -> 0 | AD48: ='9'!$L$48 -> 0 | AG48: ='10'!$L$48 -> 0 | AJ48: ='11'!$L$48 -> 0 | AM48: ='12'!$L$48 -> 0 | AP48: =SUM(F48,I48,L48,O48,R48,U48,X48,AA48,AD48,AG48,AJ48,AM48) -> 0
A49: =+B49&C49 -> Véhicules neufsSalaires en absences | B49: Véhicules neufs | C49: Salaires en absences | F49: ='1'!$L$49 -> 7394.06 | I49: ='2'!$L$49 -> 10835.22 | L49: ='3'!$L$49 -> 9708.4 | O49: ='4'!$L$49 -> 13664.22 | R49: ='5'!$L$49 -> 15115.93 | U49: ='6'!$L$49 -> 16636.16 | X49: ='7'!$L$49 -> 88767.11 | AA49: ='8'!$L$49 -> 101576.04 | AD49: ='9'!$L$49 -> 0 | AG49: ='10'!$L$49 -> 0 | AJ49: ='11'!$L$49 -> 0 | AM49: ='12'!$L$49 -> 0 | AP49: =SUM(F49,I49,L49,O49,R49,U49,X49,AA49,AD49,AG49,AJ49,AM49) -> 263697.14
A50: =+B50&C50 -> Véhicules neufsDéduction à la source | B50: Véhicules neufs | C50: Déduction à la source | F50: ='1'!$L$50 -> 14260.56 | I50: ='2'!$L$50 -> 13919.38 | L50: ='3'!$L$50 -> -707.4 | O50: ='4'!$L$50 -> 10566.27 | R50: ='5'!$L$50 -> 12289.25 | U50: ='6'!$L$50 -> 12245.78 | X50: ='7'!$L$50 -> 73689.74 | AA50: ='8'!$L$50 -> 85145.66 | AD50: ='9'!$L$50 -> 0 | AG50: ='10'!$L$50 -> 0 | AJ50: ='11'!$L$50 -> 0 | AM50: ='12'!$L$50 -> 0 | AP50: =SUM(F50,I50,L50,O50,R50,U50,X50,AA50,AD50,AG50,AJ50,AM50) -> 221409.24
A51: =+B51&C51 -> Véhicules neufsBénéfices marginaux | B51: Véhicules neufs | C51: Bénéfices marginaux | F51: ='1'!$L$51 -> 5856 | I51: ='2'!$L$51 -> 5662.03 | L51: ='3'!$L$51 -> 8170.62 | O51: ='4'!$L$51 -> 7572.49 | R51: ='5'!$L$51 -> 8807.29 | U51: ='6'!$L$51 -> 8776.15 | X51: ='7'!$L$51 -> 52810.97 | AA51: ='8'!$L$51 -> 61021.04 | AD51: ='9'!$L$51 -> 0 | AG51: ='10'!$L$51 -> 0 | AJ51: ='11'!$L$51 -> 0 | AM51: ='12'!$L$51 -> 0 | AP51: =SUM(F51,I51,L51,O51,R51,U51,X51,AA51,AD51,AG51,AJ51,AM51) -> 158676.59
A52: =+B52&C52 -> Véhicules neufsCsst | B52: Véhicules neufs | C52: Csst | F52: ='1'!$L$52 -> 0 | I52: ='2'!$L$52 -> 2918.05 | L52: ='3'!$L$52 -> 10660.71 | O52: ='4'!$L$52 -> 1761.05 | R52: ='5'!$L$52 -> 2048.21 | U52: ='6'!$L$52 -> 2040.96 | X52: ='7'!$L$52 -> 21281.63 | AA52: ='8'!$L$52 -> 23190.95 | AD52: ='9'!$L$52 -> 0 | AG52: ='10'!$L$52 -> 0 | AJ52: ='11'!$L$52 -> 0 | AM52: ='12'!$L$52 -> 0 | AP52: =SUM(F52,I52,L52,O52,R52,U52,X52,AA52,AD52,AG52,AJ52,AM52) -> 63901.56
A53: =+B53&C53 -> Véhicules neufs[...] | B53: Véhicules neufs | C53: [...] | F53: ='1'!$L$53 -> 0 | I53: ='2'!$L$53 -> 0 | L53: ='3'!$L$53 -> 0 | O53: ='4'!$L$53 -> 0 | R53: ='5'!$L$53 -> 0 | U53: ='6'!$L$53 -> 0 | X53: ='7'!$L$53 -> 0 | AA53: ='8'!$L$53 -> 0 | AD53: ='9'!$L$53 -> 0 | AG53: ='10'!$L$53 -> 0 | AJ53: ='11'!$L$53 -> 0 | AM53: ='12'!$L$53 -> 0 | AP53: =SUM(F53,I53,L53,O53,R53,U53,X53,AA53,AD53,AG53,AJ53,AM53) -> 0
A54: =+B54&C54 -> Véhicules neufsTOTAL PERSONNEL | B54: Véhicules neufs | C54: TOTAL PERSONNEL | D54: % brut | E54: =F54/F$27 -> 0.92941098 | F54: =+SUM(F42:F53) -> 43482.79 | G54: % brut | H54: =I54/I$27 -> 0.62061379 | I54: =+SUM(I42:I53) -> 68576.98 | J54: % brut | K54: =L54/L$27 -> 0.42077402 | L54: =+SUM(L42:L53) -> 78167 | M54: % brut | N54: =O54/O$27 -> 0.41177568 | O54: =+SUM(O42:O53) -> 76210.1 | P54: % brut | Q54: =R54/R$27 -> 0.31992105 | R54: =+SUM(R42:R53) -> 78065.59 | S54: % brut | T54: =U54/U$27 -> 0.46193051 | U54: =+SUM(U42:U53) -> 83490.3 | V54: % brut | W54: =X54/X$27 -> 0.43401127 | X54: =+SUM(X42:X53) -> 496432.16 | Y54: % brut | Z54: =AA54/AA$27 -> 0.41491637 | AA54: =+SUM(AA42:AA53) -> 564306.31 | AB54: % brut | AC54: =AD54/AD$27 -> #DIV/0! | AD54: =+SUM(AD42:AD53) -> 0 | AE54: % brut | AF54: =AG54/AG$27 -> #DIV/0! | AG54: =+SUM(AG42:AG53) -> 0 | AH54: % brut | AI54: =AJ54/AJ$27 -> #DIV/0! | AJ54: =+SUM(AJ42:AJ53) -> 0 | AK54: % brut | AL54: =AM54/AM$27 -> #DIV/0! | AM54: =+SUM(AM42:AM53) -> 0 | AN54: % brut | AO54: =AP54/AP$27 -> 0.43067255 | AP54: =+SUM(AP42:AP53) -> 1488731.2
A55: =+B55&C55 -> Véhicules neufsPublicité 2 | B55: Véhicules neufs | C55: Publicité 2 | F55: ='1'!$L$55 -> 0 | I55: ='2'!$L$55 -> 0 | L55: ='3'!$L$55 -> 0 | O55: ='4'!$L$55 -> 0 | R55: ='5'!$L$55 -> 0 | U55: ='6'!$L$55 -> 0 | X55: ='7'!$L$55 -> 0 | AA55: ='8'!$L$55 -> 0 | AD55: ='9'!$L$55 -> 0 | AG55: ='10'!$L$55 -> 0 | AJ55: ='11'!$L$55 -> 0 | AM55: ='12'!$L$55 -> 0 | AP55: =SUM(F55,I55,L55,O55,R55,U55,X55,AA55,AD55,AG55,AJ55,AM55) -> 0
A56: =+B56&C56 -> Véhicules neufsService gratuit 2 | B56: Véhicules neufs | C56: Service gratuit 2 | F56: ='1'!$L$56 -> 0 | I56: ='2'!$L$56 -> 0 | L56: ='3'!$L$56 -> 0 | O56: ='4'!$L$56 -> 0 | R56: ='5'!$L$56 -> 0 | U56: ='6'!$L$56 -> 0 | X56: ='7'!$L$56 -> 0 | AA56: ='8'!$L$56 -> 0 | AD56: ='9'!$L$56 -> 0 | AG56: ='10'!$L$56 -> 0 | AJ56: ='11'!$L$56 -> 0 | AM56: ='12'!$L$56 -> 0 | AP56: =SUM(F56,I56,L56,O56,R56,U56,X56,AA56,AD56,AG56,AJ56,AM56) -> 0
A57: =+B57&C57 -> Véhicules neufsFrais véhicules de cie | B57: Véhicules neufs | C57: Frais véhicules de cie | F57: ='1'!$L$57 -> 5359.43 | I57: ='2'!$L$57 -> 5064.99 | L57: ='3'!$L$57 -> 5758.38 | O57: ='4'!$L$57 -> 5494.87 | R57: ='5'!$L$57 -> 6376 | U57: ='6'!$L$57 -> 7978.53 | X57: ='7'!$L$57 -> 41713.31 | AA57: ='8'!$L$57 -> 50385.55 | AD57: ='9'!$L$57 -> 0 | AG57: ='10'!$L$57 -> 0 | AJ57: ='11'!$L$57 -> 0 | AM57: ='12'!$L$57 -> 0 | AP57: =SUM(F57,I57,L57,O57,R57,U57,X57,AA57,AD57,AG57,AJ57,AM57) -> 128131.06
A58: =+B58&C58 -> Véhicules neufsInformatique | B58: Véhicules neufs | C58: Informatique | F58: ='1'!$L$58 -> 5798.14 | I58: ='2'!$L$58 -> 6368.15 | L58: ='3'!$L$58 -> 5346.08 | O58: ='4'!$L$58 -> 4538.32 | R58: ='5'!$L$58 -> 6391.27 | U58: ='6'!$L$58 -> 5204 | X58: ='7'!$L$58 -> 39020.85 | AA58: ='8'!$L$58 -> 45006.86 | AD58: ='9'!$L$58 -> 0 | AG58: ='10'!$L$58 -> 0 | AJ58: ='11'!$L$58 -> 0 | AM58: ='12'!$L$58 -> 0 | AP58: =SUM(F58,I58,L58,O58,R58,U58,X58,AA58,AD58,AG58,AJ58,AM58) -> 117673.67
A59: =+B59&C59 -> Véhicules neufsFrais de déplacement | B59: Véhicules neufs | C59: Frais de déplacement | F59: ='1'!$L$59 -> 98.29 | I59: ='2'!$L$59 -> 72.73 | L59: ='3'!$L$59 -> 587.39 | O59: ='4'!$L$59 -> 209.82 | R59: ='5'!$L$59 -> 612.46 | U59: ='6'!$L$59 -> 755.69 | X59: ='7'!$L$59 -> 4127.33 | AA59: ='8'!$L$59 -> 4345.06 | AD59: ='9'!$L$59 -> 0 | AG59: ='10'!$L$59 -> 0 | AJ59: ='11'!$L$59 -> 0 | AM59: ='12'!$L$59 -> 0 | AP59: =SUM(F59,I59,L59,O59,R59,U59,X59,AA59,AD59,AG59,AJ59,AM59) -> 10808.77
A60: =+B60&C60 -> Véhicules neufsServices extérieurs | B60: Véhicules neufs | C60: Services extérieurs | F60: ='1'!$L$60 -> 6042.08 | I60: ='2'!$L$60 -> 9258.25 | L60: ='3'!$L$60 -> 6231.54 | O60: ='4'!$L$60 -> 8488.96 | R60: ='5'!$L$60 -> 7206.23 | U60: ='6'!$L$60 -> 6757.48 | X60: ='7'!$L$60 -> 50753.3 | AA60: ='8'!$L$60 -> 57108.26 | AD60: ='9'!$L$60 -> 0 | AG60: ='10'!$L$60 -> 0 | AJ60: ='11'!$L$60 -> 0 | AM60: ='12'!$L$60 -> 0 | AP60: =SUM(F60,I60,L60,O60,R60,U60,X60,AA60,AD60,AG60,AJ60,AM60) -> 151846.1
A61: =+B61&C61 -> Véhicules neufsFournitures autres | B61: Véhicules neufs | C61: Fournitures autres | F61: ='1'!$L$61 -> 0 | I61: ='2'!$L$61 -> 0 | L61: ='3'!$L$61 -> 0 | O61: ='4'!$L$61 -> 477.01 | R61: ='5'!$L$61 -> 74.93 | U61: ='6'!$L$61 -> 8.92 | X61: ='7'!$L$61 -> 560.86 | AA61: ='8'!$L$61 -> 568.3 | AD61: ='9'!$L$61 -> 0 | AG61: ='10'!$L$61 -> 0 | AJ61: ='11'!$L$61 -> 0 | AM61: ='12'!$L$61 -> 0 | AP61: =SUM(F61,I61,L61,O61,R61,U61,X61,AA61,AD61,AG61,AJ61,AM61) -> 1690.02
A62: =+B62&C62 -> Véhicules neufsUniformes | B62: Véhicules neufs | C62: Uniformes | F62: ='1'!$L$62 -> 0 | I62: ='2'!$L$62 -> 0 | L62: ='3'!$L$62 -> 0 | O62: ='4'!$L$62 -> 0 | R62: ='5'!$L$62 -> 0 | U62: ='6'!$L$62 -> 0 | X62: ='7'!$L$62 -> 0 | AA62: ='8'!$L$62 -> 0 | AD62: ='9'!$L$62 -> 0 | AG62: ='10'!$L$62 -> 0 | AJ62: ='11'!$L$62 -> 0 | AM62: ='12'!$L$62 -> 0 | AP62: =SUM(F62,I62,L62,O62,R62,U62,X62,AA62,AD62,AG62,AJ62,AM62) -> 0
A63: =+B63&C63 -> Véhicules neufsPapeterie | B63: Véhicules neufs | C63: Papeterie | F63: ='1'!$L$63 -> 248.87 | I63: ='2'!$L$63 -> 674.94 | L63: ='3'!$L$63 -> 500.69 | O63: ='4'!$L$63 -> 548.68 | R63: ='5'!$L$63 -> 755.68 | U63: ='6'!$L$63 -> 639.75 | X63: ='7'!$L$63 -> 3835.27 | AA63: ='8'!$L$63 -> 4598.83 | AD63: ='9'!$L$63 -> 0 | AG63: ='10'!$L$63 -> 0 | AJ63: ='11'!$L$63 -> 0 | AM63: ='12'!$L$63 -> 0 | AP63: =SUM(F63,I63,L63,O63,R63,U63,X63,AA63,AD63,AG63,AJ63,AM63) -> 11802.71
A64: =+B64&C64 -> Véhicules neufsTéléphone | B64: Véhicules neufs | C64: Téléphone | F64: ='1'!$L$64 -> 456.53 | I64: ='2'!$L$64 -> 462.41 | L64: ='3'!$L$64 -> 238.05 | O64: ='4'!$L$64 -> 130.22 | R64: ='5'!$L$64 -> 257.26 | U64: ='6'!$L$64 -> 228.24 | X64: ='7'!$L$64 -> 1989.7 | AA64: ='8'!$L$64 -> 2207.6 | AD64: ='9'!$L$64 -> 0 | AG64: ='10'!$L$64 -> 0 | AJ64: ='11'!$L$64 -> 0 | AM64: ='12'!$L$64 -> 0 | AP64: =SUM(F64,I64,L64,O64,R64,U64,X64,AA64,AD64,AG64,AJ64,AM64) -> 5970.01
A65: =+B65&C65 -> Véhicules neufsFrais postaux | B65: Véhicules neufs | C65: Frais postaux | F65: ='1'!$L$65 -> 65.22 | I65: ='2'!$L$65 -> 78.74 | L65: ='3'!$L$65 -> 136.35 | O65: ='4'!$L$65 -> 134.19 | R65: ='5'!$L$65 -> 162.85 | U65: ='6'!$L$65 -> 191.45 | X65: ='7'!$L$65 -> 1011.29 | AA65: ='8'!$L$65 -> 1254.48 | AD65: ='9'!$L$65 -> 0 | AG65: ='10'!$L$65 -> 0 | AJ65: ='11'!$L$65 -> 0 | AM65: ='12'!$L$65 -> 0 | AP65: =SUM(F65,I65,L65,O65,R65,U65,X65,AA65,AD65,AG65,AJ65,AM65) -> 3034.57
A66: =+B66&C66 -> Véhicules neufsDivers | B66: Véhicules neufs | C66: Divers | F66: ='1'!$L$66 -> 252.3 | I66: ='2'!$L$66 -> 386.13 | L66: ='3'!$L$66 -> 3441.41 | O66: ='4'!$L$66 -> 264.06 | R66: ='5'!$L$66 -> 1198.42 | U66: ='6'!$L$66 -> 40.97 | X66: ='7'!$L$66 -> 6387 | AA66: ='8'!$L$66 -> 6545.67 | AD66: ='9'!$L$66 -> 0 | AG66: ='10'!$L$66 -> 0 | AJ66: ='11'!$L$66 -> 0 | AM66: ='12'!$L$66 -> 0 | AP66: =SUM(F66,I66,L66,O66,R66,U66,X66,AA66,AD66,AG66,AJ66,AM66) -> 18515.96
A67: =+B67&C67 -> Véhicules neufsFormation | B67: Véhicules neufs | C67: Formation | F67: ='1'!$L$67 -> 523.33 | I67: ='2'!$L$67 -> 523.33 | L67: ='3'!$L$67 -> 523.33 | O67: ='4'!$L$67 -> 523.33 | R67: ='5'!$L$67 -> 843.33 | U67: ='6'!$L$67 -> 2923.33 | X67: ='7'!$L$67 -> 6383.31 | AA67: ='8'!$L$67 -> 7526.64 | AD67: ='9'!$L$67 -> 0 | AG67: ='10'!$L$67 -> 0 | AJ67: ='11'!$L$67 -> 0 | AM67: ='12'!$L$67 -> 0 | AP67: =SUM(F67,I67,L67,O67,R67,U67,X67,AA67,AD67,AG67,AJ67,AM67) -> 19769.93
A68: =+B68&C68 -> Véhicules neufsFrais bancaires | B68: Véhicules neufs | C68: Frais bancaires | F68: ='1'!$L$68 -> 1926.549 | I68: ='2'!$L$68 -> 2379.7485 | L68: ='3'!$L$68 -> 3004.101 | O68: ='4'!$L$68 -> 4056.885 | R68: ='5'!$L$68 -> 3102.8445 | U68: ='6'!$L$68 -> 2653.137 | X68: ='7'!$L$68 -> 20291.301 | AA68: ='8'!$L$68 -> 23118.404 | AD68: ='9'!$L$68 -> 0 | AG68: ='10'!$L$68 -> 0 | AJ68: ='11'!$L$68 -> 0 | AM68: ='12'!$L$68 -> 0 | AP68: =SUM(F68,I68,L68,O68,R68,U68,X68,AA68,AD68,AG68,AJ68,AM68) -> 60532.969
A69: =+B69&C69 -> Véhicules neufs[...] | B69: Véhicules neufs | C69: [...] | F69: ='1'!$L$69 -> 0 | I69: ='2'!$L$69 -> 0 | L69: ='3'!$L$69 -> 0 | O69: ='4'!$L$69 -> 0 | R69: ='5'!$L$69 -> 0 | U69: ='6'!$L$69 -> 0 | X69: ='7'!$L$69 -> 0 | AA69: ='8'!$L$69 -> 0 | AD69: ='9'!$L$69 -> 0 | AG69: ='10'!$L$69 -> 0 | AJ69: ='11'!$L$69 -> 0 | AM69: ='12'!$L$69 -> 0 | AP69: =SUM(F69,I69,L69,O69,R69,U69,X69,AA69,AD69,AG69,AJ69,AM69) -> 0
A70: =+B70&C70 -> Véhicules neufs[...] | B70: Véhicules neufs | C70: [...] | F70: ='1'!$L$70 -> 0 | I70: ='2'!$L$70 -> 0 | L70: ='3'!$L$70 -> 0 | O70: ='4'!$L$70 -> 0 | R70: ='5'!$L$70 -> 0 | U70: ='6'!$L$70 -> 0 | X70: ='7'!$L$70 -> 0 | AA70: ='8'!$L$70 -> 0 | AD70: ='9'!$L$70 -> 0 | AG70: ='10'!$L$70 -> 0 | AJ70: ='11'!$L$70 -> 0 | AM70: ='12'!$L$70 -> 0 | AP70: =SUM(F70,I70,L70,O70,R70,U70,X70,AA70,AD70,AG70,AJ70,AM70) -> 0
A71: =+B71&C71 -> Véhicules neufs[...] | B71: Véhicules neufs | C71: [...] | F71: ='1'!$L$71 -> 0 | I71: ='2'!$L$71 -> 0 | L71: ='3'!$L$71 -> 0 | O71: ='4'!$L$71 -> 0 | R71: ='5'!$L$71 -> 0 | U71: ='6'!$L$71 -> 0 | X71: ='7'!$L$71 -> 0 | AA71: ='8'!$L$71 -> 0 | AD71: ='9'!$L$71 -> 0 | AG71: ='10'!$L$71 -> 0 | AJ71: ='11'!$L$71 -> 0 | AM71: ='12'!$L$71 -> 0 | AP71: =SUM(F71,I71,L71,O71,R71,U71,X71,AA71,AD71,AG71,AJ71,AM71) -> 0
A72: =+B72&C72 -> Véhicules neufsTOTAL SEMI-FIXES | B72: Véhicules neufs | C72: TOTAL SEMI-FIXES | D72: % brut | E72: =F72/F$27 -> 0.44395847 | F72: =+SUM(F55:F71) -> 20770.739 | G72: % brut | H72: =I72/I$27 -> 0.22868533 | I72: =+SUM(I55:I71) -> 25269.419 | J72: % brut | K72: =L72/L$27 -> 0.13870584 | L72: =+SUM(L55:L71) -> 25767.321 | M72: % brut | N72: =O72/O$27 -> 0.13435694 | O72: =+SUM(O55:O71) -> 24866.345 | P72: % brut | Q72: =R72/R$27 -> 0.11057212 | R72: =+SUM(R55:R71) -> 26981.274 | S72: % brut | T72: =U72/U$27 -> 0.15149483 | U72: =+SUM(U55:U71) -> 27381.497 | V72: % brut | W72: =X72/X$27 -> 0.15393421 | X72: =+SUM(X55:X71) -> 176073.52 | Y72: % brut | Z72: =AA72/AA$27 -> 0.14901357 | AA72: =+SUM(AA55:AA71) -> 202665.65 | AB72: % brut | AC72: =AD72/AD$27 -> #DIV/0! | AD72: =+SUM(AD55:AD71) -> 0 | AE72: % brut | AF72: =AG72/AG$27 -> #DIV/0! | AG72: =+SUM(AG55:AG71) -> 0 | AH72: % brut | AI72: =AJ72/AJ$27 -> #DIV/0! | AJ72: =+SUM(AJ55:AJ71) -> 0 | AK72: % brut | AL72: =AM72/AM$27 -> #DIV/0! | AM72: =+SUM(AM55:AM71) -> 0 | AN72: % brut | AO72: =AP72/AP$27 -> 0.15325794 | AP72: =+SUM(AP55:AP71) -> 529775.77
A73: =+B73&C73 -> Véhicules neufs | B73: Véhicules neufs
A74: =+B74&C74 -> Véhicules neufsTOTAL DES DÉPENSES | B74: Véhicules neufs | C74: TOTAL DES DÉPENSES | D74: % brut | E74: =F74/F$27 -> 2.4151082 | F74: =F41+F54+F72 -> 112991.61 | G74: % brut | H74: =I74/I$27 -> 1.4495734 | I74: =I41+I54+I72 -> 160175.89 | J74: % brut | K74: =L74/L$27 -> 1.041079 | L74: =L41+L54+L72 -> 193400.78 | M74: % brut | N74: =O74/O$27 -> 1.0990819 | O74: =O41+O54+O72 -> 203414.5 | P74: % brut | Q74: =R74/R$27 -> 0.86838431 | R74: =R41+R54+R72 -> 211898.94 | S74: % brut | T74: =U74/U$27 -> 1.1614465 | U74: =U41+U54+U72 -> 209922.31 | V74: % brut | W74: =X74/X$27 -> 1.1185026 | X74: =X41+X54+X72 -> 1279369.2 | Y74: % brut | Z74: =AA74/AA$27 -> 1.0874992 | AA74: =AA41+AA54+AA72 -> 1479051.5 | AB74: % brut | AC74: =AD74/AD$27 -> #DIV/0! | AD74: =AD41+AD54+AD72 -> 0 | AE74: % brut | AF74: =AG74/AG$27 -> #DIV/0! | AG74: =AG41+AG54+AG72 -> 0 | AH74: % brut | AI74: =AJ74/AJ$27 -> #DIV/0! | AJ74: =AJ41+AJ54+AJ72 -> 0 | AK74: % brut | AL74: =AM74/AM$27 -> #DIV/0! | AM74: =AM41+AM54+AM72 -> 0 | AN74: % brut | AO74: =AP74/AP$27 -> 1.113825 | AP74: =AP41+AP54+AP72 -> 3850224.8
A75: =+B75&C75 -> Véhicules neufsProgramme neuf 1 | B75: Véhicules neufs | C75: Programme neuf 1 | F75: ='1'!$L$75 -> 11500 | I75: ='2'!$L$75 -> 19676.52 | L75: ='3'!$L$75 -> 26100 | O75: ='4'!$L$75 -> 0 | R75: ='5'!$L$75 -> 0 | U75: ='6'!$L$75 -> 19500 | X75: ='7'!$L$75 -> 96776.52 | AA75: ='8'!$L$75 -> 96776.52 | AD75: ='9'!$L$75 -> 0 | AG75: ='10'!$L$75 -> 0 | AJ75: ='11'!$L$75 -> 0 | AM75: ='12'!$L$75 -> 0 | AP75: =SUM(F75,I75,L75,O75,R75,U75,X75,AA75,AD75,AG75,AJ75,AM75) -> 270329.56
A76: =+B76&C76 -> Véhicules neufsProgramme neuf 2 | B76: Véhicules neufs | C76: Programme neuf 2 | F76: ='1'!$L$76 -> 0 | I76: ='2'!$L$76 -> 0 | L76: ='3'!$L$76 -> 0 | O76: ='4'!$L$76 -> 0 | R76: ='5'!$L$76 -> 0 | U76: ='6'!$L$76 -> 0 | X76: ='7'!$L$76 -> 0 | AA76: ='8'!$L$76 -> 0 | AD76: ='9'!$L$76 -> 0 | AG76: ='10'!$L$76 -> 0 | AJ76: ='11'!$L$76 -> 0 | AM76: ='12'!$L$76 -> 0 | AP76: =SUM(F76,I76,L76,O76,R76,U76,X76,AA76,AD76,AG76,AJ76,AM76) -> 0
A77: =+B77&C77 -> Véhicules neufsProgramme neuf 3 | B77: Véhicules neufs | C77: Programme neuf 3 | F77: ='1'!$L$77 -> 0 | I77: ='2'!$L$77 -> 0 | L77: ='3'!$L$77 -> 0 | O77: ='4'!$L$77 -> 0 | R77: ='5'!$L$77 -> 0 | U77: ='6'!$L$77 -> 0 | X77: ='7'!$L$77 -> 0 | AA77: ='8'!$L$77 -> 0 | AD77: ='9'!$L$77 -> 0 | AG77: ='10'!$L$77 -> 0 | AJ77: ='11'!$L$77 -> 0 | AM77: ='12'!$L$77 -> 0 | AP77: =SUM(F77,I77,L77,O77,R77,U77,X77,AA77,AD77,AG77,AJ77,AM77) -> 0
A78: =+B78&C78 -> Véhicules neufsHoldbacks | B78: Véhicules neufs | C78: Holdbacks | F78: ='1'!$L$78 -> 22341 | I78: ='2'!$L$78 -> 115388 | L78: ='3'!$L$78 -> 91841 | O78: ='4'!$L$78 -> 64999 | R78: ='5'!$L$78 -> 102678 | U78: ='6'!$L$78 -> 45674 | X78: ='7'!$L$78 -> 480818 | AA78: ='8'!$L$78 -> 575488.15 | AD78: ='9'!$L$78 -> 0 | AG78: ='10'!$L$78 -> 0 | AJ78: ='11'!$L$78 -> 0 | AM78: ='12'!$L$78 -> 0 | AP78: =SUM(F78,I78,L78,O78,R78,U78,X78,AA78,AD78,AG78,AJ78,AM78) -> 1499227.1
A79: =+B79&C79 -> Véhicules neufs[...] | B79: Véhicules neufs | C79: [...] | F79: ='1'!$L$79 -> 0 | I79: ='2'!$L$79 -> 0 | L79: ='3'!$L$79 -> 0 | O79: ='4'!$L$79 -> 0 | R79: ='5'!$L$79 -> 0 | U79: ='6'!$L$79 -> 0 | X79: ='7'!$L$79 -> 0 | AA79: ='8'!$L$79 -> 0 | AD79: ='9'!$L$79 -> 0 | AG79: ='10'!$L$79 -> 0 | AJ79: ='11'!$L$79 -> 0 | AM79: ='12'!$L$79 -> 0 | AP79: =SUM(F79,I79,L79,O79,R79,U79,X79,AA79,AD79,AG79,AJ79,AM79) -> 0
A80: =+B80&C80 -> Véhicules neufs[...] | B80: Véhicules neufs | C80: [...] | F80: ='1'!$L$80 -> 0 | I80: ='2'!$L$80 -> 0 | L80: ='3'!$L$80 -> 0 | O80: ='4'!$L$80 -> 0 | R80: ='5'!$L$80 -> 0 | U80: ='6'!$L$80 -> 0 | X80: ='7'!$L$80 -> 0 | AA80: ='8'!$L$80 -> 0 | AD80: ='9'!$L$80 -> 0 | AG80: ='10'!$L$80 -> 0 | AJ80: ='11'!$L$80 -> 0 | AM80: ='12'!$L$80 -> 0 | AP80: =SUM(F80,I80,L80,O80,R80,U80,X80,AA80,AD80,AG80,AJ80,AM80) -> 0
A81: =+B81&C81 -> Véhicules neufs[...] | B81: Véhicules neufs | C81: [...] | F81: ='1'!$L$81 -> 0 | I81: ='2'!$L$81 -> 0 | L81: ='3'!$L$81 -> 0 | O81: ='4'!$L$81 -> 0 | R81: ='5'!$L$81 -> 0 | U81: ='6'!$L$81 -> 0 | X81: ='7'!$L$81 -> 0 | AA81: ='8'!$L$81 -> 0 | AD81: ='9'!$L$81 -> 0 | AG81: ='10'!$L$81 -> 0 | AJ81: ='11'!$L$81 -> 0 | AM81: ='12'!$L$81 -> 0 | AP81: =SUM(F81,I81,L81,O81,R81,U81,X81,AA81,AD81,AG81,AJ81,AM81) -> 0
A82: =+B82&C82 -> Véhicules neufsFrais administration | B82: Véhicules neufs | C82: Frais administration | F82: ='1'!$L$82 -> 6261 | I82: ='2'!$L$82 -> 15902.7 | L82: ='3'!$L$82 -> 20188 | O82: ='4'!$L$82 -> 18363 | R82: ='5'!$L$82 -> 25377 | U82: ='6'!$L$82 -> 19801 | X82: ='7'!$L$82 -> 125994.7 | AA82: ='8'!$L$82 -> 146682.69 | AD82: ='9'!$L$82 -> 0 | AG82: ='10'!$L$82 -> 0 | AJ82: ='11'!$L$82 -> 0 | AM82: ='12'!$L$82 -> 0 | AP82: =SUM(F82,I82,L82,O82,R82,U82,X82,AA82,AD82,AG82,AJ82,AM82) -> 378570.09
A83: =+B83&C83 -> Véhicules neufsAUTRES REVENUS | B83: Véhicules neufs | C83: AUTRES REVENUS | F83: =+SUM(F75:F82) -> 40102 | I83: =+SUM(I75:I82) -> 150967.22 | L83: =+SUM(L75:L82) -> 138129 | O83: =+SUM(O75:O82) -> 83362 | R83: =+SUM(R75:R82) -> 128055 | U83: =+SUM(U75:U82) -> 84975 | X83: =+SUM(X75:X82) -> 703589.22 | AA83: =+SUM(AA75:AA82) -> 818947.36 | AD83: =+SUM(AD75:AD82) -> 0 | AG83: =+SUM(AG75:AG82) -> 0 | AJ83: =+SUM(AJ75:AJ82) -> 0 | AM83: =+SUM(AM75:AM82) -> 0 | AP83: =+SUM(AP75:AP82) -> 2148126.8
A84: =+B84&C84 -> Véhicules neufs | B84: Véhicules neufs
A85: =+B85&C85 -> Véhicules neufsPROFIT DÉPARTEMENTAL | B85: Véhicules neufs | C85: PROFIT DÉPARTEMENTAL | F85: =F27-F74+F83 -> -26104.289 | I85: =I27-I74+I83 -> 101289.97 | L85: =L27-L74+L83 -> 130497.77 | O85: =O27-O74+O83 -> 65024.245 | R85: =R27-R74+R83 -> 160171.23 | U85: =U27-U74+U83 -> 55794.813 | X85: =X27-X74+X83 -> 568043.19 | AA85: =AA27-AA74+AA83 -> 699944.16 | AD85: =AD27-AD74+AD83 -> 0 | AG85: =AG27-AG74+AG83 -> 0 | AJ85: =AJ27-AJ74+AJ83 -> 0 | AM85: =AM27-AM74+AM83 -> 0 | AP85: =AP27-AP74+AP83 -> 1754661.1
C89: Véhicules usagés | D89: Véhicules usagés
D91: RÉALISATION | G91: RÉALISATION | J91: RÉALISATION | M91: RÉALISATION | P91: RÉALISATION | S91: RÉALISATION | V91: RÉALISATION | Y91: RÉALISATION | AB91: RÉALISATION | AE91: RÉALISATION | AH91: RÉALISATION | AK91: RÉALISATION | AN91: RÉALISATION
D92: UNITE | E92: $P/UNITE | F92: $PROFITS | G92: UNITE | H92: $P/UNITE | I92: $PROFITS | J92: UNITE | K92: $P/UNITE | L92: $PROFITS | M92: UNITE | N92: $P/UNITE | O92: $PROFITS | P92: UNITE | Q92: $P/UNITE | R92: $PROFITS | S92: UNITE | T92: $P/UNITE | U92: $PROFITS | V92: UNITE | W92: $P/UNITE | X92: $PROFITS | Y92: UNITE | Z92: $P/UNITE | AA92: $PROFITS | AB92: UNITE | AC92: $P/UNITE | AD92: $PROFITS | AE92: UNITE | AF92: $P/UNITE | AG92: $PROFITS | AH92: UNITE | AI92: $P/UNITE | AJ92: $PROFITS | AK92: UNITE | AL92: $P/UNITE | AM92: $PROFITS | AN92: UNITE | AO92: $P/UNITE | AP92: $PROFITS
A93: =+B93&C93 -> Véhicules usagésVentes nettes | B93: Véhicules usagés | C93: Ventes nettes | F93: ='1'!$L$93 -> 495435.11 | I93: ='2'!$L$93 -> 954945.51 | L93: ='3'!$L$93 -> 1538216.9 | O93: ='4'!$L$93 -> 1146628.7 | R93: ='5'!$L$93 -> 1342441.4 | U93: ='6'!$L$93 -> 1661612 | X93: ='7'!$L$93 -> 9172979.1 | AA93: ='8'!$L$93 -> 10569238 | AD93: ='9'!$L$93 -> 0 | AG93: ='10'!$L$93 -> 0 | AJ93: ='11'!$L$93 -> 0 | AM93: ='12'!$L$93 -> 0 | AP93: =SUM(F93,I93,L93,O93,R93,U93,X93,AA93,AD93,AG93,AJ93,AM93) -> 26881497
A94: =+B94&C94 -> Véhicules usagésCertifié | B94: Véhicules usagés | C94: Certifié | D94: ='1'!$J$94 -> 14 | E94: =IF(D94=0,0,F94/D94) -> 1047.64 | F94: ='1'!$L$94 -> 14666.96 | G94: ='2'!$J$94 -> 30 | H94: =IF(G94=0,0,I94/G94) -> 765.23067 | I94: ='2'!$L$94 -> 22956.92 | J94: ='3'!$J$94 -> 42 | K94: =IF(J94=0,0,L94/J94) -> 932.81976 | L94: ='3'!$L$94 -> 39178.43 | M94: ='4'!$J$94 -> 39 | N94: =IF(M94=0,0,O94/M94) -> 1018.0956 | O94: ='4'!$L$94 -> 39705.73 | P94: ='5'!$J$94 -> 38 | Q94: =IF(P94=0,0,R94/P94) -> 1319.41 | R94: ='5'!$L$94 -> 50137.58 | S94: ='6'!$J$94 -> 36 | T94: =IF(S94=0,0,U94/S94) -> 870.74722 | U94: ='6'!$L$94 -> 31346.9 | V94: ='7'!$J$94 -> 239 | W94: =IF(V94=0,0,X94/V94) -> 1104.7834 | X94: ='7'!$L$94 -> 264043.24 | Y94: ='8'!$J$94 -> 278 | Z94: =IF(Y94=0,0,AA94/Y94) -> 1092.457 | AA94: ='8'!$L$94 -> 303703.05 | AB94: ='9'!$J$94 -> 0 | AC94: =IF(AB94=0,0,AD94/AB94) -> 0 | AD94: ='9'!$L$94 -> 0 | AE94: ='10'!$J$94 -> 0 | AF94: =IF(AE94=0,0,AG94/AE94) -> 0 | AG94: ='10'!$L$94 -> 0 | AH94: ='11'!$J$94 -> 0 | AI94: =IF(AH94=0,0,AJ94/AH94) -> 0 | AJ94: ='11'!$L$94 -> 0 | AK94: ='12'!$J$94 -> 0 | AL94: =IF(AK94=0,0,AM94/AK94) -> 0 | AM94: ='12'!$L$94 -> 0 | AN94: =SUM(D94,G94,J94,M94,P94,S94,V94,Y94,AB94,AE94,AH94,AK94) -> 716 | AO94: =IF(AN94=0,0,AP94/AN94) -> 1069.4676 | AP94: =SUM(F94,I94,L94,O94,R94,U94,X94,AA94,AD94,AG94,AJ94,AM94) -> 765738.81
A95: =+B95&C95 -> Véhicules usagésNon Certifié | B95: Véhicules usagés | C95: Non Certifié | D95: ='1'!$J$95 -> 1 | E95: =IF(D95=0,0,F95/D95) -> 715 | F95: ='1'!$L$95 -> 715 | G95: ='2'!$J$95 -> 0 | H95: =IF(G95=0,0,I95/G95) -> 0 | I95: ='2'!$L$95 -> 0 | J95: ='3'!$J$95 -> 0 | K95: =IF(J95=0,0,L95/J95) -> 0 | L95: ='3'!$L$95 -> 0 | M95: ='4'!$J$95 -> 2 | N95: =IF(M95=0,0,O95/M95) -> 755.545 | O95: ='4'!$L$95 -> 1511.09 | P95: ='5'!$J$95 -> 1 | Q95: =IF(P95=0,0,R95/P95) -> -434 | R95: ='5'!$L$95 -> -434 | S95: ='6'!$J$95 -> 1 | T95: =IF(S95=0,0,U95/S95) -> 39.68 | U95: ='6'!$L$95 -> 39.68 | V95: ='7'!$J$95 -> 6 | W95: =IF(V95=0,0,X95/V95) -> 340.11167 | X95: ='7'!$L$95 -> 2040.67 | Y95: ='8'!$J$95 -> 6 | Z95: =IF(Y95=0,0,AA95/Y95) -> 242.61167 | AA95: ='8'!$L$95 -> 1455.67 | AB95: ='9'!$J$95 -> 0 | AC95: =IF(AB95=0,0,AD95/AB95) -> 0 | AD95: ='9'!$L$95 -> 0 | AE95: ='10'!$J$95 -> 0 | AF95: =IF(AE95=0,0,AG95/AE95) -> 0 | AG95: ='10'!$L$95 -> 0 | AH95: ='11'!$J$95 -> 0 | AI95: =IF(AH95=0,0,AJ95/AH95) -> 0 | AJ95: ='11'!$L$95 -> 0 | AK95: ='12'!$J$95 -> 0 | AL95: =IF(AK95=0,0,AM95/AK95) -> 0 | AM95: ='12'!$L$95 -> 0 | AN95: =SUM(D95,G95,J95,M95,P95,S95,V95,Y95,AB95,AE95,AH95,AK95) -> 17 | AO95: =IF(AN95=0,0,AP95/AN95) -> 313.41824 | AP95: =SUM(F95,I95,L95,O95,R95,U95,X95,AA95,AD95,AG95,AJ95,AM95) -> 5328.11
A96: =+B96&C96 -> Véhicules usagésTotal Usagés | B96: Véhicules usagés | C96: Total Usagés | D96: =+D94+D95 -> 15 | E96: =IF(D96<=0,0,F96/D96) -> 1025.464 | F96: =+F94+F95 -> 15381.96 | G96: =+G94+G95 -> 30 | H96: =IF(G96<=0,0,I96/G96) -> 765.23067 | I96: =+I94+I95 -> 22956.92 | J96: =+J94+J95 -> 42 | K96: =IF(J96<=0,0,L96/J96) -> 932.81976 | L96: =+L94+L95 -> 39178.43 | M96: =+M94+M95 -> 41 | N96: =IF(M96<=0,0,O96/M96) -> 1005.2883 | O96: =+O94+O95 -> 41216.82 | P96: =+P94+P95 -> 39 | Q96: =IF(P96<=0,0,R96/P96) -> 1274.4508 | R96: =+R94+R95 -> 49703.58 | S96: =+S94+S95 -> 37 | T96: =IF(S96<=0,0,U96/S96) -> 848.28595 | U96: =+U94+U95 -> 31386.58 | V96: =+V94+V95 -> 245 | W96: =IF(V96<=0,0,X96/V96) -> 1086.0568 | X96: =+X94+X95 -> 266083.91 | Y96: =+Y94+Y95 -> 284 | Z96: =IF(Y96<=0,0,AA96/Y96) -> 1074.5025 | AA96: =+AA94+AA95 -> 305158.72 | AB96: =+AB94+AB95 -> 0 | AC96: =IF(AB96<=0,0,AD96/AB96) -> 0 | AD96: =+AD94+AD95 -> 0 | AE96: =+AE94+AE95 -> 0 | AF96: =IF(AE96<=0,0,AG96/AE96) -> 0 | AG96: =+AG94+AG95 -> 0 | AH96: =+AH94+AH95 -> 0 | AI96: =IF(AH96<=0,0,AJ96/AH96) -> 0 | AJ96: =+AJ94+AJ95 -> 0 | AK96: =+AK94+AK95 -> 0 | AL96: =IF(AK96<=0,0,AM96/AK96) -> 0 | AM96: =+AM94+AM95 -> 0 | AN96: =+AN94+AN95 -> 733 | AO96: =IF(AN96<=0,0,AP96/AN96) -> 1051.933 | AP96: =+AP94+AP95 -> 771066.92
A97: =+B97&C97 -> Véhicules usagés | B97: Véhicules usagés
A98: =+B98&C98 -> Véhicules usagésUS | B98: Véhicules usagés | C98: US | D98: ='1'!$J$98 -> 0 | E98: =IF(D98=0,0,F98/D98) -> 0 | F98: ='1'!$L$98 -> 0 | G98: ='2'!$J$98 -> 0 | H98: =IF(G98=0,0,I98/G98) -> 0 | I98: ='2'!$L$98 -> 0 | J98: ='3'!$J$98 -> 0 | K98: =IF(J98=0,0,L98/J98) -> 0 | L98: ='3'!$L$98 -> 0 | M98: ='4'!$J$98 -> 0 | N98: =IF(M98=0,0,O98/M98) -> 0 | O98: ='4'!$L$98 -> 0 | P98: ='5'!$J$98 -> 0 | Q98: =IF(P98=0,0,R98/P98) -> 0 | R98: ='5'!$L$98 -> 0 | S98: ='6'!$J$98 -> 0 | T98: =IF(S98=0,0,U98/S98) -> 0 | U98: ='6'!$L$98 -> 0 | V98: ='7'!$J$98 -> 0 | W98: =IF(V98=0,0,X98/V98) -> 0 | X98: ='7'!$L$98 -> 0 | Y98: ='8'!$J$98 -> 0 | Z98: =IF(Y98=0,0,AA98/Y98) -> 0 | AA98: ='8'!$L$98 -> 0 | AB98: ='9'!$J$98 -> 0 | AC98: =IF(AB98=0,0,AD98/AB98) -> 0 | AD98: ='9'!$L$98 -> 0 | AE98: ='10'!$J$98 -> 0 | AF98: =IF(AE98=0,0,AG98/AE98) -> 0 | AG98: ='10'!$L$98 -> 0 | AH98: ='11'!$J$98 -> 0 | AI98: =IF(AH98=0,0,AJ98/AH98) -> 0 | AJ98: ='11'!$L$98 -> 0 | AK98: ='12'!$J$98 -> 0 | AL98: =IF(AK98=0,0,AM98/AK98) -> 0 | AM98: ='12'!$L$98 -> 0 | AN98: =SUM(D98,G98,J98,M98,P98,S98,V98,Y98,AB98,AE98,AH98,AK98) -> 0 | AO98: =IF(AN98=0,0,AP98/AN98) -> 0 | AP98: =SUM(F98,I98,L98,O98,R98,U98,X98,AA98,AD98,AG98,AJ98,AM98) -> 0
A99: =+B99&C99 -> Véhicules usagésVentes au Gros | B99: Véhicules usagés | C99: Ventes au Gros | D99: ='1'!$J$99 -> 20 | E99: =IF(D99=0,0,F99/D99) -> -41.21 | F99: ='1'!$L$99 -> -824.2 | G99: ='2'!$J$99 -> 23 | H99: =IF(G99=0,0,I99/G99) -> 116.85522 | I99: ='2'!$L$99 -> 2687.67 | J99: ='3'!$J$99 -> 49 | K99: =IF(J99=0,0,L99/J99) -> 121.56245 | L99: ='3'!$L$99 -> 5956.56 | M99: ='4'!$J$99 -> 25 | N99: =IF(M99=0,0,O99/M99) -> 340.5116 | O99: ='4'!$L$99 -> 8512.79 | P99: ='5'!$J$99 -> 41 | Q99: =IF(P99=0,0,R99/P99) -> 611.62902 | R99: ='5'!$L$99 -> 25076.79 | S99: ='6'!$J$99 -> 47 | T99: =IF(S99=0,0,U99/S99) -> 230.93681 | U99: ='6'!$L$99 -> 10854.03 | V99: ='7'!$J$99 -> 266 | W99: =IF(V99=0,0,X99/V99) -> 224.93383 | X99: ='7'!$L$99 -> 59832.4 | Y99: ='8'!$J$99 -> 301 | Z99: =IF(Y99=0,0,AA99/Y99) -> 231.08522 | AA99: ='8'!$L$99 -> 69556.65 | AB99: ='9'!$J$99 -> 0 | AC99: =IF(AB99=0,0,AD99/AB99) -> 0 | AD99: ='9'!$L$99 -> 0 | AE99: ='10'!$J$99 -> 0 | AF99: =IF(AE99=0,0,AG99/AE99) -> 0 | AG99: ='10'!$L$99 -> 0 | AH99: ='11'!$J$99 -> 0 | AI99: =IF(AH99=0,0,AJ99/AH99) -> 0 | AJ99: ='11'!$L$99 -> 0 | AK99: ='12'!$J$99 -> 0 | AL99: =IF(AK99=0,0,AM99/AK99) -> 0 | AM99: ='12'!$L$99 -> 0 | AN99: =SUM(D99,G99,J99,M99,P99,S99,V99,Y99,AB99,AE99,AH99,AK99) -> 772 | AO99: =IF(AN99=0,0,AP99/AN99) -> 235.30141 | AP99: =SUM(F99,I99,L99,O99,R99,U99,X99,AA99,AD99,AG99,AJ99,AM99) -> 181652.69
A100: =+B100&C100 -> Véhicules usagés | B100: Véhicules usagés
A101: =+B101&C101 -> Véhicules usagésRev. Finances | B101: Véhicules usagés | C101: Rev. Finances | E101: =IF(D96=0,0,F101/D96) -> 309.40733 | F101: ='1'!$L$101 -> 4641.11 | H101: =IF(G96=0,0,I101/G96) -> 426.26367 | I101: ='2'!$L$101 -> 12787.91 | K101: =IF(J96=0,0,L101/J96) -> 635.76024 | L101: ='3'!$L$101 -> 26701.93 | N101: =IF(M96=0,0,O101/M96) -> 522.44707 | O101: ='4'!$L$101 -> 21420.33 | Q101: =IF(P96=0,0,R101/P96) -> 799.67385 | R101: ='5'!$L$101 -> 31187.28 | T101: =IF(S96=0,0,U101/S96) -> 1024.1838 | U101: ='6'!$L$101 -> 37894.8 | W101: =IF(V96=0,0,X101/V96) -> 717.59722 | X101: ='7'!$L$101 -> 175811.32 | Z101: =IF(Y96=0,0,AA101/Y96) -> 700.66926 | AA101: ='8'!$L$101 -> 198990.07 | AC101: =IF(AB96=0,0,AD101/AB96) -> 0 | AD101: ='9'!$L$101 -> 0 | AF101: =IF(AE96=0,0,AG101/AE96) -> 0 | AG101: ='10'!$L$101 -> 0 | AI101: =IF(AH96=0,0,AJ101/AH96) -> 0 | AJ101: ='11'!$L$101 -> 0 | AL101: =IF(AK96=0,0,AM101/AK96) -> 0 | AM101: ='12'!$L$101 -> 0 | AO101: =IF(AN96=0,0,AP101/AN96) -> 694.99966 | AP101: =SUM(F101,I101,L101,O101,R101,U101,X101,AA101,AD101,AG101,AJ101,AM101) -> 509434.75
A102: =+B102&C102 -> Véhicules usagésRev. Protections | B102: Véhicules usagés | C102: Rev. Protections | E102: =IF(D96=0,0,F102/D96) -> 1352.4093 | F102: ='1'!$L$102 -> 20286.14 | H102: =IF(G96=0,0,I102/G96) -> 1170.841 | I102: ='2'!$L$102 -> 35125.23 | K102: =IF(J96=0,0,L102/J96) -> 951.75143 | L102: ='3'!$L$102 -> 39973.56 | N102: =IF(M96=0,0,O102/M96) -> 981.94195 | O102: ='4'!$L$102 -> 40259.62 | Q102: =IF(P96=0,0,R102/P96) -> 1285.4226 | R102: ='5'!$L$102 -> 50131.48 | T102: =IF(S96=0,0,U102/S96) -> 1138.2676 | U102: ='6'!$L$102 -> 42115.9 | W102: =IF(V96=0,0,X102/V96) -> 1170.2397 | X102: ='7'!$L$102 -> 286708.72 | Z102: =IF(Y96=0,0,AA102/Y96) -> 1160.1815 | AA102: ='8'!$L$102 -> 329491.54 | AC102: =IF(AB96=0,0,AD102/AB96) -> 0 | AD102: ='9'!$L$102 -> 0 | AF102: =IF(AE96=0,0,AG102/AE96) -> 0 | AG102: ='10'!$L$102 -> 0 | AI102: =IF(AH96=0,0,AJ102/AH96) -> 0 | AJ102: ='11'!$L$102 -> 0 | AL102: =IF(AK96=0,0,AM102/AK96) -> 0 | AM102: ='12'!$L$102 -> 0 | AO102: =IF(AN96=0,0,AP102/AN96) -> 1151.5582 | AP102: =SUM(F102,I102,L102,O102,R102,U102,X102,AA102,AD102,AG102,AJ102,AM102) -> 844092.19
A103: =+B103&C103 -> Véhicules usagésRev. Autres | B103: Véhicules usagés | C103: Rev. Autres | E103: =IF(D96=0,0,F103/D96) -> 43.192667 | F103: ='1'!$L$103 -> 647.89 | H103: =IF(G96=0,0,I103/G96) -> 30.513667 | I103: ='2'!$L$103 -> 915.41 | K103: =IF(J96=0,0,L103/J96) -> 75.814048 | L103: ='3'!$L$103 -> 3184.19 | N103: =IF(M96=0,0,O103/M96) -> 4.9360976 | O103: ='4'!$L$103 -> 202.38 | Q103: =IF(P96=0,0,R103/P96) -> 41.958462 | R103: ='5'!$L$103 -> 1636.38 | T103: =IF(S96=0,0,U103/S96) -> 88.647297 | U103: ='6'!$L$103 -> 3279.95 | W103: =IF(V96=0,0,X103/V96) -> 55.461959 | X103: ='7'!$L$103 -> 13588.18 | Z103: =IF(Y96=0,0,AA103/Y96) -> 49.197746 | AA103: ='8'!$L$103 -> 13972.16 | AC103: =IF(AB96=0,0,AD103/AB96) -> 0 | AD103: ='9'!$L$103 -> 0 | AF103: =IF(AE96=0,0,AG103/AE96) -> 0 | AG103: ='10'!$L$103 -> 0 | AI103: =IF(AH96=0,0,AJ103/AH96) -> 0 | AJ103: ='11'!$L$103 -> 0 | AL103: =IF(AK96=0,0,AM103/AK96) -> 0 | AM103: ='12'!$L$103 -> 0 | AO103: =IF(AN96=0,0,AP103/AN96) -> 51.0594 | AP103: =SUM(F103,I103,L103,O103,R103,U103,X103,AA103,AD103,AG103,AJ103,AM103) -> 37426.54
A104: =+B104&C104 -> Véhicules usagésTotal F&I | B104: Véhicules usagés | C104: Total F&I | D104: =D96 -> 15 | E104: =IF(D104<=0,0,F104/D104) -> 1705.0093 | F104: =F101+F102+F103 -> 25575.14 | G104: =G96 -> 30 | H104: =IF(G104<=0,0,I104/G104) -> 1627.6183 | I104: =I101+I102+I103 -> 48828.55 | J104: =J96 -> 42 | K104: =IF(J104<=0,0,L104/J104) -> 1663.3257 | L104: =L101+L102+L103 -> 69859.68 | M104: =M96 -> 41 | N104: =IF(M104<=0,0,O104/M104) -> 1509.3251 | O104: =O101+O102+O103 -> 61882.33 | P104: =P96 -> 39 | Q104: =IF(P104<=0,0,R104/P104) -> 2127.0549 | R104: =R101+R102+R103 -> 82955.14 | S104: =S96 -> 37 | T104: =IF(S104<=0,0,U104/S104) -> 2251.0986 | U104: =U101+U102+U103 -> 83290.65 | V104: =V96 -> 245 | W104: =IF(V104<=0,0,X104/V104) -> 1943.2989 | X104: =X101+X102+X103 -> 476108.22 | Y104: =Y96 -> 284 | Z104: =IF(Y104<=0,0,AA104/Y104) -> 1910.0485 | AA104: =AA101+AA102+AA103 -> 542453.77 | AB104: =AB96 -> 0 | AC104: =IF(AB104<=0,0,AD104/AB104) -> 0 | AD104: =AD101+AD102+AD103 -> 0 | AE104: =AE96 -> 0 | AF104: =IF(AE104<=0,0,AG104/AE104) -> 0 | AG104: =AG101+AG102+AG103 -> 0 | AH104: =AH96 -> 0 | AI104: =IF(AH104<=0,0,AJ104/AH104) -> 0 | AJ104: =AJ101+AJ102+AJ103 -> 0 | AK104: =AK96 -> 0 | AL104: =IF(AK104<=0,0,AM104/AK104) -> 0 | AM104: =AM101+AM102+AM103 -> 0 | AN104: =AN96 -> 733 | AO104: =IF(AN104<=0,0,AP104/AN104) -> 1897.6173 | AP104: =AP101+AP102+AP103 -> 1390953.5
...

Sheet Conso
C1: Conso | K1: Véhicules neufs | V1: BUDGET | W1: RÉVISÉ | X1: ACTUAL | Y1: LY
D2: X | E2: O | F2: U | G2: X | H2: O | I2: U
D3: BUDGET ORIGINAL | G3: BUDGET REVISE | J3: RÉALISATION | M3: ÉCART réel / révisé | O3: ANNÉE PRÉCÉDENTE | R3: ÉCART réel / original
D4: UNITE | E4: $P/UNITÉ | F4: $PROFITS | G4: UNITE | H4: $P/UNITÉ | I4: $PROFITS | J4: UNITE | K4: $P/UNITE | L4: $PROFITS | M4: UNITÉ | N4: $PROFITS | O4: UNITE | P4: $P/UNITE | Q4: $PROFITS | R4: UNITE | S4: $PROFITS | V4: =+SUM(V5:V398) -> 0 | W4: =+SUM(W5:W398) -> 0 | X4: =+SUM(X5:X398) -> 0 | Y4: =+SUM(Y5:Y398) -> 0
A5: =+B5&C5 -> Véhicules neufsVentes nettes | B5: =+$K$1 -> Véhicules neufs | C5: Ventes nettes | F5: =+SUM(START:END!F5) -> 18402517 | I5: =+SUM(START:END!I5) -> 18402517 | L5: =+SUM(START:END!L5) -> 56888968 | Q5: =+SUM(START:END!Q5) -> 55050918
A6: =+B6&C6 -> Véhicules neufsAutos détail | B6: =+$K$1 -> Véhicules neufs | C6: Autos détail | D6: =+SUM(START:END!D6) -> 535.19724 | E6: =IF(D6=0,0,F6/D6) -> 871.7138 | F6: =+SUM(START:END!F6) -> 466538.82 | G6: =+SUM(START:END!G6) -> 535.19724 | H6: =IF(G6=0,0,I6/G6) -> 939.93141 | I6: =+SUM(START:END!I6) -> 503048.7 | J6: =+SUM(START:END!J6) -> 450 | K6: =IF(J6=0,0,L6/J6) -> 1019.553 | L6: =+SUM(START:END!L6) -> 458798.85 | M6: =J6-G6 -> -85.197239 | N6: =L6-I6 -> -44249.846 | O6: =+SUM(START:END!O6) -> 864 | P6: =IF(O6=0,0,Q6/O6) -> 597.53912 | Q6: =+SUM(START:END!Q6) -> 516273.8 | R6: =J6-O6 -> -414 | S6: =L6-Q6 -> -57474.95
A7: =+B7&C7 -> Véhicules neufsCamions détail | B7: =+$K$1 -> Véhicules neufs | C7: Camions détail | D7: =+SUM(START:END!D7) -> 719.31444 | E7: =IF(D7=0,0,F7/D7) -> 1609.9676 | F7: =+SUM(START:END!F7) -> 1158073 | G7: =+SUM(START:END!G7) -> 719.31444 | H7: =IF(G7=0,0,I7/G7) -> 1685.2248 | I7: =+SUM(START:END!I7) -> 1212206.5 | J7: =+SUM(START:END!J7) -> 719 | K7: =IF(J7=0,0,L7/J7) -> 2160.5239 | L7: =+SUM(START:END!L7) -> 1553416.7 | M7: =J7-G7 -> -0.3144427 | N7: =L7-I7 -> 341210.21 | O7: =+SUM(START:END!O7) -> 555 | P7: =IF(O7=0,0,Q7/O7) -> 746.38342 | Q7: =+SUM(START:END!Q7) -> 414242.8 | R7: =J7-O7 -> 164 | S7: =L7-Q7 -> 1139173.9
A8: =+B8&C8 -> Véhicules neufsSprinter | B8: =+$K$1 -> Véhicules neufs | C8: Sprinter | D8: =+SUM(START:END!D8) -> 0 | E8: =IF(D8=0,0,F8/D8) -> 0 | F8: =+SUM(START:END!F8) -> 0 | G8: =+SUM(START:END!G8) -> 0 | H8: =IF(G8=0,0,I8/G8) -> 0 | I8: =+SUM(START:END!I8) -> 0 | J8: =+SUM(START:END!J8) -> 0 | K8: =IF(J8=0,0,L8/J8) -> 0 | L8: =+SUM(START:END!L8) -> 0 | M8: =J8-G8 -> 0 | N8: =L8-I8 -> 0 | O8: =+SUM(START:END!O8) -> 0 | P8: =IF(O8=0,0,Q8/O8) -> 0 | Q8: =+SUM(START:END!Q8) -> 0 | R8: =J8-O8 -> 0 | S8: =L8-Q8 -> 0
A9: =+B9&C9 -> Véhicules neufsMoto détail | B9: =+$K$1 -> Véhicules neufs | C9: Moto détail | D9: =+SUM(START:END!D9) -> 0 | E9: =IF(D9=0,0,F9/D9) -> 0 | F9: =+SUM(START:END!F9) -> 0 | G9: =+SUM(START:END!G9) -> 0 | H9: =IF(G9=0,0,I9/G9) -> 0 | I9: =+SUM(START:END!I9) -> 0 | J9: =+SUM(START:END!J9) -> 0 | K9: =IF(J9=0,0,L9/J9) -> 0 | L9: =+SUM(START:END!L9) -> 0 | M9: =J9-G9 -> 0 | N9: =L9-I9 -> 0 | O9: =+SUM(START:END!O9) -> 0 | P9: =IF(O9=0,0,Q9/O9) -> 0 | Q9: =+SUM(START:END!Q9) -> 0 | R9: =J9-O9 -> 0 | S9: =L9-Q9 -> 0
A10: =+B10&C10 -> Véhicules neufs[...] | B10: =+$K$1 -> Véhicules neufs | C10: [...] | D10: =+SUM(START:END!D10) -> 0 | E10: =IF(D10=0,0,F10/D10) -> 0 | F10: =+SUM(START:END!F10) -> 0 | G10: =+SUM(START:END!G10) -> 0 | H10: =IF(G10=0,0,I10/G10) -> 0 | I10: =+SUM(START:END!I10) -> 0 | J10: =+SUM(START:END!J10) -> 0 | K10: =IF(J10=0,0,L10/J10) -> 0 | L10: =+SUM(START:END!L10) -> 0 | M10: =J10-G10 -> 0 | N10: =L10-I10 -> 0 | O10: =+SUM(START:END!O10) -> 0 | P10: =IF(O10=0,0,Q10/O10) -> 0 | Q10: =+SUM(START:END!Q10) -> 0 | R10: =J10-O10 -> 0 | S10: =L10-Q10 -> 0
A11: =+B11&C11 -> Véhicules neufs[...] | B11: =+$K$1 -> Véhicules neufs | C11: [...] | D11: =+SUM(START:END!D11) -> 0 | E11: =IF(D11=0,0,F11/D11) -> 0 | F11: =+SUM(START:END!F11) -> 0 | G11: =+SUM(START:END!G11) -> 0 | H11: =IF(G11=0,0,I11/G11) -> 0 | I11: =+SUM(START:END!I11) -> 0 | J11: =+SUM(START:END!J11) -> 0 | K11: =IF(J11=0,0,L11/J11) -> 0 | L11: =+SUM(START:END!L11) -> 0 | M11: =J11-G11 -> 0 | N11: =L11-I11 -> 0 | O11: =+SUM(START:END!O11) -> 0 | P11: =IF(O11=0,0,Q11/O11) -> 0 | Q11: =+SUM(START:END!Q11) -> 0 | R11: =J11-O11 -> 0 | S11: =L11-Q11 -> 0
A12: =+B12&C12 -> Véhicules neufs[...] | B12: =+$K$1 -> Véhicules neufs | C12: [...] | D12: =+SUM(START:END!D12) -> 0 | E12: =IF(D12=0,0,F12/D12) -> 0 | F12: =+SUM(START:END!F12) -> 0 | G12: =+SUM(START:END!G12) -> 0 | H12: =IF(G12=0,0,I12/G12) -> 0 | I12: =+SUM(START:END!I12) -> 0 | J12: =+SUM(START:END!J12) -> 0 | K12: =IF(J12=0,0,L12/J12) -> 0 | L12: =+SUM(START:END!L12) -> 0 | M12: =J12-G12 -> 0 | N12: =L12-I12 -> 0 | O12: =+SUM(START:END!O12) -> 0 | P12: =IF(O12=0,0,Q12/O12) -> 0 | Q12: =+SUM(START:END!Q12) -> 0 | R12: =J12-O12 -> 0 | S12: =L12-Q12 -> 0
A13: =+B13&C13 -> Véhicules neufsTotal Neufs | B13: =+$K$1 -> Véhicules neufs | C13: Total Neufs | D13: =+SUM(D6:D12) -> 1254.5117 | E13: =IF(D13<=0,0,F13/D13) -> 1295.0153 | F13: =+SUM(F6:F12) -> 1624611.8 | G13: =+SUM(G6:G12) -> 1254.5117 | H13: =IF(G13<=0,0,I13/G13) -> 1367.2692 | I13: =+SUM(I6:I12) -> 1715255.2 | J13: =+SUM(J6:J12) -> 1169 | K13: =IF(J13<=0,0,L13/J13) -> 1721.3136 | L13: =+SUM(L6:L12) -> 2012215.6 | M13: =+SUM(M6:M12) -> -85.511681 | N13: =+SUM(N6:N12) -> 296960.36 | O13: =+SUM(O6:O12) -> 1419 | P13: =IF(O13<=0,0,Q13/O13) -> 655.75518 | Q13: =+SUM(Q6:Q12) -> 930516.6 | R13: =+SUM(R6:R12) -> -250 | S13: =+SUM(S6:S12) -> 1081699 | V13: =+SUM(START:END!D13)-D13 -> 0 | W13: =+SUM(START:END!G13)-G13 -> 0 | X13: =+SUM(START:END!J13)-J13 -> 0 | Y13: =+SUM(START:END!O13)-O13 -> 0
A14: =+B14&C14 -> Véhicules neufs | B14: =+$K$1 -> Véhicules neufs | M14: =IF(G13=0,0,M13/G13) -> -0.06816332 | N14: =IF(I13=0,0,N13/I13) -> 0.17312897 | R14: =R13/O13 -> -0.17618041 | S14: =IF(Q13=0,0,(S13/Q13)) -> 1.1624714
A15: =+B15&C15 -> Véhicules neufsEx-Démos et courtoisies | B15: =+$K$1 -> Véhicules neufs | C15: Ex-Démos et courtoisies | D15: =+SUM(START:END!D15) -> 130.60263 | E15: =IF(D15=0,0,F15/D15) -> 697.82622 | F15: =+SUM(START:END!F15) -> 91137.937 | G15: =+SUM(START:END!G15) -> 130.60263 | H15: =IF(G15=0,0,I15/G15) -> 773.74209 | I15: =+SUM(START:END!I15) -> 101052.75 | J15: =+SUM(START:END!J15) -> 148 | K15: =IF(J15=0,0,L15/J15) -> 1170.5766 | L15: =+SUM(START:END!L15) -> 173245.33 | M15: =J15-G15 -> 17.397374 | N15: =L15-I15 -> 72192.582 | O15: =+SUM(START:END!O15) -> 83 | P15: =IF(O15=0,0,Q15/O15) -> 188.66807 | Q15: =+SUM(START:END!Q15) -> 15659.45 | R15: =J15-O15 -> 65 | S15: =L15-Q15 -> 157585.88 | V15: =+SUM(START:END!D15)-D15 -> 0 | W15: =+SUM(START:END!G15)-G15 -> 0 | X15: =+SUM(START:END!J15)-J15 -> 0 | Y15: =+SUM(START:END!O15)-O15 -> 0
A16: =+B16&C16 -> Véhicules neufs | B16: =+$K$1 -> Véhicules neufs
A17: =+B17&C17 -> Véhicules neufsFlottes | B17: =+$K$1 -> Véhicules neufs | C17: Flottes | D17: =+SUM(START:END!D17) -> 32.001635 | E17: =IF(D17=0,0,F17/D17) -> 806.35971 | F17: =+SUM(START:END!F17) -> 25804.829 | G17: =+SUM(START:END!G17) -> 41.315239 | H17: =IF(G17=0,0,I17/G17) -> 804.92606 | I17: =+SUM(START:END!I17) -> 33255.712 | J17: =+SUM(START:END!J17) -> 53 | K17: =IF(J17=0,0,L17/J17) -> 1808.3185 | L17: =+SUM(START:END!L17) -> 95840.88 | M17: =J17-G17 -> 11.684761 | N17: =L17-I17 -> 62585.168 | O17: =+SUM(START:END!O17) -> 22 | P17: =IF(O17=0,0,Q17/O17) -> 1171.9732 | Q17: =+SUM(START:END!Q17) -> 25783.41 | R17: =J17-O17 -> 31 | S17: =L17-Q17 -> 70057.47 | V17: =+SUM(START:END!D17)-D17 -> 0 | W17: =+SUM(START:END!G17)-G17 -> 0 | X17: =+SUM(START:END!J17)-J17 -> 0 | Y17: =+SUM(START:END!O17)-O17 -> 0
A18: =+B18&C18 -> Véhicules neufs | B18: =+$K$1 -> Véhicules neufs
A19: =+B19&C19 -> Véhicules neufsRachat bail | B19: =+$K$1 -> Véhicules neufs | C19: Rachat bail | F19: =+SUM(START:END!F19) -> 105000 | I19: =+SUM(START:END!I19) -> 105000 | L19: =+SUM(START:END!L19) -> 118780.38 | N19: =L19-I19 -> 13780.38 | Q19: =+SUM(START:END!Q19) -> 112194.09 | R19: =O19-K19 -> 0 | S19: =L19-Q19 -> 6586.29
A20: =+B20&C20 -> Véhicules neufs | B20: =+$K$1 -> Véhicules neufs
A21: =+B21&C21 -> Véhicules neufsRev. Finances | B21: =+$K$1 -> Véhicules neufs | C21: Rev. Finances | D21: 0 | E21: =IF(D21=0,0,F21/D21) -> 0 | F21: =+SUM(START:END!F21) -> 130329.13 | G21: 0 | H21: =IF(G21=0,0,I21/G21) -> 0 | I21: =+SUM(START:END!I21) -> 130329.13 | K21: =IF(J13=0,0,L21/(J13+J15)) -> 15.382384 | L21: =+SUM(START:END!L21) -> 20258.6 | N21: =L21-I21 -> -110070.53 | P21: =IF(O13=0,0,Q21/(O13+O15)) -> 103.1598 | Q21: =+SUM(START:END!Q21) -> 154946.02 | R21: =O21-K21 -> -15.382384 | S21: =L21-Q21 -> -134687.42
A22: =+B22&C22 -> Véhicules neufsRev. Protections | B22: =+$K$1 -> Véhicules neufs | C22: Rev. Protections | D22: 0 | E22: =IF(D22=0,0,F22/D22) -> 0 | F22: =+SUM(START:END!F22) -> 1021416.7 | G22: 0 | H22: =IF(G22=0,0,I22/G22) -> 0 | I22: =+SUM(START:END!I22) -> 1021416.7 | K22: =IF(J13=0,0,L22/(J13+J15)) -> 764.06582 | L22: =+SUM(START:END!L22) -> 1006274.7 | N22: =L22-I22 -> -15141.997 | P22: =IF(O13=0,0,Q22/(O13+O15)) -> 517.43455 | Q22: =+SUM(START:END!Q22) -> 777186.7 | R22: =O22-K22 -> -764.06582 | S22: =L22-Q22 -> 229087.98
A23: =+B23&C23 -> Véhicules neufsRev. Autres | B23: =+$K$1 -> Véhicules neufs | C23: Rev. Autres | D23: 0 | E23: =IF(D23=0,0,F23/D23) -> 0 | F23: =+SUM(START:END!F23) -> 25762.735 | G23: 0 | H23: =IF(G23=0,0,I23/G23) -> 0 | I23: =+SUM(START:END!I23) -> 25762.735 | K23: =IF(J13=0,0,L23/(J13+J15)) -> 22.888109 | L23: =+SUM(START:END!L23) -> 30143.64 | N23: =L23-I23 -> 4380.9048 | P23: =IF(O13=0,0,Q23/(O13+O15)) -> 25.935999 | Q23: =+SUM(START:END!Q23) -> 38955.87 | R23: =O23-K23 -> -22.888109 | S23: =L23-Q23 -> -8812.23
A24: =+B24&C24 -> Véhicules neufsTotal F&I | B24: =+$K$1 -> Véhicules neufs | C24: Total F&I | D24: =+D15+D13 -> 1385.1143 | E24: =IF(D24<=0,0,F24/D24) -> 850.11651 | F24: =F21+F22+F23 -> 1177508.5 | G24: =+G15+G13 -> 1385.1143 | H24: =IF(G24<=0,0,I24/G24) -> 850.11651 | I24: =I21+I22+I23 -> 1177508.5 | J24: =+J15+J13 -> 1317 | K24: =IF(J24<=0,0,L24/J24) -> 802.33631 | L24: =L21+L22+L23 -> 1056676.9 | M24: =J24-G24 -> -68.114307 | N24: =L24-I24 -> -120831.62 | O24: =+O15+O13 -> 1502 | P24: =IF(O24<=0,0,Q24/O24) -> 646.53035 | Q24: =Q21+Q22+Q23 -> 971088.59 | S24: =L24-Q24 -> 85588.33 | V24: =+SUM(START:END!D24)-D24 -> 0 | W24: =+SUM(START:END!G24)-G24 -> 0 | X24: =+SUM(START:END!J24)-J24 -> 0 | Y24: =+SUM(START:END!O24)-O24 -> 0
A25: =+B25&C25 -> Véhicules neufs | B25: =+$K$1 -> Véhicules neufs | N25: =IF(N24=0,0,N24/I24) -> -0.10261635 | S25: =IF(Q24=0,0,(S24/Q24)) -> 0.08813648
A26: =+B26&C26 -> Véhicules neufs | B26: =+$K$1 -> Véhicules neufs
A27: =+B27&C27 -> Véhicules neufsTotal Dépt. Neufs | B27: =+$K$1 -> Véhicules neufs | C27: Total Dépt. Neufs | D27: =+D13+D15+D17 -> 1417.1159 | E27: =IF(D27<=0,0,F27/D27) -> 2133.956 | F27: =F13+F17+F24+F19+F15 -> 3024063.1 | G27: =+G13+G15+G17 -> 1426.4295 | H27: =IF(G27<=0,0,I27/G27) -> 2195.7427 | I27: =I13+I17+I24+I19+I15 -> 3132072.2 | J27: =+J13+J15+J17 -> 1370 | K27: =IF(J27<=0,0,L27/J27) -> 2523.1818 | L27: =L13+L17+L24+L19+L15 -> 3456759.1 | M27: =J27-G27 -> -56.429546 | N27: =L27-I27 -> 324686.87 | O27: =+O13+O15+O17 -> 1524 | P27: =IF(O27<=0,0,Q27/O27) -> 1348.5841 | Q27: =Q13+Q17+Q24+Q19+Q15 -> 2055242.1 | R27: =J27-O27 -> -154 | S27: =L27-Q27 -> 1401516.9 | V27: =+SUM(START:END!D27)-D27 -> 0 | W27: =+SUM(START:END!G27)-G27 -> 0 | X27: =+SUM(START:END!J27)-J27 -> 0 | Y27: =+SUM(START:END!O27)-O27 -> 0
A28: =+B28&C28 -> Véhicules neufs | B28: =+$K$1 -> Véhicules neufs | M28: =M27/G27 -> -0.039559995 | N28: =N27/I27 -> 0.10366519 | R28: =R27/O27 -> -0.10104987 | S28: =IF(Q27=0,0,S27/Q27) -> 0.68192302
A29: =+B29&C29 -> Véhicules neufs | B29: =+$K$1 -> Véhicules neufs
A30: =+B30&C30 -> Véhicules neufsDEPENSES | B30: =+$K$1 -> Véhicules neufs | C30: DEPENSES
A31: =+B31&C31 -> Véhicules neufsComm. vendeurs | B31: =+$K$1 -> Véhicules neufs | C31: Comm. vendeurs | E31: =F31/D$24 -> 384.07694 | F31: =+SUM(START:END!F31) -> 531990.46 | H31: =I31/G$24 -> 385.514 | I31: =+SUM(START:END!I31) -> 533980.96 | J31: =L31/L13 -> 0.3973293 | K31: =IF(L31=0,0,L31/J$24) -> 607.07077 | L31: =+SUM(START:END!L31) -> 799512.2 | N31: =L31-I31 -> 265531.24 | P31: =IF(Q31=0,0,Q31/O$24) -> 442.49044 | Q31: =+SUM(START:END!Q31) -> 664620.64 | S31: =L31-Q31 -> 134891.56
A32: =+B32&C32 -> Véhicules neufsComm. F&I | B32: =+$K$1 -> Véhicules neufs | C32: Comm. F&I | E32: =F32/D$24 -> 255.03495 | F32: =+SUM(START:END!F32) -> 353252.56 | H32: =I32/G$24 -> 255.03495 | I32: =+SUM(START:END!I32) -> 353252.56 | J32: =L32/L24 -> 0.30269927 | K32: =IF(L32=0,0,L32/J$24) -> 242.86661 | L32: =+SUM(START:END!L32) -> 319855.33 | N32: =L32-I32 -> -33397.233 | P32: =IF(Q32=0,0,Q32/O$24) -> 241.33196 | Q32: =+SUM(START:END!Q32) -> 362480.61 | S32: =L32-Q32 -> -42625.28
A33: =+B33&C33 -> Véhicules neufsFrais de livraison | B33: =+$K$1 -> Véhicules neufs | C33: Frais de livraison | E33: =F33/D$24 -> 197.027 | F33: =+SUM(START:END!F33) -> 272904.92 | H33: =I33/G$24 -> 197.027 | I33: =+SUM(START:END!I33) -> 272904.92 | K33: =IF(L33=0,0,L33/J$24) -> 153.10699 | L33: =+SUM(START:END!L33) -> 201641.9 | N33: =L33-I33 -> -71263.021 | P33: =IF(Q33=0,0,Q33/O$24) -> 169.48019 | Q33: =+SUM(START:END!Q33) -> 254559.25 | S33: =L33-Q33 -> -52917.35
A34: =+B34&C34 -> Véhicules neufsService gratuit 1 | B34: =+$K$1 -> Véhicules neufs | C34: Service gratuit 1 | E34: =F34/D$24 -> 6.0008224 | F34: =+SUM(START:END!F34) -> 8311.825 | H34: =I34/G$24 -> 6.0008224 | I34: =+SUM(START:END!I34) -> 8311.825 | K34: =IF(L34=0,0,L34/J$24) -> 7.692126 | L34: =+SUM(START:END!L34) -> 10130.53 | N34: =L34-I34 -> 1818.705 | P34: =IF(Q34=0,0,Q34/O$24) -> 4.9610386 | Q34: =+SUM(START:END!Q34) -> 7451.48 | S34: =L34-Q34 -> 2679.05
A35: =+B35&C35 -> Véhicules neufsEntretien stock | B35: =+$K$1 -> Véhicules neufs | C35: Entretien stock | E35: =F35/D$24 -> 34.00466 | F35: =+SUM(START:END!F35) -> 47100.342 | H35: =I35/G$24 -> 34.00466 | I35: =+SUM(START:END!I35) -> 47100.342 | K35: =IF(L35=0,0,L35/J$24) -> 10.459453 | L35: =+SUM(START:END!L35) -> 13775.1 | N35: =L35-I35 -> -33325.242 | P35: =IF(Q35=0,0,Q35/O$24) -> 30.586678 | Q35: =+SUM(START:END!Q35) -> 45941.19 | S35: =L35-Q35 -> -32166.09
A36: =+B36&C36 -> Véhicules neufsPublicité 1 | B36: =+$K$1 -> Véhicules neufs | C36: Publicité 1 | E36: =F36/D$24 -> 180.69441 | F36: =+SUM(START:END!F36) -> 250282.41 | H36: =I36/G$24 -> 180.69441 | I36: =+SUM(START:END!I36) -> 250282.41 | K36: =IF(L36=0,0,L36/J$24) -> 159.76488 | L36: =+SUM(START:END!L36) -> 210410.35 | N36: =L36-I36 -> -39872.059 | P36: =IF(Q36=0,0,Q36/O$24) -> 98.548602 | Q36: =+SUM(START:END!Q36) -> 148020 | S36: =L36-Q36 -> 62390.35
A37: =+B37&C37 -> Véhicules neufsIntérêt de gros | B37: =+$K$1 -> Véhicules neufs | C37: Intérêt de gros | E37: =F37/D$24 -> 222.95901 | F37: =+SUM(START:END!F37) -> 308823.72 | H37: =I37/G$24 -> 223.32884 | I37: =+SUM(START:END!I37) -> 309335.97 | K37: =IF(L37=0,0,L37/J$24) -> 209.86513 | L37: =+SUM(START:END!L37) -> 276392.38 | N37: =L37-I37 -> -32943.594 | P37: =IF(Q37=0,0,Q37/O$24) -> 281.9746 | Q37: =+SUM(START:END!Q37) -> 423525.85 | S37: =L37-Q37 -> -147133.47
A38: =+B38&C38 -> Véhicules neufs[...] | B38: =+$K$1 -> Véhicules neufs | C38: [...] | E38: =F38/D$24 -> 0 | F38: =+SUM(START:END!F38) -> 0 | H38: =I38/G$24 -> 0 | I38: =+SUM(START:END!I38) -> 0 | K38: =IF(L38=0,0,L38/J$24) -> 0 | L38: =+SUM(START:END!L38) -> 0 | N38: =L38-I38 -> 0 | P38: =IF(Q38=0,0,Q38/O$24) -> 0 | Q38: =+SUM(START:END!Q38) -> 0 | S38: =L38-Q38 -> 0
A39: =+B39&C39 -> Véhicules neufs[...] | B39: =+$K$1 -> Véhicules neufs | C39: [...] | E39: =F39/D$24 -> 0 | F39: =+SUM(START:END!F39) -> 0 | H39: =I39/G$24 -> 0 | I39: =+SUM(START:END!I39) -> 0 | K39: =IF(L39=0,0,L39/J$24) -> 0 | L39: =+SUM(START:END!L39) -> 0 | N39: =L39-I39 -> 0 | P39: =IF(Q39=0,0,Q39/O$24) -> 0 | Q39: =+SUM(START:END!Q39) -> 0 | S39: =L39-Q39 -> 0
A40: =+B40&C40 -> Véhicules neufs[...] | B40: =+$K$1 -> Véhicules neufs | C40: [...] | E40: =F40/D$24 -> 0 | F40: =+SUM(START:END!F40) -> 0 | H40: =I40/G$24 -> 0 | I40: =+SUM(START:END!I40) -> 0 | K40: =IF(L40=0,0,L40/J$24) -> 0 | L40: =+SUM(START:END!L40) -> 0 | N40: =L40-I40 -> 0 | P40: =IF(Q40=0,0,Q40/O$24) -> 0 | Q40: =+SUM(START:END!Q40) -> 0 | S40: =L40-Q40 -> 0
A41: =+B41&C41 -> Véhicules neufsTOTAL VARIABLES | B41: =+$K$1 -> Véhicules neufs | C41: TOTAL VARIABLES | D41: % brut | E41: =F41/F$27 -> 0.58618692 | F41: =SUM(F31:F40) -> 1772666.2 | G41: % brut | H41: =I41/I$27 -> 0.56677142 | I41: =SUM(I31:I40) -> 1775169 | J41: % brut | K41: =L41/L$27 -> 0.52989455 | L41: =SUM(L31:L40) -> 1831717.8 | N41: =SUM(N31:N40) -> 56548.792 | O41: % brut | P41: =Q41/Q$27 -> 0.9276761 | Q41: =SUM(Q31:Q40) -> 1906599 | S41: =L41-Q41 -> -74881.23
A42: =+B42&C42 -> Véhicules neufsSalaires cadres | B42: =+$K$1 -> Véhicules neufs | C42: Salaires cadres | F42: =+SUM(START:END!F42) -> 521049.29 | I42: =+SUM(START:END!I42) -> 521049.29 | L42: =+SUM(START:END!L42) -> 432818.61 | N42: =L42-I42 -> -88230.681 | Q42: =+SUM(START:END!Q42) -> 459734.91
A43: =+B43&C43 -> Véhicules neufsSalaires commis | B43: =+$K$1 -> Véhicules neufs | C43: Salaires commis | F43: =+SUM(START:END!F43) -> 206513.65 | I43: =+SUM(START:END!I43) -> 206513.65 | L43: =+SUM(START:END!L43) -> 178323.83 | N43: =L43-I43 -> -28189.821 | Q43: =+SUM(START:END!Q43) -> 190907.96 | S43: =L43-Q43 -> -12584.13
A44: =+B44&C44 -> Véhicules neufsSalaires autres | B44: =+$K$1 -> Véhicules neufs | C44: Salaires autres | F44: =+SUM(START:END!F44) -> 130133.25 | I44: =+SUM(START:END!I44) -> 130133.25 | L44: =+SUM(START:END!L44) -> 169904.26 | N44: =L44-I44 -> 39771.009 | Q44: =+SUM(START:END!Q44) -> 132905.45 | S44: =L44-Q44 -> 36998.81
A45: =+B45&C45 -> Véhicules neufsSalaires spécialistes | B45: =+$K$1 -> Véhicules neufs | C45: Salaires spécialistes | F45: =+SUM(START:END!F45) -> 0 | I45: =+SUM(START:END!I45) -> 0 | L45: =+SUM(START:END!L45) -> 0 | N45: =L45-I45 -> 0 | Q45: =+SUM(START:END!Q45) -> 0 | S45: =L45-Q45 -> 0
A46: =+B46&C46 -> Véhicules neufs[...] | B46: =+$K$1 -> Véhicules neufs | C46: [...] | F46: =+SUM(START:END!F46) -> 0 | I46: =+SUM(START:END!I46) -> 0 | L46: =+SUM(START:END!L46) -> 0 | N46: =L46-I46 -> 0 | Q46: =+SUM(START:END!Q46) -> 0 | S46: =L46-Q46 -> 0
A47: =+B47&C47 -> Véhicules neufs[...] | B47: =+$K$1 -> Véhicules neufs | C47: [...] | F47: =+SUM(START:END!F47) -> 0 | I47: =+SUM(START:END!I47) -> 0 | L47: =+SUM(START:END!L47) -> 0 | N47: =L47-I47 -> 0 | Q47: =+SUM(START:END!Q47) -> 0 | S47: =L47-Q47 -> 0
A48: =+B48&C48 -> Véhicules neufs[...] | B48: =+$K$1 -> Véhicules neufs | C48: [...] | F48: =+SUM(START:END!F48) -> 0 | I48: =+SUM(START:END!I48) -> 0 | L48: =+SUM(START:END!L48) -> 0 | N48: =L48-I48 -> 0 | Q48: =+SUM(START:END!Q48) -> 0 | S48: =L48-Q48 -> 0
A49: =+B49&C49 -> Véhicules neufsSalaires en absences | B49: =+$K$1 -> Véhicules neufs | C49: Salaires en absences | F49: =+SUM(START:END!F49) -> 209152.71 | I49: =+SUM(START:END!I49) -> 209391.57 | L49: =+SUM(START:END!L49) -> 263697.14 | N49: =L49-I49 -> 54305.574 | Q49: =+SUM(START:END!Q49) -> 284200.01 | S49: =L49-Q49 -> -20502.87
A50: =+B50&C50 -> Véhicules neufsDéduction à la source | B50: =+$K$1 -> Véhicules neufs | C50: Déduction à la source | F50: =+SUM(START:END!F50) -> 209152.71 | I50: =+SUM(START:END!I50) -> 209391.57 | L50: =+SUM(START:END!L50) -> 221409.24 | N50: =L50-I50 -> 12017.674 | Q50: =+SUM(START:END!Q50) -> 249936.6 | S50: =L50-Q50 -> -28527.36
A51: =+B51&C51 -> Véhicules neufsBénéfices marginaux | B51: =+$K$1 -> Véhicules neufs | C51: Bénéfices marginaux | F51: =+SUM(START:END!F51) -> 149892.77 | I51: =+SUM(START:END!I51) -> 150063.96 | L51: =+SUM(START:END!L51) -> 158676.59 | N51: =L51-I51 -> 8612.6341 | Q51: =+SUM(START:END!Q51) -> 169253.87 | S51: =L51-Q51 -> -10577.28
A52: =+B52&C52 -> Véhicules neufsCsst | B52: =+$K$1 -> Véhicules neufs | C52: Csst | F52: =+SUM(START:END!F52) -> 34858.784 | I52: =+SUM(START:END!I52) -> 34898.594 | L52: =+SUM(START:END!L52) -> 63901.56 | N52: =L52-I52 -> 29002.966 | Q52: =+SUM(START:END!Q52) -> 61459.11 | S52: =L52-Q52 -> 2442.45
A53: =+B53&C53 -> Véhicules neufs[...] | B53: =+$K$1 -> Véhicules neufs | C53: [...] | F53: =+SUM(START:END!F53) -> 0 | I53: =+SUM(START:END!I53) -> 0 | L53: =+SUM(START:END!L53) -> 0 | N53: =L53-I53 -> 0 | Q53: =+SUM(START:END!Q53) -> 0 | S53: =L53-Q53 -> 0
A54: =+B54&C54 -> Véhicules neufsTOTAL PERSONNEL | B54: =+$K$1 -> Véhicules neufs | C54: TOTAL PERSONNEL | D54: % brut | E54: =F54/F$27 -> 0.48304322 | F54: =+SUM(F42:F53) -> 1460753.2 | G54: % brut | H54: =I54/I$27 -> 0.46660542 | I54: =+SUM(I42:I53) -> 1461441.9 | J54: % brut | K54: =L54/L$27 -> 0.43067255 | L54: =+SUM(L42:L53) -> 1488731.2 | N54: =+SUM(N42:N53) -> 27289.354 | O54: % brut | P54: =Q54/Q$27 -> 0.75338953 | Q54: =+SUM(Q42:Q53) -> 1548397.9 | S54: =+SUM(S42:S53) -> -32750.38
A55: =+B55&C55 -> Véhicules neufsPublicité 2 | B55: =+$K$1 -> Véhicules neufs | C55: Publicité 2 | F55: =+SUM(START:END!F55) -> 0 | I55: =+SUM(START:END!I55) -> 0 | L55: =+SUM(START:END!L55) -> 0 | N55: =L55-I55 -> 0 | Q55: =+SUM(START:END!Q55) -> 0 | S55: =L55-Q55 -> 0
A56: =+B56&C56 -> Véhicules neufsService gratuit 2 | B56: =+$K$1 -> Véhicules neufs | C56: Service gratuit 2 | F56: =+SUM(START:END!F56) -> 0 | I56: =+SUM(START:END!I56) -> 0 | L56: =+SUM(START:END!L56) -> 0 | N56: =L56-I56 -> 0 | Q56: =+SUM(START:END!Q56) -> 0 | S56: =L56-Q56 -> 0
A57: =+B57&C57 -> Véhicules neufsFrais véhicules de cie | B57: =+$K$1 -> Véhicules neufs | C57: Frais véhicules de cie | F57: =+SUM(START:END!F57) -> 190866.43 | I57: =+SUM(START:END!I57) -> 190866.43 | L57: =+SUM(START:END!L57) -> 128131.06 | N57: =L57-I57 -> -62735.368 | Q57: =+SUM(START:END!Q57) -> 298443.74 | S57: =L57-Q57 -> -170312.68
A58: =+B58&C58 -> Véhicules neufsInformatique | B58: =+$K$1 -> Véhicules neufs | C58: Informatique | F58: =+SUM(START:END!F58) -> 140225.32 | I58: =+SUM(START:END!I58) -> 140225.32 | L58: =+SUM(START:END!L58) -> 117673.67 | N58: =L58-I58 -> -22551.652 | Q58: =+SUM(START:END!Q58) -> 143559.66 | S58: =L58-Q58 -> -25885.99
A59: =+B59&C59 -> Véhicules neufsFrais de déplacement | B59: =+$K$1 -> Véhicules neufs | C59: Frais de déplacement | F59: =+SUM(START:END!F59) -> 33526.433 | I59: =+SUM(START:END!I59) -> 33526.433 | L59: =+SUM(START:END!L59) -> 10808.77 | N59: =L59-I59 -> -22717.663 | Q59: =+SUM(START:END!Q59) -> 40837.44 | S59: =L59-Q59 -> -30028.67
A60: =+B60&C60 -> Véhicules neufsServices extérieurs | B60: =+$K$1 -> Véhicules neufs | C60: Services extérieurs | F60: =+SUM(START:END!F60) -> 200295.79 | I60: =+SUM(START:END!I60) -> 200295.79 | L60: =+SUM(START:END!L60) -> 151846.1 | N60: =L60-I60 -> -48449.688 | Q60: =+SUM(START:END!Q60) -> 144587.36 | S60: =L60-Q60 -> 7258.74
A61: =+B61&C61 -> Véhicules neufsFournitures autres | B61: =+$K$1 -> Véhicules neufs | C61: Fournitures autres | F61: =+SUM(START:END!F61) -> 5541.2167 | I61: =+SUM(START:END!I61) -> 5541.2167 | L61: =+SUM(START:END!L61) -> 1690.02 | N61: =L61-I61 -> -3851.1967 | Q61: =+SUM(START:END!Q61) -> 5268 | S61: =L61-Q61 -> -3577.98
A62: =+B62&C62 -> Véhicules neufsUniformes | B62: =+$K$1 -> Véhicules neufs | C62: Uniformes | F62: =+SUM(START:END!F62) -> 735 | I62: =+SUM(START:END!I62) -> 735 | L62: =+SUM(START:END!L62) -> 0 | N62: =L62-I62 -> -735 | Q62: =+SUM(START:END!Q62) -> 735 | S62: =L62-Q62 -> -735
A63: =+B63&C63 -> Véhicules neufsPapeterie | B63: =+$K$1 -> Véhicules neufs | C63: Papeterie | F63: =+SUM(START:END!F63) -> 14649.6 | I63: =+SUM(START:END!I63) -> 14649.6 | L63: =+SUM(START:END!L63) -> 11802.71 | N63: =L63-I63 -> -2846.89 | Q63: =+SUM(START:END!Q63) -> 12432 | S63: =L63-Q63 -> -629.29
A64: =+B64&C64 -> Véhicules neufsTéléphone | B64: =+$K$1 -> Véhicules neufs | C64: Téléphone | F64: =+SUM(START:END!F64) -> 12388.152 | I64: =+SUM(START:END!I64) -> 12388.152 | L64: =+SUM(START:END!L64) -> 5970.01 | N64: =L64-I64 -> -6418.142 | Q64: =+SUM(START:END!Q64) -> 11443.87 | S64: =L64-Q64 -> -5473.86
A65: =+B65&C65 -> Véhicules neufsFrais postaux | B65: =+$K$1 -> Véhicules neufs | C65: Frais postaux | F65: =+SUM(START:END!F65) -> 5812.8 | I65: =+SUM(START:END!I65) -> 5812.8 | L65: =+SUM(START:END!L65) -> 3034.57 | N65: =L65-I65 -> -2778.23 | Q65: =+SUM(START:END!Q65) -> 2748.39 | S65: =L65-Q65 -> 286.18
A66: =+B66&C66 -> Véhicules neufsDivers | B66: =+$K$1 -> Véhicules neufs | C66: Divers | F66: =+SUM(START:END!F66) -> 28331.52 | I66: =+SUM(START:END!I66) -> 28331.52 | L66: =+SUM(START:END!L66) -> 18515.96 | N66: =L66-I66 -> -9815.56 | Q66: =+SUM(START:END!Q66) -> 35946.32 | S66: =L66-Q66 -> -17430.36
... A71: =+B71&C71 -> Véhicules neufs[...] | B71: =+$K$1 -> Véhicules neufs | C71: [...] | F71: =+SUM(START:END!F71) -> 0 | I71: =+SUM(START:END!I71) -> 0 | L71: =+SUM(START:END!L71) -> 0 | N71: =L71-I71 -> 0 | Q71: =+SUM(START:END!Q71) -> 0 | S71: =L71-Q71 -> 0
A72: =+B72&C72 -> Véhicules neufsTOTAL SEMI-FIXES | B72: =+$K$1 -> Véhicules neufs | C72: TOTAL SEMI-FIXES | D72: % brut | E72: =F72/F$27 -> 0.23739392 | F72: =+SUM(F55:F71) -> 717894.17 | G72: % brut | H72: =I72/I$27 -> 0.22920742 | I72: =+SUM(I55:I71) -> 717894.17 | J72: % brut | K72: =L72/L$27 -> 0.15325794 | L72: =+SUM(L55:L71) -> 529775.77 | N72: =+SUM(N55:N71) -> -188118.41 | O72: % brut | P72: =Q72/Q$27 -> 0.42053281 | Q72: =+SUM(Q55:Q71) -> 864296.74 | S72: =+SUM(S55:S71) -> -334520.97
A73: =+B73&C73 -> Véhicules neufs | B73: =+$K$1 -> Véhicules neufs
A74: =+B74&C74 -> Véhicules neufsTOTAL DES DÉPENSES | B74: =+$K$1 -> Véhicules neufs | C74: TOTAL DES DÉPENSES | D74: % brut | E74: =F74/F$27 -> 1.3066241 | F74: =F41+F54+F72 -> 3951313.6 | G74: % brut | H74: =I74/I$27 -> 1.2625843 | I74: =I41+I54+I72 -> 3954505 | J74: % brut | K74: =L74/L$27 -> 1.113825 | L74: =L41+L54+L72 -> 3850224.8 | N74: =L74-I74 -> -104280.26 | O74: % brut | P74: =Q74/Q$27 -> 2.1015984 | Q74: =Q41+Q54+Q72 -> 4319293.7 | S74: =L74-Q74 -> -469068.88
A75: =+B75&C75 -> Véhicules neufsProgramme neuf 1 | B75: =+$K$1 -> Véhicules neufs | C75: Programme neuf 1 | F75: =+SUM(START:END!F75) -> 302408.96 | I75: =+SUM(START:END!I75) -> 157594 | L75: =+SUM(START:END!L75) -> 270329.56 | N75: =L75-I75 -> 112735.56 | Q75: =+SUM(START:END!Q75) -> 495208.78
A76: =+B76&C76 -> Véhicules neufsProgramme neuf 2 | B76: =+$K$1 -> Véhicules neufs | C76: Programme neuf 2 | F76: =+SUM(START:END!F76) -> 0 | I76: =+SUM(START:END!I76) -> 0 | L76: =+SUM(START:END!L76) -> 0 | N76: =L76-I76 -> 0 | Q76: =+SUM(START:END!Q76) -> 0 | S76: =L76-Q76 -> 0
A77: =+B77&C77 -> Véhicules neufsProgramme neuf 3 | B77: =+$K$1 -> Véhicules neufs | C77: Programme neuf 3 | F77: =+SUM(START:END!F77) -> 0 | I77: =+SUM(START:END!I77) -> 0 | L77: =+SUM(START:END!L77) -> 0 | N77: =L77-I77 -> 0 | Q77: =+SUM(START:END!Q77) -> 0 | S77: =L77-Q77 -> 0
A78: =+B78&C78 -> Véhicules neufsHoldbacks | B78: =+$K$1 -> Véhicules neufs | C78: Holdbacks | F78: =+SUM(START:END!F78) -> 1259420 | I78: =+SUM(START:END!I78) -> 1263562.2 | L78: =+SUM(START:END!L78) -> 1499227.1 | N78: =L78-I78 -> 235664.95 | Q78: =+SUM(START:END!Q78) -> 1850936 | S78: =L78-Q78 -> -351708.9
A79: =+B79&C79 -> Véhicules neufs[...] | B79: =+$K$1 -> Véhicules neufs | C79: [...] | F79: =+SUM(START:END!F79) -> 0 | I79: =+SUM(START:END!I79) -> 0 | L79: =+SUM(START:END!L79) -> 0 | N79: =L79-I79 -> 0 | Q79: =+SUM(START:END!Q79) -> 0 | S79: =L79-Q79 -> 0
A80: =+B80&C80 -> Véhicules neufs[...] | B80: =+$K$1 -> Véhicules neufs | C80: [...] | F80: =+SUM(START:END!F80) -> 0 | I80: =+SUM(START:END!I80) -> 0 | L80: =+SUM(START:END!L80) -> 0 | N80: =L80-I80 -> 0 | Q80: =+SUM(START:END!Q80) -> 0 | S80: =L80-Q80 -> 0
A81: =+B81&C81 -> Véhicules neufs[...] | B81: =+$K$1 -> Véhicules neufs | C81: [...] | F81: =+SUM(START:END!F81) -> 0 | I81: =+SUM(START:END!I81) -> 0 | L81: =+SUM(START:END!L81) -> 0 | N81: =L81-I81 -> 0 | Q81: =+SUM(START:END!Q81) -> 0 | S81: =L81-Q81 -> 0
A82: =+B82&C82 -> Véhicules neufsFrais administration | B82: =+$K$1 -> Véhicules neufs | C82: Frais administration | F82: =+SUM(START:END!F82) -> 435124.04 | I82: =+SUM(START:END!I82) -> 435124.04 | L82: =+SUM(START:END!L82) -> 378570.09 | N82: =L82-I82 -> -56553.949 | Q82: =+SUM(START:END!Q82) -> 352075.75 | S82: =L82-Q82 -> 26494.34
A83: =+B83&C83 -> Véhicules neufsAUTRES REVENUS | B83: =+$K$1 -> Véhicules neufs | C83: AUTRES REVENUS | F83: =+SUM(F75:F82) -> 1996953 | I83: =+SUM(I75:I82) -> 1856280.2 | L83: =+SUM(L75:L82) -> 2148126.8 | N83: =+SUM(N75:N82) -> 291846.57 | Q83: =+SUM(Q75:Q82) -> 2698220.6 | S83: =+SUM(S75:S82) -> -325214.56
A84: =+B84&C84 -> Véhicules neufs | B84: =+$K$1 -> Véhicules neufs
A85: =+B85&C85 -> Véhicules neufsPROFIT DÉPARTEMENTAL | B85: =+$K$1 -> Véhicules neufs | C85: PROFIT DÉPARTEMENTAL | F85: =F27-F74+F83 -> 1069702.5 | I85: =I27-I74+I83 -> 1033847.4 | L85: =L27-L74+L83 -> 1754661.1 | N85: =N27-N41-N54-N72+N83 -> 720813.7 | Q85: =Q27-Q74+Q83 -> 434169.05 | S85: =S27-S41-S54-S72+S83 -> 1518455
C89: =C1 -> Conso | K89: Véhicules usagés | S89: =$S$1 -> 0
D91: BUDGET ORIGINAL | G91: BUDGET RÉVISÉ | J91: RÉALISATION | M91: ÉCART réel / révisé | O91: ANNÉE PRÉCÉDENTE | R91: ÉCART réel / original
D92: UNITE | E92: $P/UNITÉ | F92: $PROFITS | G92: UNITE | H92: $P/UNITÉ | I92: $PROFITS | J92: UNITE | K92: $P/UNITE | L92: $PROFITS | M92: UNITÉ | N92: $PROFITS | O92: UNITE | P92: $P/UNITE | Q92: $PROFITS | R92: UNITE | S92: $PROFITS
A93: =+B93&C93 -> Véhicules usagésVentes nettes | B93: Véhicules usagés | C93: Ventes nettes | F93: =+SUM(START:END!F93) -> 20194763 | I93: =+SUM(START:END!I93) -> 20194763 | L93: =+SUM(START:END!L93) -> 26881497 | Q93: =+SUM(START:END!Q93) -> 18438206
A94: =+B94&C94 -> Véhicules usagésCertifié | B94: Véhicules usagés | C94: Certifié | D94: =+SUM(START:END!D94) -> 606.09515 | E94: =IF(D94=0,0,F94/D94) -> 750 | F94: =+SUM(START:END!F94) -> 454571.36 | G94: =+SUM(START:END!G94) -> 606.09515 | H94: =IF(G94=0,0,I94/G94) -> 750 | I94: =+SUM(START:END!I94) -> 454571.36 | J94: =+SUM(START:END!J94) -> 716 | K94: =IF(J94=0,0,L94/J94) -> 1069.4676 | L94: =+SUM(START:END!L94) -> 765738.81 | M94: =J94-G94 -> 109.90485 | N94: =L94-I94 -> 311167.45 | O94: =+SUM(START:END!O94) -> 159 | P94: =IF(O94=0,0,Q94/O94) -> 630.83013 | Q94: =+SUM(START:END!Q94) -> 100301.99 | R94: =J94-O94 -> 557 | S94: =L94-Q94 -> 665436.82
A95: =+B95&C95 -> Véhicules usagésNon Certifié | B95: Véhicules usagés | C95: Non Certifié | D95: =+SUM(START:END!D95) -> 34.568165 | E95: =IF(D95=0,0,F95/D95) -> 750 | F95: =+SUM(START:END!F95) -> 25926.123 | G95: =+SUM(START:END!G95) -> 34.568165 | H95: =IF(G95=0,0,I95/G95) -> 750 | I95: =+SUM(START:END!I95) -> 25926.123 | J95: =+SUM(START:END!J95) -> 17 | K95: =IF(J95=0,0,L95/J95) -> 313.41824 | L95: =+SUM(START:END!L95) -> 5328.11 | O95: =+SUM(START:END!O95) -> 537 | P95: =IF(O95=0,0,Q95/O95) -> 482.89918 | Q95: =+SUM(START:END!Q95) -> 259316.86 | R95: =J95-O95 -> -520 | S95: =L95-Q95 -> -253988.75
A96: =+B96&C96 -> Véhicules usagésTotal Usagés | B96: Véhicules usagés | C96: Total Usagés | D96: =+D95+D94 -> 640.66332 | E96: =IF(D96=0,0,F96/D96) -> 750 | F96: =+F94+F95 -> 480497.49 | G96: =+G95+G94 -> 640.66332 | H96: =IF(G96=0,0,I96/G96) -> 750 | I96: =+I94+I95 -> 480497.49 | J96: =+J94+J95 -> 733 | K96: =IF(J96<=0,0,L96/J96) -> 1051.933 | L96: =+L94+L95 -> 771066.92 | M96: =J96-G96 -> 92.336683 | N96: =L96-I96 -> 290569.43 | O96: =+O94+O95 -> 696 | P96: =IF(O96<=0,0,Q96/O96) -> 516.69375 | Q96: =+Q94+Q95 -> 359618.85 | R96: =R94+R95 -> 37 | S96: =S94+S95 -> 411448.07 | V96: =+SUM(START:END!D96)-D96 -> 0 | W96: =+SUM(START:END!G96)-G96 -> 0 | X96: =+SUM(START:END!J96)-J96 -> 0 | Y96: =+SUM(START:END!O96)-O96 -> 0
A97: =+B97&C97 -> Véhicules usagés | B97: Véhicules usagés | E97: =IF(D97=0,0,F97/D97) -> 0 | H97: =IF(G97=0,0,I97/G97) -> 0 | M97: =M96/G96 -> 0.14412669 | N97: =N96/I96 -> 0.60472623 | R97: =R96/O96 -> 0.05316092 | S97: =IF(Q96=0,0,(S96/Q96)) -> 1.1441226
A98: =+B98&C98 -> Véhicules usagésUS | B98: Véhicules usagés | C98: US | D98: =+SUM(START:END!D98) -> 0 | E98: =IF(D98=0,0,F98/D98) -> 0 | F98: =+SUM(START:END!F98) -> 0 | G98: =+SUM(START:END!G98) -> 0 | H98: =IF(G98=0,0,I98/G98) -> 0 | I98: =+SUM(START:END!I98) -> 0 | J98: =+SUM(START:END!J98) -> 0 | K98: =IF(J98=0,0,L98/J98) -> 0 | L98: =+SUM(START:END!L98) -> 0 | M98: =J98-G98 -> 0 | N98: =L98-I98 -> 0 | O98: =+SUM(START:END!O98) -> 0 | P98: =IF(O98=0,0,Q98/O98) -> 0 | Q98: =+SUM(START:END!Q98) -> 0 | V98: =+SUM(START:END!D98)-D98 -> 0 | W98: =+SUM(START:END!G98)-G98 -> 0 | X98: =+SUM(START:END!J98)-J98 -> 0 | Y98: =+SUM(START:END!O98)-O98 -> 0
A99: =+B99&C99 -> Véhicules usagésVentes au Gros | B99: Véhicules usagés | C99: Ventes au Gros | D99: =+SUM(START:END!D99) -> 542.87786 | E99: =IF(D99=0,0,F99/D99) -> 120 | F99: =+SUM(START:END!F99) -> 65145.344 | G99: =+SUM(START:END!G99) -> 542.87786 | H99: =IF(G99=0,0,I99/G99) -> 120 | I99: =+SUM(START:END!I99) -> 65145.344 | J99: =+SUM(START:END!J99) -> 772 | K99: =IF(J99=0,0,L99/J99) -> 235.30141 | L99: =+SUM(START:END!L99) -> 181652.69 | M99: =J99-G99 -> 229.12214 | N99: =L99-I99 -> 116507.35 | O99: =+SUM(START:END!O99) -> 529 | P99: =IF(O99=0,0,Q99/O99) -> 206.49854 | Q99: =+SUM(START:END!Q99) -> 109237.73 | R99: =J99-O99 -> 243 | S99: =L99-Q99 -> 72414.96 | V99: =+SUM(START:END!D99)-D99 -> 0 | W99: =+SUM(START:END!G99)-G99 -> 0 | X99: =+SUM(START:END!J99)-J99 -> 0 | Y99: =+SUM(START:END!O99)-O99 -> 0
A100: =+B100&C100 -> Véhicules usagés | B100: Véhicules usagés
A101: =+B101&C101 -> Véhicules usagésRev. Finances | B101: Véhicules usagés | C101: Rev. Finances | D101: 0 | E101: =IF(D101=0,0,F101/D101) -> 0 | F101: =+SUM(START:END!F101) -> 515153.25 | G101: 0 | H101: =IF(G101=0,0,I101/G101) -> 0 | I101: =+SUM(START:END!I101) -> 515153.25 | K101: =IF(J96=0,0,L101/J96) -> 694.99966 | L101: =+SUM(START:END!L101) -> 509434.75 | N101: =L101-I101 -> -5718.5018 | P101: =IF(O96=0,0,Q101/O96) -> 515.0669 | Q101: =+SUM(START:END!Q101) -> 358486.56 | R101: =O101-K101 -> -694.99966 | S101: =L101-Q101 -> 150948.19
A102: =+B102&C102 -> Véhicules usagésRev. Protections | B102: Véhicules usagés | C102: Rev. Protections | D102: 0 | E102: =IF(D102=0,0,F102/D102) -> 0 | F102: =+SUM(START:END!F102) -> 583840.35 | G102: 0 | H102: =IF(G102=0,0,I102/G102) -> 0 | I102: =+SUM(START:END!I102) -> 583840.35 | K102: =IF(J96=0,0,L102/J96) -> 1151.5582 | L102: =+SUM(START:END!L102) -> 844092.19 | N102: =L102-I102 -> 260251.84 | P102: =IF(O96=0,0,Q102/O96) -> 661.42675 | Q102: =+SUM(START:END!Q102) -> 460353.02 | R102: =O102-K102 -> -1151.5582 | S102: =L102-Q102 -> 383739.17
A103: =+B103&C103 -> Véhicules usagésRev. Autres | B103: Véhicules usagés | C103: Rev. Autres | D103: 0 | E103: =IF(D103=0,0,F103/D103) -> 0 | F103: =+SUM(START:END!F103) -> 0 | G103: 0 | H103: =IF(G103=0,0,I103/G103) -> 0 | I103: =+SUM(START:END!I103) -> 0 | K103: =IF(J96=0,0,L103/J96) -> 51.0594 | L103: =+SUM(START:END!L103) -> 37426.54 | N103: =L103-I103 -> 37426.54 | P103: =IF(O96=0,0,Q103/O96) -> 46.183089 | Q103: =+SUM(START:END!Q103) -> 32143.43 | R103: =O103-K103 -> -51.0594 | S103: =L103-Q103 -> 5283.11
A104: =+B104&C104 -> Véhicules usagésTotal F&I | B104: Véhicules usagés | C104: Total F&I | D104: =D96 -> 640.66332 | E104: =IF(D104=0,0,F104/D104) -> 1715.3996 | F104: =F101+F102+F103 -> 1098993.6 | G104: =G96 -> 640.66332 | H104: =IF(G104=0,0,I104/G104) -> 1715.3996 | I104: =I101+I102+I103 -> 1098993.6 | J104: =J96 -> 733 | K104: =IF(J104<=0,0,L104/J104) -> 1897.6173 | L104: =L101+L102+L103 -> 1390953.5 | M104: =J104-G104 -> 92.336683 | N104: =L104-I104 -> 291959.88 | O104: =O96 -> 696 | P104: =IF(O104<=0,0,Q104/O104) -> 1222.6767 | Q104: =Q101+Q102+Q103 -> 850983.01 | S104: =L104-Q104 -> 539970.47 | V104: =+SUM(START:END!D104)-D104 -> 0 | W104: =+SUM(START:END!G104)-G104 -> 0 | X104: =+SUM(START:END!J104)-J104 -> 0 | Y104: =+SUM(START:END!O104)-O104 -> 0
A105: =+B105&C105 -> Véhicules usagés | B105: Véhicules usagés | N105: =N104/I104 -> 0.26566112 | S105: =IF(Q104=0,0,(S104/Q104)) -> 0.63452556
A106: =+B106&C106 -> Véhicules usagés | B106: Véhicules usagés
A107: =+B107&C107 -> Véhicules usagésTotal Dépt. Usagés | B107: Véhicules usagés | C107: Total Dépt. Usagés | D107: =D96+D99 -> 1183.5412 | E107: =IF(D107<=0,0,F107/D107) -> 1389.5895 | F107: =F96+F104+F99 -> 1644636.4 | G107: =G96+G99 -> 1183.5412 | H107: =IF(G107<=0,0,I107/G107) -> 1389.5895 | I107: =I96+I104+I99 -> 1644636.4 | J107: =J96+J99+J98 -> 1505 | K107: =IF(J107<=0,0,L107/J107) -> 1557.2579 | L107: =L96+L104+L99+L98 -> 2343673.1 | M107: =J107-G107 -> 321.45882 | N107: =L107-I107 -> 699036.65 | O107: =O96+O99+O98 -> 1225 | P107: =IF(O107<=0,0,Q107/O107) -> 1077.4201 | Q107: =Q96+Q104+Q99+Q98 -> 1319839.6 | R107: =J107-O107 -> 280 | S107: =L107-Q107 -> 1023833.5 | V107: =+SUM(START:END!D107)-D107 -> 0 | W107: =+SUM(START:END!G107)-G107 -> 0 | X107: =+SUM(START:END!J107)-J107 -> 0 | Y107: =+SUM(START:END!O107)-O107 -> 0
A108: =+B108&C108 -> Véhicules usagés | B108: Véhicules usagés | M108: =M107/G107 -> 0.27160763 | N108: =N107/I107 -> 0.42504023 | R108: =O107/R107 -> 4.375 | S108: =IF(Q107=0,0,(S107/Q107)) -> 0.77572571
...

Sheet START

Sheet 1
C1: Volks | K1: Véhicules neufs | S1: Réalisé, Janvier 2021
D2: X | E2: O | F2: U | G2: X | H2: O | I2: U | J2: NB | L2: $ | O2: NB | Q2: $
D3: BUDGET ORIGINAL | G3: BUDGET REVISE | J3: RÉALISATION | M3: ÉCART réel / révisé | O3: ANNÉE PRÉCÉDENTE | R3: ÉCART réel / original | V3: NEUF | W3: 0.45
D4: UNITE | E4: $P/UNITÉ | F4: $PROFITS | G4: UNITE | H4: $P/UNITÉ | I4: $PROFITS | J4: UNITE | K4: $P/UNITE | L4: $PROFITS | M4: UNITÉ | N4: $PROFITS | O4: UNITE | P4: $P/UNITE | Q4: $PROFITS | R4: UNITE | S4: $PROFITS | V4: USAGE | W4: 0.1
A5: Véhicules neufsVentes nettes | B5: Véhicules neufs | C5: Ventes nettes | F5: 1882577.9 | I5: 1882577.9 | L5: 1000810 | Q5: 2192034.2 | V5: SERVICE | W5: 0.225
A6: Véhicules neufsAutos détail | B6: Véhicules neufs | C6: Autos détail | D6: 23.607096 | E6: 604.29043 | F6: 14265.542 | G6: 23.607096 | H6: 604.29043 | I6: 14265.542 | J6: 7 | K6: 590.46 | L6: 4133.22 | M6: -16.607096 | N6: -10132.322 | O6: 43 | P6: 741.05116 | Q6: 31865.2 | R6: -36 | S6: -27731.98 | V6: CARROSSERIE | W6: 0.025
A7: Véhicules neufsCamions détail | B7: Véhicules neufs | C7: Camions détail | D7: 31.709861 | E7: 1315.4791 | F7: 41713.66 | G7: 31.709861 | H7: 1315.4791 | I7: 41713.66 | J7: 13 | K7: 1549.7277 | L7: 20146.46 | M7: -18.709861 | N7: -21567.2 | O7: 23 | P7: 639.19261 | Q7: 14701.43 | R7: -10 | S7: 5445.03 | V7: PIECES | W7: 0.2
A8: Véhicules neufsSprinter | B8: Véhicules neufs | C8: Sprinter | D8: 0 | E8: 0 | F8: 0 | G8: 0 | H8: 0 | I8: 0 | J8: 0 | K8: 0 | L8: 0 | M8: 0 | N8: 0 | O8: 0 | P8: 0 | Q8: 0 | R8: 0 | S8: 0 | W8: 1
A9: Véhicules neufsMoto détail | B9: Véhicules neufs | C9: Moto détail | D9: 0 | E9: 0 | F9: 0 | G9: 0 | H9: 0 | I9: 0 | J9: 0 | K9: 0 | L9: 0 | M9: 0 | N9: 0 | O9: 0 | P9: 0 | Q9: 0 | R9: 0 | S9: 0
A10: Véhicules neufs[...] | B10: Véhicules neufs | C10: [...] | D10: 0 | E10: 0 | F10: 0 | G10: 0 | H10: 0 | I10: 0 | J10: 0 | K10: 0 | L10: 0 | M10: 0 | N10: 0 | O10: 0 | P10: 0 | Q10: 0 | R10: 0 | S10: 0
A11: Véhicules neufs[...] | B11: Véhicules neufs | C11: [...] | D11: 0 | E11: 0 | F11: 0 | G11: 0 | H11: 0 | I11: 0 | J11: 0 | K11: 0 | L11: 0 | M11: 0 | N11: 0 | O11: 0 | P11: 0 | Q11: 0 | R11: 0 | S11: 0
A12: Véhicules neufs[...] | B12: Véhicules neufs | C12: [...] | D12: 0 | E12: 0 | F12: 0 | G12: 0 | H12: 0 | I12: 0 | J12: 0 | K12: 0 | L12: 0 | M12: 0 | N12: 0 | O12: 0 | P12: 0 | Q12: 0 | R12: 0 | S12: 0
A13: Véhicules neufsTotal Neufs | B13: Véhicules neufs | C13: Total Neufs | D13: 55.316957 | E13: 1011.9718 | F13: 55979.202 | G13: 55.316957 | H13: 1011.9718 | I13: 55979.202 | J13: 20 | K13: 1213.984 | L13: 24279.68 | M13: -35.316957 | N13: -31699.522 | O13: 66 | P13: 705.555 | Q13: 46566.63 | R13: -46 | S13: -22286.95
A14: Véhicules neufs | B14: Véhicules neufs | M14: -0.63844721 | N14: -0.5662732 | R14: -0.6969697 | S14: -0.47860345
A15: Véhicules neufsEx-Démos et courtoisies | B15: Véhicules neufs | C15: Ex-Démos et courtoisies | D15: 5.7654293 | E15: 400 | F15: 2306.1717 | G15: 5.7654293 | H15: 400 | I15: 2306.1717 | J15: 4 | K15: 1253.6675 | L15: 5014.67 | M15: -1.7654293 | N15: 2708.4983 | O15: 0 | P15: 0 | Q15: 0 | R15: 4 | S15: 5014.67
A16: Véhicules neufs | B16: Véhicules neufs
A17: Véhicules neufsFlottes | B17: Véhicules neufs | C17: Flottes | D17: 0 | E17: 0 | F17: 0 | G17: 0 | H17: 0 | I17: 0 | J17: 0 | K17: 0 | L17: 0 | M17: 0 | N17: 0 | O17: 0 | P17: 0 | Q17: 0 | R17: 0 | S17: 0
A18: Véhicules neufs | B18: Véhicules neufs
A19: Véhicules neufsRachat bail | B19: Véhicules neufs | C19: Rachat bail | D19: 0 | E19: 0 | F19: 5000 | G19: 0 | H19: 0 | I19: 5000 | L19: 898.55 | N19: -4101.45 | Q19: 3889.15 | R19: 0 | S19: -2990.6
A20: Véhicules neufs | B20: Véhicules neufs
A21: Véhicules neufsRev. Finances | B21: Véhicules neufs | C21: Rev. Finances | D21: 0 | E21: 0 | F21: 5746.6183 | G21: 0 | H21: 0 | I21: 5746.6183 | K21: 0 | L21: 0 | N21: -5746.6183 | P21: 159.33621 | Q21: 10516.19 | R21: 0 | S21: -10516.19
A22: Véhicules neufsRev. Protections | B22: Véhicules neufs | C22: Rev. Protections | D22: 0 | E22: 0 | F22: 45037.45 | G22: 0 | H22: 0 | I22: 45037.45 | K22: 677.14833 | L22: 16251.56 | N22: -28785.89 | P22: 468.00955 | Q22: 30888.63 | R22: -677.14833 | S22: -14637.07
A23: Véhicules neufsRev. Autres | B23: Véhicules neufs | C23: Rev. Autres | D23: 0 | E23: 0 | F23: 1135.9594 | G23: 0 | H23: 0 | I23: 1135.9594 | K23: 14.2025 | L23: 340.86 | N23: -795.09943 | P23: 68.940152 | Q23: 4550.05 | R23: -14.2025 | S23: -4209.19
A24: Véhicules neufsTotal F&I | B24: Véhicules neufs | C24: Total F&I | D24: 61.082386 | E24: 850 | F24: 51920.028 | G24: 61.082386 | H24: 850 | I24: 51920.028 | J24: 24 | K24: 691.35083 | L24: 16592.42 | M24: -37.082386 | N24: -35327.608 | O24: 66 | P24: 696.28591 | Q24: 45954.87 | S24: -29362.45
A25: Véhicules neufs | B25: Véhicules neufs | N25: -0.68042352 | S25: -0.63894099
A26: Véhicules neufs | B26: Véhicules neufs
A27: Véhicules neufsTotal Dépt. Neufs | B27: Véhicules neufs | C27: Total Dépt. Neufs | D27: 61.082386 | E27: 1886.0658 | F27: 115205.4 | G27: 61.082386 | H27: 1886.0658 | I27: 115205.4 | J27: 24 | K27: 1949.3883 | L27: 46785.32 | M27: -37.082386 | N27: -68420.081 | O27: 66 | P27: 1460.7674 | Q27: 96410.65 | R27: -42 | S27: -49625.33
A28: Véhicules neufs | B28: Véhicules neufs | M28: -0.60708804 | N28: -0.59389647 | R28: -0.63636364 | S28: -0.51472872
A29: Véhicules neufs | B29: Véhicules neufs
A30: Véhicules neufsDEPENSES | B30: Véhicules neufs | C30: DEPENSES
A31: Véhicules neufsComm. vendeurs | B31: Véhicules neufs | C31: Comm. vendeurs | E31: 386.83015 | F31: 23628.508 | H31: 386.83015 | I31: 23628.508 | J31: 0.66693441 | K31: 814.05875 | L31: 19537.41 | N31: -4091.0983 | P31: 450.04288 | Q31: 29702.83 | S31: -10165.42
A32: Véhicules neufsComm. F&I | B32: Véhicules neufs | C32: Comm. F&I | E32: 255 | F32: 15576.008 | H32: 255 | I32: 15576.008 | J32: 0.29489188 | K32: 203.87375 | L32: 4892.97 | N32: -10683.038 | P32: 207.66303 | Q32: 13705.76 | S32: -8812.79
A33: Véhicules neufsFrais de livraison | B33: Véhicules neufs | C33: Frais de livraison | E33: 197 | F33: 12033.23 | H33: 197 | I33: 12033.23 | K33: 199.92917 | L33: 4798.3 | N33: -7234.93 | P33: 122.0353 | Q33: 8054.33 | S33: -3256.03 | W33: 4148.105
A34: Véhicules neufsService gratuit 1 | B34: Véhicules neufs | C34: Service gratuit 1 | E34: 6 | F34: 366.49431 | H34: 6 | I34: 366.49431 | K34: 17.662917 | L34: 423.91 | N34: 57.415685 | P34: 0 | Q34: 0 | S34: 423.91
A35: Véhicules neufsEntretien stock | B35: Véhicules neufs | C35: Entretien stock | E35: 34 | F35: 2076.8011 | H35: 34 | I35: 2076.8011 | K35: 7.08125 | L35: 169.95 | N35: -1906.8511 | P35: 24.252273 | Q35: 1600.65 | S35: -1430.7 | W35: 744.865
A36: Véhicules neufsPublicité 1 | B36: Véhicules neufs | C36: Publicité 1 | E36: 180.66964 | F36: 11035.733 | H36: 180.66964 | I36: 11035.733 | K36: 307.50417 | L36: 7380.1 | N36: -3655.6328 | P36: 93.181818 | Q36: 6150 | S36: 1230.1
A37: Véhicules neufsIntérêt de gros | B37: Véhicules neufs | C37: Intérêt de gros | E37: 226.36716 | F37: 13827.046 | H37: 226.36716 | I37: 13827.046 | K37: 480.64333 | L37: 11535.44 | N37: -2291.6065 | P37: 277.71682 | Q37: 18329.31 | S37: -6793.87
A38: Véhicules neufs[...] | B38: Véhicules neufs | C38: [...] | E38: 0 | F38: 0 | H38: 0 | I38: 0 | K38: 0 | L38: 0 | N38: 0 | P38: 0 | Q38: 0 | S38: 0
A39: Véhicules neufs[...] | B39: Véhicules neufs | C39: [...] | E39: 0 | F39: 0 | H39: 0 | I39: 0 | K39: 0 | L39: 0 | N39: 0 | P39: 0 | Q39: 0 | S39: 0
A40: Véhicules neufs[...] | B40: Véhicules neufs | C40: [...] | E40: 0 | F40: 0 | H40: 0 | I40: 0 | K40: 0 | L40: 0 | N40: 0 | P40: 0 | Q40: 0 | S40: 0
A41: Véhicules neufsTOTAL VARIABLES | B41: Véhicules neufs | C41: TOTAL VARIABLES | D41: % brut | E41: 0.68177204 | F41: 78543.821 | G41: % brut | H41: 0.68177204 | I41: 78543.821 | J41: % brut | K41: 1.0417387 | L41: 48738.08 | N41: -29805.741 | O41: % brut | P41: 0.80429787 | Q41: 77542.88 | S41: -28804.8
A42: Véhicules neufsSalaires cadres | B42: Véhicules neufs | C42: Salaires cadres | F42: 24368.632 | I42: 24368.632 | L42: 6384.14 | N42: -17984.492 | Q42: 17655.26 | S42: -11271.12 | U42: Pierre Charles -67%
A43: Véhicules neufsSalaires commis | B43: Véhicules neufs | C43: Salaires commis | F43: 9573.4805 | I43: 9573.4805 | L43: 5390.92 | N43: -4182.5605 | Q43: 9148.48 | S43: -3757.56 | V43: 3 commis en moin
A44: Véhicules neufsSalaires autres | B44: Véhicules neufs | C44: Salaires autres | F44: 6032.6672 | I44: 6032.6672 | L44: 4197.11 | N44: -1835.5572 | Q44: 5931.63 | S44: -1734.52
A45: Véhicules neufsSalaires spécialistes | B45: Véhicules neufs | C45: Salaires spécialistes | F45: 0 | I45: 0 | L45: 0 | N45: 0 | Q45: 0 | S45: 0
A46: Véhicules neufs[...] | B46: Véhicules neufs | C46: [...] | F46: 0 | I46: 0 | L46: 0 | N46: 0 | Q46: 0 | S46: 0
A47: Véhicules neufs[...] | B47: Véhicules neufs | C47: [...] | F47: 0 | I47: 0 | L47: 0 | N47: 0 | Q47: 0 | S47: 0
A48: Véhicules neufs[...] | B48: Véhicules neufs | C48: [...] | F48: 0 | I48: 0 | L48: 0 | N48: 0 | Q48: 0 | S48: 0
A49: Véhicules neufsSalaires en absences | B49: Véhicules neufs | C49: Salaires en absences | F49: 9501.5155 | I49: 9501.5155 | L49: 7394.06 | N49: -2107.4555 | Q49: 13018.58 | S49: -5624.52
A50: Véhicules neufsDéduction à la source | B50: Véhicules neufs | C50: Déduction à la source | F50: 9501.5155 | I50: 9501.5155 | L50: 14260.56 | N50: 4759.0445 | Q50: 11499.23 | S50: 2761.33
A51: Véhicules neufsBénéfices marginaux | B51: Véhicules neufs | C51: Bénéfices marginaux | F51: 6809.4195 | I51: 6809.4195 | L51: 5856 | N51: -953.41946 | Q51: 7872.52 | S51: -2016.52
A52: Véhicules neufsCsst | B52: Véhicules neufs | C52: Csst | F52: 1583.5859 | I52: 1583.5859 | L52: 0 | N52: -1583.5859 | Q52: 3111.06 | S52: -3111.06
A53: Véhicules neufs[...] | B53: Véhicules neufs | C53: [...] | F53: 0 | I53: 0 | L53: 0 | N53: 0 | Q53: 0 | S53: 0
A54: Véhicules neufsTOTAL PERSONNEL | B54: Véhicules neufs | C54: TOTAL PERSONNEL | D54: % brut | E54: 0.58478869 | F54: 67370.816 | G54: % brut | H54: 0.58478869 | I54: 67370.816 | J54: % brut | K54: 0.92941098 | L54: 43482.79 | N54: -23888.026 | O54: % brut | P54: 0.70777201 | Q54: 68236.76 | S54: -24753.97
A55: Véhicules neufsPublicité 2 | B55: Véhicules neufs | C55: Publicité 2 | F55: 0 | I55: 0 | L55: 0 | N55: 0 | Q55: 0 | S55: 0
A56: Véhicules neufsService gratuit 2 | B56: Véhicules neufs | C56: Service gratuit 2 | F56: 0 | I56: 0 | L56: 0 | N56: 0 | Q56: 0 | S56: 0
A57: Véhicules neufsFrais véhicules de cie | B57: Véhicules neufs | C57: Frais véhicules de cie | F57: 9088.8775 | I57: 9088.8775 | L57: 5359.43 | N57: -3729.4475 | Q57: 14381.38 | S57: -9021.95
A58: Véhicules neufsInformatique | B58: Véhicules neufs | C58: Informatique | F58: 6677.3963 | I58: 6677.3963 | L58: 5798.14 | N58: -879.25627 | Q58: 8274.69 | S58: -2476.55
A59: Véhicules neufsFrais de déplacement | B59: Véhicules neufs | C59: Frais de déplacement | F59: 1596.4968 | I59: 1596.4968 | L59: 98.29 | N59: -1498.2068 | Q59: 1944.64 | S59: -1846.35
A60: Véhicules neufsServices extérieurs | B60: Véhicules neufs | C60: Services extérieurs | F60: 9409.8947 | I60: 9409.8947 | L60: 6042.08 | N60: -3367.8147 | Q60: 7752.53 | S60: -1710.45
A61: Véhicules neufsFournitures autres | B61: Véhicules neufs | C61: Fournitures autres | F61: 244.32954 | I61: 244.32954 | L61: 0 | N61: -244.32954 | Q61: 225 | S61: -225
A62: Véhicules neufsUniformes | B62: Véhicules neufs | C62: Uniformes | F62: 35 | I62: 35 | L62: 0 | N62: -35 | Q62: 35 | S62: -35
A63: Véhicules neufsPapeterie | B63: Véhicules neufs | C63: Papeterie | F63: 697.6 | I63: 697.6 | L63: 248.87 | N63: -448.73 | Q63: 592 | S63: -343.13
A64: Véhicules neufsTéléphone | B64: Véhicules neufs | C64: Téléphone | F64: 589.912 | I64: 589.912 | L64: 456.53 | N64: -133.382 | Q64: 482.96 | S64: -26.43
A65: Véhicules neufsFrais postaux | B65: Véhicules neufs | C65: Frais postaux | F65: 276.8 | I65: 276.8 | L65: 65.22 | N65: -211.58 | Q65: 210.02 | S65: -144.8
A66: Véhicules neufsDivers | B66: Véhicules neufs | C66: Divers | F66: 1349.12 | I66: 1349.12 | L66: 252.3 | N66: -1096.82 | Q66: 1705.28 | S66: -1452.98
... A68: Véhicules neufsFrais bancaires | B68: Véhicules neufs | C68: Frais bancaires | F68: 2087.6738 | I68: 2087.6738 | L68: 1926.549 | N68: -161.12483 | Q68: 5310.96 | S68: -3384.411
A69: Véhicules neufs[...] | B69: Véhicules neufs | C69: [...] | F69: 0 | I69: 0 | N69: 0 | Q69: 0 | S69: 0
A70: Véhicules neufs[...] | B70: Véhicules neufs | C70: [...] | F70: 0 | I70: 0 | L70: 0 | N70: 0 | Q70: 0 | S70: 0
A71: Véhicules neufs[...] | B71: Véhicules neufs | C71: [...] | F71: 0 | I71: 0 | L71: 0 | N71: 0 | Q71: 0 | S71: 0
A72: Véhicules neufsTOTAL SEMI-FIXES | B72: Véhicules neufs | C72: TOTAL SEMI-FIXES | D72: % brut | E72: 0.29071074 | F72: 33491.447 | G72: % brut | H72: 0.29071074 | I72: 33491.447 | J72: % brut | K72: 0.44395847 | L72: 20770.739 | N72: -12720.708 | O72: % brut | P72: 0.4716314 | Q72: 45470.29 | S72: -24699.551
A73: Véhicules neufs | B73: Véhicules neufs
A74: Véhicules neufsTOTAL DES DÉPENSES | B74: Véhicules neufs | C74: TOTAL DES DÉPENSES | D74: % brut | E74: 1.5572715 | F74: 179406.08 | G74: % brut | H74: 1.5572715 | I74: 179406.08 | J74: % brut | K74: 2.4151082 | L74: 112991.61 | N74: -66414.475 | O74: % brut | P74: 1.9837013 | Q74: 191249.93 | S74: -78258.321
A75: Véhicules neufsProgramme neuf 1 | B75: Véhicules neufs | C75: Programme neuf 1 | F75: 22678.819 | I75: 22678.819 | L75: 11500 | N75: -11178.819 | Q75: 7920
A76: Véhicules neufsProgramme neuf 2 | B76: Véhicules neufs | C76: Programme neuf 2 | F76: 0 | I76: 0 | L76: 0 | N76: 0 | Q76: 0 | S76: 0
A77: Véhicules neufsProgramme neuf 3 | B77: Véhicules neufs | C77: Programme neuf 3 | F77: 0 | I77: 0 | L77: 0 | N77: 0 | Q77: 0 | S77: 0
A78: Véhicules neufsHoldbacks | B78: Véhicules neufs | C78: Holdbacks | F78: 36387.784 | I78: 36387.784 | L78: 22341 | N78: -14046.784 | Q78: 73636.1 | S78: -51295.1
A79: Véhicules neufs[...] | B79: Véhicules neufs | C79: [...] | F79: 0 | I79: 0 | L79: 0 | N79: 0 | Q79: 0 | S79: 0
A80: Véhicules neufs[...] | B80: Véhicules neufs | C80: [...] | F80: 0 | I80: 0 | L80: 0 | N80: 0 | Q80: 0 | S80: 0
A81: Véhicules neufs[...] | B81: Véhicules neufs | C81: [...] | F81: 0 | I81: 0 | L81: 0 | N81: 0 | Q81: 0 | S81: 0
A82: Véhicules neufsFrais administration | B82: Véhicules neufs | C82: Frais administration | F82: 19185.977 | I82: 19185.977 | L82: 6261 | N82: -12924.977 | Q82: 23795.25 | S82: -17534.25
A83: Véhicules neufsAUTRES REVENUS | B83: Véhicules neufs | C83: AUTRES REVENUS | F83: 78252.58 | I83: 78252.58 | L83: 40102 | N83: -38150.58 | Q83: 105351.35 | S83: -68829.35
A84: Véhicules neufs | B84: Véhicules neufs
A85: Véhicules neufsPROFIT DÉPARTEMENTAL | B85: Véhicules neufs | C85: PROFIT DÉPARTEMENTAL | F85: 14051.897 | I85: 14051.897 | L85: -26104.289 | N85: -40156.186 | Q85: 10512.07 | S85: -40196.359
C89: Volks | K89: Véhicules usagés | S89: Réalisé, Janvier 2021
D91: BUDGET ORIGINAL | G91: BUDGET RÉVISÉ | J91: RÉALISATION | M91: ÉCART réel / révisé | O91: ANNÉE PRÉCÉDENTE | R91: ÉCART réel / original
D92: UNITE | E92: $P/UNITÉ | F92: $PROFITS | G92: UNITE | H92: $P/UNITÉ | I92: $PROFITS | J92: UNITE | K92: $P/UNITE | L92: $PROFITS | M92: UNITÉ | N92: $PROFITS | O92: UNITE | P92: $P/UNITE | Q92: $PROFITS | R92: UNITE | S92: $PROFITS
A93: Véhicules usagésVentes nettes | B93: Véhicules usagés | C93: Ventes nettes | F93: 641081.33 | I93: 641081.33 | L93: 495435.11 | Q93: 470881.1
A94: Véhicules usagésCertifié | B94: Véhicules usagés | C94: Certifié | D94: 19.240448 | E94: 750 | F94: 14430.336 | G94: 19.240448 | H94: 750 | I94: 14430.336 | J94: 14 | K94: 1047.64 | L94: 14666.96 | M94: -5.2404477 | N94: 236.62421 | O94: 0 | P94: 0 | Q94: 0 | R94: 14 | S94: 14666.96
A95: Véhicules usagésNon Certifié | B95: Véhicules usagés | C95: Non Certifié | D95: 1.0973639 | E95: 750 | F95: 823.02295 | G95: 1.0973639 | H95: 750 | I95: 823.02295 | J95: 1 | K95: 715 | L95: 715 | O95: 18 | P95: 664.77944 | Q95: 11966.03 | R95: -17 | S95: -11251.03
A96: Véhicules usagésTotal Usagés | B96: Véhicules usagés | C96: Total Usagés | D96: 20.337812 | E96: 750 | F96: 15253.359 | G96: 20.337812 | H96: 750 | I96: 15253.359 | J96: 15 | K96: 1025.464 | L96: 15381.96 | M96: -5.3378117 | N96: 128.60126 | O96: 18 | P96: 664.77944 | Q96: 11966.03 | R96: -3 | S96: 3415.93
A97: Véhicules usagés | B97: Véhicules usagés | E97: 0 | H97: 0 | M97: -0.26245752 | N97: 0.0084310125 | R97: -0.16666667 | S97: 0.28546895
A98: Véhicules usagésUS | B98: Véhicules usagés | C98: US
A99: Véhicules usagésVentes au Gros | B99: Véhicules usagés | C99: Ventes au Gros | D99: 17.233619 | E99: 120 | F99: 2068.0343 | G99: 17.233619 | H99: 120 | I99: 2068.0343 | J99: 20 | K99: -41.21 | L99: -824.2 | M99: 2.7663807 | N99: -2892.2343 | O99: 11 | P99: -490.35545 | Q99: -5393.91 | R99: 9 | S99: 4569.71
A100: Véhicules usagés | B100: Véhicules usagés
A101: Véhicules usagésRev. Finances | B101: Véhicules usagés | C101: Rev. Finances | D101: 0 | E101: 0 | F101: 16353.504 | G101: 0 | H101: 0 | I101: 16353.504 | K101: 309.40733 | L101: 4641.11 | N101: -11712.394 | P101: 268.61222 | Q101: 4835.02 | R101: -309.40733 | S101: -193.91
A102: Véhicules usagésRev. Protections | B102: Véhicules usagés | C102: Rev. Protections | D102: 0 | E102: 0 | F102: 18533.971 | G102: 0 | H102: 0 | I102: 18533.971 | K102: 1352.4093 | L102: 20286.14 | N102: 1752.1693 | P102: 437.56278 | Q102: 7876.13 | R102: -1352.4093 | S102: 12410.01
A103: Véhicules usagésRev. Autres | B103: Véhicules usagés | C103: Rev. Autres | D103: 0 | E103: 0 | F103: 0 | G103: 0 | H103: 0 | I103: 0 | K103: 43.192667 | L103: 647.89 | N103: 647.89 | P103: 24.228889 | Q103: 436.12 | R103: -43.192667 | S103: 211.77
A104: Véhicules usagésTotal F&I | B104: Véhicules usagés | C104: Total F&I | D104: 20.337812 | E104: 1715.3996 | F104: 34887.474 | G104: 20.337812 | H104: 1715.3996 | I104: 34887.474 | J104: 15 | K104: 1705.0093 | L104: 25575.14 | M104: -5.3378117 | N104: -9312.3342 | O104: 18 | P104: 730.40389 | Q104: 13147.27 | S104: 12427.87
A105: Véhicules usagés | B105: Véhicules usagés | N105: -0.26692486 | S105: 0.94528142
...

Sheet 2
C1: Volks | K1: Véhicules neufs | S1: Réalisé, Février 2021
D2: X | E2: O | F2: U | G2: X | H2: O | I2: U | J2: NB | L2: $ | O2: NB | Q2: $
D3: BUDGET ORIGINAL | G3: BUDGET REVISE | J3: RÉALISATION | M3: ÉCART réel / révisé | O3: ANNÉE PRÉCÉDENTE | R3: ÉCART réel / original | V3: NEUF | W3: 0.45
D4: UNITE | E4: $P/UNITÉ | F4: $PROFITS | G4: UNITE | H4: $P/UNITÉ | I4: $PROFITS | J4: UNITE | K4: $P/UNITE | L4: $PROFITS | M4: UNITÉ | N4: $PROFITS | O4: UNITE | P4: $P/UNITE | Q4: $PROFITS | R4: UNITE | S4: $PROFITS | V4: USAGE | W4: 0.1
A5: Véhicules neufsVentes nettes | B5: Véhicules neufs | C5: Ventes nettes | F5: 446219.11 | I5: 446219.11 | L5: 2019283.1 | Q5: 1936803.6 | V5: SERVICE | W5: 0.225
A6: Véhicules neufsAutos détail | B6: Véhicules neufs | C6: Autos détail | D6: 16.252745 | E6: 604.29043 | F6: 9821.3783 | G6: 16.252745 | H6: 955.05622 | I6: 15522.285 | J6: 15 | K6: 1396.284 | L6: 20944.26 | M6: -1.252745 | N6: 5421.9748 | O6: 17 | P6: 522.84765 | Q6: 8888.41 | R6: -2 | S6: 12055.85 | V6: CARROSSERIE | W6: 0.025
A7: Véhicules neufsCamions détail | B7: Véhicules neufs | C7: Camions détail | D7: 21.831245 | E7: 1315.4791 | F7: 28718.547 | G7: 21.831245 | H7: 1702.6669 | I7: 37171.338 | J7: 21 | K7: 2079.4924 | L7: 43669.34 | M7: -0.83124494 | N7: 6498.0023 | O7: 30 | P7: 644.324 | Q7: 19329.72 | R7: -9 | S7: 24339.62 | V7: PIECES | W7: 0.2
A8: Véhicules neufsSprinter | B8: Véhicules neufs | C8: Sprinter | D8: 0 | E8: 0 | F8: 0 | G8: 0 | H8: 0 | I8: 0 | J8: 0 | K8: 0 | L8: 0 | M8: 0 | N8: 0 | O8: 0 | P8: 0 | Q8: 0 | R8: 0 | S8: 0 | W8: 1
A9: Véhicules neufsMoto détail | B9: Véhicules neufs | C9: Moto détail | D9: 0 | E9: 0 | F9: 0 | G9: 0 | H9: 0 | I9: 0 | J9: 0 | K9: 0 | L9: 0 | M9: 0 | N9: 0 | O9: 0 | P9: 0 | Q9: 0 | R9: 0 | S9: 0
