Workbook
Name _Dates_Conc: [1]Dealers!$BF$37:$KA$63
Name _scen: '[1]Scen & Sens'!$E$26
Name _scen1: '[1]Scen & Sens'!$E$27
Name _scen2: '[1]Scen & Sens'!$E$28
Name _SCenarios: '[1]Scen & Sens'!$J$26:$O$26
Name _Sens1: '[1]Scen & Sens'!$F$9
Name _Sens2: '[1]Scen & Sens'!$F$10
Name _sensRes1: '[1]Scen & Sens'!$E$15
Name _sensRes2: '[1]Scen & Sens'!$E$16
Name _sensRes3: '[1]Scen & Sens'!$E$17
Name _sensRes4: '[1]Scen & Sens'!$E$18
Name _sensRes5: '[1]Scen & Sens'!$E$19
Name _sensRes6: '[1]Scen & Sens'!$E$20
Name _sensRes7: '[1]Scen & Sens'!$E$21
Name DateRange: [1]Volkswagen!$BF$6:$DY$6
Name Monetary_Unit: [1]Parameters!$B$15
Name Months: [1]Parameters!$E$9:$E$20
Name Rng_Dealers_Names: [1]!Tbl_Dealers[Dealer Name]
Name Rng_Dlr_Dates: [1]!Tbl_V_Dlr_Dates[Date]
Name Ticker: #REF!
Name Ticker: #REF!
Name Ticker: #REF!
Name Titre: [1]Front!$A$9

Sheet Paramètre
B3: Quarter
B6: BUDGET | F6: BUDGET RÉVISÉ | J6: ACTUAL | N6: LAST YEAR
B7: Ventes | C7: Profits bruts | D7: BAIIA | E7: EBIT | F7: Ventes | G7: Profits bruts | H7: BAIIA | I7: EBIT | J7: Ventes | K7: Profits bruts | L7: BAIIA | M7: EBIT | N7: Ventes | O7: Profits bruts | P7: BAIIA | Q7: EBIT
A8: CTRL | B8: =+B9-B10 -> #REF! | C8: =+C9-C10 -> #REF! | D8: =+D9-D10 -> #REF! | E8: =+E9-E10 -> #REF! | F8: =+F9-F10 -> #REF! | G8: =+G9-G10 -> #REF! | H8: =+H9-H10 -> #REF! | I8: =+I9-I10 -> #REF! | ... Q8: =+Q9-Q10 -> #REF!
A9: CONSO | B9: =+Conso!$Z$405 -> 19264267 | C9: =+Conso!$Z$406 -> 2767342.7 | D9: =+Conso!$Z$482 -> 1036365.6 | E9: =+Conso!$Z$497 -> 1031420.6 | F9: =+Conso!$AC$405 -> 0 | G9: =+Conso!$AC$406 -> 0 | H9: =+Conso!$AC$482 -> 0 | I9: =+Conso!$AC$497 -> 0 | J9: =+Conso!$AF$405 -> 16428062 | K9: =+Conso!$AF$406 -> 1897181 | L9: =+Conso!$AF$482 -> 366005.68 | M9: =+Conso!$AF$497 -> 361195.19 | N9: =+Conso!$AL$405 -> 13893961 | O9: =+Conso!$AL$406 -> 1960729.2 | P9: =+Conso!$AL$482 -> 554891.33 | Q9: =+Conso!$AL$497 -> 541947.83
A10: TOTAL | B10: =+SUM(B11:B13) -> #REF! | C10: =+SUM(C11:C13) -> #REF! | D10: =+SUM(D11:D13) -> #REF! | E10: =+SUM(E11:E13) -> #REF! | F10: =+SUM(F11:F13) -> #REF! | G10: =+SUM(G11:G13) -> #REF! | H10: =+SUM(H11:H13) -> #REF! | I10: =+SUM(I11:I13) -> #REF! | ... Q10: =+SUM(Q11:Q13) -> #REF!
A11: Mois 1 | B11: =+#REF! -> #REF! | C11: =+#REF! -> #REF! | D11: =+#REF! -> #REF! | E11: =+#REF! -> #REF! | F11: =+#REF! -> #REF! | G11: =+#REF! -> #REF! | H11: =+#REF! -> #REF! | I11: =+#REF! -> #REF! | ... Q11: =+#REF! -> #REF!
A12: Mois 2 | B12: =+#REF! -> #REF! | C12: =+#REF! -> #REF! | D12: =+#REF! -> #REF! | E12: =+#REF! -> #REF! | F12: =+#REF! -> #REF! | G12: =+#REF! -> #REF! | H12: =+#REF! -> #REF! | I12: =+#REF! -> #REF! | ... Q12: =+#REF! -> #REF!
A13: Mois 3 | B13: =+#REF! -> #REF! | C13: =+#REF! -> #REF! | D13: =+#REF! -> #REF! | E13: =+#REF! -> #REF! | F13: =+#REF! -> #REF! | G13: =+#REF! -> #REF! | H13: =+#REF! -> #REF! | I13: =+#REF! -> #REF! | ... Q13: =+#REF! -> #REF!

Sheet Conso
C1: Conso | K1: Véhicules neufs | S1: =CONCATENATE("Réalisé"," ",Paramètre!$C$2," ",Paramètre!$C$3) -> Réalisé
D2: X | E2: O | F2: U | G2: X | H2: O | I2: U
D3: BUDGET ORIGINAL | G3: BUDGET REVISE | J3: RÉALISATION | M3: ÉCART réel / original | O3: ANNÉE PRÉCÉDENTE | R3: ÉCART réel / année précédente
D4: UNITE | E4: $P/UNITÉ | F4: $PROFITS | G4: UNITE | H4: $P/UNITÉ | I4: $PROFITS | J4: UNITE | K4: $P/UNITE | L4: $PROFITS | M4: UNITÉ | N4: $PROFITS | O4: UNITE | P4: $P/UNITE | Q4: $PROFITS | R4: UNITE | S4: $PROFITS
A5: =+B5&C5 -> Véhicules neufsVentes nettes | B5: =+$K$1 -> Véhicules neufs | C5: Ventes nettes | F5: =+SUM(START:END!F5) -> 9890625.2 | I5: =+SUM(START:END!I5) -> 0 | L5: =+SUM(START:END!L5) -> 9890070 | Q5: =+SUM(START:END!Q5) -> 7425353.9
A6: =+B6&C6 -> Véhicules neufsAutos détail | B6: =+$K$1 -> Véhicules neufs | C6: Autos détail | D6: =+SUM(START:END!D6) -> 37 | E6: =IF(D6=0,0,F6/D6) -> 2174.3584 | F6: =+SUM(START:END!F6) -> 80451.263 | G6: =+SUM(START:END!G6) -> 0 | H6: =IF(G6=0,0,I6/G6) -> 0 | I6: =+SUM(START:END!I6) -> 0 | J6: =+SUM(START:END!J6) -> 51 | K6: =IF(J6=0,0,L6/J6) -> 1956.158 | L6: =+SUM(START:END!L6) -> 99764.06 | M6: =J6-D6 -> 14 | N6: =L6-F6 -> 19312.797 | O6: =+SUM(START:END!O6) -> 40 | P6: =IF(O6=0,0,Q6/O6) -> 2348.4692 | Q6: =+SUM(START:END!Q6) -> 93938.77 | R6: =J6-O6 -> 11 | S6: =L6-Q6 -> 5825.29
A7: =+B7&C7 -> Véhicules neufsCamions détail | B7: =+$K$1 -> Véhicules neufs | C7: Camions détail | D7: =+SUM(START:END!D7) -> 151.68 | E7: =IF(D7=0,0,F7/D7) -> 2865.6675 | F7: =+SUM(START:END!F7) -> 434664.45 | G7: =+SUM(START:END!G7) -> 0 | H7: =IF(G7=0,0,I7/G7) -> 0 | I7: =+SUM(START:END!I7) -> 0 | J7: =+SUM(START:END!J7) -> 127 | K7: =IF(J7=0,0,L7/J7) -> 2623.2423 | L7: =+SUM(START:END!L7) -> 333151.77 | M7: =J7-D7 -> -24.68 | N7: =L7-F7 -> -101512.68 | O7: =+SUM(START:END!O7) -> 89 | P7: =IF(O7=0,0,Q7/O7) -> 2474.2398 | Q7: =+SUM(START:END!Q7) -> 220207.34 | R7: =J7-O7 -> 38 | S7: =L7-Q7 -> 112944.43
A8: =+B8&C8 -> Véhicules neufsSprinter | B8: =+$K$1 -> Véhicules neufs | C8: Sprinter | D8: =+SUM(START:END!D8) -> 0 | E8: =IF(D8=0,0,F8/D8) -> 0 | F8: =+SUM(START:END!F8) -> 0 | G8: =+SUM(START:END!G8) -> 0 | H8: =IF(G8=0,0,I8/G8) -> 0 | I8: =+SUM(START:END!I8) -> 0 | J8: =+SUM(START:END!J8) -> 0 | K8: =IF(J8=0,0,L8/J8) -> 0 | L8: =+SUM(START:END!L8) -> 0 | M8: =J8-D8 -> 0 | N8: =L8-F8 -> 0 | O8: =+SUM(START:END!O8) -> 0 | P8: =IF(O8=0,0,Q8/O8) -> 0 | Q8: =+SUM(START:END!Q8) -> 0 | R8: =J8-O8 -> 0 | S8: =L8-Q8 -> 0
A9: =+B9&C9 -> Véhicules neufsMoto détail | B9: =+$K$1 -> Véhicules neufs | C9: Moto détail | D9: =+SUM(START:END!D9) -> 0 | E9: =IF(D9=0,0,F9/D9) -> 0 | F9: =+SUM(START:END!F9) -> 0 | G9: =+SUM(START:END!G9) -> 0 | H9: =IF(G9=0,0,I9/G9) -> 0 | I9: =+SUM(START:END!I9) -> 0 | J9: =+SUM(START:END!J9) -> 0 | K9: =IF(J9=0,0,L9/J9) -> 0 | L9: =+SUM(START:END!L9) -> 0 | M9: =J9-D9 -> 0 | N9: =L9-F9 -> 0 | O9: =+SUM(START:END!O9) -> 0 | P9: =IF(O9=0,0,Q9/O9) -> 0 | Q9: =+SUM(START:END!Q9) -> 0 | R9: =J9-O9 -> 0 | S9: =L9-Q9 -> 0
A10: =+B10&C10 -> Véhicules neufs[...] | B10: =+$K$1 -> Véhicules neufs | C10: [...] | D10: =+SUM(START:END!D10) -> 0 | E10: =IF(D10=0,0,F10/D10) -> 0 | F10: =+SUM(START:END!F10) -> 0 | G10: =+SUM(START:END!G10) -> 0 | H10: =IF(G10=0,0,I10/G10) -> 0 | I10: =+SUM(START:END!I10) -> 0 | J10: =+SUM(START:END!J10) -> 0 | K10: =IF(J10=0,0,L10/J10) -> 0 | L10: =+SUM(START:END!L10) -> 0 | M10: =J10-G10 -> 0 | N10: =L10-I10 -> 0 | O10: =+SUM(START:END!O10) -> 0 | P10: =IF(O10=0,0,Q10/O10) -> 0 | Q10: =+SUM(START:END!Q10) -> 0 | R10: =J10-O10 -> 0 | S10: =L10-Q10 -> 0
A11: =+B11&C11 -> Véhicules neufs[...] | B11: =+$K$1 -> Véhicules neufs | C11: [...] | D11: =+SUM(START:END!D11) -> 0 | E11: =IF(D11=0,0,F11/D11) -> 0 | F11: =+SUM(START:END!F11) -> 0 | G11: =+SUM(START:END!G11) -> 0 | H11: =IF(G11=0,0,I11/G11) -> 0 | I11: =+SUM(START:END!I11) -> 0 | J11: =+SUM(START:END!J11) -> 0 | K11: =IF(J11=0,0,L11/J11) -> 0 | L11: =+SUM(START:END!L11) -> 0 | M11: =J11-G11 -> 0 | N11: =L11-I11 -> 0 | O11: =+SUM(START:END!O11) -> 0 | P11: =IF(O11=0,0,Q11/O11) -> 0 | Q11: =+SUM(START:END!Q11) -> 0 | R11: =J11-O11 -> 0 | S11: =L11-Q11 -> 0
A12: =+B12&C12 -> Véhicules neufs[...] | B12: =+$K$1 -> Véhicules neufs | C12: [...] | D12: =+SUM(START:END!D12) -> 0 | E12: =IF(D12=0,0,F12/D12) -> 0 | F12: =+SUM(START:END!F12) -> 0 | G12: =+SUM(START:END!G12) -> 0 | H12: =IF(G12=0,0,I12/G12) -> 0 | I12: =+SUM(START:END!I12) -> 0 | J12: =+SUM(START:END!J12) -> 0 | K12: =IF(J12=0,0,L12/J12) -> 0 | L12: =+SUM(START:END!L12) -> 0 | M12: =J12-G12 -> 0 | N12: =L12-I12 -> 0 | O12: =+SUM(START:END!O12) -> 0 | P12: =IF(O12=0,0,Q12/O12) -> 0 | Q12: =+SUM(START:END!Q12) -> 0 | R12: =J12-O12 -> 0 | S12: =L12-Q12 -> 0
A13: =+B13&C13 -> Véhicules neufsTotal Neufs | B13: =+$K$1 -> Véhicules neufs | C13: Total Neufs | D13: =+SUM(D6:D12) -> 188.68 | E13: =IF(D13<=0,0,F13/D13) -> 2730.1024 | F13: =+SUM(F6:F12) -> 515115.71 | G13: =+SUM(G6:G12) -> 0 | H13: =IF(G13<=0,0,I13/G13) -> 0 | I13: =+SUM(I6:I12) -> 0 | J13: =+SUM(J6:J12) -> 178 | K13: =IF(J13<=0,0,L13/J13) -> 2432.1114 | L13: =+SUM(L6:L12) -> 432915.83 | M13: =+SUM(M6:M12) -> -10.68 | N13: =+SUM(N6:N12) -> -82199.884 | O13: =+SUM(O6:O12) -> 129 | P13: =IF(O13<=0,0,Q13/O13) -> 2435.2412 | Q13: =+SUM(Q6:Q12) -> 314146.11 | R13: =+SUM(R6:R12) -> 49 | S13: =+SUM(S6:S12) -> 118769.72
A14: =+B14&C14 -> Véhicules neufs | B14: =+$K$1 -> Véhicules neufs | N14: =IF(F13=0,0,N13/F13) -> -0.15957557 | R14: =R13/O13 -> 0.37984496 | S14: =IF(Q13=0,0,(S13/Q13)) -> 0.37807159
A15: =+B15&C15 -> Véhicules neufsEx-Démos et courtoisies | B15: =+$K$1 -> Véhicules neufs | C15: Ex-Démos et courtoisies | D15: =+SUM(START:END!D15) -> 15.045 | E15: =IF(D15=0,0,F15/D15) -> 2518.2713 | F15: =+SUM(START:END!F15) -> 37887.392 | G15: =+SUM(START:END!G15) -> 0 | H15: =IF(G15=0,0,I15/G15) -> 0 | I15: =+SUM(START:END!I15) -> 0 | J15: =+SUM(START:END!J15) -> 9 | K15: =IF(J15=0,0,L15/J15) -> 1653.9344 | L15: =+SUM(START:END!L15) -> 14885.41 | M15: =J15-G15 -> 9 | N15: =L15-I15 -> 14885.41 | O15: =+SUM(START:END!O15) -> 15 | P15: =IF(O15=0,0,Q15/O15) -> 2083.5413 | Q15: =+SUM(START:END!Q15) -> 31253.12 | R15: =J15-O15 -> -6 | S15: =L15-Q15 -> -16367.71
A16: =+B16&C16 -> Véhicules neufs | B16: =+$K$1 -> Véhicules neufs
A17: =+B17&C17 -> Véhicules neufsFlottes | B17: =+$K$1 -> Véhicules neufs | C17: Flottes | D17: =+SUM(START:END!D17) -> 13.725 | E17: =IF(D17=0,0,F17/D17) -> 2664.4641 | F17: =+SUM(START:END!F17) -> 36569.769 | G17: =+SUM(START:END!G17) -> 0 | H17: =IF(G17=0,0,I17/G17) -> 0 | I17: =+SUM(START:END!I17) -> 0 | J17: =+SUM(START:END!J17) -> 0 | K17: =IF(J17=0,0,L17/J17) -> 0 | L17: =+SUM(START:END!L17) -> 0 | M17: =J17-D17 -> -13.725 | N17: =L17-F17 -> -36569.769 | O17: =+SUM(START:END!O17) -> 8 | P17: =IF(O17=0,0,Q17/O17) -> 2410.1687 | Q17: =+SUM(START:END!Q17) -> 19281.35 | R17: =J17-O17 -> -8 | S17: =L17-Q17 -> -19281.35
A18: =+B18&C18 -> Véhicules neufs | B18: =+$K$1 -> Véhicules neufs
A19: =+B19&C19 -> Véhicules neufsRachat bail | B19: =+$K$1 -> Véhicules neufs | C19: Rachat bail | F19: =+SUM(START:END!F19) -> 25925 | I19: =+SUM(START:END!I19) -> 0 | L19: =+SUM(START:END!L19) -> 22060.37 | N19: =L19-F19 -> -3864.63 | Q19: =+SUM(START:END!Q19) -> 32801.63 | R19: =O19-K19 -> 0 | S19: =L19-Q19 -> -10741.26
A20: =+B20&C20 -> Véhicules neufs | B20: =+$K$1 -> Véhicules neufs
A21: =+B21&C21 -> Véhicules neufsRev. Finances | B21: =+$K$1 -> Véhicules neufs | C21: Rev. Finances | D21: 0 | E21: =IF(D21=0,0,F21/D21) -> 0 | F21: =+SUM(START:END!F21) -> 40745 | G21: 0 | H21: =IF(G21=0,0,I21/G21) -> 0 | I21: =+SUM(START:END!I21) -> 0 | K21: =IF(J13=0,0,L21/(J13+J15)) -> 4.2780749 | L21: =+SUM(START:END!L21) -> 800 | N21: =L21-F21 -> -39945 | P21: =IF(O13=0,0,Q21/(O13+O15)) -> 102.54681 | Q21: =+SUM(START:END!Q21) -> 14766.74 | R21: =O21-K21 -> -4.2780749 | S21: =L21-Q21 -> -13966.74
A22: =+B22&C22 -> Véhicules neufsRev. Protections | B22: =+$K$1 -> Véhicules neufs | C22: Rev. Protections | D22: 0 | E22: =IF(D22=0,0,F22/D22) -> 0 | F22: =+SUM(START:END!F22) -> 220023 | G22: 0 | H22: =IF(G22=0,0,I22/G22) -> 0 | I22: =+SUM(START:END!I22) -> 0 | K22: =IF(J13=0,0,L22/(J13+J15)) -> 777.99171 | L22: =+SUM(START:END!L22) -> 145484.45 | N22: =L22-F22 -> -74538.55 | P22: =IF(O13=0,0,Q22/(O13+O15)) -> 928.50687 | Q22: =+SUM(START:END!Q22) -> 133704.99 | R22: =O22-K22 -> -777.99171 | S22: =L22-Q22 -> 11779.46
A23: =+B23&C23 -> Véhicules neufsRev. Autres | B23: =+$K$1 -> Véhicules neufs | C23: Rev. Autres | D23: 0 | E23: =IF(D23=0,0,F23/D23) -> 0 | F23: =+SUM(START:END!F23) -> 4074.5 | G23: 0 | H23: =IF(G23=0,0,I23/G23) -> 0 | I23: =+SUM(START:END!I23) -> 0 | K23: =IF(J13=0,0,L23/(J13+J15)) -> 21.696417 | L23: =+SUM(START:END!L23) -> 4057.23 | N23: =L23-F23 -> -17.27 | P23: =IF(O13=0,0,Q23/(O13+O15)) -> 12.119236 | Q23: =+SUM(START:END!Q23) -> 1745.17 | R23: =O23-K23 -> -21.696417 | S23: =L23-Q23 -> 2312.06
A24: =+B24&C24 -> Véhicules neufsTotal F&I | B24: =+$K$1 -> Véhicules neufs | C24: Total F&I | D24: =+D15+D13 -> 203.725 | E24: =IF(D24<=0,0,F24/D24) -> 1300 | F24: =F21+F22+F23 -> 264842.5 | G24: =+G15+G13 -> 0 | H24: =IF(G24<=0,0,I24/G24) -> 0 | I24: =I21+I22+I23 -> 0 | J24: =+J15+J13 -> 187 | K24: =IF(J24<=0,0,L24/J24) -> 803.9662 | L24: =L21+L22+L23 -> 150341.68 | M24: =+M15+M13 -> -1.68 | N24: =N21+N22+N23 -> -114500.82 | O24: =+O15+O13 -> 144 | P24: =IF(O24<=0,0,Q24/O24) -> 1043.1729 | Q24: =Q21+Q22+Q23 -> 150216.9 | S24: =L24-Q24 -> 124.78
A25: =+B25&C25 -> Véhicules neufs | B25: =+$K$1 -> Véhicules neufs | S25: =IF(Q24=0,0,(S24/Q24)) -> 0.00083066552
A26: =+B26&C26 -> Véhicules neufs | B26: =+$K$1 -> Véhicules neufs
A27: =+B27&C27 -> Véhicules neufsTotal Dépt. Neufs | B27: =+$K$1 -> Véhicules neufs | C27: Total Dépt. Neufs | D27: =+D13+D15+D17 -> 217.45 | E27: =IF(D27<=0,0,F27/D27) -> 4048.4726 | F27: =F13+F17+F24+F19+F15 -> 880340.38 | G27: =+G13+G15+G17 -> 0 | H27: =IF(G27<=0,0,I27/G27) -> 0 | I27: =I13+I17+I24+I19+I15 -> 0 | J27: =+J13+J15+J17 -> 187 | K27: =IF(J27<=0,0,L27/J27) -> 3316.5951 | L27: =L13+L17+L24+L19+L15 -> 620203.29 | M27: =+M13+M15+M17 -> -15.405 | N27: =N13+N17+N24+N19+N15 -> -222249.69 | O27: =+O13+O15+O17 -> 152 | P27: =IF(O27<=0,0,Q27/O27) -> 3603.2836 | Q27: =Q13+Q17+Q24+Q19+Q15 -> 547699.11 | R27: =J27-O27 -> 35 | S27: =L27-Q27 -> 72504.18
A28: =+B28&C28 -> Véhicules neufs | B28: =+$K$1 -> Véhicules neufs | M28: =M27/D27 -> -0.070843872 | N28: =N27/F27 -> -0.25245882 | R28: =R27/O27 -> 0.23026316 | S28: =IF(Q27=0,0,S27/Q27) -> 0.13237958
A29: =+B29&C29 -> Véhicules neufs | B29: =+$K$1 -> Véhicules neufs
A30: =+B30&C30 -> Véhicules neufsDEPENSES | B30: =+$K$1 -> Véhicules neufs | C30: DEPENSES
A31: =+B31&C31 -> Véhicules neufsComm. vendeurs | B31: =+$K$1 -> Véhicules neufs | C31: Comm. vendeurs | E31: =F31/D$24 -> 922.91597 | F31: =+SUM(START:END!F31) -> 188021.06 | H31: =I31/G$24 -> #DIV/0! | I31: =+SUM(START:END!I31) -> 0 | J31: =L31/L13 -> 0.25250262 | K31: =IF(L31=0,0,L31/J$24) -> 584.55818 | L31: =+SUM(START:END!L31) -> 109312.38 | N31: =L31-F31 -> -78708.676 | P31: =IF(Q31=0,0,Q31/O$24) -> 853.17653 | Q31: =+SUM(START:END!Q31) -> 122857.42 | S31: =L31-Q31 -> -13545.04
A32: =+B32&C32 -> Véhicules neufsComm. F&I | B32: =+$K$1 -> Véhicules neufs | C32: Comm. F&I | E32: =F32/D$24 -> 390 | F32: =+SUM(START:END!F32) -> 79452.75 | H32: =I32/G$24 -> #DIV/0! | I32: =+SUM(START:END!I32) -> 0 | J32: =L32/L24 -> 0.23238792 | K32: =IF(L32=0,0,L32/J$24) -> 186.83203 | L32: =+SUM(START:END!L32) -> 34937.59 | N32: =L32-F32 -> -44515.16 | P32: =IF(Q32=0,0,Q32/O$24) -> 312.93014 | Q32: =+SUM(START:END!Q32) -> 45061.94 | S32: =L32-Q32 -> -10124.35
A33: =+B33&C33 -> Véhicules neufsFrais de livraison | B33: =+$K$1 -> Véhicules neufs | C33: Frais de livraison | E33: =F33/D$24 -> 115 | F33: =+SUM(START:END!F33) -> 23428.375 | H33: =I33/G$24 -> #DIV/0! | I33: =+SUM(START:END!I33) -> 0 | K33: =IF(L33=0,0,L33/J$24) -> 108.74684 | L33: =+SUM(START:END!L33) -> 20335.66 | N33: =L33-F33 -> -3092.715 | P33: =IF(Q33=0,0,Q33/O$24) -> 103.9 | Q33: =+SUM(START:END!Q33) -> 14961.6 | S33: =L33-Q33 -> 5374.06
A34: =+B34&C34 -> Véhicules neufsService gratuit 1 | B34: =+$K$1 -> Véhicules neufs | C34: Service gratuit 1 | E34: =F34/D$24 -> 3 | F34: =+SUM(START:END!F34) -> 611.175 | H34: =I34/G$24 -> #DIV/0! | I34: =+SUM(START:END!I34) -> 0 | K34: =IF(L34=0,0,L34/J$24) -> 6.8069519 | L34: =+SUM(START:END!L34) -> 1272.9 | N34: =L34-F34 -> 661.725 | P34: =IF(Q34=0,0,Q34/O$24) -> 0.55555556 | Q34: =+SUM(START:END!Q34) -> 80 | S34: =L34-Q34 -> 1192.9
A35: =+B35&C35 -> Véhicules neufsEntretien stock | B35: =+$K$1 -> Véhicules neufs | C35: Entretien stock | E35: =F35/D$24 -> 85.05 | F35: =+SUM(START:END!F35) -> 17326.811 | H35: =I35/G$24 -> #DIV/0! | I35: =+SUM(START:END!I35) -> 0 | K35: =IF(L35=0,0,L35/J$24) -> 156.67278 | L35: =+SUM(START:END!L35) -> 29297.81 | N35: =L35-F35 -> 11970.999 | P35: =IF(Q35=0,0,Q35/O$24) -> 73.293611 | Q35: =+SUM(START:END!Q35) -> 10554.28 | S35: =L35-Q35 -> 18743.53
A36: =+B36&C36 -> Véhicules neufsPublicité 1 | B36: =+$K$1 -> Véhicules neufs | C36: Publicité 1 | E36: =F36/D$24 -> 87.546938 | F36: =+SUM(START:END!F36) -> 17835.5 | H36: =I36/G$24 -> #DIV/0! | I36: =+SUM(START:END!I36) -> 0 | K36: =IF(L36=0,0,L36/J$24) -> 173.37182 | L36: =+SUM(START:END!L36) -> 32420.53 | N36: =L36-F36 -> 14585.03 | P36: =IF(Q36=0,0,Q36/O$24) -> 106.97472 | Q36: =+SUM(START:END!Q36) -> 15404.36 | S36: =L36-Q36 -> 17016.17
A37: =+B37&C37 -> Véhicules neufsIntérêt de gros | B37: =+$K$1 -> Véhicules neufs | C37: Intérêt de gros | E37: =F37/D$24 -> 274.63015 | F37: =+SUM(START:END!F37) -> 55949.028 | H37: =I37/G$24 -> #DIV/0! | I37: =+SUM(START:END!I37) -> 0 | K37: =IF(L37=0,0,L37/J$24) -> 654.65048 | L37: =+SUM(START:END!L37) -> 122419.64 | N37: =L37-F37 -> 66470.612 | P37: =IF(Q37=0,0,Q37/O$24) -> 86.623472 | Q37: =+SUM(START:END!Q37) -> 12473.78 | S37: =L37-Q37 -> 109945.86
A38: =+B38&C38 -> Véhicules neufs[...] | B38: =+$K$1 -> Véhicules neufs | C38: [...] | E38: =F38/D$24 -> 0 | F38: =+SUM(START:END!F38) -> 0 | H38: =I38/G$24 -> #DIV/0! | I38: =+SUM(START:END!I38) -> 0 | K38: =IF(L38=0,0,L38/J$24) -> 0 | L38: =+SUM(START:END!L38) -> 0 | N38: =L38-I38 -> 0 | P38: =IF(Q38=0,0,Q38/O$24) -> 0 | Q38: =+SUM(START:END!Q38) -> 0 | S38: =L38-Q38 -> 0
A39: =+B39&C39 -> Véhicules neufs[...] | B39: =+$K$1 -> Véhicules neufs | C39: [...] | E39: =F39/D$24 -> 0 | F39: =+SUM(START:END!F39) -> 0 | H39: =I39/G$24 -> #DIV/0! | I39: =+SUM(START:END!I39) -> 0 | K39: =IF(L39=0,0,L39/J$24) -> 0 | L39: =+SUM(START:END!L39) -> 0 | N39: =L39-I39 -> 0 | P39: =IF(Q39=0,0,Q39/O$24) -> 0 | Q39: =+SUM(START:END!Q39) -> 0 | S39: =L39-Q39 -> 0
A40: =+B40&C40 -> Véhicules neufs[...] | B40: =+$K$1 -> Véhicules neufs | C40: [...] | E40: =F40/D$24 -> 0 | F40: =+SUM(START:END!F40) -> 0 | H40: =I40/G$24 -> #DIV/0! | I40: =+SUM(START:END!I40) -> 0 | K40: =IF(L40=0,0,L40/J$24) -> 0 | L40: =+SUM(START:END!L40) -> 0 | N40: =L40-I40 -> 0 | P40: =IF(Q40=0,0,Q40/O$24) -> 0 | Q40: =+SUM(START:END!Q40) -> 0 | S40: =L40-Q40 -> 0
A41: =+B41&C41 -> Véhicules neufsTOTAL VARIABLES | B41: =+$K$1 -> Véhicules neufs | C41: TOTAL VARIABLES | D41: % brut | E41: =F41/F$27 -> 0.43463268 | F41: =SUM(F31:F40) -> 382624.7 | G41: % brut | H41: =I41/I$27 -> #DIV/0! | I41: =SUM(I31:I40) -> 0 | J41: % brut | K41: =L41/L$27 -> 0.56432546 | L41: =SUM(L31:L40) -> 349996.51 | N41: =SUM(N31:N40) -> -32628.185 | O41: % brut | P41: =Q41/Q$27 -> 0.40422447 | Q41: =SUM(Q31:Q40) -> 221393.38 | S41: =L41-Q41 -> 128603.13
A42: =+B42&C42 -> Véhicules neufsSalaires cadres | B42: =+$K$1 -> Véhicules neufs | C42: Salaires cadres | F42: =+SUM(START:END!F42) -> 57527.713 | I42: =+SUM(START:END!I42) -> 0 | L42: =+SUM(START:END!L42) -> 37570.23 | N42: =L42-F42 -> -19957.483 | Q42: =+SUM(START:END!Q42) -> 40618.61
A43: =+B43&C43 -> Véhicules neufsSalaires commis | B43: =+$K$1 -> Véhicules neufs | C43: Salaires commis | F43: =+SUM(START:END!F43) -> 36489.411 | I43: =+SUM(START:END!I43) -> 0 | L43: =+SUM(START:END!L43) -> 29871.64 | N43: =L43-F43 -> -6617.771 | Q43: =+SUM(START:END!Q43) -> 37255.95 | S43: =L43-Q43 -> -7384.31
A44: =+B44&C44 -> Véhicules neufsSalaires autres | B44: =+$K$1 -> Véhicules neufs | C44: Salaires autres | F44: =+SUM(START:END!F44) -> 8659.15 | I44: =+SUM(START:END!I44) -> 0 | L44: =+SUM(START:END!L44) -> 11085.06 | N44: =L44-F44 -> 2425.91 | Q44: =+SUM(START:END!Q44) -> 39850.16 | S44: =L44-Q44 -> -28765.1
A45: =+B45&C45 -> Véhicules neufsSalaires spécialistes | B45: =+$K$1 -> Véhicules neufs | C45: Salaires spécialistes | F45: =+SUM(START:END!F45) -> 0 | I45: =+SUM(START:END!I45) -> 0 | L45: =+SUM(START:END!L45) -> 0 | N45: =L45-F45 -> 0 | Q45: =+SUM(START:END!Q45) -> 0 | S45: =L45-Q45 -> 0
A46: =+B46&C46 -> Véhicules neufs[...] | B46: =+$K$1 -> Véhicules neufs | C46: [...] | F46: =+SUM(START:END!F46) -> 0 | I46: =+SUM(START:END!I46) -> 0 | L46: =+SUM(START:END!L46) -> 0 | N46: =L46-F46 -> 0 | Q46: =+SUM(START:END!Q46) -> 0 | S46: =L46-Q46 -> 0
A47: =+B47&C47 -> Véhicules neufs[...] | B47: =+$K$1 -> Véhicules neufs | C47: [...] | F47: =+SUM(START:END!F47) -> 0 | I47: =+SUM(START:END!I47) -> 0 | L47: =+SUM(START:END!L47) -> 0 | N47: =L47-F47 -> 0 | Q47: =+SUM(START:END!Q47) -> 0 | S47: =L47-Q47 -> 0
A48: =+B48&C48 -> Véhicules neufs[...] | B48: =+$K$1 -> Véhicules neufs | C48: [...] | F48: =+SUM(START:END!F48) -> 0 | I48: =+SUM(START:END!I48) -> 0 | L48: =+SUM(START:END!L48) -> 0 | N48: =L48-F48 -> 0 | Q48: =+SUM(START:END!Q48) -> 0 | S48: =L48-Q48 -> 0
A49: =+B49&C49 -> Véhicules neufsSalaires en absences | B49: =+$K$1 -> Véhicules neufs | C49: Salaires en absences | F49: =+SUM(START:END!F49) -> 37259.511 | I49: =+SUM(START:END!I49) -> 0 | L49: =+SUM(START:END!L49) -> 36530.25 | N49: =L49-F49 -> -729.26052 | Q49: =+SUM(START:END!Q49) -> 36604.96 | S49: =L49-Q49 -> -74.71
A50: =+B50&C50 -> Véhicules neufsDéduction à la source | B50: =+$K$1 -> Véhicules neufs | C50: Déduction à la source | F50: =+SUM(START:END!F50) -> 45302.312 | I50: =+SUM(START:END!I50) -> 0 | L50: =+SUM(START:END!L50) -> 46567.67 | N50: =L50-F50 -> 1265.3576 | Q50: =+SUM(START:END!Q50) -> 41184.46 | S50: =L50-Q50 -> 5383.21
A51: =+B51&C51 -> Véhicules neufsBénéfices marginaux | B51: =+$K$1 -> Véhicules neufs | C51: Bénéfices marginaux | F51: =+SUM(START:END!F51) -> 23340.539 | I51: =+SUM(START:END!I51) -> 0 | L51: =+SUM(START:END!L51) -> 22166.69 | N51: =L51-F51 -> -1173.8492 | Q51: =+SUM(START:END!Q51) -> 21410.25 | S51: =L51-Q51 -> 756.44
A52: =+B52&C52 -> Véhicules neufsCsst | B52: =+$K$1 -> Véhicules neufs | C52: Csst | F52: =+SUM(START:END!F52) -> 10176.606 | I52: =+SUM(START:END!I52) -> 0 | L52: =+SUM(START:END!L52) -> 8614.36 | N52: =L52-F52 -> -1562.2464 | Q52: =+SUM(START:END!Q52) -> 8386.98 | S52: =L52-Q52 -> 227.38
A53: =+B53&C53 -> Véhicules neufs[...] | B53: =+$K$1 -> Véhicules neufs | C53: [...] | F53: =+SUM(START:END!F53) -> 0 | I53: =+SUM(START:END!I53) -> 0 | L53: =+SUM(START:END!L53) -> 0 | N53: =L53-I53 -> 0 | Q53: =+SUM(START:END!Q53) -> 0 | S53: =L53-Q53 -> 0
A54: =+B54&C54 -> Véhicules neufsTOTAL PERSONNEL | B54: =+$K$1 -> Véhicules neufs | C54: TOTAL PERSONNEL | D54: % brut | E54: =F54/F$27 -> 0.24848939 | F54: =+SUM(F42:F53) -> 218755.24 | G54: % brut | H54: =I54/I$27 -> #DIV/0! | I54: =+SUM(I42:I53) -> 0 | J54: % brut | K54: =L54/L$27 -> 0.31023038 | L54: =+SUM(L42:L53) -> 192405.9 | N54: =+SUM(N42:N53) -> -26349.342 | O54: % brut | P54: =Q54/Q$27 -> 0.41137801 | Q54: =+SUM(Q42:Q53) -> 225311.37 | S54: =+SUM(S42:S53) -> -29857.09
A55: =+B55&C55 -> Véhicules neufsPublicité 2 | B55: =+$K$1 -> Véhicules neufs | C55: Publicité 2 | F55: =+SUM(START:END!F55) -> 0 | I55: =+SUM(START:END!I55) -> 0 | L55: =+SUM(START:END!L55) -> 0 | N55: =L55-F55 -> 0 | Q55: =+SUM(START:END!Q55) -> 0 | S55: =L55-Q55 -> 0
A56: =+B56&C56 -> Véhicules neufsService gratuit 2 | B56: =+$K$1 -> Véhicules neufs | C56: Service gratuit 2 | F56: =+SUM(START:END!F56) -> 0 | I56: =+SUM(START:END!I56) -> 0 | L56: =+SUM(START:END!L56) -> 0 | N56: =L56-F56 -> 0 | Q56: =+SUM(START:END!Q56) -> 0 | S56: =L56-Q56 -> 0
A57: =+B57&C57 -> Véhicules neufsFrais véhicules de cie | B57: =+$K$1 -> Véhicules neufs | C57: Frais véhicules de cie | F57: =+SUM(START:END!F57) -> 27600 | I57: =+SUM(START:END!I57) -> 0 | L57: =+SUM(START:END!L57) -> 26284.78 | N57: =L57-F57 -> -1315.22 | Q57: =+SUM(START:END!Q57) -> 19573.96 | S57: =L57-Q57 -> 6710.82
A58: =+B58&C58 -> Véhicules neufsInformatique | B58: =+$K$1 -> Véhicules neufs | C58: Informatique | F58: =+SUM(START:END!F58) -> 27119.086 | I58: =+SUM(START:END!I58) -> 0 | L58: =+SUM(START:END!L58) -> 22020.98 | N58: =L58-F58 -> -5098.1064 | Q58: =+SUM(START:END!Q58) -> 22876.67 | S58: =L58-Q58 -> -855.69
A59: =+B59&C59 -> Véhicules neufsFrais de déplacement | B59: =+$K$1 -> Véhicules neufs | C59: Frais de déplacement | F59: =+SUM(START:END!F59) -> 3315.6777 | I59: =+SUM(START:END!I59) -> 0 | L59: =+SUM(START:END!L59) -> 5300.42 | N59: =L59-F59 -> 1984.7423 | Q59: =+SUM(START:END!Q59) -> 4892.99 | S59: =L59-Q59 -> 407.43
A60: =+B60&C60 -> Véhicules neufsServices extérieurs | B60: =+$K$1 -> Véhicules neufs | C60: Services extérieurs | F60: =+SUM(START:END!F60) -> 20134.256 | I60: =+SUM(START:END!I60) -> 0 | L60: =+SUM(START:END!L60) -> 21333.34 | N60: =L60-F60 -> 1199.0841 | Q60: =+SUM(START:END!Q60) -> 18065.25 | S60: =L60-Q60 -> 3268.09
A61: =+B61&C61 -> Véhicules neufsFournitures autres | B61: =+$K$1 -> Véhicules neufs | C61: Fournitures autres | F61: =+SUM(START:END!F61) -> 375 | I61: =+SUM(START:END!I61) -> 0 | L61: =+SUM(START:END!L61) -> 58.06 | N61: =L61-F61 -> -316.94 | Q61: =+SUM(START:END!Q61) -> 0 | S61: =L61-Q61 -> 58.06
A62: =+B62&C62 -> Véhicules neufsUniformes | B62: =+$K$1 -> Véhicules neufs | C62: Uniformes | F62: =+SUM(START:END!F62) -> 250 | I62: =+SUM(START:END!I62) -> 0 | L62: =+SUM(START:END!L62) -> 0 | N62: =L62-F62 -> -250 | Q62: =+SUM(START:END!Q62) -> 0 | S62: =L62-Q62 -> 0
A63: =+B63&C63 -> Véhicules neufsPapeterie | B63: =+$K$1 -> Véhicules neufs | C63: Papeterie | F63: =+SUM(START:END!F63) -> 2270.8398 | I63: =+SUM(START:END!I63) -> 0 | L63: =+SUM(START:END!L63) -> 1654.51 | N63: =L63-F63 -> -616.32981 | Q63: =+SUM(START:END!Q63) -> 1925.96 | S63: =L63-Q63 -> -271.45
A64: =+B64&C64 -> Véhicules neufsTéléphone | B64: =+$K$1 -> Véhicules neufs | C64: Téléphone | F64: =+SUM(START:END!F64) -> 928.21046 | I64: =+SUM(START:END!I64) -> 0 | L64: =+SUM(START:END!L64) -> 985.98 | N64: =L64-F64 -> 57.769545 | Q64: =+SUM(START:END!Q64) -> 804.44 | S64: =L64-Q64 -> 181.54
A65: =+B65&C65 -> Véhicules neufsFrais postaux | B65: =+$K$1 -> Véhicules neufs | C65: Frais postaux | F65: =+SUM(START:END!F65) -> 339.38643 | I65: =+SUM(START:END!I65) -> 0 | L65: =+SUM(START:END!L65) -> 54.08 | N65: =L65-F65 -> -285.30643 | Q65: =+SUM(START:END!Q65) -> 326.53 | S65: =L65-Q65 -> -272.45
A66: =+B66&C66 -> Véhicules neufsDivers | B66: =+$K$1 -> Véhicules neufs | C66: Divers | F66: =+SUM(START:END!F66) -> 847.38781 | I66: =+SUM(START:END!I66) -> 0 | L66: =+SUM(START:END!L66) -> 431.03 | N66: =L66-F66 -> -416.35781 | Q66: =+SUM(START:END!Q66) -> 306.74 | S66: =L66-Q66 -> 124.29
... A68: =+B68&C68 -> Véhicules neufsFrais bancaires | B68: =+$K$1 -> Véhicules neufs | C68: Frais bancaires | F68: =+SUM(START:END!F68) -> 10089.888 | I68: =+SUM(START:END!I68) -> 0 | L68: =+SUM(START:END!L68) -> 12385.38 | N68: =L68-F68 -> 2295.4922 | Q68: =+SUM(START:END!Q68) -> 14309.5 | S68: =L68-Q68 -> -1924.12
A69: =+B69&C69 -> Véhicules neufs[...] | B69: =+$K$1 -> Véhicules neufs | C69: [...] | F69: =+SUM(START:END!F69) -> 0 | I69: =+SUM(START:END!I69) -> 0 | L69: =+SUM(START:END!L69) -> 0 | N69: =L69-I69 -> 0 | Q69: =+SUM(START:END!Q69) -> 0 | S69: =L69-Q69 -> 0
A70: =+B70&C70 -> Véhicules neufs[...] | B70: =+$K$1 -> Véhicules neufs | C70: [...] | F70: =+SUM(START:END!F70) -> 0 | I70: =+SUM(START:END!I70) -> 0 | L70: =+SUM(START:END!L70) -> 0 | N70: =L70-I70 -> 0 | Q70: =+SUM(START:END!Q70) -> 0 | S70: =L70-Q70 -> 0
A71: =+B71&C71 -> Véhicules neufs[...] | B71: =+$K$1 -> Véhicules neufs | C71: [...] | F71: =+SUM(START:END!F71) -> 0 | I71: =+SUM(START:END!I71) -> 0 | L71: =+SUM(START:END!L71) -> 0 | N71: =L71-I71 -> 0 | Q71: =+SUM(START:END!Q71) -> 0 | S71: =L71-Q71 -> 0
A72: =+B72&C72 -> Véhicules neufsTOTAL SEMI-FIXES | B72: =+$K$1 -> Véhicules neufs | C72: TOTAL SEMI-FIXES | D72: % brut | E72: =F72/F$27 -> 0.11241908 | F72: =+SUM(F55:F71) -> 98967.055 | G72: % brut | H72: =I72/I$27 -> #DIV/0! | I72: =+SUM(I55:I71) -> 0 | J72: % brut | K72: =L72/L$27 -> 0.15192025 | L72: =+SUM(L55:L71) -> 94221.44 | N72: =+SUM(N55:N71) -> -4745.6148 | O72: % brut | P72: =Q72/Q$27 -> 0.15892109 | Q72: =+SUM(Q55:Q71) -> 87040.94 | S72: =+SUM(S55:S71) -> 7180.5
A73: =+B73&C73 -> Véhicules neufs | B73: =+$K$1 -> Véhicules neufs
A74: =+B74&C74 -> Véhicules neufsTOTAL DES DÉPENSES | B74: =+$K$1 -> Véhicules neufs | C74: TOTAL DES DÉPENSES | D74: % brut | E74: =F74/F$27 -> 0.79554115 | F74: =F41+F54+F72 -> 700346.99 | G74: % brut | H74: =I74/I$27 -> #DIV/0! | I74: =I41+I54+I72 -> 0 | J74: % brut | K74: =L74/L$27 -> 1.0264761 | L74: =L41+L54+L72 -> 636623.85 | N74: =N41+N54+N72 -> -63723.142 | O74: % brut | P74: =Q74/Q$27 -> 0.97452357 | Q74: =Q41+Q54+Q72 -> 533745.69 | S74: =L74-Q74 -> 102878.16
A75: =+B75&C75 -> Véhicules neufsProgramme neuf 1 | B75: =+$K$1 -> Véhicules neufs | C75: Programme neuf 1 | F75: =+SUM(START:END!F75) -> 20000 | I75: =+SUM(START:END!I75) -> 0 | L75: =+SUM(START:END!L75) -> 20695 | N75: =L75-F75 -> 695 | Q75: =+SUM(START:END!Q75) -> 0
A76: =+B76&C76 -> Véhicules neufsProgramme neuf 2 | B76: =+$K$1 -> Véhicules neufs | C76: Programme neuf 2 | F76: =+SUM(START:END!F76) -> 0 | I76: =+SUM(START:END!I76) -> 0 | L76: =+SUM(START:END!L76) -> 0 | N76: =L76-F76 -> 0 | Q76: =+SUM(START:END!Q76) -> 0 | S76: =L76-Q76 -> 0
A77: =+B77&C77 -> Véhicules neufsProgramme neuf 3 | B77: =+$K$1 -> Véhicules neufs | C77: Programme neuf 3 | F77: =+SUM(START:END!F77) -> 0 | I77: =+SUM(START:END!I77) -> 0 | L77: =+SUM(START:END!L77) -> 0 | N77: =L77-F77 -> 0 | Q77: =+SUM(START:END!Q77) -> 0 | S77: =L77-Q77 -> 0
A78: =+B78&C78 -> Véhicules neufsHoldbacks | B78: =+$K$1 -> Véhicules neufs | C78: Holdbacks | F78: =+SUM(START:END!F78) -> 283999.03 | I78: =+SUM(START:END!I78) -> 0 | L78: =+SUM(START:END!L78) -> 260645.55 | N78: =L78-F78 -> -23353.478 | Q78: =+SUM(START:END!Q78) -> 169980.38 | S78: =L78-Q78 -> 90665.17
A79: =+B79&C79 -> Véhicules neufs[...] | B79: =+$K$1 -> Véhicules neufs | C79: [...] | F79: =+SUM(START:END!F79) -> 0 | I79: =+SUM(START:END!I79) -> 0 | L79: =+SUM(START:END!L79) -> 0 | N79: =L79-F79 -> 0 | Q79: =+SUM(START:END!Q79) -> 0 | S79: =L79-Q79 -> 0
A80: =+B80&C80 -> Véhicules neufs[...] | B80: =+$K$1 -> Véhicules neufs | C80: [...] | F80: =+SUM(START:END!F80) -> 0 | I80: =+SUM(START:END!I80) -> 0 | L80: =+SUM(START:END!L80) -> 0 | N80: =L80-F80 -> 0 | Q80: =+SUM(START:END!Q80) -> 0 | S80: =L80-Q80 -> 0
A81: =+B81&C81 -> Véhicules neufs[...] | B81: =+$K$1 -> Véhicules neufs | C81: [...] | F81: =+SUM(START:END!F81) -> 0 | I81: =+SUM(START:END!I81) -> 0 | L81: =+SUM(START:END!L81) -> 0 | N81: =L81-F81 -> 0 | Q81: =+SUM(START:END!Q81) -> 0 | S81: =L81-Q81 -> 0
A82: =+B82&C82 -> Véhicules neufsFrais administration | B82: =+$K$1 -> Véhicules neufs | C82: Frais administration | F82: =+SUM(START:END!F82) -> 96575.836 | I82: =+SUM(START:END!I82) -> 0 | L82: =+SUM(START:END!L82) -> 88156.5 | N82: =L82-F82 -> -8419.3362 | Q82: =+SUM(START:END!Q82) -> 62286 | S82: =L82-Q82 -> 25870.5
A83: =+B83&C83 -> Véhicules neufsAUTRES REVENUS | B83: =+$K$1 -> Véhicules neufs | C83: AUTRES REVENUS | F83: =+SUM(F75:F82) -> 400574.86 | I83: =+SUM(I75:I82) -> 0 | L83: =+SUM(L75:L82) -> 369497.05 | N83: =+SUM(N75:N82) -> -31077.814 | Q83: =+SUM(Q75:Q82) -> 232266.38 | S83: =+SUM(S75:S82) -> 116535.67
A84: =+B84&C84 -> Véhicules neufs | B84: =+$K$1 -> Véhicules neufs
A85: =+B85&C85 -> Véhicules neufsPROFIT DÉPARTEMENTAL | B85: =+$K$1 -> Véhicules neufs | C85: PROFIT DÉPARTEMENTAL | F85: =F27-F74+F83 -> 580568.25 | I85: =I27-I74+I83 -> 0 | L85: =L27-L74+L83 -> 353076.49 | N85: =N27-N74+N83 -> -189604.36 | Q85: =Q27-Q74+Q83 -> 246219.8 | S85: =S27-S41-S54-S72+S83 -> 83113.31
F86: =+F85-#REF!-#REF!-#REF! -> #REF! | L86: =+L85-#REF!-#REF!-#REF! -> #REF! | N86: =+N85-#REF!-#REF!-#REF! -> #REF! | Q86: =+Q85-#REF!-#REF!-#REF! -> #REF! | S86: =+S85-#REF!-#REF!-#REF! -> #REF!
C89: =C1 -> Conso | K89: Véhicules usagés | S89: =$S$1 -> Réalisé
D91: BUDGET ORIGINAL | G91: BUDGET RÉVISÉ | J91: RÉALISATION | M91: ÉCART réel / original | O91: ANNÉE PRÉCÉDENTE | R91: ÉCART réel / année précédente
D92: UNITE | E92: $P/UNITÉ | F92: $PROFITS | G92: UNITE | H92: $P/UNITÉ | I92: $PROFITS | J92: UNITE | K92: $P/UNITE | L92: $PROFITS | M92: UNITÉ | N92: $PROFITS | O92: UNITE | P92: $P/UNITE | Q92: $PROFITS | R92: UNITE | S92: $PROFITS
A93: =+B93&C93 -> Véhicules usagésVentes nettes | B93: Véhicules usagés | C93: Ventes nettes | F93: =+SUM(START:END!F93) -> 6174615.3 | I93: =+SUM(START:END!I93) -> 0 | L93: =+SUM(START:END!L93) -> 4212048.8 | Q93: =+SUM(START:END!Q93) -> 4271243.8
A94: =+B94&C94 -> Véhicules usagésCertifié | B94: Véhicules usagés | C94: Certifié | D94: =+SUM(START:END!D94) -> 113.919 | E94: =IF(D94=0,0,F94/D94) -> 1800 | F94: =+SUM(START:END!F94) -> 205054.2 | G94: =+SUM(START:END!G94) -> 0 | H94: =IF(G94=0,0,I94/G94) -> 0 | I94: =+SUM(START:END!I94) -> 0 | J94: =+SUM(START:END!J94) -> 91 | K94: =IF(J94=0,0,L94/J94) -> 620.13967 | L94: =+SUM(START:END!L94) -> 56432.71 | M94: =J94-D94 -> -22.919 | N94: =L94-F94 -> -148621.49 | O94: =+SUM(START:END!O94) -> 48 | P94: =IF(O94=0,0,Q94/O94) -> 2082.5087 | Q94: =+SUM(START:END!Q94) -> 99960.42 | R94: =J94-O94 -> 43 | S94: =L94-Q94 -> -43527.71
A95: =+B95&C95 -> Véhicules usagésNon Certifié | B95: Véhicules usagés | C95: Non Certifié | D95: =+SUM(START:END!D95) -> 6.4262 | E95: =IF(D95=0,0,F95/D95) -> 1800 | F95: =+SUM(START:END!F95) -> 11567.16 | G95: =+SUM(START:END!G95) -> 0 | H95: =IF(G95=0,0,I95/G95) -> 0 | I95: =+SUM(START:END!I95) -> 0 | J95: =+SUM(START:END!J95) -> 5 | K95: =IF(J95=0,0,L95/J95) -> 471.856 | L95: =+SUM(START:END!L95) -> 2359.28 | M95: =J95-D95 -> -1.4262 | N95: =L95-F95 -> -9207.88 | O95: =+SUM(START:END!O95) -> 22 | P95: =IF(O95=0,0,Q95/O95) -> 2295.1036 | Q95: =+SUM(START:END!Q95) -> 50492.28 | R95: =J95-O95 -> -17 | S95: =L95-Q95 -> -48133
A96: =+B96&C96 -> Véhicules usagésAutres marques | B96: Véhicules usagés | C96: Autres marques | D96: =+SUM(START:END!D96) -> 3.7973 | E96: =IF(D96=0,0,F96/D96) -> 1800 | F96: =+SUM(START:END!F96) -> 6835.14 | G96: =+SUM(START:END!G96) -> 0 | H96: =IF(G96=0,0,I96/G96) -> 0 | I96: =+SUM(START:END!I96) -> 0 | J96: =+SUM(START:END!J96) -> 0 | K96: =IF(J96=0,0,L96/J96) -> 0 | L96: =+SUM(START:END!L96) -> 0 | M96: =J96-D96 -> -3.7973 | N96: =L96-F96 -> -6835.14 | O96: =+SUM(START:END!O96) -> 0 | P96: =IF(O96=0,0,Q96/O96) -> 0 | Q96: =+SUM(START:END!Q96) -> 0 | R96: =J96-O96 -> 0 | S96: =L96-Q96 -> 0
A97: =+B97&C97 -> Véhicules usagésTotal Usagés | B97: Véhicules usagés | C97: Total Usagés | D97: =+D95+D94+D96 -> 124.1425 | E97: =IF(D97=0,0,F97/D97) -> 1800 | F97: =+F94+F95+F96 -> 223456.5 | G97: =+G95+G94+G96 -> 0 | H97: =IF(G97=0,0,I97/G97) -> 0 | I97: =+I94+I95+I96 -> 0 | J97: =+J95+J94+J96 -> 96 | K97: =IF(J97=0,0,L97/J97) -> 612.41656 | L97: =+L94+L95+L96 -> 58791.99 | M97: =+M95+M94+M96 -> -28.1425 | N97: =+N94+N95+N96 -> -164664.51 | O97: =+O95+O94+O96 -> 70 | P97: =IF(O97<=0,0,Q97/O97) -> 2149.3243 | Q97: =+Q94+Q95+Q96 -> 150452.7 | R97: =R94+R95+R96 -> 26 | S97: =S94+S95+S96 -> -91660.71
A98: =+B98&C98 -> Véhicules usagés | B98: Véhicules usagés | E98: =IF(D98=0,0,F98/D98) -> 0 | H98: =IF(G98=0,0,I98/G98) -> 0 | M98: =D97/D97 -> 1 | N98: =N97/F97 -> -0.73689738 | R98: =R97/O97 -> 0.37142857 | S98: =IF(Q97=0,0,(S97/Q97)) -> -0.60923274
A99: =+B99&C99 -> Véhicules usagésUS | B99: Véhicules usagés | C99: US | D99: =+SUM(START:END!D99) -> 0 | E99: =IF(D99=0,0,F99/D99) -> 0 | F99: =+SUM(START:END!F99) -> 0 | G99: =+SUM(START:END!G99) -> 0 | H99: =IF(G99=0,0,I99/G99) -> 0 | I99: =+SUM(START:END!I99) -> 0 | J99: =+SUM(START:END!J99) -> 0 | K99: =IF(J99=0,0,L99/J99) -> 0 | L99: =+SUM(START:END!L99) -> 0 | M99: =J99-D99 -> 0 | N99: =L99-F99 -> 0 | O99: =+SUM(START:END!O99) -> 0 | P99: =IF(O99=0,0,Q99/O99) -> 0 | Q99: =+SUM(START:END!Q99) -> 0
A100: =+B100&C100 -> Véhicules usagésVentes au Gros | B100: Véhicules usagés | C100: Ventes au Gros | D100: =+SUM(START:END!D100) -> 127.0635 | E100: =IF(D100=0,0,F100/D100) -> 400 | F100: =+SUM(START:END!F100) -> 50825.4 | G100: =+SUM(START:END!G100) -> 0 | H100: =IF(G100=0,0,I100/G100) -> 0 | I100: =+SUM(START:END!I100) -> 0 | J100: =+SUM(START:END!J100) -> 107 | K100: =IF(J100=0,0,L100/J100) -> -358.56888 | L100: =+SUM(START:END!L100) -> -38366.87 | M100: =J100-D100 -> -20.0635 | N100: =L100-F100 -> -89192.27 | O100: =+SUM(START:END!O100) -> 110 | P100: =IF(O100=0,0,Q100/O100) -> 620.26964 | Q100: =+SUM(START:END!Q100) -> 68229.66 | R100: =J100-O100 -> -3 | S100: =L100-Q100 -> -106596.53
A101: =+B101&C101 -> Véhicules usagés | B101: Véhicules usagés
A102: =+B102&C102 -> Véhicules usagésRev. Finances | B102: Véhicules usagés | C102: Rev. Finances | D102: =+SUM(START:END!D102) -> 0 | E102: =IF(D102=0,0,F102/D102) -> 0 | F102: =+SUM(START:END!F102) -> 86899.75 | G102: =+SUM(START:END!G102) -> 0 | H102: =IF(G102=0,0,I102/G102) -> 0 | I102: =+SUM(START:END!I102) -> 0 | J102: =+SUM(START:END!J102) -> 0 | K102: =IF(J102=0,0,L102/J102) -> 0 | L102: =+SUM(START:END!L102) -> 27863.97 | M102: =J102-G102 -> 0 | N102: =L102-F102 -> -59035.78 | O102: =+SUM(START:END!O102) -> 0 | P102: =IF(O102=0,0,Q102/O102) -> 0 | Q102: =+SUM(START:END!Q102) -> 58096.08 | R102: =J102-O102 -> 0 | S102: =L102-Q102 -> -30232.11
A103: =+B103&C103 -> Véhicules usagésRev. Protections | B103: Véhicules usagés | C103: Rev. Protections | D103: =+SUM(START:END!D103) -> 0 | E103: =IF(D103=0,0,F103/D103) -> 0 | F103: =+SUM(START:END!F103) -> 180006.62 | G103: =+SUM(START:END!G103) -> 0 | H103: =IF(G103=0,0,I103/G103) -> 0 | I103: =+SUM(START:END!I103) -> 0 | J103: =+SUM(START:END!J103) -> 0 | K103: =IF(J103=0,0,L103/J103) -> 0 | L103: =+SUM(START:END!L103) -> 146636.99 | M103: =J103-G103 -> 0 | N103: =L103-F103 -> -33369.635 | O103: =+SUM(START:END!O103) -> 0 | P103: =IF(O103=0,0,Q103/O103) -> 0 | Q103: =+SUM(START:END!Q103) -> 121288.61 | R103: =J103-O103 -> 0 | S103: =L103-Q103 -> 25348.38
A104: =+B104&C104 -> Véhicules usagésRev. Autres | B104: Véhicules usagés | C104: Rev. Autres | D104: =+SUM(START:END!D104) -> 0 | E104: =IF(D104=0,0,F104/D104) -> 0 | F104: =+SUM(START:END!F104) -> 6207.125 | G104: =+SUM(START:END!G104) -> 0 | H104: =IF(G104=0,0,I104/G104) -> 0 | I104: =+SUM(START:END!I104) -> 0 | J104: =+SUM(START:END!J104) -> 0 | K104: =IF(J104=0,0,L104/J104) -> 0 | L104: =+SUM(START:END!L104) -> 1973 | M104: =J104-G104 -> 0 | N104: =L104-F104 -> -4234.125 | O104: =+SUM(START:END!O104) -> 0 | P104: =IF(O104=0,0,Q104/O104) -> 0 | Q104: =+SUM(START:END!Q104) -> 2391.51 | R104: =J104-O104 -> 0 | S104: =L104-Q104 -> -418.51
...

Sheet START

Sheet Avril 2024
C1: Volks | K1: Véhicules neufs | S1: Réalisé, Avril 2024
D2: X | E2: O | F2: U | J2: NB | L2: $ | O2: X | P2: O | Q2: U | V2: *** NE PAS EFFACER / Pour An Précédente ***
D3: BUDGET ORIGINAL | J3: RÉALISATION | M3: ÉCART réel / Budget | O3: ANNÉE PRÉCÉDENTE | R3: ECART (réel/ Ann.Préc.) | V3: NEUF | W3: 0.45
D4: UNITE | E4: $P/UNITÉ | F4: $PROFITS | J4: UNITÉS | K4: $P/UNITE | L4: $PROFITS | M4: UNITÉS | N4: $PROFITS | O4: UNITE | P4: $P/UNITÉ | Q4: $PROFITS | R4: UNITÉS | S4: $PROFITS | V4: USAGE | W4: 0.1
A5: Véhicules neufsVentes nettes | B5: Véhicules neufs | C5: Ventes nettes | F5: 3243094.3 | L5: 3890022.9 | Q5: 1765867 | V5: SERVICE | W5: 0.225
A6: Véhicules neufsAutos détail | B6: Véhicules neufs | C6: Autos détail | D6: 12 | E6: 2198.1219 | F6: 26377.463 | J6: 18 | K6: 2168.0939 | L6: 39025.69 | M6: 6 | N6: 12648.227 | O6: 12 | P6: 2975.6025 | Q6: 35707.23 | R6: 6 | S6: 3318.46 | V6: CARROSSERIE | W6: 0.025
A7: Véhicules neufsCamions détail | B7: Véhicules neufs | C7: Camions détail | D7: 50 | E7: 2850.2587 | F7: 142512.93 | J7: 51 | K7: 2906.2869 | L7: 148220.63 | M7: 1 | N7: 5707.6952 | O7: 16 | P7: 2481.2725 | Q7: 39700.36 | R7: 35 | S7: 108520.27 | V7: PIECES | W7: 0.2
A8: Véhicules neufsSprinter | B8: Véhicules neufs | C8: Sprinter | D8: 0 | E8: 0 | F8: 0 | J8: 0 | K8: 0 | L8: 0 | M8: 0 | N8: 0 | O8: 0 | P8: 0 | Q8: 0 | R8: 0 | S8: 0 | W8: 1
A9: Véhicules neufsMoto détail | B9: Véhicules neufs | C9: Moto détail | D9: 0 | E9: 0 | F9: 0 | J9: 0 | K9: 0 | L9: 0 | M9: 0 | N9: 0 | O9: 0 | P9: 0 | Q9: 0 | R9: 0 | S9: 0
A10: Véhicules neufs[...] | B10: Véhicules neufs | C10: [...] | D10: 0 | E10: 0 | F10: 0 | J10: 0 | K10: 0 | L10: 0 | M10: 0 | N10: 0 | O10: 0 | P10: 0 | Q10: 0 | R10: 0 | S10: 0
A11: Véhicules neufs[...] | B11: Véhicules neufs | C11: [...] | D11: 0 | E11: 0 | F11: 0 | J11: 0 | K11: 0 | L11: 0 | M11: 0 | N11: 0 | O11: 0 | P11: 0 | Q11: 0 | R11: 0 | S11: 0
A12: Véhicules neufs[...] | B12: Véhicules neufs | C12: [...] | D12: 0 | E12: 0 | F12: 0 | J12: 0 | K12: 0 | L12: 0 | M12: 0 | N12: 0 | O12: 0 | P12: 0 | Q12: 0 | R12: 0 | S12: 0
A13: Véhicules neufsTotal Neufs | B13: Véhicules neufs | C13: Total Neufs | D13: 62 | E13: 2724.0387 | F13: 168890.4 | J13: 69 | K13: 2713.7148 | L13: 187246.32 | M13: 7 | N13: 18355.922 | O13: 28 | P13: 2693.1282 | Q13: 75407.59 | R13: 41 | S13: 111838.73
A14: Véhicules neufs | B14: Véhicules neufs | M14: 0.11290323 | N14: 0.10868541 | R14: 1.4642857 | S14: 1.483123 | AD14: 20 | AE14: 1000 | AF14: 20000
A15: Véhicules neufsEx-Démos et courtoisies | B15: Véhicules neufs | C15: Ex-Démos et courtoisies | D15: 5 | E15: 2484.4192 | F15: 12422.096 | J15: 4 | K15: 2264.375 | L15: 9057.5 | M15: -1 | N15: -3364.5958 | O15: 6 | P15: 1717.8083 | Q15: 10306.85 | R15: -2 | S15: -1249.35 | AD15: 25 | AE15: 800 | AF15: 20000
A16: Véhicules neufs | B16: Véhicules neufs
A17: Véhicules neufsFlottes | B17: Véhicules neufs | C17: Flottes | D17: 4.5 | E17: 2664.4641 | F17: 11990.088 | J17: 0 | K17: 0 | L17: 0 | M17: -4.5 | N17: -11990.088 | O17: 3 | P17: 3228.9067 | Q17: 9686.72 | R17: -3 | S17: -9686.72
A18: Véhicules neufs | B18: Véhicules neufs
A19: Véhicules neufsRachat bail | B19: Véhicules neufs | C19: Rachat bail | D19: 0 | E19: 0 | F19: 8500 | L19: 6030.37 | N19: -2469.63 | Q19: 7229.27 | R19: 0 | S19: -1198.9
A20: Véhicules neufs | B20: Véhicules neufs
A21: Véhicules neufsRev. Finances | B21: Véhicules neufs | C21: Rev. Finances | D21: 0 | E21: 0 | F21: 13400 | K21: 0 | L21: 0 | N21: -13400 | Q21: 2434.63 | R21: 0 | S21: -2434.63
A22: Véhicules neufsRev. Protections | B22: Véhicules neufs | C22: Rev. Protections | D22: 0 | E22: 0 | F22: 72360 | K22: 765.92219 | L22: 55912.32 | N22: -16447.68 | Q22: 31050.48 | R22: -765.92219 | S22: 24861.84
A23: Véhicules neufsRev. Autres | B23: Véhicules neufs | C23: Rev. Autres | D23: 0 | E23: 0 | F23: 1340 | K23: 18.60589 | L23: 1358.23 | N23: 18.23 | Q23: 0 | R23: -18.60589 | S23: 1358.23
A24: Véhicules neufsTotal F&I | B24: Véhicules neufs | C24: Total F&I | D24: 67 | E24: 1300 | F24: 87100 | J24: 73 | K24: 784.52808 | L24: 57270.55 | M24: 6 | N24: -29829.45 | O24: 34 | P24: 984.85618 | Q24: 33485.11 | S24: 23785.44
A25: Véhicules neufs | B25: Véhicules neufs | N25: -0.34247359 | S25: 0.71032886
A26: Véhicules neufs | B26: Véhicules neufs
A27: Véhicules neufsTotal Dépt. Neufs | B27: Véhicules neufs | C27: Total Dépt. Neufs | D27: 71.5 | E27: 4040.5956 | F27: 288902.58 | J27: 73 | K27: 3556.2293 | L27: 259604.74 | M27: 1.5 | N27: -29297.842 | O27: 37 | P27: 3678.7984 | Q27: 136115.54 | R27: 36 | S27: 123489.2
A28: Véhicules neufs | B28: Véhicules neufs | L28: 0.8985892 | M28: 0.020979021 | N28: -0.1014108 | R28: 0.97297297 | S28: 0.90723807
A29: Véhicules neufs | B29: Véhicules neufs
A30: Véhicules neufsDEPENSES | B30: Véhicules neufs | C30: DEPENSES
A31: Véhicules neufsComm. vendeurs | B31: Véhicules neufs | C31: Comm. vendeurs | D31: 0.34 | E31: 920.09325 | F31: 61646.248 | J31: 0.24820205 | K31: 667.43849 | L31: 48723.01 | N31: -12923.238 | O31: 0.38883657 | P31: 1091.0429 | Q31: 37095.46 | S31: 11627.55
A32: Véhicules neufsComm. F&I | B32: Véhicules neufs | C32: Comm. F&I | D32: 0.3 | E32: 390 | F32: 26130 | J32: 0.29711868 | K32: 233.09795 | L32: 17016.15 | N32: -9113.85 | O32: 0.2997816 | P32: 295.24176 | Q32: 10038.22 | S32: 6977.93
A33: Véhicules neufsFrais de livraison | B33: Véhicules neufs | C33: Frais de livraison | E33: 115 | F33: 7705 | K33: 51.42137 | L33: 3753.76 | N33: -3951.24 | P33: 99.448824 | Q33: 3381.26 | S33: 372.5
A34: Véhicules neufsService gratuit 1 | B34: Véhicules neufs | C34: Service gratuit 1 | E34: 3 | F34: 201 | K34: 1.5160274 | L34: 110.67 | N34: -90.33 | P34: 2.3529412 | Q34: 80 | S34: 30.67
A35: Véhicules neufsEntretien stock | B35: Véhicules neufs | C35: Entretien stock | E35: 85.05 | F35: 5698.35 | K35: 164.94 | L35: 12040.62 | N35: 6342.27 | P35: 88.82 | Q35: 3019.88 | S35: 9020.74
A36: Véhicules neufsPublicité 1 | B36: Véhicules neufs | C36: Publicité 1 | E36: 112.47761 | F36: 7536 | K36: 131.05397 | L36: 9566.94 | N36: 2030.94 | P36: 159.71529 | Q36: 5430.32 | S36: 4136.62
A37: Véhicules neufsIntérêt de gros | B37: Véhicules neufs | C37: Intérêt de gros | E37: 318.30489 | F37: 21326.428 | K37: 474.72863 | L37: 34655.19 | N37: 13328.762 | P37: 54.914412 | Q37: 1867.09 | S37: 32788.1
A38: Véhicules neufs[...] | B38: Véhicules neufs | C38: [...] | E38: 0 | F38: 0 | K38: 0 | L38: 0 | N38: 0 | P38: 0 | Q38: 0 | S38: 0
A39: Véhicules neufs[...] | B39: Véhicules neufs | C39: [...] | E39: 0 | F39: 0 | K39: 0 | L39: 0 | N39: 0 | P39: 0 | Q39: 0 | S39: 0
A40: Véhicules neufs[...] | B40: Véhicules neufs | C40: [...] | E40: 0 | F40: 0 | K40: 0 | L40: 0 | N40: 0 | P40: 0 | Q40: 0 | S40: 0
A41: Véhicules neufsTOTAL VARIABLES | B41: Véhicules neufs | C41: TOTAL VARIABLES | D41: % brut | E41: 0.45081987 | F41: 130243.03 | J41: % brut | K41: 0.48483837 | L41: 125866.34 | N41: -4376.6858 | O41: % brut | P41: 0.44750386 | Q41: 60912.23 | S41: 64954.11
A42: Véhicules neufsSalaires cadres | B42: Véhicules neufs | C42: Salaires cadres | F42: 18197.117 | L42: 13149.05 | N42: -5048.0667 | P42: 0.097681426 | Q42: 13295.96 | S42: -146.91
A43: Véhicules neufsSalaires commis | B43: Véhicules neufs | C43: Salaires commis | F43: 11267.511 | L43: 9365.85 | N43: -1901.6611 | Q43: 10544.06 | S43: -1178.21
A44: Véhicules neufsSalaires autres | B44: Véhicules neufs | C44: Salaires autres | F44: 2664.3538 | L44: 4575.36 | N44: 1911.0062 | Q44: 12250.19 | S44: -7674.83
A45: Véhicules neufsSalaires spécialistes | B45: Véhicules neufs | C45: Salaires spécialistes | F45: 0 | L45: 0 | N45: 0 | Q45: 0 | S45: 0
A46: Véhicules neufs[...] | B46: Véhicules neufs | C46: [...] | F46: 0 | L46: 0 | N46: 0 | Q46: 0 | S46: 0
A47: Véhicules neufs[...] | B47: Véhicules neufs | C47: [...] | F47: 0 | L47: 0 | N47: 0 | Q47: 0 | S47: 0
A48: Véhicules neufs[...] | B48: Véhicules neufs | C48: [...] | F48: 0 | L48: 0 | N48: 0 | Q48: 0 | S48: 0
A49: Véhicules neufsSalaires en absences | B49: Véhicules neufs | C49: Salaires en absences | F49: 12428.152 | L49: 11763.15 | N49: -665.00195 | Q49: 11060.27 | S49: 702.88
A50: Véhicules neufsDéduction à la source | B50: Véhicules neufs | C50: Déduction à la source | F50: 15110.881 | L50: 18598.07 | N50: 3487.1892 | Q50: 16153.21 | S50: 2444.86
A51: Véhicules neufsBénéfices marginaux | B51: Véhicules neufs | C51: Bénéfices marginaux | F51: 7785.3886 | L51: 7275.41 | N51: -509.97858 | Q51: 9403.86 | S51: -2128.45
A52: Véhicules neufsCsst | B52: Véhicules neufs | C52: Csst | F52: 3394.4732 | L52: 3705.07 | N52: 310.59678 | Q52: 2775.98 | S52: 929.09
A53: Véhicules neufs[...] | B53: Véhicules neufs | C53: [...] | D53: #N/A | F53: 0 | L53: 0 | N53: 0 | Q53: 0 | S53: 0
A54: Véhicules neufsTOTAL PERSONNEL | B54: Véhicules neufs | C54: TOTAL PERSONNEL | D54: % brut | E54: 0.24523102 | F54: 70847.876 | J54: % brut | K54: 0.26360058 | L54: 68431.96 | N54: -2415.9161 | O54: % brut | P54: 0.55455483 | Q54: 75483.53 | S54: -7051.57
A55: Véhicules neufsPublicité 2 | B55: Véhicules neufs | C55: Publicité 2 | F55: 0 | L55: 0 | N55: 0 | Q55: 0 | S55: 0
A56: Véhicules neufsService gratuit 2 | B56: Véhicules neufs | C56: Service gratuit 2 | F56: 0 | L56: 0 | N56: 0 | Q56: 0 | S56: 0
A57: Véhicules neufsFrais véhicules de cie | B57: Véhicules neufs | C57: Frais véhicules de cie | F57: 9200 | L57: 11626.31 | N57: 2426.31 | Q57: 6050.54 | S57: 5575.77
A58: Véhicules neufsInformatique | B58: Véhicules neufs | C58: Informatique | F58: 9039.6955 | L58: 7516.3 | N58: -1523.3955 | Q58: 6422.17 | S58: 1094.13
A59: Véhicules neufsFrais de déplacement | B59: Véhicules neufs | C59: Frais de déplacement | F59: 1105.2259 | L59: 2705.19 | N59: 1599.9641 | Q59: 925.52 | S59: 1779.67
A60: Véhicules neufsServices extérieurs | B60: Véhicules neufs | C60: Services extérieurs | F60: 6711.4186 | L60: 6746.26 | N60: 34.841358 | Q60: 5703.27 | S60: 1042.99
A61: Véhicules neufsFournitures autres | B61: Véhicules neufs | C61: Fournitures autres | F61: 125 | L61: 36.28 | N61: -88.72 | Q61: 0 | S61: 36.28
A62: Véhicules neufsUniformes | B62: Véhicules neufs | C62: Uniformes | F62: 83.333333 | L62: 0 | N62: -83.333333 | Q62: 0 | S62: 0
A63: Véhicules neufsPapeterie | B63: Véhicules neufs | C63: Papeterie | F63: 756.9466 | L63: 381.04 | N63: -375.9066 | Q63: 783.41 | S63: -402.37
A64: Véhicules neufsTéléphone | B64: Véhicules neufs | C64: Téléphone | F64: 309.40349 | L64: 318.9 | N64: 9.4965149 | Q64: 233.07 | S64: 85.83
A65: Véhicules neufsFrais postaux | B65: Véhicules neufs | C65: Frais postaux | F65: 113.12881 | L65: 10.56 | N65: -102.56881 | Q65: 129.09 | S65: -118.53
A66: Véhicules neufsDivers | B66: Véhicules neufs | C66: Divers | F66: 282.4626 | L66: 201.95 | N66: -80.512603 | Q66: 116.88 | S66: 85.07
... A68: Véhicules neufsFrais bancaires | B68: Véhicules neufs | C68: Frais bancaires | F68: 3363.2959 | L68: 4277.07 | N68: 913.77407 | Q68: 3025.62 | S68: 1251.45
A69: Véhicules neufs[...] | B69: Véhicules neufs | C69: [...] | F69: 0 | N69: 0 | Q69: 0 | S69: 0
A70: Véhicules neufs[...] | B70: Véhicules neufs | C70: [...] | F70: 0 | L70: 0 | N70: 0 | Q70: 0 | S70: 0
A71: Véhicules neufs[...] | B71: Véhicules neufs | C71: [...] | F71: 0 | L71: 0 | N71: 0 | Q71: 0 | S71: 0
A72: Véhicules neufsTOTAL SEMI-FIXES | B72: Véhicules neufs | C72: TOTAL SEMI-FIXES | D72: % brut | E72: 0.11418734 | F72: 32989.018 | J72: % brut | K72: 0.13469404 | L72: 34967.21 | N72: 1978.1917 | O72: % brut | P72: 0.1915804 | Q72: 26077.07 | S72: 8890.14
A73: Véhicules neufs | B73: Véhicules neufs
A74: Véhicules neufsTOTAL DES DÉPENSES | B74: Véhicules neufs | C74: TOTAL DES DÉPENSES | D74: % brut | E74: 0.81023824 | F74: 234079.92 | J74: % brut | K74: 0.88313299 | L74: 229265.51 | N74: -4814.4101 | O74: % brut | P74: 1.1936391 | Q74: 162472.83 | S74: 66792.68
A75: Véhicules neufsProgramme neuf 1 | B75: Véhicules neufs | C75: Programme neuf 1 | F75: 0 | L75: 695 | N75: 695 | Q75: 0
A76: Véhicules neufsProgramme neuf 2 | B76: Véhicules neufs | C76: Programme neuf 2 | F76: 0 | L76: 0 | N76: 0 | Q76: 0 | S76: 0
A77: Véhicules neufsProgramme neuf 3 | B77: Véhicules neufs | C77: Programme neuf 3 | F77: 0 | L77: 0 | N77: 0 | Q77: 0 | S77: 0
A78: Véhicules neufsHoldbacks | B78: Véhicules neufs | C78: Holdbacks | E78: 1304.7121 | F78: 93286.912 | K78: 1453.1349 | L78: 106078.85 | N78: 12791.938 | Q78: 39086.08 | S78: 66992.77
A79: Véhicules neufs[...] | B79: Véhicules neufs | C79: [...] | F79: 0 | L79: 0 | N79: 0 | Q79: 0 | S79: 0
A80: Véhicules neufs[...] | B80: Véhicules neufs | C80: [...] | F80: 0 | L80: 0 | N80: 0 | Q80: 0 | S80: 0
A81: Véhicules neufs[...] | B81: Véhicules neufs | C81: [...] | F81: 0 | L81: 0 | N81: 0 | Q81: 0 | S81: 0
A82: Véhicules neufsFrais administration | B82: Véhicules neufs | C82: Frais administration | D82: 0.95 | E82: 474.05 | F82: 31761.35 | J82: 0.98932111 | K82: 493.67123 | L82: 36038 | N82: 4276.65 | Q82: 12599 | S82: 23439
A83: Véhicules neufsAUTRES REVENUS | B83: Véhicules neufs | C83: AUTRES REVENUS | F83: 125048.26 | L83: 142811.85 | N83: 17763.588 | Q83: 51685.08 | S83: 90431.77
A84: Véhicules neufs | B84: Véhicules neufs
A85: Véhicules neufsPROFIT DÉPARTEMENTAL | B85: Véhicules neufs | C85: PROFIT DÉPARTEMENTAL | F85: 179870.92 | L85: 173151.08 | N85: -6719.8439 | P85: 0.014342977 | Q85: 25327.79 | S85: 147128.29
C89: Volks | K89: Véhicules usagés | S89: Réalisé, Avril 2024
D91: BUDGET ORIGINAL | J91: RÉALISATION | M91: ÉCART réel / Budget | O91: ANNÉE PRÉCÉDENTE | R91: ECART (réel/ Ann.Préc.)
D92: UNITE | E92: $P/UNITÉ | F92: $PROFITS | J92: UNITÉS | K92: $P/UNITE | L92: $PROFITS | M92: UNITÉS | N92: $PROFITS | O92: UNITE | P92: $P/UNITÉ | Q92: $PROFITS | R92: UNITÉS | S92: $PROFITS
A93: Véhicules usagésVentes nettes | B93: Véhicules usagés | C93: Ventes nettes | F93: 2101187.1 | L93: 1101235.5 | Q93: 738971.18
A94: Véhicules usagésCertifié | B94: Véhicules usagés | C94: Certifié | D94: 38.766 | E94: 1800 | F94: 69778.8 | J94: 22 | K94: 1680.7486 | L94: 36976.47 | M94: -16.766 | N94: -32802.33 | O94: 15 | P94: 1983.744 | Q94: 29756.16 | R94: 7 | S94: 7220.31
A95: Véhicules usagésNon Certifié | B95: Véhicules usagés | C95: Non Certifié | D95: 2.1868 | E95: 1800 | F95: 3936.24 | J95: 1 | K95: 1000 | L95: 1000 | M95: -1.1868 | N95: -2936.24 | O95: 5 | P95: 2587.164 | Q95: 12935.82 | R95: -4 | S95: -11935.82
A96: Véhicules usagésAutres Marques | B96: Véhicules usagés | C96: Autres Marques | D96: 1.2922 | E96: 1800 | F96: 2325.96 | J96: 0 | K96: 0 | L96: 0 | M96: -1.2922 | N96: -2325.96 | O96: 0 | P96: 0 | Q96: 0 | R96: 0 | S96: 0
A97: Véhicules usagésTotal Usagés | B97: Véhicules usagés | C97: Total Usagés | D97: 42.245 | E97: 1800 | F97: 76041 | J97: 23 | K97: 1651.1509 | L97: 37976.47 | M97: -19.245 | N97: -38064.53 | O97: 20 | P97: 2134.599 | Q97: 42691.98 | R97: 3 | S97: -4715.51
A98: Véhicules usagés | B98: Véhicules usagés | E98: 0 | M98: -0.45555687 | N98: -0.50057903 | P98: 0 | R98: 0.15 | S98: -0.11045424
A99: Véhicules usagés | B99: Véhicules usagés | D99: 0 | E99: 0 | F99: 0
A100: Véhicules usagésVentes au Gros | B100: Véhicules usagés | C100: Ventes au Gros | D100: 43.239 | E100: 400 | F100: 17295.6 | J100: 31 | K100: -367.3229 | L100: -11387.01 | M100: -12.239 | N100: -28682.61 | O100: 10 | P100: 1818 | Q100: 18180 | R100: 21 | S100: -29567.01
A101: Véhicules usagés | B101: Véhicules usagés
A102: Véhicules usagésRev. Finances | B102: Véhicules usagés | C102: Rev. Finances | D102: 0 | E102: 0 | F102: 29571.5 | K102: 360.09913 | L102: 8282.28 | N102: -21289.22 | Q102: 18972.05 | R102: -360.09913 | S102: -10689.77
A103: Véhicules usagésRev. Protections | B103: Véhicules usagés | C103: Rev. Protections | D103: 0 | E103: 0 | F103: 61255.25 | K103: 1173.4048 | L103: 26988.31 | N103: -34266.94 | Q103: 40333.22 | R103: -1173.4048 | S103: -13344.91
A104: Véhicules usagésRev. Autres | B104: Véhicules usagés | C104: Rev. Autres | D104: 0 | E104: 0 | F104: 2112.25 | K104: 28.495217 | L104: 655.39 | N104: -1456.86 | Q104: 0 | R104: -28.495217 | S104: 655.39
A105: Véhicules usagésTotal F&I | B105: Véhicules usagés | C105: Total F&I | D105: 42.245 | E105: 2200 | F105: 92939 | J105: 23 | K105: 1561.9991 | L105: 35925.98 | M105: -19.245 | N105: -57013.02 | O105: 20 | P105: 2965.2635 | Q105: 59305.27 | S105: -23379.29
...

Sheet Mai 2024
C1: Volks | K1: Véhicules neufs | S1: Réalisé, Mai 2024
D2: X | E2: O | F2: U | J2: NB | L2: $ | O2: X | P2: O | Q2: U | V2: *** NE PAS EFFACER / Pour An Précédente ***
D3: BUDGET ORIGINAL | J3: RÉALISATION | M3: ÉCART réel / Budget | O3: ANNÉE PRÉCÉDENTE | R3: ECART (réel/ Ann.Préc.) | V3: NEUF | W3: 0.45
D4: UNITE | E4: $P/UNITÉ | F4: $PROFITS | J4: UNITÉS | K4: $P/UNITE | L4: $PROFITS | M4: UNITÉS | N4: $PROFITS | O4: UNITE | P4: $P/UNITÉ | Q4: $PROFITS | R4: UNITÉS | S4: $PROFITS | V4: USAGE | W4: 0.1
A5: Véhicules neufsVentes nettes | B5: Véhicules neufs | C5: Ventes nettes | F5: 3729071 | L5: 3906259.8 | Q5: 2808157.7 | V5: SERVICE | W5: 0.225
A6: Véhicules neufsAutos détail | B6: Véhicules neufs | C6: Autos détail | D6: 14 | E6: 2166.7202 | F6: 30334.083 | J6: 18 | K6: 1997.7756 | L6: 35959.96 | M6: 4 | N6: 5625.8774 | O6: 12 | P6: 2048.03 | Q6: 24576.36 | R6: 6 | S6: 11383.6 | V6: CARROSSERIE | W6: 0.025
A7: Véhicules neufsCamions détail | B7: Véhicules neufs | C7: Camions détail | D7: 57.04 | E7: 2873.2447 | F7: 163889.88 | J7: 51 | K7: 2441.8604 | L7: 124534.88 | M7: -6.04 | N7: -39354.995 | O7: 34 | P7: 2504.1768 | Q7: 85142.01 | R7: 17 | S7: 39392.87 | V7: PIECES | W7: 0.2
A8: Véhicules neufsSprinter | B8: Véhicules neufs | C8: Sprinter | D8: 0 | E8: 0 | F8: 0 | J8: 0 | K8: 0 | L8: 0 | M8: 0 | N8: 0 | O8: 0 | P8: 0 | Q8: 0 | R8: 0 | S8: 0 | W8: 1
A9: Véhicules neufsMoto détail | B9: Véhicules neufs | C9: Moto détail | D9: 0 | E9: 0 | F9: 0 | J9: 0 | K9: 0 | L9: 0 | M9: 0 | N9: 0 | O9: 0 | P9: 0 | Q9: 0 | R9: 0 | S9: 0
A10: Véhicules neufs[...] | B10: Véhicules neufs | C10: [...] | D10: 0 | E10: 0 | F10: 0 | J10: 0 | K10: 0 | L10: 0 | M10: 0 | N10: 0 | O10: 0 | P10: 0 | Q10: 0 | R10: 0 | S10: 0
A11: Véhicules neufs[...] | B11: Véhicules neufs | C11: [...] | D11: 0 | E11: 0 | F11: 0 | J11: 0 | K11: 0 | L11: 0 | M11: 0 | N11: 0 | O11: 0 | P11: 0 | Q11: 0 | R11: 0 | S11: 0
A12: Véhicules neufs[...] | B12: Véhicules neufs | C12: [...] | D12: 0 | E12: 0 | F12: 0 | J12: 0 | K12: 0 | L12: 0 | M12: 0 | N12: 0 | O12: 0 | P12: 0 | Q12: 0 | R12: 0 | S12: 0
A13: Véhicules neufsTotal Neufs | B13: Véhicules neufs | C13: Total Neufs | D13: 71.04 | E13: 2734.0084 | F13: 194223.96 | J13: 69 | K13: 2326.0122 | L13: 160494.84 | M13: -2.04 | N13: -33729.118 | O13: 46 | P13: 2385.182 | Q13: 109718.37 | R13: 23 | S13: 50776.47
A14: Véhicules neufs | B14: Véhicules neufs | M14: -0.028716216 | N14: -0.17366095 | R14: 0.5 | S14: 0.46278914 | AD14: 20 | AE14: 1000 | AF14: 20000
A15: Véhicules neufsEx-Démos et courtoisies | B15: Véhicules neufs | C15: Ex-Démos et courtoisies | D15: 5.635 | E15: 2535.1216 | F15: 14285.41 | J15: 5 | K15: 1165.582 | L15: 5827.91 | M15: -0.635 | N15: -8457.5001 | O15: 7 | P15: 2567.5443 | Q15: 17972.81 | R15: -2 | S15: -12144.9 | AD15: 25 | AE15: 800 | AF15: 20000
A16: Véhicules neufs | B16: Véhicules neufs
A17: Véhicules neufsFlottes | B17: Véhicules neufs | C17: Flottes | D17: 5.175 | E17: 2664.4641 | F17: 13788.602 | J17: 0 | K17: 0 | L17: 0 | M17: -5.175 | N17: -13788.602 | O17: 3 | P17: 1222.9133 | Q17: 3668.74 | R17: -3 | S17: -3668.74
A18: Véhicules neufs | B18: Véhicules neufs
A19: Véhicules neufsRachat bail | B19: Véhicules neufs | C19: Rachat bail | D19: 0 | E19: 0 | F19: 9775 | L19: 9930 | N19: 155 | Q19: 12671.61 | R19: 0 | S19: -2741.61
A20: Véhicules neufs | B20: Véhicules neufs
A21: Véhicules neufsRev. Finances | B21: Véhicules neufs | C21: Rev. Finances | D21: 0 | E21: 0 | F21: 15335 | K21: 10.810811 | L21: 800 | N21: -14535 | Q21: 7236.22 | R21: -10.810811 | S21: -6436.22
A22: Véhicules neufsRev. Protections | B22: Véhicules neufs | C22: Rev. Protections | D22: 0 | E22: 0 | F22: 82809 | K22: 791.51257 | L22: 58571.93 | N22: -24237.07 | Q22: 53155.27 | R22: -791.51257 | S22: 5416.66
A23: Véhicules neufsRev. Autres | B23: Véhicules neufs | C23: Rev. Autres | D23: 0 | E23: 0 | F23: 1533.5 | K23: 0 | L23: 0 | N23: -1533.5 | Q23: 1745.17 | R23: 0 | S23: -1745.17
A24: Véhicules neufsTotal F&I | B24: Véhicules neufs | C24: Total F&I | D24: 76.675 | E24: 1300 | F24: 99677.5 | J24: 74 | K24: 802.32338 | L24: 59371.93 | M24: -2.675 | N24: -40305.57 | O24: 53 | P24: 1172.3898 | Q24: 62136.66 | S24: -2764.73
A25: Véhicules neufs | B25: Véhicules neufs | N25: -0.40435976 | S25: -0.044494345
A26: Véhicules neufs | B26: Véhicules neufs
A27: Véhicules neufsTotal Dépt. Neufs | B27: Véhicules neufs | C27: Total Dépt. Neufs | D27: 81.85 | E27: 4053.1517 | F27: 331750.47 | J27: 74 | K27: 3184.1173 | L27: 235624.68 | M27: -7.85 | N27: -96125.789 | O27: 56 | P27: 3681.5748 | Q27: 206168.19 | R27: 18 | S27: 29456.49
A28: Véhicules neufs | B28: Véhicules neufs | L28: 0.71024671 | M28: -0.095907147 | N28: -0.28975329 | R28: 0.32142857 | S28: 0.14287602
A29: Véhicules neufs | B29: Véhicules neufs
A30: Véhicules neufsDEPENSES | B30: Véhicules neufs | C30: DEPENSES
A31: Véhicules neufsComm. vendeurs | B31: Véhicules neufs | C31: Comm. vendeurs | D31: 0.34 | E31: 924.59322 | F31: 70893.185 | J31: 0.21053999 | K31: 473.21068 | L31: 35017.59 | N31: -35875.595 | O31: 0.3181647 | P31: 788.56774 | Q31: 41794.09 | S31: -6776.5
A32: Véhicules neufsComm. F&I | B32: Véhicules neufs | C32: Comm. F&I | D32: 0.3 | E32: 390 | F32: 29903.25 | J32: 0.29999833 | K32: 240.69568 | L32: 17811.48 | N32: -12091.77 | O32: 0.29997187 | P32: 351.68396 | Q32: 18639.25 | S32: -827.77
A33: Véhicules neufsFrais de livraison | B33: Véhicules neufs | C33: Frais de livraison | E33: 115 | F33: 8817.625 | K33: 153.52486 | L33: 11360.84 | N33: 2543.215 | P33: 112.82151 | Q33: 5979.54 | S33: 5381.3
A34: Véhicules neufsService gratuit 1 | B34: Véhicules neufs | C34: Service gratuit 1 | E34: 3 | F34: 230.025 | K34: 13.206486 | L34: 977.28 | N34: 747.255 | P34: 0 | Q34: 0 | S34: 977.28
A35: Véhicules neufsEntretien stock | B35: Véhicules neufs | C35: Entretien stock | E35: 85.05 | F35: 6521.2087 | K35: 132.78284 | L35: 9825.93 | N35: 3304.7213 | P35: 66.649057 | Q35: 3532.4 | S35: 6293.53
A36: Véhicules neufsPublicité 1 | B36: Véhicules neufs | C36: Publicité 1 | E36: 26.977502 | F36: 2068.5 | K36: 164.58405 | L36: 12179.22 | N36: 10110.72 | P36: 56.458679 | Q36: 2992.31 | S36: 9186.91 | U36: PPM VENTE PRIVEE - 5K
A37: Véhicules neufsIntérêt de gros | B37: Véhicules neufs | C37: Intérêt de gros | E37: 234.37935 | F37: 17971.036 | K37: 644.70649 | L37: 47708.28 | N37: 29737.244 | P37: 110.78396 | Q37: 5871.55 | S37: 41836.73
A38: Véhicules neufs[...] | B38: Véhicules neufs | C38: [...] | E38: 0 | F38: 0 | K38: 0 | L38: 0 | N38: 0 | P38: 0 | Q38: 0 | S38: 0
A39: Véhicules neufs[...] | B39: Véhicules neufs | C39: [...] | E39: 0 | F39: 0 | K39: 0 | L39: 0 | N39: 0 | P39: 0 | Q39: 0 | S39: 0
A40: Véhicules neufs[...] | B40: Véhicules neufs | C40: [...] | E40: 0 | F40: 0 | K40: 0 | L40: 0 | N40: 0 | P40: 0 | Q40: 0 | S40: 0
A41: Véhicules neufsTOTAL VARIABLES | B41: Véhicules neufs | C41: TOTAL VARIABLES | D41: % brut | E41: 0.41116695 | F41: 136404.83 | J41: % brut | K41: 0.57243842 | L41: 134880.62 | N41: -1524.2101 | O41: % brut | P41: 0.38225655 | Q41: 78809.14 | S41: 56071.48
A42: Véhicules neufsSalaires cadres | B42: Véhicules neufs | C42: Salaires cadres | F42: 21133.479 | L42: 11905.98 | N42: -9227.4992 | P42: 0.06570519 | Q42: 13546.32 | S42: -1640.34
A43: Véhicules neufsSalaires commis | B43: Véhicules neufs | C43: Salaires commis | F43: 13954.389 | L43: 9609.39 | N43: -4344.9988 | Q43: 12202.83 | S43: -2593.44
A44: Véhicules neufsSalaires autres | B44: Véhicules neufs | C44: Salaires autres | F44: 3330.4423 | L44: 3925.06 | N44: 594.61769 | Q44: 14212.21 | S44: -10287.15
A45: Véhicules neufsSalaires spécialistes | B45: Véhicules neufs | C45: Salaires spécialistes | F45: 0 | L45: 0 | N45: 0 | Q45: 0 | S45: 0
A46: Véhicules neufs[...] | B46: Véhicules neufs | C46: [...] | F46: 0 | L46: 0 | N46: 0 | Q46: 0 | S46: 0
A47: Véhicules neufs[...] | B47: Véhicules neufs | C47: [...] | F47: 0 | L47: 0 | N47: 0 | Q47: 0 | S47: 0
A48: Véhicules neufs[...] | B48: Véhicules neufs | C48: [...] | F48: 0 | L48: 0 | N48: 0 | Q48: 0 | S48: 0
A49: Véhicules neufsSalaires en absences | B49: Véhicules neufs | C49: Salaires en absences | F49: 14002.318 | L49: 14577.13 | N49: 574.81203 | Q49: 12615.57 | S49: 1961.56
A50: Véhicules neufsDéduction à la source | B50: Véhicules neufs | C50: Déduction à la source | F50: 17024.845 | L50: 16512.36 | N50: -512.48476 | Q50: 12626.31 | S50: 3886.05
A51: Véhicules neufsBénéfices marginaux | B51: Véhicules neufs | C51: Bénéfices marginaux | F51: 8771.4961 | L51: 8805.59 | N51: 34.093895 | Q51: 6414.78 | S51: 2390.81
A52: Véhicules neufsCsst | B52: Véhicules neufs | C52: Csst | F52: 3824.4216 | L52: 3234.85 | N52: -589.57165 | Q52: 2337.24 | S52: 897.61
A53: Véhicules neufs[...] | B53: Véhicules neufs | C53: [...] | D53: #N/A | F53: 0 | L53: 0 | N53: 0 | Q53: 0 | S53: 0
A54: Véhicules neufsTOTAL PERSONNEL | B54: Véhicules neufs | C54: TOTAL PERSONNEL | D54: % brut | E54: 0.24729849 | F54: 82041.391 | J54: % brut | K54: 0.29101519 | L54: 68570.36 | N54: -13471.031 | O54: % brut | P54: 0.35871324 | Q54: 73955.26 | S54: -5384.9
A55: Véhicules neufsPublicité 2 | B55: Véhicules neufs | C55: Publicité 2 | F55: 0 | L55: 0 | N55: 0 | Q55: 0 | S55: 0
A56: Véhicules neufsService gratuit 2 | B56: Véhicules neufs | C56: Service gratuit 2 | F56: 0 | L56: 0 | N56: 0 | Q56: 0 | S56: 0
A57: Véhicules neufsFrais véhicules de cie | B57: Véhicules neufs | C57: Frais véhicules de cie | F57: 9200 | L57: 7403.65 | N57: -1796.35 | Q57: 7607.19 | S57: -203.54
A58: Véhicules neufsInformatique | B58: Véhicules neufs | C58: Informatique | F58: 9039.6955 | L58: 7461.29 | N58: -1578.4055 | Q58: 9434.75 | S58: -1973.46
A59: Véhicules neufsFrais de déplacement | B59: Véhicules neufs | C59: Frais de déplacement | F59: 1105.2259 | L59: 1278.4 | N59: 173.17412 | Q59: 3463.39 | S59: -2184.99
A60: Véhicules neufsServices extérieurs | B60: Véhicules neufs | C60: Services extérieurs | F60: 6711.4186 | L60: 7123.34 | N60: 411.92136 | Q60: 6186.31 | S60: 937.03
A61: Véhicules neufsFournitures autres | B61: Véhicules neufs | C61: Fournitures autres | F61: 125 | L61: 17.22 | N61: -107.78 | Q61: 0 | S61: 17.22
A62: Véhicules neufsUniformes | B62: Véhicules neufs | C62: Uniformes | F62: 83.333333 | L62: 0 | N62: -83.333333 | Q62: 0 | S62: 0
A63: Véhicules neufsPapeterie | B63: Véhicules neufs | C63: Papeterie | F63: 756.9466 | L63: 885.48 | N63: 128.5334 | Q63: 536.74 | S63: 348.74
A64: Véhicules neufsTéléphone | B64: Véhicules neufs | C64: Téléphone | F64: 309.40349 | L64: 340.16 | N64: 30.756515 | Q64: 338.47 | S64: 1.69
A65: Véhicules neufsFrais postaux | B65: Véhicules neufs | C65: Frais postaux | F65: 113.12881 | L65: 10.56 | N65: -102.56881 | Q65: 115.6 | S65: -105.04
A66: Véhicules neufsDivers | B66: Véhicules neufs | C66: Divers | F66: 282.4626 | L66: 105.31 | N66: -177.1526 | Q66: 78.52 | S66: 26.79
... A68: Véhicules neufsFrais bancaires | B68: Véhicules neufs | C68: Frais bancaires | F68: 3363.2959 | L68: 4750.5 | N68: 1387.2041 | Q68: 7746.73 | S68: -2996.23
A69: Véhicules neufs[...] | B69: Véhicules neufs | C69: [...] | F69: 0 | N69: 0 | Q69: 0 | S69: 0
A70: Véhicules neufs[...] | B70: Véhicules neufs | C70: [...] | F70: 0 | L70: 0 | N70: 0 | Q70: 0 | S70: 0
A71: Véhicules neufs[...] | B71: Véhicules neufs | C71: [...] | F71: 0 | L71: 0 | N71: 0 | Q71: 0 | S71: 0
A72: Véhicules neufsTOTAL SEMI-FIXES | B72: Véhicules neufs | C72: TOTAL SEMI-FIXES | D72: % brut | E72: 0.099439251 | F72: 32989.018 | J72: % brut | K72: 0.12965552 | L72: 30550.04 | N72: -2438.9783 | O72: % brut | P72: 0.17602701 | Q72: 36291.17 | S72: -5741.13
A73: Véhicules neufs | B73: Véhicules neufs
A74: Véhicules neufsTOTAL DES DÉPENSES | B74: Véhicules neufs | C74: TOTAL DES DÉPENSES | D74: % brut | E74: 0.7579047 | F74: 251435.24 | J74: % brut | K74: 0.99310913 | L74: 234001.02 | N74: -17434.219 | O74: % brut | P74: 0.9169968 | Q74: 189055.57 | S74: 44945.45
A75: Véhicules neufsProgramme neuf 1 | B75: Véhicules neufs | C75: Programme neuf 1 | F75: 0 | L75: 0 | N75: 0 | Q75: 0
A76: Véhicules neufsProgramme neuf 2 | B76: Véhicules neufs | C76: Programme neuf 2 | F76: 0 | L76: 0 | N76: 0 | Q76: 0 | S76: 0
A77: Véhicules neufsProgramme neuf 3 | B77: Véhicules neufs | C77: Programme neuf 3 | F77: 0 | L77: 0 | N77: 0 | Q77: 0 | S77: 0
A78: Véhicules neufsHoldbacks | B78: Véhicules neufs | C78: Holdbacks | E78: 1317.1167 | F78: 107806 | K78: 1338.4419 | L78: 99044.7 | N78: -8761.3029 | Q78: 67424.75 | S78: 31619.95
A79: Véhicules neufs[...] | B79: Véhicules neufs | C79: [...] | F79: 0 | L79: 0 | N79: 0 | Q79: 0 | S79: 0
A80: Véhicules neufs[...] | B80: Véhicules neufs | C80: [...] | F80: 0 | L80: 0 | N80: 0 | Q80: 0 | S80: 0
A81: Véhicules neufs[...] | B81: Véhicules neufs | C81: [...] | F81: 0 | L81: 0 | N81: 0 | Q81: 0 | S81: 0
A82: Véhicules neufsFrais administration | B82: Véhicules neufs | C82: Frais administration | D82: 0.95 | E82: 474.05 | F82: 36347.784 | J82: 0.92901129 | K82: 440.35135 | L82: 32586 | N82: -3761.7837 | Q82: 23301 | S82: 9285
A83: Véhicules neufsAUTRES REVENUS | B83: Véhicules neufs | C83: AUTRES REVENUS | F83: 144153.79 | L83: 131630.7 | N83: -12523.087 | Q83: 90725.75 | S83: 40904.95
A84: Véhicules neufs | B84: Véhicules neufs
A85: Véhicules neufsPROFIT DÉPARTEMENTAL | B85: Véhicules neufs | C85: PROFIT DÉPARTEMENTAL | F85: 224469.02 | L85: 133254.36 | N85: -91214.657 | P85: 0.038401822 | Q85: 107838.37 | S85: 25415.99
C89: Volks | K89: Véhicules usagés | S89: Réalisé, Mai 2024
D91: BUDGET ORIGINAL | J91: RÉALISATION | M91: ÉCART réel / Budget | O91: ANNÉE PRÉCÉDENTE | R91: ECART (réel/ Ann.Préc.)
D92: UNITE | E92: $P/UNITÉ | F92: $PROFITS | J92: UNITÉS | K92: $P/UNITE | L92: $PROFITS | M92: UNITÉS | N92: $PROFITS | O92: UNITE | P92: $P/UNITÉ | Q92: $PROFITS | R92: UNITÉS | S92: $PROFITS
A93: Véhicules usagésVentes nettes | B93: Véhicules usagés | C93: Ventes nettes | F93: 2139236.8 | L93: 1785178.6 | Q93: 1554686.6
A94: Véhicules usagésCertifié | B94: Véhicules usagés | C94: Certifié | D94: 39.468 | E94: 1800 | F94: 71042.4 | J94: 38 | K94: 23.055789 | L94: 876.12 | M94: -1.468 | N94: -70166.28 | O94: 15 | P94: 1755.5307 | Q94: 26332.96 | R94: 23 | S94: -25456.84
A95: Véhicules usagésNon Certifié | B95: Véhicules usagés | C95: Non Certifié | D95: 2.2264 | E95: 1800 | F95: 4007.52 | J95: 2 | K95: -811.45 | L95: -1622.9 | M95: -0.2264 | N95: -5630.42 | O95: 10 | P95: 2407.581 | Q95: 24075.81 | R95: -8 | S95: -25698.71
A96: Véhicules usagésAutres Marques | B96: Véhicules usagés | C96: Autres Marques | D96: 1.3156 | E96: 1800 | F96: 2368.08 | J96: 0 | K96: 0 | L96: 0 | M96: -1.3156 | N96: -2368.08 | O96: 0 | P96: 0 | Q96: 0 | R96: 0 | S96: 0
A97: Véhicules usagésTotal Usagés | B97: Véhicules usagés | C97: Total Usagés | D97: 43.01 | E97: 1800 | F97: 77418 | J97: 40 | K97: -18.6695 | L97: -746.78 | M97: -3.01 | N97: -78164.78 | O97: 25 | P97: 2016.3508 | Q97: 50408.77 | R97: 15 | S97: -51155.55
A98: Véhicules usagés | B98: Véhicules usagés | E98: 0 | M98: -0.069983725 | N98: -1.0096461 | P98: 0 | R98: 0.6 | S98: -1.0148145
A99: Véhicules usagés | B99: Véhicules usagés | D99: 0 | E99: 0 | F99: 0
A100: Véhicules usagésVentes au Gros | B100: Véhicules usagés | C100: Ventes au Gros | D100: 44.022 | E100: 400 | F100: 17608.8 | J100: 47 | K100: -663.50468 | L100: -31184.72 | M100: 2.978 | N100: -48793.52 | O100: 43 | P100: 409.93326 | Q100: 17627.13 | R100: 4 | S100: -48811.85
A101: Véhicules usagés | B101: Véhicules usagés
A102: Véhicules usagésRev. Finances | B102: Véhicules usagés | C102: Rev. Finances | D102: 0 | E102: 0 | F102: 30107 | K102: 264.2365 | L102: 10569.46 | N102: -19537.54 | Q102: 20749.86 | R102: -264.2365 | S102: -10180.4
A103: Véhicules usagésRev. Protections | B103: Véhicules usagés | C103: Rev. Protections | D103: 0 | E103: 0 | F103: 62364.5 | K103: 1738.2057 | L103: 69528.23 | N103: 7163.73 | Q103: 37089.24 | R103: -1738.2057 | S103: 32438.99
A104: Véhicules usagésRev. Autres | B104: Véhicules usagés | C104: Rev. Autres | D104: 0 | E104: 0 | F104: 2150.5 | K104: 32.94025 | L104: 1317.61 | N104: -832.89 | Q104: 893.2 | R104: -32.94025 | S104: 424.41
A105: Véhicules usagésTotal F&I | B105: Véhicules usagés | C105: Total F&I | D105: 43.01 | E105: 2200 | F105: 94622 | J105: 40 | K105: 2035.3825 | L105: 81415.3 | M105: -3.01 | N105: -13206.7 | O105: 25 | P105: 2349.292 | Q105: 58732.3 | S105: 22683
...

Sheet Juin 2024
C1: Volks | K1: Véhicules neufs | S1: Réalisé, Juin 2024
D2: X | E2: O | F2: U | J2: NB | L2: $ | O2: X | P2: O | Q2: U | V2: *** NE PAS EFFACER / Pour An Précédente ***
D3: BUDGET ORIGINAL | J3: RÉALISATION | M3: ÉCART réel / Budget | O3: ANNÉE PRÉCÉDENTE | R3: ECART (réel/ Ann.Préc.) | V3: NEUF | W3: 0.45
D4: UNITE | E4: $P/UNITÉ | F4: $PROFITS | J4: UNITÉS | K4: $P/UNITE | L4: $PROFITS | M4: UNITÉS | N4: $PROFITS | O4: UNITE | P4: $P/UNITÉ | Q4: $PROFITS | R4: UNITÉS | S4: $PROFITS | V4: USAGE | W4: 0.1
A5: Véhicules neufsVentes nettes | B5: Véhicules neufs | C5: Ventes nettes | F5: 2918459.9 | L5: 2093787.4 | Q5: 2851329.3 | V5: SERVICE | W5: 0.225
A6: Véhicules neufsAutos détail | B6: Véhicules neufs | C6: Autos détail | D6: 11 | E6: 2158.1561 | F6: 23739.717 | J6: 15 | K6: 1651.894 | L6: 24778.41 | M6: 4 | N6: 1038.6932 | O6: 16 | P6: 2103.4488 | Q6: 33655.18 | R6: -1 | S6: -8876.77 | V6: CARROSSERIE | W6: 0.025
A7: Véhicules neufsCamions détail | B7: Véhicules neufs | C7: Camions détail | D7: 44.64 | E7: 2873.2447 | F7: 128261.64 | J7: 25 | K7: 2415.8504 | L7: 60396.26 | M7: -19.64 | N7: -67865.381 | O7: 39 | P7: 2445.2556 | Q7: 95364.97 | R7: -14 | S7: -34968.71 | V7: PIECES | W7: 0.2
A8: Véhicules neufsSprinter | B8: Véhicules neufs | C8: Sprinter | D8: 0 | E8: 0 | F8: 0 | J8: 0 | K8: 0 | L8: 0 | M8: 0 | N8: 0 | O8: 0 | P8: 0 | Q8: 0 | R8: 0 | S8: 0 | W8: 1
A9: Véhicules neufsMoto détail | B9: Véhicules neufs | C9: Moto détail | D9: 0 | E9: 0 | F9: 0 | J9: 0 | K9: 0 | L9: 0 | M9: 0 | N9: 0 | O9: 0 | P9: 0 | Q9: 0 | R9: 0 | S9: 0
A10: Véhicules neufs[...] | B10: Véhicules neufs | C10: [...] | D10: 0 | E10: 0 | F10: 0 | J10: 0 | K10: 0 | L10: 0 | M10: 0 | N10: 0 | O10: 0 | P10: 0 | Q10: 0 | R10: 0 | S10: 0
A11: Véhicules neufs[...] | B11: Véhicules neufs | C11: [...] | D11: 0 | E11: 0 | F11: 0 | J11: 0 | K11: 0 | L11: 0 | M11: 0 | N11: 0 | O11: 0 | P11: 0 | Q11: 0 | R11: 0 | S11: 0
A12: Véhicules neufs[...] | B12: Véhicules neufs | C12: [...] | D12: 0 | E12: 0 | F12: 0 | J12: 0 | K12: 0 | L12: 0 | M12: 0 | N12: 0 | O12: 0 | P12: 0 | Q12: 0 | R12: 0 | S12: 0
A13: Véhicules neufsTotal Neufs | B13: Véhicules neufs | C13: Total Neufs | D13: 55.64 | E13: 2731.872 | F13: 152001.36 | J13: 40 | K13: 2129.3667 | L13: 85174.67 | M13: -15.64 | N13: -66826.688 | O13: 55 | P13: 2345.8209 | Q13: 129020.15 | R13: -15 | S13: -43845.48
A14: Véhicules neufs | B14: Véhicules neufs | M14: -0.28109274 | N14: -0.43964534 | R14: -0.27272727 | S14: -0.33983436 | AD14: 20 | AE14: 1000 | AF14: 20000
A15: Véhicules neufsEx-Démos et courtoisies | B15: Véhicules neufs | C15: Ex-Démos et courtoisies | D15: 4.41 | E15: 2535.1216 | F15: 11179.886 | J15: 0 | K15: 0 | L15: 0 | M15: -4.41 | N15: -11179.886 | O15: 2 | P15: 1486.73 | Q15: 2973.46 | R15: -2 | S15: -2973.46 | AD15: 25 | AE15: 800 | AF15: 20000
A16: Véhicules neufs | B16: Véhicules neufs
A17: Véhicules neufsFlottes | B17: Véhicules neufs | C17: Flottes | D17: 4.05 | E17: 2664.4641 | F17: 10791.079 | J17: 0 | K17: 0 | L17: 0 | M17: -4.05 | N17: -10791.079 | O17: 2 | P17: 2962.945 | Q17: 5925.89 | R17: -2 | S17: -5925.89
A18: Véhicules neufs | B18: Véhicules neufs
A19: Véhicules neufsRachat bail | B19: Véhicules neufs | C19: Rachat bail | D19: 0 | E19: 0 | F19: 7650 | L19: 6100 | N19: -1550 | Q19: 12900.75 | R19: 0 | S19: -6800.75
A20: Véhicules neufs | B20: Véhicules neufs
A21: Véhicules neufsRev. Finances | B21: Véhicules neufs | C21: Rev. Finances | D21: 0 | E21: 0 | F21: 12010 | K21: 0 | L21: 0 | N21: -12010 | Q21: 5095.89 | R21: 0 | S21: -5095.89
A22: Véhicules neufsRev. Protections | B22: Véhicules neufs | C22: Rev. Protections | D22: 0 | E22: 0 | F22: 64854 | K22: 775.005 | L22: 31000.2 | N22: -33853.8 | Q22: 49499.24 | R22: -775.005 | S22: -18499.04
A23: Véhicules neufsRev. Autres | B23: Véhicules neufs | C23: Rev. Autres | D23: 0 | E23: 0 | F23: 1201 | K23: 67.475 | L23: 2699 | N23: 1498 | Q23: 0 | R23: -67.475 | S23: 2699
A24: Véhicules neufsTotal F&I | B24: Véhicules neufs | C24: Total F&I | D24: 60.05 | E24: 1300 | F24: 78065 | J24: 40 | K24: 842.48 | L24: 33699.2 | M24: -20.05 | N24: -44365.8 | O24: 57 | P24: 957.8093 | Q24: 54595.13 | S24: -20895.93
A25: Véhicules neufs | B25: Véhicules neufs | N25: -0.56831871 | S25: -0.38274348
A26: Véhicules neufs | B26: Véhicules neufs
A27: Véhicules neufsTotal Dépt. Neufs | B27: Véhicules neufs | C27: Total Dépt. Neufs | D27: 64.1 | E27: 4051.2843 | F27: 259687.32 | J27: 40 | K27: 3124.3467 | L27: 124973.87 | M27: -24.1 | N27: -134713.45 | O27: 59 | P27: 3481.6166 | Q27: 205415.38 | R27: -19 | S27: -80441.51
A28: Véhicules neufs | B28: Véhicules neufs | L28: 0.48124748 | M28: -0.37597504 | N28: -0.51875252 | R28: -0.3220339 | S28: -0.39160412
A29: Véhicules neufs | B29: Véhicules neufs
A30: Véhicules neufsDEPENSES | B30: Véhicules neufs | C30: DEPENSES
A31: Véhicules neufsComm. vendeurs | B31: Véhicules neufs | C31: Comm. vendeurs | D31: 0.34 | E31: 923.92378 | F31: 55481.623 | J31: 0.30022752 | K31: 639.2945 | L31: 25571.78 | N31: -29909.843 | O31: 0.31879372 | P31: 771.36614 | Q31: 43967.87 | S31: -18396.09
A32: Véhicules neufsComm. F&I | B32: Véhicules neufs | C32: Comm. F&I | D32: 0.3 | E32: 390 | F32: 23419.5 | J32: 0.0032629855 | K32: 2.749 | L32: 109.96 | N32: -23309.54 | O32: 0.30010864 | P32: 287.44684 | Q32: 16384.47 | S32: -16274.51
A33: Véhicules neufsFrais de livraison | B33: Véhicules neufs | C33: Frais de livraison | E33: 115 | F33: 6905.75 | K33: 130.5265 | L33: 5221.06 | N33: -1684.69 | P33: 98.259649 | Q33: 5600.8 | S33: -379.74
A34: Véhicules neufsService gratuit 1 | B34: Véhicules neufs | C34: Service gratuit 1 | E34: 3 | F34: 180.15 | K34: 4.62375 | L34: 184.95 | N34: 4.8 | P34: 0 | Q34: 0 | S34: 184.95
A35: Véhicules neufsEntretien stock | B35: Véhicules neufs | C35: Entretien stock | E35: 85.05 | F35: 5107.2525 | K35: 185.7815 | L35: 7431.26 | N35: 2324.0075 | P35: 70.210526 | Q35: 4002 | S35: 3429.26
A36: Véhicules neufsPublicité 1 | B36: Véhicules neufs | C36: Publicité 1 | E36: 137.06911 | F36: 8231 | K36: 266.85925 | L36: 10674.37 | N36: 2443.37 | P36: 122.48649 | Q36: 6981.73 | S36: 3692.64 | U36: PPM VENTE PRIVEE - 5K
A37: Véhicules neufsIntérêt de gros | B37: Véhicules neufs | C37: Intérêt de gros | E37: 277.29499 | F37: 16651.564 | K37: 1001.4042 | L37: 40056.17 | N37: 23404.606 | P37: 83.072632 | Q37: 4735.14 | S37: 35321.03
A38: Véhicules neufs[...] | B38: Véhicules neufs | C38: [...] | E38: 0 | F38: 0 | K38: 0 | L38: 0 | N38: 0 | P38: 0 | Q38: 0 | S38: 0
A39: Véhicules neufs[...] | B39: Véhicules neufs | C39: [...] | E39: 0 | F39: 0 | K39: 0 | L39: 0 | N39: 0 | P39: 0 | Q39: 0 | S39: 0
A40: Véhicules neufs[...] | B40: Véhicules neufs | C40: [...] | E40: 0 | F40: 0 | K40: 0 | L40: 0 | N40: 0 | P40: 0 | Q40: 0 | S40: 0
A41: Véhicules neufsTOTAL VARIABLES | B41: Véhicules neufs | C41: TOTAL VARIABLES | D41: % brut | E41: 0.44660185 | F41: 115976.84 | J41: % brut | K41: 0.71414569 | L41: 89249.55 | N41: -26727.29 | O41: % brut | P41: 0.39759443 | Q41: 81672.01 | S41: 7577.54
A42: Véhicules neufsSalaires cadres | B42: Véhicules neufs | C42: Salaires cadres | F42: 18197.117 | L42: 12515.2 | N42: -5681.9167 | P42: 0.067065718 | Q42: 13776.33 | S42: -1261.13
A43: Véhicules neufsSalaires commis | B43: Véhicules neufs | C43: Salaires commis | F43: 11267.511 | L43: 10896.4 | N43: -371.11108 | Q43: 14509.06 | S43: -3612.66
A44: Véhicules neufsSalaires autres | B44: Véhicules neufs | C44: Salaires autres | F44: 2664.3538 | L44: 2584.64 | N44: -79.713846 | Q44: 13387.76 | S44: -10803.12
A45: Véhicules neufsSalaires spécialistes | B45: Véhicules neufs | C45: Salaires spécialistes | F45: 0 | L45: 0 | N45: 0 | Q45: 0 | S45: 0
A46: Véhicules neufs[...] | B46: Véhicules neufs | C46: [...] | F46: 0 | L46: 0 | N46: 0 | Q46: 0 | S46: 0
A47: Véhicules neufs[...] | B47: Véhicules neufs | C47: [...] | F47: 0 | L47: 0 | N47: 0 | Q47: 0 | S47: 0
A48: Véhicules neufs[...] | B48: Véhicules neufs | C48: [...] | F48: 0 | L48: 0 | N48: 0 | Q48: 0 | S48: 0
A49: Véhicules neufsSalaires en absences | B49: Véhicules neufs | C49: Salaires en absences | F49: 10829.041 | L49: 10189.97 | N49: -639.0706 | Q49: 12929.12 | S49: -2739.15
A50: Véhicules neufsDéduction à la source | B50: Véhicules neufs | C50: Déduction à la source | F50: 13166.587 | L50: 11457.24 | N50: -1709.3468 | Q50: 12404.94 | S50: -947.7
A51: Véhicules neufsBénéfices marginaux | B51: Véhicules neufs | C51: Bénéfices marginaux | F51: 6783.6545 | L51: 6085.69 | N51: -697.96451 | Q51: 5591.61 | S51: 494.08
A52: Véhicules neufsCsst | B52: Véhicules neufs | C52: Csst | F52: 2957.7115 | L52: 1674.44 | N52: -1283.2715 | Q52: 3273.76 | S52: -1599.32
A53: Véhicules neufs[...] | B53: Véhicules neufs | C53: [...] | D53: #N/A | F53: 0 | L53: 0 | N53: 0 | Q53: 0 | S53: 0
A54: Véhicules neufsTOTAL PERSONNEL | B54: Véhicules neufs | C54: TOTAL PERSONNEL | D54: % brut | E54: 0.2536357 | F54: 65865.975 | J54: % brut | K54: 0.44332131 | L54: 55403.58 | N54: -10462.395 | O54: % brut | P54: 0.36936173 | Q54: 75872.58 | S54: -20469
A55: Véhicules neufsPublicité 2 | B55: Véhicules neufs | C55: Publicité 2 | F55: 0 | L55: 0 | N55: 0 | Q55: 0 | S55: 0
A56: Véhicules neufsService gratuit 2 | B56: Véhicules neufs | C56: Service gratuit 2 | F56: 0 | L56: 0 | N56: 0 | Q56: 0 | S56: 0
A57: Véhicules neufsFrais véhicules de cie | B57: Véhicules neufs | C57: Frais véhicules de cie | F57: 9200 | L57: 7254.82 | N57: -1945.18 | Q57: 5916.23 | S57: 1338.59
A58: Véhicules neufsInformatique | B58: Véhicules neufs | C58: Informatique | F58: 9039.6955 | L58: 7043.39 | N58: -1996.3055 | Q58: 7019.75 | S58: 23.64
A59: Véhicules neufsFrais de déplacement | B59: Véhicules neufs | C59: Frais de déplacement | F59: 1105.2259 | L59: 1316.83 | N59: 211.60412 | Q59: 504.08 | S59: 812.75
A60: Véhicules neufsServices extérieurs | B60: Véhicules neufs | C60: Services extérieurs | F60: 6711.4186 | L60: 7463.74 | N60: 752.32136 | Q60: 6175.67 | S60: 1288.07
A61: Véhicules neufsFournitures autres | B61: Véhicules neufs | C61: Fournitures autres | F61: 125 | L61: 4.56 | N61: -120.44 | Q61: 0 | S61: 4.56
A62: Véhicules neufsUniformes | B62: Véhicules neufs | C62: Uniformes | F62: 83.333333 | L62: 0 | N62: -83.333333 | Q62: 0 | S62: 0
A63: Véhicules neufsPapeterie | B63: Véhicules neufs | C63: Papeterie | F63: 756.9466 | L63: 387.99 | N63: -368.9566 | Q63: 605.81 | S63: -217.82
A64: Véhicules neufsTéléphone | B64: Véhicules neufs | C64: Téléphone | F64: 309.40349 | L64: 326.92 | N64: 17.516515 | Q64: 232.9 | S64: 94.02
A65: Véhicules neufsFrais postaux | B65: Véhicules neufs | C65: Frais postaux | F65: 113.12881 | L65: 32.96 | N65: -80.16881 | Q65: 81.84 | S65: -48.88
A66: Véhicules neufsDivers | B66: Véhicules neufs | C66: Divers | F66: 282.4626 | L66: 123.77 | N66: -158.6926 | Q66: 111.34 | S66: 12.43
... A68: Véhicules neufsFrais bancaires | B68: Véhicules neufs | C68: Frais bancaires | F68: 3363.2959 | L68: 3357.81 | N68: -5.485929 | Q68: 3537.15 | S68: -179.34
A69: Véhicules neufs[...] | B69: Véhicules neufs | C69: [...] | F69: 0 | N69: 0 | Q69: 0 | S69: 0
A70: Véhicules neufs[...] | B70: Véhicules neufs | C70: [...] | F70: 0 | L70: 0 | N70: 0 | Q70: 0 | S70: 0
A71: Véhicules neufs[...] | B71: Véhicules neufs | C71: [...] | F71: 0 | L71: 0 | N71: 0 | Q71: 0 | S71: 0
A72: Véhicules neufsTOTAL SEMI-FIXES | B72: Véhicules neufs | C72: TOTAL SEMI-FIXES | D72: % brut | E72: 0.12703361 | F72: 32989.018 | J72: % brut | K72: 0.22968153 | L72: 28704.19 | N72: -4284.8283 | O72: % brut | P72: 0.12011126 | Q72: 24672.7 | S72: 4031.49
A73: Véhicules neufs | B73: Véhicules neufs
A74: Véhicules neufsTOTAL DES DÉPENSES | B74: Véhicules neufs | C74: TOTAL DES DÉPENSES | D74: % brut | E74: 0.82727116 | F74: 214831.83 | J74: % brut | K74: 1.3871485 | L74: 173357.32 | N74: -41474.513 | O74: % brut | P74: 0.88706741 | Q74: 182217.29 | S74: -8859.97
A75: Véhicules neufsProgramme neuf 1 | B75: Véhicules neufs | C75: Programme neuf 1 | F75: 20000 | L75: 20000 | N75: 0 | Q75: 0
A76: Véhicules neufsProgramme neuf 2 | B76: Véhicules neufs | C76: Programme neuf 2 | F76: 0 | L76: 0 | N76: 0 | Q76: 0 | S76: 0
A77: Véhicules neufsProgramme neuf 3 | B77: Véhicules neufs | C77: Programme neuf 3 | F77: 0 | L77: 0 | N77: 0 | Q77: 0 | S77: 0
A78: Véhicules neufsHoldbacks | B78: Véhicules neufs | C78: Holdbacks | E78: 1293.3871 | F78: 82906.113 | K78: 1388.05 | L78: 55522 | N78: -27384.113 | Q78: 63469.55 | S78: -7947.55
A79: Véhicules neufs[...] | B79: Véhicules neufs | C79: [...] | F79: 0 | L79: 0 | N79: 0 | Q79: 0 | S79: 0
A80: Véhicules neufs[...] | B80: Véhicules neufs | C80: [...] | F80: 0 | L80: 0 | N80: 0 | Q80: 0 | S80: 0
A81: Véhicules neufs[...] | B81: Véhicules neufs | C81: [...] | F81: 0 | L81: 0 | N81: 0 | Q81: 0 | S81: 0
A82: Véhicules neufsFrais administration | B82: Véhicules neufs | C82: Frais administration | D82: 0.95 | E82: 474.05 | F82: 28466.702 | J82: 0.97858216 | K82: 488.3125 | L82: 19532.5 | N82: -8934.2025 | Q82: 26386 | S82: -6853.5
A83: Véhicules neufsAUTRES REVENUS | B83: Véhicules neufs | C83: AUTRES REVENUS | F83: 131372.82 | L83: 95054.5 | N83: -36318.315 | Q83: 89855.55 | S83: -14801.05
A84: Véhicules neufs | B84: Véhicules neufs
A85: Véhicules neufsPROFIT DÉPARTEMENTAL | B85: Véhicules neufs | C85: PROFIT DÉPARTEMENTAL | F85: 176228.31 | L85: 46671.05 | N85: -129557.26 | P85: 0.03964945 | Q85: 113053.64 | S85: -86382.59
C89: Volks | K89: Véhicules usagés | S89: Réalisé, Juin 2024
D91: BUDGET ORIGINAL | J91: RÉALISATION | M91: ÉCART réel / Budget | O91: ANNÉE PRÉCÉDENTE | R91: ECART (réel/ Ann.Préc.)
D92: UNITE | E92: $P/UNITÉ | F92: $PROFITS | J92: UNITÉS | K92: $P/UNITE | L92: $PROFITS | M92: UNITÉS | N92: $PROFITS | O92: UNITE | P92: $P/UNITÉ | Q92: $PROFITS | R92: UNITÉS | S92: $PROFITS
A93: Véhicules usagésVentes nettes | B93: Véhicules usagés | C93: Ventes nettes | F93: 1934191.4 | L93: 1325634.6 | Q93: 1977586.1
A94: Véhicules usagésCertifié | B94: Véhicules usagés | C94: Certifié | D94: 35.685 | E94: 1800 | F94: 64233 | J94: 31 | K94: 599.35871 | L94: 18580.12 | M94: -4.685 | N94: -45652.88 | O94: 18 | P94: 2437.2944 | Q94: 43871.3 | R94: 13 | S94: -25291.18
A95: Véhicules usagésNon Certifié | B95: Véhicules usagés | C95: Non Certifié | D95: 2.013 | E95: 1800 | F95: 3623.4 | J95: 2 | K95: 1491.09 | L95: 2982.18 | M95: -0.013 | N95: -641.22 | O95: 7 | P95: 1925.8071 | Q95: 13480.65 | R95: -5 | S95: -10498.47
A96: Véhicules usagésAutres Marques | B96: Véhicules usagés | C96: Autres Marques | D96: 1.1895 | E96: 1800 | F96: 2141.1 | J96: 0 | K96: 0 | L96: 0 | M96: -1.1895 | N96: -2141.1 | O96: 0 | P96: 0 | Q96: 0 | R96: 0 | S96: 0
A97: Véhicules usagésTotal Usagés | B97: Véhicules usagés | C97: Total Usagés | D97: 38.8875 | E97: 1800 | F97: 69997.5 | J97: 33 | K97: 653.40303 | L97: 21562.3 | M97: -5.8875 | N97: -48435.2 | O97: 25 | P97: 2294.078 | Q97: 57351.95 | R97: 8 | S97: -35789.65
A98: Véhicules usagés | B98: Véhicules usagés | E98: 0 | M98: -0.15139826 | N98: -0.69195614 | P98: 0 | R98: 0.32 | S98: -0.62403545
A99: Véhicules usagés | B99: Véhicules usagés | D99: 0 | E99: 0 | F99: 0
A100: Véhicules usagésVentes au Gros | B100: Véhicules usagés | C100: Ventes au Gros | D100: 39.8025 | E100: 400 | F100: 15921 | J100: 29 | K100: 144.99517 | L100: 4204.86 | M100: -10.8025 | N100: -11716.14 | O100: 57 | P100: 568.81632 | Q100: 32422.53 | R100: -28 | S100: -28217.67
A101: Véhicules usagés | B101: Véhicules usagés
A102: Véhicules usagésRev. Finances | B102: Véhicules usagés | C102: Rev. Finances | D102: 0 | E102: 0 | F102: 27221.25 | K102: 273.09788 | L102: 9012.23 | N102: -18209.02 | Q102: 18374.17 | R102: -273.09788 | S102: -9361.94
A103: Véhicules usagésRev. Protections | B103: Véhicules usagés | C103: Rev. Protections | D103: 0 | E103: 0 | F103: 56386.875 | K103: 1518.8015 | L103: 50120.45 | N103: -6266.425 | Q103: 43866.15 | R103: -1518.8015 | S103: 6254.3
A104: Véhicules usagésRev. Autres | B104: Véhicules usagés | C104: Rev. Autres | D104: 0 | E104: 0 | F104: 1944.375 | K104: 0 | L104: 0 | N104: -1944.375 | Q104: 1498.31 | R104: 0 | S104: -1498.31
A105: Véhicules usagésTotal F&I | B105: Véhicules usagés | C105: Total F&I | D105: 38.8875 | E105: 2200 | F105: 85552.5 | J105: 33 | K105: 1791.8994 | L105: 59132.68 | M105: -5.8875 | N105: -26419.82 | O105: 25 | P105: 2549.5452 | Q105: 63738.63 | S105: -4605.95
...

Sheet END
