Workbook
Name _Dates_Conc: [1]Dealers!$BF$37:$KA$63
Name _scen: '[1]Scen & Sens'!$E$26
Name _scen1: '[1]Scen & Sens'!$E$27
Name _scen2: '[1]Scen & Sens'!$E$28
Name _SCenarios: '[1]Scen & Sens'!$J$26:$O$26
Name _Sens1: '[1]Scen & Sens'!$F$9
Name _Sens2: '[1]Scen & Sens'!$F$10
Name _sensRes1: '[1]Scen & Sens'!$E$15
Name _sensRes2: '[1]Scen & Sens'!$E$16
Name _sensRes3: '[1]Scen & Sens'!$E$17
Name _sensRes4: '[1]Scen & Sens'!$E$18
Name _sensRes5: '[1]Scen & Sens'!$E$19
Name _sensRes6: '[1]Scen & Sens'!$E$20
Name _sensRes7: '[1]Scen & Sens'!$E$21
Name DateRange: [1]Volkswagen!$BF$6:$DY$6
Name Monetary_Unit: [1]Parameters!$B$15
Name Months: [1]Parameters!$E$9:$E$20
Name Rng_Dealers_Names: [1]!Tbl_Dealers[Dealer Name]
Name Rng_Dlr_Dates: [1]!Tbl_V_Dlr_Dates[Date]
Name Ticker: #REF!
Name Ticker: #REF!
Name Ticker: #REF!
Name Titre: [1]Front!$A$9

Sheet Paramètre
B3: Quarter
B6: BUDGET | F6: BUDGET RÉVISÉ | J6: ACTUAL | N6: LAST YEAR
B7: Ventes | C7: Profits bruts | D7: BAIIA | E7: EBIT | F7: Ventes | G7: Profits bruts | H7: BAIIA | I7: EBIT | J7: Ventes | K7: Profits bruts | L7: BAIIA | M7: EBIT | N7: Ventes | O7: Profits bruts | P7: BAIIA | Q7: EBIT
A8: CTRL | B8: =+B9-B10 -> #REF! | C8: =+C9-C10 -> #REF! | D8: =+D9-D10 -> #REF! | E8: =+E9-E10 -> #REF! | F8: =+F9-F10 -> #REF! | G8: =+G9-G10 -> #REF! | H8: =+H9-H10 -> #REF! | I8: =+I9-I10 -> #REF! | ... Q8: =+Q9-Q10 -> #REF!
A9: CONSO | B9: =+Conso!$Z$405 -> 16892003 | C9: =+Conso!$Z$406 -> 2515613.3 | D9: =+Conso!$Z$482 -> 825406.03 | E9: =+Conso!$Z$497 -> 735461.03 | F9: =+Conso!$AC$405 -> 0 | G9: =+Conso!$AC$406 -> 0 | H9: =+Conso!$AC$482 -> 0 | I9: =+Conso!$AC$497 -> 0 | J9: =+Conso!$AF$405 -> 12663799 | K9: =+Conso!$AF$406 -> 1865550.7 | L9: =+Conso!$AF$482 -> 391433.22 | M9: =+Conso!$AF$497 -> 281096.29 | N9: =+Conso!$AL$405 -> 32561866 | O9: =+Conso!$AL$406 -> 2083377.1 | P9: =+Conso!$AL$482 -> 627120.36 | Q9: =+Conso!$AL$497 -> 616275.63
A10: TOTAL | B10: =+SUM(B11:B13) -> #REF! | C10: =+SUM(C11:C13) -> #REF! | D10: =+SUM(D11:D13) -> #REF! | E10: =+SUM(E11:E13) -> #REF! | F10: =+SUM(F11:F13) -> #REF! | G10: =+SUM(G11:G13) -> #REF! | H10: =+SUM(H11:H13) -> #REF! | I10: =+SUM(I11:I13) -> #REF! | ... Q10: =+SUM(Q11:Q13) -> #REF!
A11: Mois 1 | B11: =+#REF! -> #REF! | C11: =+#REF! -> #REF! | D11: =+#REF! -> #REF! | E11: =+#REF! -> #REF! | F11: =+#REF! -> #REF! | G11: =+#REF! -> #REF! | H11: =+#REF! -> #REF! | I11: =+#REF! -> #REF! | ... Q11: =+#REF! -> #REF!
A12: Mois 2 | B12: =+#REF! -> #REF! | C12: =+#REF! -> #REF! | D12: =+#REF! -> #REF! | E12: =+#REF! -> #REF! | F12: =+#REF! -> #REF! | G12: =+#REF! -> #REF! | H12: =+#REF! -> #REF! | I12: =+#REF! -> #REF! | ... Q12: =+#REF! -> #REF!
A13: Mois 3 | B13: =+#REF! -> #REF! | C13: =+#REF! -> #REF! | D13: =+#REF! -> #REF! | E13: =+#REF! -> #REF! | F13: =+#REF! -> #REF! | G13: =+#REF! -> #REF! | H13: =+#REF! -> #REF! | I13: =+#REF! -> #REF! | ... Q13: =+#REF! -> #REF!

Sheet Conso
C1: Conso | K1: Véhicules neufs | S1: =CONCATENATE("Réalisé"," ",Paramètre!$C$2," ",Paramètre!$C$3) -> Réalisé
D2: X | E2: O | F2: U | G2: X | H2: O | I2: U
D3: BUDGET ORIGINAL | G3: BUDGET REVISE | J3: RÉALISATION | M3: ÉCART réel / original | O3: ANNÉE PRÉCÉDENTE | R3: ÉCART réel / année précédente
D4: UNITE | E4: $P/UNITÉ | F4: $PROFITS | G4: UNITE | H4: $P/UNITÉ | I4: $PROFITS | J4: UNITE | K4: $P/UNITE | L4: $PROFITS | M4: UNITÉ | N4: $PROFITS | O4: UNITE | P4: $P/UNITE | Q4: $PROFITS | R4: UNITE | S4: $PROFITS
A5: =+B5&C5 -> Véhicules neufsVentes nettes | B5: =+$K$1 -> Véhicules neufs | C5: Ventes nettes | F5: =+SUM(START:END!F5) -> 8755197.7 | I5: =+SUM(START:END!I5) -> 0 | L5: =+SUM(START:END!L5) -> 6739517.4 | Q5: =+SUM(START:END!Q5) -> 26535985
A6: =+B6&C6 -> Véhicules neufsAutos détail | B6: =+$K$1 -> Véhicules neufs | C6: Autos détail | D6: =+SUM(START:END!D6) -> 32.4 | E6: =IF(D6=0,0,F6/D6) -> 2198.1219 | F6: =+SUM(START:END!F6) -> 71219.15 | G6: =+SUM(START:END!G6) -> 0 | H6: =IF(G6=0,0,I6/G6) -> 0 | I6: =+SUM(START:END!I6) -> 0 | J6: =+SUM(START:END!J6) -> 26 | K6: =IF(J6=0,0,L6/J6) -> 1810.325 | L6: =+SUM(START:END!L6) -> 47068.45 | M6: =J6-D6 -> -6.4 | N6: =L6-F6 -> -24150.7 | O6: =+SUM(START:END!O6) -> 44 | P6: =IF(O6=0,0,Q6/O6) -> 2072.8732 | Q6: =+SUM(START:END!Q6) -> 91206.42 | R6: =J6-O6 -> -18 | S6: =L6-Q6 -> -44137.97
A7: =+B7&C7 -> Véhicules neufsCamions détail | B7: =+$K$1 -> Véhicules neufs | C7: Camions détail | D7: =+SUM(START:END!D7) -> 134.32 | E7: =IF(D7=0,0,F7/D7) -> 2864.6882 | F7: =+SUM(START:END!F7) -> 384784.92 | G7: =+SUM(START:END!G7) -> 0 | H7: =IF(G7=0,0,I7/G7) -> 0 | I7: =+SUM(START:END!I7) -> 0 | J7: =+SUM(START:END!J7) -> 83 | K7: =IF(J7=0,0,L7/J7) -> 1820.1257 | L7: =+SUM(START:END!L7) -> 151070.43 | M7: =J7-D7 -> -51.32 | N7: =L7-F7 -> -233714.49 | O7: =+SUM(START:END!O7) -> 155 | P7: =IF(O7=0,0,Q7/O7) -> 2443.4194 | Q7: =+SUM(START:END!Q7) -> 378730.01 | R7: =J7-O7 -> -72 | S7: =L7-Q7 -> -227659.58
A8: =+B8&C8 -> Véhicules neufsSprinter | B8: =+$K$1 -> Véhicules neufs | C8: Sprinter | D8: =+SUM(START:END!D8) -> 0 | E8: =IF(D8=0,0,F8/D8) -> 0 | F8: =+SUM(START:END!F8) -> 0 | G8: =+SUM(START:END!G8) -> 0 | H8: =IF(G8=0,0,I8/G8) -> 0 | I8: =+SUM(START:END!I8) -> 0 | J8: =+SUM(START:END!J8) -> 0 | K8: =IF(J8=0,0,L8/J8) -> 0 | L8: =+SUM(START:END!L8) -> 0 | M8: =J8-D8 -> 0 | N8: =L8-F8 -> 0 | O8: =+SUM(START:END!O8) -> 0 | P8: =IF(O8=0,0,Q8/O8) -> 0 | Q8: =+SUM(START:END!Q8) -> 0 | R8: =J8-O8 -> 0 | S8: =L8-Q8 -> 0
A9: =+B9&C9 -> Véhicules neufsMoto détail | B9: =+$K$1 -> Véhicules neufs | C9: Moto détail | D9: =+SUM(START:END!D9) -> 0 | E9: =IF(D9=0,0,F9/D9) -> 0 | F9: =+SUM(START:END!F9) -> 0 | G9: =+SUM(START:END!G9) -> 0 | H9: =IF(G9=0,0,I9/G9) -> 0 | I9: =+SUM(START:END!I9) -> 0 | J9: =+SUM(START:END!J9) -> 0 | K9: =IF(J9=0,0,L9/J9) -> 0 | L9: =+SUM(START:END!L9) -> 0 | M9: =J9-D9 -> 0 | N9: =L9-F9 -> 0 | O9: =+SUM(START:END!O9) -> 0 | P9: =IF(O9=0,0,Q9/O9) -> 0 | Q9: =+SUM(START:END!Q9) -> 0 | R9: =J9-O9 -> 0 | S9: =L9-Q9 -> 0
A10: =+B10&C10 -> Véhicules neufs[...] | B10: =+$K$1 -> Véhicules neufs | C10: [...] | D10: =+SUM(START:END!D10) -> 0 | E10: =IF(D10=0,0,F10/D10) -> 0 | F10: =+SUM(START:END!F10) -> 0 | G10: =+SUM(START:END!G10) -> 0 | H10: =IF(G10=0,0,I10/G10) -> 0 | I10: =+SUM(START:END!I10) -> 0 | J10: =+SUM(START:END!J10) -> 0 | K10: =IF(J10=0,0,L10/J10) -> 0 | L10: =+SUM(START:END!L10) -> 0 | M10: =J10-G10 -> 0 | N10: =L10-I10 -> 0 | O10: =+SUM(START:END!O10) -> 0 | P10: =IF(O10=0,0,Q10/O10) -> 0 | Q10: =+SUM(START:END!Q10) -> 0 | R10: =J10-O10 -> 0 | S10: =L10-Q10 -> 0
A11: =+B11&C11 -> Véhicules neufs[...] | B11: =+$K$1 -> Véhicules neufs | C11: [...] | D11: =+SUM(START:END!D11) -> 0 | E11: =IF(D11=0,0,F11/D11) -> 0 | F11: =+SUM(START:END!F11) -> 0 | G11: =+SUM(START:END!G11) -> 0 | H11: =IF(G11=0,0,I11/G11) -> 0 | I11: =+SUM(START:END!I11) -> 0 | J11: =+SUM(START:END!J11) -> 0 | K11: =IF(J11=0,0,L11/J11) -> 0 | L11: =+SUM(START:END!L11) -> 0 | M11: =J11-G11 -> 0 | N11: =L11-I11 -> 0 | O11: =+SUM(START:END!O11) -> 0 | P11: =IF(O11=0,0,Q11/O11) -> 0 | Q11: =+SUM(START:END!Q11) -> 0 | R11: =J11-O11 -> 0 | S11: =L11-Q11 -> 0
A12: =+B12&C12 -> Véhicules neufs[...] | B12: =+$K$1 -> Véhicules neufs | C12: [...] | D12: =+SUM(START:END!D12) -> 0 | E12: =IF(D12=0,0,F12/D12) -> 0 | F12: =+SUM(START:END!F12) -> 0 | G12: =+SUM(START:END!G12) -> 0 | H12: =IF(G12=0,0,I12/G12) -> 0 | I12: =+SUM(START:END!I12) -> 0 | J12: =+SUM(START:END!J12) -> 0 | K12: =IF(J12=0,0,L12/J12) -> 0 | L12: =+SUM(START:END!L12) -> 0 | M12: =J12-G12 -> 0 | N12: =L12-I12 -> 0 | O12: =+SUM(START:END!O12) -> 0 | P12: =IF(O12=0,0,Q12/O12) -> 0 | Q12: =+SUM(START:END!Q12) -> 0 | R12: =J12-O12 -> 0 | S12: =L12-Q12 -> 0
A13: =+B13&C13 -> Véhicules neufsTotal Neufs | B13: =+$K$1 -> Véhicules neufs | C13: Total Neufs | D13: =+SUM(D6:D12) -> 166.72 | E13: =IF(D13<=0,0,F13/D13) -> 2735.1492 | F13: =+SUM(F6:F12) -> 456004.07 | G13: =+SUM(G6:G12) -> 0 | H13: =IF(G13<=0,0,I13/G13) -> 0 | I13: =+SUM(I6:I12) -> 0 | J13: =+SUM(J6:J12) -> 109 | K13: =IF(J13<=0,0,L13/J13) -> 1817.7879 | L13: =+SUM(L6:L12) -> 198138.88 | M13: =+SUM(M6:M12) -> -57.72 | N13: =+SUM(N6:N12) -> -257865.19 | O13: =+SUM(O6:O12) -> 199 | P13: =IF(O13<=0,0,Q13/O13) -> 2361.4896 | Q13: =+SUM(Q6:Q12) -> 469936.43 | R13: =+SUM(R6:R12) -> -90 | S13: =+SUM(S6:S12) -> -271797.55
A14: =+B14&C14 -> Véhicules neufs | B14: =+$K$1 -> Véhicules neufs | N14: =IF(F13=0,0,N13/F13) -> -0.56548879 | R14: =R13/O13 -> -0.45226131 | S14: =IF(Q13=0,0,(S13/Q13)) -> -0.57837089
A15: =+B15&C15 -> Véhicules neufsEx-Démos et courtoisies | B15: =+$K$1 -> Véhicules neufs | C15: Ex-Démos et courtoisies | D15: =+SUM(START:END!D15) -> 13.29 | E15: =IF(D15=0,0,F15/D15) -> 2523.6763 | F15: =+SUM(START:END!F15) -> 33539.659 | G15: =+SUM(START:END!G15) -> 0 | H15: =IF(G15=0,0,I15/G15) -> 0 | I15: =+SUM(START:END!I15) -> 0 | J15: =+SUM(START:END!J15) -> 12 | K15: =IF(J15=0,0,L15/J15) -> 1517.4408 | L15: =+SUM(START:END!L15) -> 18209.29 | M15: =J15-G15 -> 12 | N15: =L15-F15 -> -15330.369 | O15: =+SUM(START:END!O15) -> 2 | P15: =IF(O15=0,0,Q15/O15) -> 2937.965 | Q15: =+SUM(START:END!Q15) -> 5875.93 | R15: =J15-O15 -> 10 | S15: =L15-Q15 -> 12333.36
A16: =+B16&C16 -> Véhicules neufs | B16: =+$K$1 -> Véhicules neufs
A17: =+B17&C17 -> Véhicules neufsFlottes | B17: =+$K$1 -> Véhicules neufs | C17: Flottes | D17: =+SUM(START:END!D17) -> 12.15 | E17: =IF(D17=0,0,F17/D17) -> 2664.4641 | F17: =+SUM(START:END!F17) -> 32373.238 | G17: =+SUM(START:END!G17) -> 0 | H17: =IF(G17=0,0,I17/G17) -> 0 | I17: =+SUM(START:END!I17) -> 0 | J17: =+SUM(START:END!J17) -> 11 | K17: =IF(J17=0,0,L17/J17) -> 1058.8518 | L17: =+SUM(START:END!L17) -> 11647.37 | M17: =J17-D17 -> -1.15 | N17: =L17-F17 -> -20725.868 | O17: =+SUM(START:END!O17) -> 10 | P17: =IF(O17=0,0,Q17/O17) -> 3147.371 | Q17: =+SUM(START:END!Q17) -> 31473.71 | R17: =J17-O17 -> 1 | S17: =L17-Q17 -> -19826.34
A18: =+B18&C18 -> Véhicules neufs | B18: =+$K$1 -> Véhicules neufs
A19: =+B19&C19 -> Véhicules neufsRachat bail | B19: =+$K$1 -> Véhicules neufs | C19: Rachat bail | F19: =+SUM(START:END!F19) -> 22950 | I19: =+SUM(START:END!I19) -> 0 | L19: =+SUM(START:END!L19) -> 23749 | N19: =L19-F19 -> 799 | Q19: =+SUM(START:END!Q19) -> 17381.51 | R19: =O19-K19 -> 0 | S19: =L19-Q19 -> 6367.49
A20: =+B20&C20 -> Véhicules neufs | B20: =+$K$1 -> Véhicules neufs
A21: =+B21&C21 -> Véhicules neufsRev. Finances | B21: =+$K$1 -> Véhicules neufs | C21: Rev. Finances | D21: 0 | E21: =IF(D21=0,0,F21/D21) -> 0 | F21: =+SUM(START:END!F21) -> 36002 | G21: 0 | H21: =IF(G21=0,0,I21/G21) -> 0 | I21: =+SUM(START:END!I21) -> 0 | K21: =IF(J13=0,0,L21/(J13+J15)) -> 10.65157 | L21: =+SUM(START:END!L21) -> 1288.84 | N21: =L21-F21 -> -34713.16 | P21: =IF(O13=0,0,Q21/(O13+O15)) -> 56.331891 | Q21: =+SUM(START:END!Q21) -> 11322.71 | R21: =O21-K21 -> -10.65157 | S21: =L21-Q21 -> -10033.87
A22: =+B22&C22 -> Véhicules neufsRev. Protections | B22: =+$K$1 -> Véhicules neufs | C22: Rev. Protections | D22: 0 | E22: =IF(D22=0,0,F22/D22) -> 0 | F22: =+SUM(START:END!F22) -> 194410.8 | G22: 0 | H22: =IF(G22=0,0,I22/G22) -> 0 | I22: =+SUM(START:END!I22) -> 0 | K22: =IF(J13=0,0,L22/(J13+J15)) -> 1036.308 | L22: =+SUM(START:END!L22) -> 125393.27 | N22: =L22-F22 -> -69017.53 | P22: =IF(O13=0,0,Q22/(O13+O15)) -> 987.88144 | Q22: =+SUM(START:END!Q22) -> 198564.17 | R22: =O22-K22 -> -1036.308 | S22: =L22-Q22 -> -73170.9
A23: =+B23&C23 -> Véhicules neufsRev. Autres | B23: =+$K$1 -> Véhicules neufs | C23: Rev. Autres | D23: 0 | E23: =IF(D23=0,0,F23/D23) -> 0 | F23: =+SUM(START:END!F23) -> 3600.2 | G23: 0 | H23: =IF(G23=0,0,I23/G23) -> 0 | I23: =+SUM(START:END!I23) -> 0 | K23: =IF(J13=0,0,L23/(J13+J15)) -> 10.65438 | L23: =+SUM(START:END!L23) -> 1289.18 | N23: =L23-F23 -> -2311.02 | P23: =IF(O13=0,0,Q23/(O13+O15)) -> 20.941791 | Q23: =+SUM(START:END!Q23) -> 4209.3 | R23: =O23-K23 -> -10.65438 | S23: =L23-Q23 -> -2920.12
A24: =+B24&C24 -> Véhicules neufsTotal F&I | B24: =+$K$1 -> Véhicules neufs | C24: Total F&I | D24: =+D15+D13 -> 180.01 | E24: =IF(D24<=0,0,F24/D24) -> 1300 | F24: =F21+F22+F23 -> 234013 | G24: =+G15+G13 -> 0 | H24: =IF(G24<=0,0,I24/G24) -> 0 | I24: =I21+I22+I23 -> 0 | J24: =+J15+J13 -> 121 | K24: =IF(J24<=0,0,L24/J24) -> 1057.614 | L24: =L21+L22+L23 -> 127971.29 | M24: =+M15+M13 -> -45.72 | N24: =N21+N22+N23 -> -106041.71 | O24: =+O15+O13 -> 201 | P24: =IF(O24<=0,0,Q24/O24) -> 1065.1551 | Q24: =Q21+Q22+Q23 -> 214096.18 | S24: =L24-Q24 -> -86124.89
A25: =+B25&C25 -> Véhicules neufs | B25: =+$K$1 -> Véhicules neufs | S25: =IF(Q24=0,0,(S24/Q24)) -> -0.40227196
A26: =+B26&C26 -> Véhicules neufs | B26: =+$K$1 -> Véhicules neufs
A27: =+B27&C27 -> Véhicules neufsTotal Dépt. Neufs | B27: =+$K$1 -> Véhicules neufs | C27: Total Dépt. Neufs | D27: =+D13+D15+D17 -> 192.16 | E27: =IF(D27<=0,0,F27/D27) -> 4053.2888 | F27: =F13+F17+F24+F19+F15 -> 778879.97 | G27: =+G13+G15+G17 -> 0 | H27: =IF(G27<=0,0,I27/G27) -> 0 | I27: =I13+I17+I24+I19+I15 -> 0 | J27: =+J13+J15+J17 -> 132 | K27: =IF(J27<=0,0,L27/J27) -> 2876.6351 | L27: =L13+L17+L24+L19+L15 -> 379715.83 | M27: =+M13+M15+M17 -> -46.87 | N27: =N13+N17+N24+N19+N15 -> -399164.14 | O27: =+O13+O15+O17 -> 211 | P27: =IF(O27<=0,0,Q27/O27) -> 3501.25 | Q27: =Q13+Q17+Q24+Q19+Q15 -> 738763.76 | R27: =J27-O27 -> -79 | S27: =L27-Q27 -> -359047.93
A28: =+B28&C28 -> Véhicules neufs | B28: =+$K$1 -> Véhicules neufs | M28: =M27/D27 -> -0.24391132 | N28: =N27/F27 -> -0.51248479 | R28: =R27/O27 -> -0.37440758 | S28: =IF(Q27=0,0,S27/Q27) -> -0.48601183
A29: =+B29&C29 -> Véhicules neufs | B29: =+$K$1 -> Véhicules neufs
A30: =+B30&C30 -> Véhicules neufsDEPENSES | B30: =+$K$1 -> Véhicules neufs | C30: DEPENSES
A31: =+B31&C31 -> Véhicules neufsComm. vendeurs | B31: =+$K$1 -> Véhicules neufs | C31: Comm. vendeurs | E31: =F31/D$24 -> 924.64235 | F31: =+SUM(START:END!F31) -> 166444.87 | H31: =I31/G$24 -> #DIV/0! | I31: =+SUM(START:END!I31) -> 0 | J31: =L31/L13 -> 0.38011581 | K31: =IF(L31=0,0,L31/J$24) -> 622.44397 | L31: =+SUM(START:END!L31) -> 75315.72 | N31: =L31-F31 -> -91129.149 | P31: =IF(Q31=0,0,Q31/O$24) -> 601.63682 | Q31: =+SUM(START:END!Q31) -> 120929 | S31: =L31-Q31 -> -45613.28
A32: =+B32&C32 -> Véhicules neufsComm. F&I | B32: =+$K$1 -> Véhicules neufs | C32: Comm. F&I | E32: =F32/D$24 -> 390 | F32: =+SUM(START:END!F32) -> 70203.9 | H32: =I32/G$24 -> #DIV/0! | I32: =+SUM(START:END!I32) -> 0 | J32: =L32/L24 -> 0.28380991 | K32: =IF(L32=0,0,L32/J$24) -> 300.16132 | L32: =+SUM(START:END!L32) -> 36319.52 | N32: =L32-F32 -> -33884.38 | P32: =IF(Q32=0,0,Q32/O$24) -> 318.93955 | Q32: =+SUM(START:END!Q32) -> 64106.85 | S32: =L32-Q32 -> -27787.33
A33: =+B33&C33 -> Véhicules neufsFrais de livraison | B33: =+$K$1 -> Véhicules neufs | C33: Frais de livraison | E33: =F33/D$24 -> 115 | F33: =+SUM(START:END!F33) -> 20701.15 | H33: =I33/G$24 -> #DIV/0! | I33: =+SUM(START:END!I33) -> 0 | K33: =IF(L33=0,0,L33/J$24) -> 157.53769 | L33: =+SUM(START:END!L33) -> 19062.06 | N33: =L33-F33 -> -1639.09 | P33: =IF(Q33=0,0,Q33/O$24) -> 150.03144 | Q33: =+SUM(START:END!Q33) -> 30156.32 | S33: =L33-Q33 -> -11094.26
A34: =+B34&C34 -> Véhicules neufsService gratuit 1 | B34: =+$K$1 -> Véhicules neufs | C34: Service gratuit 1 | E34: =F34/D$24 -> 3 | F34: =+SUM(START:END!F34) -> 540.03 | H34: =I34/G$24 -> #DIV/0! | I34: =+SUM(START:END!I34) -> 0 | K34: =IF(L34=0,0,L34/J$24) -> 47.640496 | L34: =+SUM(START:END!L34) -> 5764.5 | N34: =L34-F34 -> 5224.47 | P34: =IF(Q34=0,0,Q34/O$24) -> 38.430746 | Q34: =+SUM(START:END!Q34) -> 7724.58 | S34: =L34-Q34 -> -1960.08
A35: =+B35&C35 -> Véhicules neufsEntretien stock | B35: =+$K$1 -> Véhicules neufs | C35: Entretien stock | E35: =F35/D$24 -> 85.05 | F35: =+SUM(START:END!F35) -> 15309.85 | H35: =I35/G$24 -> #DIV/0! | I35: =+SUM(START:END!I35) -> 0 | K35: =IF(L35=0,0,L35/J$24) -> 158.87983 | L35: =+SUM(START:END!L35) -> 19224.46 | N35: =L35-F35 -> 3914.6095 | P35: =IF(Q35=0,0,Q35/O$24) -> 83.521542 | Q35: =+SUM(START:END!Q35) -> 16787.83 | S35: =L35-Q35 -> 2436.63
A36: =+B36&C36 -> Véhicules neufsPublicité 1 | B36: =+$K$1 -> Véhicules neufs | C36: Publicité 1 | E36: =F36/D$24 -> 112.25487 | F36: =+SUM(START:END!F36) -> 20207 | H36: =I36/G$24 -> #DIV/0! | I36: =+SUM(START:END!I36) -> 0 | K36: =IF(L36=0,0,L36/J$24) -> 342.80653 | L36: =+SUM(START:END!L36) -> 41479.59 | N36: =L36-F36 -> 21272.59 | P36: =IF(Q36=0,0,Q36/O$24) -> 101.00746 | Q36: =+SUM(START:END!Q36) -> 20302.5 | S36: =L36-Q36 -> 21177.09
A37: =+B37&C37 -> Véhicules neufsIntérêt de gros | B37: =+$K$1 -> Véhicules neufs | C37: Intérêt de gros | E37: =F37/D$24 -> 244.87222 | F37: =+SUM(START:END!F37) -> 44079.449 | H37: =I37/G$24 -> #DIV/0! | I37: =+SUM(START:END!I37) -> 0 | K37: =IF(L37=0,0,L37/J$24) -> -117.72405 | L37: =+SUM(START:END!L37) -> -14244.61 | N37: =L37-F37 -> -58324.059 | P37: =IF(Q37=0,0,Q37/O$24) -> 183.21866 | Q37: =+SUM(START:END!Q37) -> 36826.95 | S37: =L37-Q37 -> -51071.56
A38: =+B38&C38 -> Véhicules neufs[...] | B38: =+$K$1 -> Véhicules neufs | C38: [...] | E38: =F38/D$24 -> 0 | F38: =+SUM(START:END!F38) -> 0 | H38: =I38/G$24 -> #DIV/0! | I38: =+SUM(START:END!I38) -> 0 | K38: =IF(L38=0,0,L38/J$24) -> 0 | L38: =+SUM(START:END!L38) -> 0 | N38: =L38-I38 -> 0 | P38: =IF(Q38=0,0,Q38/O$24) -> 0 | Q38: =+SUM(START:END!Q38) -> 0 | S38: =L38-Q38 -> 0
A39: =+B39&C39 -> Véhicules neufs[...] | B39: =+$K$1 -> Véhicules neufs | C39: [...] | E39: =F39/D$24 -> 0 | F39: =+SUM(START:END!F39) -> 0 | H39: =I39/G$24 -> #DIV/0! | I39: =+SUM(START:END!I39) -> 0 | K39: =IF(L39=0,0,L39/J$24) -> 0 | L39: =+SUM(START:END!L39) -> 0 | N39: =L39-I39 -> 0 | P39: =IF(Q39=0,0,Q39/O$24) -> 0 | Q39: =+SUM(START:END!Q39) -> 0 | S39: =L39-Q39 -> 0
A40: =+B40&C40 -> Véhicules neufs[...] | B40: =+$K$1 -> Véhicules neufs | C40: [...] | E40: =F40/D$24 -> 0 | F40: =+SUM(START:END!F40) -> 0 | H40: =I40/G$24 -> #DIV/0! | I40: =+SUM(START:END!I40) -> 0 | K40: =IF(L40=0,0,L40/J$24) -> 0 | L40: =+SUM(START:END!L40) -> 0 | N40: =L40-I40 -> 0 | P40: =IF(Q40=0,0,Q40/O$24) -> 0 | Q40: =+SUM(START:END!Q40) -> 0 | S40: =L40-Q40 -> 0
A41: =+B41&C41 -> Véhicules neufsTOTAL VARIABLES | B41: =+$K$1 -> Véhicules neufs | C41: TOTAL VARIABLES | D41: % brut | E41: =F41/F$27 -> 0.43329686 | F41: =SUM(F31:F40) -> 337486.25 | G41: % brut | H41: =I41/I$27 -> #DIV/0! | I41: =SUM(I31:I40) -> 0 | J41: % brut | K41: =L41/L$27 -> 0.48173193 | L41: =SUM(L31:L40) -> 182921.24 | N41: =SUM(N31:N40) -> -154565.01 | O41: % brut | P41: =Q41/Q$27 -> 0.40179831 | Q41: =SUM(Q31:Q40) -> 296834.03 | S41: =L41-Q41 -> -113912.79
A42: =+B42&C42 -> Véhicules neufsSalaires cadres | B42: =+$K$1 -> Véhicules neufs | C42: Salaires cadres | F42: =+SUM(START:END!F42) -> 57527.713 | I42: =+SUM(START:END!I42) -> 0 | L42: =+SUM(START:END!L42) -> 42916.83 | N42: =L42-F42 -> -14610.883 | Q42: =+SUM(START:END!Q42) -> 37807.07
A43: =+B43&C43 -> Véhicules neufsSalaires commis | B43: =+$K$1 -> Véhicules neufs | C43: Salaires commis | F43: =+SUM(START:END!F43) -> 36489.411 | I43: =+SUM(START:END!I43) -> 0 | L43: =+SUM(START:END!L43) -> 30835.88 | N43: =L43-F43 -> -5653.531 | Q43: =+SUM(START:END!Q43) -> 31805.12 | S43: =L43-Q43 -> -969.24
A44: =+B44&C44 -> Véhicules neufsSalaires autres | B44: =+$K$1 -> Véhicules neufs | C44: Salaires autres | F44: =+SUM(START:END!F44) -> 8659.15 | I44: =+SUM(START:END!I44) -> 0 | L44: =+SUM(START:END!L44) -> 9321.24 | N44: =L44-F44 -> 662.09 | Q44: =+SUM(START:END!Q44) -> 11775.78 | S44: =L44-Q44 -> -2454.54
A45: =+B45&C45 -> Véhicules neufsSalaires spécialistes | B45: =+$K$1 -> Véhicules neufs | C45: Salaires spécialistes | F45: =+SUM(START:END!F45) -> 0 | I45: =+SUM(START:END!I45) -> 0 | L45: =+SUM(START:END!L45) -> 0 | N45: =L45-F45 -> 0 | Q45: =+SUM(START:END!Q45) -> 0 | S45: =L45-Q45 -> 0
A46: =+B46&C46 -> Véhicules neufs[...] | B46: =+$K$1 -> Véhicules neufs | C46: [...] | F46: =+SUM(START:END!F46) -> 0 | I46: =+SUM(START:END!I46) -> 0 | L46: =+SUM(START:END!L46) -> 0 | N46: =L46-F46 -> 0 | Q46: =+SUM(START:END!Q46) -> 0 | S46: =L46-Q46 -> 0
A47: =+B47&C47 -> Véhicules neufs[...] | B47: =+$K$1 -> Véhicules neufs | C47: [...] | F47: =+SUM(START:END!F47) -> 0 | I47: =+SUM(START:END!I47) -> 0 | L47: =+SUM(START:END!L47) -> 0 | N47: =L47-F47 -> 0 | Q47: =+SUM(START:END!Q47) -> 0 | S47: =L47-Q47 -> 0
A48: =+B48&C48 -> Véhicules neufs[...] | B48: =+$K$1 -> Véhicules neufs | C48: [...] | F48: =+SUM(START:END!F48) -> 0 | I48: =+SUM(START:END!I48) -> 0 | L48: =+SUM(START:END!L48) -> 0 | N48: =L48-F48 -> 0 | Q48: =+SUM(START:END!Q48) -> 0 | S48: =L48-Q48 -> 0
A49: =+B49&C49 -> Véhicules neufsSalaires en absences | B49: =+$K$1 -> Véhicules neufs | C49: Salaires en absences | F49: =+SUM(START:END!F49) -> 34718.337 | I49: =+SUM(START:END!I49) -> 0 | L49: =+SUM(START:END!L49) -> 31124.08 | N49: =L49-F49 -> -3594.2565 | Q49: =+SUM(START:END!Q49) -> 27780.69 | S49: =L49-Q49 -> 3343.39
A50: =+B50&C50 -> Véhicules neufsDéduction à la source | B50: =+$K$1 -> Véhicules neufs | C50: Déduction à la source | F50: =+SUM(START:END!F50) -> 42212.603 | I50: =+SUM(START:END!I50) -> 0 | L50: =+SUM(START:END!L50) -> 37824.34 | N50: =L50-F50 -> -4388.263 | Q50: =+SUM(START:END!Q50) -> 31683.11 | S50: =L50-Q50 -> 6141.23
A51: =+B51&C51 -> Véhicules neufsBénéfices marginaux | B51: =+$K$1 -> Véhicules neufs | C51: Bénéfices marginaux | F51: =+SUM(START:END!F51) -> 21748.667 | I51: =+SUM(START:END!I51) -> 0 | L51: =+SUM(START:END!L51) -> 11323.66 | N51: =L51-F51 -> -10425.007 | Q51: =+SUM(START:END!Q51) -> 15911.68 | S51: =L51-Q51 -> -4588.02
A52: =+B52&C52 -> Véhicules neufsCsst | B52: =+$K$1 -> Véhicules neufs | C52: Csst | F52: =+SUM(START:END!F52) -> 9482.5413 | I52: =+SUM(START:END!I52) -> 0 | L52: =+SUM(START:END!L52) -> 5653.92 | N52: =L52-F52 -> -3828.6213 | Q52: =+SUM(START:END!Q52) -> 3041.64 | S52: =L52-Q52 -> 2612.28
A53: =+B53&C53 -> Véhicules neufs[...] | B53: =+$K$1 -> Véhicules neufs | C53: [...] | F53: =+SUM(START:END!F53) -> 0 | I53: =+SUM(START:END!I53) -> 0 | L53: =+SUM(START:END!L53) -> 0 | N53: =L53-I53 -> 0 | Q53: =+SUM(START:END!Q53) -> 0 | S53: =L53-Q53 -> 0
A54: =+B54&C54 -> Véhicules neufsTOTAL PERSONNEL | B54: =+$K$1 -> Véhicules neufs | C54: TOTAL PERSONNEL | D54: % brut | E54: =F54/F$27 -> 0.27069437 | F54: =+SUM(F42:F53) -> 210838.42 | G54: % brut | H54: =I54/I$27 -> #DIV/0! | I54: =+SUM(I42:I53) -> 0 | J54: % brut | K54: =L54/L$27 -> 0.44506954 | L54: =+SUM(L42:L53) -> 168999.95 | N54: =+SUM(N42:N53) -> -41838.472 | O54: % brut | P54: =Q54/Q$27 -> 0.2163142 | Q54: =+SUM(Q42:Q53) -> 159805.09 | S54: =+SUM(S42:S53) -> 4085.1
A55: =+B55&C55 -> Véhicules neufsPublicité 2 | B55: =+$K$1 -> Véhicules neufs | C55: Publicité 2 | F55: =+SUM(START:END!F55) -> 0 | I55: =+SUM(START:END!I55) -> 0 | L55: =+SUM(START:END!L55) -> 0 | N55: =L55-F55 -> 0 | Q55: =+SUM(START:END!Q55) -> 0 | S55: =L55-Q55 -> 0
A56: =+B56&C56 -> Véhicules neufsService gratuit 2 | B56: =+$K$1 -> Véhicules neufs | C56: Service gratuit 2 | F56: =+SUM(START:END!F56) -> 0 | I56: =+SUM(START:END!I56) -> 0 | L56: =+SUM(START:END!L56) -> 0 | N56: =L56-F56 -> 0 | Q56: =+SUM(START:END!Q56) -> 0 | S56: =L56-Q56 -> 0
A57: =+B57&C57 -> Véhicules neufsFrais véhicules de cie | B57: =+$K$1 -> Véhicules neufs | C57: Frais véhicules de cie | F57: =+SUM(START:END!F57) -> 27600 | I57: =+SUM(START:END!I57) -> 0 | L57: =+SUM(START:END!L57) -> 28844.14 | N57: =L57-F57 -> 1244.14 | Q57: =+SUM(START:END!Q57) -> 24104.65 | S57: =L57-Q57 -> 4739.49
A58: =+B58&C58 -> Véhicules neufsInformatique | B58: =+$K$1 -> Véhicules neufs | C58: Informatique | F58: =+SUM(START:END!F58) -> 27119.086 | I58: =+SUM(START:END!I58) -> 0 | L58: =+SUM(START:END!L58) -> 21883.84 | N58: =L58-F58 -> -5235.2464 | Q58: =+SUM(START:END!Q58) -> 20023.38 | S58: =L58-Q58 -> 1860.46
A59: =+B59&C59 -> Véhicules neufsFrais de déplacement | B59: =+$K$1 -> Véhicules neufs | C59: Frais de déplacement | F59: =+SUM(START:END!F59) -> 3315.6777 | I59: =+SUM(START:END!I59) -> 0 | L59: =+SUM(START:END!L59) -> 5836.41 | N59: =L59-F59 -> 2520.7323 | Q59: =+SUM(START:END!Q59) -> 4228.11 | S59: =L59-Q59 -> 1608.3
A60: =+B60&C60 -> Véhicules neufsServices extérieurs | B60: =+$K$1 -> Véhicules neufs | C60: Services extérieurs | F60: =+SUM(START:END!F60) -> 20134.256 | I60: =+SUM(START:END!I60) -> 0 | L60: =+SUM(START:END!L60) -> 22830.12 | N60: =L60-F60 -> 2695.8641 | Q60: =+SUM(START:END!Q60) -> 23890.94 | S60: =L60-Q60 -> -1060.82
A61: =+B61&C61 -> Véhicules neufsFournitures autres | B61: =+$K$1 -> Véhicules neufs | C61: Fournitures autres | F61: =+SUM(START:END!F61) -> 375 | I61: =+SUM(START:END!I61) -> 0 | L61: =+SUM(START:END!L61) -> 176.44 | N61: =L61-F61 -> -198.56 | Q61: =+SUM(START:END!Q61) -> 322.07 | S61: =L61-Q61 -> -145.63
A62: =+B62&C62 -> Véhicules neufsUniformes | B62: =+$K$1 -> Véhicules neufs | C62: Uniformes | F62: =+SUM(START:END!F62) -> 250 | I62: =+SUM(START:END!I62) -> 0 | L62: =+SUM(START:END!L62) -> 434.88 | N62: =L62-F62 -> 184.88 | Q62: =+SUM(START:END!Q62) -> 0 | S62: =L62-Q62 -> 434.88
A63: =+B63&C63 -> Véhicules neufsPapeterie | B63: =+$K$1 -> Véhicules neufs | C63: Papeterie | F63: =+SUM(START:END!F63) -> 2270.8398 | I63: =+SUM(START:END!I63) -> 0 | L63: =+SUM(START:END!L63) -> 2702.08 | N63: =L63-F63 -> 431.24019 | Q63: =+SUM(START:END!Q63) -> 3423.48 | S63: =L63-Q63 -> -721.4
A64: =+B64&C64 -> Véhicules neufsTéléphone | B64: =+$K$1 -> Véhicules neufs | C64: Téléphone | F64: =+SUM(START:END!F64) -> 928.21046 | I64: =+SUM(START:END!I64) -> 0 | L64: =+SUM(START:END!L64) -> 1073.56 | N64: =L64-F64 -> 145.34954 | Q64: =+SUM(START:END!Q64) -> 900.44 | S64: =L64-Q64 -> 173.12
A65: =+B65&C65 -> Véhicules neufsFrais postaux | B65: =+$K$1 -> Véhicules neufs | C65: Frais postaux | F65: =+SUM(START:END!F65) -> 339.38643 | I65: =+SUM(START:END!I65) -> 0 | L65: =+SUM(START:END!L65) -> 106.17 | N65: =L65-F65 -> -233.21643 | Q65: =+SUM(START:END!Q65) -> 653.03 | S65: =L65-Q65 -> -546.86
A66: =+B66&C66 -> Véhicules neufsDivers | B66: =+$K$1 -> Véhicules neufs | C66: Divers | F66: =+SUM(START:END!F66) -> 847.38781 | I66: =+SUM(START:END!I66) -> 0 | L66: =+SUM(START:END!L66) -> 776.91 | N66: =L66-F66 -> -70.47781 | Q66: =+SUM(START:END!Q66) -> 317.02 | S66: =L66-Q66 -> 459.89
... A68: =+B68&C68 -> Véhicules neufsFrais bancaires | B68: =+$K$1 -> Véhicules neufs | C68: Frais bancaires | F68: =+SUM(START:END!F68) -> 10089.888 | I68: =+SUM(START:END!I68) -> 0 | L68: =+SUM(START:END!L68) -> 15688.78 | N68: =L68-F68 -> 5598.8922 | Q68: =+SUM(START:END!Q68) -> 12337.71 | S68: =L68-Q68 -> 3351.07
A69: =+B69&C69 -> Véhicules neufs[...] | B69: =+$K$1 -> Véhicules neufs | C69: [...] | F69: =+SUM(START:END!F69) -> 0 | I69: =+SUM(START:END!I69) -> 0 | L69: =+SUM(START:END!L69) -> 0 | N69: =L69-I69 -> 0 | Q69: =+SUM(START:END!Q69) -> 0 | S69: =L69-Q69 -> 0
A70: =+B70&C70 -> Véhicules neufs[...] | B70: =+$K$1 -> Véhicules neufs | C70: [...] | F70: =+SUM(START:END!F70) -> 0 | I70: =+SUM(START:END!I70) -> 0 | L70: =+SUM(START:END!L70) -> 0 | N70: =L70-I70 -> 0 | Q70: =+SUM(START:END!Q70) -> 0 | S70: =L70-Q70 -> 0
A71: =+B71&C71 -> Véhicules neufs[...] | B71: =+$K$1 -> Véhicules neufs | C71: [...] | F71: =+SUM(START:END!F71) -> 0 | I71: =+SUM(START:END!I71) -> 0 | L71: =+SUM(START:END!L71) -> 0 | N71: =L71-I71 -> 0 | Q71: =+SUM(START:END!Q71) -> 0 | S71: =L71-Q71 -> 0
A72: =+B72&C72 -> Véhicules neufsTOTAL SEMI-FIXES | B72: =+$K$1 -> Véhicules neufs | C72: TOTAL SEMI-FIXES | D72: % brut | E72: =F72/F$27 -> 0.12706329 | F72: =+SUM(F55:F71) -> 98967.055 | G72: % brut | H72: =I72/I$27 -> #DIV/0! | I72: =+SUM(I55:I71) -> 0 | J72: % brut | K72: =L72/L$27 -> 0.27548975 | L72: =+SUM(L55:L71) -> 104607.82 | N72: =+SUM(N55:N71) -> 5640.7652 | O72: % brut | P72: =Q72/Q$27 -> 0.12864027 | Q72: =+SUM(Q55:Q71) -> 95034.77 | S72: =+SUM(S55:S71) -> 9573.05
A73: =+B73&C73 -> Véhicules neufs | B73: =+$K$1 -> Véhicules neufs
A74: =+B74&C74 -> Véhicules neufsTOTAL DES DÉPENSES | B74: =+$K$1 -> Véhicules neufs | C74: TOTAL DES DÉPENSES | D74: % brut | E74: =F74/F$27 -> 0.83105452 | F74: =F41+F54+F72 -> 647291.72 | G74: % brut | H74: =I74/I$27 -> #DIV/0! | I74: =I41+I54+I72 -> 0 | J74: % brut | K74: =L74/L$27 -> 1.2022912 | L74: =L41+L54+L72 -> 456529.01 | N74: =N41+N54+N72 -> -190762.71 | O74: % brut | P74: =Q74/Q$27 -> 0.74675278 | Q74: =Q41+Q54+Q72 -> 551673.89 | S74: =L74-Q74 -> -95144.88
A75: =+B75&C75 -> Véhicules neufsProgramme neuf 1 | B75: =+$K$1 -> Véhicules neufs | C75: Programme neuf 1 | F75: =+SUM(START:END!F75) -> 20000 | I75: =+SUM(START:END!I75) -> 0 | L75: =+SUM(START:END!L75) -> 32500 | N75: =L75-F75 -> 12500 | Q75: =+SUM(START:END!Q75) -> 31556
A76: =+B76&C76 -> Véhicules neufsProgramme neuf 2 | B76: =+$K$1 -> Véhicules neufs | C76: Programme neuf 2 | F76: =+SUM(START:END!F76) -> 0 | I76: =+SUM(START:END!I76) -> 0 | L76: =+SUM(START:END!L76) -> 0 | N76: =L76-F76 -> 0 | Q76: =+SUM(START:END!Q76) -> 0 | S76: =L76-Q76 -> 0
A77: =+B77&C77 -> Véhicules neufsProgramme neuf 3 | B77: =+$K$1 -> Véhicules neufs | C77: Programme neuf 3 | F77: =+SUM(START:END!F77) -> 0 | I77: =+SUM(START:END!I77) -> 0 | L77: =+SUM(START:END!L77) -> 0 | N77: =L77-F77 -> 0 | Q77: =+SUM(START:END!Q77) -> 0 | S77: =L77-Q77 -> 0
A78: =+B78&C78 -> Véhicules neufsHoldbacks | B78: =+$K$1 -> Véhicules neufs | C78: Holdbacks | F78: =+SUM(START:END!F78) -> 248521.94 | I78: =+SUM(START:END!I78) -> 0 | L78: =+SUM(START:END!L78) -> 175923.85 | N78: =L78-F78 -> -72598.095 | Q78: =+SUM(START:END!Q78) -> 232846.94 | S78: =L78-Q78 -> -56923.09
A79: =+B79&C79 -> Véhicules neufs[...] | B79: =+$K$1 -> Véhicules neufs | C79: [...] | F79: =+SUM(START:END!F79) -> 0 | I79: =+SUM(START:END!I79) -> 0 | L79: =+SUM(START:END!L79) -> 0 | N79: =L79-F79 -> 0 | Q79: =+SUM(START:END!Q79) -> 0 | S79: =L79-Q79 -> 0
A80: =+B80&C80 -> Véhicules neufs[...] | B80: =+$K$1 -> Véhicules neufs | C80: [...] | F80: =+SUM(START:END!F80) -> 0 | I80: =+SUM(START:END!I80) -> 0 | L80: =+SUM(START:END!L80) -> 0 | N80: =L80-F80 -> 0 | Q80: =+SUM(START:END!Q80) -> 0 | S80: =L80-Q80 -> 0
A81: =+B81&C81 -> Véhicules neufs[...] | B81: =+$K$1 -> Véhicules neufs | C81: [...] | F81: =+SUM(START:END!F81) -> 0 | I81: =+SUM(START:END!I81) -> 0 | L81: =+SUM(START:END!L81) -> 0 | N81: =L81-F81 -> 0 | Q81: =+SUM(START:END!Q81) -> 0 | S81: =L81-Q81 -> 0
A82: =+B82&C82 -> Véhicules neufsFrais administration | B82: =+$K$1 -> Véhicules neufs | C82: Frais administration | F82: =+SUM(START:END!F82) -> 85333.74 | I82: =+SUM(START:END!I82) -> 0 | L82: =+SUM(START:END!L82) -> 57657 | N82: =L82-F82 -> -27676.74 | Q82: =+SUM(START:END!Q82) -> 93512.9 | S82: =L82-Q82 -> -35855.9
A83: =+B83&C83 -> Véhicules neufsAUTRES REVENUS | B83: =+$K$1 -> Véhicules neufs | C83: AUTRES REVENUS | F83: =+SUM(F75:F82) -> 353855.69 | I83: =+SUM(I75:I82) -> 0 | L83: =+SUM(L75:L82) -> 266080.85 | N83: =+SUM(N75:N82) -> -87774.835 | Q83: =+SUM(Q75:Q82) -> 357915.84 | S83: =+SUM(S75:S82) -> -92778.99
A84: =+B84&C84 -> Véhicules neufs | B84: =+$K$1 -> Véhicules neufs
A85: =+B85&C85 -> Véhicules neufsPROFIT DÉPARTEMENTAL | B85: =+$K$1 -> Véhicules neufs | C85: PROFIT DÉPARTEMENTAL | F85: =F27-F74+F83 -> 485443.93 | I85: =I27-I74+I83 -> 0 | L85: =L27-L74+L83 -> 189267.67 | N85: =N27-N74+N83 -> -296176.26 | Q85: =Q27-Q74+Q83 -> 545005.71 | S85: =S27-S41-S54-S72+S83 -> -351572.28
F86: =+F85-#REF!-#REF!-#REF! -> #REF! | L86: =+L85-#REF!-#REF!-#REF! -> #REF! | N86: =+N85-#REF!-#REF!-#REF! -> #REF! | Q86: =+Q85-#REF!-#REF!-#REF! -> #REF! | S86: =+S85-#REF!-#REF!-#REF! -> #REF!
C89: =C1 -> Conso | K89: Véhicules usagés | S89: =$S$1 -> Réalisé
D91: BUDGET ORIGINAL | G91: BUDGET RÉVISÉ | J91: RÉALISATION | M91: ÉCART réel / original | O91: ANNÉE PRÉCÉDENTE | R91: ÉCART réel / année précédente
D92: UNITE | E92: $P/UNITÉ | F92: $PROFITS | G92: UNITE | H92: $P/UNITÉ | I92: $PROFITS | J92: UNITE | K92: $P/UNITE | L92: $PROFITS | M92: UNITÉ | N92: $PROFITS | O92: UNITE | P92: $P/UNITE | Q92: $PROFITS | R92: UNITE | S92: $PROFITS
A93: =+B93&C93 -> Véhicules usagésVentes nettes | B93: Véhicules usagés | C93: Ventes nettes | F93: =+SUM(START:END!F93) -> 5007758.9 | I93: =+SUM(START:END!I93) -> 0 | L93: =+SUM(START:END!L93) -> 3170590 | Q93: =+SUM(START:END!Q93) -> 3303558.4
A94: =+B94&C94 -> Véhicules usagésCertifié | B94: Véhicules usagés | C94: Certifié | D94: =+SUM(START:END!D94) -> 92.391 | E94: =IF(D94=0,0,F94/D94) -> 1800 | F94: =+SUM(START:END!F94) -> 166303.8 | G94: =+SUM(START:END!G94) -> 0 | H94: =IF(G94=0,0,I94/G94) -> 0 | I94: =+SUM(START:END!I94) -> 0 | J94: =+SUM(START:END!J94) -> 84 | K94: =IF(J94=0,0,L94/J94) -> 1254.9132 | L94: =+SUM(START:END!L94) -> 105412.71 | M94: =J94-D94 -> -8.391 | N94: =L94-F94 -> -60891.09 | O94: =+SUM(START:END!O94) -> 50 | P94: =IF(O94=0,0,Q94/O94) -> 1496.2264 | Q94: =+SUM(START:END!Q94) -> 74811.32 | R94: =J94-O94 -> 34 | S94: =L94-Q94 -> 30601.39
A95: =+B95&C95 -> Véhicules usagésNon Certifié | B95: Véhicules usagés | C95: Non Certifié | D95: =+SUM(START:END!D95) -> 5.2118 | E95: =IF(D95=0,0,F95/D95) -> 1800 | F95: =+SUM(START:END!F95) -> 9381.24 | G95: =+SUM(START:END!G95) -> 0 | H95: =IF(G95=0,0,I95/G95) -> 0 | I95: =+SUM(START:END!I95) -> 0 | J95: =+SUM(START:END!J95) -> 5 | K95: =IF(J95=0,0,L95/J95) -> -1216.644 | L95: =+SUM(START:END!L95) -> -6083.22 | M95: =J95-D95 -> -0.2118 | N95: =L95-F95 -> -15464.46 | O95: =+SUM(START:END!O95) -> 14 | P95: =IF(O95=0,0,Q95/O95) -> 1719.2943 | Q95: =+SUM(START:END!Q95) -> 24070.12 | R95: =J95-O95 -> -9 | S95: =L95-Q95 -> -30153.34
A96: =+B96&C96 -> Véhicules usagésAutres marques | B96: Véhicules usagés | C96: Autres marques | D96: =+SUM(START:END!D96) -> 3.0797 | E96: =IF(D96=0,0,F96/D96) -> 1800 | F96: =+SUM(START:END!F96) -> 5543.46 | G96: =+SUM(START:END!G96) -> 0 | H96: =IF(G96=0,0,I96/G96) -> 0 | I96: =+SUM(START:END!I96) -> 0 | J96: =+SUM(START:END!J96) -> 7 | K96: =IF(J96=0,0,L96/J96) -> 2177 | L96: =+SUM(START:END!L96) -> 15239 | M96: =J96-D96 -> 3.9203 | N96: =L96-F96 -> 9695.54 | O96: =+SUM(START:END!O96) -> 0 | P96: =IF(O96=0,0,Q96/O96) -> 0 | Q96: =+SUM(START:END!Q96) -> 0 | R96: =J96-O96 -> 7 | S96: =L96-Q96 -> 15239
A97: =+B97&C97 -> Véhicules usagésTotal Usagés | B97: Véhicules usagés | C97: Total Usagés | D97: =+D95+D94+D96 -> 100.6825 | E97: =IF(D97=0,0,F97/D97) -> 1800 | F97: =+F94+F95+F96 -> 181228.5 | G97: =+G95+G94+G96 -> 0 | H97: =IF(G97=0,0,I97/G97) -> 0 | I97: =+I94+I95+I96 -> 0 | J97: =+J95+J94+J96 -> 96 | K97: =IF(J97=0,0,L97/J97) -> 1193.4218 | L97: =+L94+L95+L96 -> 114568.49 | M97: =+M95+M94+M96 -> -4.6825 | N97: =+N94+N95+N96 -> -66660.01 | O97: =+O95+O94+O96 -> 64 | P97: =IF(O97<=0,0,Q97/O97) -> 1545.0225 | Q97: =+Q94+Q95+Q96 -> 98881.44 | R97: =R94+R95+R96 -> 32 | S97: =S94+S95+S96 -> 15687.05
A98: =+B98&C98 -> Véhicules usagés | B98: Véhicules usagés | E98: =IF(D98=0,0,F98/D98) -> 0 | H98: =IF(G98=0,0,I98/G98) -> 0 | M98: =D97/D97 -> 1 | N98: =N97/F97 -> -0.367823 | R98: =R97/O97 -> 0.5 | S98: =IF(Q97=0,0,(S97/Q97)) -> 0.15864504
A99: =+B99&C99 -> Véhicules usagésUS | B99: Véhicules usagés | C99: US | D99: =+SUM(START:END!D99) -> 0 | E99: =IF(D99=0,0,F99/D99) -> 0 | F99: =+SUM(START:END!F99) -> 0 | G99: =+SUM(START:END!G99) -> 0 | H99: =IF(G99=0,0,I99/G99) -> 0 | I99: =+SUM(START:END!I99) -> 0 | J99: =+SUM(START:END!J99) -> 0 | K99: =IF(J99=0,0,L99/J99) -> 0 | L99: =+SUM(START:END!L99) -> 0 | M99: =J99-D99 -> 0 | N99: =L99-F99 -> 0 | O99: =+SUM(START:END!O99) -> 0 | P99: =IF(O99=0,0,Q99/O99) -> 0 | Q99: =+SUM(START:END!Q99) -> 0
A100: =+B100&C100 -> Véhicules usagésVentes au Gros | B100: Véhicules usagés | C100: Ventes au Gros | D100: =+SUM(START:END!D100) -> 103.0515 | E100: =IF(D100=0,0,F100/D100) -> 400 | F100: =+SUM(START:END!F100) -> 41220.6 | G100: =+SUM(START:END!G100) -> 0 | H100: =IF(G100=0,0,I100/G100) -> 0 | I100: =+SUM(START:END!I100) -> 0 | J100: =+SUM(START:END!J100) -> 64 | K100: =IF(J100=0,0,L100/J100) -> 9.3240625 | L100: =+SUM(START:END!L100) -> 596.74 | M100: =J100-D100 -> -39.0515 | N100: =L100-F100 -> -40623.86 | O100: =+SUM(START:END!O100) -> 90 | P100: =IF(O100=0,0,Q100/O100) -> 70.327889 | Q100: =+SUM(START:END!Q100) -> 6329.51 | R100: =J100-O100 -> -26 | S100: =L100-Q100 -> -5732.77
A101: =+B101&C101 -> Véhicules usagés | B101: Véhicules usagés
A102: =+B102&C102 -> Véhicules usagésRev. Finances | B102: Véhicules usagés | C102: Rev. Finances | D102: =+SUM(START:END!D102) -> 0 | E102: =IF(D102=0,0,F102/D102) -> 0 | F102: =+SUM(START:END!F102) -> 70477.75 | G102: =+SUM(START:END!G102) -> 0 | H102: =IF(G102=0,0,I102/G102) -> 0 | I102: =+SUM(START:END!I102) -> 0 | J102: =+SUM(START:END!J102) -> 0 | K102: =IF(J102=0,0,L102/J102) -> 0 | L102: =+SUM(START:END!L102) -> 29057.01 | M102: =J102-G102 -> 0 | N102: =L102-F102 -> -41420.74 | O102: =+SUM(START:END!O102) -> 0 | P102: =IF(O102=0,0,Q102/O102) -> 0 | Q102: =+SUM(START:END!Q102) -> 32371.82 | R102: =J102-O102 -> 0 | S102: =L102-Q102 -> -3314.81
A103: =+B103&C103 -> Véhicules usagésRev. Protections | B103: Véhicules usagés | C103: Rev. Protections | D103: =+SUM(START:END!D103) -> 0 | E103: =IF(D103=0,0,F103/D103) -> 0 | F103: =+SUM(START:END!F103) -> 145989.62 | G103: =+SUM(START:END!G103) -> 0 | H103: =IF(G103=0,0,I103/G103) -> 0 | I103: =+SUM(START:END!I103) -> 0 | J103: =+SUM(START:END!J103) -> 0 | K103: =IF(J103=0,0,L103/J103) -> 0 | L103: =+SUM(START:END!L103) -> 138631.75 | M103: =J103-G103 -> 0 | N103: =L103-F103 -> -7357.875 | O103: =+SUM(START:END!O103) -> 0 | P103: =IF(O103=0,0,Q103/O103) -> 0 | Q103: =+SUM(START:END!Q103) -> 80610.58 | R103: =J103-O103 -> 0 | S103: =L103-Q103 -> 58021.17
A104: =+B104&C104 -> Véhicules usagésRev. Autres | B104: Véhicules usagés | C104: Rev. Autres | D104: =+SUM(START:END!D104) -> 0 | E104: =IF(D104=0,0,F104/D104) -> 0 | F104: =+SUM(START:END!F104) -> 5034.125 | G104: =+SUM(START:END!G104) -> 0 | H104: =IF(G104=0,0,I104/G104) -> 0 | I104: =+SUM(START:END!I104) -> 0 | J104: =+SUM(START:END!J104) -> 0 | K104: =IF(J104=0,0,L104/J104) -> 0 | L104: =+SUM(START:END!L104) -> 1705.68 | M104: =J104-G104 -> 0 | N104: =L104-F104 -> -3328.445 | O104: =+SUM(START:END!O104) -> 0 | P104: =IF(O104=0,0,Q104/O104) -> 0 | Q104: =+SUM(START:END!Q104) -> 1946.22 | R104: =J104-O104 -> 0 | S104: =L104-Q104 -> -240.54
...

Sheet START

Sheet 2024-10
C1: =[5]Parametres!B1 -> Volks | K1: Véhicules neufs | S1: =CONCATENATE("Réalisé,"," ",[5]Parametres!B3," ",[5]Parametres!B4) -> Réalisé, Octobre 2024
D2: X | E2: O | F2: U | J2: NB | L2: $ | O2: X | P2: O | Q2: U | V2: *** NE PAS EFFACER / Pour An Précédente ***
D3: BUDGET ORIGINAL | J3: RÉALISATION | M3: ÉCART réel / Budget | O3: ANNÉE PRÉCÉDENTE | R3: ECART (réel/ Ann.Préc.) | V3: NEUF | W3: 0.45
D4: UNITE | E4: $P/UNITÉ | F4: $PROFITS | J4: UNITÉS | K4: $P/UNITE | L4: $PROFITS | M4: UNITÉS | N4: $PROFITS | O4: UNITE | P4: $P/UNITÉ | Q4: $PROFITS | R4: UNITÉS | S4: $PROFITS | V4: USAGE | W4: 0.1
A5: Véhicules neufsVentes nettes | B5: Véhicules neufs | C5: Ventes nettes | F5: =+INDEX('[5]Budget original'!$A$2:$AO$501,MATCH($A5,'[5]Budget original'!$A$2:$A$501,0),MATCH(F$2,'[5]Budget original'!$A$2:$AO$2,0)) -> 3890933.2 | L5: =-SUMIFS([5]BV_Data_An_Cour!$O:$O,[5]BV_Data_An_Cour!$X:$X,"Oui",[5]BV_Data_An_Cour!$U:$U,$B5) -> 2470114 | Q5: {=+INDEX('[5]Réel 2023'!$A$2:$AO$501,MATCH($A5,'[5]Réel 2023'!$A$2:$A$501,0),MATCH(Q$2,'[5]Réel 2023'!$A$2:$AO$2,0))} -> 8285274.9 | V5: SERVICE | W5: 0.225
A6: Véhicules neufsAutos détail | B6: Véhicules neufs | C6: Autos détail | D6: =+INDEX('[5]Budget original'!$A$2:$AO$501,MATCH($A6,'[5]Budget original'!$A$2:$A$501,0),MATCH(D$2,'[5]Budget original'!$A$2:$AO$2,0)) -> 14.4 | E6: =IF(D6=0,0,F6/D6) -> 2198.1219 | F6: =+INDEX('[5]Budget original'!$A$2:$AO$501,MATCH($A6,'[5]Budget original'!$A$2:$A$501,0),MATCH(F$2,'[5]Budget original'!$A$2:$AO$2,0)) -> 31652.956 | J6: =-SUMIFS([5]BV_Data_An_Cour!$O:$O,[5]BV_Data_An_Cour!$U:$U,$B6,[5]BV_Data_An_Cour!$V:$V,$C6,[5]BV_Data_An_Cour!$W:$W,J$2) -> 12 | K6: =IF(J6=0,0,L6/J6) -> 1802.2583 | L6: =-SUMIFS([5]BV_Data_An_Cour!$O:$O,[5]BV_Data_An_Cour!$U:$U,$B6,[5]BV_Data_An_Cour!$V:$V,$C6,[5]BV_Data_An_Cour!$W:$W,L$2) -> 21627.1 | M6: =J6-D6 -> -2.4 | N6: =L6-F6 -> -10025.856 | O6: =+INDEX('[5]Réel 2023'!$A$2:$AO$501,MATCH($A6,'[5]Réel 2023'!$A$2:$A$501,0),MATCH(O$2,'[5]Réel 2023'!$A$2:$AO$2,0)) -> 14 | P6: =IF(O6=0,0,Q6/O6) -> 2125.1657 | Q6: {=+INDEX('[5]Réel 2023'!$A$2:$AO$501,MATCH($A6,'[5]Réel 2023'!$A$2:$A$501,0),MATCH(Q$2,'[5]Réel 2023'!$A$2:$AO$2,0))} -> 29752.32 | R6: =J6-O6 -> -2 | S6: =L6-Q6 -> -8125.22 | V6: CARROSSERIE | W6: 0.025
A7: Véhicules neufsCamions détail | B7: Véhicules neufs | C7: Camions détail | D7: =+INDEX('[5]Budget original'!$A$2:$AO$501,MATCH($A7,'[5]Budget original'!$A$2:$A$501,0),MATCH(D$2,'[5]Budget original'!$A$2:$AO$2,0)) -> 59.52 | E7: =IF(D7=0,0,F7/D7) -> 2873.2447 | F7: =+INDEX('[5]Budget original'!$A$2:$AO$501,MATCH($A7,'[5]Budget original'!$A$2:$A$501,0),MATCH(F$2,'[5]Budget original'!$A$2:$AO$2,0)) -> 171015.52 | J7: =-SUMIFS([5]BV_Data_An_Cour!$O:$O,[5]BV_Data_An_Cour!$U:$U,$B7,[5]BV_Data_An_Cour!$V:$V,$C7,[5]BV_Data_An_Cour!$W:$W,J$2) -> 32 | K7: =IF(J7=0,0,L7/J7) -> 1508.5388 | L7: =-SUMIFS([5]BV_Data_An_Cour!$O:$O,[5]BV_Data_An_Cour!$U:$U,$B7,[5]BV_Data_An_Cour!$V:$V,$C7,[5]BV_Data_An_Cour!$W:$W,L$2) -> 48273.24 | M7: =J7-D7 -> -27.52 | N7: =L7-F7 -> -122742.28 | O7: {=+INDEX('[5]Réel 2023'!$A$2:$AO$501,MATCH($A7,'[5]Réel 2023'!$A$2:$A$501,0),MATCH(O$2,'[5]Réel 2023'!$A$2:$AO$2,0))} -> 45 | P7: =IF(O7=0,0,Q7/O7) -> 2647.1667 | Q7: {=+INDEX('[5]Réel 2023'!$A$2:$AO$501,MATCH($A7,'[5]Réel 2023'!$A$2:$A$501,0),MATCH(Q$2,'[5]Réel 2023'!$A$2:$AO$2,0))} -> 119122.5 | R7: =J7-O7 -> -13 | S7: =L7-Q7 -> -70849.26 | V7: PIECES | W7: 0.2
A8: Véhicules neufsSprinter | B8: Véhicules neufs | C8: Sprinter | D8: =+INDEX('[5]Budget original'!$A$2:$AO$501,MATCH($A8,'[5]Budget original'!$A$2:$A$501,0),MATCH(D$2,'[5]Budget original'!$A$2:$AO$2,0)) -> 0 | E8: =IF(D8=0,0,F8/D8) -> 0 | F8: =+INDEX('[5]Budget original'!$A$2:$AO$501,MATCH($A8,'[5]Budget original'!$A$2:$A$501,0),MATCH(F$2,'[5]Budget original'!$A$2:$AO$2,0)) -> 0 | J8: =-SUMIFS([5]BV_Data_An_Cour!$O:$O,[5]BV_Data_An_Cour!$U:$U,$B8,[5]BV_Data_An_Cour!$V:$V,$C8,[5]BV_Data_An_Cour!$W:$W,J$2) -> 0 | K8: =IF(J8=0,0,L8/J8) -> 0 | L8: =-SUMIFS([5]BV_Data_An_Cour!$O:$O,[5]BV_Data_An_Cour!$U:$U,$B8,[5]BV_Data_An_Cour!$V:$V,$C8,[5]BV_Data_An_Cour!$W:$W,L$2) -> 0 | M8: =J8-D8 -> 0 | N8: =L8-F8 -> 0 | O8: {=+INDEX('[5]Réel 2023'!$A$2:$AO$501,MATCH($A8,'[5]Réel 2023'!$A$2:$A$501,0),MATCH(O$2,'[5]Réel 2023'!$A$2:$AO$2,0))} -> 0 | P8: =IF(O8=0,0,Q8/O8) -> 0 | Q8: {=+INDEX('[5]Réel 2023'!$A$2:$AO$501,MATCH($A8,'[5]Réel 2023'!$A$2:$A$501,0),MATCH(Q$2,'[5]Réel 2023'!$A$2:$AO$2,0))} -> 0 | R8: =J8-O8 -> 0 | S8: =L8-Q8 -> 0 | W8: =SUM(W3:W7) -> 1
A9: Véhicules neufsMoto détail | B9: Véhicules neufs | C9: Moto détail | D9: =+INDEX('[5]Budget original'!$A$2:$AO$501,MATCH($A9,'[5]Budget original'!$A$2:$A$501,0),MATCH(D$2,'[5]Budget original'!$A$2:$AO$2,0)) -> 0 | E9: =IF(D9=0,0,F9/D9) -> 0 | F9: =+INDEX('[5]Budget original'!$A$2:$AO$501,MATCH($A9,'[5]Budget original'!$A$2:$A$501,0),MATCH(F$2,'[5]Budget original'!$A$2:$AO$2,0)) -> 0 | J9: =-SUMIFS([5]BV_Data_An_Cour!$O:$O,[5]BV_Data_An_Cour!$U:$U,$B9,[5]BV_Data_An_Cour!$V:$V,$C9,[5]BV_Data_An_Cour!$W:$W,J$2) -> 0 | K9: =IF(J9=0,0,L9/J9) -> 0 | L9: =-SUMIFS([5]BV_Data_An_Cour!$O:$O,[5]BV_Data_An_Cour!$U:$U,$B9,[5]BV_Data_An_Cour!$V:$V,$C9,[5]BV_Data_An_Cour!$W:$W,L$2) -> 0 | M9: =J9-D9 -> 0 | N9: =L9-F9 -> 0 | O9: {=+INDEX('[5]Réel 2023'!$A$2:$AO$501,MATCH($A9,'[5]Réel 2023'!$A$2:$A$501,0),MATCH(O$2,'[5]Réel 2023'!$A$2:$AO$2,0))} -> 0 | P9: =IF(O9=0,0,Q9/O9) -> 0 | Q9: {=+INDEX('[5]Réel 2023'!$A$2:$AO$501,MATCH($A9,'[5]Réel 2023'!$A$2:$A$501,0),MATCH(Q$2,'[5]Réel 2023'!$A$2:$AO$2,0))} -> 0 | R9: =J9-O9 -> 0 | S9: =L9-Q9 -> 0
A10: Véhicules neufs[...] | B10: Véhicules neufs | C10: [...] | D10: =+INDEX('[5]Budget original'!$A$2:$AO$501,MATCH($A10,'[5]Budget original'!$A$2:$A$501,0),MATCH(D$2,'[5]Budget original'!$A$2:$AO$2,0)) -> 0 | E10: =IF(D10=0,0,F10/D10) -> 0 | F10: =+INDEX('[5]Budget original'!$A$2:$AO$501,MATCH($A10,'[5]Budget original'!$A$2:$A$501,0),MATCH(F$2,'[5]Budget original'!$A$2:$AO$2,0)) -> 0 | J10: =-SUMIFS([5]BV_Data_An_Cour!$O:$O,[5]BV_Data_An_Cour!$U:$U,$B10,[5]BV_Data_An_Cour!$V:$V,$C10,[5]BV_Data_An_Cour!$W:$W,J$2) -> 0 | K10: =IF(J10=0,0,L10/J10) -> 0 | L10: =-SUMIFS([5]BV_Data_An_Cour!$O:$O,[5]BV_Data_An_Cour!$U:$U,$B10,[5]BV_Data_An_Cour!$V:$V,$C10,[5]BV_Data_An_Cour!$W:$W,L$2) -> 0 | M10: =J10-D10 -> 0 | N10: =L10-F10 -> 0 | O10: {=+INDEX('[5]Réel 2023'!$A$2:$AO$501,MATCH($A10,'[5]Réel 2023'!$A$2:$A$501,0),MATCH(O$2,'[5]Réel 2023'!$A$2:$AO$2,0))} -> 0 | P10: =IF(O10=0,0,Q10/O10) -> 0 | Q10: {=+INDEX('[5]Réel 2023'!$A$2:$AO$501,MATCH($A10,'[5]Réel 2023'!$A$2:$A$501,0),MATCH(Q$2,'[5]Réel 2023'!$A$2:$AO$2,0))} -> 0 | R10: =J10-O10 -> 0 | S10: =L10-Q10 -> 0
A11: Véhicules neufs[...] | B11: Véhicules neufs | C11: [...] | D11: =+INDEX('[5]Budget original'!$A$2:$AO$501,MATCH($A11,'[5]Budget original'!$A$2:$A$501,0),MATCH(D$2,'[5]Budget original'!$A$2:$AO$2,0)) -> 0 | E11: =IF(D11=0,0,F11/D11) -> 0 | F11: =+INDEX('[5]Budget original'!$A$2:$AO$501,MATCH($A11,'[5]Budget original'!$A$2:$A$501,0),MATCH(F$2,'[5]Budget original'!$A$2:$AO$2,0)) -> 0 | J11: =-SUMIFS([5]BV_Data_An_Cour!$O:$O,[5]BV_Data_An_Cour!$U:$U,$B11,[5]BV_Data_An_Cour!$V:$V,$C11,[5]BV_Data_An_Cour!$W:$W,J$2) -> 0 | K11: =IF(J11=0,0,L11/J11) -> 0 | L11: =-SUMIFS([5]BV_Data_An_Cour!$O:$O,[5]BV_Data_An_Cour!$U:$U,$B11,[5]BV_Data_An_Cour!$V:$V,$C11,[5]BV_Data_An_Cour!$W:$W,L$2) -> 0 | M11: =J11-D11 -> 0 | N11: =L11-F11 -> 0 | O11: {=+INDEX('[5]Réel 2023'!$A$2:$AO$501,MATCH($A11,'[5]Réel 2023'!$A$2:$A$501,0),MATCH(O$2,'[5]Réel 2023'!$A$2:$AO$2,0))} -> 0 | P11: =IF(O11=0,0,Q11/O11) -> 0 | Q11: {=+INDEX('[5]Réel 2023'!$A$2:$AO$501,MATCH($A11,'[5]Réel 2023'!$A$2:$A$501,0),MATCH(Q$2,'[5]Réel 2023'!$A$2:$AO$2,0))} -> 0 | R11: =J11-O11 -> 0 | S11: =L11-Q11 -> 0
A12: Véhicules neufs[...] | B12: Véhicules neufs | C12: [...] | D12: =+INDEX('[5]Budget original'!$A$2:$AO$501,MATCH($A12,'[5]Budget original'!$A$2:$A$501,0),MATCH(D$2,'[5]Budget original'!$A$2:$AO$2,0)) -> 0 | E12: =IF(D12=0,0,F12/D12) -> 0 | F12: =+INDEX('[5]Budget original'!$A$2:$AO$501,MATCH($A12,'[5]Budget original'!$A$2:$A$501,0),MATCH(F$2,'[5]Budget original'!$A$2:$AO$2,0)) -> 0 | J12: =-SUMIFS([5]BV_Data_An_Cour!$O:$O,[5]BV_Data_An_Cour!$U:$U,$B12,[5]BV_Data_An_Cour!$V:$V,$C12,[5]BV_Data_An_Cour!$W:$W,J$2) -> 0 | K12: =IF(J12=0,0,L12/J12) -> 0 | L12: =-SUMIFS([5]BV_Data_An_Cour!$O:$O,[5]BV_Data_An_Cour!$U:$U,$B12,[5]BV_Data_An_Cour!$V:$V,$C12,[5]BV_Data_An_Cour!$W:$W,L$2) -> 0 | M12: =J12-D12 -> 0 | N12: =L12-F12 -> 0 | O12: {=+INDEX('[5]Réel 2023'!$A$2:$AO$501,MATCH($A12,'[5]Réel 2023'!$A$2:$A$501,0),MATCH(O$2,'[5]Réel 2023'!$A$2:$AO$2,0))} -> 0 | P12: =IF(O12=0,0,Q12/O12) -> 0 | Q12: {=+INDEX('[5]Réel 2023'!$A$2:$AO$501,MATCH($A12,'[5]Réel 2023'!$A$2:$A$501,0),MATCH(Q$2,'[5]Réel 2023'!$A$2:$AO$2,0))} -> 0 | R12: =J12-O12 -> 0 | S12: =L12-Q12 -> 0
A13: Véhicules neufsTotal Neufs | B13: Véhicules neufs | C13: Total Neufs | D13: =+SUM(D6:D12) -> 73.92 | E13: =IF(D13<=0,0,F13/D13) -> 2741.7272 | F13: =+SUM(F6:F12) -> 202668.48 | J13: =+SUM(J6:J12) -> 44 | K13: =IF(J13<=0,0,L13/J13) -> 1588.6441 | L13: =+SUM(L6:L12) -> 69900.34 | M13: =+SUM(M6:M12) -> -29.92 | N13: =+SUM(N6:N12) -> -132768.14 | O13: =+SUM(O6:O12) -> 59 | P13: =IF(O13<=0,0,Q13/O13) -> 2523.302 | Q13: =+SUM(Q6:Q12) -> 148874.82 | R13: =+SUM(R6:R12) -> -15 | S13: =+SUM(S6:S12) -> -78974.48
A14: Véhicules neufs | B14: Véhicules neufs | M14: =IF(D13=0,0,M13/D13) -> -0.4047619 | N14: =IF(F13=0,0,N13/F13) -> -0.65510009 | R14: =R13/O13 -> -0.25423729 | S14: =IF(Q13=0,0,(S13/Q13)) -> -0.53047574 | AD14: 20 | AE14: 1000 | AF14: =AD14*AE14 -> 20000
A15: Véhicules neufsEx-Démos et courtoisies | B15: Véhicules neufs | C15: Ex-Démos et courtoisies | D15: =+INDEX('[5]Budget original'!$A$2:$AO$501,MATCH($A15,'[5]Budget original'!$A$2:$A$501,0),MATCH(D$2,'[5]Budget original'!$A$2:$AO$2,0)) -> 5.88 | E15: =IF(D15=0,0,F15/D15) -> 2535.1216 | F15: =+INDEX('[5]Budget original'!$A$2:$AO$501,MATCH($A15,'[5]Budget original'!$A$2:$A$501,0),MATCH(F$2,'[5]Budget original'!$A$2:$AO$2,0)) -> 14906.515 | J15: =-SUMIFS([5]BV_Data_An_Cour!$O:$O,[5]BV_Data_An_Cour!$U:$U,$B15,[5]BV_Data_An_Cour!$V:$V,$C15,[5]BV_Data_An_Cour!$W:$W,J$2) -> 6 | K15: =IF(J15=0,0,L15/J15) -> 1038.8833 | L15: =-SUMIFS([5]BV_Data_An_Cour!$O:$O,[5]BV_Data_An_Cour!$U:$U,$B15,[5]BV_Data_An_Cour!$V:$V,$C15,[5]BV_Data_An_Cour!$W:$W,L$2) -> 6233.3 | M15: =J15-D15 -> 0.12 | N15: =L15-F15 -> -8673.2149 | O15: {=+INDEX('[5]Réel 2023'!$A$2:$AO$501,MATCH($A15,'[5]Réel 2023'!$A$2:$A$501,0),MATCH(O$2,'[5]Réel 2023'!$A$2:$AO$2,0))} -> 0 | P15: =IF(O15=0,0,Q15/O15) -> 0 | Q15: {=+INDEX('[5]Réel 2023'!$A$2:$AO$501,MATCH($A15,'[5]Réel 2023'!$A$2:$A$501,0),MATCH(Q$2,'[5]Réel 2023'!$A$2:$AO$2,0))} -> 3550 | R15: =J15-O15 -> 6 | S15: =L15-Q15 -> 2683.3 | AD15: 25 | AE15: =AF15/AD15 -> 800 | AF15: =AF14 -> 20000
A16: Véhicules neufs | B16: Véhicules neufs
A17: Véhicules neufsFlottes | B17: Véhicules neufs | C17: Flottes | D17: =+INDEX('[5]Budget original'!$A$2:$AO$501,MATCH($A17,'[5]Budget original'!$A$2:$A$501,0),MATCH(D$2,'[5]Budget original'!$A$2:$AO$2,0)) -> 5.4 | E17: =IF(D17=0,0,F17/D17) -> 2664.4641 | F17: =+INDEX('[5]Budget original'!$A$2:$AO$501,MATCH($A17,'[5]Budget original'!$A$2:$A$501,0),MATCH(F$2,'[5]Budget original'!$A$2:$AO$2,0)) -> 14388.106 | J17: =-SUMIFS([5]BV_Data_An_Cour!$O:$O,[5]BV_Data_An_Cour!$U:$U,$B17,[5]BV_Data_An_Cour!$V:$V,$C17,[5]BV_Data_An_Cour!$W:$W,J$2) -> 2 | K17: =IF(J17=0,0,L17/J17) -> 383.48 | L17: =-SUMIFS([5]BV_Data_An_Cour!$O:$O,[5]BV_Data_An_Cour!$U:$U,$B17,[5]BV_Data_An_Cour!$V:$V,$C17,[5]BV_Data_An_Cour!$W:$W,L$2) -> 766.96 | M17: =J17-D17 -> -3.4 | N17: =L17-F17 -> -13621.146 | O17: {=+INDEX('[5]Réel 2023'!$A$2:$AO$501,MATCH($A17,'[5]Réel 2023'!$A$2:$A$501,0),MATCH(O$2,'[5]Réel 2023'!$A$2:$AO$2,0))} -> 8 | P17: =IF(O17=0,0,Q17/O17) -> 3193.38 | Q17: {=+INDEX('[5]Réel 2023'!$A$2:$AO$501,MATCH($A17,'[5]Réel 2023'!$A$2:$A$501,0),MATCH(Q$2,'[5]Réel 2023'!$A$2:$AO$2,0))} -> 25547.04 | R17: =J17-O17 -> -6 | S17: =L17-Q17 -> -24780.08
A18: Véhicules neufs | B18: Véhicules neufs
A19: Véhicules neufsRachat bail | B19: Véhicules neufs | C19: Rachat bail | D19: =+INDEX('[5]Budget original'!$A$2:$AO$501,MATCH($A19,'[5]Budget original'!$A$2:$A$501,0),MATCH(D$2,'[5]Budget original'!$A$2:$AO$2,0)) -> 0 | E19: =IF(D19=0,0,F19/D19) -> 0 | F19: =+INDEX('[5]Budget original'!$A$2:$AO$501,MATCH($A19,'[5]Budget original'!$A$2:$A$501,0),MATCH(F$2,'[5]Budget original'!$A$2:$AO$2,0)) -> 10200 | L19: =-SUMIFS([5]BV_Data_An_Cour!$O:$O,[5]BV_Data_An_Cour!$U:$U,$B19,[5]BV_Data_An_Cour!$V:$V,$C19,[5]BV_Data_An_Cour!$W:$W,L$2) -> 10100 | N19: =L19-F19 -> -100 | Q19: {=+INDEX('[5]Réel 2023'!$A$2:$AO$501,MATCH($A19,'[5]Réel 2023'!$A$2:$A$501,0),MATCH(Q$2,'[5]Réel 2023'!$A$2:$AO$2,0))} -> 8229.71 | R19: =O19-K19 -> 0 | S19: =L19-Q19 -> 1870.29
A20: Véhicules neufs | B20: Véhicules neufs
A21: Véhicules neufsRev. Finances | B21: Véhicules neufs | C21: Rev. Finances | D21: =+INDEX('[5]Budget original'!$A$2:$AO$501,MATCH($A21,'[5]Budget original'!$A$2:$A$501,0),MATCH(D$2,'[5]Budget original'!$A$2:$AO$2,0)) -> 0 | E21: =IF(D21=0,0,F21/D21) -> 0 | F21: =+INDEX('[5]Budget original'!$A$2:$AO$501,MATCH($A21,'[5]Budget original'!$A$2:$A$501,0),MATCH(F$2,'[5]Budget original'!$A$2:$AO$2,0)) -> 15960 | K21: =IF(J13=0,0,L21/(J13+J15)) -> 0 | L21: =-SUMIFS([5]BV_Data_An_Cour!$O:$O,[5]BV_Data_An_Cour!$U:$U,$B21,[5]BV_Data_An_Cour!$V:$V,$C21,[5]BV_Data_An_Cour!$W:$W,L$2) -> 0 | N21: =L21-F21 -> -15960 | Q21: {=+INDEX('[5]Réel 2023'!$A$2:$AO$501,MATCH($A21,'[5]Réel 2023'!$A$2:$A$501,0),MATCH(Q$2,'[5]Réel 2023'!$A$2:$AO$2,0))} -> 3481.61 | R21: =O21-K21 -> 0 | S21: =L21-Q21 -> -3481.61
A22: Véhicules neufsRev. Protections | B22: Véhicules neufs | C22: Rev. Protections | D22: =+INDEX('[5]Budget original'!$A$2:$AO$501,MATCH($A22,'[5]Budget original'!$A$2:$A$501,0),MATCH(D$2,'[5]Budget original'!$A$2:$AO$2,0)) -> 0 | E22: =IF(D22=0,0,F22/D22) -> 0 | F22: =+INDEX('[5]Budget original'!$A$2:$AO$501,MATCH($A22,'[5]Budget original'!$A$2:$A$501,0),MATCH(F$2,'[5]Budget original'!$A$2:$AO$2,0)) -> 86184 | K22: =IF(J13=0,0,L22/(J13+J15)) -> 844.5266 | L22: =-SUMIFS([5]BV_Data_An_Cour!$O:$O,[5]BV_Data_An_Cour!$U:$U,$B22,[5]BV_Data_An_Cour!$V:$V,$C22,[5]BV_Data_An_Cour!$W:$W,L$2) -> 42226.33 | N22: =L22-F22 -> -43957.67 | Q22: {=+INDEX('[5]Réel 2023'!$A$2:$AO$501,MATCH($A22,'[5]Réel 2023'!$A$2:$A$501,0),MATCH(Q$2,'[5]Réel 2023'!$A$2:$AO$2,0))} -> 55582.9 | R22: =O22-K22 -> -844.5266 | S22: =L22-Q22 -> -13356.57
A23: Véhicules neufsRev. Autres | B23: Véhicules neufs | C23: Rev. Autres | D23: =+INDEX('[5]Budget original'!$A$2:$AO$501,MATCH($A23,'[5]Budget original'!$A$2:$A$501,0),MATCH(D$2,'[5]Budget original'!$A$2:$AO$2,0)) -> 0 | E23: =IF(D23=0,0,F23/D23) -> 0 | F23: =+INDEX('[5]Budget original'!$A$2:$AO$501,MATCH($A23,'[5]Budget original'!$A$2:$A$501,0),MATCH(F$2,'[5]Budget original'!$A$2:$AO$2,0)) -> 1596 | K23: =IF(J13=0,0,L23/(J13+J15)) -> 12.8804 | L23: =-SUMIFS([5]BV_Data_An_Cour!$O:$O,[5]BV_Data_An_Cour!$U:$U,$B23,[5]BV_Data_An_Cour!$V:$V,$C23,[5]BV_Data_An_Cour!$W:$W,L$2) -> 644.02 | N23: =L23-F23 -> -951.98 | Q23: {=+INDEX('[5]Réel 2023'!$A$2:$AO$501,MATCH($A23,'[5]Réel 2023'!$A$2:$A$501,0),MATCH(Q$2,'[5]Réel 2023'!$A$2:$AO$2,0))} -> 398.21 | R23: =O23-K23 -> -12.8804 | S23: =L23-Q23 -> 245.81
A24: Véhicules neufsTotal F&I | B24: Véhicules neufs | C24: Total F&I | D24: =+D15+D13 -> 79.8 | E24: =IF(D24<=0,0,F24/D24) -> 1300 | F24: =F21+F22+F23 -> 103740 | J24: =+J15+J13 -> 50 | K24: =IF(J24<=0,0,L24/J24) -> 857.407 | L24: =L21+L22+L23 -> 42870.35 | M24: =J24-D24 -> -29.8 | N24: =L24-F24 -> -60869.65 | O24: =+O15+O13 -> 59 | P24: =IF(O24<=0,0,Q24/O24) -> 1007.8427 | Q24: =Q21+Q22+Q23 -> 59462.72 | S24: =L24-Q24 -> -16592.37
A25: Véhicules neufs | B25: Véhicules neufs | N25: =IF(N24=0,0,N24/F24) -> -0.58675198 | S25: =IF(Q24=0,0,(S24/Q24)) -> -0.27903819
A26: Véhicules neufs | B26: Véhicules neufs
A27: Véhicules neufsTotal Dépt. Neufs | B27: Véhicules neufs | C27: Total Dépt. Neufs | D27: =+D13+D15+D17 -> 85.2 | E27: =IF(D27<=0,0,F27/D27) -> 4059.8955 | F27: =F13+F17+F24+F19+F15 -> 345903.1 | J27: =+J13+J15+J17 -> 52 | K27: =IF(J27<=0,0,L27/J27) -> 2497.5183 | L27: =L13+L17+L24+L19+L15 -> 129870.95 | M27: =J27-D27 -> -33.2 | N27: =L27-F27 -> -216032.15 | O27: =+O13+O15+O17 -> 67 | P27: =IF(O27<=0,0,Q27/O27) -> 3666.6312 | Q27: =Q13+Q17+Q24+Q19+Q15 -> 245664.29 | R27: =J27-O27 -> -15 | S27: =L27-Q27 -> -115793.34
A28: Véhicules neufs | B28: Véhicules neufs | L28: =L27/F27 -> 0.37545472 | M28: =M27/D27 -> -0.38967136 | N28: =N27/F27 -> -0.62454528 | R28: =R27/O27 -> -0.2238806 | S28: =IF(Q27=0,0,S27/Q27) -> -0.47134787
A29: Véhicules neufs | B29: Véhicules neufs
A30: Véhicules neufsDEPENSES | B30: Véhicules neufs | C30: DEPENSES
A31: Véhicules neufsComm. vendeurs | B31: Véhicules neufs | C31: Comm. vendeurs | D31: =F31/(F13+F15) -> 0.34 | E31: =F31/D$24 -> 927.01125 | F31: =+INDEX('[5]Budget original'!$A$2:$AO$501,MATCH($A31,'[5]Budget original'!$A$2:$A$501,0),MATCH(F$2,'[5]Budget original'!$A$2:$AO$2,0)) -> 73975.497 | J31: =L31/(L15+L13+L17) -> 0.36538037 | K31: =IF(L31=0,0,L31/J$24) -> 561.9594 | L31: =SUMIFS([5]BV_Data_An_Cour!$O:$O,[5]BV_Data_An_Cour!$U:$U,$B31,[5]BV_Data_An_Cour!$V:$V,$C31,[5]BV_Data_An_Cour!$W:$W,L$2) -> 28097.97 | N31: =L31-F31 -> -45877.527 | O31: =Q31/(Q13+Q15+Q17) -> 0.23546953 | P31: =Q31/O$24 -> 710.28729 | Q31: {=+INDEX('[5]Réel 2023'!$A$2:$AO$501,MATCH($A31,'[5]Réel 2023'!$A$2:$A$501,0),MATCH(Q$2,'[5]Réel 2023'!$A$2:$AO$2,0))} -> 41906.95 | S31: =L31-Q31 -> -13808.98
A32: Véhicules neufsComm. F&I | B32: Véhicules neufs | C32: Comm. F&I | D32: =F32/F24 -> 0.3 | E32: =F32/D$24 -> 390 | F32: =+INDEX('[5]Budget original'!$A$2:$AO$501,MATCH($A32,'[5]Budget original'!$A$2:$A$501,0),MATCH(F$2,'[5]Budget original'!$A$2:$AO$2,0)) -> 31122 | J32: =L32/L24 -> 0.26999336 | K32: =IF(L32=0,0,L32/J$24) -> 231.4942 | L32: =SUMIFS([5]BV_Data_An_Cour!$O:$O,[5]BV_Data_An_Cour!$U:$U,$B32,[5]BV_Data_An_Cour!$V:$V,$C32,[5]BV_Data_An_Cour!$W:$W,L$2) -> 11574.71 | N32: =L32-F32 -> -19547.29 | O32: =Q32/Q24 -> 0.29873305 | P32: =Q32/O$24 -> 301.07593 | Q32: {=+INDEX('[5]Réel 2023'!$A$2:$AO$501,MATCH($A32,'[5]Réel 2023'!$A$2:$A$501,0),MATCH(Q$2,'[5]Réel 2023'!$A$2:$AO$2,0))} -> 17763.48 | S32: =L32-Q32 -> -6188.77
A33: Véhicules neufsFrais de livraison | B33: Véhicules neufs | C33: Frais de livraison | E33: =F33/D$24 -> 115 | F33: =+INDEX('[5]Budget original'!$A$2:$AO$501,MATCH($A33,'[5]Budget original'!$A$2:$A$501,0),MATCH(F$2,'[5]Budget original'!$A$2:$AO$2,0)) -> 9177 | K33: =IF(L33=0,0,L33/J$24) -> 156.3466 | L33: =SUMIFS([5]BV_Data_An_Cour!$O:$O,[5]BV_Data_An_Cour!$U:$U,$B33,[5]BV_Data_An_Cour!$V:$V,$C33,[5]BV_Data_An_Cour!$W:$W,L$2) -> 7817.33 | N33: =L33-F33 -> -1359.67 | P33: =Q33/O$24 -> 131.92102 | Q33: {=+INDEX('[5]Réel 2023'!$A$2:$AO$501,MATCH($A33,'[5]Réel 2023'!$A$2:$A$501,0),MATCH(Q$2,'[5]Réel 2023'!$A$2:$AO$2,0))} -> 7783.34 | S33: =L33-Q33 -> 33.99
A34: Véhicules neufsService gratuit 1 | B34: Véhicules neufs | C34: Service gratuit 1 | E34: =F34/D$24 -> 3 | F34: =+INDEX('[5]Budget original'!$A$2:$AO$501,MATCH($A34,'[5]Budget original'!$A$2:$A$501,0),MATCH(F$2,'[5]Budget original'!$A$2:$AO$2,0)) -> 239.4 | K34: =IF(L34=0,0,L34/J$24) -> 16.8636 | L34: =SUMIFS([5]BV_Data_An_Cour!$O:$O,[5]BV_Data_An_Cour!$U:$U,$B34,[5]BV_Data_An_Cour!$V:$V,$C34,[5]BV_Data_An_Cour!$W:$W,L$2) -> 843.18 | N34: =L34-F34 -> 603.78 | P34: =Q34/O$24 -> 9.4247458 | Q34: {=+INDEX('[5]Réel 2023'!$A$2:$AO$501,MATCH($A34,'[5]Réel 2023'!$A$2:$A$501,0),MATCH(Q$2,'[5]Réel 2023'!$A$2:$AO$2,0))} -> 556.06 | S34: =L34-Q34 -> 287.12
A35: Véhicules neufsEntretien stock | B35: Véhicules neufs | C35: Entretien stock | E35: =F35/D$24 -> 85.05 | F35: =+INDEX('[5]Budget original'!$A$2:$AO$501,MATCH($A35,'[5]Budget original'!$A$2:$A$501,0),MATCH(F$2,'[5]Budget original'!$A$2:$AO$2,0)) -> 6786.99 | K35: =IF(L35=0,0,L35/J$24) -> 159.8588 | L35: =SUMIFS([5]BV_Data_An_Cour!$O:$O,[5]BV_Data_An_Cour!$U:$U,$B35,[5]BV_Data_An_Cour!$V:$V,$C35,[5]BV_Data_An_Cour!$W:$W,L$2) -> 7992.94 | N35: =L35-F35 -> 1205.95 | P35: =Q35/O$24 -> 92.110169 | Q35: {=+INDEX('[5]Réel 2023'!$A$2:$AO$501,MATCH($A35,'[5]Réel 2023'!$A$2:$A$501,0),MATCH(Q$2,'[5]Réel 2023'!$A$2:$AO$2,0))} -> 5434.5 | S35: =L35-Q35 -> 2558.44
A36: Véhicules neufsPublicité 1 | B36: Véhicules neufs | C36: Publicité 1 | E36: =F36/D$24 -> 78.39599 | F36: =+INDEX('[5]Budget original'!$A$2:$AO$501,MATCH($A36,'[5]Budget original'!$A$2:$A$501,0),MATCH(F$2,'[5]Budget original'!$A$2:$AO$2,0)) -> 6256 | K36: =IF(L36=0,0,L36/J$24) -> 224.6836 | L36: =SUMIFS([5]BV_Data_An_Cour!$O:$O,[5]BV_Data_An_Cour!$U:$U,$B36,[5]BV_Data_An_Cour!$V:$V,$C36,[5]BV_Data_An_Cour!$W:$W,L$2) -> 11234.18 | N36: =L36-F36 -> 4978.18 | P36: =Q36/O$24 -> 155.86983 | Q36: {=+INDEX('[5]Réel 2023'!$A$2:$AO$501,MATCH($A36,'[5]Réel 2023'!$A$2:$A$501,0),MATCH(Q$2,'[5]Réel 2023'!$A$2:$AO$2,0))} -> 9196.32 | S36: =L36-Q36 -> 2037.86
A37: Véhicules neufsIntérêt de gros | B37: Véhicules neufs | C37: Intérêt de gros | E37: =F37/D$24 -> 242.16209 | F37: =+INDEX('[5]Budget original'!$A$2:$AO$501,MATCH($A37,'[5]Budget original'!$A$2:$A$501,0),MATCH(F$2,'[5]Budget original'!$A$2:$AO$2,0)) -> 19324.535 | K37: =IF(L37=0,0,L37/J$24) -> 530.407 | L37: =SUMIFS([5]BV_Data_An_Cour!$O:$O,[5]BV_Data_An_Cour!$U:$U,$B37,[5]BV_Data_An_Cour!$V:$V,$C37,[5]BV_Data_An_Cour!$W:$W,L$2) -> 26520.35 | N37: =L37-F37 -> 7195.8149 | P37: =Q37/O$24 -> 0 | Q37: {=+INDEX('[5]Réel 2023'!$A$2:$AO$501,MATCH($A37,'[5]Réel 2023'!$A$2:$A$501,0),MATCH(Q$2,'[5]Réel 2023'!$A$2:$AO$2,0))} -> 0 | S37: =L37-Q37 -> 26520.35
A38: Véhicules neufs[...] | B38: Véhicules neufs | C38: [...] | E38: =F38/D$24 -> 0 | F38: =+INDEX('[5]Budget original'!$A$2:$AO$501,MATCH($A38,'[5]Budget original'!$A$2:$A$501,0),MATCH(F$2,'[5]Budget original'!$A$2:$AO$2,0)) -> 0 | K38: =IF(L38=0,0,L38/J$24) -> 0 | L38: =SUMIFS([5]BV_Data_An_Cour!$O:$O,[5]BV_Data_An_Cour!$U:$U,$B38,[5]BV_Data_An_Cour!$V:$V,$C38,[5]BV_Data_An_Cour!$W:$W,L$2) -> 0 | N38: =L38-F38 -> 0 | P38: =Q38/O$24 -> 0 | Q38: {=+INDEX('[5]Réel 2023'!$A$2:$AO$501,MATCH($A38,'[5]Réel 2023'!$A$2:$A$501,0),MATCH(Q$2,'[5]Réel 2023'!$A$2:$AO$2,0))} -> 0 | S38: =L38-Q38 -> 0
A39: Véhicules neufs[...] | B39: Véhicules neufs | C39: [...] | E39: =F39/D$24 -> 0 | F39: =+INDEX('[5]Budget original'!$A$2:$AO$501,MATCH($A39,'[5]Budget original'!$A$2:$A$501,0),MATCH(F$2,'[5]Budget original'!$A$2:$AO$2,0)) -> 0 | K39: =IF(L39=0,0,L39/J$24) -> 0 | L39: =SUMIFS([5]BV_Data_An_Cour!$O:$O,[5]BV_Data_An_Cour!$U:$U,$B39,[5]BV_Data_An_Cour!$V:$V,$C39,[5]BV_Data_An_Cour!$W:$W,L$2) -> 0 | N39: =L39-F39 -> 0 | P39: =Q39/O$24 -> 0 | Q39: {=+INDEX('[5]Réel 2023'!$A$2:$AO$501,MATCH($A39,'[5]Réel 2023'!$A$2:$A$501,0),MATCH(Q$2,'[5]Réel 2023'!$A$2:$AO$2,0))} -> 0 | S39: =L39-Q39 -> 0
A40: Véhicules neufs[...] | B40: Véhicules neufs | C40: [...] | E40: =F40/D$24 -> 0 | F40: =+INDEX('[5]Budget original'!$A$2:$AO$501,MATCH($A40,'[5]Budget original'!$A$2:$A$501,0),MATCH(F$2,'[5]Budget original'!$A$2:$AO$2,0)) -> 0 | K40: =IF(L40=0,0,L40/J$24) -> 0 | L40: =SUMIFS([5]BV_Data_An_Cour!$O:$O,[5]BV_Data_An_Cour!$U:$U,$B40,[5]BV_Data_An_Cour!$V:$V,$C40,[5]BV_Data_An_Cour!$W:$W,L$2) -> 0 | N40: =L40-F40 -> 0 | P40: =Q40/O$24 -> 0 | Q40: {=+INDEX('[5]Réel 2023'!$A$2:$AO$501,MATCH($A40,'[5]Réel 2023'!$A$2:$A$501,0),MATCH(Q$2,'[5]Réel 2023'!$A$2:$AO$2,0))} -> 0 | S40: =L40-Q40 -> 0
A41: Véhicules neufsTOTAL VARIABLES | B41: Véhicules neufs | C41: TOTAL VARIABLES | D41: % brut | E41: =F41/F$27 -> 0.42463171 | F41: =SUM(F31:F40) -> 146881.42 | J41: % brut | K41: =L41/L$27 -> 0.72441651 | L41: =SUM(L31:L40) -> 94080.66 | N41: =L41-F41 -> -52800.763 | O41: % brut | P41: =Q41/Q$27 -> 0.33639667 | Q41: =SUM(Q31:Q40) -> 82640.65 | S41: =L41-Q41 -> 11440.01
A42: Véhicules neufsSalaires cadres | B42: Véhicules neufs | C42: Salaires cadres | F42: =+INDEX('[5]Budget original'!$A$2:$AO$501,MATCH($A42,'[5]Budget original'!$A$2:$A$501,0),MATCH(F$2,'[5]Budget original'!$A$2:$AO$2,0)) -> 18197.117 | L42: =SUMIFS([5]BV_Data_An_Cour!$O:$O,[5]BV_Data_An_Cour!$U:$U,$B42,[5]BV_Data_An_Cour!$V:$V,$C42,[5]BV_Data_An_Cour!$W:$W,L$2) -> 12188.2 | N42: =L42-F42 -> -6008.9167 | P42: =Q42/Q27 -> 0.047233727 | Q42: {=+INDEX('[5]Réel 2023'!$A$2:$AO$501,MATCH($A42,'[5]Réel 2023'!$A$2:$A$501,0),MATCH(Q$2,'[5]Réel 2023'!$A$2:$AO$2,0))} -> 11603.64 | S42: =L42-Q42 -> 584.56
A43: Véhicules neufsSalaires commis | B43: Véhicules neufs | C43: Salaires commis | F43: =+INDEX('[5]Budget original'!$A$2:$AO$501,MATCH($A43,'[5]Budget original'!$A$2:$A$501,0),MATCH(F$2,'[5]Budget original'!$A$2:$AO$2,0)) -> 11267.511 | L43: =SUMIFS([5]BV_Data_An_Cour!$O:$O,[5]BV_Data_An_Cour!$U:$U,$B43,[5]BV_Data_An_Cour!$V:$V,$C43,[5]BV_Data_An_Cour!$W:$W,L$2) -> 8630.72 | N43: =L43-F43 -> -2636.7911 | Q43: {=+INDEX('[5]Réel 2023'!$A$2:$AO$501,MATCH($A43,'[5]Réel 2023'!$A$2:$A$501,0),MATCH(Q$2,'[5]Réel 2023'!$A$2:$AO$2,0))} -> 11332.89 | S43: =L43-Q43 -> -2702.17
A44: Véhicules neufsSalaires autres | B44: Véhicules neufs | C44: Salaires autres | F44: =+INDEX('[5]Budget original'!$A$2:$AO$501,MATCH($A44,'[5]Budget original'!$A$2:$A$501,0),MATCH(F$2,'[5]Budget original'!$A$2:$AO$2,0)) -> 2664.3538 | L44: =SUMIFS([5]BV_Data_An_Cour!$O:$O,[5]BV_Data_An_Cour!$U:$U,$B44,[5]BV_Data_An_Cour!$V:$V,$C44,[5]BV_Data_An_Cour!$W:$W,L$2) -> 2146.12 | N44: =L44-F44 -> -518.23385 | Q44: {=+INDEX('[5]Réel 2023'!$A$2:$AO$501,MATCH($A44,'[5]Réel 2023'!$A$2:$A$501,0),MATCH(Q$2,'[5]Réel 2023'!$A$2:$AO$2,0))} -> 3994.82 | S44: =L44-Q44 -> -1848.7
A45: Véhicules neufsSalaires spécialistes | B45: Véhicules neufs | C45: Salaires spécialistes | F45: =+INDEX('[5]Budget original'!$A$2:$AO$501,MATCH($A45,'[5]Budget original'!$A$2:$A$501,0),MATCH(F$2,'[5]Budget original'!$A$2:$AO$2,0)) -> 0 | L45: =SUMIFS([5]BV_Data_An_Cour!$O:$O,[5]BV_Data_An_Cour!$U:$U,$B45,[5]BV_Data_An_Cour!$V:$V,$C45,[5]BV_Data_An_Cour!$W:$W,L$2) -> 0 | N45: =L45-F45 -> 0 | Q45: {=+INDEX('[5]Réel 2023'!$A$2:$AO$501,MATCH($A45,'[5]Réel 2023'!$A$2:$A$501,0),MATCH(Q$2,'[5]Réel 2023'!$A$2:$AO$2,0))} -> 0 | S45: =L45-Q45 -> 0
A46: Véhicules neufs[...] | B46: Véhicules neufs | C46: [...] | F46: =+INDEX('[5]Budget original'!$A$2:$AO$501,MATCH($A46,'[5]Budget original'!$A$2:$A$501,0),MATCH(F$2,'[5]Budget original'!$A$2:$AO$2,0)) -> 0 | L46: =SUMIFS([5]BV_Data_An_Cour!$O:$O,[5]BV_Data_An_Cour!$U:$U,$B46,[5]BV_Data_An_Cour!$V:$V,$C46,[5]BV_Data_An_Cour!$W:$W,L$2) -> 0 | N46: =L46-F46 -> 0 | Q46: {=+INDEX('[5]Réel 2023'!$A$2:$AO$501,MATCH($A46,'[5]Réel 2023'!$A$2:$A$501,0),MATCH(Q$2,'[5]Réel 2023'!$A$2:$AO$2,0))} -> 0 | S46: =L46-Q46 -> 0
A47: Véhicules neufs[...] | B47: Véhicules neufs | C47: [...] | F47: =+INDEX('[5]Budget original'!$A$2:$AO$501,MATCH($A47,'[5]Budget original'!$A$2:$A$501,0),MATCH(F$2,'[5]Budget original'!$A$2:$AO$2,0)) -> 0 | L47: =SUMIFS([5]BV_Data_An_Cour!$O:$O,[5]BV_Data_An_Cour!$U:$U,$B47,[5]BV_Data_An_Cour!$V:$V,$C47,[5]BV_Data_An_Cour!$W:$W,L$2) -> 0 | N47: =L47-F47 -> 0 | Q47: {=+INDEX('[5]Réel 2023'!$A$2:$AO$501,MATCH($A47,'[5]Réel 2023'!$A$2:$A$501,0),MATCH(Q$2,'[5]Réel 2023'!$A$2:$AO$2,0))} -> 0 | S47: =L47-Q47 -> 0
A48: Véhicules neufs[...] | B48: Véhicules neufs | C48: [...] | F48: =+INDEX('[5]Budget original'!$A$2:$AO$501,MATCH($A48,'[5]Budget original'!$A$2:$A$501,0),MATCH(F$2,'[5]Budget original'!$A$2:$AO$2,0)) -> 0 | L48: =SUMIFS([5]BV_Data_An_Cour!$O:$O,[5]BV_Data_An_Cour!$U:$U,$B48,[5]BV_Data_An_Cour!$V:$V,$C48,[5]BV_Data_An_Cour!$W:$W,L$2) -> 0 | N48: =L48-F48 -> 0 | Q48: {=+INDEX('[5]Réel 2023'!$A$2:$AO$501,MATCH($A48,'[5]Réel 2023'!$A$2:$A$501,0),MATCH(Q$2,'[5]Réel 2023'!$A$2:$AO$2,0))} -> 0 | S48: =L48-Q48 -> 0
A49: Véhicules neufsSalaires en absences | B49: Véhicules neufs | C49: Salaires en absences | F49: =+INDEX('[5]Budget original'!$A$2:$AO$501,MATCH($A49,'[5]Budget original'!$A$2:$A$501,0),MATCH(F$2,'[5]Budget original'!$A$2:$AO$2,0)) -> 12326.505 | L49: =SUMIFS([5]BV_Data_An_Cour!$O:$O,[5]BV_Data_An_Cour!$U:$U,$B49,[5]BV_Data_An_Cour!$V:$V,$C49,[5]BV_Data_An_Cour!$W:$W,L$2) -> 10528.2 | N49: =L49-F49 -> -1798.305 | Q49: {=+INDEX('[5]Réel 2023'!$A$2:$AO$501,MATCH($A49,'[5]Réel 2023'!$A$2:$A$501,0),MATCH(Q$2,'[5]Réel 2023'!$A$2:$AO$2,0))} -> 9419.91 | S49: =L49-Q49 -> 1108.29
A50: Véhicules neufsDéduction à la source | B50: Véhicules neufs | C50: Déduction à la source | F50: =+INDEX('[5]Budget original'!$A$2:$AO$501,MATCH($A50,'[5]Budget original'!$A$2:$A$501,0),MATCH(F$2,'[5]Budget original'!$A$2:$AO$2,0)) -> 14987.292 | L50: =SUMIFS([5]BV_Data_An_Cour!$O:$O,[5]BV_Data_An_Cour!$U:$U,$B50,[5]BV_Data_An_Cour!$V:$V,$C50,[5]BV_Data_An_Cour!$W:$W,L$2) -> 14036.34 | N50: =L50-F50 -> -950.95241 | Q50: {=+INDEX('[5]Réel 2023'!$A$2:$AO$501,MATCH($A50,'[5]Réel 2023'!$A$2:$A$501,0),MATCH(Q$2,'[5]Réel 2023'!$A$2:$AO$2,0))} -> 8905.21 | S50: =L50-Q50 -> 5131.13
A51: Véhicules neufsBénéfices marginaux | B51: Véhicules neufs | C51: Bénéfices marginaux | F51: =+INDEX('[5]Budget original'!$A$2:$AO$501,MATCH($A51,'[5]Budget original'!$A$2:$A$501,0),MATCH(F$2,'[5]Budget original'!$A$2:$AO$2,0)) -> 7721.7137 | L51: =SUMIFS([5]BV_Data_An_Cour!$O:$O,[5]BV_Data_An_Cour!$U:$U,$B51,[5]BV_Data_An_Cour!$V:$V,$C51,[5]BV_Data_An_Cour!$W:$W,L$2) -> 6769.08 | N51: =L51-F51 -> -952.6337 | Q51: {=+INDEX('[5]Réel 2023'!$A$2:$AO$501,MATCH($A51,'[5]Réel 2023'!$A$2:$A$501,0),MATCH(Q$2,'[5]Réel 2023'!$A$2:$AO$2,0))} -> 5383.41 | S51: =L51-Q51 -> 1385.67
A52: Véhicules neufsCsst | B52: Véhicules neufs | C52: Csst | F52: =+INDEX('[5]Budget original'!$A$2:$AO$501,MATCH($A52,'[5]Budget original'!$A$2:$A$501,0),MATCH(F$2,'[5]Budget original'!$A$2:$AO$2,0)) -> 3366.7106 | L52: =SUMIFS([5]BV_Data_An_Cour!$O:$O,[5]BV_Data_An_Cour!$U:$U,$B52,[5]BV_Data_An_Cour!$V:$V,$C52,[5]BV_Data_An_Cour!$W:$W,L$2) -> 1167.34 | N52: =L52-F52 -> -2199.3706 | Q52: {=+INDEX('[5]Réel 2023'!$A$2:$AO$501,MATCH($A52,'[5]Réel 2023'!$A$2:$A$501,0),MATCH(Q$2,'[5]Réel 2023'!$A$2:$AO$2,0))} -> 686.07 | S52: =L52-Q52 -> 481.27
A53: Véhicules neufs[...] | B53: Véhicules neufs | C53: [...] | D53: =VLOOKUP(C53,$B$2:$B$46,1,FALSE) -> #N/A | F53: =+INDEX('[5]Budget original'!$A$2:$AO$501,MATCH($A53,'[5]Budget original'!$A$2:$A$501,0),MATCH(F$2,'[5]Budget original'!$A$2:$AO$2,0)) -> 0 | L53: =SUMIFS([5]BV_Data_An_Cour!$O:$O,[5]BV_Data_An_Cour!$U:$U,$B53,[5]BV_Data_An_Cour!$V:$V,$C53,[5]BV_Data_An_Cour!$W:$W,L$2) -> 0 | N53: =L53-F53 -> 0 | Q53: {=+INDEX('[5]Réel 2023'!$A$2:$AO$501,MATCH($A53,'[5]Réel 2023'!$A$2:$A$501,0),MATCH(Q$2,'[5]Réel 2023'!$A$2:$AO$2,0))} -> 0 | S53: =L53-Q53 -> 0
A54: Véhicules neufsTOTAL PERSONNEL | B54: Véhicules neufs | C54: TOTAL PERSONNEL | D54: % brut | E54: =F54/F$27 -> 0.20390451 | F54: =+SUM(F42:F53) -> 70531.203 | J54: % brut | K54: =L54/L$27 -> 0.4270855 | L54: =+SUM(L42:L53) -> 55466 | N54: =+SUM(N42:N53) -> -15065.203 | O54: % brut | P54: =Q54/Q$27 -> 0.20892719 | Q54: =+SUM(Q42:Q53) -> 51325.95 | S54: =+SUM(S42:S53) -> 4140.05
A55: Véhicules neufsPublicité 2 | B55: Véhicules neufs | C55: Publicité 2 | F55: =+INDEX('[5]Budget original'!$A$2:$AO$501,MATCH($A55,'[5]Budget original'!$A$2:$A$501,0),MATCH(F$2,'[5]Budget original'!$A$2:$AO$2,0)) -> 0 | L55: =SUMIFS([5]BV_Data_An_Cour!$O:$O,[5]BV_Data_An_Cour!$U:$U,$B55,[5]BV_Data_An_Cour!$V:$V,$C55,[5]BV_Data_An_Cour!$W:$W,L$2) -> 0 | N55: =L55-F55 -> 0 | Q55: {=+INDEX('[5]Réel 2023'!$A$2:$AO$501,MATCH($A55,'[5]Réel 2023'!$A$2:$A$501,0),MATCH(Q$2,'[5]Réel 2023'!$A$2:$AO$2,0))} -> 0 | S55: =L55-Q55 -> 0
A56: Véhicules neufsService gratuit 2 | B56: Véhicules neufs | C56: Service gratuit 2 | F56: =+INDEX('[5]Budget original'!$A$2:$AO$501,MATCH($A56,'[5]Budget original'!$A$2:$A$501,0),MATCH(F$2,'[5]Budget original'!$A$2:$AO$2,0)) -> 0 | L56: =SUMIFS([5]BV_Data_An_Cour!$O:$O,[5]BV_Data_An_Cour!$U:$U,$B56,[5]BV_Data_An_Cour!$V:$V,$C56,[5]BV_Data_An_Cour!$W:$W,L$2) -> 0 | N56: =L56-F56 -> 0 | Q56: {=+INDEX('[5]Réel 2023'!$A$2:$AO$501,MATCH($A56,'[5]Réel 2023'!$A$2:$A$501,0),MATCH(Q$2,'[5]Réel 2023'!$A$2:$AO$2,0))} -> 0 | S56: =L56-Q56 -> 0
A57: Véhicules neufsFrais véhicules de cie | B57: Véhicules neufs | C57: Frais véhicules de cie | F57: =+INDEX('[5]Budget original'!$A$2:$AO$501,MATCH($A57,'[5]Budget original'!$A$2:$A$501,0),MATCH(F$2,'[5]Budget original'!$A$2:$AO$2,0)) -> 9200 | L57: =SUMIFS([5]BV_Data_An_Cour!$O:$O,[5]BV_Data_An_Cour!$U:$U,$B57,[5]BV_Data_An_Cour!$V:$V,$C57,[5]BV_Data_An_Cour!$W:$W,L$2) -> 8473.11 | N57: =L57-F57 -> -726.89 | Q57: {=+INDEX('[5]Réel 2023'!$A$2:$AO$501,MATCH($A57,'[5]Réel 2023'!$A$2:$A$501,0),MATCH(Q$2,'[5]Réel 2023'!$A$2:$AO$2,0))} -> 10080.58 | S57: =L57-Q57 -> -1607.47
A58: Véhicules neufsInformatique | B58: Véhicules neufs | C58: Informatique | F58: =+INDEX('[5]Budget original'!$A$2:$AO$501,MATCH($A58,'[5]Budget original'!$A$2:$A$501,0),MATCH(F$2,'[5]Budget original'!$A$2:$AO$2,0)) -> 9039.6955 | L58: =SUMIFS([5]BV_Data_An_Cour!$O:$O,[5]BV_Data_An_Cour!$U:$U,$B58,[5]BV_Data_An_Cour!$V:$V,$C58,[5]BV_Data_An_Cour!$W:$W,L$2) -> 7015.5 | N58: =L58-F58 -> -2024.1955 | Q58: {=+INDEX('[5]Réel 2023'!$A$2:$AO$501,MATCH($A58,'[5]Réel 2023'!$A$2:$A$501,0),MATCH(Q$2,'[5]Réel 2023'!$A$2:$AO$2,0))} -> 6701.59 | S58: =L58-Q58 -> 313.91
A59: Véhicules neufsFrais de déplacement | B59: Véhicules neufs | C59: Frais de déplacement | F59: =+INDEX('[5]Budget original'!$A$2:$AO$501,MATCH($A59,'[5]Budget original'!$A$2:$A$501,0),MATCH(F$2,'[5]Budget original'!$A$2:$AO$2,0)) -> 1105.2259 | L59: =SUMIFS([5]BV_Data_An_Cour!$O:$O,[5]BV_Data_An_Cour!$U:$U,$B59,[5]BV_Data_An_Cour!$V:$V,$C59,[5]BV_Data_An_Cour!$W:$W,L$2) -> 2344.34 | N59: =L59-F59 -> 1239.1141 | Q59: {=+INDEX('[5]Réel 2023'!$A$2:$AO$501,MATCH($A59,'[5]Réel 2023'!$A$2:$A$501,0),MATCH(Q$2,'[5]Réel 2023'!$A$2:$AO$2,0))} -> 1507.17 | S59: =L59-Q59 -> 837.17
A60: Véhicules neufsServices extérieurs | B60: Véhicules neufs | C60: Services extérieurs | F60: =+INDEX('[5]Budget original'!$A$2:$AO$501,MATCH($A60,'[5]Budget original'!$A$2:$A$501,0),MATCH(F$2,'[5]Budget original'!$A$2:$AO$2,0)) -> 6711.4186 | L60: =SUMIFS([5]BV_Data_An_Cour!$O:$O,[5]BV_Data_An_Cour!$U:$U,$B60,[5]BV_Data_An_Cour!$V:$V,$C60,[5]BV_Data_An_Cour!$W:$W,L$2) -> 8179.53 | N60: =L60-F60 -> 1468.1114 | Q60: {=+INDEX('[5]Réel 2023'!$A$2:$AO$501,MATCH($A60,'[5]Réel 2023'!$A$2:$A$501,0),MATCH(Q$2,'[5]Réel 2023'!$A$2:$AO$2,0))} -> 8041.2 | S60: =L60-Q60 -> 138.33
A61: Véhicules neufsFournitures autres | B61: Véhicules neufs | C61: Fournitures autres | F61: =+INDEX('[5]Budget original'!$A$2:$AO$501,MATCH($A61,'[5]Budget original'!$A$2:$A$501,0),MATCH(F$2,'[5]Budget original'!$A$2:$AO$2,0)) -> 125 | L61: =SUMIFS([5]BV_Data_An_Cour!$O:$O,[5]BV_Data_An_Cour!$U:$U,$B61,[5]BV_Data_An_Cour!$V:$V,$C61,[5]BV_Data_An_Cour!$W:$W,L$2) -> 0 | N61: =L61-F61 -> -125 | Q61: {=+INDEX('[5]Réel 2023'!$A$2:$AO$501,MATCH($A61,'[5]Réel 2023'!$A$2:$A$501,0),MATCH(Q$2,'[5]Réel 2023'!$A$2:$AO$2,0))} -> 0 | S61: =L61-Q61 -> 0
A62: Véhicules neufsUniformes | B62: Véhicules neufs | C62: Uniformes | F62: =+INDEX('[5]Budget original'!$A$2:$AO$501,MATCH($A62,'[5]Budget original'!$A$2:$A$501,0),MATCH(F$2,'[5]Budget original'!$A$2:$AO$2,0)) -> 83.333333 | L62: =SUMIFS([5]BV_Data_An_Cour!$O:$O,[5]BV_Data_An_Cour!$U:$U,$B62,[5]BV_Data_An_Cour!$V:$V,$C62,[5]BV_Data_An_Cour!$W:$W,L$2) -> 434.88 | N62: =L62-F62 -> 351.54667 | Q62: {=+INDEX('[5]Réel 2023'!$A$2:$AO$501,MATCH($A62,'[5]Réel 2023'!$A$2:$A$501,0),MATCH(Q$2,'[5]Réel 2023'!$A$2:$AO$2,0))} -> 0 | S62: =L62-Q62 -> 434.88
A63: Véhicules neufsPapeterie | B63: Véhicules neufs | C63: Papeterie | F63: =+INDEX('[5]Budget original'!$A$2:$AO$501,MATCH($A63,'[5]Budget original'!$A$2:$A$501,0),MATCH(F$2,'[5]Budget original'!$A$2:$AO$2,0)) -> 756.9466 | L63: =SUMIFS([5]BV_Data_An_Cour!$O:$O,[5]BV_Data_An_Cour!$U:$U,$B63,[5]BV_Data_An_Cour!$V:$V,$C63,[5]BV_Data_An_Cour!$W:$W,L$2) -> 377.56 | N63: =L63-F63 -> -379.3866 | Q63: {=+INDEX('[5]Réel 2023'!$A$2:$AO$501,MATCH($A63,'[5]Réel 2023'!$A$2:$A$501,0),MATCH(Q$2,'[5]Réel 2023'!$A$2:$AO$2,0))} -> 281.8 | S63: =L63-Q63 -> 95.76
A64: Véhicules neufsTéléphone | B64: Véhicules neufs | C64: Téléphone | F64: =+INDEX('[5]Budget original'!$A$2:$AO$501,MATCH($A64,'[5]Budget original'!$A$2:$A$501,0),MATCH(F$2,'[5]Budget original'!$A$2:$AO$2,0)) -> 309.40349 | L64: =SUMIFS([5]BV_Data_An_Cour!$O:$O,[5]BV_Data_An_Cour!$U:$U,$B64,[5]BV_Data_An_Cour!$V:$V,$C64,[5]BV_Data_An_Cour!$W:$W,L$2) -> 393.48 | N64: =L64-F64 -> 84.076515 | Q64: {=+INDEX('[5]Réel 2023'!$A$2:$AO$501,MATCH($A64,'[5]Réel 2023'!$A$2:$A$501,0),MATCH(Q$2,'[5]Réel 2023'!$A$2:$AO$2,0))} -> 303.89 | S64: =L64-Q64 -> 89.59
A65: Véhicules neufsFrais postaux | B65: Véhicules neufs | C65: Frais postaux | F65: =+INDEX('[5]Budget original'!$A$2:$AO$501,MATCH($A65,'[5]Budget original'!$A$2:$A$501,0),MATCH(F$2,'[5]Budget original'!$A$2:$AO$2,0)) -> 113.12881 | L65: =SUMIFS([5]BV_Data_An_Cour!$O:$O,[5]BV_Data_An_Cour!$U:$U,$B65,[5]BV_Data_An_Cour!$V:$V,$C65,[5]BV_Data_An_Cour!$W:$W,L$2) -> 32.96 | N65: =L65-F65 -> -80.16881 | Q65: {=+INDEX('[5]Réel 2023'!$A$2:$AO$501,MATCH($A65,'[5]Réel 2023'!$A$2:$A$501,0),MATCH(Q$2,'[5]Réel 2023'!$A$2:$AO$2,0))} -> 252.96 | S65: =L65-Q65 -> -220
A66: Véhicules neufsDivers | B66: Véhicules neufs | C66: Divers | F66: =+INDEX('[5]Budget original'!$A$2:$AO$501,MATCH($A66,'[5]Budget original'!$A$2:$A$501,0),MATCH(F$2,'[5]Budget original'!$A$2:$AO$2,0)) -> 282.4626 | L66: =SUMIFS([5]BV_Data_An_Cour!$O:$O,[5]BV_Data_An_Cour!$U:$U,$B66,[5]BV_Data_An_Cour!$V:$V,$C66,[5]BV_Data_An_Cour!$W:$W,L$2) -> 234.47 | N66: =L66-F66 -> -47.992603 | Q66: {=+INDEX('[5]Réel 2023'!$A$2:$AO$501,MATCH($A66,'[5]Réel 2023'!$A$2:$A$501,0),MATCH(Q$2,'[5]Réel 2023'!$A$2:$AO$2,0))} -> 120 | S66: =L66-Q66 -> 114.47
... A68: Véhicules neufsFrais bancaires | B68: Véhicules neufs | C68: Frais bancaires | F68: =+INDEX('[5]Budget original'!$A$2:$AO$501,MATCH($A68,'[5]Budget original'!$A$2:$A$501,0),MATCH(F$2,'[5]Budget original'!$A$2:$AO$2,0)) -> 3363.2959 | L68: =SUMIFS([5]BV_Data_An_Cour!$O:$O,[5]BV_Data_An_Cour!$U:$U,$B68,[5]BV_Data_An_Cour!$V:$V,$C68,[5]BV_Data_An_Cour!$W:$W,L$2) -> 4782.88 | N68: =L68-F68 -> 1419.5841 | Q68: {=+INDEX('[5]Réel 2023'!$A$2:$AO$501,MATCH($A68,'[5]Réel 2023'!$A$2:$A$501,0),MATCH(Q$2,'[5]Réel 2023'!$A$2:$AO$2,0))} -> 4006.58 | S68: =L68-Q68 -> 776.3
A69: Véhicules neufs[...] | B69: Véhicules neufs | C69: [...] | F69: =+INDEX('[5]Budget original'!$A$2:$AO$501,MATCH($A69,'[5]Budget original'!$A$2:$A$501,0),MATCH(F$2,'[5]Budget original'!$A$2:$AO$2,0)) -> 0 | N69: =L69-F69 -> 0 | Q69: {=+INDEX('[5]Réel 2023'!$A$2:$AO$501,MATCH($A69,'[5]Réel 2023'!$A$2:$A$501,0),MATCH(Q$2,'[5]Réel 2023'!$A$2:$AO$2,0))} -> 0 | S69: =L69-Q69 -> 0
A70: Véhicules neufs[...] | B70: Véhicules neufs | C70: [...] | F70: =+INDEX('[5]Budget original'!$A$2:$AO$501,MATCH($A70,'[5]Budget original'!$A$2:$A$501,0),MATCH(F$2,'[5]Budget original'!$A$2:$AO$2,0)) -> 0 | L70: =SUMIFS([5]BV_Data_An_Cour!$O:$O,[5]BV_Data_An_Cour!$U:$U,$B70,[5]BV_Data_An_Cour!$V:$V,$C70,[5]BV_Data_An_Cour!$W:$W,L$2) -> 0 | N70: =L70-F70 -> 0 | Q70: {=+INDEX('[5]Réel 2023'!$A$2:$AO$501,MATCH($A70,'[5]Réel 2023'!$A$2:$A$501,0),MATCH(Q$2,'[5]Réel 2023'!$A$2:$AO$2,0))} -> 0 | S70: =L70-Q70 -> 0
A71: Véhicules neufs[...] | B71: Véhicules neufs | C71: [...] | F71: =+INDEX('[5]Budget original'!$A$2:$AO$501,MATCH($A71,'[5]Budget original'!$A$2:$A$501,0),MATCH(F$2,'[5]Budget original'!$A$2:$AO$2,0)) -> 0 | L71: =SUMIFS([5]BV_Data_An_Cour!$O:$O,[5]BV_Data_An_Cour!$U:$U,$B71,[5]BV_Data_An_Cour!$V:$V,$C71,[5]BV_Data_An_Cour!$W:$W,L$2)*0.32 -> 0 | N71: =L71-F71 -> 0 | Q71: {=+INDEX('[5]Réel 2023'!$A$2:$AO$501,MATCH($A71,'[5]Réel 2023'!$A$2:$A$501,0),MATCH(Q$2,'[5]Réel 2023'!$A$2:$AO$2,0))} -> 0 | S71: =L71-Q71 -> 0
A72: Véhicules neufsTOTAL SEMI-FIXES | B72: Véhicules neufs | C72: TOTAL SEMI-FIXES | D72: % brut | E72: =F72/F$27 -> 0.095370693 | F72: =+SUM(F55:F71) -> 32989.018 | J72: % brut | K72: =L72/L$27 -> 0.26669297 | L72: =+SUM(L55:L71) -> 34635.67 | N72: =+SUM(N55:N71) -> 1646.6517 | O72: % brut | P72: =Q72/Q$27 -> 0.13596677 | Q72: =+SUM(Q55:Q71) -> 33402.18 | S72: =+SUM(S55:S71) -> 1233.49
A73: Véhicules neufs | B73: Véhicules neufs
A74: Véhicules neufsTOTAL DES DÉPENSES | B74: Véhicules neufs | C74: TOTAL DES DÉPENSES | D74: % brut | E74: =F74/F$27 -> 0.72390691 | F74: =F41+F54+F72 -> 250401.64 | J74: % brut | K74: =L74/L$27 -> 1.418195 | L74: =L41+L54+L72 -> 184182.33 | N74: =L74-F74 -> -66219.314 | O74: % brut | P74: =Q74/Q$27 -> 0.68129063 | Q74: =Q41+Q54+Q72 -> 167368.78 | S74: =L74-Q74 -> 16813.55
A75: Véhicules neufsProgramme neuf 1 | B75: Véhicules neufs | C75: Programme neuf 1 | F75: =+INDEX('[5]Budget original'!$A$2:$AO$501,MATCH($A75,'[5]Budget original'!$A$2:$A$501,0),MATCH(F$2,'[5]Budget original'!$A$2:$AO$2,0)) -> 0 | L75: =-SUMIFS([5]BV_Data_An_Cour!$O:$O,[5]BV_Data_An_Cour!$U:$U,$B75,[5]BV_Data_An_Cour!$V:$V,$C75,[5]BV_Data_An_Cour!$W:$W,L$2)-L156 -> 0 | N75: =L75-F75 -> 0 | Q75: =+INDEX('[5]Réel 2023'!$A$2:$AO$501,MATCH($A75,'[5]Réel 2023'!$A$2:$A$501,0),MATCH(Q$2,'[5]Réel 2023'!$A$2:$AO$2,0)) -> 0
A76: Véhicules neufsProgramme neuf 2 | B76: Véhicules neufs | C76: Programme neuf 2 | F76: =+INDEX('[5]Budget original'!$A$2:$AO$501,MATCH($A76,'[5]Budget original'!$A$2:$A$501,0),MATCH(F$2,'[5]Budget original'!$A$2:$AO$2,0)) -> 0 | L76: =-SUMIFS([5]BV_Data_An_Cour!$O:$O,[5]BV_Data_An_Cour!$U:$U,$B76,[5]BV_Data_An_Cour!$V:$V,$C76,[5]BV_Data_An_Cour!$W:$W,L$2) -> 0 | N76: =L76-F76 -> 0 | Q76: {=+INDEX('[5]Réel 2023'!$A$2:$AO$501,MATCH($A76,'[5]Réel 2023'!$A$2:$A$501,0),MATCH(Q$2,'[5]Réel 2023'!$A$2:$AO$2,0))} -> 0 | S76: =L76-Q76 -> 0
A77: Véhicules neufsProgramme neuf 3 | B77: Véhicules neufs | C77: Programme neuf 3 | F77: =+INDEX('[5]Budget original'!$A$2:$AO$501,MATCH($A77,'[5]Budget original'!$A$2:$A$501,0),MATCH(F$2,'[5]Budget original'!$A$2:$AO$2,0)) -> 0 | L77: =-SUMIFS([5]BV_Data_An_Cour!$O:$O,[5]BV_Data_An_Cour!$U:$U,$B77,[5]BV_Data_An_Cour!$V:$V,$C77,[5]BV_Data_An_Cour!$W:$W,L$2) -> 0 | N77: =L77-F77 -> 0 | Q77: {=+INDEX('[5]Réel 2023'!$A$2:$AO$501,MATCH($A77,'[5]Réel 2023'!$A$2:$A$501,0),MATCH(Q$2,'[5]Réel 2023'!$A$2:$AO$2,0))} -> 0 | S77: =L77-Q77 -> 0
A78: Véhicules neufsHoldbacks | B78: Véhicules neufs | C78: Holdbacks | E78: =+F78/D27 -> 1320.4861 | F78: =+INDEX('[5]Budget original'!$A$2:$AO$501,MATCH($A78,'[5]Budget original'!$A$2:$A$501,0),MATCH(F$2,'[5]Budget original'!$A$2:$AO$2,0)) -> 112505.42 | K78: =+L78/J27 -> 1283.6702 | L78: =-SUMIFS([5]BV_Data_An_Cour!$O:$O,[5]BV_Data_An_Cour!$U:$U,$B78,[5]BV_Data_An_Cour!$V:$V,$C78,[5]BV_Data_An_Cour!$W:$W,L$2) -> 66750.85 | N78: =L78-F78 -> -45754.569 | Q78: {=+INDEX('[5]Réel 2023'!$A$2:$AO$501,MATCH($A78,'[5]Réel 2023'!$A$2:$A$501,0),MATCH(Q$2,'[5]Réel 2023'!$A$2:$AO$2,0))} -> 77258.09 | S78: =L78-Q78 -> -10507.24
A79: Véhicules neufs[...] | B79: Véhicules neufs | C79: [...] | F79: =+INDEX('[5]Budget original'!$A$2:$AO$501,MATCH($A79,'[5]Budget original'!$A$2:$A$501,0),MATCH(F$2,'[5]Budget original'!$A$2:$AO$2,0)) -> 0 | L79: =-SUMIFS([5]BV_Data_An_Cour!$O:$O,[5]BV_Data_An_Cour!$U:$U,$B79,[5]BV_Data_An_Cour!$V:$V,$C79,[5]BV_Data_An_Cour!$W:$W,L$2) -> 0 | N79: =L79-F79 -> 0 | Q79: {=+INDEX('[5]Réel 2023'!$A$2:$AO$501,MATCH($A79,'[5]Réel 2023'!$A$2:$A$501,0),MATCH(Q$2,'[5]Réel 2023'!$A$2:$AO$2,0))} -> 0 | S79: =L79-Q79 -> 0
A80: Véhicules neufs[...] | B80: Véhicules neufs | C80: [...] | F80: =+INDEX('[5]Budget original'!$A$2:$AO$501,MATCH($A80,'[5]Budget original'!$A$2:$A$501,0),MATCH(F$2,'[5]Budget original'!$A$2:$AO$2,0)) -> 0 | L80: =-SUMIFS([5]BV_Data_An_Cour!$O:$O,[5]BV_Data_An_Cour!$U:$U,$B80,[5]BV_Data_An_Cour!$V:$V,$C80,[5]BV_Data_An_Cour!$W:$W,L$2) -> 0 | N80: =L80-F80 -> 0 | Q80: {=+INDEX('[5]Réel 2023'!$A$2:$AO$501,MATCH($A80,'[5]Réel 2023'!$A$2:$A$501,0),MATCH(Q$2,'[5]Réel 2023'!$A$2:$AO$2,0))} -> 0 | S80: =L80-Q80 -> 0
A81: Véhicules neufs[...] | B81: Véhicules neufs | C81: [...] | F81: =+INDEX('[5]Budget original'!$A$2:$AO$501,MATCH($A81,'[5]Budget original'!$A$2:$A$501,0),MATCH(F$2,'[5]Budget original'!$A$2:$AO$2,0)) -> 0 | L81: =-SUMIFS([5]BV_Data_An_Cour!$O:$O,[5]BV_Data_An_Cour!$U:$U,$B81,[5]BV_Data_An_Cour!$V:$V,$C81,[5]BV_Data_An_Cour!$W:$W,L$2) -> 0 | N81: =L81-F81 -> 0 | Q81: {=+INDEX('[5]Réel 2023'!$A$2:$AO$501,MATCH($A81,'[5]Réel 2023'!$A$2:$A$501,0),MATCH(Q$2,'[5]Réel 2023'!$A$2:$AO$2,0))} -> 0 | S81: =L81-Q81 -> 0
A82: Véhicules neufsFrais administration | B82: Véhicules neufs | C82: Frais administration | D82: =E82/499 -> 0.95 | E82: =+F82/D24 -> 474.05 | F82: =+INDEX('[5]Budget original'!$A$2:$AO$501,MATCH($A82,'[5]Budget original'!$A$2:$A$501,0),MATCH(F$2,'[5]Budget original'!$A$2:$AO$2,0)) -> 37829.19 | J82: =K82/474 -> 1.0286076 | K82: =+L82/J24 -> 487.56 | L82: =-SUMIFS([5]BV_Data_An_Cour!$O:$O,[5]BV_Data_An_Cour!$U:$U,$B82,[5]BV_Data_An_Cour!$V:$V,$C82,[5]BV_Data_An_Cour!$W:$W,L$2) -> 24378 | N82: =L82-F82 -> -13451.19 | Q82: {=+INDEX('[5]Réel 2023'!$A$2:$AO$501,MATCH($A82,'[5]Réel 2023'!$A$2:$A$501,0),MATCH(Q$2,'[5]Réel 2023'!$A$2:$AO$2,0))} -> 29179 | S82: =L82-Q82 -> -4801
A83: Véhicules neufsAUTRES REVENUS | B83: Véhicules neufs | C83: AUTRES REVENUS | F83: =+SUM(F75:F82) -> 150334.61 | L83: =+SUM(L75:L82) -> 91128.85 | N83: =+SUM(N75:N82) -> -59205.759 | Q83: =+SUM(Q75:Q82) -> 106437.09 | S83: =+SUM(S75:S82) -> -15308.24
A84: Véhicules neufs | B84: Véhicules neufs
A85: Véhicules neufsPROFIT DÉPARTEMENTAL | B85: Véhicules neufs | C85: PROFIT DÉPARTEMENTAL | F85: =F27-F74+F83 -> 245836.06 | L85: =L27-L74+L83 -> 36817.47 | N85: =N27-N41-N54-N72+N83 -> -209018.59 | P85: =Q85/Q5 -> 0.022296496 | Q85: =Q27-Q74+Q83 -> 184732.6 | S85: =S27-S41-S54-S72+S83 -> -147915.13
C89: =C1 -> Volks | K89: Véhicules usagés | S89: =$S$1 -> Réalisé, Octobre 2024
D91: BUDGET ORIGINAL | J91: RÉALISATION | M91: ÉCART réel / Budget | O91: ANNÉE PRÉCÉDENTE | R91: ECART (réel/ Ann.Préc.)
D92: UNITE | E92: $P/UNITÉ | F92: $PROFITS | J92: UNITÉS | K92: $P/UNITE | L92: $PROFITS | M92: UNITÉS | N92: $PROFITS | O92: UNITE | P92: $P/UNITÉ | Q92: $PROFITS | R92: UNITÉS | S92: $PROFITS
A93: Véhicules usagésVentes nettes | B93: Véhicules usagés | C93: Ventes nettes | F93: =+INDEX('[5]Budget original'!$A$2:$AO$501,MATCH($A93,'[5]Budget original'!$A$2:$A$501,0),MATCH(F$2,'[5]Budget original'!$A$2:$AO$2,0)) -> 1872889.1 | L93: =-SUMIFS([5]BV_Data_An_Cour!$O:$O,[5]BV_Data_An_Cour!$X:$X,"Oui",[5]BV_Data_An_Cour!$U:$U,$B93) -> 1341799.5 | Q93: {=+INDEX('[5]Réel 2023'!$A$2:$AO$501,MATCH($A93,'[5]Réel 2023'!$A$2:$A$501,0),MATCH(Q$2,'[5]Réel 2023'!$A$2:$AO$2,0))} -> 1412113.8
A94: Véhicules usagésCertifié | B94: Véhicules usagés | C94: Certifié | D94: =+INDEX('[5]Budget original'!$A$2:$AO$501,MATCH($A94,'[5]Budget original'!$A$2:$A$501,0),MATCH(D$2,'[5]Budget original'!$A$2:$AO$2,0)) -> 34.554 | E94: =IF(D94=0,0,F94/D94) -> 1800 | F94: =+INDEX('[5]Budget original'!$A$2:$AO$501,MATCH($A94,'[5]Budget original'!$A$2:$A$501,0),MATCH(F$2,'[5]Budget original'!$A$2:$AO$2,0)) -> 62197.2 | J94: =-SUMIFS([5]BV_Data_An_Cour!$O:$O,[5]BV_Data_An_Cour!$U:$U,$B94,[5]BV_Data_An_Cour!$V:$V,$C94,[5]BV_Data_An_Cour!$W:$W,J$2) -> 37 | K94: =IF(J94=0,0,L94/J94) -> 1033.9343 | L94: =-SUMIFS([5]BV_Data_An_Cour!$O:$O,[5]BV_Data_An_Cour!$U:$U,$B94,[5]BV_Data_An_Cour!$V:$V,$C94,[5]BV_Data_An_Cour!$W:$W,$L2) -> 38255.57 | M94: =J94-D94 -> 2.446 | N94: =L94-F94 -> -23941.63 | O94: {=+INDEX('[5]Réel 2023'!$A$2:$AO$501,MATCH($A94,'[5]Réel 2023'!$A$2:$A$501,0),MATCH(O$2,'[5]Réel 2023'!$A$2:$AO$2,0))} -> 21 | P94: =IF(O94=0,0,Q94/O94) -> 1924.4195 | Q94: {=+INDEX('[5]Réel 2023'!$A$2:$AO$501,MATCH($A94,'[5]Réel 2023'!$A$2:$A$501,0),MATCH(Q$2,'[5]Réel 2023'!$A$2:$AO$2,0))} -> 40412.81 | R94: =J94-O94 -> 16 | S94: =L94-Q94 -> -2157.24
A95: Véhicules usagésNon Certifié | B95: Véhicules usagés | C95: Non Certifié | D95: =+INDEX('[5]Budget original'!$A$2:$AO$501,MATCH($A95,'[5]Budget original'!$A$2:$A$501,0),MATCH(D$2,'[5]Budget original'!$A$2:$AO$2,0)) -> 1.9492 | E95: =IF(D95=0,0,F95/D95) -> 1800 | F95: =+INDEX('[5]Budget original'!$A$2:$AO$501,MATCH($A95,'[5]Budget original'!$A$2:$A$501,0),MATCH(F$2,'[5]Budget original'!$A$2:$AO$2,0)) -> 3508.56 | J95: =-SUMIFS([5]BV_Data_An_Cour!$O:$O,[5]BV_Data_An_Cour!$U:$U,$B95,[5]BV_Data_An_Cour!$V:$V,$C95,[5]BV_Data_An_Cour!$W:$W,J$2) -> 3 | K95: =IF(J95=0,0,L95/J95) -> -1128.6233 | L95: =-SUMIFS([5]BV_Data_An_Cour!$O:$O,[5]BV_Data_An_Cour!$U:$U,$B95,[5]BV_Data_An_Cour!$V:$V,$C95,[5]BV_Data_An_Cour!$W:$W,$L2) -> -3385.87 | M95: =J95-D95 -> 1.0508 | N95: =L95-F95 -> -6894.43 | O95: {=+INDEX('[5]Réel 2023'!$A$2:$AO$501,MATCH($A95,'[5]Réel 2023'!$A$2:$A$501,0),MATCH(O$2,'[5]Réel 2023'!$A$2:$AO$2,0))} -> 5 | P95: =IF(O95=0,0,Q95/O95) -> 2390.022 | Q95: {=+INDEX('[5]Réel 2023'!$A$2:$AO$501,MATCH($A95,'[5]Réel 2023'!$A$2:$A$501,0),MATCH(Q$2,'[5]Réel 2023'!$A$2:$AO$2,0))} -> 11950.11 | R95: =J95-O95 -> -2 | S95: =L95-Q95 -> -15335.98
A96: =B96&C96 -> Véhicules usagésAutres Marques | B96: Véhicules usagés | C96: Autres Marques | D96: =+INDEX('[5]Budget original'!$A$2:$AO$501,MATCH($A96,'[5]Budget original'!$A$2:$A$501,0),MATCH(D$2,'[5]Budget original'!$A$2:$AO$2,0)) -> 1.1518 | E96: =IF(D96=0,0,F96/D96) -> 1800 | F96: =+INDEX('[5]Budget original'!$A$2:$AO$501,MATCH($A96,'[5]Budget original'!$A$2:$A$501,0),MATCH(F$2,'[5]Budget original'!$A$2:$AO$2,0)) -> 2073.24 | J96: =-SUMIFS([5]BV_Data_An_Cour!$O:$O,[5]BV_Data_An_Cour!$U:$U,$B96,[5]BV_Data_An_Cour!$V:$V,$C96,[5]BV_Data_An_Cour!$W:$W,J$2) -> 3 | K96: =IF(J96=0,0,L96/J96) -> 2230.9333 | L96: =-SUMIFS([5]BV_Data_An_Cour!$O:$O,[5]BV_Data_An_Cour!$U:$U,$B96,[5]BV_Data_An_Cour!$V:$V,$C96,[5]BV_Data_An_Cour!$W:$W,$L2) -> 6692.8 | M96: =J96-D96 -> 1.8482 | N96: =L96-F96 -> 4619.56 | O96: =+INDEX('[5]Réel 2023'!$A$2:$AO$501,MATCH($A96,'[5]Réel 2023'!$A$2:$A$501,0),MATCH(O$2,'[5]Réel 2023'!$A$2:$AO$2,0)) -> 0 | P96: =IF(O96=0,0,Q96/O96) -> 0 | Q96: =+INDEX('[5]Réel 2023'!$A$2:$AO$501,MATCH($A96,'[5]Réel 2023'!$A$2:$A$501,0),MATCH(Q$2,'[5]Réel 2023'!$A$2:$AO$2,0)) -> 0 | R96: =J96-O96 -> 3 | S96: =L96-Q96 -> 6692.8
A97: =B97&C97 -> Véhicules usagésTotal Usagés | B97: Véhicules usagés | C97: Total Usagés | D97: =+D95+D94+D96 -> 37.655 | E97: =IF(D97=0,0,F97/D97) -> 1800 | F97: =+F94+F95+F96 -> 67779 | J97: =+J94+J95+J96 -> 43 | K97: =IF(J97<=0,0,L97/J97) -> 966.56977 | L97: =+L94+L95+L96 -> 41562.5 | M97: =J97-D97 -> 5.345 | N97: =L97-F97 -> -26216.5 | O97: =+O95+O94+O96 -> 26 | P97: =IF(O97=0,0,Q97/O97) -> 2013.9585 | Q97: =+Q94+Q95+Q96 -> 52362.92 | R97: =R94+R95 -> 14 | S97: =S94+S95 -> -17493.22
A98: =B98&C98 -> Véhicules usagés | B98: Véhicules usagés | E98: =IF(D98=0,0,F98/D98) -> 0 | M98: =M97/D97 -> 0.14194662 | N98: =N97/F97 -> -0.38679384 | P98: =IF(O98=0,0,Q98/O98) -> 0 | R98: =R97/O97 -> 0.53846154 | S98: =IF(Q97=0,0,(S97/Q97)) -> -0.33407648
A99: =B99&C99 -> Véhicules usagés | B99: Véhicules usagés | D99: =+INDEX('[5]Budget original'!$A$2:$AO$501,MATCH($A99,'[5]Budget original'!$A$2:$A$501,0),MATCH(D$2,'[5]Budget original'!$A$2:$AO$2,0)) -> 0 | E99: =IF(D99=0,0,F99/D99) -> 0 | F99: =+INDEX('[5]Budget original'!$A$2:$AO$501,MATCH($A99,'[5]Budget original'!$A$2:$A$501,0),MATCH(F$2,'[5]Budget original'!$A$2:$AO$2,0)) -> 0
A100: Véhicules usagésVentes au Gros | B100: Véhicules usagés | C100: Ventes au Gros | D100: =+INDEX('[5]Budget original'!$A$2:$AO$501,MATCH($A100,'[5]Budget original'!$A$2:$A$501,0),MATCH(D$2,'[5]Budget original'!$A$2:$AO$2,0)) -> 38.541 | E100: =IF(D100=0,0,F100/D100) -> 400 | F100: =+INDEX('[5]Budget original'!$A$2:$AO$501,MATCH($A100,'[5]Budget original'!$A$2:$A$501,0),MATCH(F$2,'[5]Budget original'!$A$2:$AO$2,0)) -> 15416.4 | J100: =-SUMIFS([5]BV_Data_An_Cour!$O:$O,[5]BV_Data_An_Cour!$U:$U,$B100,[5]BV_Data_An_Cour!$V:$V,$C100,[5]BV_Data_An_Cour!$W:$W,J$2) -> 23 | K100: =IF(J100=0,0,L100/J100) -> 251.70435 | L100: =-SUMIFS([5]BV_Data_An_Cour!$O:$O,[5]BV_Data_An_Cour!$U:$U,$B100,[5]BV_Data_An_Cour!$V:$V,$C100,[5]BV_Data_An_Cour!$W:$W,L$2) -> 5789.2 | M100: =J100-D100 -> -15.541 | N100: =L100-F100 -> -9627.2 | O100: {=+INDEX('[5]Réel 2023'!$A$2:$AO$501,MATCH($A100,'[5]Réel 2023'!$A$2:$A$501,0),MATCH(O$2,'[5]Réel 2023'!$A$2:$AO$2,0))} -> 38 | P100: =IF(O100=0,0,Q100/O100) -> 362.24263 | Q100: {=+INDEX('[5]Réel 2023'!$A$2:$AO$501,MATCH($A100,'[5]Réel 2023'!$A$2:$A$501,0),MATCH(Q$2,'[5]Réel 2023'!$A$2:$AO$2,0))} -> 13765.22 | R100: =J100-O100 -> -15 | S100: =L100-Q100 -> -7976.02
A101: Véhicules usagés | B101: Véhicules usagés
A102: Véhicules usagésRev. Finances | B102: Véhicules usagés | C102: Rev. Finances | D102: =+INDEX('[5]Budget original'!$A$2:$AO$501,MATCH($A102,'[5]Budget original'!$A$2:$A$501,0),MATCH(D$2,'[5]Budget original'!$A$2:$AO$2,0)) -> 0 | E102: =IF(D102=0,0,F102/D102) -> 0 | F102: =+INDEX('[5]Budget original'!$A$2:$AO$501,MATCH($A102,'[5]Budget original'!$A$2:$A$501,0),MATCH(F$2,'[5]Budget original'!$A$2:$AO$2,0)) -> 26358.5 | K102: =IF(J97=0,0,L102/J97) -> 354.06837 | L102: =-SUMIFS([5]BV_Data_An_Cour!$O:$O,[5]BV_Data_An_Cour!$U:$U,$B102,[5]BV_Data_An_Cour!$V:$V,$C102,[5]BV_Data_An_Cour!$W:$W,$L2) -> 15224.94 | N102: =L102-F102 -> -11133.56 | Q102: {=+INDEX('[5]Réel 2023'!$A$2:$AO$501,MATCH($A102,'[5]Réel 2023'!$A$2:$A$501,0),MATCH(Q$2,'[5]Réel 2023'!$A$2:$AO$2,0))} -> 19677.13 | R102: =O102-K102 -> -354.06837 | S102: =L102-Q102 -> -4452.19
A103: Véhicules usagésRev. Protections | B103: Véhicules usagés | C103: Rev. Protections | D103: =+INDEX('[5]Budget original'!$A$2:$AO$501,MATCH($A103,'[5]Budget original'!$A$2:$A$501,0),MATCH(D$2,'[5]Budget original'!$A$2:$AO$2,0)) -> 0 | E103: =IF(D103=0,0,F103/D103) -> 0 | F103: =+INDEX('[5]Budget original'!$A$2:$AO$501,MATCH($A103,'[5]Budget original'!$A$2:$A$501,0),MATCH(F$2,'[5]Budget original'!$A$2:$AO$2,0)) -> 54599.75 | K103: =IF(J97=0,0,L103/J97) -> 1561.194 | L103: =-SUMIFS([5]BV_Data_An_Cour!$O:$O,[5]BV_Data_An_Cour!$U:$U,$B103,[5]BV_Data_An_Cour!$V:$V,$C103,[5]BV_Data_An_Cour!$W:$W,$L2) -> 67131.34 | N103: =L103-F103 -> 12531.59 | Q103: {=+INDEX('[5]Réel 2023'!$A$2:$AO$501,MATCH($A103,'[5]Réel 2023'!$A$2:$A$501,0),MATCH(Q$2,'[5]Réel 2023'!$A$2:$AO$2,0))} -> 43319.66 | R103: =O103-K103 -> -1561.194 | S103: =L103-Q103 -> 23811.68
A104: Véhicules usagésRev. Autres | B104: Véhicules usagés | C104: Rev. Autres | D104: =+INDEX('[5]Budget original'!$A$2:$AO$501,MATCH($A104,'[5]Budget original'!$A$2:$A$501,0),MATCH(D$2,'[5]Budget original'!$A$2:$AO$2,0)) -> 0 | E104: =IF(D104=0,0,F104/D104) -> 0 | F104: =+INDEX('[5]Budget original'!$A$2:$AO$501,MATCH($A104,'[5]Budget original'!$A$2:$A$501,0),MATCH(F$2,'[5]Budget original'!$A$2:$AO$2,0)) -> 1882.75 | K104: =IF(J97=0,0,L104/J97) -> 26.634651 | L104: =-SUMIFS([5]BV_Data_An_Cour!$O:$O,[5]BV_Data_An_Cour!$U:$U,$B104,[5]BV_Data_An_Cour!$V:$V,$C104,[5]BV_Data_An_Cour!$W:$W,$L$2) -> 1145.29 | N104: =L104-F104 -> -737.46 | Q104: {=+INDEX('[5]Réel 2023'!$A$2:$AO$501,MATCH($A104,'[5]Réel 2023'!$A$2:$A$501,0),MATCH(Q$2,'[5]Réel 2023'!$A$2:$AO$2,0))} -> 1552.27 | R104: =O104-K104 -> -26.634651 | S104: =L104-Q104 -> -406.98
A105: Véhicules usagésTotal F&I | B105: Véhicules usagés | C105: Total F&I | D105: =D97 -> 37.655 | E105: =IF(D105=0,0,F105/D105) -> 2200 | F105: =F102+F103+F104 -> 82841 | J105: =J97 -> 43 | K105: =IF(J105<=0,0,L105/J105) -> 1941.897 | L105: =L102+L103+L104 -> 83501.57 | M105: =J105-D105 -> 5.345 | N105: =L105-F105 -> 660.57 | O105: =O97 -> 26 | P105: =IF(O105=0,0,Q105/O105) -> 2482.6562 | Q105: =Q102+Q103+Q104 -> 64549.06 | S105: =L105-Q105 -> 18952.51
...

Sheet Print_Mois
C1: =[7]Parametres!B1 -> Volks | K1: Véhicules neufs | S1: =CONCATENATE("Réalisé,"," ",[7]Parametres!B3," ",[7]Parametres!B4) -> Réalisé, Novembre 2024
D2: X | E2: O | F2: U | J2: NB | L2: $ | O2: X | P2: O | Q2: U | V2: *** NE PAS EFFACER / Pour An Précédente ***
D3: BUDGET ORIGINAL | J3: RÉALISATION | M3: ÉCART réel / Budget | O3: ANNÉE PRÉCÉDENTE | R3: ECART (réel/ Ann.Préc.) | V3: NEUF | W3: 0.45
D4: UNITE | E4: $P/UNITÉ | F4: $PROFITS | J4: UNITÉS | K4: $P/UNITE | L4: $PROFITS | M4: UNITÉS | N4: $PROFITS | O4: UNITE | P4: $P/UNITÉ | Q4: $PROFITS | R4: UNITÉS | S4: $PROFITS | V4: USAGE | W4: 0.1
A5: Véhicules neufsVentes nettes | B5: Véhicules neufs | C5: Ventes nettes | F5: =+INDEX('[7]Budget original'!$A$2:$AO$501,MATCH($A5,'[7]Budget original'!$A$2:$A$501,0),MATCH(F$2,'[7]Budget original'!$A$2:$AO$2,0)) -> 3242782.3 | L5: =-SUMIFS([7]BV_Data_An_Cour!$O:$O,[7]BV_Data_An_Cour!$X:$X,"Oui",[7]BV_Data_An_Cour!$U:$U,$B5) -> 2101403.3 | Q5: {=+INDEX('[7]Réel 2023'!$A$2:$AO$501,MATCH($A5,'[7]Réel 2023'!$A$2:$A$501,0),MATCH(Q$2,'[7]Réel 2023'!$A$2:$AO$2,0))} -> 10151414 | V5: SERVICE | W5: 0.225
A6: Véhicules neufsAutos détail | B6: Véhicules neufs | C6: Autos détail | D6: =+INDEX('[7]Budget original'!$A$2:$AO$501,MATCH($A6,'[7]Budget original'!$A$2:$A$501,0),MATCH(D$2,'[7]Budget original'!$A$2:$AO$2,0)) -> 12 | E6: =IF(D6=0,0,F6/D6) -> 2198.1219 | F6: =+INDEX('[7]Budget original'!$A$2:$AO$501,MATCH($A6,'[7]Budget original'!$A$2:$A$501,0),MATCH(F$2,'[7]Budget original'!$A$2:$AO$2,0)) -> 26377.463 | J6: =-SUMIFS([7]BV_Data_An_Cour!$O:$O,[7]BV_Data_An_Cour!$U:$U,$B6,[7]BV_Data_An_Cour!$V:$V,$C6,[7]BV_Data_An_Cour!$W:$W,J$2) -> 8 | K6: =IF(J6=0,0,L6/J6) -> 2031.0612 | L6: =-SUMIFS([7]BV_Data_An_Cour!$O:$O,[7]BV_Data_An_Cour!$U:$U,$B6,[7]BV_Data_An_Cour!$V:$V,$C6,[7]BV_Data_An_Cour!$W:$W,L$2) -> 16248.49 | M6: =J6-D6 -> -4 | N6: =L6-F6 -> -10128.973 | O6: =+INDEX('[7]Réel 2023'!$A$2:$AO$501,MATCH($A6,'[7]Réel 2023'!$A$2:$A$501,0),MATCH(O$2,'[7]Réel 2023'!$A$2:$AO$2,0)) -> 18 | P6: =IF(O6=0,0,Q6/O6) -> 2139.7994 | Q6: {=+INDEX('[7]Réel 2023'!$A$2:$AO$501,MATCH($A6,'[7]Réel 2023'!$A$2:$A$501,0),MATCH(Q$2,'[7]Réel 2023'!$A$2:$AO$2,0))} -> 38516.39 | R6: =J6-O6 -> -10 | S6: =L6-Q6 -> -22267.9 | V6: CARROSSERIE | W6: 0.025
A7: Véhicules neufsCamions détail | B7: Véhicules neufs | C7: Camions détail | D7: =+INDEX('[7]Budget original'!$A$2:$AO$501,MATCH($A7,'[7]Budget original'!$A$2:$A$501,0),MATCH(D$2,'[7]Budget original'!$A$2:$AO$2,0)) -> 49.8 | E7: =IF(D7=0,0,F7/D7) -> 2861.7055 | F7: =+INDEX('[7]Budget original'!$A$2:$AO$501,MATCH($A7,'[7]Budget original'!$A$2:$A$501,0),MATCH(F$2,'[7]Budget original'!$A$2:$AO$2,0)) -> 142512.93 | J7: =-SUMIFS([7]BV_Data_An_Cour!$O:$O,[7]BV_Data_An_Cour!$U:$U,$B7,[7]BV_Data_An_Cour!$V:$V,$C7,[7]BV_Data_An_Cour!$W:$W,J$2) -> 27 | K7: =IF(J7=0,0,L7/J7) -> 2114.5019 | L7: =-SUMIFS([7]BV_Data_An_Cour!$O:$O,[7]BV_Data_An_Cour!$U:$U,$B7,[7]BV_Data_An_Cour!$V:$V,$C7,[7]BV_Data_An_Cour!$W:$W,L$2) -> 57091.55 | M7: =J7-D7 -> -22.8 | N7: =L7-F7 -> -85421.385 | O7: {=+INDEX('[7]Réel 2023'!$A$2:$AO$501,MATCH($A7,'[7]Réel 2023'!$A$2:$A$501,0),MATCH(O$2,'[7]Réel 2023'!$A$2:$AO$2,0))} -> 71 | P7: =IF(O7=0,0,Q7/O7) -> 2320.119 | Q7: {=+INDEX('[7]Réel 2023'!$A$2:$AO$501,MATCH($A7,'[7]Réel 2023'!$A$2:$A$501,0),MATCH(Q$2,'[7]Réel 2023'!$A$2:$AO$2,0))} -> 164728.45 | R7: =J7-O7 -> -44 | S7: =L7-Q7 -> -107636.9 | V7: PIECES | W7: 0.2
A8: Véhicules neufsSprinter | B8: Véhicules neufs | C8: Sprinter | D8: =+INDEX('[7]Budget original'!$A$2:$AO$501,MATCH($A8,'[7]Budget original'!$A$2:$A$501,0),MATCH(D$2,'[7]Budget original'!$A$2:$AO$2,0)) -> 0 | E8: =IF(D8=0,0,F8/D8) -> 0 | F8: =+INDEX('[7]Budget original'!$A$2:$AO$501,MATCH($A8,'[7]Budget original'!$A$2:$A$501,0),MATCH(F$2,'[7]Budget original'!$A$2:$AO$2,0)) -> 0 | J8: =-SUMIFS([7]BV_Data_An_Cour!$O:$O,[7]BV_Data_An_Cour!$U:$U,$B8,[7]BV_Data_An_Cour!$V:$V,$C8,[7]BV_Data_An_Cour!$W:$W,J$2) -> 0 | K8: =IF(J8=0,0,L8/J8) -> 0 | L8: =-SUMIFS([7]BV_Data_An_Cour!$O:$O,[7]BV_Data_An_Cour!$U:$U,$B8,[7]BV_Data_An_Cour!$V:$V,$C8,[7]BV_Data_An_Cour!$W:$W,L$2) -> 0 | M8: =J8-D8 -> 0 | N8: =L8-F8 -> 0 | O8: {=+INDEX('[7]Réel 2023'!$A$2:$AO$501,MATCH($A8,'[7]Réel 2023'!$A$2:$A$501,0),MATCH(O$2,'[7]Réel 2023'!$A$2:$AO$2,0))} -> 0 | P8: =IF(O8=0,0,Q8/O8) -> 0 | Q8: {=+INDEX('[7]Réel 2023'!$A$2:$AO$501,MATCH($A8,'[7]Réel 2023'!$A$2:$A$501,0),MATCH(Q$2,'[7]Réel 2023'!$A$2:$AO$2,0))} -> 0 | R8: =J8-O8 -> 0 | S8: =L8-Q8 -> 0 | W8: =SUM(W3:W7) -> 1
A9: Véhicules neufsMoto détail | B9: Véhicules neufs | C9: Moto détail | D9: =+INDEX('[7]Budget original'!$A$2:$AO$501,MATCH($A9,'[7]Budget original'!$A$2:$A$501,0),MATCH(D$2,'[7]Budget original'!$A$2:$AO$2,0)) -> 0 | E9: =IF(D9=0,0,F9/D9) -> 0 | F9: =+INDEX('[7]Budget original'!$A$2:$AO$501,MATCH($A9,'[7]Budget original'!$A$2:$A$501,0),MATCH(F$2,'[7]Budget original'!$A$2:$AO$2,0)) -> 0 | J9: =-SUMIFS([7]BV_Data_An_Cour!$O:$O,[7]BV_Data_An_Cour!$U:$U,$B9,[7]BV_Data_An_Cour!$V:$V,$C9,[7]BV_Data_An_Cour!$W:$W,J$2) -> 0 | K9: =IF(J9=0,0,L9/J9) -> 0 | L9: =-SUMIFS([7]BV_Data_An_Cour!$O:$O,[7]BV_Data_An_Cour!$U:$U,$B9,[7]BV_Data_An_Cour!$V:$V,$C9,[7]BV_Data_An_Cour!$W:$W,L$2) -> 0 | M9: =J9-D9 -> 0 | N9: =L9-F9 -> 0 | O9: {=+INDEX('[7]Réel 2023'!$A$2:$AO$501,MATCH($A9,'[7]Réel 2023'!$A$2:$A$501,0),MATCH(O$2,'[7]Réel 2023'!$A$2:$AO$2,0))} -> 0 | P9: =IF(O9=0,0,Q9/O9) -> 0 | Q9: {=+INDEX('[7]Réel 2023'!$A$2:$AO$501,MATCH($A9,'[7]Réel 2023'!$A$2:$A$501,0),MATCH(Q$2,'[7]Réel 2023'!$A$2:$AO$2,0))} -> 0 | R9: =J9-O9 -> 0 | S9: =L9-Q9 -> 0
A10: Véhicules neufs[...] | B10: Véhicules neufs | C10: [...] | D10: =+INDEX('[7]Budget original'!$A$2:$AO$501,MATCH($A10,'[7]Budget original'!$A$2:$A$501,0),MATCH(D$2,'[7]Budget original'!$A$2:$AO$2,0)) -> 0 | E10: =IF(D10=0,0,F10/D10) -> 0 | F10: =+INDEX('[7]Budget original'!$A$2:$AO$501,MATCH($A10,'[7]Budget original'!$A$2:$A$501,0),MATCH(F$2,'[7]Budget original'!$A$2:$AO$2,0)) -> 0 | J10: =-SUMIFS([7]BV_Data_An_Cour!$O:$O,[7]BV_Data_An_Cour!$U:$U,$B10,[7]BV_Data_An_Cour!$V:$V,$C10,[7]BV_Data_An_Cour!$W:$W,J$2) -> 0 | K10: =IF(J10=0,0,L10/J10) -> 0 | L10: =-SUMIFS([7]BV_Data_An_Cour!$O:$O,[7]BV_Data_An_Cour!$U:$U,$B10,[7]BV_Data_An_Cour!$V:$V,$C10,[7]BV_Data_An_Cour!$W:$W,L$2) -> 0 | M10: =J10-D10 -> 0 | N10: =L10-F10 -> 0 | O10: {=+INDEX('[7]Réel 2023'!$A$2:$AO$501,MATCH($A10,'[7]Réel 2023'!$A$2:$A$501,0),MATCH(O$2,'[7]Réel 2023'!$A$2:$AO$2,0))} -> 0 | P10: =IF(O10=0,0,Q10/O10) -> 0 | Q10: {=+INDEX('[7]Réel 2023'!$A$2:$AO$501,MATCH($A10,'[7]Réel 2023'!$A$2:$A$501,0),MATCH(Q$2,'[7]Réel 2023'!$A$2:$AO$2,0))} -> 0 | R10: =J10-O10 -> 0 | S10: =L10-Q10 -> 0
A11: Véhicules neufs[...] | B11: Véhicules neufs | C11: [...] | D11: =+INDEX('[7]Budget original'!$A$2:$AO$501,MATCH($A11,'[7]Budget original'!$A$2:$A$501,0),MATCH(D$2,'[7]Budget original'!$A$2:$AO$2,0)) -> 0 | E11: =IF(D11=0,0,F11/D11) -> 0 | F11: =+INDEX('[7]Budget original'!$A$2:$AO$501,MATCH($A11,'[7]Budget original'!$A$2:$A$501,0),MATCH(F$2,'[7]Budget original'!$A$2:$AO$2,0)) -> 0 | J11: =-SUMIFS([7]BV_Data_An_Cour!$O:$O,[7]BV_Data_An_Cour!$U:$U,$B11,[7]BV_Data_An_Cour!$V:$V,$C11,[7]BV_Data_An_Cour!$W:$W,J$2) -> 0 | K11: =IF(J11=0,0,L11/J11) -> 0 | L11: =-SUMIFS([7]BV_Data_An_Cour!$O:$O,[7]BV_Data_An_Cour!$U:$U,$B11,[7]BV_Data_An_Cour!$V:$V,$C11,[7]BV_Data_An_Cour!$W:$W,L$2) -> 0 | M11: =J11-D11 -> 0 | N11: =L11-F11 -> 0 | O11: {=+INDEX('[7]Réel 2023'!$A$2:$AO$501,MATCH($A11,'[7]Réel 2023'!$A$2:$A$501,0),MATCH(O$2,'[7]Réel 2023'!$A$2:$AO$2,0))} -> 0 | P11: =IF(O11=0,0,Q11/O11) -> 0 | Q11: {=+INDEX('[7]Réel 2023'!$A$2:$AO$501,MATCH($A11,'[7]Réel 2023'!$A$2:$A$501,0),MATCH(Q$2,'[7]Réel 2023'!$A$2:$AO$2,0))} -> 0 | R11: =J11-O11 -> 0 | S11: =L11-Q11 -> 0
A12: Véhicules neufs[...] | B12: Véhicules neufs | C12: [...] | D12: =+INDEX('[7]Budget original'!$A$2:$AO$501,MATCH($A12,'[7]Budget original'!$A$2:$A$501,0),MATCH(D$2,'[7]Budget original'!$A$2:$AO$2,0)) -> 0 | E12: =IF(D12=0,0,F12/D12) -> 0 | F12: =+INDEX('[7]Budget original'!$A$2:$AO$501,MATCH($A12,'[7]Budget original'!$A$2:$A$501,0),MATCH(F$2,'[7]Budget original'!$A$2:$AO$2,0)) -> 0 | J12: =-SUMIFS([7]BV_Data_An_Cour!$O:$O,[7]BV_Data_An_Cour!$U:$U,$B12,[7]BV_Data_An_Cour!$V:$V,$C12,[7]BV_Data_An_Cour!$W:$W,J$2) -> 0 | K12: =IF(J12=0,0,L12/J12) -> 0 | L12: =-SUMIFS([7]BV_Data_An_Cour!$O:$O,[7]BV_Data_An_Cour!$U:$U,$B12,[7]BV_Data_An_Cour!$V:$V,$C12,[7]BV_Data_An_Cour!$W:$W,L$2) -> 0 | M12: =J12-D12 -> 0 | N12: =L12-F12 -> 0 | O12: {=+INDEX('[7]Réel 2023'!$A$2:$AO$501,MATCH($A12,'[7]Réel 2023'!$A$2:$A$501,0),MATCH(O$2,'[7]Réel 2023'!$A$2:$AO$2,0))} -> 0 | P12: =IF(O12=0,0,Q12/O12) -> 0 | Q12: {=+INDEX('[7]Réel 2023'!$A$2:$AO$501,MATCH($A12,'[7]Réel 2023'!$A$2:$A$501,0),MATCH(Q$2,'[7]Réel 2023'!$A$2:$AO$2,0))} -> 0 | R12: =J12-O12 -> 0 | S12: =L12-Q12 -> 0
A13: Véhicules neufsTotal Neufs | B13: Véhicules neufs | C13: Total Neufs | D13: =+SUM(D6:D12) -> 61.8 | E13: =IF(D13<=0,0,F13/D13) -> 2732.8543 | F13: =+SUM(F6:F12) -> 168890.4 | J13: =+SUM(J6:J12) -> 35 | K13: =IF(J13<=0,0,L13/J13) -> 2095.4297 | L13: =+SUM(L6:L12) -> 73340.04 | M13: =+SUM(M6:M12) -> -26.8 | N13: =+SUM(N6:N12) -> -95550.358 | O13: =+SUM(O6:O12) -> 89 | P13: =IF(O13<=0,0,Q13/O13) -> 2283.6499 | Q13: =+SUM(Q6:Q12) -> 203244.84 | R13: =+SUM(R6:R12) -> -54 | S13: =+SUM(S6:S12) -> -129904.8
A14: Véhicules neufs | B14: Véhicules neufs | M14: =IF(D13=0,0,M13/D13) -> -0.43365696 | N14: =IF(F13=0,0,N13/F13) -> -0.56575364 | R14: =R13/O13 -> -0.60674157 | S14: =IF(Q13=0,0,(S13/Q13)) -> -0.63915423 | AD14: 20 | AE14: 1000 | AF14: =AD14*AE14 -> 20000
A15: Véhicules neufsEx-Démos et courtoisies | B15: Véhicules neufs | C15: Ex-Démos et courtoisies | D15: =+INDEX('[7]Budget original'!$A$2:$AO$501,MATCH($A15,'[7]Budget original'!$A$2:$A$501,0),MATCH(D$2,'[7]Budget original'!$A$2:$AO$2,0)) -> 4.96 | E15: =IF(D15=0,0,F15/D15) -> 2504.4548 | F15: =+INDEX('[7]Budget original'!$A$2:$AO$501,MATCH($A15,'[7]Budget original'!$A$2:$A$501,0),MATCH(F$2,'[7]Budget original'!$A$2:$AO$2,0)) -> 12422.096 | J15: =-SUMIFS([7]BV_Data_An_Cour!$O:$O,[7]BV_Data_An_Cour!$U:$U,$B15,[7]BV_Data_An_Cour!$V:$V,$C15,[7]BV_Data_An_Cour!$W:$W,J$2) -> 2 | K15: =IF(J15=0,0,L15/J15) -> 1396.23 | L15: =-SUMIFS([7]BV_Data_An_Cour!$O:$O,[7]BV_Data_An_Cour!$U:$U,$B15,[7]BV_Data_An_Cour!$V:$V,$C15,[7]BV_Data_An_Cour!$W:$W,L$2) -> 2792.46 | M15: =J15-D15 -> -2.96 | N15: =L15-F15 -> -9629.6358 | O15: {=+INDEX('[7]Réel 2023'!$A$2:$AO$501,MATCH($A15,'[7]Réel 2023'!$A$2:$A$501,0),MATCH(O$2,'[7]Réel 2023'!$A$2:$AO$2,0))} -> 1 | P15: =IF(O15=0,0,Q15/O15) -> 1154.94 | Q15: {=+INDEX('[7]Réel 2023'!$A$2:$AO$501,MATCH($A15,'[7]Réel 2023'!$A$2:$A$501,0),MATCH(Q$2,'[7]Réel 2023'!$A$2:$AO$2,0))} -> 1154.94 | R15: =J15-O15 -> 1 | S15: =L15-Q15 -> 1637.52 | AD15: 25 | AE15: =AF15/AD15 -> 800 | AF15: =AF14 -> 20000
A16: Véhicules neufs | B16: Véhicules neufs
A17: Véhicules neufsFlottes | B17: Véhicules neufs | C17: Flottes | D17: =+INDEX('[7]Budget original'!$A$2:$AO$501,MATCH($A17,'[7]Budget original'!$A$2:$A$501,0),MATCH(D$2,'[7]Budget original'!$A$2:$AO$2,0)) -> 4.5 | E17: =IF(D17=0,0,F17/D17) -> 2664.4641 | F17: =+INDEX('[7]Budget original'!$A$2:$AO$501,MATCH($A17,'[7]Budget original'!$A$2:$A$501,0),MATCH(F$2,'[7]Budget original'!$A$2:$AO$2,0)) -> 11990.088 | J17: =-SUMIFS([7]BV_Data_An_Cour!$O:$O,[7]BV_Data_An_Cour!$U:$U,$B17,[7]BV_Data_An_Cour!$V:$V,$C17,[7]BV_Data_An_Cour!$W:$W,J$2) -> 3 | K17: =IF(J17=0,0,L17/J17) -> 1478.8733 | L17: =-SUMIFS([7]BV_Data_An_Cour!$O:$O,[7]BV_Data_An_Cour!$U:$U,$B17,[7]BV_Data_An_Cour!$V:$V,$C17,[7]BV_Data_An_Cour!$W:$W,L$2) -> 4436.62 | M17: =J17-D17 -> -1.5 | N17: =L17-F17 -> -7553.4683 | O17: {=+INDEX('[7]Réel 2023'!$A$2:$AO$501,MATCH($A17,'[7]Réel 2023'!$A$2:$A$501,0),MATCH(O$2,'[7]Réel 2023'!$A$2:$AO$2,0))} -> 2 | P17: =IF(O17=0,0,Q17/O17) -> 3324.41 | Q17: {=+INDEX('[7]Réel 2023'!$A$2:$AO$501,MATCH($A17,'[7]Réel 2023'!$A$2:$A$501,0),MATCH(Q$2,'[7]Réel 2023'!$A$2:$AO$2,0))} -> 6648.82 | R17: =J17-O17 -> 1 | S17: =L17-Q17 -> -2212.2
A18: Véhicules neufs | B18: Véhicules neufs
A19: Véhicules neufsRachat bail | B19: Véhicules neufs | C19: Rachat bail | D19: =+INDEX('[7]Budget original'!$A$2:$AO$501,MATCH($A19,'[7]Budget original'!$A$2:$A$501,0),MATCH(D$2,'[7]Budget original'!$A$2:$AO$2,0)) -> 0 | E19: =IF(D19=0,0,F19/D19) -> 0 | F19: =+INDEX('[7]Budget original'!$A$2:$AO$501,MATCH($A19,'[7]Budget original'!$A$2:$A$501,0),MATCH(F$2,'[7]Budget original'!$A$2:$AO$2,0)) -> 8500 | L19: =-SUMIFS([7]BV_Data_An_Cour!$O:$O,[7]BV_Data_An_Cour!$U:$U,$B19,[7]BV_Data_An_Cour!$V:$V,$C19,[7]BV_Data_An_Cour!$W:$W,L$2) -> 7700 | N19: =L19-F19 -> -800 | Q19: {=+INDEX('[7]Réel 2023'!$A$2:$AO$501,MATCH($A19,'[7]Réel 2023'!$A$2:$A$501,0),MATCH(Q$2,'[7]Réel 2023'!$A$2:$AO$2,0))} -> 3732.16 | R19: =O19-K19 -> 0 | S19: =L19-Q19 -> 3967.84
A20: Véhicules neufs | B20: Véhicules neufs
A21: Véhicules neufsRev. Finances | B21: Véhicules neufs | C21: Rev. Finances | D21: =+INDEX('[7]Budget original'!$A$2:$AO$501,MATCH($A21,'[7]Budget original'!$A$2:$A$501,0),MATCH(D$2,'[7]Budget original'!$A$2:$AO$2,0)) -> 0 | E21: =IF(D21=0,0,F21/D21) -> 0 | F21: =+INDEX('[7]Budget original'!$A$2:$AO$501,MATCH($A21,'[7]Budget original'!$A$2:$A$501,0),MATCH(F$2,'[7]Budget original'!$A$2:$AO$2,0)) -> 13352 | K21: =IF(J13=0,0,L21/(J13+J15)) -> 0 | L21: =-SUMIFS([7]BV_Data_An_Cour!$O:$O,[7]BV_Data_An_Cour!$U:$U,$B21,[7]BV_Data_An_Cour!$V:$V,$C21,[7]BV_Data_An_Cour!$W:$W,L$2) -> 0 | N21: =L21-F21 -> -13352 | Q21: {=+INDEX('[7]Réel 2023'!$A$2:$AO$501,MATCH($A21,'[7]Réel 2023'!$A$2:$A$501,0),MATCH(Q$2,'[7]Réel 2023'!$A$2:$AO$2,0))} -> 4322.42 | R21: =O21-K21 -> 0 | S21: =L21-Q21 -> -4322.42
A22: Véhicules neufsRev. Protections | B22: Véhicules neufs | C22: Rev. Protections | D22: =+INDEX('[7]Budget original'!$A$2:$AO$501,MATCH($A22,'[7]Budget original'!$A$2:$A$501,0),MATCH(D$2,'[7]Budget original'!$A$2:$AO$2,0)) -> 0 | E22: =IF(D22=0,0,F22/D22) -> 0 | F22: =+INDEX('[7]Budget original'!$A$2:$AO$501,MATCH($A22,'[7]Budget original'!$A$2:$A$501,0),MATCH(F$2,'[7]Budget original'!$A$2:$AO$2,0)) -> 72100.8 | K22: =IF(J13=0,0,L22/(J13+J15)) -> 1044.0162 | L22: =-SUMIFS([7]BV_Data_An_Cour!$O:$O,[7]BV_Data_An_Cour!$U:$U,$B22,[7]BV_Data_An_Cour!$V:$V,$C22,[7]BV_Data_An_Cour!$W:$W,L$2) -> 38628.6 | N22: =L22-F22 -> -33472.2 | Q22: {=+INDEX('[7]Réel 2023'!$A$2:$AO$501,MATCH($A22,'[7]Réel 2023'!$A$2:$A$501,0),MATCH(Q$2,'[7]Réel 2023'!$A$2:$AO$2,0))} -> 89386.52 | R22: =O22-K22 -> -1044.0162 | S22: =L22-Q22 -> -50757.92
A23: Véhicules neufsRev. Autres | B23: Véhicules neufs | C23: Rev. Autres | D23: =+INDEX('[7]Budget original'!$A$2:$AO$501,MATCH($A23,'[7]Budget original'!$A$2:$A$501,0),MATCH(D$2,'[7]Budget original'!$A$2:$AO$2,0)) -> 0 | E23: =IF(D23=0,0,F23/D23) -> 0 | F23: =+INDEX('[7]Budget original'!$A$2:$AO$501,MATCH($A23,'[7]Budget original'!$A$2:$A$501,0),MATCH(F$2,'[7]Budget original'!$A$2:$AO$2,0)) -> 1335.2 | K23: =IF(J13=0,0,L23/(J13+J15)) -> 17.436757 | L23: =-SUMIFS([7]BV_Data_An_Cour!$O:$O,[7]BV_Data_An_Cour!$U:$U,$B23,[7]BV_Data_An_Cour!$V:$V,$C23,[7]BV_Data_An_Cour!$W:$W,L$2) -> 645.16 | N23: =L23-F23 -> -690.04 | Q23: {=+INDEX('[7]Réel 2023'!$A$2:$AO$501,MATCH($A23,'[7]Réel 2023'!$A$2:$A$501,0),MATCH(Q$2,'[7]Réel 2023'!$A$2:$AO$2,0))} -> 1350.84 | R23: =O23-K23 -> -17.436757 | S23: =L23-Q23 -> -705.68
A24: Véhicules neufsTotal F&I | B24: Véhicules neufs | C24: Total F&I | D24: =+D15+D13 -> 66.76 | E24: =IF(D24<=0,0,F24/D24) -> 1300 | F24: =F21+F22+F23 -> 86788 | J24: =+J15+J13 -> 37 | K24: =IF(J24<=0,0,L24/J24) -> 1061.453 | L24: =L21+L22+L23 -> 39273.76 | M24: =J24-D24 -> -29.76 | N24: =L24-F24 -> -47514.24 | O24: =+O15+O13 -> 90 | P24: =IF(O24<=0,0,Q24/O24) -> 1056.2198 | Q24: =Q21+Q22+Q23 -> 95059.78 | S24: =L24-Q24 -> -55786.02
A25: Véhicules neufs | B25: Véhicules neufs | N25: =IF(N24=0,0,N24/F24) -> -0.54747477 | S25: =IF(Q24=0,0,(S24/Q24)) -> -0.58685198
A26: Véhicules neufs | B26: Véhicules neufs
A27: Véhicules neufsTotal Dépt. Neufs | B27: Véhicules neufs | C27: Total Dépt. Neufs | D27: =+D13+D15+D17 -> 71.26 | E27: =IF(D27<=0,0,F27/D27) -> 4049.8257 | F27: =F13+F17+F24+F19+F15 -> 288590.58 | J27: =+J13+J15+J17 -> 40 | K27: =IF(J27<=0,0,L27/J27) -> 3188.572 | L27: =L13+L17+L24+L19+L15 -> 127542.88 | M27: =J27-D27 -> -31.26 | N27: =L27-F27 -> -161047.7 | O27: =+O13+O15+O17 -> 92 | P27: =IF(O27<=0,0,Q27/O27) -> 3367.832 | Q27: =Q13+Q17+Q24+Q19+Q15 -> 309840.54 | R27: =J27-O27 -> -52 | S27: =L27-Q27 -> -182297.66
A28: Véhicules neufs | B28: Véhicules neufs | L28: =L27/F27 -> 0.44195094 | M28: =M27/D27 -> -0.43867527 | N28: =N27/F27 -> -0.55804906 | R28: =R27/O27 -> -0.56521739 | S28: =IF(Q27=0,0,S27/Q27) -> -0.58835961
A29: Véhicules neufs | B29: Véhicules neufs
A30: Véhicules neufsDEPENSES | B30: Véhicules neufs | C30: DEPENSES
A31: Véhicules neufsComm. vendeurs | B31: Véhicules neufs | C31: Comm. vendeurs | D31: =F31/(F13+F15) -> 0.34 | E31: =F31/D$24 -> 923.40096 | F31: =+INDEX('[7]Budget original'!$A$2:$AO$501,MATCH($A31,'[7]Budget original'!$A$2:$A$501,0),MATCH(F$2,'[7]Budget original'!$A$2:$AO$2,0)) -> 61646.248 | J31: =L31/(L15+L13+L17) -> 0.29663462 | K31: =IF(L31=0,0,L31/J$24) -> 645.93486 | L31: =SUMIFS([7]BV_Data_An_Cour!$O:$O,[7]BV_Data_An_Cour!$U:$U,$B31,[7]BV_Data_An_Cour!$V:$V,$C31,[7]BV_Data_An_Cour!$W:$W,L$2) -> 23899.59 | N31: =L31-F31 -> -37746.658 | O31: =Q31/(Q13+Q15+Q17) -> 0.21328163 | P31: =Q31/O$24 -> 500.14211 | Q31: {=+INDEX('[7]Réel 2023'!$A$2:$AO$501,MATCH($A31,'[7]Réel 2023'!$A$2:$A$501,0),MATCH(Q$2,'[7]Réel 2023'!$A$2:$AO$2,0))} -> 45012.79 | S31: =L31-Q31 -> -21113.2
A32: Véhicules neufsComm. F&I | B32: Véhicules neufs | C32: Comm. F&I | D32: =F32/F24 -> 0.3 | E32: =F32/D$24 -> 390 | F32: =+INDEX('[7]Budget original'!$A$2:$AO$501,MATCH($A32,'[7]Budget original'!$A$2:$A$501,0),MATCH(F$2,'[7]Budget original'!$A$2:$AO$2,0)) -> 26036.4 | J32: =L32/L24 -> 0.27998974 | K32: =IF(L32=0,0,L32/J$24) -> 297.19595 | L32: =SUMIFS([7]BV_Data_An_Cour!$O:$O,[7]BV_Data_An_Cour!$U:$U,$B32,[7]BV_Data_An_Cour!$V:$V,$C32,[7]BV_Data_An_Cour!$W:$W,L$2) -> 10996.25 | N32: =L32-F32 -> -15040.15 | O32: =Q32/Q24 -> 0.29960999 | P32: =Q32/O$24 -> 316.454 | Q32: {=+INDEX('[7]Réel 2023'!$A$2:$AO$501,MATCH($A32,'[7]Réel 2023'!$A$2:$A$501,0),MATCH(Q$2,'[7]Réel 2023'!$A$2:$AO$2,0))} -> 28480.86 | S32: =L32-Q32 -> -17484.61
A33: Véhicules neufsFrais de livraison | B33: Véhicules neufs | C33: Frais de livraison | E33: =F33/D$24 -> 115 | F33: =+INDEX('[7]Budget original'!$A$2:$AO$501,MATCH($A33,'[7]Budget original'!$A$2:$A$501,0),MATCH(F$2,'[7]Budget original'!$A$2:$AO$2,0)) -> 7677.4 | K33: =IF(L33=0,0,L33/J$24) -> 233.92757 | L33: =SUMIFS([7]BV_Data_An_Cour!$O:$O,[7]BV_Data_An_Cour!$U:$U,$B33,[7]BV_Data_An_Cour!$V:$V,$C33,[7]BV_Data_An_Cour!$W:$W,L$2) -> 8655.32 | N33: =L33-F33 -> 977.92 | P33: =Q33/O$24 -> 138.78767 | Q33: {=+INDEX('[7]Réel 2023'!$A$2:$AO$501,MATCH($A33,'[7]Réel 2023'!$A$2:$A$501,0),MATCH(Q$2,'[7]Réel 2023'!$A$2:$AO$2,0))} -> 12490.89 | S33: =L33-Q33 -> -3835.57
A34: Véhicules neufsService gratuit 1 | B34: Véhicules neufs | C34: Service gratuit 1 | E34: =F34/D$24 -> 3 | F34: =+INDEX('[7]Budget original'!$A$2:$AO$501,MATCH($A34,'[7]Budget original'!$A$2:$A$501,0),MATCH(F$2,'[7]Budget original'!$A$2:$AO$2,0)) -> 200.28 | K34: =IF(L34=0,0,L34/J$24) -> 108.85892 | L34: =SUMIFS([7]BV_Data_An_Cour!$O:$O,[7]BV_Data_An_Cour!$U:$U,$B34,[7]BV_Data_An_Cour!$V:$V,$C34,[7]BV_Data_An_Cour!$W:$W,L$2) -> 4027.78 | N34: =L34-F34 -> 3827.5 | P34: =Q34/O$24 -> 63.110222 | Q34: {=+INDEX('[7]Réel 2023'!$A$2:$AO$501,MATCH($A34,'[7]Réel 2023'!$A$2:$A$501,0),MATCH(Q$2,'[7]Réel 2023'!$A$2:$AO$2,0))} -> 5679.92 | S34: =L34-Q34 -> -1652.14
A35: Véhicules neufsEntretien stock | B35: Véhicules neufs | C35: Entretien stock | E35: =F35/D$24 -> 85.05 | F35: =+INDEX('[7]Budget original'!$A$2:$AO$501,MATCH($A35,'[7]Budget original'!$A$2:$A$501,0),MATCH(F$2,'[7]Budget original'!$A$2:$AO$2,0)) -> 5677.938 | K35: =IF(L35=0,0,L35/J$24) -> 212.08676 | L35: =SUMIFS([7]BV_Data_An_Cour!$O:$O,[7]BV_Data_An_Cour!$U:$U,$B35,[7]BV_Data_An_Cour!$V:$V,$C35,[7]BV_Data_An_Cour!$W:$W,L$2) -> 7847.21 | N35: =L35-F35 -> 2169.272 | P35: =Q35/O$24 -> 83.834222 | Q35: {=+INDEX('[7]Réel 2023'!$A$2:$AO$501,MATCH($A35,'[7]Réel 2023'!$A$2:$A$501,0),MATCH(Q$2,'[7]Réel 2023'!$A$2:$AO$2,0))} -> 7545.08 | S35: =L35-Q35 -> 302.13
A36: Véhicules neufsPublicité 1 | B36: Véhicules neufs | C36: Publicité 1 | E36: =F36/D$24 -> 113.24146 | F36: =+INDEX('[7]Budget original'!$A$2:$AO$501,MATCH($A36,'[7]Budget original'!$A$2:$A$501,0),MATCH(F$2,'[7]Budget original'!$A$2:$AO$2,0)) -> 7560 | K36: =IF(L36=0,0,L36/J$24) -> 527.05568 | L36: =SUMIFS([7]BV_Data_An_Cour!$O:$O,[7]BV_Data_An_Cour!$U:$U,$B36,[7]BV_Data_An_Cour!$V:$V,$C36,[7]BV_Data_An_Cour!$W:$W,L$2) -> 19501.06 | N36: =L36-F36 -> 11941.06 | P36: =Q36/O$24 -> 38.481889 | Q36: {=+INDEX('[7]Réel 2023'!$A$2:$AO$501,MATCH($A36,'[7]Réel 2023'!$A$2:$A$501,0),MATCH(Q$2,'[7]Réel 2023'!$A$2:$AO$2,0))} -> 3463.37 | S36: =L36-Q36 -> 16037.69
A37: Véhicules neufsIntérêt de gros | B37: Véhicules neufs | C37: Intérêt de gros | E37: =F37/D$24 -> 188.77187 | F37: =+INDEX('[7]Budget original'!$A$2:$AO$501,MATCH($A37,'[7]Budget original'!$A$2:$A$501,0),MATCH(F$2,'[7]Budget original'!$A$2:$AO$2,0)) -> 12602.41 | K37: =IF(L37=0,0,L37/J$24) -> -1003.7751 | L37: =SUMIFS([7]BV_Data_An_Cour!$O:$O,[7]BV_Data_An_Cour!$U:$U,$B37,[7]BV_Data_An_Cour!$V:$V,$C37,[7]BV_Data_An_Cour!$W:$W,L$2) -> -37139.68 | N37: =L37-F37 -> -49742.09 | P37: =Q37/O$24 -> 217.76156 | Q37: {=+INDEX('[7]Réel 2023'!$A$2:$AO$501,MATCH($A37,'[7]Réel 2023'!$A$2:$A$501,0),MATCH(Q$2,'[7]Réel 2023'!$A$2:$AO$2,0))} -> 19598.54 | S37: =L37-Q37 -> -56738.22
A38: Véhicules neufs[...] | B38: Véhicules neufs | C38: [...] | E38: =F38/D$24 -> 0 | F38: =+INDEX('[7]Budget original'!$A$2:$AO$501,MATCH($A38,'[7]Budget original'!$A$2:$A$501,0),MATCH(F$2,'[7]Budget original'!$A$2:$AO$2,0)) -> 0 | K38: =IF(L38=0,0,L38/J$24) -> 0 | L38: =SUMIFS([7]BV_Data_An_Cour!$O:$O,[7]BV_Data_An_Cour!$U:$U,$B38,[7]BV_Data_An_Cour!$V:$V,$C38,[7]BV_Data_An_Cour!$W:$W,L$2) -> 0 | N38: =L38-F38 -> 0 | P38: =Q38/O$24 -> 0 | Q38: {=+INDEX('[7]Réel 2023'!$A$2:$AO$501,MATCH($A38,'[7]Réel 2023'!$A$2:$A$501,0),MATCH(Q$2,'[7]Réel 2023'!$A$2:$AO$2,0))} -> 0 | S38: =L38-Q38 -> 0
A39: Véhicules neufs[...] | B39: Véhicules neufs | C39: [...] | E39: =F39/D$24 -> 0 | F39: =+INDEX('[7]Budget original'!$A$2:$AO$501,MATCH($A39,'[7]Budget original'!$A$2:$A$501,0),MATCH(F$2,'[7]Budget original'!$A$2:$AO$2,0)) -> 0 | K39: =IF(L39=0,0,L39/J$24) -> 0 | L39: =SUMIFS([7]BV_Data_An_Cour!$O:$O,[7]BV_Data_An_Cour!$U:$U,$B39,[7]BV_Data_An_Cour!$V:$V,$C39,[7]BV_Data_An_Cour!$W:$W,L$2) -> 0 | N39: =L39-F39 -> 0 | P39: =Q39/O$24 -> 0 | Q39: {=+INDEX('[7]Réel 2023'!$A$2:$AO$501,MATCH($A39,'[7]Réel 2023'!$A$2:$A$501,0),MATCH(Q$2,'[7]Réel 2023'!$A$2:$AO$2,0))} -> 0 | S39: =L39-Q39 -> 0
A40: Véhicules neufs[...] | B40: Véhicules neufs | C40: [...] | E40: =F40/D$24 -> 0 | F40: =+INDEX('[7]Budget original'!$A$2:$AO$501,MATCH($A40,'[7]Budget original'!$A$2:$A$501,0),MATCH(F$2,'[7]Budget original'!$A$2:$AO$2,0)) -> 0 | K40: =IF(L40=0,0,L40/J$24) -> 0 | L40: =SUMIFS([7]BV_Data_An_Cour!$O:$O,[7]BV_Data_An_Cour!$U:$U,$B40,[7]BV_Data_An_Cour!$V:$V,$C40,[7]BV_Data_An_Cour!$W:$W,L$2) -> 0 | N40: =L40-F40 -> 0 | P40: =Q40/O$24 -> 0 | Q40: {=+INDEX('[7]Réel 2023'!$A$2:$AO$501,MATCH($A40,'[7]Réel 2023'!$A$2:$A$501,0),MATCH(Q$2,'[7]Réel 2023'!$A$2:$AO$2,0))} -> 0 | S40: =L40-Q40 -> 0
A41: Véhicules neufsTOTAL VARIABLES | B41: Véhicules neufs | C41: TOTAL VARIABLES | D41: % brut | E41: =F41/F$27 -> 0.42066749 | F41: =SUM(F31:F40) -> 121400.68 | J41: % brut | K41: =L41/L$27 -> 0.29627314 | L41: =SUM(L31:L40) -> 37787.53 | N41: =L41-F41 -> -83613.146 | O41: % brut | P41: =Q41/Q$27 -> 0.39462702 | Q41: =SUM(Q31:Q40) -> 122271.45 | S41: =L41-Q41 -> -84483.92
A42: Véhicules neufsSalaires cadres | B42: Véhicules neufs | C42: Salaires cadres | F42: =+INDEX('[7]Budget original'!$A$2:$AO$501,MATCH($A42,'[7]Budget original'!$A$2:$A$501,0),MATCH(F$2,'[7]Budget original'!$A$2:$AO$2,0)) -> 21133.479 | L42: =SUMIFS([7]BV_Data_An_Cour!$O:$O,[7]BV_Data_An_Cour!$U:$U,$B42,[7]BV_Data_An_Cour!$V:$V,$C42,[7]BV_Data_An_Cour!$W:$W,L$2) -> 24253.66 | N42: =L42-F42 -> 3120.1808 | P42: =Q42/Q27 -> 0.048101001 | Q42: {=+INDEX('[7]Réel 2023'!$A$2:$AO$501,MATCH($A42,'[7]Réel 2023'!$A$2:$A$501,0),MATCH(Q$2,'[7]Réel 2023'!$A$2:$AO$2,0))} -> 14903.64 | S42: =L42-Q42 -> 9350.02
A43: Véhicules neufsSalaires commis | B43: Véhicules neufs | C43: Salaires commis | F43: =+INDEX('[7]Budget original'!$A$2:$AO$501,MATCH($A43,'[7]Budget original'!$A$2:$A$501,0),MATCH(F$2,'[7]Budget original'!$A$2:$AO$2,0)) -> 13954.389 | L43: =SUMIFS([7]BV_Data_An_Cour!$O:$O,[7]BV_Data_An_Cour!$U:$U,$B43,[7]BV_Data_An_Cour!$V:$V,$C43,[7]BV_Data_An_Cour!$W:$W,L$2) -> 13792.56 | N43: =L43-F43 -> -161.82885 | Q43: {=+INDEX('[7]Réel 2023'!$A$2:$AO$501,MATCH($A43,'[7]Réel 2023'!$A$2:$A$501,0),MATCH(Q$2,'[7]Réel 2023'!$A$2:$AO$2,0))} -> 8776.47 | S43: =L43-Q43 -> 5016.09
A44: Véhicules neufsSalaires autres | B44: Véhicules neufs | C44: Salaires autres | F44: =+INDEX('[7]Budget original'!$A$2:$AO$501,MATCH($A44,'[7]Budget original'!$A$2:$A$501,0),MATCH(F$2,'[7]Budget original'!$A$2:$AO$2,0)) -> 3330.4423 | L44: =SUMIFS([7]BV_Data_An_Cour!$O:$O,[7]BV_Data_An_Cour!$U:$U,$B44,[7]BV_Data_An_Cour!$V:$V,$C44,[7]BV_Data_An_Cour!$W:$W,L$2) -> 4339.52 | N44: =L44-F44 -> 1009.0777 | Q44: {=+INDEX('[7]Réel 2023'!$A$2:$AO$501,MATCH($A44,'[7]Réel 2023'!$A$2:$A$501,0),MATCH(Q$2,'[7]Réel 2023'!$A$2:$AO$2,0))} -> 2988 | S44: =L44-Q44 -> 1351.52
A45: Véhicules neufsSalaires spécialistes | B45: Véhicules neufs | C45: Salaires spécialistes | F45: =+INDEX('[7]Budget original'!$A$2:$AO$501,MATCH($A45,'[7]Budget original'!$A$2:$A$501,0),MATCH(F$2,'[7]Budget original'!$A$2:$AO$2,0)) -> 0 | L45: =SUMIFS([7]BV_Data_An_Cour!$O:$O,[7]BV_Data_An_Cour!$U:$U,$B45,[7]BV_Data_An_Cour!$V:$V,$C45,[7]BV_Data_An_Cour!$W:$W,L$2) -> 0 | N45: =L45-F45 -> 0 | Q45: {=+INDEX('[7]Réel 2023'!$A$2:$AO$501,MATCH($A45,'[7]Réel 2023'!$A$2:$A$501,0),MATCH(Q$2,'[7]Réel 2023'!$A$2:$AO$2,0))} -> 0 | S45: =L45-Q45 -> 0
A46: Véhicules neufs[...] | B46: Véhicules neufs | C46: [...] | F46: =+INDEX('[7]Budget original'!$A$2:$AO$501,MATCH($A46,'[7]Budget original'!$A$2:$A$501,0),MATCH(F$2,'[7]Budget original'!$A$2:$AO$2,0)) -> 0 | L46: =SUMIFS([7]BV_Data_An_Cour!$O:$O,[7]BV_Data_An_Cour!$U:$U,$B46,[7]BV_Data_An_Cour!$V:$V,$C46,[7]BV_Data_An_Cour!$W:$W,L$2) -> 0 | N46: =L46-F46 -> 0 | Q46: {=+INDEX('[7]Réel 2023'!$A$2:$AO$501,MATCH($A46,'[7]Réel 2023'!$A$2:$A$501,0),MATCH(Q$2,'[7]Réel 2023'!$A$2:$AO$2,0))} -> 0 | S46: =L46-Q46 -> 0
A47: Véhicules neufs[...] | B47: Véhicules neufs | C47: [...] | F47: =+INDEX('[7]Budget original'!$A$2:$AO$501,MATCH($A47,'[7]Budget original'!$A$2:$A$501,0),MATCH(F$2,'[7]Budget original'!$A$2:$AO$2,0)) -> 0 | L47: =SUMIFS([7]BV_Data_An_Cour!$O:$O,[7]BV_Data_An_Cour!$U:$U,$B47,[7]BV_Data_An_Cour!$V:$V,$C47,[7]BV_Data_An_Cour!$W:$W,L$2) -> 0 | N47: =L47-F47 -> 0 | Q47: {=+INDEX('[7]Réel 2023'!$A$2:$AO$501,MATCH($A47,'[7]Réel 2023'!$A$2:$A$501,0),MATCH(Q$2,'[7]Réel 2023'!$A$2:$AO$2,0))} -> 0 | S47: =L47-Q47 -> 0
A48: Véhicules neufs[...] | B48: Véhicules neufs | C48: [...] | F48: =+INDEX('[7]Budget original'!$A$2:$AO$501,MATCH($A48,'[7]Budget original'!$A$2:$A$501,0),MATCH(F$2,'[7]Budget original'!$A$2:$AO$2,0)) -> 0 | L48: =SUMIFS([7]BV_Data_An_Cour!$O:$O,[7]BV_Data_An_Cour!$U:$U,$B48,[7]BV_Data_An_Cour!$V:$V,$C48,[7]BV_Data_An_Cour!$W:$W,L$2) -> 0 | N48: =L48-F48 -> 0 | Q48: {=+INDEX('[7]Réel 2023'!$A$2:$AO$501,MATCH($A48,'[7]Réel 2023'!$A$2:$A$501,0),MATCH(Q$2,'[7]Réel 2023'!$A$2:$AO$2,0))} -> 0 | S48: =L48-Q48 -> 0
A49: Véhicules neufsSalaires en absences | B49: Véhicules neufs | C49: Salaires en absences | F49: =+INDEX('[7]Budget original'!$A$2:$AO$501,MATCH($A49,'[7]Budget original'!$A$2:$A$501,0),MATCH(F$2,'[7]Budget original'!$A$2:$AO$2,0)) -> 13494.083 | L49: =SUMIFS([7]BV_Data_An_Cour!$O:$O,[7]BV_Data_An_Cour!$U:$U,$B49,[7]BV_Data_An_Cour!$V:$V,$C49,[7]BV_Data_An_Cour!$W:$W,L$2) -> 11233.56 | N49: =L49-F49 -> -2260.5232 | Q49: {=+INDEX('[7]Réel 2023'!$A$2:$AO$501,MATCH($A49,'[7]Réel 2023'!$A$2:$A$501,0),MATCH(Q$2,'[7]Réel 2023'!$A$2:$AO$2,0))} -> 8803.83 | S49: =L49-Q49 -> 2429.73
A50: Véhicules neufsDéduction à la source | B50: Véhicules neufs | C50: Déduction à la source | F50: =+INDEX('[7]Budget original'!$A$2:$AO$501,MATCH($A50,'[7]Budget original'!$A$2:$A$501,0),MATCH(F$2,'[7]Budget original'!$A$2:$AO$2,0)) -> 16406.903 | L50: =SUMIFS([7]BV_Data_An_Cour!$O:$O,[7]BV_Data_An_Cour!$U:$U,$B50,[7]BV_Data_An_Cour!$V:$V,$C50,[7]BV_Data_An_Cour!$W:$W,L$2) -> 12527.06 | N50: =L50-F50 -> -3879.8429 | Q50: {=+INDEX('[7]Réel 2023'!$A$2:$AO$501,MATCH($A50,'[7]Réel 2023'!$A$2:$A$501,0),MATCH(Q$2,'[7]Réel 2023'!$A$2:$AO$2,0))} -> 11365.4 | S50: =L50-Q50 -> 1161.66
A51: Véhicules neufsBénéfices marginaux | B51: Véhicules neufs | C51: Bénéfices marginaux | F51: =+INDEX('[7]Budget original'!$A$2:$AO$501,MATCH($A51,'[7]Budget original'!$A$2:$A$501,0),MATCH(F$2,'[7]Budget original'!$A$2:$AO$2,0)) -> 8453.1217 | L51: =SUMIFS([7]BV_Data_An_Cour!$O:$O,[7]BV_Data_An_Cour!$U:$U,$B51,[7]BV_Data_An_Cour!$V:$V,$C51,[7]BV_Data_An_Cour!$W:$W,L$2) -> 372.18 | N51: =L51-F51 -> -8080.9417 | Q51: {=+INDEX('[7]Réel 2023'!$A$2:$AO$501,MATCH($A51,'[7]Réel 2023'!$A$2:$A$501,0),MATCH(Q$2,'[7]Réel 2023'!$A$2:$AO$2,0))} -> 6383.81 | S51: =L51-Q51 -> -6011.63
A52: Véhicules neufsCsst | B52: Véhicules neufs | C52: Csst | F52: =+INDEX('[7]Budget original'!$A$2:$AO$501,MATCH($A52,'[7]Budget original'!$A$2:$A$501,0),MATCH(F$2,'[7]Budget original'!$A$2:$AO$2,0)) -> 3685.6086 | L52: =SUMIFS([7]BV_Data_An_Cour!$O:$O,[7]BV_Data_An_Cour!$U:$U,$B52,[7]BV_Data_An_Cour!$V:$V,$C52,[7]BV_Data_An_Cour!$W:$W,L$2) -> 1645.94 | N52: =L52-F52 -> -2039.6686 | Q52: {=+INDEX('[7]Réel 2023'!$A$2:$AO$501,MATCH($A52,'[7]Réel 2023'!$A$2:$A$501,0),MATCH(Q$2,'[7]Réel 2023'!$A$2:$AO$2,0))} -> 1164.96 | S52: =L52-Q52 -> 480.98
A53: Véhicules neufs[...] | B53: Véhicules neufs | C53: [...] | D53: =VLOOKUP(C53,$B$2:$B$46,1,FALSE) -> #N/A | F53: =+INDEX('[7]Budget original'!$A$2:$AO$501,MATCH($A53,'[7]Budget original'!$A$2:$A$501,0),MATCH(F$2,'[7]Budget original'!$A$2:$AO$2,0)) -> 0 | L53: =SUMIFS([7]BV_Data_An_Cour!$O:$O,[7]BV_Data_An_Cour!$U:$U,$B53,[7]BV_Data_An_Cour!$V:$V,$C53,[7]BV_Data_An_Cour!$W:$W,L$2) -> 0 | N53: =L53-F53 -> 0 | Q53: {=+INDEX('[7]Réel 2023'!$A$2:$AO$501,MATCH($A53,'[7]Réel 2023'!$A$2:$A$501,0),MATCH(Q$2,'[7]Réel 2023'!$A$2:$AO$2,0))} -> 0 | S53: =L53-Q53 -> 0
A54: Véhicules neufsTOTAL PERSONNEL | B54: Véhicules neufs | C54: TOTAL PERSONNEL | D54: % brut | E54: =F54/F$27 -> 0.27879644 | F54: =+SUM(F42:F53) -> 80458.027 | J54: % brut | K54: =L54/L$27 -> 0.53444363 | L54: =+SUM(L42:L53) -> 68164.48 | N54: =+SUM(N42:N53) -> -12293.547 | O54: % brut | P54: =Q54/Q$27 -> 0.17552935 | Q54: =+SUM(Q42:Q53) -> 54386.11 | S54: =+SUM(S42:S53) -> 13778.37
A55: Véhicules neufsPublicité 2 | B55: Véhicules neufs | C55: Publicité 2 | F55: =+INDEX('[7]Budget original'!$A$2:$AO$501,MATCH($A55,'[7]Budget original'!$A$2:$A$501,0),MATCH(F$2,'[7]Budget original'!$A$2:$AO$2,0)) -> 0 | L55: =SUMIFS([7]BV_Data_An_Cour!$O:$O,[7]BV_Data_An_Cour!$U:$U,$B55,[7]BV_Data_An_Cour!$V:$V,$C55,[7]BV_Data_An_Cour!$W:$W,L$2) -> 0 | N55: =L55-F55 -> 0 | Q55: {=+INDEX('[7]Réel 2023'!$A$2:$AO$501,MATCH($A55,'[7]Réel 2023'!$A$2:$A$501,0),MATCH(Q$2,'[7]Réel 2023'!$A$2:$AO$2,0))} -> 0 | S55: =L55-Q55 -> 0
A56: Véhicules neufsService gratuit 2 | B56: Véhicules neufs | C56: Service gratuit 2 | F56: =+INDEX('[7]Budget original'!$A$2:$AO$501,MATCH($A56,'[7]Budget original'!$A$2:$A$501,0),MATCH(F$2,'[7]Budget original'!$A$2:$AO$2,0)) -> 0 | L56: =SUMIFS([7]BV_Data_An_Cour!$O:$O,[7]BV_Data_An_Cour!$U:$U,$B56,[7]BV_Data_An_Cour!$V:$V,$C56,[7]BV_Data_An_Cour!$W:$W,L$2) -> 0 | N56: =L56-F56 -> 0 | Q56: {=+INDEX('[7]Réel 2023'!$A$2:$AO$501,MATCH($A56,'[7]Réel 2023'!$A$2:$A$501,0),MATCH(Q$2,'[7]Réel 2023'!$A$2:$AO$2,0))} -> 0 | S56: =L56-Q56 -> 0
A57: Véhicules neufsFrais véhicules de cie | B57: Véhicules neufs | C57: Frais véhicules de cie | F57: =+INDEX('[7]Budget original'!$A$2:$AO$501,MATCH($A57,'[7]Budget original'!$A$2:$A$501,0),MATCH(F$2,'[7]Budget original'!$A$2:$AO$2,0)) -> 9200 | L57: =SUMIFS([7]BV_Data_An_Cour!$O:$O,[7]BV_Data_An_Cour!$U:$U,$B57,[7]BV_Data_An_Cour!$V:$V,$C57,[7]BV_Data_An_Cour!$W:$W,L$2) -> 8283.33 | N57: =L57-F57 -> -916.67 | Q57: {=+INDEX('[7]Réel 2023'!$A$2:$AO$501,MATCH($A57,'[7]Réel 2023'!$A$2:$A$501,0),MATCH(Q$2,'[7]Réel 2023'!$A$2:$AO$2,0))} -> 7119.66 | S57: =L57-Q57 -> 1163.67
A58: Véhicules neufsInformatique | B58: Véhicules neufs | C58: Informatique | F58: =+INDEX('[7]Budget original'!$A$2:$AO$501,MATCH($A58,'[7]Budget original'!$A$2:$A$501,0),MATCH(F$2,'[7]Budget original'!$A$2:$AO$2,0)) -> 9039.6955 | L58: =SUMIFS([7]BV_Data_An_Cour!$O:$O,[7]BV_Data_An_Cour!$U:$U,$B58,[7]BV_Data_An_Cour!$V:$V,$C58,[7]BV_Data_An_Cour!$W:$W,L$2) -> 6688.36 | N58: =L58-F58 -> -2351.3355 | Q58: {=+INDEX('[7]Réel 2023'!$A$2:$AO$501,MATCH($A58,'[7]Réel 2023'!$A$2:$A$501,0),MATCH(Q$2,'[7]Réel 2023'!$A$2:$AO$2,0))} -> 6760.11 | S58: =L58-Q58 -> -71.75
A59: Véhicules neufsFrais de déplacement | B59: Véhicules neufs | C59: Frais de déplacement | F59: =+INDEX('[7]Budget original'!$A$2:$AO$501,MATCH($A59,'[7]Budget original'!$A$2:$A$501,0),MATCH(F$2,'[7]Budget original'!$A$2:$AO$2,0)) -> 1105.2259 | L59: =SUMIFS([7]BV_Data_An_Cour!$O:$O,[7]BV_Data_An_Cour!$U:$U,$B59,[7]BV_Data_An_Cour!$V:$V,$C59,[7]BV_Data_An_Cour!$W:$W,L$2) -> 2373.63 | N59: =L59-F59 -> 1268.4041 | Q59: {=+INDEX('[7]Réel 2023'!$A$2:$AO$501,MATCH($A59,'[7]Réel 2023'!$A$2:$A$501,0),MATCH(Q$2,'[7]Réel 2023'!$A$2:$AO$2,0))} -> 1646.26 | S59: =L59-Q59 -> 727.37
A60: Véhicules neufsServices extérieurs | B60: Véhicules neufs | C60: Services extérieurs | F60: =+INDEX('[7]Budget original'!$A$2:$AO$501,MATCH($A60,'[7]Budget original'!$A$2:$A$501,0),MATCH(F$2,'[7]Budget original'!$A$2:$AO$2,0)) -> 6711.4186 | L60: =SUMIFS([7]BV_Data_An_Cour!$O:$O,[7]BV_Data_An_Cour!$U:$U,$B60,[7]BV_Data_An_Cour!$V:$V,$C60,[7]BV_Data_An_Cour!$W:$W,L$2) -> 7674.68 | N60: =L60-F60 -> 963.26136 | Q60: {=+INDEX('[7]Réel 2023'!$A$2:$AO$501,MATCH($A60,'[7]Réel 2023'!$A$2:$A$501,0),MATCH(Q$2,'[7]Réel 2023'!$A$2:$AO$2,0))} -> 8387.93 | S60: =L60-Q60 -> -713.25
A61: Véhicules neufsFournitures autres | B61: Véhicules neufs | C61: Fournitures autres | F61: =+INDEX('[7]Budget original'!$A$2:$AO$501,MATCH($A61,'[7]Budget original'!$A$2:$A$501,0),MATCH(F$2,'[7]Budget original'!$A$2:$AO$2,0)) -> 125 | L61: =SUMIFS([7]BV_Data_An_Cour!$O:$O,[7]BV_Data_An_Cour!$U:$U,$B61,[7]BV_Data_An_Cour!$V:$V,$C61,[7]BV_Data_An_Cour!$W:$W,L$2) -> 0 | N61: =L61-F61 -> -125 | Q61: {=+INDEX('[7]Réel 2023'!$A$2:$AO$501,MATCH($A61,'[7]Réel 2023'!$A$2:$A$501,0),MATCH(Q$2,'[7]Réel 2023'!$A$2:$AO$2,0))} -> 250.25 | S61: =L61-Q61 -> -250.25
A62: Véhicules neufsUniformes | B62: Véhicules neufs | C62: Uniformes | F62: =+INDEX('[7]Budget original'!$A$2:$AO$501,MATCH($A62,'[7]Budget original'!$A$2:$A$501,0),MATCH(F$2,'[7]Budget original'!$A$2:$AO$2,0)) -> 83.333333 | L62: =SUMIFS([7]BV_Data_An_Cour!$O:$O,[7]BV_Data_An_Cour!$U:$U,$B62,[7]BV_Data_An_Cour!$V:$V,$C62,[7]BV_Data_An_Cour!$W:$W,L$2) -> 0 | N62: =L62-F62 -> -83.333333 | Q62: {=+INDEX('[7]Réel 2023'!$A$2:$AO$501,MATCH($A62,'[7]Réel 2023'!$A$2:$A$501,0),MATCH(Q$2,'[7]Réel 2023'!$A$2:$AO$2,0))} -> 0 | S62: =L62-Q62 -> 0
A63: Véhicules neufsPapeterie | B63: Véhicules neufs | C63: Papeterie | F63: =+INDEX('[7]Budget original'!$A$2:$AO$501,MATCH($A63,'[7]Budget original'!$A$2:$A$501,0),MATCH(F$2,'[7]Budget original'!$A$2:$AO$2,0)) -> 756.9466 | L63: =SUMIFS([7]BV_Data_An_Cour!$O:$O,[7]BV_Data_An_Cour!$U:$U,$B63,[7]BV_Data_An_Cour!$V:$V,$C63,[7]BV_Data_An_Cour!$W:$W,L$2) -> 1262.34 | N63: =L63-F63 -> 505.3934 | Q63: {=+INDEX('[7]Réel 2023'!$A$2:$AO$501,MATCH($A63,'[7]Réel 2023'!$A$2:$A$501,0),MATCH(Q$2,'[7]Réel 2023'!$A$2:$AO$2,0))} -> 2065.76 | S63: =L63-Q63 -> -803.42
A64: Véhicules neufsTéléphone | B64: Véhicules neufs | C64: Téléphone | F64: =+INDEX('[7]Budget original'!$A$2:$AO$501,MATCH($A64,'[7]Budget original'!$A$2:$A$501,0),MATCH(F$2,'[7]Budget original'!$A$2:$AO$2,0)) -> 309.40349 | L64: =SUMIFS([7]BV_Data_An_Cour!$O:$O,[7]BV_Data_An_Cour!$U:$U,$B64,[7]BV_Data_An_Cour!$V:$V,$C64,[7]BV_Data_An_Cour!$W:$W,L$2) -> 351.63 | N64: =L64-F64 -> 42.226515 | Q64: {=+INDEX('[7]Réel 2023'!$A$2:$AO$501,MATCH($A64,'[7]Réel 2023'!$A$2:$A$501,0),MATCH(Q$2,'[7]Réel 2023'!$A$2:$AO$2,0))} -> 280.55 | S64: =L64-Q64 -> 71.08
A65: Véhicules neufsFrais postaux | B65: Véhicules neufs | C65: Frais postaux | F65: =+INDEX('[7]Budget original'!$A$2:$AO$501,MATCH($A65,'[7]Budget original'!$A$2:$A$501,0),MATCH(F$2,'[7]Budget original'!$A$2:$AO$2,0)) -> 113.12881 | L65: =SUMIFS([7]BV_Data_An_Cour!$O:$O,[7]BV_Data_An_Cour!$U:$U,$B65,[7]BV_Data_An_Cour!$V:$V,$C65,[7]BV_Data_An_Cour!$W:$W,L$2) -> 40.25 | N65: =L65-F65 -> -72.87881 | Q65: {=+INDEX('[7]Réel 2023'!$A$2:$AO$501,MATCH($A65,'[7]Réel 2023'!$A$2:$A$501,0),MATCH(Q$2,'[7]Réel 2023'!$A$2:$AO$2,0))} -> 169.87 | S65: =L65-Q65 -> -129.62
A66: Véhicules neufsDivers | B66: Véhicules neufs | C66: Divers | F66: =+INDEX('[7]Budget original'!$A$2:$AO$501,MATCH($A66,'[7]Budget original'!$A$2:$A$501,0),MATCH(F$2,'[7]Budget original'!$A$2:$AO$2,0)) -> 282.4626 | L66: =SUMIFS([7]BV_Data_An_Cour!$O:$O,[7]BV_Data_An_Cour!$U:$U,$B66,[7]BV_Data_An_Cour!$V:$V,$C66,[7]BV_Data_An_Cour!$W:$W,L$2) -> 446.81 | N66: =L66-F66 -> 164.3474 | Q66: {=+INDEX('[7]Réel 2023'!$A$2:$AO$501,MATCH($A66,'[7]Réel 2023'!$A$2:$A$501,0),MATCH(Q$2,'[7]Réel 2023'!$A$2:$AO$2,0))} -> 102.8 | S66: =L66-Q66 -> 344.01
... A68: Véhicules neufsFrais bancaires | B68: Véhicules neufs | C68: Frais bancaires | F68: =+INDEX('[7]Budget original'!$A$2:$AO$501,MATCH($A68,'[7]Budget original'!$A$2:$A$501,0),MATCH(F$2,'[7]Budget original'!$A$2:$AO$2,0)) -> 3363.2959 | L68: =SUMIFS([7]BV_Data_An_Cour!$O:$O,[7]BV_Data_An_Cour!$U:$U,$B68,[7]BV_Data_An_Cour!$V:$V,$C68,[7]BV_Data_An_Cour!$W:$W,L$2) -> 6767.49 | N68: =L68-F68 -> 3404.1941 | Q68: {=+INDEX('[7]Réel 2023'!$A$2:$AO$501,MATCH($A68,'[7]Réel 2023'!$A$2:$A$501,0),MATCH(Q$2,'[7]Réel 2023'!$A$2:$AO$2,0))} -> 5124.82 | S68: =L68-Q68 -> 1642.67
A69: Véhicules neufs[...] | B69: Véhicules neufs | C69: [...] | F69: =+INDEX('[7]Budget original'!$A$2:$AO$501,MATCH($A69,'[7]Budget original'!$A$2:$A$501,0),MATCH(F$2,'[7]Budget original'!$A$2:$AO$2,0)) -> 0 | N69: =L69-F69 -> 0 | Q69: {=+INDEX('[7]Réel 2023'!$A$2:$AO$501,MATCH($A69,'[7]Réel 2023'!$A$2:$A$501,0),MATCH(Q$2,'[7]Réel 2023'!$A$2:$AO$2,0))} -> 0 | S69: =L69-Q69 -> 0
A70: Véhicules neufs[...] | B70: Véhicules neufs | C70: [...] | F70: =+INDEX('[7]Budget original'!$A$2:$AO$501,MATCH($A70,'[7]Budget original'!$A$2:$A$501,0),MATCH(F$2,'[7]Budget original'!$A$2:$AO$2,0)) -> 0 | L70: =SUMIFS([7]BV_Data_An_Cour!$O:$O,[7]BV_Data_An_Cour!$U:$U,$B70,[7]BV_Data_An_Cour!$V:$V,$C70,[7]BV_Data_An_Cour!$W:$W,L$2) -> 0 | N70: =L70-F70 -> 0 | Q70: {=+INDEX('[7]Réel 2023'!$A$2:$AO$501,MATCH($A70,'[7]Réel 2023'!$A$2:$A$501,0),MATCH(Q$2,'[7]Réel 2023'!$A$2:$AO$2,0))} -> 0 | S70: =L70-Q70 -> 0
A71: Véhicules neufs[...] | B71: Véhicules neufs | C71: [...] | F71: =+INDEX('[7]Budget original'!$A$2:$AO$501,MATCH($A71,'[7]Budget original'!$A$2:$A$501,0),MATCH(F$2,'[7]Budget original'!$A$2:$AO$2,0)) -> 0 | L71: =SUMIFS([7]BV_Data_An_Cour!$O:$O,[7]BV_Data_An_Cour!$U:$U,$B71,[7]BV_Data_An_Cour!$V:$V,$C71,[7]BV_Data_An_Cour!$W:$W,L$2)*0.32 -> 0 | N71: =L71-F71 -> 0 | Q71: {=+INDEX('[7]Réel 2023'!$A$2:$AO$501,MATCH($A71,'[7]Réel 2023'!$A$2:$A$501,0),MATCH(Q$2,'[7]Réel 2023'!$A$2:$AO$2,0))} -> 0 | S71: =L71-Q71 -> 0
A72: Véhicules neufsTOTAL SEMI-FIXES | B72: Véhicules neufs | C72: TOTAL SEMI-FIXES | D72: % brut | E72: =F72/F$27 -> 0.11431079 | F72: =+SUM(F55:F71) -> 32989.018 | J72: % brut | K72: =L72/L$27 -> 0.27970178 | L72: =+SUM(L55:L71) -> 35673.97 | N72: =+SUM(N55:N71) -> 2684.9517 | O72: % brut | P72: =Q72/Q$27 -> 0.11005193 | Q72: =+SUM(Q55:Q71) -> 34098.55 | S72: =+SUM(S55:S71) -> 1575.42
A73: Véhicules neufs | B73: Véhicules neufs
A74: Véhicules neufsTOTAL DES DÉPENSES | B74: Véhicules neufs | C74: TOTAL DES DÉPENSES | D74: % brut | E74: =F74/F$27 -> 0.81377472 | F74: =F41+F54+F72 -> 234847.72 | J74: % brut | K74: =L74/L$27 -> 1.1104186 | L74: =L41+L54+L72 -> 141625.98 | N74: =L74-F74 -> -93221.741 | O74: % brut | P74: =Q74/Q$27 -> 0.68020831 | Q74: =Q41+Q54+Q72 -> 210756.11 | S74: =L74-Q74 -> -69130.13
A75: Véhicules neufsProgramme neuf 1 | B75: Véhicules neufs | C75: Programme neuf 1 | F75: =+INDEX('[7]Budget original'!$A$2:$AO$501,MATCH($A75,'[7]Budget original'!$A$2:$A$501,0),MATCH(F$2,'[7]Budget original'!$A$2:$AO$2,0)) -> 0 | L75: =-SUMIFS([7]BV_Data_An_Cour!$O:$O,[7]BV_Data_An_Cour!$U:$U,$B75,[7]BV_Data_An_Cour!$V:$V,$C75,[7]BV_Data_An_Cour!$W:$W,L$2)-L156 -> 12500 | N75: =L75-F75 -> 12500 | Q75: =+INDEX('[7]Réel 2023'!$A$2:$AO$501,MATCH($A75,'[7]Réel 2023'!$A$2:$A$501,0),MATCH(Q$2,'[7]Réel 2023'!$A$2:$AO$2,0)) -> 0
A76: Véhicules neufsProgramme neuf 2 | B76: Véhicules neufs | C76: Programme neuf 2 | F76: =+INDEX('[7]Budget original'!$A$2:$AO$501,MATCH($A76,'[7]Budget original'!$A$2:$A$501,0),MATCH(F$2,'[7]Budget original'!$A$2:$AO$2,0)) -> 0 | L76: =-SUMIFS([7]BV_Data_An_Cour!$O:$O,[7]BV_Data_An_Cour!$U:$U,$B76,[7]BV_Data_An_Cour!$V:$V,$C76,[7]BV_Data_An_Cour!$W:$W,L$2) -> 0 | N76: =L76-F76 -> 0 | Q76: {=+INDEX('[7]Réel 2023'!$A$2:$AO$501,MATCH($A76,'[7]Réel 2023'!$A$2:$A$501,0),MATCH(Q$2,'[7]Réel 2023'!$A$2:$AO$2,0))} -> 0 | S76: =L76-Q76 -> 0
A77: Véhicules neufsProgramme neuf 3 | B77: Véhicules neufs | C77: Programme neuf 3 | F77: =+INDEX('[7]Budget original'!$A$2:$AO$501,MATCH($A77,'[7]Budget original'!$A$2:$A$501,0),MATCH(F$2,'[7]Budget original'!$A$2:$AO$2,0)) -> 0 | L77: =-SUMIFS([7]BV_Data_An_Cour!$O:$O,[7]BV_Data_An_Cour!$U:$U,$B77,[7]BV_Data_An_Cour!$V:$V,$C77,[7]BV_Data_An_Cour!$W:$W,L$2) -> 0 | N77: =L77-F77 -> 0 | Q77: {=+INDEX('[7]Réel 2023'!$A$2:$AO$501,MATCH($A77,'[7]Réel 2023'!$A$2:$A$501,0),MATCH(Q$2,'[7]Réel 2023'!$A$2:$AO$2,0))} -> 0 | S77: =L77-Q77 -> 0
A78: Véhicules neufsHoldbacks | B78: Véhicules neufs | C78: Holdbacks | E78: =+F78/D27 -> 1304.3817 | F78: =+INDEX('[7]Budget original'!$A$2:$AO$501,MATCH($A78,'[7]Budget original'!$A$2:$A$501,0),MATCH(F$2,'[7]Budget original'!$A$2:$AO$2,0)) -> 92950.237 | K78: =+L78/J27 -> 1378 | L78: =-SUMIFS([7]BV_Data_An_Cour!$O:$O,[7]BV_Data_An_Cour!$U:$U,$B78,[7]BV_Data_An_Cour!$V:$V,$C78,[7]BV_Data_An_Cour!$W:$W,L$2) -> 55120 | N78: =L78-F78 -> -37830.237 | Q78: {=+INDEX('[7]Réel 2023'!$A$2:$AO$501,MATCH($A78,'[7]Réel 2023'!$A$2:$A$501,0),MATCH(Q$2,'[7]Réel 2023'!$A$2:$AO$2,0))} -> 100428 | S78: =L78-Q78 -> -45308
A79: Véhicules neufs[...] | B79: Véhicules neufs | C79: [...] | F79: =+INDEX('[7]Budget original'!$A$2:$AO$501,MATCH($A79,'[7]Budget original'!$A$2:$A$501,0),MATCH(F$2,'[7]Budget original'!$A$2:$AO$2,0)) -> 0 | L79: =-SUMIFS([7]BV_Data_An_Cour!$O:$O,[7]BV_Data_An_Cour!$U:$U,$B79,[7]BV_Data_An_Cour!$V:$V,$C79,[7]BV_Data_An_Cour!$W:$W,L$2) -> 0 | N79: =L79-F79 -> 0 | Q79: {=+INDEX('[7]Réel 2023'!$A$2:$AO$501,MATCH($A79,'[7]Réel 2023'!$A$2:$A$501,0),MATCH(Q$2,'[7]Réel 2023'!$A$2:$AO$2,0))} -> 0 | S79: =L79-Q79 -> 0
A80: Véhicules neufs[...] | B80: Véhicules neufs | C80: [...] | F80: =+INDEX('[7]Budget original'!$A$2:$AO$501,MATCH($A80,'[7]Budget original'!$A$2:$A$501,0),MATCH(F$2,'[7]Budget original'!$A$2:$AO$2,0)) -> 0 | L80: =-SUMIFS([7]BV_Data_An_Cour!$O:$O,[7]BV_Data_An_Cour!$U:$U,$B80,[7]BV_Data_An_Cour!$V:$V,$C80,[7]BV_Data_An_Cour!$W:$W,L$2) -> 0 | N80: =L80-F80 -> 0 | Q80: {=+INDEX('[7]Réel 2023'!$A$2:$AO$501,MATCH($A80,'[7]Réel 2023'!$A$2:$A$501,0),MATCH(Q$2,'[7]Réel 2023'!$A$2:$AO$2,0))} -> 0 | S80: =L80-Q80 -> 0
A81: Véhicules neufs[...] | B81: Véhicules neufs | C81: [...] | F81: =+INDEX('[7]Budget original'!$A$2:$AO$501,MATCH($A81,'[7]Budget original'!$A$2:$A$501,0),MATCH(F$2,'[7]Budget original'!$A$2:$AO$2,0)) -> 0 | L81: =-SUMIFS([7]BV_Data_An_Cour!$O:$O,[7]BV_Data_An_Cour!$U:$U,$B81,[7]BV_Data_An_Cour!$V:$V,$C81,[7]BV_Data_An_Cour!$W:$W,L$2) -> 0 | N81: =L81-F81 -> 0 | Q81: {=+INDEX('[7]Réel 2023'!$A$2:$AO$501,MATCH($A81,'[7]Réel 2023'!$A$2:$A$501,0),MATCH(Q$2,'[7]Réel 2023'!$A$2:$AO$2,0))} -> 0 | S81: =L81-Q81 -> 0
A82: Véhicules neufsFrais administration | B82: Véhicules neufs | C82: Frais administration | D82: =E82/499 -> 0.95 | E82: =+F82/D24 -> 474.05 | F82: =+INDEX('[7]Budget original'!$A$2:$AO$501,MATCH($A82,'[7]Budget original'!$A$2:$A$501,0),MATCH(F$2,'[7]Budget original'!$A$2:$AO$2,0)) -> 31647.578 | J82: =K82/474 -> 0.9568936 | K82: =+L82/J24 -> 453.56757 | L82: =-SUMIFS([7]BV_Data_An_Cour!$O:$O,[7]BV_Data_An_Cour!$U:$U,$B82,[7]BV_Data_An_Cour!$V:$V,$C82,[7]BV_Data_An_Cour!$W:$W,L$2) -> 16782 | N82: =L82-F82 -> -14865.578 | Q82: {=+INDEX('[7]Réel 2023'!$A$2:$AO$501,MATCH($A82,'[7]Réel 2023'!$A$2:$A$501,0),MATCH(Q$2,'[7]Réel 2023'!$A$2:$AO$2,0))} -> 41872.9 | S82: =L82-Q82 -> -25090.9
A83: Véhicules neufsAUTRES REVENUS | B83: Véhicules neufs | C83: AUTRES REVENUS | F83: =+SUM(F75:F82) -> 124597.82 | L83: =+SUM(L75:L82) -> 84402 | N83: =+SUM(N75:N82) -> -40195.815 | Q83: =+SUM(Q75:Q82) -> 142300.9 | S83: =+SUM(S75:S82) -> -70398.9
A84: Véhicules neufs | B84: Véhicules neufs
A85: Véhicules neufsPROFIT DÉPARTEMENTAL | B85: Véhicules neufs | C85: PROFIT DÉPARTEMENTAL | F85: =F27-F74+F83 -> 178340.68 | L85: =L27-L74+L83 -> 70318.9 | N85: =N27-N41-N54-N72+N83 -> -108021.78 | P85: =Q85/Q5 -> 0.023778493 | Q85: =Q27-Q74+Q83 -> 241385.33 | S85: =S27-S41-S54-S72+S83 -> -183566.43
C89: =C1 -> Volks | K89: Véhicules usagés | S89: =$S$1 -> Réalisé, Novembre 2024
D91: BUDGET ORIGINAL | J91: RÉALISATION | M91: ÉCART réel / Budget | O91: ANNÉE PRÉCÉDENTE | R91: ECART (réel/ Ann.Préc.)
D92: UNITE | E92: $P/UNITÉ | F92: $PROFITS | J92: UNITÉS | K92: $P/UNITE | L92: $PROFITS | M92: UNITÉS | N92: $PROFITS | O92: UNITE | P92: $P/UNITÉ | Q92: $PROFITS | R92: UNITÉS | S92: $PROFITS
A93: Véhicules usagésVentes nettes | B93: Véhicules usagés | C93: Ventes nettes | F93: =+INDEX('[7]Budget original'!$A$2:$AO$501,MATCH($A93,'[7]Budget original'!$A$2:$A$501,0),MATCH(F$2,'[7]Budget original'!$A$2:$AO$2,0)) -> 1824270.1 | L93: =-SUMIFS([7]BV_Data_An_Cour!$O:$O,[7]BV_Data_An_Cour!$X:$X,"Oui",[7]BV_Data_An_Cour!$U:$U,$B93) -> 1025214 | Q93: {=+INDEX('[7]Réel 2023'!$A$2:$AO$501,MATCH($A93,'[7]Réel 2023'!$A$2:$A$501,0),MATCH(Q$2,'[7]Réel 2023'!$A$2:$AO$2,0))} -> 1111062.8
A94: Véhicules usagésCertifié | B94: Véhicules usagés | C94: Certifié | D94: =+INDEX('[7]Budget original'!$A$2:$AO$501,MATCH($A94,'[7]Budget original'!$A$2:$A$501,0),MATCH(D$2,'[7]Budget original'!$A$2:$AO$2,0)) -> 33.657 | E94: =IF(D94=0,0,F94/D94) -> 1800 | F94: =+INDEX('[7]Budget original'!$A$2:$AO$501,MATCH($A94,'[7]Budget original'!$A$2:$A$501,0),MATCH(F$2,'[7]Budget original'!$A$2:$AO$2,0)) -> 60582.6 | J94: =-SUMIFS([7]BV_Data_An_Cour!$O:$O,[7]BV_Data_An_Cour!$U:$U,$B94,[7]BV_Data_An_Cour!$V:$V,$C94,[7]BV_Data_An_Cour!$W:$W,J$2) -> 30 | K94: =IF(J94=0,0,L94/J94) -> 1597.681 | L94: =-SUMIFS([7]BV_Data_An_Cour!$O:$O,[7]BV_Data_An_Cour!$U:$U,$B94,[7]BV_Data_An_Cour!$V:$V,$C94,[7]BV_Data_An_Cour!$W:$W,$L2) -> 47930.43 | M94: =J94-D94 -> -3.657 | N94: =L94-F94 -> -12652.17 | O94: {=+INDEX('[7]Réel 2023'!$A$2:$AO$501,MATCH($A94,'[7]Réel 2023'!$A$2:$A$501,0),MATCH(O$2,'[7]Réel 2023'!$A$2:$AO$2,0))} -> 16 | P94: =IF(O94=0,0,Q94/O94) -> 1359.5375 | Q94: {=+INDEX('[7]Réel 2023'!$A$2:$AO$501,MATCH($A94,'[7]Réel 2023'!$A$2:$A$501,0),MATCH(Q$2,'[7]Réel 2023'!$A$2:$AO$2,0))} -> 21752.6 | R94: =J94-O94 -> 14 | S94: =L94-Q94 -> 26177.83
A95: Véhicules usagésNon Certifié | B95: Véhicules usagés | C95: Non Certifié | D95: =+INDEX('[7]Budget original'!$A$2:$AO$501,MATCH($A95,'[7]Budget original'!$A$2:$A$501,0),MATCH(D$2,'[7]Budget original'!$A$2:$AO$2,0)) -> 1.8986 | E95: =IF(D95=0,0,F95/D95) -> 1800 | F95: =+INDEX('[7]Budget original'!$A$2:$AO$501,MATCH($A95,'[7]Budget original'!$A$2:$A$501,0),MATCH(F$2,'[7]Budget original'!$A$2:$AO$2,0)) -> 3417.48 | J95: =-SUMIFS([7]BV_Data_An_Cour!$O:$O,[7]BV_Data_An_Cour!$U:$U,$B95,[7]BV_Data_An_Cour!$V:$V,$C95,[7]BV_Data_An_Cour!$W:$W,J$2) -> 2 | K95: =IF(J95=0,0,L95/J95) -> -1112.96 | L95: =-SUMIFS([7]BV_Data_An_Cour!$O:$O,[7]BV_Data_An_Cour!$U:$U,$B95,[7]BV_Data_An_Cour!$V:$V,$C95,[7]BV_Data_An_Cour!$W:$W,$L2) -> -2225.92 | M95: =J95-D95 -> 0.1014 | N95: =L95-F95 -> -5643.4 | O95: {=+INDEX('[7]Réel 2023'!$A$2:$AO$501,MATCH($A95,'[7]Réel 2023'!$A$2:$A$501,0),MATCH(O$2,'[7]Réel 2023'!$A$2:$AO$2,0))} -> 4 | P95: =IF(O95=0,0,Q95/O95) -> 817.0175 | Q95: {=+INDEX('[7]Réel 2023'!$A$2:$AO$501,MATCH($A95,'[7]Réel 2023'!$A$2:$A$501,0),MATCH(Q$2,'[7]Réel 2023'!$A$2:$AO$2,0))} -> 3268.07 | R95: =J95-O95 -> -2 | S95: =L95-Q95 -> -5493.99
A96: =B96&C96 -> Véhicules usagésAutres Marques | B96: Véhicules usagés | C96: Autres Marques | D96: =+INDEX('[7]Budget original'!$A$2:$AO$501,MATCH($A96,'[7]Budget original'!$A$2:$A$501,0),MATCH(D$2,'[7]Budget original'!$A$2:$AO$2,0)) -> 1.1219 | E96: =IF(D96=0,0,F96/D96) -> 1800 | F96: =+INDEX('[7]Budget original'!$A$2:$AO$501,MATCH($A96,'[7]Budget original'!$A$2:$A$501,0),MATCH(F$2,'[7]Budget original'!$A$2:$AO$2,0)) -> 2019.42 | J96: =-SUMIFS([7]BV_Data_An_Cour!$O:$O,[7]BV_Data_An_Cour!$U:$U,$B96,[7]BV_Data_An_Cour!$V:$V,$C96,[7]BV_Data_An_Cour!$W:$W,J$2) -> 3 | K96: =IF(J96=0,0,L96/J96) -> 2132.8667 | L96: =-SUMIFS([7]BV_Data_An_Cour!$O:$O,[7]BV_Data_An_Cour!$U:$U,$B96,[7]BV_Data_An_Cour!$V:$V,$C96,[7]BV_Data_An_Cour!$W:$W,$L2) -> 6398.6 | M96: =J96-D96 -> 1.8781 | N96: =L96-F96 -> 4379.18 | O96: =+INDEX('[7]Réel 2023'!$A$2:$AO$501,MATCH($A96,'[7]Réel 2023'!$A$2:$A$501,0),MATCH(O$2,'[7]Réel 2023'!$A$2:$AO$2,0)) -> 0 | P96: =IF(O96=0,0,Q96/O96) -> 0 | Q96: =+INDEX('[7]Réel 2023'!$A$2:$AO$501,MATCH($A96,'[7]Réel 2023'!$A$2:$A$501,0),MATCH(Q$2,'[7]Réel 2023'!$A$2:$AO$2,0)) -> 0 | R96: =J96-O96 -> 3 | S96: =L96-Q96 -> 6398.6
A97: =B97&C97 -> Véhicules usagésTotal Usagés | B97: Véhicules usagés | C97: Total Usagés | D97: =+D95+D94+D96 -> 36.6775 | E97: =IF(D97=0,0,F97/D97) -> 1800 | F97: =+F94+F95+F96 -> 66019.5 | J97: =+J94+J95+J96 -> 35 | K97: =IF(J97<=0,0,L97/J97) -> 1488.6603 | L97: =+L94+L95+L96 -> 52103.11 | M97: =J97-D97 -> -1.6775 | N97: =L97-F97 -> -13916.39 | O97: =+O95+O94+O96 -> 20 | P97: =IF(O97=0,0,Q97/O97) -> 1251.0335 | Q97: =+Q94+Q95+Q96 -> 25020.67 | R97: =R94+R95 -> 12 | S97: =S94+S95 -> 20683.84
A98: =B98&C98 -> Véhicules usagés | B98: Véhicules usagés | E98: =IF(D98=0,0,F98/D98) -> 0 | M98: =M97/D97 -> -0.045736487 | N98: =N97/F97 -> -0.21079211 | P98: =IF(O98=0,0,Q98/O98) -> 0 | R98: =R97/O97 -> 0.6 | S98: =IF(Q97=0,0,(S97/Q97)) -> 0.82667011
A99: =B99&C99 -> Véhicules usagés | B99: Véhicules usagés | D99: =+INDEX('[7]Budget original'!$A$2:$AO$501,MATCH($A99,'[7]Budget original'!$A$2:$A$501,0),MATCH(D$2,'[7]Budget original'!$A$2:$AO$2,0)) -> 0 | E99: =IF(D99=0,0,F99/D99) -> 0 | F99: =+INDEX('[7]Budget original'!$A$2:$AO$501,MATCH($A99,'[7]Budget original'!$A$2:$A$501,0),MATCH(F$2,'[7]Budget original'!$A$2:$AO$2,0)) -> 0
A100: Véhicules usagésVentes au Gros | B100: Véhicules usagés | C100: Ventes au Gros | D100: =+INDEX('[7]Budget original'!$A$2:$AO$501,MATCH($A100,'[7]Budget original'!$A$2:$A$501,0),MATCH(D$2,'[7]Budget original'!$A$2:$AO$2,0)) -> 37.5405 | E100: =IF(D100=0,0,F100/D100) -> 400 | F100: =+INDEX('[7]Budget original'!$A$2:$AO$501,MATCH($A100,'[7]Budget original'!$A$2:$A$501,0),MATCH(F$2,'[7]Budget original'!$A$2:$AO$2,0)) -> 15016.2 | J100: =-SUMIFS([7]BV_Data_An_Cour!$O:$O,[7]BV_Data_An_Cour!$U:$U,$B100,[7]BV_Data_An_Cour!$V:$V,$C100,[7]BV_Data_An_Cour!$W:$W,J$2) -> 19 | K100: =IF(J100=0,0,L100/J100) -> 279.54947 | L100: =-SUMIFS([7]BV_Data_An_Cour!$O:$O,[7]BV_Data_An_Cour!$U:$U,$B100,[7]BV_Data_An_Cour!$V:$V,$C100,[7]BV_Data_An_Cour!$W:$W,L$2) -> 5311.44 | M100: =J100-D100 -> -18.5405 | N100: =L100-F100 -> -9704.76 | O100: {=+INDEX('[7]Réel 2023'!$A$2:$AO$501,MATCH($A100,'[7]Réel 2023'!$A$2:$A$501,0),MATCH(O$2,'[7]Réel 2023'!$A$2:$AO$2,0))} -> 31 | P100: =IF(O100=0,0,Q100/O100) -> 15.867742 | Q100: {=+INDEX('[7]Réel 2023'!$A$2:$AO$501,MATCH($A100,'[7]Réel 2023'!$A$2:$A$501,0),MATCH(Q$2,'[7]Réel 2023'!$A$2:$AO$2,0))} -> 491.9 | R100: =J100-O100 -> -12 | S100: =L100-Q100 -> 4819.54
A101: Véhicules usagés | B101: Véhicules usagés
A102: Véhicules usagésRev. Finances | B102: Véhicules usagés | C102: Rev. Finances | D102: =+INDEX('[7]Budget original'!$A$2:$AO$501,MATCH($A102,'[7]Budget original'!$A$2:$A$501,0),MATCH(D$2,'[7]Budget original'!$A$2:$AO$2,0)) -> 0 | E102: =IF(D102=0,0,F102/D102) -> 0 | F102: =+INDEX('[7]Budget original'!$A$2:$AO$501,MATCH($A102,'[7]Budget original'!$A$2:$A$501,0),MATCH(F$2,'[7]Budget original'!$A$2:$AO$2,0)) -> 25674.25 | K102: =IF(J97=0,0,L102/J97) -> 283.59714 | L102: =-SUMIFS([7]BV_Data_An_Cour!$O:$O,[7]BV_Data_An_Cour!$U:$U,$B102,[7]BV_Data_An_Cour!$V:$V,$C102,[7]BV_Data_An_Cour!$W:$W,$L2) -> 9925.9 | N102: =L102-F102 -> -15748.35 | Q102: {=+INDEX('[7]Réel 2023'!$A$2:$AO$501,MATCH($A102,'[7]Réel 2023'!$A$2:$A$501,0),MATCH(Q$2,'[7]Réel 2023'!$A$2:$AO$2,0))} -> 7409.82 | R102: =O102-K102 -> -283.59714 | S102: =L102-Q102 -> 2516.08
A103: Véhicules usagésRev. Protections | B103: Véhicules usagés | C103: Rev. Protections | D103: =+INDEX('[7]Budget original'!$A$2:$AO$501,MATCH($A103,'[7]Budget original'!$A$2:$A$501,0),MATCH(D$2,'[7]Budget original'!$A$2:$AO$2,0)) -> 0 | E103: =IF(D103=0,0,F103/D103) -> 0 | F103: =+INDEX('[7]Budget original'!$A$2:$AO$501,MATCH($A103,'[7]Budget original'!$A$2:$A$501,0),MATCH(F$2,'[7]Budget original'!$A$2:$AO$2,0)) -> 53182.375 | K103: =IF(J97=0,0,L103/J97) -> 1232.4863 | L103: =-SUMIFS([7]BV_Data_An_Cour!$O:$O,[7]BV_Data_An_Cour!$U:$U,$B103,[7]BV_Data_An_Cour!$V:$V,$C103,[7]BV_Data_An_Cour!$W:$W,$L2) -> 43137.02 | N103: =L103-F103 -> -10045.355 | Q103: {=+INDEX('[7]Réel 2023'!$A$2:$AO$501,MATCH($A103,'[7]Réel 2023'!$A$2:$A$501,0),MATCH(Q$2,'[7]Réel 2023'!$A$2:$AO$2,0))} -> 18742.93 | R103: =O103-K103 -> -1232.4863 | S103: =L103-Q103 -> 24394.09
A104: Véhicules usagésRev. Autres | B104: Véhicules usagés | C104: Rev. Autres | D104: =+INDEX('[7]Budget original'!$A$2:$AO$501,MATCH($A104,'[7]Budget original'!$A$2:$A$501,0),MATCH(D$2,'[7]Budget original'!$A$2:$AO$2,0)) -> 0 | E104: =IF(D104=0,0,F104/D104) -> 0 | F104: =+INDEX('[7]Budget original'!$A$2:$AO$501,MATCH($A104,'[7]Budget original'!$A$2:$A$501,0),MATCH(F$2,'[7]Budget original'!$A$2:$AO$2,0)) -> 1833.875 | K104: =IF(J97=0,0,L104/J97) -> 16.011143 | L104: =-SUMIFS([7]BV_Data_An_Cour!$O:$O,[7]BV_Data_An_Cour!$U:$U,$B104,[7]BV_Data_An_Cour!$V:$V,$C104,[7]BV_Data_An_Cour!$W:$W,$L$2) -> 560.39 | N104: =L104-F104 -> -1273.485 | Q104: {=+INDEX('[7]Réel 2023'!$A$2:$AO$501,MATCH($A104,'[7]Réel 2023'!$A$2:$A$501,0),MATCH(Q$2,'[7]Réel 2023'!$A$2:$AO$2,0))} -> 393.95 | R104: =O104-K104 -> -16.011143 | S104: =L104-Q104 -> 166.44
A105: Véhicules usagésTotal F&I | B105: Véhicules usagés | C105: Total F&I | D105: =D97 -> 36.6775 | E105: =IF(D105=0,0,F105/D105) -> 2200 | F105: =F102+F103+F104 -> 80690.5 | J105: =J97 -> 35 | K105: =IF(J105<=0,0,L105/J105) -> 1532.0946 | L105: =L102+L103+L104 -> 53623.31 | M105: =J105-D105 -> -1.6775 | N105: =L105-F105 -> -27067.19 | O105: =O97 -> 20 | P105: =IF(O105=0,0,Q105/O105) -> 1327.335 | Q105: =Q102+Q103+Q104 -> 26546.7 | S105: =L105-Q105 -> 27076.61
...

Sheet 2024-12
C1: Volks | K1: Véhicules neufs | S1: Réalisé, Décembre 2024
D2: X | E2: O | F2: U | J2: NB | L2: $ | O2: X | P2: O | Q2: U | V2: *** NE PAS EFFACER / Pour An Précédente ***
D3: BUDGET ORIGINAL | J3: RÉALISATION | M3: ÉCART réel / Budget | O3: ANNÉE PRÉCÉDENTE | R3: ECART (réel/ Ann.Préc.) | V3: NEUF | W3: 0.45
D4: UNITE | E4: $P/UNITÉ | F4: $PROFITS | J4: UNITÉS | K4: $P/UNITE | L4: $PROFITS | M4: UNITÉS | N4: $PROFITS | O4: UNITE | P4: $P/UNITÉ | Q4: $PROFITS | R4: UNITÉS | S4: $PROFITS | V4: USAGE | W4: 0.1
A5: Véhicules neufsVentes nettes | B5: Véhicules neufs | C5: Ventes nettes | F5: 1621482.2 | L5: 2168000.1 | Q5: 8099296.2 | V5: SERVICE | W5: 0.225
A6: Véhicules neufsAutos détail | B6: Véhicules neufs | C6: Autos détail | D6: 6 | E6: 2198.1219 | F6: 13188.732 | J6: 6 | K6: 1532.1433 | L6: 9192.86 | M6: 0 | N6: -3995.8716 | O6: 12 | P6: 1911.4758 | Q6: 22937.71 | R6: -6 | S6: -13744.85 | V6: CARROSSERIE | W6: 0.025
A7: Véhicules neufsCamions détail | B7: Véhicules neufs | C7: Camions détail | D7: 25 | E7: 2850.2587 | F7: 71256.467 | J7: 24 | K7: 1904.4017 | L7: 45705.64 | M7: -1 | N7: -25550.827 | O7: 39 | P7: 2432.7964 | Q7: 94879.06 | R7: -15 | S7: -49173.42 | V7: PIECES | W7: 0.2
A8: Véhicules neufsSprinter | B8: Véhicules neufs | C8: Sprinter | D8: 0 | E8: 0 | F8: 0 | J8: 0 | K8: 0 | L8: 0 | M8: 0 | N8: 0 | O8: 0 | P8: 0 | Q8: 0 | R8: 0 | S8: 0 | W8: 1
A9: Véhicules neufsMoto détail | B9: Véhicules neufs | C9: Moto détail | D9: 0 | E9: 0 | F9: 0 | J9: 0 | K9: 0 | L9: 0 | M9: 0 | N9: 0 | O9: 0 | P9: 0 | Q9: 0 | R9: 0 | S9: 0
A10: Véhicules neufs[...] | B10: Véhicules neufs | C10: [...] | D10: 0 | E10: 0 | F10: 0 | J10: 0 | K10: 0 | L10: 0 | M10: 0 | N10: 0 | O10: 0 | P10: 0 | Q10: 0 | R10: 0 | S10: 0
A11: Véhicules neufs[...] | B11: Véhicules neufs | C11: [...] | D11: 0 | E11: 0 | F11: 0 | J11: 0 | K11: 0 | L11: 0 | M11: 0 | N11: 0 | O11: 0 | P11: 0 | Q11: 0 | R11: 0 | S11: 0
A12: Véhicules neufs[...] | B12: Véhicules neufs | C12: [...] | D12: 0 | E12: 0 | F12: 0 | J12: 0 | K12: 0 | L12: 0 | M12: 0 | N12: 0 | O12: 0 | P12: 0 | Q12: 0 | R12: 0 | S12: 0
A13: Véhicules neufsTotal Neufs | B13: Véhicules neufs | C13: Total Neufs | D13: 31 | E13: 2724.0387 | F13: 84445.199 | J13: 30 | K13: 1829.95 | L13: 54898.5 | M13: -1 | N13: -29546.699 | O13: 51 | P13: 2310.1327 | Q13: 117816.77 | R13: -21 | S13: -62918.27
A14: Véhicules neufs | B14: Véhicules neufs | M14: -0.032258065 | N14: -0.34989199 | R14: -0.41176471 | S14: -0.53403493 | AD14: 20 | AE14: 1000 | AF14: 20000
A15: Véhicules neufsEx-Démos et courtoisies | B15: Véhicules neufs | C15: Ex-Démos et courtoisies | D15: 2.45 | E15: 2535.1216 | F15: 6211.0479 | J15: 4 | K15: 2295.8825 | L15: 9183.53 | M15: 1.55 | N15: 2972.4821 | O15: 1 | P15: 1170.99 | Q15: 1170.99 | R15: 3 | S15: 8012.54 | AD15: 25 | AE15: 800 | AF15: 20000
A16: Véhicules neufs | B16: Véhicules neufs
A17: Véhicules neufsFlottes | B17: Véhicules neufs | C17: Flottes | D17: 2.25 | E17: 2664.4641 | F17: 5995.0442 | J17: 6 | K17: 1073.965 | L17: 6443.79 | M17: 3.75 | N17: 448.74585 | O17: 0 | P17: 0 | Q17: -722.15 | R17: 6 | S17: 7165.94
A18: Véhicules neufs | B18: Véhicules neufs
A19: Véhicules neufsRachat bail | B19: Véhicules neufs | C19: Rachat bail | D19: 0 | E19: 0 | F19: 4250 | L19: 5949 | N19: 1699 | Q19: 5419.64 | R19: 0 | S19: 529.36
A20: Véhicules neufs | B20: Véhicules neufs
A21: Véhicules neufsRev. Finances | B21: Véhicules neufs | C21: Rev. Finances | D21: 0 | E21: 0 | F21: 6690 | K21: 37.907059 | L21: 1288.84 | N21: -5401.16 | Q21: 3518.68 | R21: -37.907059 | S21: -2229.84
A22: Véhicules neufsRev. Protections | B22: Véhicules neufs | C22: Rev. Protections | D22: 0 | E22: 0 | F22: 36126 | K22: 1309.9512 | L22: 44538.34 | N22: 8412.34 | Q22: 53594.75 | R22: -1309.9512 | S22: -9056.41
A23: Véhicules neufsRev. Autres | B23: Véhicules neufs | C23: Rev. Autres | D23: 0 | E23: 0 | F23: 669 | K23: 0 | L23: 0 | N23: -669 | Q23: 2460.25 | R23: 0 | S23: -2460.25
A24: Véhicules neufsTotal F&I | B24: Véhicules neufs | C24: Total F&I | D24: 33.45 | E24: 1300 | F24: 43485 | J24: 34 | K24: 1347.8582 | L24: 45827.18 | M24: 0.55 | N24: 2342.18 | O24: 52 | P24: 1145.6477 | Q24: 59573.68 | S24: -13746.5
A25: Véhicules neufs | B25: Véhicules neufs | N25: 0.053861791 | S25: -0.23074787
A26: Véhicules neufs | B26: Véhicules neufs
A27: Véhicules neufsTotal Dépt. Neufs | B27: Véhicules neufs | C27: Total Dépt. Neufs | D27: 35.7 | E27: 4044.4339 | F27: 144386.29 | J27: 40 | K27: 3057.55 | L27: 122302 | M27: 4.3 | N27: -22084.291 | O27: 52 | P27: 3524.2102 | Q27: 183258.93 | R27: -12 | S27: -60956.93
A28: Véhicules neufs | B28: Véhicules neufs | L28: 0.84704718 | M28: 0.12044818 | N28: -0.15295282 | R28: -0.23076923 | S28: -0.33262734
A29: Véhicules neufs | B29: Véhicules neufs
A30: Véhicules neufsDEPENSES | B30: Véhicules neufs | C30: DEPENSES
A31: Véhicules neufsComm. vendeurs | B31: Véhicules neufs | C31: Comm. vendeurs | D31: 0.34 | E31: 921.46858 | F31: 30823.124 | J31: 0.33063295 | K31: 685.82824 | L31: 23318.16 | N31: -7504.9639 | O31: 0.28756677 | P31: 654.02423 | Q31: 34009.26 | S31: -10691.1
A32: Véhicules neufsComm. F&I | B32: Véhicules neufs | C32: Comm. F&I | D32: 0.3 | E32: 390 | F32: 13045.5 | J32: 0.30000886 | K32: 404.36941 | L32: 13748.56 | N32: 703.06 | O32: 0.29983896 | P32: 343.50981 | Q32: 17862.51 | S32: -4113.95
A33: Véhicules neufsFrais de livraison | B33: Véhicules neufs | C33: Frais de livraison | E33: 115 | F33: 3846.75 | K33: 76.159118 | L33: 2589.41 | N33: -1257.34 | P33: 190.04019 | Q33: 9882.09 | S33: -7292.68
A34: Véhicules neufsService gratuit 1 | B34: Véhicules neufs | C34: Service gratuit 1 | E34: 3 | F34: 100.35 | K34: 26.280588 | L34: 893.54 | N34: 793.19 | P34: 28.626923 | Q34: 1488.6 | S34: -595.06
A35: Véhicules neufsEntretien stock | B35: Véhicules neufs | C35: Entretien stock | E35: 85.05 | F35: 2844.9225 | K35: 99.538529 | L35: 3384.31 | N35: 539.3875 | P35: 73.235577 | Q35: 3808.25 | S35: -423.94
A36: Véhicules neufsPublicité 1 | B36: Véhicules neufs | C36: Publicité 1 | E36: 191.06129 | F36: 6391 | K36: 316.01029 | L36: 10744.35 | N36: 4353.35 | P36: 146.97712 | Q36: 7642.81 | S36: 3101.54
A37: Véhicules neufsIntérêt de gros | B37: Véhicules neufs | C37: Intérêt de gros | E37: 363.30355 | F37: 12152.504 | K37: -106.62588 | L37: -3625.28 | N37: -15777.784 | P37: 331.31558 | Q37: 17228.41 | S37: -20853.69
A38: Véhicules neufs[...] | B38: Véhicules neufs | C38: [...] | E38: 0 | F38: 0 | K38: 0 | L38: 0 | N38: 0 | P38: 0 | Q38: 0 | S38: 0
A39: Véhicules neufs[...] | B39: Véhicules neufs | C39: [...] | E39: 0 | F39: 0 | K39: 0 | L39: 0 | N39: 0 | P39: 0 | Q39: 0 | S39: 0
A40: Véhicules neufs[...] | B40: Véhicules neufs | C40: [...] | E40: 0 | F40: 0 | K40: 0 | L40: 0 | N40: 0 | P40: 0 | Q40: 0 | S40: 0
A41: Véhicules neufsTOTAL VARIABLES | B41: Véhicules neufs | C41: TOTAL VARIABLES | D41: % brut | E41: 0.47929862 | F41: 69204.15 | J41: % brut | K41: 0.4174343 | L41: 51053.05 | N41: -18151.1 | O41: % brut | P41: 0.50159591 | Q41: 91921.93 | S41: -40868.88
A42: Véhicules neufsSalaires cadres | B42: Véhicules neufs | C42: Salaires cadres | F42: 18197.117 | L42: 6474.97 | N42: -11722.147 | P42: 0.061660242 | Q42: 11299.79 | S42: -4824.82
A43: Véhicules neufsSalaires commis | B43: Véhicules neufs | C43: Salaires commis | F43: 11267.511 | L43: 8412.6 | N43: -2854.9111 | Q43: 11695.76 | S43: -3283.16
A44: Véhicules neufsSalaires autres | B44: Véhicules neufs | C44: Salaires autres | F44: 2664.3538 | L44: 2835.6 | N44: 171.24615 | Q44: 4792.96 | S44: -1957.36
A45: Véhicules neufsSalaires spécialistes | B45: Véhicules neufs | C45: Salaires spécialistes | F45: 0 | L45: 0 | N45: 0 | Q45: 0 | S45: 0
A46: Véhicules neufs[...] | B46: Véhicules neufs | C46: [...] | F46: 0 | L46: 0 | N46: 0 | Q46: 0 | S46: 0
A47: Véhicules neufs[...] | B47: Véhicules neufs | C47: [...] | F47: 0 | L47: 0 | N47: 0 | Q47: 0 | S47: 0
A48: Véhicules neufs[...] | B48: Véhicules neufs | C48: [...] | F48: 0 | L48: 0 | N48: 0 | Q48: 0 | S48: 0
A49: Véhicules neufsSalaires en absences | B49: Véhicules neufs | C49: Salaires en absences | F49: 8897.7484 | L49: 9362.32 | N49: 464.57162 | Q49: 9556.95 | S49: -194.63
A50: Véhicules neufsDéduction à la source | B50: Véhicules neufs | C50: Déduction à la source | F50: 10818.408 | L50: 11260.94 | N50: 442.53228 | Q50: 11412.5 | S50: -151.56
A51: Véhicules neufsBénéfices marginaux | B51: Véhicules neufs | C51: Bénéfices marginaux | F51: 5573.8318 | L51: 4182.4 | N51: -1391.4318 | Q51: 4144.46 | S51: 37.94
A52: Véhicules neufsCsst | B52: Véhicules neufs | C52: Csst | F52: 2430.222 | L52: 2840.64 | N52: 410.41798 | Q52: 1190.61 | S52: 1650.03
A53: Véhicules neufs[...] | B53: Véhicules neufs | C53: [...] | D53: #N/A | F53: 0 | L53: 0 | N53: 0 | Q53: 0 | S53: 0
A54: Véhicules neufsTOTAL PERSONNEL | B54: Véhicules neufs | C54: TOTAL PERSONNEL | D54: % brut | E54: 0.41450744 | F54: 59849.192 | J54: % brut | K54: 0.37096262 | L54: 45369.47 | N54: -14479.722 | O54: % brut | P54: 0.29517268 | Q54: 54093.03 | S54: -8723.56
A55: Véhicules neufsPublicité 2 | B55: Véhicules neufs | C55: Publicité 2 | F55: 0 | L55: 0 | N55: 0 | Q55: 0 | S55: 0
A56: Véhicules neufsService gratuit 2 | B56: Véhicules neufs | C56: Service gratuit 2 | F56: 0 | L56: 0 | N56: 0 | Q56: 0 | S56: 0
A57: Véhicules neufsFrais véhicules de cie | B57: Véhicules neufs | C57: Frais véhicules de cie | F57: 9200 | L57: 12087.7 | N57: 2887.7 | Q57: 6904.41 | S57: 5183.29
A58: Véhicules neufsInformatique | B58: Véhicules neufs | C58: Informatique | F58: 9039.6955 | L58: 8179.98 | N58: -859.71547 | Q58: 6561.68 | S58: 1618.3
A59: Véhicules neufsFrais de déplacement | B59: Véhicules neufs | C59: Frais de déplacement | F59: 1105.2259 | L59: 1118.44 | N59: 13.214115 | Q59: 1074.68 | S59: 43.76
A60: Véhicules neufsServices extérieurs | B60: Véhicules neufs | C60: Services extérieurs | F60: 6711.4186 | L60: 6975.91 | N60: 264.49136 | Q60: 7461.81 | S60: -485.9
A61: Véhicules neufsFournitures autres | B61: Véhicules neufs | C61: Fournitures autres | F61: 125 | L61: 176.44 | N61: 51.44 | Q61: 71.82 | S61: 104.62
A62: Véhicules neufsUniformes | B62: Véhicules neufs | C62: Uniformes | F62: 83.333333 | L62: 0 | N62: -83.333333 | Q62: 0 | S62: 0
A63: Véhicules neufsPapeterie | B63: Véhicules neufs | C63: Papeterie | F63: 756.9466 | L63: 1062.18 | N63: 305.2334 | Q63: 1075.92 | S63: -13.74
A64: Véhicules neufsTéléphone | B64: Véhicules neufs | C64: Téléphone | F64: 309.40349 | L64: 328.45 | N64: 19.046515 | Q64: 316 | S64: 12.45
A65: Véhicules neufsFrais postaux | B65: Véhicules neufs | C65: Frais postaux | F65: 113.12881 | L65: 32.96 | N65: -80.16881 | Q65: 230.2 | S65: -197.24
A66: Véhicules neufsDivers | B66: Véhicules neufs | C66: Divers | F66: 282.4626 | L66: 95.63 | N66: -186.8326 | Q66: 94.22 | S66: 1.41
... A68: Véhicules neufsFrais bancaires | B68: Véhicules neufs | C68: Frais bancaires | F68: 3363.2959 | L68: 4138.41 | N68: 775.11407 | Q68: 3206.31 | S68: 932.1
A69: Véhicules neufs[...] | B69: Véhicules neufs | C69: [...] | F69: 0 | N69: 0 | Q69: 0 | S69: 0
A70: Véhicules neufs[...] | B70: Véhicules neufs | C70: [...] | F70: 0 | L70: 0 | N70: 0 | Q70: 0 | S70: 0
A71: Véhicules neufs[...] | B71: Véhicules neufs | C71: [...] | F71: 0 | L71: 0 | N71: 0 | Q71: 0 | S71: 0
A72: Véhicules neufsTOTAL SEMI-FIXES | B72: Véhicules neufs | C72: TOTAL SEMI-FIXES | D72: % brut | E72: 0.2284775 | F72: 32989.018 | J72: % brut | K72: 0.28043842 | L72: 34298.18 | N72: 1309.1617 | O72: % brut | P72: 0.15024665 | Q72: 27534.04 | S72: 6764.14
A73: Véhicules neufs | B73: Véhicules neufs
A74: Véhicules neufsTOTAL DES DÉPENSES | B74: Véhicules neufs | C74: TOTAL DES DÉPENSES | D74: % brut | E74: 1.1222836 | F74: 162042.36 | J74: % brut | K74: 1.0688353 | L74: 130720.7 | N74: -31321.66 | O74: % brut | P74: 0.94701524 | Q74: 173549 | S74: -42828.3
A75: Véhicules neufsProgramme neuf 1 | B75: Véhicules neufs | C75: Programme neuf 1 | F75: 20000 | L75: 20000 | N75: 0 | Q75: 31556
A76: Véhicules neufsProgramme neuf 2 | B76: Véhicules neufs | C76: Programme neuf 2 | F76: 0 | L76: 0 | N76: 0 | Q76: 0 | S76: 0
A77: Véhicules neufsProgramme neuf 3 | B77: Véhicules neufs | C77: Programme neuf 3 | F77: 0 | L77: 0 | N77: 0 | Q77: 0 | S77: 0
A78: Véhicules neufsHoldbacks | B78: Véhicules neufs | C78: Holdbacks | E78: 1206.3386 | F78: 43066.289 | K78: 1351.325 | L78: 54053 | N78: 10986.711 | Q78: 55160.85 | S78: -1107.85
A79: Véhicules neufs[...] | B79: Véhicules neufs | C79: [...] | F79: 0 | L79: 0 | N79: 0 | Q79: 0 | S79: 0
A80: Véhicules neufs[...] | B80: Véhicules neufs | C80: [...] | F80: 0 | L80: 0 | N80: 0 | Q80: 0 | S80: 0
A81: Véhicules neufs[...] | B81: Véhicules neufs | C81: [...] | F81: 0 | L81: 0 | N81: 0 | Q81: 0 | S81: 0
A82: Véhicules neufsFrais administration | B82: Véhicules neufs | C82: Frais administration | D82: 0.95 | E82: 474.05 | F82: 15856.972 | J82: 1.0236411 | K82: 485.20588 | L82: 16497 | N82: 640.0275 | Q82: 22461 | S82: -5964
A83: Véhicules neufsAUTRES REVENUS | B83: Véhicules neufs | C83: AUTRES REVENUS | F83: 78923.261 | L83: 90550 | N83: 11626.739 | Q83: 109177.85 | S83: -7071.85
A84: Véhicules neufs | B84: Véhicules neufs
A85: Véhicules neufsPROFIT DÉPARTEMENTAL | B85: Véhicules neufs | C85: PROFIT DÉPARTEMENTAL | F85: 61267.192 | L85: 82131.3 | N85: 20864.108 | P85: 0.014678779 | Q85: 118887.78 | S85: -25200.48
C89: Volks | K89: Véhicules usagés | S89: Réalisé, Décembre 2024
D91: BUDGET ORIGINAL | J91: RÉALISATION | M91: ÉCART réel / Budget | O91: ANNÉE PRÉCÉDENTE | R91: ECART (réel/ Ann.Préc.)
D92: UNITE | E92: $P/UNITÉ | F92: $PROFITS | J92: UNITÉS | K92: $P/UNITE | L92: $PROFITS | M92: UNITÉS | N92: $PROFITS | O92: UNITE | P92: $P/UNITÉ | Q92: $PROFITS | R92: UNITÉS | S92: $PROFITS
A93: Véhicules usagésVentes nettes | B93: Véhicules usagés | C93: Ventes nettes | F93: 1310599.6 | L93: 803576.36 | Q93: 780381.81
A94: Véhicules usagésCertifié | B94: Véhicules usagés | C94: Certifié | D94: 24.18 | E94: 1800 | F94: 43524 | J94: 17 | K94: 1130.9829 | L94: 19226.71 | M94: -7.18 | N94: -24297.29 | O94: 13 | P94: 972.76231 | Q94: 12645.91 | R94: 4 | S94: 6580.8
A95: Véhicules usagésNon Certifié | B95: Véhicules usagés | C95: Non Certifié | D95: 1.364 | E95: 1800 | F95: 2455.2 | J95: 0 | K95: 0 | L95: -471.43 | M95: -1.364 | N95: -2926.63 | O95: 5 | P95: 1770.388 | Q95: 8851.94 | R95: -5 | S95: -9323.37
A96: Véhicules usagésAutres Marques | B96: Véhicules usagés | C96: Autres Marques | D96: 0.806 | E96: 1800 | F96: 1450.8 | J96: 1 | K96: 2147.6 | L96: 2147.6 | M96: 0.194 | N96: 696.8 | O96: 0 | P96: 0 | Q96: 0 | R96: 1 | S96: 2147.6
A97: Véhicules usagésTotal Usagés | B97: Véhicules usagés | C97: Total Usagés | D97: 26.35 | E97: 1800 | F97: 47430 | J97: 18 | K97: 1161.2711 | L97: 20902.88 | M97: -8.35 | N97: -26527.12 | O97: 18 | P97: 1194.325 | Q97: 21497.85 | R97: -1 | S97: -2742.57
A98: Véhicules usagés | B98: Véhicules usagés | E98: 0 | M98: -0.31688805 | N98: -0.5592899 | P98: 0 | R98: -0.055555556 | S98: -0.12757415
A99: Véhicules usagés | B99: Véhicules usagés | D99: 0 | E99: 0 | F99: 0
A100: Véhicules usagésVentes au Gros | B100: Véhicules usagés | C100: Ventes au Gros | D100: 26.97 | E100: 400 | F100: 10788 | J100: 22 | K100: -477.45 | L100: -10503.9 | M100: -4.97 | N100: -21291.9 | O100: 21 | P100: -377.50524 | Q100: -7927.61 | R100: 1 | S100: -2576.29
A101: Véhicules usagés | B101: Véhicules usagés
A102: Véhicules usagésRev. Finances | B102: Véhicules usagés | C102: Rev. Finances | D102: 0 | E102: 0 | F102: 18445 | K102: 217.00944 | L102: 3906.17 | N102: -14538.83 | Q102: 5284.87 | R102: -217.00944 | S102: -1378.7
A103: Véhicules usagésRev. Protections | B103: Véhicules usagés | C103: Rev. Protections | D103: 0 | E103: 0 | F103: 38207.5 | K103: 1575.7439 | L103: 28363.39 | N103: -9844.11 | Q103: 18547.99 | R103: -1575.7439 | S103: 9815.4
A104: Véhicules usagésRev. Autres | B104: Véhicules usagés | C104: Rev. Autres | D104: 0 | E104: 0 | F104: 1317.5 | K104: 0 | L104: 0 | N104: -1317.5 | Q104: 0 | R104: 0 | S104: 0
A105: Véhicules usagésTotal F&I | B105: Véhicules usagés | C105: Total F&I | D105: 26.35 | E105: 2200 | F105: 57970 | J105: 18 | K105: 1792.7533 | L105: 32269.56 | M105: -8.35 | N105: -25700.44 | O105: 18 | P105: 1324.0478 | Q105: 23832.86 | S105: 8436.7
...

Sheet END
