Workbook
Name _Dates_Conc: [1]Dealers!$BF$37:$KA$63
Name _scen: '[1]Scen & Sens'!$E$26
Name _scen1: '[1]Scen & Sens'!$E$27
Name _scen2: '[1]Scen & Sens'!$E$28
Name _SCenarios: '[1]Scen & Sens'!$J$26:$O$26
Name _Sens1: '[1]Scen & Sens'!$F$9
Name _Sens2: '[1]Scen & Sens'!$F$10
Name _sensRes1: '[1]Scen & Sens'!$E$15
Name _sensRes2: '[1]Scen & Sens'!$E$16
Name _sensRes3: '[1]Scen & Sens'!$E$17
Name _sensRes4: '[1]Scen & Sens'!$E$18
Name _sensRes5: '[1]Scen & Sens'!$E$19
Name _sensRes6: '[1]Scen & Sens'!$E$20
Name _sensRes7: '[1]Scen & Sens'!$E$21
Name DateRange: [1]Volkswagen!$BF$6:$DY$6
Name Monetary_Unit: [1]Parameters!$B$15
Name Months: [1]Parameters!$E$9:$E$20
Name Rng_Dealers_Names: [1]!Tbl_Dealers[Dealer Name]
Name Rng_Dlr_Dates: [1]!Tbl_V_Dlr_Dates[Date]
Name Ticker: #REF!
Name Ticker: #REF!
Name Ticker: #REF!
Name Titre: [1]Front!$A$9

Sheet Paramètre
B3: Quarter
B6: BUDGET | F6: BUDGET RÉVISÉ | J6: ACTUAL | N6: LAST YEAR
B7: Ventes | C7: Profits bruts | D7: BAIIA | E7: EBIT | F7: Ventes | G7: Profits bruts | H7: BAIIA | I7: EBIT | J7: Ventes | K7: Profits bruts | L7: BAIIA | M7: EBIT | N7: Ventes | O7: Profits bruts | P7: BAIIA | Q7: EBIT
A8: CTRL | B8: =+B9-B10 -> #REF! | C8: =+C9-C10 -> #REF! | D8: =+D9-D10 -> #REF! | E8: =+E9-E10 -> #REF! | F8: =+F9-F10 -> #REF! | G8: =+G9-G10 -> #REF! | H8: =+H9-H10 -> #REF! | I8: =+I9-I10 -> #REF! | ... Q8: =+Q9-Q10 -> #REF!
A9: CONSO | B9: =+Conso!$Z$405 -> 20000715 | C9: =+Conso!$Z$406 -> 2455615.9 | D9: =+Conso!$Z$482 -> 742277.72 | E9: =+Conso!$Z$497 -> 614571.22 | F9: =+Conso!$AC$405 -> 0 | G9: =+Conso!$AC$406 -> 0 | H9: =+Conso!$AC$482 -> 0 | I9: =+Conso!$AC$497 -> 0 | J9: =+Conso!$AF$405 -> 17432381 | K9: =+Conso!$AF$406 -> 2121598.6 | L9: =+Conso!$AF$482 -> 595238.07 | M9: =+Conso!$AF$497 -> 468373.07 | N9: =+Conso!$AL$405 -> 12663799 | O9: =+Conso!$AL$406 -> 1865550.7 | P9: =+Conso!$AL$482 -> 359623.03 | Q9: =+Conso!$AL$497 -> 249286.1
A10: TOTAL | B10: =+SUM(B11:B13) -> #REF! | C10: =+SUM(C11:C13) -> #REF! | D10: =+SUM(D11:D13) -> #REF! | E10: =+SUM(E11:E13) -> #REF! | F10: =+SUM(F11:F13) -> #REF! | G10: =+SUM(G11:G13) -> #REF! | H10: =+SUM(H11:H13) -> #REF! | I10: =+SUM(I11:I13) -> #REF! | ... Q10: =+SUM(Q11:Q13) -> #REF!
A11: Mois 1 | B11: =+#REF! -> #REF! | C11: =+#REF! -> #REF! | D11: =+#REF! -> #REF! | E11: =+#REF! -> #REF! | F11: =+#REF! -> #REF! | G11: =+#REF! -> #REF! | H11: =+#REF! -> #REF! | I11: =+#REF! -> #REF! | ... Q11: =+#REF! -> #REF!
A12: Mois 2 | B12: =+#REF! -> #REF! | C12: =+#REF! -> #REF! | D12: =+#REF! -> #REF! | E12: =+#REF! -> #REF! | F12: =+#REF! -> #REF! | G12: =+#REF! -> #REF! | H12: =+#REF! -> #REF! | I12: =+#REF! -> #REF! | ... Q12: =+#REF! -> #REF!
A13: Mois 3 | B13: =+#REF! -> #REF! | C13: =+#REF! -> #REF! | D13: =+#REF! -> #REF! | E13: =+#REF! -> #REF! | F13: =+#REF! -> #REF! | G13: =+#REF! -> #REF! | H13: =+#REF! -> #REF! | I13: =+#REF! -> #REF! | ... Q13: =+#REF! -> #REF!

Sheet Conso
C1: Conso | K1: Véhicules neufs | S1: =CONCATENATE("Réalisé"," ",Paramètre!$C$2," ",Paramètre!$C$3) -> Réalisé
D2: X | E2: O | F2: U | G2: X | H2: O | I2: U
D3: BUDGET ORIGINAL | G3: BUDGET REVISE | J3: RÉALISATION | M3: ÉCART réel / original | O3: ANNÉE PRÉCÉDENTE | R3: ÉCART réel / année précédente
D4: UNITE | E4: $P/UNITÉ | F4: $PROFITS | G4: UNITE | H4: $P/UNITÉ | I4: $PROFITS | J4: UNITE | K4: $P/UNITE | L4: $PROFITS | M4: UNITÉ | N4: $PROFITS | O4: UNITE | P4: $P/UNITE | Q4: $PROFITS | R4: UNITE | S4: $PROFITS
A5: =+B5&C5 -> Véhicules neufsVentes nettes | B5: =+$K$1 -> Véhicules neufs | C5: Ventes nettes | F5: =+SUM(START:END!F5) -> 11342294 | I5: =+SUM(START:END!I5) -> 0 | L5: =+SUM(START:END!L5) -> 9449688.8 | Q5: =+SUM(START:END!Q5) -> 6739517.4
A6: =+B6&C6 -> Véhicules neufsAutos détail | B6: =+$K$1 -> Véhicules neufs | C6: Autos détail | D6: =+SUM(START:END!D6) -> 56 | E6: =IF(D6=0,0,F6/D6) -> 1953.6492 | F6: =+SUM(START:END!F6) -> 109404.35 | G6: =+SUM(START:END!G6) -> 0 | H6: =IF(G6=0,0,I6/G6) -> 0 | I6: =+SUM(START:END!I6) -> 0 | J6: =+SUM(START:END!J6) -> 23 | K6: =IF(J6=0,0,L6/J6) -> 1641.91 | L6: =+SUM(START:END!L6) -> 37763.93 | M6: =J6-D6 -> -33 | N6: =L6-F6 -> -71640.423 | O6: =+SUM(START:END!O6) -> 26 | P6: =IF(O6=0,0,Q6/O6) -> 1810.325 | Q6: =+SUM(START:END!Q6) -> 47068.45 | R6: =J6-O6 -> -3 | S6: =L6-Q6 -> -9304.52
A7: =+B7&C7 -> Véhicules neufsCamions détail | B7: =+$K$1 -> Véhicules neufs | C7: Camions détail | D7: =+SUM(START:END!D7) -> 149 | E7: =IF(D7=0,0,F7/D7) -> 2435.9047 | F7: =+SUM(START:END!F7) -> 362949.8 | G7: =+SUM(START:END!G7) -> 0 | H7: =IF(G7=0,0,I7/G7) -> 0 | I7: =+SUM(START:END!I7) -> 0 | J7: =+SUM(START:END!J7) -> 134 | K7: =IF(J7=0,0,L7/J7) -> 1956.4093 | L7: =+SUM(START:END!L7) -> 262158.85 | M7: =J7-D7 -> -15 | N7: =L7-F7 -> -100790.95 | O7: =+SUM(START:END!O7) -> 83 | P7: =IF(O7=0,0,Q7/O7) -> 1820.1257 | Q7: =+SUM(START:END!Q7) -> 151070.43 | R7: =J7-O7 -> 51 | S7: =L7-Q7 -> 111088.42
A8: =+B8&C8 -> Véhicules neufsSprinter | B8: =+$K$1 -> Véhicules neufs | C8: Sprinter | D8: =+SUM(START:END!D8) -> 0 | E8: =IF(D8=0,0,F8/D8) -> 0 | F8: =+SUM(START:END!F8) -> 0 | G8: =+SUM(START:END!G8) -> 0 | H8: =IF(G8=0,0,I8/G8) -> 0 | I8: =+SUM(START:END!I8) -> 0 | J8: =+SUM(START:END!J8) -> 0 | K8: =IF(J8=0,0,L8/J8) -> 0 | L8: =+SUM(START:END!L8) -> 0 | M8: =J8-D8 -> 0 | N8: =L8-F8 -> 0 | O8: =+SUM(START:END!O8) -> 0 | P8: =IF(O8=0,0,Q8/O8) -> 0 | Q8: =+SUM(START:END!Q8) -> 0 | R8: =J8-O8 -> 0 | S8: =L8-Q8 -> 0
A9: =+B9&C9 -> Véhicules neufsMoto détail | B9: =+$K$1 -> Véhicules neufs | C9: Moto détail | D9: =+SUM(START:END!D9) -> 0 | E9: =IF(D9=0,0,F9/D9) -> 0 | F9: =+SUM(START:END!F9) -> 0 | G9: =+SUM(START:END!G9) -> 0 | H9: =IF(G9=0,0,I9/G9) -> 0 | I9: =+SUM(START:END!I9) -> 0 | J9: =+SUM(START:END!J9) -> 0 | K9: =IF(J9=0,0,L9/J9) -> 0 | L9: =+SUM(START:END!L9) -> 0 | M9: =J9-D9 -> 0 | N9: =L9-F9 -> 0 | O9: =+SUM(START:END!O9) -> 0 | P9: =IF(O9=0,0,Q9/O9) -> 0 | Q9: =+SUM(START:END!Q9) -> 0 | R9: =J9-O9 -> 0 | S9: =L9-Q9 -> 0
A10: =+B10&C10 -> Véhicules neufs[...] | B10: =+$K$1 -> Véhicules neufs | C10: [...] | D10: =+SUM(START:END!D10) -> 0 | E10: =IF(D10=0,0,F10/D10) -> 0 | F10: =+SUM(START:END!F10) -> 0 | G10: =+SUM(START:END!G10) -> 0 | H10: =IF(G10=0,0,I10/G10) -> 0 | I10: =+SUM(START:END!I10) -> 0 | J10: =+SUM(START:END!J10) -> 0 | K10: =IF(J10=0,0,L10/J10) -> 0 | L10: =+SUM(START:END!L10) -> 0 | M10: =J10-G10 -> 0 | N10: =L10-I10 -> 0 | O10: =+SUM(START:END!O10) -> 0 | P10: =IF(O10=0,0,Q10/O10) -> 0 | Q10: =+SUM(START:END!Q10) -> 0 | R10: =J10-O10 -> 0 | S10: =L10-Q10 -> 0
A11: =+B11&C11 -> Véhicules neufs[...] | B11: =+$K$1 -> Véhicules neufs | C11: [...] | D11: =+SUM(START:END!D11) -> 0 | E11: =IF(D11=0,0,F11/D11) -> 0 | F11: =+SUM(START:END!F11) -> 0 | G11: =+SUM(START:END!G11) -> 0 | H11: =IF(G11=0,0,I11/G11) -> 0 | I11: =+SUM(START:END!I11) -> 0 | J11: =+SUM(START:END!J11) -> 0 | K11: =IF(J11=0,0,L11/J11) -> 0 | L11: =+SUM(START:END!L11) -> 0 | M11: =J11-G11 -> 0 | N11: =L11-I11 -> 0 | O11: =+SUM(START:END!O11) -> 0 | P11: =IF(O11=0,0,Q11/O11) -> 0 | Q11: =+SUM(START:END!Q11) -> 0 | R11: =J11-O11 -> 0 | S11: =L11-Q11 -> 0
A12: =+B12&C12 -> Véhicules neufs[...] | B12: =+$K$1 -> Véhicules neufs | C12: [...] | D12: =+SUM(START:END!D12) -> 0 | E12: =IF(D12=0,0,F12/D12) -> 0 | F12: =+SUM(START:END!F12) -> 0 | G12: =+SUM(START:END!G12) -> 0 | H12: =IF(G12=0,0,I12/G12) -> 0 | I12: =+SUM(START:END!I12) -> 0 | J12: =+SUM(START:END!J12) -> 0 | K12: =IF(J12=0,0,L12/J12) -> 0 | L12: =+SUM(START:END!L12) -> 0 | M12: =J12-G12 -> 0 | N12: =L12-I12 -> 0 | O12: =+SUM(START:END!O12) -> 0 | P12: =IF(O12=0,0,Q12/O12) -> 0 | Q12: =+SUM(START:END!Q12) -> 0 | R12: =J12-O12 -> 0 | S12: =L12-Q12 -> 0
A13: =+B13&C13 -> Véhicules neufsTotal Neufs | B13: =+$K$1 -> Véhicules neufs | C13: Total Neufs | D13: =+SUM(D6:D12) -> 205 | E13: =IF(D13<=0,0,F13/D13) -> 2304.1666 | F13: =+SUM(F6:F12) -> 472354.15 | G13: =+SUM(G6:G12) -> 0 | H13: =IF(G13<=0,0,I13/G13) -> 0 | I13: =+SUM(I6:I12) -> 0 | J13: =+SUM(J6:J12) -> 157 | K13: =IF(J13<=0,0,L13/J13) -> 1910.3362 | L13: =+SUM(L6:L12) -> 299922.78 | M13: =+SUM(M6:M12) -> -48 | N13: =+SUM(N6:N12) -> -172431.37 | O13: =+SUM(O6:O12) -> 109 | P13: =IF(O13<=0,0,Q13/O13) -> 1817.7879 | Q13: =+SUM(Q6:Q12) -> 198138.88 | R13: =+SUM(R6:R12) -> 48 | S13: =+SUM(S6:S12) -> 101783.9
A14: =+B14&C14 -> Véhicules neufs | B14: =+$K$1 -> Véhicules neufs | N14: =IF(F13=0,0,N13/F13) -> -0.3650468 | R14: =R13/O13 -> 0.44036697 | S14: =IF(Q13=0,0,(S13/Q13)) -> 0.51369978
A15: =+B15&C15 -> Véhicules neufsEx-Démos et courtoisies | B15: =+$K$1 -> Véhicules neufs | C15: Ex-Démos et courtoisies | D15: =+SUM(START:END!D15) -> 10 | E15: =IF(D15=0,0,F15/D15) -> 1534.7521 | F15: =+SUM(START:END!F15) -> 15347.521 | G15: =+SUM(START:END!G15) -> 0 | H15: =IF(G15=0,0,I15/G15) -> 0 | I15: =+SUM(START:END!I15) -> 0 | J15: =+SUM(START:END!J15) -> 8 | K15: =IF(J15=0,0,L15/J15) -> 822.34625 | L15: =+SUM(START:END!L15) -> 6578.77 | M15: =J15-D15 -> -2 | N15: =L15-F15 -> -8768.7514 | O15: =+SUM(START:END!O15) -> 12 | P15: =IF(O15=0,0,Q15/O15) -> 1517.4408 | Q15: =+SUM(START:END!Q15) -> 18209.29 | R15: =J15-O15 -> -4 | S15: =L15-Q15 -> -11630.52
A16: =+B16&C16 -> Véhicules neufs | B16: =+$K$1 -> Véhicules neufs
A17: =+B17&C17 -> Véhicules neufsFlottes | B17: =+$K$1 -> Véhicules neufs | C17: Flottes | D17: =+SUM(START:END!D17) -> 5 | E17: =IF(D17=0,0,F17/D17) -> 2393.8521 | F17: =+SUM(START:END!F17) -> 11969.261 | G17: =+SUM(START:END!G17) -> 0 | H17: =IF(G17=0,0,I17/G17) -> 0 | I17: =+SUM(START:END!I17) -> 0 | J17: =+SUM(START:END!J17) -> 5 | K17: =IF(J17=0,0,L17/J17) -> 2778.144 | L17: =+SUM(START:END!L17) -> 13890.72 | M17: =J17-D17 -> 0 | N17: =L17-F17 -> 1921.4594 | O17: =+SUM(START:END!O17) -> 11 | P17: =IF(O17=0,0,Q17/O17) -> 1058.8518 | Q17: =+SUM(START:END!Q17) -> 11647.37 | R17: =J17-O17 -> -6 | S17: =L17-Q17 -> 2243.35
A18: =+B18&C18 -> Véhicules neufs | B18: =+$K$1 -> Véhicules neufs
A19: =+B19&C19 -> Véhicules neufsRachat bail | B19: =+$K$1 -> Véhicules neufs | C19: Rachat bail | F19: =+SUM(START:END!F19) -> 22950 | I19: =+SUM(START:END!I19) -> 0 | L19: =+SUM(START:END!L19) -> 27609.85 | N19: =L19-F19 -> 4659.85 | Q19: =+SUM(START:END!Q19) -> 23749 | R19: =O19-K19 -> 0 | S19: =L19-Q19 -> 3860.85
A20: =+B20&C20 -> Véhicules neufs | B20: =+$K$1 -> Véhicules neufs
A21: =+B21&C21 -> Véhicules neufsRev. Finances | B21: =+$K$1 -> Véhicules neufs | C21: Rev. Finances | D21: 0 | E21: =IF(D21=0,0,F21/D21) -> 0 | F21: =+SUM(START:END!F21) -> 10750 | G21: 0 | H21: =IF(G21=0,0,I21/G21) -> 0 | I21: =+SUM(START:END!I21) -> 0 | K21: =IF(J13=0,0,L21/(J13+J15)) -> 34.835879 | L21: =+SUM(START:END!L21) -> 5747.92 | N21: =L21-F21 -> -5002.08 | P21: =IF(O13=0,0,Q21/(O13+O15)) -> 10.65157 | Q21: =+SUM(START:END!Q21) -> 1288.84 | R21: =O21-K21 -> -34.835879 | S21: =L21-Q21 -> 4459.08
A22: =+B22&C22 -> Véhicules neufsRev. Protections | B22: =+$K$1 -> Véhicules neufs | C22: Rev. Protections | D22: 0 | E22: =IF(D22=0,0,F22/D22) -> 0 | F22: =+SUM(START:END!F22) -> 199950 | G22: 0 | H22: =IF(G22=0,0,I22/G22) -> 0 | I22: =+SUM(START:END!I22) -> 0 | K22: =IF(J13=0,0,L22/(J13+J15)) -> 938.41255 | L22: =+SUM(START:END!L22) -> 154838.07 | N22: =L22-F22 -> -45111.93 | P22: =IF(O13=0,0,Q22/(O13+O15)) -> 1036.308 | Q22: =+SUM(START:END!Q22) -> 125393.27 | R22: =O22-K22 -> -938.41255 | S22: =L22-Q22 -> 29444.8
A23: =+B23&C23 -> Véhicules neufsRev. Autres | B23: =+$K$1 -> Véhicules neufs | C23: Rev. Autres | D23: 0 | E23: =IF(D23=0,0,F23/D23) -> 0 | F23: =+SUM(START:END!F23) -> 4300 | G23: 0 | H23: =IF(G23=0,0,I23/G23) -> 0 | I23: =+SUM(START:END!I23) -> 0 | K23: =IF(J13=0,0,L23/(J13+J15)) -> 11.995879 | L23: =+SUM(START:END!L23) -> 1979.32 | N23: =L23-F23 -> -2320.68 | P23: =IF(O13=0,0,Q23/(O13+O15)) -> 10.65438 | Q23: =+SUM(START:END!Q23) -> 1289.18 | R23: =O23-K23 -> -11.995879 | S23: =L23-Q23 -> 690.14
A24: =+B24&C24 -> Véhicules neufsTotal F&I | B24: =+$K$1 -> Véhicules neufs | C24: Total F&I | D24: =+D15+D13 -> 215 | E24: =IF(D24<=0,0,F24/D24) -> 1000 | F24: =F21+F22+F23 -> 215000 | G24: =+G15+G13 -> 0 | H24: =IF(G24<=0,0,I24/G24) -> 0 | I24: =I21+I22+I23 -> 0 | J24: =+J15+J13 -> 165 | K24: =IF(J24<=0,0,L24/J24) -> 985.2443 | L24: =L21+L22+L23 -> 162565.31 | M24: =+M15+M13 -> -50 | N24: =N21+N22+N23 -> -52434.69 | O24: =+O15+O13 -> 121 | P24: =IF(O24<=0,0,Q24/O24) -> 1057.614 | Q24: =Q21+Q22+Q23 -> 127971.29 | S24: =L24-Q24 -> 34594.02
A25: =+B25&C25 -> Véhicules neufs | B25: =+$K$1 -> Véhicules neufs | S25: =IF(Q24=0,0,(S24/Q24)) -> 0.27032641
A26: =+B26&C26 -> Véhicules neufs | B26: =+$K$1 -> Véhicules neufs
A27: =+B27&C27 -> Véhicules neufsTotal Dépt. Neufs | B27: =+$K$1 -> Véhicules neufs | C27: Total Dépt. Neufs | D27: =+D13+D15+D17 -> 220 | E27: =IF(D27<=0,0,F27/D27) -> 3352.8224 | F27: =F13+F17+F24+F19+F15 -> 737620.93 | G27: =+G13+G15+G17 -> 0 | H27: =IF(G27<=0,0,I27/G27) -> 0 | I27: =I13+I17+I24+I19+I15 -> 0 | J27: =+J13+J15+J17 -> 170 | K27: =IF(J27<=0,0,L27/J27) -> 3003.3378 | L27: =L13+L17+L24+L19+L15 -> 510567.43 | M27: =+M13+M15+M17 -> -50 | N27: =N13+N17+N24+N19+N15 -> -227053.5 | O27: =+O13+O15+O17 -> 132 | P27: =IF(O27<=0,0,Q27/O27) -> 2876.6351 | Q27: =Q13+Q17+Q24+Q19+Q15 -> 379715.83 | R27: =J27-O27 -> 38 | S27: =L27-Q27 -> 130851.6
A28: =+B28&C28 -> Véhicules neufs | B28: =+$K$1 -> Véhicules neufs | M28: =M27/D27 -> -0.22727273 | N28: =N27/F27 -> -0.30781868 | R28: =R27/O27 -> 0.28787879 | S28: =IF(Q27=0,0,S27/Q27) -> 0.34460402
A29: =+B29&C29 -> Véhicules neufs | B29: =+$K$1 -> Véhicules neufs
A30: =+B30&C30 -> Véhicules neufsDEPENSES | B30: =+$K$1 -> Véhicules neufs | C30: DEPENSES
A31: =+B31&C31 -> Véhicules neufsComm. vendeurs | B31: =+$K$1 -> Véhicules neufs | C31: Comm. vendeurs | E31: =F31/D$24 -> 740.68293 | F31: =+SUM(START:END!F31) -> 159246.83 | H31: =I31/G$24 -> #DIV/0! | I31: =+SUM(START:END!I31) -> 0 | J31: =L31/L13 -> 0.35182456 | K31: =IF(L31=0,0,L31/J$24) -> 639.51636 | L31: =+SUM(START:END!L31) -> 105520.2 | N31: =L31-F31 -> -53726.629 | P31: =IF(Q31=0,0,Q31/O$24) -> 622.44397 | Q31: =+SUM(START:END!Q31) -> 75315.72 | S31: =L31-Q31 -> 30204.48
A32: =+B32&C32 -> Véhicules neufsComm. F&I | B32: =+$K$1 -> Véhicules neufs | C32: Comm. F&I | E32: =F32/D$24 -> 280 | F32: =+SUM(START:END!F32) -> 60200 | H32: =I32/G$24 -> #DIV/0! | I32: =+SUM(START:END!I32) -> 0 | J32: =L32/L24 -> 0.26999918 | K32: =IF(L32=0,0,L32/J$24) -> 266.01515 | L32: =+SUM(START:END!L32) -> 43892.5 | N32: =L32-F32 -> -16307.5 | P32: =IF(Q32=0,0,Q32/O$24) -> 300.16132 | Q32: =+SUM(START:END!Q32) -> 36319.52 | S32: =L32-Q32 -> 7572.98
A33: =+B33&C33 -> Véhicules neufsFrais de livraison | B33: =+$K$1 -> Véhicules neufs | C33: Frais de livraison | E33: =F33/D$24 -> 115 | F33: =+SUM(START:END!F33) -> 24725 | H33: =I33/G$24 -> #DIV/0! | I33: =+SUM(START:END!I33) -> 0 | K33: =IF(L33=0,0,L33/J$24) -> 98.449515 | L33: =+SUM(START:END!L33) -> 16244.17 | N33: =L33-F33 -> -8480.83 | P33: =IF(Q33=0,0,Q33/O$24) -> 157.53769 | Q33: =+SUM(START:END!Q33) -> 19062.06 | S33: =L33-Q33 -> -2817.89
A34: =+B34&C34 -> Véhicules neufsService gratuit 1 | B34: =+$K$1 -> Véhicules neufs | C34: Service gratuit 1 | E34: =F34/D$24 -> 10 | F34: =+SUM(START:END!F34) -> 2150 | H34: =I34/G$24 -> #DIV/0! | I34: =+SUM(START:END!I34) -> 0 | K34: =IF(L34=0,0,L34/J$24) -> 3.3441818 | L34: =+SUM(START:END!L34) -> 551.79 | N34: =L34-F34 -> -1598.21 | P34: =IF(Q34=0,0,Q34/O$24) -> 47.640496 | Q34: =+SUM(START:END!Q34) -> 5764.5 | S34: =L34-Q34 -> -5212.71
A35: =+B35&C35 -> Véhicules neufsEntretien stock | B35: =+$K$1 -> Véhicules neufs | C35: Entretien stock | E35: =F35/D$24 -> 120.75 | F35: =+SUM(START:END!F35) -> 25961.25 | H35: =I35/G$24 -> #DIV/0! | I35: =+SUM(START:END!I35) -> 0 | K35: =IF(L35=0,0,L35/J$24) -> 119.71527 | L35: =+SUM(START:END!L35) -> 19753.02 | N35: =L35-F35 -> -6208.23 | P35: =IF(Q35=0,0,Q35/O$24) -> 158.87983 | Q35: =+SUM(START:END!Q35) -> 19224.46 | S35: =L35-Q35 -> 528.56
A36: =+B36&C36 -> Véhicules neufsPublicité 1 | B36: =+$K$1 -> Véhicules neufs | C36: Publicité 1 | E36: =F36/D$24 -> 115.74884 | F36: =+SUM(START:END!F36) -> 24886 | H36: =I36/G$24 -> #DIV/0! | I36: =+SUM(START:END!I36) -> 0 | K36: =IF(L36=0,0,L36/J$24) -> 166.23073 | L36: =+SUM(START:END!L36) -> 27428.07 | N36: =L36-F36 -> 2542.07 | P36: =IF(Q36=0,0,Q36/O$24) -> 342.80653 | Q36: =+SUM(START:END!Q36) -> 41479.59 | S36: =L36-Q36 -> -14051.52
A37: =+B37&C37 -> Véhicules neufsIntérêt de gros | B37: =+$K$1 -> Véhicules neufs | C37: Intérêt de gros | E37: =F37/D$24 -> 514.75141 | F37: =+SUM(START:END!F37) -> 110671.55 | H37: =I37/G$24 -> #DIV/0! | I37: =+SUM(START:END!I37) -> 0 | K37: =IF(L37=0,0,L37/J$24) -> 393.62709 | L37: =+SUM(START:END!L37) -> 64948.47 | N37: =L37-F37 -> -45723.082 | P37: =IF(Q37=0,0,Q37/O$24) -> -117.72405 | Q37: =+SUM(START:END!Q37) -> -14244.61 | S37: =L37-Q37 -> 79193.08
A38: =+B38&C38 -> Véhicules neufs[...] | B38: =+$K$1 -> Véhicules neufs | C38: [...] | E38: =F38/D$24 -> 0 | F38: =+SUM(START:END!F38) -> 0 | H38: =I38/G$24 -> #DIV/0! | I38: =+SUM(START:END!I38) -> 0 | K38: =IF(L38=0,0,L38/J$24) -> 0 | L38: =+SUM(START:END!L38) -> 0 | N38: =L38-I38 -> 0 | P38: =IF(Q38=0,0,Q38/O$24) -> 0 | Q38: =+SUM(START:END!Q38) -> 0 | S38: =L38-Q38 -> 0
A39: =+B39&C39 -> Véhicules neufs[...] | B39: =+$K$1 -> Véhicules neufs | C39: [...] | E39: =F39/D$24 -> 0 | F39: =+SUM(START:END!F39) -> 0 | H39: =I39/G$24 -> #DIV/0! | I39: =+SUM(START:END!I39) -> 0 | K39: =IF(L39=0,0,L39/J$24) -> 0 | L39: =+SUM(START:END!L39) -> 0 | N39: =L39-I39 -> 0 | P39: =IF(Q39=0,0,Q39/O$24) -> 0 | Q39: =+SUM(START:END!Q39) -> 0 | S39: =L39-Q39 -> 0
A40: =+B40&C40 -> Véhicules neufs[...] | B40: =+$K$1 -> Véhicules neufs | C40: [...] | E40: =F40/D$24 -> 0 | F40: =+SUM(START:END!F40) -> 0 | H40: =I40/G$24 -> #DIV/0! | I40: =+SUM(START:END!I40) -> 0 | K40: =IF(L40=0,0,L40/J$24) -> 0 | L40: =+SUM(START:END!L40) -> 0 | N40: =L40-I40 -> 0 | P40: =IF(Q40=0,0,Q40/O$24) -> 0 | Q40: =+SUM(START:END!Q40) -> 0 | S40: =L40-Q40 -> 0
A41: =+B41&C41 -> Véhicules neufsTOTAL VARIABLES | B41: =+$K$1 -> Véhicules neufs | C41: TOTAL VARIABLES | D41: % brut | E41: =F41/F$27 -> 0.55291358 | F41: =SUM(F31:F40) -> 407840.63 | G41: % brut | H41: =I41/I$27 -> #DIV/0! | I41: =SUM(I31:I40) -> 0 | J41: % brut | K41: =L41/L$27 -> 0.54515467 | L41: =SUM(L31:L40) -> 278338.22 | N41: =SUM(N31:N40) -> -129502.41 | O41: % brut | P41: =Q41/Q$27 -> 0.48173193 | Q41: =SUM(Q31:Q40) -> 182921.24 | S41: =L41-Q41 -> 95416.98
A42: =+B42&C42 -> Véhicules neufsSalaires cadres | B42: =+$K$1 -> Véhicules neufs | C42: Salaires cadres | F42: =+SUM(START:END!F42) -> 77393.513 | I42: =+SUM(START:END!I42) -> 0 | L42: =+SUM(START:END!L42) -> 51077.44 | N42: =L42-F42 -> -26316.073 | Q42: =+SUM(START:END!Q42) -> 52366.83
A43: =+B43&C43 -> Véhicules neufsSalaires commis | B43: =+$K$1 -> Véhicules neufs | C43: Salaires commis | F43: =+SUM(START:END!F43) -> 44976.212 | I43: =+SUM(START:END!I43) -> 0 | L43: =+SUM(START:END!L43) -> 48329.27 | N43: =L43-F43 -> 3353.058 | Q43: =+SUM(START:END!Q43) -> 30835.88 | S43: =L43-Q43 -> 17493.39
A44: =+B44&C44 -> Véhicules neufsSalaires autres | B44: =+$K$1 -> Véhicules neufs | C44: Salaires autres | F44: =+SUM(START:END!F44) -> 1025.55 | I44: =+SUM(START:END!I44) -> 0 | L44: =+SUM(START:END!L44) -> 3533.95 | N44: =L44-F44 -> 2508.4 | Q44: =+SUM(START:END!Q44) -> 9321.24 | S44: =L44-Q44 -> -5787.29
A45: =+B45&C45 -> Véhicules neufsSalaires spécialistes | B45: =+$K$1 -> Véhicules neufs | C45: Salaires spécialistes | F45: =+SUM(START:END!F45) -> 0 | I45: =+SUM(START:END!I45) -> 0 | L45: =+SUM(START:END!L45) -> 0 | N45: =L45-F45 -> 0 | Q45: =+SUM(START:END!Q45) -> 0 | S45: =L45-Q45 -> 0
A46: =+B46&C46 -> Véhicules neufs[...] | B46: =+$K$1 -> Véhicules neufs | C46: [...] | F46: =+SUM(START:END!F46) -> 0 | I46: =+SUM(START:END!I46) -> 0 | L46: =+SUM(START:END!L46) -> 0 | N46: =L46-F46 -> 0 | Q46: =+SUM(START:END!Q46) -> 0 | S46: =L46-Q46 -> 0
A47: =+B47&C47 -> Véhicules neufs[...] | B47: =+$K$1 -> Véhicules neufs | C47: [...] | F47: =+SUM(START:END!F47) -> 0 | I47: =+SUM(START:END!I47) -> 0 | L47: =+SUM(START:END!L47) -> 0 | N47: =L47-F47 -> 0 | Q47: =+SUM(START:END!Q47) -> 0 | S47: =L47-Q47 -> 0
A48: =+B48&C48 -> Véhicules neufs[...] | B48: =+$K$1 -> Véhicules neufs | C48: [...] | F48: =+SUM(START:END!F48) -> 0 | I48: =+SUM(START:END!I48) -> 0 | L48: =+SUM(START:END!L48) -> 0 | N48: =L48-F48 -> 0 | Q48: =+SUM(START:END!Q48) -> 0 | S48: =L48-Q48 -> 0
A49: =+B49&C49 -> Véhicules neufsSalaires en absences | B49: =+$K$1 -> Véhicules neufs | C49: Salaires en absences | F49: =+SUM(START:END!F49) -> 37234.098 | I49: =+SUM(START:END!I49) -> 0 | L49: =+SUM(START:END!L49) -> 34992.24 | N49: =L49-F49 -> -2241.8582 | Q49: =+SUM(START:END!Q49) -> 31124.08 | S49: =L49-Q49 -> 3868.16
A50: =+B50&C50 -> Véhicules neufsDéduction à la source | B50: =+$K$1 -> Véhicules neufs | C50: Déduction à la source | F50: =+SUM(START:END!F50) -> 45271.415 | I50: =+SUM(START:END!I50) -> 0 | L50: =+SUM(START:END!L50) -> 42118.21 | N50: =L50-F50 -> -3153.2046 | Q50: =+SUM(START:END!Q50) -> 37824.34 | S50: =L50-Q50 -> 4293.87
A51: =+B51&C51 -> Véhicules neufsBénéfices marginaux | B51: =+$K$1 -> Véhicules neufs | C51: Bénéfices marginaux | F51: =+SUM(START:END!F51) -> 23324.62 | I51: =+SUM(START:END!I51) -> 0 | L51: =+SUM(START:END!L51) -> 22867.25 | N51: =L51-F51 -> -457.37011 | Q51: =+SUM(START:END!Q51) -> 11323.66 | S51: =L51-Q51 -> 11543.59
A52: =+B52&C52 -> Véhicules neufsCsst | B52: =+$K$1 -> Véhicules neufs | C52: Csst | F52: =+SUM(START:END!F52) -> 10169.666 | I52: =+SUM(START:END!I52) -> 0 | L52: =+SUM(START:END!L52) -> 7050.78 | N52: =L52-F52 -> -3118.8856 | Q52: =+SUM(START:END!Q52) -> 5653.92 | S52: =L52-Q52 -> 1396.86
A53: =+B53&C53 -> Véhicules neufs[...] | B53: =+$K$1 -> Véhicules neufs | C53: [...] | F53: =+SUM(START:END!F53) -> 0 | I53: =+SUM(START:END!I53) -> 0 | L53: =+SUM(START:END!L53) -> 0 | N53: =L53-I53 -> 0 | Q53: =+SUM(START:END!Q53) -> 0 | S53: =L53-Q53 -> 0
A54: =+B54&C54 -> Véhicules neufsTOTAL PERSONNEL | B54: =+$K$1 -> Véhicules neufs | C54: TOTAL PERSONNEL | D54: % brut | E54: =F54/F$27 -> 0.32455027 | F54: =+SUM(F42:F53) -> 239395.07 | G54: % brut | H54: =I54/I$27 -> #DIV/0! | I54: =+SUM(I42:I53) -> 0 | J54: % brut | K54: =L54/L$27 -> 0.41124664 | L54: =+SUM(L42:L53) -> 209969.14 | N54: =+SUM(N42:N53) -> -29425.933 | O54: % brut | P54: =Q54/Q$27 -> 0.46995657 | Q54: =+SUM(Q42:Q53) -> 178449.95 | S54: =+SUM(S42:S53) -> 32808.58
A55: =+B55&C55 -> Véhicules neufsPublicité 2 | B55: =+$K$1 -> Véhicules neufs | C55: Publicité 2 | F55: =+SUM(START:END!F55) -> 0 | I55: =+SUM(START:END!I55) -> 0 | L55: =+SUM(START:END!L55) -> 0 | N55: =L55-F55 -> 0 | Q55: =+SUM(START:END!Q55) -> 0 | S55: =L55-Q55 -> 0
A56: =+B56&C56 -> Véhicules neufsService gratuit 2 | B56: =+$K$1 -> Véhicules neufs | C56: Service gratuit 2 | F56: =+SUM(START:END!F56) -> 0 | I56: =+SUM(START:END!I56) -> 0 | L56: =+SUM(START:END!L56) -> 0 | N56: =L56-F56 -> 0 | Q56: =+SUM(START:END!Q56) -> 0 | S56: =L56-Q56 -> 0
A57: =+B57&C57 -> Véhicules neufsFrais véhicules de cie | B57: =+$K$1 -> Véhicules neufs | C57: Frais véhicules de cie | F57: =+SUM(START:END!F57) -> 26857.644 | I57: =+SUM(START:END!I57) -> 0 | L57: =+SUM(START:END!L57) -> 26778.66 | N57: =L57-F57 -> -78.9838 | Q57: =+SUM(START:END!Q57) -> 28844.14 | S57: =L57-Q57 -> -2065.48
A58: =+B58&C58 -> Véhicules neufsInformatique | B58: =+$K$1 -> Véhicules neufs | C58: Informatique | F58: =+SUM(START:END!F58) -> 23882.984 | I58: =+SUM(START:END!I58) -> 0 | L58: =+SUM(START:END!L58) -> 24605.63 | N58: =L58-F58 -> 722.64572 | Q58: =+SUM(START:END!Q58) -> 21883.84 | S58: =L58-Q58 -> 2721.79
A59: =+B59&C59 -> Véhicules neufsFrais de déplacement | B59: =+$K$1 -> Véhicules neufs | C59: Frais de déplacement | F59: =+SUM(START:END!F59) -> 3800.0925 | I59: =+SUM(START:END!I59) -> 0 | L59: =+SUM(START:END!L59) -> 5988.46 | N59: =L59-F59 -> 2188.3675 | Q59: =+SUM(START:END!Q59) -> 5836.41 | S59: =L59-Q59 -> 152.05
A60: =+B60&C60 -> Véhicules neufsServices extérieurs | B60: =+$K$1 -> Véhicules neufs | C60: Services extérieurs | F60: =+SUM(START:END!F60) -> 21647.222 | I60: =+SUM(START:END!I60) -> 0 | L60: =+SUM(START:END!L60) -> 27978.36 | N60: =L60-F60 -> 6331.1378 | Q60: =+SUM(START:END!Q60) -> 22830.12 | S60: =L60-Q60 -> 5148.24
A61: =+B61&C61 -> Véhicules neufsFournitures autres | B61: =+$K$1 -> Véhicules neufs | C61: Fournitures autres | F61: =+SUM(START:END!F61) -> 291.772 | I61: =+SUM(START:END!I61) -> 0 | L61: =+SUM(START:END!L61) -> 0 | N61: =L61-F61 -> -291.772 | Q61: =+SUM(START:END!Q61) -> 176.44 | S61: =L61-Q61 -> -176.44
A62: =+B62&C62 -> Véhicules neufsUniformes | B62: =+$K$1 -> Véhicules neufs | C62: Uniformes | F62: =+SUM(START:END!F62) -> 85 | I62: =+SUM(START:END!I62) -> 0 | L62: =+SUM(START:END!L62) -> 0 | N62: =L62-F62 -> -85 | Q62: =+SUM(START:END!Q62) -> 434.88 | S62: =L62-Q62 -> -434.88
A63: =+B63&C63 -> Véhicules neufsPapeterie | B63: =+$K$1 -> Véhicules neufs | C63: Papeterie | F63: =+SUM(START:END!F63) -> 2224.2927 | I63: =+SUM(START:END!I63) -> 0 | L63: =+SUM(START:END!L63) -> 1789.39 | N63: =L63-F63 -> -434.90268 | Q63: =+SUM(START:END!Q63) -> 2702.08 | S63: =L63-Q63 -> -912.69
A64: =+B64&C64 -> Véhicules neufsTéléphone | B64: =+$K$1 -> Véhicules neufs | C64: Téléphone | F64: =+SUM(START:END!F64) -> 1034.406 | I64: =+SUM(START:END!I64) -> 0 | L64: =+SUM(START:END!L64) -> 1168.72 | N64: =L64-F64 -> 134.31405 | Q64: =+SUM(START:END!Q64) -> 1073.56 | S64: =L64-Q64 -> 95.16
A65: =+B65&C65 -> Véhicules neufsFrais postaux | B65: =+$K$1 -> Véhicules neufs | C65: Frais postaux | F65: =+SUM(START:END!F65) -> 308.46719 | I65: =+SUM(START:END!I65) -> 0 | L65: =+SUM(START:END!L65) -> 339.02 | N65: =L65-F65 -> 30.552814 | Q65: =+SUM(START:END!Q65) -> 106.17 | S65: =L65-Q65 -> 232.85
A66: =+B66&C66 -> Véhicules neufsDivers | B66: =+$K$1 -> Véhicules neufs | C66: Divers | F66: =+SUM(START:END!F66) -> 603.51116 | I66: =+SUM(START:END!I66) -> 0 | L66: =+SUM(START:END!L66) -> 1208.69 | N66: =L66-F66 -> 605.17884 | Q66: =+SUM(START:END!Q66) -> 776.91 | S66: =L66-Q66 -> 431.78
... A68: =+B68&C68 -> Véhicules neufsFrais bancaires | B68: =+$K$1 -> Véhicules neufs | C68: Frais bancaires | F68: =+SUM(START:END!F68) -> 12342.474 | I68: =+SUM(START:END!I68) -> 0 | L68: =+SUM(START:END!L68) -> 14989.81 | N68: =L68-F68 -> 2647.3361 | Q68: =+SUM(START:END!Q68) -> 15688.78 | S68: =L68-Q68 -> -698.97
A69: =+B69&C69 -> Véhicules neufs[...] | B69: =+$K$1 -> Véhicules neufs | C69: [...] | F69: =+SUM(START:END!F69) -> 0 | I69: =+SUM(START:END!I69) -> 0 | L69: =+SUM(START:END!L69) -> 0 | N69: =L69-I69 -> 0 | Q69: =+SUM(START:END!Q69) -> 0 | S69: =L69-Q69 -> 0
A70: =+B70&C70 -> Véhicules neufs[...] | B70: =+$K$1 -> Véhicules neufs | C70: [...] | F70: =+SUM(START:END!F70) -> 0 | I70: =+SUM(START:END!I70) -> 0 | L70: =+SUM(START:END!L70) -> 0 | N70: =L70-I70 -> 0 | Q70: =+SUM(START:END!Q70) -> 0 | S70: =L70-Q70 -> 0
A71: =+B71&C71 -> Véhicules neufs[...] | B71: =+$K$1 -> Véhicules neufs | C71: [...] | F71: =+SUM(START:END!F71) -> 0 | I71: =+SUM(START:END!I71) -> 0 | L71: =+SUM(START:END!L71) -> 0 | N71: =L71-I71 -> 0 | Q71: =+SUM(START:END!Q71) -> 0 | S71: =L71-Q71 -> 0
A72: =+B72&C72 -> Véhicules neufsTOTAL SEMI-FIXES | B72: =+$K$1 -> Véhicules neufs | C72: TOTAL SEMI-FIXES | D72: % brut | E72: =F72/F$27 -> 0.13405529 | F72: =+SUM(F55:F71) -> 98881.984 | G72: % brut | H72: =I72/I$27 -> #DIV/0! | I72: =+SUM(I55:I71) -> 0 | J72: % brut | K72: =L72/L$27 -> 0.20787431 | L72: =+SUM(L55:L71) -> 106133.85 | N72: =+SUM(N55:N71) -> 7251.8656 | O72: % brut | P72: =Q72/Q$27 -> 0.27548975 | Q72: =+SUM(Q55:Q71) -> 104607.82 | S72: =+SUM(S55:S71) -> 1526.03
A73: =+B73&C73 -> Véhicules neufs | B73: =+$K$1 -> Véhicules neufs
A74: =+B74&C74 -> Véhicules neufsTOTAL DES DÉPENSES | B74: =+$K$1 -> Véhicules neufs | C74: TOTAL DES DÉPENSES | D74: % brut | E74: =F74/F$27 -> 1.0115191 | F74: =F41+F54+F72 -> 746117.69 | G74: % brut | H74: =I74/I$27 -> #DIV/0! | I74: =I41+I54+I72 -> 0 | J74: % brut | K74: =L74/L$27 -> 1.1642756 | L74: =L41+L54+L72 -> 594441.21 | N74: =N41+N54+N72 -> -151676.48 | O74: % brut | P74: =Q74/Q$27 -> 1.2271783 | Q74: =Q41+Q54+Q72 -> 465979.01 | S74: =L74-Q74 -> 128462.2
A75: =+B75&C75 -> Véhicules neufsProgramme neuf 1 | B75: =+$K$1 -> Véhicules neufs | C75: Programme neuf 1 | F75: =+SUM(START:END!F75) -> 25000 | I75: =+SUM(START:END!I75) -> 0 | L75: =+SUM(START:END!L75) -> 56650 | N75: =L75-F75 -> 31650 | Q75: =+SUM(START:END!Q75) -> 32500
A76: =+B76&C76 -> Véhicules neufsProgramme neuf 2 | B76: =+$K$1 -> Véhicules neufs | C76: Programme neuf 2 | F76: =+SUM(START:END!F76) -> 0 | I76: =+SUM(START:END!I76) -> 0 | L76: =+SUM(START:END!L76) -> 0 | N76: =L76-F76 -> 0 | Q76: =+SUM(START:END!Q76) -> 0 | S76: =L76-Q76 -> 0
A77: =+B77&C77 -> Véhicules neufsProgramme neuf 3 | B77: =+$K$1 -> Véhicules neufs | C77: Programme neuf 3 | F77: =+SUM(START:END!F77) -> 0 | I77: =+SUM(START:END!I77) -> 0 | L77: =+SUM(START:END!L77) -> 0 | N77: =L77-F77 -> 0 | Q77: =+SUM(START:END!Q77) -> 0 | S77: =L77-Q77 -> 0
A78: =+B78&C78 -> Véhicules neufsHoldbacks | B78: =+$K$1 -> Véhicules neufs | C78: Holdbacks | F78: =+SUM(START:END!F78) -> 309091.51 | I78: =+SUM(START:END!I78) -> 0 | L78: =+SUM(START:END!L78) -> 229545 | N78: =L78-F78 -> -79546.514 | Q78: =+SUM(START:END!Q78) -> 175923.85 | S78: =L78-Q78 -> 53621.15
A79: =+B79&C79 -> Véhicules neufs[...] | B79: =+$K$1 -> Véhicules neufs | C79: [...] | F79: =+SUM(START:END!F79) -> 0 | I79: =+SUM(START:END!I79) -> 0 | L79: =+SUM(START:END!L79) -> 0 | N79: =L79-F79 -> 0 | Q79: =+SUM(START:END!Q79) -> 0 | S79: =L79-Q79 -> 0
A80: =+B80&C80 -> Véhicules neufs[...] | B80: =+$K$1 -> Véhicules neufs | C80: [...] | F80: =+SUM(START:END!F80) -> 0 | I80: =+SUM(START:END!I80) -> 0 | L80: =+SUM(START:END!L80) -> 0 | N80: =L80-F80 -> 0 | Q80: =+SUM(START:END!Q80) -> 0 | S80: =L80-Q80 -> 0
A81: =+B81&C81 -> Véhicules neufs[...] | B81: =+$K$1 -> Véhicules neufs | C81: [...] | F81: =+SUM(START:END!F81) -> 0 | I81: =+SUM(START:END!I81) -> 0 | L81: =+SUM(START:END!L81) -> 0 | N81: =L81-F81 -> 0 | Q81: =+SUM(START:END!Q81) -> 0 | S81: =L81-Q81 -> 0
A82: =+B82&C82 -> Véhicules neufsFrais administration | B82: =+$K$1 -> Véhicules neufs | C82: Frais administration | F82: =+SUM(START:END!F82) -> 101920.75 | I82: =+SUM(START:END!I82) -> 0 | L82: =+SUM(START:END!L82) -> 75714 | N82: =L82-F82 -> -26206.75 | Q82: =+SUM(START:END!Q82) -> 57657 | S82: =L82-Q82 -> 18057
A83: =+B83&C83 -> Véhicules neufsAUTRES REVENUS | B83: =+$K$1 -> Véhicules neufs | C83: AUTRES REVENUS | F83: =+SUM(F75:F82) -> 436012.26 | I83: =+SUM(I75:I82) -> 0 | L83: =+SUM(L75:L82) -> 361909 | N83: =+SUM(N75:N82) -> -74103.264 | Q83: =+SUM(Q75:Q82) -> 266080.85 | S83: =+SUM(S75:S82) -> 71678.15
A84: =+B84&C84 -> Véhicules neufs | B84: =+$K$1 -> Véhicules neufs
A85: =+B85&C85 -> Véhicules neufsPROFIT DÉPARTEMENTAL | B85: =+$K$1 -> Véhicules neufs | C85: PROFIT DÉPARTEMENTAL | F85: =F27-F74+F83 -> 427515.51 | I85: =I27-I74+I83 -> 0 | L85: =L27-L74+L83 -> 278035.22 | N85: =N27-N74+N83 -> -149480.29 | Q85: =Q27-Q74+Q83 -> 179817.67 | S85: =S27-S41-S54-S72+S83 -> 72778.16
F86: =+F85-#REF!-#REF!-#REF! -> #REF! | L86: =L85/F85 -> 0.65035119 | N86: =+N85-#REF!-#REF!-#REF! -> #REF! | Q86: =+Q85-#REF!-#REF!-#REF! -> #REF! | S86: =+S85-#REF!-#REF!-#REF! -> #REF!
C89: =C1 -> Conso | K89: Véhicules usagés | S89: =$S$1 -> Réalisé
D91: BUDGET ORIGINAL | G91: BUDGET RÉVISÉ | J91: RÉALISATION | M91: ÉCART réel / original | O91: ANNÉE PRÉCÉDENTE | R91: ÉCART réel / année précédente
D92: UNITE | E92: $P/UNITÉ | F92: $PROFITS | G92: UNITE | H92: $P/UNITÉ | I92: $PROFITS | J92: UNITE | K92: $P/UNITE | L92: $PROFITS | M92: UNITÉ | N92: $PROFITS | O92: UNITE | P92: $P/UNITE | Q92: $PROFITS | R92: UNITE | S92: $PROFITS
A93: =+B93&C93 -> Véhicules usagésVentes nettes | B93: Véhicules usagés | C93: Ventes nettes | F93: =+SUM(START:END!F93) -> 5554122.9 | I93: =+SUM(START:END!I93) -> 0 | L93: =+SUM(START:END!L93) -> 4629658.6 | Q93: =+SUM(START:END!Q93) -> 3170589.9
A94: =+B94&C94 -> Véhicules usagésCertifié | B94: Véhicules usagés | C94: Certifié | D94: =+SUM(START:END!D94) -> 80 | E94: =IF(D94=0,0,F94/D94) -> 1400 | F94: =+SUM(START:END!F94) -> 112000 | G94: =+SUM(START:END!G94) -> 0 | H94: =IF(G94=0,0,I94/G94) -> 0 | I94: =+SUM(START:END!I94) -> 0 | J94: =+SUM(START:END!J94) -> 64 | K94: =IF(J94=0,0,L94/J94) -> 1467.5927 | L94: =+SUM(START:END!L94) -> 93925.93 | M94: =J94-D94 -> -16 | N94: =L94-F94 -> -18074.07 | O94: =+SUM(START:END!O94) -> 84 | P94: =IF(O94=0,0,Q94/O94) -> 1254.9132 | Q94: =+SUM(START:END!Q94) -> 105412.71 | R94: =J94-O94 -> -20 | S94: =L94-Q94 -> -11486.78
A95: =+B95&C95 -> Véhicules usagésNon Certifié | B95: Véhicules usagés | C95: Non Certifié | D95: =+SUM(START:END!D95) -> 10 | E95: =IF(D95=0,0,F95/D95) -> 1800 | F95: =+SUM(START:END!F95) -> 18000 | G95: =+SUM(START:END!G95) -> 0 | H95: =IF(G95=0,0,I95/G95) -> 0 | I95: =+SUM(START:END!I95) -> 0 | J95: =+SUM(START:END!J95) -> 0 | K95: =IF(J95=0,0,L95/J95) -> 0 | L95: =+SUM(START:END!L95) -> -556.43 | M95: =J95-D95 -> -10 | N95: =L95-F95 -> -18556.43 | O95: =+SUM(START:END!O95) -> 5 | P95: =IF(O95=0,0,Q95/O95) -> -1216.644 | Q95: =+SUM(START:END!Q95) -> -6083.22 | R95: =J95-O95 -> -5 | S95: =L95-Q95 -> 5526.79
A96: =+B96&C96 -> Véhicules usagésAutres marques | B96: Véhicules usagés | C96: Autres marques | D96: =+SUM(START:END!D96) -> 13 | E96: =IF(D96=0,0,F96/D96) -> 1500 | F96: =+SUM(START:END!F96) -> 19500 | G96: =+SUM(START:END!G96) -> 0 | H96: =IF(G96=0,0,I96/G96) -> 0 | I96: =+SUM(START:END!I96) -> 0 | J96: =+SUM(START:END!J96) -> 1 | K96: =IF(J96=0,0,L96/J96) -> 4147.3 | L96: =+SUM(START:END!L96) -> 4147.3 | M96: =J96-D96 -> -12 | N96: =L96-F96 -> -15352.7 | O96: =+SUM(START:END!O96) -> 7 | P96: =IF(O96=0,0,Q96/O96) -> 2177 | Q96: =+SUM(START:END!Q96) -> 15239 | R96: =J96-O96 -> -6 | S96: =L96-Q96 -> -11091.7
A97: =+B97&C97 -> Véhicules usagésTotal Usagés | B97: Véhicules usagés | C97: Total Usagés | D97: =+D95+D94+D96 -> 103 | E97: =IF(D97=0,0,F97/D97) -> 1451.4563 | F97: =+F94+F95+F96 -> 149500 | G97: =+G95+G94+G96 -> 0 | H97: =IF(G97=0,0,I97/G97) -> 0 | I97: =+I94+I95+I96 -> 0 | J97: =+J95+J94+J96 -> 65 | K97: =IF(J97=0,0,L97/J97) -> 1500.2585 | L97: =+L94+L95+L96 -> 97516.8 | M97: =+M95+M94+M96 -> -38 | N97: =+N94+N95+N96 -> -51983.2 | O97: =+O95+O94+O96 -> 96 | P97: =IF(O97<=0,0,Q97/O97) -> 1193.4218 | Q97: =+Q94+Q95+Q96 -> 114568.49 | R97: =R94+R95+R96 -> -31 | S97: =S94+S95+S96 -> -17051.69
A98: =+B98&C98 -> Véhicules usagés | B98: Véhicules usagés | E98: =IF(D98=0,0,F98/D98) -> 0 | H98: =IF(G98=0,0,I98/G98) -> 0 | M98: =D97/D97 -> 1 | N98: =N97/F97 -> -0.34771371 | R98: =R97/O97 -> -0.32291667 | S98: =IF(Q97=0,0,(S97/Q97)) -> -0.14883403
A99: =+B99&C99 -> Véhicules usagésUS | B99: Véhicules usagés | C99: US | D99: =+SUM(START:END!D99) -> 0 | E99: =IF(D99=0,0,F99/D99) -> 0 | F99: =+SUM(START:END!F99) -> 0 | G99: =+SUM(START:END!G99) -> 0 | H99: =IF(G99=0,0,I99/G99) -> 0 | I99: =+SUM(START:END!I99) -> 0 | J99: =+SUM(START:END!J99) -> 0 | K99: =IF(J99=0,0,L99/J99) -> 0 | L99: =+SUM(START:END!L99) -> 0 | M99: =J99-D99 -> 0 | N99: =L99-F99 -> 0 | O99: =+SUM(START:END!O99) -> 0 | P99: =IF(O99=0,0,Q99/O99) -> 0 | Q99: =+SUM(START:END!Q99) -> 0
A100: =+B100&C100 -> Véhicules usagésVentes au Gros | B100: Véhicules usagés | C100: Ventes au Gros | D100: =+SUM(START:END!D100) -> 119 | E100: =IF(D100=0,0,F100/D100) -> 400 | F100: =+SUM(START:END!F100) -> 47600 | G100: =+SUM(START:END!G100) -> 0 | H100: =IF(G100=0,0,I100/G100) -> 0 | I100: =+SUM(START:END!I100) -> 0 | J100: =+SUM(START:END!J100) -> 137 | K100: =IF(J100=0,0,L100/J100) -> -80.515985 | L100: =+SUM(START:END!L100) -> -11030.69 | M100: =J100-D100 -> 18 | N100: =L100-F100 -> -58630.69 | O100: =+SUM(START:END!O100) -> 64 | P100: =IF(O100=0,0,Q100/O100) -> 9.3240625 | Q100: =+SUM(START:END!Q100) -> 596.74 | R100: =J100-O100 -> 73 | S100: =L100-Q100 -> -11627.43
A101: =+B101&C101 -> Véhicules usagés | B101: Véhicules usagés
A102: =+B102&C102 -> Véhicules usagésRev. Finances | B102: Véhicules usagés | C102: Rev. Finances | D102: =+SUM(START:END!D102) -> 0 | E102: =IF(D102=0,0,F102/D102) -> 0 | F102: =+SUM(START:END!F102) -> 61800 | G102: =+SUM(START:END!G102) -> 0 | H102: =IF(G102=0,0,I102/G102) -> 0 | I102: =+SUM(START:END!I102) -> 0 | J102: =+SUM(START:END!J102) -> 0 | K102: =IF(J102=0,0,L102/J102) -> 0 | L102: =+SUM(START:END!L102) -> 8191.87 | M102: =J102-G102 -> 0 | N102: =L102-F102 -> -53608.13 | O102: =+SUM(START:END!O102) -> 0 | P102: =IF(O102=0,0,Q102/O102) -> 0 | Q102: =+SUM(START:END!Q102) -> 29057.01 | R102: =J102-O102 -> 0 | S102: =L102-Q102 -> -20865.14
A103: =+B103&C103 -> Véhicules usagésRev. Protections | B103: Véhicules usagés | C103: Rev. Protections | D103: =+SUM(START:END!D103) -> 0 | E103: =IF(D103=0,0,F103/D103) -> 0 | F103: =+SUM(START:END!F103) -> 128750 | G103: =+SUM(START:END!G103) -> 0 | H103: =IF(G103=0,0,I103/G103) -> 0 | I103: =+SUM(START:END!I103) -> 0 | J103: =+SUM(START:END!J103) -> 0 | K103: =IF(J103=0,0,L103/J103) -> 0 | L103: =+SUM(START:END!L103) -> 125622.32 | M103: =J103-G103 -> 0 | N103: =L103-F103 -> -3127.68 | O103: =+SUM(START:END!O103) -> 0 | P103: =IF(O103=0,0,Q103/O103) -> 0 | Q103: =+SUM(START:END!Q103) -> 138631.75 | R103: =J103-O103 -> 0 | S103: =L103-Q103 -> -13009.43
A104: =+B104&C104 -> Véhicules usagésRev. Autres | B104: Véhicules usagés | C104: Rev. Autres | D104: =+SUM(START:END!D104) -> 0 | E104: =IF(D104=0,0,F104/D104) -> 0 | F104: =+SUM(START:END!F104) -> 5150 | G104: =+SUM(START:END!G104) -> 0 | H104: =IF(G104=0,0,I104/G104) -> 0 | I104: =+SUM(START:END!I104) -> 0 | J104: =+SUM(START:END!J104) -> 0 | K104: =IF(J104=0,0,L104/J104) -> 0 | L104: =+SUM(START:END!L104) -> 1965.4 | M104: =J104-G104 -> 0 | N104: =L104-F104 -> -3184.6 | O104: =+SUM(START:END!O104) -> 0 | P104: =IF(O104=0,0,Q104/O104) -> 0 | Q104: =+SUM(START:END!Q104) -> 1705.68 | R104: =J104-O104 -> 0 | S104: =L104-Q104 -> 259.72
...

Sheet START

Sheet 2025-10
C1: Volks | K1: Véhicules neufs | S1: Réalisé, Octobre 2025
D2: X | E2: O | F2: U | J2: NB | L2: $ | O2: X | P2: O | Q2: U | V2: *** NE PAS EFFACER / Pour An Précédente ***
D3: BUDGET ORIGINAL | J3: RÉALISATION | M3: ÉCART réel / Budget | O3: ANNÉE PRÉCÉDENTE | R3: ECART (réel/ Ann.Préc.) | V3: NEUF | W3: 0.45
D4: UNITE | E4: $P/UNITÉ | F4: $PROFITS | J4: UNITÉS | K4: $P/UNITE | L4: $PROFITS | M4: UNITÉS | N4: $PROFITS | O4: UNITE | P4: $P/UNITÉ | Q4: $PROFITS | R4: UNITÉS | S4: $PROFITS | V4: USAGE | W4: 0.1
A5: Véhicules neufsVentes nettes | B5: Véhicules neufs | C5: Ventes nettes | F5: 3781098.2 | L5: 2861489.8 | Q5: 2470114 | V5: SERVICE | W5: 0.225
A6: Véhicules neufsAutos détail | B6: Véhicules neufs | C6: Autos détail | D6: 19 | E6: 1953.6492 | F6: 37119.334 | J6: 11 | K6: 1392.1182 | L6: 15313.3 | M6: -8 | N6: -21806.034 | O6: 12 | P6: 1802.2583 | Q6: 21627.1 | R6: -1 | S6: -6313.8 | V6: CARROSSERIE | W6: 0.025
A7: Véhicules neufsCamions détail | B7: Véhicules neufs | C7: Camions détail | D7: 50 | E7: 2435.9047 | F7: 121795.23 | J7: 37 | K7: 2420.7516 | L7: 89567.81 | M7: -13 | N7: -32227.424 | O7: 32 | P7: 1508.5388 | Q7: 48273.24 | R7: 5 | S7: 41294.57 | V7: PIECES | W7: 0.2
A8: Véhicules neufsSprinter | B8: Véhicules neufs | C8: Sprinter | D8: 0 | E8: 0 | F8: 0 | J8: 0 | K8: 0 | L8: 0 | M8: 0 | N8: 0 | O8: 0 | P8: 0 | Q8: 0 | R8: 0 | S8: 0 | W8: 1
A9: Véhicules neufsMoto détail | B9: Véhicules neufs | C9: Moto détail | D9: 0 | E9: 0 | F9: 0 | J9: 0 | K9: 0 | L9: 0 | M9: 0 | N9: 0 | O9: 0 | P9: 0 | Q9: 0 | R9: 0 | S9: 0
A10: Véhicules neufs[...] | B10: Véhicules neufs | C10: [...] | D10: 0 | E10: 0 | F10: 0 | J10: 0 | K10: 0 | L10: 0 | M10: 0 | N10: 0 | O10: 0 | P10: 0 | Q10: 0 | R10: 0 | S10: 0
A11: Véhicules neufs[...] | B11: Véhicules neufs | C11: [...] | D11: 0 | E11: 0 | F11: 0 | J11: 0 | K11: 0 | L11: 0 | M11: 0 | N11: 0 | O11: 0 | P11: 0 | Q11: 0 | R11: 0 | S11: 0
A12: Véhicules neufs[...] | B12: Véhicules neufs | C12: [...] | D12: 0 | E12: 0 | F12: 0 | J12: 0 | K12: 0 | L12: 0 | M12: 0 | N12: 0 | O12: 0 | P12: 0 | Q12: 0 | R12: 0 | S12: 0
A13: Véhicules neufsTotal Neufs | B13: Véhicules neufs | C13: Total Neufs | D13: 69 | E13: 2303.1097 | F13: 158914.57 | J13: 48 | K13: 2185.0231 | L13: 104881.11 | M13: -21 | N13: -54033.458 | O13: 44 | P13: 1588.6441 | Q13: 69900.34 | R13: 4 | S13: 34980.77
A14: Véhicules neufs | B14: Véhicules neufs | M14: -0.30434783 | N14: -0.34001576 | R14: 0.090909091 | S14: 0.50043777 | AD14: 20 | AE14: 1000 | AF14: 20000
A15: Véhicules neufsEx-Démos et courtoisies | B15: Véhicules neufs | C15: Ex-Démos et courtoisies | D15: 3 | E15: 1534.7521 | F15: 4604.2564 | J15: 3 | K15: 1277.7867 | L15: 3833.36 | M15: 0 | N15: -770.89643 | O15: 6 | P15: 1038.8833 | Q15: 6233.3 | R15: -3 | S15: -2399.94 | AD15: 25 | AE15: 800 | AF15: 20000
A16: Véhicules neufs | B16: Véhicules neufs
A17: Véhicules neufsFlottes | B17: Véhicules neufs | C17: Flottes | D17: 2 | E17: 2393.8521 | F17: 4787.7042 | J17: 3 | K17: 2106.1833 | L17: 6318.55 | M17: 1 | N17: 1530.8458 | O17: 2 | P17: 383.48 | Q17: 766.96 | R17: 1 | S17: 5551.59
A18: Véhicules neufs | B18: Véhicules neufs
A19: Véhicules neufsRachat bail | B19: Véhicules neufs | C19: Rachat bail | D19: 0 | E19: 0 | F19: 7650 | L19: 9560 | N19: 1910 | Q19: 10100 | R19: 0 | S19: -540
A20: Véhicules neufs | B20: Véhicules neufs
A21: Véhicules neufsRev. Finances | B21: Véhicules neufs | C21: Rev. Finances | D21: 0 | E21: 0 | F21: 3600 | K21: 38.216863 | L21: 1949.06 | N21: -1650.94 | Q21: 0 | R21: -38.216863 | S21: 1949.06
A22: Véhicules neufsRev. Protections | B22: Véhicules neufs | C22: Rev. Protections | D22: 0 | E22: 0 | F22: 66960 | K22: 968.15549 | L22: 49375.93 | N22: -17584.07 | Q22: 42226.33 | R22: -968.15549 | S22: 7149.6
A23: Véhicules neufsRev. Autres | B23: Véhicules neufs | C23: Rev. Autres | D23: 0 | E23: 0 | F23: 1440 | K23: 0 | L23: 0 | N23: -1440 | Q23: 644.02 | R23: 0 | S23: -644.02
A24: Véhicules neufsTotal F&I | B24: Véhicules neufs | C24: Total F&I | D24: 72 | E24: 1000 | F24: 72000 | J24: 51 | K24: 1006.3724 | L24: 51324.99 | M24: -21 | N24: -20675.01 | O24: 50 | P24: 857.407 | Q24: 42870.35 | S24: 8454.64
A25: Véhicules neufs | B25: Véhicules neufs | N25: -0.28715292 | S25: 0.19721416
A26: Véhicules neufs | B26: Véhicules neufs
A27: Véhicules neufsTotal Dépt. Neufs | B27: Véhicules neufs | C27: Total Dépt. Neufs | D27: 74 | E27: 3350.7639 | F27: 247956.53 | J27: 54 | K27: 3257.7409 | L27: 175918.01 | M27: -20 | N27: -72038.519 | O27: 52 | P27: 2497.5183 | Q27: 129870.95 | R27: 2 | S27: 46047.06
A28: Véhicules neufs | B28: Véhicules neufs | L28: 0.70947118 | M28: -0.27027027 | N28: -0.29052882 | R28: 0.038461538 | S28: 0.35456012
A29: Véhicules neufs | B29: Véhicules neufs
A30: Véhicules neufsDEPENSES | B30: Véhicules neufs | C30: DEPENSES
A31: Véhicules neufsComm. vendeurs | B31: Véhicules neufs | C31: Comm. vendeurs | D31: 0.33313833 | E31: 756.58872 | F31: 54474.388 | J31: 0.35861573 | K31: 808.87549 | L31: 41252.65 | N31: -13221.738 | O31: 0.36538037 | P31: 561.9594 | Q31: 28097.97 | S31: 13154.68
A32: Véhicules neufsComm. F&I | B32: Véhicules neufs | C32: Comm. F&I | D32: 0.28 | E32: 280 | F32: 20160 | J32: 0.26999966 | K32: 271.7202 | L32: 13857.73 | N32: -6302.27 | O32: 0.26999336 | P32: 231.4942 | Q32: 11574.71 | S32: 2283.02
A33: Véhicules neufsFrais de livraison | B33: Véhicules neufs | C33: Frais de livraison | E33: 115 | F33: 8280 | K33: 127.63843 | L33: 6509.56 | N33: -1770.44 | P33: 156.3466 | Q33: 7817.33 | S33: -1307.77
A34: Véhicules neufsService gratuit 1 | B34: Véhicules neufs | C34: Service gratuit 1 | E34: 10 | F34: 720 | K34: 4.0194118 | L34: 204.99 | N34: -515.01 | P34: 16.8636 | Q34: 843.18 | S34: -638.19
A35: Véhicules neufsEntretien stock | B35: Véhicules neufs | C35: Entretien stock | E35: 120.75 | F35: 8694 | K35: 94.619412 | L35: 4825.59 | N35: -3868.41 | P35: 159.8588 | Q35: 7992.94 | S35: -3167.35
A36: Véhicules neufsPublicité 1 | B36: Véhicules neufs | C36: Publicité 1 | E36: 225.86111 | F36: 16262 | K36: 233.87333 | L36: 11927.54 | N36: -4334.46 | P36: 224.6836 | Q36: 11234.18 | S36: 693.36 | U36: credit 8,000 glassroom
A37: Véhicules neufsIntérêt de gros | B37: Véhicules neufs | C37: Intérêt de gros | E37: 565.31871 | F37: 40702.947 | K37: 425.86784 | L37: 21719.26 | N37: -18983.687 | P37: 530.407 | Q37: 26520.35 | S37: -4801.09
A38: Véhicules neufs[...] | B38: Véhicules neufs | C38: [...] | E38: 0 | F38: 0 | K38: 0 | L38: 0 | N38: 0 | P38: 0 | Q38: 0 | S38: 0
A39: Véhicules neufs[...] | B39: Véhicules neufs | C39: [...] | E39: 0 | F39: 0 | K39: 0 | L39: 0 | N39: 0 | P39: 0 | Q39: 0 | S39: 0
A40: Véhicules neufs[...] | B40: Véhicules neufs | C40: [...] | E40: 0 | F40: 0 | K40: 0 | L40: 0 | N40: 0 | P40: 0 | Q40: 0 | S40: 0
A41: Véhicules neufsTOTAL VARIABLES | B41: Véhicules neufs | C41: TOTAL VARIABLES | D41: % brut | E41: 0.6020948 | F41: 149293.34 | J41: % brut | K41: 0.57013674 | L41: 100297.32 | N41: -48996.015 | O41: % brut | P41: 0.72441651 | Q41: 94080.66 | S41: 6216.66
A42: Véhicules neufsSalaires cadres | B42: Véhicules neufs | C42: Salaires cadres | F42: 28420.582 | L42: 20142.13 | N42: -8278.4517 | P42: 0.093848547 | Q42: 12188.2 | S42: 7953.93
A43: Véhicules neufsSalaires commis | B43: Véhicules neufs | C43: Salaires commis | F43: 17167.774 | L43: 20057.19 | N43: 2889.4162 | Q43: 8630.72 | S43: 11426.47
A44: Véhicules neufsSalaires autres | B44: Véhicules neufs | C44: Salaires autres | F44: 394.44231 | L44: 930.2 | N44: 535.75769 | Q44: 2146.12 | S44: -1215.92
A45: Véhicules neufsSalaires spécialistes | B45: Véhicules neufs | C45: Salaires spécialistes | F45: 0 | L45: 0 | N45: 0 | Q45: 0 | S45: 0
A46: Véhicules neufs[...] | B46: Véhicules neufs | C46: [...] | F46: 0 | L46: 0 | N46: 0 | Q46: 0 | S46: 0
A47: Véhicules neufs[...] | B47: Véhicules neufs | C47: [...] | F47: 0 | L47: 0 | N47: 0 | Q47: 0 | S47: 0
A48: Véhicules neufs[...] | B48: Véhicules neufs | C48: [...] | F48: 0 | L48: 0 | N48: 0 | Q48: 0 | S48: 0
A49: Véhicules neufsSalaires en absences | B49: Véhicules neufs | C49: Salaires en absences | F49: 14095.712 | L49: 13521.92 | N49: -573.79166 | Q49: 10528.2 | S49: 2993.72
A50: Véhicules neufsDéduction à la source | B50: Véhicules neufs | C50: Déduction à la source | F50: 17138.398 | L50: 15758.45 | N50: -1379.9483 | Q50: 14036.34 | S50: 1722.11
A51: Véhicules neufsBénéfices marginaux | B51: Véhicules neufs | C51: Bénéfices marginaux | F51: 8830.0009 | L51: 8227.63 | N51: -602.37087 | Q51: 6769.08 | S51: 1458.55
A52: Véhicules neufsCsst | B52: Véhicules neufs | C52: Csst | F52: 3849.9301 | L52: 3456.94 | N52: -392.99006 | Q52: 1167.34 | S52: 2289.6
A53: Véhicules neufs[...] | B53: Véhicules neufs | C53: [...] | D53: #N/A | F53: 0 | L53: 0 | N53: 0 | Q53: 0 | S53: 0
A54: Véhicules neufsTOTAL PERSONNEL | B54: Véhicules neufs | C54: TOTAL PERSONNEL | D54: % brut | E54: 0.3625508 | F54: 89896.839 | J54: % brut | K54: 0.46666319 | L54: 82094.46 | N54: -7802.3788 | O54: % brut | P54: 0.4270855 | Q54: 55466 | S54: 26628.46
A55: Véhicules neufsPublicité 2 | B55: Véhicules neufs | C55: Publicité 2 | F55: 0 | L55: 0 | N55: 0 | Q55: 0 | S55: 0
A56: Véhicules neufsService gratuit 2 | B56: Véhicules neufs | C56: Service gratuit 2 | F56: 0 | L56: 0 | N56: 0 | Q56: 0 | S56: 0
A57: Véhicules neufsFrais véhicules de cie | B57: Véhicules neufs | C57: Frais véhicules de cie | F57: 8952.5479 | L57: 6523.11 | N57: -2429.4379 | Q57: 8473.11 | S57: -1950
A58: Véhicules neufsInformatique | B58: Véhicules neufs | C58: Informatique | F58: 7960.9948 | L58: 7696.69 | N58: -264.30476 | Q58: 7015.5 | S58: 681.19
A59: Véhicules neufsFrais de déplacement | B59: Véhicules neufs | C59: Frais de déplacement | F59: 1266.6975 | L59: 2623.13 | N59: 1356.4325 | Q59: 2344.34 | S59: 278.79
A60: Véhicules neufsServices extérieurs | B60: Véhicules neufs | C60: Services extérieurs | F60: 7215.7407 | L60: 8395.97 | N60: 1180.2293 | Q60: 8179.53 | S60: 216.44
A61: Véhicules neufsFournitures autres | B61: Véhicules neufs | C61: Fournitures autres | F61: 97.257333 | L61: 0 | N61: -97.257333 | Q61: 0 | S61: 0
A62: Véhicules neufsUniformes | B62: Véhicules neufs | C62: Uniformes | F62: 28.333333 | L62: 0 | N62: -28.333333 | Q62: 434.88 | S62: -434.88
A63: Véhicules neufsPapeterie | B63: Véhicules neufs | C63: Papeterie | F63: 741.43089 | L63: 58.95 | N63: -682.48089 | Q63: 377.56 | S63: -318.61
A64: Véhicules neufsTéléphone | B64: Véhicules neufs | C64: Téléphone | F64: 344.80198 | L64: 402.18 | N64: 57.378015 | Q64: 393.48 | S64: 8.7
A65: Véhicules neufsFrais postaux | B65: Véhicules neufs | C65: Frais postaux | F65: 102.8224 | L65: 87.27 | N65: -15.552395 | Q65: 32.96 | S65: 54.31
A66: Véhicules neufsDivers | B66: Véhicules neufs | C66: Divers | F66: 201.17039 | L66: 62.72 | N66: -138.45039 | Q66: 234.47 | S66: -171.75
... A68: Véhicules neufsFrais bancaires | B68: Véhicules neufs | C68: Frais bancaires | F68: 4283.1051 | L68: 4645.42 | N68: 362.31488 | Q68: 4782.88 | S68: -137.46
A69: Véhicules neufs[...] | B69: Véhicules neufs | C69: [...] | F69: 0 | N69: 0 | Q69: 0 | S69: 0
A70: Véhicules neufs[...] | B70: Véhicules neufs | C70: [...] | F70: 0 | L70: 0 | N70: 0 | Q70: 0 | S70: 0
A71: Véhicules neufs[...] | B71: Véhicules neufs | C71: [...] | F71: 0 | L71: 0 | N71: 0 | Q71: 0 | S71: 0
A72: Véhicules neufsTOTAL SEMI-FIXES | B72: Véhicules neufs | C72: TOTAL SEMI-FIXES | D72: % brut | E72: 0.13361055 | F72: 33129.609 | J72: % brut | K72: 0.17682504 | L72: 31106.71 | N72: -2022.8986 | O72: % brut | P72: 0.26669297 | Q72: 34635.67 | S72: -3528.96
A73: Véhicules neufs | B73: Véhicules neufs
A74: Véhicules neufsTOTAL DES DÉPENSES | B74: Véhicules neufs | C74: TOTAL DES DÉPENSES | D74: % brut | E74: 1.0982562 | F74: 272319.78 | J74: % brut | K74: 1.213625 | L74: 213498.49 | N74: -58821.293 | O74: % brut | P74: 1.418195 | Q74: 184182.33 | S74: 29316.16
A75: Véhicules neufsProgramme neuf 1 | B75: Véhicules neufs | C75: Programme neuf 1 | F75: 0 | L75: 45250 | N75: 45250 | Q75: 0
A76: Véhicules neufsProgramme neuf 2 | B76: Véhicules neufs | C76: Programme neuf 2 | F76: 0 | L76: 0 | N76: 0 | Q76: 0 | S76: 0
A77: Véhicules neufsProgramme neuf 3 | B77: Véhicules neufs | C77: Programme neuf 3 | F77: 0 | L77: 0 | N77: 0 | Q77: 0 | S77: 0
A78: Véhicules neufsHoldbacks | B78: Véhicules neufs | C78: Holdbacks | E78: 1405.8876 | F78: 104035.68 | J78: 1.0121193 | K78: 1422.9259 | L78: 76838 | N78: -27197.68 | Q78: 66750.85 | S78: 10087.15
A79: Véhicules neufs[...] | B79: Véhicules neufs | C79: [...] | F79: 0 | L79: 0 | N79: 0 | Q79: 0 | S79: 0
A80: Véhicules neufs[...] | B80: Véhicules neufs | C80: [...] | F80: 0 | L80: 0 | N80: 0 | Q80: 0 | S80: 0
A81: Véhicules neufs[...] | B81: Véhicules neufs | C81: [...] | F81: 0 | L81: 0 | N81: 0 | Q81: 0 | S81: 0
A82: Véhicules neufsFrais administration | B82: Véhicules neufs | C82: Frais administration | D82: 0.95 | E82: 474.05 | F82: 34131.6 | J82: 0.95011169 | K82: 450.35294 | L82: 22968 | N82: -11163.6 | Q82: 24378 | S82: -1410
A83: Véhicules neufsAUTRES REVENUS | B83: Véhicules neufs | C83: AUTRES REVENUS | F83: 138167.28 | L83: 145056 | N83: 6888.7198 | Q83: 91128.85 | S83: 8677.15
A84: Véhicules neufs | B84: Véhicules neufs
A85: Véhicules neufsPROFIT DÉPARTEMENTAL | B85: Véhicules neufs | C85: PROFIT DÉPARTEMENTAL | F85: 113804.03 | L85: 107475.52 | N85: -6328.506 | P85: 0.01490517 | Q85: 36817.47 | S85: 25408.05
C89: Volks | K89: Véhicules usagés | S89: Réalisé, Octobre 2025
D91: BUDGET ORIGINAL | J91: RÉALISATION | M91: ÉCART réel / Budget | O91: ANNÉE PRÉCÉDENTE | R91: ECART (réel/ Ann.Préc.)
D92: UNITE | E92: $P/UNITÉ | F92: $PROFITS | J92: UNITÉS | K92: $P/UNITE | L92: $PROFITS | M92: UNITÉS | N92: $PROFITS | O92: UNITE | P92: $P/UNITÉ | Q92: $PROFITS | R92: UNITÉS | S92: $PROFITS
A93: Véhicules usagésVentes nettes | B93: Véhicules usagés | C93: Ventes nettes | F93: 2168676.7 | L93: 1500069.8 | Q93: 1341799.5
A94: Véhicules usagésCertifié | B94: Véhicules usagés | C94: Certifié | D94: 33 | E94: 1400 | F94: 46200 | J94: 15 | K94: 2694.2227 | L94: 40413.34 | M94: -18 | N94: -5786.66 | O94: 37 | P94: 1033.9343 | Q94: 38255.57 | R94: -22 | S94: 2157.77
A95: Véhicules usagésNon Certifié | B95: Véhicules usagés | C95: Non Certifié | D95: 4 | E95: 1800 | F95: 7200 | J95: 0 | K95: 0 | L95: 0 | M95: -4 | N95: -7200 | O95: 3 | P95: -1128.6233 | Q95: -3385.87 | R95: -3 | S95: 3385.87
A96: Véhicules usagésAutres Marques | B96: Véhicules usagés | C96: Autres Marques | D96: 5 | E96: 1500 | F96: 7500 | J96: 0 | K96: 0 | L96: 0 | M96: -5 | N96: -7500 | O96: 3 | P96: 2230.9333 | Q96: 6692.8 | R96: -3 | S96: -6692.8
A97: Véhicules usagésTotal Usagés | B97: Véhicules usagés | C97: Total Usagés | D97: 42 | E97: 1450 | F97: 60900 | J97: 15 | K97: 2694.2227 | L97: 40413.34 | M97: -27 | N97: -20486.66 | O97: 43 | P97: 966.56977 | Q97: 41562.5 | R97: -25 | S97: 5543.64
A98: Véhicules usagés | B98: Véhicules usagés | E98: 0 | M98: -0.64285714 | N98: -0.33639836 | P98: 0 | R98: -0.58139535 | S98: 0.13338081
A99: Véhicules usagés | B99: Véhicules usagés | D99: 0 | E99: 0 | F99: 0
A100: Véhicules usagésVentes au Gros | B100: Véhicules usagés | C100: Ventes au Gros | D100: 45 | E100: 400 | F100: 18000 | J100: 52 | K100: 182.21538 | L100: 9475.2 | M100: 7 | N100: -8524.8 | O100: 23 | P100: 251.70435 | Q100: 5789.2 | R100: 29 | S100: 3686
A101: Véhicules usagés | B101: Véhicules usagés
A102: Véhicules usagésRev. Finances | B102: Véhicules usagés | C102: Rev. Finances | D102: 0 | E102: 0 | F102: 25200 | K102: 75.055333 | L102: 1125.83 | N102: -24074.17 | Q102: 15224.94 | R102: -75.055333 | S102: -14099.11
A103: Véhicules usagésRev. Protections | B103: Véhicules usagés | C103: Rev. Protections | D103: 0 | E103: 0 | F103: 52500 | K103: 1976.5013 | L103: 29647.52 | N103: -22852.48 | Q103: 67131.34 | R103: -1976.5013 | S103: -37483.82
A104: Véhicules usagésRev. Autres | B104: Véhicules usagés | C104: Rev. Autres | D104: 0 | E104: 0 | F104: 2100 | K104: 17.580667 | L104: 263.71 | N104: -1836.29 | Q104: 1145.29 | R104: -17.580667 | S104: -881.58
A105: Véhicules usagésTotal F&I | B105: Véhicules usagés | C105: Total F&I | D105: 42 | E105: 1900 | F105: 79800 | J105: 15 | K105: 2069.1373 | L105: 31037.06 | M105: -27 | N105: -48762.94 | O105: 43 | P105: 1941.897 | Q105: 83501.57 | S105: -52464.51
...

Sheet 2025-11
C1: Volks | K1: Véhicules neufs | S1: Réalisé, Novembre 2025
D2: X | E2: O | F2: U | J2: NB | L2: $ | O2: X | P2: O | Q2: U | V2: *** NE PAS EFFACER / Pour An Précédente ***
D3: BUDGET ORIGINAL | J3: RÉALISATION | M3: ÉCART réel / Budget | O3: ANNÉE PRÉCÉDENTE | R3: ECART (réel/ Ann.Préc.) | V3: NEUF | W3: 0.45
D4: UNITE | E4: $P/UNITÉ | F4: $PROFITS | J4: UNITÉS | K4: $P/UNITE | L4: $PROFITS | M4: UNITÉS | N4: $PROFITS | O4: UNITE | P4: $P/UNITÉ | Q4: $PROFITS | R4: UNITÉS | S4: $PROFITS | V4: USAGE | W4: 0.1
A5: Véhicules neufsVentes nettes | B5: Véhicules neufs | C5: Ventes nettes | F5: 4620342.2 | L5: 4142859.5 | Q5: 2101403.3 | V5: SERVICE | W5: 0.225
A6: Véhicules neufsAutos détail | B6: Véhicules neufs | C6: Autos détail | D6: 23 | E6: 1953.6492 | F6: 44933.931 | J6: 10 | K6: 1542.296 | L6: 15422.96 | M6: -13 | N6: -29510.971 | O6: 8 | P6: 2031.0612 | Q6: 16248.49 | R6: 2 | S6: -825.53 | V6: CARROSSERIE | W6: 0.025
A7: Véhicules neufsCamions détail | B7: Véhicules neufs | C7: Camions détail | D7: 60 | E7: 2435.9047 | F7: 146154.28 | J7: 60 | K7: 1856.0265 | L7: 111361.59 | M7: 0 | N7: -34792.691 | O7: 27 | P7: 2114.5019 | Q7: 57091.55 | R7: 33 | S7: 54270.04 | V7: PIECES | W7: 0.2
A8: Véhicules neufsSprinter | B8: Véhicules neufs | C8: Sprinter | D8: 0 | E8: 0 | F8: 0 | J8: 0 | K8: 0 | L8: 0 | M8: 0 | N8: 0 | O8: 0 | P8: 0 | Q8: 0 | R8: 0 | S8: 0 | W8: 1
A9: Véhicules neufsMoto détail | B9: Véhicules neufs | C9: Moto détail | D9: 0 | E9: 0 | F9: 0 | J9: 0 | K9: 0 | L9: 0 | M9: 0 | N9: 0 | O9: 0 | P9: 0 | Q9: 0 | R9: 0 | S9: 0
A10: Véhicules neufs[...] | B10: Véhicules neufs | C10: [...] | D10: 0 | E10: 0 | F10: 0 | J10: 0 | K10: 0 | L10: 0 | M10: 0 | N10: 0 | O10: 0 | P10: 0 | Q10: 0 | R10: 0 | S10: 0
A11: Véhicules neufs[...] | B11: Véhicules neufs | C11: [...] | D11: 0 | E11: 0 | F11: 0 | J11: 0 | K11: 0 | L11: 0 | M11: 0 | N11: 0 | O11: 0 | P11: 0 | Q11: 0 | R11: 0 | S11: 0
A12: Véhicules neufs[...] | B12: Véhicules neufs | C12: [...] | D12: 0 | E12: 0 | F12: 0 | J12: 0 | K12: 0 | L12: 0 | M12: 0 | N12: 0 | O12: 0 | P12: 0 | Q12: 0 | R12: 0 | S12: 0
A13: Véhicules neufsTotal Neufs | B13: Véhicules neufs | C13: Total Neufs | D13: 83 | E13: 2302.2676 | F13: 191088.21 | J13: 70 | K13: 1811.2079 | L13: 126784.55 | M13: -13 | N13: -64303.662 | O13: 35 | P13: 2095.4297 | Q13: 73340.04 | R13: 35 | S13: 53444.51
A14: Véhicules neufs | B14: Véhicules neufs | M14: -0.15662651 | N14: -0.33651297 | R14: 1 | S14: 0.72872213 | AD14: 20 | AE14: 1000 | AF14: 20000
A15: Véhicules neufsEx-Démos et courtoisies | B15: Véhicules neufs | C15: Ex-Démos et courtoisies | D15: 4 | E15: 1534.7521 | F15: 6139.0086 | J15: 2 | K15: 2386.71 | L15: 4773.42 | M15: -2 | N15: -1365.5886 | O15: 2 | P15: 1396.23 | Q15: 2792.46 | R15: 0 | S15: 1980.96 | AD15: 25 | AE15: 800 | AF15: 20000
A16: Véhicules neufs | B16: Véhicules neufs
A17: Véhicules neufsFlottes | B17: Véhicules neufs | C17: Flottes | D17: 2 | E17: 2393.8521 | F17: 4787.7042 | J17: 2 | K17: 3786.085 | L17: 7572.17 | M17: 0 | N17: 2784.4658 | O17: 3 | P17: 1478.8733 | Q17: 4436.62 | R17: -1 | S17: 3135.55
A18: Véhicules neufs | B18: Véhicules neufs
A19: Véhicules neufsRachat bail | B19: Véhicules neufs | C19: Rachat bail | D19: 0 | E19: 0 | F19: 9350 | L19: 10650.01 | N19: 1300.01 | Q19: 7700 | R19: 0 | S19: 2950.01
A20: Véhicules neufs | B20: Véhicules neufs
A21: Véhicules neufsRev. Finances | B21: Véhicules neufs | C21: Rev. Finances | D21: 0 | E21: 0 | F21: 4350 | K21: 0 | L21: 0 | N21: -4350 | Q21: 0 | R21: 0 | S21: 0
A22: Véhicules neufsRev. Protections | B22: Véhicules neufs | C22: Rev. Protections | D22: 0 | E22: 0 | F22: 80910 | K22: 995.15556 | L22: 71651.2 | N22: -9258.8 | Q22: 38628.6 | R22: -995.15556 | S22: 33022.6
A23: Véhicules neufsRev. Autres | B23: Véhicules neufs | C23: Rev. Autres | D23: 0 | E23: 0 | F23: 1740 | K23: 13.881806 | L23: 999.49 | N23: -740.51 | Q23: 645.16 | R23: -13.881806 | S23: 354.33
A24: Véhicules neufsTotal F&I | B24: Véhicules neufs | C24: Total F&I | D24: 87 | E24: 1000 | F24: 87000 | J24: 72 | K24: 1009.0374 | L24: 72650.69 | M24: -15 | N24: -14349.31 | O24: 37 | P24: 1061.453 | Q24: 39273.76 | S24: 33376.93
A25: Véhicules neufs | B25: Véhicules neufs | N25: -0.1649346 | S25: 0.84985318
A26: Véhicules neufs | B26: Véhicules neufs
A27: Véhicules neufsTotal Dépt. Neufs | B27: Véhicules neufs | C27: Total Dépt. Neufs | D27: 89 | E27: 3352.4149 | F27: 298364.92 | J27: 74 | K27: 3005.8222 | L27: 222430.84 | M27: -15 | N27: -75934.084 | O27: 40 | P27: 3188.572 | Q27: 127542.88 | R27: 34 | S27: 94887.96
A28: Véhicules neufs | B28: Véhicules neufs | L28: 0.74549929 | M28: -0.16853933 | N28: -0.25450071 | R28: 0.85 | S28: 0.74396909
A29: Véhicules neufs | B29: Véhicules neufs
A30: Véhicules neufsDEPENSES | B30: Véhicules neufs | C30: DEPENSES
A31: Véhicules neufsComm. vendeurs | B31: Véhicules neufs | C31: Comm. vendeurs | D31: 0.31738468 | E31: 719.50459 | F31: 62596.899 | J31: 0.26163339 | K31: 505.57069 | L31: 36401.09 | N31: -26195.809 | O31: 0.29663462 | P31: 645.93486 | Q31: 23899.59 | S31: 12501.5
A32: Véhicules neufsComm. F&I | B32: Véhicules neufs | C32: Comm. F&I | D32: 0.28 | E32: 280 | F32: 24360 | J32: 0.26999661 | K32: 272.43667 | L32: 19615.44 | N32: -4744.56 | O32: 0.27998974 | P32: 297.19595 | Q32: 10996.25 | S32: 8619.19
A33: Véhicules neufsFrais de livraison | B33: Véhicules neufs | C33: Frais de livraison | E33: 115 | F33: 10005 | K33: 73.22125 | L33: 5271.93 | N33: -4733.07 | P33: 233.92757 | Q33: 8655.32 | S33: -3383.39
A34: Véhicules neufsService gratuit 1 | B34: Véhicules neufs | C34: Service gratuit 1 | E34: 10 | F34: 870 | K34: 3.7194444 | L34: 267.8 | N34: -602.2 | P34: 108.85892 | Q34: 4027.78 | S34: -3759.98
A35: Véhicules neufsEntretien stock | B35: Véhicules neufs | C35: Entretien stock | E35: 120.75 | F35: 10505.25 | K35: 109.28875 | L35: 7868.79 | N35: -2636.46 | P35: 212.08676 | Q35: 7847.21 | S35: 21.58
A36: Véhicules neufsPublicité 1 | B36: Véhicules neufs | C36: Publicité 1 | E36: 31.747126 | F36: 2762 | K36: 53.550417 | L36: 3855.63 | N36: 1093.63 | P36: 527.05568 | Q36: 19501.06 | S36: -15645.43
A37: Véhicules neufsIntérêt de gros | B37: Véhicules neufs | C37: Intérêt de gros | E37: 402.18682 | F37: 34990.253 | K37: 337.88694 | L37: 24327.86 | N37: -10662.393 | P37: -1003.7751 | Q37: -37139.68 | S37: 61467.54
A38: Véhicules neufs[...] | B38: Véhicules neufs | C38: [...] | E38: 0 | F38: 0 | K38: 0 | L38: 0 | N38: 0 | P38: 0 | Q38: 0 | S38: 0
A39: Véhicules neufs[...] | B39: Véhicules neufs | C39: [...] | E39: 0 | F39: 0 | K39: 0 | L39: 0 | N39: 0 | P39: 0 | Q39: 0 | S39: 0
A40: Véhicules neufs[...] | B40: Véhicules neufs | C40: [...] | E40: 0 | F40: 0 | K40: 0 | L40: 0 | N40: 0 | P40: 0 | Q40: 0 | S40: 0
A41: Véhicules neufsTOTAL VARIABLES | B41: Véhicules neufs | C41: TOTAL VARIABLES | D41: % brut | E41: 0.4896333 | F41: 146089.4 | J41: % brut | K41: 0.43882647 | L41: 97608.54 | N41: -48480.862 | O41: % brut | P41: 0.29627314 | Q41: 37787.53 | S41: 59821.01
A42: Véhicules neufsSalaires cadres | B42: Véhicules neufs | C42: Salaires cadres | F42: 24486.465 | L42: 16358.33 | N42: -8128.1354 | P42: 0.19016083 | Q42: 24253.66 | S42: -7895.33
A43: Véhicules neufsSalaires commis | B43: Véhicules neufs | C43: Salaires commis | F43: 13904.219 | L43: 13068.19 | N43: -836.02908 | Q43: 13792.56 | S43: -724.37
A44: Véhicules neufsSalaires autres | B44: Véhicules neufs | C44: Salaires autres | F44: 315.55385 | L44: 1451.6 | N44: 1136.0462 | Q44: 4339.52 | S44: -2887.92
A45: Véhicules neufsSalaires spécialistes | B45: Véhicules neufs | C45: Salaires spécialistes | F45: 0 | L45: 0 | N45: 0 | Q45: 0 | S45: 0
A46: Véhicules neufs[...] | B46: Véhicules neufs | C46: [...] | F46: 0 | L46: 0 | N46: 0 | Q46: 0 | S46: 0
A47: Véhicules neufs[...] | B47: Véhicules neufs | C47: [...] | F47: 0 | L47: 0 | N47: 0 | Q47: 0 | S47: 0
A48: Véhicules neufs[...] | B48: Véhicules neufs | C48: [...] | F48: 0 | L48: 0 | N48: 0 | Q48: 0 | S48: 0
A49: Véhicules neufsSalaires en absences | B49: Véhicules neufs | C49: Salaires en absences | F49: 13449.662 | L49: 12767.3 | N49: -682.36202 | Q49: 11233.56 | S49: 1533.74
A50: Véhicules neufsDéduction à la source | B50: Véhicules neufs | C50: Déduction à la source | F50: 16352.893 | L50: 15446.59 | N50: -906.30303 | Q50: 12527.06 | S50: 2919.53
A51: Véhicules neufsBénéfices marginaux | B51: Véhicules neufs | C51: Bénéfices marginaux | F51: 8425.2949 | L51: 8320.04 | N51: -105.25489 | Q51: 372.18 | S51: 7947.86
A52: Véhicules neufsCsst | B52: Véhicules neufs | C52: Csst | F52: 3673.476 | L52: 1641.57 | N52: -2031.906 | Q52: 1645.94 | S52: -4.37
A53: Véhicules neufs[...] | B53: Véhicules neufs | C53: [...] | D53: #N/A | F53: 0 | L53: 0 | N53: 0 | Q53: 0 | S53: 0
A54: Véhicules neufsTOTAL PERSONNEL | B54: Véhicules neufs | C54: TOTAL PERSONNEL | D54: % brut | E54: 0.27016434 | F54: 80607.564 | J54: % brut | K54: 0.31044985 | L54: 69053.62 | N54: -11553.944 | O54: % brut | P54: 0.53444363 | Q54: 68164.48 | S54: 889.14
A55: Véhicules neufsPublicité 2 | B55: Véhicules neufs | C55: Publicité 2 | F55: 0 | L55: 0 | N55: 0 | Q55: 0 | S55: 0
A56: Véhicules neufsService gratuit 2 | B56: Véhicules neufs | C56: Service gratuit 2 | F56: 0 | L56: 0 | N56: 0 | Q56: 0 | S56: 0
A57: Véhicules neufsFrais véhicules de cie | B57: Véhicules neufs | C57: Frais véhicules de cie | F57: 8952.5479 | L57: 9881.78 | N57: 929.23207 | Q57: 8283.33 | S57: 1598.45
A58: Véhicules neufsInformatique | B58: Véhicules neufs | C58: Informatique | F58: 7960.9948 | L58: 6971.19 | N58: -989.80476 | Q58: 6688.36 | S58: 282.83
A59: Véhicules neufsFrais de déplacement | B59: Véhicules neufs | C59: Frais de déplacement | F59: 1266.6975 | L59: 1668.07 | N59: 401.3725 | Q59: 2373.63 | S59: -705.56
A60: Véhicules neufsServices extérieurs | B60: Véhicules neufs | C60: Services extérieurs | F60: 7215.7407 | L60: 9175.12 | N60: 1959.3793 | Q60: 7674.68 | S60: 1500.44
A61: Véhicules neufsFournitures autres | B61: Véhicules neufs | C61: Fournitures autres | F61: 97.257333 | L61: 0 | N61: -97.257333 | Q61: 0 | S61: 0
A62: Véhicules neufsUniformes | B62: Véhicules neufs | C62: Uniformes | F62: 28.333333 | L62: 0 | N62: -28.333333 | Q62: 0 | S62: 0
A63: Véhicules neufsPapeterie | B63: Véhicules neufs | C63: Papeterie | F63: 741.43089 | L63: 1466.35 | N63: 724.91911 | Q63: 1262.34 | S63: 204.01
A64: Véhicules neufsTéléphone | B64: Véhicules neufs | C64: Téléphone | F64: 344.80198 | L64: 398.61 | N64: 53.808015 | Q64: 351.63 | S64: 46.98
A65: Véhicules neufsFrais postaux | B65: Véhicules neufs | C65: Frais postaux | F65: 102.8224 | L65: 116.66 | N65: 13.837605 | Q65: 40.25 | S65: 76.41
A66: Véhicules neufsDivers | B66: Véhicules neufs | C66: Divers | F66: 201.17039 | L66: 410.38 | N66: 209.20961 | Q66: 446.81 | S66: -36.43
... A68: Véhicules neufsFrais bancaires | B68: Véhicules neufs | C68: Frais bancaires | F68: 5035.3183 | L68: 6358.02 | N68: 1322.7017 | Q68: 6767.49 | S68: -409.47
A69: Véhicules neufs[...] | B69: Véhicules neufs | C69: [...] | F69: 0 | N69: 0 | Q69: 0 | S69: 0
A70: Véhicules neufs[...] | B70: Véhicules neufs | C70: [...] | F70: 0 | L70: 0 | N70: 0 | Q70: 0 | S70: 0
A71: Véhicules neufs[...] | B71: Véhicules neufs | C71: [...] | F71: 0 | L71: 0 | N71: 0 | Q71: 0 | S71: 0
A72: Véhicules neufsTOTAL SEMI-FIXES | B72: Véhicules neufs | C72: TOTAL SEMI-FIXES | D72: % brut | E72: 0.11355833 | F72: 33881.822 | J72: % brut | K72: 0.16643349 | L72: 37019.94 | N72: 3138.1182 | O72: % brut | P72: 0.27970178 | Q72: 35673.97 | S72: 1345.97
A73: Véhicules neufs | B73: Véhicules neufs
A74: Véhicules neufsTOTAL DES DÉPENSES | B74: Véhicules neufs | C74: TOTAL DES DÉPENSES | D74: % brut | E74: 0.87335597 | F74: 260578.79 | J74: % brut | K74: 0.9157098 | L74: 203682.1 | N74: -56896.688 | O74: % brut | P74: 1.1104186 | Q74: 141625.98 | S74: 62056.12
A75: Véhicules neufsProgramme neuf 1 | B75: Véhicules neufs | C75: Programme neuf 1 | F75: 0 | L75: 0 | N75: 0 | Q75: 12500
A76: Véhicules neufsProgramme neuf 2 | B76: Véhicules neufs | C76: Programme neuf 2 | F76: 0 | L76: 0 | N76: 0 | Q76: 0 | S76: 0
A77: Véhicules neufsProgramme neuf 3 | B77: Véhicules neufs | C77: Programme neuf 3 | F77: 0 | L77: 0 | N77: 0 | Q77: 0 | S77: 0
A78: Véhicules neufsHoldbacks | B78: Véhicules neufs | C78: Holdbacks | E78: 1423.0577 | F78: 126652.13 | J78: 0.90527375 | K78: 1288.2568 | L78: 95331 | N78: -31321.132 | Q78: 55120 | S78: 40211
A79: Véhicules neufs[...] | B79: Véhicules neufs | C79: [...] | F79: 0 | L79: 0 | N79: 0 | Q79: 0 | S79: 0
A80: Véhicules neufs[...] | B80: Véhicules neufs | C80: [...] | F80: 0 | L80: 0 | N80: 0 | Q80: 0 | S80: 0
A81: Véhicules neufs[...] | B81: Véhicules neufs | C81: [...] | F81: 0 | L81: 0 | N81: 0 | Q81: 0 | S81: 0
A82: Véhicules neufsFrais administration | B82: Véhicules neufs | C82: Frais administration | D82: 0.95 | E82: 474.05 | F82: 41242.35 | J82: 0.93020394 | K82: 440.91667 | L82: 31746 | N82: -9496.35 | Q82: 16782 | S82: 14964
A83: Véhicules neufsAUTRES REVENUS | B83: Véhicules neufs | C83: AUTRES REVENUS | F83: 167894.48 | L83: 127077 | N83: -40817.482 | Q83: 84402 | S83: 55175
A84: Véhicules neufs | B84: Véhicules neufs
A85: Véhicules neufsPROFIT DÉPARTEMENTAL | B85: Véhicules neufs | C85: PROFIT DÉPARTEMENTAL | F85: 205680.62 | L85: 145825.74 | N85: -59854.879 | P85: 0.033462829 | Q85: 70318.9 | S85: 88006.84
C89: Volks | K89: Véhicules usagés | S89: Réalisé, Novembre 2025
D91: BUDGET ORIGINAL | J91: RÉALISATION | M91: ÉCART réel / Budget | O91: ANNÉE PRÉCÉDENTE | R91: ECART (réel/ Ann.Préc.)
D92: UNITE | E92: $P/UNITÉ | F92: $PROFITS | J92: UNITÉS | K92: $P/UNITE | L92: $PROFITS | M92: UNITÉS | N92: $PROFITS | O92: UNITE | P92: $P/UNITÉ | Q92: $PROFITS | R92: UNITÉS | S92: $PROFITS
A93: Véhicules usagésVentes nettes | B93: Véhicules usagés | C93: Ventes nettes | F93: 1792093.8 | L93: 2000604.9 | Q93: 1025214
A94: Véhicules usagésCertifié | B94: Véhicules usagés | C94: Certifié | D94: 27 | E94: 1400 | F94: 37800 | J94: 28 | K94: 1446.2436 | L94: 40494.82 | M94: 1 | N94: 2694.82 | O94: 30 | P94: 1597.681 | Q94: 47930.43 | R94: -2 | S94: -7435.61
A95: Véhicules usagésNon Certifié | B95: Véhicules usagés | C95: Non Certifié | D95: 3 | E95: 1800 | F95: 5400 | J95: 0 | K95: 0 | L95: 0 | M95: -3 | N95: -5400 | O95: 2 | P95: -1112.96 | Q95: -2225.92 | R95: -2 | S95: 2225.92
A96: Véhicules usagésAutres Marques | B96: Véhicules usagés | C96: Autres Marques | D96: 5 | E96: 1500 | F96: 7500 | J96: 0 | K96: 0 | L96: 0 | M96: -5 | N96: -7500 | O96: 3 | P96: 2132.8667 | Q96: 6398.6 | R96: -3 | S96: -6398.6
A97: Véhicules usagésTotal Usagés | B97: Véhicules usagés | C97: Total Usagés | D97: 35 | E97: 1448.5714 | F97: 50700 | J97: 28 | K97: 1446.2436 | L97: 40494.82 | M97: -7 | N97: -10205.18 | O97: 35 | P97: 1488.6603 | Q97: 52103.11 | R97: -4 | S97: -5209.69
A98: Véhicules usagés | B98: Véhicules usagés | E98: 0 | M98: -0.2 | N98: -0.2012856 | P98: 0 | R98: -0.11428571 | S98: -0.099988081
A99: Véhicules usagés | B99: Véhicules usagés | D99: 0 | E99: 0 | F99: 0
A100: Véhicules usagésVentes au Gros | B100: Véhicules usagés | C100: Ventes au Gros | D100: 39 | E100: 400 | F100: 15600 | J100: 57 | K100: -132.43754 | L100: -7548.94 | M100: 18 | N100: -23148.94 | O100: 19 | P100: 279.54947 | Q100: 5311.44 | R100: 38 | S100: -12860.38
A101: Véhicules usagés | B101: Véhicules usagés
A102: Véhicules usagésRev. Finances | B102: Véhicules usagés | C102: Rev. Finances | D102: 0 | E102: 0 | F102: 21000 | K102: 134.03429 | L102: 3752.96 | N102: -17247.04 | Q102: 9925.9 | R102: -134.03429 | S102: -6172.94
A103: Véhicules usagésRev. Protections | B103: Véhicules usagés | C103: Rev. Protections | D103: 0 | E103: 0 | F103: 43750 | K103: 2014.1729 | L103: 56396.84 | N103: 12646.84 | Q103: 43137.02 | R103: -2014.1729 | S103: 13259.82
A104: Véhicules usagésRev. Autres | B104: Véhicules usagés | C104: Rev. Autres | D104: 0 | E104: 0 | F104: 1750 | K104: 0 | L104: 0 | N104: -1750 | Q104: 560.39 | R104: 0 | S104: -560.39
A105: Véhicules usagésTotal F&I | B105: Véhicules usagés | C105: Total F&I | D105: 35 | E105: 1900 | F105: 66500 | J105: 28 | K105: 2148.2071 | L105: 60149.8 | M105: -7 | N105: -6350.2 | O105: 35 | P105: 1532.0946 | Q105: 53623.31 | S105: 6526.49
...

Sheet 2025-12
C1: Volks | K1: Véhicules neufs | S1: Réalisé, Décembre 2025
D2: X | E2: O | F2: U | J2: NB | L2: $ | O2: X | P2: O | Q2: U | V2: *** NE PAS EFFACER / Pour An Précédente ***
D3: BUDGET ORIGINAL | J3: RÉALISATION | M3: ÉCART réel / Budget | O3: ANNÉE PRÉCÉDENTE | R3: ECART (réel/ Ann.Préc.) | V3: NEUF | W3: 0.45
D4: UNITE | E4: $P/UNITÉ | F4: $PROFITS | J4: UNITÉS | K4: $P/UNITE | L4: $PROFITS | M4: UNITÉS | N4: $PROFITS | O4: UNITE | P4: $P/UNITÉ | Q4: $PROFITS | R4: UNITÉS | S4: $PROFITS | V4: USAGE | W4: 0.1
A5: Véhicules neufsVentes nettes | B5: Véhicules neufs | C5: Ventes nettes | F5: 2940854.1 | L5: 2445339.6 | Q5: 2168000.1 | V5: SERVICE | W5: 0.225
A6: Véhicules neufsAutos détail | B6: Véhicules neufs | C6: Autos détail | D6: 14 | E6: 1953.6492 | F6: 27351.088 | J6: 2 | K6: 3513.835 | L6: 7027.67 | M6: -12 | N6: -20323.418 | O6: 6 | P6: 1532.1433 | Q6: 9192.86 | R6: -4 | S6: -2165.19 | V6: CARROSSERIE | W6: 0.025
A7: Véhicules neufsCamions détail | B7: Véhicules neufs | C7: Camions détail | D7: 39 | E7: 2435.9047 | F7: 95000.282 | J7: 37 | K7: 1654.85 | L7: 61229.45 | M7: -2 | N7: -33770.832 | O7: 24 | P7: 1904.4017 | Q7: 45705.64 | R7: 13 | S7: 15523.81 | V7: PIECES | W7: 0.2
A8: Véhicules neufsSprinter | B8: Véhicules neufs | C8: Sprinter | D8: 0 | E8: 0 | F8: 0 | J8: 0 | K8: 0 | L8: 0 | M8: 0 | N8: 0 | O8: 0 | P8: 0 | Q8: 0 | R8: 0 | S8: 0 | W8: 1
A9: Véhicules neufsMoto détail | B9: Véhicules neufs | C9: Moto détail | D9: 0 | E9: 0 | F9: 0 | J9: 0 | K9: 0 | L9: 0 | M9: 0 | N9: 0 | O9: 0 | P9: 0 | Q9: 0 | R9: 0 | S9: 0
A10: Véhicules neufs[...] | B10: Véhicules neufs | C10: [...] | D10: 0 | E10: 0 | F10: 0 | J10: 0 | K10: 0 | L10: 0 | M10: 0 | N10: 0 | O10: 0 | P10: 0 | Q10: 0 | R10: 0 | S10: 0
A11: Véhicules neufs[...] | B11: Véhicules neufs | C11: [...] | D11: 0 | E11: 0 | F11: 0 | J11: 0 | K11: 0 | L11: 0 | M11: 0 | N11: 0 | O11: 0 | P11: 0 | Q11: 0 | R11: 0 | S11: 0
A12: Véhicules neufs[...] | B12: Véhicules neufs | C12: [...] | D12: 0 | E12: 0 | F12: 0 | J12: 0 | K12: 0 | L12: 0 | M12: 0 | N12: 0 | O12: 0 | P12: 0 | Q12: 0 | R12: 0 | S12: 0
A13: Véhicules neufsTotal Neufs | B13: Véhicules neufs | C13: Total Neufs | D13: 53 | E13: 2308.5164 | F13: 122351.37 | J13: 39 | K13: 1750.1826 | L13: 68257.12 | M13: -14 | N13: -54094.251 | O13: 30 | P13: 1829.95 | Q13: 54898.5 | R13: 9 | S13: 13358.62
A14: Véhicules neufs | B14: Véhicules neufs | M14: -0.26415094 | N14: -0.44212215 | R14: 0.3 | S14: 0.24333306 | AD14: 20 | AE14: 1000 | AF14: 20000
A15: Véhicules neufsEx-Démos et courtoisies | B15: Véhicules neufs | C15: Ex-Démos et courtoisies | D15: 3 | E15: 1534.7521 | F15: 4604.2564 | J15: 3 | K15: -676.00333 | L15: -2028.01 | M15: 0 | N15: -6632.2664 | O15: 4 | P15: 2295.8825 | Q15: 9183.53 | R15: -1 | S15: -11211.54 | AD15: 25 | AE15: 800 | AF15: 20000
A16: Véhicules neufs | B16: Véhicules neufs
A17: Véhicules neufsFlottes | B17: Véhicules neufs | C17: Flottes | D17: 1 | E17: 2393.8521 | F17: 2393.8521 | J17: 0 | K17: 0 | L17: 0 | M17: -1 | N17: -2393.8521 | O17: 6 | P17: 1073.965 | Q17: 6443.79 | R17: -6 | S17: -6443.79
A18: Véhicules neufs | B18: Véhicules neufs
A19: Véhicules neufsRachat bail | B19: Véhicules neufs | C19: Rachat bail | D19: 0 | E19: 0 | F19: 5950 | L19: 7399.84 | N19: 1449.84 | Q19: 5949 | R19: 0 | S19: 1450.84
A20: Véhicules neufs | B20: Véhicules neufs
A21: Véhicules neufsRev. Finances | B21: Véhicules neufs | C21: Rev. Finances | D21: 0 | E21: 0 | F21: 2800 | K21: 90.449048 | L21: 3798.86 | N21: 998.86 | Q21: 1288.84 | R21: -90.449048 | S21: 2510.02
A22: Véhicules neufsRev. Protections | B22: Véhicules neufs | C22: Rev. Protections | D22: 0 | E22: 0 | F22: 52080 | K22: 805.02238 | L22: 33810.94 | N22: -18269.06 | Q22: 44538.34 | R22: -805.02238 | S22: -10727.4
A23: Véhicules neufsRev. Autres | B23: Véhicules neufs | C23: Rev. Autres | D23: 0 | E23: 0 | F23: 1120 | K23: 23.329286 | L23: 979.83 | N23: -140.17 | Q23: 0 | R23: -23.329286 | S23: 979.83
A24: Véhicules neufsTotal F&I | B24: Véhicules neufs | C24: Total F&I | D24: 56 | E24: 1000 | F24: 56000 | J24: 42 | K24: 918.80071 | L24: 38589.63 | M24: -14 | N24: -17410.37 | O24: 34 | P24: 1347.8582 | Q24: 45827.18 | S24: -7237.55
A25: Véhicules neufs | B25: Véhicules neufs | N25: -0.31089946 | S25: -0.15793138
A26: Véhicules neufs | B26: Véhicules neufs
A27: Véhicules neufsTotal Dépt. Neufs | B27: Véhicules neufs | C27: Total Dépt. Neufs | D27: 57 | E27: 3356.1312 | F27: 191299.48 | J27: 42 | K27: 2671.871 | L27: 112218.58 | M27: -15 | N27: -79080.899 | O27: 40 | P27: 3057.55 | Q27: 122302 | R27: 2 | S27: -10083.42
A28: Véhicules neufs | B28: Véhicules neufs | L28: 0.58661205 | M28: -0.26315789 | N28: -0.41338795 | R28: 0.05 | S28: -0.082446894
A29: Véhicules neufs | B29: Véhicules neufs
A30: Véhicules neufsDEPENSES | B30: Véhicules neufs | C30: DEPENSES
A31: Véhicules neufsComm. vendeurs | B31: Véhicules neufs | C31: Comm. vendeurs | D31: 0.33220695 | E31: 753.13468 | F31: 42175.542 | J31: 0.42075849 | K31: 663.48714 | L31: 27866.46 | N31: -14309.082 | O31: 0.33063295 | P31: 685.82824 | Q31: 23318.16 | S31: 4548.3
A32: Véhicules neufsComm. F&I | B32: Véhicules neufs | C32: Comm. F&I | D32: 0.28 | E32: 280 | F32: 15680 | J32: 0.27000337 | K32: 248.07929 | L32: 10419.33 | N32: -5260.67 | O32: 0.30000886 | P32: 404.36941 | Q32: 13748.56 | S32: -3329.23
A33: Véhicules neufsFrais de livraison | B33: Véhicules neufs | C33: Frais de livraison | E33: 115 | F33: 6440 | K33: 106.25429 | L33: 4462.68 | N33: -1977.32 | P33: 76.159118 | Q33: 2589.41 | S33: 1873.27
A34: Véhicules neufsService gratuit 1 | B34: Véhicules neufs | C34: Service gratuit 1 | E34: 10 | F34: 560 | K34: 1.8809524 | L34: 79 | N34: -481 | P34: 26.280588 | Q34: 893.54 | S34: -814.54
A35: Véhicules neufsEntretien stock | B35: Véhicules neufs | C35: Entretien stock | E35: 120.75 | F35: 6762 | K35: 168.06286 | L35: 7058.64 | N35: 296.64 | P35: 99.538529 | Q35: 3384.31 | S35: 3674.33
A36: Véhicules neufsPublicité 1 | B36: Véhicules neufs | C36: Publicité 1 | E36: 104.67857 | F36: 5862 | K36: 277.25952 | L36: 11644.9 | N36: 5782.9 | P36: 316.01029 | Q36: 10744.35 | S36: 900.55
A37: Véhicules neufsIntérêt de gros | B37: Véhicules neufs | C37: Intérêt de gros | E37: 624.61342 | F37: 34978.352 | K37: 450.03214 | L37: 18901.35 | N37: -16077.002 | P37: -106.62588 | Q37: -3625.28 | S37: 22526.63
A38: Véhicules neufs[...] | B38: Véhicules neufs | C38: [...] | E38: 0 | F38: 0 | K38: 0 | L38: 0 | N38: 0 | P38: 0 | Q38: 0 | S38: 0
A39: Véhicules neufs[...] | B39: Véhicules neufs | C39: [...] | E39: 0 | F39: 0 | K39: 0 | L39: 0 | N39: 0 | P39: 0 | Q39: 0 | S39: 0
A40: Véhicules neufs[...] | B40: Véhicules neufs | C40: [...] | E40: 0 | F40: 0 | K40: 0 | L40: 0 | N40: 0 | P40: 0 | Q40: 0 | S40: 0
A41: Véhicules neufsTOTAL VARIABLES | B41: Véhicules neufs | C41: TOTAL VARIABLES | D41: % brut | E41: 0.58786304 | F41: 112457.89 | J41: % brut | K41: 0.71674726 | L41: 80432.36 | N41: -32025.534 | O41: % brut | P41: 0.4174343 | Q41: 51053.05 | S41: 29379.31
A42: Véhicules neufsSalaires cadres | B42: Véhicules neufs | C42: Salaires cadres | F42: 24486.465 | L42: 14576.98 | N42: -9909.4854 | P42: 0.13021022 | Q42: 15924.97 | S42: -1347.99
A43: Véhicules neufsSalaires commis | B43: Véhicules neufs | C43: Salaires commis | F43: 13904.219 | L43: 15203.89 | N43: 1299.6709 | Q43: 8412.6 | S43: 6791.29
A44: Véhicules neufsSalaires autres | B44: Véhicules neufs | C44: Salaires autres | F44: 315.55385 | L44: 1152.15 | N44: 836.59615 | Q44: 2835.6 | S44: -1683.45
A45: Véhicules neufsSalaires spécialistes | B45: Véhicules neufs | C45: Salaires spécialistes | F45: 0 | L45: 0 | N45: 0 | Q45: 0 | S45: 0
A46: Véhicules neufs[...] | B46: Véhicules neufs | C46: [...] | F46: 0 | L46: 0 | N46: 0 | Q46: 0 | S46: 0
A47: Véhicules neufs[...] | B47: Véhicules neufs | C47: [...] | F47: 0 | L47: 0 | N47: 0 | Q47: 0 | S47: 0
A48: Véhicules neufs[...] | B48: Véhicules neufs | C48: [...] | F48: 0 | L48: 0 | N48: 0 | Q48: 0 | S48: 0
A49: Véhicules neufsSalaires en absences | B49: Véhicules neufs | C49: Salaires en absences | F49: 9688.7245 | L49: 8703.02 | N49: -985.70453 | Q49: 9362.32 | S49: -659.3
A50: Véhicules neufsDéduction à la source | B50: Véhicules neufs | C50: Déduction à la source | F50: 11780.123 | L50: 10913.17 | N50: -866.95322 | Q50: 11260.94 | S50: -347.77
A51: Véhicules neufsBénéfices marginaux | B51: Véhicules neufs | C51: Bénéfices marginaux | F51: 6069.3244 | L51: 6319.58 | N51: 250.25565 | Q51: 4182.4 | S51: 2137.18
A52: Véhicules neufsCsst | B52: Véhicules neufs | C52: Csst | F52: 2646.2596 | L52: 1952.27 | N52: -693.98956 | Q52: 2840.64 | S52: -888.37
A53: Véhicules neufs[...] | B53: Véhicules neufs | C53: [...] | D53: #N/A | F53: 0 | L53: 0 | N53: 0 | Q53: 0 | S53: 0
A54: Véhicules neufsTOTAL PERSONNEL | B54: Véhicules neufs | C54: TOTAL PERSONNEL | D54: % brut | E54: 0.36011948 | F54: 68890.67 | J54: % brut | K54: 0.52416507 | L54: 58821.06 | N54: -10069.61 | O54: % brut | P54: 0.44823036 | Q54: 54819.47 | S54: 4001.59
A55: Véhicules neufsPublicité 2 | B55: Véhicules neufs | C55: Publicité 2 | F55: 0 | L55: 0 | N55: 0 | Q55: 0 | S55: 0
A56: Véhicules neufsService gratuit 2 | B56: Véhicules neufs | C56: Service gratuit 2 | F56: 0 | L56: 0 | N56: 0 | Q56: 0 | S56: 0
A57: Véhicules neufsFrais véhicules de cie | B57: Véhicules neufs | C57: Frais véhicules de cie | F57: 8952.5479 | L57: 10373.77 | N57: 1421.2221 | Q57: 12087.7 | S57: -1713.93
A58: Véhicules neufsInformatique | B58: Véhicules neufs | C58: Informatique | F58: 7960.9948 | L58: 9937.75 | N58: 1976.7552 | Q58: 8179.98 | S58: 1757.77
A59: Véhicules neufsFrais de déplacement | B59: Véhicules neufs | C59: Frais de déplacement | F59: 1266.6975 | L59: 1697.26 | N59: 430.5625 | Q59: 1118.44 | S59: 578.82
A60: Véhicules neufsServices extérieurs | B60: Véhicules neufs | C60: Services extérieurs | F60: 7215.7407 | L60: 10407.27 | N60: 3191.5293 | Q60: 6975.91 | S60: 3431.36
A61: Véhicules neufsFournitures autres | B61: Véhicules neufs | C61: Fournitures autres | F61: 97.257333 | L61: 0 | N61: -97.257333 | Q61: 176.44 | S61: -176.44
A62: Véhicules neufsUniformes | B62: Véhicules neufs | C62: Uniformes | F62: 28.333333 | L62: 0 | N62: -28.333333 | Q62: 0 | S62: 0
A63: Véhicules neufsPapeterie | B63: Véhicules neufs | C63: Papeterie | F63: 741.43089 | L63: 264.09 | N63: -477.34089 | Q63: 1062.18 | S63: -798.09
A64: Véhicules neufsTéléphone | B64: Véhicules neufs | C64: Téléphone | F64: 344.80198 | L64: 367.93 | N64: 23.128015 | Q64: 328.45 | S64: 39.48
A65: Véhicules neufsFrais postaux | B65: Véhicules neufs | C65: Frais postaux | F65: 102.8224 | L65: 135.09 | N65: 32.267605 | Q65: 32.96 | S65: 102.13
A66: Véhicules neufsDivers | B66: Véhicules neufs | C66: Divers | F66: 201.17039 | L66: 735.59 | N66: 534.41961 | Q66: 95.63 | S66: 639.96
... A68: Véhicules neufsFrais bancaires | B68: Véhicules neufs | C68: Frais bancaires | F68: 3024.0505 | L68: 3986.37 | N68: 962.3195 | Q68: 4138.41 | S68: -152.04
A69: Véhicules neufs[...] | B69: Véhicules neufs | C69: [...] | F69: 0 | N69: 0 | Q69: 0 | S69: 0
A70: Véhicules neufs[...] | B70: Véhicules neufs | C70: [...] | F70: 0 | L70: 0 | N70: 0 | Q70: 0 | S70: 0
A71: Véhicules neufs[...] | B71: Véhicules neufs | C71: [...] | F71: 0 | L71: 0 | N71: 0 | Q71: 0 | S71: 0
A72: Véhicules neufsTOTAL SEMI-FIXES | B72: Véhicules neufs | C72: TOTAL SEMI-FIXES | D72: % brut | E72: 0.16660032 | F72: 31870.554 | J72: % brut | K72: 0.33868901 | L72: 38007.2 | N72: 6136.646 | O72: % brut | P72: 0.28043842 | Q72: 34298.18 | S72: 3709.02
A73: Véhicules neufs | B73: Véhicules neufs
A74: Véhicules neufsTOTAL DES DÉPENSES | B74: Véhicules neufs | C74: TOTAL DES DÉPENSES | D74: % brut | E74: 1.1145828 | F74: 213219.12 | J74: % brut | K74: 1.5796013 | L74: 177260.62 | N74: -35958.498 | O74: % brut | P74: 1.1461031 | Q74: 140170.7 | S74: 37089.92
A75: Véhicules neufsProgramme neuf 1 | B75: Véhicules neufs | C75: Programme neuf 1 | F75: 25000 | L75: 11400 | N75: -13600 | Q75: 20000
A76: Véhicules neufsProgramme neuf 2 | B76: Véhicules neufs | C76: Programme neuf 2 | F76: 0 | L76: 0 | N76: 0 | Q76: 0 | S76: 0
A77: Véhicules neufsProgramme neuf 3 | B77: Véhicules neufs | C77: Programme neuf 3 | F77: 0 | L77: 0 | N77: 0 | Q77: 0 | S77: 0
A78: Véhicules neufsHoldbacks | B78: Véhicules neufs | C78: Holdbacks | E78: 1375.5035 | F78: 78403.701 | J78: 0.99316011 | K78: 1366.0952 | L78: 57376 | N78: -21027.701 | Q78: 54053 | S78: 3323
A79: Véhicules neufs[...] | B79: Véhicules neufs | C79: [...] | F79: 0 | L79: 0 | N79: 0 | Q79: 0 | S79: 0
A80: Véhicules neufs[...] | B80: Véhicules neufs | C80: [...] | F80: 0 | L80: 0 | N80: 0 | Q80: 0 | S80: 0
A81: Véhicules neufs[...] | B81: Véhicules neufs | C81: [...] | F81: 0 | L81: 0 | N81: 0 | Q81: 0 | S81: 0
A82: Véhicules neufsFrais administration | B82: Véhicules neufs | C82: Frais administration | D82: 0.95 | E82: 474.05 | F82: 26546.8 | J82: 1.0548523 | K82: 500 | L82: 21000 | N82: -5546.8 | Q82: 16497 | S82: 4503
A83: Véhicules neufsAUTRES REVENUS | B83: Véhicules neufs | C83: AUTRES REVENUS | F83: 129950.5 | L83: 89776 | N83: -40174.501 | Q83: 90550 | S83: 7826
A84: Véhicules neufs | B84: Véhicules neufs
A85: Véhicules neufsPROFIT DÉPARTEMENTAL | B85: Véhicules neufs | C85: PROFIT DÉPARTEMENTAL | F85: 108030.86 | L85: 24733.96 | N85: -83296.903 | P85: 0.033524583 | Q85: 72681.3 | S85: -39347.34
C89: Volks | K89: Véhicules usagés | S89: Réalisé, Décembre 2025
D91: BUDGET ORIGINAL | J91: RÉALISATION | M91: ÉCART réel / Budget | O91: ANNÉE PRÉCÉDENTE | R91: ECART (réel/ Ann.Préc.)
D92: UNITE | E92: $P/UNITÉ | F92: $PROFITS | J92: UNITÉS | K92: $P/UNITE | L92: $PROFITS | M92: UNITÉS | N92: $PROFITS | O92: UNITE | P92: $P/UNITÉ | Q92: $PROFITS | R92: UNITÉS | S92: $PROFITS
A93: Véhicules usagésVentes nettes | B93: Véhicules usagés | C93: Ventes nettes | F93: 1593352.4 | L93: 1128983.9 | Q93: 803576.36
A94: Véhicules usagésCertifié | B94: Véhicules usagés | C94: Certifié | D94: 20 | E94: 1400 | F94: 28000 | J94: 21 | K94: 619.89381 | L94: 13017.77 | M94: 1 | N94: -14982.23 | O94: 17 | P94: 1130.9829 | Q94: 19226.71 | R94: 4 | S94: -6208.94
A95: Véhicules usagésNon Certifié | B95: Véhicules usagés | C95: Non Certifié | D95: 3 | E95: 1800 | F95: 5400 | J95: 0 | K95: 0 | L95: -556.43 | M95: -3 | N95: -5956.43 | O95: 0 | P95: 0 | Q95: -471.43 | R95: 0 | S95: -85
A96: Véhicules usagésAutres Marques | B96: Véhicules usagés | C96: Autres Marques | D96: 3 | E96: 1500 | F96: 4500 | J96: 1 | K96: 4147.3 | L96: 4147.3 | M96: -2 | N96: -352.7 | O96: 1 | P96: 2147.6 | Q96: 2147.6 | R96: 0 | S96: 1999.7
A97: Véhicules usagésTotal Usagés | B97: Véhicules usagés | C97: Total Usagés | D97: 26 | E97: 1457.6923 | F97: 37900 | J97: 22 | K97: 754.93818 | L97: 16608.64 | M97: -4 | N97: -21291.36 | O97: 18 | P97: 1161.2711 | Q97: 20902.88 | R97: 4 | S97: -6293.94
A98: Véhicules usagés | B98: Véhicules usagés | E98: 0 | M98: -0.15384615 | N98: -0.56177731 | P98: 0 | R98: 0.22222222 | S98: -0.30110396
A99: Véhicules usagés | B99: Véhicules usagés | D99: 0 | E99: 0 | F99: 0
A100: Véhicules usagésVentes au Gros | B100: Véhicules usagés | C100: Ventes au Gros | D100: 35 | E100: 400 | F100: 14000 | J100: 28 | K100: -462.74821 | L100: -12956.95 | M100: -7 | N100: -26956.95 | O100: 22 | P100: -477.45 | Q100: -10503.9 | R100: 6 | S100: -2453.05
A101: Véhicules usagés | B101: Véhicules usagés
A102: Véhicules usagésRev. Finances | B102: Véhicules usagés | C102: Rev. Finances | D102: 0 | E102: 0 | F102: 15600 | K102: 150.59455 | L102: 3313.08 | N102: -12286.92 | Q102: 3906.17 | R102: -150.59455 | S102: -593.09
A103: Véhicules usagésRev. Protections | B103: Véhicules usagés | C103: Rev. Protections | D103: 0 | E103: 0 | F103: 32500 | K103: 1798.9982 | L103: 39577.96 | N103: 7077.96 | Q103: 28363.39 | R103: -1798.9982 | S103: 11214.57
A104: Véhicules usagésRev. Autres | B104: Véhicules usagés | C104: Rev. Autres | D104: 0 | E104: 0 | F104: 1300 | K104: 77.349545 | L104: 1701.69 | N104: 401.69 | Q104: 0 | R104: -77.349545 | S104: 1701.69
A105: Véhicules usagésTotal F&I | B105: Véhicules usagés | C105: Total F&I | D105: 26 | E105: 1900 | F105: 49400 | J105: 22 | K105: 2026.9423 | L105: 44592.73 | M105: -4 | N105: -4807.27 | O105: 18 | P105: 1792.7533 | Q105: 32269.56 | S105: 12323.17
...

Sheet END
