Workbook
Name _Dates_Conc: [1]Dealers!$BF$37:$KA$63
Name _scen: '[1]Scen & Sens'!$E$26
Name _scen1: '[1]Scen & Sens'!$E$27
Name _scen2: '[1]Scen & Sens'!$E$28
Name _SCenarios: '[1]Scen & Sens'!$J$26:$O$26
Name _Sens1: '[1]Scen & Sens'!$F$9
Name _Sens2: '[1]Scen & Sens'!$F$10
Name _sensRes1: '[1]Scen & Sens'!$E$15
Name _sensRes2: '[1]Scen & Sens'!$E$16
Name _sensRes3: '[1]Scen & Sens'!$E$17
Name _sensRes4: '[1]Scen & Sens'!$E$18
Name _sensRes5: '[1]Scen & Sens'!$E$19
Name _sensRes6: '[1]Scen & Sens'!$E$20
Name _sensRes7: '[1]Scen & Sens'!$E$21
Name DateRange: [1]Volkswagen!$BF$6:$DY$6
Name Monetary_Unit: [1]Parameters!$B$15
Name Months: [1]Parameters!$E$9:$E$20
Name Rng_Dealers_Names: [1]!Tbl_Dealers[Dealer Name]
Name Rng_Dlr_Dates: [1]!Tbl_V_Dlr_Dates[Date]
Name Ticker: #REF!
Name Ticker: #REF!
Name Ticker: #REF!
Name Titre: [1]Front!$A$9

Sheet Paramètre
B3: Quarter
B6: BUDGET | F6: BUDGET RÉVISÉ | J6: ACTUAL | N6: LAST YEAR
B7: Ventes | C7: Profits bruts | D7: BAIIA | E7: EBIT | F7: Ventes | G7: Profits bruts | H7: BAIIA | I7: EBIT | J7: Ventes | K7: Profits bruts | L7: BAIIA | M7: EBIT | N7: Ventes | O7: Profits bruts | P7: BAIIA | Q7: EBIT
A8: CTRL | B8: =+B9-B10 -> #REF! | C8: =+C9-C10 -> #REF! | D8: =+D9-D10 -> #REF! | E8: =+E9-E10 -> #REF! | F8: =+F9-F10 -> #REF! | G8: =+G9-G10 -> #REF! | H8: =+H9-H10 -> #REF! | I8: =+I9-I10 -> #REF! | ... Q8: =+Q9-Q10 -> #REF!
A9: CONSO | B9: =+Conso!$Z$405 -> 18083868 | C9: =+Conso!$Z$406 -> 2262964.7 | D9: =+Conso!$Z$482 -> 548567.16 | E9: =+Conso!$Z$497 -> 423860.66 | F9: =+Conso!$AC$405 -> 0 | G9: =+Conso!$AC$406 -> 0 | H9: =+Conso!$AC$482 -> 0 | I9: =+Conso!$AC$497 -> 0 | J9: =+Conso!$AF$405 -> 14843581 | K9: =+Conso!$AF$406 -> 2095633.8 | L9: =+Conso!$AF$482 -> 482154.45 | M9: =+Conso!$AF$497 -> 357447.45 | N9: =+Conso!$AL$405 -> 16428062 | O9: =+Conso!$AL$406 -> 1897181 | P9: =+Conso!$AL$482 -> 366005.68 | Q9: =+Conso!$AL$497 -> 361195.19
A10: TOTAL | B10: =+SUM(B11:B13) -> #REF! | C10: =+SUM(C11:C13) -> #REF! | D10: =+SUM(D11:D13) -> #REF! | E10: =+SUM(E11:E13) -> #REF! | F10: =+SUM(F11:F13) -> #REF! | G10: =+SUM(G11:G13) -> #REF! | H10: =+SUM(H11:H13) -> #REF! | I10: =+SUM(I11:I13) -> #REF! | ... Q10: =+SUM(Q11:Q13) -> #REF!
A11: Mois 1 | B11: =+#REF! -> #REF! | C11: =+#REF! -> #REF! | D11: =+#REF! -> #REF! | E11: =+#REF! -> #REF! | F11: =+#REF! -> #REF! | G11: =+#REF! -> #REF! | H11: =+#REF! -> #REF! | I11: =+#REF! -> #REF! | ... Q11: =+#REF! -> #REF!
A12: Mois 2 | B12: =+#REF! -> #REF! | C12: =+#REF! -> #REF! | D12: =+#REF! -> #REF! | E12: =+#REF! -> #REF! | F12: =+#REF! -> #REF! | G12: =+#REF! -> #REF! | H12: =+#REF! -> #REF! | I12: =+#REF! -> #REF! | ... Q12: =+#REF! -> #REF!
A13: Mois 3 | B13: =+#REF! -> #REF! | C13: =+#REF! -> #REF! | D13: =+#REF! -> #REF! | E13: =+#REF! -> #REF! | F13: =+#REF! -> #REF! | G13: =+#REF! -> #REF! | H13: =+#REF! -> #REF! | I13: =+#REF! -> #REF! | ... Q13: =+#REF! -> #REF!

Sheet Conso
C1: Conso | K1: Véhicules neufs | S1: =CONCATENATE("Réalisé"," ",Paramètre!$C$2," ",Paramètre!$C$3) -> Réalisé
D2: X | E2: O | F2: U | G2: X | H2: O | I2: U
D3: BUDGET ORIGINAL | G3: BUDGET REVISE | J3: RÉALISATION | M3: ÉCART réel / original | O3: ANNÉE PRÉCÉDENTE | R3: ÉCART réel / année précédente
D4: UNITE | E4: $P/UNITÉ | F4: $PROFITS | G4: UNITE | H4: $P/UNITÉ | I4: $PROFITS | J4: UNITE | K4: $P/UNITE | L4: $PROFITS | M4: UNITÉ | N4: $PROFITS | O4: UNITE | P4: $P/UNITE | Q4: $PROFITS | R4: UNITE | S4: $PROFITS
A5: =+B5&C5 -> Véhicules neufsVentes nettes | B5: =+$K$1 -> Véhicules neufs | C5: Ventes nettes | F5: =+SUM(START:END!F5) -> 10167353 | I5: =+SUM(START:END!I5) -> 0 | L5: =+SUM(START:END!L5) -> 8306066.7 | Q5: =+SUM(START:END!Q5) -> 9890070
A6: =+B6&C6 -> Véhicules neufsAutos détail | B6: =+$K$1 -> Véhicules neufs | C6: Autos détail | D6: =+SUM(START:END!D6) -> 50 | E6: =IF(D6=0,0,F6/D6) -> 1953.6492 | F6: =+SUM(START:END!F6) -> 97682.458 | G6: =+SUM(START:END!G6) -> 0 | H6: =IF(G6=0,0,I6/G6) -> 0 | I6: =+SUM(START:END!I6) -> 0 | J6: =+SUM(START:END!J6) -> 46 | K6: =IF(J6=0,0,L6/J6) -> 2161.2191 | L6: =+SUM(START:END!L6) -> 99416.08 | M6: =J6-D6 -> -4 | N6: =L6-F6 -> 1733.6216 | O6: =+SUM(START:END!O6) -> 51 | P6: =IF(O6=0,0,Q6/O6) -> 1956.158 | Q6: =+SUM(START:END!Q6) -> 99764.06 | R6: =J6-O6 -> -5 | S6: =L6-Q6 -> -347.98
A7: =+B7&C7 -> Véhicules neufsCamions détail | B7: =+$K$1 -> Véhicules neufs | C7: Camions détail | D7: =+SUM(START:END!D7) -> 135 | E7: =IF(D7=0,0,F7/D7) -> 2435.9047 | F7: =+SUM(START:END!F7) -> 328847.13 | G7: =+SUM(START:END!G7) -> 0 | H7: =IF(G7=0,0,I7/G7) -> 0 | I7: =+SUM(START:END!I7) -> 0 | J7: =+SUM(START:END!J7) -> 103 | K7: =IF(J7=0,0,L7/J7) -> 2274.877 | L7: =+SUM(START:END!L7) -> 234312.33 | M7: =J7-D7 -> -32 | N7: =L7-F7 -> -94534.801 | O7: =+SUM(START:END!O7) -> 127 | P7: =IF(O7=0,0,Q7/O7) -> 2623.2423 | Q7: =+SUM(START:END!Q7) -> 333151.77 | R7: =J7-O7 -> -24 | S7: =L7-Q7 -> -98839.44
A8: =+B8&C8 -> Véhicules neufsSprinter | B8: =+$K$1 -> Véhicules neufs | C8: Sprinter | D8: =+SUM(START:END!D8) -> 0 | E8: =IF(D8=0,0,F8/D8) -> 0 | F8: =+SUM(START:END!F8) -> 0 | G8: =+SUM(START:END!G8) -> 0 | H8: =IF(G8=0,0,I8/G8) -> 0 | I8: =+SUM(START:END!I8) -> 0 | J8: =+SUM(START:END!J8) -> 0 | K8: =IF(J8=0,0,L8/J8) -> 0 | L8: =+SUM(START:END!L8) -> 0 | M8: =J8-D8 -> 0 | N8: =L8-F8 -> 0 | O8: =+SUM(START:END!O8) -> 0 | P8: =IF(O8=0,0,Q8/O8) -> 0 | Q8: =+SUM(START:END!Q8) -> 0 | R8: =J8-O8 -> 0 | S8: =L8-Q8 -> 0
A9: =+B9&C9 -> Véhicules neufsMoto détail | B9: =+$K$1 -> Véhicules neufs | C9: Moto détail | D9: =+SUM(START:END!D9) -> 0 | E9: =IF(D9=0,0,F9/D9) -> 0 | F9: =+SUM(START:END!F9) -> 0 | G9: =+SUM(START:END!G9) -> 0 | H9: =IF(G9=0,0,I9/G9) -> 0 | I9: =+SUM(START:END!I9) -> 0 | J9: =+SUM(START:END!J9) -> 0 | K9: =IF(J9=0,0,L9/J9) -> 0 | L9: =+SUM(START:END!L9) -> 0 | M9: =J9-D9 -> 0 | N9: =L9-F9 -> 0 | O9: =+SUM(START:END!O9) -> 0 | P9: =IF(O9=0,0,Q9/O9) -> 0 | Q9: =+SUM(START:END!Q9) -> 0 | R9: =J9-O9 -> 0 | S9: =L9-Q9 -> 0
A10: =+B10&C10 -> Véhicules neufs[...] | B10: =+$K$1 -> Véhicules neufs | C10: [...] | D10: =+SUM(START:END!D10) -> 0 | E10: =IF(D10=0,0,F10/D10) -> 0 | F10: =+SUM(START:END!F10) -> 0 | G10: =+SUM(START:END!G10) -> 0 | H10: =IF(G10=0,0,I10/G10) -> 0 | I10: =+SUM(START:END!I10) -> 0 | J10: =+SUM(START:END!J10) -> 0 | K10: =IF(J10=0,0,L10/J10) -> 0 | L10: =+SUM(START:END!L10) -> 0 | M10: =J10-G10 -> 0 | N10: =L10-I10 -> 0 | O10: =+SUM(START:END!O10) -> 0 | P10: =IF(O10=0,0,Q10/O10) -> 0 | Q10: =+SUM(START:END!Q10) -> 0 | R10: =J10-O10 -> 0 | S10: =L10-Q10 -> 0
A11: =+B11&C11 -> Véhicules neufs[...] | B11: =+$K$1 -> Véhicules neufs | C11: [...] | D11: =+SUM(START:END!D11) -> 0 | E11: =IF(D11=0,0,F11/D11) -> 0 | F11: =+SUM(START:END!F11) -> 0 | G11: =+SUM(START:END!G11) -> 0 | H11: =IF(G11=0,0,I11/G11) -> 0 | I11: =+SUM(START:END!I11) -> 0 | J11: =+SUM(START:END!J11) -> 0 | K11: =IF(J11=0,0,L11/J11) -> 0 | L11: =+SUM(START:END!L11) -> 0 | M11: =J11-G11 -> 0 | N11: =L11-I11 -> 0 | O11: =+SUM(START:END!O11) -> 0 | P11: =IF(O11=0,0,Q11/O11) -> 0 | Q11: =+SUM(START:END!Q11) -> 0 | R11: =J11-O11 -> 0 | S11: =L11-Q11 -> 0
A12: =+B12&C12 -> Véhicules neufs[...] | B12: =+$K$1 -> Véhicules neufs | C12: [...] | D12: =+SUM(START:END!D12) -> 0 | E12: =IF(D12=0,0,F12/D12) -> 0 | F12: =+SUM(START:END!F12) -> 0 | G12: =+SUM(START:END!G12) -> 0 | H12: =IF(G12=0,0,I12/G12) -> 0 | I12: =+SUM(START:END!I12) -> 0 | J12: =+SUM(START:END!J12) -> 0 | K12: =IF(J12=0,0,L12/J12) -> 0 | L12: =+SUM(START:END!L12) -> 0 | M12: =J12-G12 -> 0 | N12: =L12-I12 -> 0 | O12: =+SUM(START:END!O12) -> 0 | P12: =IF(O12=0,0,Q12/O12) -> 0 | Q12: =+SUM(START:END!Q12) -> 0 | R12: =J12-O12 -> 0 | S12: =L12-Q12 -> 0
A13: =+B13&C13 -> Véhicules neufsTotal Neufs | B13: =+$K$1 -> Véhicules neufs | C13: Total Neufs | D13: =+SUM(D6:D12) -> 185 | E13: =IF(D13<=0,0,F13/D13) -> 2305.5654 | F13: =+SUM(F6:F12) -> 426529.59 | G13: =+SUM(G6:G12) -> 0 | H13: =IF(G13<=0,0,I13/G13) -> 0 | I13: =+SUM(I6:I12) -> 0 | J13: =+SUM(J6:J12) -> 149 | K13: =IF(J13<=0,0,L13/J13) -> 2239.788 | L13: =+SUM(L6:L12) -> 333728.41 | M13: =+SUM(M6:M12) -> -36 | N13: =+SUM(N6:N12) -> -92801.18 | O13: =+SUM(O6:O12) -> 178 | P13: =IF(O13<=0,0,Q13/O13) -> 2432.1114 | Q13: =+SUM(Q6:Q12) -> 432915.83 | R13: =+SUM(R6:R12) -> -29 | S13: =+SUM(S6:S12) -> -99187.42
A14: =+B14&C14 -> Véhicules neufs | B14: =+$K$1 -> Véhicules neufs | N14: =IF(F13=0,0,N13/F13) -> -0.21757267 | R14: =R13/O13 -> -0.16292135 | S14: =IF(Q13=0,0,(S13/Q13)) -> -0.22911479
A15: =+B15&C15 -> Véhicules neufsEx-Démos et courtoisies | B15: =+$K$1 -> Véhicules neufs | C15: Ex-Démos et courtoisies | D15: =+SUM(START:END!D15) -> 9 | E15: =IF(D15=0,0,F15/D15) -> 1534.7521 | F15: =+SUM(START:END!F15) -> 13812.769 | G15: =+SUM(START:END!G15) -> 0 | H15: =IF(G15=0,0,I15/G15) -> 0 | I15: =+SUM(START:END!I15) -> 0 | J15: =+SUM(START:END!J15) -> 13 | K15: =IF(J15=0,0,L15/J15) -> 1451.6415 | L15: =+SUM(START:END!L15) -> 18871.34 | M15: =J15-D15 -> 4 | N15: =L15-F15 -> 5058.5707 | O15: =+SUM(START:END!O15) -> 9 | P15: =IF(O15=0,0,Q15/O15) -> 1653.9344 | Q15: =+SUM(START:END!Q15) -> 14885.41 | R15: =J15-O15 -> 4 | S15: =L15-Q15 -> 3985.93
A16: =+B16&C16 -> Véhicules neufs | B16: =+$K$1 -> Véhicules neufs
A17: =+B17&C17 -> Véhicules neufsFlottes | B17: =+$K$1 -> Véhicules neufs | C17: Flottes | D17: =+SUM(START:END!D17) -> 6 | E17: =IF(D17=0,0,F17/D17) -> 2393.8521 | F17: =+SUM(START:END!F17) -> 14363.113 | G17: =+SUM(START:END!G17) -> 0 | H17: =IF(G17=0,0,I17/G17) -> 0 | I17: =+SUM(START:END!I17) -> 0 | J17: =+SUM(START:END!J17) -> 0 | K17: =IF(J17=0,0,L17/J17) -> 0 | L17: =+SUM(START:END!L17) -> 0 | M17: =J17-D17 -> -6 | N17: =L17-F17 -> -14363.113 | O17: =+SUM(START:END!O17) -> 0 | P17: =IF(O17=0,0,Q17/O17) -> 0 | Q17: =+SUM(START:END!Q17) -> 0 | R17: =J17-O17 -> 0 | S17: =L17-Q17 -> 0
A18: =+B18&C18 -> Véhicules neufs | B18: =+$K$1 -> Véhicules neufs
A19: =+B19&C19 -> Véhicules neufsRachat bail | B19: =+$K$1 -> Véhicules neufs | C19: Rachat bail | F19: =+SUM(START:END!F19) -> 20570 | I19: =+SUM(START:END!I19) -> 0 | L19: =+SUM(START:END!L19) -> 23810.21 | N19: =L19-F19 -> 3240.21 | Q19: =+SUM(START:END!Q19) -> 22060.37 | R19: =O19-K19 -> 0 | S19: =L19-Q19 -> 1749.84
A20: =+B20&C20 -> Véhicules neufs | B20: =+$K$1 -> Véhicules neufs
A21: =+B21&C21 -> Véhicules neufsRev. Finances | B21: =+$K$1 -> Véhicules neufs | C21: Rev. Finances | D21: 0 | E21: =IF(D21=0,0,F21/D21) -> 0 | F21: =+SUM(START:END!F21) -> 9700 | G21: 0 | H21: =IF(G21=0,0,I21/G21) -> 0 | I21: =+SUM(START:END!I21) -> 0 | K21: =IF(J13=0,0,L21/(J13+J15)) -> 8.1129012 | L21: =+SUM(START:END!L21) -> 1314.29 | N21: =L21-F21 -> -8385.71 | P21: =IF(O13=0,0,Q21/(O13+O15)) -> 4.2780749 | Q21: =+SUM(START:END!Q21) -> 800 | R21: =O21-K21 -> -8.1129012 | S21: =L21-Q21 -> 514.29
A22: =+B22&C22 -> Véhicules neufsRev. Protections | B22: =+$K$1 -> Véhicules neufs | C22: Rev. Protections | D22: 0 | E22: =IF(D22=0,0,F22/D22) -> 0 | F22: =+SUM(START:END!F22) -> 180420 | G22: 0 | H22: =IF(G22=0,0,I22/G22) -> 0 | I22: =+SUM(START:END!I22) -> 0 | K22: =IF(J13=0,0,L22/(J13+J15)) -> 1014.0912 | L22: =+SUM(START:END!L22) -> 164282.77 | N22: =L22-F22 -> -16137.23 | P22: =IF(O13=0,0,Q22/(O13+O15)) -> 777.99171 | Q22: =+SUM(START:END!Q22) -> 145484.45 | R22: =O22-K22 -> -1014.0912 | S22: =L22-Q22 -> 18798.32
A23: =+B23&C23 -> Véhicules neufsRev. Autres | B23: =+$K$1 -> Véhicules neufs | C23: Rev. Autres | D23: 0 | E23: =IF(D23=0,0,F23/D23) -> 0 | F23: =+SUM(START:END!F23) -> 3880 | G23: 0 | H23: =IF(G23=0,0,I23/G23) -> 0 | I23: =+SUM(START:END!I23) -> 0 | K23: =IF(J13=0,0,L23/(J13+J15)) -> 1.6458642 | L23: =+SUM(START:END!L23) -> 266.63 | N23: =L23-F23 -> -3613.37 | P23: =IF(O13=0,0,Q23/(O13+O15)) -> 21.696417 | Q23: =+SUM(START:END!Q23) -> 4057.23 | R23: =O23-K23 -> -1.6458642 | S23: =L23-Q23 -> -3790.6
A24: =+B24&C24 -> Véhicules neufsTotal F&I | B24: =+$K$1 -> Véhicules neufs | C24: Total F&I | D24: =+D15+D13 -> 194 | E24: =IF(D24<=0,0,F24/D24) -> 1000 | F24: =F21+F22+F23 -> 194000 | G24: =+G15+G13 -> 0 | H24: =IF(G24<=0,0,I24/G24) -> 0 | I24: =I21+I22+I23 -> 0 | J24: =+J15+J13 -> 162 | K24: =IF(J24<=0,0,L24/J24) -> 1023.8499 | L24: =L21+L22+L23 -> 165863.69 | M24: =+M15+M13 -> -32 | N24: =N21+N22+N23 -> -28136.31 | O24: =+O15+O13 -> 187 | P24: =IF(O24<=0,0,Q24/O24) -> 803.9662 | Q24: =Q21+Q22+Q23 -> 150341.68 | S24: =L24-Q24 -> 15522.01
A25: =+B25&C25 -> Véhicules neufs | B25: =+$K$1 -> Véhicules neufs | S25: =IF(Q24=0,0,(S24/Q24)) -> 0.10324489
A26: =+B26&C26 -> Véhicules neufs | B26: =+$K$1 -> Véhicules neufs
A27: =+B27&C27 -> Véhicules neufsTotal Dépt. Neufs | B27: =+$K$1 -> Véhicules neufs | C27: Total Dépt. Neufs | D27: =+D13+D15+D17 -> 200 | E27: =IF(D27<=0,0,F27/D27) -> 3346.3774 | F27: =F13+F17+F24+F19+F15 -> 669275.47 | G27: =+G13+G15+G17 -> 0 | H27: =IF(G27<=0,0,I27/G27) -> 0 | I27: =I13+I17+I24+I19+I15 -> 0 | J27: =+J13+J15+J17 -> 162 | K27: =IF(J27<=0,0,L27/J27) -> 3347.3682 | L27: =L13+L17+L24+L19+L15 -> 542273.65 | M27: =+M13+M15+M17 -> -38 | N27: =N13+N17+N24+N19+N15 -> -127001.82 | O27: =+O13+O15+O17 -> 187 | P27: =IF(O27<=0,0,Q27/O27) -> 3316.5951 | Q27: =Q13+Q17+Q24+Q19+Q15 -> 620203.29 | R27: =J27-O27 -> -25 | S27: =L27-Q27 -> -77929.64
A28: =+B28&C28 -> Véhicules neufs | B28: =+$K$1 -> Véhicules neufs | M28: =M27/D27 -> -0.19 | N28: =N27/F27 -> -0.18976016 | R28: =R27/O27 -> -0.13368984 | S28: =IF(Q27=0,0,S27/Q27) -> -0.12565177
A29: =+B29&C29 -> Véhicules neufs | B29: =+$K$1 -> Véhicules neufs
A30: =+B30&C30 -> Véhicules neufsDEPENSES | B30: =+$K$1 -> Véhicules neufs | C30: DEPENSES
A31: =+B31&C31 -> Véhicules neufsComm. vendeurs | B31: =+$K$1 -> Véhicules neufs | C31: Comm. vendeurs | E31: =F31/D$24 -> 755.06949 | F31: =+SUM(START:END!F31) -> 146483.48 | H31: =I31/G$24 -> #DIV/0! | I31: =+SUM(START:END!I31) -> 0 | J31: =L31/L13 -> 0.34752193 | K31: =IF(L31=0,0,L31/J$24) -> 715.91321 | L31: =+SUM(START:END!L31) -> 115977.94 | N31: =L31-F31 -> -30505.541 | P31: =IF(Q31=0,0,Q31/O$24) -> 584.55818 | Q31: =+SUM(START:END!Q31) -> 109312.38 | S31: =L31-Q31 -> 6665.56
A32: =+B32&C32 -> Véhicules neufsComm. F&I | B32: =+$K$1 -> Véhicules neufs | C32: Comm. F&I | E32: =F32/D$24 -> 280 | F32: =+SUM(START:END!F32) -> 54320 | H32: =I32/G$24 -> #DIV/0! | I32: =+SUM(START:END!I32) -> 0 | J32: =L32/L24 -> 0.26720592 | K32: =IF(L32=0,0,L32/J$24) -> 273.57877 | L32: =+SUM(START:END!L32) -> 44319.76 | N32: =L32-F32 -> -10000.24 | P32: =IF(Q32=0,0,Q32/O$24) -> 186.83203 | Q32: =+SUM(START:END!Q32) -> 34937.59 | S32: =L32-Q32 -> 9382.17
A33: =+B33&C33 -> Véhicules neufsFrais de livraison | B33: =+$K$1 -> Véhicules neufs | C33: Frais de livraison | E33: =F33/D$24 -> 115 | F33: =+SUM(START:END!F33) -> 22310 | H33: =I33/G$24 -> #DIV/0! | I33: =+SUM(START:END!I33) -> 0 | K33: =IF(L33=0,0,L33/J$24) -> 140.65593 | L33: =+SUM(START:END!L33) -> 22786.26 | N33: =L33-F33 -> 476.26 | P33: =IF(Q33=0,0,Q33/O$24) -> 108.74684 | Q33: =+SUM(START:END!Q33) -> 20335.66 | S33: =L33-Q33 -> 2450.6
A34: =+B34&C34 -> Véhicules neufsService gratuit 1 | B34: =+$K$1 -> Véhicules neufs | C34: Service gratuit 1 | E34: =F34/D$24 -> 10 | F34: =+SUM(START:END!F34) -> 1940 | H34: =I34/G$24 -> #DIV/0! | I34: =+SUM(START:END!I34) -> 0 | K34: =IF(L34=0,0,L34/J$24) -> 3.7731481 | L34: =+SUM(START:END!L34) -> 611.25 | N34: =L34-F34 -> -1328.75 | P34: =IF(Q34=0,0,Q34/O$24) -> 6.8069519 | Q34: =+SUM(START:END!Q34) -> 1272.9 | S34: =L34-Q34 -> -661.65
A35: =+B35&C35 -> Véhicules neufsEntretien stock | B35: =+$K$1 -> Véhicules neufs | C35: Entretien stock | E35: =F35/D$24 -> 120.75 | F35: =+SUM(START:END!F35) -> 23425.5 | H35: =I35/G$24 -> #DIV/0! | I35: =+SUM(START:END!I35) -> 0 | K35: =IF(L35=0,0,L35/J$24) -> 156.02105 | L35: =+SUM(START:END!L35) -> 25275.41 | N35: =L35-F35 -> 1849.91 | P35: =IF(Q35=0,0,Q35/O$24) -> 156.67278 | Q35: =+SUM(START:END!Q35) -> 29297.81 | S35: =L35-Q35 -> -4022.4
A36: =+B36&C36 -> Véhicules neufsPublicité 1 | B36: =+$K$1 -> Véhicules neufs | C36: Publicité 1 | E36: =F36/D$24 -> 77.247423 | F36: =+SUM(START:END!F36) -> 14986 | H36: =I36/G$24 -> #DIV/0! | I36: =+SUM(START:END!I36) -> 0 | K36: =IF(L36=0,0,L36/J$24) -> 179.76198 | L36: =+SUM(START:END!L36) -> 29121.44 | N36: =L36-F36 -> 14135.44 | P36: =IF(Q36=0,0,Q36/O$24) -> 173.37182 | Q36: =+SUM(START:END!Q36) -> 32420.53 | S36: =L36-Q36 -> -3299.09
A37: =+B37&C37 -> Véhicules neufsIntérêt de gros | B37: =+$K$1 -> Véhicules neufs | C37: Intérêt de gros | E37: =F37/D$24 -> 579.73542 | F37: =+SUM(START:END!F37) -> 112468.67 | H37: =I37/G$24 -> #DIV/0! | I37: =+SUM(START:END!I37) -> 0 | K37: =IF(L37=0,0,L37/J$24) -> 130.63019 | L37: =+SUM(START:END!L37) -> 21162.09 | N37: =L37-F37 -> -91306.581 | P37: =IF(Q37=0,0,Q37/O$24) -> 654.65048 | Q37: =+SUM(START:END!Q37) -> 122419.64 | S37: =L37-Q37 -> -101257.55
A38: =+B38&C38 -> Véhicules neufs[...] | B38: =+$K$1 -> Véhicules neufs | C38: [...] | E38: =F38/D$24 -> 0 | F38: =+SUM(START:END!F38) -> 0 | H38: =I38/G$24 -> #DIV/0! | I38: =+SUM(START:END!I38) -> 0 | K38: =IF(L38=0,0,L38/J$24) -> 0 | L38: =+SUM(START:END!L38) -> 0 | N38: =L38-I38 -> 0 | P38: =IF(Q38=0,0,Q38/O$24) -> 0 | Q38: =+SUM(START:END!Q38) -> 0 | S38: =L38-Q38 -> 0
A39: =+B39&C39 -> Véhicules neufs[...] | B39: =+$K$1 -> Véhicules neufs | C39: [...] | E39: =F39/D$24 -> 0 | F39: =+SUM(START:END!F39) -> 0 | H39: =I39/G$24 -> #DIV/0! | I39: =+SUM(START:END!I39) -> 0 | K39: =IF(L39=0,0,L39/J$24) -> 0 | L39: =+SUM(START:END!L39) -> 0 | N39: =L39-I39 -> 0 | P39: =IF(Q39=0,0,Q39/O$24) -> 0 | Q39: =+SUM(START:END!Q39) -> 0 | S39: =L39-Q39 -> 0
A40: =+B40&C40 -> Véhicules neufs[...] | B40: =+$K$1 -> Véhicules neufs | C40: [...] | E40: =F40/D$24 -> 0 | F40: =+SUM(START:END!F40) -> 0 | H40: =I40/G$24 -> #DIV/0! | I40: =+SUM(START:END!I40) -> 0 | K40: =IF(L40=0,0,L40/J$24) -> 0 | L40: =+SUM(START:END!L40) -> 0 | N40: =L40-I40 -> 0 | P40: =IF(Q40=0,0,Q40/O$24) -> 0 | Q40: =+SUM(START:END!Q40) -> 0 | S40: =L40-Q40 -> 0
A41: =+B41&C41 -> Véhicules neufsTOTAL VARIABLES | B41: =+$K$1 -> Véhicules neufs | C41: TOTAL VARIABLES | D41: % brut | E41: =F41/F$27 -> 0.56170242 | F41: =SUM(F31:F40) -> 375933.65 | G41: % brut | H41: =I41/I$27 -> #DIV/0! | I41: =SUM(I31:I40) -> 0 | J41: % brut | K41: =L41/L$27 -> 0.47808731 | L41: =SUM(L31:L40) -> 259254.15 | N41: =SUM(N31:N40) -> -116679.5 | O41: % brut | P41: =Q41/Q$27 -> 0.56432546 | Q41: =SUM(Q31:Q40) -> 349996.51 | S41: =L41-Q41 -> -90742.36
A42: =+B42&C42 -> Véhicules neufsSalaires cadres | B42: =+$K$1 -> Véhicules neufs | C42: Salaires cadres | F42: =+SUM(START:END!F42) -> 77393.513 | I42: =+SUM(START:END!I42) -> 0 | L42: =+SUM(START:END!L42) -> 58984.08 | N42: =L42-F42 -> -18409.433 | Q42: =+SUM(START:END!Q42) -> 37570.23
A43: =+B43&C43 -> Véhicules neufsSalaires commis | B43: =+$K$1 -> Véhicules neufs | C43: Salaires commis | F43: =+SUM(START:END!F43) -> 44976.212 | I43: =+SUM(START:END!I43) -> 0 | L43: =+SUM(START:END!L43) -> 39966.64 | N43: =L43-F43 -> -5009.572 | Q43: =+SUM(START:END!Q43) -> 29871.64 | S43: =L43-Q43 -> 10095
A44: =+B44&C44 -> Véhicules neufsSalaires autres | B44: =+$K$1 -> Véhicules neufs | C44: Salaires autres | F44: =+SUM(START:END!F44) -> 1025.55 | I44: =+SUM(START:END!I44) -> 0 | L44: =+SUM(START:END!L44) -> 5931.85 | N44: =L44-F44 -> 4906.3 | Q44: =+SUM(START:END!Q44) -> 11085.06 | S44: =L44-Q44 -> -5153.21
A45: =+B45&C45 -> Véhicules neufsSalaires spécialistes | B45: =+$K$1 -> Véhicules neufs | C45: Salaires spécialistes | F45: =+SUM(START:END!F45) -> 0 | I45: =+SUM(START:END!I45) -> 0 | L45: =+SUM(START:END!L45) -> 0 | N45: =L45-F45 -> 0 | Q45: =+SUM(START:END!Q45) -> 0 | S45: =L45-Q45 -> 0
A46: =+B46&C46 -> Véhicules neufs[...] | B46: =+$K$1 -> Véhicules neufs | C46: [...] | F46: =+SUM(START:END!F46) -> 0 | I46: =+SUM(START:END!I46) -> 0 | L46: =+SUM(START:END!L46) -> 0 | N46: =L46-F46 -> 0 | Q46: =+SUM(START:END!Q46) -> 0 | S46: =L46-Q46 -> 0
A47: =+B47&C47 -> Véhicules neufs[...] | B47: =+$K$1 -> Véhicules neufs | C47: [...] | F47: =+SUM(START:END!F47) -> 0 | I47: =+SUM(START:END!I47) -> 0 | L47: =+SUM(START:END!L47) -> 0 | N47: =L47-F47 -> 0 | Q47: =+SUM(START:END!Q47) -> 0 | S47: =L47-Q47 -> 0
A48: =+B48&C48 -> Véhicules neufs[...] | B48: =+$K$1 -> Véhicules neufs | C48: [...] | F48: =+SUM(START:END!F48) -> 0 | I48: =+SUM(START:END!I48) -> 0 | L48: =+SUM(START:END!L48) -> 0 | N48: =L48-F48 -> 0 | Q48: =+SUM(START:END!Q48) -> 0 | S48: =L48-Q48 -> 0
A49: =+B49&C49 -> Véhicules neufsSalaires en absences | B49: =+$K$1 -> Véhicules neufs | C49: Salaires en absences | F49: =+SUM(START:END!F49) -> 39775.272 | I49: =+SUM(START:END!I49) -> 0 | L49: =+SUM(START:END!L49) -> 38058.07 | N49: =L49-F49 -> -1717.2022 | Q49: =+SUM(START:END!Q49) -> 36530.25 | S49: =L49-Q49 -> 1527.82
A50: =+B50&C50 -> Véhicules neufsDéduction à la source | B50: =+$K$1 -> Véhicules neufs | C50: Déduction à la source | F50: =+SUM(START:END!F50) -> 48361.124 | I50: =+SUM(START:END!I50) -> 0 | L50: =+SUM(START:END!L50) -> 47214.32 | N50: =L50-F50 -> -1146.8039 | Q50: =+SUM(START:END!Q50) -> 46567.67 | S50: =L50-Q50 -> 646.65
A51: =+B51&C51 -> Véhicules neufsBénéfices marginaux | B51: =+$K$1 -> Véhicules neufs | C51: Bénéfices marginaux | F51: =+SUM(START:END!F51) -> 24916.492 | I51: =+SUM(START:END!I51) -> 0 | L51: =+SUM(START:END!L51) -> 23071.53 | N51: =L51-F51 -> -1844.9621 | Q51: =+SUM(START:END!Q51) -> 22166.69 | S51: =L51-Q51 -> 904.84
A52: =+B52&C52 -> Véhicules neufsCsst | B52: =+$K$1 -> Véhicules neufs | C52: Csst | F52: =+SUM(START:END!F52) -> 10863.731 | I52: =+SUM(START:END!I52) -> 0 | L52: =+SUM(START:END!L52) -> 8638.53 | N52: =L52-F52 -> -2225.2007 | Q52: =+SUM(START:END!Q52) -> 8614.36 | S52: =L52-Q52 -> 24.17
A53: =+B53&C53 -> Véhicules neufs[...] | B53: =+$K$1 -> Véhicules neufs | C53: [...] | F53: =+SUM(START:END!F53) -> 0 | I53: =+SUM(START:END!I53) -> 0 | L53: =+SUM(START:END!L53) -> 0 | N53: =L53-I53 -> 0 | Q53: =+SUM(START:END!Q53) -> 0 | S53: =L53-Q53 -> 0
A54: =+B54&C54 -> Véhicules neufsTOTAL PERSONNEL | B54: =+$K$1 -> Véhicules neufs | C54: TOTAL PERSONNEL | D54: % brut | E54: =F54/F$27 -> 0.36952182 | F54: =+SUM(F42:F53) -> 247311.89 | G54: % brut | H54: =I54/I$27 -> #DIV/0! | I54: =+SUM(I42:I53) -> 0 | J54: % brut | K54: =L54/L$27 -> 0.40913849 | L54: =+SUM(L42:L53) -> 221865.02 | N54: =+SUM(N42:N53) -> -25446.873 | O54: % brut | P54: =Q54/Q$27 -> 0.31023038 | Q54: =+SUM(Q42:Q53) -> 192405.9 | S54: =+SUM(S42:S53) -> 8045.27
A55: =+B55&C55 -> Véhicules neufsPublicité 2 | B55: =+$K$1 -> Véhicules neufs | C55: Publicité 2 | F55: =+SUM(START:END!F55) -> 0 | I55: =+SUM(START:END!I55) -> 0 | L55: =+SUM(START:END!L55) -> 0 | N55: =L55-F55 -> 0 | Q55: =+SUM(START:END!Q55) -> 0 | S55: =L55-Q55 -> 0
A56: =+B56&C56 -> Véhicules neufsService gratuit 2 | B56: =+$K$1 -> Véhicules neufs | C56: Service gratuit 2 | F56: =+SUM(START:END!F56) -> 0 | I56: =+SUM(START:END!I56) -> 0 | L56: =+SUM(START:END!L56) -> 0 | N56: =L56-F56 -> 0 | Q56: =+SUM(START:END!Q56) -> 0 | S56: =L56-Q56 -> 0
A57: =+B57&C57 -> Véhicules neufsFrais véhicules de cie | B57: =+$K$1 -> Véhicules neufs | C57: Frais véhicules de cie | F57: =+SUM(START:END!F57) -> 26857.644 | I57: =+SUM(START:END!I57) -> 0 | L57: =+SUM(START:END!L57) -> 30444.04 | N57: =L57-F57 -> 3586.3962 | Q57: =+SUM(START:END!Q57) -> 26284.78 | S57: =L57-Q57 -> 4159.26
A58: =+B58&C58 -> Véhicules neufsInformatique | B58: =+$K$1 -> Véhicules neufs | C58: Informatique | F58: =+SUM(START:END!F58) -> 23882.984 | I58: =+SUM(START:END!I58) -> 0 | L58: =+SUM(START:END!L58) -> 22471.69 | N58: =L58-F58 -> -1411.2943 | Q58: =+SUM(START:END!Q58) -> 22020.98 | S58: =L58-Q58 -> 450.71
A59: =+B59&C59 -> Véhicules neufsFrais de déplacement | B59: =+$K$1 -> Véhicules neufs | C59: Frais de déplacement | F59: =+SUM(START:END!F59) -> 3800.0925 | I59: =+SUM(START:END!I59) -> 0 | L59: =+SUM(START:END!L59) -> 5505.95 | N59: =L59-F59 -> 1705.8575 | Q59: =+SUM(START:END!Q59) -> 5300.42 | S59: =L59-Q59 -> 205.53
A60: =+B60&C60 -> Véhicules neufsServices extérieurs | B60: =+$K$1 -> Véhicules neufs | C60: Services extérieurs | F60: =+SUM(START:END!F60) -> 21647.222 | I60: =+SUM(START:END!I60) -> 0 | L60: =+SUM(START:END!L60) -> 20864.12 | N60: =L60-F60 -> -783.10217 | Q60: =+SUM(START:END!Q60) -> 21333.34 | S60: =L60-Q60 -> -469.22
A61: =+B61&C61 -> Véhicules neufsFournitures autres | B61: =+$K$1 -> Véhicules neufs | C61: Fournitures autres | F61: =+SUM(START:END!F61) -> 291.772 | I61: =+SUM(START:END!I61) -> 0 | L61: =+SUM(START:END!L61) -> 0 | N61: =L61-F61 -> -291.772 | Q61: =+SUM(START:END!Q61) -> 58.06 | S61: =L61-Q61 -> -58.06
A62: =+B62&C62 -> Véhicules neufsUniformes | B62: =+$K$1 -> Véhicules neufs | C62: Uniformes | F62: =+SUM(START:END!F62) -> 85 | I62: =+SUM(START:END!I62) -> 0 | L62: =+SUM(START:END!L62) -> 0 | N62: =L62-F62 -> -85 | Q62: =+SUM(START:END!Q62) -> 0 | S62: =L62-Q62 -> 0
A63: =+B63&C63 -> Véhicules neufsPapeterie | B63: =+$K$1 -> Véhicules neufs | C63: Papeterie | F63: =+SUM(START:END!F63) -> 2224.2927 | I63: =+SUM(START:END!I63) -> 0 | L63: =+SUM(START:END!L63) -> 1514.01 | N63: =L63-F63 -> -710.28268 | Q63: =+SUM(START:END!Q63) -> 1654.51 | S63: =L63-Q63 -> -140.5
A64: =+B64&C64 -> Véhicules neufsTéléphone | B64: =+$K$1 -> Véhicules neufs | C64: Téléphone | F64: =+SUM(START:END!F64) -> 1034.406 | I64: =+SUM(START:END!I64) -> 0 | L64: =+SUM(START:END!L64) -> 1257.85 | N64: =L64-F64 -> 223.44405 | Q64: =+SUM(START:END!Q64) -> 985.98 | S64: =L64-Q64 -> 271.87
A65: =+B65&C65 -> Véhicules neufsFrais postaux | B65: =+$K$1 -> Véhicules neufs | C65: Frais postaux | F65: =+SUM(START:END!F65) -> 308.46719 | I65: =+SUM(START:END!I65) -> 0 | L65: =+SUM(START:END!L65) -> 430.79 | N65: =L65-F65 -> 122.32281 | Q65: =+SUM(START:END!Q65) -> 54.08 | S65: =L65-Q65 -> 376.71
A66: =+B66&C66 -> Véhicules neufsDivers | B66: =+$K$1 -> Véhicules neufs | C66: Divers | F66: =+SUM(START:END!F66) -> 603.51116 | I66: =+SUM(START:END!I66) -> 0 | L66: =+SUM(START:END!L66) -> 295.48 | N66: =L66-F66 -> -308.03116 | Q66: =+SUM(START:END!Q66) -> 431.03 | S66: =L66-Q66 -> -135.55
... A68: =+B68&C68 -> Véhicules neufsFrais bancaires | B68: =+$K$1 -> Véhicules neufs | C68: Frais bancaires | F68: =+SUM(START:END!F68) -> 11374.166 | I68: =+SUM(START:END!I68) -> 0 | L68: =+SUM(START:END!L68) -> 12681.92 | N68: =L68-F68 -> 1307.7541 | Q68: =+SUM(START:END!Q68) -> 12385.38 | S68: =L68-Q68 -> 296.54
A69: =+B69&C69 -> Véhicules neufs[...] | B69: =+$K$1 -> Véhicules neufs | C69: [...] | F69: =+SUM(START:END!F69) -> 0 | I69: =+SUM(START:END!I69) -> 0 | L69: =+SUM(START:END!L69) -> 0 | N69: =L69-I69 -> 0 | Q69: =+SUM(START:END!Q69) -> 0 | S69: =L69-Q69 -> 0
A70: =+B70&C70 -> Véhicules neufs[...] | B70: =+$K$1 -> Véhicules neufs | C70: [...] | F70: =+SUM(START:END!F70) -> 0 | I70: =+SUM(START:END!I70) -> 0 | L70: =+SUM(START:END!L70) -> 0 | N70: =L70-I70 -> 0 | Q70: =+SUM(START:END!Q70) -> 0 | S70: =L70-Q70 -> 0
A71: =+B71&C71 -> Véhicules neufs[...] | B71: =+$K$1 -> Véhicules neufs | C71: [...] | F71: =+SUM(START:END!F71) -> 0 | I71: =+SUM(START:END!I71) -> 0 | L71: =+SUM(START:END!L71) -> 0 | N71: =L71-I71 -> 0 | Q71: =+SUM(START:END!Q71) -> 0 | S71: =L71-Q71 -> 0
A72: =+B72&C72 -> Véhicules neufsTOTAL SEMI-FIXES | B72: =+$K$1 -> Véhicules neufs | C72: TOTAL SEMI-FIXES | D72: % brut | E72: =F72/F$27 -> 0.14629802 | F72: =+SUM(F55:F71) -> 97913.676 | G72: % brut | H72: =I72/I$27 -> #DIV/0! | I72: =+SUM(I55:I71) -> 0 | J72: % brut | K72: =L72/L$27 -> 0.18737099 | L72: =+SUM(L55:L71) -> 101606.35 | N72: =+SUM(N55:N71) -> 3692.6737 | O72: % brut | P72: =Q72/Q$27 -> 0.15192025 | Q72: =+SUM(Q55:Q71) -> 94221.44 | S72: =+SUM(S55:S71) -> 7384.91
A73: =+B73&C73 -> Véhicules neufs | B73: =+$K$1 -> Véhicules neufs
A74: =+B74&C74 -> Véhicules neufsTOTAL DES DÉPENSES | B74: =+$K$1 -> Véhicules neufs | C74: TOTAL DES DÉPENSES | D74: % brut | E74: =F74/F$27 -> 1.0775223 | F74: =F41+F54+F72 -> 721159.22 | G74: % brut | H74: =I74/I$27 -> #DIV/0! | I74: =I41+I54+I72 -> 0 | J74: % brut | K74: =L74/L$27 -> 1.0745968 | L74: =L41+L54+L72 -> 582725.52 | N74: =N41+N54+N72 -> -138433.7 | O74: % brut | P74: =Q74/Q$27 -> 1.0264761 | Q74: =Q41+Q54+Q72 -> 636623.85 | S74: =L74-Q74 -> -53898.33
A75: =+B75&C75 -> Véhicules neufsProgramme neuf 1 | B75: =+$K$1 -> Véhicules neufs | C75: Programme neuf 1 | F75: =+SUM(START:END!F75) -> 25000 | I75: =+SUM(START:END!I75) -> 0 | L75: =+SUM(START:END!L75) -> 12000 | N75: =L75-F75 -> -13000 | Q75: =+SUM(START:END!Q75) -> 20695
A76: =+B76&C76 -> Véhicules neufsProgramme neuf 2 | B76: =+$K$1 -> Véhicules neufs | C76: Programme neuf 2 | F76: =+SUM(START:END!F76) -> 0 | I76: =+SUM(START:END!I76) -> 0 | L76: =+SUM(START:END!L76) -> 0 | N76: =L76-F76 -> 0 | Q76: =+SUM(START:END!Q76) -> 0 | S76: =L76-Q76 -> 0
A77: =+B77&C77 -> Véhicules neufsProgramme neuf 3 | B77: =+$K$1 -> Véhicules neufs | C77: Programme neuf 3 | F77: =+SUM(START:END!F77) -> 0 | I77: =+SUM(START:END!I77) -> 0 | L77: =+SUM(START:END!L77) -> 0 | N77: =L77-F77 -> 0 | Q77: =+SUM(START:END!Q77) -> 0 | S77: =L77-Q77 -> 0
A78: =+B78&C78 -> Véhicules neufsHoldbacks | B78: =+$K$1 -> Véhicules neufs | C78: Holdbacks | F78: =+SUM(START:END!F78) -> 278936.24 | I78: =+SUM(START:END!I78) -> 0 | L78: =+SUM(START:END!L78) -> 208299.55 | N78: =L78-F78 -> -70636.694 | Q78: =+SUM(START:END!Q78) -> 260645.55 | S78: =L78-Q78 -> -52346
A79: =+B79&C79 -> Véhicules neufs[...] | B79: =+$K$1 -> Véhicules neufs | C79: [...] | F79: =+SUM(START:END!F79) -> 0 | I79: =+SUM(START:END!I79) -> 0 | L79: =+SUM(START:END!L79) -> 0 | N79: =L79-F79 -> 0 | Q79: =+SUM(START:END!Q79) -> 0 | S79: =L79-Q79 -> 0
A80: =+B80&C80 -> Véhicules neufs[...] | B80: =+$K$1 -> Véhicules neufs | C80: [...] | F80: =+SUM(START:END!F80) -> 0 | I80: =+SUM(START:END!I80) -> 0 | L80: =+SUM(START:END!L80) -> 0 | N80: =L80-F80 -> 0 | Q80: =+SUM(START:END!Q80) -> 0 | S80: =L80-Q80 -> 0
A81: =+B81&C81 -> Véhicules neufs[...] | B81: =+$K$1 -> Véhicules neufs | C81: [...] | F81: =+SUM(START:END!F81) -> 0 | I81: =+SUM(START:END!I81) -> 0 | L81: =+SUM(START:END!L81) -> 0 | N81: =L81-F81 -> 0 | Q81: =+SUM(START:END!Q81) -> 0 | S81: =L81-Q81 -> 0
A82: =+B82&C82 -> Véhicules neufsFrais administration | B82: =+$K$1 -> Véhicules neufs | C82: Frais administration | F82: =+SUM(START:END!F82) -> 91965.7 | I82: =+SUM(START:END!I82) -> 0 | L82: =+SUM(START:END!L82) -> 74283 | N82: =L82-F82 -> -17682.7 | Q82: =+SUM(START:END!Q82) -> 88156.5 | S82: =L82-Q82 -> -13873.5
A83: =+B83&C83 -> Véhicules neufsAUTRES REVENUS | B83: =+$K$1 -> Véhicules neufs | C83: AUTRES REVENUS | F83: =+SUM(F75:F82) -> 395901.94 | I83: =+SUM(I75:I82) -> 0 | L83: =+SUM(L75:L82) -> 294582.55 | N83: =+SUM(N75:N82) -> -101319.39 | Q83: =+SUM(Q75:Q82) -> 369497.05 | S83: =+SUM(S75:S82) -> -66219.5
A84: =+B84&C84 -> Véhicules neufs | B84: =+$K$1 -> Véhicules neufs
A85: =+B85&C85 -> Véhicules neufsPROFIT DÉPARTEMENTAL | B85: =+$K$1 -> Véhicules neufs | C85: PROFIT DÉPARTEMENTAL | F85: =F27-F74+F83 -> 344018.19 | I85: =I27-I74+I83 -> 0 | L85: =L27-L74+L83 -> 254130.68 | N85: =N27-N74+N83 -> -89887.514 | Q85: =Q27-Q74+Q83 -> 353076.49 | S85: =S27-S41-S54-S72+S83 -> -68836.96
F86: =+F85-#REF!-#REF!-#REF! -> #REF! | L86: =L85/F85 -> 0.73871291 | N86: =+N85-#REF!-#REF!-#REF! -> #REF! | Q86: =+Q85-#REF!-#REF!-#REF! -> #REF! | S86: =+S85-#REF!-#REF!-#REF! -> #REF!
C89: =C1 -> Conso | K89: Véhicules usagés | S89: =$S$1 -> Réalisé
D91: BUDGET ORIGINAL | G91: BUDGET RÉVISÉ | J91: RÉALISATION | M91: ÉCART réel / original | O91: ANNÉE PRÉCÉDENTE | R91: ÉCART réel / année précédente
D92: UNITE | E92: $P/UNITÉ | F92: $PROFITS | G92: UNITE | H92: $P/UNITÉ | I92: $PROFITS | J92: UNITE | K92: $P/UNITE | L92: $PROFITS | M92: UNITÉ | N92: $PROFITS | O92: UNITE | P92: $P/UNITE | Q92: $PROFITS | R92: UNITE | S92: $PROFITS
A93: =+B93&C93 -> Véhicules usagésVentes nettes | B93: Véhicules usagés | C93: Ventes nettes | F93: =+SUM(START:END!F93) -> 5198440 | I93: =+SUM(START:END!I93) -> 0 | L93: =+SUM(START:END!L93) -> 3925309.4 | Q93: =+SUM(START:END!Q93) -> 4212048.8
A94: =+B94&C94 -> Véhicules usagésCertifié | B94: Véhicules usagés | C94: Certifié | D94: =+SUM(START:END!D94) -> 83 | E94: =IF(D94=0,0,F94/D94) -> 1400 | F94: =+SUM(START:END!F94) -> 116200 | G94: =+SUM(START:END!G94) -> 0 | H94: =IF(G94=0,0,I94/G94) -> 0 | I94: =+SUM(START:END!I94) -> 0 | J94: =+SUM(START:END!J94) -> 87 | K94: =IF(J94=0,0,L94/J94) -> 1453.593 | L94: =+SUM(START:END!L94) -> 126462.59 | M94: =J94-D94 -> 4 | N94: =L94-F94 -> 10262.59 | O94: =+SUM(START:END!O94) -> 91 | P94: =IF(O94=0,0,Q94/O94) -> 620.13967 | Q94: =+SUM(START:END!Q94) -> 56432.71 | R94: =J94-O94 -> -4 | S94: =L94-Q94 -> 70029.88
A95: =+B95&C95 -> Véhicules usagésNon Certifié | B95: Véhicules usagés | C95: Non Certifié | D95: =+SUM(START:END!D95) -> 10 | E95: =IF(D95=0,0,F95/D95) -> 1800 | F95: =+SUM(START:END!F95) -> 18000 | G95: =+SUM(START:END!G95) -> 0 | H95: =IF(G95=0,0,I95/G95) -> 0 | I95: =+SUM(START:END!I95) -> 0 | J95: =+SUM(START:END!J95) -> 1 | K95: =IF(J95=0,0,L95/J95) -> -3329.92 | L95: =+SUM(START:END!L95) -> -3329.92 | M95: =J95-D95 -> -9 | N95: =L95-F95 -> -21329.92 | O95: =+SUM(START:END!O95) -> 5 | P95: =IF(O95=0,0,Q95/O95) -> 471.856 | Q95: =+SUM(START:END!Q95) -> 2359.28 | R95: =J95-O95 -> -4 | S95: =L95-Q95 -> -5689.2
A96: =+B96&C96 -> Véhicules usagésAutres marques | B96: Véhicules usagés | C96: Autres marques | D96: =+SUM(START:END!D96) -> 14 | E96: =IF(D96=0,0,F96/D96) -> 1500 | F96: =+SUM(START:END!F96) -> 21000 | G96: =+SUM(START:END!G96) -> 0 | H96: =IF(G96=0,0,I96/G96) -> 0 | I96: =+SUM(START:END!I96) -> 0 | J96: =+SUM(START:END!J96) -> 2 | K96: =IF(J96=0,0,L96/J96) -> 2899.8 | L96: =+SUM(START:END!L96) -> 5799.6 | M96: =J96-D96 -> -12 | N96: =L96-F96 -> -15200.4 | O96: =+SUM(START:END!O96) -> 0 | P96: =IF(O96=0,0,Q96/O96) -> 0 | Q96: =+SUM(START:END!Q96) -> 0 | R96: =J96-O96 -> 2 | S96: =L96-Q96 -> 5799.6
A97: =+B97&C97 -> Véhicules usagésTotal Usagés | B97: Véhicules usagés | C97: Total Usagés | D97: =+D95+D94+D96 -> 107 | E97: =IF(D97=0,0,F97/D97) -> 1450.4673 | F97: =+F94+F95+F96 -> 155200 | G97: =+G95+G94+G96 -> 0 | H97: =IF(G97=0,0,I97/G97) -> 0 | I97: =+I94+I95+I96 -> 0 | J97: =+J95+J94+J96 -> 90 | K97: =IF(J97=0,0,L97/J97) -> 1432.5808 | L97: =+L94+L95+L96 -> 128932.27 | M97: =+M95+M94+M96 -> -17 | N97: =+N94+N95+N96 -> -26267.73 | O97: =+O95+O94+O96 -> 96 | P97: =IF(O97<=0,0,Q97/O97) -> 612.41656 | Q97: =+Q94+Q95+Q96 -> 58791.99 | R97: =R94+R95+R96 -> -6 | S97: =S94+S95+S96 -> 70140.28
A98: =+B98&C98 -> Véhicules usagés | B98: Véhicules usagés | E98: =IF(D98=0,0,F98/D98) -> 0 | H98: =IF(G98=0,0,I98/G98) -> 0 | M98: =D97/D97 -> 1 | N98: =N97/F97 -> -0.16925084 | R98: =R97/O97 -> -0.0625 | S98: =IF(Q97=0,0,(S97/Q97)) -> 1.1930244
A99: =+B99&C99 -> Véhicules usagésUS | B99: Véhicules usagés | C99: US | D99: =+SUM(START:END!D99) -> 0 | E99: =IF(D99=0,0,F99/D99) -> 0 | F99: =+SUM(START:END!F99) -> 0 | G99: =+SUM(START:END!G99) -> 0 | H99: =IF(G99=0,0,I99/G99) -> 0 | I99: =+SUM(START:END!I99) -> 0 | J99: =+SUM(START:END!J99) -> 0 | K99: =IF(J99=0,0,L99/J99) -> 0 | L99: =+SUM(START:END!L99) -> 0 | M99: =J99-D99 -> 0 | N99: =L99-F99 -> 0 | O99: =+SUM(START:END!O99) -> 0 | P99: =IF(O99=0,0,Q99/O99) -> 0 | Q99: =+SUM(START:END!Q99) -> 0
A100: =+B100&C100 -> Véhicules usagésVentes au Gros | B100: Véhicules usagés | C100: Ventes au Gros | D100: =+SUM(START:END!D100) -> 113 | E100: =IF(D100=0,0,F100/D100) -> 400 | F100: =+SUM(START:END!F100) -> 45200 | G100: =+SUM(START:END!G100) -> 0 | H100: =IF(G100=0,0,I100/G100) -> 0 | I100: =+SUM(START:END!I100) -> 0 | J100: =+SUM(START:END!J100) -> 89 | K100: =IF(J100=0,0,L100/J100) -> 982.57876 | L100: =+SUM(START:END!L100) -> 87449.51 | M100: =J100-D100 -> -24 | N100: =L100-F100 -> 42249.51 | O100: =+SUM(START:END!O100) -> 107 | P100: =IF(O100=0,0,Q100/O100) -> -358.56888 | Q100: =+SUM(START:END!Q100) -> -38366.87 | R100: =J100-O100 -> -18 | S100: =L100-Q100 -> 125816.38
A101: =+B101&C101 -> Véhicules usagés | B101: Véhicules usagés
A102: =+B102&C102 -> Véhicules usagésRev. Finances | B102: Véhicules usagés | C102: Rev. Finances | D102: =+SUM(START:END!D102) -> 0 | E102: =IF(D102=0,0,F102/D102) -> 0 | F102: =+SUM(START:END!F102) -> 64200 | G102: =+SUM(START:END!G102) -> 0 | H102: =IF(G102=0,0,I102/G102) -> 0 | I102: =+SUM(START:END!I102) -> 0 | J102: =+SUM(START:END!J102) -> 0 | K102: =IF(J102=0,0,L102/J102) -> 0 | L102: =+SUM(START:END!L102) -> 31118.34 | M102: =J102-G102 -> 0 | N102: =L102-F102 -> -33081.66 | O102: =+SUM(START:END!O102) -> 0 | P102: =IF(O102=0,0,Q102/O102) -> 0 | Q102: =+SUM(START:END!Q102) -> 27863.97 | R102: =J102-O102 -> 0 | S102: =L102-Q102 -> 3254.37
A103: =+B103&C103 -> Véhicules usagésRev. Protections | B103: Véhicules usagés | C103: Rev. Protections | D103: =+SUM(START:END!D103) -> 0 | E103: =IF(D103=0,0,F103/D103) -> 0 | F103: =+SUM(START:END!F103) -> 133750 | G103: =+SUM(START:END!G103) -> 0 | H103: =IF(G103=0,0,I103/G103) -> 0 | I103: =+SUM(START:END!I103) -> 0 | J103: =+SUM(START:END!J103) -> 0 | K103: =IF(J103=0,0,L103/J103) -> 0 | L103: =+SUM(START:END!L103) -> 144769.14 | M103: =J103-G103 -> 0 | N103: =L103-F103 -> 11019.14 | O103: =+SUM(START:END!O103) -> 0 | P103: =IF(O103=0,0,Q103/O103) -> 0 | Q103: =+SUM(START:END!Q103) -> 146636.99 | R103: =J103-O103 -> 0 | S103: =L103-Q103 -> -1867.85
A104: =+B104&C104 -> Véhicules usagésRev. Autres | B104: Véhicules usagés | C104: Rev. Autres | D104: =+SUM(START:END!D104) -> 0 | E104: =IF(D104=0,0,F104/D104) -> 0 | F104: =+SUM(START:END!F104) -> 5350 | G104: =+SUM(START:END!G104) -> 0 | H104: =IF(G104=0,0,I104/G104) -> 0 | I104: =+SUM(START:END!I104) -> 0 | J104: =+SUM(START:END!J104) -> 0 | K104: =IF(J104=0,0,L104/J104) -> 0 | L104: =+SUM(START:END!L104) -> 3636.48 | M104: =J104-G104 -> 0 | N104: =L104-F104 -> -1713.52 | O104: =+SUM(START:END!O104) -> 0 | P104: =IF(O104=0,0,Q104/O104) -> 0 | Q104: =+SUM(START:END!Q104) -> 1973 | R104: =J104-O104 -> 0 | S104: =L104-Q104 -> 1663.48
...

Sheet START

Sheet Avril 2025
C1: Volks | K1: Véhicules neufs | S1: Réalisé, Avril 2025
D2: X | E2: O | F2: U | J2: NB | L2: $ | O2: X | P2: O | Q2: U | V2: *** NE PAS EFFACER / Pour An Précédente ***
D3: BUDGET ORIGINAL | J3: RÉALISATION | M3: ÉCART réel / Budget | O3: ANNÉE PRÉCÉDENTE | R3: ECART (réel/ Ann.Préc.) | V3: NEUF | W3: 0.45
D4: UNITE | E4: $P/UNITÉ | F4: $PROFITS | J4: UNITÉS | K4: $P/UNITE | L4: $PROFITS | M4: UNITÉS | N4: $PROFITS | O4: UNITE | P4: $P/UNITÉ | Q4: $PROFITS | R4: UNITÉS | S4: $PROFITS | V4: USAGE | W4: 0.1
A5: Véhicules neufsVentes nettes | B5: Véhicules neufs | C5: Ventes nettes | F5: 3150915.1 | L5: 2860821 | Q5: 3890022.9 | V5: SERVICE | W5: 0.225
A6: Véhicules neufsAutos détail | B6: Véhicules neufs | C6: Autos détail | D6: 15 | E6: 1953.6492 | F6: 29304.738 | J6: 24 | K6: 1996.3658 | L6: 47912.78 | M6: 9 | N6: 18608.042 | O6: 18 | P6: 2168.0939 | Q6: 39025.69 | R6: 6 | S6: 8887.09 | V6: CARROSSERIE | W6: 0.025
A7: Véhicules neufsCamions détail | B7: Véhicules neufs | C7: Camions détail | D7: 42 | E7: 2435.9047 | F7: 102308 | J7: 32 | K7: 2603.3338 | L7: 83306.68 | M7: -10 | N7: -19001.316 | O7: 51 | P7: 2906.2869 | Q7: 148220.63 | R7: -19 | S7: -64913.95 | V7: PIECES | W7: 0.2
A8: Véhicules neufsSprinter | B8: Véhicules neufs | C8: Sprinter | D8: 0 | E8: 0 | F8: 0 | J8: 0 | K8: 0 | L8: 0 | M8: 0 | N8: 0 | O8: 0 | P8: 0 | Q8: 0 | R8: 0 | S8: 0 | W8: 1
A9: Véhicules neufsMoto détail | B9: Véhicules neufs | C9: Moto détail | D9: 0 | E9: 0 | F9: 0 | J9: 0 | K9: 0 | L9: 0 | M9: 0 | N9: 0 | O9: 0 | P9: 0 | Q9: 0 | R9: 0 | S9: 0
A10: Véhicules neufs[...] | B10: Véhicules neufs | C10: [...] | D10: 0 | E10: 0 | F10: 0 | J10: 0 | K10: 0 | L10: 0 | M10: 0 | N10: 0 | O10: 0 | P10: 0 | Q10: 0 | R10: 0 | S10: 0
A11: Véhicules neufs[...] | B11: Véhicules neufs | C11: [...] | D11: 0 | E11: 0 | F11: 0 | J11: 0 | K11: 0 | L11: 0 | M11: 0 | N11: 0 | O11: 0 | P11: 0 | Q11: 0 | R11: 0 | S11: 0
A12: Véhicules neufs[...] | B12: Véhicules neufs | C12: [...] | D12: 0 | E12: 0 | F12: 0 | J12: 0 | K12: 0 | L12: 0 | M12: 0 | N12: 0 | O12: 0 | P12: 0 | Q12: 0 | R12: 0 | S12: 0
A13: Véhicules neufsTotal Neufs | B13: Véhicules neufs | C13: Total Neufs | D13: 57 | E13: 2308.9953 | F13: 131612.73 | J13: 56 | K13: 2343.2046 | L13: 131219.46 | M13: -1 | N13: -393.27398 | O13: 69 | P13: 2713.7148 | Q13: 187246.32 | R13: -13 | S13: -56026.86
A14: Véhicules neufs | B14: Véhicules neufs | M14: -0.01754386 | N14: -0.002988115 | R14: -0.1884058 | S14: -0.29921475 | AD14: 20 | AE14: 1000 | AF14: 20000
A15: Véhicules neufsEx-Démos et courtoisies | B15: Véhicules neufs | C15: Ex-Démos et courtoisies | D15: 3 | E15: 1534.7521 | F15: 4604.2564 | J15: 2 | K15: 495.505 | L15: 991.01 | M15: -1 | N15: -3613.2464 | O15: 4 | P15: 2264.375 | Q15: 9057.5 | R15: -2 | S15: -8066.49 | AD15: 25 | AE15: 800 | AF15: 20000
A16: Véhicules neufs | B16: Véhicules neufs
A17: Véhicules neufsFlottes | B17: Véhicules neufs | C17: Flottes | D17: 2 | E17: 2393.8521 | F17: 4787.7042 | J17: 0 | K17: 0 | L17: 0 | M17: -2 | N17: -4787.7042 | O17: 0 | P17: 0 | Q17: 0 | R17: 0 | S17: 0
A18: Véhicules neufs | B18: Véhicules neufs
A19: Véhicules neufsRachat bail | B19: Véhicules neufs | C19: Rachat bail | D19: 0 | E19: 0 | F19: 6375 | L19: 5903.29 | N19: -471.71 | Q19: 6030.37 | R19: 0 | S19: -127.08
A20: Véhicules neufs | B20: Véhicules neufs
A21: Véhicules neufsRev. Finances | B21: Véhicules neufs | C21: Rev. Finances | D21: 0 | E21: 0 | F21: 3000 | K21: 0 | L21: 0 | N21: -3000 | Q21: 0 | R21: 0 | S21: 0
A22: Véhicules neufsRev. Protections | B22: Véhicules neufs | C22: Rev. Protections | D22: 0 | E22: 0 | F22: 55800 | K22: 931.86034 | L22: 54047.9 | N22: -1752.1 | Q22: 55912.32 | R22: -931.86034 | S22: -1864.42
A23: Véhicules neufsRev. Autres | B23: Véhicules neufs | C23: Rev. Autres | D23: 0 | E23: 0 | F23: 1200 | K23: 0 | L23: 0 | N23: -1200 | Q23: 1358.23 | R23: 0 | S23: -1358.23
A24: Véhicules neufsTotal F&I | B24: Véhicules neufs | C24: Total F&I | D24: 60 | E24: 1000 | F24: 60000 | J24: 58 | K24: 931.86034 | L24: 54047.9 | M24: -2 | N24: -5952.1 | O24: 73 | P24: 784.52808 | Q24: 57270.55 | S24: -3222.65
A25: Véhicules neufs | B25: Véhicules neufs | N25: -0.099201667 | S25: -0.056270631
A26: Véhicules neufs | B26: Véhicules neufs
A27: Véhicules neufsTotal Dépt. Neufs | B27: Véhicules neufs | C27: Total Dépt. Neufs | D27: 62 | E27: 3344.8338 | F27: 207379.69 | J27: 58 | K27: 3313.1321 | L27: 192161.66 | M27: -4 | N27: -15218.035 | O27: 73 | P27: 3556.2293 | Q27: 259604.74 | R27: -15 | S27: -67443.08
A28: Véhicules neufs | B28: Véhicules neufs | L28: 0.92661753 | M28: -0.064516129 | N28: -0.073382472 | R28: -0.20547945 | S28: -0.2597914
A29: Véhicules neufs | B29: Véhicules neufs
A30: Véhicules neufsDEPENSES | B30: Véhicules neufs | C30: DEPENSES
A31: Véhicules neufsComm. vendeurs | B31: Véhicules neufs | C31: Comm. vendeurs | D31: 0.33304494 | E31: 756.10632 | F31: 45366.379 | J31: 0.30815298 | K31: 702.4319 | L31: 40741.05 | N31: -4625.3291 | O31: 0.24820205 | P31: 667.43849 | Q31: 48723.01 | S31: -7981.96
A32: Véhicules neufsComm. F&I | B32: Véhicules neufs | C32: Comm. F&I | D32: 0.28 | E32: 280 | F32: 16800 | J32: 0.2000087 | K32: 186.38017 | L32: 10810.05 | N32: -5989.95 | O32: 0.29711868 | P32: 233.09795 | Q32: 17016.15 | S32: -6206.1
A33: Véhicules neufsFrais de livraison | B33: Véhicules neufs | C33: Frais de livraison | E33: 115 | F33: 6900 | K33: 166.21517 | L33: 9640.48 | N33: 2740.48 | P33: 51.42137 | Q33: 3753.76 | S33: 5886.72
A34: Véhicules neufsService gratuit 1 | B34: Véhicules neufs | C34: Service gratuit 1 | E34: 10 | F34: 600 | K34: 6.017069 | L34: 348.99 | N34: -251.01 | P34: 1.5160274 | Q34: 110.67 | S34: 238.32
A35: Véhicules neufsEntretien stock | B35: Véhicules neufs | C35: Entretien stock | E35: 120.75 | F35: 7245 | K35: 133.99603 | L35: 7771.77 | N35: 526.77 | P35: 164.94 | Q35: 12040.62 | S35: -4268.85
A36: Véhicules neufsPublicité 1 | B36: Véhicules neufs | C36: Publicité 1 | E36: 91.033333 | F36: 5462 | K36: 245.72724 | L36: 14252.18 | N36: 8790.18 | P36: 131.05397 | Q36: 9566.94 | S36: 4685.24
A37: Véhicules neufsIntérêt de gros | B37: Véhicules neufs | C37: Intérêt de gros | E37: 601.02305 | F37: 36061.383 | K37: -85.485517 | L37: -4958.16 | N37: -41019.543 | P37: 474.72863 | Q37: 34655.19 | S37: -39613.35
A38: Véhicules neufs[...] | B38: Véhicules neufs | C38: [...] | E38: 0 | F38: 0 | K38: 0 | L38: 0 | N38: 0 | P38: 0 | Q38: 0 | S38: 0
A39: Véhicules neufs[...] | B39: Véhicules neufs | C39: [...] | E39: 0 | F39: 0 | K39: 0 | L39: 0 | N39: 0 | P39: 0 | Q39: 0 | S39: 0
A40: Véhicules neufs[...] | B40: Véhicules neufs | C40: [...] | E40: 0 | F40: 0 | K40: 0 | L40: 0 | N40: 0 | P40: 0 | Q40: 0 | S40: 0
A41: Véhicules neufsTOTAL VARIABLES | B41: Véhicules neufs | C41: TOTAL VARIABLES | D41: % brut | E41: 0.57110106 | F41: 118434.76 | J41: % brut | K41: 0.4090637 | L41: 78606.36 | N41: -39828.402 | O41: % brut | P41: 0.48483837 | Q41: 125866.34 | S41: -47259.98
A42: Véhicules neufsSalaires cadres | B42: Véhicules neufs | C42: Salaires cadres | F42: 24486.465 | L42: 22738.29 | N42: -1748.1754 | P42: 0.050650269 | Q42: 13149.05 | S42: 9589.24
A43: Véhicules neufsSalaires commis | B43: Véhicules neufs | C43: Salaires commis | F43: 13904.219 | L43: 12985.89 | N43: -918.32908 | Q43: 9365.85 | S43: 3620.04
A44: Véhicules neufsSalaires autres | B44: Véhicules neufs | C44: Salaires autres | F44: 315.55385 | L44: 1208.75 | N44: 893.19615 | Q44: 4575.36 | S44: -3366.61
A45: Véhicules neufsSalaires spécialistes | B45: Véhicules neufs | C45: Salaires spécialistes | F45: 0 | L45: 0 | N45: 0 | Q45: 0 | S45: 0
A46: Véhicules neufs[...] | B46: Véhicules neufs | C46: [...] | F46: 0 | L46: 0 | N46: 0 | Q46: 0 | S46: 0
A47: Véhicules neufs[...] | B47: Véhicules neufs | C47: [...] | F47: 0 | L47: 0 | N47: 0 | Q47: 0 | S47: 0
A48: Véhicules neufs[...] | B48: Véhicules neufs | C48: [...] | F48: 0 | L48: 0 | N48: 0 | Q48: 0 | S48: 0
A49: Véhicules neufsSalaires en absences | B49: Véhicules neufs | C49: Salaires en absences | F49: 13219.128 | L49: 12288.84 | N49: -930.2881 | Q49: 11763.15 | S49: 525.69
A50: Véhicules neufsDéduction à la source | B50: Véhicules neufs | C50: Déduction à la source | F50: 16072.596 | L50: 15510.75 | N50: -561.84628 | Q50: 18598.07 | S50: -3087.32
A51: Véhicules neufsBénéfices marginaux | B51: Véhicules neufs | C51: Bénéfices marginaux | F51: 8280.8811 | L51: 8178.51 | N51: -102.37113 | Q51: 7275.41 | S51: 903.1
A52: Véhicules neufsCsst | B52: Véhicules neufs | C52: Csst | F52: 3610.5108 | L52: 3094.69 | N52: -515.82076 | Q52: 3705.07 | S52: -610.38
A53: Véhicules neufs[...] | B53: Véhicules neufs | C53: [...] | D53: #N/A | F53: 0 | L53: 0 | N53: 0 | Q53: 0 | S53: 0
A54: Véhicules neufsTOTAL PERSONNEL | B54: Véhicules neufs | C54: TOTAL PERSONNEL | D54: % brut | E54: 0.38523229 | F54: 79889.355 | J54: % brut | K54: 0.3955301 | L54: 76005.72 | N54: -3883.6346 | O54: % brut | P54: 0.26360058 | Q54: 68431.96 | S54: 7573.76
A55: Véhicules neufsPublicité 2 | B55: Véhicules neufs | C55: Publicité 2 | F55: 0 | L55: 0 | N55: 0 | Q55: 0 | S55: 0
A56: Véhicules neufsService gratuit 2 | B56: Véhicules neufs | C56: Service gratuit 2 | F56: 0 | L56: 0 | N56: 0 | Q56: 0 | S56: 0
A57: Véhicules neufsFrais véhicules de cie | B57: Véhicules neufs | C57: Frais véhicules de cie | F57: 8952.5479 | L57: 5799.11 | N57: -3153.4379 | Q57: 11626.31 | S57: -5827.2
A58: Véhicules neufsInformatique | B58: Véhicules neufs | C58: Informatique | F58: 7960.9948 | L58: 7784.61 | N58: -176.38476 | Q58: 7516.3 | S58: 268.31
A59: Véhicules neufsFrais de déplacement | B59: Véhicules neufs | C59: Frais de déplacement | F59: 1266.6975 | L59: 1501.77 | N59: 235.0725 | Q59: 2705.19 | S59: -1203.42
A60: Véhicules neufsServices extérieurs | B60: Véhicules neufs | C60: Services extérieurs | F60: 7215.7407 | L60: 7415.88 | N60: 200.13928 | Q60: 6746.26 | S60: 669.62
A61: Véhicules neufsFournitures autres | B61: Véhicules neufs | C61: Fournitures autres | F61: 97.257333 | L61: 0 | N61: -97.257333 | Q61: 36.28 | S61: -36.28
A62: Véhicules neufsUniformes | B62: Véhicules neufs | C62: Uniformes | F62: 28.333333 | L62: 0 | N62: -28.333333 | Q62: 0 | S62: 0
A63: Véhicules neufsPapeterie | B63: Véhicules neufs | C63: Papeterie | F63: 741.43089 | L63: 58.13 | N63: -683.30089 | Q63: 381.04 | S63: -322.91
A64: Véhicules neufsTéléphone | B64: Véhicules neufs | C64: Téléphone | F64: 344.80198 | L64: 396.63 | N64: 51.828015 | Q64: 318.9 | S64: 77.73
A65: Véhicules neufsFrais postaux | B65: Véhicules neufs | C65: Frais postaux | F65: 102.8224 | L65: 131.27 | N65: 28.447605 | Q65: 10.56 | S65: 120.71
A66: Véhicules neufsDivers | B66: Véhicules neufs | C66: Divers | F66: 201.17039 | L66: 121.08 | N66: -80.090385 | Q66: 201.95 | S66: -80.87
... A68: Véhicules neufsFrais bancaires | B68: Véhicules neufs | C68: Frais bancaires | F68: 3725.0158 | L68: 4608.58 | N68: 883.56417 | Q68: 4277.07 | S68: 331.51
A69: Véhicules neufs[...] | B69: Véhicules neufs | C69: [...] | F69: 0 | N69: 0 | Q69: 0 | S69: 0
A70: Véhicules neufs[...] | B70: Véhicules neufs | C70: [...] | F70: 0 | L70: 0 | N70: 0 | Q70: 0 | S70: 0
A71: Véhicules neufs[...] | B71: Véhicules neufs | C71: [...] | F71: 0 | L71: 0 | N71: 0 | Q71: 0 | S71: 0
A72: Véhicules neufsTOTAL SEMI-FIXES | B72: Véhicules neufs | C72: TOTAL SEMI-FIXES | D72: % brut | E72: 0.15706224 | F72: 32571.519 | J72: % brut | K72: 0.16496079 | L72: 31699.14 | N72: -872.37932 | O72: % brut | P72: 0.13469404 | Q72: 34967.21 | S72: -3268.07
A73: Véhicules neufs | B73: Véhicules neufs
A74: Véhicules neufsTOTAL DES DÉPENSES | B74: Véhicules neufs | C74: TOTAL DES DÉPENSES | D74: % brut | E74: 1.1133956 | F74: 230895.64 | J74: % brut | K74: 0.96955459 | L74: 186311.22 | N74: -44584.416 | O74: % brut | P74: 0.88313299 | Q74: 229265.51 | S74: -42954.29
A75: Véhicules neufsProgramme neuf 1 | B75: Véhicules neufs | C75: Programme neuf 1 | F75: 0 | L75: 0 | N75: 0 | Q75: 695
A76: Véhicules neufsProgramme neuf 2 | B76: Véhicules neufs | C76: Programme neuf 2 | F76: 0 | L76: 0 | N76: 0 | Q76: 0 | S76: 0
A77: Véhicules neufsProgramme neuf 3 | B77: Véhicules neufs | C77: Programme neuf 3 | F77: 0 | L77: 0 | N77: 0 | Q77: 0 | S77: 0
A78: Véhicules neufsHoldbacks | B78: Véhicules neufs | C78: Holdbacks | E78: 1386.1697 | F78: 85942.518 | J78: 0.96464035 | K78: 1337.1552 | L78: 77555 | N78: -8387.5184 | Q78: 106078.85 | S78: -28523.85
A79: Véhicules neufs[...] | B79: Véhicules neufs | C79: [...] | F79: 0 | L79: 0 | N79: 0 | Q79: 0 | S79: 0
A80: Véhicules neufs[...] | B80: Véhicules neufs | C80: [...] | F80: 0 | L80: 0 | N80: 0 | Q80: 0 | S80: 0
A81: Véhicules neufs[...] | B81: Véhicules neufs | C81: [...] | F81: 0 | L81: 0 | N81: 0 | Q81: 0 | S81: 0
A82: Véhicules neufsFrais administration | B82: Véhicules neufs | C82: Frais administration | D82: 0.95 | E82: 474.05 | F82: 28443 | J82: 0.88902226 | K82: 421.39655 | L82: 24441 | N82: -4002 | Q82: 36038 | S82: -11597
A83: Véhicules neufsAUTRES REVENUS | B83: Véhicules neufs | C83: AUTRES REVENUS | F83: 114385.52 | L83: 101996 | N83: -12389.518 | Q83: 142811.85 | S83: -40120.85
A84: Véhicules neufs | B84: Véhicules neufs
A85: Véhicules neufsPROFIT DÉPARTEMENTAL | B85: Véhicules neufs | C85: PROFIT DÉPARTEMENTAL | F85: 90869.577 | L85: 107846.44 | N85: 16976.863 | P85: 0.044511584 | Q85: 173151.08 | S85: -64609.64
C89: Volks | K89: Véhicules usagés | S89: Réalisé, Avril 2025
D91: BUDGET ORIGINAL | J91: RÉALISATION | M91: ÉCART réel / Budget | O91: ANNÉE PRÉCÉDENTE | R91: ECART (réel/ Ann.Préc.)
D92: UNITE | E92: $P/UNITÉ | F92: $PROFITS | J92: UNITÉS | K92: $P/UNITE | L92: $PROFITS | M92: UNITÉS | N92: $PROFITS | O92: UNITE | P92: $P/UNITÉ | Q92: $PROFITS | R92: UNITÉS | S92: $PROFITS
A93: Véhicules usagésVentes nettes | B93: Véhicules usagés | C93: Ventes nettes | F93: 1417410.9 | L93: 1017681 | Q93: 1101235.5
A94: Véhicules usagésCertifié | B94: Véhicules usagés | C94: Certifié | D94: 22 | E94: 1400 | F94: 30800 | J94: 28 | K94: 952.90393 | L94: 26681.31 | M94: 6 | N94: -4118.69 | O94: 22 | P94: 1680.7486 | Q94: 36976.47 | R94: 6 | S94: -10295.16
A95: Véhicules usagésNon Certifié | B95: Véhicules usagés | C95: Non Certifié | D95: 3 | E95: 1800 | F95: 5400 | J95: 0 | K95: 0 | L95: -4705.95 | M95: -3 | N95: -10105.95 | O95: 1 | P95: 1000 | Q95: 1000 | R95: -1 | S95: -5705.95
A96: Véhicules usagésAutres Marques | B96: Véhicules usagés | C96: Autres Marques | D96: 4 | E96: 1500 | F96: 6000 | J96: 2 | K96: 2899.8 | L96: 5799.6 | M96: -2 | N96: -200.4 | O96: 0 | P96: 0 | Q96: 0 | R96: 2 | S96: 5799.6
A97: Véhicules usagésTotal Usagés | B97: Véhicules usagés | C97: Total Usagés | D97: 29 | E97: 1455.1724 | F97: 42200 | J97: 30 | K97: 925.832 | L97: 27774.96 | M97: 1 | N97: -14425.04 | O97: 23 | P97: 1651.1509 | Q97: 37976.47 | R97: 5 | S97: -16001.11
A98: Véhicules usagés | B98: Véhicules usagés | E98: 0 | M98: 0.034482759 | N98: -0.34182559 | P98: 0 | R98: 0.2173913 | S98: -0.42134274
A99: Véhicules usagés | B99: Véhicules usagés | D99: 0 | E99: 0 | F99: 0
A100: Véhicules usagésVentes au Gros | B100: Véhicules usagés | C100: Ventes au Gros | D100: 31 | E100: 400 | F100: 12400 | J100: 18 | K100: 1446.8283 | L100: 26042.91 | M100: -13 | N100: 13642.91 | O100: 31 | P100: -367.3229 | Q100: -11387.01 | R100: -13 | S100: 37429.92
A101: Véhicules usagés | B101: Véhicules usagés
A102: Véhicules usagésRev. Finances | B102: Véhicules usagés | C102: Rev. Finances | D102: 0 | E102: 0 | F102: 17400 | K102: 305.93433 | L102: 9178.03 | N102: -8221.97 | Q102: 8282.28 | R102: -305.93433 | S102: 895.75
A103: Véhicules usagésRev. Protections | B103: Véhicules usagés | C103: Rev. Protections | D103: 0 | E103: 0 | F103: 36250 | K103: 1730.1367 | L103: 51904.1 | N103: 15654.1 | Q103: 26988.31 | R103: -1730.1367 | S103: 24915.79
A104: Véhicules usagésRev. Autres | B104: Véhicules usagés | C104: Rev. Autres | D104: 0 | E104: 0 | F104: 1450 | K104: 9.5846667 | L104: 287.54 | N104: -1162.46 | Q104: 655.39 | R104: -9.5846667 | S104: -367.85
A105: Véhicules usagésTotal F&I | B105: Véhicules usagés | C105: Total F&I | D105: 29 | E105: 1900 | F105: 55100 | J105: 30 | K105: 2045.6557 | L105: 61369.67 | M105: 1 | N105: 6269.67 | O105: 23 | P105: 1561.9991 | Q105: 35925.98 | S105: 25443.69
...

Sheet Mai 2025
C1: Volks | K1: Véhicules neufs | S1: Réalisé, Mai 2025
D2: X | E2: O | F2: U | J2: NB | L2: $ | O2: X | P2: O | Q2: U | V2: *** NE PAS EFFACER / Pour An Précédente ***
D3: BUDGET ORIGINAL | J3: RÉALISATION | M3: ÉCART réel / Budget | O3: ANNÉE PRÉCÉDENTE | R3: ECART (réel/ Ann.Préc.) | V3: NEUF | W3: 0.45
D4: UNITE | E4: $P/UNITÉ | F4: $PROFITS | J4: UNITÉS | K4: $P/UNITE | L4: $PROFITS | M4: UNITÉS | N4: $PROFITS | O4: UNITE | P4: $P/UNITÉ | Q4: $PROFITS | R4: UNITÉS | S4: $PROFITS | V4: USAGE | W4: 0.1
A5: Véhicules neufsVentes nettes | B5: Véhicules neufs | C5: Ventes nettes | F5: 3234339.5 | L5: 3181778.8 | Q5: 3906259.8 | V5: SERVICE | W5: 0.225
A6: Véhicules neufsAutos détail | B6: Véhicules neufs | C6: Autos détail | D6: 16 | E6: 1953.6492 | F6: 31258.387 | J6: 10 | K6: 2530.125 | L6: 25301.25 | M6: -6 | N6: -5957.1367 | O6: 18 | P6: 1997.7756 | Q6: 35959.96 | R6: -8 | S6: -10658.71 | V6: CARROSSERIE | W6: 0.025
A7: Véhicules neufsCamions détail | B7: Véhicules neufs | C7: Camions détail | D7: 43 | E7: 2435.9047 | F7: 104743.9 | J7: 42 | K7: 2234.159 | L7: 93834.68 | M7: -1 | N7: -10909.221 | O7: 51 | P7: 2441.8604 | Q7: 124534.88 | R7: -9 | S7: -30700.2 | V7: PIECES | W7: 0.2
A8: Véhicules neufsSprinter | B8: Véhicules neufs | C8: Sprinter | D8: 0 | E8: 0 | F8: 0 | J8: 0 | K8: 0 | L8: 0 | M8: 0 | N8: 0 | O8: 0 | P8: 0 | Q8: 0 | R8: 0 | S8: 0 | W8: 1
A9: Véhicules neufsMoto détail | B9: Véhicules neufs | C9: Moto détail | D9: 0 | E9: 0 | F9: 0 | J9: 0 | K9: 0 | L9: 0 | M9: 0 | N9: 0 | O9: 0 | P9: 0 | Q9: 0 | R9: 0 | S9: 0
A10: Véhicules neufs[...] | B10: Véhicules neufs | C10: [...] | D10: 0 | E10: 0 | F10: 0 | J10: 0 | K10: 0 | L10: 0 | M10: 0 | N10: 0 | O10: 0 | P10: 0 | Q10: 0 | R10: 0 | S10: 0
A11: Véhicules neufs[...] | B11: Véhicules neufs | C11: [...] | D11: 0 | E11: 0 | F11: 0 | J11: 0 | K11: 0 | L11: 0 | M11: 0 | N11: 0 | O11: 0 | P11: 0 | Q11: 0 | R11: 0 | S11: 0
A12: Véhicules neufs[...] | B12: Véhicules neufs | C12: [...] | D12: 0 | E12: 0 | F12: 0 | J12: 0 | K12: 0 | L12: 0 | M12: 0 | N12: 0 | O12: 0 | P12: 0 | Q12: 0 | R12: 0 | S12: 0
A13: Véhicules neufsTotal Neufs | B13: Véhicules neufs | C13: Total Neufs | D13: 59 | E13: 2305.1235 | F13: 136002.29 | J13: 52 | K13: 2291.0756 | L13: 119135.93 | M13: -7 | N13: -16866.358 | O13: 69 | P13: 2326.0122 | Q13: 160494.84 | R13: -17 | S13: -41358.91
A14: Véhicules neufs | B14: Véhicules neufs | M14: -0.11864407 | N14: -0.12401525 | R14: -0.24637681 | S14: -0.2576962 | AD14: 20 | AE14: 1000 | AF14: 20000
A15: Véhicules neufsEx-Démos et courtoisies | B15: Véhicules neufs | C15: Ex-Démos et courtoisies | D15: 2 | E15: 1534.7521 | F15: 3069.5043 | J15: 5 | K15: 2015.852 | L15: 10079.26 | M15: 3 | N15: 7009.7557 | O15: 5 | P15: 1165.582 | Q15: 5827.91 | R15: 0 | S15: 4251.35 | AD15: 25 | AE15: 800 | AF15: 20000
A16: Véhicules neufs | B16: Véhicules neufs
A17: Véhicules neufsFlottes | B17: Véhicules neufs | C17: Flottes | D17: 2 | E17: 2393.8521 | F17: 4787.7042 | J17: 0 | K17: 0 | L17: 0 | M17: -2 | N17: -4787.7042 | O17: 0 | P17: 0 | Q17: 0 | R17: 0 | S17: 0
A18: Véhicules neufs | B18: Véhicules neufs
A19: Véhicules neufsRachat bail | B19: Véhicules neufs | C19: Rachat bail | D19: 0 | E19: 0 | F19: 6545 | L19: 11767.32 | N19: 5222.32 | Q19: 9930 | R19: 0 | S19: 1837.32
A20: Véhicules neufs | B20: Véhicules neufs
A21: Véhicules neufsRev. Finances | B21: Véhicules neufs | C21: Rev. Finances | D21: 0 | E21: 0 | F21: 3050 | K21: 11.182281 | L21: 637.39 | N21: -2412.61 | Q21: 800 | R21: -11.182281 | S21: -162.61
A22: Véhicules neufsRev. Protections | B22: Véhicules neufs | C22: Rev. Protections | D22: 0 | E22: 0 | F22: 56730 | K22: 1090.3154 | L22: 62147.98 | N22: 5417.98 | Q22: 58571.93 | R22: -1090.3154 | S22: 3576.05
A23: Véhicules neufsRev. Autres | B23: Véhicules neufs | C23: Rev. Autres | D23: 0 | E23: 0 | F23: 1220 | K23: 4.6777193 | L23: 266.63 | N23: -953.37 | Q23: 0 | R23: -4.6777193 | S23: 266.63
A24: Véhicules neufsTotal F&I | B24: Véhicules neufs | C24: Total F&I | D24: 61 | E24: 1000 | F24: 61000 | J24: 57 | K24: 1106.1754 | L24: 63052 | M24: -4 | N24: 2052 | O24: 74 | P24: 802.32338 | Q24: 59371.93 | S24: 3680.07
A25: Véhicules neufs | B25: Véhicules neufs | N25: 0.033639344 | S25: 0.061983331
A26: Véhicules neufs | B26: Véhicules neufs
A27: Véhicules neufsTotal Dépt. Neufs | B27: Véhicules neufs | C27: Total Dépt. Neufs | D27: 63 | E27: 3355.6269 | F27: 211404.5 | J27: 57 | K27: 3579.5528 | L27: 204034.51 | M27: -6 | N27: -7369.9864 | O27: 74 | P27: 3184.1173 | Q27: 235624.68 | R27: -17 | S27: -31590.17
A28: Véhicules neufs | B28: Véhicules neufs | L28: 0.96513799 | M28: -0.095238095 | N28: -0.034862013 | R28: -0.22972973 | S28: -0.13406987
A29: Véhicules neufs | B29: Véhicules neufs
A30: Véhicules neufsDEPENSES | B30: Véhicules neufs | C30: DEPENSES
A31: Véhicules neufsComm. vendeurs | B31: Véhicules neufs | C31: Comm. vendeurs | D31: 0.34122338 | E31: 777.94339 | F31: 47454.547 | J31: 0.33936869 | K31: 769.32614 | L31: 43851.59 | N31: -3602.9565 | O31: 0.21053999 | P31: 473.21068 | Q31: 35017.59 | S31: 8834
A32: Véhicules neufsComm. F&I | B32: Véhicules neufs | C32: Comm. F&I | D32: 0.28 | E32: 280 | F32: 17080 | J32: 0.29999762 | K32: 331.85 | L32: 18915.45 | N32: 1835.45 | O32: 0.29999833 | P32: 240.69568 | Q32: 17811.48 | S32: 1103.97
A33: Véhicules neufsFrais de livraison | B33: Véhicules neufs | C33: Frais de livraison | E33: 115 | F33: 7015 | K33: 138.49439 | L33: 7894.18 | N33: 879.18 | P33: 153.52486 | Q33: 11360.84 | S33: -3466.66
A34: Véhicules neufsService gratuit 1 | B34: Véhicules neufs | C34: Service gratuit 1 | E34: 10 | F34: 610 | K34: 0.066315789 | L34: 3.78 | N34: -606.22 | P34: 13.206486 | Q34: 977.28 | S34: -973.5
A35: Véhicules neufsEntretien stock | B35: Véhicules neufs | C35: Entretien stock | E35: 120.75 | F35: 7365.75 | K35: 167.94544 | L35: 9572.89 | N35: 2207.14 | P35: 132.78284 | Q35: 9825.93 | S35: -253.04
A36: Véhicules neufsPublicité 1 | B36: Véhicules neufs | C36: Publicité 1 | E36: 87.901639 | F36: 5362 | K36: 171.58053 | L36: 9780.09 | N36: 4418.09 | P36: 164.58405 | Q36: 12179.22 | S36: -2399.13
A37: Véhicules neufsIntérêt de gros | B37: Véhicules neufs | C37: Intérêt de gros | E37: 626.28924 | F37: 38203.644 | K37: 227.21439 | L37: 12951.22 | N37: -25252.424 | P37: 644.70649 | Q37: 47708.28 | S37: -34757.06
A38: Véhicules neufs[...] | B38: Véhicules neufs | C38: [...] | E38: 0 | F38: 0 | K38: 0 | L38: 0 | N38: 0 | P38: 0 | Q38: 0 | S38: 0
A39: Véhicules neufs[...] | B39: Véhicules neufs | C39: [...] | E39: 0 | F39: 0 | K39: 0 | L39: 0 | N39: 0 | P39: 0 | Q39: 0 | S39: 0
A40: Véhicules neufs[...] | B40: Véhicules neufs | C40: [...] | E40: 0 | F40: 0 | K40: 0 | L40: 0 | N40: 0 | P40: 0 | Q40: 0 | S40: 0
A41: Véhicules neufsTOTAL VARIABLES | B41: Véhicules neufs | C41: TOTAL VARIABLES | D41: % brut | E41: 0.58225318 | F41: 123090.94 | J41: % brut | K41: 0.50466561 | L41: 102969.2 | N41: -20121.74 | O41: % brut | P41: 0.57243842 | Q41: 134880.62 | S41: -31911.42
A42: Véhicules neufsSalaires cadres | B42: Véhicules neufs | C42: Salaires cadres | F42: 28420.582 | L42: 18969.05 | N42: -9451.5317 | P42: 0.050529427 | Q42: 11905.98 | S42: 7063.07
A43: Véhicules neufsSalaires commis | B43: Véhicules neufs | C43: Salaires commis | F43: 17167.774 | L43: 14463.37 | N43: -2704.4038 | Q43: 9609.39 | S43: 4853.98
A44: Véhicules neufsSalaires autres | B44: Véhicules neufs | C44: Salaires autres | F44: 394.44231 | L44: 2903.5 | N44: 2509.0577 | Q44: 3925.06 | S44: -1021.56
A45: Véhicules neufsSalaires spécialistes | B45: Véhicules neufs | C45: Salaires spécialistes | F45: 0 | L45: 0 | N45: 0 | Q45: 0 | S45: 0
A46: Véhicules neufs[...] | B46: Véhicules neufs | C46: [...] | F46: 0 | L46: 0 | N46: 0 | Q46: 0 | S46: 0
A47: Véhicules neufs[...] | B47: Véhicules neufs | C47: [...] | F47: 0 | L47: 0 | N47: 0 | Q47: 0 | S47: 0
A48: Véhicules neufs[...] | B48: Véhicules neufs | C48: [...] | F48: 0 | L48: 0 | N48: 0 | Q48: 0 | S48: 0
A49: Véhicules neufsSalaires en absences | B49: Véhicules neufs | C49: Salaires en absences | F49: 14936.127 | L49: 14676.27 | N49: -259.85733 | Q49: 14577.13 | S49: 99.14
A50: Véhicules neufsDéduction à la source | B50: Véhicules neufs | C50: Déduction à la source | F50: 18160.225 | L50: 17960 | N50: -200.22531 | Q50: 16512.36 | S50: 1447.64
A51: Véhicules neufsBénéfices marginaux | B51: Véhicules neufs | C51: Bénéfices marginaux | F51: 9356.4639 | L51: 8486.02 | N51: -870.44391 | Q51: 8805.59 | S51: -319.57
A52: Véhicules neufsCsst | B52: Véhicules neufs | C52: Csst | F52: 4079.4709 | L52: 2876.17 | N52: -1203.3009 | Q52: 3234.85 | S52: -358.68
A53: Véhicules neufs[...] | B53: Véhicules neufs | C53: [...] | D53: #N/A | F53: 0 | L53: 0 | N53: 0 | Q53: 0 | S53: 0
A54: Véhicules neufsTOTAL PERSONNEL | B54: Véhicules neufs | C54: TOTAL PERSONNEL | D54: % brut | E54: 0.43762118 | F54: 92515.085 | J54: % brut | K54: 0.39372937 | L54: 80334.38 | N54: -12180.705 | O54: % brut | P54: 0.29101519 | Q54: 68570.36 | S54: 11764.02
A55: Véhicules neufsPublicité 2 | B55: Véhicules neufs | C55: Publicité 2 | F55: 0 | L55: 0 | N55: 0 | Q55: 0 | S55: 0
A56: Véhicules neufsService gratuit 2 | B56: Véhicules neufs | C56: Service gratuit 2 | F56: 0 | L56: 0 | N56: 0 | Q56: 0 | S56: 0
A57: Véhicules neufsFrais véhicules de cie | B57: Véhicules neufs | C57: Frais véhicules de cie | F57: 8952.5479 | L57: 13630.57 | N57: 4678.0221 | Q57: 7403.65 | S57: 6226.92
A58: Véhicules neufsInformatique | B58: Véhicules neufs | C58: Informatique | F58: 7960.9948 | L58: 9063.09 | N58: 1102.0952 | Q58: 7461.29 | S58: 1601.8
A59: Véhicules neufsFrais de déplacement | B59: Véhicules neufs | C59: Frais de déplacement | F59: 1266.6975 | L59: 1778.24 | N59: 511.5425 | Q59: 1278.4 | S59: 499.84
A60: Véhicules neufsServices extérieurs | B60: Véhicules neufs | C60: Services extérieurs | F60: 7215.7407 | L60: 7261.42 | N60: 45.679276 | Q60: 7123.34 | S60: 138.08
A61: Véhicules neufsFournitures autres | B61: Véhicules neufs | C61: Fournitures autres | F61: 97.257333 | L61: 0 | N61: -97.257333 | Q61: 17.22 | S61: -17.22
A62: Véhicules neufsUniformes | B62: Véhicules neufs | C62: Uniformes | F62: 28.333333 | L62: 0 | N62: -28.333333 | Q62: 0 | S62: 0
A63: Véhicules neufsPapeterie | B63: Véhicules neufs | C63: Papeterie | F63: 741.43089 | L63: 1047.35 | N63: 305.91911 | Q63: 885.48 | S63: 161.87
A64: Véhicules neufsTéléphone | B64: Véhicules neufs | C64: Téléphone | F64: 344.80198 | L64: 471.73 | N64: 126.92802 | Q64: 340.16 | S64: 131.57
A65: Véhicules neufsFrais postaux | B65: Véhicules neufs | C65: Frais postaux | F65: 102.8224 | L65: 211.16 | N65: 108.3376 | Q65: 10.56 | S65: 200.6
A66: Véhicules neufsDivers | B66: Véhicules neufs | C66: Divers | F66: 201.17039 | L66: 111.68 | N66: -89.490385 | Q66: 105.31 | S66: 6.37
... A68: Véhicules neufsFrais bancaires | B68: Véhicules neufs | C68: Frais bancaires | F68: 3960.0994 | L68: 4559.64 | N68: 599.54055 | Q68: 4750.5 | S68: -190.86
A69: Véhicules neufs[...] | B69: Véhicules neufs | C69: [...] | F69: 0 | N69: 0 | Q69: 0 | S69: 0
A70: Véhicules neufs[...] | B70: Véhicules neufs | C70: [...] | F70: 0 | L70: 0 | N70: 0 | Q70: 0 | S70: 0
A71: Véhicules neufs[...] | B71: Véhicules neufs | C71: [...] | F71: 0 | L71: 0 | N71: 0 | Q71: 0 | S71: 0
A72: Véhicules neufsTOTAL SEMI-FIXES | B72: Véhicules neufs | C72: TOTAL SEMI-FIXES | D72: % brut | E72: 0.15518404 | F72: 32806.603 | J72: % brut | K72: 0.18669008 | L72: 38091.22 | N72: 5284.6171 | O72: % brut | P72: 0.12965552 | Q72: 30550.04 | S72: 7541.18
A73: Véhicules neufs | B73: Véhicules neufs
A74: Véhicules neufsTOTAL DES DÉPENSES | B74: Véhicules neufs | C74: TOTAL DES DÉPENSES | D74: % brut | E74: 1.1750584 | F74: 248412.63 | J74: % brut | K74: 1.0850851 | L74: 221394.8 | N74: -27017.828 | O74: % brut | P74: 0.99310913 | Q74: 234001.02 | S74: -12606.22
A75: Véhicules neufsProgramme neuf 1 | B75: Véhicules neufs | C75: Programme neuf 1 | F75: 0 | L75: 0 | N75: 0 | Q75: 0
A76: Véhicules neufsProgramme neuf 2 | B76: Véhicules neufs | C76: Programme neuf 2 | F76: 0 | L76: 0 | N76: 0 | Q76: 0 | S76: 0
A77: Véhicules neufsProgramme neuf 3 | B77: Véhicules neufs | C77: Programme neuf 3 | F77: 0 | L77: 0 | N77: 0 | Q77: 0 | S77: 0
A78: Véhicules neufsHoldbacks | B78: Véhicules neufs | C78: Holdbacks | E78: 1388.0997 | F78: 87450.282 | J78: 0.87876037 | K78: 1219.807 | L78: 69529 | N78: -17921.282 | Q78: 99044.7 | S78: -29515.7
A79: Véhicules neufs[...] | B79: Véhicules neufs | C79: [...] | F79: 0 | L79: 0 | N79: 0 | Q79: 0 | S79: 0
A80: Véhicules neufs[...] | B80: Véhicules neufs | C80: [...] | F80: 0 | L80: 0 | N80: 0 | Q80: 0 | S80: 0
A81: Véhicules neufs[...] | B81: Véhicules neufs | C81: [...] | F81: 0 | L81: 0 | N81: 0 | Q81: 0 | S81: 0
A82: Véhicules neufsFrais administration | B82: Véhicules neufs | C82: Frais administration | D82: 0.95 | E82: 474.05 | F82: 28917.05 | J82: 0.98067955 | K82: 464.84211 | L82: 26496 | N82: -2421.05 | Q82: 32586 | S82: -6090
A83: Véhicules neufsAUTRES REVENUS | B83: Véhicules neufs | C83: AUTRES REVENUS | F83: 116367.33 | L83: 96025 | N83: -20342.332 | Q83: 131630.7 | S83: -35605.7
A84: Véhicules neufs | B84: Véhicules neufs
A85: Véhicules neufsPROFIT DÉPARTEMENTAL | B85: Véhicules neufs | C85: PROFIT DÉPARTEMENTAL | F85: 79359.2 | L85: 78664.71 | N85: -694.48974 | P85: 0.034113031 | Q85: 133254.36 | S85: -54589.65
C89: Volks | K89: Véhicules usagés | S89: Réalisé, Mai 2025
D91: BUDGET ORIGINAL | J91: RÉALISATION | M91: ÉCART réel / Budget | O91: ANNÉE PRÉCÉDENTE | R91: ECART (réel/ Ann.Préc.)
D92: UNITE | E92: $P/UNITÉ | F92: $PROFITS | J92: UNITÉS | K92: $P/UNITE | L92: $PROFITS | M92: UNITÉS | N92: $PROFITS | O92: UNITE | P92: $P/UNITÉ | Q92: $PROFITS | R92: UNITÉS | S92: $PROFITS
A93: Véhicules usagésVentes nettes | B93: Véhicules usagés | C93: Ventes nettes | F93: 2037727.7 | L93: 1290713.8 | Q93: 1785178.6
A94: Véhicules usagésCertifié | B94: Véhicules usagés | C94: Certifié | D94: 31 | E94: 1400 | F94: 43400 | J94: 29 | K94: 1404.1734 | L94: 40721.03 | M94: -2 | N94: -2678.97 | O94: 38 | P94: 23.055789 | Q94: 876.12 | R94: -9 | S94: 39844.91
A95: Véhicules usagésNon Certifié | B95: Véhicules usagés | C95: Non Certifié | D95: 4 | E95: 1800 | F95: 7200 | J95: 1 | K95: 1376.03 | L95: 1376.03 | M95: -3 | N95: -5823.97 | O95: 2 | P95: -811.45 | Q95: -1622.9 | R95: -1 | S95: 2998.93
A96: Véhicules usagésAutres Marques | B96: Véhicules usagés | C96: Autres Marques | D96: 5 | E96: 1500 | F96: 7500 | J96: 0 | K96: 0 | L96: 0 | M96: -5 | N96: -7500 | O96: 0 | P96: 0 | Q96: 0 | R96: 0 | S96: 0
A97: Véhicules usagésTotal Usagés | B97: Véhicules usagés | C97: Total Usagés | D97: 40 | E97: 1452.5 | F97: 58100 | J97: 30 | K97: 1403.2353 | L97: 42097.06 | M97: -10 | N97: -16002.94 | O97: 40 | P97: -18.6695 | Q97: -746.78 | R97: -10 | S97: 42843.84
A98: Véhicules usagés | B98: Véhicules usagés | E98: 0 | M98: -0.25 | N98: -0.27543787 | P98: 0 | R98: -0.25 | S98: -57.371435
A99: Véhicules usagés | B99: Véhicules usagés | D99: 0 | E99: 0 | F99: 0
A100: Véhicules usagésVentes au Gros | B100: Véhicules usagés | C100: Ventes au Gros | D100: 44 | E100: 400 | F100: 17600 | J100: 26 | K100: 637.83154 | L100: 16583.62 | M100: -18 | N100: -1016.38 | O100: 47 | P100: -663.50468 | Q100: -31184.72 | R100: -21 | S100: 47768.34
A101: Véhicules usagés | B101: Véhicules usagés
A102: Véhicules usagésRev. Finances | B102: Véhicules usagés | C102: Rev. Finances | D102: 0 | E102: 0 | F102: 24000 | K102: 357.35967 | L102: 10720.79 | N102: -13279.21 | Q102: 10569.46 | R102: -357.35967 | S102: 151.33
A103: Véhicules usagésRev. Protections | B103: Véhicules usagés | C103: Rev. Protections | D103: 0 | E103: 0 | F103: 50000 | K103: 1630.4857 | L103: 48914.57 | N103: -1085.43 | Q103: 69528.23 | R103: -1630.4857 | S103: -20613.66
A104: Véhicules usagésRev. Autres | B104: Véhicules usagés | C104: Rev. Autres | D104: 0 | E104: 0 | F104: 2000 | K104: 40.291 | L104: 1208.73 | N104: -791.27 | Q104: 1317.61 | R104: -40.291 | S104: -108.88
A105: Véhicules usagésTotal F&I | B105: Véhicules usagés | C105: Total F&I | D105: 40 | E105: 1900 | F105: 76000 | J105: 30 | K105: 2028.1363 | L105: 60844.09 | M105: -10 | N105: -15155.91 | O105: 40 | P105: 2035.3825 | Q105: 81415.3 | S105: -20571.21
...

Sheet Juin 2025
C1: Volks | K1: Véhicules neufs | S1: Réalisé, Juin 2025
D2: X | E2: O | F2: U | J2: NB | L2: $ | O2: X | P2: O | Q2: U | V2: *** NE PAS EFFACER / Pour An Précédente ***
D3: BUDGET ORIGINAL | J3: RÉALISATION | M3: ÉCART réel / Budget | O3: ANNÉE PRÉCÉDENTE | R3: ECART (réel/ Ann.Préc.) | V3: NEUF | W3: 0.45
D4: UNITE | E4: $P/UNITÉ | F4: $PROFITS | J4: UNITÉS | K4: $P/UNITE | L4: $PROFITS | M4: UNITÉS | N4: $PROFITS | O4: UNITE | P4: $P/UNITÉ | Q4: $PROFITS | R4: UNITÉS | S4: $PROFITS | V4: USAGE | W4: 0.1
A5: Véhicules neufsVentes nettes | B5: Véhicules neufs | C5: Ventes nettes | F5: 3782098.2 | L5: 2263467 | Q5: 2093787.4 | V5: SERVICE | W5: 0.225
A6: Véhicules neufsAutos détail | B6: Véhicules neufs | C6: Autos détail | D6: 19 | E6: 1953.6492 | F6: 37119.334 | J6: 12 | K6: 2183.5042 | L6: 26202.05 | M6: -7 | N6: -10917.284 | O6: 15 | P6: 1651.894 | Q6: 24778.41 | R6: -3 | S6: 1423.64 | V6: CARROSSERIE | W6: 0.025
A7: Véhicules neufsCamions détail | B7: Véhicules neufs | C7: Camions détail | D7: 50 | E7: 2435.9047 | F7: 121795.23 | J7: 29 | K7: 1971.4128 | L7: 57170.97 | M7: -21 | N7: -64624.264 | O7: 25 | P7: 2415.8504 | Q7: 60396.26 | R7: 4 | S7: -3225.29 | V7: PIECES | W7: 0.2
A8: Véhicules neufsSprinter | B8: Véhicules neufs | C8: Sprinter | D8: 0 | E8: 0 | F8: 0 | J8: 0 | K8: 0 | L8: 0 | M8: 0 | N8: 0 | O8: 0 | P8: 0 | Q8: 0 | R8: 0 | S8: 0 | W8: 1
A9: Véhicules neufsMoto détail | B9: Véhicules neufs | C9: Moto détail | D9: 0 | E9: 0 | F9: 0 | J9: 0 | K9: 0 | L9: 0 | M9: 0 | N9: 0 | O9: 0 | P9: 0 | Q9: 0 | R9: 0 | S9: 0
A10: Véhicules neufs[...] | B10: Véhicules neufs | C10: [...] | D10: 0 | E10: 0 | F10: 0 | J10: 0 | K10: 0 | L10: 0 | M10: 0 | N10: 0 | O10: 0 | P10: 0 | Q10: 0 | R10: 0 | S10: 0
A11: Véhicules neufs[...] | B11: Véhicules neufs | C11: [...] | D11: 0 | E11: 0 | F11: 0 | J11: 0 | K11: 0 | L11: 0 | M11: 0 | N11: 0 | O11: 0 | P11: 0 | Q11: 0 | R11: 0 | S11: 0
A12: Véhicules neufs[...] | B12: Véhicules neufs | C12: [...] | D12: 0 | E12: 0 | F12: 0 | J12: 0 | K12: 0 | L12: 0 | M12: 0 | N12: 0 | O12: 0 | P12: 0 | Q12: 0 | R12: 0 | S12: 0
A13: Véhicules neufsTotal Neufs | B13: Véhicules neufs | C13: Total Neufs | D13: 69 | E13: 2303.1097 | F13: 158914.57 | J13: 41 | K13: 2033.4883 | L13: 83373.02 | M13: -28 | N13: -75541.548 | O13: 40 | P13: 2129.3667 | Q13: 85174.67 | R13: 1 | S13: -1801.65
A14: Véhicules neufs | B14: Véhicules neufs | M14: -0.4057971 | N14: -0.47535949 | R14: 0.025 | S14: -0.021152415 | AD14: 20 | AE14: 1000 | AF14: 20000
A15: Véhicules neufsEx-Démos et courtoisies | B15: Véhicules neufs | C15: Ex-Démos et courtoisies | D15: 4 | E15: 1534.7521 | F15: 6139.0086 | J15: 6 | K15: 1300.1783 | L15: 7801.07 | M15: 2 | N15: 1662.0614 | O15: 0 | P15: 0 | Q15: 0 | R15: 6 | S15: 7801.07 | AD15: 25 | AE15: 800 | AF15: 20000
A16: Véhicules neufs | B16: Véhicules neufs
A17: Véhicules neufsFlottes | B17: Véhicules neufs | C17: Flottes | D17: 2 | E17: 2393.8521 | F17: 4787.7042 | J17: 0 | K17: 0 | L17: 0 | M17: -2 | N17: -4787.7042 | O17: 0 | P17: 0 | Q17: 0 | R17: 0 | S17: 0
A18: Véhicules neufs | B18: Véhicules neufs
A19: Véhicules neufsRachat bail | B19: Véhicules neufs | C19: Rachat bail | D19: 0 | E19: 0 | F19: 7650 | L19: 6139.6 | N19: -1510.4 | Q19: 6100 | R19: 0 | S19: 39.6
A20: Véhicules neufs | B20: Véhicules neufs
A21: Véhicules neufsRev. Finances | B21: Véhicules neufs | C21: Rev. Finances | D21: 0 | E21: 0 | F21: 3650 | K21: 14.402128 | L21: 676.9 | N21: -2973.1 | Q21: 0 | R21: -14.402128 | S21: 676.9
A22: Véhicules neufsRev. Protections | B22: Véhicules neufs | C22: Rev. Protections | D22: 0 | E22: 0 | F22: 67890 | K22: 1023.1253 | L22: 48086.89 | N22: -19803.11 | Q22: 31000.2 | R22: -1023.1253 | S22: 17086.69
A23: Véhicules neufsRev. Autres | B23: Véhicules neufs | C23: Rev. Autres | D23: 0 | E23: 0 | F23: 1460 | K23: 0 | L23: 0 | N23: -1460 | Q23: 2699 | R23: 0 | S23: -2699
A24: Véhicules neufsTotal F&I | B24: Véhicules neufs | C24: Total F&I | D24: 73 | E24: 1000 | F24: 73000 | J24: 47 | K24: 1037.5274 | L24: 48763.79 | M24: -26 | N24: -24236.21 | O24: 40 | P24: 842.48 | Q24: 33699.2 | S24: 15064.59
A25: Véhicules neufs | B25: Véhicules neufs | N25: -0.33200288 | S25: 0.44703109
A26: Véhicules neufs | B26: Véhicules neufs
A27: Véhicules neufsTotal Dépt. Neufs | B27: Véhicules neufs | C27: Total Dépt. Neufs | D27: 75 | E27: 3339.8837 | F27: 250491.28 | J27: 47 | K27: 3108.0315 | L27: 146077.48 | M27: -28 | N27: -104413.8 | O27: 40 | P27: 3124.3467 | Q27: 124973.87 | R27: 7 | S27: 21103.61
A28: Véhicules neufs | B28: Véhicules neufs | L28: 0.58316393 | M28: -0.37333333 | N28: -0.41683607 | R28: 0.175 | S28: 0.16886418
A29: Véhicules neufs | B29: Véhicules neufs
A30: Véhicules neufsDEPENSES | B30: Véhicules neufs | C30: DEPENSES
A31: Véhicules neufsComm. vendeurs | B31: Véhicules neufs | C31: Comm. vendeurs | D31: 0.32512204 | E31: 735.1035 | F31: 53662.555 | J31: 0.34423486 | K31: 667.77234 | L31: 31385.3 | N31: -22277.255 | O31: 0.30022752 | P31: 639.2945 | Q31: 25571.78 | S31: 5813.52
A32: Véhicules neufsComm. F&I | B32: Véhicules neufs | C32: Comm. F&I | D32: 0.28 | E32: 280 | F32: 20440 | J32: 0.29928478 | K32: 310.51617 | L32: 14594.26 | N32: -5845.74 | O32: 0.0032629855 | P32: 2.749 | Q32: 109.96 | S32: 14484.3
A33: Véhicules neufsFrais de livraison | B33: Véhicules neufs | C33: Frais de livraison | E33: 115 | F33: 8395 | K33: 111.73617 | L33: 5251.6 | N33: -3143.4 | P33: 130.5265 | Q33: 5221.06 | S33: 30.54
A34: Véhicules neufsService gratuit 1 | B34: Véhicules neufs | C34: Service gratuit 1 | E34: 10 | F34: 730 | K34: 5.4995745 | L34: 258.48 | N34: -471.52 | P34: 4.62375 | Q34: 184.95 | S34: 73.53
A35: Véhicules neufsEntretien stock | B35: Véhicules neufs | C35: Entretien stock | E35: 120.75 | F35: 8814.75 | K35: 168.73936 | L35: 7930.75 | N35: -884 | P35: 185.7815 | Q35: 7431.26 | S35: 499.49
A36: Véhicules neufsPublicité 1 | B36: Véhicules neufs | C36: Publicité 1 | E36: 57.013699 | F36: 4162 | K36: 108.28021 | L36: 5089.17 | N36: 927.17 | P36: 266.85925 | Q36: 10674.37 | S36: -5585.2
A37: Véhicules neufsIntérêt de gros | B37: Véhicules neufs | C37: Intérêt de gros | E37: 523.33758 | F37: 38203.644 | K37: 280.19213 | L37: 13169.03 | N37: -25034.614 | P37: 1001.4042 | Q37: 40056.17 | S37: -26887.14
A38: Véhicules neufs[...] | B38: Véhicules neufs | C38: [...] | E38: 0 | F38: 0 | K38: 0 | L38: 0 | N38: 0 | P38: 0 | Q38: 0 | S38: 0
A39: Véhicules neufs[...] | B39: Véhicules neufs | C39: [...] | E39: 0 | F39: 0 | K39: 0 | L39: 0 | N39: 0 | P39: 0 | Q39: 0 | S39: 0
A40: Véhicules neufs[...] | B40: Véhicules neufs | C40: [...] | E40: 0 | F40: 0 | K40: 0 | L40: 0 | N40: 0 | P40: 0 | Q40: 0 | S40: 0
A41: Véhicules neufsTOTAL VARIABLES | B41: Véhicules neufs | C41: TOTAL VARIABLES | D41: % brut | E41: 0.53657736 | F41: 134407.95 | J41: % brut | K41: 0.53176294 | L41: 77678.59 | N41: -56729.359 | O41: % brut | P41: 0.71414569 | Q41: 89249.55 | S41: -11570.96
A42: Véhicules neufsSalaires cadres | B42: Véhicules neufs | C42: Salaires cadres | F42: 24486.465 | L42: 17276.74 | N42: -7209.7254 | P42: 0.10014253 | Q42: 12515.2 | S42: 4761.54
A43: Véhicules neufsSalaires commis | B43: Véhicules neufs | C43: Salaires commis | F43: 13904.219 | L43: 12517.38 | N43: -1386.8391 | Q43: 10896.4 | S43: 1620.98
A44: Véhicules neufsSalaires autres | B44: Véhicules neufs | C44: Salaires autres | F44: 315.55385 | L44: 1819.6 | N44: 1504.0462 | Q44: 2584.64 | S44: -765.04
A45: Véhicules neufsSalaires spécialistes | B45: Véhicules neufs | C45: Salaires spécialistes | F45: 0 | L45: 0 | N45: 0 | Q45: 0 | S45: 0
A46: Véhicules neufs[...] | B46: Véhicules neufs | C46: [...] | F46: 0 | L46: 0 | N46: 0 | Q46: 0 | S46: 0
A47: Véhicules neufs[...] | B47: Véhicules neufs | C47: [...] | F47: 0 | L47: 0 | N47: 0 | Q47: 0 | S47: 0
A48: Véhicules neufs[...] | B48: Véhicules neufs | C48: [...] | F48: 0 | L48: 0 | N48: 0 | Q48: 0 | S48: 0
A49: Véhicules neufsSalaires en absences | B49: Véhicules neufs | C49: Salaires en absences | F49: 11620.017 | L49: 11092.96 | N49: -527.05675 | Q49: 10189.97 | S49: 902.99
A50: Véhicules neufsDéduction à la source | B50: Véhicules neufs | C50: Déduction à la source | F50: 14128.302 | L50: 13743.57 | N50: -384.73231 | Q50: 11457.24 | S50: 2286.33
A51: Véhicules neufsBénéfices marginaux | B51: Véhicules neufs | C51: Bénéfices marginaux | F51: 7279.1471 | L51: 6407 | N51: -872.14706 | Q51: 6085.69 | S51: 321.31
A52: Véhicules neufsCsst | B52: Véhicules neufs | C52: Csst | F52: 3173.7491 | L52: 2667.67 | N52: -506.07907 | Q52: 1674.44 | S52: 993.23
A53: Véhicules neufs[...] | B53: Véhicules neufs | C53: [...] | D53: #N/A | F53: 0 | L53: 0 | N53: 0 | Q53: 0 | S53: 0
A54: Véhicules neufsTOTAL PERSONNEL | B54: Véhicules neufs | C54: TOTAL PERSONNEL | D54: % brut | E54: 0.29904216 | F54: 74907.453 | J54: % brut | K54: 0.44856278 | L54: 65524.92 | N54: -9382.5335 | O54: % brut | P54: 0.44332131 | Q54: 55403.58 | S54: 10121.34
A55: Véhicules neufsPublicité 2 | B55: Véhicules neufs | C55: Publicité 2 | F55: 0 | L55: 0 | N55: 0 | Q55: 0 | S55: 0
A56: Véhicules neufsService gratuit 2 | B56: Véhicules neufs | C56: Service gratuit 2 | F56: 0 | L56: 0 | N56: 0 | Q56: 0 | S56: 0
A57: Véhicules neufsFrais véhicules de cie | B57: Véhicules neufs | C57: Frais véhicules de cie | F57: 8952.5479 | L57: 11014.36 | N57: 2061.8121 | Q57: 7254.82 | S57: 3759.54
A58: Véhicules neufsInformatique | B58: Véhicules neufs | C58: Informatique | F58: 7960.9948 | L58: 5623.99 | N58: -2337.0048 | Q58: 7043.39 | S58: -1419.4
A59: Véhicules neufsFrais de déplacement | B59: Véhicules neufs | C59: Frais de déplacement | F59: 1266.6975 | L59: 2225.94 | N59: 959.2425 | Q59: 1316.83 | S59: 909.11
A60: Véhicules neufsServices extérieurs | B60: Véhicules neufs | C60: Services extérieurs | F60: 7215.7407 | L60: 6186.82 | N60: -1028.9207 | Q60: 7463.74 | S60: -1276.92
A61: Véhicules neufsFournitures autres | B61: Véhicules neufs | C61: Fournitures autres | F61: 97.257333 | L61: 0 | N61: -97.257333 | Q61: 4.56 | S61: -4.56
A62: Véhicules neufsUniformes | B62: Véhicules neufs | C62: Uniformes | F62: 28.333333 | L62: 0 | N62: -28.333333 | Q62: 0 | S62: 0
A63: Véhicules neufsPapeterie | B63: Véhicules neufs | C63: Papeterie | F63: 741.43089 | L63: 408.53 | N63: -332.90089 | Q63: 387.99 | S63: 20.54
A64: Véhicules neufsTéléphone | B64: Véhicules neufs | C64: Téléphone | F64: 344.80198 | L64: 389.49 | N64: 44.688015 | Q64: 326.92 | S64: 62.57
A65: Véhicules neufsFrais postaux | B65: Véhicules neufs | C65: Frais postaux | F65: 102.8224 | L65: 88.36 | N65: -14.462395 | Q65: 32.96 | S65: 55.4
A66: Véhicules neufsDivers | B66: Véhicules neufs | C66: Divers | F66: 201.17039 | L66: 62.72 | N66: -138.45039 | Q66: 123.77 | S66: -61.05
... A68: Véhicules neufsFrais bancaires | B68: Véhicules neufs | C68: Frais bancaires | F68: 3689.0506 | L68: 3513.7 | N68: -175.35059 | Q68: 3357.81 | S68: 155.89
A69: Véhicules neufs[...] | B69: Véhicules neufs | C69: [...] | F69: 0 | N69: 0 | Q69: 0 | S69: 0
A70: Véhicules neufs[...] | B70: Véhicules neufs | C70: [...] | F70: 0 | L70: 0 | N70: 0 | Q70: 0 | S70: 0
A71: Véhicules neufs[...] | B71: Véhicules neufs | C71: [...] | F71: 0 | L71: 0 | N71: 0 | Q71: 0 | S71: 0
A72: Véhicules neufsTOTAL SEMI-FIXES | B72: Véhicules neufs | C72: TOTAL SEMI-FIXES | D72: % brut | E72: 0.12988697 | F72: 32535.554 | J72: % brut | K72: 0.21780216 | L72: 31815.99 | N72: -719.56408 | O72: % brut | P72: 0.22968153 | Q72: 28704.19 | S72: 3111.8
A73: Véhicules neufs | B73: Véhicules neufs
A74: Véhicules neufsTOTAL DES DÉPENSES | B74: Véhicules neufs | C74: TOTAL DES DÉPENSES | D74: % brut | E74: 0.96550649 | F74: 241850.96 | J74: % brut | K74: 1.1981279 | L74: 175019.5 | N74: -66831.457 | O74: % brut | P74: 1.3871485 | Q74: 173357.32 | S74: 1662.18
A75: Véhicules neufsProgramme neuf 1 | B75: Véhicules neufs | C75: Programme neuf 1 | F75: 25000 | L75: 12000 | N75: -13000 | Q75: 20000
A76: Véhicules neufsProgramme neuf 2 | B76: Véhicules neufs | C76: Programme neuf 2 | F76: 0 | L76: 0 | N76: 0 | Q76: 0 | S76: 0
A77: Véhicules neufsProgramme neuf 3 | B77: Véhicules neufs | C77: Programme neuf 3 | F77: 0 | L77: 0 | N77: 0 | Q77: 0 | S77: 0
A78: Véhicules neufsHoldbacks | B78: Véhicules neufs | C78: Holdbacks | E78: 1407.2459 | F78: 105543.44 | J78: 0.92553725 | K78: 1302.4585 | L78: 61215.55 | N78: -44327.894 | Q78: 55522 | S78: 5693.55
A79: Véhicules neufs[...] | B79: Véhicules neufs | C79: [...] | F79: 0 | L79: 0 | N79: 0 | Q79: 0 | S79: 0
A80: Véhicules neufs[...] | B80: Véhicules neufs | C80: [...] | F80: 0 | L80: 0 | N80: 0 | Q80: 0 | S80: 0
A81: Véhicules neufs[...] | B81: Véhicules neufs | C81: [...] | F81: 0 | L81: 0 | N81: 0 | Q81: 0 | S81: 0
A82: Véhicules neufsFrais administration | B82: Véhicules neufs | C82: Frais administration | D82: 0.95 | E82: 474.05 | F82: 34605.65 | J82: 1.0479397 | K82: 496.7234 | L82: 23346 | N82: -11259.65 | Q82: 19532.5 | S82: 3813.5
A83: Véhicules neufsAUTRES REVENUS | B83: Véhicules neufs | C83: AUTRES REVENUS | F83: 165149.09 | L83: 96561.55 | N83: -68587.544 | Q83: 95054.5 | S83: 9507.05
A84: Véhicules neufs | B84: Véhicules neufs
A85: Véhicules neufsPROFIT DÉPARTEMENTAL | B85: Véhicules neufs | C85: PROFIT DÉPARTEMENTAL | F85: 173789.42 | L85: 67619.53 | N85: -106169.89 | P85: 0.022290253 | Q85: 46671.05 | S85: 28948.48
C89: Volks | K89: Véhicules usagés | S89: Réalisé, Juin 2025
D91: BUDGET ORIGINAL | J91: RÉALISATION | M91: ÉCART réel / Budget | O91: ANNÉE PRÉCÉDENTE | R91: ECART (réel/ Ann.Préc.)
D92: UNITE | E92: $P/UNITÉ | F92: $PROFITS | J92: UNITÉS | K92: $P/UNITE | L92: $PROFITS | M92: UNITÉS | N92: $PROFITS | O92: UNITE | P92: $P/UNITÉ | Q92: $PROFITS | R92: UNITÉS | S92: $PROFITS
A93: Véhicules usagésVentes nettes | B93: Véhicules usagés | C93: Ventes nettes | F93: 1743301.4 | L93: 1616914.6 | Q93: 1325634.6
A94: Véhicules usagésCertifié | B94: Véhicules usagés | C94: Certifié | D94: 30 | E94: 1400 | F94: 42000 | J94: 30 | K94: 1968.675 | L94: 59060.25 | M94: 0 | N94: 17060.25 | O94: 31 | P94: 599.35871 | Q94: 18580.12 | R94: -1 | S94: 40480.13
A95: Véhicules usagésNon Certifié | B95: Véhicules usagés | C95: Non Certifié | D95: 3 | E95: 1800 | F95: 5400 | J95: 0 | K95: 0 | L95: 0 | M95: -3 | N95: -5400 | O95: 2 | P95: 1491.09 | Q95: 2982.18 | R95: -2 | S95: -2982.18
A96: Véhicules usagésAutres Marques | B96: Véhicules usagés | C96: Autres Marques | D96: 5 | E96: 1500 | F96: 7500 | J96: 0 | K96: 0 | L96: 0 | M96: -5 | N96: -7500 | O96: 0 | P96: 0 | Q96: 0 | R96: 0 | S96: 0
A97: Véhicules usagésTotal Usagés | B97: Véhicules usagés | C97: Total Usagés | D97: 38 | E97: 1444.7368 | F97: 54900 | J97: 30 | K97: 1968.675 | L97: 59060.25 | M97: -8 | N97: 4160.25 | O97: 33 | P97: 653.40303 | Q97: 21562.3 | R97: -3 | S97: 37497.95
A98: Véhicules usagés | B98: Véhicules usagés | E98: 0 | M98: -0.21052632 | N98: 0.075778689 | P98: 0 | R98: -0.090909091 | S98: 1.7390515
A99: Véhicules usagés | B99: Véhicules usagés | D99: 0 | E99: 0 | F99: 0
A100: Véhicules usagésVentes au Gros | B100: Véhicules usagés | C100: Ventes au Gros | D100: 38 | E100: 400 | F100: 15200 | J100: 45 | K100: 996.06622 | L100: 44822.98 | M100: 7 | N100: 29622.98 | O100: 29 | P100: 144.99517 | Q100: 4204.86 | R100: 16 | S100: 40618.12
A101: Véhicules usagés | B101: Véhicules usagés
A102: Véhicules usagésRev. Finances | B102: Véhicules usagés | C102: Rev. Finances | D102: 0 | E102: 0 | F102: 22800 | K102: 373.984 | L102: 11219.52 | N102: -11580.48 | Q102: 9012.23 | R102: -373.984 | S102: 2207.29
A103: Véhicules usagésRev. Protections | B103: Véhicules usagés | C103: Rev. Protections | D103: 0 | E103: 0 | F103: 47500 | K103: 1465.0157 | L103: 43950.47 | N103: -3549.53 | Q103: 50120.45 | R103: -1465.0157 | S103: -6169.98
A104: Véhicules usagésRev. Autres | B104: Véhicules usagés | C104: Rev. Autres | D104: 0 | E104: 0 | F104: 1900 | K104: 71.340333 | L104: 2140.21 | N104: 240.21 | Q104: 0 | R104: -71.340333 | S104: 2140.21
A105: Véhicules usagésTotal F&I | B105: Véhicules usagés | C105: Total F&I | D105: 38 | E105: 1900 | F105: 72200 | J105: 30 | K105: 1910.34 | L105: 57310.2 | M105: -8 | N105: -14889.8 | O105: 33 | P105: 1791.8994 | Q105: 59132.68 | S105: -1822.48
...

Sheet END
