Workbook
Name _Dates_Conc: [1]Dealers!$BF$37:$KA$63
Name _scen: '[1]Scen & Sens'!$E$26
Name _scen1: '[1]Scen & Sens'!$E$27
Name _scen2: '[1]Scen & Sens'!$E$28
Name _SCenarios: '[1]Scen & Sens'!$J$26:$O$26
Name _Sens1: '[1]Scen & Sens'!$F$9
Name _Sens2: '[1]Scen & Sens'!$F$10
Name _sensRes1: '[1]Scen & Sens'!$E$15
Name _sensRes2: '[1]Scen & Sens'!$E$16
Name _sensRes3: '[1]Scen & Sens'!$E$17
Name _sensRes4: '[1]Scen & Sens'!$E$18
Name _sensRes5: '[1]Scen & Sens'!$E$19
Name _sensRes6: '[1]Scen & Sens'!$E$20
Name _sensRes7: '[1]Scen & Sens'!$E$21
Name DateRange: [1]Volkswagen!$BF$6:$DY$6
Name Monetary_Unit: [1]Parameters!$B$15
Name Months: [1]Parameters!$E$9:$E$20
Name Rng_Dealers_Names: [1]!Tbl_Dealers[Dealer Name]
Name Rng_Dlr_Dates: [1]!Tbl_V_Dlr_Dates[Date]
Name Ticker: #REF!
Name Ticker: #REF!
Name Ticker: #REF!
Name Titre: [1]Front!$A$9

Sheet Paramètre
B3: Quarter
B6: BUDGET | F6: BUDGET RÉVISÉ | J6: ACTUAL | N6: LAST YEAR
B7: Ventes | C7: Profits bruts | D7: BAIIA | E7: EBIT | F7: Ventes | G7: Profits bruts | H7: BAIIA | I7: EBIT | J7: Ventes | K7: Profits bruts | L7: BAIIA | M7: EBIT | N7: Ventes | O7: Profits bruts | P7: BAIIA | Q7: EBIT
A8: CTRL | B8: =+B9-B10 -> #REF! | C8: =+C9-C10 -> #REF! | D8: =+D9-D10 -> #REF! | E8: =+E9-E10 -> #REF! | F8: =+F9-F10 -> #REF! | G8: =+G9-G10 -> #REF! | H8: =+H9-H10 -> #REF! | I8: =+I9-I10 -> #REF! | ... Q8: =+Q9-Q10 -> #REF!
A9: CONSO | B9: =+Conso!$Z$405 -> 18674893 | C9: =+Conso!$Z$406 -> 2124468.2 | D9: =+Conso!$Z$482 -> 529849.51 | E9: =+Conso!$Z$497 -> 402143.01 | F9: =+Conso!$AC$405 -> 0 | G9: =+Conso!$AC$406 -> 0 | H9: =+Conso!$AC$482 -> 0 | I9: =+Conso!$AC$497 -> 0 | J9: =+Conso!$AF$405 -> 18192349 | K9: =+Conso!$AF$406 -> 2265034.2 | L9: =+Conso!$AF$482 -> 875124.12 | M9: =+Conso!$AF$497 -> 749338.12 | N9: =+Conso!$AL$405 -> 17443640 | O9: =+Conso!$AL$406 -> 1880122.8 | P9: =+Conso!$AL$482 -> 419717.69 | Q9: =+Conso!$AL$497 -> 322893.68
A10: TOTAL | B10: =+SUM(B11:B13) -> #REF! | C10: =+SUM(C11:C13) -> #REF! | D10: =+SUM(D11:D13) -> #REF! | E10: =+SUM(E11:E13) -> #REF! | F10: =+SUM(F11:F13) -> #REF! | G10: =+SUM(G11:G13) -> #REF! | H10: =+SUM(H11:H13) -> #REF! | I10: =+SUM(I11:I13) -> #REF! | ... Q10: =+SUM(Q11:Q13) -> #REF!
A11: Mois 1 | B11: =+#REF! -> #REF! | C11: =+#REF! -> #REF! | D11: =+#REF! -> #REF! | E11: =+#REF! -> #REF! | F11: =+#REF! -> #REF! | G11: =+#REF! -> #REF! | H11: =+#REF! -> #REF! | I11: =+#REF! -> #REF! | ... Q11: =+#REF! -> #REF!
A12: Mois 2 | B12: =+#REF! -> #REF! | C12: =+#REF! -> #REF! | D12: =+#REF! -> #REF! | E12: =+#REF! -> #REF! | F12: =+#REF! -> #REF! | G12: =+#REF! -> #REF! | H12: =+#REF! -> #REF! | I12: =+#REF! -> #REF! | ... Q12: =+#REF! -> #REF!
A13: Mois 3 | B13: =+#REF! -> #REF! | C13: =+#REF! -> #REF! | D13: =+#REF! -> #REF! | E13: =+#REF! -> #REF! | F13: =+#REF! -> #REF! | G13: =+#REF! -> #REF! | H13: =+#REF! -> #REF! | I13: =+#REF! -> #REF! | ... Q13: =+#REF! -> #REF!

Sheet Conso
C1: Conso | K1: Véhicules neufs | S1: =CONCATENATE("Réalisé"," ",Paramètre!$C$2," ",Paramètre!$C$3) -> Réalisé
D2: X | E2: O | F2: U | G2: X | H2: O | I2: U
D3: BUDGET ORIGINAL | G3: BUDGET REVISE | J3: RÉALISATION | M3: ÉCART réel / original | O3: ANNÉE PRÉCÉDENTE | R3: ÉCART réel / année précédente
D4: UNITE | E4: $P/UNITÉ | F4: $PROFITS | G4: UNITE | H4: $P/UNITÉ | I4: $PROFITS | J4: UNITE | K4: $P/UNITE | L4: $PROFITS | M4: UNITÉ | N4: $PROFITS | O4: UNITE | P4: $P/UNITE | Q4: $PROFITS | R4: UNITE | S4: $PROFITS
A5: =+B5&C5 -> Véhicules neufsVentes nettes | B5: =+$K$1 -> Véhicules neufs | C5: Ventes nettes | F5: =+SUM(START:END!F5) -> 11763417 | I5: =+SUM(START:END!I5) -> 0 | L5: =+SUM(START:END!L5) -> 10668360 | Q5: =+SUM(START:END!Q5) -> 11588445
A6: =+B6&C6 -> Véhicules neufsAutos détail | B6: =+$K$1 -> Véhicules neufs | C6: Autos détail | D6: =+SUM(START:END!D6) -> 58 | E6: =IF(D6=0,0,F6/D6) -> 1953.6492 | F6: =+SUM(START:END!F6) -> 113311.65 | G6: =+SUM(START:END!G6) -> 0 | H6: =IF(G6=0,0,I6/G6) -> 0 | I6: =+SUM(START:END!I6) -> 0 | J6: =+SUM(START:END!J6) -> 27 | K6: =IF(J6=0,0,L6/J6) -> 1261.5104 | L6: =+SUM(START:END!L6) -> 34060.78 | M6: =J6-D6 -> -31 | N6: =L6-F6 -> -79250.872 | O6: =+SUM(START:END!O6) -> 58 | P6: =IF(O6=0,0,Q6/O6) -> 1768.8329 | Q6: =+SUM(START:END!Q6) -> 102592.31 | R6: =J6-O6 -> -31 | S6: =L6-Q6 -> -68531.53
A7: =+B7&C7 -> Véhicules neufsCamions détail | B7: =+$K$1 -> Véhicules neufs | C7: Camions détail | D7: =+SUM(START:END!D7) -> 155 | E7: =IF(D7=0,0,F7/D7) -> 2435.9047 | F7: =+SUM(START:END!F7) -> 377565.23 | G7: =+SUM(START:END!G7) -> 0 | H7: =IF(G7=0,0,I7/G7) -> 0 | I7: =+SUM(START:END!I7) -> 0 | J7: =+SUM(START:END!J7) -> 175 | K7: =IF(J7=0,0,L7/J7) -> 2328.2872 | L7: =+SUM(START:END!L7) -> 407450.26 | M7: =J7-D7 -> 20 | N7: =L7-F7 -> 29885.035 | O7: =+SUM(START:END!O7) -> 142 | P7: =IF(O7=0,0,Q7/O7) -> 2240.5756 | Q7: =+SUM(START:END!Q7) -> 318161.73 | R7: =J7-O7 -> 33 | S7: =L7-Q7 -> 89288.53
A8: =+B8&C8 -> Véhicules neufsSprinter | B8: =+$K$1 -> Véhicules neufs | C8: Sprinter | D8: =+SUM(START:END!D8) -> 0 | E8: =IF(D8=0,0,F8/D8) -> 0 | F8: =+SUM(START:END!F8) -> 0 | G8: =+SUM(START:END!G8) -> 0 | H8: =IF(G8=0,0,I8/G8) -> 0 | I8: =+SUM(START:END!I8) -> 0 | J8: =+SUM(START:END!J8) -> 0 | K8: =IF(J8=0,0,L8/J8) -> 0 | L8: =+SUM(START:END!L8) -> 0 | M8: =J8-D8 -> 0 | N8: =L8-F8 -> 0 | O8: =+SUM(START:END!O8) -> 0 | P8: =IF(O8=0,0,Q8/O8) -> 0 | Q8: =+SUM(START:END!Q8) -> 0 | R8: =J8-O8 -> 0 | S8: =L8-Q8 -> 0
A9: =+B9&C9 -> Véhicules neufsMoto détail | B9: =+$K$1 -> Véhicules neufs | C9: Moto détail | D9: =+SUM(START:END!D9) -> 0 | E9: =IF(D9=0,0,F9/D9) -> 0 | F9: =+SUM(START:END!F9) -> 0 | G9: =+SUM(START:END!G9) -> 0 | H9: =IF(G9=0,0,I9/G9) -> 0 | I9: =+SUM(START:END!I9) -> 0 | J9: =+SUM(START:END!J9) -> 0 | K9: =IF(J9=0,0,L9/J9) -> 0 | L9: =+SUM(START:END!L9) -> 0 | M9: =J9-D9 -> 0 | N9: =L9-F9 -> 0 | O9: =+SUM(START:END!O9) -> 0 | P9: =IF(O9=0,0,Q9/O9) -> 0 | Q9: =+SUM(START:END!Q9) -> 0 | R9: =J9-O9 -> 0 | S9: =L9-Q9 -> 0
A10: =+B10&C10 -> Véhicules neufs[...] | B10: =+$K$1 -> Véhicules neufs | C10: [...] | D10: =+SUM(START:END!D10) -> 0 | E10: =IF(D10=0,0,F10/D10) -> 0 | F10: =+SUM(START:END!F10) -> 0 | G10: =+SUM(START:END!G10) -> 0 | H10: =IF(G10=0,0,I10/G10) -> 0 | I10: =+SUM(START:END!I10) -> 0 | J10: =+SUM(START:END!J10) -> 0 | K10: =IF(J10=0,0,L10/J10) -> 0 | L10: =+SUM(START:END!L10) -> 0 | M10: =J10-G10 -> 0 | N10: =L10-I10 -> 0 | O10: =+SUM(START:END!O10) -> 0 | P10: =IF(O10=0,0,Q10/O10) -> 0 | Q10: =+SUM(START:END!Q10) -> 0 | R10: =J10-O10 -> 0 | S10: =L10-Q10 -> 0
A11: =+B11&C11 -> Véhicules neufs[...] | B11: =+$K$1 -> Véhicules neufs | C11: [...] | D11: =+SUM(START:END!D11) -> 0 | E11: =IF(D11=0,0,F11/D11) -> 0 | F11: =+SUM(START:END!F11) -> 0 | G11: =+SUM(START:END!G11) -> 0 | H11: =IF(G11=0,0,I11/G11) -> 0 | I11: =+SUM(START:END!I11) -> 0 | J11: =+SUM(START:END!J11) -> 0 | K11: =IF(J11=0,0,L11/J11) -> 0 | L11: =+SUM(START:END!L11) -> 0 | M11: =J11-G11 -> 0 | N11: =L11-I11 -> 0 | O11: =+SUM(START:END!O11) -> 0 | P11: =IF(O11=0,0,Q11/O11) -> 0 | Q11: =+SUM(START:END!Q11) -> 0 | R11: =J11-O11 -> 0 | S11: =L11-Q11 -> 0
A12: =+B12&C12 -> Véhicules neufs[...] | B12: =+$K$1 -> Véhicules neufs | C12: [...] | D12: =+SUM(START:END!D12) -> 0 | E12: =IF(D12=0,0,F12/D12) -> 0 | F12: =+SUM(START:END!F12) -> 0 | G12: =+SUM(START:END!G12) -> 0 | H12: =IF(G12=0,0,I12/G12) -> 0 | I12: =+SUM(START:END!I12) -> 0 | J12: =+SUM(START:END!J12) -> 0 | K12: =IF(J12=0,0,L12/J12) -> 0 | L12: =+SUM(START:END!L12) -> 0 | M12: =J12-G12 -> 0 | N12: =L12-I12 -> 0 | O12: =+SUM(START:END!O12) -> 0 | P12: =IF(O12=0,0,Q12/O12) -> 0 | Q12: =+SUM(START:END!Q12) -> 0 | R12: =J12-O12 -> 0 | S12: =L12-Q12 -> 0
A13: =+B13&C13 -> Véhicules neufsTotal Neufs | B13: =+$K$1 -> Véhicules neufs | C13: Total Neufs | D13: =+SUM(D6:D12) -> 213 | E13: =IF(D13<=0,0,F13/D13) -> 2304.5863 | F13: =+SUM(F6:F12) -> 490876.88 | G13: =+SUM(G6:G12) -> 0 | H13: =IF(G13<=0,0,I13/G13) -> 0 | I13: =+SUM(I6:I12) -> 0 | J13: =+SUM(J6:J12) -> 202 | K13: =IF(J13<=0,0,L13/J13) -> 2185.6982 | L13: =+SUM(L6:L12) -> 441511.04 | M13: =+SUM(M6:M12) -> -11 | N13: =+SUM(N6:N12) -> -49365.837 | O13: =+SUM(O6:O12) -> 200 | P13: =IF(O13<=0,0,Q13/O13) -> 2103.7702 | Q13: =+SUM(Q6:Q12) -> 420754.04 | R13: =+SUM(R6:R12) -> 2 | S13: =+SUM(S6:S12) -> 20757
A14: =+B14&C14 -> Véhicules neufs | B14: =+$K$1 -> Véhicules neufs | N14: =IF(F13=0,0,N13/F13) -> -0.10056664 | R14: =R13/O13 -> 0.01 | S14: =IF(Q13=0,0,(S13/Q13)) -> 0.04933286
A15: =+B15&C15 -> Véhicules neufsEx-Démos et courtoisies | B15: =+$K$1 -> Véhicules neufs | C15: Ex-Démos et courtoisies | D15: =+SUM(START:END!D15) -> 11 | E15: =IF(D15=0,0,F15/D15) -> 1534.7521 | F15: =+SUM(START:END!F15) -> 16882.274 | G15: =+SUM(START:END!G15) -> 0 | H15: =IF(G15=0,0,I15/G15) -> 0 | I15: =+SUM(START:END!I15) -> 0 | J15: =+SUM(START:END!J15) -> 6 | K15: =IF(J15=0,0,L15/J15) -> 1347.48 | L15: =+SUM(START:END!L15) -> 8084.88 | M15: =J15-D15 -> -5 | N15: =L15-F15 -> -8797.3936 | O15: =+SUM(START:END!O15) -> 12 | P15: =IF(O15=0,0,Q15/O15) -> 1630.9883 | Q15: =+SUM(START:END!Q15) -> 19571.86 | R15: =J15-O15 -> -6 | S15: =L15-Q15 -> -11486.98
A16: =+B16&C16 -> Véhicules neufs | B16: =+$K$1 -> Véhicules neufs
A17: =+B17&C17 -> Véhicules neufsFlottes | B17: =+$K$1 -> Véhicules neufs | C17: Flottes | D17: =+SUM(START:END!D17) -> 6 | E17: =IF(D17=0,0,F17/D17) -> 2393.8521 | F17: =+SUM(START:END!F17) -> 14363.113 | G17: =+SUM(START:END!G17) -> 0 | H17: =IF(G17=0,0,I17/G17) -> 0 | I17: =+SUM(START:END!I17) -> 0 | J17: =+SUM(START:END!J17) -> 6 | K17: =IF(J17=0,0,L17/J17) -> 626.18667 | L17: =+SUM(START:END!L17) -> 3757.12 | M17: =J17-D17 -> 0 | N17: =L17-F17 -> -10605.993 | O17: =+SUM(START:END!O17) -> 7 | P17: =IF(O17=0,0,Q17/O17) -> 2725.3286 | Q17: =+SUM(START:END!Q17) -> 19077.3 | R17: =J17-O17 -> -1 | S17: =L17-Q17 -> -15320.18
A18: =+B18&C18 -> Véhicules neufs | B18: =+$K$1 -> Véhicules neufs
A19: =+B19&C19 -> Véhicules neufsRachat bail | B19: =+$K$1 -> Véhicules neufs | C19: Rachat bail | F19: =+SUM(START:END!F19) -> 23800 | I19: =+SUM(START:END!I19) -> 0 | L19: =+SUM(START:END!L19) -> 35877.19 | N19: =L19-F19 -> 12077.19 | Q19: =+SUM(START:END!Q19) -> 29115 | R19: =O19-K19 -> 0 | S19: =L19-Q19 -> 6762.19
A20: =+B20&C20 -> Véhicules neufs | B20: =+$K$1 -> Véhicules neufs
A21: =+B21&C21 -> Véhicules neufsRev. Finances | B21: =+$K$1 -> Véhicules neufs | C21: Rev. Finances | D21: 0 | E21: =IF(D21=0,0,F21/D21) -> 0 | F21: =+SUM(START:END!F21) -> 11200 | G21: 0 | H21: =IF(G21=0,0,I21/G21) -> 0 | I21: =+SUM(START:END!I21) -> 0 | K21: =IF(J13=0,0,L21/(J13+J15)) -> 2.9064904 | L21: =+SUM(START:END!L21) -> 604.55 | N21: =L21-F21 -> -10595.45 | P21: =IF(O13=0,0,Q21/(O13+O15)) -> 0 | Q21: =+SUM(START:END!Q21) -> 0 | R21: =O21-K21 -> -2.9064904 | S21: =L21-Q21 -> 604.55
A22: =+B22&C22 -> Véhicules neufsRev. Protections | B22: =+$K$1 -> Véhicules neufs | C22: Rev. Protections | D22: 0 | E22: =IF(D22=0,0,F22/D22) -> 0 | F22: =+SUM(START:END!F22) -> 208320 | G22: 0 | H22: =IF(G22=0,0,I22/G22) -> 0 | I22: =+SUM(START:END!I22) -> 0 | K22: =IF(J13=0,0,L22/(J13+J15)) -> 967.72736 | L22: =+SUM(START:END!L22) -> 201287.29 | N22: =L22-F22 -> -7032.71 | P22: =IF(O13=0,0,Q22/(O13+O15)) -> 865.45189 | Q22: =+SUM(START:END!Q22) -> 183475.8 | R22: =O22-K22 -> -967.72736 | S22: =L22-Q22 -> 17811.49
A23: =+B23&C23 -> Véhicules neufsRev. Autres | B23: =+$K$1 -> Véhicules neufs | C23: Rev. Autres | D23: 0 | E23: =IF(D23=0,0,F23/D23) -> 0 | F23: =+SUM(START:END!F23) -> 4480 | G23: 0 | H23: =IF(G23=0,0,I23/G23) -> 0 | I23: =+SUM(START:END!I23) -> 0 | K23: =IF(J13=0,0,L23/(J13+J15)) -> 0.89682692 | L23: =+SUM(START:END!L23) -> 186.54 | N23: =L23-F23 -> -4293.46 | P23: =IF(O13=0,0,Q23/(O13+O15)) -> 10.368208 | Q23: =+SUM(START:END!Q23) -> 2198.06 | R23: =O23-K23 -> -0.89682692 | S23: =L23-Q23 -> -2011.52
A24: =+B24&C24 -> Véhicules neufsTotal F&I | B24: =+$K$1 -> Véhicules neufs | C24: Total F&I | D24: =+D15+D13 -> 224 | E24: =IF(D24<=0,0,F24/D24) -> 1000 | F24: =F21+F22+F23 -> 224000 | G24: =+G15+G13 -> 0 | H24: =IF(G24<=0,0,I24/G24) -> 0 | I24: =I21+I22+I23 -> 0 | J24: =+J15+J13 -> 208 | K24: =IF(J24<=0,0,L24/J24) -> 971.53067 | L24: =L21+L22+L23 -> 202078.38 | M24: =+M15+M13 -> -16 | N24: =N21+N22+N23 -> -21921.62 | O24: =+O15+O13 -> 212 | P24: =IF(O24<=0,0,Q24/O24) -> 875.82009 | Q24: =Q21+Q22+Q23 -> 185673.86 | S24: =L24-Q24 -> 16404.52
A25: =+B25&C25 -> Véhicules neufs | B25: =+$K$1 -> Véhicules neufs | S25: =IF(Q24=0,0,(S24/Q24)) -> 0.088351263
A26: =+B26&C26 -> Véhicules neufs | B26: =+$K$1 -> Véhicules neufs
A27: =+B27&C27 -> Véhicules neufsTotal Dépt. Neufs | B27: =+$K$1 -> Véhicules neufs | C27: Total Dépt. Neufs | D27: =+D13+D15+D17 -> 230 | E27: =IF(D27<=0,0,F27/D27) -> 3347.4881 | F27: =F13+F17+F24+F19+F15 -> 769922.26 | G27: =+G13+G15+G17 -> 0 | H27: =IF(G27<=0,0,I27/G27) -> 0 | I27: =I13+I17+I24+I19+I15 -> 0 | J27: =+J13+J15+J17 -> 214 | K27: =IF(J27<=0,0,L27/J27) -> 3230.4141 | L27: =L13+L17+L24+L19+L15 -> 691308.61 | M27: =+M13+M15+M17 -> -16 | N27: =N13+N17+N24+N19+N15 -> -78613.653 | O27: =+O13+O15+O17 -> 219 | P27: =IF(O27<=0,0,Q27/O27) -> 3078.5026 | Q27: =Q13+Q17+Q24+Q19+Q15 -> 674192.06 | R27: =J27-O27 -> -5 | S27: =L27-Q27 -> 17116.55
A28: =+B28&C28 -> Véhicules neufs | B28: =+$K$1 -> Véhicules neufs | M28: =M27/D27 -> -0.069565217 | N28: =N27/F27 -> -0.10210596 | R28: =R27/O27 -> -0.02283105 | S28: =IF(Q27=0,0,S27/Q27) -> 0.02538824
A29: =+B29&C29 -> Véhicules neufs | B29: =+$K$1 -> Véhicules neufs
A30: =+B30&C30 -> Véhicules neufsDEPENSES | B30: =+$K$1 -> Véhicules neufs | C30: DEPENSES
A31: =+B31&C31 -> Véhicules neufsComm. vendeurs | B31: =+$K$1 -> Véhicules neufs | C31: Comm. vendeurs | E31: =F31/D$24 -> 739.41296 | F31: =+SUM(START:END!F31) -> 165628.5 | H31: =I31/G$24 -> #DIV/0! | I31: =+SUM(START:END!I31) -> 0 | J31: =L31/L13 -> 0.29719193 | K31: =IF(L31=0,0,L31/J$24) -> 630.83423 | L31: =+SUM(START:END!L31) -> 131213.52 | N31: =L31-F31 -> -34414.983 | P31: =IF(Q31=0,0,Q31/O$24) -> 713.76486 | Q31: =+SUM(START:END!Q31) -> 151318.15 | S31: =L31-Q31 -> -20104.63
A32: =+B32&C32 -> Véhicules neufsComm. F&I | B32: =+$K$1 -> Véhicules neufs | C32: Comm. F&I | E32: =F32/D$24 -> 280 | F32: =+SUM(START:END!F32) -> 62720 | H32: =I32/G$24 -> #DIV/0! | I32: =+SUM(START:END!I32) -> 0 | J32: =L32/L24 -> 0.4246913 | K32: =IF(L32=0,0,L32/J$24) -> 412.60062 | L32: =+SUM(START:END!L32) -> 85820.93 | N32: =L32-F32 -> 23100.93 | P32: =IF(Q32=0,0,Q32/O$24) -> 242.45613 | Q32: =+SUM(START:END!Q32) -> 51400.7 | S32: =L32-Q32 -> 34420.23
A33: =+B33&C33 -> Véhicules neufsFrais de livraison | B33: =+$K$1 -> Véhicules neufs | C33: Frais de livraison | E33: =F33/D$24 -> 115 | F33: =+SUM(START:END!F33) -> 25760 | H33: =I33/G$24 -> #DIV/0! | I33: =+SUM(START:END!I33) -> 0 | K33: =IF(L33=0,0,L33/J$24) -> 99.199423 | L33: =+SUM(START:END!L33) -> 20633.48 | N33: =L33-F33 -> -5126.52 | P33: =IF(Q33=0,0,Q33/O$24) -> 111.38486 | Q33: =+SUM(START:END!Q33) -> 23613.59 | S33: =L33-Q33 -> -2980.11
A34: =+B34&C34 -> Véhicules neufsService gratuit 1 | B34: =+$K$1 -> Véhicules neufs | C34: Service gratuit 1 | E34: =F34/D$24 -> 10 | F34: =+SUM(START:END!F34) -> 2240 | H34: =I34/G$24 -> #DIV/0! | I34: =+SUM(START:END!I34) -> 0 | K34: =IF(L34=0,0,L34/J$24) -> 0 | L34: =+SUM(START:END!L34) -> 0 | N34: =L34-F34 -> -2240 | P34: =IF(Q34=0,0,Q34/O$24) -> 29.79566 | Q34: =+SUM(START:END!Q34) -> 6316.68 | S34: =L34-Q34 -> -6316.68
A35: =+B35&C35 -> Véhicules neufsEntretien stock | B35: =+$K$1 -> Véhicules neufs | C35: Entretien stock | E35: =F35/D$24 -> 120.75 | F35: =+SUM(START:END!F35) -> 27048 | H35: =I35/G$24 -> #DIV/0! | I35: =+SUM(START:END!I35) -> 0 | K35: =IF(L35=0,0,L35/J$24) -> 91.710048 | L35: =+SUM(START:END!L35) -> 19075.69 | N35: =L35-F35 -> -7972.31 | P35: =IF(Q35=0,0,Q35/O$24) -> 94.111038 | Q35: =+SUM(START:END!Q35) -> 19951.54 | S35: =L35-Q35 -> -875.85
A36: =+B36&C36 -> Véhicules neufsPublicité 1 | B36: =+$K$1 -> Véhicules neufs | C36: Publicité 1 | E36: =F36/D$24 -> 53.508929 | F36: =+SUM(START:END!F36) -> 11986 | H36: =I36/G$24 -> #DIV/0! | I36: =+SUM(START:END!I36) -> 0 | K36: =IF(L36=0,0,L36/J$24) -> 84.837163 | L36: =+SUM(START:END!L36) -> 17646.13 | N36: =L36-F36 -> 5660.13 | P36: =IF(Q36=0,0,Q36/O$24) -> 56.937264 | Q36: =+SUM(START:END!Q36) -> 12070.7 | S36: =L36-Q36 -> 5575.43
A37: =+B37&C37 -> Véhicules neufsIntérêt de gros | B37: =+$K$1 -> Véhicules neufs | C37: Intérêt de gros | E37: =F37/D$24 -> 514.84383 | F37: =+SUM(START:END!F37) -> 115325.02 | H37: =I37/G$24 -> #DIV/0! | I37: =+SUM(START:END!I37) -> 0 | K37: =IF(L37=0,0,L37/J$24) -> 236.20462 | L37: =+SUM(START:END!L37) -> 49130.56 | N37: =L37-F37 -> -66194.458 | P37: =IF(Q37=0,0,Q37/O$24) -> 521.73509 | Q37: =+SUM(START:END!Q37) -> 110607.84 | S37: =L37-Q37 -> -61477.28
A38: =+B38&C38 -> Véhicules neufs[...] | B38: =+$K$1 -> Véhicules neufs | C38: [...] | E38: =F38/D$24 -> 0 | F38: =+SUM(START:END!F38) -> 0 | H38: =I38/G$24 -> #DIV/0! | I38: =+SUM(START:END!I38) -> 0 | K38: =IF(L38=0,0,L38/J$24) -> 0 | L38: =+SUM(START:END!L38) -> 0 | N38: =L38-I38 -> 0 | P38: =IF(Q38=0,0,Q38/O$24) -> 0 | Q38: =+SUM(START:END!Q38) -> 0 | S38: =L38-Q38 -> 0
A39: =+B39&C39 -> Véhicules neufs[...] | B39: =+$K$1 -> Véhicules neufs | C39: [...] | E39: =F39/D$24 -> 0 | F39: =+SUM(START:END!F39) -> 0 | H39: =I39/G$24 -> #DIV/0! | I39: =+SUM(START:END!I39) -> 0 | K39: =IF(L39=0,0,L39/J$24) -> 0 | L39: =+SUM(START:END!L39) -> 0 | N39: =L39-I39 -> 0 | P39: =IF(Q39=0,0,Q39/O$24) -> 0 | Q39: =+SUM(START:END!Q39) -> 0 | S39: =L39-Q39 -> 0
A40: =+B40&C40 -> Véhicules neufs[...] | B40: =+$K$1 -> Véhicules neufs | C40: [...] | E40: =F40/D$24 -> 0 | F40: =+SUM(START:END!F40) -> 0 | H40: =I40/G$24 -> #DIV/0! | I40: =+SUM(START:END!I40) -> 0 | K40: =IF(L40=0,0,L40/J$24) -> 0 | L40: =+SUM(START:END!L40) -> 0 | N40: =L40-I40 -> 0 | P40: =IF(Q40=0,0,Q40/O$24) -> 0 | Q40: =+SUM(START:END!Q40) -> 0 | S40: =L40-Q40 -> 0
A41: =+B41&C41 -> Véhicules neufsTOTAL VARIABLES | B41: =+$K$1 -> Véhicules neufs | C41: TOTAL VARIABLES | D41: % brut | E41: =F41/F$27 -> 0.53344025 | F41: =SUM(F31:F40) -> 410707.52 | G41: % brut | H41: =I41/I$27 -> #DIV/0! | I41: =SUM(I31:I40) -> 0 | J41: % brut | K41: =L41/L$27 -> 0.46798247 | L41: =SUM(L31:L40) -> 323520.31 | N41: =SUM(N31:N40) -> -87187.211 | O41: % brut | P41: =Q41/Q$27 -> 0.55663545 | Q41: =SUM(Q31:Q40) -> 375279.2 | S41: =L41-Q41 -> -51758.89
A42: =+B42&C42 -> Véhicules neufsSalaires cadres | B42: =+$K$1 -> Véhicules neufs | C42: Salaires cadres | F42: =+SUM(START:END!F42) -> 77393.513 | I42: =+SUM(START:END!I42) -> 0 | L42: =+SUM(START:END!L42) -> 53536.95 | N42: =L42-F42 -> -23856.563 | Q42: =+SUM(START:END!Q42) -> 47085.99
A43: =+B43&C43 -> Véhicules neufsSalaires commis | B43: =+$K$1 -> Véhicules neufs | C43: Salaires commis | F43: =+SUM(START:END!F43) -> 44976.212 | I43: =+SUM(START:END!I43) -> 0 | L43: =+SUM(START:END!L43) -> 46605.07 | N43: =L43-F43 -> 1628.858 | Q43: =+SUM(START:END!Q43) -> 29278.4 | S43: =L43-Q43 -> 17326.67
A44: =+B44&C44 -> Véhicules neufsSalaires autres | B44: =+$K$1 -> Véhicules neufs | C44: Salaires autres | F44: =+SUM(START:END!F44) -> 1025.55 | I44: =+SUM(START:END!I44) -> 0 | L44: =+SUM(START:END!L44) -> 1985.75 | N44: =L44-F44 -> 960.2 | Q44: =+SUM(START:END!Q44) -> 10858.62 | S44: =L44-Q44 -> -8872.87
A45: =+B45&C45 -> Véhicules neufsSalaires spécialistes | B45: =+$K$1 -> Véhicules neufs | C45: Salaires spécialistes | F45: =+SUM(START:END!F45) -> 0 | I45: =+SUM(START:END!I45) -> 0 | L45: =+SUM(START:END!L45) -> 0 | N45: =L45-F45 -> 0 | Q45: =+SUM(START:END!Q45) -> 0 | S45: =L45-Q45 -> 0
A46: =+B46&C46 -> Véhicules neufs[...] | B46: =+$K$1 -> Véhicules neufs | C46: [...] | F46: =+SUM(START:END!F46) -> 0 | I46: =+SUM(START:END!I46) -> 0 | L46: =+SUM(START:END!L46) -> 0 | N46: =L46-F46 -> 0 | Q46: =+SUM(START:END!Q46) -> 0 | S46: =L46-Q46 -> 0
A47: =+B47&C47 -> Véhicules neufs[...] | B47: =+$K$1 -> Véhicules neufs | C47: [...] | F47: =+SUM(START:END!F47) -> 0 | I47: =+SUM(START:END!I47) -> 0 | L47: =+SUM(START:END!L47) -> 0 | N47: =L47-F47 -> 0 | Q47: =+SUM(START:END!Q47) -> 0 | S47: =L47-Q47 -> 0
A48: =+B48&C48 -> Véhicules neufs[...] | B48: =+$K$1 -> Véhicules neufs | C48: [...] | F48: =+SUM(START:END!F48) -> 0 | I48: =+SUM(START:END!I48) -> 0 | L48: =+SUM(START:END!L48) -> 0 | N48: =L48-F48 -> 0 | Q48: =+SUM(START:END!Q48) -> 0 | S48: =L48-Q48 -> 0
A49: =+B49&C49 -> Véhicules neufsSalaires en absences | B49: =+$K$1 -> Véhicules neufs | C49: Salaires en absences | F49: =+SUM(START:END!F49) -> 37058.044 | I49: =+SUM(START:END!I49) -> 0 | L49: =+SUM(START:END!L49) -> 30191.68 | N49: =L49-F49 -> -6866.3643 | Q49: =+SUM(START:END!Q49) -> 33105.56 | S49: =L49-Q49 -> -2913.88
A50: =+B50&C50 -> Véhicules neufsDéduction à la source | B50: =+$K$1 -> Véhicules neufs | C50: Déduction à la source | F50: =+SUM(START:END!F50) -> 45057.358 | I50: =+SUM(START:END!I50) -> 0 | L50: =+SUM(START:END!L50) -> 42430.04 | N50: =L50-F50 -> -2627.3178 | Q50: =+SUM(START:END!Q50) -> 41492.8 | S50: =L50-Q50 -> 937.24
A51: =+B51&C51 -> Véhicules neufsBénéfices marginaux | B51: =+$K$1 -> Véhicules neufs | C51: Bénéfices marginaux | F51: =+SUM(START:END!F51) -> 23214.334 | I51: =+SUM(START:END!I51) -> 0 | L51: =+SUM(START:END!L51) -> 17716.94 | N51: =L51-F51 -> -5497.3944 | Q51: =+SUM(START:END!Q51) -> 22406.8 | S51: =L51-Q51 -> -4689.86
A52: =+B52&C52 -> Véhicules neufsCsst | B52: =+$K$1 -> Véhicules neufs | C52: Csst | F52: =+SUM(START:END!F52) -> 10121.58 | I52: =+SUM(START:END!I52) -> 0 | L52: =+SUM(START:END!L52) -> 8748.19 | N52: =L52-F52 -> -1373.3904 | Q52: =+SUM(START:END!Q52) -> 7733.97 | S52: =L52-Q52 -> 1014.22
A53: =+B53&C53 -> Véhicules neufs[...] | B53: =+$K$1 -> Véhicules neufs | C53: [...] | F53: =+SUM(START:END!F53) -> 0 | I53: =+SUM(START:END!I53) -> 0 | L53: =+SUM(START:END!L53) -> 0 | N53: =L53-I53 -> 0 | Q53: =+SUM(START:END!Q53) -> 0 | S53: =L53-Q53 -> 0
A54: =+B54&C54 -> Véhicules neufsTOTAL PERSONNEL | B54: =+$K$1 -> Véhicules neufs | C54: TOTAL PERSONNEL | D54: % brut | E54: =F54/F$27 -> 0.3102217 | F54: =+SUM(F42:F53) -> 238846.59 | G54: % brut | H54: =I54/I$27 -> #DIV/0! | I54: =+SUM(I42:I53) -> 0 | J54: % brut | K54: =L54/L$27 -> 0.29106338 | L54: =+SUM(L42:L53) -> 201214.62 | N54: =+SUM(N42:N53) -> -37631.971 | O54: % brut | P54: =Q54/Q$27 -> 0.28472916 | Q54: =+SUM(Q42:Q53) -> 191962.14 | S54: =+SUM(S42:S53) -> 2801.52
A55: =+B55&C55 -> Véhicules neufsPublicité 2 | B55: =+$K$1 -> Véhicules neufs | C55: Publicité 2 | F55: =+SUM(START:END!F55) -> 0 | I55: =+SUM(START:END!I55) -> 0 | L55: =+SUM(START:END!L55) -> 0 | N55: =L55-F55 -> 0 | Q55: =+SUM(START:END!Q55) -> 0 | S55: =L55-Q55 -> 0
A56: =+B56&C56 -> Véhicules neufsService gratuit 2 | B56: =+$K$1 -> Véhicules neufs | C56: Service gratuit 2 | F56: =+SUM(START:END!F56) -> 0 | I56: =+SUM(START:END!I56) -> 0 | L56: =+SUM(START:END!L56) -> 0 | N56: =L56-F56 -> 0 | Q56: =+SUM(START:END!Q56) -> 0 | S56: =L56-Q56 -> 0
A57: =+B57&C57 -> Véhicules neufsFrais véhicules de cie | B57: =+$K$1 -> Véhicules neufs | C57: Frais véhicules de cie | F57: =+SUM(START:END!F57) -> 26857.644 | I57: =+SUM(START:END!I57) -> 0 | L57: =+SUM(START:END!L57) -> 19079.44 | N57: =L57-F57 -> -7778.2038 | Q57: =+SUM(START:END!Q57) -> 28886.61 | S57: =L57-Q57 -> -9807.17
A58: =+B58&C58 -> Véhicules neufsInformatique | B58: =+$K$1 -> Véhicules neufs | C58: Informatique | F58: =+SUM(START:END!F58) -> 23882.984 | I58: =+SUM(START:END!I58) -> 0 | L58: =+SUM(START:END!L58) -> 23535.16 | N58: =L58-F58 -> -347.82428 | Q58: =+SUM(START:END!Q58) -> 23510.29 | S58: =L58-Q58 -> 24.87
A59: =+B59&C59 -> Véhicules neufsFrais de déplacement | B59: =+$K$1 -> Véhicules neufs | C59: Frais de déplacement | F59: =+SUM(START:END!F59) -> 3800.0925 | I59: =+SUM(START:END!I59) -> 0 | L59: =+SUM(START:END!L59) -> 4137.02 | N59: =L59-F59 -> 336.9275 | Q59: =+SUM(START:END!Q59) -> 4582.91 | S59: =L59-Q59 -> -445.89
A60: =+B60&C60 -> Véhicules neufsServices extérieurs | B60: =+$K$1 -> Véhicules neufs | C60: Services extérieurs | F60: =+SUM(START:END!F60) -> 21647.222 | I60: =+SUM(START:END!I60) -> 0 | L60: =+SUM(START:END!L60) -> 25168.73 | N60: =L60-F60 -> 3521.5078 | Q60: =+SUM(START:END!Q60) -> 23509.83 | S60: =L60-Q60 -> 1658.9
A61: =+B61&C61 -> Véhicules neufsFournitures autres | B61: =+$K$1 -> Véhicules neufs | C61: Fournitures autres | F61: =+SUM(START:END!F61) -> 291.772 | I61: =+SUM(START:END!I61) -> 0 | L61: =+SUM(START:END!L61) -> 51.3 | N61: =L61-F61 -> -240.472 | Q61: =+SUM(START:END!Q61) -> 313.71 | S61: =L61-Q61 -> -262.41
A62: =+B62&C62 -> Véhicules neufsUniformes | B62: =+$K$1 -> Véhicules neufs | C62: Uniformes | F62: =+SUM(START:END!F62) -> 85 | I62: =+SUM(START:END!I62) -> 0 | L62: =+SUM(START:END!L62) -> 0 | N62: =L62-F62 -> -85 | Q62: =+SUM(START:END!Q62) -> 0 | S62: =L62-Q62 -> 0
A63: =+B63&C63 -> Véhicules neufsPapeterie | B63: =+$K$1 -> Véhicules neufs | C63: Papeterie | F63: =+SUM(START:END!F63) -> 2224.2927 | I63: =+SUM(START:END!I63) -> 0 | L63: =+SUM(START:END!L63) -> 817.61 | N63: =L63-F63 -> -1406.6827 | Q63: =+SUM(START:END!Q63) -> 2359.94 | S63: =L63-Q63 -> -1542.33
A64: =+B64&C64 -> Véhicules neufsTéléphone | B64: =+$K$1 -> Véhicules neufs | C64: Téléphone | F64: =+SUM(START:END!F64) -> 1034.406 | I64: =+SUM(START:END!I64) -> 0 | L64: =+SUM(START:END!L64) -> 1091.77 | N64: =L64-F64 -> 57.364045 | Q64: =+SUM(START:END!Q64) -> 1117.62 | S64: =L64-Q64 -> -25.85
A65: =+B65&C65 -> Véhicules neufsFrais postaux | B65: =+$K$1 -> Véhicules neufs | C65: Frais postaux | F65: =+SUM(START:END!F65) -> 308.46719 | I65: =+SUM(START:END!I65) -> 0 | L65: =+SUM(START:END!L65) -> 210.94 | N65: =L65-F65 -> -97.527186 | Q65: =+SUM(START:END!Q65) -> 76.48 | S65: =L65-Q65 -> 134.46
A66: =+B66&C66 -> Véhicules neufsDivers | B66: =+$K$1 -> Véhicules neufs | C66: Divers | F66: =+SUM(START:END!F66) -> 603.51116 | I66: =+SUM(START:END!I66) -> 0 | L66: =+SUM(START:END!L66) -> 260.16 | N66: =L66-F66 -> -343.35116 | Q66: =+SUM(START:END!Q66) -> 392.97 | S66: =L66-Q66 -> -132.81
... A68: =+B68&C68 -> Véhicules neufsFrais bancaires | B68: =+$K$1 -> Véhicules neufs | C68: Frais bancaires | F68: =+SUM(START:END!F68) -> 10678.052 | I68: =+SUM(START:END!I68) -> 0 | L68: =+SUM(START:END!L68) -> 11935.27 | N68: =L68-F68 -> 1257.2183 | Q68: =+SUM(START:END!Q68) -> 10562.14 | S68: =L68-Q68 -> 1373.13
A69: =+B69&C69 -> Véhicules neufs[...] | B69: =+$K$1 -> Véhicules neufs | C69: [...] | F69: =+SUM(START:END!F69) -> 0 | I69: =+SUM(START:END!I69) -> 0 | L69: =+SUM(START:END!L69) -> 0 | N69: =L69-I69 -> 0 | Q69: =+SUM(START:END!Q69) -> 0 | S69: =L69-Q69 -> 0
A70: =+B70&C70 -> Véhicules neufs[...] | B70: =+$K$1 -> Véhicules neufs | C70: [...] | F70: =+SUM(START:END!F70) -> 0 | I70: =+SUM(START:END!I70) -> 0 | L70: =+SUM(START:END!L70) -> 0 | N70: =L70-I70 -> 0 | Q70: =+SUM(START:END!Q70) -> 0 | S70: =L70-Q70 -> 0
A71: =+B71&C71 -> Véhicules neufs[...] | B71: =+$K$1 -> Véhicules neufs | C71: [...] | F71: =+SUM(START:END!F71) -> 0 | I71: =+SUM(START:END!I71) -> 0 | L71: =+SUM(START:END!L71) -> 0 | N71: =L71-I71 -> 0 | Q71: =+SUM(START:END!Q71) -> 0 | S71: =L71-Q71 -> 0
A72: =+B72&C72 -> Véhicules neufsTOTAL SEMI-FIXES | B72: =+$K$1 -> Véhicules neufs | C72: TOTAL SEMI-FIXES | D72: % brut | E72: =F72/F$27 -> 0.12626932 | F72: =+SUM(F55:F71) -> 97217.562 | G72: % brut | H72: =I72/I$27 -> #DIV/0! | I72: =+SUM(I55:I71) -> 0 | J72: % brut | K72: =L72/L$27 -> 0.13256608 | L72: =+SUM(L55:L71) -> 91644.07 | N72: =+SUM(N55:N71) -> -5573.4922 | O72: % brut | P72: =Q72/Q$27 -> 0.15582073 | Q72: =+SUM(Q55:Q71) -> 105053.1 | S72: =+SUM(S55:S71) -> -13409.03
A73: =+B73&C73 -> Véhicules neufs | B73: =+$K$1 -> Véhicules neufs
A74: =+B74&C74 -> Véhicules neufsTOTAL DES DÉPENSES | B74: =+$K$1 -> Véhicules neufs | C74: TOTAL DES DÉPENSES | D74: % brut | E74: =F74/F$27 -> 0.96993126 | F74: =F41+F54+F72 -> 746771.67 | G74: % brut | H74: =I74/I$27 -> #DIV/0! | I74: =I41+I54+I72 -> 0 | J74: % brut | K74: =L74/L$27 -> 0.89161192 | L74: =L41+L54+L72 -> 616379 | N74: =N41+N54+N72 -> -130392.67 | O74: % brut | P74: =Q74/Q$27 -> 0.99718534 | Q74: =Q41+Q54+Q72 -> 672294.44 | S74: =L74-Q74 -> -55915.44
A75: =+B75&C75 -> Véhicules neufsProgramme neuf 1 | B75: =+$K$1 -> Véhicules neufs | C75: Programme neuf 1 | F75: =+SUM(START:END!F75) -> 25000 | I75: =+SUM(START:END!I75) -> 0 | L75: =+SUM(START:END!L75) -> 0 | N75: =L75-F75 -> -25000 | Q75: =+SUM(START:END!Q75) -> 34100
A76: =+B76&C76 -> Véhicules neufsProgramme neuf 2 | B76: =+$K$1 -> Véhicules neufs | C76: Programme neuf 2 | F76: =+SUM(START:END!F76) -> 0 | I76: =+SUM(START:END!I76) -> 0 | L76: =+SUM(START:END!L76) -> 0 | N76: =L76-F76 -> 0 | Q76: =+SUM(START:END!Q76) -> 0 | S76: =L76-Q76 -> 0
A77: =+B77&C77 -> Véhicules neufsProgramme neuf 3 | B77: =+$K$1 -> Véhicules neufs | C77: Programme neuf 3 | F77: =+SUM(START:END!F77) -> 0 | I77: =+SUM(START:END!I77) -> 0 | L77: =+SUM(START:END!L77) -> 0 | N77: =L77-F77 -> 0 | Q77: =+SUM(START:END!Q77) -> 0 | S77: =L77-Q77 -> 0
A78: =+B78&C78 -> Véhicules neufsHoldbacks | B78: =+$K$1 -> Véhicules neufs | C78: Holdbacks | F78: =+SUM(START:END!F78) -> 324169.15 | I78: =+SUM(START:END!I78) -> 0 | L78: =+SUM(START:END!L78) -> 247496.85 | N78: =L78-F78 -> -76672.298 | Q78: =+SUM(START:END!Q78) -> 290384 | S78: =L78-Q78 -> -42887.15
A79: =+B79&C79 -> Véhicules neufs[...] | B79: =+$K$1 -> Véhicules neufs | C79: [...] | F79: =+SUM(START:END!F79) -> 0 | I79: =+SUM(START:END!I79) -> 0 | L79: =+SUM(START:END!L79) -> 0 | N79: =L79-F79 -> 0 | Q79: =+SUM(START:END!Q79) -> 0 | S79: =L79-Q79 -> 0
A80: =+B80&C80 -> Véhicules neufs[...] | B80: =+$K$1 -> Véhicules neufs | C80: [...] | F80: =+SUM(START:END!F80) -> 0 | I80: =+SUM(START:END!I80) -> 0 | L80: =+SUM(START:END!L80) -> 0 | N80: =L80-F80 -> 0 | Q80: =+SUM(START:END!Q80) -> 0 | S80: =L80-Q80 -> 0
A81: =+B81&C81 -> Véhicules neufs[...] | B81: =+$K$1 -> Véhicules neufs | C81: [...] | F81: =+SUM(START:END!F81) -> 0 | I81: =+SUM(START:END!I81) -> 0 | L81: =+SUM(START:END!L81) -> 0 | N81: =L81-F81 -> 0 | Q81: =+SUM(START:END!Q81) -> 0 | S81: =L81-Q81 -> 0
A82: =+B82&C82 -> Véhicules neufsFrais administration | B82: =+$K$1 -> Véhicules neufs | C82: Frais administration | F82: =+SUM(START:END!F82) -> 106187.2 | I82: =+SUM(START:END!I82) -> 0 | L82: =+SUM(START:END!L82) -> 102132 | N82: =L82-F82 -> -4055.2 | Q82: =+SUM(START:END!Q82) -> 94873 | S82: =L82-Q82 -> 7259
A83: =+B83&C83 -> Véhicules neufsAUTRES REVENUS | B83: =+$K$1 -> Véhicules neufs | C83: AUTRES REVENUS | F83: =+SUM(F75:F82) -> 455356.35 | I83: =+SUM(I75:I82) -> 0 | L83: =+SUM(L75:L82) -> 349628.85 | N83: =+SUM(N75:N82) -> -105727.5 | Q83: =+SUM(Q75:Q82) -> 419357 | S83: =+SUM(S75:S82) -> -35628.15
A84: =+B84&C84 -> Véhicules neufs | B84: =+$K$1 -> Véhicules neufs
A85: =+B85&C85 -> Véhicules neufsPROFIT DÉPARTEMENTAL | B85: =+$K$1 -> Véhicules neufs | C85: PROFIT DÉPARTEMENTAL | F85: =F27-F74+F83 -> 478506.94 | I85: =I27-I74+I83 -> 0 | L85: =L27-L74+L83 -> 424558.46 | N85: =N27-N74+N83 -> -53948.477 | Q85: =Q27-Q74+Q83 -> 421254.62 | S85: =S27-S41-S54-S72+S83 -> 43854.8
F86: =+F85-#REF!-#REF!-#REF! -> #REF! | L86: =L85/F85 -> 0.88725665 | N86: =+N85-#REF!-#REF!-#REF! -> #REF! | Q86: =+Q85-#REF!-#REF!-#REF! -> #REF! | S86: =+S85-#REF!-#REF!-#REF! -> #REF!
C89: =C1 -> Conso | K89: Véhicules usagés | S89: =$S$1 -> Réalisé
D91: BUDGET ORIGINAL | G91: BUDGET RÉVISÉ | J91: RÉALISATION | M91: ÉCART réel / original | O91: ANNÉE PRÉCÉDENTE | R91: ÉCART réel / année précédente
D92: UNITE | E92: $P/UNITÉ | F92: $PROFITS | G92: UNITE | H92: $P/UNITÉ | I92: $PROFITS | J92: UNITE | K92: $P/UNITE | L92: $PROFITS | M92: UNITÉ | N92: $PROFITS | O92: UNITE | P92: $P/UNITE | Q92: $PROFITS | R92: UNITE | S92: $PROFITS
A93: =+B93&C93 -> Véhicules usagésVentes nettes | B93: Véhicules usagés | C93: Ventes nettes | F93: =+SUM(START:END!F93) -> 4435774.2 | I93: =+SUM(START:END!I93) -> 0 | L93: =+SUM(START:END!L93) -> 4498542.1 | Q93: =+SUM(START:END!Q93) -> 3677685.7
A94: =+B94&C94 -> Véhicules usagésCertifié | B94: Véhicules usagés | C94: Certifié | D94: =+SUM(START:END!D94) -> 68 | E94: =IF(D94=0,0,F94/D94) -> 1400 | F94: =+SUM(START:END!F94) -> 95200 | G94: =+SUM(START:END!G94) -> 0 | H94: =IF(G94=0,0,I94/G94) -> 0 | I94: =+SUM(START:END!I94) -> 0 | J94: =+SUM(START:END!J94) -> 77 | K94: =IF(J94=0,0,L94/J94) -> 1637.7436 | L94: =+SUM(START:END!L94) -> 126106.26 | M94: =J94-D94 -> 9 | N94: =L94-F94 -> 30906.26 | O94: =+SUM(START:END!O94) -> 71 | P94: =IF(O94=0,0,Q94/O94) -> 1311.7993 | Q94: =+SUM(START:END!Q94) -> 93137.75 | R94: =J94-O94 -> 6 | S94: =L94-Q94 -> 32968.51
A95: =+B95&C95 -> Véhicules usagésNon Certifié | B95: Véhicules usagés | C95: Non Certifié | D95: =+SUM(START:END!D95) -> 8 | E95: =IF(D95=0,0,F95/D95) -> 1800 | F95: =+SUM(START:END!F95) -> 14400 | G95: =+SUM(START:END!G95) -> 0 | H95: =IF(G95=0,0,I95/G95) -> 0 | I95: =+SUM(START:END!I95) -> 0 | J95: =+SUM(START:END!J95) -> 2 | K95: =IF(J95=0,0,L95/J95) -> 1000 | L95: =+SUM(START:END!L95) -> 2000 | M95: =J95-D95 -> -6 | N95: =L95-F95 -> -12400 | O95: =+SUM(START:END!O95) -> -2 | P95: =IF(O95=0,0,Q95/O95) -> 5514.01 | Q95: =+SUM(START:END!Q95) -> -11028.02 | R95: =J95-O95 -> 4 | S95: =L95-Q95 -> 13028.02
A96: =+B96&C96 -> Véhicules usagésAutres marques | B96: Véhicules usagés | C96: Autres marques | D96: =+SUM(START:END!D96) -> 12 | E96: =IF(D96=0,0,F96/D96) -> 1500 | F96: =+SUM(START:END!F96) -> 18000 | G96: =+SUM(START:END!G96) -> 0 | H96: =IF(G96=0,0,I96/G96) -> 0 | I96: =+SUM(START:END!I96) -> 0 | J96: =+SUM(START:END!J96) -> 0 | K96: =IF(J96=0,0,L96/J96) -> 0 | L96: =+SUM(START:END!L96) -> 0 | M96: =J96-D96 -> -12 | N96: =L96-F96 -> -18000 | O96: =+SUM(START:END!O96) -> 0 | P96: =IF(O96=0,0,Q96/O96) -> 0 | Q96: =+SUM(START:END!Q96) -> 24564.57 | R96: =J96-O96 -> 0 | S96: =L96-Q96 -> -24564.57
A97: =+B97&C97 -> Véhicules usagésTotal Usagés | B97: Véhicules usagés | C97: Total Usagés | D97: =+D95+D94+D96 -> 88 | E97: =IF(D97=0,0,F97/D97) -> 1450 | F97: =+F94+F95+F96 -> 127600 | G97: =+G95+G94+G96 -> 0 | H97: =IF(G97=0,0,I97/G97) -> 0 | I97: =+I94+I95+I96 -> 0 | J97: =+J95+J94+J96 -> 79 | K97: =IF(J97=0,0,L97/J97) -> 1621.5982 | L97: =+L94+L95+L96 -> 128106.26 | M97: =+M95+M94+M96 -> -9 | N97: =+N94+N95+N96 -> 506.26 | O97: =+O95+O94+O96 -> 69 | P97: =IF(O97<=0,0,Q97/O97) -> 1546.0043 | Q97: =+Q94+Q95+Q96 -> 106674.3 | R97: =R94+R95+R96 -> 10 | S97: =S94+S95+S96 -> 21431.96
A98: =+B98&C98 -> Véhicules usagés | B98: Véhicules usagés | E98: =IF(D98=0,0,F98/D98) -> 0 | H98: =IF(G98=0,0,I98/G98) -> 0 | M98: =D97/D97 -> 1 | N98: =N97/F97 -> 0.0039675549 | R98: =R97/O97 -> 0.14492754 | S98: =IF(Q97=0,0,(S97/Q97)) -> 0.20091025
A99: =+B99&C99 -> Véhicules usagésUS | B99: Véhicules usagés | C99: US | D99: =+SUM(START:END!D99) -> 0 | E99: =IF(D99=0,0,F99/D99) -> 0 | F99: =+SUM(START:END!F99) -> 0 | G99: =+SUM(START:END!G99) -> 0 | H99: =IF(G99=0,0,I99/G99) -> 0 | I99: =+SUM(START:END!I99) -> 0 | J99: =+SUM(START:END!J99) -> 0 | K99: =IF(J99=0,0,L99/J99) -> 0 | L99: =+SUM(START:END!L99) -> 0 | M99: =J99-D99 -> 0 | N99: =L99-F99 -> 0 | O99: =+SUM(START:END!O99) -> 0 | P99: =IF(O99=0,0,Q99/O99) -> 0 | Q99: =+SUM(START:END!Q99) -> 0
A100: =+B100&C100 -> Véhicules usagésVentes au Gros | B100: Véhicules usagés | C100: Ventes au Gros | D100: =+SUM(START:END!D100) -> 97 | E100: =IF(D100=0,0,F100/D100) -> 400 | F100: =+SUM(START:END!F100) -> 38800 | G100: =+SUM(START:END!G100) -> 0 | H100: =IF(G100=0,0,I100/G100) -> 0 | I100: =+SUM(START:END!I100) -> 0 | J100: =+SUM(START:END!J100) -> 124 | K100: =IF(J100=0,0,L100/J100) -> 395.24968 | L100: =+SUM(START:END!L100) -> 49010.96 | M100: =J100-D100 -> 27 | N100: =L100-F100 -> 10210.96 | O100: =+SUM(START:END!O100) -> 111 | P100: =IF(O100=0,0,Q100/O100) -> 25.426126 | Q100: =+SUM(START:END!Q100) -> 2822.3 | R100: =J100-O100 -> 13 | S100: =L100-Q100 -> 46188.66
A101: =+B101&C101 -> Véhicules usagés | B101: Véhicules usagés
A102: =+B102&C102 -> Véhicules usagésRev. Finances | B102: Véhicules usagés | C102: Rev. Finances | D102: =+SUM(START:END!D102) -> 0 | E102: =IF(D102=0,0,F102/D102) -> 0 | F102: =+SUM(START:END!F102) -> 52800 | G102: =+SUM(START:END!G102) -> 0 | H102: =IF(G102=0,0,I102/G102) -> 0 | I102: =+SUM(START:END!I102) -> 0 | J102: =+SUM(START:END!J102) -> 0 | K102: =IF(J102=0,0,L102/J102) -> 0 | L102: =+SUM(START:END!L102) -> 39052.82 | M102: =J102-G102 -> 0 | N102: =L102-F102 -> -13747.18 | O102: =+SUM(START:END!O102) -> 0 | P102: =IF(O102=0,0,Q102/O102) -> 0 | Q102: =+SUM(START:END!Q102) -> 22826.69 | R102: =J102-O102 -> 0 | S102: =L102-Q102 -> 16226.13
A103: =+B103&C103 -> Véhicules usagésRev. Protections | B103: Véhicules usagés | C103: Rev. Protections | D103: =+SUM(START:END!D103) -> 0 | E103: =IF(D103=0,0,F103/D103) -> 0 | F103: =+SUM(START:END!F103) -> 110000 | G103: =+SUM(START:END!G103) -> 0 | H103: =IF(G103=0,0,I103/G103) -> 0 | I103: =+SUM(START:END!I103) -> 0 | J103: =+SUM(START:END!J103) -> 0 | K103: =IF(J103=0,0,L103/J103) -> 0 | L103: =+SUM(START:END!L103) -> 150885.37 | M103: =J103-G103 -> 0 | N103: =L103-F103 -> 40885.37 | O103: =+SUM(START:END!O103) -> 0 | P103: =IF(O103=0,0,Q103/O103) -> 0 | Q103: =+SUM(START:END!Q103) -> 116795.14 | R103: =J103-O103 -> 0 | S103: =L103-Q103 -> 34090.23
A104: =+B104&C104 -> Véhicules usagésRev. Autres | B104: Véhicules usagés | C104: Rev. Autres | D104: =+SUM(START:END!D104) -> 0 | E104: =IF(D104=0,0,F104/D104) -> 0 | F104: =+SUM(START:END!F104) -> 4400 | G104: =+SUM(START:END!G104) -> 0 | H104: =IF(G104=0,0,I104/G104) -> 0 | I104: =+SUM(START:END!I104) -> 0 | J104: =+SUM(START:END!J104) -> 0 | K104: =IF(J104=0,0,L104/J104) -> 0 | L104: =+SUM(START:END!L104) -> 3108.44 | M104: =J104-G104 -> 0 | N104: =L104-F104 -> -1291.56 | O104: =+SUM(START:END!O104) -> 0 | P104: =IF(O104=0,0,Q104/O104) -> 0 | Q104: =+SUM(START:END!Q104) -> 5598.07 | R104: =J104-O104 -> 0 | S104: =L104-Q104 -> -2489.63
...

Sheet START

Sheet Juillet 2025
C1: Volks | K1: Véhicules neufs | S1: Réalisé, Juillet 2025
D2: X | E2: O | F2: U | J2: NB | L2: $ | O2: X | P2: O | Q2: U | V2: *** NE PAS EFFACER / Pour An Précédente ***
D3: BUDGET ORIGINAL | J3: RÉALISATION | M3: ÉCART réel / Budget | O3: ANNÉE PRÉCÉDENTE | R3: ECART (réel/ Ann.Préc.) | V3: NEUF | W3: 0.45
D4: UNITE | E4: $P/UNITÉ | F4: $PROFITS | J4: UNITÉS | K4: $P/UNITE | L4: $PROFITS | M4: UNITÉS | N4: $PROFITS | O4: UNITE | P4: $P/UNITÉ | Q4: $PROFITS | R4: UNITÉS | S4: $PROFITS | V4: USAGE | W4: 0.1
A5: Véhicules neufsVentes nettes | B5: Véhicules neufs | C5: Ventes nettes | F5: 3782098.2 | L5: 4089468.3 | Q5: 4524162.1 | V5: SERVICE | W5: 0.225
A6: Véhicules neufsAutos détail | B6: Véhicules neufs | C6: Autos détail | D6: 19 | E6: 1953.6492 | F6: 37119.334 | J6: 13 | K6: 1905.2108 | L6: 24767.74 | M6: -6 | N6: -12351.594 | O6: 23 | P6: 1942.4757 | Q6: 44676.94 | R6: -10 | S6: -19909.2 | V6: CARROSSERIE | W6: 0.025
A7: Véhicules neufsCamions détail | B7: Véhicules neufs | C7: Camions détail | D7: 50 | E7: 2435.9047 | F7: 121795.23 | J7: 63 | K7: 2276.0851 | L7: 143393.36 | M7: 13 | N7: 21598.126 | O7: 54 | P7: 2267.4683 | Q7: 122443.29 | R7: 9 | S7: 20950.07 | V7: PIECES | W7: 0.2
A8: Véhicules neufsSprinter | B8: Véhicules neufs | C8: Sprinter | D8: 0 | E8: 0 | F8: 0 | J8: 0 | K8: 0 | L8: 0 | M8: 0 | N8: 0 | O8: 0 | P8: 0 | Q8: 0 | R8: 0 | S8: 0 | W8: 1
A9: Véhicules neufsMoto détail | B9: Véhicules neufs | C9: Moto détail | D9: 0 | E9: 0 | F9: 0 | J9: 0 | K9: 0 | L9: 0 | M9: 0 | N9: 0 | O9: 0 | P9: 0 | Q9: 0 | R9: 0 | S9: 0
A10: Véhicules neufs[...] | B10: Véhicules neufs | C10: [...] | D10: 0 | E10: 0 | F10: 0 | J10: 0 | K10: 0 | L10: 0 | M10: 0 | N10: 0 | O10: 0 | P10: 0 | Q10: 0 | R10: 0 | S10: 0
A11: Véhicules neufs[...] | B11: Véhicules neufs | C11: [...] | D11: 0 | E11: 0 | F11: 0 | J11: 0 | K11: 0 | L11: 0 | M11: 0 | N11: 0 | O11: 0 | P11: 0 | Q11: 0 | R11: 0 | S11: 0
A12: Véhicules neufs[...] | B12: Véhicules neufs | C12: [...] | D12: 0 | E12: 0 | F12: 0 | J12: 0 | K12: 0 | L12: 0 | M12: 0 | N12: 0 | O12: 0 | P12: 0 | Q12: 0 | R12: 0 | S12: 0
A13: Véhicules neufsTotal Neufs | B13: Véhicules neufs | C13: Total Neufs | D13: 69 | E13: 2303.1097 | F13: 158914.57 | J13: 76 | K13: 2212.6461 | L13: 168161.1 | M13: 7 | N13: 9246.5319 | O13: 77 | P13: 2170.3926 | Q13: 167120.23 | R13: -1 | S13: 1040.87
A14: Véhicules neufs | B14: Véhicules neufs | M14: 0.10144928 | N14: 0.058185552 | R14: -0.012987013 | S14: 0.0062282705 | AD14: 20 | AE14: 1000 | AF14: 20000
A15: Véhicules neufsEx-Démos et courtoisies | B15: Véhicules neufs | C15: Ex-Démos et courtoisies | D15: 4 | E15: 1534.7521 | F15: 6139.0086 | J15: 5 | K15: 1374.508 | L15: 6872.54 | M15: 1 | N15: 733.53143 | O15: 3 | P15: 913.29 | Q15: 2739.87 | R15: 2 | S15: 4132.67 | AD15: 25 | AE15: 800 | AF15: 20000
A16: Véhicules neufs | B16: Véhicules neufs
A17: Véhicules neufsFlottes | B17: Véhicules neufs | C17: Flottes | D17: 2 | E17: 2393.8521 | F17: 4787.7042 | J17: 0 | K17: 0 | L17: 0 | M17: -2 | N17: -4787.7042 | O17: 5 | P17: 2550.916 | Q17: 12754.58 | R17: -5 | S17: -12754.58
A18: Véhicules neufs | B18: Véhicules neufs
A19: Véhicules neufsRachat bail | B19: Véhicules neufs | C19: Rachat bail | D19: 0 | E19: 0 | F19: 7650 | L19: 12602.35 | N19: 4952.35 | Q19: 10000 | R19: 0 | S19: 2602.35
A20: Véhicules neufs | B20: Véhicules neufs
A21: Véhicules neufsRev. Finances | B21: Véhicules neufs | C21: Rev. Finances | D21: 0 | E21: 0 | F21: 3650 | K21: 7.4635802 | L21: 604.55 | N21: -3045.45 | Q21: 0 | R21: -7.4635802 | S21: 604.55
A22: Véhicules neufsRev. Protections | B22: Véhicules neufs | C22: Rev. Protections | D22: 0 | E22: 0 | F22: 67890 | K22: 985.36333 | L22: 79814.43 | N22: 11924.43 | Q22: 60986.88 | R22: -985.36333 | S22: 18827.55
A23: Véhicules neufsRev. Autres | B23: Véhicules neufs | C23: Rev. Autres | D23: 0 | E23: 0 | F23: 1460 | K23: 2.302963 | L23: 186.54 | N23: -1273.46 | Q23: 569.82 | R23: -2.302963 | S23: -383.28
A24: Véhicules neufsTotal F&I | B24: Véhicules neufs | C24: Total F&I | D24: 73 | E24: 1000 | F24: 73000 | J24: 81 | K24: 995.12988 | L24: 80605.52 | M24: 8 | N24: 7605.52 | O24: 80 | P24: 769.45875 | Q24: 61556.7 | S24: 19048.82
A25: Véhicules neufs | B25: Véhicules neufs | N25: 0.10418521 | S25: 0.30945161
A26: Véhicules neufs | B26: Véhicules neufs
A27: Véhicules neufsTotal Dépt. Neufs | B27: Véhicules neufs | C27: Total Dépt. Neufs | D27: 75 | E27: 3339.8837 | F27: 250491.28 | J27: 81 | K27: 3311.6236 | L27: 268241.51 | M27: 6 | N27: 17750.229 | O27: 85 | P27: 2990.2515 | Q27: 254171.38 | R27: -4 | S27: 14070.13
A28: Véhicules neufs | B28: Véhicules neufs | L28: 1.0708617 | M28: 0.08 | N28: 0.070861665 | R28: -0.047058824 | S28: 0.055356862
A29: Véhicules neufs | B29: Véhicules neufs
A30: Véhicules neufsDEPENSES | B30: Véhicules neufs | C30: DEPENSES
A31: Véhicules neufsComm. vendeurs | B31: Véhicules neufs | C31: Comm. vendeurs | D31: 0.32512204 | E31: 735.1035 | F31: 53662.555 | J31: 0.29871778 | K31: 645.50198 | L31: 52285.66 | N31: -1376.8954 | O31: 0.31203959 | P31: 712.28763 | Q31: 56983.01 | S31: -4697.35
A32: Véhicules neufsComm. F&I | B32: Véhicules neufs | C32: Comm. F&I | D32: 0.28 | E32: 280 | F32: 20440 | J32: 0.25000198 | K32: 248.78444 | L32: 20151.54 | N32: -288.46 | O32: 0.26999709 | P32: 207.75163 | Q32: 16620.13 | S32: 3531.41
A33: Véhicules neufsFrais de livraison | B33: Véhicules neufs | C33: Frais de livraison | E33: 115 | F33: 8395 | K33: 112.60815 | L33: 9121.26 | N33: 726.26 | P33: 95.093 | Q33: 7607.44 | S33: 1513.82
A34: Véhicules neufsService gratuit 1 | B34: Véhicules neufs | C34: Service gratuit 1 | E34: 10 | F34: 730 | K34: 0 | L34: 0 | N34: -730 | P34: 33.065625 | Q34: 2645.25 | S34: -2645.25
A35: Véhicules neufsEntretien stock | B35: Véhicules neufs | C35: Entretien stock | E35: 120.75 | F35: 8814.75 | K35: 43.995185 | L35: 3563.61 | N35: -5251.14 | P35: 79.675375 | Q35: 6374.03 | S35: -2810.42
A36: Véhicules neufsPublicité 1 | B36: Véhicules neufs | C36: Publicité 1 | E36: 57.013699 | F36: 4162 | K36: 45.389259 | L36: 3676.53 | N36: -485.47 | P36: 39.7595 | Q36: 3180.76 | S36: 495.77
A37: Véhicules neufsIntérêt de gros | B37: Véhicules neufs | C37: Intérêt de gros | E37: 560.02013 | F37: 40881.469 | K37: 273.39222 | L37: 22144.77 | N37: -18736.699 | P37: 565.70337 | Q37: 45256.27 | S37: -23111.5
A38: Véhicules neufs[...] | B38: Véhicules neufs | C38: [...] | E38: 0 | F38: 0 | K38: 0 | L38: 0 | N38: 0 | P38: 0 | Q38: 0 | S38: 0
A39: Véhicules neufs[...] | B39: Véhicules neufs | C39: [...] | E39: 0 | F39: 0 | K39: 0 | L39: 0 | N39: 0 | P39: 0 | Q39: 0 | S39: 0
A40: Véhicules neufs[...] | B40: Véhicules neufs | C40: [...] | E40: 0 | F40: 0 | K40: 0 | L40: 0 | N40: 0 | P40: 0 | Q40: 0 | S40: 0
A41: Véhicules neufsTOTAL VARIABLES | B41: Véhicules neufs | C41: TOTAL VARIABLES | D41: % brut | E41: 0.54726765 | F41: 137085.77 | J41: % brut | K41: 0.41359508 | L41: 110943.37 | N41: -26142.405 | O41: % brut | P41: 0.54556453 | Q41: 138666.89 | S41: -27723.52
A42: Véhicules neufsSalaires cadres | B42: Véhicules neufs | C42: Salaires cadres | F42: 24486.465 | L42: 21170.97 | N42: -3315.4954 | P42: 0.062411748 | Q42: 15863.28 | S42: 5307.69
A43: Véhicules neufsSalaires commis | B43: Véhicules neufs | C43: Salaires commis | F43: 13904.219 | L43: 11846.53 | N43: -2057.6891 | Q43: 8318.46 | S43: 3528.07
A44: Véhicules neufsSalaires autres | B44: Véhicules neufs | C44: Salaires autres | F44: 315.55385 | L44: 1963.25 | N44: 1647.6962 | Q44: 2420.59 | S44: -457.34
A45: Véhicules neufsSalaires spécialistes | B45: Véhicules neufs | C45: Salaires spécialistes | F45: 0 | L45: 0 | N45: 0 | Q45: 0 | S45: 0
A46: Véhicules neufs[...] | B46: Véhicules neufs | C46: [...] | F46: 0 | L46: 0 | N46: 0 | Q46: 0 | S46: 0
A47: Véhicules neufs[...] | B47: Véhicules neufs | C47: [...] | F47: 0 | L47: 0 | N47: 0 | Q47: 0 | S47: 0
A48: Véhicules neufs[...] | B48: Véhicules neufs | C48: [...] | F48: 0 | L48: 0 | N48: 0 | Q48: 0 | S48: 0
A49: Véhicules neufsSalaires en absences | B49: Véhicules neufs | C49: Salaires en absences | F49: 11796.071 | L49: 10866.84 | N49: -929.23067 | Q49: 10664.1 | S49: 202.74
A50: Véhicules neufsDéduction à la source | B50: Véhicules neufs | C50: Déduction à la source | F50: 14342.359 | L50: 13752.02 | N50: -590.33905 | Q50: 12553.25 | S50: 1198.77
A51: Véhicules neufsBénéfices marginaux | B51: Véhicules neufs | C51: Bénéfices marginaux | F51: 7389.4328 | L51: 7178.18 | N51: -211.25282 | Q51: 7041.73 | S51: 136.45
A52: Véhicules neufsCsst | B52: Véhicules neufs | C52: Csst | F52: 3221.8343 | L52: 3241.11 | N52: 19.27572 | Q52: 1892.71 | S52: 1348.4
A53: Véhicules neufs[...] | B53: Véhicules neufs | C53: [...] | D53: #N/A | F53: 0 | L53: 0 | N53: 0 | Q53: 0 | S53: 0
A54: Véhicules neufsTOTAL PERSONNEL | B54: Véhicules neufs | C54: TOTAL PERSONNEL | D54: % brut | E54: 0.30123178 | F54: 75455.935 | J54: % brut | K54: 0.26102932 | L54: 70018.9 | N54: -5437.0351 | O54: % brut | P54: 0.23115946 | Q54: 58754.12 | S54: 11264.78
A55: Véhicules neufsPublicité 2 | B55: Véhicules neufs | C55: Publicité 2 | F55: 0 | L55: 0 | N55: 0 | Q55: 0 | S55: 0
A56: Véhicules neufsService gratuit 2 | B56: Véhicules neufs | C56: Service gratuit 2 | F56: 0 | L56: 0 | N56: 0 | Q56: 0 | S56: 0
A57: Véhicules neufsFrais véhicules de cie | B57: Véhicules neufs | C57: Frais véhicules de cie | F57: 8952.5479 | L57: 7490.62 | N57: -1461.9279 | Q57: 9199.43 | S57: -1708.81
A58: Véhicules neufsInformatique | B58: Véhicules neufs | C58: Informatique | F58: 7960.9948 | L58: 7652.37 | N58: -308.62476 | Q58: 5972.42 | S58: 1679.95
A59: Véhicules neufsFrais de déplacement | B59: Véhicules neufs | C59: Frais de déplacement | F59: 1266.6975 | L59: 1293.58 | N59: 26.882499 | Q59: 1613.78 | S59: -320.2
A60: Véhicules neufsServices extérieurs | B60: Véhicules neufs | C60: Services extérieurs | F60: 7215.7407 | L60: 8436.09 | N60: 1220.3493 | Q60: 7694.41 | S60: 741.68
A61: Véhicules neufsFournitures autres | B61: Véhicules neufs | C61: Fournitures autres | F61: 97.257333 | L61: 0 | N61: -97.257333 | Q61: 97.12 | S61: -97.12
A62: Véhicules neufsUniformes | B62: Véhicules neufs | C62: Uniformes | F62: 28.333333 | L62: 0 | N62: -28.333333 | Q62: 0 | S62: 0
A63: Véhicules neufsPapeterie | B63: Véhicules neufs | C63: Papeterie | F63: 741.43089 | L63: 218.53 | N63: -522.90089 | Q63: 356.55 | S63: -138.02
A64: Véhicules neufsTéléphone | B64: Véhicules neufs | C64: Téléphone | F64: 344.80198 | L64: 355.13 | N64: 10.328015 | Q64: 330.97 | S64: 24.16
A65: Véhicules neufsFrais postaux | B65: Véhicules neufs | C65: Frais postaux | F65: 102.8224 | L65: 54.6 | N65: -48.222395 | Q65: 32.96 | S65: 21.64
A66: Véhicules neufsDivers | B66: Véhicules neufs | C66: Divers | F66: 201.17039 | L66: 62.72 | N66: -138.45039 | Q66: 188.48 | S66: -125.76
... A68: Véhicules neufsFrais bancaires | B68: Véhicules neufs | C68: Frais bancaires | F68: 3605.8794 | L68: 3902.37 | N68: 296.49063 | Q68: 3718.78 | S68: 183.59
A69: Véhicules neufs[...] | B69: Véhicules neufs | C69: [...] | F69: 0 | N69: 0 | Q69: 0 | S69: 0
A70: Véhicules neufs[...] | B70: Véhicules neufs | C70: [...] | F70: 0 | L70: 0 | N70: 0 | Q70: 0 | S70: 0
A71: Véhicules neufs[...] | B71: Véhicules neufs | C71: [...] | F71: 0 | L71: 0 | N71: 0 | Q71: 0 | S71: 0
A72: Véhicules neufsTOTAL SEMI-FIXES | B72: Véhicules neufs | C72: TOTAL SEMI-FIXES | D72: % brut | E72: 0.12955494 | F72: 32452.383 | J72: % brut | K72: 0.11927341 | L72: 31994.08 | N72: -458.30287 | O72: % brut | P72: 0.12862569 | Q72: 32692.97 | S72: -698.89
A73: Véhicules neufs | B73: Véhicules neufs
A74: Véhicules neufsTOTAL DES DÉPENSES | B74: Véhicules neufs | C74: TOTAL DES DÉPENSES | D74: % brut | E74: 0.97805437 | F74: 244994.09 | J74: % brut | K74: 0.79389782 | L74: 212956.35 | N74: -32037.743 | O74: % brut | P74: 0.90534969 | Q74: 230113.98 | S74: -17157.63
A75: Véhicules neufsProgramme neuf 1 | B75: Véhicules neufs | C75: Programme neuf 1 | F75: 0 | L75: 0 | N75: 0 | Q75: 18100
A76: Véhicules neufsProgramme neuf 2 | B76: Véhicules neufs | C76: Programme neuf 2 | F76: 0 | L76: 0 | N76: 0 | Q76: 0 | S76: 0
A77: Véhicules neufsProgramme neuf 3 | B77: Véhicules neufs | C77: Programme neuf 3 | F77: 0 | L77: 0 | N77: 0 | Q77: 0 | S77: 0
A78: Véhicules neufsHoldbacks | B78: Véhicules neufs | C78: Holdbacks | E78: 1407.2459 | F78: 105543.44 | J78: 0.83190993 | K78: 1170.7019 | L78: 94826.85 | N78: -10716.594 | Q78: 127510 | S78: -32683.15
A79: Véhicules neufs[...] | B79: Véhicules neufs | C79: [...] | F79: 0 | L79: 0 | N79: 0 | Q79: 0 | S79: 0
A80: Véhicules neufs[...] | B80: Véhicules neufs | C80: [...] | F80: 0 | L80: 0 | N80: 0 | Q80: 0 | S80: 0
A81: Véhicules neufs[...] | B81: Véhicules neufs | C81: [...] | F81: 0 | L81: 0 | N81: 0 | Q81: 0 | S81: 0
A82: Véhicules neufsFrais administration | B82: Véhicules neufs | C82: Frais administration | D82: 0.95 | E82: 474.05 | F82: 34605.65 | J82: 1.0326614 | K82: 489.48148 | L82: 39648 | N82: 5042.35 | Q82: 35590 | S82: 4058
A83: Véhicules neufsAUTRES REVENUS | B83: Véhicules neufs | C83: AUTRES REVENUS | F83: 140149.09 | L83: 134474.85 | N83: -5674.2436 | Q83: 181200 | S83: -28625.15
A84: Véhicules neufs | B84: Véhicules neufs
A85: Véhicules neufsPROFIT DÉPARTEMENTAL | B85: Véhicules neufs | C85: PROFIT DÉPARTEMENTAL | F85: 145646.28 | L85: 189760.01 | N85: 44113.728 | P85: 0.045369153 | Q85: 205257.4 | S85: 2602.61
C89: Volks | K89: Véhicules usagés | S89: Réalisé, Juillet 2025
D91: BUDGET ORIGINAL | J91: RÉALISATION | M91: ÉCART réel / Budget | O91: ANNÉE PRÉCÉDENTE | R91: ECART (réel/ Ann.Préc.)
D92: UNITE | E92: $P/UNITÉ | F92: $PROFITS | J92: UNITÉS | K92: $P/UNITE | L92: $PROFITS | M92: UNITÉS | N92: $PROFITS | O92: UNITE | P92: $P/UNITÉ | Q92: $PROFITS | R92: UNITÉS | S92: $PROFITS
A93: Véhicules usagésVentes nettes | B93: Véhicules usagés | C93: Ventes nettes | F93: 1699373.1 | L93: 1735831.8 | Q93: 1416483.6
A94: Véhicules usagésCertifié | B94: Véhicules usagés | C94: Certifié | D94: 26 | E94: 1400 | F94: 36400 | J94: 28 | K94: 1004.9229 | L94: 28137.84 | M94: 2 | N94: -8262.16 | O94: 25 | P94: 1627.8944 | Q94: 40697.36 | R94: 3 | S94: -12559.52
A95: Véhicules usagésNon Certifié | B95: Véhicules usagés | C95: Non Certifié | D95: 3 | E95: 1800 | F95: 5400 | J95: 0 | K95: 0 | L95: 0 | M95: -3 | N95: -5400 | O95: 5 | P95: 1346.904 | Q95: 6734.52 | R95: -5 | S95: -6734.52
A96: Véhicules usagésAutres Marques | B96: Véhicules usagés | C96: Autres Marques | D96: 5 | E96: 1500 | F96: 7500 | J96: 0 | K96: 0 | L96: 0 | M96: -5 | N96: -7500 | O96: 0 | P96: 0 | Q96: 0 | R96: 0 | S96: 0
A97: Véhicules usagésTotal Usagés | B97: Véhicules usagés | C97: Total Usagés | D97: 34 | E97: 1450 | F97: 49300 | J97: 28 | K97: 1004.9229 | L97: 28137.84 | M97: -6 | N97: -21162.16 | O97: 30 | P97: 1581.0627 | Q97: 47431.88 | R97: -2 | S97: -19294.04
A98: Véhicules usagés | B98: Véhicules usagés | E98: 0 | M98: -0.17647059 | N98: -0.42925274 | P98: 0 | R98: -0.066666667 | S98: -0.40677367
A99: Véhicules usagés | B99: Véhicules usagés | D99: 0 | E99: 0 | F99: 0
A100: Véhicules usagésVentes au Gros | B100: Véhicules usagés | C100: Ventes au Gros | D100: 37 | E100: 400 | F100: 14800 | J100: 51 | K100: 737.09647 | L100: 37591.92 | M100: 14 | N100: 22791.92 | O100: 37 | P100: -125.19595 | Q100: -4632.25 | R100: 14 | S100: 42224.17
A101: Véhicules usagés | B101: Véhicules usagés
A102: Véhicules usagésRev. Finances | B102: Véhicules usagés | C102: Rev. Finances | D102: 0 | E102: 0 | F102: 20400 | K102: 450.17429 | L102: 12604.88 | N102: -7795.12 | Q102: 8266.65 | R102: -450.17429 | S102: 4338.23
A103: Véhicules usagésRev. Protections | B103: Véhicules usagés | C103: Rev. Protections | D103: 0 | E103: 0 | F103: 42500 | K103: 1933.1911 | L103: 54129.35 | N103: 11629.35 | Q103: 46940.15 | R103: -1933.1911 | S103: 7189.2
A104: Véhicules usagésRev. Autres | B104: Véhicules usagés | C104: Rev. Autres | D104: 0 | E104: 0 | F104: 1700 | K104: 28.672143 | L104: 802.82 | N104: -897.18 | Q104: 2036.84 | R104: -28.672143 | S104: -1234.02
A105: Véhicules usagésTotal F&I | B105: Véhicules usagés | C105: Total F&I | D105: 34 | E105: 1900 | F105: 64600 | J105: 28 | K105: 2412.0375 | L105: 67537.05 | M105: -6 | N105: 2937.05 | O105: 30 | P105: 1908.1213 | Q105: 57243.64 | S105: 10293.41
...

Sheet Aout 2025
C1: Volks | K1: Véhicules neufs | S1: Réalisé, Août 2025
D2: X | E2: O | F2: U | J2: NB | L2: $ | O2: X | P2: O | Q2: U | V2: *** NE PAS EFFACER / Pour An Précédente ***
D3: BUDGET ORIGINAL | J3: RÉALISATION | M3: ÉCART réel / Budget | O3: ANNÉE PRÉCÉDENTE | R3: ECART (réel/ Ann.Préc.) | V3: NEUF | W3: 0.45
D4: UNITE | E4: $P/UNITÉ | F4: $PROFITS | J4: UNITÉS | K4: $P/UNITE | L4: $PROFITS | M4: UNITÉS | N4: $PROFITS | O4: UNITE | P4: $P/UNITÉ | Q4: $PROFITS | R4: UNITÉS | S4: $PROFITS | V4: USAGE | W4: 0.1
A5: Véhicules neufsVentes nettes | B5: Véhicules neufs | C5: Ventes nettes | F5: 4621342.2 | L5: 3275050 | Q5: 4621444.5 | V5: SERVICE | W5: 0.225
A6: Véhicules neufsAutos détail | B6: Véhicules neufs | C6: Autos détail | D6: 23 | E6: 1953.6492 | F6: 44933.931 | J6: 7 | K6: 639.14571 | L6: 4474.02 | M6: -16 | N6: -40459.911 | O6: 19 | P6: 1667.12 | Q6: 31675.28 | R6: -12 | S6: -27201.26 | V6: CARROSSERIE | W6: 0.025
A7: Véhicules neufsCamions détail | B7: Véhicules neufs | C7: Camions détail | D7: 61 | E7: 2435.9047 | F7: 148590.19 | J7: 56 | K7: 2079.0589 | L7: 116427.3 | M7: -5 | N7: -32162.885 | O7: 62 | P7: 2284.2913 | Q7: 141626.06 | R7: -6 | S7: -25198.76 | V7: PIECES | W7: 0.2
A8: Véhicules neufsSprinter | B8: Véhicules neufs | C8: Sprinter | D8: 0 | E8: 0 | F8: 0 | J8: 0 | K8: 0 | L8: 0 | M8: 0 | N8: 0 | O8: 0 | P8: 0 | Q8: 0 | R8: 0 | S8: 0 | W8: 1
A9: Véhicules neufsMoto détail | B9: Véhicules neufs | C9: Moto détail | D9: 0 | E9: 0 | F9: 0 | J9: 0 | K9: 0 | L9: 0 | M9: 0 | N9: 0 | O9: 0 | P9: 0 | Q9: 0 | R9: 0 | S9: 0
A10: Véhicules neufs[...] | B10: Véhicules neufs | C10: [...] | D10: 0 | E10: 0 | F10: 0 | J10: 0 | K10: 0 | L10: 0 | M10: 0 | N10: 0 | O10: 0 | P10: 0 | Q10: 0 | R10: 0 | S10: 0
A11: Véhicules neufs[...] | B11: Véhicules neufs | C11: [...] | D11: 0 | E11: 0 | F11: 0 | J11: 0 | K11: 0 | L11: 0 | M11: 0 | N11: 0 | O11: 0 | P11: 0 | Q11: 0 | R11: 0 | S11: 0
A12: Véhicules neufs[...] | B12: Véhicules neufs | C12: [...] | D12: 0 | E12: 0 | F12: 0 | J12: 0 | K12: 0 | L12: 0 | M12: 0 | N12: 0 | O12: 0 | P12: 0 | Q12: 0 | R12: 0 | S12: 0
A13: Véhicules neufsTotal Neufs | B13: Véhicules neufs | C13: Total Neufs | D13: 84 | E13: 2303.8585 | F13: 193524.12 | J13: 63 | K13: 1919.0686 | L13: 120901.32 | M13: -21 | N13: -72622.796 | O13: 81 | P13: 2139.5227 | Q13: 173301.34 | R13: -18 | S13: -52400.02
A14: Véhicules neufs | B14: Véhicules neufs | M14: -0.25 | N14: -0.37526484 | R14: -0.22222222 | S14: -0.30236362 | AD14: 20 | AE14: 1000 | AF14: 20000
A15: Véhicules neufsEx-Démos et courtoisies | B15: Véhicules neufs | C15: Ex-Démos et courtoisies | D15: 4 | E15: 1534.7521 | F15: 6139.0086 | J15: 0 | K15: 0 | L15: 0 | M15: -4 | N15: -6139.0086 | O15: 6 | P15: 1521.5767 | Q15: 9129.46 | R15: -6 | S15: -9129.46 | AD15: 25 | AE15: 800 | AF15: 20000
A16: Véhicules neufs | B16: Véhicules neufs
A17: Véhicules neufsFlottes | B17: Véhicules neufs | C17: Flottes | D17: 2 | E17: 2393.8521 | F17: 4787.7042 | J17: 3 | K17: 626.18667 | L17: 1878.56 | M17: 1 | N17: -2909.1442 | O17: 1 | P17: 1402.08 | Q17: 1402.08 | R17: 2 | S17: 476.48
A18: Véhicules neufs | B18: Véhicules neufs
A19: Véhicules neufsRachat bail | B19: Véhicules neufs | C19: Rachat bail | D19: 0 | E19: 0 | F19: 9350 | L19: 11637.42 | N19: 2287.42 | Q19: 4315 | R19: 0 | S19: 7322.42
A20: Véhicules neufs | B20: Véhicules neufs
A21: Véhicules neufsRev. Finances | B21: Véhicules neufs | C21: Rev. Finances | D21: 0 | E21: 0 | F21: 4400 | K21: 0 | L21: 0 | N21: -4400 | Q21: 0 | R21: 0 | S21: 0
A22: Véhicules neufsRev. Protections | B22: Véhicules neufs | C22: Rev. Protections | D22: 0 | E22: 0 | F22: 81840 | K22: 960.30048 | L22: 60498.93 | N22: -21341.07 | Q22: 76578.39 | R22: -960.30048 | S22: -16079.46
A23: Véhicules neufsRev. Autres | B23: Véhicules neufs | C23: Rev. Autres | D23: 0 | E23: 0 | F23: 1760 | K23: 0 | L23: 0 | N23: -1760 | Q23: 0 | R23: 0 | S23: 0
A24: Véhicules neufsTotal F&I | B24: Véhicules neufs | C24: Total F&I | D24: 88 | E24: 1000 | F24: 88000 | J24: 63 | K24: 960.30048 | L24: 60498.93 | M24: -25 | N24: -27501.07 | O24: 87 | P24: 880.21138 | Q24: 76578.39 | S24: -16079.46
A25: Véhicules neufs | B25: Véhicules neufs | N25: -0.31251216 | S25: -0.20997386
A26: Véhicules neufs | B26: Véhicules neufs
A27: Véhicules neufsTotal Dépt. Neufs | B27: Véhicules neufs | C27: Total Dépt. Neufs | D27: 90 | E27: 3353.3425 | F27: 301800.83 | J27: 66 | K27: 2953.2762 | L27: 194916.23 | M27: -24 | N27: -106884.6 | O27: 88 | P27: 3008.2531 | Q27: 264726.27 | R27: -22 | S27: -69810.04
A28: Véhicules neufs | B28: Véhicules neufs | L28: 0.64584392 | M28: -0.26666667 | N28: -0.35415608 | R28: -0.25 | S28: -0.26370651
A29: Véhicules neufs | B29: Véhicules neufs
A30: Véhicules neufsDEPENSES | B30: Véhicules neufs | C30: DEPENSES
A31: Véhicules neufsComm. vendeurs | B31: Véhicules neufs | C31: Comm. vendeurs | D31: 0.32397102 | E31: 735.05757 | F31: 64685.066 | J31: 0.29473827 | K31: 574.41159 | L31: 36187.93 | N31: -28497.136 | O31: 0.34685797 | P31: 732.91839 | Q31: 63763.9 | S31: -27575.97
A32: Véhicules neufsComm. F&I | B32: Véhicules neufs | C32: Comm. F&I | D32: 0.28 | E32: 280 | F32: 24640 | J32: 0.8234187 | K32: 790.72937 | L32: 49815.95 | N32: 25175.95 | O32: 0.26932885 | P32: 237.06632 | Q32: 20624.77 | S32: 29191.18
A33: Véhicules neufsFrais de livraison | B33: Véhicules neufs | C33: Frais de livraison | E33: 115 | F33: 10120 | K33: 50.647937 | L33: 3190.82 | N33: -6929.18 | P33: 120.29333 | Q33: 10465.52 | S33: -7274.7
A34: Véhicules neufsService gratuit 1 | B34: Véhicules neufs | C34: Service gratuit 1 | E34: 10 | F34: 880 | K34: 0 | L34: 0 | N34: -880 | P34: 23.456092 | Q34: 2040.68 | S34: -2040.68
A35: Véhicules neufsEntretien stock | B35: Véhicules neufs | C35: Entretien stock | E35: 120.75 | F35: 10626 | K35: 123.11175 | L35: 7756.04 | N35: -2869.96 | P35: 65.982069 | Q35: 5740.44 | S35: 2015.6
A36: Véhicules neufsPublicité 1 | B36: Véhicules neufs | C36: Publicité 1 | E36: 30.25 | F36: 2662 | K36: 95.550635 | L36: 6019.69 | N36: 3357.69 | P36: 8.5896552 | Q36: 747.3 | S36: 5272.39
A37: Véhicules neufsIntérêt de gros | B37: Véhicules neufs | C37: Intérêt de gros | E37: 413.84576 | F37: 36418.427 | K37: 390.07746 | L37: 24574.88 | N37: -11843.547 | P37: 400.05483 | Q37: 34804.77 | S37: -10229.89
A38: Véhicules neufs[...] | B38: Véhicules neufs | C38: [...] | E38: 0 | F38: 0 | K38: 0 | L38: 0 | N38: 0 | P38: 0 | Q38: 0 | S38: 0
A39: Véhicules neufs[...] | B39: Véhicules neufs | C39: [...] | E39: 0 | F39: 0 | K39: 0 | L39: 0 | N39: 0 | P39: 0 | Q39: 0 | S39: 0
A40: Véhicules neufs[...] | B40: Véhicules neufs | C40: [...] | E40: 0 | F40: 0 | K40: 0 | L40: 0 | N40: 0 | P40: 0 | Q40: 0 | S40: 0
A41: Véhicules neufsTOTAL VARIABLES | B41: Véhicules neufs | C41: TOTAL VARIABLES | D41: % brut | E41: 0.49712088 | F41: 150031.49 | J41: % brut | K41: 0.65435962 | L41: 127545.31 | N41: -22486.183 | O41: % brut | P41: 0.52200101 | Q41: 138187.38 | S41: -10642.07
A42: Véhicules neufsSalaires cadres | B42: Véhicules neufs | C42: Salaires cadres | F42: 28420.582 | L42: 10870.49 | N42: -17550.092 | P42: 0.059916079 | Q42: 15861.36 | S42: -4990.87
A43: Véhicules neufsSalaires commis | B43: Véhicules neufs | C43: Salaires commis | F43: 17167.774 | L43: 17179.27 | N43: 11.496154 | Q43: 11048.85 | S43: 6130.42
A44: Véhicules neufsSalaires autres | B44: Véhicules neufs | C44: Salaires autres | F44: 394.44231 | L44: 11.25 | N44: -383.19231 | Q44: 4682.53 | S44: -4671.28
A45: Véhicules neufsSalaires spécialistes | B45: Véhicules neufs | C45: Salaires spécialistes | F45: 0 | L45: 0 | N45: 0 | Q45: 0 | S45: 0
A46: Véhicules neufs[...] | B46: Véhicules neufs | C46: [...] | F46: 0 | L46: 0 | N46: 0 | Q46: 0 | S46: 0
A47: Véhicules neufs[...] | B47: Véhicules neufs | C47: [...] | F47: 0 | L47: 0 | N47: 0 | Q47: 0 | S47: 0
A48: Véhicules neufs[...] | B48: Véhicules neufs | C48: [...] | F48: 0 | L48: 0 | N48: 0 | Q48: 0 | S48: 0
A49: Véhicules neufsSalaires en absences | B49: Véhicules neufs | C49: Salaires en absences | F49: 13032.075 | L49: 10162.42 | N49: -2869.6551 | Q49: 11439.02 | S49: -1276.6
A50: Véhicules neufsDéduction à la source | B50: Véhicules neufs | C50: Déduction à la source | F50: 15845.166 | L50: 16339.01 | N50: 493.84379 | Q50: 14840.25 | S50: 1498.76
A51: Véhicules neufsBénéfices marginaux | B51: Véhicules neufs | C51: Bénéfices marginaux | F51: 8163.7052 | L51: 5769.38 | N51: -2394.3252 | Q51: 7953.48 | S51: -2184.1
A52: Véhicules neufsCsst | B52: Véhicules neufs | C52: Csst | F52: 3559.4214 | L52: 2753.54 | N52: -805.8814 | Q52: 3473.47 | S52: -719.93
A53: Véhicules neufs[...] | B53: Véhicules neufs | C53: [...] | D53: #N/A | F53: 0 | L53: 0 | N53: 0 | Q53: 0 | S53: 0
A54: Véhicules neufsTOTAL PERSONNEL | B54: Véhicules neufs | C54: TOTAL PERSONNEL | D54: % brut | E54: 0.28688843 | F54: 86583.166 | J54: % brut | K54: 0.3236537 | L54: 63085.36 | N54: -23497.806 | O54: % brut | P54: 0.26177591 | Q54: 69298.96 | S54: -6213.6
A55: Véhicules neufsPublicité 2 | B55: Véhicules neufs | C55: Publicité 2 | F55: 0 | L55: 0 | N55: 0 | Q55: 0 | S55: 0
A56: Véhicules neufsService gratuit 2 | B56: Véhicules neufs | C56: Service gratuit 2 | F56: 0 | L56: 0 | N56: 0 | Q56: 0 | S56: 0
A57: Véhicules neufsFrais véhicules de cie | B57: Véhicules neufs | C57: Frais véhicules de cie | F57: 8952.5479 | L57: 3047.1 | N57: -5905.4479 | Q57: 9189.64 | S57: -6142.54
A58: Véhicules neufsInformatique | B58: Véhicules neufs | C58: Informatique | F58: 7960.9948 | L58: 6359.43 | N58: -1601.5648 | Q58: 8684.45 | S58: -2325.02
A59: Véhicules neufsFrais de déplacement | B59: Véhicules neufs | C59: Frais de déplacement | F59: 1266.6975 | L59: 918.2 | N59: -348.4975 | Q59: 1158.94 | S59: -240.74
A60: Véhicules neufsServices extérieurs | B60: Véhicules neufs | C60: Services extérieurs | F60: 7215.7407 | L60: 8335.12 | N60: 1119.3793 | Q60: 7667.77 | S60: 667.35
A61: Véhicules neufsFournitures autres | B61: Véhicules neufs | C61: Fournitures autres | F61: 97.257333 | L61: 25.65 | N61: -71.607333 | Q61: 141.9 | S61: -116.25
A62: Véhicules neufsUniformes | B62: Véhicules neufs | C62: Uniformes | F62: 28.333333 | L62: 0 | N62: -28.333333 | Q62: 0 | S62: 0
A63: Véhicules neufsPapeterie | B63: Véhicules neufs | C63: Papeterie | F63: 741.43089 | L63: 299.54 | N63: -441.89089 | Q63: 1375.08 | S63: -1075.54
A64: Véhicules neufsTéléphone | B64: Véhicules neufs | C64: Téléphone | F64: 344.80198 | L64: 368.32 | N64: 23.518015 | Q64: 440.89 | S64: -72.57
A65: Véhicules neufsFrais postaux | B65: Véhicules neufs | C65: Frais postaux | F65: 102.8224 | L65: 78.17 | N65: -24.652395 | Q65: 10.56 | S65: 67.61
A66: Véhicules neufsDivers | B66: Véhicules neufs | C66: Divers | F66: 201.17039 | L66: 62.72 | N66: -138.45039 | Q66: 52.48 | S66: 10.24
... A68: Véhicules neufsFrais bancaires | B68: Véhicules neufs | C68: Frais bancaires | F68: 3899.9395 | L68: 4016.45 | N68: 116.51052 | Q68: 3576.25 | S68: 440.2
A69: Véhicules neufs[...] | B69: Véhicules neufs | C69: [...] | F69: 0 | N69: 0 | Q69: 0 | S69: 0
A70: Véhicules neufs[...] | B70: Véhicules neufs | C70: [...] | F70: 0 | L70: 0 | N70: 0 | Q70: 0 | S70: 0
A71: Véhicules neufs[...] | B71: Véhicules neufs | C71: [...] | F71: 0 | L71: 0 | N71: 0 | Q71: 0 | S71: 0
A72: Véhicules neufsTOTAL SEMI-FIXES | B72: Véhicules neufs | C72: TOTAL SEMI-FIXES | D72: % brut | E72: 0.10850349 | F72: 32746.443 | J72: % brut | K72: 0.12787545 | L72: 24925 | N72: -7821.443 | O72: % brut | P72: 0.13551749 | Q72: 35875.04 | S72: -10950.04
A73: Véhicules neufs | B73: Véhicules neufs
A74: Véhicules neufsTOTAL DES DÉPENSES | B74: Véhicules neufs | C74: TOTAL DES DÉPENSES | D74: % brut | E74: 0.8925128 | F74: 269361.1 | J74: % brut | K74: 1.1058888 | L74: 215555.67 | N74: -53805.432 | O74: % brut | P74: 0.91929441 | Q74: 243361.38 | S74: -27805.71
A75: Véhicules neufsProgramme neuf 1 | B75: Véhicules neufs | C75: Programme neuf 1 | F75: 0 | L75: 0 | N75: 0 | Q75: 0
A76: Véhicules neufsProgramme neuf 2 | B76: Véhicules neufs | C76: Programme neuf 2 | F76: 0 | L76: 0 | N76: 0 | Q76: 0 | S76: 0
A77: Véhicules neufsProgramme neuf 3 | B77: Véhicules neufs | C77: Programme neuf 3 | F77: 0 | L77: 0 | N77: 0 | Q77: 0 | S77: 0
A78: Véhicules neufsHoldbacks | B78: Véhicules neufs | C78: Holdbacks | E78: 1423.9988 | F78: 128159.9 | J78: 0.7998602 | K78: 1139 | L78: 75174 | N78: -52985.896 | Q78: 110039 | S78: -34865
A79: Véhicules neufs[...] | B79: Véhicules neufs | C79: [...] | F79: 0 | L79: 0 | N79: 0 | Q79: 0 | S79: 0
A80: Véhicules neufs[...] | B80: Véhicules neufs | C80: [...] | F80: 0 | L80: 0 | N80: 0 | Q80: 0 | S80: 0
A81: Véhicules neufs[...] | B81: Véhicules neufs | C81: [...] | F81: 0 | L81: 0 | N81: 0 | Q81: 0 | S81: 0
A82: Véhicules neufsFrais administration | B82: Véhicules neufs | C82: Frais administration | D82: 0.95 | E82: 474.05 | F82: 41716.4 | J82: 1.0322483 | K82: 489.28571 | L82: 30825 | N82: -10891.4 | Q82: 39816 | S82: -8991
A83: Véhicules neufsAUTRES REVENUS | B83: Véhicules neufs | C83: AUTRES REVENUS | F83: 169876.3 | L83: 105999 | N83: -63877.296 | Q83: 149855 | S83: -43856
A84: Véhicules neufs | B84: Véhicules neufs
A85: Véhicules neufsPROFIT DÉPARTEMENTAL | B85: Véhicules neufs | C85: PROFIT DÉPARTEMENTAL | F85: 202316.02 | L85: 85359.56 | N85: -116956.46 | P85: 0.037048999 | Q85: 171219.89 | S85: -85860.33
C89: Volks | K89: Véhicules usagés | S89: Réalisé, Août 2025
D91: BUDGET ORIGINAL | J91: RÉALISATION | M91: ÉCART réel / Budget | O91: ANNÉE PRÉCÉDENTE | R91: ECART (réel/ Ann.Préc.)
D92: UNITE | E92: $P/UNITÉ | F92: $PROFITS | J92: UNITÉS | K92: $P/UNITE | L92: $PROFITS | M92: UNITÉS | N92: $PROFITS | O92: UNITE | P92: $P/UNITÉ | Q92: $PROFITS | R92: UNITÉS | S92: $PROFITS
A93: Véhicules usagésVentes nettes | B93: Véhicules usagés | C93: Ventes nettes | F93: 1510131.6 | L93: 1317515 | Q93: 1094286.6
A94: Véhicules usagésCertifié | B94: Véhicules usagés | C94: Certifié | D94: 23 | E94: 1400 | F94: 32200 | J94: 24 | K94: 1864.0925 | L94: 44738.22 | M94: 1 | N94: 12538.22 | O94: 19 | P94: 922.09053 | Q94: 17519.72 | R94: 5 | S94: 27218.5
A95: Véhicules usagésNon Certifié | B95: Véhicules usagés | C95: Non Certifié | D95: 3 | E95: 1800 | F95: 5400 | J95: 1 | K95: 1000 | L95: 1000 | M95: -2 | N95: -4400 | O95: 6 | P95: 615.43667 | Q95: 3692.62 | R95: -5 | S95: -2692.62
A96: Véhicules usagésAutres Marques | B96: Véhicules usagés | C96: Autres Marques | D96: 4 | E96: 1500 | F96: 6000 | J96: 0 | K96: 0 | L96: 0 | M96: -4 | N96: -6000 | O96: 0 | P96: 0 | Q96: 0 | R96: 0 | S96: 0
A97: Véhicules usagésTotal Usagés | B97: Véhicules usagés | C97: Total Usagés | D97: 30 | E97: 1453.3333 | F97: 43600 | J97: 25 | K97: 1829.5288 | L97: 45738.22 | M97: -5 | N97: 2138.22 | O97: 25 | P97: 848.4936 | Q97: 21212.34 | R97: 0 | S97: 24525.88
A98: Véhicules usagés | B98: Véhicules usagés | E98: 0 | M98: -0.16666667 | N98: 0.049041743 | P98: 0 | R98: 0 | S98: 1.1562081
A99: Véhicules usagés | B99: Véhicules usagés | D99: 0 | E99: 0 | F99: 0
A100: Véhicules usagésVentes au Gros | B100: Véhicules usagés | C100: Ventes au Gros | D100: 33 | E100: 400 | F100: 13200 | J100: 35 | K100: -72.185143 | L100: -2526.48 | M100: 2 | N100: -15726.48 | O100: 42 | P100: 10.700238 | Q100: 449.41 | R100: -7 | S100: -2975.89
A101: Véhicules usagés | B101: Véhicules usagés
A102: Véhicules usagésRev. Finances | B102: Véhicules usagés | C102: Rev. Finances | D102: 0 | E102: 0 | F102: 18000 | K102: 528.9588 | L102: 13223.97 | N102: -4776.03 | Q102: 2727.49 | R102: -528.9588 | S102: 10496.48
A103: Véhicules usagésRev. Protections | B103: Véhicules usagés | C103: Rev. Protections | D103: 0 | E103: 0 | F103: 37500 | K103: 1886.9204 | L103: 47173.01 | N103: 9673.01 | Q103: 25456.86 | R103: -1886.9204 | S103: 21716.15
A104: Véhicules usagésRev. Autres | B104: Véhicules usagés | C104: Rev. Autres | D104: 0 | E104: 0 | F104: 1500 | K104: 46.1124 | L104: 1152.81 | N104: -347.19 | Q104: 1587.44 | R104: -46.1124 | S104: -434.63
A105: Véhicules usagésTotal F&I | B105: Véhicules usagés | C105: Total F&I | D105: 30 | E105: 1900 | F105: 57000 | J105: 25 | K105: 2461.9916 | L105: 61549.79 | M105: -5 | N105: 4549.79 | O105: 25 | P105: 1190.8716 | Q105: 29771.79 | S105: 31778
...

Sheet Septembre 2025
C1: Volks | K1: Véhicules neufs | S1: Réalisé, Septembre 2025
D2: X | E2: O | F2: U | J2: NB | L2: $ | O2: X | P2: O | Q2: U | V2: *** NE PAS EFFACER / Pour An Précédente ***
D3: BUDGET ORIGINAL | J3: RÉALISATION | M3: ÉCART réel / Budget | O3: ANNÉE PRÉCÉDENTE | R3: ECART (réel/ Ann.Préc.) | V3: NEUF | W3: 0.45
D4: UNITE | E4: $P/UNITÉ | F4: $PROFITS | J4: UNITÉS | K4: $P/UNITE | L4: $PROFITS | M4: UNITÉS | N4: $PROFITS | O4: UNITE | P4: $P/UNITÉ | Q4: $PROFITS | R4: UNITÉS | S4: $PROFITS | V4: USAGE | W4: 0.1
A5: Véhicules neufsVentes nettes | B5: Véhicules neufs | C5: Ventes nettes | F5: 3359976.1 | L5: 3303841.7 | Q5: 2442838.5 | V5: SERVICE | W5: 0.225
A6: Véhicules neufsAutos détail | B6: Véhicules neufs | C6: Autos détail | D6: 16 | E6: 1953.6492 | F6: 31258.387 | J6: 7 | K6: 688.43143 | L6: 4819.02 | M6: -9 | N6: -26439.367 | O6: 16 | P6: 1640.0056 | Q6: 26240.09 | R6: -9 | S6: -21421.07 | V6: CARROSSERIE | W6: 0.025
A7: Véhicules neufsCamions détail | B7: Véhicules neufs | C7: Camions détail | D7: 44 | E7: 2435.9047 | F7: 107179.81 | J7: 56 | K7: 2636.2429 | L7: 147629.6 | M7: 12 | N7: 40449.794 | O7: 26 | P7: 2080.4762 | Q7: 54092.38 | R7: 30 | S7: 93537.22 | V7: PIECES | W7: 0.2
A8: Véhicules neufsSprinter | B8: Véhicules neufs | C8: Sprinter | D8: 0 | E8: 0 | F8: 0 | J8: 0 | K8: 0 | L8: 0 | M8: 0 | N8: 0 | O8: 0 | P8: 0 | Q8: 0 | R8: 0 | S8: 0 | W8: 1
A9: Véhicules neufsMoto détail | B9: Véhicules neufs | C9: Moto détail | D9: 0 | E9: 0 | F9: 0 | J9: 0 | K9: 0 | L9: 0 | M9: 0 | N9: 0 | O9: 0 | P9: 0 | Q9: 0 | R9: 0 | S9: 0
A10: Véhicules neufs[...] | B10: Véhicules neufs | C10: [...] | D10: 0 | E10: 0 | F10: 0 | J10: 0 | K10: 0 | L10: 0 | M10: 0 | N10: 0 | O10: 0 | P10: 0 | Q10: 0 | R10: 0 | S10: 0
A11: Véhicules neufs[...] | B11: Véhicules neufs | C11: [...] | D11: 0 | E11: 0 | F11: 0 | J11: 0 | K11: 0 | L11: 0 | M11: 0 | N11: 0 | O11: 0 | P11: 0 | Q11: 0 | R11: 0 | S11: 0
A12: Véhicules neufs[...] | B12: Véhicules neufs | C12: [...] | D12: 0 | E12: 0 | F12: 0 | J12: 0 | K12: 0 | L12: 0 | M12: 0 | N12: 0 | O12: 0 | P12: 0 | Q12: 0 | R12: 0 | S12: 0
A13: Véhicules neufsTotal Neufs | B13: Véhicules neufs | C13: Total Neufs | D13: 60 | E13: 2307.3032 | F13: 138438.19 | J13: 63 | K13: 2419.8194 | L13: 152448.62 | M13: 3 | N13: 14010.427 | O13: 42 | P13: 1912.6779 | Q13: 80332.47 | R13: 21 | S13: 72116.15
A14: Véhicules neufs | B14: Véhicules neufs | M14: 0.05 | N14: 0.10120348 | R14: 0.5 | S14: 0.89772106 | AD14: 20 | AE14: 1000 | AF14: 20000
A15: Véhicules neufsEx-Démos et courtoisies | B15: Véhicules neufs | C15: Ex-Démos et courtoisies | D15: 3 | E15: 1534.7521 | F15: 4604.2564 | J15: 1 | K15: 1212.34 | L15: 1212.34 | M15: -2 | N15: -3391.9164 | O15: 3 | P15: 2567.51 | Q15: 7702.53 | R15: -2 | S15: -6490.19 | AD15: 25 | AE15: 800 | AF15: 20000
A16: Véhicules neufs | B16: Véhicules neufs
A17: Véhicules neufsFlottes | B17: Véhicules neufs | C17: Flottes | D17: 2 | E17: 2393.8521 | F17: 4787.7042 | J17: 3 | K17: 626.18667 | L17: 1878.56 | M17: 1 | N17: -2909.1442 | O17: 1 | P17: 4920.64 | Q17: 4920.64 | R17: 2 | S17: -3042.08
A18: Véhicules neufs | B18: Véhicules neufs
A19: Véhicules neufsRachat bail | B19: Véhicules neufs | C19: Rachat bail | D19: 0 | E19: 0 | F19: 6800 | L19: 11637.42 | N19: 4837.42 | Q19: 14800 | R19: 0 | S19: -3162.58
A20: Véhicules neufs | B20: Véhicules neufs
A21: Véhicules neufsRev. Finances | B21: Véhicules neufs | C21: Rev. Finances | D21: 0 | E21: 0 | F21: 3150 | K21: 0 | L21: 0 | N21: -3150 | Q21: 0 | R21: 0 | S21: 0
A22: Véhicules neufsRev. Protections | B22: Véhicules neufs | C22: Rev. Protections | D22: 0 | E22: 0 | F22: 58590 | K22: 952.71766 | L22: 60973.93 | N22: 2383.93 | Q22: 45910.53 | R22: -952.71766 | S22: 15063.4
A23: Véhicules neufsRev. Autres | B23: Véhicules neufs | C23: Rev. Autres | D23: 0 | E23: 0 | F23: 1260 | K23: 0 | L23: 0 | N23: -1260 | Q23: 1628.24 | R23: 0 | S23: -1628.24
A24: Véhicules neufsTotal F&I | B24: Véhicules neufs | C24: Total F&I | D24: 63 | E24: 1000 | F24: 63000 | J24: 64 | K24: 952.71766 | L24: 60973.93 | M24: 1 | N24: -2026.07 | O24: 45 | P24: 1056.4171 | Q24: 47538.77 | S24: 13435.16
A25: Véhicules neufs | B25: Véhicules neufs | N25: -0.032159841 | S25: 0.2826148
A26: Véhicules neufs | B26: Véhicules neufs
A27: Véhicules neufsTotal Dépt. Neufs | B27: Véhicules neufs | C27: Total Dépt. Neufs | D27: 65 | E27: 3348.1562 | F27: 217630.15 | J27: 67 | K27: 3405.2369 | L27: 228150.87 | M27: 2 | N27: 10520.717 | O27: 46 | P27: 3375.9654 | Q27: 155294.41 | R27: 21 | S27: 72856.46
A28: Véhicules neufs | B28: Véhicules neufs | L28: 1.0483422 | M28: 0.030769231 | N28: 0.048342184 | R28: 0.45652174 | S28: 0.46915056
A29: Véhicules neufs | B29: Véhicules neufs
A30: Véhicules neufsDEPENSES | B30: Véhicules neufs | C30: DEPENSES
A31: Véhicules neufsComm. vendeurs | B31: Véhicules neufs | C31: Comm. vendeurs | D31: 0.33053742 | E31: 750.49018 | F31: 47280.881 | J31: 0.27478502 | K31: 667.81141 | L31: 42739.93 | N31: -4540.9513 | O31: 0.32887988 | P31: 679.36089 | Q31: 30571.24 | S31: 12168.69
A32: Véhicules neufsComm. F&I | B32: Véhicules neufs | C32: Comm. F&I | D32: 0.28 | E32: 280 | F32: 17640 | J32: 0.26000358 | K32: 247.71 | L32: 15853.44 | N32: -1786.56 | O32: 0.2977738 | P32: 314.57333 | Q32: 14155.8 | S32: 1697.64
A33: Véhicules neufsFrais de livraison | B33: Véhicules neufs | C33: Frais de livraison | E33: 115 | F33: 7245 | K33: 130.02187 | L33: 8321.4 | N33: 1076.4 | P33: 123.12511 | Q33: 5540.63 | S33: 2780.77
A34: Véhicules neufsService gratuit 1 | B34: Véhicules neufs | C34: Service gratuit 1 | E34: 10 | F34: 630 | K34: 0 | L34: 0 | N34: -630 | P34: 36.238889 | Q34: 1630.75 | S34: -1630.75
A35: Véhicules neufsEntretien stock | B35: Véhicules neufs | C35: Entretien stock | E35: 120.75 | F35: 7607.25 | K35: 121.18812 | L35: 7756.04 | N35: 148.79 | P35: 174.15711 | Q35: 7837.07 | S35: -81.03
A36: Véhicules neufsPublicité 1 | B36: Véhicules neufs | C36: Publicité 1 | E36: 81.936508 | F36: 5162 | K36: 124.21734 | L36: 7949.91 | N36: 2787.91 | P36: 180.94756 | Q36: 8142.64 | S36: -192.73
A37: Véhicules neufsIntérêt de gros | B37: Véhicules neufs | C37: Intérêt de gros | E37: 603.57336 | F37: 38025.122 | K37: 37.670469 | L37: 2410.91 | N37: -35614.212 | P37: 678.81778 | Q37: 30546.8 | S37: -28135.89
A38: Véhicules neufs[...] | B38: Véhicules neufs | C38: [...] | E38: 0 | F38: 0 | K38: 0 | L38: 0 | N38: 0 | P38: 0 | Q38: 0 | S38: 0
A39: Véhicules neufs[...] | B39: Véhicules neufs | C39: [...] | E39: 0 | F39: 0 | K39: 0 | L39: 0 | N39: 0 | P39: 0 | Q39: 0 | S39: 0
A40: Véhicules neufs[...] | B40: Véhicules neufs | C40: [...] | E40: 0 | F40: 0 | K40: 0 | L40: 0 | N40: 0 | P40: 0 | Q40: 0 | S40: 0
A41: Véhicules neufsTOTAL VARIABLES | B41: Véhicules neufs | C41: TOTAL VARIABLES | D41: % brut | E41: 0.56789122 | F41: 123590.25 | J41: % brut | K41: 0.37269913 | L41: 85031.63 | N41: -38558.623 | O41: % brut | P41: 0.6337957 | Q41: 98424.93 | S41: -13393.3
A42: Véhicules neufsSalaires cadres | B42: Véhicules neufs | C42: Salaires cadres | F42: 24486.465 | L42: 21495.49 | N42: -2990.9754 | P42: 0.098917598 | Q42: 15361.35 | S42: 6134.14
A43: Véhicules neufsSalaires commis | B43: Véhicules neufs | C43: Salaires commis | F43: 13904.219 | L43: 17579.27 | N43: 3675.0509 | Q43: 9911.09 | S43: 7668.18
A44: Véhicules neufsSalaires autres | B44: Véhicules neufs | C44: Salaires autres | F44: 315.55385 | L44: 11.25 | N44: -304.30385 | Q44: 3755.5 | S44: -3744.25
A45: Véhicules neufsSalaires spécialistes | B45: Véhicules neufs | C45: Salaires spécialistes | F45: 0 | L45: 0 | N45: 0 | Q45: 0 | S45: 0
A46: Véhicules neufs[...] | B46: Véhicules neufs | C46: [...] | F46: 0 | L46: 0 | N46: 0 | Q46: 0 | S46: 0
A47: Véhicules neufs[...] | B47: Véhicules neufs | C47: [...] | F47: 0 | L47: 0 | N47: 0 | Q47: 0 | S47: 0
A48: Véhicules neufs[...] | B48: Véhicules neufs | C48: [...] | F48: 0 | L48: 0 | N48: 0 | Q48: 0 | S48: 0
A49: Véhicules neufsSalaires en absences | B49: Véhicules neufs | C49: Salaires en absences | F49: 12229.899 | L49: 9162.42 | N49: -3067.4785 | Q49: 11002.44 | S49: -1840.02
A50: Véhicules neufsDéduction à la source | B50: Véhicules neufs | C50: Déduction à la source | F50: 14869.833 | L50: 12339.01 | N50: -2530.8225 | Q50: 14099.3 | S50: -1760.29
A51: Véhicules neufsBénéfices marginaux | B51: Véhicules neufs | C51: Bénéfices marginaux | F51: 7661.1963 | L51: 4769.38 | N51: -2891.8163 | Q51: 7411.59 | S51: -2642.21
A52: Véhicules neufsCsst | B52: Véhicules neufs | C52: Csst | F52: 3340.3247 | L52: 2753.54 | N52: -586.7847 | Q52: 2367.79 | S52: 385.75
A53: Véhicules neufs[...] | B53: Véhicules neufs | C53: [...] | D53: #N/A | F53: 0 | L53: 0 | N53: 0 | Q53: 0 | S53: 0
A54: Véhicules neufsTOTAL PERSONNEL | B54: Véhicules neufs | C54: TOTAL PERSONNEL | D54: % brut | E54: 0.35292669 | F54: 76807.49 | J54: % brut | K54: 0.29853211 | L54: 68110.36 | N54: -8697.1304 | O54: % brut | P54: 0.41153484 | Q54: 63909.06 | S54: 4201.3
A55: Véhicules neufsPublicité 2 | B55: Véhicules neufs | C55: Publicité 2 | F55: 0 | L55: 0 | N55: 0 | Q55: 0 | S55: 0
A56: Véhicules neufsService gratuit 2 | B56: Véhicules neufs | C56: Service gratuit 2 | F56: 0 | L56: 0 | N56: 0 | Q56: 0 | S56: 0
A57: Véhicules neufsFrais véhicules de cie | B57: Véhicules neufs | C57: Frais véhicules de cie | F57: 8952.5479 | L57: 8541.72 | N57: -410.82793 | Q57: 10497.54 | S57: -1955.82
A58: Véhicules neufsInformatique | B58: Véhicules neufs | C58: Informatique | F58: 7960.9948 | L58: 9523.36 | N58: 1562.3652 | Q58: 8853.42 | S58: 669.94
A59: Véhicules neufsFrais de déplacement | B59: Véhicules neufs | C59: Frais de déplacement | F59: 1266.6975 | L59: 1925.24 | N59: 658.5425 | Q59: 1810.19 | S59: 115.05
A60: Véhicules neufsServices extérieurs | B60: Véhicules neufs | C60: Services extérieurs | F60: 7215.7407 | L60: 8397.52 | N60: 1181.7793 | Q60: 8147.65 | S60: 249.87
A61: Véhicules neufsFournitures autres | B61: Véhicules neufs | C61: Fournitures autres | F61: 97.257333 | L61: 25.65 | N61: -71.607333 | Q61: 74.69 | S61: -49.04
A62: Véhicules neufsUniformes | B62: Véhicules neufs | C62: Uniformes | F62: 28.333333 | L62: 0 | N62: -28.333333 | Q62: 0 | S62: 0
A63: Véhicules neufsPapeterie | B63: Véhicules neufs | C63: Papeterie | F63: 741.43089 | L63: 299.54 | N63: -441.89089 | Q63: 628.31 | S63: -328.77
A64: Véhicules neufsTéléphone | B64: Véhicules neufs | C64: Téléphone | F64: 344.80198 | L64: 368.32 | N64: 23.518015 | Q64: 345.76 | S64: 22.56
A65: Véhicules neufsFrais postaux | B65: Véhicules neufs | C65: Frais postaux | F65: 102.8224 | L65: 78.17 | N65: -24.652395 | Q65: 32.96 | S65: 45.21
A66: Véhicules neufsDivers | B66: Véhicules neufs | C66: Divers | F66: 201.17039 | L66: 134.72 | N66: -66.450385 | Q66: 152.01 | S66: -17.29
... A68: Véhicules neufsFrais bancaires | B68: Véhicules neufs | C68: Frais bancaires | F68: 3172.2328 | L68: 4016.45 | N68: 844.21717 | Q68: 3267.11 | S68: 749.34
A69: Véhicules neufs[...] | B69: Véhicules neufs | C69: [...] | F69: 0 | N69: 0 | Q69: 0 | S69: 0
A70: Véhicules neufs[...] | B70: Véhicules neufs | C70: [...] | F70: 0 | L70: 0 | N70: 0 | Q70: 0 | S70: 0
A71: Véhicules neufs[...] | B71: Véhicules neufs | C71: [...] | F71: 0 | L71: 0 | N71: 0 | Q71: 0 | S71: 0
A72: Véhicules neufsTOTAL SEMI-FIXES | B72: Véhicules neufs | C72: TOTAL SEMI-FIXES | D72: % brut | E72: 0.14712454 | F72: 32018.736 | J72: % brut | K72: 0.15220187 | L72: 34724.99 | N72: 2706.2537 | O72: % brut | P72: 0.23494143 | Q72: 36485.09 | S72: -1760.1
A73: Véhicules neufs | B73: Véhicules neufs
A74: Véhicules neufsTOTAL DES DÉPENSES | B74: Véhicules neufs | C74: TOTAL DES DÉPENSES | D74: % brut | E74: 1.0679425 | F74: 232416.48 | J74: % brut | K74: 0.82343311 | L74: 187866.98 | N74: -44549.5 | O74: % brut | P74: 1.280272 | Q74: 198819.08 | S74: -10952.1
A75: Véhicules neufsProgramme neuf 1 | B75: Véhicules neufs | C75: Programme neuf 1 | F75: 25000 | L75: 0 | N75: -25000 | Q75: 16000
A76: Véhicules neufsProgramme neuf 2 | B76: Véhicules neufs | C76: Programme neuf 2 | F76: 0 | L76: 0 | N76: 0 | Q76: 0 | S76: 0
A77: Véhicules neufsProgramme neuf 3 | B77: Véhicules neufs | C77: Programme neuf 3 | F77: 0 | L77: 0 | N77: 0 | Q77: 0 | S77: 0
A78: Véhicules neufsHoldbacks | B78: Véhicules neufs | C78: Holdbacks | E78: 1391.7817 | F78: 90465.809 | J78: 0.8310619 | K78: 1156.6567 | L78: 77496 | N78: -12969.809 | Q78: 52835 | S78: 24661
A79: Véhicules neufs[...] | B79: Véhicules neufs | C79: [...] | F79: 0 | L79: 0 | N79: 0 | Q79: 0 | S79: 0
A80: Véhicules neufs[...] | B80: Véhicules neufs | C80: [...] | F80: 0 | L80: 0 | N80: 0 | Q80: 0 | S80: 0
A81: Véhicules neufs[...] | B81: Véhicules neufs | C81: [...] | F81: 0 | L81: 0 | N81: 0 | Q81: 0 | S81: 0
A82: Véhicules neufsFrais administration | B82: Véhicules neufs | C82: Frais administration | D82: 0.95 | E82: 474.05 | F82: 29865.15 | J82: 1.0436116 | K82: 494.67188 | L82: 31659 | N82: 1793.85 | Q82: 19467 | S82: 12192
A83: Véhicules neufsAUTRES REVENUS | B83: Véhicules neufs | C83: AUTRES REVENUS | F83: 145330.96 | L83: 109155 | N83: -36175.959 | Q83: 88302 | S83: 36853
A84: Véhicules neufs | B84: Véhicules neufs
A85: Véhicules neufsPROFIT DÉPARTEMENTAL | B85: Véhicules neufs | C85: PROFIT DÉPARTEMENTAL | F85: 130544.63 | L85: 149438.89 | N85: 18894.258 | P85: 0.018330041 | Q85: 44777.33 | S85: 120661.56
C89: Volks | K89: Véhicules usagés | S89: Réalisé, Septembre 2025
D91: BUDGET ORIGINAL | J91: RÉALISATION | M91: ÉCART réel / Budget | O91: ANNÉE PRÉCÉDENTE | R91: ECART (réel/ Ann.Préc.)
D92: UNITE | E92: $P/UNITÉ | F92: $PROFITS | J92: UNITÉS | K92: $P/UNITE | L92: $PROFITS | M92: UNITÉS | N92: $PROFITS | O92: UNITE | P92: $P/UNITÉ | Q92: $PROFITS | R92: UNITÉS | S92: $PROFITS
A93: Véhicules usagésVentes nettes | B93: Véhicules usagés | C93: Ventes nettes | F93: 1226269.4 | L93: 1445195.3 | Q93: 1166915.5
A94: Véhicules usagésCertifié | B94: Véhicules usagés | C94: Certifié | D94: 19 | E94: 1400 | F94: 26600 | J94: 25 | K94: 2129.208 | L94: 53230.2 | M94: 6 | N94: 26630.2 | O94: 27 | P94: 1293.3581 | Q94: 34920.67 | R94: -2 | S94: 18309.53
A95: Véhicules usagésNon Certifié | B95: Véhicules usagés | C95: Non Certifié | D95: 2 | E95: 1800 | F95: 3600 | J95: 1 | K95: 1000 | L95: 1000 | M95: -1 | N95: -2600 | O95: -13 | P95: 1650.3969 | Q95: -21455.16 | R95: 14 | S95: 22455.16
A96: Véhicules usagésAutres Marques | B96: Véhicules usagés | C96: Autres Marques | D96: 3 | E96: 1500 | F96: 4500 | J96: 0 | K96: 0 | L96: 0 | M96: -3 | N96: -4500 | O96: 0 | P96: 0 | Q96: 24564.57 | R96: 0 | S96: -24564.57
A97: Véhicules usagésTotal Usagés | B97: Véhicules usagés | C97: Total Usagés | D97: 24 | E97: 1445.8333 | F97: 34700 | J97: 26 | K97: 2085.7769 | L97: 54230.2 | M97: 2 | N97: 19530.2 | O97: 14 | P97: 2716.4343 | Q97: 38030.08 | R97: 12 | S97: 40764.69
A98: Véhicules usagés | B98: Véhicules usagés | E98: 0 | M98: 0.083333333 | N98: 0.56282997 | P98: 0 | R98: 0.85714286 | S98: 1.0719065
A99: Véhicules usagés | B99: Véhicules usagés | D99: 0 | E99: 0 | F99: 0
A100: Véhicules usagésVentes au Gros | B100: Véhicules usagés | C100: Ventes au Gros | D100: 27 | E100: 400 | F100: 10800 | J100: 38 | K100: 366.98737 | L100: 13945.52 | M100: 11 | N100: 3145.52 | O100: 32 | P100: 218.91063 | Q100: 7005.14 | R100: 6 | S100: 6940.38
A101: Véhicules usagés | B101: Véhicules usagés
A102: Véhicules usagésRev. Finances | B102: Véhicules usagés | C102: Rev. Finances | D102: 0 | E102: 0 | F102: 14400 | K102: 508.61423 | L102: 13223.97 | N102: -1176.03 | Q102: 11832.55 | R102: -508.61423 | S102: 1391.42
A103: Véhicules usagésRev. Protections | B103: Véhicules usagés | C103: Rev. Protections | D103: 0 | E103: 0 | F103: 30000 | K103: 1907.0388 | L103: 49583.01 | N103: 19583.01 | Q103: 44398.13 | R103: -1907.0388 | S103: 5184.88
A104: Véhicules usagésRev. Autres | B104: Véhicules usagés | C104: Rev. Autres | D104: 0 | E104: 0 | F104: 1200 | K104: 44.338846 | L104: 1152.81 | N104: -47.19 | Q104: 1973.79 | R104: -44.338846 | S104: -820.98
A105: Véhicules usagésTotal F&I | B105: Véhicules usagés | C105: Total F&I | D105: 24 | E105: 1900 | F105: 45600 | J105: 26 | K105: 2459.9919 | L105: 63959.79 | M105: 2 | N105: 18359.79 | O105: 14 | P105: 4157.4621 | Q105: 58204.47 | S105: 5755.32
...

Sheet END
