Workbook
Name _Dates_Conc: [1]Dealers!$BF$37:$KA$63
Name _scen: '[1]Scen & Sens'!$E$26
Name _scen1: '[1]Scen & Sens'!$E$27
Name _scen2: '[1]Scen & Sens'!$E$28
Name _SCenarios: '[1]Scen & Sens'!$J$26:$O$26
Name _Sens1: '[1]Scen & Sens'!$F$9
Name _Sens2: '[1]Scen & Sens'!$F$10
Name _sensRes1: '[1]Scen & Sens'!$E$15
Name _sensRes2: '[1]Scen & Sens'!$E$16
Name _sensRes3: '[1]Scen & Sens'!$E$17
Name _sensRes4: '[1]Scen & Sens'!$E$18
Name _sensRes5: '[1]Scen & Sens'!$E$19
Name _sensRes6: '[1]Scen & Sens'!$E$20
Name _sensRes7: '[1]Scen & Sens'!$E$21
Name DateRange: [1]Volkswagen!$BF$6:$DY$6
Name Monetary_Unit: [1]Parameters!$B$15
Name Months: [1]Parameters!$E$9:$E$20
Name Rng_Dealers_Names: [1]!Tbl_Dealers[Dealer Name]
Name Rng_Dlr_Dates: [1]!Tbl_V_Dlr_Dates[Date]
Name Ticker: #REF!
Name Ticker: #REF!
Name Ticker: #REF!
Name Titre: [1]Front!$A$9

Sheet Paramètre
B3: VOLKS QUARTER | C3: Volks T3 2023
B6: BUDGET | F6: BUDGET RÉVISÉ | J6: ACTUAL | N6: LAST YEAR
B7: Ventes | C7: Profits bruts | D7: BAIIA | E7: EBIT | F7: Ventes | G7: Profits bruts | H7: BAIIA | I7: EBIT | J7: Ventes | K7: Profits bruts | L7: BAIIA | M7: EBIT | N7: Ventes | O7: Profits bruts | P7: BAIIA | Q7: EBIT
A8: CTRL | B8: =+B9-B10 -> #REF! | C8: =+C9-C10 -> #REF! | D8: =+D9-D10 -> #REF! | E8: =+E9-E10 -> #REF! | F8: =+F9-F10 -> #REF! | G8: =+G9-G10 -> #REF! | H8: =+H9-H10 -> #REF! | I8: =+I9-I10 -> #REF! | ... Q8: =+Q9-Q10 -> #REF!
A9: CONSO | B9: =+Conso!$Z$405 -> 14227382 | C9: =+Conso!$Z$406 -> 1964256.6 | D9: =+Conso!$Z$482 -> 516253.45 | E9: =+Conso!$Z$497 -> 500994.61 | F9: =+Conso!$AC$405 -> 0 | G9: =+Conso!$AC$406 -> 0 | H9: =+Conso!$AC$482 -> 0 | I9: =+Conso!$AC$497 -> 0 | J9: =+Conso!$AF$405 -> 14540993 | K9: =+Conso!$AF$406 -> 1891334.5 | L9: =+Conso!$AF$482 -> 537161.11 | M9: =+Conso!$AF$497 -> 524217.61 | N9: =+Conso!$AL$405 -> 16244538 | O9: =+Conso!$AL$406 -> 2131722.3 | P9: =+Conso!$AL$482 -> 790555.84 | Q9: =+Conso!$AL$497 -> 776331.97
A10: TOTAL | B10: =+SUM(B11:B13) -> #REF! | C10: =+SUM(C11:C13) -> #REF! | D10: =+SUM(D11:D13) -> #REF! | E10: =+SUM(E11:E13) -> #REF! | F10: =+SUM(F11:F13) -> #REF! | G10: =+SUM(G11:G13) -> #REF! | H10: =+SUM(H11:H13) -> #REF! | I10: =+SUM(I11:I13) -> #REF! | ... Q10: =+SUM(Q11:Q13) -> #REF!
A11: AUDI 1 | B11: =+#REF! -> #REF! | C11: =+#REF! -> #REF! | D11: =+#REF! -> #REF! | E11: =+#REF! -> #REF! | F11: =+#REF! -> #REF! | G11: =+#REF! -> #REF! | H11: =+#REF! -> #REF! | I11: =+#REF! -> #REF! | ... Q11: =+#REF! -> #REF!
A12: AUDI 2 | B12: =+#REF! -> #REF! | C12: =+#REF! -> #REF! | D12: =+#REF! -> #REF! | E12: =+#REF! -> #REF! | F12: =+#REF! -> #REF! | G12: =+#REF! -> #REF! | H12: =+#REF! -> #REF! | I12: =+#REF! -> #REF! | ... Q12: =+#REF! -> #REF!
A13: AUDI 3 | B13: =+#REF! -> #REF! | C13: =+#REF! -> #REF! | D13: =+#REF! -> #REF! | E13: =+#REF! -> #REF! | F13: =+#REF! -> #REF! | G13: =+#REF! -> #REF! | H13: =+#REF! -> #REF! | I13: =+#REF! -> #REF! | ... Q13: =+#REF! -> #REF!

Sheet Conso
C1: Conso | K1: Véhicules neufs | S1: =CONCATENATE("Réalisé"," ",Paramètre!$C$2," ",Paramètre!$C$3) -> Réalisé Volks T3 2023
D2: X | E2: O | F2: U | G2: X | H2: O | I2: U
D3: BUDGET ORIGINAL | G3: BUDGET REVISE | J3: RÉALISATION | M3: ÉCART réel / Budget | O3: ANNÉE PRÉCÉDENTE | R3: ECART (réel/ Ann.Préc.)
D4: UNITE | E4: $P/UNITÉ | F4: $PROFITS | G4: UNITE | H4: $P/UNITÉ | I4: $PROFITS | J4: UNITE | K4: $P/UNITE | L4: $PROFITS | M4: UNITÉS | N4: $PROFITS | O4: UNITE | P4: $P/UNITE | Q4: $PROFITS | R4: UNITÉS | S4: $PROFITS
A5: =+B5&C5 -> Véhicules neufsVentes nettes | B5: =+$K$1 -> Véhicules neufs | C5: Ventes nettes | F5: =+SUM(START:END!F5) -> 7317453.3 | I5: =+SUM(START:END!I5) -> 0 | L5: =+SUM(START:END!L5) -> 7302296.1 | Q5: =+SUM(START:END!Q5) -> 8779737.5
A6: =+B6&C6 -> Véhicules neufsAutos détail | B6: =+$K$1 -> Véhicules neufs | C6: Autos détail | D6: =+SUM(START:END!D6) -> 31.220571 | E6: =IF(D6=0,0,F6/D6) -> 1988.434 | F6: =+SUM(START:END!F6) -> 62080.046 | G6: =+SUM(START:END!G6) -> 0 | H6: =IF(G6=0,0,I6/G6) -> 0 | I6: =+SUM(START:END!I6) -> 0 | J6: =+SUM(START:END!J6) -> 50 | K6: =IF(J6=0,0,L6/J6) -> 2046.4024 | L6: =+SUM(START:END!L6) -> 102320.12 | M6: =J6-D6 -> 18.779429 | N6: =L6-F6 -> 40240.074 | O6: =+SUM(START:END!O6) -> 50 | P6: =IF(O6=0,0,Q6/O6) -> 2395.0896 | Q6: =+SUM(START:END!Q6) -> 119754.48 | R6: =J6-O6 -> 0 | S6: =L6-Q6 -> -17434.36
A7: =+B7&C7 -> Véhicules neufsCamions détail | B7: =+$K$1 -> Véhicules neufs | C7: Camions détail | D7: =+SUM(START:END!D7) -> 124.8698 | E7: =IF(D7=0,0,F7/D7) -> 2556.3336 | F7: =+SUM(START:END!F7) -> 319208.86 | G7: =+SUM(START:END!G7) -> 0 | H7: =IF(G7=0,0,I7/G7) -> 0 | I7: =+SUM(START:END!I7) -> 0 | J7: =+SUM(START:END!J7) -> 82 | K7: =IF(J7=0,0,L7/J7) -> 2576.8304 | L7: =+SUM(START:END!L7) -> 211300.09 | M7: =J7-D7 -> -42.869797 | N7: =L7-F7 -> -107908.77 | O7: =+SUM(START:END!O7) -> 120 | P7: =IF(O7=0,0,Q7/O7) -> 2998.4707 | Q7: =+SUM(START:END!Q7) -> 359816.49 | R7: =J7-O7 -> -38 | S7: =L7-Q7 -> -148516.4
A8: =+B8&C8 -> Véhicules neufsSprinter | B8: =+$K$1 -> Véhicules neufs | C8: Sprinter | D8: =+SUM(START:END!D8) -> 0 | E8: =IF(D8=0,0,F8/D8) -> 0 | F8: =+SUM(START:END!F8) -> 0 | G8: =+SUM(START:END!G8) -> 0 | H8: =IF(G8=0,0,I8/G8) -> 0 | I8: =+SUM(START:END!I8) -> 0 | J8: =+SUM(START:END!J8) -> 0 | K8: =IF(J8=0,0,L8/J8) -> 0 | L8: =+SUM(START:END!L8) -> 0 | M8: =J8-D8 -> 0 | N8: =L8-F8 -> 0 | O8: =+SUM(START:END!O8) -> 0 | P8: =IF(O8=0,0,Q8/O8) -> 0 | Q8: =+SUM(START:END!Q8) -> 0 | R8: =J8-O8 -> 0 | S8: =L8-Q8 -> 0
A9: =+B9&C9 -> Véhicules neufsMoto détail | B9: =+$K$1 -> Véhicules neufs | C9: Moto détail | D9: =+SUM(START:END!D9) -> 0 | E9: =IF(D9=0,0,F9/D9) -> 0 | F9: =+SUM(START:END!F9) -> 0 | G9: =+SUM(START:END!G9) -> 0 | H9: =IF(G9=0,0,I9/G9) -> 0 | I9: =+SUM(START:END!I9) -> 0 | J9: =+SUM(START:END!J9) -> 0 | K9: =IF(J9=0,0,L9/J9) -> 0 | L9: =+SUM(START:END!L9) -> 0 | M9: =J9-D9 -> 0 | N9: =L9-F9 -> 0 | O9: =+SUM(START:END!O9) -> 0 | P9: =IF(O9=0,0,Q9/O9) -> 0 | Q9: =+SUM(START:END!Q9) -> 0 | R9: =J9-O9 -> 0 | S9: =L9-Q9 -> 0
A10: =+B10&C10 -> Véhicules neufs[...] | B10: =+$K$1 -> Véhicules neufs | C10: [...] | D10: =+SUM(START:END!D10) -> 0 | E10: =IF(D10=0,0,F10/D10) -> 0 | F10: =+SUM(START:END!F10) -> 0 | G10: =+SUM(START:END!G10) -> 0 | H10: =IF(G10=0,0,I10/G10) -> 0 | I10: =+SUM(START:END!I10) -> 0 | J10: =+SUM(START:END!J10) -> 0 | K10: =IF(J10=0,0,L10/J10) -> 0 | L10: =+SUM(START:END!L10) -> 0 | M10: =J10-D10 -> 0 | N10: =L10-F10 -> 0 | O10: =+SUM(START:END!O10) -> 0 | P10: =IF(O10=0,0,Q10/O10) -> 0 | Q10: =+SUM(START:END!Q10) -> 0 | R10: =J10-O10 -> 0 | S10: =L10-Q10 -> 0
A11: =+B11&C11 -> Véhicules neufs[...] | B11: =+$K$1 -> Véhicules neufs | C11: [...] | D11: =+SUM(START:END!D11) -> 0 | E11: =IF(D11=0,0,F11/D11) -> 0 | F11: =+SUM(START:END!F11) -> 0 | G11: =+SUM(START:END!G11) -> 0 | H11: =IF(G11=0,0,I11/G11) -> 0 | I11: =+SUM(START:END!I11) -> 0 | J11: =+SUM(START:END!J11) -> 0 | K11: =IF(J11=0,0,L11/J11) -> 0 | L11: =+SUM(START:END!L11) -> 0 | M11: =J11-D11 -> 0 | N11: =L11-F11 -> 0 | O11: =+SUM(START:END!O11) -> 0 | P11: =IF(O11=0,0,Q11/O11) -> 0 | Q11: =+SUM(START:END!Q11) -> 0 | R11: =J11-O11 -> 0 | S11: =L11-Q11 -> 0
A12: =+B12&C12 -> Véhicules neufs[...] | B12: =+$K$1 -> Véhicules neufs | C12: [...] | D12: =+SUM(START:END!D12) -> 0 | E12: =IF(D12=0,0,F12/D12) -> 0 | F12: =+SUM(START:END!F12) -> 0 | G12: =+SUM(START:END!G12) -> 0 | H12: =IF(G12=0,0,I12/G12) -> 0 | I12: =+SUM(START:END!I12) -> 0 | J12: =+SUM(START:END!J12) -> 0 | K12: =IF(J12=0,0,L12/J12) -> 0 | L12: =+SUM(START:END!L12) -> 0 | M12: =J12-D12 -> 0 | N12: =L12-F12 -> 0 | O12: =+SUM(START:END!O12) -> 0 | P12: =IF(O12=0,0,Q12/O12) -> 0 | Q12: =+SUM(START:END!Q12) -> 0 | R12: =J12-O12 -> 0 | S12: =L12-Q12 -> 0
A13: =+B13&C13 -> Véhicules neufsTotal Neufs | B13: =+$K$1 -> Véhicules neufs | C13: Total Neufs | D13: =+SUM(D6:D12) -> 156.09037 | E13: =IF(D13<=0,0,F13/D13) -> 2442.7446 | F13: =+SUM(F6:F12) -> 381288.91 | G13: =+SUM(G6:G12) -> 0 | H13: =IF(G13<=0,0,I13/G13) -> 0 | I13: =+SUM(I6:I12) -> 0 | J13: =+SUM(J6:J12) -> 132 | K13: =IF(J13<=0,0,L13/J13) -> 2375.9107 | L13: =+SUM(L6:L12) -> 313620.21 | M13: =+SUM(M6:M12) -> -24.090369 | N13: =+SUM(N6:N12) -> -67668.699 | O13: =+SUM(O6:O12) -> 170 | P13: =IF(O13<=0,0,Q13/O13) -> 2821.0057 | Q13: =+SUM(Q6:Q12) -> 479570.97 | R13: =+SUM(R6:R12) -> -38 | S13: =+SUM(S6:S12) -> -165950.76
A14: =+B14&C14 -> Véhicules neufs | B14: =+$K$1 -> Véhicules neufs | M14: =IF(D13=0,0,M13/D13) -> -0.15433604 | N14: =IF(F13=0,0,N13/F13) -> -0.17747356 | R14: =R13/O13 -> -0.22352941 | S14: =IF(Q13=0,0,(S13/Q13)) -> -0.34604004
A15: =+B15&C15 -> Véhicules neufsEx-Démos et courtoisies | B15: =+$K$1 -> Véhicules neufs | C15: Ex-Démos et courtoisies | D15: =+SUM(START:END!D15) -> 7.4571429 | E15: =IF(D15=0,0,F15/D15) -> 2442.5492 | F15: =+SUM(START:END!F15) -> 18214.438 | G15: =+SUM(START:END!G15) -> 0 | H15: =IF(G15=0,0,I15/G15) -> 0 | I15: =+SUM(START:END!I15) -> 0 | J15: =+SUM(START:END!J15) -> 12 | K15: =IF(J15=0,0,L15/J15) -> 1085.3925 | L15: =+SUM(START:END!L15) -> 13024.71 | M15: =J15-D15 -> 4.5428571 | N15: =L15-F15 -> -5189.7283 | O15: =+SUM(START:END!O15) -> 6 | P15: =IF(O15=0,0,Q15/O15) -> 3041.8483 | Q15: =+SUM(START:END!Q15) -> 18251.09 | R15: =J15-O15 -> 6 | S15: =L15-Q15 -> -5226.38
A16: =+B16&C16 -> Véhicules neufs | B16: =+$K$1 -> Véhicules neufs
A17: =+B17&C17 -> Véhicules neufsFlottes | B17: =+$K$1 -> Véhicules neufs | C17: Flottes | D17: =+SUM(START:END!D17) -> 5.9657143 | E17: =IF(D17=0,0,F17/D17) -> 2442.5492 | F17: =+SUM(START:END!F17) -> 14571.551 | G17: =+SUM(START:END!G17) -> 0 | H17: =IF(G17=0,0,I17/G17) -> 0 | I17: =+SUM(START:END!I17) -> 0 | J17: =+SUM(START:END!J17) -> 6 | K17: =IF(J17=0,0,L17/J17) -> 3562.0233 | L17: =+SUM(START:END!L17) -> 21372.14 | M17: =J17-D17 -> 0.034285714 | N17: =L17-F17 -> 6800.5893 | O17: =+SUM(START:END!O17) -> 9 | P17: =IF(O17=0,0,Q17/O17) -> 2185.0778 | Q17: =+SUM(START:END!Q17) -> 19665.7 | R17: =J17-O17 -> -3 | S17: =L17-Q17 -> 1706.44
A18: =+B18&C18 -> Véhicules neufs | B18: =+$K$1 -> Véhicules neufs
A19: =+B19&C19 -> Véhicules neufsRachat bail | B19: =+$K$1 -> Véhicules neufs | C19: Rachat bail | F19: =+SUM(START:END!F19) -> 23040 | I19: =+SUM(START:END!I19) -> 0 | L19: =+SUM(START:END!L19) -> 25661.02 | N19: =L19-F19 -> 2621.02 | Q19: =+SUM(START:END!Q19) -> 47656.29 | R19: =O19-K19 -> 0 | S19: =L19-Q19 -> -21995.27
A20: =+B20&C20 -> Véhicules neufs | B20: =+$K$1 -> Véhicules neufs
A21: =+B21&C21 -> Véhicules neufsRev. Finances | B21: =+$K$1 -> Véhicules neufs | C21: Rev. Finances | D21: 0 | E21: =IF(D21=0,0,F21/D21) -> 0 | F21: =+SUM(START:END!F21) -> 28130.172 | G21: 0 | H21: =IF(G21=0,0,I21/G21) -> 0 | I21: =+SUM(START:END!I21) -> 0 | K21: =IF(J13=0,0,L21/(J13+J15)) -> 163.83465 | L21: =+SUM(START:END!L21) -> 23592.19 | N21: =L21-F21 -> -4537.982 | P21: =IF(O13=0,0,Q21/(O13+O15)) -> 194.34903 | Q21: =+SUM(START:END!Q21) -> 34205.43 | R21: =O21-K21 -> -163.83465 | S21: =L21-Q21 -> -10613.24
A22: =+B22&C22 -> Véhicules neufsRev. Protections | B22: =+$K$1 -> Véhicules neufs | C22: Rev. Protections | D22: 0 | E22: =IF(D22=0,0,F22/D22) -> 0 | F22: =+SUM(START:END!F22) -> 154715.95 | G22: 0 | H22: =IF(G22=0,0,I22/G22) -> 0 | I22: =+SUM(START:END!I22) -> 0 | K22: =IF(J13=0,0,L22/(J13+J15)) -> 1082.3578 | L22: =+SUM(START:END!L22) -> 155859.52 | N22: =L22-F22 -> 1143.5739 | P22: =IF(O13=0,0,Q22/(O13+O15)) -> 896.49438 | Q22: =+SUM(START:END!Q22) -> 157783.01 | R22: =O22-K22 -> -1082.3578 | S22: =L22-Q22 -> -1923.49
A23: =+B23&C23 -> Véhicules neufsRev. Autres | B23: =+$K$1 -> Véhicules neufs | C23: Rev. Autres | D23: 0 | E23: =IF(D23=0,0,F23/D23) -> 0 | F23: =+SUM(START:END!F23) -> 4742.8778 | G23: 0 | H23: =IF(G23=0,0,I23/G23) -> 0 | I23: =+SUM(START:END!I23) -> 0 | K23: =IF(J13=0,0,L23/(J13+J15)) -> 8.1495833 | L23: =+SUM(START:END!L23) -> 1173.54 | N23: =L23-F23 -> -3569.3378 | P23: =IF(O13=0,0,Q23/(O13+O15)) -> 24.29125 | Q23: =+SUM(START:END!Q23) -> 4275.26 | R23: =O23-K23 -> -8.1495833 | S23: =L23-Q23 -> -3101.72
A24: =+B24&C24 -> Véhicules neufsTotal F&I | B24: =+$K$1 -> Véhicules neufs | C24: Total F&I | D24: =+D15+D13 -> 163.54751 | E24: =IF(D24<=0,0,F24/D24) -> 1147 | F24: =F21+F22+F23 -> 187589 | G24: =+G15+G13 -> 0 | H24: =IF(G24<=0,0,I24/G24) -> 0 | I24: =I21+I22+I23 -> 0 | J24: =+J15+J13 -> 144 | K24: =IF(J24<=0,0,L24/J24) -> 1254.342 | L24: =L21+L22+L23 -> 180625.25 | M24: =J24-D24 -> -19.547512 | N24: =L24-F24 -> -6963.746 | O24: =+O15+O13 -> 176 | P24: =IF(O24<=0,0,Q24/O24) -> 1115.1347 | Q24: =Q21+Q22+Q23 -> 196263.7 | S24: =L24-Q24 -> -15638.45
A25: =+B25&C25 -> Véhicules neufs | B25: =+$K$1 -> Véhicules neufs | N25: =IF(N24=0,0,N24/F24) -> -0.037122359 | S25: =IF(Q24=0,0,(S24/Q24)) -> -0.079680807
A26: =+B26&C26 -> Véhicules neufs | B26: =+$K$1 -> Véhicules neufs
A27: =+B27&C27 -> Véhicules neufsTotal Dépt. Neufs | B27: =+$K$1 -> Véhicules neufs | C27: Total Dépt. Neufs | D27: =+D13+D15+D17 -> 169.51323 | E27: =IF(D27<=0,0,F27/D27) -> 3685.2811 | F27: =F13+F17+F24+F19+F15 -> 624703.89 | G27: =+G13+G15+G17 -> 0 | H27: =IF(G27<=0,0,I27/G27) -> 0 | I27: =I13+I17+I24+I19+I15 -> 0 | J27: =+J13+J15+J17 -> 150 | K27: =IF(J27<=0,0,L27/J27) -> 3695.3555 | L27: =L13+L17+L24+L19+L15 -> 554303.33 | M27: =J27-D27 -> -19.513226 | N27: =L27-F27 -> -70400.564 | O27: =+O13+O15+O17 -> 185 | P27: =IF(O27<=0,0,Q27/O27) -> 4115.7176 | Q27: =Q13+Q17+Q24+Q19+Q15 -> 761407.75 | R27: =J27-O27 -> -35 | S27: =L27-Q27 -> -207104.42
A28: =+B28&C28 -> Véhicules neufs | B28: =+$K$1 -> Véhicules neufs | M28: =M27/D27 -> -0.1151133 | N28: =N27/F27 -> -0.11269429 | R28: =R27/O27 -> -0.18918919 | S28: =IF(Q27=0,0,S27/Q27) -> -0.27200199
A29: =+B29&C29 -> Véhicules neufs | B29: =+$K$1 -> Véhicules neufs
A30: =+B30&C30 -> Véhicules neufsDEPENSES | B30: =+$K$1 -> Véhicules neufs | C30: DEPENSES
A31: =+B31&C31 -> Véhicules neufsComm. vendeurs | B31: =+$K$1 -> Véhicules neufs | C31: Comm. vendeurs | E31: =F31/D$24 -> 769.7587 | F31: =+SUM(START:END!F31) -> 125892.12 | H31: =I31/G$24 -> #DIV/0! | I31: =+SUM(START:END!I31) -> 0 | J31: =L31/L13 -> 0.3139336 | K31: =IF(L31=0,0,L31/J$24) -> 683.72167 | L31: =+SUM(START:END!L31) -> 98455.92 | N31: =L31-F31 -> -27436.2 | P31: =IF(Q31=0,0,Q31/O$24) -> 820.38722 | Q31: =+SUM(START:END!Q31) -> 144388.15 | S31: =L31-Q31 -> -45932.23
A32: =+B32&C32 -> Véhicules neufsComm. F&I | B32: =+$K$1 -> Véhicules neufs | C32: Comm. F&I | E32: =F32/D$24 -> 344.1 | F32: =+SUM(START:END!F32) -> 56276.699 | H32: =I32/G$24 -> #DIV/0! | I32: =+SUM(START:END!I32) -> 0 | J32: =L32/L24 -> 0.30029207 | K32: =IF(L32=0,0,L32/J$24) -> 376.66896 | L32: =+SUM(START:END!L32) -> 54240.33 | N32: =L32-F32 -> -2036.3688 | P32: =IF(Q32=0,0,Q32/O$24) -> 393.62602 | Q32: =+SUM(START:END!Q32) -> 69278.18 | S32: =L32-Q32 -> -15037.85
A33: =+B33&C33 -> Véhicules neufsFrais de livraison | B33: =+$K$1 -> Véhicules neufs | C33: Frais de livraison | E33: =F33/D$24 -> 113.25898 | F33: =+SUM(START:END!F33) -> 18523.224 | H33: =I33/G$24 -> #DIV/0! | I33: =+SUM(START:END!I33) -> 0 | K33: =IF(L33=0,0,L33/J$24) -> 120.79181 | L33: =+SUM(START:END!L33) -> 17394.02 | N33: =L33-F33 -> -1129.2038 | P33: =IF(Q33=0,0,Q33/O$24) -> 47.600852 | Q33: =+SUM(START:END!Q33) -> 8377.75 | S33: =L33-Q33 -> 9016.27
A34: =+B34&C34 -> Véhicules neufsService gratuit 1 | B34: =+$K$1 -> Véhicules neufs | C34: Service gratuit 1 | E34: =F34/D$24 -> 5.1177856 | F34: =+SUM(START:END!F34) -> 837.00111 | H34: =I34/G$24 -> #DIV/0! | I34: =+SUM(START:END!I34) -> 0 | K34: =IF(L34=0,0,L34/J$24) -> 2.4093056 | L34: =+SUM(START:END!L34) -> 346.94 | N34: =L34-F34 -> -490.06111 | P34: =IF(Q34=0,0,Q34/O$24) -> 1.2465341 | Q34: =+SUM(START:END!Q34) -> 219.39 | S34: =L34-Q34 -> 127.55
A35: =+B35&C35 -> Véhicules neufsEntretien stock | B35: =+$K$1 -> Véhicules neufs | C35: Entretien stock | E35: =F35/D$24 -> 105.01044 | F35: =+SUM(START:END!F35) -> 17174.197 | H35: =I35/G$24 -> #DIV/0! | I35: =+SUM(START:END!I35) -> 0 | K35: =IF(L35=0,0,L35/J$24) -> 89.936389 | L35: =+SUM(START:END!L35) -> 12950.84 | N35: =L35-F35 -> -4223.3567 | P35: =IF(Q35=0,0,Q35/O$24) -> 98.528693 | Q35: =+SUM(START:END!Q35) -> 17341.05 | S35: =L35-Q35 -> -4390.21
A36: =+B36&C36 -> Véhicules neufsPublicité 1 | B36: =+$K$1 -> Véhicules neufs | C36: Publicité 1 | E36: =F36/D$24 -> 300.75552 | F36: =+SUM(START:END!F36) -> 49187.817 | H36: =I36/G$24 -> #DIV/0! | I36: =+SUM(START:END!I36) -> 0 | K36: =IF(L36=0,0,L36/J$24) -> 94.534722 | L36: =+SUM(START:END!L36) -> 13613 | N36: =L36-F36 -> -35574.817 | P36: =IF(Q36=0,0,Q36/O$24) -> 87.593295 | Q36: =+SUM(START:END!Q36) -> 15416.42 | S36: =L36-Q36 -> -1803.42
A37: =+B37&C37 -> Véhicules neufsIntérêt de gros | B37: =+$K$1 -> Véhicules neufs | C37: Intérêt de gros | E37: =F37/D$24 -> 56.151613 | F37: =+SUM(START:END!F37) -> 9183.4566 | H37: =I37/G$24 -> #DIV/0! | I37: =+SUM(START:END!I37) -> 0 | K37: =IF(L37=0,0,L37/J$24) -> 60.152292 | L37: =+SUM(START:END!L37) -> 8661.93 | N37: =L37-F37 -> -521.52657 | P37: =IF(Q37=0,0,Q37/O$24) -> 57.844545 | Q37: =+SUM(START:END!Q37) -> 10180.64 | S37: =L37-Q37 -> -1518.71
A38: =+B38&C38 -> Véhicules neufs[...] | B38: =+$K$1 -> Véhicules neufs | C38: [...] | E38: =F38/D$24 -> 0 | F38: =+SUM(START:END!F38) -> 0 | H38: =I38/G$24 -> #DIV/0! | I38: =+SUM(START:END!I38) -> 0 | K38: =IF(L38=0,0,L38/J$24) -> 0 | L38: =+SUM(START:END!L38) -> 0 | N38: =L38-F38 -> 0 | P38: =IF(Q38=0,0,Q38/O$24) -> 0 | Q38: =+SUM(START:END!Q38) -> 0 | S38: =L38-Q38 -> 0
A39: =+B39&C39 -> Véhicules neufs[...] | B39: =+$K$1 -> Véhicules neufs | C39: [...] | E39: =F39/D$24 -> 0 | F39: =+SUM(START:END!F39) -> 0 | H39: =I39/G$24 -> #DIV/0! | I39: =+SUM(START:END!I39) -> 0 | K39: =IF(L39=0,0,L39/J$24) -> 0 | L39: =+SUM(START:END!L39) -> 0 | N39: =L39-F39 -> 0 | P39: =IF(Q39=0,0,Q39/O$24) -> 0 | Q39: =+SUM(START:END!Q39) -> 0 | S39: =L39-Q39 -> 0
A40: =+B40&C40 -> Véhicules neufs[...] | B40: =+$K$1 -> Véhicules neufs | C40: [...] | E40: =F40/D$24 -> 0 | F40: =+SUM(START:END!F40) -> 0 | H40: =I40/G$24 -> #DIV/0! | I40: =+SUM(START:END!I40) -> 0 | K40: =IF(L40=0,0,L40/J$24) -> 0 | L40: =+SUM(START:END!L40) -> 0 | N40: =L40-F40 -> 0 | P40: =IF(Q40=0,0,Q40/O$24) -> 0 | Q40: =+SUM(START:END!Q40) -> 0 | S40: =L40-Q40 -> 0
A41: =+B41&C41 -> Véhicules neufsTOTAL VARIABLES | B41: =+$K$1 -> Véhicules neufs | C41: TOTAL VARIABLES | D41: % brut | E41: =F41/F$27 -> 0.44352935 | F41: =SUM(F31:F40) -> 277074.51 | G41: % brut | H41: =I41/I$27 -> #DIV/0! | I41: =SUM(I31:I40) -> 0 | J41: % brut | K41: =L41/L$27 -> 0.37102967 | L41: =SUM(L31:L40) -> 205662.98 | N41: =L41-F41 -> -71411.534 | O41: % brut | P41: =Q41/Q$27 -> 0.34830428 | Q41: =SUM(Q31:Q40) -> 265201.58 | S41: =L41-Q41 -> -59538.6
A42: =+B42&C42 -> Véhicules neufsSalaires cadres | B42: =+$K$1 -> Véhicules neufs | C42: Salaires cadres | F42: =+SUM(START:END!F42) -> 51877.49 | G42: =I41/(I27+I83) -> #DIV/0! | I42: =+SUM(START:END!I42) -> 0 | L42: =+SUM(START:END!L42) -> 46357.07 | N42: =L42-F42 -> -5520.4197 | Q42: =+SUM(START:END!Q42) -> 56096.98 | S42: =L42-Q42 -> -9739.91
A43: =+B43&C43 -> Véhicules neufsSalaires commis | B43: =+$K$1 -> Véhicules neufs | C43: Salaires commis | F43: =+SUM(START:END!F43) -> 30673.912 | I43: =+SUM(START:END!I43) -> 0 | L43: =+SUM(START:END!L43) -> 37677.03 | N43: =L43-F43 -> 7003.1183 | Q43: =+SUM(START:END!Q43) -> 21785.59 | S43: =L43-Q43 -> 15891.44
A44: =+B44&C44 -> Véhicules neufsSalaires autres | B44: =+$K$1 -> Véhicules neufs | C44: Salaires autres | F44: =+SUM(START:END!F44) -> 24626.952 | I44: =+SUM(START:END!I44) -> 0 | L44: =+SUM(START:END!L44) -> 29983.23 | N44: =L44-F44 -> 5356.2783 | Q44: =+SUM(START:END!Q44) -> 12958.3 | S44: =L44-Q44 -> 17024.93
A45: =+B45&C45 -> Véhicules neufsSalaires spécialistes | B45: =+$K$1 -> Véhicules neufs | C45: Salaires spécialistes | F45: =+SUM(START:END!F45) -> 0 | I45: =+SUM(START:END!I45) -> 0 | L45: =+SUM(START:END!L45) -> 0 | N45: =L45-F45 -> 0 | Q45: =+SUM(START:END!Q45) -> 0 | S45: =L45-Q45 -> 0
A46: =+B46&C46 -> Véhicules neufs[...] | B46: =+$K$1 -> Véhicules neufs | C46: [...] | F46: =+SUM(START:END!F46) -> 0 | I46: =+SUM(START:END!I46) -> 0 | L46: =+SUM(START:END!L46) -> 0 | N46: =L46-F46 -> 0 | Q46: =+SUM(START:END!Q46) -> 0 | S46: =L46-Q46 -> 0
A47: =+B47&C47 -> Véhicules neufs[...] | B47: =+$K$1 -> Véhicules neufs | C47: [...] | F47: =+SUM(START:END!F47) -> 0 | I47: =+SUM(START:END!I47) -> 0 | L47: =+SUM(START:END!L47) -> 0 | N47: =L47-F47 -> 0 | Q47: =+SUM(START:END!Q47) -> 0 | S47: =L47-Q47 -> 0
A48: =+B48&C48 -> Véhicules neufs[...] | B48: =+$K$1 -> Véhicules neufs | C48: [...] | F48: =+SUM(START:END!F48) -> 0 | I48: =+SUM(START:END!I48) -> 0 | L48: =+SUM(START:END!L48) -> 0 | N48: =L48-F48 -> 0 | Q48: =+SUM(START:END!Q48) -> 0 | S48: =L48-Q48 -> 0
A49: =+B49&C49 -> Véhicules neufsSalaires en absences | B49: =+$K$1 -> Véhicules neufs | C49: Salaires en absences | F49: =+SUM(START:END!F49) -> 35051.054 | I49: =+SUM(START:END!I49) -> 0 | L49: =+SUM(START:END!L49) -> 27193.29 | N49: =L49-F49 -> -7857.7636 | Q49: =+SUM(START:END!Q49) -> 51999.4 | S49: =L49-Q49 -> -24806.11
A50: =+B50&C50 -> Véhicules neufsDéduction à la source | B50: =+$K$1 -> Véhicules neufs | C50: Déduction à la source | F50: =+SUM(START:END!F50) -> 34844.198 | I50: =+SUM(START:END!I50) -> 0 | L50: =+SUM(START:END!L50) -> 35459.68 | N50: =L50-F50 -> 615.48165 | Q50: =+SUM(START:END!Q50) -> 49227.53 | S50: =L50-Q50 -> -13767.85
A51: =+B51&C51 -> Véhicules neufsBénéfices marginaux | B51: =+$K$1 -> Véhicules neufs | C51: Bénéfices marginaux | F51: =+SUM(START:END!F51) -> 24399.93 | I51: =+SUM(START:END!I51) -> 0 | L51: =+SUM(START:END!L51) -> 19135 | N51: =L51-F51 -> -5264.9298 | Q51: =+SUM(START:END!Q51) -> 18228.37 | S51: =L51-Q51 -> 906.63
A52: =+B52&C52 -> Véhicules neufsCsst | B52: =+$K$1 -> Véhicules neufs | C52: Csst | F52: =+SUM(START:END!F52) -> 11656.55 | I52: =+SUM(START:END!I52) -> 0 | L52: =+SUM(START:END!L52) -> 5668.88 | N52: =L52-F52 -> -5987.6698 | Q52: =+SUM(START:END!Q52) -> 10960.38 | S52: =L52-Q52 -> -5291.5
A53: =+B53&C53 -> Véhicules neufs[...] | B53: =+$K$1 -> Véhicules neufs | C53: [...] | F53: =+SUM(START:END!F53) -> 0 | I53: =+SUM(START:END!I53) -> 0 | L53: =+SUM(START:END!L53) -> 0 | N53: =L53-F53 -> 0 | Q53: =+SUM(START:END!Q53) -> 0 | S53: =L53-Q53 -> 0
A54: =+B54&C54 -> Véhicules neufsTOTAL PERSONNEL | B54: =+$K$1 -> Véhicules neufs | C54: TOTAL PERSONNEL | D54: % brut | E54: =F54/F$27 -> 0.34116977 | F54: =+SUM(F42:F53) -> 213130.08 | G54: % brut | H54: =I54/I$27 -> #DIV/0! | I54: =+SUM(I42:I53) -> 0 | J54: % brut | K54: =L54/L$27 -> 0.36347279 | L54: =+SUM(L42:L53) -> 201474.18 | N54: =+SUM(N42:N53) -> -11655.905 | O54: % brut | P54: =Q54/Q$27 -> 0.29058878 | Q54: =+SUM(Q42:Q53) -> 221256.55 | S54: =+SUM(S42:S53) -> -19782.37
A55: =+B55&C55 -> Véhicules neufsPublicité 2 | B55: =+$K$1 -> Véhicules neufs | C55: Publicité 2 | F55: =+SUM(START:END!F55) -> 0 | G55: =I54/(I27+I83) -> #DIV/0! | I55: =+SUM(START:END!I55) -> 0 | L55: =+SUM(START:END!L55) -> 0 | N55: =L55-F55 -> 0 | Q55: =+SUM(START:END!Q55) -> 0 | S55: =L55-Q55 -> 0
A56: =+B56&C56 -> Véhicules neufsService gratuit 2 | B56: =+$K$1 -> Véhicules neufs | C56: Service gratuit 2 | F56: =+SUM(START:END!F56) -> 0 | I56: =+SUM(START:END!I56) -> 0 | L56: =+SUM(START:END!L56) -> 0 | N56: =L56-F56 -> 0 | Q56: =+SUM(START:END!Q56) -> 0 | S56: =L56-Q56 -> 0
A57: =+B57&C57 -> Véhicules neufsFrais véhicules de cie | B57: =+$K$1 -> Véhicules neufs | C57: Frais véhicules de cie | F57: =+SUM(START:END!F57) -> 23837.5 | I57: =+SUM(START:END!I57) -> 0 | L57: =+SUM(START:END!L57) -> 15156.03 | N57: =L57-F57 -> -8681.47 | Q57: =+SUM(START:END!Q57) -> 24962.74 | S57: =L57-Q57 -> -9806.71
A58: =+B58&C58 -> Véhicules neufsInformatique | B58: =+$K$1 -> Véhicules neufs | C58: Informatique | F58: =+SUM(START:END!F58) -> 18782.599 | I58: =+SUM(START:END!I58) -> 0 | L58: =+SUM(START:END!L58) -> 21049.43 | N58: =L58-F58 -> 2266.8308 | Q58: =+SUM(START:END!Q58) -> 23611.17 | S58: =L58-Q58 -> -2561.74
A59: =+B59&C59 -> Véhicules neufsFrais de déplacement | B59: =+$K$1 -> Véhicules neufs | C59: Frais de déplacement | F59: =+SUM(START:END!F59) -> 3000.2641 | I59: =+SUM(START:END!I59) -> 0 | L59: =+SUM(START:END!L59) -> 3704.1 | N59: =L59-F59 -> 703.83587 | Q59: =+SUM(START:END!Q59) -> 3663.08 | S59: =L59-Q59 -> 41.02
A60: =+B60&C60 -> Véhicules neufsServices extérieurs | B60: =+$K$1 -> Véhicules neufs | C60: Services extérieurs | F60: =+SUM(START:END!F60) -> 19831.396 | I60: =+SUM(START:END!I60) -> 0 | L60: =+SUM(START:END!L60) -> 18587.6 | N60: =L60-F60 -> -1243.796 | Q60: =+SUM(START:END!Q60) -> 20308.14 | S60: =L60-Q60 -> -1720.54
A61: =+B61&C61 -> Véhicules neufsFournitures autres | B61: =+$K$1 -> Véhicules neufs | C61: Fournitures autres | F61: =+SUM(START:END!F61) -> 366.73155 | I61: =+SUM(START:END!I61) -> 0 | L61: =+SUM(START:END!L61) -> 141.18 | N61: =L61-F61 -> -225.55155 | Q61: =+SUM(START:END!Q61) -> 154.98 | S61: =L61-Q61 -> -13.8
A62: =+B62&C62 -> Véhicules neufsUniformes | B62: =+$K$1 -> Véhicules neufs | C62: Uniformes | F62: =+SUM(START:END!F62) -> 189.37599 | I62: =+SUM(START:END!I62) -> 0 | L62: =+SUM(START:END!L62) -> 0 | N62: =L62-F62 -> -189.37599 | Q62: =+SUM(START:END!Q62) -> 0 | S62: =L62-Q62 -> 0
A63: =+B63&C63 -> Véhicules neufsPapeterie | B63: =+$K$1 -> Véhicules neufs | C63: Papeterie | F63: =+SUM(START:END!F63) -> 2290.3531 | I63: =+SUM(START:END!I63) -> 0 | L63: =+SUM(START:END!L63) -> 2345.81 | N63: =L63-F63 -> 55.456894 | Q63: =+SUM(START:END!Q63) -> 2582.64 | S63: =L63-Q63 -> -236.83
A64: =+B64&C64 -> Véhicules neufsTéléphone | B64: =+$K$1 -> Véhicules neufs | C64: Téléphone | F64: =+SUM(START:END!F64) -> 776.16075 | I64: =+SUM(START:END!I64) -> 0 | L64: =+SUM(START:END!L64) -> 1125.53 | N64: =L64-F64 -> 349.36925 | Q64: =+SUM(START:END!Q64) -> 761.74 | S64: =L64-Q64 -> 363.79
A65: =+B65&C65 -> Véhicules neufsFrais postaux | B65: =+$K$1 -> Véhicules neufs | C65: Frais postaux | F65: =+SUM(START:END!F65) -> 371.23288 | I65: =+SUM(START:END!I65) -> 0 | L65: =+SUM(START:END!L65) -> 367.13 | N65: =L65-F65 -> -4.1028815 | Q65: =+SUM(START:END!Q65) -> 486.82 | S65: =L65-Q65 -> -119.69
A66: =+B66&C66 -> Véhicules neufsDivers | B66: =+$K$1 -> Véhicules neufs | C66: Divers | F66: =+SUM(START:END!F66) -> 1410.5471 | I66: =+SUM(START:END!I66) -> 0 | L66: =+SUM(START:END!L66) -> 418.79 | N66: =L66-F66 -> -991.75709 | Q66: =+SUM(START:END!Q66) -> 354.51 | S66: =L66-Q66 -> 64.28
A67: =+B67&C67 -> Véhicules neufsFormation | B67: =+$K$1 -> Véhicules neufs | C67: Formation | F67: =+SUM(START:END!F67) -> 1838.2209 | I67: =+SUM(START:END!I67) -> 0 | L67: =+SUM(START:END!L67) -> 2653.16 | N67: =L67-F67 -> 814.93909 | Q67: =+SUM(START:END!Q67) -> 3451.57 | S67: =L67-Q67 -> -798.41
... A71: =+B71&C71 -> Véhicules neufs[...] | B71: =+$K$1 -> Véhicules neufs | C71: [...] | F71: =+SUM(START:END!F71) -> 0 | I71: =+SUM(START:END!I71) -> 0 | L71: =+SUM(START:END!L71) -> 0 | N71: =L71-F71 -> 0 | Q71: =+SUM(START:END!Q71) -> 0 | S71: =L71-Q71 -> 0
A72: =+B72&C72 -> Véhicules neufsTOTAL SEMI-FIXES | B72: =+$K$1 -> Véhicules neufs | C72: TOTAL SEMI-FIXES | D72: % brut | E72: =F72/F$27 -> 0.12167474 | F72: =+SUM(F55:F71) -> 76010.681 | G72: % brut | H72: =I72/I$27 -> #DIV/0! | I72: =+SUM(I55:I71) -> 0 | J72: % brut | K72: =L72/L$27 -> 0.13569933 | L72: =+SUM(L55:L71) -> 75218.59 | N72: =+SUM(N55:N71) -> -792.09144 | O72: % brut | P72: =Q72/Q$27 -> 0.12031035 | Q72: =+SUM(Q55:Q71) -> 91605.233 | S72: =+SUM(S55:S71) -> -16386.643
A73: =+B73&C73 -> Véhicules neufs | B73: =+$K$1 -> Véhicules neufs
A74: =+B74&C74 -> Véhicules neufsTOTAL DES DÉPENSES | B74: =+$K$1 -> Véhicules neufs | C74: TOTAL DES DÉPENSES | D74: % brut | E74: =F74/F$27 -> 0.90637386 | F74: =F41+F54+F72 -> 566215.28 | G74: % brut | H74: =I74/I$27 -> #DIV/0! | I74: =I41+I54+I72 -> 0 | J74: % brut | K74: =L74/L$27 -> 0.87020179 | L74: =L41+L54+L72 -> 482355.75 | N74: =L74-F74 -> -83859.53 | O74: % brut | P74: =Q74/Q$27 -> 0.75920341 | Q74: =Q41+Q54+Q72 -> 578063.36 | S74: =L74-Q74 -> -95707.613
A75: =+B75&C75 -> Véhicules neufsProgramme neuf 1 | B75: =+$K$1 -> Véhicules neufs | C75: Programme neuf 1 | F75: =+SUM(START:END!F75) -> 15729.13 | I75: =+SUM(START:END!I75) -> 0 | L75: =+SUM(START:END!L75) -> 0 | N75: =L75-F75 -> -15729.13 | Q75: =+SUM(START:END!Q75) -> 0
A76: =+B76&C76 -> Véhicules neufsProgramme neuf 2 | B76: =+$K$1 -> Véhicules neufs | C76: Programme neuf 2 | F76: =+SUM(START:END!F76) -> 0 | I76: =+SUM(START:END!I76) -> 0 | L76: =+SUM(START:END!L76) -> 0 | N76: =L76-F76 -> 0 | Q76: =+SUM(START:END!Q76) -> 0 | S76: =L76-Q76 -> 0
A77: =+B77&C77 -> Véhicules neufsProgramme neuf 3 | B77: =+$K$1 -> Véhicules neufs | C77: Programme neuf 3 | F77: =+SUM(START:END!F77) -> 0 | I77: =+SUM(START:END!I77) -> 0 | L77: =+SUM(START:END!L77) -> 0 | N77: =L77-F77 -> 0 | Q77: =+SUM(START:END!Q77) -> 0 | S77: =L77-Q77 -> 0
A78: =+B78&C78 -> Véhicules neufsHoldbacks | B78: =+$K$1 -> Véhicules neufs | C78: Holdbacks | F78: =+SUM(START:END!F78) -> 193205.5 | I78: =+SUM(START:END!I78) -> 0 | L78: =+SUM(START:END!L78) -> 161519.4 | N78: =L78-F78 -> -31686.098 | Q78: =+SUM(START:END!Q78) -> 233500.07 | S78: =L78-Q78 -> -71980.67
A79: =+B79&C79 -> Véhicules neufs[...] | B79: =+$K$1 -> Véhicules neufs | C79: [...] | F79: =+SUM(START:END!F79) -> 0 | I79: =+SUM(START:END!I79) -> 0 | L79: =+SUM(START:END!L79) -> 0 | N79: =L79-F79 -> 0 | Q79: =+SUM(START:END!Q79) -> 0 | S79: =L79-Q79 -> 0
A80: =+B80&C80 -> Véhicules neufs[...] | B80: =+$K$1 -> Véhicules neufs | C80: [...] | F80: =+SUM(START:END!F80) -> 0 | I80: =+SUM(START:END!I80) -> 0 | L80: =+SUM(START:END!L80) -> 0 | N80: =L80-F80 -> 0 | Q80: =+SUM(START:END!Q80) -> 0 | S80: =L80-Q80 -> 0
A81: =+B81&C81 -> Véhicules neufs[...] | B81: =+$K$1 -> Véhicules neufs | C81: [...] | F81: =+SUM(START:END!F81) -> 0 | I81: =+SUM(START:END!I81) -> 0 | L81: =+SUM(START:END!L81) -> 0 | N81: =L81-F81 -> 0 | Q81: =+SUM(START:END!Q81) -> 0 | S81: =L81-Q81 -> 0
A82: =+B82&C82 -> Véhicules neufsFrais administration | B82: =+$K$1 -> Véhicules neufs | C82: Frais administration | F82: =+SUM(START:END!F82) -> 60872.199 | I82: =+SUM(START:END!I82) -> 0 | L82: =+SUM(START:END!L82) -> 72033 | N82: =L82-F82 -> 11160.801 | Q82: =+SUM(START:END!Q82) -> 68780 | S82: =L82-Q82 -> 3253
A83: =+B83&C83 -> Véhicules neufsAUTRES REVENUS | B83: =+$K$1 -> Véhicules neufs | C83: AUTRES REVENUS | F83: =+SUM(F75:F82) -> 269806.83 | I83: =+SUM(I75:I82) -> 0 | L83: =+SUM(L75:L82) -> 233552.4 | N83: =+SUM(N75:N82) -> -36254.428 | Q83: =+SUM(Q75:Q82) -> 302280.07 | S83: =+SUM(S75:S82) -> -68727.67
A84: =+B84&C84 -> Véhicules neufs | B84: =+$K$1 -> Véhicules neufs
A85: =+B85&C85 -> Véhicules neufsPROFIT DÉPARTEMENTAL | B85: =+$K$1 -> Véhicules neufs | C85: PROFIT DÉPARTEMENTAL | F85: =F27-F74+F83 -> 328295.44 | I85: =I27-I74+I83 -> 0 | L85: =L27-L74+L83 -> 305499.98 | N85: =N27-N41-N54-N72+N83 -> -22795.462 | Q85: =Q27-Q74+Q83 -> 485624.46 | S85: =S27-S41-S54-S72+S83 -> -180124.48
C89: =C1 -> Conso | K89: Véhicules usagés | S89: =$S$1 -> Réalisé Volks T3 2023
D91: BUDGET ORIGINAL | G91: BUDGET RÉVISÉ | J91: RÉALISATION | M91: ÉCART réel / Budget | O91: ANNÉE PRÉCÉDENTE | R91: ECART (réel/ Ann.Préc.)
D92: UNITE | E92: $P/UNITÉ | F92: $PROFITS | G92: UNITE | H92: $P/UNITÉ | I92: $PROFITS | J92: UNITE | K92: $P/UNITE | L92: $PROFITS | M92: UNITÉS | N92: $PROFITS | O92: UNITE | P92: $P/UNITE | Q92: $PROFITS | R92: UNITÉS | S92: $PROFITS
A93: =+B93&C93 -> Véhicules usagésVentes nettes | B93: Véhicules usagés | C93: Ventes nettes | F93: =+SUM(START:END!F93) -> 4763378.1 | I93: =+SUM(START:END!I93) -> 0 | L93: =+SUM(START:END!L93) -> 4866193.2 | Q93: =+SUM(START:END!Q93) -> 5180887.5
A94: =+B94&C94 -> Véhicules usagésCertifié | B94: Véhicules usagés | C94: Certifié | D94: =+SUM(START:END!D94) -> 114 | E94: =IF(D94=0,0,F94/D94) -> 1858 | F94: =+SUM(START:END!F94) -> 211812 | G94: =+SUM(START:END!G94) -> 0 | H94: =IF(G94=0,0,I94/G94) -> 0 | I94: =+SUM(START:END!I94) -> 0 | J94: =+SUM(START:END!J94) -> 96 | K94: =IF(J94=0,0,L94/J94) -> 1504.624 | L94: =+SUM(START:END!L94) -> 144443.9 | M94: =J94-D94 -> -18 | N94: =L94-F94 -> -67368.1 | O94: =+SUM(START:END!O94) -> 110 | P94: =IF(O94=0,0,Q94/O94) -> 1759.0522 | Q94: =+SUM(START:END!Q94) -> 193495.74 | R94: =J94-O94 -> -14 | S94: =L94-Q94 -> -49051.84
A95: =+B95&C95 -> Véhicules usagésNon Certifié | B95: Véhicules usagés | C95: Non Certifié | D95: =+SUM(START:END!D95) -> 0 | E95: =IF(D95=0,0,F95/D95) -> 0 | F95: =+SUM(START:END!F95) -> 0 | G95: =+SUM(START:END!G95) -> 0 | H95: =IF(G95=0,0,I95/G95) -> 0 | I95: =+SUM(START:END!I95) -> 0 | J95: =+SUM(START:END!J95) -> 9 | K95: =IF(J95=0,0,L95/J95) -> 2054.2622 | L95: =+SUM(START:END!L95) -> 18488.36 | M95: =J95-D95 -> 9 | N95: =L95-F95 -> 18488.36 | O95: =+SUM(START:END!O95) -> 0 | P95: =IF(O95=0,0,Q95/O95) -> 0 | Q95: =+SUM(START:END!Q95) -> 0 | R95: =J95-O95 -> 9 | S95: =L95-Q95 -> 18488.36
A96: =+B96&C96 -> Véhicules usagésTotal Usagés | B96: Véhicules usagés | C96: Total Usagés | D96: =+D95+D94 -> 114 | E96: =IF(D96=0,0,F96/D96) -> 1858 | F96: =+F94+F95 -> 211812 | G96: =+G95+G94 -> 0 | H96: =IF(G96=0,0,I96/G96) -> 0 | I96: =+I94+I95 -> 0 | J96: =+J94+J95 -> 105 | K96: =IF(J96<=0,0,L96/J96) -> 1551.7358 | L96: =+L94+L95 -> 162932.26 | M96: =J96-D96 -> -9 | N96: =L96-F96 -> -48879.74 | O96: =+O94+O95 -> 110 | P96: =IF(O96<=0,0,Q96/O96) -> 1759.0522 | Q96: =+Q94+Q95 -> 193495.74 | R96: =R94+R95 -> -5 | S96: =S94+S95 -> -30563.48
A97: =+B97&C97 -> Véhicules usagés | B97: Véhicules usagés | E97: =IF(D97=0,0,F97/D97) -> 0 | H97: =IF(G97=0,0,I97/G97) -> 0 | M97: =M96/D96 -> -0.078947368 | N97: =N96/F96 -> -0.23076946 | R97: =R96/O96 -> -0.045454545 | S97: =IF(Q96=0,0,(S96/Q96)) -> -0.15795428
A98: =+B98&C98 -> Véhicules usagésUS | B98: Véhicules usagés | C98: US | D98: =+SUM(START:END!D98) -> 0 | E98: =IF(D98=0,0,F98/D98) -> 0 | F98: =+SUM(START:END!F98) -> 0 | G98: =+SUM(START:END!G98) -> 0 | H98: =IF(G98=0,0,I98/G98) -> 0 | I98: =+SUM(START:END!I98) -> 0 | J98: =+SUM(START:END!J98) -> 0 | K98: =IF(J98=0,0,L98/J98) -> 0 | L98: =+SUM(START:END!L98) -> 0 | O98: =+SUM(START:END!O98) -> 0 | P98: =IF(O98=0,0,Q98/O98) -> 0 | Q98: =+SUM(START:END!Q98) -> 0
A99: =+B99&C99 -> Véhicules usagésVentes au Gros | B99: Véhicules usagés | C99: Ventes au Gros | D99: =+SUM(START:END!D99) -> 96.461538 | E99: =IF(D99=0,0,F99/D99) -> 399 | F99: =+SUM(START:END!F99) -> 38488.154 | G99: =+SUM(START:END!G99) -> 0 | H99: =IF(G99=0,0,I99/G99) -> 0 | I99: =+SUM(START:END!I99) -> 0 | J99: =+SUM(START:END!J99) -> 92 | K99: =IF(J99=0,0,L99/J99) -> 310.57957 | L99: =+SUM(START:END!L99) -> 28573.32 | M99: =J99-D99 -> -4.4615385 | N99: =L99-F99 -> -9914.8338 | O99: =+SUM(START:END!O99) -> 117 | P99: =IF(O99=0,0,Q99/O99) -> 382.78248 | Q99: =+SUM(START:END!Q99) -> 44785.55 | R99: =J99-O99 -> -25 | S99: =L99-Q99 -> -16212.23
A100: =+B100&C100 -> Véhicules usagés | B100: Véhicules usagés
A101: =+B101&C101 -> Véhicules usagésRev. Finances | B101: Véhicules usagés | C101: Rev. Finances | D101: 0 | E101: =IF(D101=0,0,F101/D101) -> 0 | F101: =+SUM(START:END!F101) -> 57000 | G101: 0 | H101: =IF(G101=0,0,I101/G101) -> 0 | I101: =+SUM(START:END!I101) -> 0 | K101: =IF(J96=0,0,L101/J96) -> 559.65724 | L101: =+SUM(START:END!L101) -> 58764.01 | N101: =L101-F101 -> 1764.01 | P101: =IF(O96=0,0,Q101/O96) -> 717.36391 | Q101: =+SUM(START:END!Q101) -> 78910.03 | R101: =O101-K101 -> -559.65724 | S101: =L101-Q101 -> -20146.02
A102: =+B102&C102 -> Véhicules usagésRev. Protections | B102: Véhicules usagés | C102: Rev. Protections | D102: 0 | E102: =IF(D102=0,0,F102/D102) -> 0 | F102: =+SUM(START:END!F102) -> 142500 | G102: 0 | H102: =IF(G102=0,0,I102/G102) -> 0 | I102: =+SUM(START:END!I102) -> 0 | K102: =IF(J96=0,0,L102/J96) -> 1265.2108 | L102: =+SUM(START:END!L102) -> 132847.13 | N102: =L102-F102 -> -9652.87 | P102: =IF(O96=0,0,Q102/O96) -> 1184.6819 | Q102: =+SUM(START:END!Q102) -> 130315.01 | R102: =O102-K102 -> -1265.2108 | S102: =L102-Q102 -> 2532.12
A103: =+B103&C103 -> Véhicules usagésRev. Autres | B103: Véhicules usagés | C103: Rev. Autres | D103: 0 | E103: =IF(D103=0,0,F103/D103) -> 0 | F103: =+SUM(START:END!F103) -> 39900 | G103: 0 | H103: =IF(G103=0,0,I103/G103) -> 0 | I103: =+SUM(START:END!I103) -> 0 | K103: =IF(J96=0,0,L103/J96) -> 31.456381 | L103: =+SUM(START:END!L103) -> 3302.92 | N103: =L103-F103 -> -36597.08 | P103: =IF(O96=0,0,Q103/O96) -> 35.744636 | Q103: =+SUM(START:END!Q103) -> 3931.91 | R103: =O103-K103 -> -31.456381 | S103: =L103-Q103 -> -628.99
A104: =+B104&C104 -> Véhicules usagésTotal F&I | B104: Véhicules usagés | C104: Total F&I | D104: =D96 -> 114 | E104: =IF(D104=0,0,F104/D104) -> 2100 | F104: =F101+F102+F103 -> 239400 | G104: =G96 -> 0 | H104: =IF(G104=0,0,I104/G104) -> 0 | I104: =I101+I102+I103 -> 0 | J104: =J96 -> 105 | K104: =IF(J104<=0,0,L104/J104) -> 1856.3244 | L104: =L101+L102+L103 -> 194914.06 | M104: =J104-D104 -> -9 | N104: =L104-F104 -> -44485.94 | O104: =O96 -> 110 | P104: =IF(O104<=0,0,Q104/O104) -> 1937.7905 | Q104: =Q101+Q102+Q103 -> 213156.95 | S104: =L104-Q104 -> -18242.89
A105: =+B105&C105 -> Véhicules usagés | B105: Véhicules usagés | N105: =N104/F104 -> -0.18582264 | S105: =IF(Q104=0,0,(S104/Q104)) -> -0.085584308
A106: =+B106&C106 -> Véhicules usagés | B106: Véhicules usagés
A107: =+B107&C107 -> Véhicules usagésTotal Dépt. Usagés | B107: Véhicules usagés | C107: Total Dépt. Usagés | D107: =D96+D99 -> 210.46154 | E107: =IF(D107<=0,0,F107/D107) -> 2326.7917 | F107: =F96+F104+F99 -> 489700.15 | G107: =G96+G99 -> 0 | H107: =IF(G107<=0,0,I107/G107) -> 0 | I107: =I96+I104+I99 -> 0 | J107: =J96+J99+J98 -> 197 | K107: =IF(J107<=0,0,L107/J107) -> 1961.521 | L107: =L96+L104+L99+L98 -> 386419.64 | M107: =J107-D107 -> -13.461538 | N107: =L107-F107 -> -103280.51 | O107: =O96+O99+O98 -> 227 | P107: =IF(O107<=0,0,Q107/O107) -> 1988.7147 | Q107: =Q96+Q104+Q99+Q98 -> 451438.24 | R107: =J107-O107 -> -30 | S107: =L107-Q107 -> -65018.6
...

Sheet START

Sheet 2023-07
C1: Volks | K1: Véhicules neufs | S1: Réalisé, Juillet 2023
D2: X | E2: O | F2: U | J2: NB | L2: $ | O2: NB | Q2: $ | V2: *** NE PAS EFFACER / Pour An Précédente ***
D3: BUDGET ORIGINAL | J3: RÉALISATION | M3: ÉCART réel / Budget | O3: ANNÉE PRÉCÉDENTE | R3: ECART (réel/ Ann.Préc.) | V3: NEUF | W3: 0.45
D4: UNITÉS | E4: $P/UNITÉ | F4: $PROFITS | J4: UNITÉS | K4: $P/UNITE | L4: $PROFITS | M4: UNITÉS | N4: $PROFITS | O4: UNITÉS | P4: $P/UNITE | Q4: $PROFITS | R4: UNITÉS | S4: $PROFITS | V4: USAGE | W4: 0.1
A5: Véhicules neufsVentes nettes | B5: Véhicules neufs | C5: Ventes nettes | F5: 2357227.3 | L5: 2122186.9 | Q5: 2657067 | V5: SERVICE | W5: 0.225
A6: Véhicules neufsAutos détail | B6: Véhicules neufs | C6: Autos détail | D6: 10.048 | E6: 1988.434 | F6: 19979.785 | J6: 12 | K6: 1882.1942 | L6: 22586.33 | M6: 1.952 | N6: 2606.5452 | O6: 13 | P6: 2819.2123 | Q6: 36649.76 | R6: -1 | S6: -14063.43 | V6: CARROSSERIE | W6: 0.025
A7: Véhicules neufsCamions détail | B7: Véhicules neufs | C7: Camions détail | D7: 40.187981 | E7: 2556.3336 | F7: 102733.89 | J7: 24 | K7: 2577.0196 | L7: 61848.47 | M7: -16.187981 | N7: -40885.417 | O7: 37 | P7: 3278.5565 | Q7: 121306.59 | R7: -13 | S7: -59458.12 | V7: PIECES | W7: 0.2
A8: Véhicules neufsSprinter | B8: Véhicules neufs | C8: Sprinter | D8: 0 | E8: 0 | F8: 0 | J8: 0 | K8: 0 | L8: 0 | M8: 0 | N8: 0 | O8: 0 | P8: 0 | Q8: 0 | R8: 0 | S8: 0 | W8: 1
A9: Véhicules neufsMoto détail | B9: Véhicules neufs | C9: Moto détail | D9: 0 | E9: 0 | F9: 0 | J9: 0 | K9: 0 | L9: 0 | M9: 0 | N9: 0 | O9: 0 | P9: 0 | Q9: 0 | R9: 0 | S9: 0
A10: Véhicules neufs[...] | B10: Véhicules neufs | C10: [...] | D10: 0 | E10: 0 | F10: 0 | J10: 0 | K10: 0 | L10: 0 | M10: 0 | N10: 0 | O10: 0 | P10: 0 | Q10: 0 | R10: 0 | S10: 0
A11: Véhicules neufs[...] | B11: Véhicules neufs | C11: [...] | D11: 0 | E11: 0 | F11: 0 | J11: 0 | K11: 0 | L11: 0 | M11: 0 | N11: 0 | O11: 0 | P11: 0 | Q11: 0 | R11: 0 | S11: 0
A12: Véhicules neufs[...] | B12: Véhicules neufs | C12: [...] | D12: 0 | E12: 0 | F12: 0 | J12: 0 | K12: 0 | L12: 0 | M12: 0 | N12: 0 | O12: 0 | P12: 0 | Q12: 0 | R12: 0 | S12: 0
A13: Véhicules neufsTotal Neufs | B13: Véhicules neufs | C13: Total Neufs | D13: 50.235981 | E13: 2442.7446 | F13: 122713.67 | J13: 36 | K13: 2345.4111 | L13: 84434.8 | M13: -14.235981 | N13: -38278.872 | O13: 50 | P13: 3159.127 | Q13: 157956.35 | R13: -14 | S13: -73521.55
A14: Véhicules neufs | B14: Véhicules neufs | M14: -0.28338216 | N14: -0.31193649 | R14: -0.28 | S14: -0.46545486 | AD14: 20 | AE14: 1000 | AF14: 20000
A15: Véhicules neufsEx-Démos et courtoisies | B15: Véhicules neufs | C15: Ex-Démos et courtoisies | D15: 2.4 | E15: 2442.5492 | F15: 5862.1181 | J15: 3 | K15: 851.18 | L15: 2553.54 | M15: 0.6 | N15: -3308.5781 | O15: 3 | P15: 2992.6 | Q15: 8977.8 | R15: 0 | S15: -6424.26 | AD15: 25 | AE15: 800 | AF15: 20000
A16: Véhicules neufs | B16: Véhicules neufs
A17: Véhicules neufsFlottes | B17: Véhicules neufs | C17: Flottes | D17: 1.92 | E17: 2442.5492 | F17: 4689.6945 | J17: 1 | K17: 4279.05 | L17: 4279.05 | M17: -0.92 | N17: -410.64446 | O17: 2 | P17: 4190.8 | Q17: 8381.6 | R17: -1 | S17: -4102.55 | V17: 87267.39
A18: Véhicules neufs | B18: Véhicules neufs | V18: 0.37581129
A19: Véhicules neufsRachat bail | B19: Véhicules neufs | C19: Rachat bail | D19: 0 | E19: 0 | F19: 9600 | L19: 9971 | N19: 371 | Q19: 13968.33 | R19: 0 | S19: -3997.33
A20: Véhicules neufs | B20: Véhicules neufs
A21: Véhicules neufsRev. Finances | B21: Véhicules neufs | C21: Rev. Finances | D21: 0 | E21: 0 | F21: 9053.3887 | K21: 247.8859 | L21: 9667.55 | N21: 614.1613 | P21: 208.71698 | Q21: 11062 | R21: -247.8859 | S21: -1394.45
A22: Véhicules neufsRev. Protections | B22: Véhicules neufs | C22: Rev. Protections | D22: 0 | E22: 0 | F22: 49793.638 | K22: 1110.4236 | L22: 43306.52 | N22: -6487.1178 | P22: 1043.6472 | Q22: 55313.3 | R22: -1110.4236 | S22: -12006.78
A23: Véhicules neufsRev. Autres | B23: Véhicules neufs | C23: Rev. Autres | D23: 0 | E23: 0 | F23: 1526.4434 | K23: 0 | L23: 0 | N23: -1526.4434 | P23: 26.998868 | Q23: 1430.94 | R23: 0 | S23: -1430.94
A24: Véhicules neufsTotal F&I | B24: Véhicules neufs | C24: Total F&I | D24: 52.635981 | E24: 1147 | F24: 60373.47 | J24: 39 | K24: 1358.3095 | L24: 52974.07 | M24: -13.635981 | N24: -7399.4 | O24: 53 | P24: 1279.363 | Q24: 67806.24 | S24: -14832.17
A25: Véhicules neufs | B25: Véhicules neufs | N25: -0.12256046 | S25: -0.21874344
A26: Véhicules neufs | B26: Véhicules neufs
A27: Véhicules neufsTotal Dépt. Neufs | B27: Véhicules neufs | C27: Total Dépt. Neufs | D27: 54.555981 | E27: 3725.3286 | F27: 203238.95 | J27: 40 | K27: 3855.3115 | L27: 154212.46 | M27: -14.555981 | N27: -49026.494 | O27: 55 | P27: 4674.3695 | Q27: 257090.32 | R27: -15 | S27: -102877.86
A28: Véhicules neufs | B28: Véhicules neufs | L28: 0.75877413 | M28: -0.26680816 | N28: -0.24122587 | R28: -0.27272727 | S28: -0.40016232
A29: Véhicules neufs | B29: Véhicules neufs
A30: Véhicules neufsDEPENSES | B30: Véhicules neufs | C30: DEPENSES
A31: Véhicules neufsComm. vendeurs | B31: Véhicules neufs | C31: Comm. vendeurs | D31: 0.30450317 | E31: 770.95101 | F31: 40579.763 | J31: 0.3593405 | K31: 840.92487 | L31: 32796.07 | N31: -7783.6926 | P31: 1067.6589 | Q31: 56585.92 | S31: -23789.85
A32: Véhicules neufsComm. F&I | B32: Véhicules neufs | C32: Comm. F&I | D32: 0.3 | E32: 344.1 | F32: 18112.041 | J32: 0.30073846 | K32: 408.4959 | L32: 15931.34 | N32: -2180.701 | P32: 423.97528 | Q32: 22470.69 | S32: -6539.35 | U32: 0.26707524 | V32: <<- F&A total Neuf Usagé Rachat | X32: 14148.063 | Y32: 1783.2773
A33: Véhicules neufsFrais de livraison | B33: Véhicules neufs | C33: Frais de livraison | E33: 113.25898 | F33: 5961.4973 | K33: 168.41974 | L33: 6568.37 | N33: 606.87268 | P33: 145.86774 | Q33: 7730.99 | S33: -1162.62
A34: Véhicules neufsService gratuit 1 | B34: Véhicules neufs | C34: Service gratuit 1 | E34: 5.1177856 | F34: 269.37967 | K34: 1.025641 | L34: 40 | N34: -229.37967 | P34: 3.5922642 | Q34: 190.39 | S34: -150.39
A35: Véhicules neufsEntretien stock | B35: Véhicules neufs | C35: Entretien stock | E35: 105.01044 | F35: 5527.3277 | K35: 118.07769 | L35: 4605.03 | N35: -922.29768 | P35: 176.23962 | Q35: 9340.7 | S35: -4735.67
A36: Véhicules neufsPublicité 1 | B36: Véhicules neufs | C36: Publicité 1 | E36: 300.75552 | F36: 15830.562 | K36: 154.58692 | L36: 6028.89 | N36: -9801.6719 | P36: 185.94774 | Q36: 9855.23 | S36: -3826.34
A37: Véhicules neufsIntérêt de gros | B37: Véhicules neufs | C37: Intérêt de gros | E37: 50.687592 | F37: 2667.9911 | K37: 90.482564 | L37: 3528.82 | N37: 860.82887 | P37: 21.345283 | Q37: 1131.3 | S37: 2397.52
A38: Véhicules neufs[...] | B38: Véhicules neufs | C38: [...] | E38: 0 | F38: 0 | K38: 0 | L38: 0 | N38: 0 | P38: 0 | Q38: 0 | S38: 0
A39: Véhicules neufs[...] | B39: Véhicules neufs | C39: [...] | E39: 0 | F39: 0 | K39: 0 | L39: 0 | N39: 0 | P39: 0 | Q39: 0 | S39: 0
A40: Véhicules neufs[...] | B40: Véhicules neufs | C40: [...] | E40: 0 | F40: 0 | K40: 0 | L40: 0 | N40: 0 | P40: 0 | Q40: 0 | S40: 0
A41: Véhicules neufsTOTAL VARIABLES | B41: Véhicules neufs | C41: TOTAL VARIABLES | D41: % brut | E41: 0.43765508 | F41: 88948.561 | J41: % brut | K41: 0.45066735 | L41: 69498.52 | N41: -19450.041 | O41: % brut | P41: 0.41738335 | Q41: 107305.22 | S41: -37806.7
A42: Véhicules neufsSalaires cadres | B42: Véhicules neufs | C42: Salaires cadres | F42: 17292.497 | L42: 17842.1 | N42: 549.60345 | Q42: 15898.03 | S42: 1944.07
A43: Véhicules neufsSalaires commis | B43: Véhicules neufs | C43: Salaires commis | F43: 10224.637 | L43: 9643.58 | N43: -581.05724 | Q43: 7132.73 | S43: 2510.85
A44: Véhicules neufsSalaires autres | B44: Véhicules neufs | C44: Salaires autres | F44: 8208.9839 | L44: 12343.13 | N44: 4134.1461 | Q44: 3509.01 | S44: 8834.12
A45: Véhicules neufsSalaires spécialistes | B45: Véhicules neufs | C45: Salaires spécialistes | F45: 0 | L45: 0 | N45: 0 | Q45: 0 | S45: 0
A46: Véhicules neufs[...] | B46: Véhicules neufs | C46: [...] | F46: 0 | L46: 0 | N46: 0 | Q46: 0 | S46: 0
A47: Véhicules neufs[...] | B47: Véhicules neufs | C47: [...] | F47: 0 | L47: 0 | N47: 0 | Q47: 0 | S47: 0
A48: Véhicules neufs[...] | B48: Véhicules neufs | C48: [...] | F48: 0 | L48: 0 | N48: 0 | Q48: 0 | S48: 0
A49: Véhicules neufsSalaires en absences | B49: Véhicules neufs | C49: Salaires en absences | F49: 11454.455 | L49: 10139.23 | N49: -1315.2249 | Q49: 20543.52 | S49: -10404.29
A50: Véhicules neufsDéduction à la source | B50: Véhicules neufs | C50: Déduction à la source | F50: 11386.856 | L50: 14378.55 | N50: 2991.6941 | Q50: 17936.94 | S50: -3558.39
A51: Véhicules neufsBénéfices marginaux | B51: Véhicules neufs | C51: Bénéfices marginaux | F51: 7973.7373 | L51: 7088.75 | N51: -884.98733 | Q51: 7345.74 | S51: -256.99
A52: Véhicules neufsCsst | B52: Véhicules neufs | C52: Csst | F52: 3809.2842 | L52: 2311.3 | N52: -1497.9842 | Q52: 5097.38 | S52: -2786.08
A53: Véhicules neufs[...] | B53: Véhicules neufs | C53: [...] | F53: 0 | L53: 0 | N53: 0 | Q53: 0 | S53: 0
A54: Véhicules neufsTOTAL PERSONNEL | B54: Véhicules neufs | C54: TOTAL PERSONNEL | D54: % brut | E54: 0.34614649 | F54: 70350.45 | J54: % brut | K54: 0.47821454 | L54: 73746.64 | N54: 3396.1901 | O54: % brut | P54: 0.30130792 | Q54: 77463.35 | S54: -3716.71
A55: Véhicules neufsPublicité 2 | B55: Véhicules neufs | C55: Publicité 2 | F55: 0 | L55: 0 | N55: 0 | Q55: 0 | S55: 0
A56: Véhicules neufsService gratuit 2 | B56: Véhicules neufs | C56: Service gratuit 2 | F56: 0 | L56: 0 | N56: 0 | Q56: 0 | S56: 0
A57: Véhicules neufsFrais véhicules de cie | B57: Véhicules neufs | C57: Frais véhicules de cie | F57: 7945.8333 | L57: 7279.84 | N57: -665.99333 | Q57: 6354.05 | S57: 925.79
A58: Véhicules neufsInformatique | B58: Véhicules neufs | C58: Informatique | F58: 6260.8664 | L58: 7196.92 | N58: 936.0536 | Q58: 7289.36 | S58: -92.44
A59: Véhicules neufsFrais de déplacement | B59: Véhicules neufs | C59: Frais de déplacement | F59: 1000.088 | L59: 818.1 | N59: -181.98804 | Q59: 966.86 | S59: -148.76
A60: Véhicules neufsServices extérieurs | B60: Véhicules neufs | C60: Services extérieurs | F60: 6796.8453 | L60: 5967.65 | N60: -829.19533 | Q60: 6513.05 | S60: -545.4
A61: Véhicules neufsFournitures autres | B61: Véhicules neufs | C61: Fournitures autres | F61: 117.13646 | L61: 0 | N61: -117.13646 | Q61: 0 | S61: 0
A62: Véhicules neufsUniformes | B62: Véhicules neufs | C62: Uniformes | F62: 60.487931 | L62: 0 | N62: -60.487931 | Q62: 0 | S62: 0
A63: Véhicules neufsPapeterie | B63: Véhicules neufs | C63: Papeterie | F63: 763.45104 | L63: 479.83 | N63: -283.62104 | Q63: 984.46 | S63: -504.63
A64: Véhicules neufsTéléphone | B64: Véhicules neufs | C64: Téléphone | F64: 258.72025 | L64: 233.9 | N64: -24.82025 | Q64: 261.12 | S64: -27.22
A65: Véhicules neufsFrais postaux | B65: Véhicules neufs | C65: Frais postaux | F65: 123.74429 | L65: 130.12 | N65: 6.3757062 | Q65: 200.99 | S65: -70.87
A66: Véhicules neufsDivers | B66: Véhicules neufs | C66: Divers | F66: 470.18236 | L66: 106.21 | N66: -363.97236 | Q66: 140.21 | S66: -34
... A68: Véhicules neufsFrais bancaires | B68: Véhicules neufs | C68: Frais bancaires | F68: 1131.0254 | L68: 3406.43 | N68: 2275.4046 | Q68: 3741.192 | S68: -334.762
A69: Véhicules neufs[...] | B69: Véhicules neufs | C69: [...] | F69: 0 | N69: 0 | Q69: 0 | S69: 0
A70: Véhicules neufs[...] | B70: Véhicules neufs | C70: [...] | F70: 0 | L70: 0 | N70: 0 | Q70: 0 | S70: 0
A71: Véhicules neufs[...] | B71: Véhicules neufs | C71: [...] | F71: 0 | L71: 0 | N71: 0 | Q71: 0 | S71: 0
A72: Véhicules neufsTOTAL SEMI-FIXES | B72: Véhicules neufs | C72: TOTAL SEMI-FIXES | D72: % brut | E72: 0.1256704 | F72: 25541.121 | J72: % brut | K72: 0.16727624 | L72: 25796.08 | N72: 254.9589 | O72: % brut | P72: 0.10828736 | Q72: 27839.632 | S72: -2043.552
A73: Véhicules neufs | B73: Véhicules neufs
A74: Véhicules neufsTOTAL DES DÉPENSES | B74: Véhicules neufs | C74: TOTAL DES DÉPENSES | D74: % brut | E74: 0.90947197 | F74: 184840.13 | J74: % brut | K74: 1.0961581 | L74: 169041.24 | N74: -15798.892 | O74: % brut | P74: 0.82697864 | Q74: 212608.2 | S74: -43566.962
A75: Véhicules neufsProgramme neuf 1 | B75: Véhicules neufs | C75: Programme neuf 1 | F75: 0 | L75: 0 | N75: 0 | Q75: 0
A76: Véhicules neufsProgramme neuf 2 | B76: Véhicules neufs | C76: Programme neuf 2 | F76: 0 | L76: 0 | N76: 0 | Q76: 0 | S76: 0
A77: Véhicules neufsProgramme neuf 3 | B77: Véhicules neufs | C77: Programme neuf 3 | F77: 0 | L77: 0 | N77: 0 | Q77: 0 | S77: 0
A78: Véhicules neufsHoldbacks | B78: Véhicules neufs | C78: Holdbacks | E78: 1181.3417 | F78: 62181.08 | K78: 1094.8346 | L78: 42698.55 | N78: -19482.53 | Q78: 69130 | S78: -26431.45
A79: Véhicules neufs[...] | B79: Véhicules neufs | C79: [...] | F79: 0 | L79: 0 | N79: 0 | Q79: 0 | S79: 0
A80: Véhicules neufs[...] | B80: Véhicules neufs | C80: [...] | F80: 0 | L80: 0 | N80: 0 | Q80: 0 | S80: 0
A81: Véhicules neufs[...] | B81: Véhicules neufs | C81: [...] | F81: 0 | L81: 0 | N81: 0 | Q81: 0 | S81: 0
A82: Véhicules neufsFrais administration | B82: Véhicules neufs | C82: Frais administration | F82: 19591.053 | J82: 40 | K82: 486.15 | L82: 19446 | N82: -145.05271 | Q82: 20382 | S82: -936
A83: Véhicules neufsAUTRES REVENUS | B83: Véhicules neufs | C83: AUTRES REVENUS | F83: 81772.133 | L83: 62144.55 | N83: -19627.583 | Q83: 89512 | S83: -27367.45
A84: Véhicules neufs | B84: Véhicules neufs
A85: Véhicules neufsPROFIT DÉPARTEMENTAL | B85: Véhicules neufs | C85: PROFIT DÉPARTEMENTAL | F85: 100170.95 | L85: 47315.77 | N85: -52855.185 | Q85: 133994.12 | S85: -86678.348
C89: Volks | K89: Véhicules usagés | S89: Réalisé, Juillet 2023
D91: BUDGET ORIGINAL | J91: RÉALISATION | M91: ÉCART réel / Budget | O91: ANNÉE PRÉCÉDENTE | R91: ECART (réel/ Ann.Préc.)
D92: UNITÉS | E92: $P/UNITÉ | F92: $PROFITS | J92: UNITÉS | K92: $P/UNITE | L92: $PROFITS | M92: UNITÉS | N92: $PROFITS | O92: UNITÉS | P92: $P/UNITE | Q92: $PROFITS | R92: UNITÉS | S92: $PROFITS
A93: Véhicules usagésVentes nettes | B93: Véhicules usagés | C93: Ventes nettes | F93: 1504224.7 | L93: 1727866.7 | Q93: 1722927
A94: Véhicules usagésCertifié | B94: Véhicules usagés | C94: Certifié | D94: 36 | E94: 1858 | F94: 66888 | J94: 32 | K94: 1803.6106 | L94: 57715.54 | M94: -4 | N94: -9172.46 | O94: 39 | P94: 1866.1264 | Q94: 72778.93 | R94: -7 | S94: -15063.39
A95: Véhicules usagésNon Certifié | B95: Véhicules usagés | C95: Non Certifié | D95: 0 | E95: 0 | F95: 0 | J95: 4 | K95: 1549.3475 | L95: 6197.39 | M95: 4 | N95: 6197.39 | O95: 0 | P95: 0 | Q95: 0 | R95: 4 | S95: 6197.39
A96: Véhicules usagésTotal Usagés | B96: Véhicules usagés | C96: Total Usagés | D96: 36 | E96: 1858 | F96: 66888 | J96: 36 | K96: 1775.3592 | L96: 63912.93 | M96: 0 | N96: -2975.07 | O96: 39 | P96: 1866.1264 | Q96: 72778.93 | R96: -3 | S96: -8866
A97: Véhicules usagés | B97: Véhicules usagés | E97: 0 | M97: 0 | N97: -0.044478382 | R97: -0.076923077 | S97: -0.12182097
A98: Véhicules usagésUS | B98: Véhicules usagés | C98: US
A99: Véhicules usagésVentes au Gros | B99: Véhicules usagés | C99: Ventes au Gros | D99: 30.461538 | E99: 399 | F99: 12154.154 | J99: 28 | K99: 616.26179 | L99: 17255.33 | M99: -2.4615385 | N99: 5101.1762 | O99: 39 | P99: 417.18231 | Q99: 16270.11 | R99: -11 | S99: 985.22
A100: Véhicules usagés | B100: Véhicules usagés
A101: Véhicules usagésRev. Finances | B101: Véhicules usagés | C101: Rev. Finances | D101: 0 | E101: 0 | F101: 18000 | K101: 517.39306 | L101: 18626.15 | N101: 626.15 | P101: 567.12359 | Q101: 22117.82 | R101: -517.39306 | S101: -3491.67
A102: Véhicules usagésRev. Protections | B102: Véhicules usagés | C102: Rev. Protections | D102: 0 | E102: 0 | F102: 45000 | K102: 997.11056 | L102: 35895.98 | N102: -9104.02 | P102: 1053.2949 | Q102: 41078.5 | R102: -997.11056 | S102: -5182.52
A103: Véhicules usagésRev. Autres | B103: Véhicules usagés | C103: Rev. Autres | D103: 0 | E103: 0 | F103: 12600 | K103: 25.253889 | L103: 909.14 | N103: -11690.86 | P103: 41.861538 | Q103: 1632.6 | R103: -25.253889 | S103: -723.46
A104: Véhicules usagésTotal F&I | B104: Véhicules usagés | C104: Total F&I | D104: 36 | E104: 2100 | F104: 75600 | J104: 36 | K104: 1539.7575 | L104: 55431.27 | M104: 0 | N104: -20168.73 | O104: 39 | P104: 1662.28 | Q104: 64828.92 | S104: -9397.65
A105: Véhicules usagés | B105: Véhicules usagés | N105: -0.26678214 | S105: -0.14496077
...

Sheet 2023-08
C1: Volks | K1: Véhicules neufs | S1: Réalisé, Août 2023
D2: X | E2: O | F2: U | J2: NB | L2: $ | O2: NB | Q2: $ | V2: *** NE PAS EFFACER / Pour An Précédente ***
D3: BUDGET ORIGINAL | J3: RÉALISATION | M3: ÉCART réel / Budget | O3: ANNÉE PRÉCÉDENTE | R3: ECART (réel/ Ann.Préc.) | V3: NEUF | W3: 0.45
D4: UNITÉS | E4: $P/UNITÉ | F4: $PROFITS | J4: UNITÉS | K4: $P/UNITE | L4: $PROFITS | M4: UNITÉS | N4: $PROFITS | O4: UNITÉS | P4: $P/UNITE | Q4: $PROFITS | R4: UNITÉS | S4: $PROFITS | V4: USAGE | W4: 0.1
A5: Véhicules neufsVentes nettes | B5: Véhicules neufs | C5: Ventes nettes | F5: 2438191.1 | L5: 2567524.5 | Q5: 3632125.1 | V5: SERVICE | W5: 0.225
A6: Véhicules neufsAutos détail | B6: Véhicules neufs | C6: Autos détail | D6: 10.406857 | E6: 1988.434 | F6: 20693.349 | J6: 21 | K6: 2336.3824 | L6: 49064.03 | M6: 10.593143 | N6: 28370.681 | O6: 21 | P6: 2507.92 | Q6: 52666.32 | R6: 0 | S6: -3602.29 | V6: CARROSSERIE | W6: 0.025
A7: Véhicules neufsCamions détail | B7: Véhicules neufs | C7: Camions détail | D7: 41.623266 | E7: 2556.3336 | F7: 106402.95 | J7: 22 | K7: 2712.29 | L7: 59670.38 | M7: -19.623266 | N7: -46732.574 | O7: 50 | P7: 3039.8858 | Q7: 151994.29 | R7: -28 | S7: -92323.91 | V7: PIECES | W7: 0.2
A8: Véhicules neufsSprinter | B8: Véhicules neufs | C8: Sprinter | D8: 0 | E8: 0 | F8: 0 | J8: 0 | K8: 0 | L8: 0 | M8: 0 | N8: 0 | O8: 0 | P8: 0 | Q8: 0 | R8: 0 | S8: 0 | W8: 1
A9: Véhicules neufsMoto détail | B9: Véhicules neufs | C9: Moto détail | D9: 0 | E9: 0 | F9: 0 | J9: 0 | K9: 0 | L9: 0 | M9: 0 | N9: 0 | O9: 0 | P9: 0 | Q9: 0 | R9: 0 | S9: 0
A10: Véhicules neufs[...] | B10: Véhicules neufs | C10: [...] | D10: 0 | E10: 0 | F10: 0 | J10: 0 | K10: 0 | L10: 0 | M10: 0 | N10: 0 | O10: 0 | P10: 0 | Q10: 0 | R10: 0 | S10: 0
A11: Véhicules neufs[...] | B11: Véhicules neufs | C11: [...] | D11: 0 | E11: 0 | F11: 0 | J11: 0 | K11: 0 | L11: 0 | M11: 0 | N11: 0 | O11: 0 | P11: 0 | Q11: 0 | R11: 0 | S11: 0
A12: Véhicules neufs[...] | B12: Véhicules neufs | C12: [...] | D12: 0 | E12: 0 | F12: 0 | J12: 0 | K12: 0 | L12: 0 | M12: 0 | N12: 0 | O12: 0 | P12: 0 | Q12: 0 | R12: 0 | S12: 0
A13: Véhicules neufsTotal Neufs | B13: Véhicules neufs | C13: Total Neufs | D13: 52.030123 | E13: 2442.7446 | F13: 127096.3 | J13: 43 | K13: 2528.7072 | L13: 108734.41 | M13: -9.030123 | N13: -18361.893 | O13: 71 | P13: 2882.5438 | Q13: 204660.61 | R13: -28 | S13: -95926.2
A14: Véhicules neufs | B14: Véhicules neufs | M14: -0.17355567 | N14: -0.14447228 | R14: -0.3943662 | S14: -0.46870866 | AD14: 20 | AE14: 1000 | AF14: 20000
A15: Véhicules neufsEx-Démos et courtoisies | B15: Véhicules neufs | C15: Ex-Démos et courtoisies | D15: 2.4857143 | E15: 2442.5492 | F15: 6071.4794 | J15: 8 | K15: 1186.9175 | L15: 9495.34 | M15: 5.5142857 | N15: 3423.8606 | O15: 2 | P15: 4516.805 | Q15: 9033.61 | R15: 6 | S15: 461.73 | AD15: 25 | AE15: 800 | AF15: 20000
A16: Véhicules neufs | B16: Véhicules neufs
A17: Véhicules neufsFlottes | B17: Véhicules neufs | C17: Flottes | D17: 1.9885714 | E17: 2442.5492 | F17: 4857.1836 | J17: 4 | K17: 3473.7725 | L17: 13895.09 | M17: 2.0114286 | N17: 9037.9064 | O17: 4 | P17: 1549.0925 | Q17: 6196.37 | R17: 0 | S17: 7698.72 | V17: 128124.84
A18: Véhicules neufs | B18: Véhicules neufs | V18: 0.32626078
A19: Véhicules neufsRachat bail | B19: Véhicules neufs | C19: Rachat bail | D19: 0 | E19: 0 | F19: 6720 | L19: 7757.94 | N19: 1037.94 | Q19: 19995.21 | R19: 0 | S19: -12237.27
A20: Véhicules neufs | B20: Véhicules neufs
A21: Véhicules neufsRev. Finances | B21: Véhicules neufs | C21: Rev. Finances | D21: 0 | E21: 0 | F21: 9376.724 | K21: 175.29412 | L21: 8940 | N21: -436.72401 | P21: 172.24973 | Q21: 12574.23 | R21: -175.29412 | S21: -3634.23
A22: Véhicules neufsRev. Protections | B22: Véhicules neufs | C22: Rev. Protections | D22: 0 | E22: 0 | F22: 51571.982 | K22: 1030.0339 | L22: 52531.73 | N22: 959.74795 | P22: 810.39493 | Q22: 59158.83 | R22: -1030.0339 | S22: -6627.1
A23: Véhicules neufsRev. Autres | B23: Véhicules neufs | C23: Rev. Autres | D23: 0 | E23: 0 | F23: 1580.9593 | K23: 12.943529 | L23: 660.12 | N23: -920.83928 | P23: 16.719726 | Q23: 1220.54 | R23: -12.943529 | S23: -560.42
A24: Véhicules neufsTotal F&I | B24: Véhicules neufs | C24: Total F&I | D24: 54.515837 | E24: 1147 | F24: 62529.665 | J24: 51 | K24: 1218.2716 | L24: 62131.85 | M24: -3.5158373 | N24: -397.81533 | O24: 73 | P24: 999.36438 | Q24: 72953.6 | S24: -10821.75
A25: Véhicules neufs | B25: Véhicules neufs | N25: -0.0063620256 | S25: -0.14833744
A26: Véhicules neufs | B26: Véhicules neufs
A27: Véhicules neufsTotal Dépt. Neufs | B27: Véhicules neufs | C27: Total Dépt. Neufs | D27: 56.504409 | E27: 3668.2913 | F27: 207274.63 | J27: 55 | K27: 3672.9933 | L27: 202014.63 | M27: -1.5044087 | N27: -5260.0013 | O27: 77 | P27: 4062.8494 | Q27: 312839.4 | R27: -22 | S27: -110824.77
A28: Véhicules neufs | B28: Véhicules neufs | L28: 0.97462303 | M28: -0.026624625 | N28: -0.025376966 | R28: -0.28571429 | S28: -0.35425452
A29: Véhicules neufs | B29: Véhicules neufs
A30: Véhicules neufsDEPENSES | B30: Véhicules neufs | C30: DEPENSES
A31: Véhicules neufsComm. vendeurs | B31: Véhicules neufs | C31: Comm. vendeurs | D31: 0.30577106 | E31: 774.16109 | F31: 42204.04 | J31: 0.31638343 | K31: 819.64922 | L31: 41802.11 | N31: -401.92986 | P31: 676.68315 | Q31: 49397.87 | S31: -7595.76
A32: Véhicules neufsComm. F&I | B32: Véhicules neufs | C32: Comm. F&I | D32: 0.3 | E32: 344.1 | F32: 18758.9 | J32: 0.2998974 | K32: 365.35647 | L32: 18633.18 | N32: -125.7196 | P32: 376.9889 | Q32: 27520.19 | S32: -8887.01 | U32: 0.2844261 | V32: <<- F&A total Neuf Usagé Rachat | X32: 17671.92 | Y32: 961.26013
A33: Véhicules neufsFrais de livraison | B33: Véhicules neufs | C33: Frais de livraison | E33: 113.25898 | F33: 6174.4079 | K33: 121.67235 | L33: 6205.29 | N33: 30.88206 | P33: 24.27137 | Q33: 1771.81 | S33: 4433.48
A34: Véhicules neufsService gratuit 1 | B34: Véhicules neufs | C34: Service gratuit 1 | E34: 5.1177856 | F34: 279.00037 | K34: 1.8039216 | L34: 92 | N34: -187.00037 | P34: 0 | Q34: 0 | S34: 92
A35: Véhicules neufsEntretien stock | B35: Véhicules neufs | C35: Entretien stock | E35: 105.01044 | F35: 5724.7322 | K35: 78.708235 | L35: 4014.12 | N35: -1710.6122 | P35: 60.332329 | Q35: 4404.26 | S35: -390.14
A36: Véhicules neufsPublicité 1 | B36: Véhicules neufs | C36: Publicité 1 | E36: 300.75552 | F36: 16395.939 | K36: 40.121961 | L36: 2046.22 | N36: -14349.719 | P36: 48.655068 | Q36: 3551.82 | S36: -1505.6
A37: Véhicules neufsIntérêt de gros | B37: Véhicules neufs | C37: Intérêt de gros | E37: 53.963736 | F37: 2941.8783 | K37: 0 | L37: 0 | N37: -2941.8783 | P37: 51.69 | Q37: 3773.37 | S37: -3773.37
A38: Véhicules neufs[...] | B38: Véhicules neufs | C38: [...] | E38: 0 | F38: 0 | K38: 0 | L38: 0 | N38: 0 | P38: 0 | Q38: 0 | S38: 0
A39: Véhicules neufs[...] | B39: Véhicules neufs | C39: [...] | E39: 0 | F39: 0 | K39: 0 | L39: 0 | N39: 0 | P39: 0 | Q39: 0 | S39: 0
A40: Véhicules neufs[...] | B40: Véhicules neufs | C40: [...] | E40: 0 | F40: 0 | K40: 0 | L40: 0 | N40: 0 | P40: 0 | Q40: 0 | S40: 0
A41: Véhicules neufsTOTAL VARIABLES | B41: Véhicules neufs | C41: TOTAL VARIABLES | D41: % brut | E41: 0.44616602 | F41: 92478.897 | J41: % brut | K41: 0.36033489 | L41: 72792.92 | N41: -19685.977 | O41: % brut | P41: 0.28902792 | Q41: 90419.32 | S41: -17626.4
A42: Véhicules neufsSalaires cadres | B42: Véhicules neufs | C42: Salaires cadres | F42: 17292.497 | L42: 14353.64 | N42: -2938.8566 | Q42: 24887.25 | S42: -10533.61
A43: Véhicules neufsSalaires commis | B43: Véhicules neufs | C43: Salaires commis | F43: 10224.637 | L43: 12006.55 | N43: 1781.9128 | Q43: 7402.55 | S43: 4604
A44: Véhicules neufsSalaires autres | B44: Véhicules neufs | C44: Salaires autres | F44: 8208.9839 | L44: 11151.24 | N44: 2942.2561 | Q44: 4747.31 | S44: 6403.93
A45: Véhicules neufsSalaires spécialistes | B45: Véhicules neufs | C45: Salaires spécialistes | F45: 0 | L45: 0 | N45: 0 | Q45: 0 | S45: 0
A46: Véhicules neufs[...] | B46: Véhicules neufs | C46: [...] | F46: 0 | L46: 0 | N46: 0 | Q46: 0 | S46: 0
A47: Véhicules neufs[...] | B47: Véhicules neufs | C47: [...] | F47: 0 | L47: 0 | N47: 0 | Q47: 0 | S47: 0
A48: Véhicules neufs[...] | B48: Véhicules neufs | C48: [...] | F48: 0 | L48: 0 | N48: 0 | Q48: 0 | S48: 0
A49: Véhicules neufsSalaires en absences | B49: Véhicules neufs | C49: Salaires en absences | F49: 11710.77 | L49: 6780.38 | N49: -4930.3904 | Q49: 15306.49 | S49: -8526.11
A50: Véhicules neufsDéduction à la source | B50: Véhicules neufs | C50: Déduction à la source | F50: 11641.659 | L50: 10620.12 | N50: -1021.5388 | Q50: 15327.04 | S50: -4706.92
A51: Véhicules neufsBénéfices marginaux | B51: Véhicules neufs | C51: Bénéfices marginaux | F51: 8152.1651 | L51: 5958.04 | N51: -2194.1251 | Q51: 7021.56 | S51: -1063.52
A52: Véhicules neufsCsst | B52: Véhicules neufs | C52: Csst | F52: 3894.5243 | L52: 1830.69 | N52: -2063.8343 | Q52: 2399 | S52: -568.31
A53: Véhicules neufs[...] | B53: Véhicules neufs | C53: [...] | F53: 0 | L53: 0 | N53: 0 | Q53: 0 | S53: 0
A54: Véhicules neufsTOTAL PERSONNEL | B54: Véhicules neufs | C54: TOTAL PERSONNEL | D54: % brut | E54: 0.34314492 | F54: 71125.236 | J54: % brut | K54: 0.31037683 | L54: 62700.66 | N54: -8424.5763 | O54: % brut | P54: 0.2464242 | Q54: 77091.2 | S54: -14390.54
A55: Véhicules neufsPublicité 2 | B55: Véhicules neufs | C55: Publicité 2 | F55: 0 | L55: 0 | N55: 0 | Q55: 0 | S55: 0
A56: Véhicules neufsService gratuit 2 | B56: Véhicules neufs | C56: Service gratuit 2 | F56: 0 | L56: 0 | N56: 0 | Q56: 0 | S56: 0
A57: Véhicules neufsFrais véhicules de cie | B57: Véhicules neufs | C57: Frais véhicules de cie | F57: 7945.8333 | L57: 2665.34 | N57: -5280.4933 | Q57: 7615.92 | S57: -4950.58
A58: Véhicules neufsInformatique | B58: Véhicules neufs | C58: Informatique | F58: 6260.8664 | L58: 6738.03 | N58: 477.1636 | Q58: 7197.56 | S58: -459.53
A59: Véhicules neufsFrais de déplacement | B59: Véhicules neufs | C59: Frais de déplacement | F59: 1000.088 | L59: 1465.98 | N59: 465.89196 | Q59: 1421.01 | S59: 44.97
A60: Véhicules neufsServices extérieurs | B60: Véhicules neufs | C60: Services extérieurs | F60: 6506.5765 | L60: 6269.32 | N60: -237.2565 | Q60: 7061.26 | S60: -791.94
A61: Véhicules neufsFournitures autres | B61: Véhicules neufs | C61: Fournitures autres | F61: 124.8309 | L61: 0 | N61: -124.8309 | Q61: 17.4 | S61: -17.4
A62: Véhicules neufsUniformes | B62: Véhicules neufs | C62: Uniformes | F62: 64.461253 | L62: 0 | N62: -64.461253 | Q62: 0 | S62: 0
A63: Véhicules neufsPapeterie | B63: Véhicules neufs | C63: Papeterie | F63: 763.45104 | L63: 1114.19 | N63: 350.73896 | Q63: 694.32 | S63: 419.87
A64: Véhicules neufsTéléphone | B64: Véhicules neufs | C64: Téléphone | F64: 258.72025 | L64: 597.5 | N64: 338.77975 | Q64: 248.14 | S64: 349.36
A65: Véhicules neufsFrais postaux | B65: Véhicules neufs | C65: Frais postaux | F65: 123.74429 | L65: 103.55 | N65: -20.194294 | Q65: 133.59 | S65: -30.04
A66: Véhicules neufsDivers | B66: Véhicules neufs | C66: Divers | F66: 470.18236 | L66: 112.7 | N66: -357.48236 | Q66: 62.72 | S66: 49.98
... A68: Véhicules neufsFrais bancaires | B68: Véhicules neufs | C68: Frais bancaires | F68: 1255.436 | L68: 2659.84 | N68: 1404.404 | Q68: 4087.827 | S68: -1427.987
A69: Véhicules neufs[...] | B69: Véhicules neufs | C69: [...] | F69: 0 | N69: 0 | Q69: 0 | S69: 0
A70: Véhicules neufs[...] | B70: Véhicules neufs | C70: [...] | F70: 0 | L70: 0 | N70: 0 | Q70: 0 | S70: 0
A71: Véhicules neufs[...] | B71: Véhicules neufs | C71: [...] | F71: 0 | L71: 0 | N71: 0 | Q71: 0 | S71: 0
A72: Véhicules neufsTOTAL SEMI-FIXES | B72: Véhicules neufs | C72: TOTAL SEMI-FIXES | D72: % brut | E72: 0.12247968 | F72: 25386.931 | J72: % brut | K72: 0.1116677 | L72: 22558.51 | N72: -2828.4206 | O72: % brut | P72: 0.093620839 | Q72: 29288.287 | S72: -6729.777
A73: Véhicules neufs | B73: Véhicules neufs
A74: Véhicules neufsTOTAL DES DÉPENSES | B74: Véhicules neufs | C74: TOTAL DES DÉPENSES | D74: % brut | E74: 0.91179062 | F74: 188991.06 | J74: % brut | K74: 0.78237942 | L74: 158052.09 | N74: -30938.974 | O74: % brut | P74: 0.62907296 | Q74: 196798.81 | S74: -38746.717
A75: Véhicules neufsProgramme neuf 1 | B75: Véhicules neufs | C75: Programme neuf 1 | F75: 0 | L75: 0 | N75: 0 | Q75: 0
A76: Véhicules neufsProgramme neuf 2 | B76: Véhicules neufs | C76: Programme neuf 2 | F76: 0 | L76: 0 | N76: 0 | Q76: 0 | S76: 0
A77: Véhicules neufsProgramme neuf 3 | B77: Véhicules neufs | C77: Programme neuf 3 | F77: 0 | L77: 0 | N77: 0 | Q77: 0 | S77: 0
A78: Véhicules neufsHoldbacks | B78: Véhicules neufs | C78: Holdbacks | E78: 1181.3417 | F78: 64401.833 | K78: 1174.1735 | L78: 59882.85 | N78: -4518.9828 | Q78: 101582.07 | S78: -41699.22
A79: Véhicules neufs[...] | B79: Véhicules neufs | C79: [...] | F79: 0 | L79: 0 | N79: 0 | Q79: 0 | S79: 0
A80: Véhicules neufs[...] | B80: Véhicules neufs | C80: [...] | F80: 0 | L80: 0 | N80: 0 | Q80: 0 | S80: 0
A81: Véhicules neufs[...] | B81: Véhicules neufs | C81: [...] | F81: 0 | L81: 0 | N81: 0 | Q81: 0 | S81: 0
A82: Véhicules neufsFrais administration | B82: Véhicules neufs | C82: Frais administration | F82: 20290.733 | J82: 55 | K82: 489.49091 | L82: 26922 | N82: 6631.2668 | Q82: 29344 | S82: -2422
A83: Véhicules neufsAUTRES REVENUS | B83: Véhicules neufs | C83: AUTRES REVENUS | F83: 84692.566 | L83: 86804.85 | N83: 2112.2841 | Q83: 130926.07 | S83: -44121.22
A84: Véhicules neufs | B84: Véhicules neufs
A85: Véhicules neufsPROFIT DÉPARTEMENTAL | B85: Véhicules neufs | C85: PROFIT DÉPARTEMENTAL | F85: 102976.13 | L85: 130767.39 | N85: 27791.257 | Q85: 246966.66 | S85: -116199.27
C89: Volks | K89: Véhicules usagés | S89: Réalisé, Août 2023
D91: BUDGET ORIGINAL | J91: RÉALISATION | M91: ÉCART réel / Budget | O91: ANNÉE PRÉCÉDENTE | R91: ECART (réel/ Ann.Préc.)
D92: UNITÉS | E92: $P/UNITÉ | F92: $PROFITS | J92: UNITÉS | K92: $P/UNITE | L92: $PROFITS | M92: UNITÉS | N92: $PROFITS | O92: UNITÉS | P92: $P/UNITE | Q92: $PROFITS | R92: UNITÉS | S92: $PROFITS
A93: Véhicules usagésVentes nettes | B93: Véhicules usagés | C93: Ventes nettes | F93: 1671360.8 | L93: 1894182.2 | Q93: 1707858.5
A94: Véhicules usagésCertifié | B94: Véhicules usagés | C94: Certifié | D94: 40 | E94: 1858 | F94: 74320 | J94: 35 | K94: 878.82857 | L94: 30759 | M94: -5 | N94: -43561 | O94: 37 | P94: 1588.5049 | Q94: 58774.68 | R94: -2 | S94: -28015.68
A95: Véhicules usagésNon Certifié | B95: Véhicules usagés | C95: Non Certifié | D95: 0 | E95: 0 | F95: 0 | J95: 1 | K95: 3601.1 | L95: 3601.1 | M95: 1 | N95: 3601.1 | O95: 0 | P95: 0 | Q95: 0 | R95: 1 | S95: 3601.1
A96: Véhicules usagésTotal Usagés | B96: Véhicules usagés | C96: Total Usagés | D96: 40 | E96: 1858 | F96: 74320 | J96: 36 | K96: 954.44722 | L96: 34360.1 | M96: -4 | N96: -39959.9 | O96: 37 | P96: 1588.5049 | Q96: 58774.68 | R96: -1 | S96: -24414.58
A97: Véhicules usagés | B97: Véhicules usagés | E97: 0 | M97: -0.1 | N97: -0.53767357 | R97: -0.027027027 | S97: -0.41539282
A98: Véhicules usagésUS | B98: Véhicules usagés | C98: US
A99: Véhicules usagésVentes au Gros | B99: Véhicules usagés | C99: Ventes au Gros | D99: 33.846154 | E99: 399 | F99: 13504.615 | J99: 38 | K99: -4.6778947 | L99: -177.76 | M99: 4.1538462 | N99: -13682.375 | O99: 39 | P99: 330.44385 | Q99: 12887.31 | R99: -1 | S99: -13065.07
A100: Véhicules usagés | B100: Véhicules usagés
A101: Véhicules usagésRev. Finances | B101: Véhicules usagés | C101: Rev. Finances | D101: 0 | E101: 0 | F101: 20000 | K101: 707.17361 | L101: 25458.25 | N101: 5458.25 | P101: 827.65405 | Q101: 30623.2 | R101: -707.17361 | S101: -5164.95
A102: Véhicules usagésRev. Protections | B102: Véhicules usagés | C102: Rev. Protections | D102: 0 | E102: 0 | F102: 50000 | K102: 1507.8911 | L102: 54284.08 | N102: 4284.08 | P102: 1416.5568 | Q102: 52412.6 | R102: -1507.8911 | S102: 1871.48
A103: Véhicules usagésRev. Autres | B103: Véhicules usagés | C103: Rev. Autres | D103: 0 | E103: 0 | F103: 14000 | K103: 29.091667 | L103: 1047.3 | N103: -12952.7 | P103: 48.754595 | Q103: 1803.92 | R103: -29.091667 | S103: -756.62
A104: Véhicules usagésTotal F&I | B104: Véhicules usagés | C104: Total F&I | D104: 40 | E104: 2100 | F104: 84000 | J104: 36 | K104: 2244.1564 | L104: 80789.63 | M104: -4 | N104: -3210.37 | O104: 37 | P104: 2292.9654 | Q104: 84839.72 | S104: -4050.09
A105: Véhicules usagés | B105: Véhicules usagés | N105: -0.03821869 | S105: -0.047738135
...

Sheet 2023-09
C1: Volks | K1: Véhicules neufs | S1: Réalisé, Septembre 2023
D2: X | E2: O | F2: U | J2: NB | L2: $ | O2: NB | Q2: $ | V2: *** NE PAS EFFACER / Pour An Précédente ***
D3: BUDGET ORIGINAL | J3: RÉALISATION | M3: ÉCART réel / Budget | O3: ANNÉE PRÉCÉDENTE | R3: ECART (réel/ Ann.Préc.) | V3: NEUF | W3: 0.45
D4: UNITÉS | E4: $P/UNITÉ | F4: $PROFITS | J4: UNITÉS | K4: $P/UNITE | L4: $PROFITS | M4: UNITÉS | N4: $PROFITS | O4: UNITÉS | P4: $P/UNITE | Q4: $PROFITS | R4: UNITÉS | S4: $PROFITS | V4: USAGE | W4: 0.1
A5: Véhicules neufsVentes nettes | B5: Véhicules neufs | C5: Ventes nettes | F5: 2522034.9 | L5: 2612584.6 | Q5: 2490545.3 | V5: SERVICE | W5: 0.225
A6: Véhicules neufsAutos détail | B6: Véhicules neufs | C6: Autos détail | D6: 10.765714 | E6: 1988.434 | F6: 21406.912 | J6: 17 | K6: 1804.1035 | L6: 30669.76 | M6: 6.2342857 | N6: 9262.8477 | O6: 16 | P6: 1902.4 | Q6: 30438.4 | R6: 1 | S6: 231.36 | V6: CARROSSERIE | W6: 0.025
A7: Véhicules neufsCamions détail | B7: Véhicules neufs | C7: Camions détail | D7: 43.058551 | E7: 2556.3336 | F7: 110072.02 | J7: 36 | K7: 2493.9233 | L7: 89781.24 | M7: -7.0585509 | N7: -20290.782 | O7: 33 | P7: 2621.6852 | Q7: 86515.61 | R7: 3 | S7: 3265.63 | V7: PIECES | W7: 0.2
A8: Véhicules neufsSprinter | B8: Véhicules neufs | C8: Sprinter | D8: 0 | E8: 0 | F8: 0 | J8: 0 | K8: 0 | L8: 0 | M8: 0 | N8: 0 | O8: 0 | P8: 0 | Q8: 0 | R8: 0 | S8: 0 | W8: 1
A9: Véhicules neufsMoto détail | B9: Véhicules neufs | C9: Moto détail | D9: 0 | E9: 0 | F9: 0 | J9: 0 | K9: 0 | L9: 0 | M9: 0 | N9: 0 | O9: 0 | P9: 0 | Q9: 0 | R9: 0 | S9: 0
A10: Véhicules neufs[...] | B10: Véhicules neufs | C10: [...] | D10: 0 | E10: 0 | F10: 0 | J10: 0 | K10: 0 | L10: 0 | M10: 0 | N10: 0 | O10: 0 | P10: 0 | Q10: 0 | R10: 0 | S10: 0
A11: Véhicules neufs[...] | B11: Véhicules neufs | C11: [...] | D11: 0 | E11: 0 | F11: 0 | J11: 0 | K11: 0 | L11: 0 | M11: 0 | N11: 0 | O11: 0 | P11: 0 | Q11: 0 | R11: 0 | S11: 0
A12: Véhicules neufs[...] | B12: Véhicules neufs | C12: [...] | D12: 0 | E12: 0 | F12: 0 | J12: 0 | K12: 0 | L12: 0 | M12: 0 | N12: 0 | O12: 0 | P12: 0 | Q12: 0 | R12: 0 | S12: 0
A13: Véhicules neufsTotal Neufs | B13: Véhicules neufs | C13: Total Neufs | D13: 53.824265 | E13: 2442.7446 | F13: 131478.93 | J13: 53 | K13: 2272.6604 | L13: 120451 | M13: -0.82426514 | N13: -11027.934 | O13: 49 | P13: 2386.8165 | Q13: 116954.01 | R13: 4 | S13: 3496.99
A14: Véhicules neufs | B14: Véhicules neufs | M14: -0.015314006 | N14: -0.083876053 | R14: 0.081632653 | S14: 0.029900557 | AD14: 20 | AE14: 1000 | AF14: 20000
A15: Véhicules neufsEx-Démos et courtoisies | B15: Véhicules neufs | C15: Ex-Démos et courtoisies | D15: 2.5714286 | E15: 2442.5492 | F15: 6280.8408 | J15: 1 | K15: 975.83 | L15: 975.83 | M15: -1.5714286 | N15: -5305.0108 | O15: 1 | P15: 239.68 | Q15: 239.68 | R15: 0 | S15: 736.15 | AD15: 25 | AE15: 800 | AF15: 20000
A16: Véhicules neufs | B16: Véhicules neufs
A17: Véhicules neufsFlottes | B17: Véhicules neufs | C17: Flottes | D17: 2.0571429 | E17: 2442.5492 | F17: 5024.6726 | J17: 1 | K17: 3198 | L17: 3198 | M17: -1.0571429 | N17: -1826.6726 | O17: 3 | P17: 1695.91 | Q17: 5087.73 | R17: -2 | S17: -1889.73 | V17: 120624.83
A18: Véhicules neufs | B18: Véhicules neufs | V18: 0.19778465
A19: Véhicules neufsRachat bail | B19: Véhicules neufs | C19: Rachat bail | D19: 0 | E19: 0 | F19: 6720 | L19: 7932.08 | N19: 1212.08 | Q19: 13692.75 | R19: 0 | S19: -5760.67
A20: Véhicules neufs | B20: Véhicules neufs
A21: Véhicules neufsRev. Finances | B21: Véhicules neufs | C21: Rev. Finances | D21: 0 | E21: 0 | F21: 9700.0593 | K21: 92.308148 | L21: 4984.64 | N21: -4715.4193 | P21: 211.384 | Q21: 10569.2 | R21: -92.308148 | S21: -5584.56
A22: Véhicules neufsRev. Protections | B22: Véhicules neufs | C22: Rev. Protections | D22: 0 | E22: 0 | F22: 53350.326 | K22: 1111.505 | L22: 60021.27 | N22: 6670.9437 | P22: 866.2176 | Q22: 43310.88 | R22: -1111.505 | S22: 16710.39
A23: Véhicules neufsRev. Autres | B23: Véhicules neufs | C23: Rev. Autres | D23: 0 | E23: 0 | F23: 1635.4751 | K23: 9.5077778 | L23: 513.42 | N23: -1122.0551 | P23: 32.4756 | Q23: 1623.78 | R23: -9.5077778 | S23: -1110.36
A24: Véhicules neufsTotal F&I | B24: Véhicules neufs | C24: Total F&I | D24: 56.395694 | E24: 1147 | F24: 64685.861 | J24: 54 | K24: 1213.3209 | L24: 65519.33 | M24: -2.3956937 | N24: 833.46931 | O24: 50 | P24: 1110.0772 | Q24: 55503.86 | S24: 10015.47
A25: Véhicules neufs | B25: Véhicules neufs | N25: 0.012884876 | S25: 0.18044637
A26: Véhicules neufs | B26: Véhicules neufs
A27: Véhicules neufsTotal Dépt. Neufs | B27: Véhicules neufs | C27: Total Dépt. Neufs | D27: 58.452837 | E27: 3664.327 | F27: 214190.31 | J27: 55 | K27: 3601.3862 | L27: 198076.24 | M27: -3.4528366 | N27: -16114.068 | O27: 53 | P27: 3612.793 | Q27: 191478.03 | R27: 2 | S27: 6598.21
A28: Véhicules neufs | B28: Véhicules neufs | L28: 0.92476752 | M28: -0.059070471 | N28: -0.075232481 | R28: 0.037735849 | S28: 0.034459358
A29: Véhicules neufs | B29: Véhicules neufs
A30: Véhicules neufsDEPENSES | B30: Véhicules neufs | C30: DEPENSES
A31: Véhicules neufsComm. vendeurs | B31: Véhicules neufs | C31: Comm. vendeurs | D31: 0.30191185 | E31: 764.39023 | F31: 43108.317 | J31: 0.19143649 | K31: 441.81 | L31: 23857.74 | N31: -19250.577 | P31: 768.0872 | Q31: 38404.36 | S31: -14546.62
A32: Véhicules neufsComm. F&I | B32: Véhicules neufs | C32: Comm. F&I | D32: 0.3 | E32: 344.1 | F32: 19405.758 | J32: 0.30030542 | K32: 364.36685 | L32: 19675.81 | N32: 270.05179 | P32: 385.746 | Q32: 19287.3 | S32: 388.51 | U32: 0.2823413 | V32: <<- F&A total Neuf Usagé Rachat | X32: 18498.813 | Y32: 1176.997
A33: Véhicules neufsFrais de livraison | B33: Véhicules neufs | C33: Frais de livraison | E33: 113.25898 | F33: 6387.3186 | K33: 85.562222 | L33: 4620.36 | N33: -1766.9586 | P33: -22.501 | Q33: -1125.05 | S33: 5745.41
A34: Véhicules neufsService gratuit 1 | B34: Véhicules neufs | C34: Service gratuit 1 | E34: 5.1177856 | F34: 288.62107 | K34: 3.9803704 | L34: 214.94 | N34: -73.681072 | P34: 0.58 | Q34: 29 | S34: 185.94
A35: Véhicules neufsEntretien stock | B35: Véhicules neufs | C35: Entretien stock | E35: 105.01044 | F35: 5922.1368 | K35: 80.216481 | L35: 4331.69 | N35: -1590.4468 | P35: 71.9218 | Q35: 3596.09 | S35: 735.6
A36: Véhicules neufsPublicité 1 | B36: Véhicules neufs | C36: Publicité 1 | E36: 300.75552 | F36: 16961.316 | K36: 102.55352 | L36: 5537.89 | N36: -11423.426 | P36: 40.1874 | Q36: 2009.37 | S36: 3528.52
A37: Véhicules neufsIntérêt de gros | B37: Véhicules neufs | C37: Intérêt de gros | E37: 63.366313 | F37: 3573.5872 | K37: 95.057593 | L37: 5133.11 | N37: 1559.5228 | P37: 105.5194 | Q37: 5275.97 | S37: -142.86
A38: Véhicules neufs[...] | B38: Véhicules neufs | C38: [...] | E38: 0 | F38: 0 | K38: 0 | L38: 0 | N38: 0 | P38: 0 | Q38: 0 | S38: 0
A39: Véhicules neufs[...] | B39: Véhicules neufs | C39: [...] | E39: 0 | F39: 0 | K39: 0 | L39: 0 | N39: 0 | P39: 0 | Q39: 0 | S39: 0
A40: Véhicules neufs[...] | B40: Véhicules neufs | C40: [...] | E40: 0 | F40: 0 | K40: 0 | L40: 0 | N40: 0 | P40: 0 | Q40: 0 | S40: 0
A41: Véhicules neufsTOTAL VARIABLES | B41: Véhicules neufs | C41: TOTAL VARIABLES | D41: % brut | E41: 0.44655174 | F41: 95647.055 | J41: % brut | K41: 0.31993509 | L41: 63371.54 | N41: -32275.515 | O41: % brut | P41: 0.35240095 | Q41: 67477.04 | S41: -4105.5
A42: Véhicules neufsSalaires cadres | B42: Véhicules neufs | C42: Salaires cadres | F42: 17292.497 | L42: 14161.33 | N42: -3131.1666 | Q42: 15311.7 | S42: -1150.37
A43: Véhicules neufsSalaires commis | B43: Véhicules neufs | C43: Salaires commis | F43: 10224.637 | L43: 16026.9 | N43: 5802.2628 | Q43: 7250.31 | S43: 8776.59
A44: Véhicules neufsSalaires autres | B44: Véhicules neufs | C44: Salaires autres | F44: 8208.9839 | L44: 6488.86 | N44: -1720.1239 | Q44: 4701.98 | S44: 1786.88
A45: Véhicules neufsSalaires spécialistes | B45: Véhicules neufs | C45: Salaires spécialistes | F45: 0 | L45: 0 | N45: 0 | Q45: 0 | S45: 0
A46: Véhicules neufs[...] | B46: Véhicules neufs | C46: [...] | F46: 0 | L46: 0 | N46: 0 | Q46: 0 | S46: 0
A47: Véhicules neufs[...] | B47: Véhicules neufs | C47: [...] | F47: 0 | L47: 0 | N47: 0 | Q47: 0 | S47: 0
A48: Véhicules neufs[...] | B48: Véhicules neufs | C48: [...] | F48: 0 | L48: 0 | N48: 0 | Q48: 0 | S48: 0
A49: Véhicules neufsSalaires en absences | B49: Véhicules neufs | C49: Salaires en absences | F49: 11885.828 | L49: 10273.68 | N49: -1612.1483 | Q49: 16149.39 | S49: -5875.71
A50: Véhicules neufsDéduction à la source | B50: Véhicules neufs | C50: Déduction à la source | F50: 11815.684 | L50: 10461.01 | N50: -1354.6736 | Q50: 15963.55 | S50: -5502.54
A51: Véhicules neufsBénéfices marginaux | B51: Véhicules neufs | C51: Bénéfices marginaux | F51: 8274.0274 | L51: 6088.21 | N51: -2185.8174 | Q51: 3861.07 | S51: 2227.14
A52: Véhicules neufsCsst | B52: Véhicules neufs | C52: Csst | F52: 3952.7414 | L52: 1526.89 | N52: -2425.8514 | Q52: 3464 | S52: -1937.11
A53: Véhicules neufs[...] | B53: Véhicules neufs | C53: [...] | F53: 0 | L53: 0 | N53: 0 | Q53: 0 | S53: 0
A54: Véhicules neufsTOTAL PERSONNEL | B54: Véhicules neufs | C54: TOTAL PERSONNEL | D54: % brut | E54: 0.33453614 | F54: 71654.398 | J54: % brut | K54: 0.32829218 | L54: 65026.88 | N54: -6627.5184 | O54: % brut | P54: 0.34835328 | Q54: 66702 | S54: -1675.12
A55: Véhicules neufsPublicité 2 | B55: Véhicules neufs | C55: Publicité 2 | F55: 0 | L55: 0 | N55: 0 | Q55: 0 | S55: 0
A56: Véhicules neufsService gratuit 2 | B56: Véhicules neufs | C56: Service gratuit 2 | F56: 0 | L56: 0 | N56: 0 | Q56: 0 | S56: 0
A57: Véhicules neufsFrais véhicules de cie | B57: Véhicules neufs | C57: Frais véhicules de cie | F57: 7945.8333 | L57: 5210.85 | N57: -2734.9833 | Q57: 10992.77 | S57: -5781.92
A58: Véhicules neufsInformatique | B58: Véhicules neufs | C58: Informatique | F58: 6260.8664 | L58: 7114.48 | N58: 853.6136 | Q58: 9124.25 | S58: -2009.77
A59: Véhicules neufsFrais de déplacement | B59: Véhicules neufs | C59: Frais de déplacement | F59: 1000.088 | L59: 1420.02 | N59: 419.93196 | Q59: 1275.21 | S59: 144.81
A60: Véhicules neufsServices extérieurs | B60: Véhicules neufs | C60: Services extérieurs | F60: 6527.9741 | L60: 6350.63 | N60: -177.34413 | Q60: 6733.83 | S60: -383.2
A61: Véhicules neufsFournitures autres | B61: Véhicules neufs | C61: Fournitures autres | F61: 124.76419 | L61: 141.18 | N61: 16.41581 | Q61: 137.58 | S61: 3.6
A62: Véhicules neufsUniformes | B62: Véhicules neufs | C62: Uniformes | F62: 64.426805 | L62: 0 | N62: -64.426805 | Q62: 0 | S62: 0
A63: Véhicules neufsPapeterie | B63: Véhicules neufs | C63: Papeterie | F63: 763.45104 | L63: 751.79 | N63: -11.661035 | Q63: 903.86 | S63: -152.07
A64: Véhicules neufsTéléphone | B64: Véhicules neufs | C64: Téléphone | F64: 258.72025 | L64: 294.13 | N64: 35.40975 | Q64: 252.48 | S64: 41.65
A65: Véhicules neufsFrais postaux | B65: Véhicules neufs | C65: Frais postaux | F65: 123.74429 | L65: 133.46 | N65: 9.7157062 | Q65: 152.24 | S65: -18.78
A66: Véhicules neufsDivers | B66: Véhicules neufs | C66: Divers | F66: 470.18236 | L66: 199.88 | N66: -270.30236 | Q66: 151.58 | S66: 48.3
... A68: Véhicules neufsFrais bancaires | B68: Véhicules neufs | C68: Frais bancaires | F68: 929.83857 | L68: 3603.56 | N68: 2673.7214 | Q68: 3438.8235 | S68: 164.7365
A69: Véhicules neufs[...] | B69: Véhicules neufs | C69: [...] | F69: 0 | N69: 0 | Q69: 0 | S69: 0
A70: Véhicules neufs[...] | B70: Véhicules neufs | C70: [...] | F70: 0 | L70: 0 | N70: 0 | Q70: 0 | S70: 0
A71: Véhicules neufs[...] | B71: Véhicules neufs | C71: [...] | F71: 0 | L71: 0 | N71: 0 | Q71: 0 | S71: 0
A72: Véhicules neufsTOTAL SEMI-FIXES | B72: Véhicules neufs | C72: TOTAL SEMI-FIXES | D72: % brut | E72: 0.11710441 | F72: 25082.63 | J72: % brut | K72: 0.13562455 | L72: 26864 | N72: 1781.3703 | O72: % brut | P72: 0.18005885 | Q72: 34477.314 | S72: -7613.3135
A73: Véhicules neufs | B73: Véhicules neufs
A74: Véhicules neufsTOTAL DES DÉPENSES | B74: Véhicules neufs | C74: TOTAL DES DÉPENSES | D74: % brut | E74: 0.89819229 | F74: 192384.08 | J74: % brut | K74: 0.78385181 | L74: 155262.42 | N74: -37121.663 | O74: % brut | P74: 0.88081308 | Q74: 168656.35 | S74: -13393.933
A75: Véhicules neufsProgramme neuf 1 | B75: Véhicules neufs | C75: Programme neuf 1 | F75: 15729.13 | L75: 0 | N75: -15729.13 | Q75: 0
A76: Véhicules neufsProgramme neuf 2 | B76: Véhicules neufs | C76: Programme neuf 2 | F76: 0 | L76: 0 | N76: 0 | Q76: 0 | S76: 0
A77: Véhicules neufsProgramme neuf 3 | B77: Véhicules neufs | C77: Programme neuf 3 | F77: 0 | L77: 0 | N77: 0 | Q77: 0 | S77: 0
A78: Véhicules neufsHoldbacks | B78: Véhicules neufs | C78: Holdbacks | E78: 1181.3417 | F78: 66622.586 | K78: 1091.4444 | L78: 58938 | N78: -7684.5856 | Q78: 62788 | S78: -3850
A79: Véhicules neufs[...] | B79: Véhicules neufs | C79: [...] | F79: 0 | L79: 0 | N79: 0 | Q79: 0 | S79: 0
A80: Véhicules neufs[...] | B80: Véhicules neufs | C80: [...] | F80: 0 | L80: 0 | N80: 0 | Q80: 0 | S80: 0
A81: Véhicules neufs[...] | B81: Véhicules neufs | C81: [...] | F81: 0 | L81: 0 | N81: 0 | Q81: 0 | S81: 0
A82: Véhicules neufsFrais administration | B82: Véhicules neufs | C82: Frais administration | F82: 20990.414 | J82: 55 | K82: 466.63636 | L82: 25665 | N82: 4674.5864 | Q82: 19054 | S82: 6611
A83: Véhicules neufsAUTRES REVENUS | B83: Véhicules neufs | C83: AUTRES REVENUS | F83: 103342.13 | L83: 84603 | N83: -18739.129 | Q83: 81842 | S83: 2761
A84: Véhicules neufs | B84: Véhicules neufs
A85: Véhicules neufsPROFIT DÉPARTEMENTAL | B85: Véhicules neufs | C85: PROFIT DÉPARTEMENTAL | F85: 125148.35 | L85: 127416.82 | N85: 2268.4658 | Q85: 104663.68 | S85: 22753.144
C89: Volks | K89: Véhicules usagés | S89: Réalisé, Septembre 2023
D91: BUDGET ORIGINAL | J91: RÉALISATION | M91: ÉCART réel / Budget | O91: ANNÉE PRÉCÉDENTE | R91: ECART (réel/ Ann.Préc.)
D92: UNITÉS | E92: $P/UNITÉ | F92: $PROFITS | J92: UNITÉS | K92: $P/UNITE | L92: $PROFITS | M92: UNITÉS | N92: $PROFITS | O92: UNITÉS | P92: $P/UNITE | Q92: $PROFITS | R92: UNITÉS | S92: $PROFITS
A93: Véhicules usagésVentes nettes | B93: Véhicules usagés | C93: Ventes nettes | F93: 1587792.7 | L93: 1244144.3 | Q93: 1750102
A94: Véhicules usagésCertifié | B94: Véhicules usagés | C94: Certifié | D94: 38 | E94: 1858 | F94: 70604 | J94: 29 | K94: 1929.9779 | L94: 55969.36 | M94: -9 | N94: -14634.64 | O94: 34 | P94: 1821.8274 | Q94: 61942.13 | R94: -5 | S94: -5972.77
A95: Véhicules usagésNon Certifié | B95: Véhicules usagés | C95: Non Certifié | D95: 0 | E95: 0 | F95: 0 | J95: 4 | K95: 2172.4675 | L95: 8689.87 | M95: 4 | N95: 8689.87 | O95: 0 | P95: 0 | Q95: 0 | R95: 4 | S95: 8689.87
A96: Véhicules usagésTotal Usagés | B96: Véhicules usagés | C96: Total Usagés | D96: 38 | E96: 1858 | F96: 70604 | J96: 33 | K96: 1959.3706 | L96: 64659.23 | M96: -5 | N96: -5944.77 | O96: 34 | P96: 1821.8274 | Q96: 61942.13 | R96: -1 | S96: 2717.1
A97: Véhicules usagés | B97: Véhicules usagés | E97: 0 | M97: -0.13157895 | N97: -0.084198771 | R97: -0.029411765 | S97: 0.043865137
A98: Véhicules usagésUS | B98: Véhicules usagés | C98: US
A99: Véhicules usagésVentes au Gros | B99: Véhicules usagés | C99: Ventes au Gros | D99: 32.153846 | E99: 399 | F99: 12829.385 | J99: 26 | K99: 442.14423 | L99: 11495.75 | M99: -6.1538462 | N99: -1333.6346 | O99: 39 | P99: 400.72128 | Q99: 15628.13 | R99: -13 | S99: -4132.38
A100: Véhicules usagés | B100: Véhicules usagés
A101: Véhicules usagésRev. Finances | B101: Véhicules usagés | C101: Rev. Finances | D101: 0 | E101: 0 | F101: 19000 | K101: 444.83667 | L101: 14679.61 | N101: -4320.39 | P101: 769.67676 | Q101: 26169.01 | R101: -444.83667 | S101: -11489.4
A102: Véhicules usagésRev. Protections | B102: Véhicules usagés | C102: Rev. Protections | D102: 0 | E102: 0 | F102: 47500 | K102: 1292.9415 | L102: 42667.07 | N102: -4832.93 | P102: 1083.0562 | Q102: 36823.91 | R102: -1292.9415 | S102: 5843.16
A103: Véhicules usagésRev. Autres | B103: Véhicules usagés | C103: Rev. Autres | D103: 0 | E103: 0 | F103: 13300 | K103: 40.802424 | L103: 1346.48 | N103: -11953.52 | P103: 14.570294 | Q103: 495.39 | R103: -40.802424 | S103: 851.09
A104: Véhicules usagésTotal F&I | B104: Véhicules usagés | C104: Total F&I | D104: 38 | E104: 2100 | F104: 79800 | J104: 33 | K104: 1778.5806 | L104: 58693.16 | M104: -5 | N104: -21106.84 | O104: 34 | P104: 1867.3032 | Q104: 63488.31 | S104: -4795.15
A105: Véhicules usagés | B105: Véhicules usagés | N105: -0.26449674 | S105: -0.075528078
...

Sheet END
