Workbook
Name _Dates_Conc: [1]Dealers!$BF$37:$KA$63
Name _scen: '[1]Scen & Sens'!$E$26
Name _scen1: '[1]Scen & Sens'!$E$27
Name _scen2: '[1]Scen & Sens'!$E$28
Name _SCenarios: '[1]Scen & Sens'!$J$26:$O$26
Name _Sens1: '[1]Scen & Sens'!$F$9
Name _Sens2: '[1]Scen & Sens'!$F$10
Name _sensRes1: '[1]Scen & Sens'!$E$15
Name _sensRes2: '[1]Scen & Sens'!$E$16
Name _sensRes3: '[1]Scen & Sens'!$E$17
Name _sensRes4: '[1]Scen & Sens'!$E$18
Name _sensRes5: '[1]Scen & Sens'!$E$19
Name _sensRes6: '[1]Scen & Sens'!$E$20
Name _sensRes7: '[1]Scen & Sens'!$E$21
Name DateRange: [1]Volkswagen!$BF$6:$DY$6
Name Monetary_Unit: [1]Parameters!$B$15
Name Months: [1]Parameters!$E$9:$E$20
Name Rng_Dealers_Names: [1]!Tbl_Dealers[Dealer Name]
Name Rng_Dlr_Dates: [1]!Tbl_V_Dlr_Dates[Date]
Name Titre: [1]Front!$A$9

Sheet Parametres
A1: Compagnie | B1: Volks
G2: 1-Mémo | M2: Mois | N2: YTD
A3: Mois Courant | B3: Mars | C3: =+VLOOKUP(B3,$K$3:$L$14,2,0) -> 3 | G3: 10-Compte compteur | K3: Janvier | L3: 1 | M3: =+IF($K3=$B$3,"X","") | N3: =+IF(K3=B3,"X",IF(L3<=$C$3,"X","")) -> X
A4: Année | B4: 2021 | K4: Février | L4: 2 | M4: =+IF($K4=$B$3,"X","") | N4: =+IF(K4=B4,"X",IF(L4<=$C$3,"X","")) -> X
K5: Mars | L5: 3 | M5: =+IF($K5=$B$3,"X","") -> X | N5: =+IF(K5=B5,"X",IF(L5<=$C$3,"X","")) -> X
K6: Avril | L6: 4 | M6: =+IF($K6=$B$3,"X","") | N6: =+IF(K6=B6,"X",IF(L6<=$C$3,"X",""))
K7: Mai | L7: 5 | M7: =+IF($K7=$B$3,"X","") | N7: =+IF(K7=B7,"X",IF(L7<=$C$3,"X",""))
K8: Juin | L8: 6 | M8: =+IF($K8=$B$3,"X","") | N8: =+IF(K8=B8,"X",IF(L8<=$C$3,"X",""))
A9: Sélectionner le mois en B3 | K9: Juillet | L9: 7 | M9: =+IF($K9=$B$3,"X","") | N9: =+IF(K9=B9,"X",IF(L9<=$C$3,"X",""))
A10: Coller les balances de vérification respectives en cellule A1 dans les onglets BV_Data_An_Cour et BV_Data_An_Prec | K10: Août | L10: 8 | M10: =+IF($K10=$B$3,"X","") | N10: =+IF(K10=B10,"X",IF(L10<=$C$3,"X",""))
A11: Vérifier s'il y a des #N/A dans les colonnes T à X des onlgets de BV | K11: Septembre | L11: 9 | M11: =+IF($K11=$B$3,"X","") | N11: =+IF(K11=B11,"X",IF(L11<=$C$3,"X",""))
A12: Vérifier les chiffres avec l'état financier et les réalisés an passé pour les résultat net mois et aad | K12: Octobre | L12: 10 | M12: =+IF($K12=$B$3,"X","") | N12: =+IF(K12=B12,"X",IF(L12<=$C$3,"X",""))
K13: Novembre | L13: 11 | M13: =+IF($K13=$B$3,"X","") | N13: =+IF(K13=B13,"X",IF(L13<=$C$3,"X",""))
K14: Décembre | L14: 12 | M14: =+IF($K14=$B$3,"X","") | N14: =+IF(K14=B14,"X",IF(L14<=$C$3,"X",""))

Sheet Bilan
A1: BILAN
A2: =+Parametres!B1 -> Volks
A3: =CONCATENATE("",,Parametres!B3," ",Parametres!B4) -> Mars 2021
A5: Encaisse | B5: =SUMIFS(BV_Data_An_Cour!$P:$P,BV_Data_An_Cour!$U:$U,$A$1,BV_Data_An_Cour!$V:$V,$A5) -> 2208856.3 | D5: Marge de crédit | E5: =-SUMIFS(BV_Data_An_Cour!$P:$P,BV_Data_An_Cour!$U:$U,$A$1,BV_Data_An_Cour!$V:$V,$D5) -> 0
A6: Total Trésorerie et équivalent de Trésorerie | B6: =SUM(B5) -> 2208856.3
D7: Portion Court Terme de la Dette Long Terme | E7: =-SUMIFS(BV_Data_An_Cour!$P:$P,BV_Data_An_Cour!$U:$U,$A$1,BV_Data_An_Cour!$V:$V,$D7) -> 15810
A8: Recevables Contrats en Transit | B8: =SUMIFS(BV_Data_An_Cour!$P:$P,BV_Data_An_Cour!$U:$U,$A$1,BV_Data_An_Cour!$V:$V,$A8) -> 2230376.1
A9: Recevables Véhicules | B9: =SUMIFS(BV_Data_An_Cour!$P:$P,BV_Data_An_Cour!$U:$U,$A$1,BV_Data_An_Cour!$V:$V,$A9) -> 216729.42 | D9: Avances à payer | E9: =-SUMIFS(BV_Data_An_Cour!$P:$P,BV_Data_An_Cour!$U:$U,$A$1,BV_Data_An_Cour!$V:$V,$D9) -> 0
A10: Recevables Manufacturier | B10: =SUMIFS(BV_Data_An_Cour!$P:$P,BV_Data_An_Cour!$U:$U,$A$1,BV_Data_An_Cour!$V:$V,$A10) -> 262318.72 | D10: Comptes à Payer Fournisseurs | E10: =-SUMIFS(BV_Data_An_Cour!$P:$P,BV_Data_An_Cour!$U:$U,$A$1,BV_Data_An_Cour!$V:$V,$D10) -> 75113.78
A11: Recevables Pièces et Service | B11: =SUMIFS(BV_Data_An_Cour!$P:$P,BV_Data_An_Cour!$U:$U,$A$1,BV_Data_An_Cour!$V:$V,$A11) -> 11720.5 | D11: Taxes de Vente à Payer | E11: =-SUMIFS(BV_Data_An_Cour!$P:$P,BV_Data_An_Cour!$U:$U,$A$1,BV_Data_An_Cour!$V:$V,$D11) -> 79114.99
A12: Recevables Garantie Manufacturier | B12: =SUMIFS(BV_Data_An_Cour!$P:$P,BV_Data_An_Cour!$U:$U,$A$1,BV_Data_An_Cour!$V:$V,$A12) -> 41335.66 | D12: Impôts à payer | E12: =-SUMIFS(BV_Data_An_Cour!$P:$P,BV_Data_An_Cour!$U:$U,$A$1,BV_Data_An_Cour!$V:$V,$D12) -> 0
A13: Recevables Carrosserie | B13: =SUMIFS(BV_Data_An_Cour!$P:$P,BV_Data_An_Cour!$U:$U,$A$1,BV_Data_An_Cour!$V:$V,$A13) -> 49488.46 | D13: Dépôts de Client | E13: =-SUMIFS(BV_Data_An_Cour!$P:$P,BV_Data_An_Cour!$U:$U,$A$1,BV_Data_An_Cour!$V:$V,$D13) -> 5450
A14: Recevables Intercos | B14: =SUMIFS(BV_Data_An_Cour!$P:$P,BV_Data_An_Cour!$U:$U,$A$1,BV_Data_An_Cour!$V:$V,$A14) -> 0 | D14: Payables Intercos | E14: =-SUMIFS(BV_Data_An_Cour!$P:$P,BV_Data_An_Cour!$U:$U,$A$1,BV_Data_An_Cour!$V:$V,$D14) -> 0
A15: Recevables Autres | B15: =SUMIFS(BV_Data_An_Cour!$P:$P,BV_Data_An_Cour!$U:$U,$A$1,BV_Data_An_Cour!$V:$V,$A15) -> 128036.83 | D15: Autres Comptes à Payer | E15: =-SUMIFS(BV_Data_An_Cour!$P:$P,BV_Data_An_Cour!$U:$U,$A$1,BV_Data_An_Cour!$V:$V,$D15) -> 759599.57
A16: Total Comptes à Recevoir | B16: =+SUM(B8:B15) -> 2940005.7 | D16: Total Comptes à Payer | E16: =+SUM(E10:E15) -> 919278.34
A18: Inventaire Véhicules Neufs | B18: =SUMIFS(BV_Data_An_Cour!$P:$P,BV_Data_An_Cour!$U:$U,$A$1,BV_Data_An_Cour!$V:$V,$A18) -> 5406498.6 | D18: Effet à Payer Véhicules Neufs | E18: =-SUMIFS(BV_Data_An_Cour!$P:$P,BV_Data_An_Cour!$U:$U,$A$1,BV_Data_An_Cour!$V:$V,$D18) -> 7036543.5
A19: Inventaire Véhicules Usagés | B19: =SUMIFS(BV_Data_An_Cour!$P:$P,BV_Data_An_Cour!$U:$U,$A$1,BV_Data_An_Cour!$V:$V,$A19) -> 1545206.7 | D19: Effet à Payer Véhicules Usagés | E19: =-SUMIFS(BV_Data_An_Cour!$P:$P,BV_Data_An_Cour!$U:$U,$A$1,BV_Data_An_Cour!$V:$V,$D19) -> 286517.08
A20: Inventaire Pièces, Pneus, Huile | B20: =SUMIFS(BV_Data_An_Cour!$P:$P,BV_Data_An_Cour!$U:$U,$A$1,BV_Data_An_Cour!$V:$V,$A20) -> 383225.37 | D20: Total Effets à Payer | E20: =+SUM(E18:E19) -> 7323060.6
A21: Total Inventaires | B21: =SUM(B18:B20) -> 7334930.7
D22: Salaires à Payer | E22: =-SUMIFS(BV_Data_An_Cour!$P:$P,BV_Data_An_Cour!$U:$U,$A$1,BV_Data_An_Cour!$V:$V,$D22) -> 389840.6
A23: Avances à recevoir | B23: =SUMIFS(BV_Data_An_Cour!$P:$P,BV_Data_An_Cour!$U:$U,$A$1,BV_Data_An_Cour!$V:$V,$A23) -> 0 | D23: DAS à Payer | E23: =-SUMIFS(BV_Data_An_Cour!$P:$P,BV_Data_An_Cour!$U:$U,$A$1,BV_Data_An_Cour!$V:$V,$D23) -> 23855.95
A24: Travaux en Cours | B24: =SUMIFS(BV_Data_An_Cour!$P:$P,BV_Data_An_Cour!$U:$U,$A$1,BV_Data_An_Cour!$V:$V,$A24) -> 9187.7 | D24: Autres Courus | E24: =-SUMIFS(BV_Data_An_Cour!$P:$P,BV_Data_An_Cour!$U:$U,$A$1,BV_Data_An_Cour!$V:$V,$D24) -> 40040.82
A25: Sous-Traitance | B25: =SUMIFS(BV_Data_An_Cour!$P:$P,BV_Data_An_Cour!$U:$U,$A$1,BV_Data_An_Cour!$V:$V,$A25) -> -3164.81 | D25: [...] | E25: =-SUMIFS(BV_Data_An_Cour!$P:$P,BV_Data_An_Cour!$U:$U,$A$1,BV_Data_An_Cour!$V:$V,$D25) -> 0
A26: Frais Payés d'Avance | B26: =SUMIFS(BV_Data_An_Cour!$P:$P,BV_Data_An_Cour!$U:$U,$A$1,BV_Data_An_Cour!$V:$V,$A26) -> 133193.71 | D26: [...] | E26: =-SUMIFS(BV_Data_An_Cour!$P:$P,BV_Data_An_Cour!$U:$U,$A$1,BV_Data_An_Cour!$V:$V,$D26) -> 0
A27: [...] | B27: =SUMIFS(BV_Data_An_Cour!$P:$P,BV_Data_An_Cour!$U:$U,$A$1,BV_Data_An_Cour!$V:$V,$A27) -> 0 | D27: [...] | E27: =-SUMIFS(BV_Data_An_Cour!$P:$P,BV_Data_An_Cour!$U:$U,$A$1,BV_Data_An_Cour!$V:$V,$D27) -> 0
A28: [...] | B28: =SUMIFS(BV_Data_An_Cour!$P:$P,BV_Data_An_Cour!$U:$U,$A$1,BV_Data_An_Cour!$V:$V,$A28) -> 0 | D28: Total Frais Courus | E28: =SUM(E22:E24) -> 453737.37
A29: [...] | B29: =SUMIFS(BV_Data_An_Cour!$P:$P,BV_Data_An_Cour!$U:$U,$A$1,BV_Data_An_Cour!$V:$V,$A29) -> 0
A30: Total Autres | B30: =SUM(B23:B29) -> 139216.6 | D30: Total Passif Court Terme | E30: =+E5+E7+E16+E20+E28 -> 8711886.3
A32: Total Actif Court Terme | B32: =+B6+B16+B21+B30 -> 12623009
D33: Impôts Futurs à payer | E33: =-SUMIFS(BV_Data_An_Cour!$P:$P,BV_Data_An_Cour!$U:$U,$A$1,BV_Data_An_Cour!$V:$V,$D33) -> 0
A35: Terrain | B35: =SUMIFS(BV_Data_An_Cour!$P:$P,BV_Data_An_Cour!$U:$U,$A$1,BV_Data_An_Cour!$V:$V,$A35) -> 0 | D35: Avances Long Terme à Payer | E35: =-SUMIFS(BV_Data_An_Cour!$P:$P,BV_Data_An_Cour!$U:$U,$A$1,BV_Data_An_Cour!$V:$V,$D35) -> 0
A36: Bâtisse | B36: =SUMIFS(BV_Data_An_Cour!$P:$P,BV_Data_An_Cour!$U:$U,$A$1,BV_Data_An_Cour!$V:$V,$A36) -> 0 | D36: Hypothèque à Payer | E36: =-SUMIFS(BV_Data_An_Cour!$P:$P,BV_Data_An_Cour!$U:$U,$A$1,BV_Data_An_Cour!$V:$V,$D36) -> 0
A37: Améliorations Locatives | B37: =SUMIFS(BV_Data_An_Cour!$P:$P,BV_Data_An_Cour!$U:$U,$A$1,BV_Data_An_Cour!$V:$V,$A37) -> -2490.69 | D37: Dette à Long Terme | E37: =-SUMIFS(BV_Data_An_Cour!$P:$P,BV_Data_An_Cour!$U:$U,$A$1,BV_Data_An_Cour!$V:$V,$D37) -> 24206.25
A38: Améliorations Locatives Permanentes | B38: =SUMIFS(BV_Data_An_Cour!$P:$P,BV_Data_An_Cour!$U:$U,$A$1,BV_Data_An_Cour!$V:$V,$A38) -> 0 | D38: Autres Dettes à Long Terme | E38: =-SUMIFS(BV_Data_An_Cour!$P:$P,BV_Data_An_Cour!$U:$U,$A$1,BV_Data_An_Cour!$V:$V,$D38) -> 0
A39: Équipements Service | B39: =SUMIFS(BV_Data_An_Cour!$P:$P,BV_Data_An_Cour!$U:$U,$A$1,BV_Data_An_Cour!$V:$V,$A39) -> 176871.8 | D39: [...] | E39: =-SUMIFS(BV_Data_An_Cour!$P:$P,BV_Data_An_Cour!$U:$U,$A$1,BV_Data_An_Cour!$V:$V,$D39) -> 0
A40: Mobilier | B40: =SUMIFS(BV_Data_An_Cour!$P:$P,BV_Data_An_Cour!$U:$U,$A$1,BV_Data_An_Cour!$V:$V,$A40) -> 33213.95 | D40: [...] | E40: =-SUMIFS(BV_Data_An_Cour!$P:$P,BV_Data_An_Cour!$U:$U,$A$1,BV_Data_An_Cour!$V:$V,$D40) -> 0
A41: Équipements Informatique | B41: =SUMIFS(BV_Data_An_Cour!$P:$P,BV_Data_An_Cour!$U:$U,$A$1,BV_Data_An_Cour!$V:$V,$A41) -> 21605.62 | D41: [...] | E41: =-SUMIFS(BV_Data_An_Cour!$P:$P,BV_Data_An_Cour!$U:$U,$A$1,BV_Data_An_Cour!$V:$V,$D41) -> 0
A42: Équipements Téléphonique | B42: =SUMIFS(BV_Data_An_Cour!$P:$P,BV_Data_An_Cour!$U:$U,$A$1,BV_Data_An_Cour!$V:$V,$A42) -> 60 | D42: Total Passif long terme | E42: =+SUM(E33:E38) -> 24206.25
A43: Enseigne | B43: =SUMIFS(BV_Data_An_Cour!$P:$P,BV_Data_An_Cour!$U:$U,$A$1,BV_Data_An_Cour!$V:$V,$A43) -> -554.99
A44: Total Immobilisations Nettes | B44: =SUM(B35:B43) -> 228705.69
D45: Total Passifs | E45: =+E42+E30 -> 8736092.6
A46: Avances à Recevoir Long Terme | B46: =SUMIFS(BV_Data_An_Cour!$P:$P,BV_Data_An_Cour!$U:$U,$A$1,BV_Data_An_Cour!$V:$V,$A46) -> 1623600
A48: Achalandage | B48: =SUMIFS(BV_Data_An_Cour!$P:$P,BV_Data_An_Cour!$U:$U,$A$1,BV_Data_An_Cour!$V:$V,$A48) -> 0 | D48: Capital Actions | E48: =-SUMIFS(BV_Data_An_Cour!$P:$P,BV_Data_An_Cour!$U:$U,$A$1,BV_Data_An_Cour!$V:$V,$D48) -> 2697547.5
D49: Apport | E49: =-SUMIFS(BV_Data_An_Cour!$P:$P,BV_Data_An_Cour!$U:$U,$A$1,BV_Data_An_Cour!$V:$V,$D49) -> 1723617
A50: [...] | B50: =SUMIFS(BV_Data_An_Cour!$P:$P,BV_Data_An_Cour!$U:$U,$A$1,BV_Data_An_Cour!$V:$V,$A50) -> 0 | D50: Bénéfices non répartis | E50: =-SUMIFS(BV_Data_An_Cour!$P:$P,BV_Data_An_Cour!$U:$U,$A$1,BV_Data_An_Cour!$V:$V,$D50)+Print_AAD!AF497 -> #VALUE!
A51: [...] | B51: =SUMIFS(BV_Data_An_Cour!$P:$P,BV_Data_An_Cour!$U:$U,$A$1,BV_Data_An_Cour!$V:$V,$A51) -> 0 | D51: Dividendes | E51: =-SUMIFS(BV_Data_An_Cour!$P:$P,BV_Data_An_Cour!$U:$U,$A$1,BV_Data_An_Cour!$V:$V,$D51) -> 0
A52: [...] | B52: =SUMIFS(BV_Data_An_Cour!$P:$P,BV_Data_An_Cour!$U:$U,$A$1,BV_Data_An_Cour!$V:$V,$A52) -> 0
A53: Total Actif Long Terme | B53: =+B44+B48+B46 -> 1852305.7 | D53: Total Capitaux Propres / Avoir | E53: =SUM(E48:E51) -> #VALUE!
A56: Total Actif | B56: =+B32+B53 -> 14475315 | D56: Total Passif et Capitaux Propres / Avoir | E56: =+E53+E45 -> #VALUE!
E65: =+B56-E56 -> #VALUE!

Sheet Budget original
B1: ="Budget 2021 Mensuel"&" "&Parametres!$B$1 -> Budget 2021 Mensuel Volks
B2: Mois | F2: =+IF(Parametres!$B$3=F$6,"X","") | G2: =+IF(Parametres!$B$3=F$6,"O","") | H2: =+IF(Parametres!$B$3=F$6,"U","") | I2: =+IF(Parametres!$B$3=I$6,"X","") | J2: =+IF(Parametres!$B$3=I$6,"O","") | K2: =+IF(Parametres!$B$3=I$6,"U","") | L2: =+IF(Parametres!$B$3=L$6,"X","") -> X | M2: =+IF(Parametres!$B$3=L$6,"O","") -> O | N2: =+IF(Parametres!$B$3=L$6,"U","") -> U | O2: =+IF(Parametres!$B$3=O$6,"X","") | P2: =+IF(Parametres!$B$3=O$6,"O","") | Q2: =+IF(Parametres!$B$3=O$6,"U","") | R2: =+IF(Parametres!$B$3=R$6,"X","") | S2: =+IF(Parametres!$B$3=R$6,"O","") | T2: =+IF(Parametres!$B$3=R$6,"U","") | U2: =+IF(Parametres!$B$3=U$6,"X","") | V2: =+IF(Parametres!$B$3=U$6,"O","") | W2: =+IF(Parametres!$B$3=U$6,"U","") | X2: =+IF(Parametres!$B$3=X$6,"X","") | Y2: =+IF(Parametres!$B$3=X$6,"O","") | Z2: =+IF(Parametres!$B$3=X$6,"U","") | AA2: =+IF(Parametres!$B$3=AA$6,"X","") | AB2: =+IF(Parametres!$B$3=AA$6,"O","") | AC2: =+IF(Parametres!$B$3=AA$6,"U","") | AD2: =+IF(Parametres!$B$3=AD$6,"X","") | AE2: =+IF(Parametres!$B$3=AD$6,"O","") | AF2: =+IF(Parametres!$B$3=AD$6,"U","") | AG2: =+IF(Parametres!$B$3=AG$6,"X","") | AH2: =+IF(Parametres!$B$3=AG$6,"O","") | AI2: =+IF(Parametres!$B$3=AG$6,"U","") | AJ2: =+IF(Parametres!$B$3=AJ$6,"X","") | AK2: =+IF(Parametres!$B$3=AJ$6,"O","") | AL2: =+IF(Parametres!$B$3=AJ$6,"U","") | AM2: =+IF(Parametres!$B$3=AM$6,"X","") | AN2: =+IF(Parametres!$B$3=AM$6,"O","") | AO2: =+IF(Parametres!$B$3=AM$6,"U","")
B3: YTD | F3: =+IF(VLOOKUP(F$6,Parametres!$K$3:$N$14,4,0)="X","X","") -> X | G3: =+IF(VLOOKUP(F$6,Parametres!$K$3:$N$14,4,0)="X","O","") -> O | H3: =+IF(VLOOKUP(F$6,Parametres!$K$3:$N$14,4,0)="X","U","") -> U | I3: =+IF(VLOOKUP(I$6,Parametres!$K$3:$N$14,4,0)="X","X","") -> X | J3: =+IF(VLOOKUP(I$6,Parametres!$K$3:$N$14,4,0)="X","O","") -> O | K3: =+IF(VLOOKUP(I$6,Parametres!$K$3:$N$14,4,0)="X","U","") -> U | L3: =+IF(VLOOKUP(L$6,Parametres!$K$3:$N$14,4,0)="X","X","") -> X | M3: =+IF(VLOOKUP(L$6,Parametres!$K$3:$N$14,4,0)="X","O","") -> O | N3: =+IF(VLOOKUP(L$6,Parametres!$K$3:$N$14,4,0)="X","U","") -> U | O3: =+IF(VLOOKUP(O$6,Parametres!$K$3:$N$14,4,0)="X","X","") | P3: =+IF(VLOOKUP(O$6,Parametres!$K$3:$N$14,4,0)="X","O","") | Q3: =+IF(VLOOKUP(O$6,Parametres!$K$3:$N$14,4,0)="X","U","") | R3: =+IF(VLOOKUP(R$6,Parametres!$K$3:$N$14,4,0)="X","X","") | S3: =+IF(VLOOKUP(R$6,Parametres!$K$3:$N$14,4,0)="X","O","") | T3: =+IF(VLOOKUP(R$6,Parametres!$K$3:$N$14,4,0)="X","U","") | U3: =+IF(VLOOKUP(U$6,Parametres!$K$3:$N$14,4,0)="X","X","") | V3: =+IF(VLOOKUP(U$6,Parametres!$K$3:$N$14,4,0)="X","O","") | W3: =+IF(VLOOKUP(U$6,Parametres!$K$3:$N$14,4,0)="X","U","") | X3: =+IF(VLOOKUP(X$6,Parametres!$K$3:$N$14,4,0)="X","X","") | Y3: =+IF(VLOOKUP(X$6,Parametres!$K$3:$N$14,4,0)="X","O","") | Z3: =+IF(VLOOKUP(X$6,Parametres!$K$3:$N$14,4,0)="X","U","") | AA3: =+IF(VLOOKUP(AA$6,Parametres!$K$3:$N$14,4,0)="X","X","") | AB3: =+IF(VLOOKUP(AA$6,Parametres!$K$3:$N$14,4,0)="X","O","") | AC3: =+IF(VLOOKUP(AA$6,Parametres!$K$3:$N$14,4,0)="X","U","") | AD3: =+IF(VLOOKUP(AD$6,Parametres!$K$3:$N$14,4,0)="X","X","") | AE3: =+IF(VLOOKUP(AD$6,Parametres!$K$3:$N$14,4,0)="X","O","") | AF3: =+IF(VLOOKUP(AD$6,Parametres!$K$3:$N$14,4,0)="X","U","") | AG3: =+IF(VLOOKUP(AG$6,Parametres!$K$3:$N$14,4,0)="X","X","") | AH3: =+IF(VLOOKUP(AG$6,Parametres!$K$3:$N$14,4,0)="X","O","") | AI3: =+IF(VLOOKUP(AG$6,Parametres!$K$3:$N$14,4,0)="X","U","") | AJ3: =+IF(VLOOKUP(AJ$6,Parametres!$K$3:$N$14,4,0)="X","X","") | AK3: =+IF(VLOOKUP(AJ$6,Parametres!$K$3:$N$14,4,0)="X","O","") | AL3: =+IF(VLOOKUP(AJ$6,Parametres!$K$3:$N$14,4,0)="X","U","") | AM3: =+IF(VLOOKUP(AM$6,Parametres!$K$3:$N$14,4,0)="X","X","") | AN3: =+IF(VLOOKUP(AM$6,Parametres!$K$3:$N$14,4,0)="X","O","") | AO3: =+IF(VLOOKUP(AM$6,Parametres!$K$3:$N$14,4,0)="X","U","")
B4: Budget 2021 | C4: Véhicules neufs
B6: Mois | C6: TOTAL | F6: Janvier | I6: Février | L6: Mars | O6: Avril | R6: Mai | U6: Juin | X6: Juillet | AA6: Août | AD6: Septembre | AG6: Octobre | AJ6: Novembre | AM6: Décembre
C7: UNITE | D7: $P/UNITE | E7: $PROFITS | F7: UNITE | G7: $P/UNITE | H7: $PROFITS | I7: UNITE | J7: $P/UNITE | K7: $PROFITS | L7: UNITE | M7: $P/UNITE | N7: $PROFITS | O7: UNITE | P7: $P/UNITE | Q7: $PROFITS | R7: UNITE | S7: $P/UNITE | T7: $PROFITS | U7: UNITE | V7: $P/UNITE | W7: $PROFITS | X7: UNITE | Y7: $P/UNITE | Z7: $PROFITS | AA7: UNITE | AB7: $P/UNITE | AC7: $PROFITS | AD7: UNITE | AE7: $P/UNITE | AF7: $PROFITS | AG7: UNITE | AH7: $P/UNITE | AI7: $PROFITS | AJ7: UNITE | AK7: $P/UNITE | AL7: $PROFITS | AM7: UNITE | AN7: $P/UNITE | AO7: $PROFITS
A8: =+$C$4&B8 -> Véhicules neufsVentes nettes | B8: Ventes nettes | E8: =+SUM(H8,K8,N8,Q8,T8,W8,Z8,AC8,AF8,AI8,AL8,AO8) -> 9553310.1 | H8: 1882577.9 | K8: 446219.11 | N8: 678330.08 | Q8: 751340.66 | T8: 981796.55 | W8: 691716.4 | Z8: 688676.89 | AC8: 729220.97 | AF8: 799077.54 | AI8: 991144.07 | AL8: 576007.02 | AO8: 337202.89
A9: =+$C$4&B9 -> Véhicules neufsAutos détail | B9: Autos détail | C9: =+SUM(F9,I9,L9,O9,R9,U9,X9,AA9,AD9,AG9,AJ9,AM9) -> 303 | D9: =IF(C9=0,0,E9/C9) -> 604.29043 | E9: =+SUM(H9,K9,N9,Q9,T9,W9,Z9,AC9,AF9,AI9,AL9,AO9) -> 183100 | F9: 23.607096 | G9: =IF(F9=0,0,H9/F9) -> 604.29043 | H9: 14265.542 | I9: 16.252745 | J9: =IF(I9=0,0,K9/I9) -> 604.29043 | K9: 9821.3783 | L9: 24.706978 | M9: =IF(L9=0,0,N9/L9) -> 604.29043 | N9: 14930.19 | O9: 27.36626 | P9: =IF(O9=0,0,Q9/O9) -> 604.29043 | Q9: 16537.169 | R9: 35.76021 | S9: =IF(R9=0,0,T9/R9) -> 604.29043 | T9: 21609.552 | U9: 25.194551 | V9: =IF(U9=0,0,W9/U9) -> 604.29043 | W9: 15224.826 | X9: 25.083842 | Y9: =IF(X9=0,0,Z9/X9) -> 604.29043 | Z9: 15157.926 | AA9: 26.560589 | AB9: =IF(AA9=0,0,AC9/AA9) -> 604.29043 | AC9: 16050.31 | AD9: 29.104991 | AE9: =IF(AD9=0,0,AF9/AD9) -> 604.29043 | AF9: 17587.868 | AG9: 36.100676 | AH9: =IF(AG9=0,0,AI9/AG9) -> 604.29043 | AI9: 21815.293 | AJ9: 20.980041 | AK9: =IF(AJ9=0,0,AL9/AJ9) -> 604.29043 | AL9: 12678.038 | AM9: 12.282021 | AN9: =IF(AM9=0,0,AO9/AM9) -> 604.29043 | AO9: 7421.9079
A10: =+$C$4&B10 -> Véhicules neufsCamions détail | B10: Camions détail | C10: =+SUM(F10,I10,L10,O10,R10,U10,X10,AA10,AD10,AG10,AJ10,AM10) -> 407 | D10: =IF(C10=0,0,E10/C10) -> 1315.4791 | E10: =+SUM(H10,K10,N10,Q10,T10,W10,Z10,AC10,AF10,AI10,AL10,AO10) -> 535400 | F10: 31.709861 | G10: =IF(F10=0,0,H10/F10) -> 1315.4791 | H10: 41713.66 | I10: 21.831245 | J10: =IF(I10=0,0,K10/I10) -> 1315.4791 | K10: 28718.547 | L10: 33.187261 | M10: =IF(L10=0,0,N10/L10) -> 1315.4791 | N10: 43657.149 | O10: 36.759299 | P10: =IF(O10=0,0,Q10/O10) -> 1315.4791 | Q10: 48356.09 | R10: 48.034341 | S10: =IF(R10=0,0,T10/R10) -> 1315.4791 | T10: 63188.172 | U10: 33.842186 | V10: =IF(U10=0,0,W10/U10) -> 1315.4791 | W10: 44518.688 | X10: 33.693478 | Y10: =IF(X10=0,0,Z10/X10) -> 1315.4791 | Z10: 44323.067 | AA10: 35.677095 | AB10: =IF(AA10=0,0,AC10/AA10) -> 1315.4791 | AC10: 46932.473 | AD10: 39.094824 | AE10: =IF(AD10=0,0,AF10/AD10) -> 1315.4791 | AF10: 51428.424 | AG10: 48.491668 | AH10: =IF(AG10=0,0,AI10/AG10) -> 1315.4791 | AI10: 63789.776 | AJ10: 28.181111 | AK10: =IF(AJ10=0,0,AL10/AJ10) -> 1315.4791 | AL10: 37071.663 | AM10: 16.497633 | AN10: =IF(AM10=0,0,AO10/AM10) -> 1315.4791 | AO10: 21702.291
A11: =+$C$4&B11 -> Véhicules neufsSprinter | B11: Sprinter | C11: =+SUM(F11,I11,L11,O11,R11,U11,X11,AA11,AD11,AG11,AJ11,AM11) -> 0 | D11: =IF(C11=0,0,E11/C11) -> 0 | E11: =+SUM(H11,K11,N11,Q11,T11,W11,Z11,AC11,AF11,AI11,AL11,AO11) -> 0 | G11: =IF(F11=0,0,H11/F11) -> 0 | J11: =IF(I11=0,0,K11/I11) -> 0 | M11: =IF(L11=0,0,N11/L11) -> 0 | P11: =IF(O11=0,0,Q11/O11) -> 0 | S11: =IF(R11=0,0,T11/R11) -> 0 | V11: =IF(U11=0,0,W11/U11) -> 0 | Y11: =IF(X11=0,0,Z11/X11) -> 0 | AB11: =IF(AA11=0,0,AC11/AA11) -> 0 | AE11: =IF(AD11=0,0,AF11/AD11) -> 0 | AH11: =IF(AG11=0,0,AI11/AG11) -> 0 | AK11: =IF(AJ11=0,0,AL11/AJ11) -> 0 | AN11: =IF(AM11=0,0,AO11/AM11) -> 0
A12: =+$C$4&B12 -> Véhicules neufsMoto détail | B12: Moto détail | C12: =+SUM(F12,I12,L12,O12,R12,U12,X12,AA12,AD12,AG12,AJ12,AM12) -> 0 | D12: =IF(C12=0,0,E12/C12) -> 0 | E12: =+SUM(H12,K12,N12,Q12,T12,W12,Z12,AC12,AF12,AI12,AL12,AO12) -> 0 | G12: =IF(F12=0,0,H12/F12) -> 0 | J12: =IF(I12=0,0,K12/I12) -> 0 | M12: =IF(L12=0,0,N12/L12) -> 0 | P12: =IF(O12=0,0,Q12/O12) -> 0 | S12: =IF(R12=0,0,T12/R12) -> 0 | V12: =IF(U12=0,0,W12/U12) -> 0 | Y12: =IF(X12=0,0,Z12/X12) -> 0 | AB12: =IF(AA12=0,0,AC12/AA12) -> 0 | AE12: =IF(AD12=0,0,AF12/AD12) -> 0 | AH12: =IF(AG12=0,0,AI12/AG12) -> 0 | AK12: =IF(AJ12=0,0,AL12/AJ12) -> 0 | AN12: =IF(AM12=0,0,AO12/AM12) -> 0
A13: =+$C$4&B13 -> Véhicules neufs[...] | B13: [...] | C13: =+SUM(F13,I13,L13,O13,R13,U13,X13,AA13,AD13,AG13,AJ13,AM13) -> 0 | D13: =IF(C13=0,0,E13/C13) -> 0 | E13: =+SUM(H13,K13,N13,Q13,T13,W13,Z13,AC13,AF13,AI13,AL13,AO13) -> 0 | G13: =IF(F13=0,0,H13/F13) -> 0 | J13: =IF(I13=0,0,K13/I13) -> 0 | M13: =IF(L13=0,0,N13/L13) -> 0 | P13: =IF(O13=0,0,Q13/O13) -> 0 | S13: =IF(R13=0,0,T13/R13) -> 0 | V13: =IF(U13=0,0,W13/U13) -> 0 | Y13: =IF(X13=0,0,Z13/X13) -> 0 | AB13: =IF(AA13=0,0,AC13/AA13) -> 0 | AE13: =IF(AD13=0,0,AF13/AD13) -> 0 | AH13: =IF(AG13=0,0,AI13/AG13) -> 0 | AK13: =IF(AJ13=0,0,AL13/AJ13) -> 0 | AN13: =IF(AM13=0,0,AO13/AM13) -> 0
A14: =+$C$4&B14 -> Véhicules neufs[...] | B14: [...] | C14: =+SUM(F14,I14,L14,O14,R14,U14,X14,AA14,AD14,AG14,AJ14,AM14) -> 0 | D14: =IF(C14=0,0,E14/C14) -> 0 | E14: =+SUM(H14,K14,N14,Q14,T14,W14,Z14,AC14,AF14,AI14,AL14,AO14) -> 0 | G14: =IF(F14=0,0,H14/F14) -> 0 | J14: =IF(I14=0,0,K14/I14) -> 0 | M14: =IF(L14=0,0,N14/L14) -> 0 | P14: =IF(O14=0,0,Q14/O14) -> 0 | S14: =IF(R14=0,0,T14/R14) -> 0 | V14: =IF(U14=0,0,W14/U14) -> 0 | Y14: =IF(X14=0,0,Z14/X14) -> 0 | AB14: =IF(AA14=0,0,AC14/AA14) -> 0 | AE14: =IF(AD14=0,0,AF14/AD14) -> 0 | AH14: =IF(AG14=0,0,AI14/AG14) -> 0 | AK14: =IF(AJ14=0,0,AL14/AJ14) -> 0 | AN14: =IF(AM14=0,0,AO14/AM14) -> 0
A15: =+$C$4&B15 -> Véhicules neufs[...] | B15: [...] | C15: =+SUM(F15,I15,L15,O15,R15,U15,X15,AA15,AD15,AG15,AJ15,AM15) -> 0 | D15: =IF(C15=0,0,E15/C15) -> 0 | E15: =+SUM(H15,K15,N15,Q15,T15,W15,Z15,AC15,AF15,AI15,AL15,AO15) -> 0 | G15: =IF(F15=0,0,H15/F15) -> 0 | J15: =IF(I15=0,0,K15/I15) -> 0 | M15: =IF(L15=0,0,N15/L15) -> 0 | P15: =IF(O15=0,0,Q15/O15) -> 0 | S15: =IF(R15=0,0,T15/R15) -> 0 | V15: =IF(U15=0,0,W15/U15) -> 0 | Y15: =IF(X15=0,0,Z15/X15) -> 0 | AB15: =IF(AA15=0,0,AC15/AA15) -> 0 | AE15: =IF(AD15=0,0,AF15/AD15) -> 0 | AH15: =IF(AG15=0,0,AI15/AG15) -> 0 | AK15: =IF(AJ15=0,0,AL15/AJ15) -> 0 | AN15: =IF(AM15=0,0,AO15/AM15) -> 0
A16: =+$C$4&B16 -> Véhicules neufsTotal Neufs | B16: Total Neufs | C16: =+SUM(C9:C15) -> 710 | D16: =IF(C16<=0,0,E16/C16) -> 1011.9718 | E16: =+SUM(E9:E15) -> 718500 | F16: =+SUM(F9:F15) -> 55.316957 | G16: =IF(F16<=0,0,H16/F16) -> 1011.9718 | H16: =+SUM(H9:H15) -> 55979.202 | I16: =+SUM(I9:I15) -> 38.08399 | J16: =IF(I16<=0,0,K16/I16) -> 1011.9718 | K16: =+SUM(K9:K15) -> 38539.925 | L16: =+SUM(L9:L15) -> 57.894239 | M16: =IF(L16<=0,0,N16/L16) -> 1011.9718 | N16: =+SUM(N9:N15) -> 58587.339 | O16: =+SUM(O9:O15) -> 64.125559 | P16: =IF(O16<=0,0,Q16/O16) -> 1011.9718 | Q16: =+SUM(Q9:Q15) -> 64893.259 | R16: =+SUM(R9:R15) -> 83.79455 | S16: =IF(R16<=0,0,T16/R16) -> 1011.9718 | T16: =+SUM(T9:T15) -> 84797.725 | U16: =+SUM(U9:U15) -> 59.036736 | V16: =IF(U16<=0,0,W16/U16) -> 1011.9718 | W16: =+SUM(W9:W15) -> 59743.514 | X16: =+SUM(X9:X15) -> 58.77732 | Y16: =IF(X16<=0,0,Z16/X16) -> 1011.9718 | Z16: =+SUM(Z9:Z15) -> 59480.992 | AA16: =+SUM(AA9:AA15) -> 62.237684 | AB16: =IF(AA16<=0,0,AC16/AA16) -> 1011.9718 | AC16: =+SUM(AC9:AC15) -> 62982.783 | AD16: =+SUM(AD9:AD15) -> 68.199815 | AE16: =IF(AD16<=0,0,AF16/AD16) -> 1011.9718 | AF16: =+SUM(AF9:AF15) -> 69016.292 | AG16: =+SUM(AG9:AG15) -> 84.592344 | AH16: =IF(AG16<=0,0,AI16/AG16) -> 1011.9718 | AI16: =+SUM(AI9:AI15) -> 85605.069 | AJ16: =+SUM(AJ9:AJ15) -> 49.161152 | AK16: =IF(AJ16<=0,0,AL16/AJ16) -> 1011.9718 | AL16: =+SUM(AL9:AL15) -> 49749.701 | AM16: =+SUM(AM9:AM15) -> 28.779654 | AN16: =IF(AM16<=0,0,AO16/AM16) -> 1011.9718 | AO16: =+SUM(AO9:AO15) -> 29124.199
A17: =+$C$4&B17 -> Véhicules neufs
A18: =+$C$4&B18 -> Véhicules neufsEx-Démos et courtoisies | B18: Ex-Démos et courtoisies | C18: =+SUM(F18,I18,L18,O18,R18,U18,X18,AA18,AD18,AG18,AJ18,AM18) -> 74 | D18: =IF(C18=0,0,E18/C18) -> 400 | E18: =+SUM(H18,K18,N18,Q18,T18,W18,Z18,AC18,AF18,AI18,AL18,AO18) -> 29600 | F18: 5.7654293 | G18: =IF(F18=0,0,H18/F18) -> 400 | H18: 2306.1717 | I18: 3.9693173 | J18: =IF(I18=0,0,K18/I18) -> 400 | K18: 1587.7269 | L18: 6.0340474 | M18: =IF(L18=0,0,N18/L18) -> 400 | N18: 2413.619 | O18: 6.683509 | P18: =IF(O18=0,0,Q18/O18) -> 400 | Q18: 2673.4036 | R18: 8.7335165 | S18: =IF(R18=0,0,T18/R18) -> 400 | T18: 3493.4066 | U18: 6.1531246 | V18: =IF(U18=0,0,W18/U18) -> 400 | W18: 2461.2499 | X18: 6.1260869 | Y18: =IF(X18=0,0,Z18/X18) -> 400 | Z18: 2450.4348 | AA18: 6.4867445 | AB18: =IF(AA18=0,0,AC18/AA18) -> 400 | AC18: 2594.6978 | AD18: 7.1081497 | AE18: =IF(AD18=0,0,AF18/AD18) -> 400 | AF18: 2843.2599 | AG18: 8.8166669 | AH18: =IF(AG18=0,0,AI18/AG18) -> 400 | AI18: 3526.6667 | AJ18: 5.1238383 | AK18: =IF(AJ18=0,0,AL18/AJ18) -> 400 | AL18: 2049.5353 | AM18: 2.9995696 | AN18: =IF(AM18=0,0,AO18/AM18) -> 400 | AO18: 1199.8278
A19: =+$C$4&B19 -> Véhicules neufs
A20: =+$C$4&B20 -> Véhicules neufsFlottes | B20: Flottes | C20: =+SUM(F20,I20,L20,O20,R20,U20,X20,AA20,AD20,AG20,AJ20,AM20) -> 0 | D20: =IF(C20=0,0,E20/C20) -> 0 | E20: =+SUM(H20,K20,N20,Q20,T20,W20,Z20,AC20,AF20,AI20,AL20,AO20) -> 0 | F20: 0 | G20: =IF(F20=0,0,H20/F20) -> 0 | H20: 0 | I20: 0 | J20: =IF(I20=0,0,K20/I20) -> 0 | K20: 0 | L20: 0 | M20: =IF(L20=0,0,N20/L20) -> 0 | N20: 0 | O20: 0 | P20: =IF(O20=0,0,Q20/O20) -> 0 | Q20: 0 | R20: 0 | S20: =IF(R20=0,0,T20/R20) -> 0 | T20: 0 | U20: 0 | V20: =IF(U20=0,0,W20/U20) -> 0 | W20: 0 | X20: 0 | Y20: =IF(X20=0,0,Z20/X20) -> 0 | Z20: 0 | AA20: 0 | AB20: =IF(AA20=0,0,AC20/AA20) -> 0 | AC20: 0 | AD20: 0 | AE20: =IF(AD20=0,0,AF20/AD20) -> 0 | AF20: 0 | AG20: 0 | AH20: =IF(AG20=0,0,AI20/AG20) -> 0 | AI20: 0 | AJ20: 0 | AK20: =IF(AJ20=0,0,AL20/AJ20) -> 0 | AL20: 0 | AM20: 0 | AN20: =IF(AM20=0,0,AO20/AM20) -> 0 | AO20: 0
A21: =+$C$4&B21 -> Véhicules neufs
A22: =+$C$4&B22 -> Véhicules neufsRachat bail | B22: Rachat bail | E22: =+SUM(H22,K22,N22,Q22,T22,W22,Z22,AC22,AF22,AI22,AL22,AO22) -> 60000 | H22: 5000 | K22: 5000 | N22: 5000 | Q22: 5000 | T22: 5000 | W22: 5000 | Z22: 5000 | AC22: 5000 | AF22: 5000 | AI22: 5000 | AL22: 5000 | AO22: 5000
A23: =+$C$4&B23 -> Véhicules neufs
A24: =+$C$4&B24 -> Véhicules neufsRev. Finances | B24: Rev. Finances | D24: =IF(C16=0,0,E24/(C16+C18)) -> 94.079794 | E24: =+SUM(H24,K24,N24,Q24,T24,W24,Z24,AC24,AF24,AI24,AL24,AO24) -> 73758.559 | G24: =IF(F16=0,0,H24/(F16+F18)) -> 94.079794 | H24: 5746.6183 | J24: =IF(I16=0,0,K24/(I16+I18)) -> 94.079794 | K24: 3956.3665 | M24: =IF(L16=0,0,N24/(L16+L18)) -> 94.079794 | N24: 6014.36 | P24: =IF(O16=0,0,Q24/(O16+O18)) -> 94.079794 | Q24: 6661.7025 | S24: =IF(R16=0,0,T24/(R16+R18)) -> 94.079794 | T24: 8705.0215 | V24: =IF(U16=0,0,W24/(U16+U18)) -> 94.079794 | W24: 6133.0487 | Y24: =IF(X16=0,0,Z24/(X16+X18)) -> 94.079794 | Z24: 6106.0992 | AB24: =IF(AA16=0,0,AC24/(AA16+AA18)) -> 94.079794 | AC24: 6465.5801 | AE24: =IF(AD16=0,0,AF24/(AD16+AD18)) -> 94.079794 | AF24: 7084.9578 | AH24: =IF(AG16=0,0,AI24/(AG16+AG18)) -> 94.079794 | AI24: 8787.9005 | AK24: =IF(AJ16=0,0,AL24/(AJ16+AJ18)) -> 94.079794 | AL24: 5107.1207 | AN24: =IF(AM16=0,0,AO24/(AM16+AM18)) -> 94.079794 | AO24: 2989.7828
A25: =+$C$4&B25 -> Véhicules neufsRev. Protections | B25: Rev. Protections | D25: =IF(C16=0,0,E25/(C16+C18)) -> 737.32304 | E25: =+SUM(H25,K25,N25,Q25,T25,W25,Z25,AC25,AF25,AI25,AL25,AO25) -> 578061.26 | G25: =IF(F16=0,0,H25/(F16+F18)) -> 737.32304 | H25: 45037.45 | J25: =IF(I16=0,0,K25/(I16+I18)) -> 737.32304 | K25: 31006.872 | M25: =IF(L16=0,0,N25/(L16+L18)) -> 737.32304 | N25: 47135.798 | P25: =IF(O16=0,0,Q25/(O16+O18)) -> 737.32304 | Q25: 52209.157 | S25: =IF(R16=0,0,T25/(R16+R18)) -> 737.32304 | T25: 68223.075 | V25: =IF(U16=0,0,W25/(U16+U18)) -> 737.32304 | W25: 48065.986 | Y25: =IF(X16=0,0,Z25/(X16+X18)) -> 737.32304 | Z25: 47854.777 | AB25: =IF(AA16=0,0,AC25/(AA16+AA18)) -> 737.32304 | AC25: 50672.104 | AE25: =IF(AD16=0,0,AF25/(AD16+AD18)) -> 737.32304 | AF25: 55526.297 | AH25: =IF(AG16=0,0,AI25/(AG16+AG18)) -> 737.32304 | AI25: 68872.616 | AK25: =IF(AJ16=0,0,AL25/(AJ16+AJ18)) -> 737.32304 | AL25: 40025.574 | AN25: =IF(AM16=0,0,AO25/(AM16+AM18)) -> 737.32304 | AO25: 23431.554
A26: =+$C$4&B26 -> Véhicules neufsRev. Autres | B26: Rev. Autres | D26: =IF(C16=0,0,E26/(C16+C18)) -> 18.597169 | E26: =+SUM(H26,K26,N26,Q26,T26,W26,Z26,AC26,AF26,AI26,AL26,AO26) -> 14580.18 | G26: =IF(F16=0,0,H26/(F16+F18)) -> 18.597169 | H26: 1135.9594 | J26: =IF(I16=0,0,K26/(I16+I18)) -> 18.597169 | K26: 782.07244 | M26: =IF(L16=0,0,N26/(L16+L18)) -> 18.597169 | N26: 1188.8851 | P26: =IF(O16=0,0,Q26/(O16+O18)) -> 18.597169 | Q26: 1316.8482 | S26: =IF(R16=0,0,T26/(R16+R18)) -> 18.597169 | T26: 1720.7601 | V26: =IF(U16=0,0,W26/(U16+U18)) -> 18.597169 | W26: 1212.3468 | Y26: =IF(X16=0,0,Z26/(X16+X18)) -> 18.597169 | Z26: 1207.0196 | AB26: =IF(AA16=0,0,AC26/(AA16+AA18)) -> 18.597169 | AC26: 1278.0798 | AE26: =IF(AD16=0,0,AF26/(AD16+AD18)) -> 18.597169 | AF26: 1400.5149 | AH26: =IF(AG16=0,0,AI26/(AG16+AG18)) -> 18.597169 | AI26: 1737.1431 | AK26: =IF(AJ16=0,0,AL26/(AJ16+AJ18)) -> 18.597169 | AL26: 1009.5471 | AN26: =IF(AM16=0,0,AO26/(AM16+AM18)) -> 18.597169 | AO26: 591.00358
A27: =+$C$4&B27 -> Véhicules neufsTotal F&I | B27: Total F&I | C27: =+C18+C16 -> 784 | D27: =IF(C27<=0,0,E27/C27) -> 850 | E27: =E24+E25+E26 -> 666400 | F27: =+F18+F16 -> 61.082386 | G27: =IF(F27<=0,0,H27/F27) -> 850 | H27: =H24+H25+H26 -> 51920.028 | I27: =+I18+I16 -> 42.053307 | J27: =IF(I27<=0,0,K27/I27) -> 850 | K27: =K24+K25+K26 -> 35745.311 | L27: =+L18+L16 -> 63.928286 | M27: =IF(L27<=0,0,N27/L27) -> 850 | N27: =N24+N25+N26 -> 54339.043 | O27: =+O18+O16 -> 70.809068 | P27: =IF(O27<=0,0,Q27/O27) -> 850 | Q27: =Q24+Q25+Q26 -> 60187.708 | R27: =+R18+R16 -> 92.528067 | S27: =IF(R27<=0,0,T27/R27) -> 850 | T27: =$T$24+$T$25+$T$26 -> 78648.857 | U27: =+U18+U16 -> 65.189861 | V27: =IF(U27<=0,0,W27/U27) -> 850 | W27: =W24+W25+W26 -> 55411.382 | X27: =+X18+X16 -> 64.903407 | Y27: =IF(X27<=0,0,Z27/X27) -> 850 | Z27: =Z24+Z25+Z26 -> 55167.896 | AA27: =+AA18+AA16 -> 68.724428 | AB27: =IF(AA27<=0,0,AC27/AA27) -> 850 | AC27: =AC24+AC25+AC26 -> 58415.764 | AD27: =+AD18+AD16 -> 75.307965 | AE27: =IF(AD27<=0,0,AF27/AD27) -> 850 | AF27: =AF24+AF25+AF26 -> 64011.77 | AG27: =+AG18+AG16 -> 93.409011 | AH27: =IF(AG27<=0,0,AI27/AG27) -> 850 | AI27: =AI24+AI25+AI26 -> 79397.659 | AJ27: =+AJ18+AJ16 -> 54.28499 | AK27: =IF(AJ27<=0,0,AL27/AJ27) -> 850 | AL27: =AL24+AL25+AL26 -> 46142.241 | AM27: =+AM18+AM16 -> 31.779223 | AN27: =IF(AM27<=0,0,AO27/AM27) -> 850 | AO27: =AO24+AO25+AO26 -> 27012.34
A28: =+$C$4&B28 -> Véhicules neufs
A29: =+$C$4&B29 -> Véhicules neufs
A30: =+$C$4&B30 -> Véhicules neufsTotal Dépt. Neufs | B30: Total Dépt. Neufs | C30: =+C16+C18+C20 -> 784 | D30: =IF(C30<=0,0,E30/C30) -> 1880.7398 | E30: =E16+E20+E27+E22+E18 -> 1474500 | F30: =+F16+F18+F20 -> 61.082386 | G30: =IF(F30<=0,0,H30/F30) -> 1886.0658 | H30: =H16+H20+H27+H22+H18 -> 115205.4 | I30: =+I16+I18+I20 -> 42.053307 | J30: =IF(I30<=0,0,K30/I30) -> 1923.1059 | K30: =K16+K20+K27+K22+K18 -> 80872.963 | L30: =+L16+L18+L20 -> 63.928286 | M30: =IF(L30<=0,0,N30/L30) -> 1882.4218 | N30: =N16+N20+N27+N22+N18 -> 120340 | O30: =+O16+O18+O20 -> 70.809068 | P30: =IF(O30<=0,0,Q30/O30) -> 1874.8216 | Q30: =Q16+Q20+Q27+Q22+Q18 -> 132754.37 | R30: =+R16+R18+R20 -> 92.528067 | S30: =IF(R30<=0,0,T30/R30) -> 1858.2468 | T30: =T16+T20+T27+T22+T18 -> 171939.99 | U30: =+U16+U18+U20 -> 65.189861 | V30: =IF(U30<=0,0,W30/U30) -> 1880.9082 | W30: =W16+W20+W27+W22+W18 -> 122616.15 | X30: =+X16+X18+X20 -> 64.903407 | Y30: =IF(X30<=0,0,Z30/X30) -> 1881.2467 | Z30: =Z16+Z20+Z27+Z22+Z18 -> 122099.32 | AA30: =+AA16+AA18+AA20 -> 68.724428 | AB30: =IF(AA30<=0,0,AC30/AA30) -> 1876.9635 | AC30: =AC16+AC20+AC27+AC22+AC18 -> 128993.24 | AD30: =+AD16+AD18+AD20 -> 75.307965 | AE30: =IF(AD30<=0,0,AF30/AD30) -> 1870.6032 | AF30: =AF16+AF20+AF27+AF22+AF18 -> 140871.32 | AG30: =+AG16+AG18+AG20 -> 93.409011 | AH30: =IF(AG30<=0,0,AI30/AG30) -> 1857.7372 | AI30: =AI16+AI20+AI27+AI22+AI18 -> 173529.4 | AJ30: =+AJ16+AJ18+AJ20 -> 54.28499 | AK30: =IF(AJ30<=0,0,AL30/AJ30) -> 1896.3157 | AL30: =AL16+AL20+AL27+AL22+AL18 -> 102941.48 | AM30: =+AM16+AM18+AM20 -> 31.779223 | AN30: =IF(AM30<=0,0,AO30/AM30) -> 1961.5447 | AO30: =AO16+AO20+AO27+AO22+AO18 -> 62336.367
A31: =+$C$4&B31 -> Véhicules neufs
A32: =+$C$4&B32 -> Véhicules neufs
A33: =+$C$4&B33 -> Véhicules neufsDEPENSES | B33: DEPENSES
A34: =+$C$4&B34 -> Véhicules neufsComm. vendeurs | B34: Comm. vendeurs | C34: =E34/(E16+E18) -> 0.39740476 | D34: =IF(E34=0,0,E34/C$27) -> 379.20727 | E34: =+SUM(H34,K34,N34,Q34,T34,W34,Z34,AC34,AF34,AI34,AL34,AO34) -> 297298.5 | F34: =H34/(H16+H18) -> 0.40539344 | G34: =IF(H34=0,0,H34/F$27) -> 386.83015 | H34: 23628.508 | I34: =K34/(K16+K18) -> 0.44880474 | J34: =IF(K34=0,0,K34/I$27) -> 428.25361 | K34: 18009.481 | L34: =N34/(N16+N18) -> 0.40432916 | M34: =IF(N34=0,0,N34/L$27) -> 385.8146 | N34: 24664.466 | O34: =Q34/(Q16+Q18) -> 0.39047512 | P34: =IF(Q34=0,0,Q34/O$27) -> 372.59495 | Q34: 26383.101 | R34: =T34/(T16+T18) -> 0.36587948 | S34: =IF(T34=0,0,T34/R$27) -> 349.12556 | T34: 32303.913 | U34: =W34/(W16+W18) -> 0.39855056 | V34: =IF(W34=0,0,W34/U$27) -> 380.30061 | W34: 24791.744 | X34: =Z34/(Z16+Z18) -> 0.40271347 | Y34: =IF(Z34=0,0,Z34/X$27) -> 384.27289 | Z34: 24940.62 | AA34: =AC34/(AC16+AC18) -> 0.39331691 | AB34: =IF(AC34=0,0,AC34/AA$27) -> 375.3066 | AC34: 25792.732 | AD34: =AF34/(AF16+AF18) -> 0.38487837 | AE34: =IF(AF34=0,0,AF34/AD$27) -> 367.25447 | AF34: 27657.187 | AG34: =AI34/(AI16+AI18) -> 0.36780834 | AH34: =IF(AI34=0,0,AI34/AG$27) -> 350.9661 | AI34: 32783.396 | AJ34: =AL34/(AL16+AL18) -> 0.41899244 | AK34: =IF(AL34=0,0,AL34/AJ$27) -> 399.80644 | AL34: 21703.488 | AM34: =AO34/(AO16+AO18) -> 0.482781 | AN34: =IF(AO34=0,0,AO34/AM$27) -> 460.67406 | AO34: 14639.864
A35: =+$C$4&B35 -> Véhicules neufsComm. F&I | B35: Comm. F&I | C35: =E35/E27 -> 0.3 | D35: =IF(E35=0,0,E35/C$27) -> 255 | E35: =+SUM(H35,K35,N35,Q35,T35,W35,Z35,AC35,AF35,AI35,AL35,AO35) -> 199920 | F35: =H35/H27 -> 0.3 | G35: =IF(H35=0,0,H35/F$27) -> 255 | H35: 15576.008 | I35: =K35/K27 -> 0.3 | J35: =IF(K35=0,0,K35/I$27) -> 255 | K35: 10723.593 | L35: =N35/N27 -> 0.3 | M35: =IF(N35=0,0,N35/L$27) -> 255 | N35: 16301.713 | O35: =Q35/Q27 -> 0.3 | P35: =IF(Q35=0,0,Q35/O$27) -> 255 | Q35: 18056.312 | R35: =T35/T27 -> 0.3 | S35: =IF(T35=0,0,T35/R$27) -> 255 | T35: 23594.657 | U35: =W35/W27 -> 0.3 | V35: =IF(W35=0,0,W35/U$27) -> 255 | W35: 16623.415 | X35: =Z35/Z27 -> 0.3 | Y35: =IF(Z35=0,0,Z35/X$27) -> 255 | Z35: 16550.369 | AA35: =AC35/AC27 -> 0.3 | AB35: =IF(AC35=0,0,AC35/AA$27) -> 255 | AC35: 17524.729 | AD35: =AF35/AF27 -> 0.3 | AE35: =IF(AF35=0,0,AF35/AD$27) -> 255 | AF35: 19203.531 | AG35: =AI35/AI27 -> 0.3 | AH35: =IF(AI35=0,0,AI35/AG$27) -> 255 | AI35: 23819.298 | AJ35: =AL35/AL27 -> 0.3 | AK35: =IF(AL35=0,0,AL35/AJ$27) -> 255 | AL35: 13842.672 | AM35: =AO35/AO27 -> 0.3 | AN35: =IF(AO35=0,0,AO35/AM$27) -> 255 | AO35: 8103.702
A36: =+$C$4&B36 -> Véhicules neufsFrais de livraison | B36: Frais de livraison | D36: =IF(E36=0,0,E36/C$27) -> 197 | E36: =+SUM(H36,K36,N36,Q36,T36,W36,Z36,AC36,AF36,AI36,AL36,AO36) -> 154448 | G36: =IF(H36=0,0,H36/F$27) -> 197 | H36: 12033.23 | J36: =IF(K36=0,0,K36/I$27) -> 197 | K36: 8284.5015 | M36: =IF(N36=0,0,N36/L$27) -> 197 | N36: 12593.872 | P36: =IF(Q36=0,0,Q36/O$27) -> 197 | Q36: 13949.386 | S36: =IF(T36=0,0,T36/R$27) -> 197 | T36: 18228.029 | V36: =IF(W36=0,0,W36/U$27) -> 197 | W36: 12842.403 | Y36: =IF(Z36=0,0,Z36/X$27) -> 197 | Z36: 12785.971 | AB36: =IF(AC36=0,0,AC36/AA$27) -> 197 | AC36: 13538.712 | AE36: =IF(AF36=0,0,AF36/AD$27) -> 197 | AF36: 14835.669 | AH36: =IF(AI36=0,0,AI36/AG$27) -> 197 | AI36: 18401.575 | AK36: =IF(AL36=0,0,AL36/AJ$27) -> 197 | AL36: 10694.143 | AN36: =IF(AO36=0,0,AO36/AM$27) -> 197 | AO36: 6260.507
A37: =+$C$4&B37 -> Véhicules neufsService gratuit 1 | B37: Service gratuit 1 | D37: =IF(E37=0,0,E37/C$27) -> 6 | E37: =+SUM(H37,K37,N37,Q37,T37,W37,Z37,AC37,AF37,AI37,AL37,AO37) -> 4704 | G37: =IF(H37=0,0,H37/F$27) -> 6 | H37: 366.49431 | J37: =IF(K37=0,0,K37/I$27) -> 6 | K37: 252.31984 | M37: =IF(N37=0,0,N37/L$27) -> 6 | N37: 383.56972 | P37: =IF(Q37=0,0,Q37/O$27) -> 6 | Q37: 424.85441 | S37: =IF(T37=0,0,T37/R$27) -> 6 | T37: 555.1684 | V37: =IF(W37=0,0,W37/U$27) -> 6 | W37: 391.13917 | Y37: =IF(Z37=0,0,Z37/X$27) -> 6 | Z37: 389.42044 | AB37: =IF(AC37=0,0,AC37/AA$27) -> 6 | AC37: 412.34657 | AE37: =IF(AF37=0,0,AF37/AD$27) -> 6 | AF37: 451.84779 | AH37: =IF(AI37=0,0,AI37/AG$27) -> 6 | AI37: 560.45407 | AK37: =IF(AL37=0,0,AL37/AJ$27) -> 6 | AL37: 325.70994 | AN37: =IF(AO37=0,0,AO37/AM$27) -> 6 | AO37: 190.67534
A38: =+$C$4&B38 -> Véhicules neufsEntretien stock | B38: Entretien stock | D38: =IF(E38=0,0,E38/C$27) -> 34 | E38: =+SUM(H38,K38,N38,Q38,T38,W38,Z38,AC38,AF38,AI38,AL38,AO38) -> 26656 | G38: =IF(H38=0,0,H38/F$27) -> 34 | H38: 2076.8011 | J38: =IF(K38=0,0,K38/I$27) -> 34 | K38: 1429.8124 | M38: =IF(N38=0,0,N38/L$27) -> 34 | N38: 2173.5617 | P38: =IF(Q38=0,0,Q38/O$27) -> 34 | Q38: 2407.5083 | S38: =IF(T38=0,0,T38/R$27) -> 34 | T38: 3145.9543 | V38: =IF(W38=0,0,W38/U$27) -> 34 | W38: 2216.4553 | Y38: =IF(Z38=0,0,Z38/X$27) -> 34 | Z38: 2206.7158 | AB38: =IF(AC38=0,0,AC38/AA$27) -> 34 | AC38: 2336.6306 | AE38: =IF(AF38=0,0,AF38/AD$27) -> 34 | AF38: 2560.4708 | AH38: =IF(AI38=0,0,AI38/AG$27) -> 34 | AI38: 3175.9064 | AK38: =IF(AL38=0,0,AL38/AJ$27) -> 34 | AL38: 1845.6897 | AN38: =IF(AO38=0,0,AO38/AM$27) -> 34 | AO38: 1080.4936
A39: =+$C$4&B39 -> Véhicules neufsPublicité 1 | B39: Publicité 1 | D39: =IF(E39=0,0,E39/C$27) -> 180.66964 | E39: =+SUM(H39,K39,N39,Q39,T39,W39,Z39,AC39,AF39,AI39,AL39,AO39) -> 141645 | G39: =IF(H39=0,0,H39/F$27) -> 180.66964 | H39: 11035.733 | J39: =IF(K39=0,0,K39/I$27) -> 180.66964 | K39: 7597.756 | M39: =IF(N39=0,0,N39/L$27) -> 180.66964 | N39: 11549.901 | P39: =IF(Q39=0,0,Q39/O$27) -> 180.66964 | Q39: 12793.049 | S39: =IF(T39=0,0,T39/R$27) -> 180.66964 | T39: 16717.013 | V39: =IF(W39=0,0,W39/U$27) -> 180.66964 | W39: 11777.829 | Y39: =IF(Z39=0,0,Z39/X$27) -> 180.66964 | Z39: 11726.075 | AB39: =IF(AC39=0,0,AC39/AA$27) -> 180.66964 | AC39: 12416.418 | AE39: =IF(AF39=0,0,AF39/AD$27) -> 180.66964 | AF39: 13605.863 | AH39: =IF(AI39=0,0,AI39/AG$27) -> 180.66964 | AI39: 16876.173 | AK39: =IF(AL39=0,0,AL39/AJ$27) -> 180.66964 | AL39: 9807.6498 | AN39: =IF(AO39=0,0,AO39/AM$27) -> 180.66964 | AO39: 5741.5409
A40: =+$C$4&B40 -> Véhicules neufsIntérêt de gros | B40: Intérêt de gros | D40: =IF(E40=0,0,E40/C$27) -> 222.74973 | E40: =+SUM(H40,K40,N40,Q40,T40,W40,Z40,AC40,AF40,AI40,AL40,AO40) -> 174635.78 | G40: =IF(H40=0,0,H40/F$27) -> 226.36716 | H40: 13827.046 | J40: =IF(K40=0,0,K40/I$27) -> 330.58249 | K40: 13902.087 | M40: =IF(N40=0,0,N40/L$27) -> 229.32443 | N40: 14660.318 | P40: =IF(Q40=0,0,Q40/O$27) -> 217.69014 | Q40: 15414.436 | S40: =IF(T40=0,0,T40/R$27) -> 164.99068 | T40: 15266.269 | V40: =IF(W40=0,0,W40/U$27) -> 223.00803 | W40: 14537.863 | Y40: =IF(Z40=0,0,Z40/X$27) -> 225.42826 | Z40: 14631.062 | AB40: =IF(AC40=0,0,AC40/AA$27) -> 216.88662 | AC40: 14905.409 | AE40: =IF(AF40=0,0,AF40/AD$27) -> 206.569 | AF40: 15556.291 | AH40: =IF(AI40=0,0,AI40/AG$27) -> 160.60504 | AI40: 15001.958 | AK40: =IF(AL40=0,0,AL40/AJ$27) -> 246.41998 | AL40: 13376.906 | AN40: =IF(AO40=0,0,AO40/AM$27) -> 426.57241 | AO40: 13556.14
A41: =+$C$4&B41 -> Véhicules neufs[...] | B41: [...] | D41: =IF(E41=0,0,E41/C$27) -> 0 | E41: =+SUM(H41,K41,N41,Q41,T41,W41,Z41,AC41,AF41,AI41,AL41,AO41) -> 0 | G41: =IF(H41=0,0,H41/F$27) -> 0 | J41: =IF(K41=0,0,K41/I$27) -> 0 | M41: =IF(N41=0,0,N41/L$27) -> 0 | P41: =IF(Q41=0,0,Q41/O$27) -> 0 | S41: =IF(T41=0,0,T41/R$27) -> 0 | V41: =IF(W41=0,0,W41/U$27) -> 0 | Y41: =IF(Z41=0,0,Z41/X$27) -> 0 | AB41: =IF(AC41=0,0,AC41/AA$27) -> 0 | AE41: =IF(AF41=0,0,AF41/AD$27) -> 0 | AH41: =IF(AI41=0,0,AI41/AG$27) -> 0 | AK41: =IF(AL41=0,0,AL41/AJ$27) -> 0 | AN41: =IF(AO41=0,0,AO41/AM$27) -> 0
A42: =+$C$4&B42 -> Véhicules neufs[...] | B42: [...] | D42: =IF(E42=0,0,E42/C$27) -> 0 | E42: =+SUM(H42,K42,N42,Q42,T42,W42,Z42,AC42,AF42,AI42,AL42,AO42) -> 0 | G42: =IF(H42=0,0,H42/F$27) -> 0 | J42: =IF(K42=0,0,K42/I$27) -> 0 | M42: =IF(N42=0,0,N42/L$27) -> 0 | P42: =IF(Q42=0,0,Q42/O$27) -> 0 | S42: =IF(T42=0,0,T42/R$27) -> 0 | V42: =IF(W42=0,0,W42/U$27) -> 0 | Y42: =IF(Z42=0,0,Z42/X$27) -> 0 | AB42: =IF(AC42=0,0,AC42/AA$27) -> 0 | AE42: =IF(AF42=0,0,AF42/AD$27) -> 0 | AH42: =IF(AI42=0,0,AI42/AG$27) -> 0 | AK42: =IF(AL42=0,0,AL42/AJ$27) -> 0 | AN42: =IF(AO42=0,0,AO42/AM$27) -> 0
A43: =+$C$4&B43 -> Véhicules neufs[...] | B43: [...] | D43: =IF(E43=0,0,E43/C$27) -> 0 | E43: =+SUM(H43,K43,N43,Q43,T43,W43,Z43,AC43,AF43,AI43,AL43,AO43) -> 0 | G43: =IF(H43=0,0,H43/F$27) -> 0 | J43: =IF(K43=0,0,K43/I$27) -> 0 | M43: =IF(N43=0,0,N43/L$27) -> 0 | P43: =IF(Q43=0,0,Q43/O$27) -> 0 | S43: =IF(T43=0,0,T43/R$27) -> 0 | V43: =IF(W43=0,0,W43/U$27) -> 0 | Y43: =IF(Z43=0,0,Z43/X$27) -> 0 | AB43: =IF(AC43=0,0,AC43/AA$27) -> 0 | AE43: =IF(AF43=0,0,AF43/AD$27) -> 0 | AH43: =IF(AI43=0,0,AI43/AG$27) -> 0 | AK43: =IF(AL43=0,0,AL43/AJ$27) -> 0 | AN43: =IF(AO43=0,0,AO43/AM$27) -> 0
A44: =+$C$4&B44 -> Véhicules neufsTOTAL VARIABLES | B44: TOTAL VARIABLES | C44: % brut | D44: =IFERROR(E44/E$30,0) -> 0.6777262 | E44: =SUM(E34:E43) -> 999307.28 | F44: % brut | G44: =IFERROR(H44/H$30,0) -> 0.68177204 | H44: =SUM(H34:H43) -> 78543.821 | I44: % brut | J44: =IFERROR(K44/K$30,0) -> 0.74437177 | K44: =SUM(K34:K43) -> 60199.551 | L44: % brut | M44: =IFERROR(N44/N$30,0) -> 0.68412332 | N44: =SUM(N34:N43) -> 82327.402 | O44: % brut | P44: =IFERROR(Q44/Q$30,0) -> 0.67363995 | Q44: =SUM(Q34:Q43) -> 89428.647 | R44: % brut | S44: =IFERROR(T44/T$30,0) -> 0.6386589 | T44: =SUM(T34:T43) -> 109811 | U44: % brut | V44: =IFERROR(W44/W$30,0) -> 0.67838413 | W44: =SUM(W34:W43) -> 83180.847 | X44: % brut | Y44: =IFERROR(Z44/Z$30,0) -> 0.68166007 | Z44: =SUM(Z34:Z43) -> 83230.234 | AA44: % brut | AB44: =IFERROR(AC44/AC$30,0) -> 0.67388783 | AC44: =SUM(AC34:AC43) -> 86926.978 | AD44: % brut | AE44: =IFERROR(AF44/AF$30,0) -> 0.6663589 | AF44: =SUM(AF34:AF43) -> 93870.86 | AG44: % brut | AH44: =IFERROR(AI44/AI$30,0) -> 0.6374641 | AI44: =SUM(AI34:AI43) -> 110618.76 | AJ44: % brut | AK44: =IFERROR(AL44/AL$30,0) -> 0.69550449 | AL44: =SUM(AL34:AL43) -> 71596.26 | AM44: % brut | AN44: =IFERROR(AO44/AO$30,0) -> 0.79524883 | AO44: =SUM(AO34:AO43) -> 49572.923
A45: =+$C$4&B45 -> Véhicules neufsSalaires cadres | B45: Salaires cadres | E45: =+SUM(H45,K45,N45,Q45,T45,W45,Z45,AC45,AF45,AI45,AL45,AO45) -> 299404.6 | H45: 24368.632 | K45: 23592.963 | N45: 25919.97 | Q45: 24368.632 | T45: 25144.301 | W45: 25144.301 | Z45: 25144.301 | AC45: 25144.301 | AF45: 25144.301 | AI45: 24368.632 | AL45: 25144.301 | AO45: 25919.97
A46: =+$C$4&B46 -> Véhicules neufsSalaires commis | B46: Salaires commis | E46: =+SUM(H46,K46,N46,Q46,T46,W46,Z46,AC46,AF46,AI46,AL46,AO46) -> 118984.69 | H46: 9573.4805 | K46: 9117.6005 | N46: 10485.241 | Q46: 9573.4805 | T46: 10029.361 | W46: 10029.361 | Z46: 10029.361 | AC46: 10029.361 | AF46: 10029.361 | AI46: 9573.4805 | AL46: 10029.361 | AO46: 10485.241
A47: =+$C$4&B47 -> Véhicules neufsSalaires autres | B47: Salaires autres | E47: =+SUM(H47,K47,N47,Q47,T47,W47,Z47,AC47,AF47,AI47,AL47,AO47) -> 74977.436 | H47: 6032.6672 | K47: 5745.3974 | N47: 6607.207 | Q47: 6032.6672 | T47: 6319.9371 | W47: 6319.9371 | Z47: 6319.9371 | AC47: 6319.9371 | AF47: 6319.9371 | AI47: 6032.6672 | AL47: 6319.9371 | AO47: 6607.207
A48: =+$C$4&B48 -> Véhicules neufsSalaires spécialistes | B48: Salaires spécialistes | E48: =+SUM(H48,K48,N48,Q48,T48,W48,Z48,AC48,AF48,AI48,AL48,AO48) -> 0
A49: =+$C$4&B49 -> Véhicules neufs[...] | B49: [...] | E49: =+SUM(H49,K49,N49,Q49,T49,W49,Z49,AC49,AF49,AI49,AL49,AO49) -> 0
A50: =+$C$4&B50 -> Véhicules neufs[...] | B50: [...] | E50: =+SUM(H50,K50,N50,Q50,T50,W50,Z50,AC50,AF50,AI50,AL50,AO50) -> 0
A51: =+$C$4&B51 -> Véhicules neufs[...] | B51: [...] | E51: =+SUM(H51,K51,N51,Q51,T51,W51,Z51,AC51,AF51,AI51,AL51,AO51) -> 0
A52: =+$C$4&B52 -> Véhicules neufsSalaires en absences | B52: Salaires en absences | E52: =+SUM(H52,K52,N52,Q52,T52,W52,Z52,AC52,AF52,AI52,AL52,AO52) -> 118870.23 | H52: 9501.5155 | K52: 8062.6841 | N52: 10077.432 | Q52: 10129.703 | T52: 11687.06 | W52: 9949.0508 | Z52: 9958.1505 | AC52: 10177.327 | AF52: 10602.518 | AI52: 11589.297 | AL52: 9244.7711 | AO52: 7890.718
A53: =+$C$4&B53 -> Véhicules neufsDéduction à la source | B53: Déduction à la source | E53: =+SUM(H53,K53,N53,Q53,T53,W53,Z53,AC53,AF53,AI53,AL53,AO53) -> 118870.23 | H53: 9501.5155 | K53: 8062.6841 | N53: 10077.432 | Q53: 10129.703 | T53: 11687.06 | W53: 9949.0508 | Z53: 9958.1505 | AC53: 10177.327 | AF53: 10602.518 | AI53: 11589.297 | AL53: 9244.7711 | AO53: 7890.718
A54: =+$C$4&B54 -> Véhicules neufsBénéfices marginaux | B54: Bénéfices marginaux | E54: =+SUM(H54,K54,N54,Q54,T54,W54,Z54,AC54,AF54,AI54,AL54,AO54) -> 85190.329 | H54: 6809.4195 | K54: 5778.257 | N54: 7222.1593 | Q54: 7259.6206 | T54: 8375.7265 | W54: 7130.1531 | Z54: 7136.6745 | AC54: 7293.7511 | AF54: 7598.4712 | AI54: 8305.6627 | AL54: 6625.4193 | AO54: 5655.0145
A55: =+$C$4&B55 -> Véhicules neufsCsst | B55: Csst | E55: =+SUM(H55,K55,N55,Q55,T55,W55,Z55,AC55,AF55,AI55,AL55,AO55) -> 19811.704 | H55: 1583.5859 | K55: 1343.7807 | N55: 1679.5719 | Q55: 1688.2839 | T55: 1947.8434 | W55: 1658.1751 | Z55: 1659.6917 | AC55: 1696.2212 | AF55: 1767.0863 | AI55: 1931.5495 | AL55: 1540.7952 | AO55: 1315.1197
A56: =+$C$4&B56 -> Véhicules neufs[...] | B56: [...] | E56: =+SUM(H56,K56,N56,Q56,T56,W56,Z56,AC56,AF56,AI56,AL56,AO56) -> 0
A57: =+$C$4&B57 -> Véhicules neufsTOTAL PERSONNEL | B57: TOTAL PERSONNEL | C57: % brut | D57: =IFERROR(E57/E$30,0) -> 0.56704592 | E57: =+SUM(E45:E56) -> 836109.21 | F57: % brut | G57: =IFERROR(H57/H$30,0) -> 0.58478869 | H57: =+SUM(H45:H56) -> 67370.816 | I57: % brut | J57: =IFERROR(K57/K$30,0) -> 0.76296656 | K57: =+SUM(K45:K56) -> 61703.366 | L57: % brut | M57: =IFERROR(N57/N$30,0) -> 0.59887827 | N57: =+SUM(N45:N56) -> 72069.011 | O57: % brut | P57: =IFERROR(Q57/Q$30,0) -> 0.52112853 | Q57: =+SUM(Q45:Q56) -> 69182.09 | R57: % brut | S57: =IFERROR(T57/T$30,0) -> 0.43731123 | T57: =+SUM(T45:T56) -> 75191.289 | U57: % brut | V57: =IFERROR(W57/W$30,0) -> 0.57235552 | W57: =+SUM(W45:W56) -> 70180.028 | X57: % brut | Y57: =IFERROR(Z57/Z$30,0) -> 0.57499308 | Z57: =+SUM(Z45:Z56) -> 70206.265 | AA57: % brut | AB57: =IFERROR(AC57/AC$30,0) -> 0.54916228 | AC57: =+SUM(AC45:AC56) -> 70838.225 | AD57: % brut | AE57: =IFERROR(AF57/AF$30,0) -> 0.51156041 | AF57: =+SUM(AF45:AF56) -> 72064.192 | AG57: % brut | AH57: =IFERROR(AI57/AI$30,0) -> 0.42292884 | AI57: =+SUM(AI45:AI56) -> 73390.585 | AJ57: % brut | AK57: =IFERROR(AL57/AL$30,0) -> 0.66202037 | AL57: =+SUM(AL45:AL56) -> 68149.355 | AM57: % brut | AN57: =IFERROR(AO57/AO$30,0) -> 1.0549859 | AO57: =+SUM(AO45:AO56) -> 65763.987
A58: =+$C$4&B58 -> Véhicules neufsPublicité 2 | B58: Publicité 2 | E58: =+SUM(H58,K58,N58,Q58,T58,W58,Z58,AC58,AF58,AI58,AL58,AO58) -> 0 | H58: 0 | K58: 0 | N58: 0 | Q58: 0 | T58: 0 | W58: 0 | Z58: 0 | AC58: 0 | AF58: 0 | AI58: 0 | AL58: 0 | AO58: 0
A59: =+$C$4&B59 -> Véhicules neufsService gratuit 2 | B59: Service gratuit 2 | E59: =+SUM(H59,K59,N59,Q59,T59,W59,Z59,AC59,AF59,AI59,AL59,AO59) -> 0 | H59: 0 | K59: 0 | N59: 0 | Q59: 0 | T59: 0 | W59: 0 | Z59: 0 | AC59: 0 | AF59: 0 | AI59: 0 | AL59: 0 | AO59: 0
A60: =+$C$4&B60 -> Véhicules neufsFrais véhicules de cie | B60: Frais véhicules de cie | E60: =+SUM(H60,K60,N60,Q60,T60,W60,Z60,AC60,AF60,AI60,AL60,AO60) -> 109066.53 | H60: 9088.8775 | K60: 9088.8775 | N60: 9088.8775 | Q60: 9088.8775 | T60: 9088.8775 | W60: 9088.8775 | Z60: 9088.8775 | AC60: 9088.8775 | AF60: 9088.8775 | AI60: 9088.8775 | AL60: 9088.8775 | AO60: 9088.8775
A61: =+$C$4&B61 -> Véhicules neufsInformatique | B61: Informatique | E61: =+SUM(H61,K61,N61,Q61,T61,W61,Z61,AC61,AF61,AI61,AL61,AO61) -> 80128.755 | H61: 6677.3963 | K61: 6677.3963 | N61: 6677.3963 | Q61: 6677.3963 | T61: 6677.3963 | W61: 6677.3963 | Z61: 6677.3963 | AC61: 6677.3963 | AF61: 6677.3963 | AI61: 6677.3963 | AL61: 6677.3963 | AO61: 6677.3963
A62: =+$C$4&B62 -> Véhicules neufsFrais de déplacement | B62: Frais de déplacement | E62: =+SUM(H62,K62,N62,Q62,T62,W62,Z62,AC62,AF62,AI62,AL62,AO62) -> 19157.962 | H62: 1596.4968 | K62: 1596.4968 | N62: 1596.4968 | Q62: 1596.4968 | T62: 1596.4968 | W62: 1596.4968 | Z62: 1596.4968 | AC62: 1596.4968 | AF62: 1596.4968 | AI62: 1596.4968 | AL62: 1596.4968 | AO62: 1596.4968
A63: =+$C$4&B63 -> Véhicules neufsServices extérieurs | B63: Services extérieurs | E63: =+SUM(H63,K63,N63,Q63,T63,W63,Z63,AC63,AF63,AI63,AL63,AO63) -> 114710.74 | H63: 9409.8947 | K63: 9409.8947 | N63: 9409.8947 | Q63: 9857.8947 | T63: 9857.8947 | W63: 9409.8947 | Z63: 9409.8947 | AC63: 9409.8947 | AF63: 9409.8947 | AI63: 9857.8947 | AL63: 9857.8947 | AO63: 9409.8947
A64: =+$C$4&B64 -> Véhicules neufsFournitures autres | B64: Fournitures autres | E64: =+SUM(H64,K64,N64,Q64,T64,W64,Z64,AC64,AF64,AI64,AL64,AO64) -> 3136 | H64: 244.32954 | K64: 168.21323 | N64: 255.71315 | Q64: 283.23627 | T64: 370.11227 | W64: 260.75944 | Z64: 259.61363 | AC64: 274.89771 | AF64: 301.23186 | AI64: 373.63604 | AL64: 217.13996 | AO64: 127.11689
A65: =+$C$4&B65 -> Véhicules neufsUniformes | B65: Uniformes | E65: =+SUM(H65,K65,N65,Q65,T65,W65,Z65,AC65,AF65,AI65,AL65,AO65) -> 420 | H65: 35 | K65: 35 | N65: 35 | Q65: 35 | T65: 35 | W65: 35 | Z65: 35 | AC65: 35 | AF65: 35 | AI65: 35 | AL65: 35 | AO65: 35
A66: =+$C$4&B66 -> Véhicules neufsPapeterie | B66: Papeterie | E66: =+SUM(H66,K66,N66,Q66,T66,W66,Z66,AC66,AF66,AI66,AL66,AO66) -> 8371.2 | H66: 697.6 | K66: 697.6 | N66: 697.6 | Q66: 697.6 | T66: 697.6 | W66: 697.6 | Z66: 697.6 | AC66: 697.6 | AF66: 697.6 | AI66: 697.6 | AL66: 697.6 | AO66: 697.6
A67: =+$C$4&B67 -> Véhicules neufsTéléphone | B67: Téléphone | E67: =+SUM(H67,K67,N67,Q67,T67,W67,Z67,AC67,AF67,AI67,AL67,AO67) -> 7078.944 | H67: 589.912 | K67: 589.912 | N67: 589.912 | Q67: 589.912 | T67: 589.912 | W67: 589.912 | Z67: 589.912 | AC67: 589.912 | AF67: 589.912 | AI67: 589.912 | AL67: 589.912 | AO67: 589.912
A68: =+$C$4&B68 -> Véhicules neufsFrais postaux | B68: Frais postaux | E68: =+SUM(H68,K68,N68,Q68,T68,W68,Z68,AC68,AF68,AI68,AL68,AO68) -> 3321.6 | H68: 276.8 | K68: 276.8 | N68: 276.8 | Q68: 276.8 | T68: 276.8 | W68: 276.8 | Z68: 276.8 | AC68: 276.8 | AF68: 276.8 | AI68: 276.8 | AL68: 276.8 | AO68: 276.8
A69: =+$C$4&B69 -> Véhicules neufsDivers | B69: Divers | E69: =+SUM(H69,K69,N69,Q69,T69,W69,Z69,AC69,AF69,AI69,AL69,AO69) -> 16189.44 | H69: 1349.12 | K69: 1349.12 | N69: 1349.12 | Q69: 1349.12 | T69: 1349.12 | W69: 1349.12 | Z69: 1349.12 | AC69: 1349.12 | AF69: 1349.12 | AI69: 1349.12 | AL69: 1349.12 | AO69: 1349.12
... A71: =+$C$4&B71 -> Véhicules neufsFrais bancaires | B71: Frais bancaires | E71: =+SUM(H71,K71,N71,Q71,T71,W71,Z71,AC71,AF71,AI71,AL71,AO71) -> 33942.4 | H71: 2087.6738 | K71: 1800.7474 | N71: 2083.3142 | Q71: 4004.986 | T71: 3670.6574 | W71: 2426.188 | Z71: 2287.378 | AC71: 2521.1801 | AF71: 1909.292 | AI71: 3579.0423 | AL71: 5208.1297 | AO71: 2363.8111
A72: =+$C$4&B72 -> Véhicules neufs[...] | B72: [...] | E72: =+SUM(H72,K72,N72,Q72,T72,W72,Z72,AC72,AF72,AI72,AL72,AO72) -> 0
A73: =+$C$4&B73 -> Véhicules neufs[...] | B73: [...] | E73: =+SUM(H73,K73,N73,Q73,T73,W73,Z73,AC73,AF73,AI73,AL73,AO73) -> 0
A74: =+$C$4&B74 -> Véhicules neufs[...] | B74: [...] | E74: =+SUM(H74,K74,N74,Q74,T74,W74,Z74,AC74,AF74,AI74,AL74,AO74) -> 0
A75: =+$C$4&B75 -> Véhicules neufsTOTAL SEMI-FIXES | B75: TOTAL SEMI-FIXES | C75: % brut | D75: =IFERROR(E75/E$30,0) -> 0.27994827 | E75: =+SUM(E58:E74) -> 412783.73 | F75: % brut | G75: =IFERROR(H75/H$30,0) -> 0.29071074 | H75: =+SUM(H58:H74) -> 33491.447 | I75: % brut | J75: =IFERROR(K75/K$30,0) -> 0.4096351 | K75: =+SUM(K58:K74) -> 33128.405 | L75: % brut | M75: =IFERROR(N75/N$30,0) -> 0.27836522 | N75: =+SUM(N58:N74) -> 33498.471 | O75: % brut | P75: =IFERROR(Q75/Q$30,0) -> 0.2703916 | Q75: =+SUM(Q58:Q74) -> 35895.666 | R75: % brut | S75: =IFERROR(T75/T$30,0) -> 0.20732939 | T75: =+SUM(T58:T74) -> 35648.214 | U75: % brut | V75: =IFERROR(W75/W$30,0) -> 0.27603535 | W75: =+SUM(W58:W74) -> 33846.391 | X75: % brut | Y75: =IFERROR(Z75/Z$30,0) -> 0.27605751 | Z75: =+SUM(Z58:Z74) -> 33706.435 | AA75: % brut | AB75: =IFERROR(AC75/AC$30,0) -> 0.26323488 | AC75: =+SUM(AC58:AC74) -> 33955.522 | AD75: % brut | AE75: =IFERROR(AF75/AF$30,0) -> 0.23688262 | AF75: =+SUM(AF58:AF74) -> 33369.968 | AG75: % brut | AH75: =IFERROR(AI75/AI$30,0) -> 0.20492276 | AI75: =+SUM(AI58:AI74) -> 35560.122 | AJ75: % brut | AK75: =IFERROR(AL75/AL$30,0) -> 0.35974531 | AL75: =+SUM(AL58:AL74) -> 37032.714 | AM75: % brut | AN75: =IFERROR(AO75/AO$30,0) -> 0.53981927 | AO75: =+SUM(AO58:AO74) -> 33650.372
A76: =+$C$4&B76 -> Véhicules neufs
A77: =+$C$4&B77 -> Véhicules neufsTOTAL DES DÉPENSES | B77: TOTAL DES DÉPENSES | C77: % brut | D77: =IFERROR(E77/E$30,0) -> 1.5247204 | E77: =E44+E57+E75 -> 2248200.2 | F77: % brut | G77: =IFERROR(H77/H$30,0) -> 1.5572715 | H77: =H44+H57+H75 -> 179406.08 | I77: % brut | J77: =IFERROR(K77/K$30,0) -> 1.9169734 | K77: =K44+K57+K75 -> 155031.32 | L77: % brut | M77: =IFERROR(N77/N$30,0) -> 1.5613668 | N77: =N44+N57+N75 -> 187894.88 | O77: % brut | P77: =IFERROR(Q77/Q$30,0) -> 1.4651601 | Q77: =Q44+Q57+Q75 -> 194506.4 | R77: % brut | S77: =IFERROR(T77/T$30,0) -> 1.2832995 | T77: =T44+T57+T75 -> 220650.51 | U77: % brut | V77: =IFERROR(W77/W$30,0) -> 1.526775 | W77: =W44+W57+W75 -> 187207.27 | X77: % brut | Y77: =IFERROR(Z77/Z$30,0) -> 1.5327107 | Z77: =Z44+Z57+Z75 -> 187142.93 | AA77: % brut | AB77: =IFERROR(AC77/AC$30,0) -> 1.486285 | AC77: =AC44+AC57+AC75 -> 191720.72 | AD77: % brut | AE77: =IFERROR(AF77/AF$30,0) -> 1.4148019 | AF77: =AF44+AF57+AF75 -> 199305.02 | AG77: % brut | AH77: =IFERROR(AI77/AI$30,0) -> 1.2653157 | AI77: =AI44+AI57+AI75 -> 219569.47 | AJ77: % brut | AK77: =IFERROR(AL77/AL$30,0) -> 1.7172702 | AL77: =AL44+AL57+AL75 -> 176778.33 | AM77: % brut | AN77: =IFERROR(AO77/AO$30,0) -> 2.390054 | AO77: =AO44+AO57+AO75 -> 148987.28
A78: =+$C$4&B78 -> Véhicules neufsProgramme neuf 1 | B78: Programme neuf 1 | E78: =+SUM(H78,K78,N78,Q78,T78,W78,Z78,AC78,AF78,AI78,AL78,AO78) -> 453576.38 | H78: 22678.819 | K78: 22678.819 | N78: 45357.638 | Q78: 45357.638 | T78: 49893.401 | W78: 36286.11 | Z78: 31750.346 | AC78: 45357.638 | AF78: 45357.638 | AI78: 49893.401 | AL78: 45357.638 | AO78: 13607.291
A79: =+$C$4&B79 -> Véhicules neufsProgramme neuf 2 | B79: Programme neuf 2 | E79: =+SUM(H79,K79,N79,Q79,T79,W79,Z79,AC79,AF79,AI79,AL79,AO79) -> 0
A80: =+$C$4&B80 -> Véhicules neufsProgramme neuf 3 | B80: Programme neuf 3 | E80: =+SUM(H80,K80,N80,Q80,T80,W80,Z80,AC80,AF80,AI80,AL80,AO80) -> 0
A81: =+$C$4&B81 -> Véhicules neufsHoldbacks | B81: Holdbacks | E81: =+SUM(H81,K81,N81,Q81,T81,W81,Z81,AC81,AF81,AI81,AL81,AO81) -> 727755.67 | H81: 36387.784 | K81: 36387.784 | N81: 72775.568 | Q81: 72775.568 | T81: 80053.124 | W81: 58220.454 | Z81: 50942.897 | AC81: 72775.568 | AF81: 72775.568 | AI81: 80053.124 | AL81: 72775.568 | AO81: 21832.67
A82: =+$C$4&B82 -> Véhicules neufs[...] | B82: [...] | E82: =+SUM(H82,K82,N82,Q82,T82,W82,Z82,AC82,AF82,AI82,AL82,AO82) -> 0
A83: =+$C$4&B83 -> Véhicules neufs[...] | B83: [...] | E83: =+SUM(H83,K83,N83,Q83,T83,W83,Z83,AC83,AF83,AI83,AL83,AO83) -> 0
A84: =+$C$4&B84 -> Véhicules neufs[...] | B84: [...] | E84: =+SUM(H84,K84,N84,Q84,T84,W84,Z84,AC84,AF84,AI84,AL84,AO84) -> 0
A85: =+$C$4&B85 -> Véhicules neufsFrais administration | B85: Frais administration | E85: =+SUM(H85,K85,N85,Q85,T85,W85,Z85,AC85,AF85,AI85,AL85,AO85) -> 246254.4 | H85: 19185.977 | K85: 13208.944 | N85: 20079.875 | Q85: 22241.128 | T85: 29063.066 | W85: 20476.135 | Z85: 20386.16 | AC85: 21586.343 | AF85: 23654.232 | AI85: 29339.77 | AL85: 17050.915 | AO85: 9981.8541
A86: =+$C$4&B86 -> Véhicules neufsAUTRES REVENUS | B86: AUTRES REVENUS | E86: =+SUM(E78:E85) -> 1427586.5 | H86: =+SUM(H78:H85) -> 78252.58 | K86: =+SUM(K78:K85) -> 72275.546 | N86: =+SUM(N78:N85) -> 138213.08 | Q86: =+SUM(Q78:Q85) -> 140374.33 | T86: =+SUM(T78:T85) -> 159009.59 | W86: =+SUM(W78:W85) -> 114982.7 | Z86: =+SUM(Z78:Z85) -> 103079.4 | AC86: =+SUM(AC78:AC85) -> 139719.55 | AF86: =+SUM(AF78:AF85) -> 141787.44 | AI86: =+SUM(AI78:AI85) -> 159286.3 | AL86: =+SUM(AL78:AL85) -> 135184.12 | AO86: =+SUM(AO78:AO85) -> 45421.816
A87: =+$C$4&B87 -> Véhicules neufs
A88: =+$C$4&B88 -> Véhicules neufsPROFIT DÉPARTEMENTAL | B88: PROFIT DÉPARTEMENTAL | E88: =E30-E77+E86 -> 653886.23 | H88: =H30-H77+H86 -> 14051.897 | K88: =K30-K77+K86 -> -1882.8123 | N88: =N30-N77+N86 -> 70658.197 | Q88: =Q30-Q77+Q86 -> 78622.301 | T88: =T30-T77+T86 -> 110299.07 | W88: =W30-W77+W86 -> 50391.579 | Z88: =Z30-Z77+Z86 -> 38035.792 | AC88: =AC30-AC77+AC86 -> 76992.069 | AF88: =AF30-AF77+AF86 -> 83353.739 | AI88: =AI30-AI77+AI86 -> 113246.22 | AL88: =AL30-AL77+AL86 -> 61347.27 | AO88: =AO30-AO77+AO86 -> -41229.099
B92: =B4 -> Budget 2021 | C92: Véhicules usagés
B94: Mois | C94: TOTAL | F94: Janvier | I94: Février | L94: Mars | O94: Avril | R94: Mai | U94: Juin | X94: Juillet | AA94: Août | AD94: Septembre | AG94: Octobre | AJ94: Novembre | AM94: Décembre
C95: UNITE | D95: $P/UNITE | E95: $PROFITS | F95: UNITE | G95: $P/UNITE | H95: $PROFITS | I95: UNITE | J95: $P/UNITE | K95: $PROFITS | L95: UNITE | M95: $P/UNITE | N95: $PROFITS | O95: UNITE | P95: $P/UNITE | Q95: $PROFITS | R95: UNITE | S95: $P/UNITE | T95: $PROFITS | U95: UNITE | V95: $P/UNITE | W95: $PROFITS | X95: UNITE | Y95: $P/UNITE | Z95: $PROFITS | AA95: UNITE | AB95: $P/UNITE | AC95: $PROFITS | AD95: UNITE | AE95: $P/UNITE | AF95: $PROFITS | AG95: UNITE | AH95: $P/UNITE | AI95: $PROFITS | AJ95: UNITE | AK95: $P/UNITE | AL95: $PROFITS | AM95: UNITE | AN95: $P/UNITE | AO95: $PROFITS
A96: =+$C$92&B96 -> Véhicules usagésVentes nettes | B96: Ventes nettes | E96: =+SUM(H96,K96,N96,Q96,T96,W96,Z96,AC96,AF96,AI96,AL96,AO96) -> 11978226 | H96: 641081.33 | K96: 810373.52 | N96: 758716.19 | Q96: 994929.55 | T96: 1240477.2 | W96: 1127433 | Z96: 1147134.4 | AC96: 1181462.1 | AF96: 952211.2 | AI96: 1285172.1 | AL96: 1165165.4 | AO96: 674070.1
A97: =+$C$92&B97 -> Véhicules usagésCertifié | B97: Certifié | C97: =+SUM(F97,I97,L97,O97,R97,U97,X97,AA97,AD97,AG97,AJ97,AM97) -> 359.4964 | D97: =IF(C97=0,0,E97/C97) -> 750 | E97: =+SUM(H97,K97,N97,Q97,T97,W97,Z97,AC97,AF97,AI97,AL97,AO97) -> 269622.3 | F97: 19.240448 | G97: =IF(F97=0,0,H97/F97) -> 750 | H97: 14430.336 | I97: 24.321328 | J97: =IF(I97=0,0,K97/I97) -> 750 | K97: 18240.996 | L97: 22.770963 | M97: =IF(L97=0,0,N97/L97) -> 750 | N97: 17078.222 | O97: 29.860315 | P97: =IF(O97=0,0,Q97/O97) -> 750 | Q97: 22395.236 | R97: 37.229811 | S97: =IF(R97=0,0,T97/R97) -> 750 | T97: 27922.358 | U97: 33.837072 | V97: =IF(U97=0,0,W97/U97) -> 750 | W97: 25377.804 | X97: 34.428361 | Y97: =IF(X97=0,0,Z97/X97) -> 750 | Z97: 25821.271 | AA97: 35.458621 | AB97: =IF(AA97=0,0,AC97/AA97) -> 750 | AC97: 26593.966 | AD97: 28.57823 | AE97: =IF(AD97=0,0,AF97/AD97) -> 750 | AF97: 21433.673 | AG97: 38.571215 | AH97: =IF(AG97=0,0,AI97/AG97) -> 750 | AI97: 28928.412 | AJ97: 34.969516 | AK97: =IF(AJ97=0,0,AL97/AJ97) -> 750 | AL97: 26227.137 | AM97: 20.230523 | AN97: =IF(AM97=0,0,AO97/AM97) -> 750 | AO97: 15172.892
A98: =+$C$92&B98 -> Véhicules usagésNon Certifié | B98: Non Certifié | C98: =+SUM(F98,I98,L98,O98,R98,U98,X98,AA98,AD98,AG98,AJ98,AM98) -> 20.503597 | D98: =IF(C98=0,0,E98/C98) -> 750 | E98: =+SUM(H98,K98,N98,Q98,T98,W98,Z98,AC98,AF98,AI98,AL98,AO98) -> 15377.698 | F98: 1.0973639 | G98: =IF(F98=0,0,H98/F98) -> 750 | H98: 823.02295 | I98: 1.387148 | J98: =IF(I98=0,0,K98/I98) -> 750 | K98: 1040.361 | L98: 1.2987241 | M98: =IF(L98=0,0,N98/L98) -> 750 | N98: 974.0431 | O98: 1.7030598 | P98: =IF(O98=0,0,Q98/O98) -> 750 | Q98: 1277.2948 | R98: 2.1233732 | S98: =IF(R98=0,0,T98/R98) -> 750 | T98: 1592.5299 | U98: 1.929871 | V98: =IF(U98=0,0,W98/U98) -> 750 | W98: 1447.4033 | X98: 1.9635948 | Y98: =IF(X98=0,0,Z98/X98) -> 750 | Z98: 1472.6961 | AA98: 2.0223548 | AB98: =IF(AA98=0,0,AC98/AA98) -> 750 | AC98: 1516.7661 | AD98: 1.6299371 | AE98: =IF(AD98=0,0,AF98/AD98) -> 750 | AF98: 1222.4528 | AG98: 2.1998792 | AH98: =IF(AG98=0,0,AI98/AG98) -> 750 | AI98: 1649.9094 | AJ98: 1.9944591 | AK98: =IF(AJ98=0,0,AL98/AJ98) -> 750 | AL98: 1495.8443 | AM98: 1.1538321 | AN98: =IF(AM98=0,0,AO98/AM98) -> 750 | AO98: 865.37408
A99: =+$C$92&B99 -> Véhicules usagésTotal Usagés | B99: Total Usagés | C99: =+C97+C98 -> 380 | D99: =IF(C99<=0,0,E99/C99) -> 750 | E99: =+E97+E98 -> 285000 | F99: =+F97+F98 -> 20.337812 | G99: =IF(F99<=0,0,H99/F99) -> 750 | H99: =+H97+H98 -> 15253.359 | I99: =+I97+I98 -> 25.708476 | J99: =IF(I99<=0,0,K99/I99) -> 750 | K99: =+K97+K98 -> 19281.357 | L99: =+L97+L98 -> 24.069687 | M99: =IF(L99<=0,0,N99/L99) -> 750 | N99: =+N97+N98 -> 18052.265 | O99: =+O97+O98 -> 31.563374 | P99: =IF(O99<=0,0,Q99/O99) -> 750 | Q99: =+Q97+Q98 -> 23672.531 | R99: =+R97+R98 -> 39.353184 | S99: =IF(R99<=0,0,T99/R99) -> 750 | T99: =+T97+T98 -> 29514.888 | U99: =+U97+U98 -> 35.766943 | V99: =IF(U99<=0,0,W99/U99) -> 750 | W99: =+W97+W98 -> 26825.207 | X99: =+X97+X98 -> 36.391956 | Y99: =IF(X99<=0,0,Z99/X99) -> 750 | Z99: =+Z97+Z98 -> 27293.967 | AA99: =+AA97+AA98 -> 37.480976 | AB99: =IF(AA99<=0,0,AC99/AA99) -> 750 | AC99: =+AC97+AC98 -> 28110.732 | AD99: =+AD97+AD98 -> 30.208167 | AE99: =IF(AD99<=0,0,AF99/AD99) -> 750 | AF99: =+AF97+AF98 -> 22656.126 | AG99: =+AG97+AG98 -> 40.771095 | AH99: =IF(AG99<=0,0,AI99/AG99) -> 750 | AI99: =+AI97+AI98 -> 30578.321 | AJ99: =+AJ97+AJ98 -> 36.963975 | AK99: =IF(AJ99<=0,0,AL99/AJ99) -> 750 | AL99: =+AL97+AL98 -> 27722.981 | AM99: =+AM97+AM98 -> 21.384355 | AN99: =IF(AM99<=0,0,AO99/AM99) -> 750 | AO99: =+AO97+AO98 -> 16038.266
A100: =+$C$92&B100 -> Véhicules usagés
A101: =+$C$92&B101 -> Véhicules usagés
A102: =+$C$92&B102 -> Véhicules usagésVentes au Gros | B102: Ventes au Gros | C102: =+SUM(F102,I102,L102,O102,R102,U102,X102,AA102,AD102,AG102,AJ102,AM102) -> 322 | D102: =IF(C102=0,0,E102/C102) -> 120 | E102: =+SUM(H102,K102,N102,Q102,T102,W102,Z102,AC102,AF102,AI102,AL102,AO102) -> 38640 | F102: 17.233619 | G102: =IF(F102=0,0,H102/F102) -> 120 | H102: 2068.0343 | I102: 21.784551 | J102: =IF(I102=0,0,K102/I102) -> 120 | K102: 2614.1461 | L102: 20.395893 | M102: =IF(L102=0,0,N102/L102) -> 120 | N102: 2447.5071 | O102: 26.745807 | P102: =IF(O102=0,0,Q102/O102) -> 120 | Q102: 3209.4968 | R102: 33.346646 | S102: =IF(R102=0,0,T102/R102) -> 120 | T102: 4001.5975 | U102: 30.307778 | V102: =IF(U102=0,0,W102/U102) -> 120 | W102: 3636.9333 | X102: 30.837394 | Y102: =IF(X102=0,0,Z102/X102) -> 120 | Z102: 3700.4873 | AA102: 31.760195 | AB102: =IF(AA102=0,0,AC102/AA102) -> 120 | AC102: 3811.2235 | AD102: 25.597447 | AE102: =IF(AD102=0,0,AF102/AD102) -> 120 | AF102: 3071.6937 | AG102: 34.548138 | AH102: =IF(AG102=0,0,AI102/AG102) -> 120 | AI102: 4145.7766 | AJ102: 31.322105 | AK102: =IF(AJ102=0,0,AL102/AJ102) -> 120 | AL102: 3758.6526 | AM102: 18.120427 | AN102: =IF(AM102=0,0,AO102/AM102) -> 120 | AO102: 2174.4513
A103: =+$C$92&B103 -> Véhicules usagés
A104: =+$C$92&B104 -> Véhicules usagésRev. Finances | B104: Rev. Finances | D104: =IF(C99=0,0,E104/C99) -> 804.09357 | E104: =+SUM(H104,K104,N104,Q104,T104,W104,Z104,AC104,AF104,AI104,AL104,AO104) -> 305555.56 | G104: =IF(F99=0,0,H104/F99) -> 804.09357 | H104: 16353.504 | J104: =IF(I99=0,0,K104/I99) -> 804.09357 | K104: 20672.02 | M104: =IF(L99=0,0,N104/L99) -> 804.09357 | N104: 19354.281 | P104: =IF(O99=0,0,Q104/O99) -> 804.09357 | Q104: 25379.906 | S104: =IF(R99=0,0,T104/R99) -> 804.09357 | T104: 31643.642 | V104: =IF(U99=0,0,W104/U99) -> 804.09357 | W104: 28759.969 | Y104: =IF(X99=0,0,Z104/X99) -> 804.09357 | Z104: 29262.538 | AB104: =IF(AA99=0,0,AC104/AA99) -> 804.09357 | AC104: 30138.212 | AE104: =IF(AD99=0,0,AF104/AD99) -> 804.09357 | AF104: 24290.193 | AH104: =IF(AG99=0,0,AI104/AG99) -> 804.09357 | AI104: 32783.775 | AK104: =IF(AJ99=0,0,AL104/AJ99) -> 804.09357 | AL104: 29722.494 | AN104: =IF(AM99=0,0,AO104/AM99) -> 804.09357 | AO104: 17195.022
A105: =+$C$92&B105 -> Véhicules usagésRev. Protections | B105: Rev. Protections | D105: =IF(C99=0,0,E105/C99) -> 911.30604 | E105: =+SUM(H105,K105,N105,Q105,T105,W105,Z105,AC105,AF105,AI105,AL105,AO105) -> 346296.3 | G105: =IF(F99=0,0,H105/F99) -> 911.30604 | H105: 18533.971 | J105: =IF(I99=0,0,K105/I99) -> 911.30604 | K105: 23428.29 | M105: =IF(L99=0,0,N105/L99) -> 911.30604 | N105: 21934.851 | P105: =IF(O99=0,0,Q105/O99) -> 911.30604 | Q105: 28763.894 | S105: =IF(R99=0,0,T105/R99) -> 911.30604 | T105: 35862.795 | V105: =IF(U99=0,0,W105/U99) -> 911.30604 | W105: 32594.631 | Y105: =IF(X99=0,0,Z105/X99) -> 911.30604 | Z105: 33164.209 | AB105: =IF(AA99=0,0,AC105/AA99) -> 911.30604 | AC105: 34156.64 | AE105: =IF(AD99=0,0,AF105/AD99) -> 911.30604 | AF105: 27528.886 | AH105: =IF(AG99=0,0,AI105/AG99) -> 911.30604 | AI105: 37154.945 | AK105: =IF(AJ99=0,0,AL105/AJ99) -> 911.30604 | AL105: 33685.494 | AN105: =IF(AM99=0,0,AO105/AM99) -> 911.30604 | AO105: 19487.692
A106: =+$C$92&B106 -> Véhicules usagésRev. Autres | B106: Rev. Autres | D106: =IF(C99=0,0,E106/C99) -> 0 | E106: =+SUM(H106,K106,N106,Q106,T106,W106,Z106,AC106,AF106,AI106,AL106,AO106) -> 0 | G106: =IF(F99=0,0,H106/F99) -> 0 | H106: 0 | J106: =IF(I99=0,0,K106/I99) -> 0 | K106: 0 | M106: =IF(L99=0,0,N106/L99) -> 0 | N106: 0 | P106: =IF(O99=0,0,Q106/O99) -> 0 | Q106: 0 | S106: =IF(R99=0,0,T106/R99) -> 0 | T106: 0 | V106: =IF(U99=0,0,W106/U99) -> 0 | W106: 0 | Y106: =IF(X99=0,0,Z106/X99) -> 0 | Z106: 0 | AB106: =IF(AA99=0,0,AC106/AA99) -> 0 | AC106: 0 | AE106: =IF(AD99=0,0,AF106/AD99) -> 0 | AF106: 0 | AH106: =IF(AG99=0,0,AI106/AG99) -> 0 | AI106: 0 | AK106: =IF(AJ99=0,0,AL106/AJ99) -> 0 | AL106: 0 | AN106: =IF(AM99=0,0,AO106/AM99) -> 0 | AO106: 0
...

Sheet 2pager
B1: =Parametres!$B$1&" "&"2 pager"&" "&Parametres!$B$3&" "&Parametres!$B$4 -> Volks 2 pager Mars 2021
B3: New | C3: Actual | D3: Forecast | E3: Budget | F3: 2019 | G3: ▲ Forecast | H3: ▲ Budget | I3: ▲2019 | J3: % ▲ Forecast | K3: % ▲ Budget | L3: % ▲ 2019 | M3: Commentaires
B4: Units | C4: =+Print_Mois!$J$13+Print_Mois!$J$15 -> 78 | D4: =+Print_Mois!$G$13+Print_Mois!$G$15 -> 63.928286 | E4: =+Print_Mois!$D$13+Print_Mois!$D$15 -> 63.928286 | F4: =+Print_Mois!$O$13+Print_Mois!$O$15 -> 75 | G4: =+IFERROR($C4-D4,"") -> 14.071714 | H4: =+IFERROR($C4-E4,"") -> 14.071714 | I4: =+IFERROR($C4-F4,"") -> 3 | J4: =+IFERROR(G4/ABS($D4),"") -> 0.22011717 | K4: =+IFERROR(H4/ABS($E4),"") -> 0.22011717 | L4: =+IFERROR(I4/ABS($F4),"") -> 0.04 | M4: -Excellente moyenne en ligne avec V3. Volume aussi au RV pour février. -Salaire et commission encore légèrement élevé. à suivre de près -F&I aussi difficile chez VW. Moyenne plus tough avec le type d'acheteur hivernal moins émotif. -Other incomes explosé par le versement final des TOTS et beaucoup de HB. - Bonne gestion des frais variable de Louis et son équipe dans le neuf.
B5: Front Margin | C5: =+Print_Mois!$L$13+Print_Mois!$L$15 -> 122247.05 | D5: =+Print_Mois!$I$13+Print_Mois!$I$15 -> 84870.504 | E5: =+Print_Mois!$F$13+Print_Mois!$F$15 -> 61000.958 | F5: =+Print_Mois!$Q$13+Print_Mois!$Q$15 -> 41360.79 | G5: =+IFERROR($C5-D5,"") -> 37376.546 | H5: =+IFERROR($C5-E5,"") -> 61246.092 | I5: =+IFERROR($C5-F5,"") -> 80886.26 | J5: =+IFERROR(G5/ABS($D5),"") -> 0.440395 | K5: =+IFERROR(H5/ABS($E5),"") -> 1.0040185 | L5: =+IFERROR(I5/ABS($F5),"") -> 1.9556266
B6: Front margin / unit | C6: =+C5/C4 -> 1567.2699 | D6: =+D5/D4 -> 1327.5892 | E6: =+E5/E4 -> 954.20918 | F6: =+F5/F4 -> 551.4772 | G6: =+IFERROR($C6-D6,"") -> 239.68064 | H6: =+IFERROR($C6-E6,"") -> 613.06069 | I6: =+IFERROR($C6-F6,"") -> 1015.7927 | J6: =+IFERROR(G6/ABS($D6),"") -> 0.18053826 | K6: =+IFERROR(H6/ABS($E6),"") -> 0.64248039 | L6: =+IFERROR(I6/ABS($F6),"") -> 1.8419486
B7: $ Salaires et commission | C7: =+Print_Mois!$L$31 -> 41980.82 | D7: =+Print_Mois!$I$31 -> 25136.953 | E7: =+Print_Mois!$F$31 -> 24664.466 | F7: =+Print_Mois!$Q$31 -> 30014.5 | G7: =+IFERROR($C7-D7,"") -> 16843.867 | H7: =+IFERROR($C7-E7,"") -> 17316.354 | I7: =+IFERROR($C7-F7,"") -> 11966.32 | J7: =+IFERROR(G7/ABS($D7),"") -> 0.67008389 | K7: =+IFERROR(H7/ABS($E7),"") -> 0.70207697 | L7: =+IFERROR(I7/ABS($F7),"") -> 0.39868464
B8: % Salaires et commission | C8: =+C7/C5 -> 0.34340968 | D8: =+D7/D5 -> 0.29618008 | E8: =+E7/E5 -> 0.40432916 | F8: =+F7/F5 -> 0.72567521 | G8: =+IFERROR($C8-D8,"") -> 0.047229596 | H8: =+IFERROR($C8-E8,"") -> -0.060919485 | I8: =+IFERROR($C8-F8,"") -> -0.38226553 | J8: =+IFERROR(G8/ABS($D8),"") -> 0.15946243 | K8: =+IFERROR(H8/ABS($E8),"") -> -0.15066805 | L8: =+IFERROR(I8/ABS($F8),"") -> -0.52677221
B9: Back Margin | C9: =+Print_Mois!$L$24 -> 53578.88 | D9: =+Print_Mois!$I$24 -> 54339.043 | E9: =+Print_Mois!$F$24 -> 54339.043 | F9: =+Print_Mois!$Q$24 -> 46251.59 | G9: =+IFERROR($C9-D9,"") -> -760.16344 | H9: =+IFERROR($C9-E9,"") -> -760.16344 | I9: =+IFERROR($C9-F9,"") -> 7327.29 | J9: =+IFERROR(G9/ABS($D9),"") -> -0.013989268 | K9: =+IFERROR(H9/ABS($E9),"") -> -0.013989268 | L9: =+IFERROR(I9/ABS($F9),"") -> 0.15842245
B10: Back Margin / unit | C10: =+C9/C4 -> 686.90872 | D10: =+D9/D4 -> 850 | E10: =+E9/E4 -> 850 | F10: =+F9/F4 -> 616.68787 | G10: =+IFERROR($C10-D10,"") -> -163.09128 | H10: =+IFERROR($C10-E10,"") -> -163.09128 | I10: =+IFERROR($C10-F10,"") -> 70.220851 | J10: =+IFERROR(G10/ABS($D10),"") -> -0.1918721 | K10: =+IFERROR(H10/ABS($E10),"") -> -0.1918721 | L10: =+IFERROR(I10/ABS($F10),"") -> 0.11386774
B11: $ commission FI | C11: =+Print_Mois!$L$32 -> 15873.98 | D11: =+Print_Mois!$I$32 -> 16301.713 | E11: =+Print_Mois!$F$32 -> 16301.713 | F11: =+Print_Mois!$Q$32 -> 20977.35 | G11: =+IFERROR($C11-D11,"") -> -427.73303 | H11: =+IFERROR($C11-E11,"") -> -427.73303 | I11: =+IFERROR($C11-F11,"") -> -5103.37 | J11: =+IFERROR(G11/ABS($D11),"") -> -0.026238533 | K11: =+IFERROR(H11/ABS($E11),"") -> -0.026238533 | L11: =+IFERROR(I11/ABS($F11),"") -> -0.24328001
B12: % commission FI | C12: =+C11/C9 -> 0.29627308 | D12: =+D11/D9 -> 0.3 | E12: =+E11/E9 -> 0.3 | F12: =+F11/F9 -> 0.45354873 | G12: =+IFERROR($C12-D12,"") -> -0.0037269163 | H12: =+IFERROR($C12-E12,"") -> -0.0037269163 | I12: =+IFERROR($C12-F12,"") -> -0.15727565 | J12: =+IFERROR(G12/ABS($D12),"") -> -0.012423054 | K12: =+IFERROR(H12/ABS($E12),"") -> -0.012423054 | L12: =+IFERROR(I12/ABS($F12),"") -> -0.34676681
B13: Variable fees | C13: =+Print_Mois!$L$41-C7-C11 -> 31611.66 | D13: =+Print_Mois!$I$41-D7-D11 -> 41484.084 | E13: =+Print_Mois!$F$41-E7-E11 -> 41361.222 | F13: =+Print_Mois!$Q$41-F7-F11 -> 42339.06 | G13: =+IFERROR($C13-D13,"") -> -9872.4238 | H13: =+IFERROR($C13-E13,"") -> -9749.5623 | I13: =+IFERROR($C13-F13,"") -> -10727.4 | J13: =+IFERROR(G13/ABS($D13),"") -> -0.237981 | K13: =+IFERROR(H13/ABS($E13),"") -> -0.23571746 | L13: =+IFERROR(I13/ABS($F13),"") -> -0.25336887
B14: Variable fees / units | C14: =+C13/C4 -> 405.27769 | D14: =+D13/D4 -> 648.91594 | E14: =+E13/E4 -> 646.99407 | F14: =+F13/F4 -> 564.5208 | G14: =+IFERROR($C14-D14,"") -> -243.63824 | H14: =+IFERROR($C14-E14,"") -> -241.71638 | I14: =+IFERROR($C14-F14,"") -> -159.24311 | J14: =+IFERROR(G14/ABS($D14),"") -> -0.37545425 | K14: =+IFERROR(H14/ABS($E14),"") -> -0.37359906 | L14: =+IFERROR(I14/ABS($F14),"") -> -0.28208546
B15: Other Revenues | C15: =+Print_Mois!$L$83 -> 138129 | D15: =+Print_Mois!$I$83 -> 94764.54 | E15: =+Print_Mois!$F$83 -> 138213.08 | F15: =+Print_Mois!$Q$83 -> 105593 | G15: =+IFERROR($C15-D15,"") -> 43364.46 | H15: =+IFERROR($C15-E15,"") -> -84.079759 | I15: =+IFERROR($C15-F15,"") -> 32536 | J15: =+IFERROR(G15/ABS($D15),"") -> 0.45760218 | K15: =+IFERROR(H15/ABS($E15),"") -> -0.00060833432 | L15: =+IFERROR(I15/ABS($F15),"") -> 0.30812649
B16: Inventory
B17: Units | C17: 164 | D17: 164 | E17: 141 | F17: 306 | G17: =+IFERROR($C17-D17,"") -> 0 | H17: =+IFERROR($C17-E17,"") -> 23 | I17: =+IFERROR($C17-F17,"") -> -142 | J17: =+IFERROR(G17/ABS($D17),"") -> 0 | K17: =+IFERROR(H17/ABS($E17),"") -> 0.16312057 | L17: =+IFERROR(I17/ABS($F17),"") -> -0.46405229
B18: $ | C18: 5689693.2 | D18: 5689693.2 | E18: 4513319 | F18: 9372292.9 | G18: =+IFERROR($C18-D18,"") -> 0 | H18: =+IFERROR($C18-E18,"") -> 1176374.2 | I18: =+IFERROR($C18-F18,"") -> -3682599.7 | J18: =+IFERROR(G18/ABS($D18),"") -> 0 | K18: =+IFERROR(H18/ABS($E18),"") -> 0.26064503 | L18: =+IFERROR(I18/ABS($F18),"") -> -0.39292409
B20: Used | C20: Actual | D20: Forecast | E20: Budget | F20: 2019 | G20: ▲ Forecast | H20: ▲ Budget | I20: ▲2019 | J20: % ▲ Forecast | K20: % ▲ Budget | L20: % ▲ 2019 | M20: Commentaires
B21: Units | C21: =+Print_Mois!$J$96 -> 42 | D21: =+Print_Mois!$G$96 -> 24.069687 | E21: =+Print_Mois!$D$96 -> 24.069687 | F21: =+Print_Mois!$O$96 -> 33 | G21: =+IFERROR($C21-D21,"") -> 17.930313 | H21: =+IFERROR($C21-E21,"") -> 17.930313 | I21: =+IFERROR($C21-F21,"") -> 9 | J21: =+IFERROR(G21/ABS($D21),"") -> 0.74493335 | K21: =+IFERROR(H21/ABS($E21),"") -> 0.74493335 | L21: =+IFERROR(I21/ABS($F21),"") -> 0.27272727 | M21: -Front margin au budegt. Volume au RV. Il faut continuer de travailler la moyenne chez VW dans le used -Salaire et commissions en ligne cependant -F&I tout près du budget. Donc ok! -Frais variable par unités un peu élevé. à surveiller! -autre revenus. ok!
B22: Front Margin | C22: =+Print_Mois!$L$96 -> 39178.43 | D22: =+Print_Mois!$I$96 -> 18052.265 | E22: =+Print_Mois!$F$96 -> 18052.265 | F22: =+Print_Mois!$Q$96 -> 4871.72 | G22: =+IFERROR($C22-D22,"") -> 21126.165 | H22: =+IFERROR($C22-E22,"") -> 21126.165 | I22: =+IFERROR($C22-F22,"") -> 34306.71 | J22: =+IFERROR(G22/ABS($D22),"") -> 1.1702778 | K22: =+IFERROR(H22/ABS($E22),"") -> 1.1702778 | L22: =+IFERROR(I22/ABS($F22),"") -> 7.0420119
B23: Front margin / unit | C23: =+C22/C21 -> 932.81976 | D23: =+D22/D21 -> 750 | E23: =+E22/E21 -> 750 | F23: =+F22/F21 -> 147.62788 | G23: =+IFERROR($C23-D23,"") -> 182.81976 | H23: =+IFERROR($C23-E23,"") -> 182.81976 | I23: =+IFERROR($C23-F23,"") -> 785.19188 | J23: =+IFERROR(G23/ABS($D23),"") -> 0.24375968 | K23: =+IFERROR(H23/ABS($E23),"") -> 0.24375968 | L23: =+IFERROR(I23/ABS($F23),"") -> 5.3187236
B24: $ Salaires et commission | C24: =+Print_Mois!$L$111 -> 19590.26 | D24: =+Print_Mois!$I$111 -> 11976.554 | E24: =+Print_Mois!$F$111 -> 11976.554 | F24: =+Print_Mois!$Q$111 -> 11183.93 | G24: =+IFERROR($C24-D24,"") -> 7613.7058 | H24: =+IFERROR($C24-E24,"") -> 7613.7058 | I24: =+IFERROR($C24-F24,"") -> 8406.33 | J24: =+IFERROR(G24/ABS($D24),"") -> 0.63571756 | K24: =+IFERROR(H24/ABS($E24),"") -> 0.63571756 | L24: =+IFERROR(I24/ABS($F24),"") -> 0.75164365
B25: % Salaires et commission | C25: =+C24/C22 -> 0.50002667 | D25: =+D24/D22 -> 0.66343774 | E25: =+E24/E22 -> 0.66343774 | F25: =+F24/F22 -> 2.2956841 | G25: =+IFERROR($C25-D25,"") -> -0.16341107 | H25: =+IFERROR($C25-E25,"") -> -0.16341107 | I25: =+IFERROR($C25-F25,"") -> -1.7956574 | J25: =+IFERROR(G25/ABS($D25),"") -> -0.24630958 | K25: =+IFERROR(H25/ABS($E25),"") -> -0.24630958 | L25: =+IFERROR(I25/ABS($F25),"") -> -0.78218838
B26: Back Margin | C26: =+Print_Mois!$L$104 -> 69859.68 | D26: =+Print_Mois!$I$104 -> 41289.132 | E26: =+Print_Mois!$F$104 -> 41289.132 | F26: =+Print_Mois!$Q$104 -> 42143.94 | G26: =+IFERROR($C26-D26,"") -> 28570.548 | H26: =+IFERROR($C26-E26,"") -> 28570.548 | I26: =+IFERROR($C26-F26,"") -> 27715.74 | J26: =+IFERROR(G26/ABS($D26),"") -> 0.69196291 | K26: =+IFERROR(H26/ABS($E26),"") -> 0.69196291 | L26: =+IFERROR(I26/ABS($F26),"") -> 0.65764473
B27: Back Margin / unit | C27: =+C26/C21 -> 1663.3257 | D27: =+D26/D21 -> 1715.3996 | E27: =+E26/E21 -> 1715.3996 | F27: =+F26/F21 -> 1277.0891 | G27: =+IFERROR($C27-D27,"") -> -52.073896 | H27: =+IFERROR($C27-E27,"") -> -52.073896 | I27: =+IFERROR($C27-F27,"") -> 386.23662 | J27: =+IFERROR(G27/ABS($D27),"") -> -0.030356714 | K27: =+IFERROR(H27/ABS($E27),"") -> -0.030356714 | L27: =+IFERROR(I27/ABS($F27),"") -> 0.30243514
B28: $ commission FI | C28: =+Print_Mois!$L$112 -> 22319.2 | D28: =+Print_Mois!$I$112 -> 12386.74 | E28: =+Print_Mois!$F$112 -> 12386.74 | F28: =+Print_Mois!$Q$112 -> 7116.21 | G28: =+IFERROR($C28-D28,"") -> 9932.4604 | H28: =+IFERROR($C28-E28,"") -> 9932.4604 | I28: =+IFERROR($C28-F28,"") -> 15202.99 | J28: =+IFERROR(G28/ABS($D28),"") -> 0.80186237 | K28: =+IFERROR(H28/ABS($E28),"") -> 0.80186237 | L28: =+IFERROR(I28/ABS($F28),"") -> 2.1363886
B29: % commission FI | C29: =+C28/C26 -> 0.31948615 | D29: =+D28/D26 -> 0.3 | E29: =+E28/E26 -> 0.3 | F29: =+F28/F26 -> 0.16885488 | G29: =+IFERROR($C29-D29,"") -> 0.019486147 | H29: =+IFERROR($C29-E29,"") -> 0.019486147 | I29: =+IFERROR($C29-F29,"") -> 0.15063127 | J29: =+IFERROR(G29/ABS($D29),"") -> 0.064953824 | K29: =+IFERROR(H29/ABS($E29),"") -> 0.064953824 | L29: =+IFERROR(I29/ABS($F29),"") -> 0.89207528
B30: Variable fees | C30: =+Print_Mois!$L$121-C24-C28 -> 9002.56 | D30: =+Print_Mois!$I$121-D24-D28 -> 7134.6511 | E30: =+Print_Mois!$F$121-E24-E28 -> 7134.6511 | F30: =+Print_Mois!$Q$121-F24-F28 -> 7499.93 | G30: =+IFERROR($C30-D30,"") -> 1867.9089 | H30: =+IFERROR($C30-E30,"") -> 1867.9089 | I30: =+IFERROR($C30-F30,"") -> 1502.63 | J30: =+IFERROR(G30/ABS($D30),"") -> 0.26180802 | K30: =+IFERROR(H30/ABS($E30),"") -> 0.26180802 | L30: =+IFERROR(I30/ABS($F30),"") -> 0.20035254
B31: Variable fees / units | C31: =+C30/C21 -> 214.34667 | D31: =+D30/D21 -> 296.41644 | E31: =+E30/E21 -> 296.41644 | F31: =+F30/F21 -> 227.27061 | G31: =+IFERROR($C31-D31,"") -> -82.069778 | H31: =+IFERROR($C31-E31,"") -> -82.069778 | I31: =+IFERROR($C31-F31,"") -> -12.923939 | J31: =+IFERROR(G31/ABS($D31),"") -> -0.27687323 | K31: =+IFERROR(H31/ABS($E31),"") -> -0.27687323 | L31: =+IFERROR(I31/ABS($F31),"") -> -0.056865864
B32: Other Revenues | C32: =+Print_Mois!$L$162 -> 23158 | D32: =+Print_Mois!$I$162 -> 16060.289 | E32: =+Print_Mois!$F$162 -> 16060.289 | F32: =+Print_Mois!$Q$162 -> 0 | G32: =+IFERROR($C32-D32,"") -> 7097.7112 | H32: =+IFERROR($C32-E32,"") -> 7097.7112 | I32: =+IFERROR($C32-F32,"") -> 23158 | J32: =+IFERROR(G32/ABS($D32),"") -> 0.4419417 | K32: =+IFERROR(H32/ABS($E32),"") -> 0.4419417 | L32: =+IFERROR(I32/ABS($F32),"")
B33: Inventory
B34: Units | C34: 92 | D34: 92 | E34: 55 | F34: 49 | G34: =+IFERROR($C34-D34,"") -> 0 | H34: =+IFERROR($C34-E34,"") -> 37 | I34: =+IFERROR($C34-F34,"") -> 43 | J34: =+IFERROR(G34/ABS($D34),"") -> 0 | K34: =+IFERROR(H34/ABS($E34),"") -> 0.67272727 | L34: =+IFERROR(I34/ABS($F34),"") -> 0.87755102
B35: $ | C35: 1510979 | D35: 1510979 | E35: 919262 | F35: 813537 | G35: =+IFERROR($C35-D35,"") -> 0 | H35: =+IFERROR($C35-E35,"") -> 591717 | I35: =+IFERROR($C35-F35,"") -> 697442 | J35: =+IFERROR(G35/ABS($D35),"") -> 0 | K35: =+IFERROR(H35/ABS($E35),"") -> 0.643687 | L35: =+IFERROR(I35/ABS($F35),"") -> 0.85729598
B37: Service | C37: Actual | D37: Forecast | E37: Budget | F37: 2019 | G37: ▲ Forecast | H37: ▲ Budget | I37: ▲2019 | J37: % ▲ Forecast | K37: % ▲ Budget | L37: % ▲ 2019 | M37: Commentaires
B38: Revenus | C38: =+Print_Mois!$K$193 -> 230012.55 | D38: =+Print_Mois!$H$193 -> 224331.67 | E38: =+Print_Mois!$E$193 -> 224331.67 | F38: =+Print_Mois!$P$193 -> 219906.5 | G38: =+IFERROR($C38-D38,"") -> 5680.875 | H38: =+IFERROR($C38-E38,"") -> 5680.875 | I38: =+IFERROR($C38-F38,"") -> 10106.05 | J38: =+IFERROR(G38/ABS($D38),"") -> 0.025323553 | K38: =+IFERROR(H38/ABS($E38),"") -> 0.025323553 | L38: =+IFERROR(I38/ABS($F38),"") -> 0.045956122 | M38: -Belle réalisatio presque qu'a budget en client. Mars sera bon pour VW! -Moyenne par bon légèrement sous la cible. à suivre de près sans over sale. -Bonne gestion des salaires -Véhicule de compagnie en lien avec le budget -Bonne gestion du lost time -Gestion efficace, maintenant il faut entrer du volume!
B39: Gross margin | C39: =+Print_Mois!$L$193 -> 160416.79 | D39: =+Print_Mois!$I$193 -> 148974.88 | E39: =+Print_Mois!$F$193 -> 148974.88 | F39: =+Print_Mois!$Q$193 -> 136594.91 | G39: =+IFERROR($C39-D39,"") -> 11441.911 | H39: =+IFERROR($C39-E39,"") -> 11441.911 | I39: =+IFERROR($C39-F39,"") -> 23821.88 | J39: =+IFERROR(G39/ABS($D39),"") -> 0.076804299 | K39: =+IFERROR(H39/ABS($E39),"") -> 0.076804299 | L39: =+IFERROR(I39/ABS($F39),"") -> 0.17439801
B40: $ Revenus / #WO client | C40: =+Print_Mois!$K$171/Print_Mois!$J$171 -> 224.72885 | D40: =+IFERROR(Print_Mois!$H$171/Print_Mois!$G$171,"") -> 245.43849 | E40: =+IFERROR(Print_Mois!$E$171/Print_Mois!$D$171,"") -> 245.43849 | F40: =+Print_Mois!$P$171/Print_Mois!$O$171 -> 239.17334 | G40: =+IFERROR($C40-D40,"") -> -20.709639 | H40: =+IFERROR($C40-E40,"") -> -20.709639 | I40: =+IFERROR($C40-F40,"") -> -14.444496 | J40: =+IFERROR(G40/ABS($D40),"") -> -0.084378123 | K40: =+IFERROR(H40/ABS($E40),"") -> -0.084378123 | L40: =+IFERROR(I40/ABS($F40),"") -> -0.060393419
B41: $ Revenus / #WO garantie | C41: =+Print_Mois!$K$174/Print_Mois!$J$174 -> 207.33353 | D41: =+IFERROR(Print_Mois!$H$174/Print_Mois!$G$174,"") -> 176.734 | E41: =+IFERROR(Print_Mois!$E$174/Print_Mois!$D$174,"") -> 176.734 | F41: =+Print_Mois!$P$174/Print_Mois!$O$174 -> 229.84493 | G41: =+IFERROR($C41-D41,"") -> 30.599527 | H41: =+IFERROR($C41-E41,"") -> 30.599527 | I41: =+IFERROR($C41-F41,"") -> -22.5114 | J41: =+IFERROR(G41/ABS($D41),"") -> 0.17313888 | K41: =+IFERROR(H41/ABS($E41),"") -> 0.17313888 | L41: =+IFERROR(I41/ABS($F41),"") -> -0.097941685
B42: Lost time | C42: =+Print_Mois!$L$183 -> -3087.66 | D42: =+Print_Mois!$I$183 -> -3475.708 | E42: =+Print_Mois!$F$183 -> -3475.708 | F42: =+Print_Mois!$Q$183 -> -3388.98 | G42: =+IFERROR($C42-D42,"") -> 388.04804 | H42: =+IFERROR($C42-E42,"") -> 388.04804 | I42: =+IFERROR($C42-F42,"") -> 301.32 | J42: =+IFERROR(G42/ABS($D42),"") -> 0.11164575 | K42: =+IFERROR(H42/ABS($E42),"") -> 0.11164575 | L42: =+IFERROR(I42/ABS($F42),"") -> 0.088911708
B43: Total salaries | C43: =+Print_Mois!$L$209 -> 112764.76 | D43: =+Print_Mois!$I$209 -> 118025.5 | E43: =+Print_Mois!$F$209 -> 118025.5 | F43: =+Print_Mois!$Q$209 -> 83086.49 | G43: =+IFERROR($C43-D43,"") -> -5260.7378 | H43: =+IFERROR($C43-E43,"") -> -5260.7378 | I43: =+IFERROR($C43-F43,"") -> 29678.27 | J43: =+IFERROR(G43/ABS($D43),"") -> -0.044572892 | K43: =+IFERROR(H43/ABS($E43),"") -> -0.044572892 | L43: =+IFERROR(I43/ABS($F43),"") -> 0.3571973
B44: Salaries | C44: =+SUM(Print_Mois!$L$197:$L$203) -> 55084.76 | D44: =+SUM(Print_Mois!$I$197:$I$203) -> 67264.682 | E44: =+SUM(Print_Mois!$F$197:$F$203) -> 67264.682 | F44: =+SUM(Print_Mois!$Q$197:$Q$203) -> 44715.77 | G44: =+IFERROR($C44-D44,"") -> -12179.922 | H44: =+IFERROR($C44-E44,"") -> -12179.922 | I44: =+IFERROR($C44-F44,"") -> 10368.99 | J44: =+IFERROR(G44/ABS($D44),"") -> -0.18107454 | K44: =+IFERROR(H44/ABS($E44),"") -> -0.18107454 | L44: =+IFERROR(I44/ABS($F44),"") -> 0.23188665
B45: Fringes | C45: =+SUM(Print_Mois!$L$204:$L$208) -> 57680 | D45: =+SUM(Print_Mois!$I$204:$I$208) -> 50760.816 | E45: =+SUM(Print_Mois!$F$204:$F$208) -> 50760.816 | F45: =+SUM(Print_Mois!$Q$204:$Q$208) -> 38370.72 | G45: =+IFERROR($C45-D45,"") -> 6919.1837 | H45: =+IFERROR($C45-E45,"") -> 6919.1837 | I45: =+IFERROR($C45-F45,"") -> 19309.28 | J45: =+IFERROR(G45/ABS($D45),"") -> 0.13630954 | K45: =+IFERROR(H45/ABS($E45),"") -> 0.13630954 | L45: =+IFERROR(I45/ABS($F45),"") -> 0.50322955
B46: Total salaries / Revenus | C46: =+C43/C38 -> 0.49025481 | D46: =+D43/D38 -> 0.52612052 | E46: =+E43/E38 -> 0.52612052 | F46: =+F43/F38 -> 0.37782644 | G46: =+IFERROR($C46-D46,"") -> -0.035865707 | H46: =+IFERROR($C46-E46,"") -> -0.035865707 | I46: =+IFERROR($C46-F46,"") -> 0.11242837 | J46: =+IFERROR(G46/ABS($D46),"") -> -0.068170135 | K46: =+IFERROR(H46/ABS($E46),"") -> -0.068170135 | L46: =+IFERROR(I46/ABS($F46),"") -> 0.29756619
B47: Frais véhicules de cie | C47: =+Print_Mois!$L$212 -> 17414.1 | D47: =+Print_Mois!$I$212 -> 16764.08 | E47: =+Print_Mois!$F$212 -> 16764.08 | F47: =+Print_Mois!$Q$212 -> 12606.24 | G47: =+IFERROR($C47-D47,"") -> 650.02 | H47: =+IFERROR($C47-E47,"") -> 650.02 | I47: =+IFERROR($C47-F47,"") -> 4807.86 | J47: =+IFERROR(G47/ABS($D47),"") -> 0.03877457 | K47: =+IFERROR(H47/ABS($E47),"") -> 0.03877457 | L47: =+IFERROR(I47/ABS($F47),"") -> 0.38138731
B49: Pieces | C49: Actual | D49: Forecast | E49: Budget | F49: 2019 | G49: ▲ Forecast | H49: ▲ Budget | I49: ▲2019 | J49: % ▲ Forecast | K49: % ▲ Budget | L49: % ▲ 2019 | M49: Commentaires
B50: Revenus | C50: =+Print_Mois!$J$313 -> 298360.32 | D50: =+Print_Mois!$G$313 -> 324516.88 | E50: =+Print_Mois!$D$313 -> 324516.88 | F50: =+Print_Mois!$O$313 -> 345654.53 | G50: =+IFERROR($C50-D50,"") -> -26156.555 | H50: =+IFERROR($C50-E50,"") -> -26156.555 | I50: =+IFERROR($C50-F50,"") -> -47294.21 | J50: =+IFERROR(G50/ABS($D50),"") -> -0.080601525 | K50: =+IFERROR(H50/ABS($E50),"") -> -0.080601525 | L50: =+IFERROR(I50/ABS($F50),"") -> -0.13682508 | M50: - Retard sur budget en client. Travaux de relance au QG snipper - Travaux à faire avec l'équipe de Mario. Volume à ramener pour mars-avril-mai
B51: Clients | C51: =+Print_Mois!$J$294 -> 51335.82 | D51: =+Print_Mois!$G$294 -> 59152.79 | E51: =+Print_Mois!$D$294 -> 59152.79 | F51: =+Print_Mois!$O$294 -> 58273.84 | G51: =+IFERROR($C51-D51,"") -> -7816.9705 | H51: =+IFERROR($C51-E51,"") -> -7816.9705 | I51: =+IFERROR($C51-F51,"") -> -6938.02 | J51: =+IFERROR(G51/ABS($D51),"") -> -0.1321488 | K51: =+IFERROR(H51/ABS($E51),"") -> -0.1321488 | L51: =+IFERROR(I51/ABS($F51),"") -> -0.11905891
B52: Garantie | C52: =+Print_Mois!$J$296 -> 48253 | D52: =+Print_Mois!$G$296 -> 73637.815 | E52: =+Print_Mois!$D$296 -> 73637.815 | F52: =+Print_Mois!$O$296 -> 78789.27 | G52: =+IFERROR($C52-D52,"") -> -25384.815 | H52: =+IFERROR($C52-E52,"") -> -25384.815 | I52: =+IFERROR($C52-F52,"") -> -30536.27 | J52: =+IFERROR(G52/ABS($D52),"") -> -0.34472526 | K52: =+IFERROR(H52/ABS($E52),"") -> -0.34472526 | L52: =+IFERROR(I52/ABS($F52),"") -> -0.38756889
B53: Wholesale | C53: =+Print_Mois!$J$299 -> 51046.5 | D53: =+Print_Mois!$G$299 -> 57358.522 | E53: =+Print_Mois!$D$299 -> 57358.522 | F53: =+Print_Mois!$O$299 -> 46810.51 | G53: =+IFERROR($C53-D53,"") -> -6312.0216 | H53: =+IFERROR($C53-E53,"") -> -6312.0216 | I53: =+IFERROR($C53-F53,"") -> 4235.99 | J53: =+IFERROR(G53/ABS($D53),"") -> -0.11004505 | K53: =+IFERROR(H53/ABS($E53),"") -> -0.11004505 | L53: =+IFERROR(I53/ABS($F53),"") -> 0.090492285
B54: Tires | C54: =+Print_Mois!$J$306 -> 28202.46 | D54: =+Print_Mois!$G$306 -> 26460.11 | E54: =+Print_Mois!$D$306 -> 26460.11 | F54: =+Print_Mois!$O$306 -> 29530.14 | G54: =+IFERROR($C54-D54,"") -> 1742.3504 | H54: =+IFERROR($C54-E54,"") -> 1742.3504 | I54: =+IFERROR($C54-F54,"") -> -1327.68 | J54: =+IFERROR(G54/ABS($D54),"") -> 0.065848193 | K54: =+IFERROR(H54/ABS($E54),"") -> 0.065848193 | L54: =+IFERROR(I54/ABS($F54),"") -> -0.044960166
B55: All others | C55: =+C50-SUM(C51:C54) -> 119522.54 | D55: =+D50-SUM(D51:D54) -> 107907.64 | E55: =+E50-SUM(E51:E54) -> 107907.64 | F55: =+F50-SUM(F51:F54) -> 132250.77 | G55: =+IFERROR($C55-D55,"") -> 11614.901 | H55: =+IFERROR($C55-E55,"") -> 11614.901 | I55: =+IFERROR($C55-F55,"") -> -12728.23 | J55: =+IFERROR(G55/ABS($D55),"") -> 0.10763743 | K55: =+IFERROR(H55/ABS($E55),"") -> 0.10763743 | L55: =+IFERROR(I55/ABS($F55),"") -> -0.096243145
B56: Gross margin | C56: =+Print_Mois!$L$313 -> 86790.78 | D56: =+Print_Mois!$I$313 -> 96414.239 | E56: =+Print_Mois!$F$313 -> 96414.239 | F56: =+Print_Mois!$Q$313 -> 127460.2 | G56: =+IFERROR($C56-D56,"") -> -9623.4594 | H56: =+IFERROR($C56-E56,"") -> -9623.4594 | I56: =+IFERROR($C56-F56,"") -> -40669.42 | J56: =+IFERROR(G56/ABS($D56),"") -> -0.099813673 | K56: =+IFERROR(H56/ABS($E56),"") -> -0.099813673 | L56: =+IFERROR(I56/ABS($F56),"") -> -0.31907544
B57: $ Revenus / #WO client | C57: =+Print_Mois!$J$294/Print_Mois!$J$171 -> 128.6612 | D57: =+IFERROR(Print_Mois!$G$294/Print_Mois!$G$171,"") -> 149.40802 | E57: =+IFERROR(Print_Mois!$D$294/Print_Mois!$D$171,"") -> 149.40802 | F57: =+Print_Mois!$O$294/Print_Mois!$O$171 -> 169.4007 | G57: =+IFERROR($C57-D57,"") -> -20.746819 | H57: =+IFERROR($C57-E57,"") -> -20.746819 | I57: =+IFERROR($C57-F57,"") -> -40.739495 | J57: =+IFERROR(G57/ABS($D57),"") -> -0.13886014 | K57: =+IFERROR(H57/ABS($E57),"") -> -0.13886014 | L57: =+IFERROR(I57/ABS($F57),"") -> -0.24049189
B58: $ Revenus / #WO garantie | C58: =+Print_Mois!$J$296/Print_Mois!$J$174 -> 236.53431 | D58: =+IFERROR(Print_Mois!$G$296/Print_Mois!$G$174,"") -> 258.16046 | E58: =+IFERROR(Print_Mois!$D$296/Print_Mois!$D$174,"") -> 258.16046 | F58: =+Print_Mois!$O$296/Print_Mois!$O$174 -> 279.39457 | G58: =+IFERROR($C58-D58,"") -> -21.626144 | H58: =+IFERROR($C58-E58,"") -> -21.626144 | I58: =+IFERROR($C58-F58,"") -> -42.860261 | J58: =+IFERROR(G58/ABS($D58),"") -> -0.083770163 | K58: =+IFERROR(H58/ABS($E58),"") -> -0.083770163 | L58: =+IFERROR(I58/ABS($F58),"") -> -0.15340406
B59: Salaires autres | C59: =+Print_Mois!$L$319 -> 18839.57 | D59: =+Print_Mois!$I$319 -> 17319.702 | E59: =+Print_Mois!$F$319 -> 17319.702 | F59: =+Print_Mois!$Q$319 -> 14497.42 | G59: =+IFERROR($C59-D59,"") -> 1519.8681 | H59: =+IFERROR($C59-E59,"") -> 1519.8681 | I59: =+IFERROR($C59-F59,"") -> 4342.15 | J59: =+IFERROR(G59/ABS($D59),"") -> 0.087753708 | K59: =+IFERROR(H59/ABS($E59),"") -> 0.087753708 | L59: =+IFERROR(I59/ABS($F59),"") -> 0.29951191
B61: Others | C61: Actual | D61: Forecast | E61: Budget | F61: 2019 | G61: ▲ Forecast | H61: ▲ Budget | I61: ▲2019 | J61: % ▲ Forecast | K61: % ▲ Budget | L61: % ▲ 2019 | M61: Commentaires
B62: Total salaries / Gross profits | C62: =+Print_Mois!$AF$432/Print_Mois!$AF$406 -> 0.41913808 | D62: =+Print_Mois!$AC$432/Print_Mois!$AC$406 -> 0.58014113 | E62: =+Print_Mois!$Z$432/Print_Mois!$Z$406 -> 0.61301704 | F62: =+Print_Mois!$AL$432/Print_Mois!$AL$406 -> 0.6134561 | G62: =+IFERROR($C62-D62,"") -> -0.16100304 | H62: =+IFERROR($C62-E62,"") -> -0.19387895 | I62: =+IFERROR($C62-F62,"") -> -0.19431802 | J62: =+IFERROR(G62/ABS($D62),"") -> -0.27752392 | K62: =+IFERROR(H62/ABS($E62),"") -> -0.31627009 | L62: =+IFERROR(I62/ABS($F62),"") -> -0.31675945 | M62: - Bonne gestion du personnel en place.
B63: Headcounts | C63: 42 | D63: 42 | E63: 50.8 | F63: 62 | G63: =+IFERROR($C63-D63,"") -> 0 | H63: =+IFERROR($C63-E63,"") -> -8.8 | I63: =+IFERROR($C63-F63,"") -> -20 | J63: =+IFERROR(G63/ABS($D63),"") -> 0 | K63: =+IFERROR(H63/ABS($E63),"") -> -0.17322835 | L63: =+IFERROR(I63/ABS($F63),"") -> -0.32258065
B64: Marketing | C64: =+Print_Mois!$AF$413+Print_Mois!$AF$433 -> 26467.94 | D64: =+Print_Mois!$AC$413+Print_Mois!$AC$433 -> 23091.497 | E64: =+Print_Mois!$Z$413+Print_Mois!$Z$433 -> 23091.497 | F64: =+Print_Mois!$AL$413+Print_Mois!$AL$433 -> 32616.31 | G64: =+IFERROR($C64-D64,"") -> 3376.4432 | H64: =+IFERROR($C64-E64,"") -> 3376.4432 | I64: =+IFERROR($C64-F64,"") -> -6148.37 | J64: =+IFERROR(G64/ABS($D64),"") -> 0.1462202 | K64: =+IFERROR(H64/ABS($E64),"") -> 0.1462202 | L64: =+IFERROR(I64/ABS($F64),"") -> -0.188506
B65: Other semi-fixed expenses | C65: =+Print_Mois!$AF$451-Print_Mois!$AF$433 -> 83169.47 | D65: =+Print_Mois!$AC$451-Print_Mois!$AC$433 -> 101826.58 | E65: =+Print_Mois!$Z$451-Print_Mois!$Z$433 -> 101826.58 | F65: =+Print_Mois!$AL$451-Print_Mois!$AL$433 -> 108300.77 | G65: =+IFERROR($C65-D65,"") -> -18657.108 | H65: =+IFERROR($C65-E65,"") -> -18657.108 | I65: =+IFERROR($C65-F65,"") -> -25131.3 | J65: =+IFERROR(G65/ABS($D65),"") -> -0.18322435 | K65: =+IFERROR(H65/ABS($E65),"") -> -0.18322435 | L65: =+IFERROR(I65/ABS($F65),"") -> -0.23205098
B66: Floor plan interest | C66: =+Print_Mois!$AF$414 -> 14050.29 | D66: =+Print_Mois!$AC$414 -> 15962.736 | E66: =+Print_Mois!$Z$414 -> 15839.875 | F66: =+Print_Mois!$AL$414 -> 20497.56 | G66: =+IFERROR($C66-D66,"") -> -1912.4464 | H66: =+IFERROR($C66-E66,"") -> -1789.5849 | I66: =+IFERROR($C66-F66,"") -> -6447.27 | J66: =+IFERROR(G66/ABS($D66),"") -> -0.11980693 | K66: =+IFERROR(H66/ABS($E66),"") -> -0.11297974 | L66: =+IFERROR(I66/ABS($F66),"") -> -0.31453841
B67: Others Revenues | C67: =+Print_Mois!$AF$480-C32-C15 -> 72972.09 | D67: =+Print_Mois!$AC$480-D32-D15 -> 0 | E67: =+Print_Mois!$Z$480-E32-E15 -> 0 | F67: =+Print_Mois!$AL$480-F32-F15 -> 37185.8 | G67: =+IFERROR($C67-D67,"") -> 72972.09 | H67: =+IFERROR($C67-E67,"") -> 72972.09 | I67: =+IFERROR($C67-F67,"") -> 35786.29 | J67: =+IFERROR(G67/ABS($D67),"") | K67: =+IFERROR(H67/ABS($E67),"") | L67: =+IFERROR(I67/ABS($F67),"") -> 0.9623644
B69: P&L | C69: Actual | D69: Forecast | E69: Budget | F69: 2019 | G69: ▲ Forecast | H69: ▲ Budget | I69: ▲2019 | J69: % ▲ Forecast | K69: % ▲ Budget | L69: % ▲ 2019 | M69: Commentaires
B70: Selling and Marketing | C70: =+Print_Mois!$AF$418-Print_Mois!$AF$414+Print_Mois!$AF$433+Print_Mois!$AF$434+Print_Mois!$AF$435 -> 171624.7 | D70: =+Print_Mois!$AC$418-Print_Mois!$AC$414+Print_Mois!$AC$433+Print_Mois!$AC$434+Print_Mois!$AC$435 -> 141086.16 | E70: =+Print_Mois!$Z$418-Print_Mois!$Z$414+Print_Mois!$Z$433+Print_Mois!$Z$434+Print_Mois!$Z$435 -> 140613.67 | F70: =+Print_Mois!$AL$418-Print_Mois!$AL$414+Print_Mois!$AL$433+Print_Mois!$AL$434+Print_Mois!$AL$435 -> 145089.82 | G70: =+IFERROR($C70-D70,"") -> 30538.544 | H70: =+IFERROR($C70-E70,"") -> 31011.031 | I70: =+IFERROR($C70-F70,"") -> 26534.88 | J70: =+IFERROR(G70/ABS($D70),"") -> 0.21645316 | K70: =+IFERROR(H70/ABS($E70),"") -> 0.22054066 | L70: =+IFERROR(I70/ABS($F70),"") -> 0.18288588 | M70: - erxcellent bas de page, il faut absolument mettre du volume pour mars-avril-mai! Go team go!
B71: S&M / Brut | C71: =+C70/Print_Mois!$AF$406 -> 0.30097524 | D71: =+D70/Print_Mois!$AC$406 -> 0.29822485 | E71: =+E70/Print_Mois!$Z$406 -> 0.31425675 | F71: =+F70/Print_Mois!$AL$406 -> 0.32618658 | G71: =+IFERROR($C71-D71,"") -> 0.0027503916 | H71: =+IFERROR($C71-E71,"") -> -0.013281517 | I71: =+IFERROR($C71-F71,"") -> -0.025211344 | J71: =+IFERROR(G71/ABS($D71),"") -> 0.0092225436 | K71: =+IFERROR(H71/ABS($E71),"") -> -0.042263266 | L71: =+IFERROR(I71/ABS($F71),"") -> -0.077291174
B72: General & administrative | C72: =+Print_Mois!$AF$465+Print_Mois!$AF$432+Print_Mois!$AF$436+Print_Mois!$AF$438+SUM(Print_Mois!$AF$439:$AF$447)+Print_Mois!$AF$437 -> 344062.19 | D72: =+Print_Mois!$AC$465+Print_Mois!$AC$432+Print_Mois!$AC$436+Print_Mois!$AC$438+SUM(Print_Mois!$AC$439:$AC$447)+Print_Mois!$AC$437 -> 394182.41 | E72: =+Print_Mois!$Z$465+Print_Mois!$Z$432+Print_Mois!$Z$436+Print_Mois!$Z$438+SUM(Print_Mois!$Z$439:$Z$447)+Print_Mois!$Z$437 -> 394018.93 | F72: =+Print_Mois!$AL$465+Print_Mois!$AL$432+Print_Mois!$AL$436+Print_Mois!$AL$438+SUM(Print_Mois!$AL$439:$AL$447)+Print_Mois!$AL$437 -> 404918.91 | G72: =+IFERROR($C72-D72,"") -> -50120.223 | H72: =+IFERROR($C72-E72,"") -> -49956.743 | I72: =+IFERROR($C72-F72,"") -> -60856.72 | J72: =+IFERROR(G72/ABS($D72),"") -> -0.12714982 | K72: =+IFERROR(H72/ABS($E72),"") -> -0.12678767 | L72: =+IFERROR(I72/ABS($F72),"") -> -0.1502936
B73: G&A / Brut | C73: =+C72/Print_Mois!$AF$406 -> 0.60337585 | D73: =+D72/Print_Mois!$AC$406 -> 0.83321421 | E73: =+E72/Print_Mois!$Z$406 -> 0.88059085 | F73: =+F72/Print_Mois!$AL$406 -> 0.91032655 | G73: =+IFERROR($C73-D73,"") -> -0.22983836 | H73: =+IFERROR($C73-E73,"") -> -0.277215 | I73: =+IFERROR($C73-F73,"") -> -0.3069507 | J73: =+IFERROR(G73/ABS($D73),"") -> -0.27584546 | K73: =+IFERROR(H73/ABS($E73),"") -> -0.31480568 | L73: =+IFERROR(I73/ABS($F73),"") -> -0.33718746
B74: EBITDA | C74: =+Print_Mois!$AF$482+Print_Mois!$AF$414 -> 288800.84 | D74: =+Print_Mois!$AC$482+Print_Mois!$AC$414 -> 48642.785 | E74: =+Print_Mois!$Z$482+Print_Mois!$Z$414 -> 67089.126 | F74: =+Print_Mois!$AL$482+Print_Mois!$AL$414 -> 37576.29 | G74: =+IFERROR($C74-D74,"") -> 240158.05 | H74: =+IFERROR($C74-E74,"") -> 221711.71 | I74: =+IFERROR($C74-F74,"") -> 251224.55 | J74: =+IFERROR(G74/ABS($D74),"") -> 4.9371773 | K74: =+IFERROR(H74/ABS($E74),"") -> 3.3047339 | L74: =+IFERROR(I74/ABS($F74),"") -> 6.6857199
B75: EBITDA % | C75: =+C74/Print_Mois!$AF$405 -> 0.053390513 | D75: =+D74/Print_Mois!$AC$405 -> 0.023460726 | E75: =+E74/Print_Mois!$Z$405 -> 0.032357515 | F75: =+F74/Print_Mois!$AL$405 -> 0.0087718834 | G75: =+IFERROR($C75-D75,"") -> 0.029929787 | H75: =+IFERROR($C75-E75,"") -> 0.021032998 | I75: =+IFERROR($C75-F75,"") -> 0.04461863 | J75: =+IFERROR(G75/ABS($D75),"") -> 1.27574 | K75: =+IFERROR(H75/ABS($E75),"") -> 0.65001896 | L75: =+IFERROR(I75/ABS($F75),"") -> 5.0865507
B76: EBIT | C76: =+Print_Mois!$AF$497 -> 264799.08 | D76: =+Print_Mois!$AC$497 -> 22469.636 | E76: =+Print_Mois!$Z$497 -> 41038.839 | F76: =+Print_Mois!$AL$497 -> 2859.32 | G76: =+IFERROR($C76-D76,"") -> 242329.44 | H76: =+IFERROR($C76-E76,"") -> 223760.24 | I76: =+IFERROR($C76-F76,"") -> 261939.76 | J76: =+IFERROR(G76/ABS($D76),"") -> 10.784751 | K76: =+IFERROR(H76/ABS($E76),"") -> 5.4524018 | L76: =+IFERROR(I76/ABS($F76),"") -> 91.60911
B77: EBIT % | C77: =+C76/Print_Mois!$AF$405 -> 0.048953316 | D77: =+D76/Print_Mois!$AC$405 -> 0.010837249 | E77: =+E76/Print_Mois!$Z$405 -> 0.019793295 | F77: =+F76/Print_Mois!$AL$405 -> 0.00066748531 | G77: =+IFERROR($C77-D77,"") -> 0.038116067 | H77: =+IFERROR($C77-E77,"") -> 0.029160021 | I77: =+IFERROR($C77-F77,"") -> 0.048285831 | J77: =+IFERROR(G77/ABS($D77),"") -> 3.5171348 | K77: =+IFERROR(H77/ABS($E77),"") -> 1.4732273 | L77: =+IFERROR(I77/ABS($F77),"") -> 72.339915

Sheet Budget révisé
B1: ="Budget 2021 Mensuel Révisé"&" "&Parametres!$B$1 -> Budget 2021 Mensuel Révisé Volks
B2: Mois | F2: =+IF(Parametres!$B$3=F$6,"X","") | G2: =+IF(Parametres!$B$3=F$6,"O","") | H2: =+IF(Parametres!$B$3=F$6,"U","") | I2: =+IF(Parametres!$B$3=I$6,"X","") | J2: =+IF(Parametres!$B$3=I$6,"O","") | K2: =+IF(Parametres!$B$3=I$6,"U","") | L2: =+IF(Parametres!$B$3=L$6,"X","") -> X | M2: =+IF(Parametres!$B$3=L$6,"O","") -> O | N2: =+IF(Parametres!$B$3=L$6,"U","") -> U | O2: =+IF(Parametres!$B$3=O$6,"X","") | P2: =+IF(Parametres!$B$3=O$6,"O","") | Q2: =+IF(Parametres!$B$3=O$6,"U","") | R2: =+IF(Parametres!$B$3=R$6,"X","") | S2: =+IF(Parametres!$B$3=R$6,"O","") | T2: =+IF(Parametres!$B$3=R$6,"U","") | U2: =+IF(Parametres!$B$3=U$6,"X","") | V2: =+IF(Parametres!$B$3=U$6,"O","") | W2: =+IF(Parametres!$B$3=U$6,"U","") | X2: =+IF(Parametres!$B$3=X$6,"X","") | Y2: =+IF(Parametres!$B$3=X$6,"O","") | Z2: =+IF(Parametres!$B$3=X$6,"U","") | AA2: =+IF(Parametres!$B$3=AA$6,"X","") | AB2: =+IF(Parametres!$B$3=AA$6,"O","") | AC2: =+IF(Parametres!$B$3=AA$6,"U","") | AD2: =+IF(Parametres!$B$3=AD$6,"X","") | AE2: =+IF(Parametres!$B$3=AD$6,"O","") | AF2: =+IF(Parametres!$B$3=AD$6,"U","") | AG2: =+IF(Parametres!$B$3=AG$6,"X","") | AH2: =+IF(Parametres!$B$3=AG$6,"O","") | AI2: =+IF(Parametres!$B$3=AG$6,"U","") | AJ2: =+IF(Parametres!$B$3=AJ$6,"X","") | AK2: =+IF(Parametres!$B$3=AJ$6,"O","") | AL2: =+IF(Parametres!$B$3=AJ$6,"U","") | AM2: =+IF(Parametres!$B$3=AM$6,"X","") | AN2: =+IF(Parametres!$B$3=AM$6,"O","") | AO2: =+IF(Parametres!$B$3=AM$6,"U","")
B3: YTD | F3: =+IF(VLOOKUP(F$6,Parametres!$K$3:$N$14,4,0)="X","X","") -> X | G3: =+IF(VLOOKUP(F$6,Parametres!$K$3:$N$14,4,0)="X","O","") -> O | H3: =+IF(VLOOKUP(F$6,Parametres!$K$3:$N$14,4,0)="X","U","") -> U | I3: =+IF(VLOOKUP(I$6,Parametres!$K$3:$N$14,4,0)="X","X","") -> X | J3: =+IF(VLOOKUP(I$6,Parametres!$K$3:$N$14,4,0)="X","O","") -> O | K3: =+IF(VLOOKUP(I$6,Parametres!$K$3:$N$14,4,0)="X","U","") -> U | L3: =+IF(VLOOKUP(L$6,Parametres!$K$3:$N$14,4,0)="X","X","") -> X | M3: =+IF(VLOOKUP(L$6,Parametres!$K$3:$N$14,4,0)="X","O","") -> O | N3: =+IF(VLOOKUP(L$6,Parametres!$K$3:$N$14,4,0)="X","U","") -> U | O3: =+IF(VLOOKUP(O$6,Parametres!$K$3:$N$14,4,0)="X","X","") | P3: =+IF(VLOOKUP(O$6,Parametres!$K$3:$N$14,4,0)="X","O","") | Q3: =+IF(VLOOKUP(O$6,Parametres!$K$3:$N$14,4,0)="X","U","") | R3: =+IF(VLOOKUP(R$6,Parametres!$K$3:$N$14,4,0)="X","X","") | S3: =+IF(VLOOKUP(R$6,Parametres!$K$3:$N$14,4,0)="X","O","") | T3: =+IF(VLOOKUP(R$6,Parametres!$K$3:$N$14,4,0)="X","U","") | U3: =+IF(VLOOKUP(U$6,Parametres!$K$3:$N$14,4,0)="X","X","") | V3: =+IF(VLOOKUP(U$6,Parametres!$K$3:$N$14,4,0)="X","O","") | W3: =+IF(VLOOKUP(U$6,Parametres!$K$3:$N$14,4,0)="X","U","") | X3: =+IF(VLOOKUP(X$6,Parametres!$K$3:$N$14,4,0)="X","X","") | Y3: =+IF(VLOOKUP(X$6,Parametres!$K$3:$N$14,4,0)="X","O","") | Z3: =+IF(VLOOKUP(X$6,Parametres!$K$3:$N$14,4,0)="X","U","") | AA3: =+IF(VLOOKUP(AA$6,Parametres!$K$3:$N$14,4,0)="X","X","") | AB3: =+IF(VLOOKUP(AA$6,Parametres!$K$3:$N$14,4,0)="X","O","") | AC3: =+IF(VLOOKUP(AA$6,Parametres!$K$3:$N$14,4,0)="X","U","") | AD3: =+IF(VLOOKUP(AD$6,Parametres!$K$3:$N$14,4,0)="X","X","") | AE3: =+IF(VLOOKUP(AD$6,Parametres!$K$3:$N$14,4,0)="X","O","") | AF3: =+IF(VLOOKUP(AD$6,Parametres!$K$3:$N$14,4,0)="X","U","") | AG3: =+IF(VLOOKUP(AG$6,Parametres!$K$3:$N$14,4,0)="X","X","") | AH3: =+IF(VLOOKUP(AG$6,Parametres!$K$3:$N$14,4,0)="X","O","") | AI3: =+IF(VLOOKUP(AG$6,Parametres!$K$3:$N$14,4,0)="X","U","") | AJ3: =+IF(VLOOKUP(AJ$6,Parametres!$K$3:$N$14,4,0)="X","X","") | AK3: =+IF(VLOOKUP(AJ$6,Parametres!$K$3:$N$14,4,0)="X","O","") | AL3: =+IF(VLOOKUP(AJ$6,Parametres!$K$3:$N$14,4,0)="X","U","") | AM3: =+IF(VLOOKUP(AM$6,Parametres!$K$3:$N$14,4,0)="X","X","") | AN3: =+IF(VLOOKUP(AM$6,Parametres!$K$3:$N$14,4,0)="X","O","") | AO3: =+IF(VLOOKUP(AM$6,Parametres!$K$3:$N$14,4,0)="X","U","")
B4: Budget 2021 | C4: Véhicules neufs
B6: Mois | C6: 2021 | F6: Janvier | I6: Février | L6: Mars | O6: Avril | R6: Mai | U6: Juin | X6: Juillet | AA6: Août | AD6: Septembre | AG6: Octobre | AJ6: Novembre | AM6: Décembre
C7: UNITE | D7: $P/UNITE | E7: $PROFITS | F7: UNITE | G7: $P/UNITE | H7: $PROFITS | I7: UNITE | J7: $P/UNITE | K7: $PROFITS | L7: UNITE | M7: $P/UNITE | N7: $PROFITS | O7: UNITE | P7: $P/UNITE | Q7: $PROFITS | R7: UNITE | S7: $P/UNITE | T7: $PROFITS | U7: UNITE | V7: $P/UNITE | W7: $PROFITS | X7: UNITE | Y7: $P/UNITE | Z7: $PROFITS | AA7: UNITE | AB7: $P/UNITE | AC7: $PROFITS | AD7: UNITE | AE7: $P/UNITE | AF7: $PROFITS | AG7: UNITE | AH7: $P/UNITE | AI7: $PROFITS | AJ7: UNITE | AK7: $P/UNITE | AL7: $PROFITS | AM7: UNITE | AN7: $P/UNITE | AO7: $PROFITS
A8: =+$C$4&B8 -> Véhicules neufsVentes nettes | B8: Ventes nettes | E8: =+SUM(H8,K8,N8,Q8,T8,W8,Z8,AC8,AF8,AI8,AL8,AO8) -> 9553310.1 | H8: ='[5]véh neufs'!E7+'[5]véh neufs'!E23+'[5]véh neufs'!E38+H27 -> 1882577.9 | K8: ='[5]véh neufs'!$F$7 -> 446219.11 | N8: ='[5]véh neufs'!$G$7 -> 678330.08 | Q8: ='[5]véh neufs'!$H$7 -> 751340.66 | T8: ='[5]véh neufs'!$I$7 -> 981796.55 | W8: ='[5]véh neufs'!$J$7 -> 691716.4 | Z8: ='[5]véh neufs'!$K$7 -> 688676.89 | AC8: ='[5]véh neufs'!$L$7 -> 729220.97 | AF8: ='[5]véh neufs'!$M$7 -> 799077.54 | AI8: ='[5]véh neufs'!$N$7 -> 991144.07 | AL8: ='[5]véh neufs'!$O$7 -> 576007.02 | AO8: ='[5]véh neufs'!$P$7 -> 337202.89
A9: =+$C$4&B9 -> Véhicules neufsAutos détail | B9: Autos détail | C9: =+SUM(F9,I9,L9,O9,R9,U9,X9,AA9,AD9,AG9,AJ9,AM9) -> 303 | D9: =IF(C9=0,0,E9/C9) -> 955.05622 | E9: =+SUM(H9,K9,N9,Q9,T9,W9,Z9,AC9,AF9,AI9,AL9,AO9) -> 289382.03 | F9: ='[5]véh neufs'!$E$4 -> 23.607096 | G9: =IF(F9=0,0,H9/F9) -> 955.05622 | H9: ='[5]véh neufs'!$E$6 -> 22546.103 | I9: ='[5]véh neufs'!$F$4 -> 16.252745 | J9: =IF(I9=0,0,K9/I9) -> 955.05622 | K9: ='[5]véh neufs'!$F$6 -> 15522.285 | L9: ='[5]véh neufs'!$G$4 -> 24.706978 | M9: =IF(L9=0,0,N9/L9) -> 955.05622 | N9: ='[5]véh neufs'!$G$6 -> 23596.553 | O9: ='[5]véh neufs'!$H$4 -> 27.36626 | P9: =IF(O9=0,0,Q9/O9) -> 955.05622 | Q9: ='[5]véh neufs'!$H$6 -> 26136.316 | R9: ='[5]véh neufs'!$I$4 -> 35.76021 | S9: =IF(R9=0,0,T9/R9) -> 955.05622 | T9: ='[5]véh neufs'!$I$6 -> 34153.01 | U9: ='[5]véh neufs'!$J$4 -> 25.194551 | V9: =IF(U9=0,0,W9/U9) -> 955.05622 | W9: ='[5]véh neufs'!$J$6 -> 24062.213 | X9: ='[5]véh neufs'!$K$4 -> 25.083842 | Y9: =IF(X9=0,0,Z9/X9) -> 955.05622 | Z9: ='[5]véh neufs'!$K$6 -> 23956.48 | AA9: ='[5]véh neufs'!$L$4 -> 26.560589 | AB9: =IF(AA9=0,0,AC9/AA9) -> 955.05622 | AC9: ='[5]véh neufs'!$L$6 -> 25366.856 | AD9: ='[5]véh neufs'!$M$4 -> 29.104991 | AE9: =IF(AD9=0,0,AF9/AD9) -> 955.05622 | AF9: ='[5]véh neufs'!$M$6 -> 27796.903 | AG9: ='[5]véh neufs'!$N$4 -> 36.100676 | AH9: =IF(AG9=0,0,AI9/AG9) -> 955.05622 | AI9: ='[5]véh neufs'!$N$6 -> 34478.176 | AJ9: ='[5]véh neufs'!$O$4 -> 20.980041 | AK9: =IF(AJ9=0,0,AL9/AJ9) -> 955.05622 | AL9: ='[5]véh neufs'!$O$6 -> 20037.118 | AM9: ='[5]véh neufs'!$P$4 -> 12.282021 | AN9: =IF(AM9=0,0,AO9/AM9) -> 955.05622 | AO9: ='[5]véh neufs'!$P$6 -> 11730.021
A10: =+$C$4&B10 -> Véhicules neufsCamions détail | B10: Camions détail | C10: =+SUM(F10,I10,L10,O10,R10,U10,X10,AA10,AD10,AG10,AJ10,AM10) -> 407 | D10: =IF(C10=0,0,E10/C10) -> 1702.6669 | E10: =+SUM(H10,K10,N10,Q10,T10,W10,Z10,AC10,AF10,AI10,AL10,AO10) -> 692985.42 | F10: ='[5]véh neufs'!$E$20 -> 31.709861 | G10: =IF(F10=0,0,H10/F10) -> 1702.6669 | H10: ='[5]véh neufs'!$E$22 -> 53991.33 | I10: ='[5]véh neufs'!$F$20 -> 21.831245 | J10: =IF(I10=0,0,K10/I10) -> 1702.6669 | K10: ='[5]véh neufs'!$F$22 -> 37171.338 | L10: ='[5]véh neufs'!$G$20 -> 33.187261 | M10: =IF(L10=0,0,N10/L10) -> 1702.6669 | N10: ='[5]véh neufs'!$G$22 -> 56506.85 | O10: ='[5]véh neufs'!$H$20 -> 36.759299 | P10: =IF(O10=0,0,Q10/O10) -> 1702.6669 | Q10: ='[5]véh neufs'!$H$22 -> 62588.841 | R10: ='[5]véh neufs'!$I$20 -> 48.034341 | S10: =IF(R10=0,0,T10/R10) -> 1702.6669 | T10: ='[5]véh neufs'!$I$22 -> 81786.481 | U10: ='[5]véh neufs'!$J$20 -> 33.842186 | V10: =IF(U10=0,0,W10/U10) -> 1702.6669 | W10: ='[5]véh neufs'!$J$22 -> 57621.969 | X10: ='[5]véh neufs'!$K$20 -> 33.693478 | Y10: =IF(X10=0,0,Z10/X10) -> 1702.6669 | Z10: ='[5]véh neufs'!$K$22 -> 57368.769 | AA10: ='[5]véh neufs'!$L$20 -> 35.677095 | AB10: =IF(AA10=0,0,AC10/AA10) -> 1702.6669 | AC10: ='[5]véh neufs'!$L$22 -> 60746.208 | AD10: ='[5]véh neufs'!$M$20 -> 39.094824 | AE10: =IF(AD10=0,0,AF10/AD10) -> 1702.6669 | AF10: ='[5]véh neufs'!$M$22 -> 66565.461 | AG10: ='[5]véh neufs'!$N$20 -> 48.491668 | AH10: =IF(AG10=0,0,AI10/AG10) -> 1702.6669 | AI10: ='[5]véh neufs'!$N$22 -> 82565.157 | AJ10: ='[5]véh neufs'!$O$20 -> 28.181111 | AK10: =IF(AJ10=0,0,AL10/AJ10) -> 1702.6669 | AL10: ='[5]véh neufs'!$O$22 -> 47983.044 | AM10: ='[5]véh neufs'!$P$20 -> 16.497633 | AN10: =IF(AM10=0,0,AO10/AM10) -> 1702.6669 | AO10: ='[5]véh neufs'!$P$22 -> 28089.973
A11: =+$C$4&B11 -> Véhicules neufsSprinter | B11: Sprinter | C11: =+SUM(F11,I11,L11,O11,R11,U11,X11,AA11,AD11,AG11,AJ11,AM11) -> 0 | D11: =IF(C11=0,0,E11/C11) -> 0 | E11: =+SUM(H11,K11,N11,Q11,T11,W11,Z11,AC11,AF11,AI11,AL11,AO11) -> 0 | G11: =IF(F11=0,0,H11/F11) -> 0 | J11: =IF(I11=0,0,K11/I11) -> 0 | M11: =IF(L11=0,0,N11/L11) -> 0 | P11: =IF(O11=0,0,Q11/O11) -> 0 | S11: =IF(R11=0,0,T11/R11) -> 0 | V11: =IF(U11=0,0,W11/U11) -> 0 | Y11: =IF(X11=0,0,Z11/X11) -> 0 | AB11: =IF(AA11=0,0,AC11/AA11) -> 0 | AE11: =IF(AD11=0,0,AF11/AD11) -> 0 | AH11: =IF(AG11=0,0,AI11/AG11) -> 0 | AK11: =IF(AJ11=0,0,AL11/AJ11) -> 0 | AN11: =IF(AM11=0,0,AO11/AM11) -> 0
A12: =+$C$4&B12 -> Véhicules neufsMoto détail | B12: Moto détail | C12: =+SUM(F12,I12,L12,O12,R12,U12,X12,AA12,AD12,AG12,AJ12,AM12) -> 0 | D12: =IF(C12=0,0,E12/C12) -> 0 | E12: =+SUM(H12,K12,N12,Q12,T12,W12,Z12,AC12,AF12,AI12,AL12,AO12) -> 0 | G12: =IF(F12=0,0,H12/F12) -> 0 | J12: =IF(I12=0,0,K12/I12) -> 0 | M12: =IF(L12=0,0,N12/L12) -> 0 | P12: =IF(O12=0,0,Q12/O12) -> 0 | S12: =IF(R12=0,0,T12/R12) -> 0 | V12: =IF(U12=0,0,W12/U12) -> 0 | Y12: =IF(X12=0,0,Z12/X12) -> 0 | AB12: =IF(AA12=0,0,AC12/AA12) -> 0 | AE12: =IF(AD12=0,0,AF12/AD12) -> 0 | AH12: =IF(AG12=0,0,AI12/AG12) -> 0 | AK12: =IF(AJ12=0,0,AL12/AJ12) -> 0 | AN12: =IF(AM12=0,0,AO12/AM12) -> 0
A13: =+$C$4&B13 -> Véhicules neufs[...] | B13: [...] | C13: =+SUM(F13,I13,L13,O13,R13,U13,X13,AA13,AD13,AG13,AJ13,AM13) -> 0 | D13: =IF(C13=0,0,E13/C13) -> 0 | E13: =+SUM(H13,K13,N13,Q13,T13,W13,Z13,AC13,AF13,AI13,AL13,AO13) -> 0 | G13: =IF(F13=0,0,H13/F13) -> 0 | J13: =IF(I13=0,0,K13/I13) -> 0 | M13: =IF(L13=0,0,N13/L13) -> 0 | P13: =IF(O13=0,0,Q13/O13) -> 0 | S13: =IF(R13=0,0,T13/R13) -> 0 | V13: =IF(U13=0,0,W13/U13) -> 0 | Y13: =IF(X13=0,0,Z13/X13) -> 0 | AB13: =IF(AA13=0,0,AC13/AA13) -> 0 | AE13: =IF(AD13=0,0,AF13/AD13) -> 0 | AH13: =IF(AG13=0,0,AI13/AG13) -> 0 | AK13: =IF(AJ13=0,0,AL13/AJ13) -> 0 | AN13: =IF(AM13=0,0,AO13/AM13) -> 0
A14: =+$C$4&B14 -> Véhicules neufs[...] | B14: [...] | C14: =+SUM(F14,I14,L14,O14,R14,U14,X14,AA14,AD14,AG14,AJ14,AM14) -> 0 | D14: =IF(C14=0,0,E14/C14) -> 0 | E14: =+SUM(H14,K14,N14,Q14,T14,W14,Z14,AC14,AF14,AI14,AL14,AO14) -> 0 | G14: =IF(F14=0,0,H14/F14) -> 0 | J14: =IF(I14=0,0,K14/I14) -> 0 | M14: =IF(L14=0,0,N14/L14) -> 0 | P14: =IF(O14=0,0,Q14/O14) -> 0 | S14: =IF(R14=0,0,T14/R14) -> 0 | V14: =IF(U14=0,0,W14/U14) -> 0 | Y14: =IF(X14=0,0,Z14/X14) -> 0 | AB14: =IF(AA14=0,0,AC14/AA14) -> 0 | AE14: =IF(AD14=0,0,AF14/AD14) -> 0 | AH14: =IF(AG14=0,0,AI14/AG14) -> 0 | AK14: =IF(AJ14=0,0,AL14/AJ14) -> 0 | AN14: =IF(AM14=0,0,AO14/AM14) -> 0
A15: =+$C$4&B15 -> Véhicules neufs[...] | B15: [...] | C15: =+SUM(F15,I15,L15,O15,R15,U15,X15,AA15,AD15,AG15,AJ15,AM15) -> 0 | D15: =IF(C15=0,0,E15/C15) -> 0 | E15: =+SUM(H15,K15,N15,Q15,T15,W15,Z15,AC15,AF15,AI15,AL15,AO15) -> 0 | G15: =IF(F15=0,0,H15/F15) -> 0 | J15: =IF(I15=0,0,K15/I15) -> 0 | M15: =IF(L15=0,0,N15/L15) -> 0 | P15: =IF(O15=0,0,Q15/O15) -> 0 | S15: =IF(R15=0,0,T15/R15) -> 0 | V15: =IF(U15=0,0,W15/U15) -> 0 | Y15: =IF(X15=0,0,Z15/X15) -> 0 | AB15: =IF(AA15=0,0,AC15/AA15) -> 0 | AE15: =IF(AD15=0,0,AF15/AD15) -> 0 | AH15: =IF(AG15=0,0,AI15/AG15) -> 0 | AK15: =IF(AJ15=0,0,AL15/AJ15) -> 0 | AN15: =IF(AM15=0,0,AO15/AM15) -> 0
A16: =+$C$4&B16 -> Véhicules neufsTotal Neufs | B16: Total Neufs | C16: =+SUM(C9:C15) -> 710 | D16: =IF(C16<=0,0,E16/C16) -> 1383.6161 | E16: =+SUM(E9:E15) -> 982367.45 | F16: =+SUM(F9:F15) -> 55.316957 | G16: =IF(F16<=0,0,H16/F16) -> 1383.6161 | H16: =+SUM(H9:H15) -> 76537.434 | I16: =+SUM(I9:I15) -> 38.08399 | J16: =IF(I16<=0,0,K16/I16) -> 1383.6161 | K16: =+SUM(K9:K15) -> 52693.623 | L16: =+SUM(L9:L15) -> 57.894239 | M16: =IF(L16<=0,0,N16/L16) -> 1383.6161 | N16: =+SUM(N9:N15) -> 80103.403 | O16: =+SUM(O9:O15) -> 64.125559 | P16: =IF(O16<=0,0,Q16/O16) -> 1383.6161 | Q16: =+SUM(Q9:Q15) -> 88725.158 | R16: =+SUM(R9:R15) -> 83.79455 | S16: =IF(R16<=0,0,T16/R16) -> 1383.6161 | T16: =+SUM(T9:T15) -> 115939.49 | U16: =+SUM(U9:U15) -> 59.036736 | V16: =IF(U16<=0,0,W16/U16) -> 1383.6161 | W16: =+SUM(W9:W15) -> 81684.181 | X16: =+SUM(X9:X15) -> 58.77732 | Y16: =IF(X16<=0,0,Z16/X16) -> 1383.6161 | Z16: =+SUM(Z9:Z15) -> 81325.249 | AA16: =+SUM(AA9:AA15) -> 62.237684 | AB16: =IF(AA16<=0,0,AC16/AA16) -> 1383.6161 | AC16: =+SUM(AC9:AC15) -> 86113.064 | AD16: =+SUM(AD9:AD15) -> 68.199815 | AE16: =IF(AD16<=0,0,AF16/AD16) -> 1383.6161 | AF16: =+SUM(AF9:AF15) -> 94362.364 | AG16: =+SUM(AG9:AG15) -> 84.592344 | AH16: =IF(AG16<=0,0,AI16/AG16) -> 1383.6161 | AI16: =+SUM(AI9:AI15) -> 117043.33 | AJ16: =+SUM(AJ9:AJ15) -> 49.161152 | AK16: =IF(AJ16<=0,0,AL16/AJ16) -> 1383.6161 | AL16: =+SUM(AL9:AL15) -> 68020.163 | AM16: =+SUM(AM9:AM15) -> 28.779654 | AN16: =IF(AM16<=0,0,AO16/AM16) -> 1383.6161 | AO16: =+SUM(AO9:AO15) -> 39819.993
A17: =+$C$4&B17 -> Véhicules neufs
A18: =+$C$4&B18 -> Véhicules neufsEx-Démos et courtoisies | B18: Ex-Démos et courtoisies | C18: =+SUM(F18,I18,L18,O18,R18,U18,X18,AA18,AD18,AG18,AJ18,AM18) -> 74 | D18: =IF(C18=0,0,E18/C18) -> 790.03378 | E18: =+SUM(H18,K18,N18,Q18,T18,W18,Z18,AC18,AF18,AI18,AL18,AO18) -> 58462.5 | F18: ='[5]véh neufs'!$E$35 -> 5.7654293 | G18: =IF(F18=0,0,H18/F18) -> 790.03378 | H18: ='[5]véh neufs'!$E$37 -> 4554.8839 | I18: ='[5]véh neufs'!$F$35 -> 3.9693173 | J18: =IF(I18=0,0,K18/I18) -> 790.03378 | K18: ='[5]véh neufs'!$F$37 -> 3135.8947 | L18: ='[5]véh neufs'!$G$35 -> 6.0340474 | M18: =IF(L18=0,0,N18/L18) -> 790.03378 | N18: ='[5]véh neufs'!$G$37 -> 4767.1013 | O18: ='[5]véh neufs'!$H$35 -> 6.683509 | P18: =IF(O18=0,0,Q18/O18) -> 790.03378 | Q18: ='[5]véh neufs'!$H$37 -> 5280.1979 | R18: ='[5]véh neufs'!$I$35 -> 8.7335165 | S18: =IF(R18=0,0,T18/R18) -> 790.03378 | T18: ='[5]véh neufs'!$I$37 -> 6899.7731 | U18: ='[5]véh neufs'!$J$35 -> 6.1531246 | V18: =IF(U18=0,0,W18/U18) -> 790.03378 | W18: ='[5]véh neufs'!$J$37 -> 4861.1763 | X18: ='[5]véh neufs'!$K$35 -> 6.1260869 | Y18: =IF(X18=0,0,Z18/X18) -> 790.03378 | Z18: ='[5]véh neufs'!$K$37 -> 4839.8156 | AA18: ='[5]véh neufs'!$L$35 -> 6.4867445 | AB18: =IF(AA18=0,0,AC18/AA18) -> 790.03378 | AC18: ='[5]véh neufs'!$L$37 -> 5124.7473 | AD18: ='[5]véh neufs'!$M$35 -> 7.1081497 | AE18: =IF(AD18=0,0,AF18/AD18) -> 790.03378 | AF18: ='[5]véh neufs'!$M$37 -> 5615.6784 | AG18: ='[5]véh neufs'!$N$35 -> 8.8166669 | AH18: =IF(AG18=0,0,AI18/AG18) -> 790.03378 | AI18: ='[5]véh neufs'!$N$37 -> 6965.4647 | AJ18: ='[5]véh neufs'!$O$35 -> 5.1238383 | AK18: =IF(AJ18=0,0,AL18/AJ18) -> 790.03378 | AL18: ='[5]véh neufs'!$O$37 -> 4048.0054 | AM18: ='[5]véh neufs'!$P$35 -> 2.9995696 | AN18: =IF(AM18=0,0,AO18/AM18) -> 790.03378 | AO18: ='[5]véh neufs'!$P$37 -> 2369.7613
A19: =+$C$4&B19 -> Véhicules neufs
A20: =+$C$4&B20 -> Véhicules neufsFlottes | B20: Flottes | C20: =+SUM(F20,I20,L20,O20,R20,U20,X20,AA20,AD20,AG20,AJ20,AM20) -> 25 | D20: =IF(C20=0,0,E20/C20) -> 800 | E20: =+SUM(H20,K20,N20,Q20,T20,W20,Z20,AC20,AF20,AI20,AL20,AO20) -> 20000 | F20: ='[5]véh neufs'!$E$50 -> 0 | G20: =IF(F20=0,0,H20/F20) -> 0 | H20: ='[5]véh neufs'!$E$52 -> 0 | I20: ='[5]véh neufs'!$F$50 -> 1.4542911 | J20: =IF(I20=0,0,K20/I20) -> 800 | K20: ='[5]véh neufs'!$F$52 -> 1163.4329 | L20: ='[5]véh neufs'!$G$50 -> 2.2107736 | M20: =IF(L20=0,0,N20/L20) -> 800 | N20: ='[5]véh neufs'!$G$52 -> 1768.6189 | O20: ='[5]véh neufs'!$H$50 -> 2.4487254 | P20: =IF(O20=0,0,Q20/O20) -> 800 | Q20: ='[5]véh neufs'!$H$52 -> 1958.9803 | R20: ='[5]véh neufs'!$I$50 -> 3.1998137 | S20: =IF(R20=0,0,T20/R20) -> 800 | T20: ='[5]véh neufs'!$I$52 -> 2559.8509 | U20: ='[5]véh neufs'!$J$50 -> 2.2544015 | V20: =IF(U20=0,0,W20/U20) -> 800 | W20: ='[5]véh neufs'!$J$52 -> 1803.5212 | X20: ='[5]véh neufs'!$K$50 -> 2.2444953 | Y20: =IF(X20=0,0,Z20/X20) -> 800 | Z20: ='[5]véh neufs'!$K$52 -> 1795.5962 | AA20: ='[5]véh neufs'!$L$50 -> 2.3766342 | AB20: =IF(AA20=0,0,AC20/AA20) -> 800 | AC20: ='[5]véh neufs'!$L$52 -> 1901.3073 | AD20: ='[5]véh neufs'!$M$50 -> 2.6043066 | AE20: =IF(AD20=0,0,AF20/AD20) -> 800 | AF20: ='[5]véh neufs'!$M$52 -> 2083.4453 | AG20: ='[5]véh neufs'!$N$50 -> 3.2302786 | AH20: =IF(AG20=0,0,AI20/AG20) -> 800 | AI20: ='[5]véh neufs'!$N$52 -> 2584.2229 | AJ20: ='[5]véh neufs'!$O$50 -> 1.8772883 | AK20: =IF(AJ20=0,0,AL20/AJ20) -> 800 | AL20: ='[5]véh neufs'!$O$52 -> 1501.8306 | AM20: ='[5]véh neufs'!$P$50 -> 1.0989919 | AN20: =IF(AM20=0,0,AO20/AM20) -> 800 | AO20: ='[5]véh neufs'!$P$52 -> 879.1935
A21: =+$C$4&B21 -> Véhicules neufs
A22: =+$C$4&B22 -> Véhicules neufsRachat bail | B22: Rachat bail | E22: =+SUM(H22,K22,N22,Q22,T22,W22,Z22,AC22,AF22,AI22,AL22,AO22) -> 60000 | H22: ='[5]Volume et Profit Front'!$C$7 -> 5000 | K22: ='[5]Volume et Profit Front'!$C$7 -> 5000 | N22: ='[5]Volume et Profit Front'!$C$7 -> 5000 | Q22: ='[5]Volume et Profit Front'!$C$7 -> 5000 | T22: ='[5]Volume et Profit Front'!$C$7 -> 5000 | W22: ='[5]Volume et Profit Front'!$C$7 -> 5000 | Z22: ='[5]Volume et Profit Front'!$C$7 -> 5000 | AC22: ='[5]Volume et Profit Front'!$C$7 -> 5000 | AF22: ='[5]Volume et Profit Front'!$C$7 -> 5000 | AI22: ='[5]Volume et Profit Front'!$C$7 -> 5000 | AL22: ='[5]Volume et Profit Front'!$C$7 -> 5000 | AO22: ='[5]Volume et Profit Front'!$C$7 -> 5000
A23: =+$C$4&B23 -> Véhicules neufs
A24: =+$C$4&B24 -> Véhicules neufsRev. Finances | B24: Rev. Finances | D24: =IF(C16=0,0,E24/(C16+C18)) -> 94.079794 | E24: =+SUM(H24,K24,N24,Q24,T24,W24,Z24,AC24,AF24,AI24,AL24,AO24) -> 73758.559 | G24: =IF(F16=0,0,H24/(F16+F18)) -> 94.079794 | H24: ='[5]véh neufs'!$E$150 -> 5746.6183 | J24: =IF(I16=0,0,K24/(I16+I18)) -> 94.079794 | K24: ='[5]véh neufs'!$F$150 -> 3956.3665 | M24: =IF(L16=0,0,N24/(L16+L18)) -> 94.079794 | N24: ='[5]véh neufs'!$G$150 -> 6014.36 | P24: =IF(O16=0,0,Q24/(O16+O18)) -> 94.079794 | Q24: ='[5]véh neufs'!$H$150 -> 6661.7025 | S24: =IF(R16=0,0,T24/(R16+R18)) -> 94.079794 | T24: ='[5]véh neufs'!$I$150 -> 8705.0215 | V24: =IF(U16=0,0,W24/(U16+U18)) -> 94.079794 | W24: ='[5]véh neufs'!$J$150 -> 6133.0487 | Y24: =IF(X16=0,0,Z24/(X16+X18)) -> 94.079794 | Z24: ='[5]véh neufs'!$K$150 -> 6106.0992 | AB24: =IF(AA16=0,0,AC24/(AA16+AA18)) -> 94.079794 | AC24: ='[5]véh neufs'!$L$150 -> 6465.5801 | AE24: =IF(AD16=0,0,AF24/(AD16+AD18)) -> 94.079794 | AF24: ='[5]véh neufs'!$M$150 -> 7084.9578 | AH24: =IF(AG16=0,0,AI24/(AG16+AG18)) -> 94.079794 | AI24: ='[5]véh neufs'!$N$150 -> 8787.9005 | AK24: =IF(AJ16=0,0,AL24/(AJ16+AJ18)) -> 94.079794 | AL24: ='[5]véh neufs'!$O$150 -> 5107.1207 | AN24: =IF(AM16=0,0,AO24/(AM16+AM18)) -> 94.079794 | AO24: ='[5]véh neufs'!$P$150 -> 2989.7828
A25: =+$C$4&B25 -> Véhicules neufsRev. Protections | B25: Rev. Protections | D25: =IF(C16=0,0,E25/(C16+C18)) -> 737.32304 | E25: =+SUM(H25,K25,N25,Q25,T25,W25,Z25,AC25,AF25,AI25,AL25,AO25) -> 578061.26 | G25: =IF(F16=0,0,H25/(F16+F18)) -> 737.32304 | H25: ='[5]véh neufs'!$E$151 -> 45037.45 | J25: =IF(I16=0,0,K25/(I16+I18)) -> 737.32304 | K25: ='[5]véh neufs'!$F$151 -> 31006.872 | M25: =IF(L16=0,0,N25/(L16+L18)) -> 737.32304 | N25: ='[5]véh neufs'!$G$151 -> 47135.798 | P25: =IF(O16=0,0,Q25/(O16+O18)) -> 737.32304 | Q25: ='[5]véh neufs'!$H$151 -> 52209.157 | S25: =IF(R16=0,0,T25/(R16+R18)) -> 737.32304 | T25: ='[5]véh neufs'!$I$151 -> 68223.075 | V25: =IF(U16=0,0,W25/(U16+U18)) -> 737.32304 | W25: ='[5]véh neufs'!$J$151 -> 48065.986 | Y25: =IF(X16=0,0,Z25/(X16+X18)) -> 737.32304 | Z25: ='[5]véh neufs'!$K$151 -> 47854.777 | AB25: =IF(AA16=0,0,AC25/(AA16+AA18)) -> 737.32304 | AC25: ='[5]véh neufs'!$L$151 -> 50672.104 | AE25: =IF(AD16=0,0,AF25/(AD16+AD18)) -> 737.32304 | AF25: ='[5]véh neufs'!$M$151 -> 55526.297 | AH25: =IF(AG16=0,0,AI25/(AG16+AG18)) -> 737.32304 | AI25: ='[5]véh neufs'!$N$151 -> 68872.616 | AK25: =IF(AJ16=0,0,AL25/(AJ16+AJ18)) -> 737.32304 | AL25: ='[5]véh neufs'!$O$151 -> 40025.574 | AN25: =IF(AM16=0,0,AO25/(AM16+AM18)) -> 737.32304 | AO25: ='[5]véh neufs'!$P$151 -> 23431.554
A26: =+$C$4&B26 -> Véhicules neufsRev. Autres | B26: Rev. Autres | D26: =IF(C16=0,0,E26/(C16+C18)) -> 18.597169 | E26: =+SUM(H26,K26,N26,Q26,T26,W26,Z26,AC26,AF26,AI26,AL26,AO26) -> 14580.18 | G26: =IF(F16=0,0,H26/(F16+F18)) -> 18.597169 | H26: ='[5]véh neufs'!$E$152 -> 1135.9594 | J26: =IF(I16=0,0,K26/(I16+I18)) -> 18.597169 | K26: ='[5]véh neufs'!$F$152 -> 782.07244 | M26: =IF(L16=0,0,N26/(L16+L18)) -> 18.597169 | N26: ='[5]véh neufs'!$G$152 -> 1188.8851 | P26: =IF(O16=0,0,Q26/(O16+O18)) -> 18.597169 | Q26: ='[5]véh neufs'!$H$152 -> 1316.8482 | S26: =IF(R16=0,0,T26/(R16+R18)) -> 18.597169 | T26: ='[5]véh neufs'!$I$152 -> 1720.7601 | V26: =IF(U16=0,0,W26/(U16+U18)) -> 18.597169 | W26: ='[5]véh neufs'!$J$152 -> 1212.3468 | Y26: =IF(X16=0,0,Z26/(X16+X18)) -> 18.597169 | Z26: ='[5]véh neufs'!$K$152 -> 1207.0196 | AB26: =IF(AA16=0,0,AC26/(AA16+AA18)) -> 18.597169 | AC26: ='[5]véh neufs'!$L$152 -> 1278.0798 | AE26: =IF(AD16=0,0,AF26/(AD16+AD18)) -> 18.597169 | AF26: ='[5]véh neufs'!$M$152 -> 1400.5149 | AH26: =IF(AG16=0,0,AI26/(AG16+AG18)) -> 18.597169 | AI26: ='[5]véh neufs'!$N$152 -> 1737.1431 | AK26: =IF(AJ16=0,0,AL26/(AJ16+AJ18)) -> 18.597169 | AL26: ='[5]véh neufs'!$O$152 -> 1009.5471 | AN26: =IF(AM16=0,0,AO26/(AM16+AM18)) -> 18.597169 | AO26: ='[5]véh neufs'!$P$152 -> 591.00358
A27: =+$C$4&B27 -> Véhicules neufsTotal F&I | B27: Total F&I | C27: =+C18+C16 -> 784 | D27: =IF(C27<=0,0,E27/C27) -> 850 | E27: =E24+E25+E26 -> 666400 | F27: =+F18+F16 -> 61.082386 | G27: =IF(F27<=0,0,H27/F27) -> 850 | H27: =H24+H25+H26 -> 51920.028 | I27: =+I18+I16 -> 42.053307 | J27: =IF(I27<=0,0,K27/I27) -> 850 | K27: =K24+K25+K26 -> 35745.311 | L27: =+L18+L16 -> 63.928286 | M27: =IF(L27<=0,0,N27/L27) -> 850 | N27: =N24+N25+N26 -> 54339.043 | O27: =+O18+O16 -> 70.809068 | P27: =IF(O27<=0,0,Q27/O27) -> 850 | Q27: =Q24+Q25+Q26 -> 60187.708 | R27: =+R18+R16 -> 92.528067 | S27: =IF(R27<=0,0,T27/R27) -> 850 | T27: =$T$24+$T$25+$T$26 -> 78648.857 | U27: =+U18+U16 -> 65.189861 | V27: =IF(U27<=0,0,W27/U27) -> 850 | W27: =W24+W25+W26 -> 55411.382 | X27: =+X18+X16 -> 64.903407 | Y27: =IF(X27<=0,0,Z27/X27) -> 850 | Z27: =Z24+Z25+Z26 -> 55167.896 | AA27: =+AA18+AA16 -> 68.724428 | AB27: =IF(AA27<=0,0,AC27/AA27) -> 850 | AC27: =AC24+AC25+AC26 -> 58415.764 | AD27: =+AD18+AD16 -> 75.307965 | AE27: =IF(AD27<=0,0,AF27/AD27) -> 850 | AF27: =AF24+AF25+AF26 -> 64011.77 | AG27: =+AG18+AG16 -> 93.409011 | AH27: =IF(AG27<=0,0,AI27/AG27) -> 850 | AI27: =AI24+AI25+AI26 -> 79397.659 | AJ27: =+AJ18+AJ16 -> 54.28499 | AK27: =IF(AJ27<=0,0,AL27/AJ27) -> 850 | AL27: =AL24+AL25+AL26 -> 46142.241 | AM27: =+AM18+AM16 -> 31.779223 | AN27: =IF(AM27<=0,0,AO27/AM27) -> 850 | AO27: =AO24+AO25+AO26 -> 27012.34
A28: =+$C$4&B28 -> Véhicules neufs
A29: =+$C$4&B29 -> Véhicules neufs
A30: =+$C$4&B30 -> Véhicules neufsTotal Dépt. Neufs | B30: Total Dépt. Neufs | C30: =+C16+C18+C20 -> 809 | D30: =IF(C30<=0,0,E30/C30) -> 2209.1841 | E30: =E16+E20+E27+E22+E18 -> 1787230 | F30: =+F16+F18+F20 -> 61.082386 | G30: =IF(F30<=0,0,H30/F30) -> 2259.4459 | H30: =H16+H20+H27+H22+H18 -> 138012.35 | I30: =+I16+I18+I20 -> 43.507598 | J30: =IF(I30<=0,0,K30/I30) -> 2246.4642 | K30: =K16+K20+K27+K22+K18 -> 97738.262 | L30: =+L16+L18+L20 -> 66.13906 | M30: =IF(L30<=0,0,N30/L30) -> 2207.14 | N30: =N16+N20+N27+N22+N18 -> 145978.17 | O30: =+O16+O18+O20 -> 73.257793 | P30: =IF(O30<=0,0,Q30/O30) -> 2199.7939 | Q30: =Q16+Q20+Q27+Q22+Q18 -> 161152.04 | R30: =+R16+R18+R20 -> 95.727881 | S30: =IF(R30<=0,0,T30/R30) -> 2183.7731 | T30: =T16+T20+T27+T22+T18 -> 209047.97 | U30: =+U16+U18+U20 -> 67.444263 | V30: =IF(U30<=0,0,W30/U30) -> 2205.677 | W30: =W16+W20+W27+W22+W18 -> 148760.26 | X30: =+X16+X18+X20 -> 67.147902 | Y30: =IF(X30<=0,0,Z30/X30) -> 2206.0042 | Z30: =Z16+Z20+Z27+Z22+Z18 -> 148128.56 | AA30: =+AA16+AA18+AA20 -> 71.101063 | AB30: =IF(AA30<=0,0,AC30/AA30) -> 2201.8642 | AC30: =AC16+AC20+AC27+AC22+AC18 -> 156554.88 | AD30: =+AD16+AD18+AD20 -> 77.912271 | AE30: =IF(AD30<=0,0,AF30/AD30) -> 2195.7165 | AF30: =AF16+AF20+AF27+AF22+AF18 -> 171073.26 | AG30: =+AG16+AG18+AG20 -> 96.63929 | AH30: =IF(AG30<=0,0,AI30/AG30) -> 2183.2805 | AI30: =AI16+AI20+AI27+AI22+AI18 -> 210990.68 | AJ30: =+AJ16+AJ18+AJ20 -> 56.162278 | AK30: =IF(AJ30<=0,0,AL30/AJ30) -> 2220.5695 | AL30: =AL16+AL20+AL27+AL22+AL18 -> 124712.24 | AM30: =+AM16+AM18+AM20 -> 32.878215 | AN30: =IF(AM30<=0,0,AO30/AM30) -> 2283.6181 | AO30: =AO16+AO20+AO27+AO22+AO18 -> 75081.288
A31: =+$C$4&B31 -> Véhicules neufs
A32: =+$C$4&B32 -> Véhicules neufs
A33: =+$C$4&B33 -> Véhicules neufsDEPENSES | B33: DEPENSES
A34: =+$C$4&B34 -> Véhicules neufsComm. vendeurs | B34: Comm. vendeurs | C34: =E34/(E16+E18) -> 0.29080739 | D34: =IF(E34=0,0,E34/C$27) -> 386.07276 | E34: =+SUM(H34,K34,N34,Q34,T34,W34,Z34,AC34,AF34,AI34,AL34,AO34) -> 302681.05 | F34: =H34/(H16+H18) -> 0.29186552 | G34: =IF(H34=0,0,H34/F$27) -> 387.47753 | H34: ='[5]véh neufs'!$E$263 -> 23668.052 | I34: =K34/(K16+K18) -> 0.32814705 | J34: =IF(K34=0,0,K34/I$27) -> 435.64449 | K34: ='[5]véh neufs'!$F$263 -> 18320.292 | L34: =N34/(N16+N18) -> 0.29618008 | M34: =IF(N34=0,0,N34/L$27) -> 393.20549 | N34: ='[5]véh neufs'!$G$263 -> 25136.953 | O34: =Q34/(Q16+Q18) -> 0.28622244 | P34: =IF(Q34=0,0,Q34/O$27) -> 379.98583 | Q34: ='[5]véh neufs'!$H$263 -> 26906.443 | R34: =T34/(T16+T18) -> 0.26854424 | S34: =IF(T34=0,0,T34/R$27) -> 356.51645 | T34: ='[5]véh neufs'!$I$263 -> 32987.778 | U34: =W34/(W16+W18) -> 0.29202669 | V34: =IF(W34=0,0,W34/U$27) -> 387.69149 | W34: ='[5]véh neufs'!$J$263 -> 25273.555 | X34: =Z34/(Z16+Z18) -> 0.2950188 | Y34: =IF(Z34=0,0,Z34/X$27) -> 391.66378 | Z34: ='[5]véh neufs'!$K$263 -> 25420.314 | AA34: =AC34/(AC16+AC18) -> 0.28826499 | AB34: =IF(AC34=0,0,AC34/AA$27) -> 382.69749 | AC34: ='[5]véh neufs'!$L$263 -> 26300.666 | AD34: =AF34/(AF16+AF18) -> 0.28219976 | AE34: =IF(AF34=0,0,AF34/AD$27) -> 374.64536 | AF34: ='[5]véh neufs'!$M$263 -> 28213.779 | AG34: =AI34/(AI16+AI18) -> 0.26993062 | AH34: =IF(AI34=0,0,AI34/AG$27) -> 358.35698 | AI34: ='[5]véh neufs'!$N$263 -> 33473.772 | AJ34: =AL34/(AL16+AL18) -> 0.30671936 | AK34: =IF(AL34=0,0,AL34/AJ$27) -> 407.19732 | AL34: ='[5]véh neufs'!$O$263 -> 22104.703 | AM34: =AO34/(AO16+AO18) -> 0.3525676 | AN34: =IF(AO34=0,0,AO34/AM$27) -> 468.06495 | AO34: ='[5]véh neufs'!$P$263 -> 14874.741
A35: =+$C$4&B35 -> Véhicules neufsComm. F&I | B35: Comm. F&I | C35: =E35/E27 -> 0.3 | D35: =IF(E35=0,0,E35/C$27) -> 255 | E35: =+SUM(H35,K35,N35,Q35,T35,W35,Z35,AC35,AF35,AI35,AL35,AO35) -> 199920 | F35: =H35/H27 -> 0.3 | G35: =IF(H35=0,0,H35/F$27) -> 255 | H35: ='[5]véh neufs'!$E$271 -> 15576.008 | I35: =K35/K27 -> 0.3 | J35: =IF(K35=0,0,K35/I$27) -> 255 | K35: ='[5]véh neufs'!$F$271 -> 10723.593 | L35: =N35/N27 -> 0.3 | M35: =IF(N35=0,0,N35/L$27) -> 255 | N35: ='[5]véh neufs'!$G$271 -> 16301.713 | O35: =Q35/Q27 -> 0.3 | P35: =IF(Q35=0,0,Q35/O$27) -> 255 | Q35: ='[5]véh neufs'!$H$271 -> 18056.312 | R35: =T35/T27 -> 0.3 | S35: =IF(T35=0,0,T35/R$27) -> 255 | T35: ='[5]véh neufs'!$I$271 -> 23594.657 | U35: =W35/W27 -> 0.3 | V35: =IF(W35=0,0,W35/U$27) -> 255 | W35: ='[5]véh neufs'!$J$271 -> 16623.415 | X35: =Z35/Z27 -> 0.3 | Y35: =IF(Z35=0,0,Z35/X$27) -> 255 | Z35: ='[5]véh neufs'!$K$271 -> 16550.369 | AA35: =AC35/AC27 -> 0.3 | AB35: =IF(AC35=0,0,AC35/AA$27) -> 255 | AC35: ='[5]véh neufs'!$L$271 -> 17524.729 | AD35: =AF35/AF27 -> 0.3 | AE35: =IF(AF35=0,0,AF35/AD$27) -> 255 | AF35: ='[5]véh neufs'!$M$271 -> 19203.531 | AG35: =AI35/AI27 -> 0.3 | AH35: =IF(AI35=0,0,AI35/AG$27) -> 255 | AI35: ='[5]véh neufs'!$N$271 -> 23819.298 | AJ35: =AL35/AL27 -> 0.3 | AK35: =IF(AL35=0,0,AL35/AJ$27) -> 255 | AL35: ='[5]véh neufs'!$O$271 -> 13842.672 | AM35: =AO35/AO27 -> 0.3 | AN35: =IF(AO35=0,0,AO35/AM$27) -> 255 | AO35: ='[5]véh neufs'!$P$271 -> 8103.702
A36: =+$C$4&B36 -> Véhicules neufsFrais de livraison | B36: Frais de livraison | D36: =IF(E36=0,0,E36/C$27) -> 197 | E36: =+SUM(H36,K36,N36,Q36,T36,W36,Z36,AC36,AF36,AI36,AL36,AO36) -> 154448 | G36: =IF(H36=0,0,H36/F$27) -> 197 | H36: =[5]DEPA!$E$9 -> 12033.23 | J36: =IF(K36=0,0,K36/I$27) -> 197 | K36: =[5]DEPA!$F$9 -> 8284.5015 | M36: =IF(N36=0,0,N36/L$27) -> 197 | N36: =[5]DEPA!$G$9 -> 12593.872 | P36: =IF(Q36=0,0,Q36/O$27) -> 197 | Q36: =[5]DEPA!$H$9 -> 13949.386 | S36: =IF(T36=0,0,T36/R$27) -> 197 | T36: =[5]DEPA!$I$9 -> 18228.029 | V36: =IF(W36=0,0,W36/U$27) -> 197 | W36: =[5]DEPA!$J$9 -> 12842.403 | Y36: =IF(Z36=0,0,Z36/X$27) -> 197 | Z36: =[5]DEPA!$K$9 -> 12785.971 | AB36: =IF(AC36=0,0,AC36/AA$27) -> 197 | AC36: =[5]DEPA!$L$9 -> 13538.712 | AE36: =IF(AF36=0,0,AF36/AD$27) -> 197 | AF36: =[5]DEPA!$M$9 -> 14835.669 | AH36: =IF(AI36=0,0,AI36/AG$27) -> 197 | AI36: =[5]DEPA!$N$9 -> 18401.575 | AK36: =IF(AL36=0,0,AL36/AJ$27) -> 197 | AL36: =[5]DEPA!$O$9 -> 10694.143 | AN36: =IF(AO36=0,0,AO36/AM$27) -> 197 | AO36: =[5]DEPA!$P$9 -> 6260.507
A37: =+$C$4&B37 -> Véhicules neufsService gratuit 1 | B37: Service gratuit 1 | D37: =IF(E37=0,0,E37/C$27) -> 6 | E37: =+SUM(H37,K37,N37,Q37,T37,W37,Z37,AC37,AF37,AI37,AL37,AO37) -> 4704 | G37: =IF(H37=0,0,H37/F$27) -> 6 | H37: =[5]DEPA!$E$18 -> 366.49431 | J37: =IF(K37=0,0,K37/I$27) -> 6 | K37: =[5]DEPA!$F$18 -> 252.31984 | M37: =IF(N37=0,0,N37/L$27) -> 6 | N37: =[5]DEPA!$G$18 -> 383.56972 | P37: =IF(Q37=0,0,Q37/O$27) -> 6 | Q37: =[5]DEPA!$H$18 -> 424.85441 | S37: =IF(T37=0,0,T37/R$27) -> 6 | T37: =[5]DEPA!$I$18 -> 555.1684 | V37: =IF(W37=0,0,W37/U$27) -> 6 | W37: =[5]DEPA!$J$18 -> 391.13917 | Y37: =IF(Z37=0,0,Z37/X$27) -> 6 | Z37: =[5]DEPA!$K$18 -> 389.42044 | AB37: =IF(AC37=0,0,AC37/AA$27) -> 6 | AC37: =[5]DEPA!$L$18 -> 412.34657 | AE37: =IF(AF37=0,0,AF37/AD$27) -> 6 | AF37: =[5]DEPA!$M$18 -> 451.84779 | AH37: =IF(AI37=0,0,AI37/AG$27) -> 6 | AI37: =[5]DEPA!$N$18 -> 560.45407 | AK37: =IF(AL37=0,0,AL37/AJ$27) -> 6 | AL37: =[5]DEPA!$O$18 -> 325.70994 | AN37: =IF(AO37=0,0,AO37/AM$27) -> 6 | AO37: =[5]DEPA!$P$18 -> 190.67534
A38: =+$C$4&B38 -> Véhicules neufsEntretien stock | B38: Entretien stock | D38: =IF(E38=0,0,E38/C$27) -> 34 | E38: =+SUM(H38,K38,N38,Q38,T38,W38,Z38,AC38,AF38,AI38,AL38,AO38) -> 26656 | G38: =IF(H38=0,0,H38/F$27) -> 34 | H38: =[5]DEPA!$E$24 -> 2076.8011 | J38: =IF(K38=0,0,K38/I$27) -> 34 | K38: =[5]DEPA!$F$24 -> 1429.8124 | M38: =IF(N38=0,0,N38/L$27) -> 34 | N38: =[5]DEPA!$G$24 -> 2173.5617 | P38: =IF(Q38=0,0,Q38/O$27) -> 34 | Q38: =[5]DEPA!$H$24 -> 2407.5083 | S38: =IF(T38=0,0,T38/R$27) -> 34 | T38: =[5]DEPA!$I$24 -> 3145.9543 | V38: =IF(W38=0,0,W38/U$27) -> 34 | W38: =[5]DEPA!$J$24 -> 2216.4553 | Y38: =IF(Z38=0,0,Z38/X$27) -> 34 | Z38: =[5]DEPA!$K$24 -> 2206.7158 | AB38: =IF(AC38=0,0,AC38/AA$27) -> 34 | AC38: =[5]DEPA!$L$24 -> 2336.6306 | AE38: =IF(AF38=0,0,AF38/AD$27) -> 34 | AF38: =[5]DEPA!$M$24 -> 2560.4708 | AH38: =IF(AI38=0,0,AI38/AG$27) -> 34 | AI38: =[5]DEPA!$N$24 -> 3175.9064 | AK38: =IF(AL38=0,0,AL38/AJ$27) -> 34 | AL38: =[5]DEPA!$O$24 -> 1845.6897 | AN38: =IF(AO38=0,0,AO38/AM$27) -> 34 | AO38: =[5]DEPA!$P$24 -> 1080.4936
A39: =+$C$4&B39 -> Véhicules neufsPublicité 1 | B39: Publicité 1 | D39: =IF(E39=0,0,E39/C$27) -> 180.66964 | E39: =+SUM(H39,K39,N39,Q39,T39,W39,Z39,AC39,AF39,AI39,AL39,AO39) -> 141645 | G39: =IF(H39=0,0,H39/F$27) -> 180.66964 | H39: =[5]DEPA!$E$33+[5]DEPA!$E$34 -> 11035.733 | J39: =IF(K39=0,0,K39/I$27) -> 180.66964 | K39: =[5]DEPA!$F$33+[5]DEPA!$F$34 -> 7597.756 | M39: =IF(N39=0,0,N39/L$27) -> 180.66964 | N39: =[5]DEPA!$G$33+[5]DEPA!$G$34 -> 11549.901 | P39: =IF(Q39=0,0,Q39/O$27) -> 180.66964 | Q39: =[5]DEPA!$H$33+[5]DEPA!$H$34 -> 12793.049 | S39: =IF(T39=0,0,T39/R$27) -> 180.66964 | T39: =[5]DEPA!$I$33+[5]DEPA!$I$34 -> 16717.013 | V39: =IF(W39=0,0,W39/U$27) -> 180.66964 | W39: =[5]DEPA!$J$33+[5]DEPA!$J$34 -> 11777.829 | Y39: =IF(Z39=0,0,Z39/X$27) -> 180.66964 | Z39: =[5]DEPA!$K$33+[5]DEPA!$K$34 -> 11726.075 | AB39: =IF(AC39=0,0,AC39/AA$27) -> 180.66964 | AC39: =[5]DEPA!$L$33+[5]DEPA!$L$34 -> 12416.418 | AE39: =IF(AF39=0,0,AF39/AD$27) -> 180.66964 | AF39: =[5]DEPA!$M$33+[5]DEPA!$M$34 -> 13605.863 | AH39: =IF(AI39=0,0,AI39/AG$27) -> 180.66964 | AI39: =[5]DEPA!$N$33+[5]DEPA!$N$34 -> 16876.173 | AK39: =IF(AL39=0,0,AL39/AJ$27) -> 180.66964 | AL39: =[5]DEPA!$O$33+[5]DEPA!$O$34 -> 9807.6498 | AN39: =IF(AO39=0,0,AO39/AM$27) -> 180.66964 | AO39: =[5]DEPA!$P$33+[5]DEPA!$P$34 -> 5741.5409
A40: =+$C$4&B40 -> Véhicules neufsIntérêt de gros | B40: Intérêt de gros | D40: =IF(E40=0,0,E40/C$27) -> 224.43136 | E40: =+SUM(H40,K40,N40,Q40,T40,W40,Z40,AC40,AF40,AI40,AL40,AO40) -> 175954.18 | G40: =IF(H40=0,0,H40/F$27) -> 226.99495 | H40: =[5]DEPA!$E$46 -> 13865.393 | J40: =IF(K40=0,0,K40/I$27) -> 332.88053 | K40: =[5]DEPA!$F$46 -> 13998.727 | M40: =IF(N40=0,0,N40/L$27) -> 231.24629 | N40: =[5]DEPA!$G$46 -> 14783.179 | P40: =IF(Q40=0,0,Q40/O$27) -> 219.79355 | Q40: =[5]DEPA!$H$46 -> 15563.376 | S40: =IF(T40=0,0,T40/R$27) -> 166.54498 | T40: =[5]DEPA!$I$46 -> 15410.085 | V40: =IF(W40=0,0,W40/U$27) -> 224.82774 | W40: =[5]DEPA!$J$46 -> 14656.489 | Y40: =IF(Z40=0,0,Z40/X$27) -> 227.30566 | Z40: =[5]DEPA!$K$46 -> 14752.912 | AB40: =IF(AC40=0,0,AC40/AA$27) -> 218.79769 | AC40: =[5]DEPA!$L$46 -> 15036.746 | AE40: =IF(AF40=0,0,AF40/AD$27) -> 208.61189 | AF40: =[5]DEPA!$M$46 -> 15710.137 | AH40: =IF(AI40=0,0,AI40/AG$27) -> 162.04683 | AI40: =[5]DEPA!$N$46 -> 15136.634 | AK40: =IF(AL40=0,0,AL40/AJ$27) -> 247.86566 | AL40: =[5]DEPA!$O$46 -> 13455.385 | AN40: =IF(AO40=0,0,AO40/AM$27) -> 427.48427 | AO40: =[5]DEPA!$P$46 -> 13585.118
A41: =+$C$4&B41 -> Véhicules neufs[...] | B41: [...] | D41: =IF(E41=0,0,E41/C$27) -> 0 | E41: =+SUM(H41,K41,N41,Q41,T41,W41,Z41,AC41,AF41,AI41,AL41,AO41) -> 0 | G41: =IF(H41=0,0,H41/F$27) -> 0 | J41: =IF(K41=0,0,K41/I$27) -> 0 | M41: =IF(N41=0,0,N41/L$27) -> 0 | P41: =IF(Q41=0,0,Q41/O$27) -> 0 | S41: =IF(T41=0,0,T41/R$27) -> 0 | V41: =IF(W41=0,0,W41/U$27) -> 0 | Y41: =IF(Z41=0,0,Z41/X$27) -> 0 | AB41: =IF(AC41=0,0,AC41/AA$27) -> 0 | AE41: =IF(AF41=0,0,AF41/AD$27) -> 0 | AH41: =IF(AI41=0,0,AI41/AG$27) -> 0 | AK41: =IF(AL41=0,0,AL41/AJ$27) -> 0 | AN41: =IF(AO41=0,0,AO41/AM$27) -> 0
A42: =+$C$4&B42 -> Véhicules neufs[...] | B42: [...] | D42: =IF(E42=0,0,E42/C$27) -> 0 | E42: =+SUM(H42,K42,N42,Q42,T42,W42,Z42,AC42,AF42,AI42,AL42,AO42) -> 0 | G42: =IF(H42=0,0,H42/F$27) -> 0 | J42: =IF(K42=0,0,K42/I$27) -> 0 | M42: =IF(N42=0,0,N42/L$27) -> 0 | P42: =IF(Q42=0,0,Q42/O$27) -> 0 | S42: =IF(T42=0,0,T42/R$27) -> 0 | V42: =IF(W42=0,0,W42/U$27) -> 0 | Y42: =IF(Z42=0,0,Z42/X$27) -> 0 | AB42: =IF(AC42=0,0,AC42/AA$27) -> 0 | AE42: =IF(AF42=0,0,AF42/AD$27) -> 0 | AH42: =IF(AI42=0,0,AI42/AG$27) -> 0 | AK42: =IF(AL42=0,0,AL42/AJ$27) -> 0 | AN42: =IF(AO42=0,0,AO42/AM$27) -> 0
A43: =+$C$4&B43 -> Véhicules neufs[...] | B43: [...] | D43: =IF(E43=0,0,E43/C$27) -> 0 | E43: =+SUM(H43,K43,N43,Q43,T43,W43,Z43,AC43,AF43,AI43,AL43,AO43) -> 0 | G43: =IF(H43=0,0,H43/F$27) -> 0 | J43: =IF(K43=0,0,K43/I$27) -> 0 | M43: =IF(N43=0,0,N43/L$27) -> 0 | P43: =IF(Q43=0,0,Q43/O$27) -> 0 | S43: =IF(T43=0,0,T43/R$27) -> 0 | V43: =IF(W43=0,0,W43/U$27) -> 0 | Y43: =IF(Z43=0,0,Z43/X$27) -> 0 | AB43: =IF(AC43=0,0,AC43/AA$27) -> 0 | AE43: =IF(AF43=0,0,AF43/AD$27) -> 0 | AH43: =IF(AI43=0,0,AI43/AG$27) -> 0 | AK43: =IF(AL43=0,0,AL43/AJ$27) -> 0 | AN43: =IF(AO43=0,0,AO43/AM$27) -> 0
A44: =+$C$4&B44 -> Véhicules neufsTOTAL VARIABLES | B44: TOTAL VARIABLES | C44: % brut | D44: =IFERROR(E44/E$30,0) -> 0.56288684 | E44: =SUM(E34:E43) -> 1006008.2 | F44: % brut | G44: =IFERROR(H44/H$30,0) -> 0.56967159 | H44: =SUM(H34:H43) -> 78621.712 | I44: % brut | J44: =IFERROR(K44/K$30,0) -> 0.62009495 | K44: =SUM(K34:K43) -> 60607.002 | L44: % brut | M44: =IFERROR(N44/N$30,0) -> 0.56804899 | N44: =SUM(N34:N43) -> 82922.75 | O44: % brut | P44: =IFERROR(Q44/Q$30,0) -> 0.5591051 | Q44: =SUM(Q34:Q43) -> 90100.929 | R44: % brut | S44: =IFERROR(T44/T$30,0) -> 0.52925021 | T44: =SUM(T34:T43) -> 110638.68 | U44: % brut | V44: =IFERROR(W44/W$30,0) -> 0.56319668 | W44: =SUM(W34:W43) -> 83781.285 | X44: % brut | Y44: =IFERROR(Z44/Z$30,0) -> 0.56593934 | Z44: =SUM(Z34:Z43) -> 83831.777 | AA44: % brut | AB44: =IFERROR(AC44/AC$30,0) -> 0.5593326 | AC44: =SUM(AC34:AC43) -> 87566.249 | AD44: % brut | AE44: =IFERROR(AF44/AF$30,0) -> 0.55287015 | AF44: =SUM(AF34:AF43) -> 94581.298 | AG44: % brut | AH44: =IFERROR(AI44/AI$30,0) -> 0.52819306 | AI44: =SUM(AI34:AI43) -> 111443.81 | AJ44: % brut | AK44: =IFERROR(AL44/AL$30,0) -> 0.57793808 | AL44: =SUM(AL34:AL43) -> 72075.952 | AM44: % brut | AN44: =IFERROR(AO44/AO$30,0) -> 0.66377094 | AO44: =SUM(AO34:AO43) -> 49836.777
A45: =+$C$4&B45 -> Véhicules neufsSalaires cadres | B45: Salaires cadres | E45: =+SUM(H45,K45,N45,Q45,T45,W45,Z45,AC45,AF45,AI45,AL45,AO45) -> 299404.6 | H45: =[5]Salaire!$E$33 -> 24368.632 | K45: =[5]Salaire!$F$33 -> 23592.963 | N45: =[5]Salaire!$G$33 -> 25919.97 | Q45: =[5]Salaire!$H$33 -> 24368.632 | T45: =[5]Salaire!$I$33 -> 25144.301 | W45: =[5]Salaire!$J$33 -> 25144.301 | Z45: =[5]Salaire!$K$33 -> 25144.301 | AC45: =[5]Salaire!$L$33 -> 25144.301 | AF45: =[5]Salaire!$M$33 -> 25144.301 | AI45: =[5]Salaire!$N$33 -> 24368.632 | AL45: =[5]Salaire!$O$33 -> 25144.301 | AO45: =[5]Salaire!$P$33 -> 25919.97
A46: =+$C$4&B46 -> Véhicules neufsSalaires commis | B46: Salaires commis | E46: =+SUM(H46,K46,N46,Q46,T46,W46,Z46,AC46,AF46,AI46,AL46,AO46) -> 118984.69 | H46: =[5]Salaire!$E$77 -> 9573.4805 | K46: =[5]Salaire!$F$77 -> 9117.6005 | N46: =[5]Salaire!$G$77 -> 10485.241 | Q46: =[5]Salaire!$H$77 -> 9573.4805 | T46: =[5]Salaire!$I$77 -> 10029.361 | W46: =[5]Salaire!$J$77 -> 10029.361 | Z46: =[5]Salaire!$K$77 -> 10029.361 | AC46: =[5]Salaire!$L$77 -> 10029.361 | AF46: =[5]Salaire!$M$77 -> 10029.361 | AI46: =[5]Salaire!$N$77 -> 9573.4805 | AL46: =[5]Salaire!$O$77 -> 10029.361 | AO46: =[5]Salaire!$P$77 -> 10485.241
A47: =+$C$4&B47 -> Véhicules neufsSalaires autres | B47: Salaires autres | E47: =+SUM(H47,K47,N47,Q47,T47,W47,Z47,AC47,AF47,AI47,AL47,AO47) -> 74977.436 | H47: =[5]Salaire!$E$145 -> 6032.6672 | K47: =[5]Salaire!$F$145 -> 5745.3974 | N47: =[5]Salaire!$G$145 -> 6607.207 | Q47: =[5]Salaire!$H$145 -> 6032.6672 | T47: =[5]Salaire!$I$145 -> 6319.9371 | W47: =[5]Salaire!$J$145 -> 6319.9371 | Z47: =[5]Salaire!$K$145 -> 6319.9371 | AC47: =[5]Salaire!$L$145 -> 6319.9371 | AF47: =[5]Salaire!$M$145 -> 6319.9371 | AI47: =[5]Salaire!$N$145 -> 6032.6672 | AL47: =[5]Salaire!$O$145 -> 6319.9371 | AO47: =[5]Salaire!$P$145 -> 6607.207
A48: =+$C$4&B48 -> Véhicules neufsSalaires spécialistes | B48: Salaires spécialistes | E48: =+SUM(H48,K48,N48,Q48,T48,W48,Z48,AC48,AF48,AI48,AL48,AO48) -> 0
A49: =+$C$4&B49 -> Véhicules neufs[...] | B49: [...] | E49: =+SUM(H49,K49,N49,Q49,T49,W49,Z49,AC49,AF49,AI49,AL49,AO49) -> 0
A50: =+$C$4&B50 -> Véhicules neufs[...] | B50: [...] | E50: =+SUM(H50,K50,N50,Q50,T50,W50,Z50,AC50,AF50,AI50,AL50,AO50) -> 0
A51: =+$C$4&B51 -> Véhicules neufs[...] | B51: [...] | E51: =+SUM(H51,K51,N51,Q51,T51,W51,Z51,AC51,AF51,AI51,AL51,AO51) -> 0
A52: =+$C$4&B52 -> Véhicules neufsSalaires en absences | B52: Salaires en absences | E52: =+SUM(H52,K52,N52,Q52,T52,W52,Z52,AC52,AF52,AI52,AL52,AO52) -> 119516.13 | H52: ='[5]DAS-VAC'!$E$45 -> 9506.2607 | K52: ='[5]DAS-VAC'!$F$45 -> 8099.9815 | N52: ='[5]DAS-VAC'!$G$45 -> 10134.13 | Q52: ='[5]DAS-VAC'!$H$45 -> 10192.504 | T52: ='[5]DAS-VAC'!$I$45 -> 11769.124 | W52: ='[5]DAS-VAC'!$J$45 -> 10006.868 | Z52: ='[5]DAS-VAC'!$K$45 -> 10015.714 | AC52: ='[5]DAS-VAC'!$L$45 -> 10238.279 | AF52: ='[5]DAS-VAC'!$M$45 -> 10669.309 | AI52: ='[5]DAS-VAC'!$N$45 -> 11672.142 | AL52: ='[5]DAS-VAC'!$O$45 -> 9292.9168 | AO52: ='[5]DAS-VAC'!$P$45 -> 7918.9032
A53: =+$C$4&B53 -> Véhicules neufsDéduction à la source | B53: Déduction à la source | E53: =+SUM(H53,K53,N53,Q53,T53,W53,Z53,AC53,AF53,AI53,AL53,AO53) -> 119516.13 | H53: ='[5]DAS-VAC'!$E$53 -> 9506.2607 | K53: ='[5]DAS-VAC'!$F$53 -> 8099.9815 | N53: ='[5]DAS-VAC'!$G$53 -> 10134.13 | Q53: ='[5]DAS-VAC'!$H$53 -> 10192.504 | T53: ='[5]DAS-VAC'!$I$53 -> 11769.124 | W53: ='[5]DAS-VAC'!$J$53 -> 10006.868 | Z53: ='[5]DAS-VAC'!$K$53 -> 10015.714 | AC53: ='[5]DAS-VAC'!$L$53 -> 10238.279 | AF53: ='[5]DAS-VAC'!$M$53 -> 10669.309 | AI53: ='[5]DAS-VAC'!$N$53 -> 11672.142 | AL53: ='[5]DAS-VAC'!$O$53 -> 9292.9168 | AO53: ='[5]DAS-VAC'!$P$53 -> 7918.9032
A54: =+$C$4&B54 -> Véhicules neufsBénéfices marginaux | B54: Bénéfices marginaux | E54: =+SUM(H54,K54,N54,Q54,T54,W54,Z54,AC54,AF54,AI54,AL54,AO54) -> 85653.228 | H54: ='[5]DAS-VAC'!$E$61 -> 6812.8202 | K54: ='[5]DAS-VAC'!$F$61 -> 5804.9867 | N54: ='[5]DAS-VAC'!$G$61 -> 7262.7931 | Q54: ='[5]DAS-VAC'!$H$61 -> 7304.628 | T54: ='[5]DAS-VAC'!$I$61 -> 8434.5388 | W54: ='[5]DAS-VAC'!$J$61 -> 7171.5888 | Z54: ='[5]DAS-VAC'!$K$61 -> 7177.9281 | AC54: ='[5]DAS-VAC'!$L$61 -> 7337.4335 | AF54: ='[5]DAS-VAC'!$M$61 -> 7646.3381 | AI54: ='[5]DAS-VAC'!$N$61 -> 8365.035 | AL54: ='[5]DAS-VAC'!$O$61 -> 6659.9237 | AO54: ='[5]DAS-VAC'!$P$61 -> 5675.2139
A55: =+$C$4&B55 -> Véhicules neufsCsst | B55: Csst | E55: =+SUM(H55,K55,N55,Q55,T55,W55,Z55,AC55,AF55,AI55,AL55,AO55) -> 19919.355 | H55: ='[5]DAS-VAC'!$E$69 -> 1584.3768 | K55: ='[5]DAS-VAC'!$F$69 -> 1349.9969 | N55: ='[5]DAS-VAC'!$G$69 -> 1689.0217 | Q55: ='[5]DAS-VAC'!$H$69 -> 1698.7507 | T55: ='[5]DAS-VAC'!$I$69 -> 1961.5207 | W55: ='[5]DAS-VAC'!$J$69 -> 1667.8113 | Z55: ='[5]DAS-VAC'!$K$69 -> 1669.2856 | AC55: ='[5]DAS-VAC'!$L$69 -> 1706.3799 | AF55: ='[5]DAS-VAC'!$M$69 -> 1778.2182 | AI55: ='[5]DAS-VAC'!$N$69 -> 1945.357 | AL55: ='[5]DAS-VAC'!$O$69 -> 1548.8195 | AO55: ='[5]DAS-VAC'!$P$69 -> 1319.8172
A56: =+$C$4&B56 -> Véhicules neufs[...] | B56: [...] | E56: =+SUM(H56,K56,N56,Q56,T56,W56,Z56,AC56,AF56,AI56,AL56,AO56) -> 0
A57: =+$C$4&B57 -> Véhicules neufsTOTAL PERSONNEL | B57: TOTAL PERSONNEL | C57: % brut | D57: =IFERROR(E57/E$30,0) -> 0.46886612 | E57: =+SUM(E45:E56) -> 837971.57 | F57: % brut | G57: =IFERROR(H57/H$30,0) -> 0.48824978 | H57: =+SUM(H45:H56) -> 67384.498 | I57: % brut | J57: =IFERROR(K57/K$30,0) -> 0.63241259 | K57: =+SUM(K45:K56) -> 61810.907 | L57: % brut | M57: =IFERROR(N57/N$30,0) -> 0.49481709 | N57: =+SUM(N45:N56) -> 72232.492 | O57: % brut | P57: =IFERROR(Q57/Q$30,0) -> 0.43042064 | Q57: =+SUM(Q45:Q56) -> 69363.166 | R57: % brut | S57: =IFERROR(T57/T$30,0) -> 0.36081625 | T57: =+SUM(T45:T56) -> 75427.906 | U57: % brut | V57: =IFERROR(W57/W$30,0) -> 0.47288661 | W57: =+SUM(W45:W56) -> 70346.735 | X57: % brut | Y57: =IFERROR(Z57/Z$30,0) -> 0.47507544 | Z57: =+SUM(Z45:Z56) -> 70372.239 | AA57: % brut | AB57: =IFERROR(AC57/AC$30,0) -> 0.45360431 | AC57: =+SUM(AC45:AC56) -> 71013.97 | AD57: % brut | AE57: =IFERROR(AF57/AF$30,0) -> 0.42237328 | AF57: =+SUM(AF45:AF56) -> 72256.773 | AG57: % brut | AH57: =IFERROR(AI57/AI$30,0) -> 0.34897018 | AI57: =+SUM(AI45:AI56) -> 73629.455 | AJ57: % brut | AK57: =IFERROR(AL57/AL$30,0) -> 0.54756594 | AL57: =+SUM(AL45:AL56) -> 68288.175 | AM57: % brut | AN57: =IFERROR(AO57/AO$30,0) -> 0.87698621 | AO57: =+SUM(AO45:AO56) -> 65845.255
A58: =+$C$4&B58 -> Véhicules neufsPublicité 2 | B58: Publicité 2 | E58: =+SUM(H58,K58,N58,Q58,T58,W58,Z58,AC58,AF58,AI58,AL58,AO58) -> 0 | H58: =[5]DEPA!$E$102 -> 0 | K58: =[5]DEPA!$F$102 -> 0 | N58: =[5]DEPA!$G$102 -> 0 | Q58: =[5]DEPA!$H$102 -> 0 | T58: =[5]DEPA!$I$102 -> 0 | W58: =[5]DEPA!$J$102 -> 0 | Z58: =[5]DEPA!$K$102 -> 0 | AC58: =[5]DEPA!$L$102 -> 0 | AF58: =[5]DEPA!$M$102 -> 0 | AI58: =[5]DEPA!$N$102 -> 0 | AL58: =[5]DEPA!$O$102 -> 0 | AO58: =[5]DEPA!$P$102 -> 0
A59: =+$C$4&B59 -> Véhicules neufsService gratuit 2 | B59: Service gratuit 2 | E59: =+SUM(H59,K59,N59,Q59,T59,W59,Z59,AC59,AF59,AI59,AL59,AO59) -> 0 | H59: =[5]DEPA!$E$92 -> 0 | K59: =[5]DEPA!$F$92 -> 0 | N59: =[5]DEPA!$G$92 -> 0 | Q59: =[5]DEPA!$H$92 -> 0 | T59: =[5]DEPA!$I$92 -> 0 | W59: =[5]DEPA!$J$92 -> 0 | Z59: =[5]DEPA!$K$92 -> 0 | AC59: =[5]DEPA!$L$92 -> 0 | AF59: =[5]DEPA!$M$92 -> 0 | AI59: =[5]DEPA!$N$92 -> 0 | AL59: =[5]DEPA!$O$92 -> 0 | AO59: =[5]DEPA!$P$92 -> 0
A60: =+$C$4&B60 -> Véhicules neufsFrais véhicules de cie | B60: Frais véhicules de cie | E60: =+SUM(H60,K60,N60,Q60,T60,W60,Z60,AC60,AF60,AI60,AL60,AO60) -> 109066.53 | H60: =[5]DEPA!$E$115 -> 9088.8775 | K60: =[5]DEPA!$F$115 -> 9088.8775 | N60: =[5]DEPA!$G$115 -> 9088.8775 | Q60: =[5]DEPA!$H$115 -> 9088.8775 | T60: =[5]DEPA!$I$115 -> 9088.8775 | W60: =[5]DEPA!$J$115 -> 9088.8775 | Z60: =[5]DEPA!$K$115 -> 9088.8775 | AC60: =[5]DEPA!$L$115 -> 9088.8775 | AF60: =[5]DEPA!$M$115 -> 9088.8775 | AI60: =[5]DEPA!$N$115 -> 9088.8775 | AL60: =[5]DEPA!$O$115 -> 9088.8775 | AO60: =[5]DEPA!$P$115 -> 9088.8775
A61: =+$C$4&B61 -> Véhicules neufsInformatique | B61: Informatique | E61: =+SUM(H61,K61,N61,Q61,T61,W61,Z61,AC61,AF61,AI61,AL61,AO61) -> 80128.755 | H61: =[5]DEPA!$E$133 -> 6677.3963 | K61: =[5]DEPA!$F$133 -> 6677.3963 | N61: =[5]DEPA!$G$133 -> 6677.3963 | Q61: =[5]DEPA!$H$133 -> 6677.3963 | T61: =[5]DEPA!$I$133 -> 6677.3963 | W61: =[5]DEPA!$J$133 -> 6677.3963 | Z61: =[5]DEPA!$K$133 -> 6677.3963 | AC61: =[5]DEPA!$L$133 -> 6677.3963 | AF61: =[5]DEPA!$M$133 -> 6677.3963 | AI61: =[5]DEPA!$N$133 -> 6677.3963 | AL61: =[5]DEPA!$O$133 -> 6677.3963 | AO61: =[5]DEPA!$P$133 -> 6677.3963
A62: =+$C$4&B62 -> Véhicules neufsFrais de déplacement | B62: Frais de déplacement | E62: =+SUM(H62,K62,N62,Q62,T62,W62,Z62,AC62,AF62,AI62,AL62,AO62) -> 19157.962 | H62: =[5]DEPA!$E$150 -> 1596.4968 | K62: =[5]DEPA!$F$150 -> 1596.4968 | N62: =[5]DEPA!$G$150 -> 1596.4968 | Q62: =[5]DEPA!$H$150 -> 1596.4968 | T62: =[5]DEPA!$I$150 -> 1596.4968 | W62: =[5]DEPA!$J$150 -> 1596.4968 | Z62: =[5]DEPA!$K$150 -> 1596.4968 | AC62: =[5]DEPA!$L$150 -> 1596.4968 | AF62: =[5]DEPA!$M$150 -> 1596.4968 | AI62: =[5]DEPA!$N$150 -> 1596.4968 | AL62: =[5]DEPA!$O$150 -> 1596.4968 | AO62: =[5]DEPA!$P$150 -> 1596.4968
A63: =+$C$4&B63 -> Véhicules neufsServices extérieurs | B63: Services extérieurs | E63: =+SUM(H63,K63,N63,Q63,T63,W63,Z63,AC63,AF63,AI63,AL63,AO63) -> 114710.74 | H63: =[5]DEPA!$E$181 -> 9409.8947 | K63: =[5]DEPA!$F$181 -> 9409.8947 | N63: =[5]DEPA!$G$181 -> 9409.8947 | Q63: =[5]DEPA!$H$181 -> 9857.8947 | T63: =[5]DEPA!$I$181 -> 9857.8947 | W63: =[5]DEPA!$J$181 -> 9409.8947 | Z63: =[5]DEPA!$K$181 -> 9409.8947 | AC63: =[5]DEPA!$L$181 -> 9409.8947 | AF63: =[5]DEPA!$M$181 -> 9409.8947 | AI63: =[5]DEPA!$N$181 -> 9857.8947 | AL63: =[5]DEPA!$O$181 -> 9857.8947 | AO63: =[5]DEPA!$P$181 -> 9409.8947
A64: =+$C$4&B64 -> Véhicules neufsFournitures autres | B64: Fournitures autres | E64: =+SUM(H64,K64,N64,Q64,T64,W64,Z64,AC64,AF64,AI64,AL64,AO64) -> 3136 | H64: =[5]DEPA!$E$72 -> 244.32954 | K64: =[5]DEPA!$F$72 -> 168.21323 | N64: =[5]DEPA!$G$72 -> 255.71315 | Q64: =[5]DEPA!$H$72 -> 283.23627 | T64: =[5]DEPA!$I$72 -> 370.11227 | W64: =[5]DEPA!$J$72 -> 260.75944 | Z64: =[5]DEPA!$K$72 -> 259.61363 | AC64: =[5]DEPA!$L$72 -> 274.89771 | AF64: =[5]DEPA!$M$72 -> 301.23186 | AI64: =[5]DEPA!$N$72 -> 373.63604 | AL64: =[5]DEPA!$O$72 -> 217.13996 | AO64: =[5]DEPA!$P$72 -> 127.11689
A65: =+$C$4&B65 -> Véhicules neufsUniformes | B65: Uniformes | E65: =+SUM(H65,K65,N65,Q65,T65,W65,Z65,AC65,AF65,AI65,AL65,AO65) -> 420 | H65: =[5]DEPA!$E$81 -> 35 | K65: =[5]DEPA!$F$81 -> 35 | N65: =[5]DEPA!$G$81 -> 35 | Q65: =[5]DEPA!$H$81 -> 35 | T65: =[5]DEPA!$I$81 -> 35 | W65: =[5]DEPA!$J$81 -> 35 | Z65: =[5]DEPA!$K$81 -> 35 | AC65: =[5]DEPA!$L$81 -> 35 | AF65: =[5]DEPA!$M$81 -> 35 | AI65: =[5]DEPA!$N$81 -> 35 | AL65: =[5]DEPA!$O$81 -> 35 | AO65: =[5]DEPA!$P$81 -> 35
A66: =+$C$4&B66 -> Véhicules neufsPapeterie | B66: Papeterie | E66: =+SUM(H66,K66,N66,Q66,T66,W66,Z66,AC66,AF66,AI66,AL66,AO66) -> 8371.2 | H66: =[5]DEPA!$E$63 -> 697.6 | K66: =[5]DEPA!$F$63 -> 697.6 | N66: =[5]DEPA!$G$63 -> 697.6 | Q66: =[5]DEPA!$H$63 -> 697.6 | T66: =[5]DEPA!$I$63 -> 697.6 | W66: =[5]DEPA!$J$63 -> 697.6 | Z66: =[5]DEPA!$K$63 -> 697.6 | AC66: =[5]DEPA!$L$63 -> 697.6 | AF66: =[5]DEPA!$M$63 -> 697.6 | AI66: =[5]DEPA!$N$63 -> 697.6 | AL66: =[5]DEPA!$O$63 -> 697.6 | AO66: =[5]DEPA!$P$63 -> 697.6
A67: =+$C$4&B67 -> Véhicules neufsTéléphone | B67: Téléphone | E67: =+SUM(H67,K67,N67,Q67,T67,W67,Z67,AC67,AF67,AI67,AL67,AO67) -> 7078.944 | H67: =[5]DEPA!$E$160 -> 589.912 | K67: =[5]DEPA!$F$160 -> 589.912 | N67: =[5]DEPA!$G$160 -> 589.912 | Q67: =[5]DEPA!$H$160 -> 589.912 | T67: =[5]DEPA!$I$160 -> 589.912 | W67: =[5]DEPA!$J$160 -> 589.912 | Z67: =[5]DEPA!$K$160 -> 589.912 | AC67: =[5]DEPA!$L$160 -> 589.912 | AF67: =[5]DEPA!$M$160 -> 589.912 | AI67: =[5]DEPA!$N$160 -> 589.912 | AL67: =[5]DEPA!$O$160 -> 589.912 | AO67: =[5]DEPA!$P$160 -> 589.912
A68: =+$C$4&B68 -> Véhicules neufsFrais postaux | B68: Frais postaux | E68: =+SUM(H68,K68,N68,Q68,T68,W68,Z68,AC68,AF68,AI68,AL68,AO68) -> 3321.6 | H68: =[5]DEPA!$E$170 -> 276.8 | K68: =[5]DEPA!$F$170 -> 276.8 | N68: =[5]DEPA!$G$170 -> 276.8 | Q68: =[5]DEPA!$H$170 -> 276.8 | T68: =[5]DEPA!$I$170 -> 276.8 | W68: =[5]DEPA!$J$170 -> 276.8 | Z68: =[5]DEPA!$K$170 -> 276.8 | AC68: =[5]DEPA!$L$170 -> 276.8 | AF68: =[5]DEPA!$M$170 -> 276.8 | AI68: =[5]DEPA!$N$170 -> 276.8 | AL68: =[5]DEPA!$O$170 -> 276.8 | AO68: =[5]DEPA!$P$170 -> 276.8
A69: =+$C$4&B69 -> Véhicules neufsDivers | B69: Divers | E69: =+SUM(H69,K69,N69,Q69,T69,W69,Z69,AC69,AF69,AI69,AL69,AO69) -> 16189.44 | H69: =[5]DEPA!$E$213 -> 1349.12 | K69: =[5]DEPA!$F$213 -> 1349.12 | N69: =[5]DEPA!$G$213 -> 1349.12 | Q69: =[5]DEPA!$H$213 -> 1349.12 | T69: =[5]DEPA!$I$213 -> 1349.12 | W69: =[5]DEPA!$J$213 -> 1349.12 | Z69: =[5]DEPA!$K$213 -> 1349.12 | AC69: =[5]DEPA!$L$213 -> 1349.12 | AF69: =[5]DEPA!$M$213 -> 1349.12 | AI69: =[5]DEPA!$N$213 -> 1349.12 | AL69: =[5]DEPA!$O$213 -> 1349.12 | AO69: =[5]DEPA!$P$213 -> 1349.12
A70: =+$C$4&B70 -> Véhicules neufsFormation | B70: Formation | E70: =+SUM(H70,K70,N70,Q70,T70,W70,Z70,AC70,AF70,AI70,AL70,AO70) -> 17260.16 | H70: =[5]DEPA!$E$229 -> 1438.3467 | K70: =[5]DEPA!$F$229 -> 1438.3467 | N70: =[5]DEPA!$G$229 -> 1438.3467 | Q70: =[5]DEPA!$H$229 -> 1438.3467 | T70: =[5]DEPA!$I$229 -> 1438.3467 | W70: =[5]DEPA!$J$229 -> 1438.3467 | Z70: =[5]DEPA!$K$229 -> 1438.3467 | AC70: =[5]DEPA!$L$229 -> 1438.3467 | AF70: =[5]DEPA!$M$229 -> 1438.3467 | AI70: =[5]DEPA!$N$229 -> 1438.3467 | AL70: =[5]DEPA!$O$229 -> 1438.3467 | AO70: =[5]DEPA!$P$229 -> 1438.3467
A71: =+$C$4&B71 -> Véhicules neufsFrais bancaires | B71: Frais bancaires | E71: =+SUM(H71,K71,N71,Q71,T71,W71,Z71,AC71,AF71,AI71,AL71,AO71) -> 33942.4 | H71: =[5]DEPA!$E$240 -> 2087.6738 | K71: =[5]DEPA!$F$240 -> 1800.7474 | N71: =[5]DEPA!$G$240 -> 2083.3142 | Q71: =[5]DEPA!$H$240 -> 4004.986 | T71: =[5]DEPA!$I$240 -> 3670.6574 | W71: =[5]DEPA!$J$240 -> 2426.188 | Z71: =[5]DEPA!$K$240 -> 2287.378 | AC71: =[5]DEPA!$L$240 -> 2521.1801 | AF71: =[5]DEPA!$M$240 -> 1909.292 | AI71: =[5]DEPA!$N$240 -> 3579.0423 | AL71: =[5]DEPA!$O$240 -> 5208.1297 | AO71: =[5]DEPA!$P$240 -> 2363.8111
A72: =+$C$4&B72 -> Véhicules neufs[...] | B72: [...] | E72: =+SUM(H72,K72,N72,Q72,T72,W72,Z72,AC72,AF72,AI72,AL72,AO72) -> 0
A73: =+$C$4&B73 -> Véhicules neufs[...] | B73: [...] | E73: =+SUM(H73,K73,N73,Q73,T73,W73,Z73,AC73,AF73,AI73,AL73,AO73) -> 0
A74: =+$C$4&B74 -> Véhicules neufs[...] | B74: [...] | E74: =+SUM(H74,K74,N74,Q74,T74,W74,Z74,AC74,AF74,AI74,AL74,AO74) -> 0
A75: =+$C$4&B75 -> Véhicules neufsTOTAL SEMI-FIXES | B75: TOTAL SEMI-FIXES | C75: % brut | D75: =IFERROR(E75/E$30,0) -> 0.23096285 | E75: =+SUM(E58:E74) -> 412783.73 | F75: % brut | G75: =IFERROR(H75/H$30,0) -> 0.24266994 | H75: =+SUM(H58:H74) -> 33491.447 | I75: % brut | J75: =IFERROR(K75/K$30,0) -> 0.33895021 | K75: =+SUM(K58:K74) -> 33128.405 | L75: % brut | M75: =IFERROR(N75/N$30,0) -> 0.2294759 | N75: =+SUM(N58:N74) -> 33498.471 | O75: % brut | P75: =IFERROR(Q75/Q$30,0) -> 0.2227441 | Q75: =+SUM(Q58:Q74) -> 35895.666 | R75: % brut | S75: =IFERROR(T75/T$30,0) -> 0.17052647 | T75: =+SUM(T58:T74) -> 35648.214 | U75: % brut | V75: =IFERROR(W75/W$30,0) -> 0.22752307 | W75: =+SUM(W58:W74) -> 33846.391 | X75: % brut | Y75: =IFERROR(Z75/Z$30,0) -> 0.22754853 | Z75: =+SUM(Z58:Z74) -> 33706.435 | AA75: % brut | AB75: =IFERROR(AC75/AC$30,0) -> 0.21689213 | AC75: =+SUM(AC58:AC74) -> 33955.522 | AD75: % brut | AE75: =IFERROR(AF75/AF$30,0) -> 0.19506244 | AF75: =+SUM(AF58:AF74) -> 33369.968 | AG75: % brut | AH75: =IFERROR(AI75/AI$30,0) -> 0.16853883 | AI75: =+SUM(AI58:AI74) -> 35560.122 | AJ75: % brut | AK75: =IFERROR(AL75/AL$30,0) -> 0.2969453 | AL75: =+SUM(AL58:AL74) -> 37032.714 | AM75: % brut | AN75: =IFERROR(AO75/AO$30,0) -> 0.44818586 | AO75: =+SUM(AO58:AO74) -> 33650.372
A76: =+$C$4&B76 -> Véhicules neufs
A77: =+$C$4&B77 -> Véhicules neufsTOTAL DES DÉPENSES | B77: TOTAL DES DÉPENSES | C77: % brut | D77: =IFERROR(E77/E$30,0) -> 1.2627158 | E77: =E44+E57+E75 -> 2256763.5 | F77: % brut | G77: =IFERROR(H77/H$30,0) -> 1.3005913 | H77: =H44+H57+H75 -> 179497.66 | I77: % brut | J77: =IFERROR(K77/K$30,0) -> 1.5914577 | K77: =K44+K57+K75 -> 155546.31 | L77: % brut | M77: =IFERROR(N77/N$30,0) -> 1.292342 | N77: =N44+N57+N75 -> 188653.71 | O77: % brut | P77: =IFERROR(Q77/Q$30,0) -> 1.2122698 | Q77: =Q44+Q57+Q75 -> 195359.76 | R77: % brut | S77: =IFERROR(T77/T$30,0) -> 1.0605929 | T77: =T44+T57+T75 -> 221714.8 | U77: % brut | V77: =IFERROR(W77/W$30,0) -> 1.2636064 | W77: =W44+W57+W75 -> 187974.41 | X77: % brut | Y77: =IFERROR(Z77/Z$30,0) -> 1.2685633 | Z77: =Z44+Z57+Z75 -> 187910.45 | AA77: % brut | AB77: =IFERROR(AC77/AC$30,0) -> 1.229829 | AC77: =AC44+AC57+AC75 -> 192535.74 | AD77: % brut | AE77: =IFERROR(AF77/AF$30,0) -> 1.1703059 | AF77: =AF44+AF57+AF75 -> 200208.04 | AG77: % brut | AH77: =IFERROR(AI77/AI$30,0) -> 1.0457021 | AI77: =AI44+AI57+AI75 -> 220633.39 | AJ77: % brut | AK77: =IFERROR(AL77/AL$30,0) -> 1.4224493 | AL77: =AL44+AL57+AL75 -> 177396.84 | AM77: % brut | AN77: =IFERROR(AO77/AO$30,0) -> 1.988943 | AO77: =AO44+AO57+AO75 -> 149332.4
A78: =+$C$4&B78 -> Véhicules neufsProgramme neuf 1 | B78: Programme neuf 1 | E78: =+SUM(H78,K78,N78,Q78,T78,W78,Z78,AC78,AF78,AI78,AL78,AO78) -> 84157.371 | H78: ='[5]véh neufs'!$E$123 -> 19827.767 | K78: ='[5]véh neufs'!$F$123 -> 1201.2881 | N78: ='[5]véh neufs'!$G$123 -> 758.49607 | Q78: ='[5]véh neufs'!$H$123 -> 7158.52 | T78: ='[5]véh neufs'!$I$123 -> 9354.2259 | W78: ='[5]véh neufs'!$J$123 -> 6590.4401 | Z78: ='[5]véh neufs'!$K$123 -> 6561.4807 | AC78: ='[5]véh neufs'!$L$123 -> 6947.7711 | AF78: ='[5]véh neufs'!$M$123 -> 7613.3409 | AI78: ='[5]véh neufs'!$N$123 -> 9443.2859 | AL78: ='[5]véh neufs'!$O$123 -> 5488.0003 | AO78: ='[5]véh neufs'!$P$123 -> 3212.7553
A79: =+$C$4&B79 -> Véhicules neufsProgramme neuf 2 | B79: Programme neuf 2 | E79: =+SUM(H79,K79,N79,Q79,T79,W79,Z79,AC79,AF79,AI79,AL79,AO79) -> 0
A80: =+$C$4&B80 -> Véhicules neufsProgramme neuf 3 | B80: Programme neuf 3 | E80: =+SUM(H80,K80,N80,Q80,T80,W80,Z80,AC80,AF80,AI80,AL80,AO80) -> 0
A81: =+$C$4&B81 -> Véhicules neufsHoldbacks | B81: Holdbacks | E81: =+SUM(H81,K81,N81,Q81,T81,W81,Z81,AC81,AF81,AI81,AL81,AO81) -> 739261.69 | H81: ='[5]véh neufs'!$E$118 -> 36963.085 | K81: ='[5]véh neufs'!$F$118 -> 36963.085 | N81: ='[5]véh neufs'!$G$118 -> 73926.169 | Q81: ='[5]véh neufs'!$H$118 -> 73926.169 | T81: ='[5]véh neufs'!$I$118 -> 81318.786 | W81: ='[5]véh neufs'!$J$118 -> 59140.935 | Z81: ='[5]véh neufs'!$K$118 -> 51748.319 | AC81: ='[5]véh neufs'!$L$118 -> 73926.169 | AF81: ='[5]véh neufs'!$M$118 -> 73926.169 | AI81: ='[5]véh neufs'!$N$118 -> 81318.786 | AL81: ='[5]véh neufs'!$O$118 -> 73926.169 | AO81: ='[5]véh neufs'!$P$118 -> 22177.851
A82: =+$C$4&B82 -> Véhicules neufs[...] | B82: [...] | E82: =+SUM(H82,K82,N82,Q82,T82,W82,Z82,AC82,AF82,AI82,AL82,AO82) -> 0
A83: =+$C$4&B83 -> Véhicules neufs[...] | B83: [...] | E83: =+SUM(H83,K83,N83,Q83,T83,W83,Z83,AC83,AF83,AI83,AL83,AO83) -> 0
A84: =+$C$4&B84 -> Véhicules neufs[...] | B84: [...] | E84: =+SUM(H84,K84,N84,Q84,T84,W84,Z84,AC84,AF84,AI84,AL84,AO84) -> 0
A85: =+$C$4&B85 -> Véhicules neufsFrais administration | B85: Frais administration | E85: =+SUM(H85,K85,N85,Q85,T85,W85,Z85,AC85,AF85,AI85,AL85,AO85) -> 246254.4 | H85: ='[5]véh neufs'!$E$134 -> 19185.977 | K85: ='[5]véh neufs'!$F$134 -> 13208.944 | N85: ='[5]véh neufs'!$G$134 -> 20079.875 | Q85: ='[5]véh neufs'!$H$134 -> 22241.128 | T85: ='[5]véh neufs'!$I$134 -> 29063.066 | W85: ='[5]véh neufs'!$J$134 -> 20476.135 | Z85: ='[5]véh neufs'!$K$134 -> 20386.16 | AC85: ='[5]véh neufs'!$L$134 -> 21586.343 | AF85: ='[5]véh neufs'!$M$134 -> 23654.232 | AI85: ='[5]véh neufs'!$N$134 -> 29339.77 | AL85: ='[5]véh neufs'!$O$134 -> 17050.915 | AO85: ='[5]véh neufs'!$P$134 -> 9981.8541
A86: =+$C$4&B86 -> Véhicules neufsAUTRES REVENUS | B86: AUTRES REVENUS | E86: =+SUM(E78:E85) -> 1069673.5 | H86: =+SUM(H78:H85) -> 75976.829 | K86: =+SUM(K78:K85) -> 51373.317 | N86: =+SUM(N78:N85) -> 94764.54 | Q86: =+SUM(Q78:Q85) -> 103325.82 | T86: =+SUM(T78:T85) -> 119736.08 | W86: =+SUM(W78:W85) -> 86207.511 | Z86: =+SUM(Z78:Z85) -> 78695.959 | AC86: =+SUM(AC78:AC85) -> 102460.28 | AF86: =+SUM(AF78:AF85) -> 105193.74 | AI86: =+SUM(AI78:AI85) -> 120101.84 | AL86: =+SUM(AL78:AL85) -> 96465.085 | AO86: =+SUM(AO78:AO85) -> 35372.46
A87: =+$C$4&B87 -> Véhicules neufs
A88: =+$C$4&B88 -> Véhicules neufsPROFIT DÉPARTEMENTAL | B88: PROFIT DÉPARTEMENTAL | E88: =E30-E77+E86 -> 600139.9 | H88: =H30-H77+H86 -> 34491.518 | K88: =K30-K77+K86 -> -6434.7355 | N88: =N30-N77+N86 -> 52088.994 | Q88: =Q30-Q77+Q86 -> 69118.1 | T88: =T30-T77+T86 -> 107069.25 | W88: =W30-W77+W86 -> 46993.361 | Z88: =Z30-Z77+Z86 -> 38914.064 | AC88: =AC30-AC77+AC86 -> 66479.425 | AF88: =AF30-AF77+AF86 -> 76058.961 | AI88: =AI30-AI77+AI86 -> 110459.13 | AL88: =AL30-AL77+AL86 -> 43780.484 | AO88: =AO30-AO77+AO86 -> -38878.656
B92: =B4 -> Budget 2021 | C92: Véhicules usagés
B94: Mois | C94: 2021 | F94: Janvier | I94: Février | L94: Mars | O94: Avril | R94: Mai | U94: Juin | X94: Juillet | AA94: Août | AD94: Septembre | AG94: Octobre | AJ94: Novembre | AM94: Décembre
C95: UNITE | D95: $P/UNITE | E95: $PROFITS | F95: UNITE | G95: $P/UNITE | H95: $PROFITS | I95: UNITE | J95: $P/UNITE | K95: $PROFITS | L95: UNITE | M95: $P/UNITE | N95: $PROFITS | O95: UNITE | P95: $P/UNITE | Q95: $PROFITS | R95: UNITE | S95: $P/UNITE | T95: $PROFITS | U95: UNITE | V95: $P/UNITE | W95: $PROFITS | X95: UNITE | Y95: $P/UNITE | Z95: $PROFITS | AA95: UNITE | AB95: $P/UNITE | AC95: $PROFITS | AD95: UNITE | AE95: $P/UNITE | AF95: $PROFITS | AG95: UNITE | AH95: $P/UNITE | AI95: $PROFITS | AJ95: UNITE | AK95: $P/UNITE | AL95: $PROFITS | AM95: UNITE | AN95: $P/UNITE | AO95: $PROFITS
A96: =+$C$92&B96 -> Véhicules usagésVentes nettes | B96: Ventes nettes | E96: =+SUM(H96,K96,N96,Q96,T96,W96,Z96,AC96,AF96,AI96,AL96,AO96) -> 11978226 | H96: ='[5]véh usagés'!$E$68 -> 641081.33 | K96: ='[5]véh usagés'!$F$68 -> 810373.52 | N96: ='[5]véh usagés'!$G$68 -> 758716.19 | Q96: ='[5]véh usagés'!$H$68 -> 994929.55 | T96: ='[5]véh usagés'!$I$68 -> 1240477.2 | W96: ='[5]véh usagés'!$J$68 -> 1127433 | Z96: ='[5]véh usagés'!$K$68 -> 1147134.4 | AC96: ='[5]véh usagés'!$L$68 -> 1181462.1 | AF96: ='[5]véh usagés'!$M$68 -> 952211.2 | AI96: ='[5]véh usagés'!$N$68 -> 1285172.1 | AL96: ='[5]véh usagés'!$O$68 -> 1165165.4 | AO96: ='[5]véh usagés'!$P$68 -> 674070.1
A97: =+$C$92&B97 -> Véhicules usagésCertifié | B97: Certifié | C97: =+SUM(F97,I97,L97,O97,R97,U97,X97,AA97,AD97,AG97,AJ97,AM97) -> 359.4964 | D97: =IF(C97=0,0,E97/C97) -> 750 | E97: =+SUM(H97,K97,N97,Q97,T97,W97,Z97,AC97,AF97,AI97,AL97,AO97) -> 269622.3 | F97: ='[5]véh usagés'!$E$4 -> 19.240448 | G97: =IF(F97=0,0,H97/F97) -> 750 | H97: ='[5]véh usagés'!$E$6 -> 14430.336 | I97: ='[5]véh usagés'!$F$4 -> 24.321328 | J97: =IF(I97=0,0,K97/I97) -> 750 | K97: ='[5]véh usagés'!$F$6 -> 18240.996 | L97: ='[5]véh usagés'!$G$4 -> 22.770963 | M97: =IF(L97=0,0,N97/L97) -> 750 | N97: ='[5]véh usagés'!$G$6 -> 17078.222 | O97: ='[5]véh usagés'!$H$4 -> 29.860315 | P97: =IF(O97=0,0,Q97/O97) -> 750 | Q97: ='[5]véh usagés'!$H$6 -> 22395.236 | R97: ='[5]véh usagés'!$I$4 -> 37.229811 | S97: =IF(R97=0,0,T97/R97) -> 750 | T97: ='[5]véh usagés'!$I$6 -> 27922.358 | U97: ='[5]véh usagés'!$J$4 -> 33.837072 | V97: =IF(U97=0,0,W97/U97) -> 750 | W97: ='[5]véh usagés'!$J$6 -> 25377.804 | X97: ='[5]véh usagés'!$K$4 -> 34.428361 | Y97: =IF(X97=0,0,Z97/X97) -> 750 | Z97: ='[5]véh usagés'!$K$6 -> 25821.271 | AA97: ='[5]véh usagés'!$L$4 -> 35.458621 | AB97: =IF(AA97=0,0,AC97/AA97) -> 750 | AC97: ='[5]véh usagés'!$L$6 -> 26593.966 | AD97: ='[5]véh usagés'!$M$4 -> 28.57823 | AE97: =IF(AD97=0,0,AF97/AD97) -> 750 | AF97: ='[5]véh usagés'!$M$6 -> 21433.673 | AG97: ='[5]véh usagés'!$N$4 -> 38.571215 | AH97: =IF(AG97=0,0,AI97/AG97) -> 750 | AI97: ='[5]véh usagés'!$N$6 -> 28928.412 | AJ97: ='[5]véh usagés'!$O$4 -> 34.969516 | AK97: =IF(AJ97=0,0,AL97/AJ97) -> 750 | AL97: ='[5]véh usagés'!$O$6 -> 26227.137 | AM97: ='[5]véh usagés'!$P$4 -> 20.230523 | AN97: =IF(AM97=0,0,AO97/AM97) -> 750 | AO97: ='[5]véh usagés'!$P$6 -> 15172.892
A98: =+$C$92&B98 -> Véhicules usagésNon Certifié | B98: Non Certifié | C98: =+SUM(F98,I98,L98,O98,R98,U98,X98,AA98,AD98,AG98,AJ98,AM98) -> 20.503597 | D98: =IF(C98=0,0,E98/C98) -> 750 | E98: =+SUM(H98,K98,N98,Q98,T98,W98,Z98,AC98,AF98,AI98,AL98,AO98) -> 15377.698 | F98: ='[5]véh usagés'!$E$20 -> 1.0973639 | G98: =IF(F98=0,0,H98/F98) -> 750 | H98: ='[5]véh usagés'!$E$22 -> 823.02295 | I98: ='[5]véh usagés'!$F$20 -> 1.387148 | J98: =IF(I98=0,0,K98/I98) -> 750 | K98: ='[5]véh usagés'!$F$22 -> 1040.361 | L98: ='[5]véh usagés'!$G$20 -> 1.2987241 | M98: =IF(L98=0,0,N98/L98) -> 750 | N98: ='[5]véh usagés'!$G$22 -> 974.0431 | O98: ='[5]véh usagés'!$H$20 -> 1.7030598 | P98: =IF(O98=0,0,Q98/O98) -> 750 | Q98: ='[5]véh usagés'!$H$22 -> 1277.2948 | R98: ='[5]véh usagés'!$I$20 -> 2.1233732 | S98: =IF(R98=0,0,T98/R98) -> 750 | T98: ='[5]véh usagés'!$I$22 -> 1592.5299 | U98: ='[5]véh usagés'!$J$20 -> 1.929871 | V98: =IF(U98=0,0,W98/U98) -> 750 | W98: ='[5]véh usagés'!$J$22 -> 1447.4033 | X98: ='[5]véh usagés'!$K$20 -> 1.9635948 | Y98: =IF(X98=0,0,Z98/X98) -> 750 | Z98: ='[5]véh usagés'!$K$22 -> 1472.6961 | AA98: ='[5]véh usagés'!$L$20 -> 2.0223548 | AB98: =IF(AA98=0,0,AC98/AA98) -> 750 | AC98: ='[5]véh usagés'!$L$22 -> 1516.7661 | AD98: ='[5]véh usagés'!$M$20 -> 1.6299371 | AE98: =IF(AD98=0,0,AF98/AD98) -> 750 | AF98: ='[5]véh usagés'!$M$22 -> 1222.4528 | AG98: ='[5]véh usagés'!$N$20 -> 2.1998792 | AH98: =IF(AG98=0,0,AI98/AG98) -> 750 | AI98: ='[5]véh usagés'!$N$22 -> 1649.9094 | AJ98: ='[5]véh usagés'!$O$20 -> 1.9944591 | AK98: =IF(AJ98=0,0,AL98/AJ98) -> 750 | AL98: ='[5]véh usagés'!$O$22 -> 1495.8443 | AM98: ='[5]véh usagés'!$P$20 -> 1.1538321 | AN98: =IF(AM98=0,0,AO98/AM98) -> 750 | AO98: ='[5]véh usagés'!$P$22 -> 865.37408
A99: =+$C$92&B99 -> Véhicules usagésTotal Usagés | B99: Total Usagés | C99: =+C97+C98 -> 380 | D99: =IF(C99<=0,0,E99/C99) -> 750 | E99: =+E97+E98 -> 285000 | F99: =+F97+F98 -> 20.337812 | G99: =IF(F99<=0,0,H99/F99) -> 750 | H99: =+H97+H98 -> 15253.359 | I99: =+I97+I98 -> 25.708476 | J99: =IF(I99<=0,0,K99/I99) -> 750 | K99: =+K97+K98 -> 19281.357 | L99: =+L97+L98 -> 24.069687 | M99: =IF(L99<=0,0,N99/L99) -> 750 | N99: =+N97+N98 -> 18052.265 | O99: =+O97+O98 -> 31.563374 | P99: =IF(O99<=0,0,Q99/O99) -> 750 | Q99: =+Q97+Q98 -> 23672.531 | R99: =+R97+R98 -> 39.353184 | S99: =IF(R99<=0,0,T99/R99) -> 750 | T99: =+T97+T98 -> 29514.888 | U99: =+U97+U98 -> 35.766943 | V99: =IF(U99<=0,0,W99/U99) -> 750 | W99: =+W97+W98 -> 26825.207 | X99: =+X97+X98 -> 36.391956 | Y99: =IF(X99<=0,0,Z99/X99) -> 750 | Z99: =+Z97+Z98 -> 27293.967 | AA99: =+AA97+AA98 -> 37.480976 | AB99: =IF(AA99<=0,0,AC99/AA99) -> 750 | AC99: =+AC97+AC98 -> 28110.732 | AD99: =+AD97+AD98 -> 30.208167 | AE99: =IF(AD99<=0,0,AF99/AD99) -> 750 | AF99: =+AF97+AF98 -> 22656.126 | AG99: =+AG97+AG98 -> 40.771095 | AH99: =IF(AG99<=0,0,AI99/AG99) -> 750 | AI99: =+AI97+AI98 -> 30578.321 | AJ99: =+AJ97+AJ98 -> 36.963975 | AK99: =IF(AJ99<=0,0,AL99/AJ99) -> 750 | AL99: =+AL97+AL98 -> 27722.981 | AM99: =+AM97+AM98 -> 21.384355 | AN99: =IF(AM99<=0,0,AO99/AM99) -> 750 | AO99: =+AO97+AO98 -> 16038.266
A100: =+$C$92&B100 -> Véhicules usagés
A101: =+$C$92&B101 -> Véhicules usagés
A102: =+$C$92&B102 -> Véhicules usagésVentes au Gros | B102: Ventes au Gros | C102: =+SUM(F102,I102,L102,O102,R102,U102,X102,AA102,AD102,AG102,AJ102,AM102) -> 322 | D102: =IF(C102=0,0,E102/C102) -> 120 | E102: =+SUM(H102,K102,N102,Q102,T102,W102,Z102,AC102,AF102,AI102,AL102,AO102) -> 38640 | F102: ='[5]véh usagés'!$E$35 -> 17.233619 | G102: =IF(F102=0,0,H102/F102) -> 120 | H102: ='[5]véh usagés'!$E$37 -> 2068.0343 | I102: ='[5]véh usagés'!$F$35 -> 21.784551 | J102: =IF(I102=0,0,K102/I102) -> 120 | K102: ='[5]véh usagés'!$F$37 -> 2614.1461 | L102: ='[5]véh usagés'!$G$35 -> 20.395893 | M102: =IF(L102=0,0,N102/L102) -> 120 | N102: ='[5]véh usagés'!$G$37 -> 2447.5071 | O102: ='[5]véh usagés'!$H$35 -> 26.745807 | P102: =IF(O102=0,0,Q102/O102) -> 120 | Q102: ='[5]véh usagés'!$H$37 -> 3209.4968 | R102: ='[5]véh usagés'!$I$35 -> 33.346646 | S102: =IF(R102=0,0,T102/R102) -> 120 | T102: ='[5]véh usagés'!$I$37 -> 4001.5975 | U102: ='[5]véh usagés'!$J$35 -> 30.307778 | V102: =IF(U102=0,0,W102/U102) -> 120 | W102: ='[5]véh usagés'!$J$37 -> 3636.9333 | X102: ='[5]véh usagés'!$K$35 -> 30.837394 | Y102: =IF(X102=0,0,Z102/X102) -> 120 | Z102: ='[5]véh usagés'!$K$37 -> 3700.4873 | AA102: ='[5]véh usagés'!$L$35 -> 31.760195 | AB102: =IF(AA102=0,0,AC102/AA102) -> 120 | AC102: ='[5]véh usagés'!$L$37 -> 3811.2235 | AD102: ='[5]véh usagés'!$M$35 -> 25.597447 | AE102: =IF(AD102=0,0,AF102/AD102) -> 120 | AF102: ='[5]véh usagés'!$M$37 -> 3071.6937 | AG102: ='[5]véh usagés'!$N$35 -> 34.548138 | AH102: =IF(AG102=0,0,AI102/AG102) -> 120 | AI102: ='[5]véh usagés'!$N$37 -> 4145.7766 | AJ102: ='[5]véh usagés'!$O$35 -> 31.322105 | AK102: =IF(AJ102=0,0,AL102/AJ102) -> 120 | AL102: ='[5]véh usagés'!$O$37 -> 3758.6526 | AM102: ='[5]véh usagés'!$P$35 -> 18.120427 | AN102: =IF(AM102=0,0,AO102/AM102) -> 120 | AO102: ='[5]véh usagés'!$P$37 -> 2174.4513
A103: =+$C$92&B103 -> Véhicules usagés
A104: =+$C$92&B104 -> Véhicules usagésRev. Finances | B104: Rev. Finances | D104: =IF(C99=0,0,E104/C99) -> 804.09357 | E104: =+SUM(H104,K104,N104,Q104,T104,W104,Z104,AC104,AF104,AI104,AL104,AO104) -> 305555.56 | G104: =IF(F99=0,0,H104/F99) -> 804.09357 | H104: ='[5]véh usagés'!$E$136 -> 16353.504 | J104: =IF(I99=0,0,K104/I99) -> 804.09357 | K104: ='[5]véh usagés'!$F$136 -> 20672.02 | M104: =IF(L99=0,0,N104/L99) -> 804.09357 | N104: ='[5]véh usagés'!$G$136 -> 19354.281 | P104: =IF(O99=0,0,Q104/O99) -> 804.09357 | Q104: ='[5]véh usagés'!$H$136 -> 25379.906 | S104: =IF(R99=0,0,T104/R99) -> 804.09357 | T104: ='[5]véh usagés'!$I$136 -> 31643.642 | V104: =IF(U99=0,0,W104/U99) -> 804.09357 | W104: ='[5]véh usagés'!$J$136 -> 28759.969 | Y104: =IF(X99=0,0,Z104/X99) -> 804.09357 | Z104: ='[5]véh usagés'!$K$136 -> 29262.538 | AB104: =IF(AA99=0,0,AC104/AA99) -> 804.09357 | AC104: ='[5]véh usagés'!$L$136 -> 30138.212 | AE104: =IF(AD99=0,0,AF104/AD99) -> 804.09357 | AF104: ='[5]véh usagés'!$M$136 -> 24290.193 | AH104: =IF(AG99=0,0,AI104/AG99) -> 804.09357 | AI104: ='[5]véh usagés'!$N$136 -> 32783.775 | AK104: =IF(AJ99=0,0,AL104/AJ99) -> 804.09357 | AL104: ='[5]véh usagés'!$O$136 -> 29722.494 | AN104: =IF(AM99=0,0,AO104/AM99) -> 804.09357 | AO104: ='[5]véh usagés'!$P$136 -> 17195.022
A105: =+$C$92&B105 -> Véhicules usagésRev. Protections | B105: Rev. Protections | D105: =IF(C99=0,0,E105/C99) -> 911.30604 | E105: =+SUM(H105,K105,N105,Q105,T105,W105,Z105,AC105,AF105,AI105,AL105,AO105) -> 346296.3 | G105: =IF(F99=0,0,H105/F99) -> 911.30604 | H105: ='[5]véh usagés'!$E$137 -> 18533.971 | J105: =IF(I99=0,0,K105/I99) -> 911.30604 | K105: ='[5]véh usagés'!$F$137 -> 23428.29 | M105: =IF(L99=0,0,N105/L99) -> 911.30604 | N105: ='[5]véh usagés'!$G$137 -> 21934.851 | P105: =IF(O99=0,0,Q105/O99) -> 911.30604 | Q105: ='[5]véh usagés'!$H$137 -> 28763.894 | S105: =IF(R99=0,0,T105/R99) -> 911.30604 | T105: ='[5]véh usagés'!$I$137 -> 35862.795 | V105: =IF(U99=0,0,W105/U99) -> 911.30604 | W105: ='[5]véh usagés'!$J$137 -> 32594.631 | Y105: =IF(X99=0,0,Z105/X99) -> 911.30604 | Z105: ='[5]véh usagés'!$K$137 -> 33164.209 | AB105: =IF(AA99=0,0,AC105/AA99) -> 911.30604 | AC105: ='[5]véh usagés'!$L$137 -> 34156.64 | AE105: =IF(AD99=0,0,AF105/AD99) -> 911.30604 | AF105: ='[5]véh usagés'!$M$137 -> 27528.886 | AH105: =IF(AG99=0,0,AI105/AG99) -> 911.30604 | AI105: ='[5]véh usagés'!$N$137 -> 37154.945 | AK105: =IF(AJ99=0,0,AL105/AJ99) -> 911.30604 | AL105: ='[5]véh usagés'!$O$137 -> 33685.494 | AN105: =IF(AM99=0,0,AO105/AM99) -> 911.30604 | AO105: ='[5]véh usagés'!$P$137 -> 19487.692
...

Sheet Print_Mois
C1: =Parametres!B1 -> Volks | K1: Véhicules neufs | S1: =CONCATENATE("Réalisé,"," ",Parametres!B3," ",Parametres!B4) -> Réalisé, Mars 2021
D2: X | E2: O | F2: U | G2: X | H2: O | I2: U | J2: NB | L2: $ | O2: NB | Q2: $
D3: BUDGET ORIGINAL | G3: BUDGET REVISE | J3: RÉALISATION | M3: ÉCART réel / révisé | O3: ANNÉE PRÉCÉDENTE | R3: ÉCART réel / original | V3: NEUF | W3: 0.45
D4: UNITE | E4: $P/UNITÉ | F4: $PROFITS | G4: UNITE | H4: $P/UNITÉ | I4: $PROFITS | J4: UNITE | K4: $P/UNITE | L4: $PROFITS | M4: UNITÉ | N4: $PROFITS | O4: UNITE | P4: $P/UNITE | Q4: $PROFITS | R4: UNITE | S4: $PROFITS | V4: USAGE | W4: 0.1
A5: =+B5&C5 -> Véhicules neufsVentes nettes | B5: =+$K$1 -> Véhicules neufs | C5: Ventes nettes | F5: =+INDEX('Budget original'!$A$2:$AO$496,MATCH($A5,'Budget original'!$A$2:$A$496,0),MATCH(F$2,'Budget original'!$A$2:$AO$2,0)) -> 678330.08 | I5: =+INDEX('Budget révisé'!$A$2:$AO$496,MATCH($A5,'Budget révisé'!$A$2:$A$496,0),MATCH(I$2,'Budget révisé'!$A$2:$AO$2,0)) -> 678330.08 | L5: =-SUMIFS(BV_Data_An_Cour!$O:$O,BV_Data_An_Cour!$X:$X,"Oui",BV_Data_An_Cour!$U:$U,$B5) -> 3240605.2 | Q5: =-SUMIFS(BV_Data_An_Prec!$O:$O,BV_Data_An_Prec!$X:$X,"Oui",BV_Data_An_Prec!$U:$U,$B5) -> 2855919.9 | V5: SERVICE | W5: 0.225
A6: =+B6&C6 -> Véhicules neufsAutos détail | B6: =+$K$1 -> Véhicules neufs | C6: Autos détail | D6: =+INDEX('Budget original'!$A$2:$AO$496,MATCH($A6,'Budget original'!$A$2:$A$496,0),MATCH(D$2,'Budget original'!$A$2:$AO$2,0)) -> 24.706978 | E6: =IF(D6=0,0,F6/D6) -> 604.29043 | F6: =+INDEX('Budget original'!$A$2:$AO$496,MATCH($A6,'Budget original'!$A$2:$A$496,0),MATCH(F$2,'Budget original'!$A$2:$AO$2,0)) -> 14930.19 | G6: =+INDEX('Budget révisé'!$A$2:$AO$496,MATCH($A6,'Budget révisé'!$A$2:$A$496,0),MATCH(G$2,'Budget révisé'!$A$2:$AO$2,0)) -> 24.706978 | H6: =IF(G6=0,0,I6/G6) -> 955.05622 | I6: =+INDEX('Budget révisé'!$A$2:$AO$496,MATCH($A6,'Budget révisé'!$A$2:$A$496,0),MATCH(I$2,'Budget révisé'!$A$2:$AO$2,0)) -> 23596.553 | J6: =-SUMIFS(BV_Data_An_Cour!$O:$O,BV_Data_An_Cour!$U:$U,$B6,BV_Data_An_Cour!$V:$V,$C6,BV_Data_An_Cour!$W:$W,J$2) -> 32 | K6: =IF(J6=0,0,L6/J6) -> 1097.7472 | L6: =-SUMIFS(BV_Data_An_Cour!$O:$O,BV_Data_An_Cour!$U:$U,$B6,BV_Data_An_Cour!$V:$V,$C6,BV_Data_An_Cour!$W:$W,L$2) -> 35127.91 | M6: =J6-G6 -> 7.293022 | N6: =L6-I6 -> 11531.357 | O6: =-SUMIFS(BV_Data_An_Prec!$O:$O,BV_Data_An_Prec!$U:$U,$B6,BV_Data_An_Prec!$V:$V,$C6,BV_Data_An_Prec!$W:$W,O$2)-3 -> 41 | P6: =IF(O6=0,0,Q6/O6) -> 492.62537 | Q6: =-SUMIFS(BV_Data_An_Prec!$O:$O,BV_Data_An_Prec!$U:$U,$B6,BV_Data_An_Prec!$V:$V,$C6,BV_Data_An_Prec!$W:$W,Q$2) -> 20197.64 | R6: =J6-O6 -> -9 | S6: =L6-Q6 -> 14930.27 | V6: CARROSSERIE | W6: 0.025
A7: =+B7&C7 -> Véhicules neufsCamions détail | B7: =+$K$1 -> Véhicules neufs | C7: Camions détail | D7: =+INDEX('Budget original'!$A$2:$AO$496,MATCH($A7,'Budget original'!$A$2:$A$496,0),MATCH(D$2,'Budget original'!$A$2:$AO$2,0)) -> 33.187261 | E7: =IF(D7=0,0,F7/D7) -> 1315.4791 | F7: =+INDEX('Budget original'!$A$2:$AO$496,MATCH($A7,'Budget original'!$A$2:$A$496,0),MATCH(F$2,'Budget original'!$A$2:$AO$2,0)) -> 43657.149 | G7: =+INDEX('Budget révisé'!$A$2:$AO$496,MATCH($A7,'Budget révisé'!$A$2:$A$496,0),MATCH(G$2,'Budget révisé'!$A$2:$AO$2,0)) -> 33.187261 | H7: =IF(G7=0,0,I7/G7) -> 1702.6669 | I7: =+INDEX('Budget révisé'!$A$2:$AO$496,MATCH($A7,'Budget révisé'!$A$2:$A$496,0),MATCH(I$2,'Budget révisé'!$A$2:$AO$2,0)) -> 56506.85 | J7: =-SUMIFS(BV_Data_An_Cour!$O:$O,BV_Data_An_Cour!$U:$U,$B7,BV_Data_An_Cour!$V:$V,$C7,BV_Data_An_Cour!$W:$W,J$2) -> 37 | K7: =IF(J7=0,0,L7/J7) -> 2171.0773 | L7: =-SUMIFS(BV_Data_An_Cour!$O:$O,BV_Data_An_Cour!$U:$U,$B7,BV_Data_An_Cour!$V:$V,$C7,BV_Data_An_Cour!$W:$W,L$2) -> 80329.86 | M7: =J7-G7 -> 3.8127391 | N7: =L7-I7 -> 23823.01 | O7: =-SUMIFS(BV_Data_An_Prec!$O:$O,BV_Data_An_Prec!$U:$U,$B7,BV_Data_An_Prec!$V:$V,$C7,BV_Data_An_Prec!$W:$W,O$2) -> 34 | P7: =IF(O7=0,0,Q7/O7) -> 622.44559 | Q7: =-SUMIFS(BV_Data_An_Prec!$O:$O,BV_Data_An_Prec!$U:$U,$B7,BV_Data_An_Prec!$V:$V,$C7,BV_Data_An_Prec!$W:$W,Q$2) -> 21163.15 | R7: =J7-O7 -> 3 | S7: =L7-Q7 -> 59166.71 | V7: PIECES | W7: 0.2
A8: =+B8&C8 -> Véhicules neufsSprinter | B8: =+$K$1 -> Véhicules neufs | C8: Sprinter | D8: =+INDEX('Budget original'!$A$2:$AO$496,MATCH($A8,'Budget original'!$A$2:$A$496,0),MATCH(D$2,'Budget original'!$A$2:$AO$2,0)) -> 0 | E8: =IF(D8=0,0,F8/D8) -> 0 | F8: =+INDEX('Budget original'!$A$2:$AO$496,MATCH($A8,'Budget original'!$A$2:$A$496,0),MATCH(F$2,'Budget original'!$A$2:$AO$2,0)) -> 0 | G8: =+INDEX('Budget révisé'!$A$2:$AO$496,MATCH($A8,'Budget révisé'!$A$2:$A$496,0),MATCH(G$2,'Budget révisé'!$A$2:$AO$2,0)) -> 0 | H8: =IF(G8=0,0,I8/G8) -> 0 | I8: =+INDEX('Budget révisé'!$A$2:$AO$496,MATCH($A8,'Budget révisé'!$A$2:$A$496,0),MATCH(I$2,'Budget révisé'!$A$2:$AO$2,0)) -> 0 | J8: =-SUMIFS(BV_Data_An_Cour!$O:$O,BV_Data_An_Cour!$U:$U,$B8,BV_Data_An_Cour!$V:$V,$C8,BV_Data_An_Cour!$W:$W,J$2) -> 0 | K8: =IF(J8=0,0,L8/J8) -> 0 | L8: =-SUMIFS(BV_Data_An_Cour!$O:$O,BV_Data_An_Cour!$U:$U,$B8,BV_Data_An_Cour!$V:$V,$C8,BV_Data_An_Cour!$W:$W,L$2) -> 0 | M8: =J8-G8 -> 0 | N8: =L8-I8 -> 0 | O8: =-SUMIFS(BV_Data_An_Prec!$O:$O,BV_Data_An_Prec!$U:$U,$B8,BV_Data_An_Prec!$V:$V,$C8,BV_Data_An_Prec!$W:$W,O$2) -> 0 | P8: =IF(O8=0,0,Q8/O8) -> 0 | Q8: =-SUMIFS(BV_Data_An_Prec!$O:$O,BV_Data_An_Prec!$U:$U,$B8,BV_Data_An_Prec!$V:$V,$C8,BV_Data_An_Prec!$W:$W,Q$2) -> 0 | R8: =J8-O8 -> 0 | S8: =L8-Q8 -> 0 | W8: =SUM(W3:W7) -> 1
A9: =+B9&C9 -> Véhicules neufsMoto détail | B9: =+$K$1 -> Véhicules neufs | C9: Moto détail | D9: =+INDEX('Budget original'!$A$2:$AO$496,MATCH($A9,'Budget original'!$A$2:$A$496,0),MATCH(D$2,'Budget original'!$A$2:$AO$2,0)) -> 0 | E9: =IF(D9=0,0,F9/D9) -> 0 | F9: =+INDEX('Budget original'!$A$2:$AO$496,MATCH($A9,'Budget original'!$A$2:$A$496,0),MATCH(F$2,'Budget original'!$A$2:$AO$2,0)) -> 0 | G9: =+INDEX('Budget révisé'!$A$2:$AO$496,MATCH($A9,'Budget révisé'!$A$2:$A$496,0),MATCH(G$2,'Budget révisé'!$A$2:$AO$2,0)) -> 0 | H9: =IF(G9=0,0,I9/G9) -> 0 | I9: =+INDEX('Budget révisé'!$A$2:$AO$496,MATCH($A9,'Budget révisé'!$A$2:$A$496,0),MATCH(I$2,'Budget révisé'!$A$2:$AO$2,0)) -> 0 | J9: =-SUMIFS(BV_Data_An_Cour!$O:$O,BV_Data_An_Cour!$U:$U,$B9,BV_Data_An_Cour!$V:$V,$C9,BV_Data_An_Cour!$W:$W,J$2) -> 0 | K9: =IF(J9=0,0,L9/J9) -> 0 | L9: =-SUMIFS(BV_Data_An_Cour!$O:$O,BV_Data_An_Cour!$U:$U,$B9,BV_Data_An_Cour!$V:$V,$C9,BV_Data_An_Cour!$W:$W,L$2) -> 0 | M9: =J9-G9 -> 0 | N9: =L9-I9 -> 0 | O9: =-SUMIFS(BV_Data_An_Prec!$O:$O,BV_Data_An_Prec!$U:$U,$B9,BV_Data_An_Prec!$V:$V,$C9,BV_Data_An_Prec!$W:$W,O$2) -> 0 | P9: =IF(O9=0,0,Q9/O9) -> 0 | Q9: =-SUMIFS(BV_Data_An_Prec!$O:$O,BV_Data_An_Prec!$U:$U,$B9,BV_Data_An_Prec!$V:$V,$C9,BV_Data_An_Prec!$W:$W,Q$2) -> 0 | R9: =J9-O9 -> 0 | S9: =L9-Q9 -> 0
A10: =+B10&C10 -> Véhicules neufs[...] | B10: =+$K$1 -> Véhicules neufs | C10: [...] | D10: =+INDEX('Budget original'!$A$2:$AO$496,MATCH($A10,'Budget original'!$A$2:$A$496,0),MATCH(D$2,'Budget original'!$A$2:$AO$2,0)) -> 0 | E10: =IF(D10=0,0,F10/D10) -> 0 | F10: =+INDEX('Budget original'!$A$2:$AO$496,MATCH($A10,'Budget original'!$A$2:$A$496,0),MATCH(F$2,'Budget original'!$A$2:$AO$2,0)) -> 0 | G10: =+INDEX('Budget révisé'!$A$2:$AO$496,MATCH($A10,'Budget révisé'!$A$2:$A$496,0),MATCH(G$2,'Budget révisé'!$A$2:$AO$2,0)) -> 0 | H10: =IF(G10=0,0,I10/G10) -> 0 | I10: =+INDEX('Budget révisé'!$A$2:$AO$496,MATCH($A10,'Budget révisé'!$A$2:$A$496,0),MATCH(I$2,'Budget révisé'!$A$2:$AO$2,0)) -> 0 | J10: =-SUMIFS(BV_Data_An_Cour!$O:$O,BV_Data_An_Cour!$U:$U,$B10,BV_Data_An_Cour!$V:$V,$C10,BV_Data_An_Cour!$W:$W,J$2) -> 0 | K10: =IF(J10=0,0,L10/J10) -> 0 | L10: =-SUMIFS(BV_Data_An_Cour!$O:$O,BV_Data_An_Cour!$U:$U,$B10,BV_Data_An_Cour!$V:$V,$C10,BV_Data_An_Cour!$W:$W,L$2) -> 0 | M10: =J10-G10 -> 0 | N10: =L10-I10 -> 0 | O10: =-SUMIFS(BV_Data_An_Prec!$O:$O,BV_Data_An_Prec!$U:$U,$B10,BV_Data_An_Prec!$V:$V,$C10,BV_Data_An_Prec!$W:$W,O$2) -> 0 | P10: =IF(O10=0,0,Q10/O10) -> 0 | Q10: =-SUMIFS(BV_Data_An_Prec!$O:$O,BV_Data_An_Prec!$U:$U,$B10,BV_Data_An_Prec!$V:$V,$C10,BV_Data_An_Prec!$W:$W,Q$2) -> 0 | R10: =J10-O10 -> 0 | S10: =L10-Q10 -> 0
A11: =+B11&C11 -> Véhicules neufs[...] | B11: =+$K$1 -> Véhicules neufs | C11: [...] | D11: =+INDEX('Budget original'!$A$2:$AO$496,MATCH($A11,'Budget original'!$A$2:$A$496,0),MATCH(D$2,'Budget original'!$A$2:$AO$2,0)) -> 0 | E11: =IF(D11=0,0,F11/D11) -> 0 | F11: =+INDEX('Budget original'!$A$2:$AO$496,MATCH($A11,'Budget original'!$A$2:$A$496,0),MATCH(F$2,'Budget original'!$A$2:$AO$2,0)) -> 0 | G11: =+INDEX('Budget révisé'!$A$2:$AO$496,MATCH($A11,'Budget révisé'!$A$2:$A$496,0),MATCH(G$2,'Budget révisé'!$A$2:$AO$2,0)) -> 0 | H11: =IF(G11=0,0,I11/G11) -> 0 | I11: =+INDEX('Budget révisé'!$A$2:$AO$496,MATCH($A11,'Budget révisé'!$A$2:$A$496,0),MATCH(I$2,'Budget révisé'!$A$2:$AO$2,0)) -> 0 | J11: =-SUMIFS(BV_Data_An_Cour!$O:$O,BV_Data_An_Cour!$U:$U,$B11,BV_Data_An_Cour!$V:$V,$C11,BV_Data_An_Cour!$W:$W,J$2) -> 0 | K11: =IF(J11=0,0,L11/J11) -> 0 | L11: =-SUMIFS(BV_Data_An_Cour!$O:$O,BV_Data_An_Cour!$U:$U,$B11,BV_Data_An_Cour!$V:$V,$C11,BV_Data_An_Cour!$W:$W,L$2) -> 0 | M11: =J11-G11 -> 0 | N11: =L11-I11 -> 0 | O11: =-SUMIFS(BV_Data_An_Prec!$O:$O,BV_Data_An_Prec!$U:$U,$B11,BV_Data_An_Prec!$V:$V,$C11,BV_Data_An_Prec!$W:$W,O$2) -> 0 | P11: =IF(O11=0,0,Q11/O11) -> 0 | Q11: =-SUMIFS(BV_Data_An_Prec!$O:$O,BV_Data_An_Prec!$U:$U,$B11,BV_Data_An_Prec!$V:$V,$C11,BV_Data_An_Prec!$W:$W,Q$2) -> 0 | R11: =J11-O11 -> 0 | S11: =L11-Q11 -> 0
A12: =+B12&C12 -> Véhicules neufs[...] | B12: =+$K$1 -> Véhicules neufs | C12: [...] | D12: =+INDEX('Budget original'!$A$2:$AO$496,MATCH($A12,'Budget original'!$A$2:$A$496,0),MATCH(D$2,'Budget original'!$A$2:$AO$2,0)) -> 0 | E12: =IF(D12=0,0,F12/D12) -> 0 | F12: =+INDEX('Budget original'!$A$2:$AO$496,MATCH($A12,'Budget original'!$A$2:$A$496,0),MATCH(F$2,'Budget original'!$A$2:$AO$2,0)) -> 0 | G12: =+INDEX('Budget révisé'!$A$2:$AO$496,MATCH($A12,'Budget révisé'!$A$2:$A$496,0),MATCH(G$2,'Budget révisé'!$A$2:$AO$2,0)) -> 0 | H12: =IF(G12=0,0,I12/G12) -> 0 | I12: =+INDEX('Budget révisé'!$A$2:$AO$496,MATCH($A12,'Budget révisé'!$A$2:$A$496,0),MATCH(I$2,'Budget révisé'!$A$2:$AO$2,0)) -> 0 | J12: =-SUMIFS(BV_Data_An_Cour!$O:$O,BV_Data_An_Cour!$U:$U,$B12,BV_Data_An_Cour!$V:$V,$C12,BV_Data_An_Cour!$W:$W,J$2) -> 0 | K12: =IF(J12=0,0,L12/J12) -> 0 | L12: =-SUMIFS(BV_Data_An_Cour!$O:$O,BV_Data_An_Cour!$U:$U,$B12,BV_Data_An_Cour!$V:$V,$C12,BV_Data_An_Cour!$W:$W,L$2) -> 0 | M12: =J12-G12 -> 0 | N12: =L12-I12 -> 0 | O12: =-SUMIFS(BV_Data_An_Prec!$O:$O,BV_Data_An_Prec!$U:$U,$B12,BV_Data_An_Prec!$V:$V,$C12,BV_Data_An_Prec!$W:$W,O$2) -> 0 | P12: =IF(O12=0,0,Q12/O12) -> 0 | Q12: =-SUMIFS(BV_Data_An_Prec!$O:$O,BV_Data_An_Prec!$U:$U,$B12,BV_Data_An_Prec!$V:$V,$C12,BV_Data_An_Prec!$W:$W,Q$2) -> 0 | R12: =J12-O12 -> 0 | S12: =L12-Q12 -> 0
A13: =+B13&C13 -> Véhicules neufsTotal Neufs | B13: =+$K$1 -> Véhicules neufs | C13: Total Neufs | D13: =+SUM(D6:D12) -> 57.894239 | E13: =IF(D13<=0,0,F13/D13) -> 1011.9718 | F13: =+SUM(F6:F12) -> 58587.339 | G13: =+SUM(G6:G12) -> 57.894239 | H13: =IF(G13<=0,0,I13/G13) -> 1383.6161 | I13: =+SUM(I6:I12) -> 80103.403 | J13: =+SUM(J6:J12) -> 69 | K13: =IF(J13<=0,0,L13/J13) -> 1673.301 | L13: =+SUM(L6:L12) -> 115457.77 | M13: =+SUM(M6:M12) -> 11.105761 | N13: =+SUM(N6:N12) -> 35354.367 | O13: =+SUM(O6:O12) -> 75 | P13: =IF(O13<=0,0,Q13/O13) -> 551.4772 | Q13: =+SUM(Q6:Q12) -> 41360.79 | R13: =+SUM(R6:R12) -> -6 | S13: =+SUM(S6:S12) -> 74096.98
A14: =+B14&C14 -> Véhicules neufs | B14: =+$K$1 -> Véhicules neufs | M14: =IF(G13=0,0,M13/G13) -> 0.19182843 | N14: =IF(I13=0,0,N13/I13) -> 0.44135911 | R14: =R13/O13 -> -0.08 | S14: =IF(Q13=0,0,(S13/Q13)) -> 1.7914788
A15: =+B15&C15 -> Véhicules neufsEx-Démos et courtoisies | B15: =+$K$1 -> Véhicules neufs | C15: Ex-Démos et courtoisies | D15: =+INDEX('Budget original'!$A$2:$AO$496,MATCH($A15,'Budget original'!$A$2:$A$496,0),MATCH(D$2,'Budget original'!$A$2:$AO$2,0)) -> 6.0340474 | E15: =IF(D15=0,0,F15/D15) -> 400 | F15: =+INDEX('Budget original'!$A$2:$AO$496,MATCH($A15,'Budget original'!$A$2:$A$496,0),MATCH(F$2,'Budget original'!$A$2:$AO$2,0)) -> 2413.619 | G15: =+INDEX('Budget révisé'!$A$2:$AO$496,MATCH($A15,'Budget révisé'!$A$2:$A$496,0),MATCH(G$2,'Budget révisé'!$A$2:$AO$2,0)) -> 6.0340474 | H15: =IF(G15=0,0,I15/G15) -> 790.03378 | I15: =+INDEX('Budget révisé'!$A$2:$AO$496,MATCH($A15,'Budget révisé'!$A$2:$A$496,0),MATCH(I$2,'Budget révisé'!$A$2:$AO$2,0)) -> 4767.1013 | J15: =-SUMIFS(BV_Data_An_Cour!$O:$O,BV_Data_An_Cour!$U:$U,$B15,BV_Data_An_Cour!$V:$V,$C15,BV_Data_An_Cour!$W:$W,J$2) -> 9 | K15: =IF(J15=0,0,L15/J15) -> 754.36444 | L15: =-SUMIFS(BV_Data_An_Cour!$O:$O,BV_Data_An_Cour!$U:$U,$B15,BV_Data_An_Cour!$V:$V,$C15,BV_Data_An_Cour!$W:$W,L$2) -> 6789.28 | M15: =J15-G15 -> 2.9659526 | N15: =L15-I15 -> 2022.1787 | O15: =-SUMIFS(BV_Data_An_Prec!$O:$O,BV_Data_An_Prec!$U:$U,$B15,BV_Data_An_Prec!$V:$V,$C15,BV_Data_An_Prec!$W:$W,O$2) -> 0 | P15: =IF(O15=0,0,Q15/O15) -> 0 | Q15: =-SUMIFS(BV_Data_An_Prec!$O:$O,BV_Data_An_Prec!$U:$U,$B15,BV_Data_An_Prec!$V:$V,$C15,BV_Data_An_Prec!$W:$W,Q$2) -> 0 | R15: =J15-O15 -> 9 | S15: =L15-Q15 -> 6789.28
A16: =+B16&C16 -> Véhicules neufs | B16: =+$K$1 -> Véhicules neufs
A17: =+B17&C17 -> Véhicules neufsFlottes | B17: =+$K$1 -> Véhicules neufs | C17: Flottes | D17: =+INDEX('Budget original'!$A$2:$AO$496,MATCH($A17,'Budget original'!$A$2:$A$496,0),MATCH(D$2,'Budget original'!$A$2:$AO$2,0)) -> 0 | E17: =IF(D17=0,0,F17/D17) -> 0 | F17: =+INDEX('Budget original'!$A$2:$AO$496,MATCH($A17,'Budget original'!$A$2:$A$496,0),MATCH(F$2,'Budget original'!$A$2:$AO$2,0)) -> 0 | G17: =+INDEX('Budget révisé'!$A$2:$AO$496,MATCH($A17,'Budget révisé'!$A$2:$A$496,0),MATCH(G$2,'Budget révisé'!$A$2:$AO$2,0)) -> 2.2107736 | H17: =IF(G17=0,0,I17/G17) -> 800 | I17: =+INDEX('Budget révisé'!$A$2:$AO$496,MATCH($A17,'Budget révisé'!$A$2:$A$496,0),MATCH(I$2,'Budget révisé'!$A$2:$AO$2,0)) -> 1768.6189 | J17: =-SUMIFS(BV_Data_An_Cour!$O:$O,BV_Data_An_Cour!$U:$U,$B17,BV_Data_An_Cour!$V:$V,$C17,BV_Data_An_Cour!$W:$W,J$2) -> 3 | K17: =IF(J17=0,0,L17/J17) -> 1019.75 | L17: =-SUMIFS(BV_Data_An_Cour!$O:$O,BV_Data_An_Cour!$U:$U,$B17,BV_Data_An_Cour!$V:$V,$C17,BV_Data_An_Cour!$W:$W,L$2) -> 3059.25 | M17: =J17-G17 -> 0.78922642 | N17: =L17-I17 -> 1290.6311 | O17: =-SUMIFS(BV_Data_An_Prec!$O:$O,BV_Data_An_Prec!$U:$U,$B17,BV_Data_An_Prec!$V:$V,$C17,BV_Data_An_Prec!$W:$W,O$2) -> 0 | P17: =IF(O17=0,0,Q17/O17) -> 0 | Q17: =-SUMIFS(BV_Data_An_Prec!$O:$O,BV_Data_An_Prec!$U:$U,$B17,BV_Data_An_Prec!$V:$V,$C17,BV_Data_An_Prec!$W:$W,Q$2) -> 0 | R17: =J17-O17 -> 3 | S17: =L17-Q17 -> 3059.25
A18: =+B18&C18 -> Véhicules neufs | B18: =+$K$1 -> Véhicules neufs
A19: =+B19&C19 -> Véhicules neufsRachat bail | B19: =+$K$1 -> Véhicules neufs | C19: Rachat bail | D19: =+INDEX('Budget original'!$A$2:$AO$496,MATCH($A19,'Budget original'!$A$2:$A$496,0),MATCH(D$2,'Budget original'!$A$2:$AO$2,0)) -> 0 | E19: =IF(D19=0,0,F19/D19) -> 0 | F19: =+INDEX('Budget original'!$A$2:$AO$496,MATCH($A19,'Budget original'!$A$2:$A$496,0),MATCH(F$2,'Budget original'!$A$2:$AO$2,0)) -> 5000 | G19: =+INDEX('Budget révisé'!$A$2:$AO$496,MATCH($A19,'Budget révisé'!$A$2:$A$496,0),MATCH(G$2,'Budget révisé'!$A$2:$AO$2,0)) -> 0 | H19: =IF(G19=0,0,I19/G19) -> 0 | I19: =+INDEX('Budget révisé'!$A$2:$AO$496,MATCH($A19,'Budget révisé'!$A$2:$A$496,0),MATCH(I$2,'Budget révisé'!$A$2:$AO$2,0)) -> 5000 | L19: =-SUMIFS(BV_Data_An_Cour!$O:$O,BV_Data_An_Cour!$U:$U,$B19,BV_Data_An_Cour!$V:$V,$C19,BV_Data_An_Cour!$W:$W,L$2) -> 6884.37 | N19: =L19-I19 -> 1884.37 | Q19: =-SUMIFS(BV_Data_An_Prec!$O:$O,BV_Data_An_Prec!$U:$U,$B19,BV_Data_An_Prec!$V:$V,$C19,BV_Data_An_Prec!$W:$W,Q$2) -> 6677.45 | R19: =O19-K19 -> 0 | S19: =L19-Q19 -> 206.92 | U19: Budget | V19: =G13+G15+G17 -> 66.13906 | W19: =I13+I15+I17 -> 86639.123 | X19: =W19/V19 -> 1309.954
A20: =+B20&C20 -> Véhicules neufs | B20: =+$K$1 -> Véhicules neufs | U20: 2021 | V20: =J13+J15+J17 -> 81 | W20: =L13+L15+L17 -> 125306.3 | X20: =W20/V20 -> 1546.9914
A21: =+B21&C21 -> Véhicules neufsRev. Finances | B21: =+$K$1 -> Véhicules neufs | C21: Rev. Finances | D21: =+INDEX('Budget original'!$A$2:$AO$496,MATCH($A21,'Budget original'!$A$2:$A$496,0),MATCH(D$2,'Budget original'!$A$2:$AO$2,0)) -> 0 | E21: =IF(D21=0,0,F21/D21) -> 0 | F21: =+INDEX('Budget original'!$A$2:$AO$496,MATCH($A21,'Budget original'!$A$2:$A$496,0),MATCH(F$2,'Budget original'!$A$2:$AO$2,0)) -> 6014.36 | G21: =+INDEX('Budget révisé'!$A$2:$AO$496,MATCH($A21,'Budget révisé'!$A$2:$A$496,0),MATCH(G$2,'Budget révisé'!$A$2:$AO$2,0)) -> 0 | H21: =IF(G21=0,0,I21/G21) -> 0 | I21: =+INDEX('Budget révisé'!$A$2:$AO$496,MATCH($A21,'Budget révisé'!$A$2:$A$496,0),MATCH(I$2,'Budget révisé'!$A$2:$AO$2,0)) -> 6014.36 | K21: =IF(J13=0,0,L21/(J13+J15)) -> -13.910513 | L21: =-SUMIFS(BV_Data_An_Cour!$O:$O,BV_Data_An_Cour!$U:$U,$B21,BV_Data_An_Cour!$V:$V,$C21,BV_Data_An_Cour!$W:$W,L$2) -> -1085.02 | N21: =L21-I21 -> -7099.38 | P21: =IF(O13=0,0,Q21/(O13+O15)) -> 88.860133 | Q21: =-SUMIFS(BV_Data_An_Prec!$O:$O,BV_Data_An_Prec!$U:$U,$B21,BV_Data_An_Prec!$V:$V,$C21,BV_Data_An_Prec!$W:$W,Q$2) -> 6664.51 | R21: =O21-K21 -> 13.910513 | S21: =L21-Q21 -> -7749.53
A22: =+B22&C22 -> Véhicules neufsRev. Protections | B22: =+$K$1 -> Véhicules neufs | C22: Rev. Protections | D22: =+INDEX('Budget original'!$A$2:$AO$496,MATCH($A22,'Budget original'!$A$2:$A$496,0),MATCH(D$2,'Budget original'!$A$2:$AO$2,0)) -> 0 | E22: =IF(D22=0,0,F22/D22) -> 0 | F22: =+INDEX('Budget original'!$A$2:$AO$496,MATCH($A22,'Budget original'!$A$2:$A$496,0),MATCH(F$2,'Budget original'!$A$2:$AO$2,0)) -> 47135.798 | G22: =+INDEX('Budget révisé'!$A$2:$AO$496,MATCH($A22,'Budget révisé'!$A$2:$A$496,0),MATCH(G$2,'Budget révisé'!$A$2:$AO$2,0)) -> 0 | H22: =IF(G22=0,0,I22/G22) -> 0 | I22: =+INDEX('Budget révisé'!$A$2:$AO$496,MATCH($A22,'Budget révisé'!$A$2:$A$496,0),MATCH(I$2,'Budget révisé'!$A$2:$AO$2,0)) -> 47135.798 | K22: =IF(J13=0,0,L22/(J13+J15)) -> 674.86 | L22: =-SUMIFS(BV_Data_An_Cour!$O:$O,BV_Data_An_Cour!$U:$U,$B22,BV_Data_An_Cour!$V:$V,$C22,BV_Data_An_Cour!$W:$W,L$2) -> 52639.08 | N22: =L22-I22 -> 5503.2817 | P22: =IF(O13=0,0,Q22/(O13+O15)) -> 502.97667 | Q22: =-SUMIFS(BV_Data_An_Prec!$O:$O,BV_Data_An_Prec!$U:$U,$B22,BV_Data_An_Prec!$V:$V,$C22,BV_Data_An_Prec!$W:$W,Q$2) -> 37723.25 | R22: =O22-K22 -> -674.86 | S22: =L22-Q22 -> 14915.83
A23: =+B23&C23 -> Véhicules neufsRev. Autres | B23: =+$K$1 -> Véhicules neufs | C23: Rev. Autres | D23: =+INDEX('Budget original'!$A$2:$AO$496,MATCH($A23,'Budget original'!$A$2:$A$496,0),MATCH(D$2,'Budget original'!$A$2:$AO$2,0)) -> 0 | E23: =IF(D23=0,0,F23/D23) -> 0 | F23: =+INDEX('Budget original'!$A$2:$AO$496,MATCH($A23,'Budget original'!$A$2:$A$496,0),MATCH(F$2,'Budget original'!$A$2:$AO$2,0)) -> 1188.8851 | G23: =+INDEX('Budget révisé'!$A$2:$AO$496,MATCH($A23,'Budget révisé'!$A$2:$A$496,0),MATCH(G$2,'Budget révisé'!$A$2:$AO$2,0)) -> 0 | H23: =IF(G23=0,0,I23/G23) -> 0 | I23: =+INDEX('Budget révisé'!$A$2:$AO$496,MATCH($A23,'Budget révisé'!$A$2:$A$496,0),MATCH(I$2,'Budget révisé'!$A$2:$AO$2,0)) -> 1188.8851 | K23: =IF(J13=0,0,L23/(J13+J15)) -> 25.959231 | L23: =-SUMIFS(BV_Data_An_Cour!$O:$O,BV_Data_An_Cour!$U:$U,$B23,BV_Data_An_Cour!$V:$V,$C23,BV_Data_An_Cour!$W:$W,L$2) -> 2024.82 | N23: =L23-I23 -> 835.93488 | P23: =IF(O13=0,0,Q23/(O13+O15)) -> 24.851067 | Q23: =-SUMIFS(BV_Data_An_Prec!$O:$O,BV_Data_An_Prec!$U:$U,$B23,BV_Data_An_Prec!$V:$V,$C23,BV_Data_An_Prec!$W:$W,Q$2) -> 1863.83 | R23: =O23-K23 -> -25.959231 | S23: =L23-Q23 -> 160.99 | V23: mois de location pas de financement
A24: =+B24&C24 -> Véhicules neufsTotal F&I | B24: =+$K$1 -> Véhicules neufs | C24: Total F&I | D24: =+D15+D13 -> 63.928286 | E24: =IF(D24<=0,0,F24/D24) -> 850 | F24: =F21+F22+F23 -> 54339.043 | G24: =+G15+G13 -> 63.928286 | H24: =IF(G24<=0,0,I24/G24) -> 850 | I24: =I21+I22+I23 -> 54339.043 | J24: =+J15+J13 -> 78 | K24: =IF(J24<=0,0,L24/J24) -> 686.90872 | L24: =L21+L22+L23 -> 53578.88 | M24: =J24-G24 -> 14.071714 | N24: =L24-I24 -> -760.16344 | O24: =+O15+O13 -> 75 | P24: =IF(O24<=0,0,Q24/O24) -> 616.68787 | Q24: =Q21+Q22+Q23 -> 46251.59 | S24: =L24-Q24 -> 7327.29 | V24: donc plus plus dificile
A25: =+B25&C25 -> Véhicules neufs | B25: =+$K$1 -> Véhicules neufs | N25: =IF(N24=0,0,N24/I24) -> -0.013989268 | S25: =IF(Q24=0,0,(S24/Q24)) -> 0.15842245
A26: =+B26&C26 -> Véhicules neufs | B26: =+$K$1 -> Véhicules neufs
A27: =+B27&C27 -> Véhicules neufsTotal Dépt. Neufs | B27: =+$K$1 -> Véhicules neufs | C27: Total Dépt. Neufs | D27: =+D13+D15+D17 -> 63.928286 | E27: =IF(D27<=0,0,F27/D27) -> 1882.4218 | F27: =F13+F17+F24+F19+F15 -> 120340 | G27: =+G13+G15+G17 -> 66.13906 | H27: =IF(G27<=0,0,I27/G27) -> 2207.14 | I27: =I13+I17+I24+I19+I15 -> 145978.17 | J27: =+J13+J15+J17 -> 81 | K27: =IF(J27<=0,0,L27/J27) -> 2293.4512 | L27: =L13+L17+L24+L19+L15 -> 185769.55 | M27: =J27-G27 -> 14.86094 | N27: =L27-I27 -> 39791.383 | O27: =+O13+O15+O17 -> 75 | P27: =IF(O27<=0,0,Q27/O27) -> 1257.1977 | Q27: =Q13+Q17+Q24+Q19+Q15 -> 94289.83 | R27: =J27-O27 -> 6 | S27: =L27-Q27 -> 91479.72
A28: =+B28&C28 -> Véhicules neufs | B28: =+$K$1 -> Véhicules neufs | M28: =M27/G27 -> 0.22469234 | N28: =N27/I27 -> 0.27258448 | R28: =R27/O27 -> 0.08 | S28: =IF(Q27=0,0,S27/Q27) -> 0.9701971
A29: =+B29&C29 -> Véhicules neufs | B29: =+$K$1 -> Véhicules neufs
A30: =+B30&C30 -> Véhicules neufsDEPENSES | B30: =+$K$1 -> Véhicules neufs | C30: DEPENSES
A31: =+B31&C31 -> Véhicules neufsComm. vendeurs | B31: =+$K$1 -> Véhicules neufs | C31: Comm. vendeurs | E31: =F31/D$24 -> 385.8146 | F31: =+INDEX('Budget original'!$A$2:$AO$496,MATCH($A31,'Budget original'!$A$2:$A$496,0),MATCH(F$2,'Budget original'!$A$2:$AO$2,0)) -> 24664.466 | G31: =I31/(I15+I13) -> 0.29618008 | H31: =I31/G$24 -> 393.20549 | I31: =+INDEX('Budget révisé'!$A$2:$AO$496,MATCH($A31,'Budget révisé'!$A$2:$A$496,0),MATCH(I$2,'Budget révisé'!$A$2:$AO$2,0)) -> 25136.953 | J31: =L31/(L15+L13) -> 0.34340968 | K31: =IF(L31=0,0,L31/J$24) -> 538.21564 | L31: =SUMIFS(BV_Data_An_Cour!$O:$O,BV_Data_An_Cour!$U:$U,$B31,BV_Data_An_Cour!$V:$V,$C31,BV_Data_An_Cour!$W:$W,L$2) -> 41980.82 | N31: =L31-I31 -> 16843.867 | P31: =IF(Q31=0,0,Q31/O$24) -> 400.19333 | Q31: =SUMIFS(BV_Data_An_Prec!$O:$O,BV_Data_An_Prec!$U:$U,$B31,BV_Data_An_Prec!$V:$V,$C31,BV_Data_An_Prec!$W:$W,Q$2) -> 30014.5 | S31: =L31-Q31 -> 11966.32
A32: =+B32&C32 -> Véhicules neufsComm. F&I | B32: =+$K$1 -> Véhicules neufs | C32: Comm. F&I | E32: =F32/D$24 -> 255 | F32: =+INDEX('Budget original'!$A$2:$AO$496,MATCH($A32,'Budget original'!$A$2:$A$496,0),MATCH(F$2,'Budget original'!$A$2:$AO$2,0)) -> 16301.713 | G32: =I32/I24 -> 0.3 | H32: =I32/G$24 -> 255 | I32: =+INDEX('Budget révisé'!$A$2:$AO$496,MATCH($A32,'Budget révisé'!$A$2:$A$496,0),MATCH(I$2,'Budget révisé'!$A$2:$AO$2,0)) -> 16301.713 | J32: =L32/L24 -> 0.29627308 | K32: =IF(L32=0,0,L32/J$24) -> 203.51256 | L32: =SUMIFS(BV_Data_An_Cour!$O:$O,BV_Data_An_Cour!$U:$U,$B32,BV_Data_An_Cour!$V:$V,$C32,BV_Data_An_Cour!$W:$W,L$2) -> 15873.98 | N32: =L32-I32 -> -427.73303 | P32: =IF(Q32=0,0,Q32/O$24) -> 279.698 | Q32: =SUMIFS(BV_Data_An_Prec!$O:$O,BV_Data_An_Prec!$U:$U,$B32,BV_Data_An_Prec!$V:$V,$C32,BV_Data_An_Prec!$W:$W,Q$2) -> 20977.35 | S32: =L32-Q32 -> -5103.37
A33: =+B33&C33 -> Véhicules neufsFrais de livraison | B33: =+$K$1 -> Véhicules neufs | C33: Frais de livraison | E33: =F33/D$24 -> 197 | F33: =+INDEX('Budget original'!$A$2:$AO$496,MATCH($A33,'Budget original'!$A$2:$A$496,0),MATCH(F$2,'Budget original'!$A$2:$AO$2,0)) -> 12593.872 | H33: =I33/G$24 -> 197 | I33: =+INDEX('Budget révisé'!$A$2:$AO$496,MATCH($A33,'Budget révisé'!$A$2:$A$496,0),MATCH(I$2,'Budget révisé'!$A$2:$AO$2,0)) -> 12593.872 | K33: =IF(L33=0,0,L33/J$24) -> 135.56885 | L33: =SUMIFS(BV_Data_An_Cour!$O:$O,BV_Data_An_Cour!$U:$U,$B33,BV_Data_An_Cour!$V:$V,$C33,BV_Data_An_Cour!$W:$W,L$2) -> 10574.37 | N33: =L33-I33 -> -2019.5024 | P33: =IF(Q33=0,0,Q33/O$24) -> 161.3544 | Q33: =SUMIFS(BV_Data_An_Prec!$O:$O,BV_Data_An_Prec!$U:$U,$B33,BV_Data_An_Prec!$V:$V,$C33,BV_Data_An_Prec!$W:$W,Q$2) -> 12101.58 | S33: =L33-Q33 -> -1527.21 | W33: =L24*0.25 -> 13394.72
A34: =+B34&C34 -> Véhicules neufsService gratuit 1 | B34: =+$K$1 -> Véhicules neufs | C34: Service gratuit 1 | E34: =F34/D$24 -> 6 | F34: =+INDEX('Budget original'!$A$2:$AO$496,MATCH($A34,'Budget original'!$A$2:$A$496,0),MATCH(F$2,'Budget original'!$A$2:$AO$2,0)) -> 383.56972 | H34: =I34/G$24 -> 6 | I34: =+INDEX('Budget révisé'!$A$2:$AO$496,MATCH($A34,'Budget révisé'!$A$2:$A$496,0),MATCH(I$2,'Budget révisé'!$A$2:$AO$2,0)) -> 383.56972 | K34: =IF(L34=0,0,L34/J$24) -> 0 | L34: =SUMIFS(BV_Data_An_Cour!$O:$O,BV_Data_An_Cour!$U:$U,$B34,BV_Data_An_Cour!$V:$V,$C34,BV_Data_An_Cour!$W:$W,L$2) -> 0 | N34: =L34-I34 -> -383.56972 | P34: =IF(Q34=0,0,Q34/O$24) -> 12.813067 | Q34: =SUMIFS(BV_Data_An_Prec!$O:$O,BV_Data_An_Prec!$U:$U,$B34,BV_Data_An_Prec!$V:$V,$C34,BV_Data_An_Prec!$W:$W,Q$2) -> 960.98 | S34: =L34-Q34 -> -960.98
A35: =+B35&C35 -> Véhicules neufsEntretien stock | B35: =+$K$1 -> Véhicules neufs | C35: Entretien stock | E35: =F35/D$24 -> 34 | F35: =+INDEX('Budget original'!$A$2:$AO$496,MATCH($A35,'Budget original'!$A$2:$A$496,0),MATCH(F$2,'Budget original'!$A$2:$AO$2,0)) -> 2173.5617 | H35: =I35/G$24 -> 34 | I35: =+INDEX('Budget révisé'!$A$2:$AO$496,MATCH($A35,'Budget révisé'!$A$2:$A$496,0),MATCH(I$2,'Budget révisé'!$A$2:$AO$2,0)) -> 2173.5617 | K35: =IF(L35=0,0,L35/J$24) -> 0.51282051 | L35: =SUMIFS(BV_Data_An_Cour!$O:$O,BV_Data_An_Cour!$U:$U,$B35,BV_Data_An_Cour!$V:$V,$C35,BV_Data_An_Cour!$W:$W,L$2) -> 40 | N35: =L35-I35 -> -2133.5617 | P35: =IF(Q35=0,0,Q35/O$24) -> 48.2648 | Q35: =SUMIFS(BV_Data_An_Prec!$O:$O,BV_Data_An_Prec!$U:$U,$B35,BV_Data_An_Prec!$V:$V,$C35,BV_Data_An_Prec!$W:$W,Q$2) -> 3619.86 | S35: =L35-Q35 -> -3579.86 | W35: =L32-W33 -> 2479.26
A36: =+B36&C36 -> Véhicules neufsPublicité 1 | B36: =+$K$1 -> Véhicules neufs | C36: Publicité 1 | E36: =F36/D$24 -> 180.66964 | F36: =+INDEX('Budget original'!$A$2:$AO$496,MATCH($A36,'Budget original'!$A$2:$A$496,0),MATCH(F$2,'Budget original'!$A$2:$AO$2,0)) -> 11549.901 | H36: =I36/G$24 -> 180.66964 | I36: =+INDEX('Budget révisé'!$A$2:$AO$496,MATCH($A36,'Budget révisé'!$A$2:$A$496,0),MATCH(I$2,'Budget révisé'!$A$2:$AO$2,0)) -> 11549.901 | K36: =IF(L36=0,0,L36/J$24) -> 97.126795 | L36: =SUMIFS(BV_Data_An_Cour!$O:$O,BV_Data_An_Cour!$U:$U,$B36,BV_Data_An_Cour!$V:$V,$C36,BV_Data_An_Cour!$W:$W,L$2) -> 7575.89 | N36: =L36-I36 -> -3974.0107 | P36: =IF(Q36=0,0,Q36/O$24) -> 70.533333 | Q36: =SUMIFS(BV_Data_An_Prec!$O:$O,BV_Data_An_Prec!$U:$U,$B36,BV_Data_An_Prec!$V:$V,$C36,BV_Data_An_Prec!$W:$W,Q$2) -> 5290 | S36: =L36-Q36 -> 2285.89 | V36: Media 360 set up , javier et feb
A37: =+B37&C37 -> Véhicules neufsIntérêt de gros | B37: =+$K$1 -> Véhicules neufs | C37: Intérêt de gros | E37: =F37/D$24 -> 229.32443 | F37: =+INDEX('Budget original'!$A$2:$AO$496,MATCH($A37,'Budget original'!$A$2:$A$496,0),MATCH(F$2,'Budget original'!$A$2:$AO$2,0)) -> 14660.318 | H37: =I37/G$24 -> 231.24629 | I37: =+INDEX('Budget révisé'!$A$2:$AO$496,MATCH($A37,'Budget révisé'!$A$2:$A$496,0),MATCH(I$2,'Budget révisé'!$A$2:$AO$2,0)) -> 14783.179 | K37: =IF(L37=0,0,L37/J$24) -> 172.06923 | L37: =SUMIFS(BV_Data_An_Cour!$O:$O,BV_Data_An_Cour!$U:$U,$B37,BV_Data_An_Cour!$V:$V,$C37,BV_Data_An_Cour!$W:$W,L$2) -> 13421.4 | N37: =L37-I37 -> -1361.7793 | P37: =IF(Q37=0,0,Q37/O$24) -> 271.5552 | Q37: =SUMIFS(BV_Data_An_Prec!$O:$O,BV_Data_An_Prec!$U:$U,$B37,BV_Data_An_Prec!$V:$V,$C37,BV_Data_An_Prec!$W:$W,Q$2) -> 20366.64 | S37: =L37-Q37 -> -6945.24
A38: =+B38&C38 -> Véhicules neufs[...] | B38: =+$K$1 -> Véhicules neufs | C38: [...] | E38: =F38/D$24 -> 0 | F38: =+INDEX('Budget original'!$A$2:$AO$496,MATCH($A38,'Budget original'!$A$2:$A$496,0),MATCH(F$2,'Budget original'!$A$2:$AO$2,0)) -> 0 | H38: =I38/G$24 -> 0 | I38: =+INDEX('Budget révisé'!$A$2:$AO$496,MATCH($A38,'Budget révisé'!$A$2:$A$496,0),MATCH(I$2,'Budget révisé'!$A$2:$AO$2,0)) -> 0 | K38: =IF(L38=0,0,L38/J$24) -> 0 | L38: =SUMIFS(BV_Data_An_Cour!$O:$O,BV_Data_An_Cour!$U:$U,$B38,BV_Data_An_Cour!$V:$V,$C38,BV_Data_An_Cour!$W:$W,L$2) -> 0 | N38: =L38-I38 -> 0 | P38: =IF(Q38=0,0,Q38/O$24) -> 0 | Q38: =SUMIFS(BV_Data_An_Prec!$O:$O,BV_Data_An_Prec!$U:$U,$B38,BV_Data_An_Prec!$V:$V,$C38,BV_Data_An_Prec!$W:$W,Q$2) -> 0 | S38: =L38-Q38 -> 0
A39: =+B39&C39 -> Véhicules neufs[...] | B39: =+$K$1 -> Véhicules neufs | C39: [...] | E39: =F39/D$24 -> 0 | F39: =+INDEX('Budget original'!$A$2:$AO$496,MATCH($A39,'Budget original'!$A$2:$A$496,0),MATCH(F$2,'Budget original'!$A$2:$AO$2,0)) -> 0 | H39: =I39/G$24 -> 0 | I39: =+INDEX('Budget révisé'!$A$2:$AO$496,MATCH($A39,'Budget révisé'!$A$2:$A$496,0),MATCH(I$2,'Budget révisé'!$A$2:$AO$2,0)) -> 0 | K39: =IF(L39=0,0,L39/J$24) -> 0 | L39: =SUMIFS(BV_Data_An_Cour!$O:$O,BV_Data_An_Cour!$U:$U,$B39,BV_Data_An_Cour!$V:$V,$C39,BV_Data_An_Cour!$W:$W,L$2) -> 0 | N39: =L39-I39 -> 0 | P39: =IF(Q39=0,0,Q39/O$24) -> 0 | Q39: =SUMIFS(BV_Data_An_Prec!$O:$O,BV_Data_An_Prec!$U:$U,$B39,BV_Data_An_Prec!$V:$V,$C39,BV_Data_An_Prec!$W:$W,Q$2) -> 0 | S39: =L39-Q39 -> 0
A40: =+B40&C40 -> Véhicules neufs[...] | B40: =+$K$1 -> Véhicules neufs | C40: [...] | E40: =F40/D$24 -> 0 | F40: =+INDEX('Budget original'!$A$2:$AO$496,MATCH($A40,'Budget original'!$A$2:$A$496,0),MATCH(F$2,'Budget original'!$A$2:$AO$2,0)) -> 0 | H40: =I40/G$24 -> 0 | I40: =+INDEX('Budget révisé'!$A$2:$AO$496,MATCH($A40,'Budget révisé'!$A$2:$A$496,0),MATCH(I$2,'Budget révisé'!$A$2:$AO$2,0)) -> 0 | K40: =IF(L40=0,0,L40/J$24) -> 0 | L40: =SUMIFS(BV_Data_An_Cour!$O:$O,BV_Data_An_Cour!$U:$U,$B40,BV_Data_An_Cour!$V:$V,$C40,BV_Data_An_Cour!$W:$W,L$2) -> 0 | N40: =L40-I40 -> 0 | P40: =IF(Q40=0,0,Q40/O$24) -> 0 | Q40: =SUMIFS(BV_Data_An_Prec!$O:$O,BV_Data_An_Prec!$U:$U,$B40,BV_Data_An_Prec!$V:$V,$C40,BV_Data_An_Prec!$W:$W,Q$2) -> 0 | S40: =L40-Q40 -> 0
A41: =+B41&C41 -> Véhicules neufsTOTAL VARIABLES | B41: =+$K$1 -> Véhicules neufs | C41: TOTAL VARIABLES | D41: % brut | E41: =F41/F$27 -> 0.68412332 | F41: =SUM(F31:F40) -> 82327.402 | G41: % brut | H41: =I41/I$27 -> 0.56804899 | I41: =SUM(I31:I40) -> 82922.75 | J41: % brut | K41: =L41/L$27 -> 0.48159916 | L41: =SUM(L31:L40) -> 89466.46 | N41: =L41-I41 -> 6543.7102 | O41: % brut | P41: =Q41/Q$27 -> 0.98983008 | Q41: =SUM(Q31:Q40) -> 93330.91 | S41: =L41-Q41 -> -3864.45
A42: =+B42&C42 -> Véhicules neufsSalaires cadres | B42: =+$K$1 -> Véhicules neufs | C42: Salaires cadres | F42: =+INDEX('Budget original'!$A$2:$AO$496,MATCH($A42,'Budget original'!$A$2:$A$496,0),MATCH(F$2,'Budget original'!$A$2:$AO$2,0)) -> 25919.97 | I42: =+INDEX('Budget révisé'!$A$2:$AO$496,MATCH($A42,'Budget révisé'!$A$2:$A$496,0),MATCH(I$2,'Budget révisé'!$A$2:$AO$2,0)) -> 25919.97 | L42: =SUMIFS(BV_Data_An_Cour!$O:$O,BV_Data_An_Cour!$U:$U,$B42,BV_Data_An_Cour!$V:$V,$C42,BV_Data_An_Cour!$W:$W,L$2) -> 15654.54 | N42: =L42-I42 -> -10265.43 | Q42: =SUMIFS(BV_Data_An_Prec!$O:$O,BV_Data_An_Prec!$U:$U,$B42,BV_Data_An_Prec!$V:$V,$C42,BV_Data_An_Prec!$W:$W,Q$2) -> 32957.34 | S42: =L42-Q42 -> -17302.8 | U42: Pierre Charles -67%
A43: =+B43&C43 -> Véhicules neufsSalaires commis | B43: =+$K$1 -> Véhicules neufs | C43: Salaires commis | F43: =+INDEX('Budget original'!$A$2:$AO$496,MATCH($A43,'Budget original'!$A$2:$A$496,0),MATCH(F$2,'Budget original'!$A$2:$AO$2,0)) -> 10485.241 | I43: =+INDEX('Budget révisé'!$A$2:$AO$496,MATCH($A43,'Budget révisé'!$A$2:$A$496,0),MATCH(I$2,'Budget révisé'!$A$2:$AO$2,0)) -> 10485.241 | L43: =SUMIFS(BV_Data_An_Cour!$O:$O,BV_Data_An_Cour!$U:$U,$B43,BV_Data_An_Cour!$V:$V,$C43,BV_Data_An_Cour!$W:$W,L$2) -> 9351.04 | N43: =L43-I43 -> -1134.2006 | Q43: =SUMIFS(BV_Data_An_Prec!$O:$O,BV_Data_An_Prec!$U:$U,$B43,BV_Data_An_Prec!$V:$V,$C43,BV_Data_An_Prec!$W:$W,Q$2) -> 10372.43 | S43: =L43-Q43 -> -1021.39 | V43: 3 commis en moin
A44: =+B44&C44 -> Véhicules neufsSalaires autres | B44: =+$K$1 -> Véhicules neufs | C44: Salaires autres | F44: =+INDEX('Budget original'!$A$2:$AO$496,MATCH($A44,'Budget original'!$A$2:$A$496,0),MATCH(F$2,'Budget original'!$A$2:$AO$2,0)) -> 6607.207 | I44: =+INDEX('Budget révisé'!$A$2:$AO$496,MATCH($A44,'Budget révisé'!$A$2:$A$496,0),MATCH(I$2,'Budget révisé'!$A$2:$AO$2,0)) -> 6607.207 | L44: =SUMIFS(BV_Data_An_Cour!$O:$O,BV_Data_An_Cour!$U:$U,$B44,BV_Data_An_Cour!$V:$V,$C44,BV_Data_An_Cour!$W:$W,L$2) -> 7584.35 | N44: =L44-I44 -> 977.14301 | Q44: =SUMIFS(BV_Data_An_Prec!$O:$O,BV_Data_An_Prec!$U:$U,$B44,BV_Data_An_Prec!$V:$V,$C44,BV_Data_An_Prec!$W:$W,Q$2) -> 4969.02 | S44: =L44-Q44 -> 2615.33
A45: =+B45&C45 -> Véhicules neufsSalaires spécialistes | B45: =+$K$1 -> Véhicules neufs | C45: Salaires spécialistes | F45: =+INDEX('Budget original'!$A$2:$AO$496,MATCH($A45,'Budget original'!$A$2:$A$496,0),MATCH(F$2,'Budget original'!$A$2:$AO$2,0)) -> 0 | I45: =+INDEX('Budget révisé'!$A$2:$AO$496,MATCH($A45,'Budget révisé'!$A$2:$A$496,0),MATCH(I$2,'Budget révisé'!$A$2:$AO$2,0)) -> 0 | L45: =SUMIFS(BV_Data_An_Cour!$O:$O,BV_Data_An_Cour!$U:$U,$B45,BV_Data_An_Cour!$V:$V,$C45,BV_Data_An_Cour!$W:$W,L$2) -> 0 | N45: =L45-I45 -> 0 | Q45: =SUMIFS(BV_Data_An_Prec!$O:$O,BV_Data_An_Prec!$U:$U,$B45,BV_Data_An_Prec!$V:$V,$C45,BV_Data_An_Prec!$W:$W,Q$2) -> 0 | S45: =L45-Q45 -> 0
A46: =+B46&C46 -> Véhicules neufs[...] | B46: =+$K$1 -> Véhicules neufs | C46: [...] | F46: =+INDEX('Budget original'!$A$2:$AO$496,MATCH($A46,'Budget original'!$A$2:$A$496,0),MATCH(F$2,'Budget original'!$A$2:$AO$2,0)) -> 0 | I46: =+INDEX('Budget révisé'!$A$2:$AO$496,MATCH($A46,'Budget révisé'!$A$2:$A$496,0),MATCH(I$2,'Budget révisé'!$A$2:$AO$2,0)) -> 0 | L46: =SUMIFS(BV_Data_An_Cour!$O:$O,BV_Data_An_Cour!$U:$U,$B46,BV_Data_An_Cour!$V:$V,$C46,BV_Data_An_Cour!$W:$W,L$2) -> 0 | N46: =L46-I46 -> 0 | Q46: =SUMIFS(BV_Data_An_Prec!$O:$O,BV_Data_An_Prec!$U:$U,$B46,BV_Data_An_Prec!$V:$V,$C46,BV_Data_An_Prec!$W:$W,Q$2) -> 0 | S46: =L46-Q46 -> 0
A47: =+B47&C47 -> Véhicules neufs[...] | B47: =+$K$1 -> Véhicules neufs | C47: [...] | F47: =+INDEX('Budget original'!$A$2:$AO$496,MATCH($A47,'Budget original'!$A$2:$A$496,0),MATCH(F$2,'Budget original'!$A$2:$AO$2,0)) -> 0 | I47: =+INDEX('Budget révisé'!$A$2:$AO$496,MATCH($A47,'Budget révisé'!$A$2:$A$496,0),MATCH(I$2,'Budget révisé'!$A$2:$AO$2,0)) -> 0 | L47: =SUMIFS(BV_Data_An_Cour!$O:$O,BV_Data_An_Cour!$U:$U,$B47,BV_Data_An_Cour!$V:$V,$C47,BV_Data_An_Cour!$W:$W,L$2) -> 0 | N47: =L47-I47 -> 0 | Q47: =SUMIFS(BV_Data_An_Prec!$O:$O,BV_Data_An_Prec!$U:$U,$B47,BV_Data_An_Prec!$V:$V,$C47,BV_Data_An_Prec!$W:$W,Q$2) -> 0 | S47: =L47-Q47 -> 0
A48: =+B48&C48 -> Véhicules neufs[...] | B48: =+$K$1 -> Véhicules neufs | C48: [...] | F48: =+INDEX('Budget original'!$A$2:$AO$496,MATCH($A48,'Budget original'!$A$2:$A$496,0),MATCH(F$2,'Budget original'!$A$2:$AO$2,0)) -> 0 | I48: =+INDEX('Budget révisé'!$A$2:$AO$496,MATCH($A48,'Budget révisé'!$A$2:$A$496,0),MATCH(I$2,'Budget révisé'!$A$2:$AO$2,0)) -> 0 | L48: =SUMIFS(BV_Data_An_Cour!$O:$O,BV_Data_An_Cour!$U:$U,$B48,BV_Data_An_Cour!$V:$V,$C48,BV_Data_An_Cour!$W:$W,L$2) -> 0 | N48: =L48-I48 -> 0 | Q48: =SUMIFS(BV_Data_An_Prec!$O:$O,BV_Data_An_Prec!$U:$U,$B48,BV_Data_An_Prec!$V:$V,$C48,BV_Data_An_Prec!$W:$W,Q$2) -> 0 | S48: =L48-Q48 -> 0
