Workbook
Name _Dates_Conc: [1]Dealers!$BF$37:$KA$63
Name _scen: '[1]Scen & Sens'!$E$26
Name _scen1: '[1]Scen & Sens'!$E$27
Name _scen2: '[1]Scen & Sens'!$E$28
Name _SCenarios: '[1]Scen & Sens'!$J$26:$O$26
Name _Sens1: '[1]Scen & Sens'!$F$9
Name _Sens2: '[1]Scen & Sens'!$F$10
Name _sensRes1: '[1]Scen & Sens'!$E$15
Name _sensRes2: '[1]Scen & Sens'!$E$16
Name _sensRes3: '[1]Scen & Sens'!$E$17
Name _sensRes4: '[1]Scen & Sens'!$E$18
Name _sensRes5: '[1]Scen & Sens'!$E$19
Name _sensRes6: '[1]Scen & Sens'!$E$20
Name _sensRes7: '[1]Scen & Sens'!$E$21
Name DateRange: [1]Volkswagen!$BF$6:$DY$6
Name Monetary_Unit: [1]Parameters!$B$15
Name Months: [1]Parameters!$E$9:$E$20
Name Rng_Dealers_Names: [1]!Tbl_Dealers[Dealer Name]
Name Rng_Dlr_Dates: [1]!Tbl_V_Dlr_Dates[Date]
Name Titre: [1]Front!$A$9

Sheet Paramètre
B3: VOLKS QUARTER | C3: Volks T3 2022
B6: BUDGET | F6: BUDGET RÉVISÉ | J6: ACTUAL | N6: LAST YEAR
B7: Ventes | C7: Profits bruts | D7: BAIIA | E7: EBIT | F7: Ventes | G7: Profits bruts | H7: BAIIA | I7: EBIT | J7: Ventes | K7: Profits bruts | L7: BAIIA | M7: EBIT | N7: Ventes | O7: Profits bruts | P7: BAIIA | Q7: EBIT
A8: CTRL | B8: =+B9-B10 -> #REF! | C8: =+C9-C10 -> #REF! | D8: =+D9-D10 -> #REF! | E8: =+E9-E10 -> #REF! | F8: =+F9-F10 -> #REF! | G8: =+G9-G10 -> #REF! | H8: =+H9-H10 -> #REF! | I8: =+I9-I10 -> #REF! | ... Q8: =+Q9-Q10 -> #REF!
A9: CONSO | B9: =+Conso!$Z$405 -> 15410876 | C9: =+Conso!$Z$406 -> 1937855.6 | D9: =+Conso!$Z$482 -> 599108.28 | E9: =+Conso!$Z$497 -> 575436.8 | F9: =+Conso!$AC$405 -> 15410876 | G9: =+Conso!$AC$406 -> 1937855.6 | H9: =+Conso!$AC$482 -> 599108.28 | I9: =+Conso!$AC$497 -> 575436.8 | J9: =+Conso!$AF$405 -> 16244538 | K9: =+Conso!$AF$406 -> 2131721.5 | L9: =+Conso!$AF$482 -> 790555.34 | M9: =+Conso!$AF$497 -> 776331.47 | N9: =+Conso!$AL$405 -> 16217057 | O9: =+Conso!$AL$406 -> 1882405.7 | P9: =+Conso!$AL$482 -> 621516.25 | Q9: =+Conso!$AL$497 -> 605825.37
A10: TOTAL | B10: =+SUM(B11:B13) -> #REF! | C10: =+SUM(C11:C13) -> #REF! | D10: =+SUM(D11:D13) -> #REF! | E10: =+SUM(E11:E13) -> #REF! | F10: =+SUM(F11:F13) -> #REF! | G10: =+SUM(G11:G13) -> #REF! | H10: =+SUM(H11:H13) -> #REF! | I10: =+SUM(I11:I13) -> #REF! | ... Q10: =+SUM(Q11:Q13) -> #REF!
A11: AUDI 1 | B11: =+#REF! -> #REF! | C11: =+#REF! -> #REF! | D11: =+#REF! -> #REF! | E11: =+#REF! -> #REF! | F11: =+#REF! -> #REF! | G11: =+#REF! -> #REF! | H11: =+#REF! -> #REF! | I11: =+#REF! -> #REF! | ... Q11: =+#REF! -> #REF!
A12: AUDI 2 | B12: =+#REF! -> #REF! | C12: =+#REF! -> #REF! | D12: =+#REF! -> #REF! | E12: =+#REF! -> #REF! | F12: =+#REF! -> #REF! | G12: =+#REF! -> #REF! | H12: =+#REF! -> #REF! | I12: =+#REF! -> #REF! | ... Q12: =+#REF! -> #REF!
A13: AUDI 3 | B13: =+#REF! -> #REF! | C13: =+#REF! -> #REF! | D13: =+#REF! -> #REF! | E13: =+#REF! -> #REF! | F13: =+#REF! -> #REF! | G13: =+#REF! -> #REF! | H13: =+#REF! -> #REF! | I13: =+#REF! -> #REF! | ... Q13: =+#REF! -> #REF!

Sheet Conso
C1: Conso | K1: Véhicules neufs | S1: =CONCATENATE("Réalisé"," ",Paramètre!$C$2," ",Paramètre!$C$3) -> Réalisé Volks T3 2022 | V1: BUDGET | W1: RÉVISÉ | X1: ACTUAL | Y1: LY
D2: X | E2: O | F2: U | G2: X | H2: O | I2: U
D3: BUDGET ORIGINAL | G3: BUDGET REVISE | J3: RÉALISATION | M3: ÉCART réel / révisé | O3: ANNÉE PRÉCÉDENTE | R3: ÉCART réel / original
D4: UNITE | E4: $P/UNITÉ | F4: $PROFITS | G4: UNITE | H4: $P/UNITÉ | I4: $PROFITS | J4: UNITE | K4: $P/UNITE | L4: $PROFITS | M4: UNITÉ | N4: $PROFITS | O4: UNITE | P4: $P/UNITE | Q4: $PROFITS | R4: UNITE | S4: $PROFITS | V4: =+SUM(V5:V398) -> 0 | W4: =+SUM(W5:W398) -> 0 | X4: =+SUM(X5:X398) -> 0 | Y4: =+SUM(Y5:Y398) -> 0
A5: =+B5&C5 -> Véhicules neufsVentes nettes | B5: =+$K$1 -> Véhicules neufs | C5: Ventes nettes | F5: =+SUM(START:END!F5) -> 9485067.2 | I5: =+SUM(START:END!I5) -> 9485067.2 | L5: =+SUM(START:END!L5) -> 8779737.5 | Q5: =+SUM(START:END!Q5) -> 9633112.6
A6: =+B6&C6 -> Véhicules neufsAutos détail | B6: =+$K$1 -> Véhicules neufs | C6: Autos détail | D6: =+SUM(START:END!D6) -> 48.375904 | E6: =IF(D6=0,0,F6/D6) -> 1450.6298 | F6: =+SUM(START:END!F6) -> 70175.526 | G6: =+SUM(START:END!G6) -> 48.375904 | H6: =IF(G6=0,0,I6/G6) -> 1450.6298 | I6: =+SUM(START:END!I6) -> 70175.526 | J6: =+SUM(START:END!J6) -> 50 | K6: =IF(J6=0,0,L6/J6) -> 2395.0896 | L6: =+SUM(START:END!L6) -> 119754.48 | M6: =J6-G6 -> 1.6240964 | N6: =L6-I6 -> 49578.954 | O6: =+SUM(START:END!O6) -> 83 | P6: =IF(O6=0,0,Q6/O6) -> 1209.0878 | Q6: =+SUM(START:END!Q6) -> 100354.29 | R6: =J6-O6 -> -33 | S6: =L6-Q6 -> 19400.19
A7: =+B7&C7 -> Véhicules neufsCamions détail | B7: =+$K$1 -> Véhicules neufs | C7: Camions détail | D7: =+SUM(START:END!D7) -> 167.01205 | E7: =IF(D7=0,0,F7/D7) -> 2081.8276 | F7: =+SUM(START:END!F7) -> 347690.29 | G7: =+SUM(START:END!G7) -> 167.01205 | H7: =IF(G7=0,0,I7/G7) -> 2081.8276 | I7: =+SUM(START:END!I7) -> 347690.29 | J7: =+SUM(START:END!J7) -> 120 | K7: =IF(J7=0,0,L7/J7) -> 2998.4707 | L7: =+SUM(START:END!L7) -> 359816.49 | M7: =J7-G7 -> -47.012048 | N7: =L7-I7 -> 12126.201 | O7: =+SUM(START:END!O7) -> 125 | P7: =IF(O7=0,0,Q7/O7) -> 2271.0883 | Q7: =+SUM(START:END!Q7) -> 283886.04 | R7: =J7-O7 -> -5 | S7: =L7-Q7 -> 75930.45
A8: =+B8&C8 -> Véhicules neufsSprinter | B8: =+$K$1 -> Véhicules neufs | C8: Sprinter | D8: =+SUM(START:END!D8) -> 0 | E8: =IF(D8=0,0,F8/D8) -> 0 | F8: =+SUM(START:END!F8) -> 0 | G8: =+SUM(START:END!G8) -> 0 | H8: =IF(G8=0,0,I8/G8) -> 0 | I8: =+SUM(START:END!I8) -> 0 | J8: =+SUM(START:END!J8) -> 0 | K8: =IF(J8=0,0,L8/J8) -> 0 | L8: =+SUM(START:END!L8) -> 0 | M8: =J8-G8 -> 0 | N8: =L8-I8 -> 0 | O8: =+SUM(START:END!O8) -> 0 | P8: =IF(O8=0,0,Q8/O8) -> 0 | Q8: =+SUM(START:END!Q8) -> 0 | R8: =J8-O8 -> 0 | S8: =L8-Q8 -> 0
A9: =+B9&C9 -> Véhicules neufsMoto détail | B9: =+$K$1 -> Véhicules neufs | C9: Moto détail | D9: =+SUM(START:END!D9) -> 0 | E9: =IF(D9=0,0,F9/D9) -> 0 | F9: =+SUM(START:END!F9) -> 0 | G9: =+SUM(START:END!G9) -> 0 | H9: =IF(G9=0,0,I9/G9) -> 0 | I9: =+SUM(START:END!I9) -> 0 | J9: =+SUM(START:END!J9) -> 0 | K9: =IF(J9=0,0,L9/J9) -> 0 | L9: =+SUM(START:END!L9) -> 0 | M9: =J9-G9 -> 0 | N9: =L9-I9 -> 0 | O9: =+SUM(START:END!O9) -> 0 | P9: =IF(O9=0,0,Q9/O9) -> 0 | Q9: =+SUM(START:END!Q9) -> 0 | R9: =J9-O9 -> 0 | S9: =L9-Q9 -> 0
A10: =+B10&C10 -> Véhicules neufs[...] | B10: =+$K$1 -> Véhicules neufs | C10: [...] | D10: =+SUM(START:END!D10) -> 0 | E10: =IF(D10=0,0,F10/D10) -> 0 | F10: =+SUM(START:END!F10) -> 0 | G10: =+SUM(START:END!G10) -> 0 | H10: =IF(G10=0,0,I10/G10) -> 0 | I10: =+SUM(START:END!I10) -> 0 | J10: =+SUM(START:END!J10) -> 0 | K10: =IF(J10=0,0,L10/J10) -> 0 | L10: =+SUM(START:END!L10) -> 0 | M10: =J10-G10 -> 0 | N10: =L10-I10 -> 0 | O10: =+SUM(START:END!O10) -> 0 | P10: =IF(O10=0,0,Q10/O10) -> 0 | Q10: =+SUM(START:END!Q10) -> 0 | R10: =J10-O10 -> 0 | S10: =L10-Q10 -> 0
A11: =+B11&C11 -> Véhicules neufs[...] | B11: =+$K$1 -> Véhicules neufs | C11: [...] | D11: =+SUM(START:END!D11) -> 0 | E11: =IF(D11=0,0,F11/D11) -> 0 | F11: =+SUM(START:END!F11) -> 0 | G11: =+SUM(START:END!G11) -> 0 | H11: =IF(G11=0,0,I11/G11) -> 0 | I11: =+SUM(START:END!I11) -> 0 | J11: =+SUM(START:END!J11) -> 0 | K11: =IF(J11=0,0,L11/J11) -> 0 | L11: =+SUM(START:END!L11) -> 0 | M11: =J11-G11 -> 0 | N11: =L11-I11 -> 0 | O11: =+SUM(START:END!O11) -> 0 | P11: =IF(O11=0,0,Q11/O11) -> 0 | Q11: =+SUM(START:END!Q11) -> 0 | R11: =J11-O11 -> 0 | S11: =L11-Q11 -> 0
A12: =+B12&C12 -> Véhicules neufs[...] | B12: =+$K$1 -> Véhicules neufs | C12: [...] | D12: =+SUM(START:END!D12) -> 0 | E12: =IF(D12=0,0,F12/D12) -> 0 | F12: =+SUM(START:END!F12) -> 0 | G12: =+SUM(START:END!G12) -> 0 | H12: =IF(G12=0,0,I12/G12) -> 0 | I12: =+SUM(START:END!I12) -> 0 | J12: =+SUM(START:END!J12) -> 0 | K12: =IF(J12=0,0,L12/J12) -> 0 | L12: =+SUM(START:END!L12) -> 0 | M12: =J12-G12 -> 0 | N12: =L12-I12 -> 0 | O12: =+SUM(START:END!O12) -> 0 | P12: =IF(O12=0,0,Q12/O12) -> 0 | Q12: =+SUM(START:END!Q12) -> 0 | R12: =J12-O12 -> 0 | S12: =L12-Q12 -> 0
A13: =+B13&C13 -> Véhicules neufsTotal Neufs | B13: =+$K$1 -> Véhicules neufs | C13: Total Neufs | D13: =+SUM(D6:D12) -> 215.38795 | E13: =IF(D13<=0,0,F13/D13) -> 1940.0612 | F13: =+SUM(F6:F12) -> 417865.81 | G13: =+SUM(G6:G12) -> 215.38795 | H13: =IF(G13<=0,0,I13/G13) -> 1940.0612 | I13: =+SUM(I6:I12) -> 417865.81 | J13: =+SUM(J6:J12) -> 170 | K13: =IF(J13<=0,0,L13/J13) -> 2821.0057 | L13: =+SUM(L6:L12) -> 479570.97 | M13: =+SUM(M6:M12) -> -45.387952 | N13: =+SUM(N6:N12) -> 61705.155 | O13: =+SUM(O6:O12) -> 208 | P13: =IF(O13<=0,0,Q13/O13) -> 1847.3093 | Q13: =+SUM(Q6:Q12) -> 384240.33 | R13: =+SUM(R6:R12) -> -38 | S13: =+SUM(S6:S12) -> 95330.64 | V13: =+SUM(START:END!D13)-D13 -> 0 | W13: =+SUM(START:END!G13)-G13 -> 0 | X13: =+SUM(START:END!J13)-J13 -> 0 | Y13: =+SUM(START:END!O13)-O13 -> 0
A14: =+B14&C14 -> Véhicules neufs | B14: =+$K$1 -> Véhicules neufs | M14: =IF(G13=0,0,M13/G13) -> -0.21072651 | N14: =IF(I13=0,0,N13/I13) -> 0.14766739 | R14: =R13/O13 -> -0.18269231 | S14: =IF(Q13=0,0,(S13/Q13)) -> 0.2481016
A15: =+B15&C15 -> Véhicules neufsEx-Démos et courtoisies | B15: =+$K$1 -> Véhicules neufs | C15: Ex-Démos et courtoisies | D15: =+SUM(START:END!D15) -> 20.156627 | E15: =IF(D15=0,0,F15/D15) -> 1386.1016 | F15: =+SUM(START:END!F15) -> 27939.133 | G15: =+SUM(START:END!G15) -> 20.156627 | H15: =IF(G15=0,0,I15/G15) -> 1386.1016 | I15: =+SUM(START:END!I15) -> 27939.133 | J15: =+SUM(START:END!J15) -> 6 | K15: =IF(J15=0,0,L15/J15) -> 3041.8483 | L15: =+SUM(START:END!L15) -> 18251.09 | M15: =J15-G15 -> -14.156627 | N15: =L15-I15 -> -9688.0426 | O15: =+SUM(START:END!O15) -> 27 | P15: =IF(O15=0,0,Q15/O15) -> 1456.8074 | Q15: =+SUM(START:END!Q15) -> 39333.8 | R15: =J15-O15 -> -21 | S15: =L15-Q15 -> -21082.71 | V15: =+SUM(START:END!D15)-D15 -> 0 | W15: =+SUM(START:END!G15)-G15 -> 0 | X15: =+SUM(START:END!J15)-J15 -> 0 | Y15: =+SUM(START:END!O15)-O15 -> 0
A16: =+B16&C16 -> Véhicules neufs | B16: =+$K$1 -> Véhicules neufs
A17: =+B17&C17 -> Véhicules neufsFlottes | B17: =+$K$1 -> Véhicules neufs | C17: Flottes | D17: =+SUM(START:END!D17) -> 3.6257901 | E17: =IF(D17=0,0,F17/D17) -> 1938.8732 | F17: =+SUM(START:END!F17) -> 7029.9472 | G17: =+SUM(START:END!G17) -> 3.6257901 | H17: =IF(G17=0,0,I17/G17) -> 1938.8732 | I17: =+SUM(START:END!I17) -> 7029.9472 | J17: =+SUM(START:END!J17) -> 9 | K17: =IF(J17=0,0,L17/J17) -> 2185.0778 | L17: =+SUM(START:END!L17) -> 19665.7 | M17: =J17-G17 -> 5.3742099 | N17: =L17-I17 -> 12635.753 | O17: =+SUM(START:END!O17) -> 1 | P17: =IF(O17=0,0,Q17/O17) -> 707.9 | Q17: =+SUM(START:END!Q17) -> 707.9 | R17: =J17-O17 -> 8 | S17: =L17-Q17 -> 18957.8 | V17: =+SUM(START:END!D17)-D17 -> 0 | W17: =+SUM(START:END!G17)-G17 -> 0 | X17: =+SUM(START:END!J17)-J17 -> 0 | Y17: =+SUM(START:END!O17)-O17 -> 0
A18: =+B18&C18 -> Véhicules neufs | B18: =+$K$1 -> Véhicules neufs
A19: =+B19&C19 -> Véhicules neufsRachat bail | B19: =+$K$1 -> Véhicules neufs | C19: Rachat bail | F19: =+SUM(START:END!F19) -> 16832.078 | I19: =+SUM(START:END!I19) -> 16832.078 | L19: =+SUM(START:END!L19) -> 47656.29 | N19: =L19-I19 -> 30824.212 | Q19: =+SUM(START:END!Q19) -> 19061.91 | R19: =O19-K19 -> 0 | S19: =L19-Q19 -> 28594.38
A20: =+B20&C20 -> Véhicules neufs | B20: =+$K$1 -> Véhicules neufs
A21: =+B21&C21 -> Véhicules neufsRev. Finances | B21: =+$K$1 -> Véhicules neufs | C21: Rev. Finances | D21: 0 | E21: =IF(D21=0,0,F21/D21) -> 0 | F21: =+SUM(START:END!F21) -> 7048.3801 | G21: 0 | H21: =IF(G21=0,0,I21/G21) -> 0 | I21: =+SUM(START:END!I21) -> 7048.3801 | K21: =IF(J13=0,0,L21/(J13+J15)) -> 194.34903 | L21: =+SUM(START:END!L21) -> 34205.43 | N21: =L21-I21 -> 27157.05 | P21: =IF(O13=0,0,Q21/(O13+O15)) -> 7.2280426 | Q21: =+SUM(START:END!Q21) -> 1698.59 | R21: =O21-K21 -> -194.34903 | S21: =L21-Q21 -> 32506.84
A22: =+B22&C22 -> Véhicules neufsRev. Protections | B22: =+$K$1 -> Véhicules neufs | C22: Rev. Protections | D22: 0 | E22: =IF(D22=0,0,F22/D22) -> 0 | F22: =+SUM(START:END!F22) -> 188499.12 | G22: 0 | H22: =IF(G22=0,0,I22/G22) -> 0 | I22: =+SUM(START:END!I22) -> 188499.12 | K22: =IF(J13=0,0,L22/(J13+J15)) -> 896.49438 | L22: =+SUM(START:END!L22) -> 157783.01 | N22: =L22-I22 -> -30716.106 | P22: =IF(O13=0,0,Q22/(O13+O15)) -> 864.27902 | Q22: =+SUM(START:END!Q22) -> 203105.57 | R22: =O22-K22 -> -896.49438 | S22: =L22-Q22 -> -45322.56
A23: =+B23&C23 -> Véhicules neufsRev. Autres | B23: =+$K$1 -> Véhicules neufs | C23: Rev. Autres | D23: 0 | E23: =IF(D23=0,0,F23/D23) -> 0 | F23: =+SUM(START:END!F23) -> 4665.3959 | G23: 0 | H23: =IF(G23=0,0,I23/G23) -> 0 | I23: =+SUM(START:END!I23) -> 4665.3959 | K23: =IF(J13=0,0,L23/(J13+J15)) -> 24.29125 | L23: =+SUM(START:END!L23) -> 4275.26 | N23: =L23-I23 -> -390.13594 | P23: =IF(O13=0,0,Q23/(O13+O15)) -> 20.335277 | Q23: =+SUM(START:END!Q23) -> 4778.79 | R23: =O23-K23 -> -24.29125 | S23: =L23-Q23 -> -503.53
A24: =+B24&C24 -> Véhicules neufsTotal F&I | B24: =+$K$1 -> Véhicules neufs | C24: Total F&I | D24: =+D15+D13 -> 235.54458 | E24: =IF(D24<=0,0,F24/D24) -> 850 | F24: =F21+F22+F23 -> 200212.89 | G24: =+G15+G13 -> 235.54458 | H24: =IF(G24<=0,0,I24/G24) -> 850 | I24: =I21+I22+I23 -> 200212.89 | J24: =+J15+J13 -> 176 | K24: =IF(J24<=0,0,L24/J24) -> 1115.1347 | L24: =L21+L22+L23 -> 196263.7 | M24: =J24-G24 -> -59.544578 | N24: =L24-I24 -> -3949.1916 | O24: =+O15+O13 -> 235 | P24: =IF(O24<=0,0,Q24/O24) -> 891.84234 | Q24: =Q21+Q22+Q23 -> 209582.95 | S24: =L24-Q24 -> -13319.25 | V24: =+SUM(START:END!D24)-D24 -> 0 | W24: =+SUM(START:END!G24)-G24 -> 0 | X24: =+SUM(START:END!J24)-J24 -> 0 | Y24: =+SUM(START:END!O24)-O24 -> 0
A25: =+B25&C25 -> Véhicules neufs | B25: =+$K$1 -> Véhicules neufs | N25: =IF(N24=0,0,N24/I24) -> -0.019724961 | S25: =IF(Q24=0,0,(S24/Q24)) -> -0.06355121
A26: =+B26&C26 -> Véhicules neufs | B26: =+$K$1 -> Véhicules neufs
A27: =+B27&C27 -> Véhicules neufsTotal Dépt. Neufs | B27: =+$K$1 -> Véhicules neufs | C27: Total Dépt. Neufs | D27: =+D13+D15+D17 -> 239.17037 | E27: =IF(D27<=0,0,F27/D27) -> 2800.8481 | F27: =F13+F17+F24+F19+F15 -> 669879.86 | G27: =+G13+G15+G17 -> 239.17037 | H27: =IF(G27<=0,0,I27/G27) -> 2800.8481 | I27: =I13+I17+I24+I19+I15 -> 669879.86 | J27: =+J13+J15+J17 -> 185 | K27: =IF(J27<=0,0,L27/J27) -> 4115.7176 | L27: =L13+L17+L24+L19+L15 -> 761407.75 | M27: =J27-G27 -> -54.170368 | N27: =L27-I27 -> 91527.886 | O27: =+O13+O15+O17 -> 236 | P27: =IF(O27<=0,0,Q27/O27) -> 2766.6394 | Q27: =Q13+Q17+Q24+Q19+Q15 -> 652926.89 | R27: =J27-O27 -> -51 | S27: =L27-Q27 -> 108480.86 | V27: =+SUM(START:END!D27)-D27 -> 0 | W27: =+SUM(START:END!G27)-G27 -> 0 | X27: =+SUM(START:END!J27)-J27 -> 0 | Y27: =+SUM(START:END!O27)-O27 -> 0
A28: =+B28&C28 -> Véhicules neufs | B28: =+$K$1 -> Véhicules neufs | M28: =M27/G27 -> -0.22649281 | N28: =N27/I27 -> 0.13663328 | R28: =R27/O27 -> -0.21610169 | S28: =IF(Q27=0,0,S27/Q27) -> 0.16614549
A29: =+B29&C29 -> Véhicules neufs | B29: =+$K$1 -> Véhicules neufs
A30: =+B30&C30 -> Véhicules neufsDEPENSES | B30: =+$K$1 -> Véhicules neufs | C30: DEPENSES
A31: =+B31&C31 -> Véhicules neufsComm. vendeurs | B31: =+$K$1 -> Véhicules neufs | C31: Comm. vendeurs | E31: =F31/D$24 -> 611.17523 | F31: =+SUM(START:END!F31) -> 143959.01 | H31: =I31/G$24 -> 611.17523 | I31: =+SUM(START:END!I31) -> 143959.01 | J31: =L31/L13 -> 0.30107775 | K31: =IF(L31=0,0,L31/J$24) -> 820.38722 | L31: =+SUM(START:END!L31) -> 144388.15 | N31: =L31-I31 -> 429.13706 | P31: =IF(Q31=0,0,Q31/O$24) -> 603.03817 | Q31: =+SUM(START:END!Q31) -> 141713.97 | S31: =L31-Q31 -> 2674.18
A32: =+B32&C32 -> Véhicules neufsComm. F&I | B32: =+$K$1 -> Véhicules neufs | C32: Comm. F&I | E32: =F32/D$24 -> 255 | F32: =+SUM(START:END!F32) -> 60063.867 | H32: =I32/G$24 -> 255 | I32: =+SUM(START:END!I32) -> 60063.867 | J32: =L32/L24 -> 0.35298519 | K32: =IF(L32=0,0,L32/J$24) -> 393.62602 | L32: =+SUM(START:END!L32) -> 69278.18 | N32: =L32-I32 -> 9214.3125 | P32: =IF(Q32=0,0,Q32/O$24) -> 263.91732 | Q32: =+SUM(START:END!Q32) -> 62020.57 | S32: =L32-Q32 -> 7257.61
A33: =+B33&C33 -> Véhicules neufsFrais de livraison | B33: =+$K$1 -> Véhicules neufs | C33: Frais de livraison | E33: =F33/D$24 -> 167.8493 | F33: =+SUM(START:END!F33) -> 39535.993 | H33: =I33/G$24 -> 167.8493 | I33: =+SUM(START:END!I33) -> 39535.993 | K33: =IF(L33=0,0,L33/J$24) -> 47.600852 | L33: =+SUM(START:END!L33) -> 8377.75 | N33: =L33-I33 -> -31158.243 | P33: =IF(Q33=0,0,Q33/O$24) -> 157.34409 | Q33: =+SUM(START:END!Q33) -> 36975.86 | S33: =L33-Q33 -> -28598.11
A34: =+B34&C34 -> Véhicules neufsService gratuit 1 | B34: =+$K$1 -> Véhicules neufs | C34: Service gratuit 1 | E34: =F34/D$24 -> 7.3548076 | F34: =+SUM(START:END!F34) -> 1732.3851 | H34: =I34/G$24 -> 7.3548076 | I34: =+SUM(START:END!I34) -> 1732.3851 | K34: =IF(L34=0,0,L34/J$24) -> 1.2465341 | L34: =+SUM(START:END!L34) -> 219.39 | N34: =L34-I34 -> -1512.9951 | P34: =IF(Q34=0,0,Q34/O$24) -> 11.313191 | Q34: =+SUM(START:END!Q34) -> 2658.6 | S34: =L34-Q34 -> -2439.21
A35: =+B35&C35 -> Véhicules neufsEntretien stock | B35: =+$K$1 -> Véhicules neufs | C35: Entretien stock | E35: =F35/D$24 -> 17.733118 | F35: =+SUM(START:END!F35) -> 4176.9399 | H35: =I35/G$24 -> 17.733118 | I35: =+SUM(START:END!I35) -> 4176.9399 | K35: =IF(L35=0,0,L35/J$24) -> 98.528693 | L35: =+SUM(START:END!L35) -> 17341.05 | N35: =L35-I35 -> 13164.11 | P35: =IF(Q35=0,0,Q35/O$24) -> 18.307191 | Q35: =+SUM(START:END!Q35) -> 4302.19 | S35: =L35-Q35 -> 13038.86
A36: =+B36&C36 -> Véhicules neufsPublicité 1 | B36: =+$K$1 -> Véhicules neufs | C36: Publicité 1 | E36: =F36/D$24 -> 195.93765 | F36: =+SUM(START:END!F36) -> 46152.052 | H36: =I36/G$24 -> 195.93765 | I36: =+SUM(START:END!I36) -> 46152.052 | K36: =IF(L36=0,0,L36/J$24) -> 87.593295 | L36: =+SUM(START:END!L36) -> 15416.42 | N36: =L36-I36 -> -30735.632 | P36: =IF(Q36=0,0,Q36/O$24) -> 119.74332 | Q36: =+SUM(START:END!Q36) -> 28139.68 | S36: =L36-Q36 -> -12723.26
A37: =+B37&C37 -> Véhicules neufsIntérêt de gros | B37: =+$K$1 -> Véhicules neufs | C37: Intérêt de gros | E37: =F37/D$24 -> 98.977128 | F37: =+SUM(START:END!F37) -> 23313.526 | H37: =I37/G$24 -> 98.977128 | I37: =+SUM(START:END!I37) -> 23313.526 | K37: =IF(L37=0,0,L37/J$24) -> 57.844545 | L37: =+SUM(START:END!L37) -> 10180.64 | N37: =L37-I37 -> -13132.886 | P37: =IF(Q37=0,0,Q37/O$24) -> 151.65362 | Q37: =+SUM(START:END!Q37) -> 35638.6 | S37: =L37-Q37 -> -25457.96
A38: =+B38&C38 -> Véhicules neufs[...] | B38: =+$K$1 -> Véhicules neufs | C38: [...] | E38: =F38/D$24 -> 0 | F38: =+SUM(START:END!F38) -> 0 | H38: =I38/G$24 -> 0 | I38: =+SUM(START:END!I38) -> 0 | K38: =IF(L38=0,0,L38/J$24) -> 0 | L38: =+SUM(START:END!L38) -> 0 | N38: =L38-I38 -> 0 | P38: =IF(Q38=0,0,Q38/O$24) -> 0 | Q38: =+SUM(START:END!Q38) -> 0 | S38: =L38-Q38 -> 0
A39: =+B39&C39 -> Véhicules neufs[...] | B39: =+$K$1 -> Véhicules neufs | C39: [...] | E39: =F39/D$24 -> 0 | F39: =+SUM(START:END!F39) -> 0 | H39: =I39/G$24 -> 0 | I39: =+SUM(START:END!I39) -> 0 | K39: =IF(L39=0,0,L39/J$24) -> 0 | L39: =+SUM(START:END!L39) -> 0 | N39: =L39-I39 -> 0 | P39: =IF(Q39=0,0,Q39/O$24) -> 0 | Q39: =+SUM(START:END!Q39) -> 0 | S39: =L39-Q39 -> 0
A40: =+B40&C40 -> Véhicules neufs[...] | B40: =+$K$1 -> Véhicules neufs | C40: [...] | E40: =F40/D$24 -> 0 | F40: =+SUM(START:END!F40) -> 0 | H40: =I40/G$24 -> 0 | I40: =+SUM(START:END!I40) -> 0 | K40: =IF(L40=0,0,L40/J$24) -> 0 | L40: =+SUM(START:END!L40) -> 0 | N40: =L40-I40 -> 0 | P40: =IF(Q40=0,0,Q40/O$24) -> 0 | Q40: =+SUM(START:END!Q40) -> 0 | S40: =L40-Q40 -> 0
A41: =+B41&C41 -> Véhicules neufsTOTAL VARIABLES | B41: =+$K$1 -> Véhicules neufs | C41: TOTAL VARIABLES | D41: % brut | E41: =F41/F$27 -> 0.47610593 | F41: =SUM(F31:F40) -> 318933.78 | G41: % brut | H41: =I41/I$27 -> 0.47610593 | I41: =SUM(I31:I40) -> 318933.78 | J41: % brut | K41: =L41/L$27 -> 0.34830428 | L41: =SUM(L31:L40) -> 265201.58 | N41: =SUM(N31:N40) -> -53732.196 | O41: % brut | P41: =Q41/Q$27 -> 0.47700512 | Q41: =SUM(Q31:Q40) -> 311449.47 | S41: =L41-Q41 -> -46247.89
A42: =+B42&C42 -> Véhicules neufsSalaires cadres | B42: =+$K$1 -> Véhicules neufs | C42: Salaires cadres | F42: =+SUM(START:END!F42) -> 47658.783 | G42: =I41/(I27+I83) -> 0.31118067 | I42: =+SUM(START:END!I42) -> 47658.783 | J42: =L41/(L27+L83) -> 0.24932276 | L42: =+SUM(START:END!L42) -> 56096.98 | N42: =L42-I42 -> 8438.1972 | Q42: =+SUM(START:END!Q42) -> 42398.82
A43: =+B43&C43 -> Véhicules neufsSalaires commis | B43: =+$K$1 -> Véhicules neufs | C43: Salaires commis | F43: =+SUM(START:END!F43) -> 29466.083 | I43: =+SUM(START:END!I43) -> 29466.083 | L43: =+SUM(START:END!L43) -> 21785.59 | N43: =L43-I43 -> -7680.4933 | Q43: =+SUM(START:END!Q43) -> 27565.74 | S43: =L43-Q43 -> -5780.15
A44: =+B44&C44 -> Véhicules neufsSalaires autres | B44: =+$K$1 -> Véhicules neufs | C44: Salaires autres | F44: =+SUM(START:END!F44) -> 26764.207 | I44: =+SUM(START:END!I44) -> 26764.207 | L44: =+SUM(START:END!L44) -> 12958.3 | N44: =L44-I44 -> -13805.907 | Q44: =+SUM(START:END!Q44) -> 28632.13 | S44: =L44-Q44 -> -15673.83
A45: =+B45&C45 -> Véhicules neufsSalaires spécialistes | B45: =+$K$1 -> Véhicules neufs | C45: Salaires spécialistes | F45: =+SUM(START:END!F45) -> 0 | I45: =+SUM(START:END!I45) -> 0 | L45: =+SUM(START:END!L45) -> 0 | N45: =L45-I45 -> 0 | Q45: =+SUM(START:END!Q45) -> 0 | S45: =L45-Q45 -> 0
A46: =+B46&C46 -> Véhicules neufs[...] | B46: =+$K$1 -> Véhicules neufs | C46: [...] | F46: =+SUM(START:END!F46) -> 0 | I46: =+SUM(START:END!I46) -> 0 | L46: =+SUM(START:END!L46) -> 0 | N46: =L46-I46 -> 0 | Q46: =+SUM(START:END!Q46) -> 0 | S46: =L46-Q46 -> 0
A47: =+B47&C47 -> Véhicules neufs[...] | B47: =+$K$1 -> Véhicules neufs | C47: [...] | F47: =+SUM(START:END!F47) -> 0 | I47: =+SUM(START:END!I47) -> 0 | L47: =+SUM(START:END!L47) -> 0 | N47: =L47-I47 -> 0 | Q47: =+SUM(START:END!Q47) -> 0 | S47: =L47-Q47 -> 0
A48: =+B48&C48 -> Véhicules neufs[...] | B48: =+$K$1 -> Véhicules neufs | C48: [...] | F48: =+SUM(START:END!F48) -> 0 | I48: =+SUM(START:END!I48) -> 0 | L48: =+SUM(START:END!L48) -> 0 | N48: =L48-I48 -> 0 | Q48: =+SUM(START:END!Q48) -> 0 | S48: =L48-Q48 -> 0
A49: =+B49&C49 -> Véhicules neufsSalaires en absences | B49: =+$K$1 -> Véhicules neufs | C49: Salaires en absences | F49: =+SUM(START:END!F49) -> 37450.801 | I49: =+SUM(START:END!I49) -> 37450.801 | L49: =+SUM(START:END!L49) -> 51999.4 | N49: =L49-I49 -> 14548.599 | Q49: =+SUM(START:END!Q49) -> 48179.92 | S49: =L49-Q49 -> 3819.48
A50: =+B50&C50 -> Véhicules neufsDéduction à la source | B50: =+$K$1 -> Véhicules neufs | C50: Déduction à la source | F50: =+SUM(START:END!F50) -> 33541.032 | I50: =+SUM(START:END!I50) -> 33541.032 | L50: =+SUM(START:END!L50) -> 49227.53 | N50: =L50-I50 -> 15686.498 | Q50: =+SUM(START:END!Q50) -> 34215.71 | S50: =L50-Q50 -> 15011.82
A51: =+B51&C51 -> Véhicules neufsBénéfices marginaux | B51: =+$K$1 -> Véhicules neufs | C51: Bénéfices marginaux | F51: =+SUM(START:END!F51) -> 26635.525 | I51: =+SUM(START:END!I51) -> 26635.525 | L51: =+SUM(START:END!L51) -> 18228.37 | N51: =L51-I51 -> -8407.155 | Q51: =+SUM(START:END!Q51) -> 24521.25 | S51: =L51-Q51 -> -6292.88
A52: =+B52&C52 -> Véhicules neufsCsst | B52: =+$K$1 -> Véhicules neufs | C52: Csst | F52: =+SUM(START:END!F52) -> 10851.51 | I52: =+SUM(START:END!I52) -> 10851.51 | L52: =+SUM(START:END!L52) -> 10960.38 | N52: =L52-I52 -> 108.86981 | Q52: =+SUM(START:END!Q52) -> 5702.62 | S52: =L52-Q52 -> 5257.76
A53: =+B53&C53 -> Véhicules neufs[...] | B53: =+$K$1 -> Véhicules neufs | C53: [...] | F53: =+SUM(START:END!F53) -> 0 | I53: =+SUM(START:END!I53) -> 0 | L53: =+SUM(START:END!L53) -> 0 | N53: =L53-I53 -> 0 | Q53: =+SUM(START:END!Q53) -> 0 | S53: =L53-Q53 -> 0
A54: =+B54&C54 -> Véhicules neufsTOTAL PERSONNEL | B54: =+$K$1 -> Véhicules neufs | C54: TOTAL PERSONNEL | D54: % brut | E54: =F54/F$27 -> 0.31702392 | F54: =+SUM(F42:F53) -> 212367.94 | G54: % brut | H54: =I54/I$27 -> 0.31702392 | I54: =+SUM(I42:I53) -> 212367.94 | J54: % brut | K54: =L54/L$27 -> 0.29058878 | L54: =+SUM(L42:L53) -> 221256.55 | N54: =+SUM(N42:N53) -> 8888.6094 | O54: % brut | P54: =Q54/Q$27 -> 0.32349133 | Q54: =+SUM(Q42:Q53) -> 211216.19 | S54: =+SUM(S42:S53) -> -3657.8
A55: =+B55&C55 -> Véhicules neufsPublicité 2 | B55: =+$K$1 -> Véhicules neufs | C55: Publicité 2 | F55: =+SUM(START:END!F55) -> 0 | G55: =I54/(I27+I83) -> 0.20720539 | I55: =+SUM(START:END!I55) -> 0 | J55: =L54/(L27+L83) -> 0.20800892 | L55: =+SUM(START:END!L55) -> 0 | N55: =L55-I55 -> 0 | Q55: =+SUM(START:END!Q55) -> 0 | S55: =L55-Q55 -> 0
A56: =+B56&C56 -> Véhicules neufsService gratuit 2 | B56: =+$K$1 -> Véhicules neufs | C56: Service gratuit 2 | F56: =+SUM(START:END!F56) -> 0 | I56: =+SUM(START:END!I56) -> 0 | L56: =+SUM(START:END!L56) -> 0 | N56: =L56-I56 -> 0 | Q56: =+SUM(START:END!Q56) -> 0 | S56: =L56-Q56 -> 0
A57: =+B57&C57 -> Véhicules neufsFrais véhicules de cie | B57: =+$K$1 -> Véhicules neufs | C57: Frais véhicules de cie | F57: =+SUM(START:END!F57) -> 21968.82 | I57: =+SUM(START:END!I57) -> 21968.82 | L57: =+SUM(START:END!L57) -> 24962.74 | N57: =L57-I57 -> 2993.92 | Q57: =+SUM(START:END!Q57) -> 25259.95 | S57: =L57-Q57 -> -297.21
A58: =+B58&C58 -> Véhicules neufsInformatique | B58: =+$K$1 -> Véhicules neufs | C58: Informatique | F58: =+SUM(START:END!F58) -> 20502.597 | I58: =+SUM(START:END!I58) -> 20502.597 | L58: =+SUM(START:END!L58) -> 23611.17 | N58: =L58-I58 -> 3108.5735 | Q58: =+SUM(START:END!Q58) -> 16456.89 | S58: =L58-Q58 -> 7154.28
A59: =+B59&C59 -> Véhicules neufsFrais de déplacement | B59: =+$K$1 -> Véhicules neufs | C59: Frais de déplacement | F59: =+SUM(START:END!F59) -> 2376.4254 | I59: =+SUM(START:END!I59) -> 2376.4254 | L59: =+SUM(START:END!L59) -> 3663.08 | N59: =L59-I59 -> 1286.6546 | Q59: =+SUM(START:END!Q59) -> 2310.99 | S59: =L59-Q59 -> 1352.09
A60: =+B60&C60 -> Véhicules neufsServices extérieurs | B60: =+$K$1 -> Véhicules neufs | C60: Services extérieurs | F60: =+SUM(START:END!F60) -> 19645.697 | I60: =+SUM(START:END!I60) -> 19645.697 | L60: =+SUM(START:END!L60) -> 20308.14 | N60: =L60-I60 -> 662.44347 | Q60: =+SUM(START:END!Q60) -> 19319.63 | S60: =L60-Q60 -> 988.51
A61: =+B61&C61 -> Véhicules neufsFournitures autres | B61: =+$K$1 -> Véhicules neufs | C61: Fournitures autres | F61: =+SUM(START:END!F61) -> 275.4688 | I61: =+SUM(START:END!I61) -> 275.4688 | L61: =+SUM(START:END!L61) -> 154.98 | N61: =L61-I61 -> -120.4888 | Q61: =+SUM(START:END!Q61) -> 335.91 | S61: =L61-Q61 -> -180.93
A62: =+B62&C62 -> Véhicules neufsUniformes | B62: =+$K$1 -> Véhicules neufs | C62: Uniformes | F62: =+SUM(START:END!F62) -> 146.37688 | I62: =+SUM(START:END!I62) -> 146.37688 | L62: =+SUM(START:END!L62) -> 0 | N62: =L62-I62 -> -146.37688 | Q62: =+SUM(START:END!Q62) -> 0 | S62: =L62-Q62 -> 0
A63: =+B63&C63 -> Véhicules neufsPapeterie | B63: =+$K$1 -> Véhicules neufs | C63: Papeterie | F63: =+SUM(START:END!F63) -> 1958.593 | I63: =+SUM(START:END!I63) -> 1958.593 | L63: =+SUM(START:END!L63) -> 2582.64 | N63: =L63-I63 -> 624.04704 | Q63: =+SUM(START:END!Q63) -> 1478.21 | S63: =L63-Q63 -> 1104.43
A64: =+B64&C64 -> Véhicules neufsTéléphone | B64: =+$K$1 -> Véhicules neufs | C64: Téléphone | F64: =+SUM(START:END!F64) -> 904.39358 | I64: =+SUM(START:END!I64) -> 904.39358 | L64: =+SUM(START:END!L64) -> 761.74 | N64: =L64-I64 -> -142.65358 | Q64: =+SUM(START:END!Q64) -> 973.45 | S64: =L64-Q64 -> -211.71
A65: =+B65&C65 -> Véhicules neufsFrais postaux | B65: =+$K$1 -> Véhicules neufs | C65: Frais postaux | F65: =+SUM(START:END!F65) -> 482.75122 | I65: =+SUM(START:END!I65) -> 482.75122 | L65: =+SUM(START:END!L65) -> 486.82 | N65: =L65-I65 -> 4.06878 | Q65: =+SUM(START:END!Q65) -> 643.79 | S65: =L65-Q65 -> -156.97
A66: =+B66&C66 -> Véhicules neufsDivers | B66: =+$K$1 -> Véhicules neufs | C66: Divers | F66: =+SUM(START:END!F66) -> 2328.7008 | I66: =+SUM(START:END!I66) -> 2328.7008 | L66: =+SUM(START:END!L66) -> 354.51 | N66: =L66-I66 -> -1974.1908 | Q66: =+SUM(START:END!Q66) -> 1971.65 | S66: =L66-Q66 -> -1617.14
A67: =+B67&C67 -> Véhicules neufsFormation | B67: =+$K$1 -> Véhicules neufs | C67: Formation | F67: =+SUM(START:END!F67) -> 3459.7688 | I67: =+SUM(START:END!I67) -> 3459.7688 | L67: =+SUM(START:END!L67) -> 3451.57 | N67: =L67-I67 -> -8.1988 | Q67: =+SUM(START:END!Q67) -> 2410.05 | S67: =L67-Q67 -> 1041.52
... A71: =+B71&C71 -> Véhicules neufs[...] | B71: =+$K$1 -> Véhicules neufs | C71: [...] | F71: =+SUM(START:END!F71) -> 0 | I71: =+SUM(START:END!I71) -> 0 | L71: =+SUM(START:END!L71) -> 0 | N71: =L71-I71 -> 0 | Q71: =+SUM(START:END!Q71) -> 0 | S71: =L71-Q71 -> 0
A72: =+B72&C72 -> Véhicules neufsTOTAL SEMI-FIXES | B72: =+$K$1 -> Véhicules neufs | C72: TOTAL SEMI-FIXES | D72: % brut | E72: =F72/F$27 -> 0.11867328 | F72: =+SUM(F55:F71) -> 79496.843 | G72: % brut | H72: =I72/I$27 -> 0.11867328 | I72: =+SUM(I55:I71) -> 79496.843 | J72: % brut | K72: =L72/L$27 -> 0.12035262 | L72: =+SUM(L55:L71) -> 91637.42 | N72: =+SUM(N55:N71) -> 12140.577 | O72: % brut | P72: =Q72/Q$27 -> 0.12263386 | Q72: =+SUM(Q55:Q71) -> 80070.943 | S72: =+SUM(S55:S71) -> 11566.477
A73: =+B73&C73 -> Véhicules neufs | B73: =+$K$1 -> Véhicules neufs
A74: =+B74&C74 -> Véhicules neufsTOTAL DES DÉPENSES | B74: =+$K$1 -> Véhicules neufs | C74: TOTAL DES DÉPENSES | D74: % brut | E74: =F74/F$27 -> 0.91180313 | F74: =F41+F54+F72 -> 610798.56 | G74: % brut | H74: =I74/I$27 -> 0.91180313 | I74: =I41+I54+I72 -> 610798.56 | J74: % brut | K74: =L74/L$27 -> 0.75924569 | L74: =L41+L54+L72 -> 578095.55 | N74: =L74-I74 -> -32703.01 | O74: % brut | P74: =Q74/Q$27 -> 0.92313031 | Q74: =Q41+Q54+Q72 -> 602736.6 | S74: =L74-Q74 -> -24641.053
A75: =+B75&C75 -> Véhicules neufsProgramme neuf 1 | B75: =+$K$1 -> Véhicules neufs | C75: Programme neuf 1 | F75: =+SUM(START:END!F75) -> 19143.9 | I75: =+SUM(START:END!I75) -> 19143.9 | L75: =+SUM(START:END!L75) -> 0 | N75: =L75-I75 -> -19143.9 | Q75: =+SUM(START:END!Q75) -> 28500
A76: =+B76&C76 -> Véhicules neufsProgramme neuf 2 | B76: =+$K$1 -> Véhicules neufs | C76: Programme neuf 2 | F76: =+SUM(START:END!F76) -> 0 | I76: =+SUM(START:END!I76) -> 0 | L76: =+SUM(START:END!L76) -> 0 | N76: =L76-I76 -> 0 | Q76: =+SUM(START:END!Q76) -> 0 | S76: =L76-Q76 -> 0
A77: =+B77&C77 -> Véhicules neufsProgramme neuf 3 | B77: =+$K$1 -> Véhicules neufs | C77: Programme neuf 3 | F77: =+SUM(START:END!F77) -> 0 | I77: =+SUM(START:END!I77) -> 0 | L77: =+SUM(START:END!L77) -> 0 | N77: =L77-I77 -> 0 | Q77: =+SUM(START:END!Q77) -> 0 | S77: =L77-Q77 -> 0
A78: =+B78&C78 -> Véhicules neufsHoldbacks | B78: =+$K$1 -> Véhicules neufs | C78: Holdbacks | F78: =+SUM(START:END!F78) -> 250005.27 | I78: =+SUM(START:END!I78) -> 250005.27 | L78: =+SUM(START:END!L78) -> 233500.07 | N78: =L78-I78 -> -16505.205 | Q78: =+SUM(START:END!Q78) -> 214826.85 | S78: =L78-Q78 -> 18673.22
A79: =+B79&C79 -> Véhicules neufs[...] | B79: =+$K$1 -> Véhicules neufs | C79: [...] | F79: =+SUM(START:END!F79) -> 0 | I79: =+SUM(START:END!I79) -> 0 | L79: =+SUM(START:END!L79) -> 0 | N79: =L79-I79 -> 0 | Q79: =+SUM(START:END!Q79) -> 0 | S79: =L79-Q79 -> 0
A80: =+B80&C80 -> Véhicules neufs[...] | B80: =+$K$1 -> Véhicules neufs | C80: [...] | F80: =+SUM(START:END!F80) -> 0 | I80: =+SUM(START:END!I80) -> 0 | L80: =+SUM(START:END!L80) -> 0 | N80: =L80-I80 -> 0 | Q80: =+SUM(START:END!Q80) -> 0 | S80: =L80-Q80 -> 0
A81: =+B81&C81 -> Véhicules neufs[...] | B81: =+$K$1 -> Véhicules neufs | C81: [...] | F81: =+SUM(START:END!F81) -> 0 | I81: =+SUM(START:END!I81) -> 0 | L81: =+SUM(START:END!L81) -> 0 | N81: =L81-I81 -> 0 | Q81: =+SUM(START:END!Q81) -> 0 | S81: =L81-Q81 -> 0
A82: =+B82&C82 -> Véhicules neufsFrais administration | B82: =+$K$1 -> Véhicules neufs | C82: Frais administration | F82: =+SUM(START:END!F82) -> 85886.079 | I82: =+SUM(START:END!I82) -> 85886.079 | L82: =+SUM(START:END!L82) -> 68780 | N82: =L82-I82 -> -17106.079 | Q82: =+SUM(START:END!Q82) -> 69093.69 | S82: =L82-Q82 -> -313.69
A83: =+B83&C83 -> Véhicules neufsAUTRES REVENUS | B83: =+$K$1 -> Véhicules neufs | C83: AUTRES REVENUS | F83: =+SUM(F75:F82) -> 355035.25 | I83: =+SUM(I75:I82) -> 355035.25 | L83: =+SUM(L75:L82) -> 302280.07 | N83: =+SUM(N75:N82) -> -52755.184 | Q83: =+SUM(Q75:Q82) -> 312420.54 | S83: =+SUM(S75:S82) -> 18359.53
A84: =+B84&C84 -> Véhicules neufs | B84: =+$K$1 -> Véhicules neufs
A85: =+B85&C85 -> Véhicules neufsPROFIT DÉPARTEMENTAL | B85: =+$K$1 -> Véhicules neufs | C85: PROFIT DÉPARTEMENTAL | F85: =F27-F74+F83 -> 414116.56 | I85: =I27-I74+I83 -> 414116.56 | L85: =L27-L74+L83 -> 485592.27 | N85: =N27-N41-N54-N72+N83 -> 71475.711 | Q85: =Q27-Q74+Q83 -> 362610.83 | S85: =S27-S41-S54-S72+S83 -> 165179.6
C89: =C1 -> Conso | K89: Véhicules usagés | S89: =$S$1 -> Réalisé Volks T3 2022
D91: BUDGET ORIGINAL | G91: BUDGET RÉVISÉ | J91: RÉALISATION | M91: ÉCART réel / révisé | O91: ANNÉE PRÉCÉDENTE | R91: ÉCART réel / original
D92: UNITE | E92: $P/UNITÉ | F92: $PROFITS | G92: UNITE | H92: $P/UNITÉ | I92: $PROFITS | J92: UNITE | K92: $P/UNITE | L92: $PROFITS | M92: UNITÉ | N92: $PROFITS | O92: UNITE | P92: $P/UNITE | Q92: $PROFITS | R92: UNITE | S92: $PROFITS
A93: =+B93&C93 -> Véhicules usagésVentes nettes | B93: Véhicules usagés | C93: Ventes nettes | F93: =+SUM(START:END!F93) -> 3821698.7 | I93: =+SUM(START:END!I93) -> 3821698.7 | L93: =+SUM(START:END!L93) -> 5180887.5 | Q93: =+SUM(START:END!Q93) -> 4675670.9
A94: =+B94&C94 -> Véhicules usagésCertifié | B94: Véhicules usagés | C94: Certifié | D94: =+SUM(START:END!D94) -> 116.65049 | E94: =IF(D94=0,0,F94/D94) -> 1300 | F94: =+SUM(START:END!F94) -> 151645.63 | G94: =+SUM(START:END!G94) -> 116.65049 | H94: =IF(G94=0,0,I94/G94) -> 1300 | I94: =+SUM(START:END!I94) -> 151645.63 | J94: =+SUM(START:END!J94) -> 110 | K94: =IF(J94=0,0,L94/J94) -> 1759.0522 | L94: =+SUM(START:END!L94) -> 193495.74 | M94: =J94-G94 -> -6.6504854 | N94: =L94-I94 -> 41850.109 | O94: =+SUM(START:END!O94) -> 114 | P94: =IF(O94=0,0,Q94/O94) -> 1370.7451 | Q94: =+SUM(START:END!Q94) -> 156264.94 | R94: =J94-O94 -> -4 | S94: =L94-Q94 -> 37230.8
A95: =+B95&C95 -> Véhicules usagésNon Certifié | B95: Véhicules usagés | C95: Non Certifié | D95: =+SUM(START:END!D95) -> 6.5533981 | E95: =IF(D95=0,0,F95/D95) -> 900 | F95: =+SUM(START:END!F95) -> 5898.0583 | G95: =+SUM(START:END!G95) -> 6.5533981 | H95: =IF(G95=0,0,I95/G95) -> 900 | I95: =+SUM(START:END!I95) -> 5898.0583 | J95: =+SUM(START:END!J95) -> 0 | K95: =IF(J95=0,0,L95/J95) -> 0 | L95: =+SUM(START:END!L95) -> 0 | O95: =+SUM(START:END!O95) -> 4 | P95: =IF(O95=0,0,Q95/O95) -> 1709.46 | Q95: =+SUM(START:END!Q95) -> 6837.84 | R95: =J95-O95 -> -4 | S95: =L95-Q95 -> -6837.84
A96: =+B96&C96 -> Véhicules usagésTotal Usagés | B96: Véhicules usagés | C96: Total Usagés | D96: =+D95+D94 -> 123.20388 | E96: =IF(D96=0,0,F96/D96) -> 1278.7234 | F96: =+F94+F95 -> 157543.69 | G96: =+G95+G94 -> 123.20388 | H96: =IF(G96=0,0,I96/G96) -> 1278.7234 | I96: =+I94+I95 -> 157543.69 | J96: =+J94+J95 -> 110 | K96: =IF(J96<=0,0,L96/J96) -> 1759.0522 | L96: =+L94+L95 -> 193495.74 | M96: =J96-G96 -> -13.203883 | N96: =L96-I96 -> 35952.051 | O96: =+O94+O95 -> 118 | P96: =IF(O96<=0,0,Q96/O96) -> 1382.2269 | Q96: =+Q94+Q95 -> 163102.78 | R96: =R94+R95 -> -8 | S96: =S94+S95 -> 30392.96 | V96: =+SUM(START:END!D96)-D96 -> 0 | W96: =+SUM(START:END!G96)-G96 -> 0 | X96: =+SUM(START:END!J96)-J96 -> 0 | Y96: =+SUM(START:END!O96)-O96 -> 0
A97: =+B97&C97 -> Véhicules usagés | B97: Véhicules usagés | E97: =IF(D97=0,0,F97/D97) -> 0 | H97: =IF(G97=0,0,I97/G97) -> 0 | M97: =M96/G96 -> -0.107171 | N97: =N96/I96 -> 0.22820369 | R97: =R96/O96 -> -0.06779661 | S97: =IF(Q96=0,0,(S96/Q96)) -> 0.18634238
A98: =+B98&C98 -> Véhicules usagésUS | B98: Véhicules usagés | C98: US | D98: =+SUM(START:END!D98) -> 0 | E98: =IF(D98=0,0,F98/D98) -> 0 | F98: =+SUM(START:END!F98) -> 0 | G98: =+SUM(START:END!G98) -> 0 | H98: =IF(G98=0,0,I98/G98) -> 0 | I98: =+SUM(START:END!I98) -> 0 | J98: =+SUM(START:END!J98) -> 0 | K98: =IF(J98=0,0,L98/J98) -> 0 | L98: =+SUM(START:END!L98) -> 0 | M98: =J98-G98 -> 0 | N98: =L98-I98 -> 0 | O98: =+SUM(START:END!O98) -> 0 | P98: =IF(O98=0,0,Q98/O98) -> 0 | Q98: =+SUM(START:END!Q98) -> 0 | V98: =+SUM(START:END!D98)-D98 -> 0 | W98: =+SUM(START:END!G98)-G98 -> 0 | X98: =+SUM(START:END!J98)-J98 -> 0 | Y98: =+SUM(START:END!O98)-O98 -> 0
A99: =+B99&C99 -> Véhicules usagésVentes au Gros | B99: Véhicules usagés | C99: Ventes au Gros | D99: =+SUM(START:END!D99) -> 107.21115 | E99: =IF(D99=0,0,F99/D99) -> 212 | F99: =+SUM(START:END!F99) -> 22728.763 | G99: =+SUM(START:END!G99) -> 107.21115 | H99: =IF(G99=0,0,I99/G99) -> 212 | I99: =+SUM(START:END!I99) -> 22728.763 | J99: =+SUM(START:END!J99) -> 117 | K99: =IF(J99=0,0,L99/J99) -> 382.77607 | L99: =+SUM(START:END!L99) -> 44784.8 | M99: =J99-G99 -> 9.7888535 | N99: =L99-I99 -> 22056.037 | O99: =+SUM(START:END!O99) -> 147 | P99: =IF(O99=0,0,Q99/O99) -> 291.98184 | Q99: =+SUM(START:END!Q99) -> 42921.33 | R99: =J99-O99 -> -30 | S99: =L99-Q99 -> 1863.47 | V99: =+SUM(START:END!D99)-D99 -> 0 | W99: =+SUM(START:END!G99)-G99 -> 0 | X99: =+SUM(START:END!J99)-J99 -> 0 | Y99: =+SUM(START:END!O99)-O99 -> 0
A100: =+B100&C100 -> Véhicules usagés | B100: Véhicules usagés
A101: =+B101&C101 -> Véhicules usagésRev. Finances | B101: Véhicules usagés | C101: Rev. Finances | D101: 0 | E101: =IF(D101=0,0,F101/D101) -> 0 | F101: =+SUM(START:END!F101) -> 81186.543 | G101: 0 | H101: =IF(G101=0,0,I101/G101) -> 0 | I101: =+SUM(START:END!I101) -> 81186.543 | K101: =IF(J96=0,0,L101/J96) -> 717.36391 | L101: =+SUM(START:END!L101) -> 78910.03 | N101: =L101-I101 -> -2276.5134 | P101: =IF(O96=0,0,Q101/O96) -> 870.32712 | Q101: =+SUM(START:END!Q101) -> 102698.6 | R101: =O101-K101 -> -717.36391 | S101: =L101-Q101 -> -23788.57
A102: =+B102&C102 -> Véhicules usagésRev. Protections | B102: Véhicules usagés | C102: Rev. Protections | D102: 0 | E102: =IF(D102=0,0,F102/D102) -> 0 | F102: =+SUM(START:END!F102) -> 143143.78 | G102: 0 | H102: =IF(G102=0,0,I102/G102) -> 0 | I102: =+SUM(START:END!I102) -> 143143.78 | K102: =IF(J96=0,0,L102/J96) -> 1184.6819 | L102: =+SUM(START:END!L102) -> 130315.01 | N102: =L102-I102 -> -12828.767 | P102: =IF(O96=0,0,Q102/O96) -> 1237.1114 | Q102: =+SUM(START:END!Q102) -> 145979.15 | R102: =O102-K102 -> -1184.6819 | S102: =L102-Q102 -> -15664.14
A103: =+B103&C103 -> Véhicules usagésRev. Autres | B103: Véhicules usagés | C103: Rev. Autres | D103: 0 | E103: =IF(D103=0,0,F103/D103) -> 0 | F103: =+SUM(START:END!F103) -> 4059.9631 | G103: 0 | H103: =IF(G103=0,0,I103/G103) -> 0 | I103: =+SUM(START:END!I103) -> 4059.9631 | K103: =IF(J96=0,0,L103/J96) -> 35.744636 | L103: =+SUM(START:END!L103) -> 3931.91 | N103: =L103-I103 -> -128.05314 | P103: =IF(O96=0,0,Q103/O96) -> 55.284746 | Q103: =+SUM(START:END!Q103) -> 6523.6 | R103: =O103-K103 -> -35.744636 | S103: =L103-Q103 -> -2591.69
A104: =+B104&C104 -> Véhicules usagésTotal F&I | B104: Véhicules usagés | C104: Total F&I | D104: =D96 -> 123.20388 | E104: =IF(D104=0,0,F104/D104) -> 1853.7588 | F104: =F101+F102+F103 -> 228390.28 | G104: =G96 -> 123.20388 | H104: =IF(G104=0,0,I104/G104) -> 1853.7588 | I104: =I101+I102+I103 -> 228390.28 | J104: =J96 -> 110 | K104: =IF(J104<=0,0,L104/J104) -> 1937.7905 | L104: =L101+L102+L103 -> 213156.95 | M104: =J104-G104 -> -13.203883 | N104: =L104-I104 -> -15233.333 | O104: =O96 -> 118 | P104: =IF(O104<=0,0,Q104/O104) -> 2162.7233 | Q104: =Q101+Q102+Q103 -> 255201.35 | S104: =L104-Q104 -> -42044.4 | V104: =+SUM(START:END!D104)-D104 -> 0 | W104: =+SUM(START:END!G104)-G104 -> 0 | X104: =+SUM(START:END!J104)-J104 -> 0 | Y104: =+SUM(START:END!O104)-O104 -> 0
A105: =+B105&C105 -> Véhicules usagés | B105: Véhicules usagés | N105: =N104/I104 -> -0.066698692 | S105: =IF(Q104=0,0,(S104/Q104)) -> -0.16474991
A106: =+B106&C106 -> Véhicules usagés | B106: Véhicules usagés
A107: =+B107&C107 -> Véhicules usagésTotal Dépt. Usagés | B107: Véhicules usagés | C107: Total Dépt. Usagés | D107: =D96+D99 -> 230.41503 | E107: =IF(D107<=0,0,F107/D107) -> 1773.5941 | F107: =F96+F104+F99 -> 408662.74 | G107: =G96+G99 -> 230.41503 | H107: =IF(G107<=0,0,I107/G107) -> 1773.5941 | I107: =I96+I104+I99 -> 408662.74 | J107: =J96+J99+J98 -> 227 | K107: =IF(J107<=0,0,L107/J107) -> 1988.7114 | L107: =L96+L104+L99+L98 -> 451437.49 | M107: =J107-G107 -> -3.41503 | N107: =L107-I107 -> 42774.754 | O107: =O96+O99+O98 -> 265 | P107: =IF(O107<=0,0,Q107/O107) -> 1740.4734 | Q107: =Q96+Q104+Q99+Q98 -> 461225.46 | R107: =J107-O107 -> -38 | S107: =L107-Q107 -> -9787.97 | V107: =+SUM(START:END!D107)-D107 -> 0 | W107: =+SUM(START:END!G107)-G107 -> 0 | X107: =+SUM(START:END!J107)-J107 -> 0 | Y107: =+SUM(START:END!O107)-O107 -> 0
...

Sheet START

Sheet VW 2022-07
C1: Volks | K1: Véhicules neufs | S1: Réalisé, Juillet 2022
D2: X | E2: O | F2: U | G2: X | H2: O | I2: U | J2: NB | L2: $ | O2: NB | Q2: $ | V2: *** NE PAS EFFACER / Pour An Précédente ***
D3: BUDGET ORIGINAL | G3: BUDGET REVISE | J3: RÉALISATION | M3: ÉCART réel / révisé | O3: ANNÉE PRÉCÉDENTE | R3: ÉCART réel / original | V3: NEUF | W3: 0.45
D4: UNITE | E4: $P/UNITÉ | F4: $PROFITS | G4: UNITE | H4: $P/UNITÉ | I4: $PROFITS | J4: UNITE | K4: $P/UNITE | L4: $PROFITS | M4: UNITÉ | N4: $PROFITS | O4: UNITE | P4: $P/UNITE | Q4: $PROFITS | R4: UNITE | S4: $PROFITS | V4: USAGE | W4: 0.1
A5: Véhicules neufsVentes nettes | B5: Véhicules neufs | C5: Ventes nettes | F5: 3373350.3 | I5: 3373350.3 | L5: 2657067 | Q5: 2770249.7 | V5: SERVICE | W5: 0.225
A6: Véhicules neufsAutos détail | B6: Véhicules neufs | C6: Autos détail | D6: 17.204819 | E6: =IF(D6=0,0,F6/D6) -> 1450.6298 | F6: 24957.823 | G6: 17.204819 | H6: =IF(G6=0,0,I6/G6) -> 1450.6298 | I6: 24957.823 | J6: 13 | K6: =IF(J6=0,0,L6/J6) -> 2819.2123 | L6: 36649.76 | M6: =J6-G6 -> -4.2048193 | N6: =L6-I6 -> 11691.937 | O6: 24 | P6: =IF(O6=0,0,Q6/O6) -> 1259.8542 | Q6: 30236.5 | R6: =J6-O6 -> -11 | S6: =L6-Q6 -> 6413.26 | V6: CARROSSERIE | W6: 0.025
A7: Véhicules neufsCamions détail | B7: Véhicules neufs | C7: Camions détail | D7: 59.39759 | E7: =IF(D7=0,0,F7/D7) -> 2081.8276 | F7: 123655.54 | G7: 59.39759 | H7: =IF(G7=0,0,I7/G7) -> 2081.8276 | I7: 123655.54 | J7: 37 | K7: =IF(J7=0,0,L7/J7) -> 3278.5565 | L7: 121306.59 | M7: =J7-G7 -> -22.39759 | N7: =L7-I7 -> -2348.9522 | O7: 37 | P7: =IF(O7=0,0,Q7/O7) -> 2440.6305 | Q7: 90303.33 | R7: =J7-O7 -> 0 | S7: =L7-Q7 -> 31003.26 | V7: PIECES | W7: 0.2
A8: Véhicules neufsSprinter | B8: Véhicules neufs | C8: Sprinter | D8: 0 | E8: =IF(D8=0,0,F8/D8) -> 0 | F8: 0 | G8: 0 | H8: =IF(G8=0,0,I8/G8) -> 0 | I8: 0 | J8: 0 | K8: =IF(J8=0,0,L8/J8) -> 0 | L8: 0 | M8: =J8-G8 -> 0 | N8: =L8-I8 -> 0 | O8: 0 | P8: =IF(O8=0,0,Q8/O8) -> 0 | Q8: 0 | R8: =J8-O8 -> 0 | S8: =L8-Q8 -> 0 | W8: =SUM(W3:W7) -> 1
A9: Véhicules neufsMoto détail | B9: Véhicules neufs | C9: Moto détail | D9: 0 | E9: =IF(D9=0,0,F9/D9) -> 0 | F9: 0 | G9: 0 | H9: =IF(G9=0,0,I9/G9) -> 0 | I9: 0 | J9: 0 | K9: =IF(J9=0,0,L9/J9) -> 0 | L9: 0 | M9: =J9-G9 -> 0 | N9: =L9-I9 -> 0 | O9: 0 | P9: =IF(O9=0,0,Q9/O9) -> 0 | Q9: 0 | R9: =J9-O9 -> 0 | S9: =L9-Q9 -> 0
A10: Véhicules neufs[...] | B10: Véhicules neufs | C10: [...] | D10: 0 | E10: =IF(D10=0,0,F10/D10) -> 0 | F10: 0 | G10: 0 | H10: =IF(G10=0,0,I10/G10) -> 0 | I10: 0 | J10: 0 | K10: =IF(J10=0,0,L10/J10) -> 0 | L10: 0 | M10: =J10-G10 -> 0 | N10: =L10-I10 -> 0 | O10: 0 | P10: =IF(O10=0,0,Q10/O10) -> 0 | Q10: 0 | R10: =J10-O10 -> 0 | S10: =L10-Q10 -> 0
A11: Véhicules neufs[...] | B11: Véhicules neufs | C11: [...] | D11: 0 | E11: =IF(D11=0,0,F11/D11) -> 0 | F11: 0 | G11: 0 | H11: =IF(G11=0,0,I11/G11) -> 0 | I11: 0 | J11: 0 | K11: =IF(J11=0,0,L11/J11) -> 0 | L11: 0 | M11: =J11-G11 -> 0 | N11: =L11-I11 -> 0 | O11: 0 | P11: =IF(O11=0,0,Q11/O11) -> 0 | Q11: 0 | R11: =J11-O11 -> 0 | S11: =L11-Q11 -> 0
A12: Véhicules neufs[...] | B12: Véhicules neufs | C12: [...] | D12: 0 | E12: =IF(D12=0,0,F12/D12) -> 0 | F12: 0 | G12: 0 | H12: =IF(G12=0,0,I12/G12) -> 0 | I12: 0 | J12: 0 | K12: =IF(J12=0,0,L12/J12) -> 0 | L12: 0 | M12: =J12-G12 -> 0 | N12: =L12-I12 -> 0 | O12: 0 | P12: =IF(O12=0,0,Q12/O12) -> 0 | Q12: 0 | R12: =J12-O12 -> 0 | S12: =L12-Q12 -> 0
A13: Véhicules neufsTotal Neufs | B13: Véhicules neufs | C13: Total Neufs | D13: =+SUM(D6:D12) -> 76.60241 | E13: =IF(D13<=0,0,F13/D13) -> 1940.0612 | F13: =+SUM(F6:F12) -> 148613.37 | G13: =+SUM(G6:G12) -> 76.60241 | H13: =IF(G13<=0,0,I13/G13) -> 1940.0612 | I13: =+SUM(I6:I12) -> 148613.37 | J13: =+SUM(J6:J12) -> 50 | K13: =IF(J13<=0,0,L13/J13) -> 3159.127 | L13: =+SUM(L6:L12) -> 157956.35 | M13: =+SUM(M6:M12) -> -26.60241 | N13: =+SUM(N6:N12) -> 9342.9849 | O13: =+SUM(O6:O12) -> 61 | P13: =IF(O13<=0,0,Q13/O13) -> 1976.0628 | Q13: =+SUM(Q6:Q12) -> 120539.83 | R13: =+SUM(R6:R12) -> -11 | S13: =+SUM(S6:S12) -> 37416.52
A14: Véhicules neufs | B14: Véhicules neufs | R14: =R13/O13 -> -0.18032787 | S14: =IF(Q13=0,0,(S13/Q13)) -> 0.31040794
A15: Véhicules neufsEx-Démos et courtoisies | B15: Véhicules neufs | C15: Ex-Démos et courtoisies | D15: 7.1686747 | E15: =IF(D15=0,0,F15/D15) -> 1386.1016 | F15: 9936.5116 | G15: 7.1686747 | H15: =IF(G15=0,0,I15/G15) -> 1386.1016 | I15: 9936.5116 | J15: 3 | K15: =IF(J15=0,0,L15/J15) -> 2992.6 | L15: 8977.8 | M15: =J15-G15 -> -4.1686747 | N15: =L15-I15 -> -958.7116 | O15: 6 | P15: =IF(O15=0,0,Q15/O15) -> 1260.9683 | Q15: 7565.81 | R15: =J15-O15 -> -3 | S15: =L15-Q15 -> 1411.99
A16: Véhicules neufs | B16: Véhicules neufs
A17: Véhicules neufsFlottes | B17: Véhicules neufs | C17: Flottes | D17: 1.289507 | E17: =IF(D17=0,0,F17/D17) -> 1938.8732 | F17: 2500.1904 | G17: 1.289507 | H17: =IF(G17=0,0,I17/G17) -> 1938.8732 | I17: 2500.1904 | J17: 2 | K17: =IF(J17=0,0,L17/J17) -> 4190.8 | L17: 8381.6 | M17: =J17-G17 -> 0.71049305 | N17: =L17-I17 -> 5881.4096 | O17: 0 | P17: =IF(O17=0,0,Q17/O17) -> 0 | Q17: -276 | R17: =J17-O17 -> 2 | S17: =L17-Q17 -> 8657.6
A18: Véhicules neufs | B18: Véhicules neufs
A19: Véhicules neufsRachat bail | B19: Véhicules neufs | C19: Rachat bail | D19: 0 | E19: =IF(D19=0,0,F19/D19) -> 0 | F19: 7013.3658 | G19: 0 | H19: =IF(G19=0,0,I19/G19) -> 0 | I19: 7013.3658 | L19: 13968.33 | N19: =L19-I19 -> 6954.9642 | Q19: 5617.12 | R19: =O19-K19 -> 0 | S19: =L19-Q19 -> 8351.21
A20: Véhicules neufs | B20: Véhicules neufs
A21: Véhicules neufsRev. Finances | B21: Véhicules neufs | C21: Rev. Finances | D21: 0 | E21: =IF(D21=0,0,F21/D21) -> 0 | F21: 2506.7461 | G21: 0 | H21: =IF(G21=0,0,I21/G21) -> 0 | I21: 2506.7461 | K21: =IF(J13=0,0,L21/(J13+J15)) -> 208.71698 | L21: 11062 | N21: =L21-I21 -> 8555.2539 | P21: =IF(O13=0,0,Q21/(O13+O15)) -> 1.4925373 | Q21: 100 | R21: =O21-K21 -> -208.71698 | S21: =L21-Q21 -> 10962
A22: Véhicules neufsRev. Protections | B22: Véhicules neufs | C22: Rev. Protections | D22: 0 | E22: =IF(D22=0,0,F22/D22) -> 0 | F22: 67039.434 | G22: 0 | H22: =IF(G22=0,0,I22/G22) -> 0 | I22: 67039.434 | K22: =IF(J13=0,0,L22/(J13+J15)) -> 1043.6472 | L22: 55313.3 | N22: =L22-I22 -> -11726.134 | P22: =IF(O13=0,0,Q22/(O13+O15)) -> 822.7094 | Q22: 55121.53 | R22: =O22-K22 -> -1043.6472 | S22: =L22-Q22 -> 191.77
A23: Véhicules neufsRev. Autres | B23: Véhicules neufs | C23: Rev. Autres | D23: 0 | E23: =IF(D23=0,0,F23/D23) -> 0 | F23: 1659.2412 | G23: 0 | H23: =IF(G23=0,0,I23/G23) -> 0 | I23: 1659.2412 | K23: =IF(J13=0,0,L23/(J13+J15)) -> 26.998868 | L23: 1430.94 | N23: =L23-I23 -> -228.30123 | P23: =IF(O13=0,0,Q23/(O13+O15)) -> 26.582985 | Q23: 1781.06 | R23: =O23-K23 -> -26.998868 | S23: =L23-Q23 -> -350.12
A24: Véhicules neufsTotal F&I | B24: Véhicules neufs | C24: Total F&I | D24: =+D15+D13 -> 83.771084 | E24: =IF(D24<=0,0,F24/D24) -> 850 | F24: =F21+F22+F23 -> 71205.422 | G24: =+G15+G13 -> 83.771084 | H24: =IF(G24<=0,0,I24/G24) -> 850 | I24: =I21+I22+I23 -> 71205.422 | J24: =+J15+J13 -> 53 | K24: =IF(J24<=0,0,L24/J24) -> 1279.363 | L24: =L21+L22+L23 -> 67806.24 | M24: =J24-G24 -> -30.771084 | N24: =L24-I24 -> -3399.1817 | O24: =+O15+O13 -> 67 | P24: =IF(O24<=0,0,Q24/O24) -> 850.78493 | Q24: =Q21+Q22+Q23 -> 57002.59 | S24: =L24-Q24 -> 10803.65
A25: Véhicules neufs | B25: Véhicules neufs | N25: =IF(N24=0,0,N24/I24) -> -0.047737681 | S25: =IF(Q24=0,0,(S24/Q24)) -> 0.18952911
A26: Véhicules neufs | B26: Véhicules neufs
A27: Véhicules neufsTotal Dépt. Neufs | B27: Véhicules neufs | C27: Total Dépt. Neufs | D27: =+D13+D15+D17 -> 85.060591 | E27: =IF(D27<=0,0,F27/D27) -> 2812.9225 | F27: =F13+F17+F24+F19+F15 -> 239268.85 | G27: =+G13+G15+G17 -> 85.060591 | H27: =IF(G27<=0,0,I27/G27) -> 2812.9225 | I27: =I13+I17+I24+I19+I15 -> 239268.85 | J27: =+J13+J15+J17 -> 55 | K27: =IF(J27<=0,0,L27/J27) -> 4674.3695 | L27: =L13+L17+L24+L19+L15 -> 257090.32 | M27: =J27-G27 -> -30.060591 | N27: =L27-I27 -> 17821.465 | O27: =+O13+O15+O17 -> 67 | P27: =IF(O27<=0,0,Q27/O27) -> 2842.5276 | Q27: =Q13+Q17+Q24+Q19+Q15 -> 190449.35 | R27: =J27-O27 -> -12 | S27: =L27-Q27 -> 66640.97
A28: Véhicules neufs | B28: Véhicules neufs | M28: =M27/G27 -> -0.3534021 | N28: =N27/I27 -> 0.074483014 | R28: =R27/O27 -> -0.17910448 | S28: =IF(Q27=0,0,S27/Q27) -> 0.3499144
A29: Véhicules neufs | B29: Véhicules neufs
A30: Véhicules neufsDEPENSES | B30: Véhicules neufs | C30: DEPENSES
A31: Véhicules neufsComm. vendeurs | B31: Véhicules neufs | C31: Comm. vendeurs | D31: =F31/(F15+F13+F17) -> 0.31276628 | E31: =F31/D$24 -> 601.29375 | F31: 50371.03 | G31: =I31/(I15+I13) -> 0.31769832 | H31: =I31/G$24 -> 601.29375 | I31: 50371.03 | J31: =L31/(L15+L13+L17) -> 0.32276575 | K31: =IF(L31=0,0,L31/J$24) -> 1067.6589 | L31: 56585.92 | N31: =L31-I31 -> 6214.8903 | P31: =IF(Q31=0,0,Q31/O$24) -> 569.64836 | Q31: 38166.44 | S31: =L31-Q31 -> 18419.48
A32: Véhicules neufsComm. F&I | B32: Véhicules neufs | C32: Comm. F&I | D32: =F32/F24 -> 0.3 | E32: =F32/D$24 -> 255 | F32: 21361.627 | G32: =I32/I24 -> 0.3 | H32: =I32/G$24 -> 255 | I32: 21361.627 | J32: =L32/L24 -> 0.33139561 | K32: =IF(L32=0,0,L32/J$24) -> 423.97528 | L32: 22470.69 | N32: =L32-I32 -> 1109.0635 | P32: =IF(Q32=0,0,Q32/O$24) -> 260.55 | Q32: 17456.85 | S32: =L32-Q32 -> 5013.84 | U32: =(L32+L112)/(L104+L24+L19) -> 0.26924386 | V32: <<- F&A total Neuf Usagé Rachat
A33: Véhicules neufsFrais de livraison | B33: Véhicules neufs | C33: Frais de livraison | E33: =F33/D$24 -> 167.8493 | F33: 14060.918 | H33: =I33/G$24 -> 167.8493 | I33: 14060.918 | K33: =IF(L33=0,0,L33/J$24) -> 145.86774 | L33: 7730.99 | N33: =L33-I33 -> -6329.9281 | P33: =IF(Q33=0,0,Q33/O$24) -> 252.36746 | Q33: 16908.62 | S33: =L33-Q33 -> -9177.63
A34: Véhicules neufsService gratuit 1 | B34: Véhicules neufs | C34: Service gratuit 1 | E34: =F34/D$24 -> 7.3548076 | F34: 616.12021 | H34: =I34/G$24 -> 7.3548076 | I34: 616.12021 | K34: =IF(L34=0,0,L34/J$24) -> 3.5922642 | L34: 190.39 | N34: =L34-I34 -> -425.73021 | P34: =IF(Q34=0,0,Q34/O$24) -> 6.6438806 | Q34: 445.14 | S34: =L34-Q34 -> -254.75
A35: Véhicules neufsEntretien stock | B35: Véhicules neufs | C35: Entretien stock | E35: =F35/D$24 -> 17.733118 | F35: 1485.5225 | H35: =I35/G$24 -> 17.733118 | I35: 1485.5225 | K35: =IF(L35=0,0,L35/J$24) -> 176.23962 | L35: 9340.7 | N35: =L35-I35 -> 7855.1775 | P35: =IF(Q35=0,0,Q35/O$24) -> 2.6119403 | Q35: 175 | S35: =L35-Q35 -> 9165.7 | U35: Pneus 3,168 + Accroch Jess 2,000
A36: Véhicules neufsPublicité 1 | B36: Véhicules neufs | C36: Publicité 1 | E36: =F36/D$24 -> 195.93765 | F36: 16413.91 | H36: =I36/G$24 -> 195.93765 | I36: 16413.91 | K36: =IF(L36=0,0,L36/J$24) -> 185.94774 | L36: 9855.23 | N36: =L36-I36 -> -6558.6796 | P36: =IF(Q36=0,0,Q36/O$24) -> 153.44896 | Q36: 10281.08 | S36: =L36-Q36 -> -425.85
A37: Véhicules neufsIntérêt de gros | B37: Véhicules neufs | C37: Intérêt de gros | E37: =F37/D$24 -> 86.224826 | F37: 7223.1472 | H37: =I37/G$24 -> 86.224826 | I37: 7223.1472 | K37: =IF(L37=0,0,L37/J$24) -> 21.345283 | L37: 1131.3 | N37: =L37-I37 -> -6091.8472 | P37: =IF(Q37=0,0,Q37/O$24) -> 159.04104 | Q37: 10655.75 | S37: =L37-Q37 -> -9524.45
A38: Véhicules neufs[...] | B38: Véhicules neufs | C38: [...] | E38: =F38/D$24 -> 0 | F38: 0 | H38: =I38/G$24 -> 0 | I38: 0 | K38: =IF(L38=0,0,L38/J$24) -> 0 | L38: 0 | N38: =L38-I38 -> 0 | P38: =IF(Q38=0,0,Q38/O$24) -> 0 | Q38: 0 | S38: =L38-Q38 -> 0
A39: Véhicules neufs[...] | B39: Véhicules neufs | C39: [...] | E39: =F39/D$24 -> 0 | F39: 0 | H39: =I39/G$24 -> 0 | I39: 0 | K39: =IF(L39=0,0,L39/J$24) -> 0 | L39: 0 | N39: =L39-I39 -> 0 | P39: =IF(Q39=0,0,Q39/O$24) -> 0 | Q39: 0 | S39: =L39-Q39 -> 0
A40: Véhicules neufs[...] | B40: Véhicules neufs | C40: [...] | E40: =F40/D$24 -> 0 | F40: 0 | H40: =I40/G$24 -> 0 | I40: 0 | K40: =IF(L40=0,0,L40/J$24) -> 0 | L40: 0 | N40: =L40-I40 -> 0 | P40: =IF(Q40=0,0,Q40/O$24) -> 0 | Q40: 0 | S40: =L40-Q40 -> 0
A41: Véhicules neufsTOTAL VARIABLES | B41: Véhicules neufs | C41: TOTAL VARIABLES | D41: % brut | E41: =F41/F$27 -> 0.46613787 | F41: =SUM(F31:F40) -> 111532.27 | G41: % brut | H41: =I41/I$27 -> 0.46613787 | I41: =SUM(I31:I40) -> 111532.27 | J41: % brut | K41: =L41/L$27 -> 0.41738335 | L41: =SUM(L31:L40) -> 107305.22 | N41: =L41-I41 -> -4227.0538 | O41: % brut | P41: =Q41/Q$27 -> 0.49403624 | Q41: =SUM(Q31:Q40) -> 94088.88 | S41: =L41-Q41 -> 13216.34
A42: Véhicules neufsSalaires cadres | B42: Véhicules neufs | C42: Salaires cadres | F42: 15886.261 | I42: 15886.261 | L42: 15898.03 | N42: =L42-I42 -> 11.76908 | Q42: 13797.04 | S42: =L42-Q42 -> 2100.99
A43: Véhicules neufsSalaires commis | B43: Véhicules neufs | C43: Salaires commis | F43: 9822.0278 | I43: 9822.0278 | L43: 7132.73 | N43: =L43-I43 -> -2689.2978 | Q43: 8972.99 | S43: =L43-Q43 -> -1840.26
A44: Véhicules neufsSalaires autres | B44: Véhicules neufs | C44: Salaires autres | F44: 8921.4022 | I44: 8921.4022 | L44: 3509.01 | N44: =L44-I44 -> -5412.3922 | Q44: 9321.31 | S44: =L44-Q44 -> -5812.3
A45: Véhicules neufsSalaires spécialistes | B45: Véhicules neufs | C45: Salaires spécialistes | F45: 0 | I45: 0 | L45: 0 | N45: =L45-I45 -> 0 | Q45: 0 | S45: =L45-Q45 -> 0
A46: Véhicules neufs[...] | B46: Véhicules neufs | C46: [...] | F46: 0 | I46: 0 | L46: 0 | N46: =L46-I46 -> 0 | Q46: 0 | S46: =L46-Q46 -> 0
A47: Véhicules neufs[...] | B47: Véhicules neufs | C47: [...] | F47: 0 | I47: 0 | L47: 0 | N47: =L47-I47 -> 0 | Q47: 0 | S47: =L47-Q47 -> 0
A48: Véhicules neufs[...] | B48: Véhicules neufs | C48: [...] | F48: 0 | I48: 0 | L48: 0 | N48: =L48-I48 -> 0 | Q48: 0 | S48: =L48-Q48 -> 0
A49: Véhicules neufsSalaires en absences | B49: Véhicules neufs | C49: Salaires en absences | F49: 12907.843 | I49: 12907.843 | L49: 20543.52 | N49: =L49-I49 -> 7635.6767 | Q49: 15413.12 | S49: =L49-Q49 -> 5130.4
A50: Véhicules neufsDéduction à la source | B50: Véhicules neufs | C50: Déduction à la source | F50: 11560.297 | I50: 11560.297 | L50: 17936.94 | N50: =L50-I50 -> 6376.6432 | Q50: 11115.9 | S50: =L50-Q50 -> 6821.04
A51: Véhicules neufsBénéfices marginaux | B51: Véhicules neufs | C51: Bénéfices marginaux | F51: 9180.2357 | I51: 9180.2357 | L51: 7345.74 | N51: =L51-I51 -> -1834.4957 | Q51: 7966.39 | S51: =L51-Q51 -> -620.65
A52: Véhicules neufsCsst | B52: Véhicules neufs | C52: Csst | F52: 3740.096 | I52: 3740.096 | L52: 5097.38 | N52: =L52-I52 -> 1357.284 | Q52: 1852.65 | S52: =L52-Q52 -> 3244.73
A53: Véhicules neufs[...] | B53: Véhicules neufs | C53: [...] | F53: 0 | I53: 0 | L53: 0 | N53: =L53-I53 -> 0 | Q53: 0 | S53: =L53-Q53 -> 0
A54: Véhicules neufsTOTAL PERSONNEL | B54: Véhicules neufs | C54: TOTAL PERSONNEL | D54: % brut | E54: =F54/F$27 -> 0.30099263 | F54: =+SUM(F42:F53) -> 72018.163 | G54: % brut | H54: =I54/I$27 -> 0.30099263 | I54: =+SUM(I42:I53) -> 72018.163 | J54: % brut | K54: =L54/L$27 -> 0.30130792 | L54: =+SUM(L42:L53) -> 77463.35 | N54: =+SUM(N42:N53) -> 5445.1872 | O54: % brut | P54: =Q54/Q$27 -> 0.35935749 | Q54: =+SUM(Q42:Q53) -> 68439.4 | S54: =+SUM(S42:S53) -> 9023.95
A55: Véhicules neufsPublicité 2 | B55: Véhicules neufs | C55: Publicité 2 | F55: 0 | I55: 0 | L55: 0 | N55: =L55-I55 -> 0 | Q55: 0 | S55: =L55-Q55 -> 0
A56: Véhicules neufsService gratuit 2 | B56: Véhicules neufs | C56: Service gratuit 2 | F56: 0 | I56: 0 | L56: 0 | N56: =L56-I56 -> 0 | Q56: 0 | S56: =L56-Q56 -> 0
A57: Véhicules neufsFrais véhicules de cie | B57: Véhicules neufs | C57: Frais véhicules de cie | F57: 7322.94 | I57: 7322.94 | L57: 6354.05 | N57: =L57-I57 -> -968.89 | Q57: 5681.11 | S57: =L57-Q57 -> 672.94
A58: Véhicules neufsInformatique | B58: Véhicules neufs | C58: Informatique | F58: 6834.1988 | I58: 6834.1988 | L58: 7289.36 | N58: =L58-I58 -> 455.16116 | Q58: 5374.89 | S58: =L58-Q58 -> 1914.47
A59: Véhicules neufsFrais de déplacement | B59: Véhicules neufs | C59: Frais de déplacement | F59: 792.1418 | I59: 792.1418 | L59: 966.86 | N59: =L59-I59 -> 174.7182 | Q59: 1790.95 | S59: =L59-Q59 -> -824.09
A60: Véhicules neufsServices extérieurs | B60: Véhicules neufs | C60: Services extérieurs | F60: 6729.517 | I60: 6729.517 | L60: 6513.05 | N60: =L60-I60 -> -216.46698 | Q60: 6768.76 | S60: =L60-Q60 -> -255.71
A61: Véhicules neufsFournitures autres | B61: Véhicules neufs | C61: Fournitures autres | F61: 99.362812 | I61: 99.362812 | L61: 0 | N61: =L61-I61 -> -99.362812 | Q61: 0 | S61: =L61-Q61 -> 0
A62: Véhicules neufsUniformes | B62: Véhicules neufs | C62: Uniformes | F62: 52.798786 | I62: 52.798786 | L62: 0 | N62: =L62-I62 -> -52.798786 | Q62: 0 | S62: =L62-Q62 -> 0
A63: Véhicules neufsPapeterie | B63: Véhicules neufs | C63: Papeterie | F63: 652.86432 | I63: 652.86432 | L63: 984.46 | N63: =L63-I63 -> 331.59568 | Q63: 466.66 | S63: =L63-Q63 -> 517.8
A64: Véhicules neufsTéléphone | B64: Véhicules neufs | C64: Téléphone | F64: 301.46453 | I64: 301.46453 | L64: 261.12 | N64: =L64-I64 -> -40.344527 | Q64: 216.99 | S64: =L64-Q64 -> 44.13
A65: Véhicules neufsFrais postaux | B65: Véhicules neufs | C65: Frais postaux | F65: 160.91707 | I65: 160.91707 | L65: 200.99 | N65: =L65-I65 -> 40.072927 | Q65: 242.49 | S65: =L65-Q65 -> -41.5
A66: Véhicules neufsDivers | B66: Véhicules neufs | C66: Divers | F66: 776.23359 | I66: 776.23359 | L66: 140.21 | N66: =L66-I66 -> -636.02359 | Q66: 803.71 | S66: =L66-Q66 -> -663.5
A67: Véhicules neufsFormation | B67: Véhicules neufs | C67: Formation | F67: 1153.2563 | I67: 1153.2563 | L67: 1388.34 | N67: =L67-I67 -> 235.08373 | Q67: 523.33 | S67: =L67-Q67 -> 865.01 | W67: Reclass
A68: Véhicules neufsFrais bancaires | B68: Véhicules neufs | C68: Frais bancaires | F68: 1857.7872 | I68: 1857.7872 | L68: 3734.54 | N68: =L68-I68 -> 1876.7528 | Q68: =AL447*W3 -> 3168.036 | S68: =L68-Q68 -> 566.504 | U68: Changement Méthode 2022-07 | W68: 19570
A69: Véhicules neufs[...] | B69: Véhicules neufs | C69: [...] | F69: 0 | I69: 0 | N69: =L69-I69 -> 0 | Q69: 0 | S69: =L69-Q69 -> 0
A70: Véhicules neufs[...] | B70: Véhicules neufs | C70: [...] | F70: 0 | I70: 0 | L70: 0 | N70: =L70-I70 -> 0 | Q70: 0 | S70: =L70-Q70 -> 0
A71: Véhicules neufs[...] | B71: Véhicules neufs | C71: [...] | F71: 0 | I71: 0 | L71: 0 | N71: =L71-I71 -> 0 | Q71: 0 | S71: =L71-Q71 -> 0
A72: Véhicules neufsTOTAL SEMI-FIXES | B72: Véhicules neufs | C72: TOTAL SEMI-FIXES | D72: % brut | E72: =F72/F$27 -> 0.11172989 | F72: =+SUM(F55:F71) -> 26733.482 | G72: % brut | H72: =I72/I$27 -> 0.11172989 | I72: =+SUM(I55:I71) -> 26733.482 | J72: % brut | K72: =L72/L$27 -> 0.10826149 | L72: =+SUM(L55:L71) -> 27832.98 | N72: =+SUM(N55:N71) -> 1099.4978 | O72: % brut | P72: =Q72/Q$27 -> 0.13146239 | Q72: =+SUM(Q55:Q71) -> 25036.926 | S72: =+SUM(S55:S71) -> 2796.054
A73: Véhicules neufs | B73: Véhicules neufs
A74: Véhicules neufsTOTAL DES DÉPENSES | B74: Véhicules neufs | C74: TOTAL DES DÉPENSES | D74: % brut | E74: =F74/F$27 -> 0.87886039 | F74: =F41+F54+F72 -> 210283.92 | G74: % brut | H74: =I74/I$27 -> 0.87886039 | I74: =I41+I54+I72 -> 210283.92 | J74: % brut | K74: =L74/L$27 -> 0.82695276 | L74: =L41+L54+L72 -> 212601.55 | N74: =L74-I74 -> 2317.6312 | O74: % brut | P74: =Q74/Q$27 -> 0.98485611 | Q74: =Q41+Q54+Q72 -> 187565.21 | S74: =L74-Q74 -> 25036.344
A75: Véhicules neufsProgramme neuf 1 | B75: Véhicules neufs | C75: Programme neuf 1 | F75: 0 | I75: 0 | L75: 0 | N75: =L75-I75 -> 0 | Q75: 20000
A76: Véhicules neufsProgramme neuf 2 | B76: Véhicules neufs | C76: Programme neuf 2 | F76: 0 | I76: 0 | L76: 0 | N76: =L76-I76 -> 0 | Q76: 0 | S76: =L76-Q76 -> 0
A77: Véhicules neufsProgramme neuf 3 | B77: Véhicules neufs | C77: Programme neuf 3 | F77: 0 | I77: 0 | L77: 0 | N77: =L77-I77 -> 0 | Q77: 0 | S77: =L77-Q77 -> 0
A78: Véhicules neufsHoldbacks | B78: Véhicules neufs | C78: Holdbacks | F78: 88914.01 | I78: 88914.01 | L78: 69130 | N78: =L78-I78 -> -19784.01 | Q78: 37897 | S78: =L78-Q78 -> 31233
A79: Véhicules neufs[...] | B79: Véhicules neufs | C79: [...] | F79: 0 | I79: 0 | L79: 0 | N79: =L79-I79 -> 0 | Q79: 0 | S79: =L79-Q79 -> 0
A80: Véhicules neufs[...] | B80: Véhicules neufs | C80: [...] | F80: 0 | I80: 0 | L80: 0 | N80: =L80-I80 -> 0 | Q80: 0 | S80: =L80-Q80 -> 0
A81: Véhicules neufs[...] | B81: Véhicules neufs | C81: [...] | F81: 0 | I81: 0 | L81: 0 | N81: =L81-I81 -> 0 | Q81: 0 | S81: =L81-Q81 -> 0
A82: Véhicules neufsFrais administration | B82: Véhicules neufs | C82: Frais administration | F82: 30545.258 | I82: 30545.258 | J82: =+L82/K82 -> 55 | K82: =+L82/J27 -> 370.58182 | L82: 20382 | N82: =L82-I82 -> -10163.258 | Q82: 20102 | S82: =L82-Q82 -> 280
A83: Véhicules neufsAUTRES REVENUS | B83: Véhicules neufs | C83: AUTRES REVENUS | F83: =+SUM(F75:F82) -> 119459.27 | I83: =+SUM(I75:I82) -> 119459.27 | L83: =+SUM(L75:L82) -> 89512 | N83: =+SUM(N75:N82) -> -29947.268 | Q83: =+SUM(Q75:Q82) -> 77999 | S83: =+SUM(S75:S82) -> 31513
A84: Véhicules neufs | B84: Véhicules neufs
A85: Véhicules neufsPROFIT DÉPARTEMENTAL | B85: Véhicules neufs | C85: PROFIT DÉPARTEMENTAL | F85: =F27-F74+F83 -> 148444.2 | I85: =I27-I74+I83 -> 148444.2 | L85: =L27-L74+L83 -> 134000.77 | N85: =N27-N41-N54-N72+N83 -> -14443.434 | Q85: =Q27-Q74+Q83 -> 80883.144 | S85: =S27-S41-S54-S72+S83 -> 73117.626
C89: =C1 -> Volks | K89: Véhicules usagés | S89: =$S$1 -> Réalisé, Juillet 2022
D91: BUDGET ORIGINAL | G91: BUDGET RÉVISÉ | J91: RÉALISATION | M91: ÉCART réel / révisé | O91: ANNÉE PRÉCÉDENTE | R91: ÉCART réel / original
D92: UNITE | E92: $P/UNITÉ | F92: $PROFITS | G92: UNITE | H92: $P/UNITÉ | I92: $PROFITS | J92: UNITE | K92: $P/UNITE | L92: $PROFITS | M92: UNITÉ | N92: $PROFITS | O92: UNITE | P92: $P/UNITE | Q92: $PROFITS | R92: UNITE | S92: $PROFITS
A93: Véhicules usagésVentes nettes | B93: Véhicules usagés | C93: Ventes nettes | F93: 1415444 | I93: 1415444 | L93: 1722927 | Q93: 1788729.6
A94: Véhicules usagésCertifié | B94: Véhicules usagés | C94: Certifié | D94: 43.203883 | E94: =IF(D94=0,0,F94/D94) -> 1300 | F94: 56165.049 | G94: 43.203883 | H94: =IF(G94=0,0,I94/G94) -> 1300 | I94: 56165.049 | J94: 39 | K94: =IF(J94=0,0,L94/J94) -> 1866.1264 | L94: 72778.93 | M94: =J94-G94 -> -4.2038835 | N94: =L94-I94 -> 16613.881 | O94: 40 | P94: =IF(O94=0,0,Q94/O94) -> 1663.4258 | Q94: 66537.03 | R94: =J94-O94 -> -1 | S94: =L94-Q94 -> 6241.9
A95: Véhicules usagésNon Certifié | B95: Véhicules usagés | C95: Non Certifié | D95: 2.4271845 | E95: =IF(D95=0,0,F95/D95) -> 900 | F95: 2184.466 | G95: 2.4271845 | H95: =IF(G95=0,0,I95/G95) -> 900 | I95: 2184.466 | J95: 0 | K95: =IF(J95=0,0,L95/J95) -> 0 | L95: 0 | M95: =J95-G95 -> -2.4271845 | N95: =L95-I95 -> -2184.466 | O95: 1 | P95: =IF(O95=0,0,Q95/O95) -> 302.7 | Q95: 302.7 | R95: =J95-O95 -> -1 | S95: =L95-Q95 -> -302.7
A96: Véhicules usagésTotal Usagés | B96: Véhicules usagés | C96: Total Usagés | D96: =+D95+D94 -> 45.631068 | E96: =IF(D96=0,0,F96/D96) -> 1278.7234 | F96: =+F94+F95 -> 58349.515 | G96: =+G95+G94 -> 45.631068 | H96: =IF(G96=0,0,I96/G96) -> 1278.7234 | I96: =+I94+I95 -> 58349.515 | J96: =+J94+J95 -> 39 | K96: =IF(J96<=0,0,L96/J96) -> 1866.1264 | L96: =+L94+L95 -> 72778.93 | M96: =J96-G96 -> -6.631068 | N96: =L96-I96 -> 14429.415 | O96: =+O94+O95 -> 41 | P96: =IF(O96<=0,0,Q96/O96) -> 1630.2373 | Q96: =+Q94+Q95 -> 66839.73 | R96: =R94+R95 -> -2 | S96: =S94+S95 -> 5939.2
A97: Véhicules usagés | B97: Véhicules usagés | E97: =IF(D97=0,0,F97/D97) -> 0 | H97: =IF(G97=0,0,I97/G97) -> 0 | M97: =M96/G96 -> -0.14531915 | N97: =N96/I96 -> 0.24729281 | R97: =R96/O96 -> -0.048780488 | S97: =IF(Q96=0,0,(S96/Q96)) -> 0.088857331
A98: Véhicules usagésUS | B98: Véhicules usagés | C98: US | U98: Fichier Contrôle
A99: Véhicules usagésVentes au Gros | B99: Véhicules usagés | C99: Ventes au Gros | D99: 39.707832 | E99: =IF(D99=0,0,F99/D99) -> 212 | F99: 8418.0604 | G99: 39.707832 | H99: =IF(G99=0,0,I99/G99) -> 212 | I99: 8418.0604 | J99: 39 | K99: =IF(J99=0,0,L99/J99) -> 417.16308 | L99: 16269.36 | M99: =J99-G99 -> -0.70783204 | N99: =L99-I99 -> 7851.2996 | O99: 61 | P99: =IF(O99=0,0,Q99/O99) -> 124.07803 | Q99: 7568.76 | R99: =J99-O99 -> -22 | S99: =L99-Q99 -> 8700.6 | U99: 15899 | V99: =+L99-U99 -> 370.36
A100: Véhicules usagés | B100: Véhicules usagés
A101: Véhicules usagésRev. Finances | B101: Véhicules usagés | C101: Rev. Finances | D101: 0 | E101: =IF(D101=0,0,F101/D101) -> 0 | F101: 30069.09 | G101: 0 | H101: =IF(G101=0,0,I101/G101) -> 0 | I101: 30069.09 | K101: =IF(J96=0,0,L101/J96) -> 567.12359 | L101: 22117.82 | N101: =L101-I101 -> -7951.2702 | P101: =IF(O96=0,0,Q101/O96) -> 1004.3405 | Q101: 41177.96 | R101: =O101-K101 -> -567.12359 | S101: =L101-Q101 -> -19060.14
A102: Véhicules usagésRev. Protections | B102: Véhicules usagés | C102: Rev. Protections | D102: 0 | E102: =IF(D102=0,0,F102/D102) -> 0 | F102: 53016.214 | G102: 0 | H102: =IF(G102=0,0,I102/G102) -> 0 | I102: 53016.214 | K102: =IF(J96=0,0,L102/J96) -> 1053.2949 | L102: 41078.5 | N102: =L102-I102 -> -11937.714 | P102: =IF(O96=0,0,Q102/O96) -> 1434.5559 | Q102: 58816.79 | R102: =O102-K102 -> -1053.2949 | S102: =L102-Q102 -> -17738.29
A103: Véhicules usagésRev. Autres | B103: Véhicules usagés | C103: Rev. Autres | D103: 0 | E103: =IF(D103=0,0,F103/D103) -> 0 | F103: 1503.6901 | G103: 0 | H103: =IF(G103=0,0,I103/G103) -> 0 | I103: 1503.6901 | K103: =IF(J96=0,0,L103/J96) -> 41.861538 | L103: 1632.6 | N103: =L103-I103 -> 128.90995 | P103: =IF(O96=0,0,Q103/O96) -> 90.78 | Q103: 3721.98 | R103: =O103-K103 -> -41.861538 | S103: =L103-Q103 -> -2089.38
A104: Véhicules usagésTotal F&I | B104: Véhicules usagés | C104: Total F&I | D104: =D96 -> 45.631068 | E104: =IF(D104=0,0,F104/D104) -> 1853.7588 | F104: =F101+F102+F103 -> 84588.994 | G104: =G96 -> 45.631068 | H104: =IF(G104=0,0,I104/G104) -> 1853.7588 | I104: =I101+I102+I103 -> 84588.994 | J104: =J96 -> 39 | K104: =IF(J104<=0,0,L104/J104) -> 1662.28 | L104: =L101+L102+L103 -> 64828.92 | M104: =J104-G104 -> -6.631068 | N104: =L104-I104 -> -19760.074 | O104: =O96 -> 41 | P104: =IF(O104<=0,0,Q104/O104) -> 2529.6763 | Q104: =Q101+Q102+Q103 -> 103716.73 | S104: =L104-Q104 -> -38887.81
...

Sheet VW 2022-08
C1: Volks | K1: Véhicules neufs | S1: Réalisé, Août 2022
D2: X | E2: O | F2: U | G2: X | H2: O | I2: U | J2: NB | L2: $ | O2: NB | Q2: $ | V2: *** NE PAS EFFACER / Pour An Précédente ***
D3: BUDGET ORIGINAL | G3: BUDGET REVISE | J3: RÉALISATION | M3: ÉCART réel / révisé | O3: ANNÉE PRÉCÉDENTE | R3: ÉCART réel / original | V3: NEUF | W3: 0.45
D4: UNITE | E4: $P/UNITÉ | F4: $PROFITS | G4: UNITE | H4: $P/UNITÉ | I4: $PROFITS | J4: UNITE | K4: $P/UNITE | L4: $PROFITS | M4: UNITÉ | N4: $PROFITS | O4: UNITE | P4: $P/UNITE | Q4: $PROFITS | R4: UNITE | S4: $PROFITS | V4: USAGE | W4: 0.1
A5: Véhicules neufsVentes nettes | B5: Véhicules neufs | C5: Ventes nettes | F5: 3254290.8 | I5: 3254290.8 | L5: 3632125.1 | Q5: 3249436.4 | V5: SERVICE | W5: 0.225
A6: Véhicules neufsAutos détail | B6: Véhicules neufs | C6: Autos détail | D6: 16.59759 | E6: =IF(D6=0,0,F6/D6) -> 1450.6298 | F6: 24076.959 | G6: 16.59759 | H6: =IF(G6=0,0,I6/G6) -> 1450.6298 | I6: 24076.959 | J6: 21 | K6: =IF(J6=0,0,L6/J6) -> 2507.92 | L6: 52666.32 | M6: =J6-G6 -> 4.4024096 | N6: =L6-I6 -> 28589.361 | O6: 24 | P6: =IF(O6=0,0,Q6/O6) -> 1070.9171 | Q6: 25702.01 | R6: =J6-O6 -> -3 | S6: =L6-Q6 -> 26964.31 | V6: CARROSSERIE | W6: 0.025
A7: Véhicules neufsCamions détail | B7: Véhicules neufs | C7: Camions détail | D7: 57.301205 | E7: =IF(D7=0,0,F7/D7) -> 2081.8276 | F7: 119291.23 | G7: 57.301205 | H7: =IF(G7=0,0,I7/G7) -> 2081.8276 | I7: 119291.23 | J7: 50 | K7: =IF(J7=0,0,L7/J7) -> 3039.8858 | L7: 151994.29 | M7: =J7-G7 -> -7.3012048 | N7: =L7-I7 -> 32703.061 | O7: 39 | P7: =IF(O7=0,0,Q7/O7) -> 2067.4385 | Q7: 80630.1 | R7: =J7-O7 -> 11 | S7: =L7-Q7 -> 71364.19 | V7: PIECES | W7: 0.2
A8: Véhicules neufsSprinter | B8: Véhicules neufs | C8: Sprinter | D8: 0 | E8: =IF(D8=0,0,F8/D8) -> 0 | F8: 0 | G8: 0 | H8: =IF(G8=0,0,I8/G8) -> 0 | I8: 0 | J8: 0 | K8: =IF(J8=0,0,L8/J8) -> 0 | L8: 0 | M8: =J8-G8 -> 0 | N8: =L8-I8 -> 0 | O8: 0 | P8: =IF(O8=0,0,Q8/O8) -> 0 | Q8: 0 | R8: =J8-O8 -> 0 | S8: =L8-Q8 -> 0 | W8: =SUM(W3:W7) -> 1
A9: Véhicules neufsMoto détail | B9: Véhicules neufs | C9: Moto détail | D9: 0 | E9: =IF(D9=0,0,F9/D9) -> 0 | F9: 0 | G9: 0 | H9: =IF(G9=0,0,I9/G9) -> 0 | I9: 0 | J9: 0 | K9: =IF(J9=0,0,L9/J9) -> 0 | L9: 0 | M9: =J9-G9 -> 0 | N9: =L9-I9 -> 0 | O9: 0 | P9: =IF(O9=0,0,Q9/O9) -> 0 | Q9: 0 | R9: =J9-O9 -> 0 | S9: =L9-Q9 -> 0
A10: Véhicules neufs[...] | B10: Véhicules neufs | C10: [...] | D10: 0 | E10: =IF(D10=0,0,F10/D10) -> 0 | F10: 0 | G10: 0 | H10: =IF(G10=0,0,I10/G10) -> 0 | I10: 0 | J10: 0 | K10: =IF(J10=0,0,L10/J10) -> 0 | L10: 0 | M10: =J10-G10 -> 0 | N10: =L10-I10 -> 0 | O10: 0 | P10: =IF(O10=0,0,Q10/O10) -> 0 | Q10: 0 | R10: =J10-O10 -> 0 | S10: =L10-Q10 -> 0
A11: Véhicules neufs[...] | B11: Véhicules neufs | C11: [...] | D11: 0 | E11: =IF(D11=0,0,F11/D11) -> 0 | F11: 0 | G11: 0 | H11: =IF(G11=0,0,I11/G11) -> 0 | I11: 0 | J11: 0 | K11: =IF(J11=0,0,L11/J11) -> 0 | L11: 0 | M11: =J11-G11 -> 0 | N11: =L11-I11 -> 0 | O11: 0 | P11: =IF(O11=0,0,Q11/O11) -> 0 | Q11: 0 | R11: =J11-O11 -> 0 | S11: =L11-Q11 -> 0
A12: Véhicules neufs[...] | B12: Véhicules neufs | C12: [...] | D12: 0 | E12: =IF(D12=0,0,F12/D12) -> 0 | F12: 0 | G12: 0 | H12: =IF(G12=0,0,I12/G12) -> 0 | I12: 0 | J12: 0 | K12: =IF(J12=0,0,L12/J12) -> 0 | L12: 0 | M12: =J12-G12 -> 0 | N12: =L12-I12 -> 0 | O12: 0 | P12: =IF(O12=0,0,Q12/O12) -> 0 | Q12: 0 | R12: =J12-O12 -> 0 | S12: =L12-Q12 -> 0
A13: Véhicules neufsTotal Neufs | B13: Véhicules neufs | C13: Total Neufs | D13: =+SUM(D6:D12) -> 73.898795 | E13: =IF(D13<=0,0,F13/D13) -> 1940.0612 | F13: =+SUM(F6:F12) -> 143368.19 | G13: =+SUM(G6:G12) -> 73.898795 | H13: =IF(G13<=0,0,I13/G13) -> 1940.0612 | I13: =+SUM(I6:I12) -> 143368.19 | J13: =+SUM(J6:J12) -> 71 | K13: =IF(J13<=0,0,L13/J13) -> 2882.5438 | L13: =+SUM(L6:L12) -> 204660.61 | M13: =+SUM(M6:M12) -> -2.8987952 | N13: =+SUM(N6:N12) -> 61292.423 | O13: =+SUM(O6:O12) -> 63 | P13: =IF(O13<=0,0,Q13/O13) -> 1687.8113 | Q13: =+SUM(Q6:Q12) -> 106332.11 | R13: =+SUM(R6:R12) -> 8 | S13: =+SUM(S6:S12) -> 98328.5
A14: Véhicules neufs | B14: Véhicules neufs | R14: =R13/O13 -> 0.12698413 | S14: =IF(Q13=0,0,(S13/Q13)) -> 0.92473007
A15: Véhicules neufsEx-Démos et courtoisies | B15: Véhicules neufs | C15: Ex-Démos et courtoisies | D15: 6.9156627 | E15: =IF(D15=0,0,F15/D15) -> 1386.1016 | F15: 9585.8112 | G15: 6.9156627 | H15: =IF(G15=0,0,I15/G15) -> 1386.1016 | I15: 9585.8112 | J15: 2 | K15: =IF(J15=0,0,L15/J15) -> 4516.805 | L15: 9033.61 | M15: =J15-G15 -> -4.9156627 | N15: =L15-I15 -> -552.20119 | O15: 14 | P15: =IF(O15=0,0,Q15/O15) -> 2016.2536 | Q15: 28227.55 | R15: =J15-O15 -> -12 | S15: =L15-Q15 -> -19193.94
A16: Véhicules neufs | B16: Véhicules neufs
A17: Véhicules neufsFlottes | B17: Véhicules neufs | C17: Flottes | D17: 1.2439949 | E17: =IF(D17=0,0,F17/D17) -> 1938.8732 | F17: 2411.9484 | G17: 1.2439949 | H17: =IF(G17=0,0,I17/G17) -> 1938.8732 | I17: 2411.9484 | J17: 4 | K17: =IF(J17=0,0,L17/J17) -> 1549.0925 | L17: 6196.37 | M17: =J17-G17 -> 2.7560051 | N17: =L17-I17 -> 3784.4216 | O17: 1 | P17: =IF(O17=0,0,Q17/O17) -> 983.9 | Q17: 983.9 | R17: =J17-O17 -> 3 | S17: =L17-Q17 -> 5212.47
A18: Véhicules neufs | B18: Véhicules neufs
A19: Véhicules neufsRachat bail | B19: Véhicules neufs | C19: Rachat bail | D19: 0 | E19: =IF(D19=0,0,F19/D19) -> 0 | F19: 4909.3561 | G19: 0 | H19: =IF(G19=0,0,I19/G19) -> 0 | I19: 4909.3561 | L19: 19995.21 | N19: =L19-I19 -> 15085.854 | Q19: 7992.19 | R19: =O19-K19 -> 0 | S19: =L19-Q19 -> 12003.02
A20: Véhicules neufs | B20: Véhicules neufs
A21: Véhicules neufsRev. Finances | B21: Véhicules neufs | C21: Rev. Finances | D21: 0 | E21: =IF(D21=0,0,F21/D21) -> 0 | F21: 2418.2727 | G21: 0 | H21: =IF(G21=0,0,I21/G21) -> 0 | I21: 2418.2727 | K21: =IF(J13=0,0,L21/(J13+J15)) -> 172.24973 | L21: 12574.23 | N21: =L21-I21 -> 10155.957 | P21: =IF(O13=0,0,Q21/(O13+O15)) -> 0 | Q21: 0 | R21: =O21-K21 -> -172.24973 | S21: =L21-Q21 -> 12574.23
A22: Véhicules neufsRev. Protections | B22: Véhicules neufs | C22: Rev. Protections | D22: 0 | E22: =IF(D22=0,0,F22/D22) -> 0 | F22: 64673.337 | G22: 0 | H22: =IF(G22=0,0,I22/G22) -> 0 | I22: 64673.337 | K22: =IF(J13=0,0,L22/(J13+J15)) -> 810.39493 | L22: 59158.83 | N22: =L22-I22 -> -5514.5067 | P22: =IF(O13=0,0,Q22/(O13+O15)) -> 927.02481 | Q22: 71380.91 | R22: =O22-K22 -> -810.39493 | S22: =L22-Q22 -> -12222.08
A23: Véhicules neufsRev. Autres | B23: Véhicules neufs | C23: Rev. Autres | D23: 0 | E23: =IF(D23=0,0,F23/D23) -> 0 | F23: 1600.6798 | G23: 0 | H23: =IF(G23=0,0,I23/G23) -> 0 | I23: 1600.6798 | K23: =IF(J13=0,0,L23/(J13+J15)) -> 16.719726 | L23: 1220.54 | N23: =L23-I23 -> -380.13978 | P23: =IF(O13=0,0,Q23/(O13+O15)) -> 16.993117 | Q23: 1308.47 | R23: =O23-K23 -> -16.719726 | S23: =L23-Q23 -> -87.93
A24: Véhicules neufsTotal F&I | B24: Véhicules neufs | C24: Total F&I | D24: =+D15+D13 -> 80.814458 | E24: =IF(D24<=0,0,F24/D24) -> 850 | F24: =F21+F22+F23 -> 68692.289 | G24: =+G15+G13 -> 80.814458 | H24: =IF(G24<=0,0,I24/G24) -> 850 | I24: =I21+I22+I23 -> 68692.289 | J24: =+J15+J13 -> 73 | K24: =IF(J24<=0,0,L24/J24) -> 999.36438 | L24: =L21+L22+L23 -> 72953.6 | M24: =J24-G24 -> -7.8144578 | N24: =L24-I24 -> 4261.3108 | O24: =+O15+O13 -> 77 | P24: =IF(O24<=0,0,Q24/O24) -> 944.01792 | Q24: =Q21+Q22+Q23 -> 72689.38 | S24: =L24-Q24 -> 264.22
A25: Véhicules neufs | B25: Véhicules neufs | N25: =IF(N24=0,0,N24/I24) -> 0.062034777 | S25: =IF(Q24=0,0,(S24/Q24)) -> 0.0036349189
A26: Véhicules neufs | B26: Véhicules neufs
A27: Véhicules neufsTotal Dépt. Neufs | B27: Véhicules neufs | C27: Total Dépt. Neufs | D27: =+D13+D15+D17 -> 82.058453 | E27: =IF(D27<=0,0,F27/D27) -> 2790.2987 | F27: =F13+F17+F24+F19+F15 -> 228967.59 | G27: =+G13+G15+G17 -> 82.058453 | H27: =IF(G27<=0,0,I27/G27) -> 2790.2987 | I27: =I13+I17+I24+I19+I15 -> 228967.59 | J27: =+J13+J15+J17 -> 77 | K27: =IF(J27<=0,0,L27/J27) -> 4062.8494 | L27: =L13+L17+L24+L19+L15 -> 312839.4 | M27: =J27-G27 -> -5.0584528 | N27: =L27-I27 -> 83871.808 | O27: =+O13+O15+O17 -> 78 | P27: =IF(O27<=0,0,Q27/O27) -> 2772.1171 | Q27: =Q13+Q17+Q24+Q19+Q15 -> 216225.13 | R27: =J27-O27 -> -1 | S27: =L27-Q27 -> 96614.27
A28: Véhicules neufs | B28: Véhicules neufs | M28: =M27/G27 -> -0.061644506 | N28: =N27/I27 -> 0.36630427 | R28: =R27/O27 -> -0.012820513 | S28: =IF(Q27=0,0,S27/Q27) -> 0.44682258
A29: Véhicules neufs | B29: Véhicules neufs
A30: Véhicules neufsDEPENSES | B30: Véhicules neufs | C30: DEPENSES
A31: Véhicules neufsComm. vendeurs | B31: Véhicules neufs | C31: Comm. vendeurs | D31: =F31/(F15+F13+F17) -> 0.31779577 | E31: =F31/D$24 -> 610.96296 | F31: 49374.64 | G31: =I31/(I15+I13) -> 0.32280712 | H31: =I31/G$24 -> 610.96296 | I31: 49374.64 | J31: =L31/(L15+L13+L17) -> 0.22464749 | K31: =IF(L31=0,0,L31/J$24) -> 676.68315 | L31: 49397.87 | N31: =L31-I31 -> 23.229578 | P31: =IF(Q31=0,0,Q31/O$24) -> 598.30338 | Q31: 46069.36 | S31: =L31-Q31 -> 3328.51
A32: Véhicules neufsComm. F&I | B32: Véhicules neufs | C32: Comm. F&I | D32: =F32/F24 -> 0.3 | E32: =F32/D$24 -> 255 | F32: 20607.687 | G32: =I32/I24 -> 0.3 | H32: =I32/G$24 -> 255 | I32: 20607.687 | J32: =L32/L24 -> 0.37722868 | K32: =IF(L32=0,0,L32/J$24) -> 376.9889 | L32: 27520.19 | N32: =L32-I32 -> 6912.5033 | P32: =IF(Q32=0,0,Q32/O$24) -> 272.32532 | Q32: 20969.05 | S32: =L32-Q32 -> 6551.14 | U32: =(L32+L112)/(L104+L24+L19) -> 0.3095684 | V32: <<- F&A total Neuf Usagé Rachat
A33: Véhicules neufsFrais de livraison | B33: Véhicules neufs | C33: Frais de livraison | E33: =F33/D$24 -> 167.8493 | F33: 13564.65 | H33: =I33/G$24 -> 167.8493 | I33: 13564.65 | K33: =IF(L33=0,0,L33/J$24) -> 24.27137 | L33: 1771.81 | N33: =L33-I33 -> -11792.84 | P33: =IF(Q33=0,0,Q33/O$24) -> 130.65442 | Q33: 10060.39 | S33: =L33-Q33 -> -8288.58
A34: Véhicules neufsService gratuit 1 | B34: Véhicules neufs | C34: Service gratuit 1 | E34: =F34/D$24 -> 7.3548076 | F34: 594.37479 | H34: =I34/G$24 -> 7.3548076 | I34: 594.37479 | K34: =IF(L34=0,0,L34/J$24) -> 0 | L34: 0 | N34: =L34-I34 -> -594.37479 | P34: =IF(Q34=0,0,Q34/O$24) -> 7.3462338 | Q34: 565.66 | S34: =L34-Q34 -> -565.66
A35: Véhicules neufsEntretien stock | B35: Véhicules neufs | C35: Entretien stock | E35: =F35/D$24 -> 17.733118 | F35: 1433.0923 | H35: =I35/G$24 -> 17.733118 | I35: 1433.0923 | K35: =IF(L35=0,0,L35/J$24) -> 60.332329 | L35: 4404.26 | N35: =L35-I35 -> 2971.1677 | P35: =IF(Q35=0,0,Q35/O$24) -> 40.73 | Q35: 3136.21 | S35: =L35-Q35 -> 1268.05
A36: Véhicules neufsPublicité 1 | B36: Véhicules neufs | C36: Publicité 1 | E36: =F36/D$24 -> 195.93765 | F36: 15834.595 | H36: =I36/G$24 -> 195.93765 | I36: 15834.595 | K36: =IF(L36=0,0,L36/J$24) -> 48.655068 | L36: 3551.82 | N36: =L36-I36 -> -12282.775 | P36: =IF(Q36=0,0,Q36/O$24) -> 161.78143 | Q36: 12457.17 | S36: =L36-Q36 -> -8905.35
A37: Véhicules neufsIntérêt de gros | B37: Véhicules neufs | C37: Intérêt de gros | E37: =F37/D$24 -> 96.0289 | F37: 7760.5235 | H37: =I37/G$24 -> 96.0289 | I37: 7760.5235 | K37: =IF(L37=0,0,L37/J$24) -> 51.69 | L37: 3773.37 | N37: =L37-I37 -> -3987.1535 | P37: =IF(Q37=0,0,Q37/O$24) -> 155.30104 | Q37: 11958.18 | S37: =L37-Q37 -> -8184.81
A38: Véhicules neufs[...] | B38: Véhicules neufs | C38: [...] | E38: =F38/D$24 -> 0 | F38: 0 | H38: =I38/G$24 -> 0 | I38: 0 | K38: =IF(L38=0,0,L38/J$24) -> 0 | L38: 0 | N38: =L38-I38 -> 0 | P38: =IF(Q38=0,0,Q38/O$24) -> 0 | Q38: 0 | S38: =L38-Q38 -> 0
A39: Véhicules neufs[...] | B39: Véhicules neufs | C39: [...] | E39: =F39/D$24 -> 0 | F39: 0 | H39: =I39/G$24 -> 0 | I39: 0 | K39: =IF(L39=0,0,L39/J$24) -> 0 | L39: 0 | N39: =L39-I39 -> 0 | P39: =IF(Q39=0,0,Q39/O$24) -> 0 | Q39: 0 | S39: =L39-Q39 -> 0
A40: Véhicules neufs[...] | B40: Véhicules neufs | C40: [...] | E40: =F40/D$24 -> 0 | F40: 0 | H40: =I40/G$24 -> 0 | I40: 0 | K40: =IF(L40=0,0,L40/J$24) -> 0 | L40: 0 | N40: =L40-I40 -> 0 | P40: =IF(Q40=0,0,Q40/O$24) -> 0 | Q40: 0 | S40: =L40-Q40 -> 0
A41: Véhicules neufsTOTAL VARIABLES | B41: Véhicules neufs | C41: TOTAL VARIABLES | D41: % brut | E41: =F41/F$27 -> 0.47679046 | F41: =SUM(F31:F40) -> 109169.56 | G41: % brut | H41: =I41/I$27 -> 0.47679046 | I41: =SUM(I31:I40) -> 109169.56 | J41: % brut | K41: =L41/L$27 -> 0.28902792 | L41: =SUM(L31:L40) -> 90419.32 | N41: =L41-I41 -> -18750.243 | O41: % brut | P41: =Q41/Q$27 -> 0.48660403 | Q41: =SUM(Q31:Q40) -> 105216.02 | S41: =L41-Q41 -> -14796.7
A42: Véhicules neufsSalaires cadres | B42: Véhicules neufs | C42: Salaires cadres | F42: 15886.261 | I42: 15886.261 | L42: 24887.25 | N42: =L42-I42 -> 9000.9891 | Q42: 15070.12 | S42: =L42-Q42 -> 9817.13
A43: Véhicules neufsSalaires commis | B43: Véhicules neufs | C43: Salaires commis | F43: 9822.0278 | I43: 9822.0278 | L43: 7402.55 | N43: =L43-I43 -> -2419.4778 | Q43: 9222.55 | S43: =L43-Q43 -> -1820
A44: Véhicules neufsSalaires autres | B44: Véhicules neufs | C44: Salaires autres | F44: 8921.4022 | I44: 8921.4022 | L44: 4747.31 | N44: =L44-I44 -> -4174.0922 | Q44: 9197.24 | S44: =L44-Q44 -> -4449.93
A45: Véhicules neufsSalaires spécialistes | B45: Véhicules neufs | C45: Salaires spécialistes | F45: 0 | I45: 0 | L45: 0 | N45: =L45-I45 -> 0 | Q45: 0 | S45: =L45-Q45 -> 0
A46: Véhicules neufs[...] | B46: Véhicules neufs | C46: [...] | F46: 0 | I46: 0 | L46: 0 | N46: =L46-I46 -> 0 | Q46: 0 | S46: =L46-Q46 -> 0
A47: Véhicules neufs[...] | B47: Véhicules neufs | C47: [...] | F47: 0 | I47: 0 | L47: 0 | N47: =L47-I47 -> 0 | Q47: 0 | S47: =L47-Q47 -> 0
A48: Véhicules neufs[...] | B48: Véhicules neufs | C48: [...] | F48: 0 | I48: 0 | L48: 0 | N48: =L48-I48 -> 0 | Q48: 0 | S48: =L48-Q48 -> 0
A49: Véhicules neufsSalaires en absences | B49: Véhicules neufs | C49: Salaires en absences | F49: 12708.499 | I49: 12708.499 | L49: 15306.49 | N49: =L49-I49 -> 2597.9913 | Q49: 12808.93 | S49: =L49-Q49 -> 2497.56
A50: Véhicules neufsDéduction à la source | B50: Véhicules neufs | C50: Déduction à la source | F50: 11381.763 | I50: 11381.763 | L50: 15327.04 | N50: =L50-I50 -> 3945.2767 | Q50: 11455.92 | S50: =L50-Q50 -> 3871.12
A51: Véhicules neufsBénéfices marginaux | B51: Véhicules neufs | C51: Bénéfices marginaux | F51: 9038.4591 | I51: 9038.4591 | L51: 7021.56 | N51: =L51-I51 -> -2016.8991 | Q51: 8210.07 | S51: =L51-Q51 -> -1188.51
A52: Véhicules neufsCsst | B52: Véhicules neufs | C52: Csst | F52: 3682.3352 | I52: 3682.3352 | L52: 2399 | N52: =L52-I52 -> -1283.3352 | Q52: 1909.32 | S52: =L52-Q52 -> 489.68
A53: Véhicules neufs[...] | B53: Véhicules neufs | C53: [...] | F53: 0 | I53: 0 | L53: 0 | N53: =L53-I53 -> 0 | Q53: 0 | S53: =L53-Q53 -> 0
A54: Véhicules neufsTOTAL PERSONNEL | B54: Véhicules neufs | C54: TOTAL PERSONNEL | D54: % brut | E54: =F54/F$27 -> 0.31201248 | F54: =+SUM(F42:F53) -> 71440.747 | G54: % brut | H54: =I54/I$27 -> 0.31201248 | I54: =+SUM(I42:I53) -> 71440.747 | J54: % brut | K54: =L54/L$27 -> 0.2464242 | L54: =+SUM(L42:L53) -> 77091.2 | N54: =+SUM(N42:N53) -> 5650.4529 | O54: % brut | P54: =Q54/Q$27 -> 0.313905 | Q54: =+SUM(Q42:Q53) -> 67874.15 | S54: =+SUM(S42:S53) -> 9217.05
A55: Véhicules neufsPublicité 2 | B55: Véhicules neufs | C55: Publicité 2 | F55: 0 | I55: 0 | L55: 0 | N55: =L55-I55 -> 0 | Q55: 0 | S55: =L55-Q55 -> 0
A56: Véhicules neufsService gratuit 2 | B56: Véhicules neufs | C56: Service gratuit 2 | F56: 0 | I56: 0 | L56: 0 | N56: =L56-I56 -> 0 | Q56: 0 | S56: =L56-Q56 -> 0
A57: Véhicules neufsFrais véhicules de cie | B57: Véhicules neufs | C57: Frais véhicules de cie | F57: 7322.94 | I57: 7322.94 | L57: 7615.92 | N57: =L57-I57 -> 292.98 | Q57: 8672.24 | S57: =L57-Q57 -> -1056.32
A58: Véhicules neufsInformatique | B58: Véhicules neufs | C58: Informatique | F58: 6834.1988 | I58: 6834.1988 | L58: 7197.56 | N58: =L58-I58 -> 363.36116 | Q58: 5986.01 | S58: =L58-Q58 -> 1211.55
A59: Véhicules neufsFrais de déplacement | B59: Véhicules neufs | C59: Frais de déplacement | F59: 792.1418 | I59: 792.1418 | L59: 1421.01 | N59: =L59-I59 -> 628.8682 | Q59: 217.73 | S59: =L59-Q59 -> 1203.28
A60: Véhicules neufsServices extérieurs | B60: Véhicules neufs | C60: Services extérieurs | F60: 6447.7026 | I60: 6447.7026 | L60: 7061.26 | N60: =L60-I60 -> 613.55742 | Q60: 6354.96 | S60: =L60-Q60 -> 706.3
A61: Véhicules neufsFournitures autres | B61: Véhicules neufs | C61: Fournitures autres | F61: 94.464662 | I61: 94.464662 | L61: 17.4 | N61: =L61-I61 -> -77.064662 | Q61: 7.44 | S61: =L61-Q61 -> 9.96
A62: Véhicules neufsUniformes | B62: Véhicules neufs | C62: Uniformes | F62: 50.196038 | I62: 50.196038 | L62: 0 | N62: =L62-I62 -> -50.196038 | Q62: 0 | S62: =L62-Q62 -> 0
A63: Véhicules neufsPapeterie | B63: Véhicules neufs | C63: Papeterie | F63: 652.86432 | I63: 652.86432 | L63: 694.32 | N63: =L63-I63 -> 41.45568 | Q63: 763.56 | S63: =L63-Q63 -> -69.24
A64: Véhicules neufsTéléphone | B64: Véhicules neufs | C64: Téléphone | F64: 301.46453 | I64: 301.46453 | L64: 248.14 | N64: =L64-I64 -> -53.324527 | Q64: 217.9 | S64: =L64-Q64 -> 30.24
A65: Véhicules neufsFrais postaux | B65: Véhicules neufs | C65: Frais postaux | F65: 160.91707 | I65: 160.91707 | L65: 133.59 | N65: =L65-I65 -> -27.327073 | Q65: 243.19 | S65: =L65-Q65 -> -109.6
A66: Véhicules neufsDivers | B66: Véhicules neufs | C66: Divers | F66: 776.23359 | I66: 776.23359 | L66: 62.72 | N66: =L66-I66 -> -713.51359 | Q66: 158.67 | S66: =L66-Q66 -> -95.95
A67: Véhicules neufsFormation | B67: Véhicules neufs | C67: Formation | F67: 1153.2563 | I67: 1153.2563 | L67: 748.54 | N67: =L67-I67 -> -404.71627 | Q67: 1143.33 | S67: =L67-Q67 -> -394.79
A68: Véhicules neufsFrais bancaires | B68: Véhicules neufs | C68: Frais bancaires | F68: 2062.1401 | I68: 2062.1401 | L68: 4084.49 | N68: =L68-I68 -> 2022.3499 | Q68: =AL447*W3 -> 2827.1025 | S68: =L68-Q68 -> 1257.3875
A69: Véhicules neufs[...] | B69: Véhicules neufs | C69: [...] | F69: 0 | I69: 0 | N69: =L69-I69 -> 0 | Q69: 0 | S69: =L69-Q69 -> 0
A70: Véhicules neufs[...] | B70: Véhicules neufs | C70: [...] | F70: 0 | I70: 0 | L70: 0 | N70: =L70-I70 -> 0 | Q70: 0 | S70: =L70-Q70 -> 0
A71: Véhicules neufs[...] | B71: Véhicules neufs | C71: [...] | F71: 0 | I71: 0 | L71: 0 | N71: =L71-I71 -> 0 | Q71: 0 | S71: =L71-Q71 -> 0
A72: Véhicules neufsTOTAL SEMI-FIXES | B72: Véhicules neufs | C72: TOTAL SEMI-FIXES | D72: % brut | E72: =F72/F$27 -> 0.11638555 | F72: =+SUM(F55:F71) -> 26648.52 | G72: % brut | H72: =I72/I$27 -> 0.11638555 | I72: =+SUM(I55:I71) -> 26648.52 | J72: % brut | K72: =L72/L$27 -> 0.093610172 | L72: =+SUM(L55:L71) -> 29284.95 | N72: =+SUM(N55:N71) -> 2636.4302 | O72: % brut | P72: =Q72/Q$27 -> 0.12298354 | Q72: =+SUM(Q55:Q71) -> 26592.132 | S72: =+SUM(S55:S71) -> 2692.8175
A73: Véhicules neufs | B73: Véhicules neufs
A74: Véhicules neufsTOTAL DES DÉPENSES | B74: Véhicules neufs | C74: TOTAL DES DÉPENSES | D74: % brut | E74: =F74/F$27 -> 0.90518849 | F74: =F41+F54+F72 -> 207258.83 | G74: % brut | H74: =I74/I$27 -> 0.90518849 | I74: =I41+I54+I72 -> 207258.83 | J74: % brut | K74: =L74/L$27 -> 0.62906229 | L74: =L41+L54+L72 -> 196795.47 | N74: =L74-I74 -> -10463.36 | O74: % brut | P74: =Q74/Q$27 -> 0.92349258 | Q74: =Q41+Q54+Q72 -> 199682.3 | S74: =L74-Q74 -> -2886.8325
A75: Véhicules neufsProgramme neuf 1 | B75: Véhicules neufs | C75: Programme neuf 1 | F75: 0 | I75: 0 | L75: 0 | N75: =L75-I75 -> 0 | Q75: 0
A76: Véhicules neufsProgramme neuf 2 | B76: Véhicules neufs | C76: Programme neuf 2 | F76: 0 | I76: 0 | L76: 0 | N76: =L76-I76 -> 0 | Q76: 0 | S76: =L76-Q76 -> 0
A77: Véhicules neufsProgramme neuf 3 | B77: Véhicules neufs | C77: Programme neuf 3 | F77: 0 | I77: 0 | L77: 0 | N77: =L77-I77 -> 0 | Q77: 0 | S77: =L77-Q77 -> 0
A78: Véhicules neufsHoldbacks | B78: Véhicules neufs | C78: Holdbacks | E78: =+F78/D24 -> 1061.3926 | F78: 85775.868 | I78: 85775.868 | K78: =+L78/J24 -> 1391.5352 | L78: 101582.07 | N78: =L78-I78 -> 15806.202 | Q78: 94670.15 | S78: =L78-Q78 -> 6911.92 | U78: 4 Locate sans retour
A79: Véhicules neufs[...] | B79: Véhicules neufs | C79: [...] | F79: 0 | I79: 0 | L79: 0 | N79: =L79-I79 -> 0 | Q79: 0 | S79: =L79-Q79 -> 0
A80: Véhicules neufs[...] | B80: Véhicules neufs | C80: [...] | F80: 0 | I80: 0 | L80: 0 | N80: =L80-I80 -> 0 | Q80: 0 | S80: =L80-Q80 -> 0
A81: Véhicules neufs[...] | B81: Véhicules neufs | C81: [...] | F81: 0 | I81: 0 | L81: 0 | N81: =L81-I81 -> 0 | Q81: 0 | S81: =L81-Q81 -> 0
A82: Véhicules neufsFrais administration | B82: Véhicules neufs | C82: Frais administration | F82: 29467.19 | I82: 29467.19 | J82: =+L82/K82 -> 77 | K82: =+L82/J27 -> 381.09091 | L82: 29344 | N82: =L82-I82 -> -123.19039 | Q82: 20687.99 | S82: =L82-Q82 -> 8656.01
A83: Véhicules neufsAUTRES REVENUS | B83: Véhicules neufs | C83: AUTRES REVENUS | F83: =+SUM(F75:F82) -> 115243.06 | I83: =+SUM(I75:I82) -> 115243.06 | L83: =+SUM(L75:L82) -> 130926.07 | N83: =+SUM(N75:N82) -> 15683.011 | Q83: =+SUM(Q75:Q82) -> 115358.14 | S83: =+SUM(S75:S82) -> 15567.93
A84: Véhicules neufs | B84: Véhicules neufs
A85: Véhicules neufsPROFIT DÉPARTEMENTAL | B85: Véhicules neufs | C85: PROFIT DÉPARTEMENTAL | F85: =F27-F74+F83 -> 136951.82 | I85: =I27-I74+I83 -> 136951.82 | L85: =L27-L74+L83 -> 246970 | N85: =N27-N41-N54-N72+N83 -> 110018.18 | Q85: =Q27-Q74+Q83 -> 131900.97 | S85: =S27-S41-S54-S72+S83 -> 115069.03
C89: =C1 -> Volks | K89: Véhicules usagés | S89: =$S$1 -> Réalisé, Août 2022
D91: BUDGET ORIGINAL | G91: BUDGET RÉVISÉ | J91: RÉALISATION | M91: ÉCART réel / révisé | O91: ANNÉE PRÉCÉDENTE | R91: ÉCART réel / original
D92: UNITE | E92: $P/UNITÉ | F92: $PROFITS | G92: UNITE | H92: $P/UNITÉ | I92: $PROFITS | J92: UNITE | K92: $P/UNITE | L92: $PROFITS | M92: UNITÉ | N92: $PROFITS | O92: UNITE | P92: $P/UNITE | Q92: $PROFITS | R92: UNITE | S92: $PROFITS
A93: Véhicules usagésVentes nettes | B93: Véhicules usagés | C93: Ventes nettes | F93: 1309285.7 | I93: 1309285.7 | L93: 1707858.5 | Q93: 1396259.4
A94: Véhicules usagésCertifié | B94: Véhicules usagés | C94: Certifié | D94: 39.963592 | E94: =IF(D94=0,0,F94/D94) -> 1300 | F94: 51952.67 | G94: 39.963592 | H94: =IF(G94=0,0,I94/G94) -> 1300 | I94: 51952.67 | J94: 37 | K94: =IF(J94=0,0,L94/J94) -> 1588.5049 | L94: 58774.68 | M94: =J94-G94 -> -2.9635922 | N94: =L94-I94 -> 6822.0101 | O94: 39 | P94: =IF(O94=0,0,Q94/O94) -> 1016.9182 | Q94: 39659.81 | R94: =J94-O94 -> -2 | S94: =L94-Q94 -> 19114.87
A95: Véhicules usagésNon Certifié | B95: Véhicules usagés | C95: Non Certifié | D95: 2.2451456 | E95: =IF(D95=0,0,F95/D95) -> 900 | F95: 2020.6311 | G95: 2.2451456 | H95: =IF(G95=0,0,I95/G95) -> 900 | I95: 2020.6311 | J95: 0 | K95: =IF(J95=0,0,L95/J95) -> 0 | L95: 0 | M95: =J95-G95 -> -2.2451456 | N95: =L95-I95 -> -2020.6311 | O95: 0 | P95: =IF(O95=0,0,Q95/O95) -> 0 | Q95: -585 | R95: =J95-O95 -> 0 | S95: =L95-Q95 -> 585
A96: Véhicules usagésTotal Usagés | B96: Véhicules usagés | C96: Total Usagés | D96: =+D95+D94 -> 42.208738 | E96: =IF(D96=0,0,F96/D96) -> 1278.7234 | F96: =+F94+F95 -> 53973.301 | G96: =+G95+G94 -> 42.208738 | H96: =IF(G96=0,0,I96/G96) -> 1278.7234 | I96: =+I94+I95 -> 53973.301 | J96: =+J94+J95 -> 37 | K96: =IF(J96<=0,0,L96/J96) -> 1588.5049 | L96: =+L94+L95 -> 58774.68 | M96: =J96-G96 -> -5.2087379 | N96: =L96-I96 -> 4801.379 | O96: =+O94+O95 -> 39 | P96: =IF(O96<=0,0,Q96/O96) -> 1001.9182 | Q96: =+Q94+Q95 -> 39074.81 | R96: =R94+R95 -> -2 | S96: =S94+S95 -> 19699.87
A97: Véhicules usagés | B97: Véhicules usagés | E97: =IF(D97=0,0,F97/D97) -> 0 | H97: =IF(G97=0,0,I97/G97) -> 0 | M97: =M96/G96 -> -0.12340426 | N97: =N96/I96 -> 0.08895841 | R97: =R96/O96 -> -0.051282051 | S97: =IF(Q96=0,0,(S96/Q96)) -> 0.50415779
A98: Véhicules usagésUS | B98: Véhicules usagés | C98: US | U98: Fichier Contrôle
A99: Véhicules usagésVentes au Gros | B99: Véhicules usagés | C99: Ventes au Gros | D99: 36.729745 | E99: =IF(D99=0,0,F99/D99) -> 212 | F99: 7786.7059 | G99: 36.729745 | H99: =IF(G99=0,0,I99/G99) -> 212 | I99: 7786.7059 | J99: 39 | K99: =IF(J99=0,0,L99/J99) -> 330.44385 | L99: 12887.31 | M99: =J99-G99 -> 2.2702554 | N99: =L99-I99 -> 5100.6041 | O99: 35 | P99: =IF(O99=0,0,Q99/O99) -> 277.83571 | Q99: 9724.25 | R99: =J99-O99 -> 4 | S99: =L99-Q99 -> 3163.06 | U99: 0.99 | V99: =+L99-U99 -> 12886.32
A100: Véhicules usagés | B100: Véhicules usagés
A101: Véhicules usagésRev. Finances | B101: Véhicules usagés | C101: Rev. Finances | D101: 0 | E101: =IF(D101=0,0,F101/D101) -> 0 | F101: 27813.908 | G101: 0 | H101: =IF(G101=0,0,I101/G101) -> 0 | I101: 27813.908 | K101: =IF(J96=0,0,L101/J96) -> 827.65405 | L101: 30623.2 | N101: =L101-I101 -> 2809.2916 | P101: =IF(O96=0,0,Q101/O96) -> 594.32692 | Q101: 23178.75 | R101: =O101-K101 -> -827.65405 | S101: =L101-Q101 -> 7444.45
A102: Véhicules usagésRev. Protections | B102: Véhicules usagés | C102: Rev. Protections | D102: 0 | E102: =IF(D102=0,0,F102/D102) -> 0 | F102: 49039.998 | G102: 0 | H102: =IF(G102=0,0,I102/G102) -> 0 | I102: 49039.998 | K102: =IF(J96=0,0,L102/J96) -> 1416.5568 | L102: 52412.6 | N102: =L102-I102 -> 3372.6025 | P102: =IF(O96=0,0,Q102/O96) -> 1096.9954 | Q102: 42782.82 | R102: =O102-K102 -> -1416.5568 | S102: =L102-Q102 -> 9629.78
A103: Véhicules usagésRev. Autres | B103: Véhicules usagés | C103: Rev. Autres | D103: 0 | E103: =IF(D103=0,0,F103/D103) -> 0 | F103: 1390.9133 | G103: 0 | H103: =IF(G103=0,0,I103/G103) -> 0 | I103: 1390.9133 | K103: =IF(J96=0,0,L103/J96) -> 48.754595 | L103: 1803.92 | N103: =L103-I103 -> 413.0067 | P103: =IF(O96=0,0,Q103/O96) -> 9.845641 | Q103: 383.98 | R103: =O103-K103 -> -48.754595 | S103: =L103-Q103 -> 1419.94
A104: Véhicules usagésTotal F&I | B104: Véhicules usagés | C104: Total F&I | D104: =D96 -> 42.208738 | E104: =IF(D104=0,0,F104/D104) -> 1853.7588 | F104: =F101+F102+F103 -> 78244.819 | G104: =G96 -> 42.208738 | H104: =IF(G104=0,0,I104/G104) -> 1853.7588 | I104: =I101+I102+I103 -> 78244.819 | J104: =J96 -> 37 | K104: =IF(J104<=0,0,L104/J104) -> 2292.9654 | L104: =L101+L102+L103 -> 84839.72 | M104: =J104-G104 -> -5.2087379 | N104: =L104-I104 -> 6594.9008 | O104: =O96 -> 39 | P104: =IF(O104<=0,0,Q104/O104) -> 1701.1679 | Q104: =Q101+Q102+Q103 -> 66345.55 | S104: =L104-Q104 -> 18494.17
...

Sheet VW 2022-09
C1: Volks | K1: Véhicules neufs | S1: Réalisé, Septembre 2022
D2: X | E2: O | F2: U | G2: X | H2: O | I2: U | J2: NB | L2: $ | O2: NB | Q2: $ | V2: *** NE PAS EFFACER / Pour An Précédente ***
D3: BUDGET ORIGINAL | G3: BUDGET REVISE | J3: RÉALISATION | M3: ÉCART réel / révisé | O3: ANNÉE PRÉCÉDENTE | R3: ÉCART réel / original | V3: NEUF | W3: 0.45
D4: UNITE | E4: $P/UNITÉ | F4: $PROFITS | G4: UNITE | H4: $P/UNITÉ | I4: $PROFITS | J4: UNITE | K4: $P/UNITE | L4: $PROFITS | M4: UNITÉ | N4: $PROFITS | O4: UNITE | P4: $P/UNITE | Q4: $PROFITS | R4: UNITE | S4: $PROFITS | V4: USAGE | W4: 0.1
A5: Véhicules neufsVentes nettes | B5: Véhicules neufs | C5: Ventes nettes | F5: 2857426.1 | I5: 2857426.1 | L5: 2490545.3 | Q5: 3613426.6 | V5: SERVICE | W5: 0.225
A6: Véhicules neufsAutos détail | B6: Véhicules neufs | C6: Autos détail | D6: 14.573494 | E6: =IF(D6=0,0,F6/D6) -> 1450.6298 | F6: 21140.744 | G6: 14.573494 | H6: =IF(G6=0,0,I6/G6) -> 1450.6298 | I6: 21140.744 | J6: 16 | K6: =IF(J6=0,0,L6/J6) -> 1902.4 | L6: 30438.4 | M6: =J6-G6 -> 1.426506 | N6: =L6-I6 -> 9297.6559 | O6: 35 | P6: =IF(O6=0,0,Q6/O6) -> 1269.0223 | Q6: 44415.78 | R6: =J6-O6 -> -19 | S6: =L6-Q6 -> -13977.38 | V6: CARROSSERIE | W6: 0.025
A7: Véhicules neufsCamions détail | B7: Véhicules neufs | C7: Camions détail | D7: 50.313253 | E7: =IF(D7=0,0,F7/D7) -> 2081.8276 | F7: 104743.52 | G7: 50.313253 | H7: =IF(G7=0,0,I7/G7) -> 2081.8276 | I7: 104743.52 | J7: 33 | K7: =IF(J7=0,0,L7/J7) -> 2621.6852 | L7: 86515.61 | M7: =J7-G7 -> -17.313253 | N7: =L7-I7 -> -18227.908 | O7: 49 | P7: =IF(O7=0,0,Q7/O7) -> 2305.1553 | Q7: 112952.61 | R7: =J7-O7 -> -16 | S7: =L7-Q7 -> -26437 | V7: PIECES | W7: 0.2
A8: Véhicules neufsSprinter | B8: Véhicules neufs | C8: Sprinter | D8: 0 | E8: =IF(D8=0,0,F8/D8) -> 0 | F8: 0 | G8: 0 | H8: =IF(G8=0,0,I8/G8) -> 0 | I8: 0 | J8: 0 | K8: =IF(J8=0,0,L8/J8) -> 0 | L8: 0 | M8: =J8-G8 -> 0 | N8: =L8-I8 -> 0 | O8: 0 | P8: =IF(O8=0,0,Q8/O8) -> 0 | Q8: 0 | R8: =J8-O8 -> 0 | S8: =L8-Q8 -> 0 | W8: =SUM(W3:W7) -> 1
A9: Véhicules neufsMoto détail | B9: Véhicules neufs | C9: Moto détail | D9: 0 | E9: =IF(D9=0,0,F9/D9) -> 0 | F9: 0 | G9: 0 | H9: =IF(G9=0,0,I9/G9) -> 0 | I9: 0 | J9: 0 | K9: =IF(J9=0,0,L9/J9) -> 0 | L9: 0 | M9: =J9-G9 -> 0 | N9: =L9-I9 -> 0 | O9: 0 | P9: =IF(O9=0,0,Q9/O9) -> 0 | Q9: 0 | R9: =J9-O9 -> 0 | S9: =L9-Q9 -> 0
A10: Véhicules neufs[...] | B10: Véhicules neufs | C10: [...] | D10: 0 | E10: =IF(D10=0,0,F10/D10) -> 0 | F10: 0 | G10: 0 | H10: =IF(G10=0,0,I10/G10) -> 0 | I10: 0 | J10: 0 | K10: =IF(J10=0,0,L10/J10) -> 0 | L10: 0 | M10: =J10-G10 -> 0 | N10: =L10-I10 -> 0 | O10: 0 | P10: =IF(O10=0,0,Q10/O10) -> 0 | Q10: 0 | R10: =J10-O10 -> 0 | S10: =L10-Q10 -> 0
A11: Véhicules neufs[...] | B11: Véhicules neufs | C11: [...] | D11: 0 | E11: =IF(D11=0,0,F11/D11) -> 0 | F11: 0 | G11: 0 | H11: =IF(G11=0,0,I11/G11) -> 0 | I11: 0 | J11: 0 | K11: =IF(J11=0,0,L11/J11) -> 0 | L11: 0 | M11: =J11-G11 -> 0 | N11: =L11-I11 -> 0 | O11: 0 | P11: =IF(O11=0,0,Q11/O11) -> 0 | Q11: 0 | R11: =J11-O11 -> 0 | S11: =L11-Q11 -> 0
A12: Véhicules neufs[...] | B12: Véhicules neufs | C12: [...] | D12: 0 | E12: =IF(D12=0,0,F12/D12) -> 0 | F12: 0 | G12: 0 | H12: =IF(G12=0,0,I12/G12) -> 0 | I12: 0 | J12: 0 | K12: =IF(J12=0,0,L12/J12) -> 0 | L12: 0 | M12: =J12-G12 -> 0 | N12: =L12-I12 -> 0 | O12: 0 | P12: =IF(O12=0,0,Q12/O12) -> 0 | Q12: 0 | R12: =J12-O12 -> 0 | S12: =L12-Q12 -> 0
A13: Véhicules neufsTotal Neufs | B13: Véhicules neufs | C13: Total Neufs | D13: =+SUM(D6:D12) -> 64.886747 | E13: =IF(D13<=0,0,F13/D13) -> 1940.0612 | F13: =+SUM(F6:F12) -> 125884.26 | G13: =+SUM(G6:G12) -> 64.886747 | H13: =IF(G13<=0,0,I13/G13) -> 1940.0612 | I13: =+SUM(I6:I12) -> 125884.26 | J13: =+SUM(J6:J12) -> 49 | K13: =IF(J13<=0,0,L13/J13) -> 2386.8165 | L13: =+SUM(L6:L12) -> 116954.01 | M13: =+SUM(M6:M12) -> -15.886747 | N13: =+SUM(N6:N12) -> -8930.2522 | O13: =+SUM(O6:O12) -> 84 | P13: =IF(O13<=0,0,Q13/O13) -> 1873.4332 | Q13: =+SUM(Q6:Q12) -> 157368.39 | R13: =+SUM(R6:R12) -> -35 | S13: =+SUM(S6:S12) -> -40414.38
A14: Véhicules neufs | B14: Véhicules neufs | R14: =R13/O13 -> -0.41666667 | S14: =IF(Q13=0,0,(S13/Q13)) -> -0.25681384
A15: Véhicules neufsEx-Démos et courtoisies | B15: Véhicules neufs | C15: Ex-Démos et courtoisies | D15: 6.0722892 | E15: =IF(D15=0,0,F15/D15) -> 1386.1016 | F15: 8416.8098 | G15: 6.0722892 | H15: =IF(G15=0,0,I15/G15) -> 1386.1016 | I15: 8416.8098 | J15: 1 | K15: =IF(J15=0,0,L15/J15) -> 239.68 | L15: 239.68 | M15: =J15-G15 -> -5.0722892 | N15: =L15-I15 -> -8177.1298 | O15: 7 | P15: =IF(O15=0,0,Q15/O15) -> 505.77714 | Q15: 3540.44 | R15: =J15-O15 -> -6 | S15: =L15-Q15 -> -3300.76
A16: Véhicules neufs | B16: Véhicules neufs
A17: Véhicules neufsFlottes | B17: Véhicules neufs | C17: Flottes | D17: 1.0922882 | E17: =IF(D17=0,0,F17/D17) -> 1938.8732 | F17: 2117.8084 | G17: 1.0922882 | H17: =IF(G17=0,0,I17/G17) -> 1938.8732 | I17: 2117.8084 | J17: 3 | K17: =IF(J17=0,0,L17/J17) -> 1695.91 | L17: 5087.73 | M17: =J17-G17 -> 1.9077118 | N17: =L17-I17 -> 2969.9216 | O17: 0 | P17: =IF(O17=0,0,Q17/O17) -> 0 | Q17: 0 | R17: =J17-O17 -> 3 | S17: =L17-Q17 -> 5087.73
A18: Véhicules neufs | B18: Véhicules neufs
A19: Véhicules neufsRachat bail | B19: Véhicules neufs | C19: Rachat bail | D19: 0 | E19: =IF(D19=0,0,F19/D19) -> 0 | F19: 4909.3561 | G19: 0 | H19: =IF(G19=0,0,I19/G19) -> 0 | I19: 4909.3561 | L19: 13692.75 | N19: =L19-I19 -> 8783.3939 | Q19: 5452.6 | R19: =O19-K19 -> 0 | S19: =L19-Q19 -> 8240.15
A20: Véhicules neufs | B20: Véhicules neufs
A21: Véhicules neufsRev. Finances | B21: Véhicules neufs | C21: Rev. Finances | D21: 0 | E21: =IF(D21=0,0,F21/D21) -> 0 | F21: 2123.3614 | G21: 0 | H21: =IF(G21=0,0,I21/G21) -> 0 | I21: 2123.3614 | K21: =IF(J13=0,0,L21/(J13+J15)) -> 211.384 | L21: 10569.2 | N21: =L21-I21 -> 8445.8386 | P21: =IF(O13=0,0,Q21/(O13+O15)) -> 17.566923 | Q21: 1598.59 | R21: =O21-K21 -> -211.384 | S21: =L21-Q21 -> 8970.61
A22: Véhicules neufsRev. Protections | B22: Véhicules neufs | C22: Rev. Protections | D22: 0 | E22: =IF(D22=0,0,F22/D22) -> 0 | F22: 56786.344 | G22: 0 | H22: =IF(G22=0,0,I22/G22) -> 0 | I22: 56786.344 | K22: =IF(J13=0,0,L22/(J13+J15)) -> 866.2176 | L22: 43310.88 | N22: =L22-I22 -> -13475.464 | P22: =IF(O13=0,0,Q22/(O13+O15)) -> 841.79264 | Q22: 76603.13 | R22: =O22-K22 -> -866.2176 | S22: =L22-Q22 -> -33292.25
A23: Véhicules neufsRev. Autres | B23: Véhicules neufs | C23: Rev. Autres | D23: 0 | E23: =IF(D23=0,0,F23/D23) -> 0 | F23: 1405.4749 | G23: 0 | H23: =IF(G23=0,0,I23/G23) -> 0 | I23: 1405.4749 | K23: =IF(J13=0,0,L23/(J13+J15)) -> 32.4756 | L23: 1623.78 | N23: =L23-I23 -> 218.30507 | P23: =IF(O13=0,0,Q23/(O13+O15)) -> 18.563297 | Q23: 1689.26 | R23: =O23-K23 -> -32.4756 | S23: =L23-Q23 -> -65.48
A24: Véhicules neufsTotal F&I | B24: Véhicules neufs | C24: Total F&I | D24: =+D15+D13 -> 70.959036 | E24: =IF(D24<=0,0,F24/D24) -> 850 | F24: =F21+F22+F23 -> 60315.181 | G24: =+G15+G13 -> 70.959036 | H24: =IF(G24<=0,0,I24/G24) -> 850 | I24: =I21+I22+I23 -> 60315.181 | J24: =+J15+J13 -> 50 | K24: =IF(J24<=0,0,L24/J24) -> 1110.0772 | L24: =L21+L22+L23 -> 55503.86 | M24: =J24-G24 -> -20.959036 | N24: =L24-I24 -> -4811.3207 | O24: =+O15+O13 -> 91 | P24: =IF(O24<=0,0,Q24/O24) -> 877.92286 | Q24: =Q21+Q22+Q23 -> 79890.98 | S24: =L24-Q24 -> -24387.12
A25: Véhicules neufs | B25: Véhicules neufs | N25: =IF(N24=0,0,N24/I24) -> -0.079769648 | S25: =IF(Q24=0,0,(S24/Q24)) -> -0.30525499
A26: Véhicules neufs | B26: Véhicules neufs
A27: Véhicules neufsTotal Dépt. Neufs | B27: Véhicules neufs | C27: Total Dépt. Neufs | D27: =+D13+D15+D17 -> 72.051324 | E27: =IF(D27<=0,0,F27/D27) -> 2798.6081 | F27: =F13+F17+F24+F19+F15 -> 201643.42 | G27: =+G13+G15+G17 -> 72.051324 | H27: =IF(G27<=0,0,I27/G27) -> 2798.6081 | I27: =I13+I17+I24+I19+I15 -> 201643.42 | J27: =+J13+J15+J17 -> 53 | K27: =IF(J27<=0,0,L27/J27) -> 3612.793 | L27: =L13+L17+L24+L19+L15 -> 191478.03 | M27: =J27-G27 -> -19.051324 | N27: =L27-I27 -> -10165.387 | O27: =+O13+O15+O17 -> 91 | P27: =IF(O27<=0,0,Q27/O27) -> 2706.0704 | Q27: =Q13+Q17+Q24+Q19+Q15 -> 246252.41 | R27: =J27-O27 -> -38 | S27: =L27-Q27 -> -54774.38
A28: Véhicules neufs | B28: Véhicules neufs | M28: =M27/G27 -> -0.26441324 | N28: =N27/I27 -> -0.05041269 | R28: =R27/O27 -> -0.41758242 | S28: =IF(Q27=0,0,S27/Q27) -> -0.22243185
A29: Véhicules neufs | B29: Véhicules neufs
A30: Véhicules neufsDEPENSES | B30: Véhicules neufs | C30: DEPENSES
A31: Véhicules neufsComm. vendeurs | B31: Véhicules neufs | C31: Comm. vendeurs | D31: =F31/(F15+F13+F17) -> 0.32409988 | E31: =F31/D$24 -> 623.08263 | F31: 44213.343 | G31: =I31/(I15+I13) -> 0.32921065 | H31: =I31/G$24 -> 623.08263 | I31: 44213.343 | J31: =L31/(L15+L13+L17) -> 0.31406537 | K31: =IF(L31=0,0,L31/J$24) -> 768.0872 | L31: 38404.36 | N31: =L31-I31 -> -5808.9828 | P31: =IF(Q31=0,0,Q31/O$24) -> 631.62824 | Q31: 57478.17 | S31: =L31-Q31 -> -19073.81
A32: Véhicules neufsComm. F&I | B32: Véhicules neufs | C32: Comm. F&I | D32: =F32/F24 -> 0.3 | E32: =F32/D$24 -> 255 | F32: 18094.554 | G32: =I32/I24 -> 0.3 | H32: =I32/G$24 -> 255 | I32: 18094.554 | J32: =L32/L24 -> 0.34749475 | K32: =IF(L32=0,0,L32/J$24) -> 385.746 | L32: 19287.3 | N32: =L32-I32 -> 1192.7458 | P32: =IF(Q32=0,0,Q32/O$24) -> 259.28209 | Q32: 23594.67 | S32: =L32-Q32 -> -4307.37 | U32: =(L32+L112)/(L104+L24+L19) -> 0.23827681 | V32: <<- F&A total Neuf Usagé Rachat
A33: Véhicules neufsFrais de livraison | B33: Véhicules neufs | C33: Frais de livraison | E33: =F33/D$24 -> 167.8493 | F33: 11910.425 | H33: =I33/G$24 -> 167.8493 | I33: 11910.425 | K33: =IF(L33=0,0,L33/J$24) -> -22.501 | L33: -1125.05 | N33: =L33-I33 -> -13035.475 | P33: =IF(Q33=0,0,Q33/O$24) -> 109.96538 | Q33: 10006.85 | S33: =L33-Q33 -> -11131.9
A34: Véhicules neufsService gratuit 1 | B34: Véhicules neufs | C34: Service gratuit 1 | E34: =F34/D$24 -> 7.3548076 | F34: 521.89006 | H34: =I34/G$24 -> 7.3548076 | I34: 521.89006 | K34: =IF(L34=0,0,L34/J$24) -> 0.58 | L34: 29 | N34: =L34-I34 -> -492.89006 | P34: =IF(Q34=0,0,Q34/O$24) -> 18.107692 | Q34: 1647.8 | S34: =L34-Q34 -> -1618.8
A35: Véhicules neufsEntretien stock | B35: Véhicules neufs | C35: Entretien stock | E35: =F35/D$24 -> 17.733118 | F35: 1258.325 | H35: =I35/G$24 -> 17.733118 | I35: 1258.325 | K35: =IF(L35=0,0,L35/J$24) -> 71.9218 | L35: 3596.09 | N35: =L35-I35 -> 2337.765 | P35: =IF(Q35=0,0,Q35/O$24) -> 10.88989 | Q35: 990.98 | S35: =L35-Q35 -> 2605.11
A36: Véhicules neufsPublicité 1 | B36: Véhicules neufs | C36: Publicité 1 | E36: =F36/D$24 -> 195.93765 | F36: 13903.547 | H36: =I36/G$24 -> 195.93765 | I36: 13903.547 | K36: =IF(L36=0,0,L36/J$24) -> 40.1874 | L36: 2009.37 | N36: =L36-I36 -> -11894.177 | P36: =IF(Q36=0,0,Q36/O$24) -> 59.356374 | Q36: 5401.43 | S36: =L36-Q36 -> -3392.06
A37: Véhicules neufsIntérêt de gros | B37: Véhicules neufs | C37: Intérêt de gros | E37: =F37/D$24 -> 117.38963 | F37: 8329.8552 | H37: =I37/G$24 -> 117.38963 | I37: 8329.8552 | K37: =IF(L37=0,0,L37/J$24) -> 105.5194 | L37: 5275.97 | N37: =L37-I37 -> -3053.8852 | P37: =IF(Q37=0,0,Q37/O$24) -> 143.12824 | Q37: 13024.67 | S37: =L37-Q37 -> -7748.7
A38: Véhicules neufs[...] | B38: Véhicules neufs | C38: [...] | E38: =F38/D$24 -> 0 | F38: 0 | H38: =I38/G$24 -> 0 | I38: 0 | K38: =IF(L38=0,0,L38/J$24) -> 0 | L38: 0 | N38: =L38-I38 -> 0 | P38: =IF(Q38=0,0,Q38/O$24) -> 0 | Q38: 0 | S38: =L38-Q38 -> 0
A39: Véhicules neufs[...] | B39: Véhicules neufs | C39: [...] | E39: =F39/D$24 -> 0 | F39: 0 | H39: =I39/G$24 -> 0 | I39: 0 | K39: =IF(L39=0,0,L39/J$24) -> 0 | L39: 0 | N39: =L39-I39 -> 0 | P39: =IF(Q39=0,0,Q39/O$24) -> 0 | Q39: 0 | S39: =L39-Q39 -> 0
A40: Véhicules neufs[...] | B40: Véhicules neufs | C40: [...] | E40: =F40/D$24 -> 0 | F40: 0 | H40: =I40/G$24 -> 0 | I40: 0 | K40: =IF(L40=0,0,L40/J$24) -> 0 | L40: 0 | N40: =L40-I40 -> 0 | P40: =IF(Q40=0,0,Q40/O$24) -> 0 | Q40: 0 | S40: =L40-Q40 -> 0
A41: Véhicules neufsTOTAL VARIABLES | B41: Véhicules neufs | C41: TOTAL VARIABLES | D41: % brut | E41: =F41/F$27 -> 0.48715669 | F41: =SUM(F31:F40) -> 98231.939 | G41: % brut | H41: =I41/I$27 -> 0.48715669 | I41: =SUM(I31:I40) -> 98231.939 | J41: % brut | K41: =L41/L$27 -> 0.35240095 | L41: =SUM(L31:L40) -> 67477.04 | N41: =L41-I41 -> -30754.899 | O41: % brut | P41: =Q41/Q$27 -> 0.45540496 | Q41: =SUM(Q31:Q40) -> 112144.57 | S41: =L41-Q41 -> -44667.53
A42: Véhicules neufsSalaires cadres | B42: Véhicules neufs | C42: Salaires cadres | F42: 15886.261 | I42: 15886.261 | L42: 15311.7 | N42: =L42-I42 -> -574.56092 | Q42: 13531.66 | S42: =L42-Q42 -> 1780.04
A43: Véhicules neufsSalaires commis | B43: Véhicules neufs | C43: Salaires commis | F43: 9822.0278 | I43: 9822.0278 | L43: 7250.31 | N43: =L43-I43 -> -2571.7178 | Q43: 9370.2 | S43: =L43-Q43 -> -2119.89
A44: Véhicules neufsSalaires autres | B44: Véhicules neufs | C44: Salaires autres | F44: 8921.4022 | I44: 8921.4022 | L44: 4701.98 | N44: =L44-I44 -> -4219.4222 | Q44: 10113.58 | S44: =L44-Q44 -> -5411.6
A45: Véhicules neufsSalaires spécialistes | B45: Véhicules neufs | C45: Salaires spécialistes | F45: 0 | I45: 0 | L45: 0 | N45: =L45-I45 -> 0 | Q45: 0 | S45: =L45-Q45 -> 0
A46: Véhicules neufs[...] | B46: Véhicules neufs | C46: [...] | F46: 0 | I46: 0 | L46: 0 | N46: =L46-I46 -> 0 | Q46: 0 | S46: =L46-Q46 -> 0
A47: Véhicules neufs[...] | B47: Véhicules neufs | C47: [...] | F47: 0 | I47: 0 | L47: 0 | N47: =L47-I47 -> 0 | Q47: 0 | S47: =L47-Q47 -> 0
A48: Véhicules neufs[...] | B48: Véhicules neufs | C48: [...] | F48: 0 | I48: 0 | L48: 0 | N48: =L48-I48 -> 0 | Q48: 0 | S48: =L48-Q48 -> 0
A49: Véhicules neufsSalaires en absences | B49: Véhicules neufs | C49: Salaires en absences | F49: 11834.459 | I49: 11834.459 | L49: 16149.39 | N49: =L49-I49 -> 4314.9307 | Q49: 19957.87 | S49: =L49-Q49 -> -3808.48
A50: Véhicules neufsDéduction à la source | B50: Véhicules neufs | C50: Déduction à la source | F50: 10598.971 | I50: 10598.971 | L50: 15963.55 | N50: =L50-I50 -> 5364.5786 | Q50: 11643.89 | S50: =L50-Q50 -> 4319.66
A51: Véhicules neufsBénéfices marginaux | B51: Véhicules neufs | C51: Bénéfices marginaux | F51: 8416.8302 | I51: 8416.8302 | L51: 3861.07 | N51: =L51-I51 -> -4555.7602 | Q51: 8344.79 | S51: =L51-Q51 -> -4483.72
A52: Véhicules neufsCsst | B52: Véhicules neufs | C52: Csst | F52: 3429.079 | I52: 3429.079 | L52: 3464 | N52: =L52-I52 -> 34.921018 | Q52: 1940.65 | S52: =L52-Q52 -> 1523.35
A53: Véhicules neufs[...] | B53: Véhicules neufs | C53: [...] | F53: 0 | I53: 0 | L53: 0 | N53: =L53-I53 -> 0 | Q53: 0 | S53: =L53-Q53 -> 0
A54: Véhicules neufsTOTAL PERSONNEL | B54: Véhicules neufs | C54: TOTAL PERSONNEL | D54: % brut | E54: =F54/F$27 -> 0.34173707 | F54: =+SUM(F42:F53) -> 68909.031 | G54: % brut | H54: =I54/I$27 -> 0.34173707 | I54: =+SUM(I42:I53) -> 68909.031 | J54: % brut | K54: =L54/L$27 -> 0.34835328 | L54: =+SUM(L42:L53) -> 66702 | N54: =+SUM(N42:N53) -> -2207.0308 | O54: % brut | P54: =Q54/Q$27 -> 0.30417018 | Q54: =+SUM(Q42:Q53) -> 74902.64 | S54: =+SUM(S42:S53) -> -8200.64
A55: Véhicules neufsPublicité 2 | B55: Véhicules neufs | C55: Publicité 2 | F55: 0 | I55: 0 | L55: 0 | N55: =L55-I55 -> 0 | Q55: 0 | S55: =L55-Q55 -> 0
A56: Véhicules neufsService gratuit 2 | B56: Véhicules neufs | C56: Service gratuit 2 | F56: 0 | I56: 0 | L56: 0 | N56: =L56-I56 -> 0 | Q56: 0 | S56: =L56-Q56 -> 0
A57: Véhicules neufsFrais véhicules de cie | B57: Véhicules neufs | C57: Frais véhicules de cie | F57: 7322.94 | I57: 7322.94 | L57: 10992.77 | N57: =L57-I57 -> 3669.83 | Q57: 10906.6 | S57: =L57-Q57 -> 86.17
A58: Véhicules neufsInformatique | B58: Véhicules neufs | C58: Informatique | F58: 6834.1988 | I58: 6834.1988 | L58: 9124.25 | N58: =L58-I58 -> 2290.0512 | Q58: 5095.99 | S58: =L58-Q58 -> 4028.26
A59: Véhicules neufsFrais de déplacement | B59: Véhicules neufs | C59: Frais de déplacement | F59: 792.1418 | I59: 792.1418 | L59: 1275.21 | N59: =L59-I59 -> 483.0682 | Q59: 302.31 | S59: =L59-Q59 -> 972.9
A60: Véhicules neufsServices extérieurs | B60: Véhicules neufs | C60: Services extérieurs | F60: 6468.477 | I60: 6468.477 | L60: 6733.83 | N60: =L60-I60 -> 265.35302 | Q60: 6195.91 | S60: =L60-Q60 -> 537.92
A61: Véhicules neufsFournitures autres | B61: Véhicules neufs | C61: Fournitures autres | F61: 81.641328 | I61: 81.641328 | L61: 137.58 | N61: =L61-I61 -> 55.938672 | Q61: 328.47 | S61: =L61-Q61 -> -190.89
A62: Véhicules neufsUniformes | B62: Véhicules neufs | C62: Uniformes | F62: 43.382055 | I62: 43.382055 | L62: 0 | N62: =L62-I62 -> -43.382055 | Q62: 0 | S62: =L62-Q62 -> 0
A63: Véhicules neufsPapeterie | B63: Véhicules neufs | C63: Papeterie | F63: 652.86432 | I63: 652.86432 | L63: 903.86 | N63: =L63-I63 -> 250.99568 | Q63: 247.99 | S63: =L63-Q63 -> 655.87
A64: Véhicules neufsTéléphone | B64: Véhicules neufs | C64: Téléphone | F64: 301.46453 | I64: 301.46453 | L64: 252.48 | N64: =L64-I64 -> -48.984527 | Q64: 538.56 | S64: =L64-Q64 -> -286.08
A65: Véhicules neufsFrais postaux | B65: Véhicules neufs | C65: Frais postaux | F65: 160.91707 | I65: 160.91707 | L65: 152.24 | N65: =L65-I65 -> -8.6770733 | Q65: 158.11 | S65: =L65-Q65 -> -5.87
A66: Véhicules neufsDivers | B66: Véhicules neufs | C66: Divers | F66: 776.23359 | I66: 776.23359 | L66: 151.58 | N66: =L66-I66 -> -624.65359 | Q66: 1009.27 | S66: =L66-Q66 -> -857.69
A67: Véhicules neufsFormation | B67: Véhicules neufs | C67: Formation | F67: 1153.2563 | I67: 1153.2563 | L67: 1314.69 | N67: =L67-I67 -> 161.43373 | Q67: 743.39 | S67: =L67-Q67 -> 571.3
A68: Véhicules neufsFrais bancaires | B68: Véhicules neufs | C68: Frais bancaires | F68: 1527.324 | I68: 1527.324 | L68: 3481 | N68: =L68-I68 -> 1953.676 | Q68: =AL447*W3 -> 2915.2845 | S68: =L68-Q68 -> 565.7155
A69: Véhicules neufs[...] | B69: Véhicules neufs | C69: [...] | F69: 0 | I69: 0 | N69: =L69-I69 -> 0 | Q69: 0 | S69: =L69-Q69 -> 0
A70: Véhicules neufs[...] | B70: Véhicules neufs | C70: [...] | F70: 0 | I70: 0 | L70: 0 | N70: =L70-I70 -> 0 | Q70: 0 | S70: =L70-Q70 -> 0
A71: Véhicules neufs[...] | B71: Véhicules neufs | C71: [...] | F71: 0 | I71: 0 | L71: 0 | N71: =L71-I71 -> 0 | Q71: 0 | S71: =L71-Q71 -> 0
A72: Véhicules neufsTOTAL SEMI-FIXES | B72: Véhicules neufs | C72: TOTAL SEMI-FIXES | D72: % brut | E72: =F72/F$27 -> 0.12951001 | F72: =+SUM(F55:F71) -> 26114.841 | G72: % brut | H72: =I72/I$27 -> 0.12951001 | I72: =+SUM(I55:I71) -> 26114.841 | J72: % brut | K72: =L72/L$27 -> 0.18027912 | L72: =+SUM(L55:L71) -> 34519.49 | N72: =+SUM(N55:N71) -> 8404.6492 | O72: % brut | P72: =Q72/Q$27 -> 0.11549891 | Q72: =+SUM(Q55:Q71) -> 28441.885 | S72: =+SUM(S55:S71) -> 6077.6055
A73: Véhicules neufs | B73: Véhicules neufs
A74: Véhicules neufsTOTAL DES DÉPENSES | B74: Véhicules neufs | C74: TOTAL DES DÉPENSES | D74: % brut | E74: =F74/F$27 -> 0.95840377 | F74: =F41+F54+F72 -> 193255.81 | G74: % brut | H74: =I74/I$27 -> 0.95840377 | I74: =I41+I54+I72 -> 193255.81 | J74: % brut | K74: =L74/L$27 -> 0.88103335 | L74: =L41+L54+L72 -> 168698.53 | N74: =L74-I74 -> -24557.281 | O74: % brut | P74: =Q74/Q$27 -> 0.87507405 | Q74: =Q41+Q54+Q72 -> 215489.09 | S74: =L74-Q74 -> -46790.565
A75: Véhicules neufsProgramme neuf 1 | B75: Véhicules neufs | C75: Programme neuf 1 | F75: 19143.9 | I75: 19143.9 | L75: 0 | N75: =L75-I75 -> -19143.9 | Q75: 8500
A76: Véhicules neufsProgramme neuf 2 | B76: Véhicules neufs | C76: Programme neuf 2 | F76: 0 | I76: 0 | L76: 0 | N76: =L76-I76 -> 0 | Q76: 0 | S76: =L76-Q76 -> 0
A77: Véhicules neufsProgramme neuf 3 | B77: Véhicules neufs | C77: Programme neuf 3 | F77: 0 | I77: 0 | L77: 0 | N77: =L77-I77 -> 0 | Q77: 0 | S77: =L77-Q77 -> 0
A78: Véhicules neufsHoldbacks | B78: Véhicules neufs | C78: Holdbacks | E78: =+F78/D24 -> 1061.3926 | F78: 75315.397 | I78: 75315.397 | K78: =+L78/J24 -> 1255.76 | L78: 62788 | N78: =L78-I78 -> -12527.397 | Q78: 82259.7 | S78: =L78-Q78 -> -19471.7 | U78: 4 Locate sans retour
A79: Véhicules neufs[...] | B79: Véhicules neufs | C79: [...] | F79: 0 | I79: 0 | L79: 0 | N79: =L79-I79 -> 0 | Q79: 0 | S79: =L79-Q79 -> 0
A80: Véhicules neufs[...] | B80: Véhicules neufs | C80: [...] | F80: 0 | I80: 0 | L80: 0 | N80: =L80-I80 -> 0 | Q80: 0 | S80: =L80-Q80 -> 0
A81: Véhicules neufs[...] | B81: Véhicules neufs | C81: [...] | F81: 0 | I81: 0 | L81: 0 | N81: =L81-I81 -> 0 | Q81: 0 | S81: =L81-Q81 -> 0
A82: Véhicules neufsFrais administration | B82: Véhicules neufs | C82: Frais administration | F82: 25873.631 | I82: 25873.631 | J82: =+L82/K82 -> 53 | K82: =+L82/J27 -> 359.50943 | L82: 19054 | N82: =L82-I82 -> -6819.6306 | Q82: 28303.7 | S82: =L82-Q82 -> -9249.7
A83: Véhicules neufsAUTRES REVENUS | B83: Véhicules neufs | C83: AUTRES REVENUS | F83: =+SUM(F75:F82) -> 120332.93 | I83: =+SUM(I75:I82) -> 120332.93 | L83: =+SUM(L75:L82) -> 81842 | N83: =+SUM(N75:N82) -> -38490.927 | Q83: =+SUM(Q75:Q82) -> 119063.4 | S83: =+SUM(S75:S82) -> -28721.4
A84: Véhicules neufs | B84: Véhicules neufs
A85: Véhicules neufsPROFIT DÉPARTEMENTAL | B85: Véhicules neufs | C85: PROFIT DÉPARTEMENTAL | F85: =F27-F74+F83 -> 128720.53 | I85: =I27-I74+I83 -> 128720.53 | L85: =L27-L74+L83 -> 104621.5 | N85: =N27-N41-N54-N72+N83 -> -24099.034 | Q85: =Q27-Q74+Q83 -> 149826.72 | S85: =S27-S41-S54-S72+S83 -> -36705.215
C89: =C1 -> Volks | K89: Véhicules usagés | S89: =$S$1 -> Réalisé, Septembre 2022
D91: BUDGET ORIGINAL | G91: BUDGET RÉVISÉ | J91: RÉALISATION | M91: ÉCART réel / révisé | O91: ANNÉE PRÉCÉDENTE | R91: ÉCART réel / original
D92: UNITE | E92: $P/UNITÉ | F92: $PROFITS | G92: UNITE | H92: $P/UNITÉ | I92: $PROFITS | J92: UNITE | K92: $P/UNITE | L92: $PROFITS | M92: UNITÉ | N92: $PROFITS | O92: UNITE | P92: $P/UNITE | Q92: $PROFITS | R92: UNITE | S92: $PROFITS
A93: Véhicules usagésVentes nettes | B93: Véhicules usagés | C93: Ventes nettes | F93: 1096969.1 | I93: 1096969.1 | L93: 1750102 | Q93: 1490681.9
A94: Véhicules usagésCertifié | B94: Véhicules usagés | C94: Certifié | D94: 33.48301 | E94: =IF(D94=0,0,F94/D94) -> 1300 | F94: 43527.913 | G94: 33.48301 | H94: =IF(G94=0,0,I94/G94) -> 1300 | I94: 43527.913 | J94: 34 | K94: =IF(J94=0,0,L94/J94) -> 1821.8274 | L94: 61942.13 | M94: =J94-G94 -> 0.51699029 | N94: =L94-I94 -> 18414.217 | O94: 35 | P94: =IF(O94=0,0,Q94/O94) -> 1430.5171 | Q94: 50068.1 | R94: =J94-O94 -> -1 | S94: =L94-Q94 -> 11874.03
A95: Véhicules usagésNon Certifié | B95: Véhicules usagés | C95: Non Certifié | D95: 1.881068 | E95: =IF(D95=0,0,F95/D95) -> 900 | F95: 1692.9612 | G95: 1.881068 | H95: =IF(G95=0,0,I95/G95) -> 900 | I95: 1692.9612 | J95: 0 | K95: =IF(J95=0,0,L95/J95) -> 0 | L95: 0 | M95: =J95-G95 -> -1.881068 | N95: =L95-I95 -> -1692.9612 | O95: 3 | P95: =IF(O95=0,0,Q95/O95) -> 2373.38 | Q95: 7120.14 | R95: =J95-O95 -> -3 | S95: =L95-Q95 -> -7120.14
A96: Véhicules usagésTotal Usagés | B96: Véhicules usagés | C96: Total Usagés | D96: =+D95+D94 -> 35.364078 | E96: =IF(D96=0,0,F96/D96) -> 1278.7234 | F96: =+F94+F95 -> 45220.874 | G96: =+G95+G94 -> 35.364078 | H96: =IF(G96=0,0,I96/G96) -> 1278.7234 | I96: =+I94+I95 -> 45220.874 | J96: =+J94+J95 -> 34 | K96: =IF(J96<=0,0,L96/J96) -> 1821.8274 | L96: =+L94+L95 -> 61942.13 | M96: =J96-G96 -> -1.3640777 | N96: =L96-I96 -> 16721.256 | O96: =+O94+O95 -> 38 | P96: =IF(O96<=0,0,Q96/O96) -> 1504.9537 | Q96: =+Q94+Q95 -> 57188.24 | R96: =R94+R95 -> -4 | S96: =S94+S95 -> 4753.89
A97: Véhicules usagés | B97: Véhicules usagés | E97: =IF(D97=0,0,F97/D97) -> 0 | H97: =IF(G97=0,0,I97/G97) -> 0 | M97: =M96/G96 -> -0.038572409 | N97: =N96/I96 -> 0.36976853 | R97: =R96/O96 -> -0.10526316 | S97: =IF(Q96=0,0,(S96/Q96)) -> 0.083127055
A98: Véhicules usagésUS | B98: Véhicules usagés | C98: US | U98: Fichier Contrôle
A99: Véhicules usagésVentes au Gros | B99: Véhicules usagés | C99: Ventes au Gros | D99: 30.77357 | E99: =IF(D99=0,0,F99/D99) -> 212 | F99: 6523.9968 | G99: 30.77357 | H99: =IF(G99=0,0,I99/G99) -> 212 | I99: 6523.9968 | J99: 39 | K99: =IF(J99=0,0,L99/J99) -> 400.72128 | L99: 15628.13 | M99: =J99-G99 -> 8.2264302 | N99: =L99-I99 -> 9104.1332 | O99: 51 | P99: =IF(O99=0,0,Q99/O99) -> 502.51608 | Q99: 25628.32 | R99: =J99-O99 -> -12 | S99: =L99-Q99 -> -10000.19 | U99: 0.99 | V99: =+L99-U99 -> 15627.14
A100: Véhicules usagés | B100: Véhicules usagés
A101: Véhicules usagésRev. Finances | B101: Véhicules usagés | C101: Rev. Finances | D101: 0 | E101: =IF(D101=0,0,F101/D101) -> 0 | F101: 23303.545 | G101: 0 | H101: =IF(G101=0,0,I101/G101) -> 0 | I101: 23303.545 | K101: =IF(J96=0,0,L101/J96) -> 769.67676 | L101: 26169.01 | N101: =L101-I101 -> 2865.4651 | P101: =IF(O96=0,0,Q101/O96) -> 1008.9971 | Q101: 38341.89 | R101: =O101-K101 -> -769.67676 | S101: =L101-Q101 -> -12172.88
A102: Véhicules usagésRev. Protections | B102: Véhicules usagés | C102: Rev. Protections | D102: 0 | E102: =IF(D102=0,0,F102/D102) -> 0 | F102: 41087.566 | G102: 0 | H102: =IF(G102=0,0,I102/G102) -> 0 | I102: 41087.566 | K102: =IF(J96=0,0,L102/J96) -> 1083.0562 | L102: 36823.91 | N102: =L102-I102 -> -4263.6555 | P102: =IF(O96=0,0,Q102/O96) -> 1167.8826 | Q102: 44379.54 | R102: =O102-K102 -> -1083.0562 | S102: =L102-Q102 -> -7555.63
A103: Véhicules usagésRev. Autres | B103: Véhicules usagés | C103: Rev. Autres | D103: 0 | E103: =IF(D103=0,0,F103/D103) -> 0 | F103: 1165.3598 | G103: 0 | H103: =IF(G103=0,0,I103/G103) -> 0 | I103: 1165.3598 | K103: =IF(J96=0,0,L103/J96) -> 14.570294 | L103: 495.39 | N103: =L103-I103 -> -669.96979 | P103: =IF(O96=0,0,Q103/O96) -> 63.622105 | Q103: 2417.64 | R103: =O103-K103 -> -14.570294 | S103: =L103-Q103 -> -1922.25
A104: Véhicules usagésTotal F&I | B104: Véhicules usagés | C104: Total F&I | D104: =D96 -> 35.364078 | E104: =IF(D104=0,0,F104/D104) -> 1853.7588 | F104: =F101+F102+F103 -> 65556.47 | G104: =G96 -> 35.364078 | H104: =IF(G104=0,0,I104/G104) -> 1853.7588 | I104: =I101+I102+I103 -> 65556.47 | J104: =J96 -> 34 | K104: =IF(J104<=0,0,L104/J104) -> 1867.3032 | L104: =L101+L102+L103 -> 63488.31 | M104: =J104-G104 -> -1.3640777 | N104: =L104-I104 -> -2068.1602 | O104: =O96 -> 38 | P104: =IF(O104<=0,0,Q104/O104) -> 2240.5018 | Q104: =Q101+Q102+Q103 -> 85139.07 | S104: =L104-Q104 -> -21650.76
...

Sheet END
