Workbook
Name _Dates_Conc: [1]Dealers!$BF$37:$KA$63
Name _scen: '[1]Scen & Sens'!$E$26
Name _scen1: '[1]Scen & Sens'!$E$27
Name _scen2: '[1]Scen & Sens'!$E$28
Name _SCenarios: '[1]Scen & Sens'!$J$26:$O$26
Name _Sens1: '[1]Scen & Sens'!$F$9
Name _Sens2: '[1]Scen & Sens'!$F$10
Name _sensRes1: '[1]Scen & Sens'!$E$15
Name _sensRes2: '[1]Scen & Sens'!$E$16
Name _sensRes3: '[1]Scen & Sens'!$E$17
Name _sensRes4: '[1]Scen & Sens'!$E$18
Name _sensRes5: '[1]Scen & Sens'!$E$19
Name _sensRes6: '[1]Scen & Sens'!$E$20
Name _sensRes7: '[1]Scen & Sens'!$E$21
Name DateRange: [1]Volkswagen!$BF$6:$DY$6
Name Monetary_Unit: [1]Parameters!$B$15
Name Months: [1]Parameters!$E$9:$E$20
Name Rng_Dealers_Names: [1]!Tbl_Dealers[Dealer Name]
Name Rng_Dlr_Dates: [1]!Tbl_V_Dlr_Dates[Date]
Name Titre: [1]Front!$A$9

Sheet Paramètre
B3: AUDI QUARTER
B6: BUDGET | F6: BUDGET RÉVISÉ | J6: ACTUAL | N6: LAST YEAR
B7: Ventes | C7: Profits bruts | D7: BAIIA | E7: EBIT | F7: Ventes | G7: Profits bruts | H7: BAIIA | I7: EBIT | J7: Ventes | K7: Profits bruts | L7: BAIIA | M7: EBIT | N7: Ventes | O7: Profits bruts | P7: BAIIA | Q7: EBIT
A8: CTRL | B8: =+B9-B10 -> 0 | C8: =+C9-C10 -> 0 | D8: =+D9-D10 -> 0 | E8: =+E9-E10 -> 0 | F8: =+F9-F10 -> 0 | G8: =+G9-G10 -> 0 | H8: =+H9-H10 -> 0 | I8: =+I9-I10 -> 0 | ... Q8: =+Q9-Q10 -> 0
A9: CONSO | B9: =+Conso!$Z$405 -> 8038384.2 | C9: =+Conso!$Z$406 -> 1712610.5 | D9: =+Conso!$Z$482 -> 409156.36 | E9: =+Conso!$Z$497 -> 378559.99 | F9: =+Conso!$AC$405 -> 8038384.2 | G9: =+Conso!$AC$406 -> 1778116.1 | H9: =+Conso!$AC$482 -> 396422.33 | I9: =+Conso!$AC$497 -> 365825.96 | J9: =+Conso!$AF$405 -> 16048941 | K9: =+Conso!$AF$406 -> 1948196.7 | L9: =+Conso!$AF$482 -> 633129.42 | M9: =+Conso!$AF$497 -> 633961.81 | N9: =+Conso!$AL$405 -> 15054918 | O9: =+Conso!$AL$406 -> 1646743.3 | P9: =+Conso!$AL$482 -> 270793.34 | Q9: =+Conso!$AL$497 -> 231534.21
A10: TOTAL | B10: =+SUM(B11:B13) -> 8038384.2 | C10: =+SUM(C11:C13) -> 1712610.5 | D10: =+SUM(D11:D13) -> 409156.36 | E10: =+SUM(E11:E13) -> 378559.99 | F10: =+SUM(F11:F13) -> 8038384.2 | G10: =+SUM(G11:G13) -> 1778116.1 | H10: =+SUM(H11:H13) -> 396422.33 | I10: =+SUM(I11:I13) -> 365825.96 | ... Q10: =+SUM(Q11:Q13) -> 231534.21
A11: AUDI 1 | B11: =+'VW 4'!$Z$405 -> 2470120.3 | C11: =+'VW 4'!$Z$406 -> 545849 | D11: =+'VW 4'!$Z$482 -> 130720.25 | E11: =+'VW 4'!$Z$497 -> 120519.68 | F11: =+'VW 4'!$AC$405 -> 2470120.3 | G11: =+'VW 4'!$AC$406 -> 574246.67 | H11: =+'VW 4'!$AC$482 -> 121216.05 | I11: =+'VW 4'!$AC$497 -> 111015.48 | J11: =+'VW 4'!$AF$405 -> 5121135.5 | K11: =+'VW 4'!$AF$406 -> 640912.74 | L11: =+'VW 4'!$AF$482 -> 194923.31 | M11: =+'VW 4'!$AF$497 -> 187231.25 | N11: =+'VW 4'!$AL$405 -> 4604575.2 | O11: =+'VW 4'!$AL$406 -> 538002.03 | P11: =+'VW 4'!$AL$482 -> 114960.78 | Q11: =+'VW 4'!$AL$497 -> 102916.93
A12: AUDI 2 | B12: =+'VW 5'!$Z$405 -> 3070578.4 | C12: =+'VW 5'!$Z$406 -> 640640.26 | D12: =+'VW 5'!$Z$482 -> 205500.39 | E12: =+'VW 5'!$Z$497 -> 195297.69 | F12: =+'VW 5'!$AC$405 -> 3070578.4 | G12: =+'VW 5'!$AC$406 -> 677748.24 | H12: =+'VW 5'!$AC$482 -> 202270.56 | I12: =+'VW 5'!$AC$497 -> 192067.87 | J12: =+'VW 5'!$AF$405 -> 5749670.9 | K12: =+'VW 5'!$AF$406 -> 685822.65 | L12: =+'VW 5'!$AF$482 -> 267930.12 | M12: =+'VW 5'!$AF$497 -> 281298.69 | N12: =+'VW 5'!$AL$405 -> 5181423.9 | O12: =+'VW 5'!$AL$406 -> 554370.65 | P12: =+'VW 5'!$AL$482 -> 77916.28 | Q12: =+'VW 5'!$AL$497 -> 64308.64
A13: AUDI 3 | B13: =+'VW 6'!$Z$405 -> 2497685.5 | C13: =+'VW 6'!$Z$406 -> 526121.24 | D13: =+'VW 6'!$Z$482 -> 72935.719 | E13: =+'VW 6'!$Z$497 -> 62742.617 | F13: =+'VW 6'!$AC$405 -> 2497685.5 | G13: =+'VW 6'!$AC$406 -> 526121.24 | H13: =+'VW 6'!$AC$482 -> 72935.719 | I13: =+'VW 6'!$AC$497 -> 62742.617 | J13: =+'VW 6'!$AF$405 -> 5178134.8 | K13: =+'VW 6'!$AF$406 -> 621461.3 | L13: =+'VW 6'!$AF$482 -> 170275.99 | M13: =+'VW 6'!$AF$497 -> 165431.87 | N13: =+'VW 6'!$AL$405 -> 5268919.3 | O13: =+'VW 6'!$AL$406 -> 554370.65 | P13: =+'VW 6'!$AL$482 -> 77916.28 | Q13: =+'VW 6'!$AL$497 -> 64308.64

Sheet Conso
C1: Conso | K1: Véhicules neufs | S1: =CONCATENATE("Réalisé"," ",Paramètre!$C$2," ",Paramètre!$C$3) -> Réalisé | V1: BUDGET | W1: RÉVISÉ | X1: ACTUAL | Y1: LY
D2: X | E2: O | F2: U | G2: X | H2: O | I2: U
D3: BUDGET ORIGINAL | G3: BUDGET REVISE | J3: RÉALISATION | M3: ÉCART réel / révisé | O3: ANNÉE PRÉCÉDENTE | R3: ÉCART réel / original
D4: UNITE | E4: $P/UNITÉ | F4: $PROFITS | G4: UNITE | H4: $P/UNITÉ | I4: $PROFITS | J4: UNITE | K4: $P/UNITE | L4: $PROFITS | M4: UNITÉ | N4: $PROFITS | O4: UNITE | P4: $P/UNITE | Q4: $PROFITS | R4: UNITE | S4: $PROFITS | V4: =+SUM(V5:V398) -> 0 | W4: =+SUM(W5:W398) -> 0 | X4: =+SUM(X5:X398) -> 0 | Y4: =+SUM(Y5:Y398) -> 0
A5: =+B5&C5 -> Véhicules neufsVentes nettes | B5: =+$K$1 -> Véhicules neufs | C5: Ventes nettes | F5: =+SUM(START:END!F5) -> 2424853.6 | I5: =+SUM(START:END!I5) -> 2424853.6 | L5: =+SUM(START:END!L5) -> 9687350 | Q5: =+SUM(START:END!Q5) -> 9378048.7
A6: =+B6&C6 -> Véhicules neufsAutos détail | B6: =+$K$1 -> Véhicules neufs | C6: Autos détail | D6: =+SUM(START:END!D6) -> 98.886679 | E6: =IF(D6=0,0,F6/D6) -> 629.09316 | F6: =+SUM(START:END!F6) -> 62208.934 | G6: =+SUM(START:END!G6) -> 88.126469 | H6: =IF(G6=0,0,I6/G6) -> 957.16463 | I6: =+SUM(START:END!I6) -> 84351.539 | J6: =+SUM(START:END!J6) -> 72 | K6: =IF(J6=0,0,L6/J6) -> 884.42153 | L6: =+SUM(START:END!L6) -> 63678.35 | M6: =J6-G6 -> -16.126469 | N6: =L6-I6 -> -20673.189 | O6: =+SUM(START:END!O6) -> 164 | P6: =IF(O6=0,0,Q6/O6) -> 634.92622 | Q6: =+SUM(START:END!Q6) -> 104127.9 | R6: =J6-O6 -> -92 | S6: =L6-Q6 -> -40449.55
A7: =+B7&C7 -> Véhicules neufsCamions détail | B7: =+$K$1 -> Véhicules neufs | C7: Camions détail | D7: =+SUM(START:END!D7) -> 132.82798 | E7: =IF(D7=0,0,F7/D7) -> 1273.5738 | F7: =+SUM(START:END!F7) -> 169166.23 | G7: =+SUM(START:END!G7) -> 118.79364 | H7: =IF(G7=0,0,I7/G7) -> 1700.4049 | I7: =+SUM(START:END!I7) -> 201997.29 | J7: =+SUM(START:END!J7) -> 131 | K7: =IF(J7=0,0,L7/J7) -> 2187.6411 | L7: =+SUM(START:END!L7) -> 286580.99 | M7: =J7-G7 -> 12.20636 | N7: =L7-I7 -> 84583.699 | O7: =+SUM(START:END!O7) -> 74 | P7: =IF(O7=0,0,Q7/O7) -> 871.185 | Q7: =+SUM(START:END!Q7) -> 64467.69 | R7: =J7-O7 -> 57 | S7: =L7-Q7 -> 222113.3
A8: =+B8&C8 -> Véhicules neufsSprinter | B8: =+$K$1 -> Véhicules neufs | C8: Sprinter | D8: =+SUM(START:END!D8) -> 0 | E8: =IF(D8=0,0,F8/D8) -> 0 | F8: =+SUM(START:END!F8) -> 0 | G8: =+SUM(START:END!G8) -> 0 | H8: =IF(G8=0,0,I8/G8) -> 0 | I8: =+SUM(START:END!I8) -> 0 | J8: =+SUM(START:END!J8) -> 0 | K8: =IF(J8=0,0,L8/J8) -> 0 | L8: =+SUM(START:END!L8) -> 0 | M8: =J8-G8 -> 0 | N8: =L8-I8 -> 0 | O8: =+SUM(START:END!O8) -> 0 | P8: =IF(O8=0,0,Q8/O8) -> 0 | Q8: =+SUM(START:END!Q8) -> 0 | R8: =J8-O8 -> 0 | S8: =L8-Q8 -> 0
A9: =+B9&C9 -> Véhicules neufsMoto détail | B9: =+$K$1 -> Véhicules neufs | C9: Moto détail | D9: =+SUM(START:END!D9) -> 0 | E9: =IF(D9=0,0,F9/D9) -> 0 | F9: =+SUM(START:END!F9) -> 0 | G9: =+SUM(START:END!G9) -> 0 | H9: =IF(G9=0,0,I9/G9) -> 0 | I9: =+SUM(START:END!I9) -> 0 | J9: =+SUM(START:END!J9) -> 0 | K9: =IF(J9=0,0,L9/J9) -> 0 | L9: =+SUM(START:END!L9) -> 0 | M9: =J9-G9 -> 0 | N9: =L9-I9 -> 0 | O9: =+SUM(START:END!O9) -> 0 | P9: =IF(O9=0,0,Q9/O9) -> 0 | Q9: =+SUM(START:END!Q9) -> 0 | R9: =J9-O9 -> 0 | S9: =L9-Q9 -> 0
A10: =+B10&C10 -> Véhicules neufs[...] | B10: =+$K$1 -> Véhicules neufs | C10: [...] | D10: =+SUM(START:END!D10) -> 0 | E10: =IF(D10=0,0,F10/D10) -> 0 | F10: =+SUM(START:END!F10) -> 0 | G10: =+SUM(START:END!G10) -> 0 | H10: =IF(G10=0,0,I10/G10) -> 0 | I10: =+SUM(START:END!I10) -> 0 | J10: =+SUM(START:END!J10) -> 0 | K10: =IF(J10=0,0,L10/J10) -> 0 | L10: =+SUM(START:END!L10) -> 0 | M10: =J10-G10 -> 0 | N10: =L10-I10 -> 0 | O10: =+SUM(START:END!O10) -> 0 | P10: =IF(O10=0,0,Q10/O10) -> 0 | Q10: =+SUM(START:END!Q10) -> 0 | R10: =J10-O10 -> 0 | S10: =L10-Q10 -> 0
A11: =+B11&C11 -> Véhicules neufs[...] | B11: =+$K$1 -> Véhicules neufs | C11: [...] | D11: =+SUM(START:END!D11) -> 0 | E11: =IF(D11=0,0,F11/D11) -> 0 | F11: =+SUM(START:END!F11) -> 0 | G11: =+SUM(START:END!G11) -> 0 | H11: =IF(G11=0,0,I11/G11) -> 0 | I11: =+SUM(START:END!I11) -> 0 | J11: =+SUM(START:END!J11) -> 0 | K11: =IF(J11=0,0,L11/J11) -> 0 | L11: =+SUM(START:END!L11) -> 0 | M11: =J11-G11 -> 0 | N11: =L11-I11 -> 0 | O11: =+SUM(START:END!O11) -> 0 | P11: =IF(O11=0,0,Q11/O11) -> 0 | Q11: =+SUM(START:END!Q11) -> 0 | R11: =J11-O11 -> 0 | S11: =L11-Q11 -> 0
A12: =+B12&C12 -> Véhicules neufs[...] | B12: =+$K$1 -> Véhicules neufs | C12: [...] | D12: =+SUM(START:END!D12) -> 0 | E12: =IF(D12=0,0,F12/D12) -> 0 | F12: =+SUM(START:END!F12) -> 0 | G12: =+SUM(START:END!G12) -> 0 | H12: =IF(G12=0,0,I12/G12) -> 0 | I12: =+SUM(START:END!I12) -> 0 | J12: =+SUM(START:END!J12) -> 0 | K12: =IF(J12=0,0,L12/J12) -> 0 | L12: =+SUM(START:END!L12) -> 0 | M12: =J12-G12 -> 0 | N12: =L12-I12 -> 0 | O12: =+SUM(START:END!O12) -> 0 | P12: =IF(O12=0,0,Q12/O12) -> 0 | Q12: =+SUM(START:END!Q12) -> 0 | R12: =J12-O12 -> 0 | S12: =L12-Q12 -> 0
A13: =+B13&C13 -> Véhicules neufsTotal Neufs | B13: =+$K$1 -> Véhicules neufs | C13: Total Neufs | D13: =+SUM(D6:D12) -> 231.71466 | E13: =IF(D13<=0,0,F13/D13) -> 998.53486 | F13: =+SUM(F6:F12) -> 231375.16 | G13: =+SUM(G6:G12) -> 206.92011 | H13: =IF(G13<=0,0,I13/G13) -> 1383.8618 | I13: =+SUM(I6:I12) -> 286348.83 | J13: =+SUM(J6:J12) -> 203 | K13: =IF(J13<=0,0,L13/J13) -> 1725.4155 | L13: =+SUM(L6:L12) -> 350259.34 | M13: =+SUM(M6:M12) -> -3.9201093 | N13: =+SUM(N6:N12) -> 63910.509 | O13: =+SUM(O6:O12) -> 238 | P13: =IF(O13<=0,0,Q13/O13) -> 708.38483 | Q13: =+SUM(Q6:Q12) -> 168595.59 | R13: =+SUM(R6:R12) -> -35 | S13: =+SUM(S6:S12) -> 181663.75 | V13: =+SUM(START:END!D13)-D13 -> 0 | W13: =+SUM(START:END!G13)-G13 -> 0 | X13: =+SUM(START:END!J13)-J13 -> 0 | Y13: =+SUM(START:END!O13)-O13 -> 0
A14: =+B14&C14 -> Véhicules neufs | B14: =+$K$1 -> Véhicules neufs | M14: =IF(G13=0,0,M13/G13) -> -0.018945038 | N14: =IF(I13=0,0,N13/I13) -> 0.2231911 | R14: =R13/O13 -> -0.14705882 | S14: =IF(Q13=0,0,(S13/Q13)) -> 1.0775119
A15: =+B15&C15 -> Véhicules neufsEx-Démos et courtoisies | B15: =+$K$1 -> Véhicules neufs | C15: Ex-Démos et courtoisies | D15: =+SUM(START:END!D15) -> 24.150542 | E15: =IF(D15=0,0,F15/D15) -> 456.63516 | F15: =+SUM(START:END!F15) -> 11027.987 | G15: =+SUM(START:END!G15) -> 21.417025 | H15: =IF(G15=0,0,I15/G15) -> 795.68226 | I15: =+SUM(START:END!I15) -> 17041.147 | J15: =+SUM(START:END!J15) -> 16 | K15: =IF(J15=0,0,L15/J15) -> 1493.6619 | L15: =+SUM(START:END!L15) -> 23898.59 | M15: =J15-G15 -> -5.4170255 | N15: =L15-I15 -> 6857.4427 | O15: =+SUM(START:END!O15) -> 22 | P15: =IF(O15=0,0,Q15/O15) -> 30.737273 | Q15: =+SUM(START:END!Q15) -> 676.22 | R15: =J15-O15 -> -6 | S15: =L15-Q15 -> 23222.37 | V15: =+SUM(START:END!D15)-D15 -> 0 | W15: =+SUM(START:END!G15)-G15 -> 0 | X15: =+SUM(START:END!J15)-J15 -> 0 | Y15: =+SUM(START:END!O15)-O15 -> 0
A16: =+B16&C16 -> Véhicules neufs | B16: =+$K$1 -> Véhicules neufs
A17: =+B17&C17 -> Véhicules neufsFlottes | B17: =+$K$1 -> Véhicules neufs | C17: Flottes | D17: =+SUM(START:END!D17) -> 3.1998137 | E17: =IF(D17=0,0,F17/D17) -> 563.63318 | F17: =+SUM(START:END!F17) -> 1803.5212 | G17: =+SUM(START:END!G17) -> 7.648539 | H17: =IF(G17=0,0,I17/G17) -> 826.60916 | I17: =+SUM(START:END!I17) -> 6322.3524 | J17: =+SUM(START:END!J17) -> 10 | K17: =IF(J17=0,0,L17/J17) -> 2419.503 | L17: =+SUM(START:END!L17) -> 24195.03 | M17: =J17-G17 -> 2.351461 | N17: =L17-I17 -> 17872.678 | O17: =+SUM(START:END!O17) -> 6 | P17: =IF(O17=0,0,Q17/O17) -> 1624.1633 | Q17: =+SUM(START:END!Q17) -> 9744.98 | R17: =J17-O17 -> 4 | S17: =L17-Q17 -> 14450.05 | V17: =+SUM(START:END!D17)-D17 -> 0 | W17: =+SUM(START:END!G17)-G17 -> 0 | X17: =+SUM(START:END!J17)-J17 -> 0 | Y17: =+SUM(START:END!O17)-O17 -> 0
A18: =+B18&C18 -> Véhicules neufs | B18: =+$K$1 -> Véhicules neufs
A19: =+B19&C19 -> Véhicules neufsRachat bail | B19: =+$K$1 -> Véhicules neufs | C19: Rachat bail | F19: =+SUM(START:END!F19) -> 15000 | I19: =+SUM(START:END!I19) -> 15000 | L19: =+SUM(START:END!L19) -> 24413.88 | N19: =L19-I19 -> 9413.88 | Q19: =+SUM(START:END!Q19) -> 14219.24 | R19: =O19-K19 -> 0 | S19: =L19-Q19 -> 10194.64
A20: =+B20&C20 -> Véhicules neufs | B20: =+$K$1 -> Véhicules neufs
A21: =+B21&C21 -> Véhicules neufsRev. Finances | B21: =+$K$1 -> Véhicules neufs | C21: Rev. Finances | D21: 0 | E21: =IF(D21=0,0,F21/D21) -> 0 | F21: =+SUM(START:END!F21) -> 21499.773 | G21: 0 | H21: =IF(G21=0,0,I21/G21) -> 0 | I21: =+SUM(START:END!I21) -> 21499.773 | K21: =IF(J13=0,0,L21/(J13+J15)) -> 35.485023 | L21: =+SUM(START:END!L21) -> 7771.22 | N21: =L21-I21 -> -13728.553 | P21: =IF(O13=0,0,Q21/(O13+O15)) -> 89.401038 | Q21: =+SUM(START:END!Q21) -> 23244.27 | R21: =O21-K21 -> -35.485023 | S21: =L21-Q21 -> -15473.05
A22: =+B22&C22 -> Véhicules neufsRev. Protections | B22: =+$K$1 -> Véhicules neufs | C22: Rev. Protections | D22: 0 | E22: =IF(D22=0,0,F22/D22) -> 0 | F22: =+SUM(START:END!F22) -> 168498.22 | G22: 0 | H22: =IF(G22=0,0,I22/G22) -> 0 | I22: =+SUM(START:END!I22) -> 168498.22 | K22: =IF(J13=0,0,L22/(J13+J15)) -> 797.75068 | L22: =+SUM(START:END!L22) -> 174707.4 | N22: =L22-I22 -> 6209.1813 | P22: =IF(O13=0,0,Q22/(O13+O15)) -> 460.87235 | Q22: =+SUM(START:END!Q22) -> 119826.81 | R22: =O22-K22 -> -797.75068 | S22: =L22-Q22 -> 54880.59
A23: =+B23&C23 -> Véhicules neufsRev. Autres | B23: =+$K$1 -> Véhicules neufs | C23: Rev. Autres | D23: 0 | E23: =IF(D23=0,0,F23/D23) -> 0 | F23: =+SUM(START:END!F23) -> 4249.9551 | G23: 0 | H23: =IF(G23=0,0,I23/G23) -> 0 | I23: =+SUM(START:END!I23) -> 4249.9551 | K23: =IF(J13=0,0,L23/(J13+J15)) -> 20.952374 | L23: =+SUM(START:END!L23) -> 4588.57 | N23: =L23-I23 -> 338.61493 | P23: =IF(O13=0,0,Q23/(O13+O15)) -> 7.2941923 | Q23: =+SUM(START:END!Q23) -> 1896.49 | R23: =O23-K23 -> -20.952374 | S23: =L23-Q23 -> 2692.08
A24: =+B24&C24 -> Véhicules neufsTotal F&I | B24: =+$K$1 -> Véhicules neufs | C24: Total F&I | D24: =+D15+D13 -> 255.8652 | E24: =IF(D24<=0,0,F24/D24) -> 759.18079 | F24: =F21+F22+F23 -> 194247.95 | G24: =+G15+G13 -> 228.33713 | H24: =IF(G24<=0,0,I24/G24) -> 850.70677 | I24: =I21+I22+I23 -> 194247.95 | J24: =+J15+J13 -> 219 | K24: =IF(J24<=0,0,L24/J24) -> 854.18808 | L24: =L21+L22+L23 -> 187067.19 | M24: =J24-G24 -> -9.3371347 | N24: =L24-I24 -> -7180.7565 | O24: =+O15+O13 -> 260 | P24: =IF(O24<=0,0,Q24/O24) -> 557.56758 | Q24: =Q21+Q22+Q23 -> 144967.57 | S24: =L24-Q24 -> 42099.62 | V24: =+SUM(START:END!D24)-D24 -> 0 | W24: =+SUM(START:END!G24)-G24 -> 0 | X24: =+SUM(START:END!J24)-J24 -> 0 | Y24: =+SUM(START:END!O24)-O24 -> 0
A25: =+B25&C25 -> Véhicules neufs | B25: =+$K$1 -> Véhicules neufs | N25: =IF(N24=0,0,N24/I24) -> -0.036966962 | S25: =IF(Q24=0,0,(S24/Q24)) -> 0.29040716
A26: =+B26&C26 -> Véhicules neufs | B26: =+$K$1 -> Véhicules neufs
A27: =+B27&C27 -> Véhicules neufsTotal Dépt. Neufs | B27: =+$K$1 -> Véhicules neufs | C27: Total Dépt. Neufs | D27: =+D13+D15+D17 -> 259.06502 | E27: =IF(D27<=0,0,F27/D27) -> 1750.3507 | F27: =F13+F17+F24+F19+F15 -> 453454.62 | G27: =+G13+G15+G17 -> 235.98567 | H27: =IF(G27<=0,0,I27/G27) -> 2199.1177 | I27: =I13+I17+I24+I19+I15 -> 518960.28 | J27: =+J13+J15+J17 -> 229 | K27: =IF(J27<=0,0,L27/J27) -> 2663.0307 | L27: =L13+L17+L24+L19+L15 -> 609834.03 | M27: =J27-G27 -> -6.9856738 | N27: =L27-I27 -> 90873.753 | O27: =+O13+O15+O17 -> 266 | P27: =IF(O27<=0,0,Q27/O27) -> 1271.4421 | Q27: =Q13+Q17+Q24+Q19+Q15 -> 338203.6 | R27: =J27-O27 -> -37 | S27: =L27-Q27 -> 271630.43 | V27: =+SUM(START:END!D27)-D27 -> 0 | W27: =+SUM(START:END!G27)-G27 -> 0 | X27: =+SUM(START:END!J27)-J27 -> 0 | Y27: =+SUM(START:END!O27)-O27 -> 0
A28: =+B28&C28 -> Véhicules neufs | B28: =+$K$1 -> Véhicules neufs | M28: =M27/G27 -> -0.02960211 | N28: =N27/I27 -> 0.17510734 | R28: =R27/O27 -> -0.13909774 | S28: =IF(Q27=0,0,S27/Q27) -> 0.80315653
A29: =+B29&C29 -> Véhicules neufs | B29: =+$K$1 -> Véhicules neufs
A30: =+B30&C30 -> Véhicules neufsDEPENSES | B30: =+$K$1 -> Véhicules neufs | C30: DEPENSES
A31: =+B31&C31 -> Véhicules neufsComm. vendeurs | B31: =+$K$1 -> Véhicules neufs | C31: Comm. vendeurs | E31: =F31/D$24 -> 328.14376 | F31: =+SUM(START:END!F31) -> 83960.569 | H31: =I31/G$24 -> 372.99134 | I31: =+SUM(START:END!I31) -> 85167.775 | J31: =L31/L13 -> 0.38852737 | K31: =IF(L31=0,0,L31/J$24) -> 621.39425 | L31: =+SUM(START:END!L31) -> 136085.34 | N31: =L31-I31 -> 50917.565 | P31: =IF(Q31=0,0,Q31/O$24) -> 415.49396 | Q31: =+SUM(START:END!Q31) -> 108028.43 | S31: =L31-Q31 -> 28056.91
A32: =+B32&C32 -> Véhicules neufsComm. F&I | B32: =+$K$1 -> Véhicules neufs | C32: Comm. F&I | E32: =F32/D$24 -> 227.75424 | F32: =+SUM(START:END!F32) -> 58274.384 | H32: =I32/G$24 -> 255.21203 | I32: =+SUM(START:END!I32) -> 58274.384 | J32: =L32/L24 -> 0.30881375 | K32: =IF(L32=0,0,L32/J$24) -> 263.78502 | L32: =+SUM(START:END!L32) -> 57768.92 | N32: =L32-I32 -> -505.46394 | P32: =IF(Q32=0,0,Q32/O$24) -> 230.9225 | Q32: =+SUM(START:END!Q32) -> 60039.85 | S32: =L32-Q32 -> -2270.93
A33: =+B33&C33 -> Véhicules neufsFrais de livraison | B33: =+$K$1 -> Véhicules neufs | C33: Frais de livraison | E33: =F33/D$24 -> 175.95131 | F33: =+SUM(START:END!F33) -> 45019.818 | H33: =I33/G$24 -> 197.1638 | I33: =+SUM(START:END!I33) -> 45019.818 | K33: =IF(L33=0,0,L33/J$24) -> 138.73658 | L33: =+SUM(START:END!L33) -> 30383.31 | N33: =L33-I33 -> -14636.508 | P33: =IF(Q33=0,0,Q33/O$24) -> 140.66046 | Q33: =+SUM(START:END!Q33) -> 36571.72 | S33: =L33-Q33 -> -6188.41
A34: =+B34&C34 -> Véhicules neufsService gratuit 1 | B34: =+$K$1 -> Véhicules neufs | C34: Service gratuit 1 | E34: =F34/D$24 -> 5.3589232 | F34: =+SUM(START:END!F34) -> 1371.162 | H34: =I34/G$24 -> 6.004989 | I34: =+SUM(START:END!I34) -> 1371.162 | K34: =IF(L34=0,0,L34/J$24) -> 10.976895 | L34: =+SUM(START:END!L34) -> 2403.94 | N34: =L34-I34 -> 1032.778 | P34: =IF(Q34=0,0,Q34/O$24) -> 2.5856923 | Q34: =+SUM(START:END!Q34) -> 672.28 | S34: =L34-Q34 -> 1731.66
A35: =+B35&C35 -> Véhicules neufsEntretien stock | B35: =+$K$1 -> Véhicules neufs | C35: Entretien stock | E35: =F35/D$24 -> 30.367232 | F35: =+SUM(START:END!F35) -> 7769.9179 | H35: =I35/G$24 -> 34.028271 | I35: =+SUM(START:END!I35) -> 7769.9179 | K35: =IF(L35=0,0,L35/J$24) -> 9.8088128 | L35: =+SUM(START:END!L35) -> 2148.13 | N35: =L35-I35 -> -5621.7879 | P35: =IF(Q35=0,0,Q35/O$24) -> 21.498423 | Q35: =+SUM(START:END!Q35) -> 5589.59 | S35: =L35-Q35 -> -3441.46
A36: =+B36&C36 -> Véhicules neufsPublicité 1 | B36: =+$K$1 -> Véhicules neufs | C36: Publicité 1 | E36: =F36/D$24 -> 161.36579 | F36: =+SUM(START:END!F36) -> 41287.891 | H36: =I36/G$24 -> 180.81987 | I36: =+SUM(START:END!I36) -> 41287.891 | K36: =IF(L36=0,0,L36/J$24) -> 160.28037 | L36: =+SUM(START:END!L36) -> 35101.4 | N36: =L36-I36 -> -6186.4907 | P36: =IF(Q36=0,0,Q36/O$24) -> 87.653846 | Q36: =+SUM(START:END!Q36) -> 22790 | S36: =L36-Q36 -> 12311.4
A37: =+B37&C37 -> Véhicules neufsIntérêt de gros | B37: =+$K$1 -> Véhicules neufs | C37: Intérêt de gros | E37: =F37/D$24 -> 177.19171 | F37: =+SUM(START:END!F37) -> 45337.194 | H37: =I37/G$24 -> 199.83587 | I37: =+SUM(START:END!I37) -> 45629.951 | K37: =IF(L37=0,0,L37/J$24) -> 202.50959 | L37: =+SUM(START:END!L37) -> 44349.6 | N37: =L37-I37 -> -1280.3507 | P37: =IF(Q37=0,0,Q37/O$24) -> 241.01169 | Q37: =+SUM(START:END!Q37) -> 62663.04 | S37: =L37-Q37 -> -18313.44
A38: =+B38&C38 -> Véhicules neufs[...] | B38: =+$K$1 -> Véhicules neufs | C38: [...] | E38: =F38/D$24 -> 0 | F38: =+SUM(START:END!F38) -> 0 | H38: =I38/G$24 -> 0 | I38: =+SUM(START:END!I38) -> 0 | K38: =IF(L38=0,0,L38/J$24) -> 0 | L38: =+SUM(START:END!L38) -> 0 | N38: =L38-I38 -> 0 | P38: =IF(Q38=0,0,Q38/O$24) -> 0 | Q38: =+SUM(START:END!Q38) -> 0 | S38: =L38-Q38 -> 0
A39: =+B39&C39 -> Véhicules neufs[...] | B39: =+$K$1 -> Véhicules neufs | C39: [...] | E39: =F39/D$24 -> 0 | F39: =+SUM(START:END!F39) -> 0 | H39: =I39/G$24 -> 0 | I39: =+SUM(START:END!I39) -> 0 | K39: =IF(L39=0,0,L39/J$24) -> 0 | L39: =+SUM(START:END!L39) -> 0 | N39: =L39-I39 -> 0 | P39: =IF(Q39=0,0,Q39/O$24) -> 0 | Q39: =+SUM(START:END!Q39) -> 0 | S39: =L39-Q39 -> 0
A40: =+B40&C40 -> Véhicules neufs[...] | B40: =+$K$1 -> Véhicules neufs | C40: [...] | E40: =F40/D$24 -> 0 | F40: =+SUM(START:END!F40) -> 0 | H40: =I40/G$24 -> 0 | I40: =+SUM(START:END!I40) -> 0 | K40: =IF(L40=0,0,L40/J$24) -> 0 | L40: =+SUM(START:END!L40) -> 0 | N40: =L40-I40 -> 0 | P40: =IF(Q40=0,0,Q40/O$24) -> 0 | Q40: =+SUM(START:END!Q40) -> 0 | S40: =L40-Q40 -> 0
A41: =+B41&C41 -> Véhicules neufsTOTAL VARIABLES | B41: =+$K$1 -> Véhicules neufs | C41: TOTAL VARIABLES | D41: % brut | E41: =F41/F$27 -> 0.6241439 | F41: =SUM(F31:F40) -> 283020.93 | G41: % brut | H41: =I41/I$27 -> 0.54825178 | I41: =SUM(I31:I40) -> 284520.9 | J41: % brut | K41: =L41/L$27 -> 0.50545005 | L41: =SUM(L31:L40) -> 308240.64 | N41: =SUM(N31:N40) -> 23719.742 | O41: % brut | P41: =Q41/Q$27 -> 0.87626184 | Q41: =SUM(Q31:Q40) -> 296354.91 | S41: =L41-Q41 -> 11885.73
A42: =+B42&C42 -> Véhicules neufsSalaires cadres | B42: =+$K$1 -> Véhicules neufs | C42: Salaires cadres | F42: =+SUM(START:END!F42) -> 74657.233 | G42: =I41/(I27+I83) -> 0.34352898 | I42: =+SUM(START:END!I42) -> 74657.233 | J42: =L41/(L27+L83) -> 0.3401366 | L42: =+SUM(START:END!L42) -> 69242.63 | N42: =L42-I42 -> -5414.6028 | Q42: =+SUM(START:END!Q42) -> 59127.62
A43: =+B43&C43 -> Véhicules neufsSalaires commis | B43: =+$K$1 -> Véhicules neufs | C43: Salaires commis | F43: =+SUM(START:END!F43) -> 29632.202 | I43: =+SUM(START:END!I43) -> 29632.202 | L43: =+SUM(START:END!L43) -> 28323.91 | N43: =L43-I43 -> -1308.2916 | Q43: =+SUM(START:END!Q43) -> 26579.87 | S43: =L43-Q43 -> 1744.04
A44: =+B44&C44 -> Véhicules neufsSalaires autres | B44: =+$K$1 -> Véhicules neufs | C44: Salaires autres | F44: =+SUM(START:END!F44) -> 18672.541 | I44: =+SUM(START:END!I44) -> 18672.541 | L44: =+SUM(START:END!L44) -> 28675.69 | N44: =L44-I44 -> 10003.149 | Q44: =+SUM(START:END!Q44) -> 20387.56 | S44: =L44-Q44 -> 8288.13
A45: =+B45&C45 -> Véhicules neufsSalaires spécialistes | B45: =+$K$1 -> Véhicules neufs | C45: Salaires spécialistes | F45: =+SUM(START:END!F45) -> 0 | I45: =+SUM(START:END!I45) -> 0 | L45: =+SUM(START:END!L45) -> 0 | N45: =L45-I45 -> 0 | Q45: =+SUM(START:END!Q45) -> 0 | S45: =L45-Q45 -> 0
A46: =+B46&C46 -> Véhicules neufs[...] | B46: =+$K$1 -> Véhicules neufs | C46: [...] | F46: =+SUM(START:END!F46) -> 0 | I46: =+SUM(START:END!I46) -> 0 | L46: =+SUM(START:END!L46) -> 0 | N46: =L46-I46 -> 0 | Q46: =+SUM(START:END!Q46) -> 0 | S46: =L46-Q46 -> 0
A47: =+B47&C47 -> Véhicules neufs[...] | B47: =+$K$1 -> Véhicules neufs | C47: [...] | F47: =+SUM(START:END!F47) -> 0 | I47: =+SUM(START:END!I47) -> 0 | L47: =+SUM(START:END!L47) -> 0 | N47: =L47-I47 -> 0 | Q47: =+SUM(START:END!Q47) -> 0 | S47: =L47-Q47 -> 0
A48: =+B48&C48 -> Véhicules neufs[...] | B48: =+$K$1 -> Véhicules neufs | C48: [...] | F48: =+SUM(START:END!F48) -> 0 | I48: =+SUM(START:END!I48) -> 0 | L48: =+SUM(START:END!L48) -> 0 | N48: =L48-I48 -> 0 | Q48: =+SUM(START:END!Q48) -> 0 | S48: =L48-Q48 -> 0
A49: =+B49&C49 -> Véhicules neufsSalaires en absences | B49: =+$K$1 -> Véhicules neufs | C49: Salaires en absences | F49: =+SUM(START:END!F49) -> 31823.631 | I49: =+SUM(START:END!I49) -> 31968.496 | L49: =+SUM(START:END!L49) -> 45416.31 | N49: =L49-I49 -> 13447.814 | Q49: =+SUM(START:END!Q49) -> 41945.32 | S49: =L49-Q49 -> 3470.99
A50: =+B50&C50 -> Véhicules neufsDéduction à la source | B50: =+$K$1 -> Véhicules neufs | C50: Déduction à la source | F50: =+SUM(START:END!F50) -> 31823.631 | I50: =+SUM(START:END!I50) -> 31968.496 | L50: =+SUM(START:END!L50) -> 35101.3 | N50: =L50-I50 -> 3132.8039 | Q50: =+SUM(START:END!Q50) -> 36809.18 | S50: =L50-Q50 -> -1707.88
A51: =+B51&C51 -> Véhicules neufsBénéfices marginaux | B51: =+$K$1 -> Véhicules neufs | C51: Bénéfices marginaux | F51: =+SUM(START:END!F51) -> 22806.936 | I51: =+SUM(START:END!I51) -> 22910.756 | L51: =+SUM(START:END!L51) -> 25155.93 | N51: =L51-I51 -> 2245.1744 | Q51: =+SUM(START:END!Q51) -> 24721.15 | S51: =L51-Q51 -> 434.78
A52: =+B52&C52 -> Véhicules neufsCsst | B52: =+$K$1 -> Véhicules neufs | C52: Csst | F52: =+SUM(START:END!F52) -> 5303.9386 | I52: =+SUM(START:END!I52) -> 5328.0827 | L52: =+SUM(START:END!L52) -> 5850.22 | N52: =L52-I52 -> 522.13731 | Q52: =+SUM(START:END!Q52) -> 8383.49 | S52: =L52-Q52 -> -2533.27
A53: =+B53&C53 -> Véhicules neufs[...] | B53: =+$K$1 -> Véhicules neufs | C53: [...] | F53: =+SUM(START:END!F53) -> 0 | I53: =+SUM(START:END!I53) -> 0 | L53: =+SUM(START:END!L53) -> 0 | N53: =L53-I53 -> 0 | Q53: =+SUM(START:END!Q53) -> 0 | S53: =L53-Q53 -> 0
A54: =+B54&C54 -> Véhicules neufsTOTAL PERSONNEL | B54: =+$K$1 -> Véhicules neufs | C54: TOTAL PERSONNEL | D54: % brut | E54: =F54/F$27 -> 0.47352062 | F54: =+SUM(F42:F53) -> 214720.11 | G54: % brut | H54: =I54/I$27 -> 0.41455544 | I54: =+SUM(I42:I53) -> 215137.81 | J54: % brut | K54: =L54/L$27 -> 0.38988639 | L54: =+SUM(L42:L53) -> 237765.99 | N54: =+SUM(N42:N53) -> 22628.184 | O54: % brut | P54: =Q54/Q$27 -> 0.64444669 | Q54: =+SUM(Q42:Q53) -> 217954.19 | S54: =+SUM(S42:S53) -> 9696.79
A55: =+B55&C55 -> Véhicules neufsPublicité 2 | B55: =+$K$1 -> Véhicules neufs | C55: Publicité 2 | F55: =+SUM(START:END!F55) -> 0 | G55: =I54/(I27+I83) -> 0.25975621 | I55: =+SUM(START:END!I55) -> 0 | J55: =L54/(L27+L83) -> 0.26236941 | L55: =+SUM(START:END!L55) -> 0 | N55: =L55-I55 -> 0 | Q55: =+SUM(START:END!Q55) -> 0 | S55: =L55-Q55 -> 0
A56: =+B56&C56 -> Véhicules neufsService gratuit 2 | B56: =+$K$1 -> Véhicules neufs | C56: Service gratuit 2 | F56: =+SUM(START:END!F56) -> 0 | I56: =+SUM(START:END!I56) -> 0 | L56: =+SUM(START:END!L56) -> 0 | N56: =L56-I56 -> 0 | Q56: =+SUM(START:END!Q56) -> 0 | S56: =L56-Q56 -> 0
A57: =+B57&C57 -> Véhicules neufsFrais véhicules de cie | B57: =+$K$1 -> Véhicules neufs | C57: Frais véhicules de cie | F57: =+SUM(START:END!F57) -> 27266.632 | I57: =+SUM(START:END!I57) -> 27266.632 | L57: =+SUM(START:END!L57) -> 19849.4 | N57: =L57-I57 -> -7417.2325 | Q57: =+SUM(START:END!Q57) -> 48680.24 | S57: =L57-Q57 -> -28830.84
A58: =+B58&C58 -> Véhicules neufsInformatique | B58: =+$K$1 -> Véhicules neufs | C58: Informatique | F58: =+SUM(START:END!F58) -> 20032.189 | I58: =+SUM(START:END!I58) -> 20032.189 | L58: =+SUM(START:END!L58) -> 16133.59 | N58: =L58-I58 -> -3898.5988 | Q58: =+SUM(START:END!Q58) -> 19740.72 | S58: =L58-Q58 -> -3607.13
A59: =+B59&C59 -> Véhicules neufsFrais de déplacement | B59: =+$K$1 -> Véhicules neufs | C59: Frais de déplacement | F59: =+SUM(START:END!F59) -> 4789.4904 | I59: =+SUM(START:END!I59) -> 4789.4904 | L59: =+SUM(START:END!L59) -> 1577.97 | N59: =L59-I59 -> -3211.5204 | Q59: =+SUM(START:END!Q59) -> 5833.92 | S59: =L59-Q59 -> -4255.95
A60: =+B60&C60 -> Véhicules neufsServices extérieurs | B60: =+$K$1 -> Véhicules neufs | C60: Services extérieurs | F60: =+SUM(START:END!F60) -> 29125.684 | I60: =+SUM(START:END!I60) -> 29125.684 | L60: =+SUM(START:END!L60) -> 22452.67 | N60: =L60-I60 -> -6673.014 | Q60: =+SUM(START:END!Q60) -> 20452.8 | S60: =L60-Q60 -> 1999.87
A61: =+B61&C61 -> Véhicules neufsFournitures autres | B61: =+$K$1 -> Véhicules neufs | C61: Fournitures autres | F61: =+SUM(START:END!F61) -> 914.10798 | I61: =+SUM(START:END!I61) -> 914.10798 | L61: =+SUM(START:END!L61) -> 560.86 | N61: =L61-I61 -> -353.24798 | Q61: =+SUM(START:END!Q61) -> 861 | S61: =L61-Q61 -> -300.14
A62: =+B62&C62 -> Véhicules neufsUniformes | B62: =+$K$1 -> Véhicules neufs | C62: Uniformes | F62: =+SUM(START:END!F62) -> 105 | I62: =+SUM(START:END!I62) -> 105 | L62: =+SUM(START:END!L62) -> 0 | N62: =L62-I62 -> -105 | Q62: =+SUM(START:END!Q62) -> 105 | S62: =L62-Q62 -> -105
A63: =+B63&C63 -> Véhicules neufsPapeterie | B63: =+$K$1 -> Véhicules neufs | C63: Papeterie | F63: =+SUM(START:END!F63) -> 2092.8 | I63: =+SUM(START:END!I63) -> 2092.8 | L63: =+SUM(START:END!L63) -> 1944.11 | N63: =L63-I63 -> -148.69 | Q63: =+SUM(START:END!Q63) -> 1776 | S63: =L63-Q63 -> 168.11
A64: =+B64&C64 -> Véhicules neufsTéléphone | B64: =+$K$1 -> Véhicules neufs | C64: Téléphone | F64: =+SUM(START:END!F64) -> 1769.736 | I64: =+SUM(START:END!I64) -> 1769.736 | L64: =+SUM(START:END!L64) -> 615.72 | N64: =L64-I64 -> -1154.016 | Q64: =+SUM(START:END!Q64) -> 1564.04 | S64: =L64-Q64 -> -948.32
A65: =+B65&C65 -> Véhicules neufsFrais postaux | B65: =+$K$1 -> Véhicules neufs | C65: Frais postaux | F65: =+SUM(START:END!F65) -> 830.4 | I65: =+SUM(START:END!I65) -> 830.4 | L65: =+SUM(START:END!L65) -> 488.49 | N65: =L65-I65 -> -341.91 | Q65: =+SUM(START:END!Q65) -> 342.25 | S65: =L65-Q65 -> 146.24
A66: =+B66&C66 -> Véhicules neufsDivers | B66: =+$K$1 -> Véhicules neufs | C66: Divers | F66: =+SUM(START:END!F66) -> 4047.36 | I66: =+SUM(START:END!I66) -> 4047.36 | L66: =+SUM(START:END!L66) -> 1503.45 | N66: =L66-I66 -> -2543.91 | Q66: =+SUM(START:END!Q66) -> 5180.91 | S66: =L66-Q66 -> -3677.46
A67: =+B67&C67 -> Véhicules neufsFormation | B67: =+$K$1 -> Véhicules neufs | C67: Formation | F67: =+SUM(START:END!F67) -> 4315.04 | I67: =+SUM(START:END!I67) -> 4315.04 | L67: =+SUM(START:END!L67) -> 4289.99 | N67: =L67-I67 -> -25.05 | Q67: =+SUM(START:END!Q67) -> 13667.49 | S67: =L67-Q67 -> -9377.5
... A71: =+B71&C71 -> Véhicules neufs[...] | B71: =+$K$1 -> Véhicules neufs | C71: [...] | F71: =+SUM(START:END!F71) -> 0 | I71: =+SUM(START:END!I71) -> 0 | L71: =+SUM(START:END!L71) -> 0 | N71: =L71-I71 -> 0 | Q71: =+SUM(START:END!Q71) -> 0 | S71: =L71-Q71 -> 0
A72: =+B72&C72 -> Véhicules neufsTOTAL SEMI-FIXES | B72: =+$K$1 -> Véhicules neufs | C72: TOTAL SEMI-FIXES | D72: % brut | E72: =F72/F$27 -> 0.23241636 | F72: =+SUM(F55:F71) -> 105390.27 | G72: % brut | H72: =I72/I$27 -> 0.20307965 | I72: =+SUM(I55:I71) -> 105390.27 | J72: % brut | K72: =L72/L$27 -> 0.12991915 | L72: =+SUM(L55:L71) -> 79229.117 | N72: =+SUM(N55:N71) -> -26161.155 | O72: % brut | P72: =Q72/Q$27 -> 0.38788839 | Q72: =+SUM(Q55:Q71) -> 131185.25 | S72: =+SUM(S55:S71) -> -51956.134
A73: =+B73&C73 -> Véhicules neufs | B73: =+$K$1 -> Véhicules neufs
A74: =+B74&C74 -> Véhicules neufsTOTAL DES DÉPENSES | B74: =+$K$1 -> Véhicules neufs | C74: TOTAL DES DÉPENSES | D74: % brut | E74: =F74/F$27 -> 1.3300809 | F74: =F41+F54+F72 -> 603131.32 | G74: % brut | H74: =I74/I$27 -> 1.1658869 | I74: =I41+I54+I72 -> 605048.98 | J74: % brut | K74: =L74/L$27 -> 1.0252556 | L74: =L41+L54+L72 -> 625235.75 | N74: =L74-I74 -> 20186.771 | O74: % brut | P74: =Q74/Q$27 -> 1.9085969 | Q74: =Q41+Q54+Q72 -> 645494.35 | S74: =L74-Q74 -> -20258.603
A75: =+B75&C75 -> Véhicules neufsProgramme neuf 1 | B75: =+$K$1 -> Véhicules neufs | C75: Programme neuf 1 | F75: =+SUM(START:END!F75) -> 101841.48 | I75: =+SUM(START:END!I75) -> 23103.186 | L75: =+SUM(START:END!L75) -> 19500 | N75: =L75-I75 -> -3603.1859 | Q75: =+SUM(START:END!Q75) -> 128898
A76: =+B76&C76 -> Véhicules neufsProgramme neuf 2 | B76: =+$K$1 -> Véhicules neufs | C76: Programme neuf 2 | F76: =+SUM(START:END!F76) -> 0 | I76: =+SUM(START:END!I76) -> 0 | L76: =+SUM(START:END!L76) -> 0 | N76: =L76-I76 -> 0 | Q76: =+SUM(START:END!Q76) -> 0 | S76: =L76-Q76 -> 0
A77: =+B77&C77 -> Véhicules neufsProgramme neuf 3 | B77: =+$K$1 -> Véhicules neufs | C77: Programme neuf 3 | F77: =+SUM(START:END!F77) -> 0 | I77: =+SUM(START:END!I77) -> 0 | L77: =+SUM(START:END!L77) -> 0 | N77: =L77-I77 -> 0 | Q77: =+SUM(START:END!Q77) -> 0 | S77: =L77-Q77 -> 0
A78: =+B78&C78 -> Véhicules neufsHoldbacks | B78: =+$K$1 -> Véhicules neufs | C78: Holdbacks | F78: =+SUM(START:END!F78) -> 211969.63 | I78: =+SUM(START:END!I78) -> 214385.89 | L78: =+SUM(START:END!L78) -> 213351 | N78: =L78-I78 -> -1034.8911 | Q78: =+SUM(START:END!Q78) -> 238950.75 | S78: =L78-Q78 -> -25599.75
A79: =+B79&C79 -> Véhicules neufs[...] | B79: =+$K$1 -> Véhicules neufs | C79: [...] | F79: =+SUM(START:END!F79) -> 0 | I79: =+SUM(START:END!I79) -> 0 | L79: =+SUM(START:END!L79) -> 0 | N79: =L79-I79 -> 0 | Q79: =+SUM(START:END!Q79) -> 0 | S79: =L79-Q79 -> 0
A80: =+B80&C80 -> Véhicules neufs[...] | B80: =+$K$1 -> Véhicules neufs | C80: [...] | F80: =+SUM(START:END!F80) -> 0 | I80: =+SUM(START:END!I80) -> 0 | L80: =+SUM(START:END!L80) -> 0 | N80: =L80-I80 -> 0 | Q80: =+SUM(START:END!Q80) -> 0 | S80: =L80-Q80 -> 0
A81: =+B81&C81 -> Véhicules neufs[...] | B81: =+$K$1 -> Véhicules neufs | C81: [...] | F81: =+SUM(START:END!F81) -> 0 | I81: =+SUM(START:END!I81) -> 0 | L81: =+SUM(START:END!L81) -> 0 | N81: =L81-I81 -> 0 | Q81: =+SUM(START:END!Q81) -> 0 | S81: =L81-Q81 -> 0
A82: =+B82&C82 -> Véhicules neufsFrais administration | B82: =+$K$1 -> Véhicules neufs | C82: Frais administration | F82: =+SUM(START:END!F82) -> 71780.329 | I82: =+SUM(START:END!I82) -> 71780.329 | L82: =+SUM(START:END!L82) -> 63541 | N82: =L82-I82 -> -8239.3294 | Q82: =+SUM(START:END!Q82) -> 37176 | S82: =L82-Q82 -> 26365
A83: =+B83&C83 -> Véhicules neufsAUTRES REVENUS | B83: =+$K$1 -> Véhicules neufs | C83: AUTRES REVENUS | F83: =+SUM(F75:F82) -> 385591.44 | I83: =+SUM(I75:I82) -> 309269.41 | L83: =+SUM(L75:L82) -> 296392 | N83: =+SUM(N75:N82) -> -12877.406 | Q83: =+SUM(Q75:Q82) -> 405024.75 | S83: =+SUM(S75:S82) -> 765.25
A84: =+B84&C84 -> Véhicules neufs | B84: =+$K$1 -> Véhicules neufs
A85: =+B85&C85 -> Véhicules neufsPROFIT DÉPARTEMENTAL | B85: =+$K$1 -> Véhicules neufs | C85: PROFIT DÉPARTEMENTAL | F85: =F27-F74+F83 -> 235914.74 | I85: =I27-I74+I83 -> 223180.71 | L85: =L27-L74+L83 -> 280990.28 | N85: =N27-N41-N54-N72+N83 -> 57809.576 | Q85: =Q27-Q74+Q83 -> 97734 | S85: =S27-S41-S54-S72+S83 -> 302769.29
C89: =C1 -> Conso | K89: Véhicules usagés | S89: =$S$1 -> Réalisé
D91: BUDGET ORIGINAL | G91: BUDGET RÉVISÉ | J91: RÉALISATION | M91: ÉCART réel / révisé | O91: ANNÉE PRÉCÉDENTE | R91: ÉCART réel / original
D92: UNITE | E92: $P/UNITÉ | F92: $PROFITS | G92: UNITE | H92: $P/UNITÉ | I92: $PROFITS | J92: UNITE | K92: $P/UNITE | L92: $PROFITS | M92: UNITÉ | N92: $PROFITS | O92: UNITE | P92: $P/UNITE | Q92: $PROFITS | R92: UNITE | S92: $PROFITS
A93: =+B93&C93 -> Véhicules usagésVentes nettes | B93: Véhicules usagés | C93: Ventes nettes | F93: =+SUM(START:END!F93) -> 3362839.7 | I93: =+SUM(START:END!I93) -> 3362839.7 | L93: =+SUM(START:END!L93) -> 4150682.1 | Q93: =+SUM(START:END!Q93) -> 3109305.3
A94: =+B94&C94 -> Véhicules usagésCertifié | B94: Véhicules usagés | C94: Certifié | D94: =+SUM(START:END!D94) -> 100.9272 | E94: =IF(D94=0,0,F94/D94) -> 750 | F94: =+SUM(START:END!F94) -> 75695.398 | G94: =+SUM(START:END!G94) -> 100.9272 | H94: =IF(G94=0,0,I94/G94) -> 750 | I94: =+SUM(START:END!I94) -> 75695.398 | J94: =+SUM(START:END!J94) -> 113 | K94: =IF(J94=0,0,L94/J94) -> 1072.4797 | L94: =+SUM(START:END!L94) -> 121190.21 | M94: =J94-G94 -> 12.072803 | N94: =L94-I94 -> 45494.812 | O94: =+SUM(START:END!O94) -> 0 | P94: =IF(O94=0,0,Q94/O94) -> 0 | Q94: =+SUM(START:END!Q94) -> 0 | R94: =J94-O94 -> 113 | S94: =L94-Q94 -> 121190.21
A95: =+B95&C95 -> Véhicules usagésNon Certifié | B95: Véhicules usagés | C95: Non Certifié | D95: =+SUM(START:END!D95) -> 5.756304 | E95: =IF(D95=0,0,F95/D95) -> 750 | F95: =+SUM(START:END!F95) -> 4317.228 | G95: =+SUM(START:END!G95) -> 5.756304 | H95: =IF(G95=0,0,I95/G95) -> 750 | I95: =+SUM(START:END!I95) -> 4317.228 | J95: =+SUM(START:END!J95) -> 4 | K95: =IF(J95=0,0,L95/J95) -> 279.1925 | L95: =+SUM(START:END!L95) -> 1116.77 | O95: =+SUM(START:END!O95) -> 115 | P95: =IF(O95=0,0,Q95/O95) -> 516.94513 | Q95: =+SUM(START:END!Q95) -> 59448.69 | R95: =J95-O95 -> -111 | S95: =L95-Q95 -> -58331.92
A96: =+B96&C96 -> Véhicules usagésTotal Usagés | B96: Véhicules usagés | C96: Total Usagés | D96: =+D95+D94 -> 106.6835 | E96: =IF(D96=0,0,F96/D96) -> 750 | F96: =+F94+F95 -> 80012.626 | G96: =+G95+G94 -> 106.6835 | H96: =IF(G96=0,0,I96/G96) -> 750 | I96: =+I94+I95 -> 80012.626 | J96: =+J94+J95 -> 117 | K96: =IF(J96<=0,0,L96/J96) -> 1045.3588 | L96: =+L94+L95 -> 122306.98 | M96: =J96-G96 -> 10.316499 | N96: =L96-I96 -> 42294.354 | O96: =+O94+O95 -> 115 | P96: =IF(O96<=0,0,Q96/O96) -> 516.94513 | Q96: =+Q94+Q95 -> 59448.69 | R96: =R94+R95 -> 2 | S96: =S94+S95 -> 62858.29 | V96: =+SUM(START:END!D96)-D96 -> 0 | W96: =+SUM(START:END!G96)-G96 -> 0 | X96: =+SUM(START:END!J96)-J96 -> 0 | Y96: =+SUM(START:END!O96)-O96 -> 0
A97: =+B97&C97 -> Véhicules usagés | B97: Véhicules usagés | E97: =IF(D97=0,0,F97/D97) -> 0 | H97: =IF(G97=0,0,I97/G97) -> 0 | M97: =M96/G96 -> 0.096701915 | N97: =N96/I96 -> 0.528596 | R97: =R96/O96 -> 0.017391304 | S97: =IF(Q96=0,0,(S96/Q96)) -> 1.0573537
A98: =+B98&C98 -> Véhicules usagésUS | B98: Véhicules usagés | C98: US | D98: =+SUM(START:END!D98) -> 0 | E98: =IF(D98=0,0,F98/D98) -> 0 | F98: =+SUM(START:END!F98) -> 0 | G98: =+SUM(START:END!G98) -> 0 | H98: =IF(G98=0,0,I98/G98) -> 0 | I98: =+SUM(START:END!I98) -> 0 | J98: =+SUM(START:END!J98) -> 0 | K98: =IF(J98=0,0,L98/J98) -> 0 | L98: =+SUM(START:END!L98) -> 0 | M98: =J98-G98 -> 0 | N98: =L98-I98 -> 0 | O98: =+SUM(START:END!O98) -> 0 | P98: =IF(O98=0,0,Q98/O98) -> 0 | Q98: =+SUM(START:END!Q98) -> 0 | V98: =+SUM(START:END!D98)-D98 -> 0 | W98: =+SUM(START:END!G98)-G98 -> 0 | X98: =+SUM(START:END!J98)-J98 -> 0 | Y98: =+SUM(START:END!O98)-O98 -> 0
A99: =+B99&C99 -> Véhicules usagésVentes au Gros | B99: Véhicules usagés | C99: Ventes au Gros | D99: =+SUM(START:END!D99) -> 90.40023 | E99: =IF(D99=0,0,F99/D99) -> 120 | F99: =+SUM(START:END!F99) -> 10848.028 | G99: =+SUM(START:END!G99) -> 90.40023 | H99: =IF(G99=0,0,I99/G99) -> 120 | I99: =+SUM(START:END!I99) -> 10848.028 | J99: =+SUM(START:END!J99) -> 113 | K99: =IF(J99=0,0,L99/J99) -> 393.30628 | L99: =+SUM(START:END!L99) -> 44443.61 | M99: =J99-G99 -> 22.59977 | N99: =L99-I99 -> 33595.582 | O99: =+SUM(START:END!O99) -> 92 | P99: =IF(O99=0,0,Q99/O99) -> 364.65326 | Q99: =+SUM(START:END!Q99) -> 33548.1 | R99: =J99-O99 -> 21 | S99: =L99-Q99 -> 10895.51 | V99: =+SUM(START:END!D99)-D99 -> 0 | W99: =+SUM(START:END!G99)-G99 -> 0 | X99: =+SUM(START:END!J99)-J99 -> 0 | Y99: =+SUM(START:END!O99)-O99 -> 0
A100: =+B100&C100 -> Véhicules usagés | B100: Véhicules usagés
A101: =+B101&C101 -> Véhicules usagésRev. Finances | B101: Véhicules usagés | C101: Rev. Finances | D101: 0 | E101: =IF(D101=0,0,F101/D101) -> 0 | F101: =+SUM(START:END!F101) -> 85783.517 | G101: 0 | H101: =IF(G101=0,0,I101/G101) -> 0 | I101: =+SUM(START:END!I101) -> 85783.517 | K101: =IF(J96=0,0,L101/J96) -> 773.52487 | L101: =+SUM(START:END!L101) -> 90502.41 | N101: =L101-I101 -> 4718.893 | P101: =IF(O96=0,0,Q101/O96) -> 545.66374 | Q101: =+SUM(START:END!Q101) -> 62751.33 | R101: =O101-K101 -> -773.52487 | S101: =L101-Q101 -> 27751.08
A102: =+B102&C102 -> Véhicules usagésRev. Protections | B102: Véhicules usagés | C102: Rev. Protections | D102: 0 | E102: =IF(D102=0,0,F102/D102) -> 0 | F102: =+SUM(START:END!F102) -> 97221.319 | G102: 0 | H102: =IF(G102=0,0,I102/G102) -> 0 | I102: =+SUM(START:END!I102) -> 97221.319 | K102: =IF(J96=0,0,L102/J96) -> 1132.5385 | L102: =+SUM(START:END!L102) -> 132507 | N102: =L102-I102 -> 35285.681 | P102: =IF(O96=0,0,Q102/O96) -> 600.37565 | Q102: =+SUM(START:END!Q102) -> 69043.2 | R102: =O102-K102 -> -1132.5385 | S102: =L102-Q102 -> 63463.8
A103: =+B103&C103 -> Véhicules usagésRev. Autres | B103: Véhicules usagés | C103: Rev. Autres | D103: 0 | E103: =IF(D103=0,0,F103/D103) -> 0 | F103: =+SUM(START:END!F103) -> 0 | G103: 0 | H103: =IF(G103=0,0,I103/G103) -> 0 | I103: =+SUM(START:END!I103) -> 0 | K103: =IF(J96=0,0,L103/J96) -> 43.749658 | L103: =+SUM(START:END!L103) -> 5118.71 | N103: =L103-I103 -> 5118.71 | P103: =IF(O96=0,0,Q103/O96) -> 43.594261 | Q103: =+SUM(START:END!Q103) -> 5013.34 | R103: =O103-K103 -> -43.749658 | S103: =L103-Q103 -> 105.37
A104: =+B104&C104 -> Véhicules usagésTotal F&I | B104: Véhicules usagés | C104: Total F&I | D104: =D96 -> 106.6835 | E104: =IF(D104=0,0,F104/D104) -> 1715.3996 | F104: =F101+F102+F103 -> 183004.84 | G104: =G96 -> 106.6835 | H104: =IF(G104=0,0,I104/G104) -> 1715.3996 | I104: =I101+I102+I103 -> 183004.84 | J104: =J96 -> 117 | K104: =IF(J104<=0,0,L104/J104) -> 1949.813 | L104: =L101+L102+L103 -> 228128.12 | M104: =J104-G104 -> 10.316499 | N104: =L104-I104 -> 45123.284 | O104: =O96 -> 115 | P104: =IF(O104<=0,0,Q104/O104) -> 1189.6337 | Q104: =Q101+Q102+Q103 -> 136807.87 | S104: =L104-Q104 -> 91320.25 | V104: =+SUM(START:END!D104)-D104 -> 0 | W104: =+SUM(START:END!G104)-G104 -> 0 | X104: =+SUM(START:END!J104)-J104 -> 0 | Y104: =+SUM(START:END!O104)-O104 -> 0
A105: =+B105&C105 -> Véhicules usagés | B105: Véhicules usagés | N105: =N104/I104 -> 0.2465688 | S105: =IF(Q104=0,0,(S104/Q104)) -> 0.66750729
A106: =+B106&C106 -> Véhicules usagés | B106: Véhicules usagés
A107: =+B107&C107 -> Véhicules usagésTotal Dépt. Usagés | B107: Véhicules usagés | C107: Total Dépt. Usagés | D107: =D96+D99 -> 197.08373 | E107: =IF(D107<=0,0,F107/D107) -> 1389.5895 | F107: =F96+F104+F99 -> 273865.49 | G107: =G96+G99 -> 197.08373 | H107: =IF(G107<=0,0,I107/G107) -> 1389.5895 | I107: =I96+I104+I99 -> 273865.49 | J107: =J96+J99+J98 -> 230 | K107: =IF(J107<=0,0,L107/J107) -> 1716.864 | L107: =L96+L104+L99+L98 -> 394878.71 | M107: =J107-G107 -> 32.916269 | N107: =L107-I107 -> 121013.22 | O107: =O96+O99+O98 -> 207 | P107: =IF(O107<=0,0,Q107/O107) -> 1110.1674 | Q107: =Q96+Q104+Q99+Q98 -> 229804.66 | R107: =J107-O107 -> 23 | S107: =L107-Q107 -> 165074.05 | V107: =+SUM(START:END!D107)-D107 -> 0 | W107: =+SUM(START:END!G107)-G107 -> 0 | X107: =+SUM(START:END!J107)-J107 -> 0 | Y107: =+SUM(START:END!O107)-O107 -> 0
...

Sheet START

Sheet VW 4
C1: =[5]Parametres!B1 -> Volks | K1: Véhicules neufs | S1: =CONCATENATE("Réalisé,"," ",[5]Parametres!B3," ",[5]Parametres!B4) -> Réalisé, Avril 2021
D2: X | E2: O | F2: U | G2: X | H2: O | I2: U | J2: NB | L2: $ | O2: NB | Q2: $
D3: BUDGET ORIGINAL | G3: BUDGET REVISE | J3: RÉALISATION | M3: ÉCART réel / révisé | O3: ANNÉE PRÉCÉDENTE | R3: ÉCART réel / original | V3: NEUF | W3: 0.45
D4: UNITE | E4: $P/UNITÉ | F4: $PROFITS | G4: UNITE | H4: $P/UNITÉ | I4: $PROFITS | J4: UNITE | K4: $P/UNITE | L4: $PROFITS | M4: UNITÉ | N4: $PROFITS | O4: UNITE | P4: $P/UNITE | Q4: $PROFITS | R4: UNITE | S4: $PROFITS | V4: USAGE | W4: 0.1
A5: =+B5&C5 -> Véhicules neufsVentes nettes | B5: =+$K$1 -> Véhicules neufs | C5: Ventes nettes | F5: =+INDEX('[5]Budget original'!$A$2:$AO$496,MATCH($A5,'[5]Budget original'!$A$2:$A$496,0),MATCH(F$2,'[5]Budget original'!$A$2:$AO$2,0)) -> 751340.66 | I5: =+INDEX('[5]Budget révisé'!$A$2:$AO$496,MATCH($A5,'[5]Budget révisé'!$A$2:$A$496,0),MATCH(I$2,'[5]Budget révisé'!$A$2:$AO$2,0)) -> 751340.66 | L5: =-SUMIFS([5]BV_Data_An_Cour!$O:$O,[5]BV_Data_An_Cour!$X:$X,"Oui",[5]BV_Data_An_Cour!$U:$U,$B5) -> 3185397.8 | Q5: =-SUMIFS([5]BV_Data_An_Prec!$O:$O,[5]BV_Data_An_Prec!$X:$X,"Oui",[5]BV_Data_An_Prec!$U:$U,$B5) -> 3012832.6 | V5: SERVICE | W5: 0.225
A6: =+B6&C6 -> Véhicules neufsAutos détail | B6: =+$K$1 -> Véhicules neufs | C6: Autos détail | D6: =+INDEX('[5]Budget original'!$A$2:$AO$496,MATCH($A6,'[5]Budget original'!$A$2:$A$496,0),MATCH(D$2,'[5]Budget original'!$A$2:$AO$2,0)) -> 27.36626 | E6: =IF(D6=0,0,F6/D6) -> 604.29043 | F6: =+INDEX('[5]Budget original'!$A$2:$AO$496,MATCH($A6,'[5]Budget original'!$A$2:$A$496,0),MATCH(F$2,'[5]Budget original'!$A$2:$AO$2,0)) -> 16537.169 | G6: =+INDEX('[5]Budget révisé'!$A$2:$AO$496,MATCH($A6,'[5]Budget révisé'!$A$2:$A$496,0),MATCH(G$2,'[5]Budget révisé'!$A$2:$AO$2,0)) -> 27.36626 | H6: =IF(G6=0,0,I6/G6) -> 955.05622 | I6: =+INDEX('[5]Budget révisé'!$A$2:$AO$496,MATCH($A6,'[5]Budget révisé'!$A$2:$A$496,0),MATCH(I$2,'[5]Budget révisé'!$A$2:$AO$2,0)) -> 26136.316 | J6: =-SUMIFS([5]BV_Data_An_Cour!$O:$O,[5]BV_Data_An_Cour!$U:$U,$B6,[5]BV_Data_An_Cour!$V:$V,$C6,[5]BV_Data_An_Cour!$W:$W,J$2) -> 24 | K6: =IF(J6=0,0,L6/J6) -> 474.33792 | L6: =-SUMIFS([5]BV_Data_An_Cour!$O:$O,[5]BV_Data_An_Cour!$U:$U,$B6,[5]BV_Data_An_Cour!$V:$V,$C6,[5]BV_Data_An_Cour!$W:$W,L$2) -> 11384.11 | M6: =J6-G6 -> -3.3662596 | N6: =L6-I6 -> -14752.206 | O6: =-SUMIFS([5]BV_Data_An_Prec!$O:$O,[5]BV_Data_An_Prec!$U:$U,$B6,[5]BV_Data_An_Prec!$V:$V,$C6,[5]BV_Data_An_Prec!$W:$W,O$2) -> 56 | P6: =IF(O6=0,0,Q6/O6) -> 756.66714 | Q6: =-SUMIFS([5]BV_Data_An_Prec!$O:$O,[5]BV_Data_An_Prec!$U:$U,$B6,[5]BV_Data_An_Prec!$V:$V,$C6,[5]BV_Data_An_Prec!$W:$W,Q$2) -> 42373.36 | R6: =J6-O6 -> -32 | S6: =L6-Q6 -> -30989.25 | V6: CARROSSERIE | W6: 0.025
A7: =+B7&C7 -> Véhicules neufsCamions détail | B7: =+$K$1 -> Véhicules neufs | C7: Camions détail | D7: =+INDEX('[5]Budget original'!$A$2:$AO$496,MATCH($A7,'[5]Budget original'!$A$2:$A$496,0),MATCH(D$2,'[5]Budget original'!$A$2:$AO$2,0)) -> 36.759299 | E7: =IF(D7=0,0,F7/D7) -> 1315.4791 | F7: =+INDEX('[5]Budget original'!$A$2:$AO$496,MATCH($A7,'[5]Budget original'!$A$2:$A$496,0),MATCH(F$2,'[5]Budget original'!$A$2:$AO$2,0)) -> 48356.09 | G7: =+INDEX('[5]Budget révisé'!$A$2:$AO$496,MATCH($A7,'[5]Budget révisé'!$A$2:$A$496,0),MATCH(G$2,'[5]Budget révisé'!$A$2:$AO$2,0)) -> 36.759299 | H7: =IF(G7=0,0,I7/G7) -> 1702.6669 | I7: =+INDEX('[5]Budget révisé'!$A$2:$AO$496,MATCH($A7,'[5]Budget révisé'!$A$2:$A$496,0),MATCH(I$2,'[5]Budget révisé'!$A$2:$AO$2,0)) -> 62588.841 | J7: =-SUMIFS([5]BV_Data_An_Cour!$O:$O,[5]BV_Data_An_Cour!$U:$U,$B7,[5]BV_Data_An_Cour!$V:$V,$C7,[5]BV_Data_An_Cour!$W:$W,J$2) -> 41 | K7: =IF(J7=0,0,L7/J7) -> 2167.9161 | L7: =-SUMIFS([5]BV_Data_An_Cour!$O:$O,[5]BV_Data_An_Cour!$U:$U,$B7,[5]BV_Data_An_Cour!$V:$V,$C7,[5]BV_Data_An_Cour!$W:$W,L$2) -> 88884.56 | M7: =J7-G7 -> 4.2407008 | N7: =L7-I7 -> 26295.719 | O7: =-SUMIFS([5]BV_Data_An_Prec!$O:$O,[5]BV_Data_An_Prec!$U:$U,$B7,[5]BV_Data_An_Prec!$V:$V,$C7,[5]BV_Data_An_Prec!$W:$W,O$2) -> 28 | P7: =IF(O7=0,0,Q7/O7) -> 666.27321 | Q7: =-SUMIFS([5]BV_Data_An_Prec!$O:$O,[5]BV_Data_An_Prec!$U:$U,$B7,[5]BV_Data_An_Prec!$V:$V,$C7,[5]BV_Data_An_Prec!$W:$W,Q$2) -> 18655.65 | R7: =J7-O7 -> 13 | S7: =L7-Q7 -> 70228.91 | V7: PIECES | W7: 0.2
A8: =+B8&C8 -> Véhicules neufsSprinter | B8: =+$K$1 -> Véhicules neufs | C8: Sprinter | D8: =+INDEX('[5]Budget original'!$A$2:$AO$496,MATCH($A8,'[5]Budget original'!$A$2:$A$496,0),MATCH(D$2,'[5]Budget original'!$A$2:$AO$2,0)) -> 0 | E8: =IF(D8=0,0,F8/D8) -> 0 | F8: =+INDEX('[5]Budget original'!$A$2:$AO$496,MATCH($A8,'[5]Budget original'!$A$2:$A$496,0),MATCH(F$2,'[5]Budget original'!$A$2:$AO$2,0)) -> 0 | G8: =+INDEX('[5]Budget révisé'!$A$2:$AO$496,MATCH($A8,'[5]Budget révisé'!$A$2:$A$496,0),MATCH(G$2,'[5]Budget révisé'!$A$2:$AO$2,0)) -> 0 | H8: =IF(G8=0,0,I8/G8) -> 0 | I8: =+INDEX('[5]Budget révisé'!$A$2:$AO$496,MATCH($A8,'[5]Budget révisé'!$A$2:$A$496,0),MATCH(I$2,'[5]Budget révisé'!$A$2:$AO$2,0)) -> 0 | J8: =-SUMIFS([5]BV_Data_An_Cour!$O:$O,[5]BV_Data_An_Cour!$U:$U,$B8,[5]BV_Data_An_Cour!$V:$V,$C8,[5]BV_Data_An_Cour!$W:$W,J$2) -> 0 | K8: =IF(J8=0,0,L8/J8) -> 0 | L8: =-SUMIFS([5]BV_Data_An_Cour!$O:$O,[5]BV_Data_An_Cour!$U:$U,$B8,[5]BV_Data_An_Cour!$V:$V,$C8,[5]BV_Data_An_Cour!$W:$W,L$2) -> 0 | M8: =J8-G8 -> 0 | N8: =L8-I8 -> 0 | O8: =-SUMIFS([5]BV_Data_An_Prec!$O:$O,[5]BV_Data_An_Prec!$U:$U,$B8,[5]BV_Data_An_Prec!$V:$V,$C8,[5]BV_Data_An_Prec!$W:$W,O$2) -> 0 | P8: =IF(O8=0,0,Q8/O8) -> 0 | Q8: =-SUMIFS([5]BV_Data_An_Prec!$O:$O,[5]BV_Data_An_Prec!$U:$U,$B8,[5]BV_Data_An_Prec!$V:$V,$C8,[5]BV_Data_An_Prec!$W:$W,Q$2) -> 0 | R8: =J8-O8 -> 0 | S8: =L8-Q8 -> 0 | W8: =SUM(W3:W7) -> 1
A9: =+B9&C9 -> Véhicules neufsMoto détail | B9: =+$K$1 -> Véhicules neufs | C9: Moto détail | D9: =+INDEX('[5]Budget original'!$A$2:$AO$496,MATCH($A9,'[5]Budget original'!$A$2:$A$496,0),MATCH(D$2,'[5]Budget original'!$A$2:$AO$2,0)) -> 0 | E9: =IF(D9=0,0,F9/D9) -> 0 | F9: =+INDEX('[5]Budget original'!$A$2:$AO$496,MATCH($A9,'[5]Budget original'!$A$2:$A$496,0),MATCH(F$2,'[5]Budget original'!$A$2:$AO$2,0)) -> 0 | G9: =+INDEX('[5]Budget révisé'!$A$2:$AO$496,MATCH($A9,'[5]Budget révisé'!$A$2:$A$496,0),MATCH(G$2,'[5]Budget révisé'!$A$2:$AO$2,0)) -> 0 | H9: =IF(G9=0,0,I9/G9) -> 0 | I9: =+INDEX('[5]Budget révisé'!$A$2:$AO$496,MATCH($A9,'[5]Budget révisé'!$A$2:$A$496,0),MATCH(I$2,'[5]Budget révisé'!$A$2:$AO$2,0)) -> 0 | J9: =-SUMIFS([5]BV_Data_An_Cour!$O:$O,[5]BV_Data_An_Cour!$U:$U,$B9,[5]BV_Data_An_Cour!$V:$V,$C9,[5]BV_Data_An_Cour!$W:$W,J$2) -> 0 | K9: =IF(J9=0,0,L9/J9) -> 0 | L9: =-SUMIFS([5]BV_Data_An_Cour!$O:$O,[5]BV_Data_An_Cour!$U:$U,$B9,[5]BV_Data_An_Cour!$V:$V,$C9,[5]BV_Data_An_Cour!$W:$W,L$2) -> 0 | M9: =J9-G9 -> 0 | N9: =L9-I9 -> 0 | O9: =-SUMIFS([5]BV_Data_An_Prec!$O:$O,[5]BV_Data_An_Prec!$U:$U,$B9,[5]BV_Data_An_Prec!$V:$V,$C9,[5]BV_Data_An_Prec!$W:$W,O$2) -> 0 | P9: =IF(O9=0,0,Q9/O9) -> 0 | Q9: =-SUMIFS([5]BV_Data_An_Prec!$O:$O,[5]BV_Data_An_Prec!$U:$U,$B9,[5]BV_Data_An_Prec!$V:$V,$C9,[5]BV_Data_An_Prec!$W:$W,Q$2) -> 0 | R9: =J9-O9 -> 0 | S9: =L9-Q9 -> 0
A10: =+B10&C10 -> Véhicules neufs[...] | B10: =+$K$1 -> Véhicules neufs | C10: [...] | D10: =+INDEX('[5]Budget original'!$A$2:$AO$496,MATCH($A10,'[5]Budget original'!$A$2:$A$496,0),MATCH(D$2,'[5]Budget original'!$A$2:$AO$2,0)) -> 0 | E10: =IF(D10=0,0,F10/D10) -> 0 | F10: =+INDEX('[5]Budget original'!$A$2:$AO$496,MATCH($A10,'[5]Budget original'!$A$2:$A$496,0),MATCH(F$2,'[5]Budget original'!$A$2:$AO$2,0)) -> 0 | G10: =+INDEX('[5]Budget révisé'!$A$2:$AO$496,MATCH($A10,'[5]Budget révisé'!$A$2:$A$496,0),MATCH(G$2,'[5]Budget révisé'!$A$2:$AO$2,0)) -> 0 | H10: =IF(G10=0,0,I10/G10) -> 0 | I10: =+INDEX('[5]Budget révisé'!$A$2:$AO$496,MATCH($A10,'[5]Budget révisé'!$A$2:$A$496,0),MATCH(I$2,'[5]Budget révisé'!$A$2:$AO$2,0)) -> 0 | J10: =-SUMIFS([5]BV_Data_An_Cour!$O:$O,[5]BV_Data_An_Cour!$U:$U,$B10,[5]BV_Data_An_Cour!$V:$V,$C10,[5]BV_Data_An_Cour!$W:$W,J$2) -> 0 | K10: =IF(J10=0,0,L10/J10) -> 0 | L10: =-SUMIFS([5]BV_Data_An_Cour!$O:$O,[5]BV_Data_An_Cour!$U:$U,$B10,[5]BV_Data_An_Cour!$V:$V,$C10,[5]BV_Data_An_Cour!$W:$W,L$2) -> 0 | M10: =J10-G10 -> 0 | N10: =L10-I10 -> 0 | O10: =-SUMIFS([5]BV_Data_An_Prec!$O:$O,[5]BV_Data_An_Prec!$U:$U,$B10,[5]BV_Data_An_Prec!$V:$V,$C10,[5]BV_Data_An_Prec!$W:$W,O$2) -> 0 | P10: =IF(O10=0,0,Q10/O10) -> 0 | Q10: =-SUMIFS([5]BV_Data_An_Prec!$O:$O,[5]BV_Data_An_Prec!$U:$U,$B10,[5]BV_Data_An_Prec!$V:$V,$C10,[5]BV_Data_An_Prec!$W:$W,Q$2) -> 0 | R10: =J10-O10 -> 0 | S10: =L10-Q10 -> 0
A11: =+B11&C11 -> Véhicules neufs[...] | B11: =+$K$1 -> Véhicules neufs | C11: [...] | D11: =+INDEX('[5]Budget original'!$A$2:$AO$496,MATCH($A11,'[5]Budget original'!$A$2:$A$496,0),MATCH(D$2,'[5]Budget original'!$A$2:$AO$2,0)) -> 0 | E11: =IF(D11=0,0,F11/D11) -> 0 | F11: =+INDEX('[5]Budget original'!$A$2:$AO$496,MATCH($A11,'[5]Budget original'!$A$2:$A$496,0),MATCH(F$2,'[5]Budget original'!$A$2:$AO$2,0)) -> 0 | G11: =+INDEX('[5]Budget révisé'!$A$2:$AO$496,MATCH($A11,'[5]Budget révisé'!$A$2:$A$496,0),MATCH(G$2,'[5]Budget révisé'!$A$2:$AO$2,0)) -> 0 | H11: =IF(G11=0,0,I11/G11) -> 0 | I11: =+INDEX('[5]Budget révisé'!$A$2:$AO$496,MATCH($A11,'[5]Budget révisé'!$A$2:$A$496,0),MATCH(I$2,'[5]Budget révisé'!$A$2:$AO$2,0)) -> 0 | J11: =-SUMIFS([5]BV_Data_An_Cour!$O:$O,[5]BV_Data_An_Cour!$U:$U,$B11,[5]BV_Data_An_Cour!$V:$V,$C11,[5]BV_Data_An_Cour!$W:$W,J$2) -> 0 | K11: =IF(J11=0,0,L11/J11) -> 0 | L11: =-SUMIFS([5]BV_Data_An_Cour!$O:$O,[5]BV_Data_An_Cour!$U:$U,$B11,[5]BV_Data_An_Cour!$V:$V,$C11,[5]BV_Data_An_Cour!$W:$W,L$2) -> 0 | M11: =J11-G11 -> 0 | N11: =L11-I11 -> 0 | O11: =-SUMIFS([5]BV_Data_An_Prec!$O:$O,[5]BV_Data_An_Prec!$U:$U,$B11,[5]BV_Data_An_Prec!$V:$V,$C11,[5]BV_Data_An_Prec!$W:$W,O$2) -> 0 | P11: =IF(O11=0,0,Q11/O11) -> 0 | Q11: =-SUMIFS([5]BV_Data_An_Prec!$O:$O,[5]BV_Data_An_Prec!$U:$U,$B11,[5]BV_Data_An_Prec!$V:$V,$C11,[5]BV_Data_An_Prec!$W:$W,Q$2) -> 0 | R11: =J11-O11 -> 0 | S11: =L11-Q11 -> 0
A12: =+B12&C12 -> Véhicules neufs[...] | B12: =+$K$1 -> Véhicules neufs | C12: [...] | D12: =+INDEX('[5]Budget original'!$A$2:$AO$496,MATCH($A12,'[5]Budget original'!$A$2:$A$496,0),MATCH(D$2,'[5]Budget original'!$A$2:$AO$2,0)) -> 0 | E12: =IF(D12=0,0,F12/D12) -> 0 | F12: =+INDEX('[5]Budget original'!$A$2:$AO$496,MATCH($A12,'[5]Budget original'!$A$2:$A$496,0),MATCH(F$2,'[5]Budget original'!$A$2:$AO$2,0)) -> 0 | G12: =+INDEX('[5]Budget révisé'!$A$2:$AO$496,MATCH($A12,'[5]Budget révisé'!$A$2:$A$496,0),MATCH(G$2,'[5]Budget révisé'!$A$2:$AO$2,0)) -> 0 | H12: =IF(G12=0,0,I12/G12) -> 0 | I12: =+INDEX('[5]Budget révisé'!$A$2:$AO$496,MATCH($A12,'[5]Budget révisé'!$A$2:$A$496,0),MATCH(I$2,'[5]Budget révisé'!$A$2:$AO$2,0)) -> 0 | J12: =-SUMIFS([5]BV_Data_An_Cour!$O:$O,[5]BV_Data_An_Cour!$U:$U,$B12,[5]BV_Data_An_Cour!$V:$V,$C12,[5]BV_Data_An_Cour!$W:$W,J$2) -> 0 | K12: =IF(J12=0,0,L12/J12) -> 0 | L12: =-SUMIFS([5]BV_Data_An_Cour!$O:$O,[5]BV_Data_An_Cour!$U:$U,$B12,[5]BV_Data_An_Cour!$V:$V,$C12,[5]BV_Data_An_Cour!$W:$W,L$2) -> 0 | M12: =J12-G12 -> 0 | N12: =L12-I12 -> 0 | O12: =-SUMIFS([5]BV_Data_An_Prec!$O:$O,[5]BV_Data_An_Prec!$U:$U,$B12,[5]BV_Data_An_Prec!$V:$V,$C12,[5]BV_Data_An_Prec!$W:$W,O$2) -> 0 | P12: =IF(O12=0,0,Q12/O12) -> 0 | Q12: =-SUMIFS([5]BV_Data_An_Prec!$O:$O,[5]BV_Data_An_Prec!$U:$U,$B12,[5]BV_Data_An_Prec!$V:$V,$C12,[5]BV_Data_An_Prec!$W:$W,Q$2) -> 0 | R12: =J12-O12 -> 0 | S12: =L12-Q12 -> 0
A13: =+B13&C13 -> Véhicules neufsTotal Neufs | B13: =+$K$1 -> Véhicules neufs | C13: Total Neufs | D13: =+SUM(D6:D12) -> 64.125559 | E13: =IF(D13<=0,0,F13/D13) -> 1011.9718 | F13: =+SUM(F6:F12) -> 64893.259 | G13: =+SUM(G6:G12) -> 64.125559 | H13: =IF(G13<=0,0,I13/G13) -> 1383.6161 | I13: =+SUM(I6:I12) -> 88725.158 | J13: =+SUM(J6:J12) -> 65 | K13: =IF(J13<=0,0,L13/J13) -> 1542.5949 | L13: =+SUM(L6:L12) -> 100268.67 | M13: =+SUM(M6:M12) -> 0.87444115 | N13: =+SUM(N6:N12) -> 11543.512 | O13: =+SUM(O6:O12) -> 84 | P13: =IF(O13<=0,0,Q13/O13) -> 726.53583 | Q13: =+SUM(Q6:Q12) -> 61029.01 | R13: =+SUM(R6:R12) -> -19 | S13: =+SUM(S6:S12) -> 39239.66
A14: =+B14&C14 -> Véhicules neufs | B14: =+$K$1 -> Véhicules neufs | M14: =IF(G13=0,0,M13/G13) -> 0.01363639 | N14: =IF(I13=0,0,N13/I13) -> 0.13010416 | R14: =R13/O13 -> -0.22619048 | S14: =IF(Q13=0,0,(S13/Q13)) -> 0.64296734
A15: =+B15&C15 -> Véhicules neufsEx-Démos et courtoisies | B15: =+$K$1 -> Véhicules neufs | C15: Ex-Démos et courtoisies | D15: =+INDEX('[5]Budget original'!$A$2:$AO$496,MATCH($A15,'[5]Budget original'!$A$2:$A$496,0),MATCH(D$2,'[5]Budget original'!$A$2:$AO$2,0)) -> 6.683509 | E15: =IF(D15=0,0,F15/D15) -> 400 | F15: =+INDEX('[5]Budget original'!$A$2:$AO$496,MATCH($A15,'[5]Budget original'!$A$2:$A$496,0),MATCH(F$2,'[5]Budget original'!$A$2:$AO$2,0)) -> 2673.4036 | G15: =+INDEX('[5]Budget révisé'!$A$2:$AO$496,MATCH($A15,'[5]Budget révisé'!$A$2:$A$496,0),MATCH(G$2,'[5]Budget révisé'!$A$2:$AO$2,0)) -> 6.683509 | H15: =IF(G15=0,0,I15/G15) -> 790.03378 | I15: =+INDEX('[5]Budget révisé'!$A$2:$AO$496,MATCH($A15,'[5]Budget révisé'!$A$2:$A$496,0),MATCH(I$2,'[5]Budget révisé'!$A$2:$AO$2,0)) -> 5280.1979 | J15: =-SUMIFS([5]BV_Data_An_Cour!$O:$O,[5]BV_Data_An_Cour!$U:$U,$B15,[5]BV_Data_An_Cour!$V:$V,$C15,[5]BV_Data_An_Cour!$W:$W,J$2) -> 3 | K15: =IF(J15=0,0,L15/J15) -> 1041.6767 | L15: =-SUMIFS([5]BV_Data_An_Cour!$O:$O,[5]BV_Data_An_Cour!$U:$U,$B15,[5]BV_Data_An_Cour!$V:$V,$C15,[5]BV_Data_An_Cour!$W:$W,L$2) -> 3125.03 | M15: =J15-G15 -> -3.683509 | N15: =L15-I15 -> -2155.1679 | O15: =-SUMIFS([5]BV_Data_An_Prec!$O:$O,[5]BV_Data_An_Prec!$U:$U,$B15,[5]BV_Data_An_Prec!$V:$V,$C15,[5]BV_Data_An_Prec!$W:$W,O$2) -> 0 | P15: =IF(O15=0,0,Q15/O15) -> 0 | Q15: =-SUMIFS([5]BV_Data_An_Prec!$O:$O,[5]BV_Data_An_Prec!$U:$U,$B15,[5]BV_Data_An_Prec!$V:$V,$C15,[5]BV_Data_An_Prec!$W:$W,Q$2) -> 0 | R15: =J15-O15 -> 3 | S15: =L15-Q15 -> 3125.03 | V15: =3125-L15 -> -0.03
A16: =+B16&C16 -> Véhicules neufs | B16: =+$K$1 -> Véhicules neufs
A17: =+B17&C17 -> Véhicules neufsFlottes | B17: =+$K$1 -> Véhicules neufs | C17: Flottes | D17: =+INDEX('[5]Budget original'!$A$2:$AO$496,MATCH($A17,'[5]Budget original'!$A$2:$A$496,0),MATCH(D$2,'[5]Budget original'!$A$2:$AO$2,0)) -> 0 | E17: =IF(D17=0,0,F17/D17) -> 0 | F17: =+INDEX('[5]Budget original'!$A$2:$AO$496,MATCH($A17,'[5]Budget original'!$A$2:$A$496,0),MATCH(F$2,'[5]Budget original'!$A$2:$AO$2,0)) -> 0 | G17: =+INDEX('[5]Budget révisé'!$A$2:$AO$496,MATCH($A17,'[5]Budget révisé'!$A$2:$A$496,0),MATCH(G$2,'[5]Budget révisé'!$A$2:$AO$2,0)) -> 2.4487254 | H17: =IF(G17=0,0,I17/G17) -> 800 | I17: =+INDEX('[5]Budget révisé'!$A$2:$AO$496,MATCH($A17,'[5]Budget révisé'!$A$2:$A$496,0),MATCH(I$2,'[5]Budget révisé'!$A$2:$AO$2,0)) -> 1958.9803 | J17: =-SUMIFS([5]BV_Data_An_Cour!$O:$O,[5]BV_Data_An_Cour!$U:$U,$B17,[5]BV_Data_An_Cour!$V:$V,$C17,[5]BV_Data_An_Cour!$W:$W,J$2) -> 5 | K17: =IF(J17=0,0,L17/J17) -> 2400.116 | L17: =-SUMIFS([5]BV_Data_An_Cour!$O:$O,[5]BV_Data_An_Cour!$U:$U,$B17,[5]BV_Data_An_Cour!$V:$V,$C17,[5]BV_Data_An_Cour!$W:$W,L$2) -> 12000.58 | M17: =J17-G17 -> 2.5512746 | N17: =L17-I17 -> 10041.6 | O17: =-SUMIFS([5]BV_Data_An_Prec!$O:$O,[5]BV_Data_An_Prec!$U:$U,$B17,[5]BV_Data_An_Prec!$V:$V,$C17,[5]BV_Data_An_Prec!$W:$W,O$2) -> 0 | P17: =IF(O17=0,0,Q17/O17) -> 0 | Q17: =-SUMIFS([5]BV_Data_An_Prec!$O:$O,[5]BV_Data_An_Prec!$U:$U,$B17,[5]BV_Data_An_Prec!$V:$V,$C17,[5]BV_Data_An_Prec!$W:$W,Q$2) -> 0 | R17: =J17-O17 -> 5 | S17: =L17-Q17 -> 12000.58
A18: =+B18&C18 -> Véhicules neufs | B18: =+$K$1 -> Véhicules neufs
A19: =+B19&C19 -> Véhicules neufsRachat bail | B19: =+$K$1 -> Véhicules neufs | C19: Rachat bail | D19: =+INDEX('[5]Budget original'!$A$2:$AO$496,MATCH($A19,'[5]Budget original'!$A$2:$A$496,0),MATCH(D$2,'[5]Budget original'!$A$2:$AO$2,0)) -> 0 | E19: =IF(D19=0,0,F19/D19) -> 0 | F19: =+INDEX('[5]Budget original'!$A$2:$AO$496,MATCH($A19,'[5]Budget original'!$A$2:$A$496,0),MATCH(F$2,'[5]Budget original'!$A$2:$AO$2,0)) -> 5000 | G19: =+INDEX('[5]Budget révisé'!$A$2:$AO$496,MATCH($A19,'[5]Budget révisé'!$A$2:$A$496,0),MATCH(G$2,'[5]Budget révisé'!$A$2:$AO$2,0)) -> 0 | H19: =IF(G19=0,0,I19/G19) -> 0 | I19: =+INDEX('[5]Budget révisé'!$A$2:$AO$496,MATCH($A19,'[5]Budget révisé'!$A$2:$A$496,0),MATCH(I$2,'[5]Budget révisé'!$A$2:$AO$2,0)) -> 5000 | L19: =-SUMIFS([5]BV_Data_An_Cour!$O:$O,[5]BV_Data_An_Cour!$U:$U,$B19,[5]BV_Data_An_Cour!$V:$V,$C19,[5]BV_Data_An_Cour!$W:$W,L$2) -> 10386.97 | N19: =L19-I19 -> 5386.97 | Q19: =-SUMIFS([5]BV_Data_An_Prec!$O:$O,[5]BV_Data_An_Prec!$U:$U,$B19,[5]BV_Data_An_Prec!$V:$V,$C19,[5]BV_Data_An_Prec!$W:$W,Q$2) -> 6189.54 | R19: =O19-K19 -> 0 | S19: =L19-Q19 -> 4197.43 | U19: Budget | V19: =G13+G15+G17 -> 73.257793 | W19: =I13+I15+I17 -> 95964.336 | X19: =W19/V19 -> 1309.954
A20: =+B20&C20 -> Véhicules neufs | B20: =+$K$1 -> Véhicules neufs | U20: 2021 | V20: =J13+J15+J17 -> 73 | W20: =L13+L15+L17 -> 115394.28 | X20: =W20/V20 -> 1580.7436
A21: =+B21&C21 -> Véhicules neufsRev. Finances | B21: =+$K$1 -> Véhicules neufs | C21: Rev. Finances | D21: =+INDEX('[5]Budget original'!$A$2:$AO$496,MATCH($A21,'[5]Budget original'!$A$2:$A$496,0),MATCH(D$2,'[5]Budget original'!$A$2:$AO$2,0)) -> 0 | E21: =IF(D21=0,0,F21/D21) -> 0 | F21: =+INDEX('[5]Budget original'!$A$2:$AO$496,MATCH($A21,'[5]Budget original'!$A$2:$A$496,0),MATCH(F$2,'[5]Budget original'!$A$2:$AO$2,0)) -> 6661.7025 | G21: =+INDEX('[5]Budget révisé'!$A$2:$AO$496,MATCH($A21,'[5]Budget révisé'!$A$2:$A$496,0),MATCH(G$2,'[5]Budget révisé'!$A$2:$AO$2,0)) -> 0 | H21: =IF(G21=0,0,I21/G21) -> 0 | I21: =+INDEX('[5]Budget révisé'!$A$2:$AO$496,MATCH($A21,'[5]Budget révisé'!$A$2:$A$496,0),MATCH(I$2,'[5]Budget révisé'!$A$2:$AO$2,0)) -> 6661.7025 | K21: =IF(J13=0,0,L21/(J13+J15)) -> 93.977941 | L21: =-SUMIFS([5]BV_Data_An_Cour!$O:$O,[5]BV_Data_An_Cour!$U:$U,$B21,[5]BV_Data_An_Cour!$V:$V,$C21,[5]BV_Data_An_Cour!$W:$W,L$2) -> 6390.5 | N21: =L21-I21 -> -271.20252 | P21: =IF(O13=0,0,Q21/(O13+O15)) -> 136.6225 | Q21: =-SUMIFS([5]BV_Data_An_Prec!$O:$O,[5]BV_Data_An_Prec!$U:$U,$B21,[5]BV_Data_An_Prec!$V:$V,$C21,[5]BV_Data_An_Prec!$W:$W,Q$2) -> 11476.29 | R21: =O21-K21 -> -93.977941 | S21: =L21-Q21 -> -5085.79
A22: =+B22&C22 -> Véhicules neufsRev. Protections | B22: =+$K$1 -> Véhicules neufs | C22: Rev. Protections | D22: =+INDEX('[5]Budget original'!$A$2:$AO$496,MATCH($A22,'[5]Budget original'!$A$2:$A$496,0),MATCH(D$2,'[5]Budget original'!$A$2:$AO$2,0)) -> 0 | E22: =IF(D22=0,0,F22/D22) -> 0 | F22: =+INDEX('[5]Budget original'!$A$2:$AO$496,MATCH($A22,'[5]Budget original'!$A$2:$A$496,0),MATCH(F$2,'[5]Budget original'!$A$2:$AO$2,0)) -> 52209.157 | G22: =+INDEX('[5]Budget révisé'!$A$2:$AO$496,MATCH($A22,'[5]Budget révisé'!$A$2:$A$496,0),MATCH(G$2,'[5]Budget révisé'!$A$2:$AO$2,0)) -> 0 | H22: =IF(G22=0,0,I22/G22) -> 0 | I22: =+INDEX('[5]Budget révisé'!$A$2:$AO$496,MATCH($A22,'[5]Budget révisé'!$A$2:$A$496,0),MATCH(I$2,'[5]Budget révisé'!$A$2:$AO$2,0)) -> 52209.157 | K22: =IF(J13=0,0,L22/(J13+J15)) -> 763.56294 | L22: =-SUMIFS([5]BV_Data_An_Cour!$O:$O,[5]BV_Data_An_Cour!$U:$U,$B22,[5]BV_Data_An_Cour!$V:$V,$C22,[5]BV_Data_An_Cour!$W:$W,L$2) -> 51922.28 | N22: =L22-I22 -> -286.87694 | P22: =IF(O13=0,0,Q22/(O13+O15)) -> 607.75679 | Q22: =-SUMIFS([5]BV_Data_An_Prec!$O:$O,[5]BV_Data_An_Prec!$U:$U,$B22,[5]BV_Data_An_Prec!$V:$V,$C22,[5]BV_Data_An_Prec!$W:$W,Q$2) -> 51051.57 | R22: =O22-K22 -> -763.56294 | S22: =L22-Q22 -> 870.71
A23: =+B23&C23 -> Véhicules neufsRev. Autres | B23: =+$K$1 -> Véhicules neufs | C23: Rev. Autres | D23: =+INDEX('[5]Budget original'!$A$2:$AO$496,MATCH($A23,'[5]Budget original'!$A$2:$A$496,0),MATCH(D$2,'[5]Budget original'!$A$2:$AO$2,0)) -> 0 | E23: =IF(D23=0,0,F23/D23) -> 0 | F23: =+INDEX('[5]Budget original'!$A$2:$AO$496,MATCH($A23,'[5]Budget original'!$A$2:$A$496,0),MATCH(F$2,'[5]Budget original'!$A$2:$AO$2,0)) -> 1316.8482 | G23: =+INDEX('[5]Budget révisé'!$A$2:$AO$496,MATCH($A23,'[5]Budget révisé'!$A$2:$A$496,0),MATCH(G$2,'[5]Budget révisé'!$A$2:$AO$2,0)) -> 0 | H23: =IF(G23=0,0,I23/G23) -> 0 | I23: =+INDEX('[5]Budget révisé'!$A$2:$AO$496,MATCH($A23,'[5]Budget révisé'!$A$2:$A$496,0),MATCH(I$2,'[5]Budget révisé'!$A$2:$AO$2,0)) -> 1316.8482 | K23: =IF(J13=0,0,L23/(J13+J15)) -> 14.451618 | L23: =-SUMIFS([5]BV_Data_An_Cour!$O:$O,[5]BV_Data_An_Cour!$U:$U,$B23,[5]BV_Data_An_Cour!$V:$V,$C23,[5]BV_Data_An_Cour!$W:$W,L$2) -> 982.71 | N23: =L23-I23 -> -334.13817 | P23: =IF(O13=0,0,Q23/(O13+O15)) -> 9.5772619 | Q23: =-SUMIFS([5]BV_Data_An_Prec!$O:$O,[5]BV_Data_An_Prec!$U:$U,$B23,[5]BV_Data_An_Prec!$V:$V,$C23,[5]BV_Data_An_Prec!$W:$W,Q$2) -> 804.49 | R23: =O23-K23 -> -14.451618 | S23: =L23-Q23 -> 178.22
A24: =+B24&C24 -> Véhicules neufsTotal F&I | B24: =+$K$1 -> Véhicules neufs | C24: Total F&I | D24: =+D15+D13 -> 70.809068 | E24: =IF(D24<=0,0,F24/D24) -> 850 | F24: =F21+F22+F23 -> 60187.708 | G24: =+G15+G13 -> 70.809068 | H24: =IF(G24<=0,0,I24/G24) -> 850 | I24: =I21+I22+I23 -> 60187.708 | J24: =+J15+J13 -> 68 | K24: =IF(J24<=0,0,L24/J24) -> 871.9925 | L24: =L21+L22+L23 -> 59295.49 | M24: =J24-G24 -> -2.8090678 | N24: =L24-I24 -> -892.21763 | O24: =+O15+O13 -> 84 | P24: =IF(O24<=0,0,Q24/O24) -> 753.95655 | Q24: =Q21+Q22+Q23 -> 63332.35 | S24: =L24-Q24 -> -4036.86
A25: =+B25&C25 -> Véhicules neufs | B25: =+$K$1 -> Véhicules neufs | N25: =IF(N24=0,0,N24/I24) -> -0.014823918 | S25: =IF(Q24=0,0,(S24/Q24)) -> -0.063740884
A26: =+B26&C26 -> Véhicules neufs | B26: =+$K$1 -> Véhicules neufs
A27: =+B27&C27 -> Véhicules neufsTotal Dépt. Neufs | B27: =+$K$1 -> Véhicules neufs | C27: Total Dépt. Neufs | D27: =+D13+D15+D17 -> 70.809068 | E27: =IF(D27<=0,0,F27/D27) -> 1874.8216 | F27: =F13+F17+F24+F19+F15 -> 132754.37 | G27: =+G13+G15+G17 -> 73.257793 | H27: =IF(G27<=0,0,I27/G27) -> 2199.7939 | I27: =I13+I17+I24+I19+I15 -> 161152.04 | J27: =+J13+J15+J17 -> 73 | K27: =IF(J27<=0,0,L27/J27) -> 2535.2978 | L27: =L13+L17+L24+L19+L15 -> 185076.74 | M27: =J27-G27 -> -0.25779317 | N27: =L27-I27 -> 23924.696 | O27: =+O13+O15+O17 -> 84 | P27: =IF(O27<=0,0,Q27/O27) -> 1554.1774 | Q27: =Q13+Q17+Q24+Q19+Q15 -> 130550.9 | R27: =J27-O27 -> -11 | S27: =L27-Q27 -> 54525.84
A28: =+B28&C28 -> Véhicules neufs | B28: =+$K$1 -> Véhicules neufs | M28: =M27/G27 -> -0.0035189862 | N28: =N27/I27 -> 0.1484604 | R28: =R27/O27 -> -0.13095238 | S28: =IF(Q27=0,0,S27/Q27) -> 0.41765963
A29: =+B29&C29 -> Véhicules neufs | B29: =+$K$1 -> Véhicules neufs
A30: =+B30&C30 -> Véhicules neufsDEPENSES | B30: =+$K$1 -> Véhicules neufs | C30: DEPENSES
A31: =+B31&C31 -> Véhicules neufsComm. vendeurs | B31: =+$K$1 -> Véhicules neufs | C31: Comm. vendeurs | E31: =F31/D$24 -> 372.59495 | F31: =+INDEX('[5]Budget original'!$A$2:$AO$496,MATCH($A31,'[5]Budget original'!$A$2:$A$496,0),MATCH(F$2,'[5]Budget original'!$A$2:$AO$2,0)) -> 26383.101 | G31: =I31/(I15+I13) -> 0.28622244 | H31: =I31/G$24 -> 379.98583 | I31: =+INDEX('[5]Budget révisé'!$A$2:$AO$496,MATCH($A31,'[5]Budget révisé'!$A$2:$A$496,0),MATCH(I$2,'[5]Budget révisé'!$A$2:$AO$2,0)) -> 26906.443 | J31: =L31/(L15+L13) -> 0.40075885 | K31: =IF(L31=0,0,L31/J$24) -> 609.35206 | L31: =SUMIFS([5]BV_Data_An_Cour!$O:$O,[5]BV_Data_An_Cour!$U:$U,$B31,[5]BV_Data_An_Cour!$V:$V,$C31,[5]BV_Data_An_Cour!$W:$W,L$2) -> 41435.94 | N31: =L31-I31 -> 14529.497 | P31: =IF(Q31=0,0,Q31/O$24) -> 356.51679 | Q31: =SUMIFS([5]BV_Data_An_Prec!$O:$O,[5]BV_Data_An_Prec!$U:$U,$B31,[5]BV_Data_An_Prec!$V:$V,$C31,[5]BV_Data_An_Prec!$W:$W,Q$2) -> 29947.41 | S31: =L31-Q31 -> 11488.53
A32: =+B32&C32 -> Véhicules neufsComm. F&I | B32: =+$K$1 -> Véhicules neufs | C32: Comm. F&I | E32: =F32/D$24 -> 255 | F32: =+INDEX('[5]Budget original'!$A$2:$AO$496,MATCH($A32,'[5]Budget original'!$A$2:$A$496,0),MATCH(F$2,'[5]Budget original'!$A$2:$AO$2,0)) -> 18056.312 | G32: =I32/I24 -> 0.3 | H32: =I32/G$24 -> 255 | I32: =+INDEX('[5]Budget révisé'!$A$2:$AO$496,MATCH($A32,'[5]Budget révisé'!$A$2:$A$496,0),MATCH(I$2,'[5]Budget révisé'!$A$2:$AO$2,0)) -> 18056.312 | J32: =L32/L24 -> 0.31930793 | K32: =IF(L32=0,0,L32/J$24) -> 278.43412 | L32: =SUMIFS([5]BV_Data_An_Cour!$O:$O,[5]BV_Data_An_Cour!$U:$U,$B32,[5]BV_Data_An_Cour!$V:$V,$C32,[5]BV_Data_An_Cour!$W:$W,L$2) -> 18933.52 | N32: =L32-I32 -> 877.20771 | P32: =IF(Q32=0,0,Q32/O$24) -> 201.43083 | Q32: =SUMIFS([5]BV_Data_An_Prec!$O:$O,[5]BV_Data_An_Prec!$U:$U,$B32,[5]BV_Data_An_Prec!$V:$V,$C32,[5]BV_Data_An_Prec!$W:$W,Q$2) -> 16920.19 | S32: =L32-Q32 -> 2013.33
A33: =+B33&C33 -> Véhicules neufsFrais de livraison | B33: =+$K$1 -> Véhicules neufs | C33: Frais de livraison | E33: =F33/D$24 -> 197 | F33: =+INDEX('[5]Budget original'!$A$2:$AO$496,MATCH($A33,'[5]Budget original'!$A$2:$A$496,0),MATCH(F$2,'[5]Budget original'!$A$2:$AO$2,0)) -> 13949.386 | H33: =I33/G$24 -> 197 | I33: =+INDEX('[5]Budget révisé'!$A$2:$AO$496,MATCH($A33,'[5]Budget révisé'!$A$2:$A$496,0),MATCH(I$2,'[5]Budget révisé'!$A$2:$AO$2,0)) -> 13949.386 | K33: =IF(L33=0,0,L33/J$24) -> 186.22485 | L33: =SUMIFS([5]BV_Data_An_Cour!$O:$O,[5]BV_Data_An_Cour!$U:$U,$B33,[5]BV_Data_An_Cour!$V:$V,$C33,[5]BV_Data_An_Cour!$W:$W,L$2) -> 12663.29 | N33: =L33-I33 -> -1286.0964 | P33: =IF(Q33=0,0,Q33/O$24) -> 160.20167 | Q33: =SUMIFS([5]BV_Data_An_Prec!$O:$O,[5]BV_Data_An_Prec!$U:$U,$B33,[5]BV_Data_An_Prec!$V:$V,$C33,[5]BV_Data_An_Prec!$W:$W,Q$2) -> 13456.94 | S33: =L33-Q33 -> -793.65 | W33: =L24*0.3 -> 17788.647
A34: =+B34&C34 -> Véhicules neufsService gratuit 1 | B34: =+$K$1 -> Véhicules neufs | C34: Service gratuit 1 | E34: =F34/D$24 -> 6 | F34: =+INDEX('[5]Budget original'!$A$2:$AO$496,MATCH($A34,'[5]Budget original'!$A$2:$A$496,0),MATCH(F$2,'[5]Budget original'!$A$2:$AO$2,0)) -> 424.85441 | H34: =I34/G$24 -> 6 | I34: =+INDEX('[5]Budget révisé'!$A$2:$AO$496,MATCH($A34,'[5]Budget révisé'!$A$2:$A$496,0),MATCH(I$2,'[5]Budget révisé'!$A$2:$AO$2,0)) -> 424.85441 | K34: =IF(L34=0,0,L34/J$24) -> 10.717647 | L34: =SUMIFS([5]BV_Data_An_Cour!$O:$O,[5]BV_Data_An_Cour!$U:$U,$B34,[5]BV_Data_An_Cour!$V:$V,$C34,[5]BV_Data_An_Cour!$W:$W,L$2) -> 728.8 | N34: =L34-I34 -> 303.94559 | P34: =IF(Q34=0,0,Q34/O$24) -> 0 | Q34: =SUMIFS([5]BV_Data_An_Prec!$O:$O,[5]BV_Data_An_Prec!$U:$U,$B34,[5]BV_Data_An_Prec!$V:$V,$C34,[5]BV_Data_An_Prec!$W:$W,Q$2) -> 0 | S34: =L34-Q34 -> 728.8
A35: =+B35&C35 -> Véhicules neufsEntretien stock | B35: =+$K$1 -> Véhicules neufs | C35: Entretien stock | E35: =F35/D$24 -> 34 | F35: =+INDEX('[5]Budget original'!$A$2:$AO$496,MATCH($A35,'[5]Budget original'!$A$2:$A$496,0),MATCH(F$2,'[5]Budget original'!$A$2:$AO$2,0)) -> 2407.5083 | H35: =I35/G$24 -> 34 | I35: =+INDEX('[5]Budget révisé'!$A$2:$AO$496,MATCH($A35,'[5]Budget révisé'!$A$2:$A$496,0),MATCH(I$2,'[5]Budget révisé'!$A$2:$AO$2,0)) -> 2407.5083 | K35: =IF(L35=0,0,L35/J$24) -> 13.796029 | L35: =SUMIFS([5]BV_Data_An_Cour!$O:$O,[5]BV_Data_An_Cour!$U:$U,$B35,[5]BV_Data_An_Cour!$V:$V,$C35,[5]BV_Data_An_Cour!$W:$W,L$2) -> 938.13 | N35: =L35-I35 -> -1469.3783 | P35: =IF(Q35=0,0,Q35/O$24) -> 14.53869 | Q35: =SUMIFS([5]BV_Data_An_Prec!$O:$O,[5]BV_Data_An_Prec!$U:$U,$B35,[5]BV_Data_An_Prec!$V:$V,$C35,[5]BV_Data_An_Prec!$W:$W,Q$2) -> 1221.25 | S35: =L35-Q35 -> -283.12 | W35: =L32-W33 -> 1144.873
A36: =+B36&C36 -> Véhicules neufsPublicité 1 | B36: =+$K$1 -> Véhicules neufs | C36: Publicité 1 | E36: =F36/D$24 -> 180.66964 | F36: =+INDEX('[5]Budget original'!$A$2:$AO$496,MATCH($A36,'[5]Budget original'!$A$2:$A$496,0),MATCH(F$2,'[5]Budget original'!$A$2:$AO$2,0)) -> 12793.049 | H36: =I36/G$24 -> 180.66964 | I36: =+INDEX('[5]Budget révisé'!$A$2:$AO$496,MATCH($A36,'[5]Budget révisé'!$A$2:$A$496,0),MATCH(I$2,'[5]Budget révisé'!$A$2:$AO$2,0)) -> 12793.049 | K36: =IF(L36=0,0,L36/J$24) -> 179.49603 | L36: =SUMIFS([5]BV_Data_An_Cour!$O:$O,[5]BV_Data_An_Cour!$U:$U,$B36,[5]BV_Data_An_Cour!$V:$V,$C36,[5]BV_Data_An_Cour!$W:$W,L$2) -> 12205.73 | N36: =L36-I36 -> -587.31899 | P36: =IF(Q36=0,0,Q36/O$24) -> 76.071429 | Q36: =SUMIFS([5]BV_Data_An_Prec!$O:$O,[5]BV_Data_An_Prec!$U:$U,$B36,[5]BV_Data_An_Prec!$V:$V,$C36,[5]BV_Data_An_Prec!$W:$W,Q$2) -> 6390 | S36: =L36-Q36 -> 5815.73
A37: =+B37&C37 -> Véhicules neufsIntérêt de gros | B37: =+$K$1 -> Véhicules neufs | C37: Intérêt de gros | E37: =F37/D$24 -> 217.69014 | F37: =+INDEX('[5]Budget original'!$A$2:$AO$496,MATCH($A37,'[5]Budget original'!$A$2:$A$496,0),MATCH(F$2,'[5]Budget original'!$A$2:$AO$2,0)) -> 15414.436 | H37: =I37/G$24 -> 219.79355 | I37: =+INDEX('[5]Budget révisé'!$A$2:$AO$496,MATCH($A37,'[5]Budget révisé'!$A$2:$A$496,0),MATCH(I$2,'[5]Budget révisé'!$A$2:$AO$2,0)) -> 15563.376 | K37: =IF(L37=0,0,L37/J$24) -> 226.95059 | L37: =SUMIFS([5]BV_Data_An_Cour!$O:$O,[5]BV_Data_An_Cour!$U:$U,$B37,[5]BV_Data_An_Cour!$V:$V,$C37,[5]BV_Data_An_Cour!$W:$W,L$2) -> 15432.64 | N37: =L37-I37 -> -130.73608 | P37: =IF(Q37=0,0,Q37/O$24) -> 235.93357 | Q37: =SUMIFS([5]BV_Data_An_Prec!$O:$O,[5]BV_Data_An_Prec!$U:$U,$B37,[5]BV_Data_An_Prec!$V:$V,$C37,[5]BV_Data_An_Prec!$W:$W,Q$2) -> 19818.42 | S37: =L37-Q37 -> -4385.78
A38: =+B38&C38 -> Véhicules neufs[...] | B38: =+$K$1 -> Véhicules neufs | C38: [...] | E38: =F38/D$24 -> 0 | F38: =+INDEX('[5]Budget original'!$A$2:$AO$496,MATCH($A38,'[5]Budget original'!$A$2:$A$496,0),MATCH(F$2,'[5]Budget original'!$A$2:$AO$2,0)) -> 0 | H38: =I38/G$24 -> 0 | I38: =+INDEX('[5]Budget révisé'!$A$2:$AO$496,MATCH($A38,'[5]Budget révisé'!$A$2:$A$496,0),MATCH(I$2,'[5]Budget révisé'!$A$2:$AO$2,0)) -> 0 | K38: =IF(L38=0,0,L38/J$24) -> 0 | L38: =SUMIFS([5]BV_Data_An_Cour!$O:$O,[5]BV_Data_An_Cour!$U:$U,$B38,[5]BV_Data_An_Cour!$V:$V,$C38,[5]BV_Data_An_Cour!$W:$W,L$2) -> 0 | N38: =L38-I38 -> 0 | P38: =IF(Q38=0,0,Q38/O$24) -> 0 | Q38: =SUMIFS([5]BV_Data_An_Prec!$O:$O,[5]BV_Data_An_Prec!$U:$U,$B38,[5]BV_Data_An_Prec!$V:$V,$C38,[5]BV_Data_An_Prec!$W:$W,Q$2) -> 0 | S38: =L38-Q38 -> 0
A39: =+B39&C39 -> Véhicules neufs[...] | B39: =+$K$1 -> Véhicules neufs | C39: [...] | E39: =F39/D$24 -> 0 | F39: =+INDEX('[5]Budget original'!$A$2:$AO$496,MATCH($A39,'[5]Budget original'!$A$2:$A$496,0),MATCH(F$2,'[5]Budget original'!$A$2:$AO$2,0)) -> 0 | H39: =I39/G$24 -> 0 | I39: =+INDEX('[5]Budget révisé'!$A$2:$AO$496,MATCH($A39,'[5]Budget révisé'!$A$2:$A$496,0),MATCH(I$2,'[5]Budget révisé'!$A$2:$AO$2,0)) -> 0 | K39: =IF(L39=0,0,L39/J$24) -> 0 | L39: =SUMIFS([5]BV_Data_An_Cour!$O:$O,[5]BV_Data_An_Cour!$U:$U,$B39,[5]BV_Data_An_Cour!$V:$V,$C39,[5]BV_Data_An_Cour!$W:$W,L$2) -> 0 | N39: =L39-I39 -> 0 | P39: =IF(Q39=0,0,Q39/O$24) -> 0 | Q39: =SUMIFS([5]BV_Data_An_Prec!$O:$O,[5]BV_Data_An_Prec!$U:$U,$B39,[5]BV_Data_An_Prec!$V:$V,$C39,[5]BV_Data_An_Prec!$W:$W,Q$2) -> 0 | S39: =L39-Q39 -> 0
A40: =+B40&C40 -> Véhicules neufs[...] | B40: =+$K$1 -> Véhicules neufs | C40: [...] | E40: =F40/D$24 -> 0 | F40: =+INDEX('[5]Budget original'!$A$2:$AO$496,MATCH($A40,'[5]Budget original'!$A$2:$A$496,0),MATCH(F$2,'[5]Budget original'!$A$2:$AO$2,0)) -> 0 | H40: =I40/G$24 -> 0 | I40: =+INDEX('[5]Budget révisé'!$A$2:$AO$496,MATCH($A40,'[5]Budget révisé'!$A$2:$A$496,0),MATCH(I$2,'[5]Budget révisé'!$A$2:$AO$2,0)) -> 0 | K40: =IF(L40=0,0,L40/J$24) -> 0 | L40: =SUMIFS([5]BV_Data_An_Cour!$O:$O,[5]BV_Data_An_Cour!$U:$U,$B40,[5]BV_Data_An_Cour!$V:$V,$C40,[5]BV_Data_An_Cour!$W:$W,L$2) -> 0 | N40: =L40-I40 -> 0 | P40: =IF(Q40=0,0,Q40/O$24) -> 0 | Q40: =SUMIFS([5]BV_Data_An_Prec!$O:$O,[5]BV_Data_An_Prec!$U:$U,$B40,[5]BV_Data_An_Prec!$V:$V,$C40,[5]BV_Data_An_Prec!$W:$W,Q$2) -> 0 | S40: =L40-Q40 -> 0
A41: =+B41&C41 -> Véhicules neufsTOTAL VARIABLES | B41: =+$K$1 -> Véhicules neufs | C41: TOTAL VARIABLES | D41: % brut | E41: =F41/F$27 -> 0.67363995 | F41: =SUM(F31:F40) -> 89428.647 | G41: % brut | H41: =I41/I$27 -> 0.5591051 | I41: =SUM(I31:I40) -> 90100.929 | J41: % brut | K41: =L41/L$27 -> 0.55294928 | L41: =SUM(L31:L40) -> 102338.05 | N41: =L41-I41 -> 12237.121 | O41: % brut | P41: =Q41/Q$27 -> 0.67218388 | Q41: =SUM(Q31:Q40) -> 87754.21 | S41: =L41-Q41 -> 14583.84
A42: =+B42&C42 -> Véhicules neufsSalaires cadres | B42: =+$K$1 -> Véhicules neufs | C42: Salaires cadres | F42: =+INDEX('[5]Budget original'!$A$2:$AO$496,MATCH($A42,'[5]Budget original'!$A$2:$A$496,0),MATCH(F$2,'[5]Budget original'!$A$2:$AO$2,0)) -> 24368.632 | I42: =+INDEX('[5]Budget révisé'!$A$2:$AO$496,MATCH($A42,'[5]Budget révisé'!$A$2:$A$496,0),MATCH(I$2,'[5]Budget révisé'!$A$2:$AO$2,0)) -> 24368.632 | L42: =SUMIFS([5]BV_Data_An_Cour!$O:$O,[5]BV_Data_An_Cour!$U:$U,$B42,[5]BV_Data_An_Cour!$V:$V,$C42,[5]BV_Data_An_Cour!$W:$W,L$2) -> 23208.79 | N42: =L42-I42 -> -1159.8416 | Q42: =SUMIFS([5]BV_Data_An_Prec!$O:$O,[5]BV_Data_An_Prec!$U:$U,$B42,[5]BV_Data_An_Prec!$V:$V,$C42,[5]BV_Data_An_Prec!$W:$W,Q$2) -> 18256.72 | S42: =L42-Q42 -> 4952.07 | U42: Pierre Charles -67%
A43: =+B43&C43 -> Véhicules neufsSalaires commis | B43: =+$K$1 -> Véhicules neufs | C43: Salaires commis | F43: =+INDEX('[5]Budget original'!$A$2:$AO$496,MATCH($A43,'[5]Budget original'!$A$2:$A$496,0),MATCH(F$2,'[5]Budget original'!$A$2:$AO$2,0)) -> 9573.4805 | I43: =+INDEX('[5]Budget révisé'!$A$2:$AO$496,MATCH($A43,'[5]Budget révisé'!$A$2:$A$496,0),MATCH(I$2,'[5]Budget révisé'!$A$2:$AO$2,0)) -> 9573.4805 | L43: =SUMIFS([5]BV_Data_An_Cour!$O:$O,[5]BV_Data_An_Cour!$U:$U,$B43,[5]BV_Data_An_Cour!$V:$V,$C43,[5]BV_Data_An_Cour!$W:$W,L$2) -> 9482.66 | N43: =L43-I43 -> -90.820516 | Q43: =SUMIFS([5]BV_Data_An_Prec!$O:$O,[5]BV_Data_An_Prec!$U:$U,$B43,[5]BV_Data_An_Prec!$V:$V,$C43,[5]BV_Data_An_Prec!$W:$W,Q$2) -> 8581.81 | S43: =L43-Q43 -> 900.85 | V43: 3 commis en moin
A44: =+B44&C44 -> Véhicules neufsSalaires autres | B44: =+$K$1 -> Véhicules neufs | C44: Salaires autres | F44: =+INDEX('[5]Budget original'!$A$2:$AO$496,MATCH($A44,'[5]Budget original'!$A$2:$A$496,0),MATCH(F$2,'[5]Budget original'!$A$2:$AO$2,0)) -> 6032.6672 | I44: =+INDEX('[5]Budget révisé'!$A$2:$AO$496,MATCH($A44,'[5]Budget révisé'!$A$2:$A$496,0),MATCH(I$2,'[5]Budget révisé'!$A$2:$AO$2,0)) -> 6032.6672 | L44: =SUMIFS([5]BV_Data_An_Cour!$O:$O,[5]BV_Data_An_Cour!$U:$U,$B44,[5]BV_Data_An_Cour!$V:$V,$C44,[5]BV_Data_An_Cour!$W:$W,L$2) -> 9954.62 | N44: =L44-I44 -> 3921.9528 | Q44: =SUMIFS([5]BV_Data_An_Prec!$O:$O,[5]BV_Data_An_Prec!$U:$U,$B44,[5]BV_Data_An_Prec!$V:$V,$C44,[5]BV_Data_An_Prec!$W:$W,Q$2) -> 6784.68 | S44: =L44-Q44 -> 3169.94 | U44: 5e valet + Josee Massie + OT valet et homme de cout
A45: =+B45&C45 -> Véhicules neufsSalaires spécialistes | B45: =+$K$1 -> Véhicules neufs | C45: Salaires spécialistes | F45: =+INDEX('[5]Budget original'!$A$2:$AO$496,MATCH($A45,'[5]Budget original'!$A$2:$A$496,0),MATCH(F$2,'[5]Budget original'!$A$2:$AO$2,0)) -> 0 | I45: =+INDEX('[5]Budget révisé'!$A$2:$AO$496,MATCH($A45,'[5]Budget révisé'!$A$2:$A$496,0),MATCH(I$2,'[5]Budget révisé'!$A$2:$AO$2,0)) -> 0 | L45: =SUMIFS([5]BV_Data_An_Cour!$O:$O,[5]BV_Data_An_Cour!$U:$U,$B45,[5]BV_Data_An_Cour!$V:$V,$C45,[5]BV_Data_An_Cour!$W:$W,L$2) -> 0 | N45: =L45-I45 -> 0 | Q45: =SUMIFS([5]BV_Data_An_Prec!$O:$O,[5]BV_Data_An_Prec!$U:$U,$B45,[5]BV_Data_An_Prec!$V:$V,$C45,[5]BV_Data_An_Prec!$W:$W,Q$2) -> 0 | S45: =L45-Q45 -> 0
A46: =+B46&C46 -> Véhicules neufs[...] | B46: =+$K$1 -> Véhicules neufs | C46: [...] | F46: =+INDEX('[5]Budget original'!$A$2:$AO$496,MATCH($A46,'[5]Budget original'!$A$2:$A$496,0),MATCH(F$2,'[5]Budget original'!$A$2:$AO$2,0)) -> 0 | I46: =+INDEX('[5]Budget révisé'!$A$2:$AO$496,MATCH($A46,'[5]Budget révisé'!$A$2:$A$496,0),MATCH(I$2,'[5]Budget révisé'!$A$2:$AO$2,0)) -> 0 | L46: =SUMIFS([5]BV_Data_An_Cour!$O:$O,[5]BV_Data_An_Cour!$U:$U,$B46,[5]BV_Data_An_Cour!$V:$V,$C46,[5]BV_Data_An_Cour!$W:$W,L$2) -> 0 | N46: =L46-I46 -> 0 | Q46: =SUMIFS([5]BV_Data_An_Prec!$O:$O,[5]BV_Data_An_Prec!$U:$U,$B46,[5]BV_Data_An_Prec!$V:$V,$C46,[5]BV_Data_An_Prec!$W:$W,Q$2) -> 0 | S46: =L46-Q46 -> 0
A47: =+B47&C47 -> Véhicules neufs[...] | B47: =+$K$1 -> Véhicules neufs | C47: [...] | F47: =+INDEX('[5]Budget original'!$A$2:$AO$496,MATCH($A47,'[5]Budget original'!$A$2:$A$496,0),MATCH(F$2,'[5]Budget original'!$A$2:$AO$2,0)) -> 0 | I47: =+INDEX('[5]Budget révisé'!$A$2:$AO$496,MATCH($A47,'[5]Budget révisé'!$A$2:$A$496,0),MATCH(I$2,'[5]Budget révisé'!$A$2:$AO$2,0)) -> 0 | L47: =SUMIFS([5]BV_Data_An_Cour!$O:$O,[5]BV_Data_An_Cour!$U:$U,$B47,[5]BV_Data_An_Cour!$V:$V,$C47,[5]BV_Data_An_Cour!$W:$W,L$2) -> 0 | N47: =L47-I47 -> 0 | Q47: =SUMIFS([5]BV_Data_An_Prec!$O:$O,[5]BV_Data_An_Prec!$U:$U,$B47,[5]BV_Data_An_Prec!$V:$V,$C47,[5]BV_Data_An_Prec!$W:$W,Q$2) -> 0 | S47: =L47-Q47 -> 0
A48: =+B48&C48 -> Véhicules neufs[...] | B48: =+$K$1 -> Véhicules neufs | C48: [...] | F48: =+INDEX('[5]Budget original'!$A$2:$AO$496,MATCH($A48,'[5]Budget original'!$A$2:$A$496,0),MATCH(F$2,'[5]Budget original'!$A$2:$AO$2,0)) -> 0 | I48: =+INDEX('[5]Budget révisé'!$A$2:$AO$496,MATCH($A48,'[5]Budget révisé'!$A$2:$A$496,0),MATCH(I$2,'[5]Budget révisé'!$A$2:$AO$2,0)) -> 0 | L48: =SUMIFS([5]BV_Data_An_Cour!$O:$O,[5]BV_Data_An_Cour!$U:$U,$B48,[5]BV_Data_An_Cour!$V:$V,$C48,[5]BV_Data_An_Cour!$W:$W,L$2) -> 0 | N48: =L48-I48 -> 0 | Q48: =SUMIFS([5]BV_Data_An_Prec!$O:$O,[5]BV_Data_An_Prec!$U:$U,$B48,[5]BV_Data_An_Prec!$V:$V,$C48,[5]BV_Data_An_Prec!$W:$W,Q$2) -> 0 | S48: =L48-Q48 -> 0
A49: =+B49&C49 -> Véhicules neufsSalaires en absences | B49: =+$K$1 -> Véhicules neufs | C49: Salaires en absences | F49: =+INDEX('[5]Budget original'!$A$2:$AO$496,MATCH($A49,'[5]Budget original'!$A$2:$A$496,0),MATCH(F$2,'[5]Budget original'!$A$2:$AO$2,0)) -> 10129.703 | I49: =+INDEX('[5]Budget révisé'!$A$2:$AO$496,MATCH($A49,'[5]Budget révisé'!$A$2:$A$496,0),MATCH(I$2,'[5]Budget révisé'!$A$2:$AO$2,0)) -> 10192.504 | L49: =SUMIFS([5]BV_Data_An_Cour!$O:$O,[5]BV_Data_An_Cour!$U:$U,$B49,[5]BV_Data_An_Cour!$V:$V,$C49,[5]BV_Data_An_Cour!$W:$W,L$2) -> 13664.22 | N49: =L49-I49 -> 3471.7159 | Q49: =SUMIFS([5]BV_Data_An_Prec!$O:$O,[5]BV_Data_An_Prec!$U:$U,$B49,[5]BV_Data_An_Prec!$V:$V,$C49,[5]BV_Data_An_Prec!$W:$W,Q$2) -> 13443.9 | S49: =L49-Q49 -> 220.32
A50: =+B50&C50 -> Véhicules neufsDéduction à la source | B50: =+$K$1 -> Véhicules neufs | C50: Déduction à la source | F50: =+INDEX('[5]Budget original'!$A$2:$AO$496,MATCH($A50,'[5]Budget original'!$A$2:$A$496,0),MATCH(F$2,'[5]Budget original'!$A$2:$AO$2,0)) -> 10129.703 | I50: =+INDEX('[5]Budget révisé'!$A$2:$AO$496,MATCH($A50,'[5]Budget révisé'!$A$2:$A$496,0),MATCH(I$2,'[5]Budget révisé'!$A$2:$AO$2,0)) -> 10192.504 | L50: =SUMIFS([5]BV_Data_An_Cour!$O:$O,[5]BV_Data_An_Cour!$U:$U,$B50,[5]BV_Data_An_Cour!$V:$V,$C50,[5]BV_Data_An_Cour!$W:$W,L$2) -> 10566.27 | N50: =L50-I50 -> 373.76588 | Q50: =SUMIFS([5]BV_Data_An_Prec!$O:$O,[5]BV_Data_An_Prec!$U:$U,$B50,[5]BV_Data_An_Prec!$V:$V,$C50,[5]BV_Data_An_Prec!$W:$W,Q$2) -> 11807.58 | S50: =L50-Q50 -> -1241.31 | U50: CORRECTION ENTRE DEPT
A51: =+B51&C51 -> Véhicules neufsBénéfices marginaux | B51: =+$K$1 -> Véhicules neufs | C51: Bénéfices marginaux | F51: =+INDEX('[5]Budget original'!$A$2:$AO$496,MATCH($A51,'[5]Budget original'!$A$2:$A$496,0),MATCH(F$2,'[5]Budget original'!$A$2:$AO$2,0)) -> 7259.6206 | I51: =+INDEX('[5]Budget révisé'!$A$2:$AO$496,MATCH($A51,'[5]Budget révisé'!$A$2:$A$496,0),MATCH(I$2,'[5]Budget révisé'!$A$2:$AO$2,0)) -> 7304.628 | L51: =SUMIFS([5]BV_Data_An_Cour!$O:$O,[5]BV_Data_An_Cour!$U:$U,$B51,[5]BV_Data_An_Cour!$V:$V,$C51,[5]BV_Data_An_Cour!$W:$W,L$2) -> 7572.49 | N51: =L51-I51 -> 267.86205 | Q51: =SUMIFS([5]BV_Data_An_Prec!$O:$O,[5]BV_Data_An_Prec!$U:$U,$B51,[5]BV_Data_An_Prec!$V:$V,$C51,[5]BV_Data_An_Prec!$W:$W,Q$2) -> 8019.25 | S51: =L51-Q51 -> -446.76
A52: =+B52&C52 -> Véhicules neufsCsst | B52: =+$K$1 -> Véhicules neufs | C52: Csst | F52: =+INDEX('[5]Budget original'!$A$2:$AO$496,MATCH($A52,'[5]Budget original'!$A$2:$A$496,0),MATCH(F$2,'[5]Budget original'!$A$2:$AO$2,0)) -> 1688.2839 | I52: =+INDEX('[5]Budget révisé'!$A$2:$AO$496,MATCH($A52,'[5]Budget révisé'!$A$2:$A$496,0),MATCH(I$2,'[5]Budget révisé'!$A$2:$AO$2,0)) -> 1698.7507 | L52: =SUMIFS([5]BV_Data_An_Cour!$O:$O,[5]BV_Data_An_Cour!$U:$U,$B52,[5]BV_Data_An_Cour!$V:$V,$C52,[5]BV_Data_An_Cour!$W:$W,L$2) -> 1761.05 | N52: =L52-I52 -> 62.299314 | Q52: =SUMIFS([5]BV_Data_An_Prec!$O:$O,[5]BV_Data_An_Prec!$U:$U,$B52,[5]BV_Data_An_Prec!$V:$V,$C52,[5]BV_Data_An_Prec!$W:$W,Q$2) -> 2738.85 | S52: =L52-Q52 -> -977.8
A53: =+B53&C53 -> Véhicules neufs[...] | B53: =+$K$1 -> Véhicules neufs | C53: [...] | F53: =+INDEX('[5]Budget original'!$A$2:$AO$496,MATCH($A53,'[5]Budget original'!$A$2:$A$496,0),MATCH(F$2,'[5]Budget original'!$A$2:$AO$2,0)) -> 0 | I53: =+INDEX('[5]Budget révisé'!$A$2:$AO$496,MATCH($A53,'[5]Budget révisé'!$A$2:$A$496,0),MATCH(I$2,'[5]Budget révisé'!$A$2:$AO$2,0)) -> 0 | L53: =SUMIFS([5]BV_Data_An_Cour!$O:$O,[5]BV_Data_An_Cour!$U:$U,$B53,[5]BV_Data_An_Cour!$V:$V,$C53,[5]BV_Data_An_Cour!$W:$W,L$2) -> 0 | N53: =L53-I53 -> 0 | Q53: =SUMIFS([5]BV_Data_An_Prec!$O:$O,[5]BV_Data_An_Prec!$U:$U,$B53,[5]BV_Data_An_Prec!$V:$V,$C53,[5]BV_Data_An_Prec!$W:$W,Q$2) -> 0 | S53: =L53-Q53 -> 0
A54: =+B54&C54 -> Véhicules neufsTOTAL PERSONNEL | B54: =+$K$1 -> Véhicules neufs | C54: TOTAL PERSONNEL | D54: % brut | E54: =F54/F$27 -> 0.52112853 | F54: =+SUM(F42:F53) -> 69182.09 | G54: % brut | H54: =I54/I$27 -> 0.43042064 | I54: =+SUM(I42:I53) -> 69363.166 | J54: % brut | K54: =L54/L$27 -> 0.41177568 | L54: =+SUM(L42:L53) -> 76210.1 | N54: =+SUM(N42:N53) -> 6846.9338 | O54: % brut | P54: =Q54/Q$27 -> 0.53337656 | Q54: =+SUM(Q42:Q53) -> 69632.79 | S54: =+SUM(S42:S53) -> 6577.31
A55: =+B55&C55 -> Véhicules neufsPublicité 2 | B55: =+$K$1 -> Véhicules neufs | C55: Publicité 2 | F55: =+INDEX('[5]Budget original'!$A$2:$AO$496,MATCH($A55,'[5]Budget original'!$A$2:$A$496,0),MATCH(F$2,'[5]Budget original'!$A$2:$AO$2,0)) -> 0 | I55: =+INDEX('[5]Budget révisé'!$A$2:$AO$496,MATCH($A55,'[5]Budget révisé'!$A$2:$A$496,0),MATCH(I$2,'[5]Budget révisé'!$A$2:$AO$2,0)) -> 0 | L55: =SUMIFS([5]BV_Data_An_Cour!$O:$O,[5]BV_Data_An_Cour!$U:$U,$B55,[5]BV_Data_An_Cour!$V:$V,$C55,[5]BV_Data_An_Cour!$W:$W,L$2) -> 0 | N55: =L55-I55 -> 0 | Q55: =SUMIFS([5]BV_Data_An_Prec!$O:$O,[5]BV_Data_An_Prec!$U:$U,$B55,[5]BV_Data_An_Prec!$V:$V,$C55,[5]BV_Data_An_Prec!$W:$W,Q$2) -> 0 | S55: =L55-Q55 -> 0
A56: =+B56&C56 -> Véhicules neufsService gratuit 2 | B56: =+$K$1 -> Véhicules neufs | C56: Service gratuit 2 | F56: =+INDEX('[5]Budget original'!$A$2:$AO$496,MATCH($A56,'[5]Budget original'!$A$2:$A$496,0),MATCH(F$2,'[5]Budget original'!$A$2:$AO$2,0)) -> 0 | I56: =+INDEX('[5]Budget révisé'!$A$2:$AO$496,MATCH($A56,'[5]Budget révisé'!$A$2:$A$496,0),MATCH(I$2,'[5]Budget révisé'!$A$2:$AO$2,0)) -> 0 | L56: =SUMIFS([5]BV_Data_An_Cour!$O:$O,[5]BV_Data_An_Cour!$U:$U,$B56,[5]BV_Data_An_Cour!$V:$V,$C56,[5]BV_Data_An_Cour!$W:$W,L$2) -> 0 | N56: =L56-I56 -> 0 | Q56: =SUMIFS([5]BV_Data_An_Prec!$O:$O,[5]BV_Data_An_Prec!$U:$U,$B56,[5]BV_Data_An_Prec!$V:$V,$C56,[5]BV_Data_An_Prec!$W:$W,Q$2) -> 0 | S56: =L56-Q56 -> 0
A57: =+B57&C57 -> Véhicules neufsFrais véhicules de cie | B57: =+$K$1 -> Véhicules neufs | C57: Frais véhicules de cie | F57: =+INDEX('[5]Budget original'!$A$2:$AO$496,MATCH($A57,'[5]Budget original'!$A$2:$A$496,0),MATCH(F$2,'[5]Budget original'!$A$2:$AO$2,0)) -> 9088.8775 | I57: =+INDEX('[5]Budget révisé'!$A$2:$AO$496,MATCH($A57,'[5]Budget révisé'!$A$2:$A$496,0),MATCH(I$2,'[5]Budget révisé'!$A$2:$AO$2,0)) -> 9088.8775 | L57: =SUMIFS([5]BV_Data_An_Cour!$O:$O,[5]BV_Data_An_Cour!$U:$U,$B57,[5]BV_Data_An_Cour!$V:$V,$C57,[5]BV_Data_An_Cour!$W:$W,L$2) -> 5494.87 | N57: =L57-I57 -> -3594.0075 | Q57: =SUMIFS([5]BV_Data_An_Prec!$O:$O,[5]BV_Data_An_Prec!$U:$U,$B57,[5]BV_Data_An_Prec!$V:$V,$C57,[5]BV_Data_An_Prec!$W:$W,Q$2) -> 10879.06 | S57: =L57-Q57 -> -5384.19
A58: =+B58&C58 -> Véhicules neufsInformatique | B58: =+$K$1 -> Véhicules neufs | C58: Informatique | F58: =+INDEX('[5]Budget original'!$A$2:$AO$496,MATCH($A58,'[5]Budget original'!$A$2:$A$496,0),MATCH(F$2,'[5]Budget original'!$A$2:$AO$2,0)) -> 6677.3963 | I58: =+INDEX('[5]Budget révisé'!$A$2:$AO$496,MATCH($A58,'[5]Budget révisé'!$A$2:$A$496,0),MATCH(I$2,'[5]Budget révisé'!$A$2:$AO$2,0)) -> 6677.3963 | L58: =SUMIFS([5]BV_Data_An_Cour!$O:$O,[5]BV_Data_An_Cour!$U:$U,$B58,[5]BV_Data_An_Cour!$V:$V,$C58,[5]BV_Data_An_Cour!$W:$W,L$2) -> 4538.32 | N58: =L58-I58 -> -2139.0763 | Q58: =SUMIFS([5]BV_Data_An_Prec!$O:$O,[5]BV_Data_An_Prec!$U:$U,$B58,[5]BV_Data_An_Prec!$V:$V,$C58,[5]BV_Data_An_Prec!$W:$W,Q$2) -> 7418.14 | S58: =L58-Q58 -> -2879.82
A59: =+B59&C59 -> Véhicules neufsFrais de déplacement | B59: =+$K$1 -> Véhicules neufs | C59: Frais de déplacement | F59: =+INDEX('[5]Budget original'!$A$2:$AO$496,MATCH($A59,'[5]Budget original'!$A$2:$A$496,0),MATCH(F$2,'[5]Budget original'!$A$2:$AO$2,0)) -> 1596.4968 | I59: =+INDEX('[5]Budget révisé'!$A$2:$AO$496,MATCH($A59,'[5]Budget révisé'!$A$2:$A$496,0),MATCH(I$2,'[5]Budget révisé'!$A$2:$AO$2,0)) -> 1596.4968 | L59: =SUMIFS([5]BV_Data_An_Cour!$O:$O,[5]BV_Data_An_Cour!$U:$U,$B59,[5]BV_Data_An_Cour!$V:$V,$C59,[5]BV_Data_An_Cour!$W:$W,L$2) -> 209.82 | N59: =L59-I59 -> -1386.6768 | Q59: =SUMIFS([5]BV_Data_An_Prec!$O:$O,[5]BV_Data_An_Prec!$U:$U,$B59,[5]BV_Data_An_Prec!$V:$V,$C59,[5]BV_Data_An_Prec!$W:$W,Q$2) -> 1944.64 | S59: =L59-Q59 -> -1734.82
A60: =+B60&C60 -> Véhicules neufsServices extérieurs | B60: =+$K$1 -> Véhicules neufs | C60: Services extérieurs | F60: =+INDEX('[5]Budget original'!$A$2:$AO$496,MATCH($A60,'[5]Budget original'!$A$2:$A$496,0),MATCH(F$2,'[5]Budget original'!$A$2:$AO$2,0)) -> 9857.8947 | I60: =+INDEX('[5]Budget révisé'!$A$2:$AO$496,MATCH($A60,'[5]Budget révisé'!$A$2:$A$496,0),MATCH(I$2,'[5]Budget révisé'!$A$2:$AO$2,0)) -> 9857.8947 | L60: =SUMIFS([5]BV_Data_An_Cour!$O:$O,[5]BV_Data_An_Cour!$U:$U,$B60,[5]BV_Data_An_Cour!$V:$V,$C60,[5]BV_Data_An_Cour!$W:$W,L$2) -> 8488.96 | N60: =L60-I60 -> -1368.9347 | Q60: =SUMIFS([5]BV_Data_An_Prec!$O:$O,[5]BV_Data_An_Prec!$U:$U,$B60,[5]BV_Data_An_Prec!$V:$V,$C60,[5]BV_Data_An_Prec!$W:$W,Q$2) -> 5955.16 | S60: =L60-Q60 -> 2533.8
A61: =+B61&C61 -> Véhicules neufsFournitures autres | B61: =+$K$1 -> Véhicules neufs | C61: Fournitures autres | F61: =+INDEX('[5]Budget original'!$A$2:$AO$496,MATCH($A61,'[5]Budget original'!$A$2:$A$496,0),MATCH(F$2,'[5]Budget original'!$A$2:$AO$2,0)) -> 283.23627 | I61: =+INDEX('[5]Budget révisé'!$A$2:$AO$496,MATCH($A61,'[5]Budget révisé'!$A$2:$A$496,0),MATCH(I$2,'[5]Budget révisé'!$A$2:$AO$2,0)) -> 283.23627 | L61: =SUMIFS([5]BV_Data_An_Cour!$O:$O,[5]BV_Data_An_Cour!$U:$U,$B61,[5]BV_Data_An_Cour!$V:$V,$C61,[5]BV_Data_An_Cour!$W:$W,L$2) -> 477.01 | N61: =L61-I61 -> 193.77373 | Q61: =SUMIFS([5]BV_Data_An_Prec!$O:$O,[5]BV_Data_An_Prec!$U:$U,$B61,[5]BV_Data_An_Prec!$V:$V,$C61,[5]BV_Data_An_Prec!$W:$W,Q$2) -> 261 | S61: =L61-Q61 -> 216.01
A62: =+B62&C62 -> Véhicules neufsUniformes | B62: =+$K$1 -> Véhicules neufs | C62: Uniformes | F62: =+INDEX('[5]Budget original'!$A$2:$AO$496,MATCH($A62,'[5]Budget original'!$A$2:$A$496,0),MATCH(F$2,'[5]Budget original'!$A$2:$AO$2,0)) -> 35 | I62: =+INDEX('[5]Budget révisé'!$A$2:$AO$496,MATCH($A62,'[5]Budget révisé'!$A$2:$A$496,0),MATCH(I$2,'[5]Budget révisé'!$A$2:$AO$2,0)) -> 35 | L62: =SUMIFS([5]BV_Data_An_Cour!$O:$O,[5]BV_Data_An_Cour!$U:$U,$B62,[5]BV_Data_An_Cour!$V:$V,$C62,[5]BV_Data_An_Cour!$W:$W,L$2) -> 0 | N62: =L62-I62 -> -35 | Q62: =SUMIFS([5]BV_Data_An_Prec!$O:$O,[5]BV_Data_An_Prec!$U:$U,$B62,[5]BV_Data_An_Prec!$V:$V,$C62,[5]BV_Data_An_Prec!$W:$W,Q$2) -> 35 | S62: =L62-Q62 -> -35
A63: =+B63&C63 -> Véhicules neufsPapeterie | B63: =+$K$1 -> Véhicules neufs | C63: Papeterie | F63: =+INDEX('[5]Budget original'!$A$2:$AO$496,MATCH($A63,'[5]Budget original'!$A$2:$A$496,0),MATCH(F$2,'[5]Budget original'!$A$2:$AO$2,0)) -> 697.6 | I63: =+INDEX('[5]Budget révisé'!$A$2:$AO$496,MATCH($A63,'[5]Budget révisé'!$A$2:$A$496,0),MATCH(I$2,'[5]Budget révisé'!$A$2:$AO$2,0)) -> 697.6 | L63: =SUMIFS([5]BV_Data_An_Cour!$O:$O,[5]BV_Data_An_Cour!$U:$U,$B63,[5]BV_Data_An_Cour!$V:$V,$C63,[5]BV_Data_An_Cour!$W:$W,L$2) -> 548.68 | N63: =L63-I63 -> -148.92 | Q63: =SUMIFS([5]BV_Data_An_Prec!$O:$O,[5]BV_Data_An_Prec!$U:$U,$B63,[5]BV_Data_An_Prec!$V:$V,$C63,[5]BV_Data_An_Prec!$W:$W,Q$2) -> 592 | S63: =L63-Q63 -> -43.32
A64: =+B64&C64 -> Véhicules neufsTéléphone | B64: =+$K$1 -> Véhicules neufs | C64: Téléphone | F64: =+INDEX('[5]Budget original'!$A$2:$AO$496,MATCH($A64,'[5]Budget original'!$A$2:$A$496,0),MATCH(F$2,'[5]Budget original'!$A$2:$AO$2,0)) -> 589.912 | I64: =+INDEX('[5]Budget révisé'!$A$2:$AO$496,MATCH($A64,'[5]Budget révisé'!$A$2:$A$496,0),MATCH(I$2,'[5]Budget révisé'!$A$2:$AO$2,0)) -> 589.912 | L64: =SUMIFS([5]BV_Data_An_Cour!$O:$O,[5]BV_Data_An_Cour!$U:$U,$B64,[5]BV_Data_An_Cour!$V:$V,$C64,[5]BV_Data_An_Cour!$W:$W,L$2) -> 130.22 | N64: =L64-I64 -> -459.692 | Q64: =SUMIFS([5]BV_Data_An_Prec!$O:$O,[5]BV_Data_An_Prec!$U:$U,$B64,[5]BV_Data_An_Prec!$V:$V,$C64,[5]BV_Data_An_Prec!$W:$W,Q$2) -> 523.9 | S64: =L64-Q64 -> -393.68
A65: =+B65&C65 -> Véhicules neufsFrais postaux | B65: =+$K$1 -> Véhicules neufs | C65: Frais postaux | F65: =+INDEX('[5]Budget original'!$A$2:$AO$496,MATCH($A65,'[5]Budget original'!$A$2:$A$496,0),MATCH(F$2,'[5]Budget original'!$A$2:$AO$2,0)) -> 276.8 | I65: =+INDEX('[5]Budget révisé'!$A$2:$AO$496,MATCH($A65,'[5]Budget révisé'!$A$2:$A$496,0),MATCH(I$2,'[5]Budget révisé'!$A$2:$AO$2,0)) -> 276.8 | L65: =SUMIFS([5]BV_Data_An_Cour!$O:$O,[5]BV_Data_An_Cour!$U:$U,$B65,[5]BV_Data_An_Cour!$V:$V,$C65,[5]BV_Data_An_Cour!$W:$W,L$2) -> 134.19 | N65: =L65-I65 -> -142.61 | Q65: =SUMIFS([5]BV_Data_An_Prec!$O:$O,[5]BV_Data_An_Prec!$U:$U,$B65,[5]BV_Data_An_Prec!$V:$V,$C65,[5]BV_Data_An_Prec!$W:$W,Q$2) -> 178.87 | S65: =L65-Q65 -> -44.68
A66: =+B66&C66 -> Véhicules neufsDivers | B66: =+$K$1 -> Véhicules neufs | C66: Divers | F66: =+INDEX('[5]Budget original'!$A$2:$AO$496,MATCH($A66,'[5]Budget original'!$A$2:$A$496,0),MATCH(F$2,'[5]Budget original'!$A$2:$AO$2,0)) -> 1349.12 | I66: =+INDEX('[5]Budget révisé'!$A$2:$AO$496,MATCH($A66,'[5]Budget révisé'!$A$2:$A$496,0),MATCH(I$2,'[5]Budget révisé'!$A$2:$AO$2,0)) -> 1349.12 | L66: =SUMIFS([5]BV_Data_An_Cour!$O:$O,[5]BV_Data_An_Cour!$U:$U,$B66,[5]BV_Data_An_Cour!$V:$V,$C66,[5]BV_Data_An_Cour!$W:$W,L$2) -> 264.06 | N66: =L66-I66 -> -1085.06 | Q66: =SUMIFS([5]BV_Data_An_Prec!$O:$O,[5]BV_Data_An_Prec!$U:$U,$B66,[5]BV_Data_An_Prec!$V:$V,$C66,[5]BV_Data_An_Prec!$W:$W,Q$2) -> 1740.29 | S66: =L66-Q66 -> -1476.23
A67: =+B67&C67 -> Véhicules neufsFormation | B67: =+$K$1 -> Véhicules neufs | C67: Formation | F67: =+INDEX('[5]Budget original'!$A$2:$AO$496,MATCH($A67,'[5]Budget original'!$A$2:$A$496,0),MATCH(F$2,'[5]Budget original'!$A$2:$AO$2,0)) -> 1438.3467 | I67: =+INDEX('[5]Budget révisé'!$A$2:$AO$496,MATCH($A67,'[5]Budget révisé'!$A$2:$A$496,0),MATCH(I$2,'[5]Budget révisé'!$A$2:$AO$2,0)) -> 1438.3467 | L67: =SUMIFS([5]BV_Data_An_Cour!$O:$O,[5]BV_Data_An_Cour!$U:$U,$B67,[5]BV_Data_An_Cour!$V:$V,$C67,[5]BV_Data_An_Cour!$W:$W,L$2) -> 523.33 | N67: =L67-I67 -> -915.01667 | Q67: =SUMIFS([5]BV_Data_An_Prec!$O:$O,[5]BV_Data_An_Prec!$U:$U,$B67,[5]BV_Data_An_Prec!$V:$V,$C67,[5]BV_Data_An_Prec!$W:$W,Q$2) -> 4555.83 | S67: =L67-Q67 -> -4032.5
A68: =+B68&C68 -> Véhicules neufsFrais bancaires | B68: =+$K$1 -> Véhicules neufs | C68: Frais bancaires | F68: =+INDEX('[5]Budget original'!$A$2:$AO$496,MATCH($A68,'[5]Budget original'!$A$2:$A$496,0),MATCH(F$2,'[5]Budget original'!$A$2:$AO$2,0)) -> 4004.986 | I68: =+INDEX('[5]Budget révisé'!$A$2:$AO$496,MATCH($A68,'[5]Budget révisé'!$A$2:$A$496,0),MATCH(I$2,'[5]Budget révisé'!$A$2:$AO$2,0)) -> 4004.986 | L68: =AF447*W3 -> 4056.885 | N68: =L68-I68 -> 51.898958 | Q68: =AL447*W3 -> 5618.655 | S68: =L68-Q68 -> -1561.77
A69: =+B69&C69 -> Véhicules neufs[...] | B69: =+$K$1 -> Véhicules neufs | C69: [...] | F69: =+INDEX('[5]Budget original'!$A$2:$AO$496,MATCH($A69,'[5]Budget original'!$A$2:$A$496,0),MATCH(F$2,'[5]Budget original'!$A$2:$AO$2,0)) -> 0 | I69: =+INDEX('[5]Budget révisé'!$A$2:$AO$496,MATCH($A69,'[5]Budget révisé'!$A$2:$A$496,0),MATCH(I$2,'[5]Budget révisé'!$A$2:$AO$2,0)) -> 0 | N69: =L69-I69 -> 0 | Q69: =SUMIFS([5]BV_Data_An_Prec!$O:$O,[5]BV_Data_An_Prec!$U:$U,$B69,[5]BV_Data_An_Prec!$V:$V,$C69,[5]BV_Data_An_Prec!$W:$W,Q$2) -> 0 | S69: =L69-Q69 -> 0
A70: =+B70&C70 -> Véhicules neufs[...] | B70: =+$K$1 -> Véhicules neufs | C70: [...] | F70: =+INDEX('[5]Budget original'!$A$2:$AO$496,MATCH($A70,'[5]Budget original'!$A$2:$A$496,0),MATCH(F$2,'[5]Budget original'!$A$2:$AO$2,0)) -> 0 | I70: =+INDEX('[5]Budget révisé'!$A$2:$AO$496,MATCH($A70,'[5]Budget révisé'!$A$2:$A$496,0),MATCH(I$2,'[5]Budget révisé'!$A$2:$AO$2,0)) -> 0 | L70: =SUMIFS([5]BV_Data_An_Cour!$O:$O,[5]BV_Data_An_Cour!$U:$U,$B70,[5]BV_Data_An_Cour!$V:$V,$C70,[5]BV_Data_An_Cour!$W:$W,L$2) -> 0 | N70: =L70-I70 -> 0 | Q70: =SUMIFS([5]BV_Data_An_Prec!$O:$O,[5]BV_Data_An_Prec!$U:$U,$B70,[5]BV_Data_An_Prec!$V:$V,$C70,[5]BV_Data_An_Prec!$W:$W,Q$2) -> 0 | S70: =L70-Q70 -> 0
A71: =+B71&C71 -> Véhicules neufs[...] | B71: =+$K$1 -> Véhicules neufs | C71: [...] | F71: =+INDEX('[5]Budget original'!$A$2:$AO$496,MATCH($A71,'[5]Budget original'!$A$2:$A$496,0),MATCH(F$2,'[5]Budget original'!$A$2:$AO$2,0)) -> 0 | I71: =+INDEX('[5]Budget révisé'!$A$2:$AO$496,MATCH($A71,'[5]Budget révisé'!$A$2:$A$496,0),MATCH(I$2,'[5]Budget révisé'!$A$2:$AO$2,0)) -> 0 | L71: =SUMIFS([5]BV_Data_An_Cour!$O:$O,[5]BV_Data_An_Cour!$U:$U,$B71,[5]BV_Data_An_Cour!$V:$V,$C71,[5]BV_Data_An_Cour!$W:$W,L$2)*0.32 -> 0 | N71: =L71-I71 -> 0 | Q71: =SUMIFS([5]BV_Data_An_Prec!$O:$O,[5]BV_Data_An_Prec!$U:$U,$B71,[5]BV_Data_An_Prec!$V:$V,$C71,[5]BV_Data_An_Prec!$W:$W,Q$2)*0.32 -> 0 | S71: =L71-Q71 -> 0
A72: =+B72&C72 -> Véhicules neufsTOTAL SEMI-FIXES | B72: =+$K$1 -> Véhicules neufs | C72: TOTAL SEMI-FIXES | D72: % brut | E72: =F72/F$27 -> 0.2703916 | F72: =+SUM(F55:F71) -> 35895.666 | G72: % brut | H72: =I72/I$27 -> 0.2227441 | I72: =+SUM(I55:I71) -> 35895.666 | J72: % brut | K72: =L72/L$27 -> 0.13435694 | L72: =+SUM(L55:L71) -> 24866.345 | N72: =+SUM(N55:N71) -> -11029.321 | O72: % brut | P72: =Q72/Q$27 -> 0.30411544 | Q72: =+SUM(Q55:Q71) -> 39702.545 | S72: =+SUM(S55:S71) -> -14836.2
A73: =+B73&C73 -> Véhicules neufs | B73: =+$K$1 -> Véhicules neufs
A74: =+B74&C74 -> Véhicules neufsTOTAL DES DÉPENSES | B74: =+$K$1 -> Véhicules neufs | C74: TOTAL DES DÉPENSES | D74: % brut | E74: =F74/F$27 -> 1.4651601 | F74: =F41+F54+F72 -> 194506.4 | G74: % brut | H74: =I74/I$27 -> 1.2122698 | I74: =I41+I54+I72 -> 195359.76 | J74: % brut | K74: =L74/L$27 -> 1.0990819 | L74: =L41+L54+L72 -> 203414.5 | N74: =L74-I74 -> 8054.7335 | O74: % brut | P74: =Q74/Q$27 -> 1.5096759 | Q74: =Q41+Q54+Q72 -> 197089.54 | S74: =L74-Q74 -> 6324.95
A75: =+B75&C75 -> Véhicules neufsProgramme neuf 1 | B75: =+$K$1 -> Véhicules neufs | C75: Programme neuf 1 | F75: =+INDEX('[5]Budget original'!$A$2:$AO$496,MATCH($A75,'[5]Budget original'!$A$2:$A$496,0),MATCH(F$2,'[5]Budget original'!$A$2:$AO$2,0)) -> 45357.638 | I75: =+INDEX('[5]Budget révisé'!$A$2:$AO$496,MATCH($A75,'[5]Budget révisé'!$A$2:$A$496,0),MATCH(I$2,'[5]Budget révisé'!$A$2:$AO$2,0)) -> 7158.52 | L75: =-SUMIFS([5]BV_Data_An_Cour!$O:$O,[5]BV_Data_An_Cour!$U:$U,$B75,[5]BV_Data_An_Cour!$V:$V,$C75,[5]BV_Data_An_Cour!$W:$W,L$2)-L155 -> 0 | N75: =L75-I75 -> -7158.52 | Q75: =-SUMIFS([5]BV_Data_An_Prec!$O:$O,[5]BV_Data_An_Prec!$U:$U,$B75,[5]BV_Data_An_Prec!$V:$V,$C75,[5]BV_Data_An_Prec!$W:$W,Q$2)-Q155 -> 37398 | V75: new CSI selon volume arrivae
A76: =+B76&C76 -> Véhicules neufsProgramme neuf 2 | B76: =+$K$1 -> Véhicules neufs | C76: Programme neuf 2 | F76: =+INDEX('[5]Budget original'!$A$2:$AO$496,MATCH($A76,'[5]Budget original'!$A$2:$A$496,0),MATCH(F$2,'[5]Budget original'!$A$2:$AO$2,0)) -> 0 | I76: =+INDEX('[5]Budget révisé'!$A$2:$AO$496,MATCH($A76,'[5]Budget révisé'!$A$2:$A$496,0),MATCH(I$2,'[5]Budget révisé'!$A$2:$AO$2,0)) -> 0 | L76: =-SUMIFS([5]BV_Data_An_Cour!$O:$O,[5]BV_Data_An_Cour!$U:$U,$B76,[5]BV_Data_An_Cour!$V:$V,$C76,[5]BV_Data_An_Cour!$W:$W,L$2) -> 0 | N76: =L76-I76 -> 0 | Q76: =-SUMIFS([5]BV_Data_An_Prec!$O:$O,[5]BV_Data_An_Prec!$U:$U,$B76,[5]BV_Data_An_Prec!$V:$V,$C76,[5]BV_Data_An_Prec!$W:$W,Q$2) -> 0 | S76: =L76-Q76 -> 0
A77: =+B77&C77 -> Véhicules neufsProgramme neuf 3 | B77: =+$K$1 -> Véhicules neufs | C77: Programme neuf 3 | F77: =+INDEX('[5]Budget original'!$A$2:$AO$496,MATCH($A77,'[5]Budget original'!$A$2:$A$496,0),MATCH(F$2,'[5]Budget original'!$A$2:$AO$2,0)) -> 0 | I77: =+INDEX('[5]Budget révisé'!$A$2:$AO$496,MATCH($A77,'[5]Budget révisé'!$A$2:$A$496,0),MATCH(I$2,'[5]Budget révisé'!$A$2:$AO$2,0)) -> 0 | L77: =-SUMIFS([5]BV_Data_An_Cour!$O:$O,[5]BV_Data_An_Cour!$U:$U,$B77,[5]BV_Data_An_Cour!$V:$V,$C77,[5]BV_Data_An_Cour!$W:$W,L$2) -> 0 | N77: =L77-I77 -> 0 | Q77: =-SUMIFS([5]BV_Data_An_Prec!$O:$O,[5]BV_Data_An_Prec!$U:$U,$B77,[5]BV_Data_An_Prec!$V:$V,$C77,[5]BV_Data_An_Prec!$W:$W,Q$2) -> 0 | S77: =L77-Q77 -> 0
A78: =+B78&C78 -> Véhicules neufsHoldbacks | B78: =+$K$1 -> Véhicules neufs | C78: Holdbacks | F78: =+INDEX('[5]Budget original'!$A$2:$AO$496,MATCH($A78,'[5]Budget original'!$A$2:$A$496,0),MATCH(F$2,'[5]Budget original'!$A$2:$AO$2,0)) -> 72775.568 | I78: =+INDEX('[5]Budget révisé'!$A$2:$AO$496,MATCH($A78,'[5]Budget révisé'!$A$2:$A$496,0),MATCH(I$2,'[5]Budget révisé'!$A$2:$AO$2,0)) -> 73926.169 | L78: =-SUMIFS([5]BV_Data_An_Cour!$O:$O,[5]BV_Data_An_Cour!$U:$U,$B78,[5]BV_Data_An_Cour!$V:$V,$C78,[5]BV_Data_An_Cour!$W:$W,L$2) -> 64999 | N78: =L78-I78 -> -8927.1694 | Q78: =-SUMIFS([5]BV_Data_An_Prec!$O:$O,[5]BV_Data_An_Prec!$U:$U,$B78,[5]BV_Data_An_Prec!$V:$V,$C78,[5]BV_Data_An_Prec!$W:$W,Q$2) -> 94042.75 | S78: =L78-Q78 -> -29043.75
A79: =+B79&C79 -> Véhicules neufs[...] | B79: =+$K$1 -> Véhicules neufs | C79: [...] | F79: =+INDEX('[5]Budget original'!$A$2:$AO$496,MATCH($A79,'[5]Budget original'!$A$2:$A$496,0),MATCH(F$2,'[5]Budget original'!$A$2:$AO$2,0)) -> 0 | I79: =+INDEX('[5]Budget révisé'!$A$2:$AO$496,MATCH($A79,'[5]Budget révisé'!$A$2:$A$496,0),MATCH(I$2,'[5]Budget révisé'!$A$2:$AO$2,0)) -> 0 | L79: =-SUMIFS([5]BV_Data_An_Cour!$O:$O,[5]BV_Data_An_Cour!$U:$U,$B79,[5]BV_Data_An_Cour!$V:$V,$C79,[5]BV_Data_An_Cour!$W:$W,L$2) -> 0 | N79: =L79-I79 -> 0 | Q79: =-SUMIFS([5]BV_Data_An_Prec!$O:$O,[5]BV_Data_An_Prec!$U:$U,$B79,[5]BV_Data_An_Prec!$V:$V,$C79,[5]BV_Data_An_Prec!$W:$W,Q$2) -> 0 | S79: =L79-Q79 -> 0
A80: =+B80&C80 -> Véhicules neufs[...] | B80: =+$K$1 -> Véhicules neufs | C80: [...] | F80: =+INDEX('[5]Budget original'!$A$2:$AO$496,MATCH($A80,'[5]Budget original'!$A$2:$A$496,0),MATCH(F$2,'[5]Budget original'!$A$2:$AO$2,0)) -> 0 | I80: =+INDEX('[5]Budget révisé'!$A$2:$AO$496,MATCH($A80,'[5]Budget révisé'!$A$2:$A$496,0),MATCH(I$2,'[5]Budget révisé'!$A$2:$AO$2,0)) -> 0 | L80: =-SUMIFS([5]BV_Data_An_Cour!$O:$O,[5]BV_Data_An_Cour!$U:$U,$B80,[5]BV_Data_An_Cour!$V:$V,$C80,[5]BV_Data_An_Cour!$W:$W,L$2) -> 0 | N80: =L80-I80 -> 0 | Q80: =-SUMIFS([5]BV_Data_An_Prec!$O:$O,[5]BV_Data_An_Prec!$U:$U,$B80,[5]BV_Data_An_Prec!$V:$V,$C80,[5]BV_Data_An_Prec!$W:$W,Q$2) -> 0 | S80: =L80-Q80 -> 0
A81: =+B81&C81 -> Véhicules neufs[...] | B81: =+$K$1 -> Véhicules neufs | C81: [...] | F81: =+INDEX('[5]Budget original'!$A$2:$AO$496,MATCH($A81,'[5]Budget original'!$A$2:$A$496,0),MATCH(F$2,'[5]Budget original'!$A$2:$AO$2,0)) -> 0 | I81: =+INDEX('[5]Budget révisé'!$A$2:$AO$496,MATCH($A81,'[5]Budget révisé'!$A$2:$A$496,0),MATCH(I$2,'[5]Budget révisé'!$A$2:$AO$2,0)) -> 0 | L81: =-SUMIFS([5]BV_Data_An_Cour!$O:$O,[5]BV_Data_An_Cour!$U:$U,$B81,[5]BV_Data_An_Cour!$V:$V,$C81,[5]BV_Data_An_Cour!$W:$W,L$2) -> 0 | N81: =L81-I81 -> 0 | Q81: =-SUMIFS([5]BV_Data_An_Prec!$O:$O,[5]BV_Data_An_Prec!$U:$U,$B81,[5]BV_Data_An_Prec!$V:$V,$C81,[5]BV_Data_An_Prec!$W:$W,Q$2) -> 0 | S81: =L81-Q81 -> 0
A82: =+B82&C82 -> Véhicules neufsFrais administration | B82: =+$K$1 -> Véhicules neufs | C82: Frais administration | F82: =+INDEX('[5]Budget original'!$A$2:$AO$496,MATCH($A82,'[5]Budget original'!$A$2:$A$496,0),MATCH(F$2,'[5]Budget original'!$A$2:$AO$2,0)) -> 22241.128 | I82: =+INDEX('[5]Budget révisé'!$A$2:$AO$496,MATCH($A82,'[5]Budget révisé'!$A$2:$A$496,0),MATCH(I$2,'[5]Budget révisé'!$A$2:$AO$2,0)) -> 22241.128 | L82: =-SUMIFS([5]BV_Data_An_Cour!$O:$O,[5]BV_Data_An_Cour!$U:$U,$B82,[5]BV_Data_An_Cour!$V:$V,$C82,[5]BV_Data_An_Cour!$W:$W,L$2)-L158 -> 18363 | N82: =L82-I82 -> -3878.1282 | Q82: =-SUMIFS([5]BV_Data_An_Prec!$O:$O,[5]BV_Data_An_Prec!$U:$U,$B82,[5]BV_Data_An_Prec!$V:$V,$C82,[5]BV_Data_An_Prec!$W:$W,Q$2)-Q158 -> 17446 | S82: =L82-Q82 -> 917
A83: =+B83&C83 -> Véhicules neufsAUTRES REVENUS | B83: =+$K$1 -> Véhicules neufs | C83: AUTRES REVENUS | F83: =+SUM(F75:F82) -> 140374.33 | I83: =+SUM(I75:I82) -> 103325.82 | L83: =+SUM(L75:L82) -> 83362 | N83: =+SUM(N75:N82) -> -19963.818 | Q83: =+SUM(Q75:Q82) -> 148886.75 | S83: =+SUM(S75:S82) -> -28126.75
A84: =+B84&C84 -> Véhicules neufs | B84: =+$K$1 -> Véhicules neufs
A85: =+B85&C85 -> Véhicules neufsPROFIT DÉPARTEMENTAL | B85: =+$K$1 -> Véhicules neufs | C85: PROFIT DÉPARTEMENTAL | F85: =F27-F74+F83 -> 78622.301 | I85: =I27-I74+I83 -> 69118.1 | L85: =L27-L74+L83 -> 65024.245 | N85: =N27-N41-N54-N72+N83 -> -4093.8546 | Q85: =Q27-Q74+Q83 -> 82348.105 | S85: =S27-S41-S54-S72+S83 -> 20074.14
C89: =C1 -> Volks | K89: Véhicules usagés | S89: =$S$1 -> Réalisé, Avril 2021
D91: BUDGET ORIGINAL | G91: BUDGET RÉVISÉ | J91: RÉALISATION | M91: ÉCART réel / révisé | O91: ANNÉE PRÉCÉDENTE | R91: ÉCART réel / original
D92: UNITE | E92: $P/UNITÉ | F92: $PROFITS | G92: UNITE | H92: $P/UNITÉ | I92: $PROFITS | J92: UNITE | K92: $P/UNITE | L92: $PROFITS | M92: UNITÉ | N92: $PROFITS | O92: UNITE | P92: $P/UNITE | Q92: $PROFITS | R92: UNITE | S92: $PROFITS
A93: =+B93&C93 -> Véhicules usagésVentes nettes | B93: Véhicules usagés | C93: Ventes nettes | F93: =+INDEX('[5]Budget original'!$A$2:$AO$496,MATCH($A93,'[5]Budget original'!$A$2:$A$496,0),MATCH(F$2,'[5]Budget original'!$A$2:$AO$2,0)) -> 994929.55 | I93: =+INDEX('[5]Budget révisé'!$A$2:$AO$496,MATCH($A93,'[5]Budget révisé'!$A$2:$A$496,0),MATCH(I$2,'[5]Budget révisé'!$A$2:$AO$2,0)) -> 994929.55 | L93: =-SUMIFS([5]BV_Data_An_Cour!$O:$O,[5]BV_Data_An_Cour!$X:$X,"Oui",[5]BV_Data_An_Cour!$U:$U,$B93) -> 1146628.7 | Q93: =-SUMIFS([5]BV_Data_An_Prec!$O:$O,[5]BV_Data_An_Prec!$X:$X,"Oui",[5]BV_Data_An_Prec!$U:$U,$B93) -> 820044.27
A94: =+B94&C94 -> Véhicules usagésCertifié | B94: Véhicules usagés | C94: Certifié | D94: =+INDEX('[5]Budget original'!$A$2:$AO$496,MATCH($A94,'[5]Budget original'!$A$2:$A$496,0),MATCH(D$2,'[5]Budget original'!$A$2:$AO$2,0)) -> 29.860315 | E94: =IF(D94=0,0,F94/D94) -> 750 | F94: =+INDEX('[5]Budget original'!$A$2:$AO$496,MATCH($A94,'[5]Budget original'!$A$2:$A$496,0),MATCH(F$2,'[5]Budget original'!$A$2:$AO$2,0)) -> 22395.236 | G94: =+INDEX('[5]Budget révisé'!$A$2:$AO$496,MATCH($A94,'[5]Budget révisé'!$A$2:$A$496,0),MATCH(G$2,'[5]Budget révisé'!$A$2:$AO$2,0)) -> 29.860315 | H94: =IF(G94=0,0,I94/G94) -> 750 | I94: =+INDEX('[5]Budget révisé'!$A$2:$AO$496,MATCH($A94,'[5]Budget révisé'!$A$2:$A$496,0),MATCH(I$2,'[5]Budget révisé'!$A$2:$AO$2,0)) -> 22395.236 | J94: =-SUMIFS([5]BV_Data_An_Cour!$O:$O,[5]BV_Data_An_Cour!$U:$U,$B94,[5]BV_Data_An_Cour!$V:$V,$C94,[5]BV_Data_An_Cour!$W:$W,J$2) -> 39 | K94: =IF(J94=0,0,L94/J94) -> 1018.0956 | L94: =-SUMIFS([5]BV_Data_An_Cour!$O:$O,[5]BV_Data_An_Cour!$U:$U,$B94,[5]BV_Data_An_Cour!$V:$V,$C94,[5]BV_Data_An_Cour!$W:$W,$L2) -> 39705.73 | M94: =J94-G94 -> 9.1396855 | N94: =L94-I94 -> 17310.494 | O94: =-SUMIFS([5]BV_Data_An_Prec!$O:$O,[5]BV_Data_An_Prec!$U:$U,$B94,[5]BV_Data_An_Prec!$V:$V,$C94,[5]BV_Data_An_Prec!$W:$W,O$2) -> 0 | P94: =IF(O94=0,0,Q94/O94) -> 0 | Q94: =-SUMIFS([5]BV_Data_An_Prec!$O:$O,[5]BV_Data_An_Prec!$U:$U,$B94,[5]BV_Data_An_Prec!$V:$V,$C94,[5]BV_Data_An_Prec!$W:$W,$L2) -> 0 | R94: =J94-O94 -> 39 | S94: =L94-Q94 -> 39705.73
A95: =+B95&C95 -> Véhicules usagésNon Certifié | B95: Véhicules usagés | C95: Non Certifié | D95: =+INDEX('[5]Budget original'!$A$2:$AO$496,MATCH($A95,'[5]Budget original'!$A$2:$A$496,0),MATCH(D$2,'[5]Budget original'!$A$2:$AO$2,0)) -> 1.7030598 | E95: =IF(D95=0,0,F95/D95) -> 750 | F95: =+INDEX('[5]Budget original'!$A$2:$AO$496,MATCH($A95,'[5]Budget original'!$A$2:$A$496,0),MATCH(F$2,'[5]Budget original'!$A$2:$AO$2,0)) -> 1277.2948 | G95: =+INDEX('[5]Budget révisé'!$A$2:$AO$496,MATCH($A95,'[5]Budget révisé'!$A$2:$A$496,0),MATCH(G$2,'[5]Budget révisé'!$A$2:$AO$2,0)) -> 1.7030598 | H95: =IF(G95=0,0,I95/G95) -> 750 | I95: =+INDEX('[5]Budget révisé'!$A$2:$AO$496,MATCH($A95,'[5]Budget révisé'!$A$2:$A$496,0),MATCH(I$2,'[5]Budget révisé'!$A$2:$AO$2,0)) -> 1277.2948 | J95: =-SUMIFS([5]BV_Data_An_Cour!$O:$O,[5]BV_Data_An_Cour!$U:$U,$B95,[5]BV_Data_An_Cour!$V:$V,$C95,[5]BV_Data_An_Cour!$W:$W,J$2) -> 2 | K95: =IF(J95=0,0,L95/J95) -> 755.545 | L95: =-SUMIFS([5]BV_Data_An_Cour!$O:$O,[5]BV_Data_An_Cour!$U:$U,$B95,[5]BV_Data_An_Cour!$V:$V,$C95,[5]BV_Data_An_Cour!$W:$W,$L2) -> 1511.09 | O95: =-SUMIFS([5]BV_Data_An_Prec!$O:$O,[5]BV_Data_An_Prec!$U:$U,$B95,[5]BV_Data_An_Prec!$V:$V,$C95,[5]BV_Data_An_Prec!$W:$W,O$2) -> 39 | P95: =IF(O95=0,0,Q95/O95) -> 579.61718 | Q95: =-SUMIFS([5]BV_Data_An_Prec!$O:$O,[5]BV_Data_An_Prec!$U:$U,$B95,[5]BV_Data_An_Prec!$V:$V,$C95,[5]BV_Data_An_Prec!$W:$W,$L2) -> 22605.07 | R95: =J95-O95 -> -37 | S95: =L95-Q95 -> -21093.98
A96: =+B96&C96 -> Véhicules usagésTotal Usagés | B96: Véhicules usagés | C96: Total Usagés | D96: =+D95+D94 -> 31.563374 | E96: =IF(D96=0,0,F96/D96) -> 750 | F96: =+F94+F95 -> 23672.531 | G96: =+G95+G94 -> 31.563374 | H96: =IF(G96=0,0,I96/G96) -> 750 | I96: =+I94+I95 -> 23672.531 | J96: =+J94+J95 -> 41 | K96: =IF(J96<=0,0,L96/J96) -> 1005.2883 | L96: =+L94+L95 -> 41216.82 | M96: =J96-G96 -> 9.4366257 | N96: =L96-I96 -> 17544.289 | O96: =+O94+O95 -> 39 | P96: =IF(O96<=0,0,Q96/O96) -> 579.61718 | Q96: =+Q94+Q95 -> 22605.07 | R96: =R94+R95 -> 2 | S96: =S94+S95 -> 18611.75
A97: =+B97&C97 -> Véhicules usagés | B97: Véhicules usagés | E97: =IF(D97=0,0,F97/D97) -> 0 | H97: =IF(G97=0,0,I97/G97) -> 0 | M97: =M96/G96 -> 0.29897392 | N97: =N96/I96 -> 0.74112436 | R97: =R96/O96 -> 0.051282051 | S97: =IF(Q96=0,0,(S96/Q96)) -> 0.82334406
A98: =+B98&C98 -> Véhicules usagésUS | B98: Véhicules usagés | C98: US
A99: =+B99&C99 -> Véhicules usagésVentes au Gros | B99: Véhicules usagés | C99: Ventes au Gros | D99: =+INDEX('[5]Budget original'!$A$2:$AO$496,MATCH($A99,'[5]Budget original'!$A$2:$A$496,0),MATCH(D$2,'[5]Budget original'!$A$2:$AO$2,0)) -> 26.745807 | E99: =IF(D99=0,0,F99/D99) -> 120 | F99: =+INDEX('[5]Budget original'!$A$2:$AO$496,MATCH($A99,'[5]Budget original'!$A$2:$A$496,0),MATCH(F$2,'[5]Budget original'!$A$2:$AO$2,0)) -> 3209.4968 | G99: =+INDEX('[5]Budget révisé'!$A$2:$AO$496,MATCH($A99,'[5]Budget révisé'!$A$2:$A$496,0),MATCH(G$2,'[5]Budget révisé'!$A$2:$AO$2,0)) -> 26.745807 | H99: =IF(G99=0,0,I99/G99) -> 120 | I99: =+INDEX('[5]Budget révisé'!$A$2:$AO$496,MATCH($A99,'[5]Budget révisé'!$A$2:$A$496,0),MATCH(I$2,'[5]Budget révisé'!$A$2:$AO$2,0)) -> 3209.4968 | J99: =-SUMIFS([5]BV_Data_An_Cour!$O:$O,[5]BV_Data_An_Cour!$U:$U,$B99,[5]BV_Data_An_Cour!$V:$V,$C99,[5]BV_Data_An_Cour!$W:$W,J$2) -> 25 | K99: =IF(J99=0,0,L99/J99) -> 340.5116 | L99: =-SUMIFS([5]BV_Data_An_Cour!$O:$O,[5]BV_Data_An_Cour!$U:$U,$B99,[5]BV_Data_An_Cour!$V:$V,$C99,[5]BV_Data_An_Cour!$W:$W,L$2) -> 8512.79 | M99: =J99-G99 -> -1.7458066 | N99: =L99-I99 -> 5303.2932 | O99: =-SUMIFS([5]BV_Data_An_Prec!$O:$O,[5]BV_Data_An_Prec!$U:$U,$B99,[5]BV_Data_An_Prec!$V:$V,$C99,[5]BV_Data_An_Prec!$W:$W,O$2) -> 22 | P99: =IF(O99=0,0,Q99/O99) -> 332.49273 | Q99: =-SUMIFS([5]BV_Data_An_Prec!$O:$O,[5]BV_Data_An_Prec!$U:$U,$B99,[5]BV_Data_An_Prec!$V:$V,$C99,[5]BV_Data_An_Prec!$W:$W,Q$2) -> 7314.84 | R99: =J99-O99 -> 3 | S99: =L99-Q99 -> 1197.95
A100: =+B100&C100 -> Véhicules usagés | B100: Véhicules usagés
A101: =+B101&C101 -> Véhicules usagésRev. Finances | B101: Véhicules usagés | C101: Rev. Finances | D101: =+INDEX('[5]Budget original'!$A$2:$AO$496,MATCH($A101,'[5]Budget original'!$A$2:$A$496,0),MATCH(D$2,'[5]Budget original'!$A$2:$AO$2,0)) -> 0 | E101: =IF(D101=0,0,F101/D101) -> 0 | F101: =+INDEX('[5]Budget original'!$A$2:$AO$496,MATCH($A101,'[5]Budget original'!$A$2:$A$496,0),MATCH(F$2,'[5]Budget original'!$A$2:$AO$2,0)) -> 25379.906 | G101: =+INDEX('[5]Budget révisé'!$A$2:$AO$496,MATCH($A101,'[5]Budget révisé'!$A$2:$A$496,0),MATCH(G$2,'[5]Budget révisé'!$A$2:$AO$2,0)) -> 0 | H101: =IF(G101=0,0,I101/G101) -> 0 | I101: =+INDEX('[5]Budget révisé'!$A$2:$AO$496,MATCH($A101,'[5]Budget révisé'!$A$2:$A$496,0),MATCH(I$2,'[5]Budget révisé'!$A$2:$AO$2,0)) -> 25379.906 | K101: =IF(J96=0,0,L101/J96) -> 522.44707 | L101: =-SUMIFS([5]BV_Data_An_Cour!$O:$O,[5]BV_Data_An_Cour!$U:$U,$B101,[5]BV_Data_An_Cour!$V:$V,$C101,[5]BV_Data_An_Cour!$W:$W,$L2) -> 21420.33 | N101: =L101-I101 -> -3959.5762 | P101: =IF(O96=0,0,Q101/O96) -> 414.40641 | Q101: =-SUMIFS([5]BV_Data_An_Prec!$O:$O,[5]BV_Data_An_Prec!$U:$U,$B101,[5]BV_Data_An_Prec!$V:$V,$C101,[5]BV_Data_An_Prec!$W:$W,$L2) -> 16161.85 | R101: =O101-K101 -> -522.44707 | S101: =L101-Q101 -> 5258.48
A102: =+B102&C102 -> Véhicules usagésRev. Protections | B102: Véhicules usagés | C102: Rev. Protections | D102: =+INDEX('[5]Budget original'!$A$2:$AO$496,MATCH($A102,'[5]Budget original'!$A$2:$A$496,0),MATCH(D$2,'[5]Budget original'!$A$2:$AO$2,0)) -> 0 | E102: =IF(D102=0,0,F102/D102) -> 0 | F102: =+INDEX('[5]Budget original'!$A$2:$AO$496,MATCH($A102,'[5]Budget original'!$A$2:$A$496,0),MATCH(F$2,'[5]Budget original'!$A$2:$AO$2,0)) -> 28763.894 | G102: =+INDEX('[5]Budget révisé'!$A$2:$AO$496,MATCH($A102,'[5]Budget révisé'!$A$2:$A$496,0),MATCH(G$2,'[5]Budget révisé'!$A$2:$AO$2,0)) -> 0 | H102: =IF(G102=0,0,I102/G102) -> 0 | I102: =+INDEX('[5]Budget révisé'!$A$2:$AO$496,MATCH($A102,'[5]Budget révisé'!$A$2:$A$496,0),MATCH(I$2,'[5]Budget révisé'!$A$2:$AO$2,0)) -> 28763.894 | K102: =IF(J96=0,0,L102/J96) -> 981.94195 | L102: =-SUMIFS([5]BV_Data_An_Cour!$O:$O,[5]BV_Data_An_Cour!$U:$U,$B102,[5]BV_Data_An_Cour!$V:$V,$C102,[5]BV_Data_An_Cour!$W:$W,$L2) -> 40259.62 | N102: =L102-I102 -> 11495.726 | P102: =IF(O96=0,0,Q102/O96) -> 612.08974 | Q102: =-SUMIFS([5]BV_Data_An_Prec!$O:$O,[5]BV_Data_An_Prec!$U:$U,$B102,[5]BV_Data_An_Prec!$V:$V,$C102,[5]BV_Data_An_Prec!$W:$W,$L2) -> 23871.5 | R102: =O102-K102 -> -981.94195 | S102: =L102-Q102 -> 16388.12
A103: =+B103&C103 -> Véhicules usagésRev. Autres | B103: Véhicules usagés | C103: Rev. Autres | D103: =+INDEX('[5]Budget original'!$A$2:$AO$496,MATCH($A103,'[5]Budget original'!$A$2:$A$496,0),MATCH(D$2,'[5]Budget original'!$A$2:$AO$2,0)) -> 0 | E103: =IF(D103=0,0,F103/D103) -> 0 | F103: =+INDEX('[5]Budget original'!$A$2:$AO$496,MATCH($A103,'[5]Budget original'!$A$2:$A$496,0),MATCH(F$2,'[5]Budget original'!$A$2:$AO$2,0)) -> 0 | G103: =+INDEX('[5]Budget révisé'!$A$2:$AO$496,MATCH($A103,'[5]Budget révisé'!$A$2:$A$496,0),MATCH(G$2,'[5]Budget révisé'!$A$2:$AO$2,0)) -> 0 | H103: =IF(G103=0,0,I103/G103) -> 0 | I103: =+INDEX('[5]Budget révisé'!$A$2:$AO$496,MATCH($A103,'[5]Budget révisé'!$A$2:$A$496,0),MATCH(I$2,'[5]Budget révisé'!$A$2:$AO$2,0)) -> 0 | K103: =IF(J96=0,0,L103/J96) -> 4.9360976 | L103: =-SUMIFS([5]BV_Data_An_Cour!$O:$O,[5]BV_Data_An_Cour!$U:$U,$B103,[5]BV_Data_An_Cour!$V:$V,$C103,[5]BV_Data_An_Cour!$W:$W,$L$2) -> 202.38 | N103: =L103-I103 -> 202.38 | P103: =IF(O96=0,0,Q103/O96) -> 87.661538 | Q103: =-SUMIFS([5]BV_Data_An_Prec!$O:$O,[5]BV_Data_An_Prec!$U:$U,$B103,[5]BV_Data_An_Prec!$V:$V,$C103,[5]BV_Data_An_Prec!$W:$W,$L$2) -> 3418.8 | R103: =O103-K103 -> -4.9360976 | S103: =L103-Q103 -> -3216.42
A104: =+B104&C104 -> Véhicules usagésTotal F&I | B104: Véhicules usagés | C104: Total F&I | D104: =D96 -> 31.563374 | E104: =IF(D104=0,0,F104/D104) -> 1715.3996 | F104: =F101+F102+F103 -> 54143.8 | G104: =G96 -> 31.563374 | H104: =IF(G104=0,0,I104/G104) -> 1715.3996 | I104: =I101+I102+I103 -> 54143.8 | J104: =J96 -> 41 | K104: =IF(J104<=0,0,L104/J104) -> 1509.3251 | L104: =L101+L102+L103 -> 61882.33 | M104: =J104-G104 -> 9.4366257 | N104: =L104-I104 -> 7738.5301 | O104: =O96 -> 39 | P104: =IF(O104<=0,0,Q104/O104) -> 1114.1577 | Q104: =Q101+Q102+Q103 -> 43452.15 | S104: =L104-Q104 -> 18430.18
...

Sheet VW 5
C1: =[6]Parametres!B1 -> Volks | K1: Véhicules neufs | S1: =CONCATENATE("Réalisé,"," ",[6]Parametres!B3," ",[6]Parametres!B4) -> Réalisé, Mai 2021
D2: X | E2: O | F2: U | G2: X | H2: O | I2: U | J2: NB | L2: $ | O2: NB | Q2: $
D3: BUDGET ORIGINAL | G3: BUDGET REVISE | J3: RÉALISATION | M3: ÉCART réel / révisé | O3: ANNÉE PRÉCÉDENTE | R3: ÉCART réel / original | V3: NEUF | W3: 0.45
D4: UNITE | E4: $P/UNITÉ | F4: $PROFITS | G4: UNITE | H4: $P/UNITÉ | I4: $PROFITS | J4: UNITE | K4: $P/UNITE | L4: $PROFITS | M4: UNITÉ | N4: $PROFITS | O4: UNITE | P4: $P/UNITE | Q4: $PROFITS | R4: UNITE | S4: $PROFITS | V4: USAGE | W4: 0.1
A5: =+B5&C5 -> Véhicules neufsVentes nettes | B5: =+$K$1 -> Véhicules neufs | C5: Ventes nettes | F5: =+INDEX('[6]Budget original'!$A$2:$AO$496,MATCH($A5,'[6]Budget original'!$A$2:$A$496,0),MATCH(F$2,'[6]Budget original'!$A$2:$AO$2,0)) -> 981796.55 | I5: =+INDEX('[6]Budget révisé'!$A$2:$AO$496,MATCH($A5,'[6]Budget révisé'!$A$2:$A$496,0),MATCH(I$2,'[6]Budget révisé'!$A$2:$AO$2,0)) -> 981796.55 | L5: =-SUMIFS([6]BV_Data_An_Cour!$O:$O,[6]BV_Data_An_Cour!$X:$X,"Oui",[6]BV_Data_An_Cour!$U:$U,$B5) -> 3760930 | Q5: =-SUMIFS([6]BV_Data_An_Prec!$O:$O,[6]BV_Data_An_Prec!$X:$X,"Oui",[6]BV_Data_An_Prec!$U:$U,$B5) -> 3162199.2 | V5: SERVICE | W5: 0.225
A6: =+B6&C6 -> Véhicules neufsAutos détail | B6: =+$K$1 -> Véhicules neufs | C6: Autos détail | D6: =+INDEX('[6]Budget original'!$A$2:$AO$496,MATCH($A6,'[6]Budget original'!$A$2:$A$496,0),MATCH(D$2,'[6]Budget original'!$A$2:$AO$2,0)) -> 35.76021 | E6: =IF(D6=0,0,F6/D6) -> 604.29043 | F6: =+INDEX('[6]Budget original'!$A$2:$AO$496,MATCH($A6,'[6]Budget original'!$A$2:$A$496,0),MATCH(F$2,'[6]Budget original'!$A$2:$AO$2,0)) -> 21609.552 | G6: =+INDEX('[6]Budget révisé'!$A$2:$AO$496,MATCH($A6,'[6]Budget révisé'!$A$2:$A$496,0),MATCH(G$2,'[6]Budget révisé'!$A$2:$AO$2,0)) -> 35.76021 | H6: =IF(G6=0,0,I6/G6) -> 955.05622 | I6: =+INDEX('[6]Budget révisé'!$A$2:$AO$496,MATCH($A6,'[6]Budget révisé'!$A$2:$A$496,0),MATCH(I$2,'[6]Budget révisé'!$A$2:$AO$2,0)) -> 34153.01 | J6: =-SUMIFS([6]BV_Data_An_Cour!$O:$O,[6]BV_Data_An_Cour!$U:$U,$B6,[6]BV_Data_An_Cour!$V:$V,$C6,[6]BV_Data_An_Cour!$W:$W,J$2) -> 25 | K6: =IF(J6=0,0,L6/J6) -> 1020.836 | L6: =-SUMIFS([6]BV_Data_An_Cour!$O:$O,[6]BV_Data_An_Cour!$U:$U,$B6,[6]BV_Data_An_Cour!$V:$V,$C6,[6]BV_Data_An_Cour!$W:$W,L$2) -> 25520.9 | M6: =J6-G6 -> -10.76021 | N6: =L6-I6 -> -8632.1105 | O6: =-SUMIFS([6]BV_Data_An_Prec!$O:$O,[6]BV_Data_An_Prec!$U:$U,$B6,[6]BV_Data_An_Prec!$V:$V,$C6,[6]BV_Data_An_Prec!$W:$W,O$2) -> 54 | P6: =IF(O6=0,0,Q6/O6) -> 571.8013 | Q6: =-SUMIFS([6]BV_Data_An_Prec!$O:$O,[6]BV_Data_An_Prec!$U:$U,$B6,[6]BV_Data_An_Prec!$V:$V,$C6,[6]BV_Data_An_Prec!$W:$W,Q$2) -> 30877.27 | R6: =J6-O6 -> -29 | S6: =L6-Q6 -> -5356.37 | V6: CARROSSERIE | W6: 0.025
A7: =+B7&C7 -> Véhicules neufsCamions détail | B7: =+$K$1 -> Véhicules neufs | C7: Camions détail | D7: =+INDEX('[6]Budget original'!$A$2:$AO$496,MATCH($A7,'[6]Budget original'!$A$2:$A$496,0),MATCH(D$2,'[6]Budget original'!$A$2:$AO$2,0)) -> 48.034341 | E7: =IF(D7=0,0,F7/D7) -> 1315.4791 | F7: =+INDEX('[6]Budget original'!$A$2:$AO$496,MATCH($A7,'[6]Budget original'!$A$2:$A$496,0),MATCH(F$2,'[6]Budget original'!$A$2:$AO$2,0)) -> 63188.172 | G7: =+INDEX('[6]Budget révisé'!$A$2:$AO$496,MATCH($A7,'[6]Budget révisé'!$A$2:$A$496,0),MATCH(G$2,'[6]Budget révisé'!$A$2:$AO$2,0)) -> 48.034341 | H7: =IF(G7=0,0,I7/G7) -> 1702.6669 | I7: =+INDEX('[6]Budget révisé'!$A$2:$AO$496,MATCH($A7,'[6]Budget révisé'!$A$2:$A$496,0),MATCH(I$2,'[6]Budget révisé'!$A$2:$AO$2,0)) -> 81786.481 | J7: =-SUMIFS([6]BV_Data_An_Cour!$O:$O,[6]BV_Data_An_Cour!$U:$U,$B7,[6]BV_Data_An_Cour!$V:$V,$C7,[6]BV_Data_An_Cour!$W:$W,J$2) -> 58 | K7: =IF(J7=0,0,L7/J7) -> 2126.4852 | L7: =-SUMIFS([6]BV_Data_An_Cour!$O:$O,[6]BV_Data_An_Cour!$U:$U,$B7,[6]BV_Data_An_Cour!$V:$V,$C7,[6]BV_Data_An_Cour!$W:$W,L$2) -> 123336.14 | M7: =J7-G7 -> 9.9656591 | N7: =L7-I7 -> 41549.659 | O7: =-SUMIFS([6]BV_Data_An_Prec!$O:$O,[6]BV_Data_An_Prec!$U:$U,$B7,[6]BV_Data_An_Prec!$V:$V,$C7,[6]BV_Data_An_Prec!$W:$W,O$2) -> 23 | P7: =IF(O7=0,0,Q7/O7) -> 995.91391 | Q7: =-SUMIFS([6]BV_Data_An_Prec!$O:$O,[6]BV_Data_An_Prec!$U:$U,$B7,[6]BV_Data_An_Prec!$V:$V,$C7,[6]BV_Data_An_Prec!$W:$W,Q$2) -> 22906.02 | R7: =J7-O7 -> 35 | S7: =L7-Q7 -> 100430.12 | V7: PIECES | W7: 0.2
A8: =+B8&C8 -> Véhicules neufsSprinter | B8: =+$K$1 -> Véhicules neufs | C8: Sprinter | D8: =+INDEX('[6]Budget original'!$A$2:$AO$496,MATCH($A8,'[6]Budget original'!$A$2:$A$496,0),MATCH(D$2,'[6]Budget original'!$A$2:$AO$2,0)) -> 0 | E8: =IF(D8=0,0,F8/D8) -> 0 | F8: =+INDEX('[6]Budget original'!$A$2:$AO$496,MATCH($A8,'[6]Budget original'!$A$2:$A$496,0),MATCH(F$2,'[6]Budget original'!$A$2:$AO$2,0)) -> 0 | G8: =+INDEX('[6]Budget révisé'!$A$2:$AO$496,MATCH($A8,'[6]Budget révisé'!$A$2:$A$496,0),MATCH(G$2,'[6]Budget révisé'!$A$2:$AO$2,0)) -> 0 | H8: =IF(G8=0,0,I8/G8) -> 0 | I8: =+INDEX('[6]Budget révisé'!$A$2:$AO$496,MATCH($A8,'[6]Budget révisé'!$A$2:$A$496,0),MATCH(I$2,'[6]Budget révisé'!$A$2:$AO$2,0)) -> 0 | J8: =-SUMIFS([6]BV_Data_An_Cour!$O:$O,[6]BV_Data_An_Cour!$U:$U,$B8,[6]BV_Data_An_Cour!$V:$V,$C8,[6]BV_Data_An_Cour!$W:$W,J$2) -> 0 | K8: =IF(J8=0,0,L8/J8) -> 0 | L8: =-SUMIFS([6]BV_Data_An_Cour!$O:$O,[6]BV_Data_An_Cour!$U:$U,$B8,[6]BV_Data_An_Cour!$V:$V,$C8,[6]BV_Data_An_Cour!$W:$W,L$2) -> 0 | M8: =J8-G8 -> 0 | N8: =L8-I8 -> 0 | O8: =-SUMIFS([6]BV_Data_An_Prec!$O:$O,[6]BV_Data_An_Prec!$U:$U,$B8,[6]BV_Data_An_Prec!$V:$V,$C8,[6]BV_Data_An_Prec!$W:$W,O$2) -> 0 | P8: =IF(O8=0,0,Q8/O8) -> 0 | Q8: =-SUMIFS([6]BV_Data_An_Prec!$O:$O,[6]BV_Data_An_Prec!$U:$U,$B8,[6]BV_Data_An_Prec!$V:$V,$C8,[6]BV_Data_An_Prec!$W:$W,Q$2) -> 0 | R8: =J8-O8 -> 0 | S8: =L8-Q8 -> 0 | W8: =SUM(W3:W7) -> 1
A9: =+B9&C9 -> Véhicules neufsMoto détail | B9: =+$K$1 -> Véhicules neufs | C9: Moto détail | D9: =+INDEX('[6]Budget original'!$A$2:$AO$496,MATCH($A9,'[6]Budget original'!$A$2:$A$496,0),MATCH(D$2,'[6]Budget original'!$A$2:$AO$2,0)) -> 0 | E9: =IF(D9=0,0,F9/D9) -> 0 | F9: =+INDEX('[6]Budget original'!$A$2:$AO$496,MATCH($A9,'[6]Budget original'!$A$2:$A$496,0),MATCH(F$2,'[6]Budget original'!$A$2:$AO$2,0)) -> 0 | G9: =+INDEX('[6]Budget révisé'!$A$2:$AO$496,MATCH($A9,'[6]Budget révisé'!$A$2:$A$496,0),MATCH(G$2,'[6]Budget révisé'!$A$2:$AO$2,0)) -> 0 | H9: =IF(G9=0,0,I9/G9) -> 0 | I9: =+INDEX('[6]Budget révisé'!$A$2:$AO$496,MATCH($A9,'[6]Budget révisé'!$A$2:$A$496,0),MATCH(I$2,'[6]Budget révisé'!$A$2:$AO$2,0)) -> 0 | J9: =-SUMIFS([6]BV_Data_An_Cour!$O:$O,[6]BV_Data_An_Cour!$U:$U,$B9,[6]BV_Data_An_Cour!$V:$V,$C9,[6]BV_Data_An_Cour!$W:$W,J$2) -> 0 | K9: =IF(J9=0,0,L9/J9) -> 0 | L9: =-SUMIFS([6]BV_Data_An_Cour!$O:$O,[6]BV_Data_An_Cour!$U:$U,$B9,[6]BV_Data_An_Cour!$V:$V,$C9,[6]BV_Data_An_Cour!$W:$W,L$2) -> 0 | M9: =J9-G9 -> 0 | N9: =L9-I9 -> 0 | O9: =-SUMIFS([6]BV_Data_An_Prec!$O:$O,[6]BV_Data_An_Prec!$U:$U,$B9,[6]BV_Data_An_Prec!$V:$V,$C9,[6]BV_Data_An_Prec!$W:$W,O$2) -> 0 | P9: =IF(O9=0,0,Q9/O9) -> 0 | Q9: =-SUMIFS([6]BV_Data_An_Prec!$O:$O,[6]BV_Data_An_Prec!$U:$U,$B9,[6]BV_Data_An_Prec!$V:$V,$C9,[6]BV_Data_An_Prec!$W:$W,Q$2) -> 0 | R9: =J9-O9 -> 0 | S9: =L9-Q9 -> 0
A10: =+B10&C10 -> Véhicules neufs[...] | B10: =+$K$1 -> Véhicules neufs | C10: [...] | D10: =+INDEX('[6]Budget original'!$A$2:$AO$496,MATCH($A10,'[6]Budget original'!$A$2:$A$496,0),MATCH(D$2,'[6]Budget original'!$A$2:$AO$2,0)) -> 0 | E10: =IF(D10=0,0,F10/D10) -> 0 | F10: =+INDEX('[6]Budget original'!$A$2:$AO$496,MATCH($A10,'[6]Budget original'!$A$2:$A$496,0),MATCH(F$2,'[6]Budget original'!$A$2:$AO$2,0)) -> 0 | G10: =+INDEX('[6]Budget révisé'!$A$2:$AO$496,MATCH($A10,'[6]Budget révisé'!$A$2:$A$496,0),MATCH(G$2,'[6]Budget révisé'!$A$2:$AO$2,0)) -> 0 | H10: =IF(G10=0,0,I10/G10) -> 0 | I10: =+INDEX('[6]Budget révisé'!$A$2:$AO$496,MATCH($A10,'[6]Budget révisé'!$A$2:$A$496,0),MATCH(I$2,'[6]Budget révisé'!$A$2:$AO$2,0)) -> 0 | J10: =-SUMIFS([6]BV_Data_An_Cour!$O:$O,[6]BV_Data_An_Cour!$U:$U,$B10,[6]BV_Data_An_Cour!$V:$V,$C10,[6]BV_Data_An_Cour!$W:$W,J$2) -> 0 | K10: =IF(J10=0,0,L10/J10) -> 0 | L10: =-SUMIFS([6]BV_Data_An_Cour!$O:$O,[6]BV_Data_An_Cour!$U:$U,$B10,[6]BV_Data_An_Cour!$V:$V,$C10,[6]BV_Data_An_Cour!$W:$W,L$2) -> 0 | M10: =J10-G10 -> 0 | N10: =L10-I10 -> 0 | O10: =-SUMIFS([6]BV_Data_An_Prec!$O:$O,[6]BV_Data_An_Prec!$U:$U,$B10,[6]BV_Data_An_Prec!$V:$V,$C10,[6]BV_Data_An_Prec!$W:$W,O$2) -> 0 | P10: =IF(O10=0,0,Q10/O10) -> 0 | Q10: =-SUMIFS([6]BV_Data_An_Prec!$O:$O,[6]BV_Data_An_Prec!$U:$U,$B10,[6]BV_Data_An_Prec!$V:$V,$C10,[6]BV_Data_An_Prec!$W:$W,Q$2) -> 0 | R10: =J10-O10 -> 0 | S10: =L10-Q10 -> 0
A11: =+B11&C11 -> Véhicules neufs[...] | B11: =+$K$1 -> Véhicules neufs | C11: [...] | D11: =+INDEX('[6]Budget original'!$A$2:$AO$496,MATCH($A11,'[6]Budget original'!$A$2:$A$496,0),MATCH(D$2,'[6]Budget original'!$A$2:$AO$2,0)) -> 0 | E11: =IF(D11=0,0,F11/D11) -> 0 | F11: =+INDEX('[6]Budget original'!$A$2:$AO$496,MATCH($A11,'[6]Budget original'!$A$2:$A$496,0),MATCH(F$2,'[6]Budget original'!$A$2:$AO$2,0)) -> 0 | G11: =+INDEX('[6]Budget révisé'!$A$2:$AO$496,MATCH($A11,'[6]Budget révisé'!$A$2:$A$496,0),MATCH(G$2,'[6]Budget révisé'!$A$2:$AO$2,0)) -> 0 | H11: =IF(G11=0,0,I11/G11) -> 0 | I11: =+INDEX('[6]Budget révisé'!$A$2:$AO$496,MATCH($A11,'[6]Budget révisé'!$A$2:$A$496,0),MATCH(I$2,'[6]Budget révisé'!$A$2:$AO$2,0)) -> 0 | J11: =-SUMIFS([6]BV_Data_An_Cour!$O:$O,[6]BV_Data_An_Cour!$U:$U,$B11,[6]BV_Data_An_Cour!$V:$V,$C11,[6]BV_Data_An_Cour!$W:$W,J$2) -> 0 | K11: =IF(J11=0,0,L11/J11) -> 0 | L11: =-SUMIFS([6]BV_Data_An_Cour!$O:$O,[6]BV_Data_An_Cour!$U:$U,$B11,[6]BV_Data_An_Cour!$V:$V,$C11,[6]BV_Data_An_Cour!$W:$W,L$2) -> 0 | M11: =J11-G11 -> 0 | N11: =L11-I11 -> 0 | O11: =-SUMIFS([6]BV_Data_An_Prec!$O:$O,[6]BV_Data_An_Prec!$U:$U,$B11,[6]BV_Data_An_Prec!$V:$V,$C11,[6]BV_Data_An_Prec!$W:$W,O$2) -> 0 | P11: =IF(O11=0,0,Q11/O11) -> 0 | Q11: =-SUMIFS([6]BV_Data_An_Prec!$O:$O,[6]BV_Data_An_Prec!$U:$U,$B11,[6]BV_Data_An_Prec!$V:$V,$C11,[6]BV_Data_An_Prec!$W:$W,Q$2) -> 0 | R11: =J11-O11 -> 0 | S11: =L11-Q11 -> 0
A12: =+B12&C12 -> Véhicules neufs[...] | B12: =+$K$1 -> Véhicules neufs | C12: [...] | D12: =+INDEX('[6]Budget original'!$A$2:$AO$496,MATCH($A12,'[6]Budget original'!$A$2:$A$496,0),MATCH(D$2,'[6]Budget original'!$A$2:$AO$2,0)) -> 0 | E12: =IF(D12=0,0,F12/D12) -> 0 | F12: =+INDEX('[6]Budget original'!$A$2:$AO$496,MATCH($A12,'[6]Budget original'!$A$2:$A$496,0),MATCH(F$2,'[6]Budget original'!$A$2:$AO$2,0)) -> 0 | G12: =+INDEX('[6]Budget révisé'!$A$2:$AO$496,MATCH($A12,'[6]Budget révisé'!$A$2:$A$496,0),MATCH(G$2,'[6]Budget révisé'!$A$2:$AO$2,0)) -> 0 | H12: =IF(G12=0,0,I12/G12) -> 0 | I12: =+INDEX('[6]Budget révisé'!$A$2:$AO$496,MATCH($A12,'[6]Budget révisé'!$A$2:$A$496,0),MATCH(I$2,'[6]Budget révisé'!$A$2:$AO$2,0)) -> 0 | J12: =-SUMIFS([6]BV_Data_An_Cour!$O:$O,[6]BV_Data_An_Cour!$U:$U,$B12,[6]BV_Data_An_Cour!$V:$V,$C12,[6]BV_Data_An_Cour!$W:$W,J$2) -> 0 | K12: =IF(J12=0,0,L12/J12) -> 0 | L12: =-SUMIFS([6]BV_Data_An_Cour!$O:$O,[6]BV_Data_An_Cour!$U:$U,$B12,[6]BV_Data_An_Cour!$V:$V,$C12,[6]BV_Data_An_Cour!$W:$W,L$2) -> 0 | M12: =J12-G12 -> 0 | N12: =L12-I12 -> 0 | O12: =-SUMIFS([6]BV_Data_An_Prec!$O:$O,[6]BV_Data_An_Prec!$U:$U,$B12,[6]BV_Data_An_Prec!$V:$V,$C12,[6]BV_Data_An_Prec!$W:$W,O$2) -> 0 | P12: =IF(O12=0,0,Q12/O12) -> 0 | Q12: =-SUMIFS([6]BV_Data_An_Prec!$O:$O,[6]BV_Data_An_Prec!$U:$U,$B12,[6]BV_Data_An_Prec!$V:$V,$C12,[6]BV_Data_An_Prec!$W:$W,Q$2) -> 0 | R12: =J12-O12 -> 0 | S12: =L12-Q12 -> 0
A13: =+B13&C13 -> Véhicules neufsTotal Neufs | B13: =+$K$1 -> Véhicules neufs | C13: Total Neufs | D13: =+SUM(D6:D12) -> 83.79455 | E13: =IF(D13<=0,0,F13/D13) -> 1011.9718 | F13: =+SUM(F6:F12) -> 84797.725 | G13: =+SUM(G6:G12) -> 83.79455 | H13: =IF(G13<=0,0,I13/G13) -> 1383.6161 | I13: =+SUM(I6:I12) -> 115939.49 | J13: =+SUM(J6:J12) -> 83 | K13: =IF(J13<=0,0,L13/J13) -> 1793.4583 | L13: =+SUM(L6:L12) -> 148857.04 | M13: =+SUM(M6:M12) -> -0.79455041 | N13: =+SUM(N6:N12) -> 32917.548 | O13: =+SUM(O6:O12) -> 77 | P13: =IF(O13<=0,0,Q13/O13) -> 698.48429 | Q13: =+SUM(Q6:Q12) -> 53783.29 | R13: =+SUM(R6:R12) -> 6 | S13: =+SUM(S6:S12) -> 95073.75
A14: =+B14&C14 -> Véhicules neufs | B14: =+$K$1 -> Véhicules neufs | M14: =IF(G13=0,0,M13/G13) -> -0.0094821251 | N14: =IF(I13=0,0,N13/I13) -> 0.28392007 | R14: =R13/O13 -> 0.077922078 | S14: =IF(Q13=0,0,(S13/Q13)) -> 1.7677191
A15: =+B15&C15 -> Véhicules neufsEx-Démos et courtoisies | B15: =+$K$1 -> Véhicules neufs | C15: Ex-Démos et courtoisies | D15: =+INDEX('[6]Budget original'!$A$2:$AO$496,MATCH($A15,'[6]Budget original'!$A$2:$A$496,0),MATCH(D$2,'[6]Budget original'!$A$2:$AO$2,0)) -> 8.7335165 | E15: =IF(D15=0,0,F15/D15) -> 400 | F15: =+INDEX('[6]Budget original'!$A$2:$AO$496,MATCH($A15,'[6]Budget original'!$A$2:$A$496,0),MATCH(F$2,'[6]Budget original'!$A$2:$AO$2,0)) -> 3493.4066 | G15: =+INDEX('[6]Budget révisé'!$A$2:$AO$496,MATCH($A15,'[6]Budget révisé'!$A$2:$A$496,0),MATCH(G$2,'[6]Budget révisé'!$A$2:$AO$2,0)) -> 8.7335165 | H15: =IF(G15=0,0,I15/G15) -> 790.03378 | I15: =+INDEX('[6]Budget révisé'!$A$2:$AO$496,MATCH($A15,'[6]Budget révisé'!$A$2:$A$496,0),MATCH(I$2,'[6]Budget révisé'!$A$2:$AO$2,0)) -> 6899.7731 | J15: =-SUMIFS([6]BV_Data_An_Cour!$O:$O,[6]BV_Data_An_Cour!$U:$U,$B15,[6]BV_Data_An_Cour!$V:$V,$C15,[6]BV_Data_An_Cour!$W:$W,J$2) -> 4 | K15: =IF(J15=0,0,L15/J15) -> 2427.275 | L15: =-SUMIFS([6]BV_Data_An_Cour!$O:$O,[6]BV_Data_An_Cour!$U:$U,$B15,[6]BV_Data_An_Cour!$V:$V,$C15,[6]BV_Data_An_Cour!$W:$W,L$2) -> 9709.1 | M15: =J15-G15 -> -4.7335165 | N15: =L15-I15 -> 2809.3269 | O15: =-SUMIFS([6]BV_Data_An_Prec!$O:$O,[6]BV_Data_An_Prec!$U:$U,$B15,[6]BV_Data_An_Prec!$V:$V,$C15,[6]BV_Data_An_Prec!$W:$W,O$2) -> 11 | P15: =IF(O15=0,0,Q15/O15) -> 30.737273 | Q15: =-SUMIFS([6]BV_Data_An_Prec!$O:$O,[6]BV_Data_An_Prec!$U:$U,$B15,[6]BV_Data_An_Prec!$V:$V,$C15,[6]BV_Data_An_Prec!$W:$W,Q$2) -> 338.11 | R15: =J15-O15 -> -7 | S15: =L15-Q15 -> 9370.99 | V15: =3125-L15 -> -6584.1
A16: =+B16&C16 -> Véhicules neufs | B16: =+$K$1 -> Véhicules neufs
A17: =+B17&C17 -> Véhicules neufsFlottes | B17: =+$K$1 -> Véhicules neufs | C17: Flottes | D17: =+INDEX('[6]Budget original'!$A$2:$AO$496,MATCH($A17,'[6]Budget original'!$A$2:$A$496,0),MATCH(D$2,'[6]Budget original'!$A$2:$AO$2,0)) -> 0 | E17: =IF(D17=0,0,F17/D17) -> 0 | F17: =+INDEX('[6]Budget original'!$A$2:$AO$496,MATCH($A17,'[6]Budget original'!$A$2:$A$496,0),MATCH(F$2,'[6]Budget original'!$A$2:$AO$2,0)) -> 0 | G17: =+INDEX('[6]Budget révisé'!$A$2:$AO$496,MATCH($A17,'[6]Budget révisé'!$A$2:$A$496,0),MATCH(G$2,'[6]Budget révisé'!$A$2:$AO$2,0)) -> 3.1998137 | H17: =IF(G17=0,0,I17/G17) -> 800 | I17: =+INDEX('[6]Budget révisé'!$A$2:$AO$496,MATCH($A17,'[6]Budget révisé'!$A$2:$A$496,0),MATCH(I$2,'[6]Budget révisé'!$A$2:$AO$2,0)) -> 2559.8509 | J17: =-SUMIFS([6]BV_Data_An_Cour!$O:$O,[6]BV_Data_An_Cour!$U:$U,$B17,[6]BV_Data_An_Cour!$V:$V,$C17,[6]BV_Data_An_Cour!$W:$W,J$2) -> 4 | K17: =IF(J17=0,0,L17/J17) -> 2789.6125 | L17: =-SUMIFS([6]BV_Data_An_Cour!$O:$O,[6]BV_Data_An_Cour!$U:$U,$B17,[6]BV_Data_An_Cour!$V:$V,$C17,[6]BV_Data_An_Cour!$W:$W,L$2) -> 11158.45 | M17: =J17-G17 -> 0.80018632 | N17: =L17-I17 -> 8598.5991 | O17: =-SUMIFS([6]BV_Data_An_Prec!$O:$O,[6]BV_Data_An_Prec!$U:$U,$B17,[6]BV_Data_An_Prec!$V:$V,$C17,[6]BV_Data_An_Prec!$W:$W,O$2) -> 3 | P17: =IF(O17=0,0,Q17/O17) -> 1624.1633 | Q17: =-SUMIFS([6]BV_Data_An_Prec!$O:$O,[6]BV_Data_An_Prec!$U:$U,$B17,[6]BV_Data_An_Prec!$V:$V,$C17,[6]BV_Data_An_Prec!$W:$W,Q$2) -> 4872.49 | R17: =J17-O17 -> 1 | S17: =L17-Q17 -> 6285.96
A18: =+B18&C18 -> Véhicules neufs | B18: =+$K$1 -> Véhicules neufs
A19: =+B19&C19 -> Véhicules neufsRachat bail | B19: =+$K$1 -> Véhicules neufs | C19: Rachat bail | D19: =+INDEX('[6]Budget original'!$A$2:$AO$496,MATCH($A19,'[6]Budget original'!$A$2:$A$496,0),MATCH(D$2,'[6]Budget original'!$A$2:$AO$2,0)) -> 0 | E19: =IF(D19=0,0,F19/D19) -> 0 | F19: =+INDEX('[6]Budget original'!$A$2:$AO$496,MATCH($A19,'[6]Budget original'!$A$2:$A$496,0),MATCH(F$2,'[6]Budget original'!$A$2:$AO$2,0)) -> 5000 | G19: =+INDEX('[6]Budget révisé'!$A$2:$AO$496,MATCH($A19,'[6]Budget révisé'!$A$2:$A$496,0),MATCH(G$2,'[6]Budget révisé'!$A$2:$AO$2,0)) -> 0 | H19: =IF(G19=0,0,I19/G19) -> 0 | I19: =+INDEX('[6]Budget révisé'!$A$2:$AO$496,MATCH($A19,'[6]Budget révisé'!$A$2:$A$496,0),MATCH(I$2,'[6]Budget révisé'!$A$2:$AO$2,0)) -> 5000 | L19: =-SUMIFS([6]BV_Data_An_Cour!$O:$O,[6]BV_Data_An_Cour!$U:$U,$B19,[6]BV_Data_An_Cour!$V:$V,$C19,[6]BV_Data_An_Cour!$W:$W,L$2) -> 6141.99 | N19: =L19-I19 -> 1141.99 | Q19: =-SUMIFS([6]BV_Data_An_Prec!$O:$O,[6]BV_Data_An_Prec!$U:$U,$B19,[6]BV_Data_An_Prec!$V:$V,$C19,[6]BV_Data_An_Prec!$W:$W,Q$2) -> 4014.85 | R19: =O19-K19 -> 0 | S19: =L19-Q19 -> 2127.14 | U19: Budget | V19: =G13+G15+G17 -> 95.727881 | W19: =I13+I15+I17 -> 125399.12 | X19: =W19/V19 -> 1309.954
A20: =+B20&C20 -> Véhicules neufs | B20: =+$K$1 -> Véhicules neufs | U20: 2021 | V20: =J13+J15+J17 -> 91 | W20: =L13+L15+L17 -> 169724.59 | X20: =W20/V20 -> 1865.1054
A21: =+B21&C21 -> Véhicules neufsRev. Finances | B21: =+$K$1 -> Véhicules neufs | C21: Rev. Finances | D21: =+INDEX('[6]Budget original'!$A$2:$AO$496,MATCH($A21,'[6]Budget original'!$A$2:$A$496,0),MATCH(D$2,'[6]Budget original'!$A$2:$AO$2,0)) -> 0 | E21: =IF(D21=0,0,F21/D21) -> 0 | F21: =+INDEX('[6]Budget original'!$A$2:$AO$496,MATCH($A21,'[6]Budget original'!$A$2:$A$496,0),MATCH(F$2,'[6]Budget original'!$A$2:$AO$2,0)) -> 8705.0215 | G21: =+INDEX('[6]Budget révisé'!$A$2:$AO$496,MATCH($A21,'[6]Budget révisé'!$A$2:$A$496,0),MATCH(G$2,'[6]Budget révisé'!$A$2:$AO$2,0)) -> 0 | H21: =IF(G21=0,0,I21/G21) -> 0 | I21: =+INDEX('[6]Budget révisé'!$A$2:$AO$496,MATCH($A21,'[6]Budget révisé'!$A$2:$A$496,0),MATCH(I$2,'[6]Budget révisé'!$A$2:$AO$2,0)) -> 8705.0215 | K21: =IF(J13=0,0,L21/(J13+J15)) -> 0 | L21: =-SUMIFS([6]BV_Data_An_Cour!$O:$O,[6]BV_Data_An_Cour!$U:$U,$B21,[6]BV_Data_An_Cour!$V:$V,$C21,[6]BV_Data_An_Cour!$W:$W,L$2) -> 0 | N21: =L21-I21 -> -8705.0215 | P21: =IF(O13=0,0,Q21/(O13+O15)) -> 66.863523 | Q21: =-SUMIFS([6]BV_Data_An_Prec!$O:$O,[6]BV_Data_An_Prec!$U:$U,$B21,[6]BV_Data_An_Prec!$V:$V,$C21,[6]BV_Data_An_Prec!$W:$W,Q$2) -> 5883.99 | R21: =O21-K21 -> 0 | S21: =L21-Q21 -> -5883.99
A22: =+B22&C22 -> Véhicules neufsRev. Protections | B22: =+$K$1 -> Véhicules neufs | C22: Rev. Protections | D22: =+INDEX('[6]Budget original'!$A$2:$AO$496,MATCH($A22,'[6]Budget original'!$A$2:$A$496,0),MATCH(D$2,'[6]Budget original'!$A$2:$AO$2,0)) -> 0 | E22: =IF(D22=0,0,F22/D22) -> 0 | F22: =+INDEX('[6]Budget original'!$A$2:$AO$496,MATCH($A22,'[6]Budget original'!$A$2:$A$496,0),MATCH(F$2,'[6]Budget original'!$A$2:$AO$2,0)) -> 68223.075 | G22: =+INDEX('[6]Budget révisé'!$A$2:$AO$496,MATCH($A22,'[6]Budget révisé'!$A$2:$A$496,0),MATCH(G$2,'[6]Budget révisé'!$A$2:$AO$2,0)) -> 0 | H22: =IF(G22=0,0,I22/G22) -> 0 | I22: =+INDEX('[6]Budget révisé'!$A$2:$AO$496,MATCH($A22,'[6]Budget révisé'!$A$2:$A$496,0),MATCH(I$2,'[6]Budget révisé'!$A$2:$AO$2,0)) -> 68223.075 | K22: =IF(J13=0,0,L22/(J13+J15)) -> 765.23471 | L22: =-SUMIFS([6]BV_Data_An_Cour!$O:$O,[6]BV_Data_An_Cour!$U:$U,$B22,[6]BV_Data_An_Cour!$V:$V,$C22,[6]BV_Data_An_Cour!$W:$W,L$2) -> 66575.42 | N22: =L22-I22 -> -1647.6553 | P22: =IF(O13=0,0,Q22/(O13+O15)) -> 390.76841 | Q22: =-SUMIFS([6]BV_Data_An_Prec!$O:$O,[6]BV_Data_An_Prec!$U:$U,$B22,[6]BV_Data_An_Prec!$V:$V,$C22,[6]BV_Data_An_Prec!$W:$W,Q$2) -> 34387.62 | R22: =O22-K22 -> -765.23471 | S22: =L22-Q22 -> 32187.8
A23: =+B23&C23 -> Véhicules neufsRev. Autres | B23: =+$K$1 -> Véhicules neufs | C23: Rev. Autres | D23: =+INDEX('[6]Budget original'!$A$2:$AO$496,MATCH($A23,'[6]Budget original'!$A$2:$A$496,0),MATCH(D$2,'[6]Budget original'!$A$2:$AO$2,0)) -> 0 | E23: =IF(D23=0,0,F23/D23) -> 0 | F23: =+INDEX('[6]Budget original'!$A$2:$AO$496,MATCH($A23,'[6]Budget original'!$A$2:$A$496,0),MATCH(F$2,'[6]Budget original'!$A$2:$AO$2,0)) -> 1720.7601 | G23: =+INDEX('[6]Budget révisé'!$A$2:$AO$496,MATCH($A23,'[6]Budget révisé'!$A$2:$A$496,0),MATCH(G$2,'[6]Budget révisé'!$A$2:$AO$2,0)) -> 0 | H23: =IF(G23=0,0,I23/G23) -> 0 | I23: =+INDEX('[6]Budget révisé'!$A$2:$AO$496,MATCH($A23,'[6]Budget révisé'!$A$2:$A$496,0),MATCH(I$2,'[6]Budget révisé'!$A$2:$AO$2,0)) -> 1720.7601 | K23: =IF(J13=0,0,L23/(J13+J15)) -> 18.082414 | L23: =-SUMIFS([6]BV_Data_An_Cour!$O:$O,[6]BV_Data_An_Cour!$U:$U,$B23,[6]BV_Data_An_Cour!$V:$V,$C23,[6]BV_Data_An_Cour!$W:$W,L$2) -> 1573.17 | N23: =L23-I23 -> -147.59006 | P23: =IF(O13=0,0,Q23/(O13+O15)) -> 6.2045455 | Q23: =-SUMIFS([6]BV_Data_An_Prec!$O:$O,[6]BV_Data_An_Prec!$U:$U,$B23,[6]BV_Data_An_Prec!$V:$V,$C23,[6]BV_Data_An_Prec!$W:$W,Q$2) -> 546 | R23: =O23-K23 -> -18.082414 | S23: =L23-Q23 -> 1027.17
A24: =+B24&C24 -> Véhicules neufsTotal F&I | B24: =+$K$1 -> Véhicules neufs | C24: Total F&I | D24: =+D15+D13 -> 92.528067 | E24: =IF(D24<=0,0,F24/D24) -> 850 | F24: =F21+F22+F23 -> 78648.857 | G24: =+G15+G13 -> 92.528067 | H24: =IF(G24<=0,0,I24/G24) -> 850 | I24: =I21+I22+I23 -> 78648.857 | J24: =+J15+J13 -> 87 | K24: =IF(J24<=0,0,L24/J24) -> 783.31713 | L24: =L21+L22+L23 -> 68148.59 | M24: =J24-G24 -> -5.5280669 | N24: =L24-I24 -> -10500.267 | O24: =+O15+O13 -> 88 | P24: =IF(O24<=0,0,Q24/O24) -> 463.83648 | Q24: =Q21+Q22+Q23 -> 40817.61 | S24: =L24-Q24 -> 27330.98
A25: =+B25&C25 -> Véhicules neufs | B25: =+$K$1 -> Véhicules neufs | N25: =IF(N24=0,0,N24/I24) -> -0.13350819 | S25: =IF(Q24=0,0,(S24/Q24)) -> 0.66958795
A26: =+B26&C26 -> Véhicules neufs | B26: =+$K$1 -> Véhicules neufs
A27: =+B27&C27 -> Véhicules neufsTotal Dépt. Neufs | B27: =+$K$1 -> Véhicules neufs | C27: Total Dépt. Neufs | D27: =+D13+D15+D17 -> 92.528067 | E27: =IF(D27<=0,0,F27/D27) -> 1858.2468 | F27: =F13+F17+F24+F19+F15 -> 171939.99 | G27: =+G13+G15+G17 -> 95.727881 | H27: =IF(G27<=0,0,I27/G27) -> 2183.7731 | I27: =I13+I17+I24+I19+I15 -> 209047.97 | J27: =+J13+J15+J17 -> 91 | K27: =IF(J27<=0,0,L27/J27) -> 2681.4854 | L27: =L13+L17+L24+L19+L15 -> 244015.17 | M27: =J27-G27 -> -4.7278806 | N27: =L27-I27 -> 34967.197 | O27: =+O13+O15+O17 -> 91 | P27: =IF(O27<=0,0,Q27/O27) -> 1140.9489 | Q27: =Q13+Q17+Q24+Q19+Q15 -> 103826.35 | R27: =J27-O27 -> 0 | S27: =L27-Q27 -> 140188.82
A28: =+B28&C28 -> Véhicules neufs | B28: =+$K$1 -> Véhicules neufs | M28: =M27/G27 -> -0.049388753 | N28: =N27/I27 -> 0.16726877 | R28: =R27/O27 -> 0 | S28: =IF(Q27=0,0,S27/Q27) -> 1.3502239
A29: =+B29&C29 -> Véhicules neufs | B29: =+$K$1 -> Véhicules neufs
A30: =+B30&C30 -> Véhicules neufsDEPENSES | B30: =+$K$1 -> Véhicules neufs | C30: DEPENSES
A31: =+B31&C31 -> Véhicules neufsComm. vendeurs | B31: =+$K$1 -> Véhicules neufs | C31: Comm. vendeurs | E31: =F31/D$24 -> 349.12556 | F31: =+INDEX('[6]Budget original'!$A$2:$AO$496,MATCH($A31,'[6]Budget original'!$A$2:$A$496,0),MATCH(F$2,'[6]Budget original'!$A$2:$AO$2,0)) -> 32303.913 | G31: =I31/(I15+I13) -> 0.26854424 | H31: =I31/G$24 -> 356.51645 | I31: =+INDEX('[6]Budget révisé'!$A$2:$AO$496,MATCH($A31,'[6]Budget révisé'!$A$2:$A$496,0),MATCH(I$2,'[6]Budget révisé'!$A$2:$AO$2,0)) -> 32987.778 | J31: =L31/(L15+L13) -> 0.33541858 | K31: =IF(L31=0,0,L31/J$24) -> 611.33368 | L31: =SUMIFS([6]BV_Data_An_Cour!$O:$O,[6]BV_Data_An_Cour!$U:$U,$B31,[6]BV_Data_An_Cour!$V:$V,$C31,[6]BV_Data_An_Cour!$W:$W,L$2) -> 53186.03 | N31: =L31-I31 -> 20198.252 | P31: =IF(Q31=0,0,Q31/O$24) -> 443.64216 | Q31: =SUMIFS([6]BV_Data_An_Prec!$O:$O,[6]BV_Data_An_Prec!$U:$U,$B31,[6]BV_Data_An_Prec!$V:$V,$C31,[6]BV_Data_An_Prec!$W:$W,Q$2) -> 39040.51 | S31: =L31-Q31 -> 14145.52
A32: =+B32&C32 -> Véhicules neufsComm. F&I | B32: =+$K$1 -> Véhicules neufs | C32: Comm. F&I | E32: =F32/D$24 -> 255 | F32: =+INDEX('[6]Budget original'!$A$2:$AO$496,MATCH($A32,'[6]Budget original'!$A$2:$A$496,0),MATCH(F$2,'[6]Budget original'!$A$2:$AO$2,0)) -> 23594.657 | G32: =I32/I24 -> 0.3 | H32: =I32/G$24 -> 255 | I32: =+INDEX('[6]Budget révisé'!$A$2:$AO$496,MATCH($A32,'[6]Budget révisé'!$A$2:$A$496,0),MATCH(I$2,'[6]Budget révisé'!$A$2:$AO$2,0)) -> 23594.657 | J32: =L32/L24 -> 0.3073977 | K32: =IF(L32=0,0,L32/J$24) -> 240.78989 | L32: =SUMIFS([6]BV_Data_An_Cour!$O:$O,[6]BV_Data_An_Cour!$U:$U,$B32,[6]BV_Data_An_Cour!$V:$V,$C32,[6]BV_Data_An_Cour!$W:$W,L$2) -> 20948.72 | N32: =L32-I32 -> -2645.9371 | P32: =IF(Q32=0,0,Q32/O$24) -> 244.99807 | Q32: =SUMIFS([6]BV_Data_An_Prec!$O:$O,[6]BV_Data_An_Prec!$U:$U,$B32,[6]BV_Data_An_Prec!$V:$V,$C32,[6]BV_Data_An_Prec!$W:$W,Q$2) -> 21559.83 | S32: =L32-Q32 -> -611.11
A33: =+B33&C33 -> Véhicules neufsFrais de livraison | B33: =+$K$1 -> Véhicules neufs | C33: Frais de livraison | E33: =F33/D$24 -> 197 | F33: =+INDEX('[6]Budget original'!$A$2:$AO$496,MATCH($A33,'[6]Budget original'!$A$2:$A$496,0),MATCH(F$2,'[6]Budget original'!$A$2:$AO$2,0)) -> 18228.029 | H33: =I33/G$24 -> 197 | I33: =+INDEX('[6]Budget révisé'!$A$2:$AO$496,MATCH($A33,'[6]Budget révisé'!$A$2:$A$496,0),MATCH(I$2,'[6]Budget révisé'!$A$2:$AO$2,0)) -> 18228.029 | K33: =IF(L33=0,0,L33/J$24) -> 74.75069 | L33: =SUMIFS([6]BV_Data_An_Cour!$O:$O,[6]BV_Data_An_Cour!$U:$U,$B33,[6]BV_Data_An_Cour!$V:$V,$C33,[6]BV_Data_An_Cour!$W:$W,L$2) -> 6503.31 | N33: =L33-I33 -> -11724.719 | P33: =IF(Q33=0,0,Q33/O$24) -> 131.33398 | Q33: =SUMIFS([6]BV_Data_An_Prec!$O:$O,[6]BV_Data_An_Prec!$U:$U,$B33,[6]BV_Data_An_Prec!$V:$V,$C33,[6]BV_Data_An_Prec!$W:$W,Q$2) -> 11557.39 | S33: =L33-Q33 -> -5054.08 | W33: =L24*0.3 -> 20444.577
A34: =+B34&C34 -> Véhicules neufsService gratuit 1 | B34: =+$K$1 -> Véhicules neufs | C34: Service gratuit 1 | E34: =F34/D$24 -> 6 | F34: =+INDEX('[6]Budget original'!$A$2:$AO$496,MATCH($A34,'[6]Budget original'!$A$2:$A$496,0),MATCH(F$2,'[6]Budget original'!$A$2:$AO$2,0)) -> 555.1684 | H34: =I34/G$24 -> 6 | I34: =+INDEX('[6]Budget révisé'!$A$2:$AO$496,MATCH($A34,'[6]Budget révisé'!$A$2:$A$496,0),MATCH(I$2,'[6]Budget révisé'!$A$2:$AO$2,0)) -> 555.1684 | K34: =IF(L34=0,0,L34/J$24) -> 6.8565517 | L34: =SUMIFS([6]BV_Data_An_Cour!$O:$O,[6]BV_Data_An_Cour!$U:$U,$B34,[6]BV_Data_An_Cour!$V:$V,$C34,[6]BV_Data_An_Cour!$W:$W,L$2) -> 596.52 | N34: =L34-I34 -> 41.351598 | P34: =IF(Q34=0,0,Q34/O$24) -> 3.8197727 | Q34: =SUMIFS([6]BV_Data_An_Prec!$O:$O,[6]BV_Data_An_Prec!$U:$U,$B34,[6]BV_Data_An_Prec!$V:$V,$C34,[6]BV_Data_An_Prec!$W:$W,Q$2) -> 336.14 | S34: =L34-Q34 -> 260.38
A35: =+B35&C35 -> Véhicules neufsEntretien stock | B35: =+$K$1 -> Véhicules neufs | C35: Entretien stock | E35: =F35/D$24 -> 34 | F35: =+INDEX('[6]Budget original'!$A$2:$AO$496,MATCH($A35,'[6]Budget original'!$A$2:$A$496,0),MATCH(F$2,'[6]Budget original'!$A$2:$AO$2,0)) -> 3145.9543 | H35: =I35/G$24 -> 34 | I35: =+INDEX('[6]Budget révisé'!$A$2:$AO$496,MATCH($A35,'[6]Budget révisé'!$A$2:$A$496,0),MATCH(I$2,'[6]Budget révisé'!$A$2:$AO$2,0)) -> 3145.9543 | K35: =IF(L35=0,0,L35/J$24) -> 13.448276 | L35: =SUMIFS([6]BV_Data_An_Cour!$O:$O,[6]BV_Data_An_Cour!$U:$U,$B35,[6]BV_Data_An_Cour!$V:$V,$C35,[6]BV_Data_An_Cour!$W:$W,L$2) -> 1170 | N35: =L35-I35 -> -1975.9543 | P35: =IF(Q35=0,0,Q35/O$24) -> 24.820114 | Q35: =SUMIFS([6]BV_Data_An_Prec!$O:$O,[6]BV_Data_An_Prec!$U:$U,$B35,[6]BV_Data_An_Prec!$V:$V,$C35,[6]BV_Data_An_Prec!$W:$W,Q$2) -> 2184.17 | S35: =L35-Q35 -> -1014.17 | W35: =L32-W33 -> 504.143
A36: =+B36&C36 -> Véhicules neufsPublicité 1 | B36: =+$K$1 -> Véhicules neufs | C36: Publicité 1 | E36: =F36/D$24 -> 180.66964 | F36: =+INDEX('[6]Budget original'!$A$2:$AO$496,MATCH($A36,'[6]Budget original'!$A$2:$A$496,0),MATCH(F$2,'[6]Budget original'!$A$2:$AO$2,0)) -> 16717.013 | H36: =I36/G$24 -> 180.66964 | I36: =+INDEX('[6]Budget révisé'!$A$2:$AO$496,MATCH($A36,'[6]Budget révisé'!$A$2:$A$496,0),MATCH(I$2,'[6]Budget révisé'!$A$2:$AO$2,0)) -> 16717.013 | K36: =IF(L36=0,0,L36/J$24) -> 119.94092 | L36: =SUMIFS([6]BV_Data_An_Cour!$O:$O,[6]BV_Data_An_Cour!$U:$U,$B36,[6]BV_Data_An_Cour!$V:$V,$C36,[6]BV_Data_An_Cour!$W:$W,L$2) -> 10434.86 | N36: =L36-I36 -> -6282.1528 | P36: =IF(Q36=0,0,Q36/O$24) -> 93.181818 | Q36: =SUMIFS([6]BV_Data_An_Prec!$O:$O,[6]BV_Data_An_Prec!$U:$U,$B36,[6]BV_Data_An_Prec!$V:$V,$C36,[6]BV_Data_An_Prec!$W:$W,Q$2) -> 8200 | S36: =L36-Q36 -> 2234.86
A37: =+B37&C37 -> Véhicules neufsIntérêt de gros | B37: =+$K$1 -> Véhicules neufs | C37: Intérêt de gros | E37: =F37/D$24 -> 164.99068 | F37: =+INDEX('[6]Budget original'!$A$2:$AO$496,MATCH($A37,'[6]Budget original'!$A$2:$A$496,0),MATCH(F$2,'[6]Budget original'!$A$2:$AO$2,0)) -> 15266.269 | H37: =I37/G$24 -> 166.54498 | I37: =+INDEX('[6]Budget révisé'!$A$2:$AO$496,MATCH($A37,'[6]Budget révisé'!$A$2:$A$496,0),MATCH(I$2,'[6]Budget révisé'!$A$2:$AO$2,0)) -> 15410.085 | K37: =IF(L37=0,0,L37/J$24) -> 161.06483 | L37: =SUMIFS([6]BV_Data_An_Cour!$O:$O,[6]BV_Data_An_Cour!$U:$U,$B37,[6]BV_Data_An_Cour!$V:$V,$C37,[6]BV_Data_An_Cour!$W:$W,L$2) -> 14012.64 | N37: =L37-I37 -> -1397.4451 | P37: =IF(Q37=0,0,Q37/O$24) -> 243.43534 | Q37: =SUMIFS([6]BV_Data_An_Prec!$O:$O,[6]BV_Data_An_Prec!$U:$U,$B37,[6]BV_Data_An_Prec!$V:$V,$C37,[6]BV_Data_An_Prec!$W:$W,Q$2) -> 21422.31 | S37: =L37-Q37 -> -7409.67
A38: =+B38&C38 -> Véhicules neufs[...] | B38: =+$K$1 -> Véhicules neufs | C38: [...] | E38: =F38/D$24 -> 0 | F38: =+INDEX('[6]Budget original'!$A$2:$AO$496,MATCH($A38,'[6]Budget original'!$A$2:$A$496,0),MATCH(F$2,'[6]Budget original'!$A$2:$AO$2,0)) -> 0 | H38: =I38/G$24 -> 0 | I38: =+INDEX('[6]Budget révisé'!$A$2:$AO$496,MATCH($A38,'[6]Budget révisé'!$A$2:$A$496,0),MATCH(I$2,'[6]Budget révisé'!$A$2:$AO$2,0)) -> 0 | K38: =IF(L38=0,0,L38/J$24) -> 0 | L38: =SUMIFS([6]BV_Data_An_Cour!$O:$O,[6]BV_Data_An_Cour!$U:$U,$B38,[6]BV_Data_An_Cour!$V:$V,$C38,[6]BV_Data_An_Cour!$W:$W,L$2) -> 0 | N38: =L38-I38 -> 0 | P38: =IF(Q38=0,0,Q38/O$24) -> 0 | Q38: =SUMIFS([6]BV_Data_An_Prec!$O:$O,[6]BV_Data_An_Prec!$U:$U,$B38,[6]BV_Data_An_Prec!$V:$V,$C38,[6]BV_Data_An_Prec!$W:$W,Q$2) -> 0 | S38: =L38-Q38 -> 0
A39: =+B39&C39 -> Véhicules neufs[...] | B39: =+$K$1 -> Véhicules neufs | C39: [...] | E39: =F39/D$24 -> 0 | F39: =+INDEX('[6]Budget original'!$A$2:$AO$496,MATCH($A39,'[6]Budget original'!$A$2:$A$496,0),MATCH(F$2,'[6]Budget original'!$A$2:$AO$2,0)) -> 0 | H39: =I39/G$24 -> 0 | I39: =+INDEX('[6]Budget révisé'!$A$2:$AO$496,MATCH($A39,'[6]Budget révisé'!$A$2:$A$496,0),MATCH(I$2,'[6]Budget révisé'!$A$2:$AO$2,0)) -> 0 | K39: =IF(L39=0,0,L39/J$24) -> 0 | L39: =SUMIFS([6]BV_Data_An_Cour!$O:$O,[6]BV_Data_An_Cour!$U:$U,$B39,[6]BV_Data_An_Cour!$V:$V,$C39,[6]BV_Data_An_Cour!$W:$W,L$2) -> 0 | N39: =L39-I39 -> 0 | P39: =IF(Q39=0,0,Q39/O$24) -> 0 | Q39: =SUMIFS([6]BV_Data_An_Prec!$O:$O,[6]BV_Data_An_Prec!$U:$U,$B39,[6]BV_Data_An_Prec!$V:$V,$C39,[6]BV_Data_An_Prec!$W:$W,Q$2) -> 0 | S39: =L39-Q39 -> 0
A40: =+B40&C40 -> Véhicules neufs[...] | B40: =+$K$1 -> Véhicules neufs | C40: [...] | E40: =F40/D$24 -> 0 | F40: =+INDEX('[6]Budget original'!$A$2:$AO$496,MATCH($A40,'[6]Budget original'!$A$2:$A$496,0),MATCH(F$2,'[6]Budget original'!$A$2:$AO$2,0)) -> 0 | H40: =I40/G$24 -> 0 | I40: =+INDEX('[6]Budget révisé'!$A$2:$AO$496,MATCH($A40,'[6]Budget révisé'!$A$2:$A$496,0),MATCH(I$2,'[6]Budget révisé'!$A$2:$AO$2,0)) -> 0 | K40: =IF(L40=0,0,L40/J$24) -> 0 | L40: =SUMIFS([6]BV_Data_An_Cour!$O:$O,[6]BV_Data_An_Cour!$U:$U,$B40,[6]BV_Data_An_Cour!$V:$V,$C40,[6]BV_Data_An_Cour!$W:$W,L$2) -> 0 | N40: =L40-I40 -> 0 | P40: =IF(Q40=0,0,Q40/O$24) -> 0 | Q40: =SUMIFS([6]BV_Data_An_Prec!$O:$O,[6]BV_Data_An_Prec!$U:$U,$B40,[6]BV_Data_An_Prec!$V:$V,$C40,[6]BV_Data_An_Prec!$W:$W,Q$2) -> 0 | S40: =L40-Q40 -> 0
A41: =+B41&C41 -> Véhicules neufsTOTAL VARIABLES | B41: =+$K$1 -> Véhicules neufs | C41: TOTAL VARIABLES | D41: % brut | E41: =F41/F$27 -> 0.6386589 | F41: =SUM(F31:F40) -> 109811 | G41: % brut | H41: =I41/I$27 -> 0.52925021 | I41: =SUM(I31:I40) -> 110638.68 | J41: % brut | K41: =L41/L$27 -> 0.43789114 | L41: =SUM(L31:L40) -> 106852.08 | N41: =L41-I41 -> -3786.6044 | O41: % brut | P41: =Q41/Q$27 -> 1.0045653 | Q41: =SUM(Q31:Q40) -> 104300.35 | S41: =L41-Q41 -> 2551.73
A42: =+B42&C42 -> Véhicules neufsSalaires cadres | B42: =+$K$1 -> Véhicules neufs | C42: Salaires cadres | F42: =+INDEX('[6]Budget original'!$A$2:$AO$496,MATCH($A42,'[6]Budget original'!$A$2:$A$496,0),MATCH(F$2,'[6]Budget original'!$A$2:$AO$2,0)) -> 25144.301 | I42: =+INDEX('[6]Budget révisé'!$A$2:$AO$496,MATCH($A42,'[6]Budget révisé'!$A$2:$A$496,0),MATCH(I$2,'[6]Budget révisé'!$A$2:$AO$2,0)) -> 25144.301 | L42: =SUMIFS([6]BV_Data_An_Cour!$O:$O,[6]BV_Data_An_Cour!$U:$U,$B42,[6]BV_Data_An_Cour!$V:$V,$C42,[6]BV_Data_An_Cour!$W:$W,L$2) -> 21334.91 | N42: =L42-I42 -> -3809.3906 | Q42: =SUMIFS([6]BV_Data_An_Prec!$O:$O,[6]BV_Data_An_Prec!$U:$U,$B42,[6]BV_Data_An_Prec!$V:$V,$C42,[6]BV_Data_An_Prec!$W:$W,Q$2) -> 20435.45 | S42: =L42-Q42 -> 899.46 | U42: Pierre Charles -67%
A43: =+B43&C43 -> Véhicules neufsSalaires commis | B43: =+$K$1 -> Véhicules neufs | C43: Salaires commis | F43: =+INDEX('[6]Budget original'!$A$2:$AO$496,MATCH($A43,'[6]Budget original'!$A$2:$A$496,0),MATCH(F$2,'[6]Budget original'!$A$2:$AO$2,0)) -> 10029.361 | I43: =+INDEX('[6]Budget révisé'!$A$2:$AO$496,MATCH($A43,'[6]Budget révisé'!$A$2:$A$496,0),MATCH(I$2,'[6]Budget révisé'!$A$2:$AO$2,0)) -> 10029.361 | L43: =SUMIFS([6]BV_Data_An_Cour!$O:$O,[6]BV_Data_An_Cour!$U:$U,$B43,[6]BV_Data_An_Cour!$V:$V,$C43,[6]BV_Data_An_Cour!$W:$W,L$2) -> 9816.59 | N43: =L43-I43 -> -212.77054 | Q43: =SUMIFS([6]BV_Data_An_Prec!$O:$O,[6]BV_Data_An_Prec!$U:$U,$B43,[6]BV_Data_An_Prec!$V:$V,$C43,[6]BV_Data_An_Prec!$W:$W,Q$2) -> 8999.03 | S43: =L43-Q43 -> 817.56 | V43: 3 commis en moin
A44: =+B44&C44 -> Véhicules neufsSalaires autres | B44: =+$K$1 -> Véhicules neufs | C44: Salaires autres | F44: =+INDEX('[6]Budget original'!$A$2:$AO$496,MATCH($A44,'[6]Budget original'!$A$2:$A$496,0),MATCH(F$2,'[6]Budget original'!$A$2:$AO$2,0)) -> 6319.9371 | I44: =+INDEX('[6]Budget révisé'!$A$2:$AO$496,MATCH($A44,'[6]Budget révisé'!$A$2:$A$496,0),MATCH(I$2,'[6]Budget révisé'!$A$2:$AO$2,0)) -> 6319.9371 | L44: =SUMIFS([6]BV_Data_An_Cour!$O:$O,[6]BV_Data_An_Cour!$U:$U,$B44,[6]BV_Data_An_Cour!$V:$V,$C44,[6]BV_Data_An_Cour!$W:$W,L$2) -> 8653.41 | N44: =L44-I44 -> 2333.4729 | Q44: =SUMIFS([6]BV_Data_An_Prec!$O:$O,[6]BV_Data_An_Prec!$U:$U,$B44,[6]BV_Data_An_Prec!$V:$V,$C44,[6]BV_Data_An_Prec!$W:$W,Q$2) -> 6801.44 | S44: =L44-Q44 -> 1851.97 | U44: 5e valet + Josee Massie + OT valet et homme de cout
A45: =+B45&C45 -> Véhicules neufsSalaires spécialistes | B45: =+$K$1 -> Véhicules neufs | C45: Salaires spécialistes | F45: =+INDEX('[6]Budget original'!$A$2:$AO$496,MATCH($A45,'[6]Budget original'!$A$2:$A$496,0),MATCH(F$2,'[6]Budget original'!$A$2:$AO$2,0)) -> 0 | I45: =+INDEX('[6]Budget révisé'!$A$2:$AO$496,MATCH($A45,'[6]Budget révisé'!$A$2:$A$496,0),MATCH(I$2,'[6]Budget révisé'!$A$2:$AO$2,0)) -> 0 | L45: =SUMIFS([6]BV_Data_An_Cour!$O:$O,[6]BV_Data_An_Cour!$U:$U,$B45,[6]BV_Data_An_Cour!$V:$V,$C45,[6]BV_Data_An_Cour!$W:$W,L$2) -> 0 | N45: =L45-I45 -> 0 | Q45: =SUMIFS([6]BV_Data_An_Prec!$O:$O,[6]BV_Data_An_Prec!$U:$U,$B45,[6]BV_Data_An_Prec!$V:$V,$C45,[6]BV_Data_An_Prec!$W:$W,Q$2) -> 0 | S45: =L45-Q45 -> 0
A46: =+B46&C46 -> Véhicules neufs[...] | B46: =+$K$1 -> Véhicules neufs | C46: [...] | F46: =+INDEX('[6]Budget original'!$A$2:$AO$496,MATCH($A46,'[6]Budget original'!$A$2:$A$496,0),MATCH(F$2,'[6]Budget original'!$A$2:$AO$2,0)) -> 0 | I46: =+INDEX('[6]Budget révisé'!$A$2:$AO$496,MATCH($A46,'[6]Budget révisé'!$A$2:$A$496,0),MATCH(I$2,'[6]Budget révisé'!$A$2:$AO$2,0)) -> 0 | L46: =SUMIFS([6]BV_Data_An_Cour!$O:$O,[6]BV_Data_An_Cour!$U:$U,$B46,[6]BV_Data_An_Cour!$V:$V,$C46,[6]BV_Data_An_Cour!$W:$W,L$2) -> 0 | N46: =L46-I46 -> 0 | Q46: =SUMIFS([6]BV_Data_An_Prec!$O:$O,[6]BV_Data_An_Prec!$U:$U,$B46,[6]BV_Data_An_Prec!$V:$V,$C46,[6]BV_Data_An_Prec!$W:$W,Q$2) -> 0 | S46: =L46-Q46 -> 0
A47: =+B47&C47 -> Véhicules neufs[...] | B47: =+$K$1 -> Véhicules neufs | C47: [...] | F47: =+INDEX('[6]Budget original'!$A$2:$AO$496,MATCH($A47,'[6]Budget original'!$A$2:$A$496,0),MATCH(F$2,'[6]Budget original'!$A$2:$AO$2,0)) -> 0 | I47: =+INDEX('[6]Budget révisé'!$A$2:$AO$496,MATCH($A47,'[6]Budget révisé'!$A$2:$A$496,0),MATCH(I$2,'[6]Budget révisé'!$A$2:$AO$2,0)) -> 0 | L47: =SUMIFS([6]BV_Data_An_Cour!$O:$O,[6]BV_Data_An_Cour!$U:$U,$B47,[6]BV_Data_An_Cour!$V:$V,$C47,[6]BV_Data_An_Cour!$W:$W,L$2) -> 0 | N47: =L47-I47 -> 0 | Q47: =SUMIFS([6]BV_Data_An_Prec!$O:$O,[6]BV_Data_An_Prec!$U:$U,$B47,[6]BV_Data_An_Prec!$V:$V,$C47,[6]BV_Data_An_Prec!$W:$W,Q$2) -> 0 | S47: =L47-Q47 -> 0
A48: =+B48&C48 -> Véhicules neufs[...] | B48: =+$K$1 -> Véhicules neufs | C48: [...] | F48: =+INDEX('[6]Budget original'!$A$2:$AO$496,MATCH($A48,'[6]Budget original'!$A$2:$A$496,0),MATCH(F$2,'[6]Budget original'!$A$2:$AO$2,0)) -> 0 | I48: =+INDEX('[6]Budget révisé'!$A$2:$AO$496,MATCH($A48,'[6]Budget révisé'!$A$2:$A$496,0),MATCH(I$2,'[6]Budget révisé'!$A$2:$AO$2,0)) -> 0 | L48: =SUMIFS([6]BV_Data_An_Cour!$O:$O,[6]BV_Data_An_Cour!$U:$U,$B48,[6]BV_Data_An_Cour!$V:$V,$C48,[6]BV_Data_An_Cour!$W:$W,L$2) -> 0 | N48: =L48-I48 -> 0 | Q48: =SUMIFS([6]BV_Data_An_Prec!$O:$O,[6]BV_Data_An_Prec!$U:$U,$B48,[6]BV_Data_An_Prec!$V:$V,$C48,[6]BV_Data_An_Prec!$W:$W,Q$2) -> 0 | S48: =L48-Q48 -> 0
A49: =+B49&C49 -> Véhicules neufsSalaires en absences | B49: =+$K$1 -> Véhicules neufs | C49: Salaires en absences | F49: =+INDEX('[6]Budget original'!$A$2:$AO$496,MATCH($A49,'[6]Budget original'!$A$2:$A$496,0),MATCH(F$2,'[6]Budget original'!$A$2:$AO$2,0)) -> 11687.06 | I49: =+INDEX('[6]Budget révisé'!$A$2:$AO$496,MATCH($A49,'[6]Budget révisé'!$A$2:$A$496,0),MATCH(I$2,'[6]Budget révisé'!$A$2:$AO$2,0)) -> 11769.124 | L49: =SUMIFS([6]BV_Data_An_Cour!$O:$O,[6]BV_Data_An_Cour!$U:$U,$B49,[6]BV_Data_An_Cour!$V:$V,$C49,[6]BV_Data_An_Cour!$W:$W,L$2) -> 15115.93 | N49: =L49-I49 -> 3346.8061 | Q49: =SUMIFS([6]BV_Data_An_Prec!$O:$O,[6]BV_Data_An_Prec!$U:$U,$B49,[6]BV_Data_An_Prec!$V:$V,$C49,[6]BV_Data_An_Prec!$W:$W,Q$2) -> 14250.71 | S49: =L49-Q49 -> 865.22
A50: =+B50&C50 -> Véhicules neufsDéduction à la source | B50: =+$K$1 -> Véhicules neufs | C50: Déduction à la source | F50: =+INDEX('[6]Budget original'!$A$2:$AO$496,MATCH($A50,'[6]Budget original'!$A$2:$A$496,0),MATCH(F$2,'[6]Budget original'!$A$2:$AO$2,0)) -> 11687.06 | I50: =+INDEX('[6]Budget révisé'!$A$2:$AO$496,MATCH($A50,'[6]Budget révisé'!$A$2:$A$496,0),MATCH(I$2,'[6]Budget révisé'!$A$2:$AO$2,0)) -> 11769.124 | L50: =SUMIFS([6]BV_Data_An_Cour!$O:$O,[6]BV_Data_An_Cour!$U:$U,$B50,[6]BV_Data_An_Cour!$V:$V,$C50,[6]BV_Data_An_Cour!$W:$W,L$2) -> 12289.25 | N50: =L50-I50 -> 520.12606 | Q50: =SUMIFS([6]BV_Data_An_Prec!$O:$O,[6]BV_Data_An_Prec!$U:$U,$B50,[6]BV_Data_An_Prec!$V:$V,$C50,[6]BV_Data_An_Prec!$W:$W,Q$2) -> 12500.8 | S50: =L50-Q50 -> -211.55 | U50: CORRECTION ENTRE DEPT
A51: =+B51&C51 -> Véhicules neufsBénéfices marginaux | B51: =+$K$1 -> Véhicules neufs | C51: Bénéfices marginaux | F51: =+INDEX('[6]Budget original'!$A$2:$AO$496,MATCH($A51,'[6]Budget original'!$A$2:$A$496,0),MATCH(F$2,'[6]Budget original'!$A$2:$AO$2,0)) -> 8375.7265 | I51: =+INDEX('[6]Budget révisé'!$A$2:$AO$496,MATCH($A51,'[6]Budget révisé'!$A$2:$A$496,0),MATCH(I$2,'[6]Budget révisé'!$A$2:$AO$2,0)) -> 8434.5388 | L51: =SUMIFS([6]BV_Data_An_Cour!$O:$O,[6]BV_Data_An_Cour!$U:$U,$B51,[6]BV_Data_An_Cour!$V:$V,$C51,[6]BV_Data_An_Cour!$W:$W,L$2) -> 8807.29 | N51: =L51-I51 -> 372.75118 | Q51: =SUMIFS([6]BV_Data_An_Prec!$O:$O,[6]BV_Data_An_Prec!$U:$U,$B51,[6]BV_Data_An_Prec!$V:$V,$C51,[6]BV_Data_An_Prec!$W:$W,Q$2) -> 8350.95 | S51: =L51-Q51 -> 456.34
A52: =+B52&C52 -> Véhicules neufsCsst | B52: =+$K$1 -> Véhicules neufs | C52: Csst | F52: =+INDEX('[6]Budget original'!$A$2:$AO$496,MATCH($A52,'[6]Budget original'!$A$2:$A$496,0),MATCH(F$2,'[6]Budget original'!$A$2:$AO$2,0)) -> 1947.8434 | I52: =+INDEX('[6]Budget révisé'!$A$2:$AO$496,MATCH($A52,'[6]Budget révisé'!$A$2:$A$496,0),MATCH(I$2,'[6]Budget révisé'!$A$2:$AO$2,0)) -> 1961.5207 | L52: =SUMIFS([6]BV_Data_An_Cour!$O:$O,[6]BV_Data_An_Cour!$U:$U,$B52,[6]BV_Data_An_Cour!$V:$V,$C52,[6]BV_Data_An_Cour!$W:$W,L$2) -> 2048.21 | N52: =L52-I52 -> 86.689343 | Q52: =SUMIFS([6]BV_Data_An_Prec!$O:$O,[6]BV_Data_An_Prec!$U:$U,$B52,[6]BV_Data_An_Prec!$V:$V,$C52,[6]BV_Data_An_Prec!$W:$W,Q$2) -> 2822.32 | S52: =L52-Q52 -> -774.11
A53: =+B53&C53 -> Véhicules neufs[...] | B53: =+$K$1 -> Véhicules neufs | C53: [...] | F53: =+INDEX('[6]Budget original'!$A$2:$AO$496,MATCH($A53,'[6]Budget original'!$A$2:$A$496,0),MATCH(F$2,'[6]Budget original'!$A$2:$AO$2,0)) -> 0 | I53: =+INDEX('[6]Budget révisé'!$A$2:$AO$496,MATCH($A53,'[6]Budget révisé'!$A$2:$A$496,0),MATCH(I$2,'[6]Budget révisé'!$A$2:$AO$2,0)) -> 0 | L53: =SUMIFS([6]BV_Data_An_Cour!$O:$O,[6]BV_Data_An_Cour!$U:$U,$B53,[6]BV_Data_An_Cour!$V:$V,$C53,[6]BV_Data_An_Cour!$W:$W,L$2) -> 0 | N53: =L53-I53 -> 0 | Q53: =SUMIFS([6]BV_Data_An_Prec!$O:$O,[6]BV_Data_An_Prec!$U:$U,$B53,[6]BV_Data_An_Prec!$V:$V,$C53,[6]BV_Data_An_Prec!$W:$W,Q$2) -> 0 | S53: =L53-Q53 -> 0
A54: =+B54&C54 -> Véhicules neufsTOTAL PERSONNEL | B54: =+$K$1 -> Véhicules neufs | C54: TOTAL PERSONNEL | D54: % brut | E54: =F54/F$27 -> 0.43731123 | F54: =+SUM(F42:F53) -> 75191.289 | G54: % brut | H54: =I54/I$27 -> 0.36081625 | I54: =+SUM(I42:I53) -> 75427.906 | J54: % brut | K54: =L54/L$27 -> 0.31992105 | L54: =+SUM(L42:L53) -> 78065.59 | N54: =+SUM(N42:N53) -> 2637.6844 | O54: % brut | P54: =Q54/Q$27 -> 0.71427629 | Q54: =+SUM(Q42:Q53) -> 74160.7 | S54: =+SUM(S42:S53) -> 3904.89
A55: =+B55&C55 -> Véhicules neufsPublicité 2 | B55: =+$K$1 -> Véhicules neufs | C55: Publicité 2 | F55: =+INDEX('[6]Budget original'!$A$2:$AO$496,MATCH($A55,'[6]Budget original'!$A$2:$A$496,0),MATCH(F$2,'[6]Budget original'!$A$2:$AO$2,0)) -> 0 | I55: =+INDEX('[6]Budget révisé'!$A$2:$AO$496,MATCH($A55,'[6]Budget révisé'!$A$2:$A$496,0),MATCH(I$2,'[6]Budget révisé'!$A$2:$AO$2,0)) -> 0 | L55: =SUMIFS([6]BV_Data_An_Cour!$O:$O,[6]BV_Data_An_Cour!$U:$U,$B55,[6]BV_Data_An_Cour!$V:$V,$C55,[6]BV_Data_An_Cour!$W:$W,L$2) -> 0 | N55: =L55-I55 -> 0 | Q55: =SUMIFS([6]BV_Data_An_Prec!$O:$O,[6]BV_Data_An_Prec!$U:$U,$B55,[6]BV_Data_An_Prec!$V:$V,$C55,[6]BV_Data_An_Prec!$W:$W,Q$2) -> 0 | S55: =L55-Q55 -> 0
A56: =+B56&C56 -> Véhicules neufsService gratuit 2 | B56: =+$K$1 -> Véhicules neufs | C56: Service gratuit 2 | F56: =+INDEX('[6]Budget original'!$A$2:$AO$496,MATCH($A56,'[6]Budget original'!$A$2:$A$496,0),MATCH(F$2,'[6]Budget original'!$A$2:$AO$2,0)) -> 0 | I56: =+INDEX('[6]Budget révisé'!$A$2:$AO$496,MATCH($A56,'[6]Budget révisé'!$A$2:$A$496,0),MATCH(I$2,'[6]Budget révisé'!$A$2:$AO$2,0)) -> 0 | L56: =SUMIFS([6]BV_Data_An_Cour!$O:$O,[6]BV_Data_An_Cour!$U:$U,$B56,[6]BV_Data_An_Cour!$V:$V,$C56,[6]BV_Data_An_Cour!$W:$W,L$2) -> 0 | N56: =L56-I56 -> 0 | Q56: =SUMIFS([6]BV_Data_An_Prec!$O:$O,[6]BV_Data_An_Prec!$U:$U,$B56,[6]BV_Data_An_Prec!$V:$V,$C56,[6]BV_Data_An_Prec!$W:$W,Q$2) -> 0 | S56: =L56-Q56 -> 0
A57: =+B57&C57 -> Véhicules neufsFrais véhicules de cie | B57: =+$K$1 -> Véhicules neufs | C57: Frais véhicules de cie | F57: =+INDEX('[6]Budget original'!$A$2:$AO$496,MATCH($A57,'[6]Budget original'!$A$2:$A$496,0),MATCH(F$2,'[6]Budget original'!$A$2:$AO$2,0)) -> 9088.8775 | I57: =+INDEX('[6]Budget révisé'!$A$2:$AO$496,MATCH($A57,'[6]Budget révisé'!$A$2:$A$496,0),MATCH(I$2,'[6]Budget révisé'!$A$2:$AO$2,0)) -> 9088.8775 | L57: =SUMIFS([6]BV_Data_An_Cour!$O:$O,[6]BV_Data_An_Cour!$U:$U,$B57,[6]BV_Data_An_Cour!$V:$V,$C57,[6]BV_Data_An_Cour!$W:$W,L$2) -> 6376 | N57: =L57-I57 -> -2712.8775 | Q57: =SUMIFS([6]BV_Data_An_Prec!$O:$O,[6]BV_Data_An_Prec!$U:$U,$B57,[6]BV_Data_An_Prec!$V:$V,$C57,[6]BV_Data_An_Prec!$W:$W,Q$2) -> 18900.59 | S57: =L57-Q57 -> -12524.59
A58: =+B58&C58 -> Véhicules neufsInformatique | B58: =+$K$1 -> Véhicules neufs | C58: Informatique | F58: =+INDEX('[6]Budget original'!$A$2:$AO$496,MATCH($A58,'[6]Budget original'!$A$2:$A$496,0),MATCH(F$2,'[6]Budget original'!$A$2:$AO$2,0)) -> 6677.3963 | I58: =+INDEX('[6]Budget révisé'!$A$2:$AO$496,MATCH($A58,'[6]Budget révisé'!$A$2:$A$496,0),MATCH(I$2,'[6]Budget révisé'!$A$2:$AO$2,0)) -> 6677.3963 | L58: =SUMIFS([6]BV_Data_An_Cour!$O:$O,[6]BV_Data_An_Cour!$U:$U,$B58,[6]BV_Data_An_Cour!$V:$V,$C58,[6]BV_Data_An_Cour!$W:$W,L$2) -> 6391.27 | N58: =L58-I58 -> -286.12627 | Q58: =SUMIFS([6]BV_Data_An_Prec!$O:$O,[6]BV_Data_An_Prec!$U:$U,$B58,[6]BV_Data_An_Prec!$V:$V,$C58,[6]BV_Data_An_Prec!$W:$W,Q$2) -> 6161.29 | S58: =L58-Q58 -> 229.98
A59: =+B59&C59 -> Véhicules neufsFrais de déplacement | B59: =+$K$1 -> Véhicules neufs | C59: Frais de déplacement | F59: =+INDEX('[6]Budget original'!$A$2:$AO$496,MATCH($A59,'[6]Budget original'!$A$2:$A$496,0),MATCH(F$2,'[6]Budget original'!$A$2:$AO$2,0)) -> 1596.4968 | I59: =+INDEX('[6]Budget révisé'!$A$2:$AO$496,MATCH($A59,'[6]Budget révisé'!$A$2:$A$496,0),MATCH(I$2,'[6]Budget révisé'!$A$2:$AO$2,0)) -> 1596.4968 | L59: =SUMIFS([6]BV_Data_An_Cour!$O:$O,[6]BV_Data_An_Cour!$U:$U,$B59,[6]BV_Data_An_Cour!$V:$V,$C59,[6]BV_Data_An_Cour!$W:$W,L$2) -> 612.46 | N59: =L59-I59 -> -984.0368 | Q59: =SUMIFS([6]BV_Data_An_Prec!$O:$O,[6]BV_Data_An_Prec!$U:$U,$B59,[6]BV_Data_An_Prec!$V:$V,$C59,[6]BV_Data_An_Prec!$W:$W,Q$2) -> 1944.64 | S59: =L59-Q59 -> -1332.18
A60: =+B60&C60 -> Véhicules neufsServices extérieurs | B60: =+$K$1 -> Véhicules neufs | C60: Services extérieurs | F60: =+INDEX('[6]Budget original'!$A$2:$AO$496,MATCH($A60,'[6]Budget original'!$A$2:$A$496,0),MATCH(F$2,'[6]Budget original'!$A$2:$AO$2,0)) -> 9857.8947 | I60: =+INDEX('[6]Budget révisé'!$A$2:$AO$496,MATCH($A60,'[6]Budget révisé'!$A$2:$A$496,0),MATCH(I$2,'[6]Budget révisé'!$A$2:$AO$2,0)) -> 9857.8947 | L60: =SUMIFS([6]BV_Data_An_Cour!$O:$O,[6]BV_Data_An_Cour!$U:$U,$B60,[6]BV_Data_An_Cour!$V:$V,$C60,[6]BV_Data_An_Cour!$W:$W,L$2) -> 7206.23 | N60: =L60-I60 -> -2651.6647 | Q60: =SUMIFS([6]BV_Data_An_Prec!$O:$O,[6]BV_Data_An_Prec!$U:$U,$B60,[6]BV_Data_An_Prec!$V:$V,$C60,[6]BV_Data_An_Prec!$W:$W,Q$2) -> 7248.82 | S60: =L60-Q60 -> -42.59
A61: =+B61&C61 -> Véhicules neufsFournitures autres | B61: =+$K$1 -> Véhicules neufs | C61: Fournitures autres | F61: =+INDEX('[6]Budget original'!$A$2:$AO$496,MATCH($A61,'[6]Budget original'!$A$2:$A$496,0),MATCH(F$2,'[6]Budget original'!$A$2:$AO$2,0)) -> 370.11227 | I61: =+INDEX('[6]Budget révisé'!$A$2:$AO$496,MATCH($A61,'[6]Budget révisé'!$A$2:$A$496,0),MATCH(I$2,'[6]Budget révisé'!$A$2:$AO$2,0)) -> 370.11227 | L61: =SUMIFS([6]BV_Data_An_Cour!$O:$O,[6]BV_Data_An_Cour!$U:$U,$B61,[6]BV_Data_An_Cour!$V:$V,$C61,[6]BV_Data_An_Cour!$W:$W,L$2) -> 74.93 | N61: =L61-I61 -> -295.18227 | Q61: =SUMIFS([6]BV_Data_An_Prec!$O:$O,[6]BV_Data_An_Prec!$U:$U,$B61,[6]BV_Data_An_Prec!$V:$V,$C61,[6]BV_Data_An_Prec!$W:$W,Q$2) -> 300 | S61: =L61-Q61 -> -225.07
A62: =+B62&C62 -> Véhicules neufsUniformes | B62: =+$K$1 -> Véhicules neufs | C62: Uniformes | F62: =+INDEX('[6]Budget original'!$A$2:$AO$496,MATCH($A62,'[6]Budget original'!$A$2:$A$496,0),MATCH(F$2,'[6]Budget original'!$A$2:$AO$2,0)) -> 35 | I62: =+INDEX('[6]Budget révisé'!$A$2:$AO$496,MATCH($A62,'[6]Budget révisé'!$A$2:$A$496,0),MATCH(I$2,'[6]Budget révisé'!$A$2:$AO$2,0)) -> 35 | L62: =SUMIFS([6]BV_Data_An_Cour!$O:$O,[6]BV_Data_An_Cour!$U:$U,$B62,[6]BV_Data_An_Cour!$V:$V,$C62,[6]BV_Data_An_Cour!$W:$W,L$2) -> 0 | N62: =L62-I62 -> -35 | Q62: =SUMIFS([6]BV_Data_An_Prec!$O:$O,[6]BV_Data_An_Prec!$U:$U,$B62,[6]BV_Data_An_Prec!$V:$V,$C62,[6]BV_Data_An_Prec!$W:$W,Q$2) -> 35 | S62: =L62-Q62 -> -35
A63: =+B63&C63 -> Véhicules neufsPapeterie | B63: =+$K$1 -> Véhicules neufs | C63: Papeterie | F63: =+INDEX('[6]Budget original'!$A$2:$AO$496,MATCH($A63,'[6]Budget original'!$A$2:$A$496,0),MATCH(F$2,'[6]Budget original'!$A$2:$AO$2,0)) -> 697.6 | I63: =+INDEX('[6]Budget révisé'!$A$2:$AO$496,MATCH($A63,'[6]Budget révisé'!$A$2:$A$496,0),MATCH(I$2,'[6]Budget révisé'!$A$2:$AO$2,0)) -> 697.6 | L63: =SUMIFS([6]BV_Data_An_Cour!$O:$O,[6]BV_Data_An_Cour!$U:$U,$B63,[6]BV_Data_An_Cour!$V:$V,$C63,[6]BV_Data_An_Cour!$W:$W,L$2) -> 755.68 | N63: =L63-I63 -> 58.08 | Q63: =SUMIFS([6]BV_Data_An_Prec!$O:$O,[6]BV_Data_An_Prec!$U:$U,$B63,[6]BV_Data_An_Prec!$V:$V,$C63,[6]BV_Data_An_Prec!$W:$W,Q$2) -> 592 | S63: =L63-Q63 -> 163.68
A64: =+B64&C64 -> Véhicules neufsTéléphone | B64: =+$K$1 -> Véhicules neufs | C64: Téléphone | F64: =+INDEX('[6]Budget original'!$A$2:$AO$496,MATCH($A64,'[6]Budget original'!$A$2:$A$496,0),MATCH(F$2,'[6]Budget original'!$A$2:$AO$2,0)) -> 589.912 | I64: =+INDEX('[6]Budget révisé'!$A$2:$AO$496,MATCH($A64,'[6]Budget révisé'!$A$2:$A$496,0),MATCH(I$2,'[6]Budget révisé'!$A$2:$AO$2,0)) -> 589.912 | L64: =SUMIFS([6]BV_Data_An_Cour!$O:$O,[6]BV_Data_An_Cour!$U:$U,$B64,[6]BV_Data_An_Cour!$V:$V,$C64,[6]BV_Data_An_Cour!$W:$W,L$2) -> 257.26 | N64: =L64-I64 -> -332.652 | Q64: =SUMIFS([6]BV_Data_An_Prec!$O:$O,[6]BV_Data_An_Prec!$U:$U,$B64,[6]BV_Data_An_Prec!$V:$V,$C64,[6]BV_Data_An_Prec!$W:$W,Q$2) -> 520.07 | S64: =L64-Q64 -> -262.81
A65: =+B65&C65 -> Véhicules neufsFrais postaux | B65: =+$K$1 -> Véhicules neufs | C65: Frais postaux | F65: =+INDEX('[6]Budget original'!$A$2:$AO$496,MATCH($A65,'[6]Budget original'!$A$2:$A$496,0),MATCH(F$2,'[6]Budget original'!$A$2:$AO$2,0)) -> 276.8 | I65: =+INDEX('[6]Budget révisé'!$A$2:$AO$496,MATCH($A65,'[6]Budget révisé'!$A$2:$A$496,0),MATCH(I$2,'[6]Budget révisé'!$A$2:$AO$2,0)) -> 276.8 | L65: =SUMIFS([6]BV_Data_An_Cour!$O:$O,[6]BV_Data_An_Cour!$U:$U,$B65,[6]BV_Data_An_Cour!$V:$V,$C65,[6]BV_Data_An_Cour!$W:$W,L$2) -> 162.85 | N65: =L65-I65 -> -113.95 | Q65: =SUMIFS([6]BV_Data_An_Prec!$O:$O,[6]BV_Data_An_Prec!$U:$U,$B65,[6]BV_Data_An_Prec!$V:$V,$C65,[6]BV_Data_An_Prec!$W:$W,Q$2) -> 81.69 | S65: =L65-Q65 -> 81.16
A66: =+B66&C66 -> Véhicules neufsDivers | B66: =+$K$1 -> Véhicules neufs | C66: Divers | F66: =+INDEX('[6]Budget original'!$A$2:$AO$496,MATCH($A66,'[6]Budget original'!$A$2:$A$496,0),MATCH(F$2,'[6]Budget original'!$A$2:$AO$2,0)) -> 1349.12 | I66: =+INDEX('[6]Budget révisé'!$A$2:$AO$496,MATCH($A66,'[6]Budget révisé'!$A$2:$A$496,0),MATCH(I$2,'[6]Budget révisé'!$A$2:$AO$2,0)) -> 1349.12 | L66: =SUMIFS([6]BV_Data_An_Cour!$O:$O,[6]BV_Data_An_Cour!$U:$U,$B66,[6]BV_Data_An_Cour!$V:$V,$C66,[6]BV_Data_An_Cour!$W:$W,L$2) -> 1198.42 | N66: =L66-I66 -> -150.7 | Q66: =SUMIFS([6]BV_Data_An_Prec!$O:$O,[6]BV_Data_An_Prec!$U:$U,$B66,[6]BV_Data_An_Prec!$V:$V,$C66,[6]BV_Data_An_Prec!$W:$W,Q$2) -> 1720.31 | S66: =L66-Q66 -> -521.89
A67: =+B67&C67 -> Véhicules neufsFormation | B67: =+$K$1 -> Véhicules neufs | C67: Formation | F67: =+INDEX('[6]Budget original'!$A$2:$AO$496,MATCH($A67,'[6]Budget original'!$A$2:$A$496,0),MATCH(F$2,'[6]Budget original'!$A$2:$AO$2,0)) -> 1438.3467 | I67: =+INDEX('[6]Budget révisé'!$A$2:$AO$496,MATCH($A67,'[6]Budget révisé'!$A$2:$A$496,0),MATCH(I$2,'[6]Budget révisé'!$A$2:$AO$2,0)) -> 1438.3467 | L67: =SUMIFS([6]BV_Data_An_Cour!$O:$O,[6]BV_Data_An_Cour!$U:$U,$B67,[6]BV_Data_An_Cour!$V:$V,$C67,[6]BV_Data_An_Cour!$W:$W,L$2) -> 843.33 | N67: =L67-I67 -> -595.01667 | Q67: =SUMIFS([6]BV_Data_An_Prec!$O:$O,[6]BV_Data_An_Prec!$U:$U,$B67,[6]BV_Data_An_Prec!$V:$V,$C67,[6]BV_Data_An_Prec!$W:$W,Q$2) -> 4555.83 | S67: =L67-Q67 -> -3712.5
A68: =+B68&C68 -> Véhicules neufsFrais bancaires | B68: =+$K$1 -> Véhicules neufs | C68: Frais bancaires | F68: =+INDEX('[6]Budget original'!$A$2:$AO$496,MATCH($A68,'[6]Budget original'!$A$2:$A$496,0),MATCH(F$2,'[6]Budget original'!$A$2:$AO$2,0)) -> 3670.6574 | I68: =+INDEX('[6]Budget révisé'!$A$2:$AO$496,MATCH($A68,'[6]Budget révisé'!$A$2:$A$496,0),MATCH(I$2,'[6]Budget révisé'!$A$2:$AO$2,0)) -> 3670.6574 | L68: =AF447*W3 -> 3102.8445 | N68: =L68-I68 -> -567.8129 | Q68: =AL447*W3 -> 3681.1125 | S68: =L68-Q68 -> -578.268
A69: =+B69&C69 -> Véhicules neufs[...] | B69: =+$K$1 -> Véhicules neufs | C69: [...] | F69: =+INDEX('[6]Budget original'!$A$2:$AO$496,MATCH($A69,'[6]Budget original'!$A$2:$A$496,0),MATCH(F$2,'[6]Budget original'!$A$2:$AO$2,0)) -> 0 | I69: =+INDEX('[6]Budget révisé'!$A$2:$AO$496,MATCH($A69,'[6]Budget révisé'!$A$2:$A$496,0),MATCH(I$2,'[6]Budget révisé'!$A$2:$AO$2,0)) -> 0 | N69: =L69-I69 -> 0 | Q69: =SUMIFS([6]BV_Data_An_Prec!$O:$O,[6]BV_Data_An_Prec!$U:$U,$B69,[6]BV_Data_An_Prec!$V:$V,$C69,[6]BV_Data_An_Prec!$W:$W,Q$2) -> 0 | S69: =L69-Q69 -> 0
A70: =+B70&C70 -> Véhicules neufs[...] | B70: =+$K$1 -> Véhicules neufs | C70: [...] | F70: =+INDEX('[6]Budget original'!$A$2:$AO$496,MATCH($A70,'[6]Budget original'!$A$2:$A$496,0),MATCH(F$2,'[6]Budget original'!$A$2:$AO$2,0)) -> 0 | I70: =+INDEX('[6]Budget révisé'!$A$2:$AO$496,MATCH($A70,'[6]Budget révisé'!$A$2:$A$496,0),MATCH(I$2,'[6]Budget révisé'!$A$2:$AO$2,0)) -> 0 | L70: =SUMIFS([6]BV_Data_An_Cour!$O:$O,[6]BV_Data_An_Cour!$U:$U,$B70,[6]BV_Data_An_Cour!$V:$V,$C70,[6]BV_Data_An_Cour!$W:$W,L$2) -> 0 | N70: =L70-I70 -> 0 | Q70: =SUMIFS([6]BV_Data_An_Prec!$O:$O,[6]BV_Data_An_Prec!$U:$U,$B70,[6]BV_Data_An_Prec!$V:$V,$C70,[6]BV_Data_An_Prec!$W:$W,Q$2) -> 0 | S70: =L70-Q70 -> 0
A71: =+B71&C71 -> Véhicules neufs[...] | B71: =+$K$1 -> Véhicules neufs | C71: [...] | F71: =+INDEX('[6]Budget original'!$A$2:$AO$496,MATCH($A71,'[6]Budget original'!$A$2:$A$496,0),MATCH(F$2,'[6]Budget original'!$A$2:$AO$2,0)) -> 0 | I71: =+INDEX('[6]Budget révisé'!$A$2:$AO$496,MATCH($A71,'[6]Budget révisé'!$A$2:$A$496,0),MATCH(I$2,'[6]Budget révisé'!$A$2:$AO$2,0)) -> 0 | L71: =SUMIFS([6]BV_Data_An_Cour!$O:$O,[6]BV_Data_An_Cour!$U:$U,$B71,[6]BV_Data_An_Cour!$V:$V,$C71,[6]BV_Data_An_Cour!$W:$W,L$2)*0.32 -> 0 | N71: =L71-I71 -> 0 | Q71: =SUMIFS([6]BV_Data_An_Prec!$O:$O,[6]BV_Data_An_Prec!$U:$U,$B71,[6]BV_Data_An_Prec!$V:$V,$C71,[6]BV_Data_An_Prec!$W:$W,Q$2)*0.32 -> 0 | S71: =L71-Q71 -> 0
A72: =+B72&C72 -> Véhicules neufsTOTAL SEMI-FIXES | B72: =+$K$1 -> Véhicules neufs | C72: TOTAL SEMI-FIXES | D72: % brut | E72: =F72/F$27 -> 0.20732939 | F72: =+SUM(F55:F71) -> 35648.214 | G72: % brut | H72: =I72/I$27 -> 0.17052647 | I72: =+SUM(I55:I71) -> 35648.214 | J72: % brut | K72: =L72/L$27 -> 0.11057212 | L72: =+SUM(L55:L71) -> 26981.274 | N72: =+SUM(N55:N71) -> -8666.9391 | O72: % brut | P72: =Q72/Q$27 -> 0.4405563 | Q72: =+SUM(Q55:Q71) -> 45741.353 | S72: =+SUM(S55:S71) -> -18760.078
A73: =+B73&C73 -> Véhicules neufs | B73: =+$K$1 -> Véhicules neufs
A74: =+B74&C74 -> Véhicules neufsTOTAL DES DÉPENSES | B74: =+$K$1 -> Véhicules neufs | C74: TOTAL DES DÉPENSES | D74: % brut | E74: =F74/F$27 -> 1.2832995 | F74: =F41+F54+F72 -> 220650.51 | G74: % brut | H74: =I74/I$27 -> 1.0605929 | I74: =I41+I54+I72 -> 221714.8 | J74: % brut | K74: =L74/L$27 -> 0.86838431 | L74: =L41+L54+L72 -> 211898.94 | N74: =L74-I74 -> -9815.8591 | O74: % brut | P74: =Q74/Q$27 -> 2.1593979 | Q74: =Q41+Q54+Q72 -> 224202.4 | S74: =L74-Q74 -> -12303.458
A75: =+B75&C75 -> Véhicules neufsProgramme neuf 1 | B75: =+$K$1 -> Véhicules neufs | C75: Programme neuf 1 | F75: =+INDEX('[6]Budget original'!$A$2:$AO$496,MATCH($A75,'[6]Budget original'!$A$2:$A$496,0),MATCH(F$2,'[6]Budget original'!$A$2:$AO$2,0)) -> 49893.401 | I75: =+INDEX('[6]Budget révisé'!$A$2:$AO$496,MATCH($A75,'[6]Budget révisé'!$A$2:$A$496,0),MATCH(I$2,'[6]Budget révisé'!$A$2:$AO$2,0)) -> 9354.2259 | L75: =-SUMIFS([6]BV_Data_An_Cour!$O:$O,[6]BV_Data_An_Cour!$U:$U,$B75,[6]BV_Data_An_Cour!$V:$V,$C75,[6]BV_Data_An_Cour!$W:$W,L$2)-L155 -> 0 | N75: =L75-I75 -> -9354.2259 | Q75: =-SUMIFS([6]BV_Data_An_Prec!$O:$O,[6]BV_Data_An_Prec!$U:$U,$B75,[6]BV_Data_An_Prec!$V:$V,$C75,[6]BV_Data_An_Prec!$W:$W,Q$2)-Q155 -> 45750 | V75: new CSI selon volume arrivae
A76: =+B76&C76 -> Véhicules neufsProgramme neuf 2 | B76: =+$K$1 -> Véhicules neufs | C76: Programme neuf 2 | F76: =+INDEX('[6]Budget original'!$A$2:$AO$496,MATCH($A76,'[6]Budget original'!$A$2:$A$496,0),MATCH(F$2,'[6]Budget original'!$A$2:$AO$2,0)) -> 0 | I76: =+INDEX('[6]Budget révisé'!$A$2:$AO$496,MATCH($A76,'[6]Budget révisé'!$A$2:$A$496,0),MATCH(I$2,'[6]Budget révisé'!$A$2:$AO$2,0)) -> 0 | L76: =-SUMIFS([6]BV_Data_An_Cour!$O:$O,[6]BV_Data_An_Cour!$U:$U,$B76,[6]BV_Data_An_Cour!$V:$V,$C76,[6]BV_Data_An_Cour!$W:$W,L$2) -> 0 | N76: =L76-I76 -> 0 | Q76: =-SUMIFS([6]BV_Data_An_Prec!$O:$O,[6]BV_Data_An_Prec!$U:$U,$B76,[6]BV_Data_An_Prec!$V:$V,$C76,[6]BV_Data_An_Prec!$W:$W,Q$2) -> 0 | S76: =L76-Q76 -> 0
A77: =+B77&C77 -> Véhicules neufsProgramme neuf 3 | B77: =+$K$1 -> Véhicules neufs | C77: Programme neuf 3 | F77: =+INDEX('[6]Budget original'!$A$2:$AO$496,MATCH($A77,'[6]Budget original'!$A$2:$A$496,0),MATCH(F$2,'[6]Budget original'!$A$2:$AO$2,0)) -> 0 | I77: =+INDEX('[6]Budget révisé'!$A$2:$AO$496,MATCH($A77,'[6]Budget révisé'!$A$2:$A$496,0),MATCH(I$2,'[6]Budget révisé'!$A$2:$AO$2,0)) -> 0 | L77: =-SUMIFS([6]BV_Data_An_Cour!$O:$O,[6]BV_Data_An_Cour!$U:$U,$B77,[6]BV_Data_An_Cour!$V:$V,$C77,[6]BV_Data_An_Cour!$W:$W,L$2) -> 0 | N77: =L77-I77 -> 0 | Q77: =-SUMIFS([6]BV_Data_An_Prec!$O:$O,[6]BV_Data_An_Prec!$U:$U,$B77,[6]BV_Data_An_Prec!$V:$V,$C77,[6]BV_Data_An_Prec!$W:$W,Q$2) -> 0 | S77: =L77-Q77 -> 0
A78: =+B78&C78 -> Véhicules neufsHoldbacks | B78: =+$K$1 -> Véhicules neufs | C78: Holdbacks | F78: =+INDEX('[6]Budget original'!$A$2:$AO$496,MATCH($A78,'[6]Budget original'!$A$2:$A$496,0),MATCH(F$2,'[6]Budget original'!$A$2:$AO$2,0)) -> 80053.124 | I78: =+INDEX('[6]Budget révisé'!$A$2:$AO$496,MATCH($A78,'[6]Budget révisé'!$A$2:$A$496,0),MATCH(I$2,'[6]Budget révisé'!$A$2:$AO$2,0)) -> 81318.786 | L78: =-SUMIFS([6]BV_Data_An_Cour!$O:$O,[6]BV_Data_An_Cour!$U:$U,$B78,[6]BV_Data_An_Cour!$V:$V,$C78,[6]BV_Data_An_Cour!$W:$W,L$2) -> 102678 | N78: =L78-I78 -> 21359.214 | Q78: =-SUMIFS([6]BV_Data_An_Prec!$O:$O,[6]BV_Data_An_Prec!$U:$U,$B78,[6]BV_Data_An_Prec!$V:$V,$C78,[6]BV_Data_An_Prec!$W:$W,Q$2) -> 72454 | S78: =L78-Q78 -> 30224
A79: =+B79&C79 -> Véhicules neufs[...] | B79: =+$K$1 -> Véhicules neufs | C79: [...] | F79: =+INDEX('[6]Budget original'!$A$2:$AO$496,MATCH($A79,'[6]Budget original'!$A$2:$A$496,0),MATCH(F$2,'[6]Budget original'!$A$2:$AO$2,0)) -> 0 | I79: =+INDEX('[6]Budget révisé'!$A$2:$AO$496,MATCH($A79,'[6]Budget révisé'!$A$2:$A$496,0),MATCH(I$2,'[6]Budget révisé'!$A$2:$AO$2,0)) -> 0 | L79: =-SUMIFS([6]BV_Data_An_Cour!$O:$O,[6]BV_Data_An_Cour!$U:$U,$B79,[6]BV_Data_An_Cour!$V:$V,$C79,[6]BV_Data_An_Cour!$W:$W,L$2) -> 0 | N79: =L79-I79 -> 0 | Q79: =-SUMIFS([6]BV_Data_An_Prec!$O:$O,[6]BV_Data_An_Prec!$U:$U,$B79,[6]BV_Data_An_Prec!$V:$V,$C79,[6]BV_Data_An_Prec!$W:$W,Q$2) -> 0 | S79: =L79-Q79 -> 0
A80: =+B80&C80 -> Véhicules neufs[...] | B80: =+$K$1 -> Véhicules neufs | C80: [...] | F80: =+INDEX('[6]Budget original'!$A$2:$AO$496,MATCH($A80,'[6]Budget original'!$A$2:$A$496,0),MATCH(F$2,'[6]Budget original'!$A$2:$AO$2,0)) -> 0 | I80: =+INDEX('[6]Budget révisé'!$A$2:$AO$496,MATCH($A80,'[6]Budget révisé'!$A$2:$A$496,0),MATCH(I$2,'[6]Budget révisé'!$A$2:$AO$2,0)) -> 0 | L80: =-SUMIFS([6]BV_Data_An_Cour!$O:$O,[6]BV_Data_An_Cour!$U:$U,$B80,[6]BV_Data_An_Cour!$V:$V,$C80,[6]BV_Data_An_Cour!$W:$W,L$2) -> 0 | N80: =L80-I80 -> 0 | Q80: =-SUMIFS([6]BV_Data_An_Prec!$O:$O,[6]BV_Data_An_Prec!$U:$U,$B80,[6]BV_Data_An_Prec!$V:$V,$C80,[6]BV_Data_An_Prec!$W:$W,Q$2) -> 0 | S80: =L80-Q80 -> 0
A81: =+B81&C81 -> Véhicules neufs[...] | B81: =+$K$1 -> Véhicules neufs | C81: [...] | F81: =+INDEX('[6]Budget original'!$A$2:$AO$496,MATCH($A81,'[6]Budget original'!$A$2:$A$496,0),MATCH(F$2,'[6]Budget original'!$A$2:$AO$2,0)) -> 0 | I81: =+INDEX('[6]Budget révisé'!$A$2:$AO$496,MATCH($A81,'[6]Budget révisé'!$A$2:$A$496,0),MATCH(I$2,'[6]Budget révisé'!$A$2:$AO$2,0)) -> 0 | L81: =-SUMIFS([6]BV_Data_An_Cour!$O:$O,[6]BV_Data_An_Cour!$U:$U,$B81,[6]BV_Data_An_Cour!$V:$V,$C81,[6]BV_Data_An_Cour!$W:$W,L$2) -> 0 | N81: =L81-I81 -> 0 | Q81: =-SUMIFS([6]BV_Data_An_Prec!$O:$O,[6]BV_Data_An_Prec!$U:$U,$B81,[6]BV_Data_An_Prec!$V:$V,$C81,[6]BV_Data_An_Prec!$W:$W,Q$2) -> 0 | S81: =L81-Q81 -> 0
A82: =+B82&C82 -> Véhicules neufsFrais administration | B82: =+$K$1 -> Véhicules neufs | C82: Frais administration | F82: =+INDEX('[6]Budget original'!$A$2:$AO$496,MATCH($A82,'[6]Budget original'!$A$2:$A$496,0),MATCH(F$2,'[6]Budget original'!$A$2:$AO$2,0)) -> 29063.066 | I82: =+INDEX('[6]Budget révisé'!$A$2:$AO$496,MATCH($A82,'[6]Budget révisé'!$A$2:$A$496,0),MATCH(I$2,'[6]Budget révisé'!$A$2:$AO$2,0)) -> 29063.066 | L82: =-SUMIFS([6]BV_Data_An_Cour!$O:$O,[6]BV_Data_An_Cour!$U:$U,$B82,[6]BV_Data_An_Cour!$V:$V,$C82,[6]BV_Data_An_Cour!$W:$W,L$2)-L158 -> 25377 | N82: =L82-I82 -> -3686.0658 | Q82: =-SUMIFS([6]BV_Data_An_Prec!$O:$O,[6]BV_Data_An_Prec!$U:$U,$B82,[6]BV_Data_An_Prec!$V:$V,$C82,[6]BV_Data_An_Prec!$W:$W,Q$2)-Q158 -> 9865 | S82: =L82-Q82 -> 15512 | U82: plus 30 k versu estimé
A83: =+B83&C83 -> Véhicules neufsAUTRES REVENUS | B83: =+$K$1 -> Véhicules neufs | C83: AUTRES REVENUS | F83: =+SUM(F75:F82) -> 159009.59 | I83: =+SUM(I75:I82) -> 119736.08 | L83: =+SUM(L75:L82) -> 128055 | N83: =+SUM(N75:N82) -> 8318.922 | Q83: =+SUM(Q75:Q82) -> 128069 | S83: =+SUM(S75:S82) -> 45736
A84: =+B84&C84 -> Véhicules neufs | B84: =+$K$1 -> Véhicules neufs
A85: =+B85&C85 -> Véhicules neufsPROFIT DÉPARTEMENTAL | B85: =+$K$1 -> Véhicules neufs | C85: PROFIT DÉPARTEMENTAL | F85: =F27-F74+F83 -> 110299.07 | I85: =I27-I74+I83 -> 107069.25 | L85: =L27-L74+L83 -> 160171.23 | N85: =N27-N41-N54-N72+N83 -> 53101.978 | Q85: =Q27-Q74+Q83 -> 7692.9475 | S85: =S27-S41-S54-S72+S83 -> 198228.28
C89: =C1 -> Volks | K89: Véhicules usagés | S89: =$S$1 -> Réalisé, Mai 2021
D91: BUDGET ORIGINAL | G91: BUDGET RÉVISÉ | J91: RÉALISATION | M91: ÉCART réel / révisé | O91: ANNÉE PRÉCÉDENTE | R91: ÉCART réel / original
D92: UNITE | E92: $P/UNITÉ | F92: $PROFITS | G92: UNITE | H92: $P/UNITÉ | I92: $PROFITS | J92: UNITE | K92: $P/UNITE | L92: $PROFITS | M92: UNITÉ | N92: $PROFITS | O92: UNITE | P92: $P/UNITE | Q92: $PROFITS | R92: UNITE | S92: $PROFITS
A93: =+B93&C93 -> Véhicules usagésVentes nettes | B93: Véhicules usagés | C93: Ventes nettes | F93: =+INDEX('[6]Budget original'!$A$2:$AO$496,MATCH($A93,'[6]Budget original'!$A$2:$A$496,0),MATCH(F$2,'[6]Budget original'!$A$2:$AO$2,0)) -> 1240477.2 | I93: =+INDEX('[6]Budget révisé'!$A$2:$AO$496,MATCH($A93,'[6]Budget révisé'!$A$2:$A$496,0),MATCH(I$2,'[6]Budget révisé'!$A$2:$AO$2,0)) -> 1240477.2 | L93: =-SUMIFS([6]BV_Data_An_Cour!$O:$O,[6]BV_Data_An_Cour!$X:$X,"Oui",[6]BV_Data_An_Cour!$U:$U,$B93) -> 1342441.4 | Q93: =-SUMIFS([6]BV_Data_An_Prec!$O:$O,[6]BV_Data_An_Prec!$X:$X,"Oui",[6]BV_Data_An_Prec!$U:$U,$B93) -> 1121291.6
A94: =+B94&C94 -> Véhicules usagésCertifié | B94: Véhicules usagés | C94: Certifié | D94: =+INDEX('[6]Budget original'!$A$2:$AO$496,MATCH($A94,'[6]Budget original'!$A$2:$A$496,0),MATCH(D$2,'[6]Budget original'!$A$2:$AO$2,0)) -> 37.229811 | E94: =IF(D94=0,0,F94/D94) -> 750 | F94: =+INDEX('[6]Budget original'!$A$2:$AO$496,MATCH($A94,'[6]Budget original'!$A$2:$A$496,0),MATCH(F$2,'[6]Budget original'!$A$2:$AO$2,0)) -> 27922.358 | G94: =+INDEX('[6]Budget révisé'!$A$2:$AO$496,MATCH($A94,'[6]Budget révisé'!$A$2:$A$496,0),MATCH(G$2,'[6]Budget révisé'!$A$2:$AO$2,0)) -> 37.229811 | H94: =IF(G94=0,0,I94/G94) -> 750 | I94: =+INDEX('[6]Budget révisé'!$A$2:$AO$496,MATCH($A94,'[6]Budget révisé'!$A$2:$A$496,0),MATCH(I$2,'[6]Budget révisé'!$A$2:$AO$2,0)) -> 27922.358 | J94: =-SUMIFS([6]BV_Data_An_Cour!$O:$O,[6]BV_Data_An_Cour!$U:$U,$B94,[6]BV_Data_An_Cour!$V:$V,$C94,[6]BV_Data_An_Cour!$W:$W,J$2) -> 38 | K94: =IF(J94=0,0,L94/J94) -> 1319.41 | L94: =-SUMIFS([6]BV_Data_An_Cour!$O:$O,[6]BV_Data_An_Cour!$U:$U,$B94,[6]BV_Data_An_Cour!$V:$V,$C94,[6]BV_Data_An_Cour!$W:$W,$L2) -> 50137.58 | M94: =J94-G94 -> 0.77018909 | N94: =L94-I94 -> 22215.222 | O94: =-SUMIFS([6]BV_Data_An_Prec!$O:$O,[6]BV_Data_An_Prec!$U:$U,$B94,[6]BV_Data_An_Prec!$V:$V,$C94,[6]BV_Data_An_Prec!$W:$W,O$2) -> 0 | P94: =IF(O94=0,0,Q94/O94) -> 0 | Q94: =-SUMIFS([6]BV_Data_An_Prec!$O:$O,[6]BV_Data_An_Prec!$U:$U,$B94,[6]BV_Data_An_Prec!$V:$V,$C94,[6]BV_Data_An_Prec!$W:$W,$L2) -> 0 | R94: =J94-O94 -> 38 | S94: =L94-Q94 -> 50137.58
A95: =+B95&C95 -> Véhicules usagésNon Certifié | B95: Véhicules usagés | C95: Non Certifié | D95: =+INDEX('[6]Budget original'!$A$2:$AO$496,MATCH($A95,'[6]Budget original'!$A$2:$A$496,0),MATCH(D$2,'[6]Budget original'!$A$2:$AO$2,0)) -> 2.1233732 | E95: =IF(D95=0,0,F95/D95) -> 750 | F95: =+INDEX('[6]Budget original'!$A$2:$AO$496,MATCH($A95,'[6]Budget original'!$A$2:$A$496,0),MATCH(F$2,'[6]Budget original'!$A$2:$AO$2,0)) -> 1592.5299 | G95: =+INDEX('[6]Budget révisé'!$A$2:$AO$496,MATCH($A95,'[6]Budget révisé'!$A$2:$A$496,0),MATCH(G$2,'[6]Budget révisé'!$A$2:$AO$2,0)) -> 2.1233732 | H95: =IF(G95=0,0,I95/G95) -> 750 | I95: =+INDEX('[6]Budget révisé'!$A$2:$AO$496,MATCH($A95,'[6]Budget révisé'!$A$2:$A$496,0),MATCH(I$2,'[6]Budget révisé'!$A$2:$AO$2,0)) -> 1592.5299 | J95: =-SUMIFS([6]BV_Data_An_Cour!$O:$O,[6]BV_Data_An_Cour!$U:$U,$B95,[6]BV_Data_An_Cour!$V:$V,$C95,[6]BV_Data_An_Cour!$W:$W,J$2) -> 1 | K95: =IF(J95=0,0,L95/J95) -> -434 | L95: =-SUMIFS([6]BV_Data_An_Cour!$O:$O,[6]BV_Data_An_Cour!$U:$U,$B95,[6]BV_Data_An_Cour!$V:$V,$C95,[6]BV_Data_An_Cour!$W:$W,$L2) -> -434 | O95: =-SUMIFS([6]BV_Data_An_Prec!$O:$O,[6]BV_Data_An_Prec!$U:$U,$B95,[6]BV_Data_An_Prec!$V:$V,$C95,[6]BV_Data_An_Prec!$W:$W,O$2) -> 38 | P95: =IF(O95=0,0,Q95/O95) -> 484.78447 | Q95: =-SUMIFS([6]BV_Data_An_Prec!$O:$O,[6]BV_Data_An_Prec!$U:$U,$B95,[6]BV_Data_An_Prec!$V:$V,$C95,[6]BV_Data_An_Prec!$W:$W,$L2) -> 18421.81 | R95: =J95-O95 -> -37 | S95: =L95-Q95 -> -18855.81
A96: =+B96&C96 -> Véhicules usagésTotal Usagés | B96: Véhicules usagés | C96: Total Usagés | D96: =+D95+D94 -> 39.353184 | E96: =IF(D96=0,0,F96/D96) -> 750 | F96: =+F94+F95 -> 29514.888 | G96: =+G95+G94 -> 39.353184 | H96: =IF(G96=0,0,I96/G96) -> 750 | I96: =+I94+I95 -> 29514.888 | J96: =+J94+J95 -> 39 | K96: =IF(J96<=0,0,L96/J96) -> 1274.4508 | L96: =+L94+L95 -> 49703.58 | M96: =J96-G96 -> -0.35318415 | N96: =L96-I96 -> 20188.692 | O96: =+O94+O95 -> 38 | P96: =IF(O96<=0,0,Q96/O96) -> 484.78447 | Q96: =+Q94+Q95 -> 18421.81 | R96: =R94+R95 -> 1 | S96: =S94+S95 -> 31281.77
A97: =+B97&C97 -> Véhicules usagés | B97: Véhicules usagés | E97: =IF(D97=0,0,F97/D97) -> 0 | H97: =IF(G97=0,0,I97/G97) -> 0 | M97: =M96/G96 -> -0.0089747287 | N97: =N96/I96 -> 0.68401723 | R97: =R96/O96 -> 0.026315789 | S97: =IF(Q96=0,0,(S96/Q96)) -> 1.6980834
A98: =+B98&C98 -> Véhicules usagésUS | B98: Véhicules usagés | C98: US
A99: =+B99&C99 -> Véhicules usagésVentes au Gros | B99: Véhicules usagés | C99: Ventes au Gros | D99: =+INDEX('[6]Budget original'!$A$2:$AO$496,MATCH($A99,'[6]Budget original'!$A$2:$A$496,0),MATCH(D$2,'[6]Budget original'!$A$2:$AO$2,0)) -> 33.346646 | E99: =IF(D99=0,0,F99/D99) -> 120 | F99: =+INDEX('[6]Budget original'!$A$2:$AO$496,MATCH($A99,'[6]Budget original'!$A$2:$A$496,0),MATCH(F$2,'[6]Budget original'!$A$2:$AO$2,0)) -> 4001.5975 | G99: =+INDEX('[6]Budget révisé'!$A$2:$AO$496,MATCH($A99,'[6]Budget révisé'!$A$2:$A$496,0),MATCH(G$2,'[6]Budget révisé'!$A$2:$AO$2,0)) -> 33.346646 | H99: =IF(G99=0,0,I99/G99) -> 120 | I99: =+INDEX('[6]Budget révisé'!$A$2:$AO$496,MATCH($A99,'[6]Budget révisé'!$A$2:$A$496,0),MATCH(I$2,'[6]Budget révisé'!$A$2:$AO$2,0)) -> 4001.5975 | J99: =-SUMIFS([6]BV_Data_An_Cour!$O:$O,[6]BV_Data_An_Cour!$U:$U,$B99,[6]BV_Data_An_Cour!$V:$V,$C99,[6]BV_Data_An_Cour!$W:$W,J$2) -> 41 | K99: =IF(J99=0,0,L99/J99) -> 611.62902 | L99: =-SUMIFS([6]BV_Data_An_Cour!$O:$O,[6]BV_Data_An_Cour!$U:$U,$B99,[6]BV_Data_An_Cour!$V:$V,$C99,[6]BV_Data_An_Cour!$W:$W,L$2) -> 25076.79 | M99: =J99-G99 -> 7.6533545 | N99: =L99-I99 -> 21075.193 | O99: =-SUMIFS([6]BV_Data_An_Prec!$O:$O,[6]BV_Data_An_Prec!$U:$U,$B99,[6]BV_Data_An_Prec!$V:$V,$C99,[6]BV_Data_An_Prec!$W:$W,O$2) -> 35 | P99: =IF(O99=0,0,Q99/O99) -> 374.76086 | Q99: =-SUMIFS([6]BV_Data_An_Prec!$O:$O,[6]BV_Data_An_Prec!$U:$U,$B99,[6]BV_Data_An_Prec!$V:$V,$C99,[6]BV_Data_An_Prec!$W:$W,Q$2) -> 13116.63 | R99: =J99-O99 -> 6 | S99: =L99-Q99 -> 11960.16
A100: =+B100&C100 -> Véhicules usagés | B100: Véhicules usagés
A101: =+B101&C101 -> Véhicules usagésRev. Finances | B101: Véhicules usagés | C101: Rev. Finances | D101: =+INDEX('[6]Budget original'!$A$2:$AO$496,MATCH($A101,'[6]Budget original'!$A$2:$A$496,0),MATCH(D$2,'[6]Budget original'!$A$2:$AO$2,0)) -> 0 | E101: =IF(D101=0,0,F101/D101) -> 0 | F101: =+INDEX('[6]Budget original'!$A$2:$AO$496,MATCH($A101,'[6]Budget original'!$A$2:$A$496,0),MATCH(F$2,'[6]Budget original'!$A$2:$AO$2,0)) -> 31643.642 | G101: =+INDEX('[6]Budget révisé'!$A$2:$AO$496,MATCH($A101,'[6]Budget révisé'!$A$2:$A$496,0),MATCH(G$2,'[6]Budget révisé'!$A$2:$AO$2,0)) -> 0 | H101: =IF(G101=0,0,I101/G101) -> 0 | I101: =+INDEX('[6]Budget révisé'!$A$2:$AO$496,MATCH($A101,'[6]Budget révisé'!$A$2:$A$496,0),MATCH(I$2,'[6]Budget révisé'!$A$2:$AO$2,0)) -> 31643.642 | K101: =IF(J96=0,0,L101/J96) -> 799.67385 | L101: =-SUMIFS([6]BV_Data_An_Cour!$O:$O,[6]BV_Data_An_Cour!$U:$U,$B101,[6]BV_Data_An_Cour!$V:$V,$C101,[6]BV_Data_An_Cour!$W:$W,$L2) -> 31187.28 | N101: =L101-I101 -> -456.36223 | P101: =IF(O96=0,0,Q101/O96) -> 613.01947 | Q101: =-SUMIFS([6]BV_Data_An_Prec!$O:$O,[6]BV_Data_An_Prec!$U:$U,$B101,[6]BV_Data_An_Prec!$V:$V,$C101,[6]BV_Data_An_Prec!$W:$W,$L2) -> 23294.74 | R101: =O101-K101 -> -799.67385 | S101: =L101-Q101 -> 7892.54
A102: =+B102&C102 -> Véhicules usagésRev. Protections | B102: Véhicules usagés | C102: Rev. Protections | D102: =+INDEX('[6]Budget original'!$A$2:$AO$496,MATCH($A102,'[6]Budget original'!$A$2:$A$496,0),MATCH(D$2,'[6]Budget original'!$A$2:$AO$2,0)) -> 0 | E102: =IF(D102=0,0,F102/D102) -> 0 | F102: =+INDEX('[6]Budget original'!$A$2:$AO$496,MATCH($A102,'[6]Budget original'!$A$2:$A$496,0),MATCH(F$2,'[6]Budget original'!$A$2:$AO$2,0)) -> 35862.795 | G102: =+INDEX('[6]Budget révisé'!$A$2:$AO$496,MATCH($A102,'[6]Budget révisé'!$A$2:$A$496,0),MATCH(G$2,'[6]Budget révisé'!$A$2:$AO$2,0)) -> 0 | H102: =IF(G102=0,0,I102/G102) -> 0 | I102: =+INDEX('[6]Budget révisé'!$A$2:$AO$496,MATCH($A102,'[6]Budget révisé'!$A$2:$A$496,0),MATCH(I$2,'[6]Budget révisé'!$A$2:$AO$2,0)) -> 35862.795 | K102: =IF(J96=0,0,L102/J96) -> 1285.4226 | L102: =-SUMIFS([6]BV_Data_An_Cour!$O:$O,[6]BV_Data_An_Cour!$U:$U,$B102,[6]BV_Data_An_Cour!$V:$V,$C102,[6]BV_Data_An_Cour!$W:$W,$L2) -> 50131.48 | N102: =L102-I102 -> 14268.685 | P102: =IF(O96=0,0,Q102/O96) -> 594.36447 | Q102: =-SUMIFS([6]BV_Data_An_Prec!$O:$O,[6]BV_Data_An_Prec!$U:$U,$B102,[6]BV_Data_An_Prec!$V:$V,$C102,[6]BV_Data_An_Prec!$W:$W,$L2) -> 22585.85 | R102: =O102-K102 -> -1285.4226 | S102: =L102-Q102 -> 27545.63
A103: =+B103&C103 -> Véhicules usagésRev. Autres | B103: Véhicules usagés | C103: Rev. Autres | D103: =+INDEX('[6]Budget original'!$A$2:$AO$496,MATCH($A103,'[6]Budget original'!$A$2:$A$496,0),MATCH(D$2,'[6]Budget original'!$A$2:$AO$2,0)) -> 0 | E103: =IF(D103=0,0,F103/D103) -> 0 | F103: =+INDEX('[6]Budget original'!$A$2:$AO$496,MATCH($A103,'[6]Budget original'!$A$2:$A$496,0),MATCH(F$2,'[6]Budget original'!$A$2:$AO$2,0)) -> 0 | G103: =+INDEX('[6]Budget révisé'!$A$2:$AO$496,MATCH($A103,'[6]Budget révisé'!$A$2:$A$496,0),MATCH(G$2,'[6]Budget révisé'!$A$2:$AO$2,0)) -> 0 | H103: =IF(G103=0,0,I103/G103) -> 0 | I103: =+INDEX('[6]Budget révisé'!$A$2:$AO$496,MATCH($A103,'[6]Budget révisé'!$A$2:$A$496,0),MATCH(I$2,'[6]Budget révisé'!$A$2:$AO$2,0)) -> 0 | K103: =IF(J96=0,0,L103/J96) -> 41.958462 | L103: =-SUMIFS([6]BV_Data_An_Cour!$O:$O,[6]BV_Data_An_Cour!$U:$U,$B103,[6]BV_Data_An_Cour!$V:$V,$C103,[6]BV_Data_An_Cour!$W:$W,$L$2) -> 1636.38 | N103: =L103-I103 -> 1636.38 | P103: =IF(O96=0,0,Q103/O96) -> 20.980789 | Q103: =-SUMIFS([6]BV_Data_An_Prec!$O:$O,[6]BV_Data_An_Prec!$U:$U,$B103,[6]BV_Data_An_Prec!$V:$V,$C103,[6]BV_Data_An_Prec!$W:$W,$L$2) -> 797.27 | R103: =O103-K103 -> -41.958462 | S103: =L103-Q103 -> 839.11 | U103: less cash deals 6 only
A104: =+B104&C104 -> Véhicules usagésTotal F&I | B104: Véhicules usagés | C104: Total F&I | D104: =D96 -> 39.353184 | E104: =IF(D104=0,0,F104/D104) -> 1715.3996 | F104: =F101+F102+F103 -> 67506.437 | G104: =G96 -> 39.353184 | H104: =IF(G104=0,0,I104/G104) -> 1715.3996 | I104: =I101+I102+I103 -> 67506.437 | J104: =J96 -> 39 | K104: =IF(J104<=0,0,L104/J104) -> 2127.0549 | L104: =L101+L102+L103 -> 82955.14 | M104: =J104-G104 -> -0.35318415 | N104: =L104-I104 -> 15448.703 | O104: =O96 -> 38 | P104: =IF(O104<=0,0,Q104/O104) -> 1228.3647 | Q104: =Q101+Q102+Q103 -> 46677.86 | S104: =L104-Q104 -> 36277.28
...

Sheet VW 6
C1: =[7]Parametres!B1 -> Volks | K1: Véhicules neufs | S1: =CONCATENATE("Réalisé,"," ",[7]Parametres!B3," ",[7]Parametres!B4) -> Réalisé, Juin 2021
D2: X | E2: O | F2: U | G2: X | H2: O | I2: U | J2: NB | L2: $ | O2: NB | Q2: $
D3: BUDGET ORIGINAL | G3: BUDGET REVISE | J3: RÉALISATION | M3: ÉCART réel / révisé | O3: ANNÉE PRÉCÉDENTE | R3: ÉCART réel / original | V3: NEUF | W3: 0.45
D4: UNITE | E4: $P/UNITÉ | F4: $PROFITS | G4: UNITE | H4: $P/UNITÉ | I4: $PROFITS | J4: UNITE | K4: $P/UNITE | L4: $PROFITS | M4: UNITÉ | N4: $PROFITS | O4: UNITE | P4: $P/UNITE | Q4: $PROFITS | R4: UNITE | S4: $PROFITS | V4: USAGE | W4: 0.1
A5: =+B5&C5 -> Véhicules neufsVentes nettes | B5: =+$K$1 -> Véhicules neufs | C5: Ventes nettes | F5: =+INDEX('[7]Budget original'!$A$2:$AO$496,MATCH($A5,'[7]Budget original'!$A$2:$A$496,0),MATCH(F$2,'[7]Budget original'!$A$2:$AO$2,0)) -> 691716.4 | I5: =+INDEX('[7]Budget révisé'!$A$2:$AO$496,MATCH($A5,'[7]Budget révisé'!$A$2:$A$496,0),MATCH(I$2,'[7]Budget révisé'!$A$2:$AO$2,0)) -> 691716.4 | L5: =-SUMIFS([7]BV_Data_An_Cour!$O:$O,[7]BV_Data_An_Cour!$X:$X,"Oui",[7]BV_Data_An_Cour!$U:$U,$B5) -> 2741022.2 | Q5: =-SUMIFS([7]BV_Data_An_Prec!$O:$O,[7]BV_Data_An_Prec!$X:$X,"Oui",[7]BV_Data_An_Prec!$U:$U,$B5) -> 3203016.8 | V5: SERVICE | W5: 0.225
A6: =+B6&C6 -> Véhicules neufsAutos détail | B6: =+$K$1 -> Véhicules neufs | C6: Autos détail | D6: 35.76021 | E6: =IF(D6=0,0,F6/D6) -> 672.87672 | F6: =+INDEX('[7]Budget original'!$A$2:$AO$496,MATCH($A6,'[7]Budget original'!$A$2:$A$496,0),MATCH(F$2,'[7]Budget original'!$A$2:$AO$2,0)) -> 24062.213 | G6: 25 | H6: =IF(G6=0,0,I6/G6) -> 962.4885 | I6: =+INDEX('[7]Budget révisé'!$A$2:$AO$496,MATCH($A6,'[7]Budget révisé'!$A$2:$A$496,0),MATCH(I$2,'[7]Budget révisé'!$A$2:$AO$2,0)) -> 24062.213 | J6: =-SUMIFS([7]BV_Data_An_Cour!$O:$O,[7]BV_Data_An_Cour!$U:$U,$B6,[7]BV_Data_An_Cour!$V:$V,$C6,[7]BV_Data_An_Cour!$W:$W,J$2) -> 23 | K6: =IF(J6=0,0,L6/J6) -> 1164.0583 | L6: =-SUMIFS([7]BV_Data_An_Cour!$O:$O,[7]BV_Data_An_Cour!$U:$U,$B6,[7]BV_Data_An_Cour!$V:$V,$C6,[7]BV_Data_An_Cour!$W:$W,L$2) -> 26773.34 | M6: =J6-G6 -> -2 | N6: =L6-I6 -> 2711.1275 | O6: =-SUMIFS([7]BV_Data_An_Prec!$O:$O,[7]BV_Data_An_Prec!$U:$U,$B6,[7]BV_Data_An_Prec!$V:$V,$C6,[7]BV_Data_An_Prec!$W:$W,O$2) -> 54 | P6: =IF(O6=0,0,Q6/O6) -> 571.8013 | Q6: =-SUMIFS([7]BV_Data_An_Prec!$O:$O,[7]BV_Data_An_Prec!$U:$U,$B6,[7]BV_Data_An_Prec!$V:$V,$C6,[7]BV_Data_An_Prec!$W:$W,Q$2) -> 30877.27 | R6: =J6-O6 -> -31 | S6: =L6-Q6 -> -4103.93 | V6: CARROSSERIE | W6: 0.025
A7: =+B7&C7 -> Véhicules neufsCamions détail | B7: =+$K$1 -> Véhicules neufs | C7: Camions détail | D7: 48.034341 | E7: =IF(D7=0,0,F7/D7) -> 1199.5994 | F7: =+INDEX('[7]Budget original'!$A$2:$AO$496,MATCH($A7,'[7]Budget original'!$A$2:$A$496,0),MATCH(F$2,'[7]Budget original'!$A$2:$AO$2,0)) -> 57621.969 | G7: 34 | H7: =IF(G7=0,0,I7/G7) -> 1694.7638 | I7: =+INDEX('[7]Budget révisé'!$A$2:$AO$496,MATCH($A7,'[7]Budget révisé'!$A$2:$A$496,0),MATCH(I$2,'[7]Budget révisé'!$A$2:$AO$2,0)) -> 57621.969 | J7: =-SUMIFS([7]BV_Data_An_Cour!$O:$O,[7]BV_Data_An_Cour!$U:$U,$B7,[7]BV_Data_An_Cour!$V:$V,$C7,[7]BV_Data_An_Cour!$W:$W,J$2) -> 32 | K7: =IF(J7=0,0,L7/J7) -> 2323.7591 | L7: =-SUMIFS([7]BV_Data_An_Cour!$O:$O,[7]BV_Data_An_Cour!$U:$U,$B7,[7]BV_Data_An_Cour!$V:$V,$C7,[7]BV_Data_An_Cour!$W:$W,L$2) -> 74360.29 | M7: =J7-G7 -> -2 | N7: =L7-I7 -> 16738.321 | O7: =-SUMIFS([7]BV_Data_An_Prec!$O:$O,[7]BV_Data_An_Prec!$U:$U,$B7,[7]BV_Data_An_Prec!$V:$V,$C7,[7]BV_Data_An_Prec!$W:$W,O$2) -> 23 | P7: =IF(O7=0,0,Q7/O7) -> 995.91391 | Q7: =-SUMIFS([7]BV_Data_An_Prec!$O:$O,[7]BV_Data_An_Prec!$U:$U,$B7,[7]BV_Data_An_Prec!$V:$V,$C7,[7]BV_Data_An_Prec!$W:$W,Q$2) -> 22906.02 | R7: =J7-O7 -> 9 | S7: =L7-Q7 -> 51454.27 | V7: PIECES | W7: 0.2
A8: =+B8&C8 -> Véhicules neufsSprinter | B8: =+$K$1 -> Véhicules neufs | C8: Sprinter | D8: 0 | E8: =IF(D8=0,0,F8/D8) -> 0 | F8: =+INDEX('[7]Budget original'!$A$2:$AO$496,MATCH($A8,'[7]Budget original'!$A$2:$A$496,0),MATCH(F$2,'[7]Budget original'!$A$2:$AO$2,0)) -> 0 | G8: 0 | H8: =IF(G8=0,0,I8/G8) -> 0 | I8: =+INDEX('[7]Budget révisé'!$A$2:$AO$496,MATCH($A8,'[7]Budget révisé'!$A$2:$A$496,0),MATCH(I$2,'[7]Budget révisé'!$A$2:$AO$2,0)) -> 0 | J8: =-SUMIFS([7]BV_Data_An_Cour!$O:$O,[7]BV_Data_An_Cour!$U:$U,$B8,[7]BV_Data_An_Cour!$V:$V,$C8,[7]BV_Data_An_Cour!$W:$W,J$2) -> 0 | K8: =IF(J8=0,0,L8/J8) -> 0 | L8: =-SUMIFS([7]BV_Data_An_Cour!$O:$O,[7]BV_Data_An_Cour!$U:$U,$B8,[7]BV_Data_An_Cour!$V:$V,$C8,[7]BV_Data_An_Cour!$W:$W,L$2) -> 0 | M8: =J8-G8 -> 0 | N8: =L8-I8 -> 0 | O8: =-SUMIFS([7]BV_Data_An_Prec!$O:$O,[7]BV_Data_An_Prec!$U:$U,$B8,[7]BV_Data_An_Prec!$V:$V,$C8,[7]BV_Data_An_Prec!$W:$W,O$2) -> 0 | P8: =IF(O8=0,0,Q8/O8) -> 0 | Q8: =-SUMIFS([7]BV_Data_An_Prec!$O:$O,[7]BV_Data_An_Prec!$U:$U,$B8,[7]BV_Data_An_Prec!$V:$V,$C8,[7]BV_Data_An_Prec!$W:$W,Q$2) -> 0 | R8: =J8-O8 -> 0 | S8: =L8-Q8 -> 0 | W8: =SUM(W3:W7) -> 1
A9: =+B9&C9 -> Véhicules neufsMoto détail | B9: =+$K$1 -> Véhicules neufs | C9: Moto détail | D9: 0 | E9: =IF(D9=0,0,F9/D9) -> 0 | F9: =+INDEX('[7]Budget original'!$A$2:$AO$496,MATCH($A9,'[7]Budget original'!$A$2:$A$496,0),MATCH(F$2,'[7]Budget original'!$A$2:$AO$2,0)) -> 0 | G9: 0 | H9: =IF(G9=0,0,I9/G9) -> 0 | I9: =+INDEX('[7]Budget révisé'!$A$2:$AO$496,MATCH($A9,'[7]Budget révisé'!$A$2:$A$496,0),MATCH(I$2,'[7]Budget révisé'!$A$2:$AO$2,0)) -> 0 | J9: =-SUMIFS([7]BV_Data_An_Cour!$O:$O,[7]BV_Data_An_Cour!$U:$U,$B9,[7]BV_Data_An_Cour!$V:$V,$C9,[7]BV_Data_An_Cour!$W:$W,J$2) -> 0 | K9: =IF(J9=0,0,L9/J9) -> 0 | L9: =-SUMIFS([7]BV_Data_An_Cour!$O:$O,[7]BV_Data_An_Cour!$U:$U,$B9,[7]BV_Data_An_Cour!$V:$V,$C9,[7]BV_Data_An_Cour!$W:$W,L$2) -> 0 | M9: =J9-G9 -> 0 | N9: =L9-I9 -> 0 | O9: =-SUMIFS([7]BV_Data_An_Prec!$O:$O,[7]BV_Data_An_Prec!$U:$U,$B9,[7]BV_Data_An_Prec!$V:$V,$C9,[7]BV_Data_An_Prec!$W:$W,O$2) -> 0 | P9: =IF(O9=0,0,Q9/O9) -> 0 | Q9: =-SUMIFS([7]BV_Data_An_Prec!$O:$O,[7]BV_Data_An_Prec!$U:$U,$B9,[7]BV_Data_An_Prec!$V:$V,$C9,[7]BV_Data_An_Prec!$W:$W,Q$2) -> 0 | R9: =J9-O9 -> 0 | S9: =L9-Q9 -> 0
A10: =+B10&C10 -> Véhicules neufs[...] | B10: =+$K$1 -> Véhicules neufs | C10: [...] | D10: 0 | E10: =IF(D10=0,0,F10/D10) -> 0 | F10: =+INDEX('[7]Budget original'!$A$2:$AO$496,MATCH($A10,'[7]Budget original'!$A$2:$A$496,0),MATCH(F$2,'[7]Budget original'!$A$2:$AO$2,0)) -> 0 | G10: 0 | H10: =IF(G10=0,0,I10/G10) -> 0 | I10: =+INDEX('[7]Budget révisé'!$A$2:$AO$496,MATCH($A10,'[7]Budget révisé'!$A$2:$A$496,0),MATCH(I$2,'[7]Budget révisé'!$A$2:$AO$2,0)) -> 0 | J10: =-SUMIFS([7]BV_Data_An_Cour!$O:$O,[7]BV_Data_An_Cour!$U:$U,$B10,[7]BV_Data_An_Cour!$V:$V,$C10,[7]BV_Data_An_Cour!$W:$W,J$2) -> 0 | K10: =IF(J10=0,0,L10/J10) -> 0 | L10: =-SUMIFS([7]BV_Data_An_Cour!$O:$O,[7]BV_Data_An_Cour!$U:$U,$B10,[7]BV_Data_An_Cour!$V:$V,$C10,[7]BV_Data_An_Cour!$W:$W,L$2) -> 0 | M10: =J10-G10 -> 0 | N10: =L10-I10 -> 0 | O10: =-SUMIFS([7]BV_Data_An_Prec!$O:$O,[7]BV_Data_An_Prec!$U:$U,$B10,[7]BV_Data_An_Prec!$V:$V,$C10,[7]BV_Data_An_Prec!$W:$W,O$2) -> 0 | P10: =IF(O10=0,0,Q10/O10) -> 0 | Q10: =-SUMIFS([7]BV_Data_An_Prec!$O:$O,[7]BV_Data_An_Prec!$U:$U,$B10,[7]BV_Data_An_Prec!$V:$V,$C10,[7]BV_Data_An_Prec!$W:$W,Q$2) -> 0 | R10: =J10-O10 -> 0 | S10: =L10-Q10 -> 0
A11: =+B11&C11 -> Véhicules neufs[...] | B11: =+$K$1 -> Véhicules neufs | C11: [...] | D11: 0 | E11: =IF(D11=0,0,F11/D11) -> 0 | F11: =+INDEX('[7]Budget original'!$A$2:$AO$496,MATCH($A11,'[7]Budget original'!$A$2:$A$496,0),MATCH(F$2,'[7]Budget original'!$A$2:$AO$2,0)) -> 0 | G11: 0 | H11: =IF(G11=0,0,I11/G11) -> 0 | I11: =+INDEX('[7]Budget révisé'!$A$2:$AO$496,MATCH($A11,'[7]Budget révisé'!$A$2:$A$496,0),MATCH(I$2,'[7]Budget révisé'!$A$2:$AO$2,0)) -> 0 | J11: =-SUMIFS([7]BV_Data_An_Cour!$O:$O,[7]BV_Data_An_Cour!$U:$U,$B11,[7]BV_Data_An_Cour!$V:$V,$C11,[7]BV_Data_An_Cour!$W:$W,J$2) -> 0 | K11: =IF(J11=0,0,L11/J11) -> 0 | L11: =-SUMIFS([7]BV_Data_An_Cour!$O:$O,[7]BV_Data_An_Cour!$U:$U,$B11,[7]BV_Data_An_Cour!$V:$V,$C11,[7]BV_Data_An_Cour!$W:$W,L$2) -> 0 | M11: =J11-G11 -> 0 | N11: =L11-I11 -> 0 | O11: =-SUMIFS([7]BV_Data_An_Prec!$O:$O,[7]BV_Data_An_Prec!$U:$U,$B11,[7]BV_Data_An_Prec!$V:$V,$C11,[7]BV_Data_An_Prec!$W:$W,O$2) -> 0 | P11: =IF(O11=0,0,Q11/O11) -> 0 | Q11: =-SUMIFS([7]BV_Data_An_Prec!$O:$O,[7]BV_Data_An_Prec!$U:$U,$B11,[7]BV_Data_An_Prec!$V:$V,$C11,[7]BV_Data_An_Prec!$W:$W,Q$2) -> 0 | R11: =J11-O11 -> 0 | S11: =L11-Q11 -> 0
A12: =+B12&C12 -> Véhicules neufs[...] | B12: =+$K$1 -> Véhicules neufs | C12: [...] | D12: 0 | E12: =IF(D12=0,0,F12/D12) -> 0 | F12: =+INDEX('[7]Budget original'!$A$2:$AO$496,MATCH($A12,'[7]Budget original'!$A$2:$A$496,0),MATCH(F$2,'[7]Budget original'!$A$2:$AO$2,0)) -> 0 | G12: 0 | H12: =IF(G12=0,0,I12/G12) -> 0 | I12: =+INDEX('[7]Budget révisé'!$A$2:$AO$496,MATCH($A12,'[7]Budget révisé'!$A$2:$A$496,0),MATCH(I$2,'[7]Budget révisé'!$A$2:$AO$2,0)) -> 0 | J12: =-SUMIFS([7]BV_Data_An_Cour!$O:$O,[7]BV_Data_An_Cour!$U:$U,$B12,[7]BV_Data_An_Cour!$V:$V,$C12,[7]BV_Data_An_Cour!$W:$W,J$2) -> 0 | K12: =IF(J12=0,0,L12/J12) -> 0 | L12: =-SUMIFS([7]BV_Data_An_Cour!$O:$O,[7]BV_Data_An_Cour!$U:$U,$B12,[7]BV_Data_An_Cour!$V:$V,$C12,[7]BV_Data_An_Cour!$W:$W,L$2) -> 0 | M12: =J12-G12 -> 0 | N12: =L12-I12 -> 0 | O12: =-SUMIFS([7]BV_Data_An_Prec!$O:$O,[7]BV_Data_An_Prec!$U:$U,$B12,[7]BV_Data_An_Prec!$V:$V,$C12,[7]BV_Data_An_Prec!$W:$W,O$2) -> 0 | P12: =IF(O12=0,0,Q12/O12) -> 0 | Q12: =-SUMIFS([7]BV_Data_An_Prec!$O:$O,[7]BV_Data_An_Prec!$U:$U,$B12,[7]BV_Data_An_Prec!$V:$V,$C12,[7]BV_Data_An_Prec!$W:$W,Q$2) -> 0 | R12: =J12-O12 -> 0 | S12: =L12-Q12 -> 0
A13: =+B13&C13 -> Véhicules neufsTotal Neufs | B13: =+$K$1 -> Véhicules neufs | C13: Total Neufs | D13: =+SUM(D6:D12) -> 83.79455 | E13: =IF(D13<=0,0,F13/D13) -> 974.81496 | F13: =+SUM(F6:F12) -> 81684.181 | G13: =+SUM(G6:G12) -> 59 | H13: =IF(G13<=0,0,I13/G13) -> 1384.4776 | I13: =+SUM(I6:I12) -> 81684.181 | J13: =+SUM(J6:J12) -> 55 | K13: =IF(J13<=0,0,L13/J13) -> 1838.7933 | L13: =+SUM(L6:L12) -> 101133.63 | M13: =+SUM(M6:M12) -> -4 | N13: =+SUM(N6:N12) -> 19449.449 | O13: =+SUM(O6:O12) -> 77 | P13: =IF(O13<=0,0,Q13/O13) -> 698.48429 | Q13: =+SUM(Q6:Q12) -> 53783.29 | R13: =+SUM(R6:R12) -> -22 | S13: =+SUM(S6:S12) -> 47350.34
A14: =+B14&C14 -> Véhicules neufs | B14: =+$K$1 -> Véhicules neufs | M14: =IF(G13=0,0,M13/G13) -> -0.06779661 | N14: =IF(I13=0,0,N13/I13) -> 0.23810545 | R14: =R13/O13 -> -0.28571429 | S14: =IF(Q13=0,0,(S13/Q13)) -> 0.88039129
A15: =+B15&C15 -> Véhicules neufsEx-Démos et courtoisies | B15: =+$K$1 -> Véhicules neufs | C15: Ex-Démos et courtoisies | D15: 8.7335165 | E15: =IF(D15=0,0,F15/D15) -> 556.61157 | F15: =+INDEX('[7]Budget original'!$A$2:$AO$496,MATCH($A15,'[7]Budget original'!$A$2:$A$496,0),MATCH(F$2,'[7]Budget original'!$A$2:$AO$2,0)) -> 4861.1763 | G15: 6 | H15: =IF(G15=0,0,I15/G15) -> 810.19606 | I15: =+INDEX('[7]Budget révisé'!$A$2:$AO$496,MATCH($A15,'[7]Budget révisé'!$A$2:$A$496,0),MATCH(I$2,'[7]Budget révisé'!$A$2:$AO$2,0)) -> 4861.1763 | J15: =-SUMIFS([7]BV_Data_An_Cour!$O:$O,[7]BV_Data_An_Cour!$U:$U,$B15,[7]BV_Data_An_Cour!$V:$V,$C15,[7]BV_Data_An_Cour!$W:$W,J$2) -> 9 | K15: =IF(J15=0,0,L15/J15) -> 1229.3844 | L15: =-SUMIFS([7]BV_Data_An_Cour!$O:$O,[7]BV_Data_An_Cour!$U:$U,$B15,[7]BV_Data_An_Cour!$V:$V,$C15,[7]BV_Data_An_Cour!$W:$W,L$2) -> 11064.46 | M15: =J15-G15 -> 3 | N15: =L15-I15 -> 6203.2837 | O15: =-SUMIFS([7]BV_Data_An_Prec!$O:$O,[7]BV_Data_An_Prec!$U:$U,$B15,[7]BV_Data_An_Prec!$V:$V,$C15,[7]BV_Data_An_Prec!$W:$W,O$2) -> 11 | P15: =IF(O15=0,0,Q15/O15) -> 30.737273 | Q15: =-SUMIFS([7]BV_Data_An_Prec!$O:$O,[7]BV_Data_An_Prec!$U:$U,$B15,[7]BV_Data_An_Prec!$V:$V,$C15,[7]BV_Data_An_Prec!$W:$W,Q$2) -> 338.11 | R15: =J15-O15 -> -2 | S15: =L15-Q15 -> 10726.35 | V15: =3125-L15 -> -7939.46
A16: =+B16&C16 -> Véhicules neufs | B16: =+$K$1 -> Véhicules neufs
A17: =+B17&C17 -> Véhicules neufsFlottes | B17: =+$K$1 -> Véhicules neufs | C17: Flottes | D17: 3.1998137 | E17: =IF(D17=0,0,F17/D17) -> 563.63318 | F17: =+INDEX('[7]Budget original'!$A$2:$AO$496,MATCH($A17,'[7]Budget original'!$A$2:$A$496,0),MATCH(F$2,'[7]Budget original'!$A$2:$AO$2,0)) -> 1803.5212 | G17: 2 | H17: =IF(G17=0,0,I17/G17) -> 901.76059 | I17: =+INDEX('[7]Budget révisé'!$A$2:$AO$496,MATCH($A17,'[7]Budget révisé'!$A$2:$A$496,0),MATCH(I$2,'[7]Budget révisé'!$A$2:$AO$2,0)) -> 1803.5212 | J17: =-SUMIFS([7]BV_Data_An_Cour!$O:$O,[7]BV_Data_An_Cour!$U:$U,$B17,[7]BV_Data_An_Cour!$V:$V,$C17,[7]BV_Data_An_Cour!$W:$W,J$2) -> 1 | K17: =IF(J17=0,0,L17/J17) -> 1036 | L17: =-SUMIFS([7]BV_Data_An_Cour!$O:$O,[7]BV_Data_An_Cour!$U:$U,$B17,[7]BV_Data_An_Cour!$V:$V,$C17,[7]BV_Data_An_Cour!$W:$W,L$2) -> 1036 | M17: =J17-G17 -> -1 | N17: =L17-I17 -> -767.52117 | O17: =-SUMIFS([7]BV_Data_An_Prec!$O:$O,[7]BV_Data_An_Prec!$U:$U,$B17,[7]BV_Data_An_Prec!$V:$V,$C17,[7]BV_Data_An_Prec!$W:$W,O$2) -> 3 | P17: =IF(O17=0,0,Q17/O17) -> 1624.1633 | Q17: =-SUMIFS([7]BV_Data_An_Prec!$O:$O,[7]BV_Data_An_Prec!$U:$U,$B17,[7]BV_Data_An_Prec!$V:$V,$C17,[7]BV_Data_An_Prec!$W:$W,Q$2) -> 4872.49 | R17: =J17-O17 -> -2 | S17: =L17-Q17 -> -3836.49
A18: =+B18&C18 -> Véhicules neufs | B18: =+$K$1 -> Véhicules neufs
A19: =+B19&C19 -> Véhicules neufsRachat bail | B19: =+$K$1 -> Véhicules neufs | C19: Rachat bail | D19: 0 | E19: =IF(D19=0,0,F19/D19) -> 0 | F19: =+INDEX('[7]Budget original'!$A$2:$AO$496,MATCH($A19,'[7]Budget original'!$A$2:$A$496,0),MATCH(F$2,'[7]Budget original'!$A$2:$AO$2,0)) -> 5000 | G19: 0 | H19: =IF(G19=0,0,I19/G19) -> 0 | I19: =+INDEX('[7]Budget révisé'!$A$2:$AO$496,MATCH($A19,'[7]Budget révisé'!$A$2:$A$496,0),MATCH(I$2,'[7]Budget révisé'!$A$2:$AO$2,0)) -> 5000 | L19: =-SUMIFS([7]BV_Data_An_Cour!$O:$O,[7]BV_Data_An_Cour!$U:$U,$B19,[7]BV_Data_An_Cour!$V:$V,$C19,[7]BV_Data_An_Cour!$W:$W,L$2) -> 7884.92 | N19: =L19-I19 -> 2884.92 | Q19: =-SUMIFS([7]BV_Data_An_Prec!$O:$O,[7]BV_Data_An_Prec!$U:$U,$B19,[7]BV_Data_An_Prec!$V:$V,$C19,[7]BV_Data_An_Prec!$W:$W,Q$2) -> 4014.85 | R19: =O19-K19 -> 0 | S19: =L19-Q19 -> 3870.07 | U19: Budget | V19: =G13+G15+G17 -> 67 | W19: =I13+I15+I17 -> 88348.879 | X19: =W19/V19 -> 1318.64
A20: =+B20&C20 -> Véhicules neufs | B20: =+$K$1 -> Véhicules neufs | U20: 2021 | V20: =J13+J15+J17 -> 65 | W20: =L13+L15+L17 -> 113234.09 | X20: =W20/V20 -> 1742.0629
A21: =+B21&C21 -> Véhicules neufsRev. Finances | B21: =+$K$1 -> Véhicules neufs | C21: Rev. Finances | D21: 0 | E21: =IF(D21=0,0,F21/D21) -> 0 | F21: =+INDEX('[7]Budget original'!$A$2:$AO$496,MATCH($A21,'[7]Budget original'!$A$2:$A$496,0),MATCH(F$2,'[7]Budget original'!$A$2:$AO$2,0)) -> 6133.0487 | G21: 0 | H21: =IF(G21=0,0,I21/G21) -> 0 | I21: =+INDEX('[7]Budget révisé'!$A$2:$AO$496,MATCH($A21,'[7]Budget révisé'!$A$2:$A$496,0),MATCH(I$2,'[7]Budget révisé'!$A$2:$AO$2,0)) -> 6133.0487 | K21: =IF(J13=0,0,L21/(J13+J15)) -> 21.57375 | L21: =-SUMIFS([7]BV_Data_An_Cour!$O:$O,[7]BV_Data_An_Cour!$U:$U,$B21,[7]BV_Data_An_Cour!$V:$V,$C21,[7]BV_Data_An_Cour!$W:$W,L$2) -> 1380.72 | N21: =L21-I21 -> -4752.3287 | P21: =IF(O13=0,0,Q21/(O13+O15)) -> 66.863523 | Q21: =-SUMIFS([7]BV_Data_An_Prec!$O:$O,[7]BV_Data_An_Prec!$U:$U,$B21,[7]BV_Data_An_Prec!$V:$V,$C21,[7]BV_Data_An_Prec!$W:$W,Q$2) -> 5883.99 | R21: =O21-K21 -> -21.57375 | S21: =L21-Q21 -> -4503.27
A22: =+B22&C22 -> Véhicules neufsRev. Protections | B22: =+$K$1 -> Véhicules neufs | C22: Rev. Protections | D22: 0 | E22: =IF(D22=0,0,F22/D22) -> 0 | F22: =+INDEX('[7]Budget original'!$A$2:$AO$496,MATCH($A22,'[7]Budget original'!$A$2:$A$496,0),MATCH(F$2,'[7]Budget original'!$A$2:$AO$2,0)) -> 48065.986 | G22: 0 | H22: =IF(G22=0,0,I22/G22) -> 0 | I22: =+INDEX('[7]Budget révisé'!$A$2:$AO$496,MATCH($A22,'[7]Budget révisé'!$A$2:$A$496,0),MATCH(I$2,'[7]Budget révisé'!$A$2:$AO$2,0)) -> 48065.986 | K22: =IF(J13=0,0,L22/(J13+J15)) -> 878.27656 | L22: =-SUMIFS([7]BV_Data_An_Cour!$O:$O,[7]BV_Data_An_Cour!$U:$U,$B22,[7]BV_Data_An_Cour!$V:$V,$C22,[7]BV_Data_An_Cour!$W:$W,L$2) -> 56209.7 | N22: =L22-I22 -> 8143.7136 | P22: =IF(O13=0,0,Q22/(O13+O15)) -> 390.76841 | Q22: =-SUMIFS([7]BV_Data_An_Prec!$O:$O,[7]BV_Data_An_Prec!$U:$U,$B22,[7]BV_Data_An_Prec!$V:$V,$C22,[7]BV_Data_An_Prec!$W:$W,Q$2) -> 34387.62 | R22: =O22-K22 -> -878.27656 | S22: =L22-Q22 -> 21822.08
