Workbook
Name _Dates_Conc: [1]Dealers!$BF$37:$KA$63
Name _scen: '[1]Scen & Sens'!$E$26
Name _scen1: '[1]Scen & Sens'!$E$27
Name _scen2: '[1]Scen & Sens'!$E$28
Name _SCenarios: '[1]Scen & Sens'!$J$26:$O$26
Name _Sens1: '[1]Scen & Sens'!$F$9
Name _Sens2: '[1]Scen & Sens'!$F$10
Name _sensRes1: '[1]Scen & Sens'!$E$15
Name _sensRes2: '[1]Scen & Sens'!$E$16
Name _sensRes3: '[1]Scen & Sens'!$E$17
Name _sensRes4: '[1]Scen & Sens'!$E$18
Name _sensRes5: '[1]Scen & Sens'!$E$19
Name _sensRes6: '[1]Scen & Sens'!$E$20
Name _sensRes7: '[1]Scen & Sens'!$E$21
Name DateRange: [1]Volkswagen!$BF$6:$DY$6
Name Monetary_Unit: [1]Parameters!$B$15
Name Months: [1]Parameters!$E$9:$E$20
Name Rng_Dealers_Names: [1]!Tbl_Dealers[Dealer Name]
Name Rng_Dlr_Dates: [1]!Tbl_V_Dlr_Dates[Date]
Name Titre: [1]Front!$A$9

Sheet Paramètre
B3: VOLKS QUARTER | C3: Volks T2 2022
B6: BUDGET | F6: BUDGET RÉVISÉ | J6: ACTUAL | N6: LAST YEAR
B7: Ventes | C7: Profits bruts | D7: BAIIA | E7: EBIT | F7: Ventes | G7: Profits bruts | H7: BAIIA | I7: EBIT | J7: Ventes | K7: Profits bruts | L7: BAIIA | M7: EBIT | N7: Ventes | O7: Profits bruts | P7: BAIIA | Q7: EBIT
A8: CTRL | B8: =+B9-B10 -> 0 | C8: =+C9-C10 -> 0 | D8: =+D9-D10 -> 0 | E8: =+E9-E10 -> 0 | F8: =+F9-F10 -> 0 | G8: =+G9-G10 -> 0 | H8: =+H9-H10 -> 0 | I8: =+I9-I10 -> 0 | ... Q8: =+Q9-Q10 -> 0
A9: CONSO | B9: =+Conso!$Z$405 -> 16697118 | C9: =+Conso!$Z$406 -> 2208574.1 | D9: =+Conso!$Z$482 -> 799210.12 | E9: =+Conso!$Z$497 -> 775508.74 | F9: =+Conso!$AC$405 -> 16697118 | G9: =+Conso!$AC$406 -> 2208574.1 | H9: =+Conso!$AC$482 -> 799210.12 | I9: =+Conso!$AC$497 -> 775508.74 | J9: =+Conso!$AF$405 -> 14021677 | K9: =+Conso!$AF$406 -> 2196862.7 | L9: =+Conso!$AF$482 -> 639346.24 | M9: =+Conso!$AF$497 -> 625122.37 | N9: =+Conso!$AL$405 -> 17043863 | O9: =+Conso!$AL$406 -> 2012370.4 | P9: =+Conso!$AL$482 -> 730595.95 | Q9: =+Conso!$AL$497 -> 749828.63
A10: TOTAL | B10: =+SUM(B11:B13) -> 16697118 | C10: =+SUM(C11:C13) -> 2208574.1 | D10: =+SUM(D11:D13) -> 799210.12 | E10: =+SUM(E11:E13) -> 775508.74 | F10: =+SUM(F11:F13) -> 16697118 | G10: =+SUM(G11:G13) -> 2208574.1 | H10: =+SUM(H11:H13) -> 799210.12 | I10: =+SUM(I11:I13) -> 775508.74 | ... Q10: =+SUM(Q11:Q13) -> 749828.63
A11: AUDI 1 | B11: =+'VW 2022-04'!$Z$405 -> 5458038.9 | C11: =+'VW 2022-04'!$Z$406 -> 748131.55 | D11: =+'VW 2022-04'!$Z$482 -> 268136.2 | E11: =+'VW 2022-04'!$Z$497 -> 260233.46 | F11: =+'VW 2022-04'!$AC$405 -> 5458038.9 | G11: =+'VW 2022-04'!$AC$406 -> 748131.55 | H11: =+'VW 2022-04'!$AC$482 -> 268136.2 | I11: =+'VW 2022-04'!$AC$497 -> 260233.46 | J11: =+'VW 2022-04'!$AF$405 -> 3776991 | K11: =+'VW 2022-04'!$AF$406 -> 649075.44 | L11: =+'VW 2022-04'!$AF$482 -> 152748.42 | M11: =+'VW 2022-04'!$AF$497 -> 148007.13 | N11: =+'VW 2022-04'!$AL$405 -> 5242313.3 | O11: =+'VW 2022-04'!$AL$406 -> 640912.74 | P11: =+'VW 2022-04'!$AL$482 -> 194923.31 | Q11: =+'VW 2022-04'!$AL$497 -> 187231.25
A12: AUDI 2 | B12: =+'VW 2022-05'!$Z$405 -> 6023595.8 | C12: =+'VW 2022-05'!$Z$406 -> 766209.11 | D12: =+'VW 2022-05'!$Z$482 -> 291103.22 | E12: =+'VW 2022-05'!$Z$497 -> 283199.85 | F12: =+'VW 2022-05'!$AC$405 -> 6023595.8 | G12: =+'VW 2022-05'!$AC$406 -> 766209.11 | H12: =+'VW 2022-05'!$AC$482 -> 291103.22 | I12: =+'VW 2022-05'!$AC$497 -> 283199.85 | J12: =+'VW 2022-05'!$AF$405 -> 4721471.7 | K12: =+'VW 2022-05'!$AF$406 -> 749925.49 | L12: =+'VW 2022-05'!$AF$482 -> 218438.19 | M12: =+'VW 2022-05'!$AF$497 -> 213696.9 | N12: =+'VW 2022-05'!$AL$405 -> 5900774.7 | O12: =+'VW 2022-05'!$AL$406 -> 685728.85 | P12: =+'VW 2022-05'!$AL$482 -> 267836.32 | Q12: =+'VW 2022-05'!$AL$497 -> 281298.69
A13: AUDI 3 | B13: =+'VW 2022-06'!$Z$405 -> 5215482.8 | C13: =+'VW 2022-06'!$Z$406 -> 694233.43 | D13: =+'VW 2022-06'!$Z$482 -> 239970.71 | E13: =+'VW 2022-06'!$Z$497 -> 232075.44 | F13: =+'VW 2022-06'!$AC$405 -> 5215482.8 | G13: =+'VW 2022-06'!$AC$406 -> 694233.43 | H13: =+'VW 2022-06'!$AC$482 -> 239970.71 | I13: =+'VW 2022-06'!$AC$497 -> 232075.44 | J13: =+'VW 2022-06'!$AF$405 -> 5523213.9 | K13: =+'VW 2022-06'!$AF$406 -> 797861.77 | L13: =+'VW 2022-06'!$AF$482 -> 268159.63 | M13: =+'VW 2022-06'!$AF$497 -> 263418.34 | N13: =+'VW 2022-06'!$AL$405 -> 5900774.7 | O13: =+'VW 2022-06'!$AL$406 -> 685728.85 | P13: =+'VW 2022-06'!$AL$482 -> 267836.32 | Q13: =+'VW 2022-06'!$AL$497 -> 281298.69

Sheet Conso
C1: Conso | K1: Véhicules neufs | S1: =CONCATENATE("Réalisé"," ",Paramètre!$C$2," ",Paramètre!$C$3) -> Réalisé Volks T2 2022 | V1: BUDGET | W1: RÉVISÉ | X1: ACTUAL | Y1: LY
D2: X | E2: O | F2: U | G2: X | H2: O | I2: U
D3: BUDGET ORIGINAL | G3: BUDGET REVISE | J3: RÉALISATION | M3: ÉCART réel / révisé | O3: ANNÉE PRÉCÉDENTE | R3: ÉCART réel / original
D4: UNITE | E4: $P/UNITÉ | F4: $PROFITS | G4: UNITE | H4: $P/UNITÉ | I4: $PROFITS | J4: UNITE | K4: $P/UNITE | L4: $PROFITS | M4: UNITÉ | N4: $PROFITS | O4: UNITE | P4: $P/UNITE | Q4: $PROFITS | R4: UNITE | S4: $PROFITS | V4: =+SUM(V5:V398) -> 0 | W4: =+SUM(W5:W398) -> 0 | X4: =+SUM(X5:X398) -> 0 | Y4: =+SUM(Y5:Y398) -> 0
A5: =+B5&C5 -> Véhicules neufsVentes nettes | B5: =+$K$1 -> Véhicules neufs | C5: Ventes nettes | F5: =+SUM(START:END!F5) -> 10000991 | I5: =+SUM(START:END!I5) -> 10000991 | L5: =+SUM(START:END!L5) -> 7004013.6 | Q5: =+SUM(START:END!Q5) -> 10902850
A6: =+B6&C6 -> Véhicules neufsAutos détail | B6: =+$K$1 -> Véhicules neufs | C6: Autos détail | D6: =+SUM(START:END!D6) -> 51.007229 | E6: =IF(D6=0,0,F6/D6) -> 1450.6298 | F6: =+SUM(START:END!F6) -> 73992.604 | G6: =+SUM(START:END!G6) -> 51.007229 | H6: =IF(G6=0,0,I6/G6) -> 1450.6298 | I6: =+SUM(START:END!I6) -> 73992.604 | J6: =+SUM(START:END!J6) -> 25 | K6: =IF(J6=0,0,L6/J6) -> 2750.1316 | L6: =+SUM(START:END!L6) -> 68753.29 | M6: =J6-G6 -> -26.007229 | N6: =L6-I6 -> -5239.3143 | O6: =+SUM(START:END!O6) -> 74 | P6: =IF(O6=0,0,Q6/O6) -> 843.59338 | Q6: =+SUM(START:END!Q6) -> 62425.91 | R6: =J6-O6 -> -49 | S6: =L6-Q6 -> 6327.38
A7: =+B7&C7 -> Véhicules neufsCamions détail | B7: =+$K$1 -> Véhicules neufs | C7: Camions détail | D7: =+SUM(START:END!D7) -> 176.09639 | E7: =IF(D7=0,0,F7/D7) -> 2081.8276 | F7: =+SUM(START:END!F7) -> 366602.31 | G7: =+SUM(START:END!G7) -> 176.09639 | H7: =IF(G7=0,0,I7/G7) -> 2081.8276 | I7: =+SUM(START:END!I7) -> 366602.31 | J7: =+SUM(START:END!J7) -> 101 | K7: =IF(J7=0,0,L7/J7) -> 3759.3914 | L7: =+SUM(START:END!L7) -> 379698.53 | M7: =J7-G7 -> -75.096386 | N7: =L7-I7 -> 13096.217 | O7: =+SUM(START:END!O7) -> 157 | P7: =IF(O7=0,0,Q7/O7) -> 2137.3047 | Q7: =+SUM(START:END!Q7) -> 335556.84 | R7: =J7-O7 -> -56 | S7: =L7-Q7 -> 44141.69
A8: =+B8&C8 -> Véhicules neufsSprinter | B8: =+$K$1 -> Véhicules neufs | C8: Sprinter | D8: =+SUM(START:END!D8) -> 0 | E8: =IF(D8=0,0,F8/D8) -> 0 | F8: =+SUM(START:END!F8) -> 0 | G8: =+SUM(START:END!G8) -> 0 | H8: =IF(G8=0,0,I8/G8) -> 0 | I8: =+SUM(START:END!I8) -> 0 | J8: =+SUM(START:END!J8) -> 0 | K8: =IF(J8=0,0,L8/J8) -> 0 | L8: =+SUM(START:END!L8) -> 0 | M8: =J8-G8 -> 0 | N8: =L8-I8 -> 0 | O8: =+SUM(START:END!O8) -> 0 | P8: =IF(O8=0,0,Q8/O8) -> 0 | Q8: =+SUM(START:END!Q8) -> 0 | R8: =J8-O8 -> 0 | S8: =L8-Q8 -> 0
A9: =+B9&C9 -> Véhicules neufsMoto détail | B9: =+$K$1 -> Véhicules neufs | C9: Moto détail | D9: =+SUM(START:END!D9) -> 0 | E9: =IF(D9=0,0,F9/D9) -> 0 | F9: =+SUM(START:END!F9) -> 0 | G9: =+SUM(START:END!G9) -> 0 | H9: =IF(G9=0,0,I9/G9) -> 0 | I9: =+SUM(START:END!I9) -> 0 | J9: =+SUM(START:END!J9) -> 0 | K9: =IF(J9=0,0,L9/J9) -> 0 | L9: =+SUM(START:END!L9) -> 0 | M9: =J9-G9 -> 0 | N9: =L9-I9 -> 0 | O9: =+SUM(START:END!O9) -> 0 | P9: =IF(O9=0,0,Q9/O9) -> 0 | Q9: =+SUM(START:END!Q9) -> 0 | R9: =J9-O9 -> 0 | S9: =L9-Q9 -> 0
A10: =+B10&C10 -> Véhicules neufs[...] | B10: =+$K$1 -> Véhicules neufs | C10: [...] | D10: =+SUM(START:END!D10) -> 0 | E10: =IF(D10=0,0,F10/D10) -> 0 | F10: =+SUM(START:END!F10) -> 0 | G10: =+SUM(START:END!G10) -> 0 | H10: =IF(G10=0,0,I10/G10) -> 0 | I10: =+SUM(START:END!I10) -> 0 | J10: =+SUM(START:END!J10) -> 0 | K10: =IF(J10=0,0,L10/J10) -> 0 | L10: =+SUM(START:END!L10) -> 0 | M10: =J10-G10 -> 0 | N10: =L10-I10 -> 0 | O10: =+SUM(START:END!O10) -> 0 | P10: =IF(O10=0,0,Q10/O10) -> 0 | Q10: =+SUM(START:END!Q10) -> 0 | R10: =J10-O10 -> 0 | S10: =L10-Q10 -> 0
A11: =+B11&C11 -> Véhicules neufs[...] | B11: =+$K$1 -> Véhicules neufs | C11: [...] | D11: =+SUM(START:END!D11) -> 0 | E11: =IF(D11=0,0,F11/D11) -> 0 | F11: =+SUM(START:END!F11) -> 0 | G11: =+SUM(START:END!G11) -> 0 | H11: =IF(G11=0,0,I11/G11) -> 0 | I11: =+SUM(START:END!I11) -> 0 | J11: =+SUM(START:END!J11) -> 0 | K11: =IF(J11=0,0,L11/J11) -> 0 | L11: =+SUM(START:END!L11) -> 0 | M11: =J11-G11 -> 0 | N11: =L11-I11 -> 0 | O11: =+SUM(START:END!O11) -> 0 | P11: =IF(O11=0,0,Q11/O11) -> 0 | Q11: =+SUM(START:END!Q11) -> 0 | R11: =J11-O11 -> 0 | S11: =L11-Q11 -> 0
A12: =+B12&C12 -> Véhicules neufs[...] | B12: =+$K$1 -> Véhicules neufs | C12: [...] | D12: =+SUM(START:END!D12) -> 0 | E12: =IF(D12=0,0,F12/D12) -> 0 | F12: =+SUM(START:END!F12) -> 0 | G12: =+SUM(START:END!G12) -> 0 | H12: =IF(G12=0,0,I12/G12) -> 0 | I12: =+SUM(START:END!I12) -> 0 | J12: =+SUM(START:END!J12) -> 0 | K12: =IF(J12=0,0,L12/J12) -> 0 | L12: =+SUM(START:END!L12) -> 0 | M12: =J12-G12 -> 0 | N12: =L12-I12 -> 0 | O12: =+SUM(START:END!O12) -> 0 | P12: =IF(O12=0,0,Q12/O12) -> 0 | Q12: =+SUM(START:END!Q12) -> 0 | R12: =J12-O12 -> 0 | S12: =L12-Q12 -> 0
A13: =+B13&C13 -> Véhicules neufsTotal Neufs | B13: =+$K$1 -> Véhicules neufs | C13: Total Neufs | D13: =+SUM(D6:D12) -> 227.10361 | E13: =IF(D13<=0,0,F13/D13) -> 1940.0612 | F13: =+SUM(F6:F12) -> 440594.92 | G13: =+SUM(G6:G12) -> 227.10361 | H13: =IF(G13<=0,0,I13/G13) -> 1940.0612 | I13: =+SUM(I6:I12) -> 440594.92 | J13: =+SUM(J6:J12) -> 126 | K13: =IF(J13<=0,0,L13/J13) -> 3559.1414 | L13: =+SUM(L6:L12) -> 448451.82 | M13: =+SUM(M6:M12) -> -101.10361 | N13: =+SUM(N6:N12) -> 7856.9024 | O13: =+SUM(O6:O12) -> 231 | P13: =IF(O13<=0,0,Q13/O13) -> 1722.869 | Q13: =+SUM(Q6:Q12) -> 397982.75 | R13: =+SUM(R6:R12) -> -105 | S13: =+SUM(S6:S12) -> 50469.07 | V13: =+SUM(START:END!D13)-D13 -> 0 | W13: =+SUM(START:END!G13)-G13 -> 0 | X13: =+SUM(START:END!J13)-J13 -> 0 | Y13: =+SUM(START:END!O13)-O13 -> 0
A14: =+B14&C14 -> Véhicules neufs | B14: =+$K$1 -> Véhicules neufs | M14: =IF(G13=0,0,M13/G13) -> -0.44518717 | N14: =IF(I13=0,0,N13/I13) -> 0.017832485 | R14: =R13/O13 -> -0.45454545 | S14: =IF(Q13=0,0,(S13/Q13)) -> 0.1268122
A15: =+B15&C15 -> Véhicules neufsEx-Démos et courtoisies | B15: =+$K$1 -> Véhicules neufs | C15: Ex-Démos et courtoisies | D15: =+SUM(START:END!D15) -> 21.253012 | E15: =IF(D15=0,0,F15/D15) -> 1386.1016 | F15: =+SUM(START:END!F15) -> 29458.834 | G15: =+SUM(START:END!G15) -> 21.253012 | H15: =IF(G15=0,0,I15/G15) -> 1386.1016 | I15: =+SUM(START:END!I15) -> 29458.834 | J15: =+SUM(START:END!J15) -> 9 | K15: =IF(J15=0,0,L15/J15) -> 3915.0822 | L15: =+SUM(START:END!L15) -> 35235.74 | M15: =J15-G15 -> -12.253012 | N15: =L15-I15 -> 5776.9056 | O15: =+SUM(START:END!O15) -> 11 | P15: =IF(O15=0,0,Q15/O15) -> 2049.3845 | Q15: =+SUM(START:END!Q15) -> 22543.23 | R15: =J15-O15 -> -2 | S15: =L15-Q15 -> 12692.51 | V15: =+SUM(START:END!D15)-D15 -> 0 | W15: =+SUM(START:END!G15)-G15 -> 0 | X15: =+SUM(START:END!J15)-J15 -> 0 | Y15: =+SUM(START:END!O15)-O15 -> 0
A16: =+B16&C16 -> Véhicules neufs | B16: =+$K$1 -> Véhicules neufs
A17: =+B17&C17 -> Véhicules neufsFlottes | B17: =+$K$1 -> Véhicules neufs | C17: Flottes | D17: =+SUM(START:END!D17) -> 3.8230088 | E17: =IF(D17=0,0,F17/D17) -> 1938.8732 | F17: =+SUM(START:END!F17) -> 7412.3293 | G17: =+SUM(START:END!G17) -> 3.8230088 | H17: =IF(G17=0,0,I17/G17) -> 1938.8732 | I17: =+SUM(START:END!I17) -> 7412.3293 | J17: =+SUM(START:END!J17) -> 0 | K17: =IF(J17=0,0,L17/J17) -> 0 | L17: =+SUM(START:END!L17) -> 0 | M17: =J17-G17 -> -3.8230088 | N17: =L17-I17 -> -7412.3293 | O17: =+SUM(START:END!O17) -> 13 | P17: =IF(O17=0,0,Q17/O17) -> 2639.8062 | Q17: =+SUM(START:END!Q17) -> 34317.48 | R17: =J17-O17 -> -13 | S17: =L17-Q17 -> -34317.48 | V17: =+SUM(START:END!D17)-D17 -> 0 | W17: =+SUM(START:END!G17)-G17 -> 0 | X17: =+SUM(START:END!J17)-J17 -> 0 | Y17: =+SUM(START:END!O17)-O17 -> 0
A18: =+B18&C18 -> Véhicules neufs | B18: =+$K$1 -> Véhicules neufs
A19: =+B19&C19 -> Véhicules neufsRachat bail | B19: =+$K$1 -> Véhicules neufs | C19: Rachat bail | F19: =+SUM(START:END!F19) -> 25248.117 | I19: =+SUM(START:END!I19) -> 25248.117 | L19: =+SUM(START:END!L19) -> 34859.95 | N19: =L19-I19 -> 9611.8331 | Q19: =+SUM(START:END!Q19) -> 22670.95 | R19: =O19-K19 -> 0 | S19: =L19-Q19 -> 12189
A20: =+B20&C20 -> Véhicules neufs | B20: =+$K$1 -> Véhicules neufs
A21: =+B21&C21 -> Véhicules neufsRev. Finances | B21: =+$K$1 -> Véhicules neufs | C21: Rev. Finances | D21: 0 | E21: =IF(D21=0,0,F21/D21) -> 0 | F21: =+SUM(START:END!F21) -> 7431.7648 | G21: 0 | H21: =IF(G21=0,0,I21/G21) -> 0 | I21: =+SUM(START:END!I21) -> 7431.7648 | K21: =IF(J13=0,0,L21/(J13+J15)) -> 223.14963 | L21: =+SUM(START:END!L21) -> 30125.2 | N21: =L21-I21 -> 22693.435 | P21: =IF(O13=0,0,Q21/(O13+O15)) -> 26.407025 | Q21: =+SUM(START:END!Q21) -> 6390.5 | R21: =O21-K21 -> -223.14963 | S21: =L21-Q21 -> 23734.7
A22: =+B22&C22 -> Véhicules neufsRev. Protections | B22: =+$K$1 -> Véhicules neufs | C22: Rev. Protections | D22: 0 | E22: =IF(D22=0,0,F22/D22) -> 0 | F22: =+SUM(START:END!F22) -> 198752.21 | G22: 0 | H22: =IF(G22=0,0,I22/G22) -> 0 | I22: =+SUM(START:END!I22) -> 198752.21 | K22: =IF(J13=0,0,L22/(J13+J15)) -> 931.79037 | L22: =+SUM(START:END!L22) -> 125791.7 | N22: =L22-I22 -> -72960.505 | P22: =IF(O13=0,0,Q22/(O13+O15)) -> 764.76496 | Q22: =+SUM(START:END!Q22) -> 185073.12 | R22: =O22-K22 -> -931.79037 | S22: =L22-Q22 -> -59281.42
A23: =+B23&C23 -> Véhicules neufsRev. Autres | B23: =+$K$1 -> Véhicules neufs | C23: Rev. Autres | D23: 0 | E23: =IF(D23=0,0,F23/D23) -> 0 | F23: =+SUM(START:END!F23) -> 4919.1622 | G23: 0 | H23: =IF(G23=0,0,I23/G23) -> 0 | I23: =+SUM(START:END!I23) -> 4919.1622 | K23: =IF(J13=0,0,L23/(J13+J15)) -> 16.451185 | L23: =+SUM(START:END!L23) -> 2220.91 | N23: =L23-I23 -> -2698.2522 | P23: =IF(O13=0,0,Q23/(O13+O15)) -> 17.06219 | Q23: =+SUM(START:END!Q23) -> 4129.05 | R23: =O23-K23 -> -16.451185 | S23: =L23-Q23 -> -1908.14
A24: =+B24&C24 -> Véhicules neufsTotal F&I | B24: =+$K$1 -> Véhicules neufs | C24: Total F&I | D24: =+D15+D13 -> 248.35663 | E24: =IF(D24<=0,0,F24/D24) -> 850 | F24: =F21+F22+F23 -> 211103.13 | G24: =+G15+G13 -> 248.35663 | H24: =IF(G24<=0,0,I24/G24) -> 850 | I24: =I21+I22+I23 -> 211103.13 | J24: =+J15+J13 -> 135 | K24: =IF(J24<=0,0,L24/J24) -> 1171.3912 | L24: =L21+L22+L23 -> 158137.81 | M24: =J24-G24 -> -113.35663 | N24: =L24-I24 -> -52965.323 | O24: =+O15+O13 -> 242 | P24: =IF(O24<=0,0,Q24/O24) -> 808.23417 | Q24: =Q21+Q22+Q23 -> 195592.67 | S24: =L24-Q24 -> -37454.86 | V24: =+SUM(START:END!D24)-D24 -> 0 | W24: =+SUM(START:END!G24)-G24 -> 0 | X24: =+SUM(START:END!J24)-J24 -> 0 | Y24: =+SUM(START:END!O24)-O24 -> 0
A25: =+B25&C25 -> Véhicules neufs | B25: =+$K$1 -> Véhicules neufs | N25: =IF(N24=0,0,N24/I24) -> -0.25089785 | S25: =IF(Q24=0,0,(S24/Q24)) -> -0.19149419
A26: =+B26&C26 -> Véhicules neufs | B26: =+$K$1 -> Véhicules neufs
A27: =+B27&C27 -> Véhicules neufsTotal Dépt. Neufs | B27: =+$K$1 -> Véhicules neufs | C27: Total Dépt. Neufs | D27: =+D13+D15+D17 -> 252.17964 | E27: =IF(D27<=0,0,F27/D27) -> 2830.5907 | F27: =F13+F17+F24+F19+F15 -> 713817.33 | G27: =+G13+G15+G17 -> 252.17964 | H27: =IF(G27<=0,0,I27/G27) -> 2830.5907 | I27: =I13+I17+I24+I19+I15 -> 713817.33 | J27: =+J13+J15+J17 -> 135 | K27: =IF(J27<=0,0,L27/J27) -> 5012.4839 | L27: =L13+L17+L24+L19+L15 -> 676685.32 | M27: =J27-G27 -> -117.17964 | N27: =L27-I27 -> -37132.011 | O27: =+O13+O15+O17 -> 255 | P27: =IF(O27<=0,0,Q27/O27) -> 2639.6356 | Q27: =Q13+Q17+Q24+Q19+Q15 -> 673107.08 | R27: =J27-O27 -> -120 | S27: =L27-Q27 -> 3578.24 | V27: =+SUM(START:END!D27)-D27 -> 0 | W27: =+SUM(START:END!G27)-G27 -> 0 | X27: =+SUM(START:END!J27)-J27 -> 0 | Y27: =+SUM(START:END!O27)-O27 -> 0
A28: =+B28&C28 -> Véhicules neufs | B28: =+$K$1 -> Véhicules neufs | M28: =M27/G27 -> -0.46466732 | N28: =N27/I27 -> -0.052018926 | R28: =R27/O27 -> -0.47058824 | S28: =IF(Q27=0,0,S27/Q27) -> 0.0053160041
A29: =+B29&C29 -> Véhicules neufs | B29: =+$K$1 -> Véhicules neufs
A30: =+B30&C30 -> Véhicules neufsDEPENSES | B30: =+$K$1 -> Véhicules neufs | C30: DEPENSES
A31: =+B31&C31 -> Véhicules neufsComm. vendeurs | B31: =+$K$1 -> Véhicules neufs | C31: Comm. vendeurs | E31: =F31/D$24 -> 604.44008 | F31: =+SUM(START:END!F31) -> 150116.7 | H31: =I31/G$24 -> 604.44008 | I31: =+SUM(START:END!I31) -> 150116.7 | J31: =L31/L13 -> 0.3086142 | K31: =IF(L31=0,0,L31/J$24) -> 1025.1748 | L31: =+SUM(START:END!L31) -> 138398.6 | N31: =L31-I31 -> -11718.1 | P31: =IF(Q31=0,0,Q31/O$24) -> 610.77686 | Q31: =+SUM(START:END!Q31) -> 147808 | S31: =L31-Q31 -> -9409.4
A32: =+B32&C32 -> Véhicules neufsComm. F&I | B32: =+$K$1 -> Véhicules neufs | C32: Comm. F&I | E32: =F32/D$24 -> 255 | F32: =+SUM(START:END!F32) -> 63330.94 | H32: =I32/G$24 -> 255 | I32: =+SUM(START:END!I32) -> 63330.94 | J32: =L32/L24 -> 0.34819927 | K32: =IF(L32=0,0,L32/J$24) -> 407.87756 | L32: =+SUM(START:END!L32) -> 55063.47 | N32: =L32-I32 -> -8267.4698 | P32: =IF(Q32=0,0,Q32/O$24) -> 251.3676 | Q32: =+SUM(START:END!Q32) -> 60830.96 | S32: =L32-Q32 -> -5767.49
A33: =+B33&C33 -> Véhicules neufsFrais de livraison | B33: =+$K$1 -> Véhicules neufs | C33: Frais de livraison | E33: =F33/D$24 -> 167.8493 | F33: =+SUM(START:END!F33) -> 41686.486 | H33: =I33/G$24 -> 167.8493 | I33: =+SUM(START:END!I33) -> 41686.486 | K33: =IF(L33=0,0,L33/J$24) -> 106.88356 | L33: =+SUM(START:END!L33) -> 14429.28 | N33: =L33-I33 -> -27257.206 | P33: =IF(Q33=0,0,Q33/O$24) -> 106.07401 | Q33: =+SUM(START:END!Q33) -> 25669.91 | S33: =L33-Q33 -> -11240.63
A34: =+B34&C34 -> Véhicules neufsService gratuit 1 | B34: =+$K$1 -> Véhicules neufs | C34: Service gratuit 1 | E34: =F34/D$24 -> 7.3548076 | F34: =+SUM(START:END!F34) -> 1826.6152 | H34: =I34/G$24 -> 7.3548076 | I34: =+SUM(START:END!I34) -> 1826.6152 | K34: =IF(L34=0,0,L34/J$24) -> 5.2612593 | L34: =+SUM(START:END!L34) -> 710.27 | N34: =L34-I34 -> -1116.3452 | P34: =IF(Q34=0,0,Q34/O$24) -> 7.9414876 | Q34: =+SUM(START:END!Q34) -> 1921.84 | S34: =L34-Q34 -> -1211.57
A35: =+B35&C35 -> Véhicules neufsEntretien stock | B35: =+$K$1 -> Véhicules neufs | C35: Entretien stock | E35: =F35/D$24 -> 17.733118 | F35: =+SUM(START:END!F35) -> 4404.1374 | H35: =I35/G$24 -> 17.733118 | I35: =+SUM(START:END!I35) -> 4404.1374 | K35: =IF(L35=0,0,L35/J$24) -> 91.270667 | L35: =+SUM(START:END!L35) -> 12321.54 | N35: =L35-I35 -> 7917.4026 | P35: =IF(Q35=0,0,Q35/O$24) -> 13.545992 | Q35: =+SUM(START:END!Q35) -> 3278.13 | S35: =L35-Q35 -> 9043.41
A36: =+B36&C36 -> Véhicules neufsPublicité 1 | B36: =+$K$1 -> Véhicules neufs | C36: Publicité 1 | E36: =F36/D$24 -> 195.93765 | F36: =+SUM(START:END!F36) -> 48662.414 | H36: =I36/G$24 -> 195.93765 | I36: =+SUM(START:END!I36) -> 48662.414 | K36: =IF(L36=0,0,L36/J$24) -> 291.42074 | L36: =+SUM(START:END!L36) -> 39341.8 | N36: =L36-I36 -> -9320.6145 | P36: =IF(Q36=0,0,Q36/O$24) -> 136.67541 | Q36: =+SUM(START:END!Q36) -> 33075.45 | S36: =L36-Q36 -> 6266.35
A37: =+B37&C37 -> Véhicules neufsIntérêt de gros | B37: =+$K$1 -> Véhicules neufs | C37: Intérêt de gros | E37: =F37/D$24 -> 92.935022 | F37: =+SUM(START:END!F37) -> 23081.029 | H37: =I37/G$24 -> 92.935022 | I37: =+SUM(START:END!I37) -> 23081.029 | K37: =IF(L37=0,0,L37/J$24) -> 6.2387407 | L37: =+SUM(START:END!L37) -> 842.23 | N37: =L37-I37 -> -22238.799 | P37: =IF(Q37=0,0,Q37/O$24) -> 179.57818 | Q37: =+SUM(START:END!Q37) -> 43457.92 | S37: =L37-Q37 -> -42615.69
A38: =+B38&C38 -> Véhicules neufs[...] | B38: =+$K$1 -> Véhicules neufs | C38: [...] | E38: =F38/D$24 -> 0 | F38: =+SUM(START:END!F38) -> 0 | H38: =I38/G$24 -> 0 | I38: =+SUM(START:END!I38) -> 0 | K38: =IF(L38=0,0,L38/J$24) -> 0 | L38: =+SUM(START:END!L38) -> 0 | N38: =L38-I38 -> 0 | P38: =IF(Q38=0,0,Q38/O$24) -> 0 | Q38: =+SUM(START:END!Q38) -> 0 | S38: =L38-Q38 -> 0
A39: =+B39&C39 -> Véhicules neufs[...] | B39: =+$K$1 -> Véhicules neufs | C39: [...] | E39: =F39/D$24 -> 0 | F39: =+SUM(START:END!F39) -> 0 | H39: =I39/G$24 -> 0 | I39: =+SUM(START:END!I39) -> 0 | K39: =IF(L39=0,0,L39/J$24) -> 0 | L39: =+SUM(START:END!L39) -> 0 | N39: =L39-I39 -> 0 | P39: =IF(Q39=0,0,Q39/O$24) -> 0 | Q39: =+SUM(START:END!Q39) -> 0 | S39: =L39-Q39 -> 0
A40: =+B40&C40 -> Véhicules neufs[...] | B40: =+$K$1 -> Véhicules neufs | C40: [...] | E40: =F40/D$24 -> 0 | F40: =+SUM(START:END!F40) -> 0 | H40: =I40/G$24 -> 0 | I40: =+SUM(START:END!I40) -> 0 | K40: =IF(L40=0,0,L40/J$24) -> 0 | L40: =+SUM(START:END!L40) -> 0 | N40: =L40-I40 -> 0 | P40: =IF(Q40=0,0,Q40/O$24) -> 0 | Q40: =+SUM(START:END!Q40) -> 0 | S40: =L40-Q40 -> 0
A41: =+B41&C41 -> Véhicules neufsTOTAL VARIABLES | B41: =+$K$1 -> Véhicules neufs | C41: TOTAL VARIABLES | D41: % brut | E41: =F41/F$27 -> 0.46665766 | F41: =SUM(F31:F40) -> 333108.32 | G41: % brut | H41: =I41/I$27 -> 0.46665766 | I41: =SUM(I31:I40) -> 333108.32 | J41: % brut | K41: =L41/L$27 -> 0.38586206 | L41: =SUM(L31:L40) -> 261107.19 | N41: =SUM(N31:N40) -> -72001.132 | O41: % brut | P41: =Q41/Q$27 -> 0.46952739 | Q41: =SUM(Q31:Q40) -> 316042.21 | S41: =L41-Q41 -> -54935.02
A42: =+B42&C42 -> Véhicules neufsSalaires cadres | B42: =+$K$1 -> Véhicules neufs | C42: Salaires cadres | F42: =+SUM(START:END!F42) -> 47131.756 | G42: =I41/(I27+I83) -> 0.30611956 | I42: =+SUM(START:END!I42) -> 47131.756 | J42: =L41/(L27+L83) -> 0.30545665 | L42: =+SUM(START:END!L42) -> 50735.84 | N42: =L42-I42 -> 3604.0843 | Q42: =+SUM(START:END!Q42) -> 65878.61
A43: =+B43&C43 -> Véhicules neufsSalaires commis | B43: =+$K$1 -> Véhicules neufs | C43: Salaires commis | F43: =+SUM(START:END!F43) -> 29030.162 | I43: =+SUM(START:END!I43) -> 29030.162 | L43: =+SUM(START:END!L43) -> 23417.27 | N43: =L43-I43 -> -5612.8916 | Q43: =+SUM(START:END!Q43) -> 29115.84 | S43: =L43-Q43 -> -5698.57
A44: =+B44&C44 -> Véhicules neufsSalaires autres | B44: =+$K$1 -> Véhicules neufs | C44: Salaires autres | F44: =+SUM(START:END!F44) -> 26358.688 | I44: =+SUM(START:END!I44) -> 26358.688 | L44: =+SUM(START:END!L44) -> 11380.87 | N44: =L44-I44 -> -14977.818 | Q44: =+SUM(START:END!Q44) -> 27261.44 | S44: =L44-Q44 -> -15880.57
A45: =+B45&C45 -> Véhicules neufsSalaires spécialistes | B45: =+$K$1 -> Véhicules neufs | C45: Salaires spécialistes | F45: =+SUM(START:END!F45) -> 0 | I45: =+SUM(START:END!I45) -> 0 | L45: =+SUM(START:END!L45) -> 0 | N45: =L45-I45 -> 0 | Q45: =+SUM(START:END!Q45) -> 0 | S45: =L45-Q45 -> 0
A46: =+B46&C46 -> Véhicules neufs[...] | B46: =+$K$1 -> Véhicules neufs | C46: [...] | F46: =+SUM(START:END!F46) -> 0 | I46: =+SUM(START:END!I46) -> 0 | L46: =+SUM(START:END!L46) -> 0 | N46: =L46-I46 -> 0 | Q46: =+SUM(START:END!Q46) -> 0 | S46: =L46-Q46 -> 0
A47: =+B47&C47 -> Véhicules neufs[...] | B47: =+$K$1 -> Véhicules neufs | C47: [...] | F47: =+SUM(START:END!F47) -> 0 | I47: =+SUM(START:END!I47) -> 0 | L47: =+SUM(START:END!L47) -> 0 | N47: =L47-I47 -> 0 | Q47: =+SUM(START:END!Q47) -> 0 | S47: =L47-Q47 -> 0
A48: =+B48&C48 -> Véhicules neufs[...] | B48: =+$K$1 -> Véhicules neufs | C48: [...] | F48: =+SUM(START:END!F48) -> 0 | I48: =+SUM(START:END!I48) -> 0 | L48: =+SUM(START:END!L48) -> 0 | N48: =L48-I48 -> 0 | Q48: =+SUM(START:END!Q48) -> 0 | S48: =L48-Q48 -> 0
A49: =+B49&C49 -> Véhicules neufsSalaires en absences | B49: =+$K$1 -> Véhicules neufs | C49: Salaires en absences | F49: =+SUM(START:END!F49) -> 38345.072 | I49: =+SUM(START:END!I49) -> 38345.072 | L49: =+SUM(START:END!L49) -> 46365.35 | N49: =L49-I49 -> 8020.2782 | Q49: =+SUM(START:END!Q49) -> 43896.08 | S49: =L49-Q49 -> 2469.27
A50: =+B50&C50 -> Véhicules neufsDéduction à la source | B50: =+$K$1 -> Véhicules neufs | C50: Déduction à la source | F50: =+SUM(START:END!F50) -> 34341.942 | I50: =+SUM(START:END!I50) -> 34341.942 | L50: =+SUM(START:END!L50) -> 58622.97 | N50: =L50-I50 -> 24281.028 | Q50: =+SUM(START:END!Q50) -> 35144.77 | S50: =L50-Q50 -> 23478.2
A51: =+B51&C51 -> Véhicules neufsBénéfices marginaux | B51: =+$K$1 -> Véhicules neufs | C51: Bénéfices marginaux | F51: =+SUM(START:END!F51) -> 27271.543 | I51: =+SUM(START:END!I51) -> 27271.543 | L51: =+SUM(START:END!L51) -> 22121.29 | N51: =L51-I51 -> -5150.2525 | Q51: =+SUM(START:END!Q51) -> 25187.07 | S51: =L51-Q51 -> -3065.78
A52: =+B52&C52 -> Véhicules neufsCsst | B52: =+$K$1 -> Véhicules neufs | C52: Csst | F52: =+SUM(START:END!F52) -> 11110.628 | I52: =+SUM(START:END!I52) -> 11110.628 | L52: =+SUM(START:END!L52) -> 10377.54 | N52: =L52-I52 -> -733.08843 | Q52: =+SUM(START:END!Q52) -> 5857.47 | S52: =L52-Q52 -> 4520.07
A53: =+B53&C53 -> Véhicules neufs[...] | B53: =+$K$1 -> Véhicules neufs | C53: [...] | F53: =+SUM(START:END!F53) -> 0 | I53: =+SUM(START:END!I53) -> 0 | L53: =+SUM(START:END!L53) -> 0 | N53: =L53-I53 -> 0 | Q53: =+SUM(START:END!Q53) -> 0 | S53: =L53-Q53 -> 0
A54: =+B54&C54 -> Véhicules neufsTOTAL PERSONNEL | B54: =+$K$1 -> Véhicules neufs | C54: TOTAL PERSONNEL | D54: % brut | E54: =F54/F$27 -> 0.29922192 | F54: =+SUM(F42:F53) -> 213589.79 | G54: % brut | H54: =I54/I$27 -> 0.29922192 | I54: =+SUM(I42:I53) -> 213589.79 | J54: % brut | K54: =L54/L$27 -> 0.32957879 | L54: =+SUM(L42:L53) -> 223021.13 | N54: =+SUM(N42:N53) -> 9431.3392 | O54: % brut | P54: =Q54/Q$27 -> 0.34517729 | Q54: =+SUM(Q42:Q53) -> 232341.28 | S54: =+SUM(S42:S53) -> 5822.62
A55: =+B55&C55 -> Véhicules neufsPublicité 2 | B55: =+$K$1 -> Véhicules neufs | C55: Publicité 2 | F55: =+SUM(START:END!F55) -> 0 | G55: =I54/(I27+I83) -> 0.19628454 | I55: =+SUM(START:END!I55) -> 0 | J55: =L54/(L27+L83) -> 0.26090161 | L55: =+SUM(START:END!L55) -> 0 | N55: =L55-I55 -> 0 | Q55: =+SUM(START:END!Q55) -> 0 | S55: =L55-Q55 -> 0
A56: =+B56&C56 -> Véhicules neufsService gratuit 2 | B56: =+$K$1 -> Véhicules neufs | C56: Service gratuit 2 | F56: =+SUM(START:END!F56) -> 0 | I56: =+SUM(START:END!I56) -> 0 | L56: =+SUM(START:END!L56) -> 0 | N56: =L56-I56 -> 0 | Q56: =+SUM(START:END!Q56) -> 0 | S56: =L56-Q56 -> 0
A57: =+B57&C57 -> Véhicules neufsFrais véhicules de cie | B57: =+$K$1 -> Véhicules neufs | C57: Frais véhicules de cie | F57: =+SUM(START:END!F57) -> 21968.82 | I57: =+SUM(START:END!I57) -> 21968.82 | L57: =+SUM(START:END!L57) -> 22763.73 | N57: =L57-I57 -> 794.91 | Q57: =+SUM(START:END!Q57) -> 18246.87 | S57: =L57-Q57 -> 4516.86
A58: =+B58&C58 -> Véhicules neufsInformatique | B58: =+$K$1 -> Véhicules neufs | C58: Informatique | F58: =+SUM(START:END!F58) -> 20502.586 | I58: =+SUM(START:END!I58) -> 20502.586 | L58: =+SUM(START:END!L58) -> 21198.41 | N58: =L58-I58 -> 695.82372 | Q58: =+SUM(START:END!Q58) -> 17320.86 | S58: =L58-Q58 -> 3877.55
A59: =+B59&C59 -> Véhicules neufsFrais de déplacement | B59: =+$K$1 -> Véhicules neufs | C59: Frais de déplacement | F59: =+SUM(START:END!F59) -> 2376.4254 | I59: =+SUM(START:END!I59) -> 2376.4254 | L59: =+SUM(START:END!L59) -> 4668.96 | N59: =L59-I59 -> 2292.5346 | Q59: =+SUM(START:END!Q59) -> 1434.74 | S59: =L59-Q59 -> 3234.22
A60: =+B60&C60 -> Véhicules neufsServices extérieurs | B60: =+$K$1 -> Véhicules neufs | C60: Services extérieurs | F60: =+SUM(START:END!F60) -> 19976.551 | I60: =+SUM(START:END!I60) -> 19976.551 | L60: =+SUM(START:END!L60) -> 19915.71 | N60: =L60-I60 -> -60.840933 | Q60: =+SUM(START:END!Q60) -> 22901.42 | S60: =L60-Q60 -> -2985.71
A61: =+B61&C61 -> Véhicules neufsFournitures autres | B61: =+$K$1 -> Véhicules neufs | C61: Fournitures autres | F61: =+SUM(START:END!F61) -> 296.69412 | I61: =+SUM(START:END!I61) -> 296.69412 | L61: =+SUM(START:END!L61) -> 15.24 | N61: =L61-I61 -> -281.45412 | Q61: =+SUM(START:END!Q61) -> 626.87 | S61: =L61-Q61 -> -611.63
A62: =+B62&C62 -> Véhicules neufsUniformes | B62: =+$K$1 -> Véhicules neufs | C62: Uniformes | F62: =+SUM(START:END!F62) -> 157.65545 | I62: =+SUM(START:END!I62) -> 157.65545 | L62: =+SUM(START:END!L62) -> 0 | N62: =L62-I62 -> -157.65545 | Q62: =+SUM(START:END!Q62) -> 0 | S62: =L62-Q62 -> 0
A63: =+B63&C63 -> Véhicules neufsPapeterie | B63: =+$K$1 -> Véhicules neufs | C63: Papeterie | F63: =+SUM(START:END!F63) -> 1958.593 | I63: =+SUM(START:END!I63) -> 1958.593 | L63: =+SUM(START:END!L63) -> 1892.29 | N63: =L63-I63 -> -66.30296 | Q63: =+SUM(START:END!Q63) -> 2060.04 | S63: =L63-Q63 -> -167.75
A64: =+B64&C64 -> Véhicules neufsTéléphone | B64: =+$K$1 -> Véhicules neufs | C64: Téléphone | F64: =+SUM(START:END!F64) -> 904.39358 | I64: =+SUM(START:END!I64) -> 904.39358 | L64: =+SUM(START:END!L64) -> 935.44 | N64: =L64-I64 -> 31.04642 | Q64: =+SUM(START:END!Q64) -> 644.74 | S64: =L64-Q64 -> 290.7
A65: =+B65&C65 -> Véhicules neufsFrais postaux | B65: =+$K$1 -> Véhicules neufs | C65: Frais postaux | F65: =+SUM(START:END!F65) -> 482.75122 | I65: =+SUM(START:END!I65) -> 482.75122 | L65: =+SUM(START:END!L65) -> 386.45 | N65: =L65-I65 -> -96.30122 | Q65: =+SUM(START:END!Q65) -> 459.89 | S65: =L65-Q65 -> -73.44
A66: =+B66&C66 -> Véhicules neufsDivers | B66: =+$K$1 -> Véhicules neufs | C66: Divers | F66: =+SUM(START:END!F66) -> 2328.7008 | I66: =+SUM(START:END!I66) -> 2328.7008 | L66: =+SUM(START:END!L66) -> 1426.53 | N66: =L66-I66 -> -902.17078 | Q66: =+SUM(START:END!Q66) -> 2660.9 | S66: =L66-Q66 -> -1234.37
A67: =+B67&C67 -> Véhicules neufsFormation | B67: =+$K$1 -> Véhicules neufs | C67: Formation | F67: =+SUM(START:END!F67) -> 3459.7688 | I67: =+SUM(START:END!I67) -> 3459.7688 | L67: =+SUM(START:END!L67) -> 2886.39 | N67: =L67-I67 -> -573.3788 | Q67: =+SUM(START:END!Q67) -> 2209.99 | S67: =L67-Q67 -> 676.4
... A71: =+B71&C71 -> Véhicules neufs[...] | B71: =+$K$1 -> Véhicules neufs | C71: [...] | F71: =+SUM(START:END!F71) -> 0 | I71: =+SUM(START:END!I71) -> 0 | L71: =+SUM(START:END!L71) -> 0 | N71: =L71-I71 -> 0 | Q71: =+SUM(START:END!Q71) -> 0 | S71: =L71-Q71 -> 0
A72: =+B72&C72 -> Véhicules neufsTOTAL SEMI-FIXES | B72: =+$K$1 -> Véhicules neufs | C72: TOTAL SEMI-FIXES | D72: % brut | E72: =F72/F$27 -> 0.11602119 | F72: =+SUM(F55:F71) -> 82817.934 | G72: % brut | H72: =I72/I$27 -> 0.11602119 | I72: =+SUM(I55:I71) -> 82817.934 | J72: % brut | K72: =L72/L$27 -> 0.12944133 | L72: =+SUM(L55:L71) -> 87591.051 | N72: =+SUM(N55:N71) -> 4773.1168 | O72: % brut | P72: =Q72/Q$27 -> 0.11711197 | Q72: =+SUM(Q55:Q71) -> 78828.894 | S72: =+SUM(S55:S71) -> 8762.157
A73: =+B73&C73 -> Véhicules neufs | B73: =+$K$1 -> Véhicules neufs
A74: =+B74&C74 -> Véhicules neufsTOTAL DES DÉPENSES | B74: =+$K$1 -> Véhicules neufs | C74: TOTAL DES DÉPENSES | D74: % brut | E74: =F74/F$27 -> 0.88190076 | F74: =F41+F54+F72 -> 629516.05 | G74: % brut | H74: =I74/I$27 -> 0.88190076 | I74: =I41+I54+I72 -> 629516.05 | J74: % brut | K74: =L74/L$27 -> 0.84488218 | L74: =L41+L54+L72 -> 571719.37 | N74: =L74-I74 -> -57796.676 | O74: % brut | P74: =Q74/Q$27 -> 0.93181665 | Q74: =Q41+Q54+Q72 -> 627212.38 | S74: =L74-Q74 -> -55493.013
A75: =+B75&C75 -> Véhicules neufsProgramme neuf 1 | B75: =+$K$1 -> Véhicules neufs | C75: Programme neuf 1 | F75: =+SUM(START:END!F75) -> 20185.2 | I75: =+SUM(START:END!I75) -> 20185.2 | L75: =+SUM(START:END!L75) -> 22000 | N75: =L75-I75 -> 1814.8 | Q75: =+SUM(START:END!Q75) -> 0
A76: =+B76&C76 -> Véhicules neufsProgramme neuf 2 | B76: =+$K$1 -> Véhicules neufs | C76: Programme neuf 2 | F76: =+SUM(START:END!F76) -> 0 | I76: =+SUM(START:END!I76) -> 0 | L76: =+SUM(START:END!L76) -> 0 | N76: =L76-I76 -> 0 | Q76: =+SUM(START:END!Q76) -> 0 | S76: =L76-Q76 -> 0
A77: =+B77&C77 -> Véhicules neufsProgramme neuf 3 | B77: =+$K$1 -> Véhicules neufs | C77: Programme neuf 3 | F77: =+SUM(START:END!F77) -> 0 | I77: =+SUM(START:END!I77) -> 0 | L77: =+SUM(START:END!L77) -> 0 | N77: =L77-I77 -> 0 | Q77: =+SUM(START:END!Q77) -> 0 | S77: =L77-Q77 -> 0
A78: =+B78&C78 -> Véhicules neufsHoldbacks | B78: =+$K$1 -> Véhicules neufs | C78: Holdbacks | F78: =+SUM(START:END!F78) -> 263603.89 | I78: =+SUM(START:END!I78) -> 263603.89 | L78: =+SUM(START:END!L78) -> 156084 | N78: =L78-I78 -> -107519.89 | Q78: =+SUM(START:END!Q78) -> 270355 | S78: =L78-Q78 -> -114271
A79: =+B79&C79 -> Véhicules neufs[...] | B79: =+$K$1 -> Véhicules neufs | C79: [...] | F79: =+SUM(START:END!F79) -> 0 | I79: =+SUM(START:END!I79) -> 0 | L79: =+SUM(START:END!L79) -> 0 | N79: =L79-I79 -> 0 | Q79: =+SUM(START:END!Q79) -> 0 | S79: =L79-Q79 -> 0
A80: =+B80&C80 -> Véhicules neufs[...] | B80: =+$K$1 -> Véhicules neufs | C80: [...] | F80: =+SUM(START:END!F80) -> 0 | I80: =+SUM(START:END!I80) -> 0 | L80: =+SUM(START:END!L80) -> 0 | N80: =L80-I80 -> 0 | Q80: =+SUM(START:END!Q80) -> 0 | S80: =L80-Q80 -> 0
A81: =+B81&C81 -> Véhicules neufs[...] | B81: =+$K$1 -> Véhicules neufs | C81: [...] | F81: =+SUM(START:END!F81) -> 0 | I81: =+SUM(START:END!I81) -> 0 | L81: =+SUM(START:END!L81) -> 0 | N81: =L81-I81 -> 0 | Q81: =+SUM(START:END!Q81) -> 0 | S81: =L81-Q81 -> 0
A82: =+B82&C82 -> Véhicules neufsFrais administration | B82: =+$K$1 -> Véhicules neufs | C82: Frais administration | F82: =+SUM(START:END!F82) -> 90557.707 | I82: =+SUM(START:END!I82) -> 90557.707 | L82: =+SUM(START:END!L82) -> 40 | N82: =L82-I82 -> -90517.707 | Q82: =+SUM(START:END!Q82) -> 69117 | S82: =L82-Q82 -> -69077
A83: =+B83&C83 -> Véhicules neufsAUTRES REVENUS | B83: =+$K$1 -> Véhicules neufs | C83: AUTRES REVENUS | F83: =+SUM(F75:F82) -> 374346.8 | I83: =+SUM(I75:I82) -> 374346.8 | L83: =+SUM(L75:L82) -> 178124 | N83: =+SUM(N75:N82) -> -196222.8 | Q83: =+SUM(Q75:Q82) -> 339472 | S83: =+SUM(S75:S82) -> -183348
A84: =+B84&C84 -> Véhicules neufs | B84: =+$K$1 -> Véhicules neufs
A85: =+B85&C85 -> Véhicules neufsPROFIT DÉPARTEMENTAL | B85: =+$K$1 -> Véhicules neufs | C85: PROFIT DÉPARTEMENTAL | F85: =F27-F74+F83 -> 458648.08 | I85: =I27-I74+I83 -> 458648.08 | L85: =L27-L74+L83 -> 283089.95 | N85: =N27-N41-N54-N72+N83 -> -175558.13 | Q85: =Q27-Q74+Q83 -> 385366.7 | S85: =S27-S41-S54-S72+S83 -> -139419.52
C89: =C1 -> Conso | K89: Véhicules usagés | S89: =$S$1 -> Réalisé Volks T2 2022
D91: BUDGET ORIGINAL | G91: BUDGET RÉVISÉ | J91: RÉALISATION | M91: ÉCART réel / révisé | O91: ANNÉE PRÉCÉDENTE | R91: ÉCART réel / original
D92: UNITE | E92: $P/UNITÉ | F92: $PROFITS | G92: UNITE | H92: $P/UNITÉ | I92: $PROFITS | J92: UNITE | K92: $P/UNITE | L92: $PROFITS | M92: UNITÉ | N92: $PROFITS | O92: UNITE | P92: $P/UNITE | Q92: $PROFITS | R92: UNITE | S92: $PROFITS
A93: =+B93&C93 -> Véhicules usagésVentes nettes | B93: Véhicules usagés | C93: Ventes nettes | F93: =+SUM(START:END!F93) -> 4281718 | I93: =+SUM(START:END!I93) -> 4281718 | L93: =+SUM(START:END!L93) -> 4674034.2 | Q93: =+SUM(START:END!Q93) -> 4059304.1
A94: =+B94&C94 -> Véhicules usagésCertifié | B94: Véhicules usagés | C94: Certifié | D94: =+SUM(START:END!D94) -> 130.69175 | E94: =IF(D94=0,0,F94/D94) -> 1300 | F94: =+SUM(START:END!F94) -> 169899.27 | G94: =+SUM(START:END!G94) -> 130.69175 | H94: =IF(G94=0,0,I94/G94) -> 1300 | I94: =+SUM(START:END!I94) -> 169899.27 | J94: =+SUM(START:END!J94) -> 90 | K94: =IF(J94=0,0,L94/J94) -> 2372.8421 | L94: =+SUM(START:END!L94) -> 213555.79 | M94: =J94-G94 -> -40.691748 | N94: =L94-I94 -> 43656.518 | O94: =+SUM(START:END!O94) -> 115 | P94: =IF(O94=0,0,Q94/O94) -> 1217.2251 | Q94: =+SUM(START:END!Q94) -> 139980.89 | R94: =J94-O94 -> -25 | S94: =L94-Q94 -> 73574.9
A95: =+B95&C95 -> Véhicules usagésNon Certifié | B95: Véhicules usagés | C95: Non Certifié | D95: =+SUM(START:END!D95) -> 7.342233 | E95: =IF(D95=0,0,F95/D95) -> 900 | F95: =+SUM(START:END!F95) -> 6608.0097 | G95: =+SUM(START:END!G95) -> 7.342233 | H95: =IF(G95=0,0,I95/G95) -> 900 | I95: =+SUM(START:END!I95) -> 6608.0097 | J95: =+SUM(START:END!J95) -> 9 | K95: =IF(J95=0,0,L95/J95) -> 1650.08 | L95: =+SUM(START:END!L95) -> 14850.72 | O95: =+SUM(START:END!O95) -> 4 | P95: =IF(O95=0,0,Q95/O95) -> 113.8725 | Q95: =+SUM(START:END!Q95) -> 455.49 | R95: =J95-O95 -> 5 | S95: =L95-Q95 -> 14395.23
A96: =+B96&C96 -> Véhicules usagésTotal Usagés | B96: Véhicules usagés | C96: Total Usagés | D96: =+D95+D94 -> 138.03398 | E96: =IF(D96=0,0,F96/D96) -> 1278.7234 | F96: =+F94+F95 -> 176507.28 | G96: =+G95+G94 -> 138.03398 | H96: =IF(G96=0,0,I96/G96) -> 1278.7234 | I96: =+I94+I95 -> 176507.28 | J96: =+J94+J95 -> 99 | K96: =IF(J96<=0,0,L96/J96) -> 2307.1365 | L96: =+L94+L95 -> 228406.51 | M96: =J96-G96 -> -39.033981 | N96: =L96-I96 -> 51899.228 | O96: =+O94+O95 -> 119 | P96: =IF(O96<=0,0,Q96/O96) -> 1180.1376 | Q96: =+Q94+Q95 -> 140436.38 | R96: =R94+R95 -> -20 | S96: =S94+S95 -> 87970.13 | V96: =+SUM(START:END!D96)-D96 -> 0 | W96: =+SUM(START:END!G96)-G96 -> 0 | X96: =+SUM(START:END!J96)-J96 -> 0 | Y96: =+SUM(START:END!O96)-O96 -> 0
A97: =+B97&C97 -> Véhicules usagés | B97: Véhicules usagés | E97: =IF(D97=0,0,F97/D97) -> 0 | H97: =IF(G97=0,0,I97/G97) -> 0 | M97: =M96/G96 -> -0.2827853 | N97: =N96/I96 -> 0.29403449 | R97: =R96/O96 -> -0.16806723 | S97: =IF(Q96=0,0,(S96/Q96)) -> 0.62640557
A98: =+B98&C98 -> Véhicules usagésUS | B98: Véhicules usagés | C98: US | D98: =+SUM(START:END!D98) -> 0 | E98: =IF(D98=0,0,F98/D98) -> 0 | F98: =+SUM(START:END!F98) -> 0 | G98: =+SUM(START:END!G98) -> 0 | H98: =IF(G98=0,0,I98/G98) -> 0 | I98: =+SUM(START:END!I98) -> 0 | J98: =+SUM(START:END!J98) -> 0 | K98: =IF(J98=0,0,L98/J98) -> 0 | L98: =+SUM(START:END!L98) -> 0 | M98: =J98-G98 -> 0 | N98: =L98-I98 -> 0 | O98: =+SUM(START:END!O98) -> 0 | P98: =IF(O98=0,0,Q98/O98) -> 0 | Q98: =+SUM(START:END!Q98) -> 0 | V98: =+SUM(START:END!D98)-D98 -> 0 | W98: =+SUM(START:END!G98)-G98 -> 0 | X98: =+SUM(START:END!J98)-J98 -> 0 | Y98: =+SUM(START:END!O98)-O98 -> 0
A99: =+B99&C99 -> Véhicules usagésVentes au Gros | B99: Véhicules usagés | C99: Ventes au Gros | D99: =+SUM(START:END!D99) -> 120.11619 | E99: =IF(D99=0,0,F99/D99) -> 212 | F99: =+SUM(START:END!F99) -> 25464.633 | G99: =+SUM(START:END!G99) -> 120.11619 | H99: =IF(G99=0,0,I99/G99) -> 212 | I99: =+SUM(START:END!I99) -> 25464.633 | J99: =+SUM(START:END!J99) -> 78 | K99: =IF(J99=0,0,L99/J99) -> 182.29564 | L99: =+SUM(START:END!L99) -> 14219.06 | M99: =J99-G99 -> -42.116192 | N99: =L99-I99 -> -11245.573 | O99: =+SUM(START:END!O99) -> 107 | P99: =IF(O99=0,0,Q99/O99) -> 548.28383 | Q99: =+SUM(START:END!Q99) -> 58666.37 | R99: =J99-O99 -> -29 | S99: =L99-Q99 -> -44447.31 | V99: =+SUM(START:END!D99)-D99 -> 0 | W99: =+SUM(START:END!G99)-G99 -> 0 | X99: =+SUM(START:END!J99)-J99 -> 0 | Y99: =+SUM(START:END!O99)-O99 -> 0
A100: =+B100&C100 -> Véhicules usagés | B100: Véhicules usagés
A101: =+B101&C101 -> Véhicules usagésRev. Finances | B101: Véhicules usagés | C101: Rev. Finances | D101: 0 | E101: =IF(D101=0,0,F101/D101) -> 0 | F101: =+SUM(START:END!F101) -> 90958.998 | G101: 0 | H101: =IF(G101=0,0,I101/G101) -> 0 | I101: =+SUM(START:END!I101) -> 90958.998 | K101: =IF(J96=0,0,L101/J96) -> 1294.9445 | L101: =+SUM(START:END!L101) -> 128199.51 | N101: =L101-I101 -> 37240.512 | P101: =IF(O96=0,0,Q101/O96) -> 704.15874 | Q101: =+SUM(START:END!Q101) -> 83794.89 | R101: =O101-K101 -> -1294.9445 | S101: =L101-Q101 -> 44404.62
A102: =+B102&C102 -> Véhicules usagésRev. Protections | B102: Véhicules usagés | C102: Rev. Protections | D102: 0 | E102: =IF(D102=0,0,F102/D102) -> 0 | F102: =+SUM(START:END!F102) -> 160374.05 | G102: 0 | H102: =IF(G102=0,0,I102/G102) -> 0 | I102: =+SUM(START:END!I102) -> 160374.05 | K102: =IF(J96=0,0,L102/J96) -> 1349.0514 | L102: =+SUM(START:END!L102) -> 133556.09 | N102: =L102-I102 -> -26817.956 | P102: =IF(O96=0,0,Q102/O96) -> 1180.862 | Q102: =+SUM(START:END!Q102) -> 140522.58 | R102: =O102-K102 -> -1349.0514 | S102: =L102-Q102 -> -6966.49
A103: =+B103&C103 -> Véhicules usagésRev. Autres | B103: Véhicules usagés | C103: Rev. Autres | D103: 0 | E103: =IF(D103=0,0,F103/D103) -> 0 | F103: =+SUM(START:END!F103) -> 4548.6624 | G103: 0 | H103: =IF(G103=0,0,I103/G103) -> 0 | I103: =+SUM(START:END!I103) -> 4548.6624 | K103: =IF(J96=0,0,L103/J96) -> 73.025758 | L103: =+SUM(START:END!L103) -> 7229.55 | N103: =L103-I103 -> 2680.8876 | P103: =IF(O96=0,0,Q103/O96) -> 29.202857 | Q103: =+SUM(START:END!Q103) -> 3475.14 | R103: =O103-K103 -> -73.025758 | S103: =L103-Q103 -> 3754.41
A104: =+B104&C104 -> Véhicules usagésTotal F&I | B104: Véhicules usagés | C104: Total F&I | D104: =D96 -> 138.03398 | E104: =IF(D104=0,0,F104/D104) -> 1853.7588 | F104: =F101+F102+F103 -> 255881.71 | G104: =G96 -> 138.03398 | H104: =IF(G104=0,0,I104/G104) -> 1853.7588 | I104: =I101+I102+I103 -> 255881.71 | J104: =J96 -> 99 | K104: =IF(J104<=0,0,L104/J104) -> 2717.0217 | L104: =L101+L102+L103 -> 268985.15 | M104: =J104-G104 -> -39.033981 | N104: =L104-I104 -> 13103.444 | O104: =O96 -> 119 | P104: =IF(O104<=0,0,Q104/O104) -> 1914.2236 | Q104: =Q101+Q102+Q103 -> 227792.61 | S104: =L104-Q104 -> 41192.54 | V104: =+SUM(START:END!D104)-D104 -> 0 | W104: =+SUM(START:END!G104)-G104 -> 0 | X104: =+SUM(START:END!J104)-J104 -> 0 | Y104: =+SUM(START:END!O104)-O104 -> 0
A105: =+B105&C105 -> Véhicules usagés | B105: Véhicules usagés | N105: =N104/I104 -> 0.05120899 | S105: =IF(Q104=0,0,(S104/Q104)) -> 0.18083352
A106: =+B106&C106 -> Véhicules usagés | B106: Véhicules usagés
A107: =+B107&C107 -> Véhicules usagésTotal Dépt. Usagés | B107: Véhicules usagés | C107: Total Dépt. Usagés | D107: =D96+D99 -> 258.15017 | E107: =IF(D107<=0,0,F107/D107) -> 1773.5941 | F107: =F96+F104+F99 -> 457853.62 | G107: =G96+G99 -> 258.15017 | H107: =IF(G107<=0,0,I107/G107) -> 1773.5941 | I107: =I96+I104+I99 -> 457853.62 | J107: =J96+J99+J98 -> 177 | K107: =IF(J107<=0,0,L107/J107) -> 2890.456 | L107: =L96+L104+L99+L98 -> 511610.72 | M107: =J107-G107 -> -81.150173 | N107: =L107-I107 -> 53757.1 | O107: =O96+O99+O98 -> 226 | P107: =IF(O107<=0,0,Q107/O107) -> 1888.9175 | Q107: =Q96+Q104+Q99+Q98 -> 426895.36 | R107: =J107-O107 -> -49 | S107: =L107-Q107 -> 84715.36 | V107: =+SUM(START:END!D107)-D107 -> 0 | W107: =+SUM(START:END!G107)-G107 -> 0 | X107: =+SUM(START:END!J107)-J107 -> 0 | Y107: =+SUM(START:END!O107)-O107 -> 0
...

Sheet START

Sheet VW 2022-04
C1: Volks | K1: Véhicules neufs | S1: Réalisé, Avril 2022
D2: X | E2: O | F2: U | G2: X | H2: O | I2: U | J2: NB | L2: $ | O2: NB | Q2: $ | V2: *** *** NE PAS EFFACER *** ***
D3: BUDGET ORIGINAL | G3: BUDGET REVISE | J3: RÉALISATION | M3: ÉCART réel / révisé | O3: ANNÉE PRÉCÉDENTE | R3: ÉCART réel / original | V3: NEUF | W3: 0.45
D4: UNITE | E4: $P/UNITÉ | F4: $PROFITS | G4: UNITE | H4: $P/UNITÉ | I4: $PROFITS | J4: UNITE | K4: $P/UNITE | L4: $PROFITS | M4: UNITÉ | N4: $PROFITS | O4: UNITE | P4: $P/UNITE | Q4: $PROFITS | R4: UNITE | S4: $PROFITS | V4: USAGE | W4: 0.1
A5: Véhicules neufsVentes nettes | B5: Véhicules neufs | C5: Ventes nettes | F5: 3254290.8 | I5: 3254290.8 | L5: 1766312.5 | Q5: 3244693.3 | V5: SERVICE | W5: 0.225
A6: Véhicules neufsAutos détail | B6: Véhicules neufs | C6: Autos détail | D6: 16.59759 | E6: 1450.6298 | F6: 24076.959 | G6: 16.59759 | H6: 1450.6298 | I6: 24076.959 | J6: 9 | K6: 2549.2733 | L6: 22943.46 | M6: -7.5975904 | N6: -1133.4986 | O6: 24 | P6: 474.33792 | Q6: 11384.11 | R6: -15 | S6: 11559.35 | V6: CARROSSERIE | W6: 0.025
A7: Véhicules neufsCamions détail | B7: Véhicules neufs | C7: Camions détail | D7: 57.301205 | E7: 2081.8276 | F7: 119291.23 | G7: 57.301205 | H7: 2081.8276 | I7: 119291.23 | J7: 22 | K7: 3588.6732 | L7: 78950.81 | M7: -35.301205 | N7: -40340.419 | O7: 41 | P7: 2167.9161 | Q7: 88884.56 | R7: -19 | S7: -9933.75 | V7: PIECES | W7: 0.2
A8: Véhicules neufsSprinter | B8: Véhicules neufs | C8: Sprinter | D8: 0 | E8: 0 | F8: 0 | G8: 0 | H8: 0 | I8: 0 | J8: 0 | K8: 0 | L8: 0 | M8: 0 | N8: 0 | O8: 0 | P8: 0 | Q8: 0 | R8: 0 | S8: 0 | W8: 1
A9: Véhicules neufsMoto détail | B9: Véhicules neufs | C9: Moto détail | D9: 0 | E9: 0 | F9: 0 | G9: 0 | H9: 0 | I9: 0 | J9: 0 | K9: 0 | L9: 0 | M9: 0 | N9: 0 | O9: 0 | P9: 0 | Q9: 0 | R9: 0 | S9: 0
A10: Véhicules neufs[...] | B10: Véhicules neufs | C10: [...] | D10: 0 | E10: 0 | F10: 0 | G10: 0 | H10: 0 | I10: 0 | J10: 0 | K10: 0 | L10: 0 | M10: 0 | N10: 0 | O10: 0 | P10: 0 | Q10: 0 | R10: 0 | S10: 0
A11: Véhicules neufs[...] | B11: Véhicules neufs | C11: [...] | D11: 0 | E11: 0 | F11: 0 | G11: 0 | H11: 0 | I11: 0 | J11: 0 | K11: 0 | L11: 0 | M11: 0 | N11: 0 | O11: 0 | P11: 0 | Q11: 0 | R11: 0 | S11: 0
A12: Véhicules neufs[...] | B12: Véhicules neufs | C12: [...] | D12: 0 | E12: 0 | F12: 0 | G12: 0 | H12: 0 | I12: 0 | J12: 0 | K12: 0 | L12: 0 | M12: 0 | N12: 0 | O12: 0 | P12: 0 | Q12: 0 | R12: 0 | S12: 0
A13: Véhicules neufsTotal Neufs | B13: Véhicules neufs | C13: Total Neufs | D13: 73.898795 | E13: 1940.0612 | F13: 143368.19 | G13: 73.898795 | H13: 1940.0612 | I13: 143368.19 | J13: 31 | K13: 3286.9119 | L13: 101894.27 | M13: -42.898795 | N13: -41473.917 | O13: 65 | P13: 1542.5949 | Q13: 100268.67 | R13: -34 | S13: 1625.6
A14: Véhicules neufs | B14: Véhicules neufs | R14: -0.52307692 | S14: 0.016212442
A15: Véhicules neufsEx-Démos et courtoisies | B15: Véhicules neufs | C15: Ex-Démos et courtoisies | D15: 6.9156627 | E15: 1386.1016 | F15: 9585.8112 | G15: 6.9156627 | H15: 1386.1016 | I15: 9585.8112 | J15: 2 | K15: 4555.475 | L15: 9110.95 | M15: -4.9156627 | N15: -474.86119 | O15: 3 | P15: 1041.6767 | Q15: 3125.03 | R15: -1 | S15: 5985.92
A16: Véhicules neufs | B16: Véhicules neufs
A17: Véhicules neufsFlottes | B17: Véhicules neufs | C17: Flottes | D17: 1.2439949 | E17: 1938.8732 | F17: 2411.9484 | G17: 1.2439949 | H17: 1938.8732 | I17: 2411.9484 | J17: 0 | K17: 0 | L17: 0 | M17: -1.2439949 | N17: -2411.9484 | O17: 5 | P17: 2400.116 | Q17: 12000.58 | R17: -5 | S17: -12000.58
A18: Véhicules neufs | B18: Véhicules neufs
A19: Véhicules neufsRachat bail | B19: Véhicules neufs | C19: Rachat bail | D19: 0 | E19: 0 | F19: 8416.039 | G19: 0 | H19: 0 | I19: 8416.039 | L19: 11555.79 | N19: 3139.751 | Q19: 10386.97 | R19: 0 | S19: 1168.82
A20: Véhicules neufs | B20: Véhicules neufs
A21: Véhicules neufsRev. Finances | B21: Véhicules neufs | C21: Rev. Finances | D21: 0 | E21: 0 | F21: 2418.2727 | G21: 0 | H21: 0 | I21: 2418.2727 | K21: 196.24152 | L21: 6475.97 | N21: 4057.6973 | P21: 93.977941 | Q21: 6390.5 | R21: -196.24152 | S21: 85.47
A22: Véhicules neufsRev. Protections | B22: Véhicules neufs | C22: Rev. Protections | D22: 0 | E22: 0 | F22: 64673.337 | G22: 0 | H22: 0 | I22: 64673.337 | K22: 797.35424 | L22: 26312.69 | N22: -38360.647 | P22: 763.56294 | Q22: 51922.28 | R22: -797.35424 | S22: -25609.59
A23: Véhicules neufsRev. Autres | B23: Véhicules neufs | C23: Rev. Autres | D23: 0 | E23: 0 | F23: 1600.6798 | G23: 0 | H23: 0 | I23: 1600.6798 | K23: 35.381515 | L23: 1167.59 | N23: -433.08978 | P23: 14.451618 | Q23: 982.71 | R23: -35.381515 | S23: 184.88
A24: Véhicules neufsTotal F&I | B24: Véhicules neufs | C24: Total F&I | D24: 80.814458 | E24: 850 | F24: 68692.289 | G24: 80.814458 | H24: 850 | I24: 68692.289 | J24: 33 | K24: 1028.9773 | L24: 33956.25 | M24: -47.814458 | N24: -34736.039 | O24: 68 | P24: 871.9925 | Q24: 59295.49 | S24: -25339.24
A25: Véhicules neufs | B25: Véhicules neufs | N25: -0.50567596 | S25: -0.4273384
A26: Véhicules neufs | B26: Véhicules neufs
A27: Véhicules neufsTotal Dépt. Neufs | B27: Véhicules neufs | C27: Total Dépt. Neufs | D27: 82.058453 | E27: 2833.0326 | F27: 232474.28 | G27: 82.058453 | H27: 2833.0326 | I27: 232474.28 | J27: 33 | K27: 4742.9473 | L27: 156517.26 | M27: -49.058453 | N27: -75957.015 | O27: 73 | P27: 2535.2978 | Q27: 185076.74 | R27: -40 | S27: -28559.48
A28: Véhicules neufs | B28: Véhicules neufs | M28: -0.59784765 | N28: -0.32673299 | R28: -0.54794521 | S28: -0.15431156
A29: Véhicules neufs | B29: Véhicules neufs
A30: Véhicules neufsDEPENSES | B30: Véhicules neufs | C30: DEPENSES
A31: Véhicules neufsComm. vendeurs | B31: Véhicules neufs | C31: Comm. vendeurs | D31: 0.31966893 | E31: 605.02343 | F31: 48894.64 | G31: 0.31966893 | H31: 605.02343 | I31: 48894.64 | J31: 0.31139094 | K31: 1047.4552 | L31: 34566.02 | N31: -14328.62 | P31: 609.35206 | Q31: 41435.94 | S31: -6869.92
A32: Véhicules neufsComm. F&I | B32: Véhicules neufs | C32: Comm. F&I | D32: 0.3 | E32: 255 | F32: 20607.687 | G32: 0.3 | H32: 255 | I32: 20607.687 | J32: 0.35133797 | K32: 361.51879 | L32: 11930.12 | N32: -8677.5667 | P32: 278.43412 | Q32: 18933.52 | S32: -7003.4
A33: Véhicules neufsFrais de livraison | B33: Véhicules neufs | C33: Frais de livraison | E33: 167.8493 | F33: 13564.65 | H33: 167.8493 | I33: 13564.65 | K33: 149.40182 | L33: 4930.26 | N33: -8634.3904 | P33: 186.22485 | Q33: 12663.29 | S33: -7733.03
A34: Véhicules neufsService gratuit 1 | B34: Véhicules neufs | C34: Service gratuit 1 | E34: 7.3548076 | F34: 594.37479 | H34: 7.3548076 | I34: 594.37479 | K34: 3.9393939 | L34: 130 | N34: -464.37479 | P34: 10.717647 | Q34: 728.8 | S34: -598.8
A35: Véhicules neufsEntretien stock | B35: Véhicules neufs | C35: Entretien stock | E35: 17.733118 | F35: 1433.0923 | H35: 17.733118 | I35: 1433.0923 | K35: 120.78636 | L35: 3985.95 | N35: 2552.8577 | P35: 13.796029 | Q35: 938.13 | S35: 3047.82
A36: Véhicules neufsPublicité 1 | B36: Véhicules neufs | C36: Publicité 1 | E36: 195.93765 | F36: 15834.595 | H36: 195.93765 | I36: 15834.595 | K36: 401.51273 | L36: 13249.92 | N36: -2584.6752 | P36: 179.49603 | Q36: 12205.73 | S36: 1044.19
A37: Véhicules neufsIntérêt de gros | B37: Véhicules neufs | C37: Intérêt de gros | E37: 101.02946 | F37: 8164.6412 | H37: 101.02946 | I37: 8164.6412 | K37: 10.32303 | L37: 340.66 | N37: -7823.9812 | P37: 226.95059 | Q37: 15432.64 | S37: -15091.98
A38: Véhicules neufs[...] | B38: Véhicules neufs | C38: [...] | E38: 0 | F38: 0 | H38: 0 | I38: 0 | K38: 0 | L38: 0 | N38: 0 | P38: 0 | Q38: 0 | S38: 0
A39: Véhicules neufs[...] | B39: Véhicules neufs | C39: [...] | E39: 0 | F39: 0 | H39: 0 | I39: 0 | K39: 0 | L39: 0 | N39: 0 | P39: 0 | Q39: 0 | S39: 0
A40: Véhicules neufs[...] | B40: Véhicules neufs | C40: [...] | E40: 0 | F40: 0 | H40: 0 | I40: 0 | K40: 0 | L40: 0 | N40: 0 | P40: 0 | Q40: 0 | S40: 0
A41: Véhicules neufsTOTAL VARIABLES | B41: Véhicules neufs | C41: TOTAL VARIABLES | D41: % brut | E41: 0.46927206 | F41: 109093.68 | G41: % brut | H41: 0.46927206 | I41: 109093.68 | J41: % brut | K41: 0.44169525 | L41: 69132.93 | N41: -39960.751 | O41: % brut | P41: 0.55294928 | Q41: 102338.05 | S41: -33205.12
A42: Véhicules neufsSalaires cadres | B42: Véhicules neufs | C42: Salaires cadres | F42: 15359.234 | I42: 15359.234 | L42: 19366.96 | N42: 4007.7261 | Q42: 23208.79 | S42: -3841.83 | U42: Indemnité D. Giguère
A43: Véhicules neufsSalaires commis | B43: Véhicules neufs | C43: Salaires commis | F43: 9386.1061 | I43: 9386.1061 | L43: 8185.42 | N43: -1200.6861 | Q43: 9482.66 | S43: -1297.24
A44: Véhicules neufsSalaires autres | B44: Véhicules neufs | C44: Salaires autres | F44: 8515.8839 | I44: 8515.8839 | L44: 3308.98 | N44: -5206.9039 | Q44: 9954.62 | S44: -6645.64
A45: Véhicules neufsSalaires spécialistes | B45: Véhicules neufs | C45: Salaires spécialistes | F45: 0 | I45: 0 | L45: 0 | N45: 0 | Q45: 0 | S45: 0
A46: Véhicules neufs[...] | B46: Véhicules neufs | C46: [...] | F46: 0 | I46: 0 | L46: 0 | N46: 0 | Q46: 0 | S46: 0
A47: Véhicules neufs[...] | B47: Véhicules neufs | C47: [...] | F47: 0 | I47: 0 | L47: 0 | N47: 0 | Q47: 0 | S47: 0
A48: Véhicules neufs[...] | B48: Véhicules neufs | C48: [...] | F48: 0 | I48: 0 | L48: 0 | N48: 0 | Q48: 0 | S48: 0
A49: Véhicules neufsSalaires en absences | B49: Véhicules neufs | C49: Salaires en absences | F49: 12474.718 | I49: 12474.718 | L49: 12609.86 | N49: 135.14193 | Q49: 13664.22 | S49: -1054.36
A50: Véhicules neufsDéduction à la source | B50: Véhicules neufs | C50: Déduction à la source | F50: 11172.389 | I50: 11172.389 | L50: 19757.49 | N50: 8585.1012 | Q50: 10566.27 | S50: 9191.22
A51: Véhicules neufsBénéfices marginaux | B51: Véhicules neufs | C51: Bénéfices marginaux | F51: 8872.1911 | I51: 8872.1911 | L51: 6579.1 | N51: -2293.0911 | Q51: 7572.49 | S51: -993.39
A52: Véhicules neufsCsst | B52: Véhicules neufs | C52: Csst | F52: 3614.5964 | I52: 3614.5964 | L52: 2234.86 | N52: -1379.7364 | Q52: 1761.05 | S52: 473.81
A53: Véhicules neufs[...] | B53: Véhicules neufs | C53: [...] | F53: 0 | I53: 0 | L53: 0 | N53: 0 | Q53: 0 | S53: 0
A54: Véhicules neufsTOTAL PERSONNEL | B54: Véhicules neufs | C54: TOTAL PERSONNEL | D54: % brut | E54: 0.29850665 | F54: 69395.118 | G54: % brut | H54: 0.29850665 | I54: 69395.118 | J54: % brut | K54: 0.46028579 | L54: 72042.67 | N54: 2647.5519 | O54: % brut | P54: 0.41177568 | Q54: 76210.1 | S54: -4167.43
A55: Véhicules neufsPublicité 2 | B55: Véhicules neufs | C55: Publicité 2 | F55: 0 | I55: 0 | L55: 0 | N55: 0 | Q55: 0 | S55: 0
A56: Véhicules neufsService gratuit 2 | B56: Véhicules neufs | C56: Service gratuit 2 | F56: 0 | I56: 0 | L56: 0 | N56: 0 | Q56: 0 | S56: 0
A57: Véhicules neufsFrais véhicules de cie | B57: Véhicules neufs | C57: Frais véhicules de cie | F57: 7322.94 | I57: 7322.94 | L57: 6651.33 | N57: -671.61 | Q57: 5494.87 | S57: 1156.46
A58: Véhicules neufsInformatique | B58: Véhicules neufs | C58: Informatique | F58: 6834.1886 | I58: 6834.1886 | L58: 7009.13 | N58: 174.94141 | Q58: 4538.32 | S58: 2470.81
A59: Véhicules neufsFrais de déplacement | B59: Véhicules neufs | C59: Frais de déplacement | F59: 792.1418 | I59: 792.1418 | L59: 618.31 | N59: -173.8318 | Q59: 209.82 | S59: 408.49
A60: Véhicules neufsServices extérieurs | B60: Véhicules neufs | C60: Services extérieurs | F60: 6627.0466 | I60: 6627.0466 | L60: 6773.58 | N60: 146.53342 | Q60: 8488.96 | S60: -1715.38
A61: Véhicules neufsFournitures autres | B61: Véhicules neufs | C61: Fournitures autres | F61: 96.216577 | I61: 96.216577 | L61: 0 | N61: -96.216577 | Q61: 477.01 | S61: -477.01
A62: Véhicules neufsUniformes | B62: Véhicules neufs | C62: Uniformes | F62: 51.12696 | I62: 51.12696 | L62: 0 | N62: -51.12696 | Q62: 0 | S62: 0
A63: Véhicules neufsPapeterie | B63: Véhicules neufs | C63: Papeterie | F63: 652.86432 | I63: 652.86432 | L63: 742.41 | N63: 89.54568 | Q63: 548.68 | S63: 193.73
A64: Véhicules neufsTéléphone | B64: Véhicules neufs | C64: Téléphone | F64: 301.46453 | I64: 301.46453 | L64: 241.75 | N64: -59.714527 | Q64: 130.22 | S64: 111.53
A65: Véhicules neufsFrais postaux | B65: Véhicules neufs | C65: Frais postaux | F65: 160.91707 | I65: 160.91707 | L65: 172.95 | N65: 12.032927 | Q65: 134.19 | S65: 38.76
A66: Véhicules neufsDivers | B66: Véhicules neufs | C66: Divers | F66: 776.23359 | I66: 776.23359 | L66: 920.62 | N66: 144.38641 | Q66: 264.06 | S66: 656.56
... A68: Véhicules neufsFrais bancaires | B68: Véhicules neufs | C68: Frais bancaires | F68: 3359.0496 | I68: 3359.0496 | L68: 4180.9365 | N68: 821.88691 | Q68: 4056.885 | S68: 124.0515
A69: Véhicules neufs[...] | B69: Véhicules neufs | C69: [...] | F69: 0 | I69: 0 | N69: 0 | Q69: 0 | S69: 0
A70: Véhicules neufs[...] | B70: Véhicules neufs | C70: [...] | F70: 0 | I70: 0 | L70: 0 | N70: 0 | Q70: 0 | S70: 0
A71: Véhicules neufs[...] | B71: Véhicules neufs | C71: [...] | F71: 0 | I71: 0 | L71: 0 | N71: 0 | Q71: 0 | S71: 0
A72: Véhicules neufsTOTAL SEMI-FIXES | B72: Véhicules neufs | C72: TOTAL SEMI-FIXES | D72: % brut | E72: 0.12099165 | F72: 28127.446 | G72: % brut | H72: 0.12099165 | I72: 28127.446 | J72: % brut | K72: 0.17774114 | L72: 27819.556 | N72: -307.88937 | O72: % brut | P72: 0.13435694 | Q72: 24866.345 | S72: 2953.2115
A73: Véhicules neufs | B73: Véhicules neufs
A74: Véhicules neufsTOTAL DES DÉPENSES | B74: Véhicules neufs | C74: TOTAL DES DÉPENSES | D74: % brut | E74: 0.88877036 | F74: 206616.24 | G74: % brut | H74: 0.88877036 | I74: 206616.24 | J74: % brut | K74: 1.0797222 | L74: 168995.16 | N74: -37621.088 | O74: % brut | P74: 1.0990819 | Q74: 203414.5 | S74: -34419.339
A75: Véhicules neufsProgramme neuf 1 | B75: Véhicules neufs | C75: Programme neuf 1 | F75: 0 | I75: 0 | L75: 0 | N75: 0 | Q75: 0
A76: Véhicules neufsProgramme neuf 2 | B76: Véhicules neufs | C76: Programme neuf 2 | F76: 0 | I76: 0 | L76: 0 | N76: 0 | Q76: 0 | S76: 0
A77: Véhicules neufsProgramme neuf 3 | B77: Véhicules neufs | C77: Programme neuf 3 | F77: 0 | I77: 0 | L77: 0 | N77: 0 | Q77: 0 | S77: 0
A78: Véhicules neufsHoldbacks | B78: Véhicules neufs | C78: Holdbacks | F78: 85775.868 | I78: 85775.868 | L78: 36636 | N78: -49139.868 | Q78: 64999 | S78: -28363
A79: Véhicules neufs[...] | B79: Véhicules neufs | C79: [...] | F79: 0 | I79: 0 | L79: 0 | N79: 0 | Q79: 0 | S79: 0
A80: Véhicules neufs[...] | B80: Véhicules neufs | C80: [...] | F80: 0 | I80: 0 | L80: 0 | N80: 0 | Q80: 0 | S80: 0
A81: Véhicules neufs[...] | B81: Véhicules neufs | C81: [...] | F81: 0 | I81: 0 | L81: 0 | N81: 0 | Q81: 0 | S81: 0
A82: Véhicules neufsFrais administration | B82: Véhicules neufs | C82: Frais administration | F82: 29467.19 | I82: 29467.19 | J82: 29.095238 | K82: 0.88167388 | L82: 11609 | N82: -17858.19 | Q82: 18363 | S82: -6754
A83: Véhicules neufsAUTRES REVENUS | B83: Véhicules neufs | C83: AUTRES REVENUS | F83: 115243.06 | I83: 115243.06 | L83: 48245 | N83: -66998.059 | Q83: 83362 | S83: -35117
A84: Véhicules neufs | B84: Véhicules neufs
A85: Véhicules neufsPROFIT DÉPARTEMENTAL | B85: Véhicules neufs | C85: PROFIT DÉPARTEMENTAL | F85: 141101.09 | I85: 141101.09 | L85: 35767.103 | N85: -105333.99 | Q85: 65024.245 | S85: -29257.141
C89: Volks | K89: Véhicules usagés | S89: Réalisé, Avril 2022
D91: BUDGET ORIGINAL | G91: BUDGET RÉVISÉ | J91: RÉALISATION | M91: ÉCART réel / révisé | O91: ANNÉE PRÉCÉDENTE | R91: ÉCART réel / original
D92: UNITE | E92: $P/UNITÉ | F92: $PROFITS | G92: UNITE | H92: $P/UNITÉ | I92: $PROFITS | J92: UNITE | K92: $P/UNITE | L92: $PROFITS | M92: UNITÉ | N92: $PROFITS | O92: UNITE | P92: $P/UNITE | Q92: $PROFITS | R92: UNITE | S92: $PROFITS
A93: Véhicules usagésVentes nettes | B93: Véhicules usagés | C93: Ventes nettes | F93: 1380057.9 | I93: 1380057.9 | L93: 1272948.7 | Q93: 1208511
A94: Véhicules usagésCertifié | B94: Véhicules usagés | C94: Certifié | D94: 42.123786 | E94: 1300 | F94: 54760.922 | G94: 42.123786 | H94: 1300 | I94: 54760.922 | J94: 26 | K94: 2395.8292 | L94: 62291.56 | M94: -16.123786 | N94: 7530.6377 | O94: 39 | P94: 1018.0956 | Q94: 39705.73 | R94: -13 | S94: 22585.83
A95: Véhicules usagésNon Certifié | B95: Véhicules usagés | C95: Non Certifié | D95: 2.3665049 | E95: 900 | F95: 2129.8544 | G95: 2.3665049 | H95: 900 | I95: 2129.8544 | J95: 5 | K95: 1906.164 | L95: 9530.82 | O95: 2 | P95: 755.545 | Q95: 1511.09 | R95: 3 | S95: 8019.73
A96: Véhicules usagésTotal Usagés | B96: Véhicules usagés | C96: Total Usagés | D96: 44.490291 | E96: 1278.7234 | F96: 56890.777 | G96: 44.490291 | H96: 1278.7234 | I96: 56890.777 | J96: 31 | K96: 2316.851 | L96: 71822.38 | M96: -13.490291 | N96: 14931.603 | O96: 41 | P96: 1005.2883 | Q96: 41216.82 | R96: -10 | S96: 30605.56
A97: Véhicules usagés | B97: Véhicules usagés | E97: 0 | H97: 0 | M97: -0.30321877 | N97: 0.26246088 | R97: -0.24390244 | S97: 0.74255025
A98: Véhicules usagésUS | B98: Véhicules usagés | C98: US
A99: Véhicules usagésVentes au Gros | B99: Véhicules usagés | C99: Ventes au Gros | D99: 38.715136 | E99: 212 | F99: 8207.6089 | G99: 38.715136 | H99: 212 | I99: 8207.6089 | J99: 21 | K99: 363.17905 | L99: 7626.76 | M99: -17.715136 | N99: -580.84888 | O99: 25 | P99: 340.5116 | Q99: 8512.79 | R99: -4 | S99: -886.03
A100: Véhicules usagés | B100: Véhicules usagés
A101: Véhicules usagésRev. Finances | B101: Véhicules usagés | C101: Rev. Finances | D101: 0 | E101: 0 | F101: 29317.363 | G101: 0 | H101: 0 | I101: 29317.363 | K101: 1317.9881 | L101: 40857.63 | N101: 11540.267 | P101: 522.44707 | Q101: 21420.33 | R101: -1317.9881 | S101: 19437.3
A102: Véhicules usagésRev. Protections | B102: Véhicules usagés | C102: Rev. Protections | D102: 0 | E102: 0 | F102: 51690.808 | G102: 0 | H102: 0 | I102: 51690.808 | K102: 1280.9784 | L102: 39710.33 | N102: -11980.478 | P102: 981.94195 | Q102: 40259.62 | R102: -1280.9784 | S102: -549.29
A103: Véhicules usagésRev. Autres | B103: Véhicules usagés | C103: Rev. Autres | D103: 0 | E103: 0 | F103: 1466.0978 | G103: 0 | H103: 0 | I103: 1466.0978 | K103: 72.283226 | L103: 2240.78 | N103: 774.6822 | P103: 4.9360976 | Q103: 202.38 | R103: -72.283226 | S103: 2038.4
A104: Véhicules usagésTotal F&I | B104: Véhicules usagés | C104: Total F&I | D104: 44.490291 | E104: 1853.7588 | F104: 82474.269 | G104: 44.490291 | H104: 1853.7588 | I104: 82474.269 | J104: 31 | K104: 2671.2497 | L104: 82808.74 | M104: -13.490291 | N104: 334.47108 | O104: 41 | P104: 1509.3251 | Q104: 61882.33 | S104: 20926.41
A105: Véhicules usagés | B105: Véhicules usagés | N105: 0.0040554597 | S105: 0.33816455
...

Sheet VW 2022-05
C1: Volks | K1: Véhicules neufs | S1: Réalisé, Mai 2022
D2: X | E2: O | F2: U | G2: X | H2: O | I2: U | J2: NB | L2: $ | O2: NB | Q2: $ | V2: *** *** NE PAS EFFACER *** ***
D3: BUDGET ORIGINAL | G3: BUDGET REVISE | J3: RÉALISATION | M3: ÉCART réel / révisé | O3: ANNÉE PRÉCÉDENTE | R3: ÉCART réel / original | V3: NEUF | W3: 0.45
D4: UNITE | E4: $P/UNITÉ | F4: $PROFITS | G4: UNITE | H4: $P/UNITÉ | I4: $PROFITS | J4: UNITE | K4: $P/UNITE | L4: $PROFITS | M4: UNITÉ | N4: $PROFITS | O4: UNITE | P4: $P/UNITE | Q4: $PROFITS | R4: UNITE | S4: $PROFITS | V4: USAGE | W4: 0.1
A5: Véhicules neufsVentes nettes | B5: Véhicules neufs | C5: Ventes nettes | F5: 3809901.5 | I5: 3809901.5 | L5: 2400932.7 | Q5: 3829078.6 | V5: SERVICE | W5: 0.225
A6: Véhicules neufsAutos détail | B6: Véhicules neufs | C6: Autos détail | D6: 19.431325 | E6: 1450.6298 | F6: 28187.659 | G6: 19.431325 | H6: 1450.6298 | I6: 28187.659 | J6: 7 | K6: 3196.7429 | L6: 22377.2 | M6: -12.431325 | N6: -5810.4588 | O6: 25 | P6: 1020.836 | Q6: 25520.9 | R6: -18 | S6: -3143.7 | V6: CARROSSERIE | W6: 0.025
A7: Véhicules neufsCamions détail | B7: Véhicules neufs | C7: Camions détail | D7: 67.084337 | E7: 2081.8276 | F7: 139658.02 | G7: 67.084337 | H7: 2081.8276 | I7: 139658.02 | J7: 36 | K7: 3783.5983 | L7: 136209.54 | M7: -31.084337 | N7: -3448.4841 | O7: 58 | P7: 2126.4852 | Q7: 123336.14 | R7: -22 | S7: 12873.4 | V7: PIECES | W7: 0.2
A8: Véhicules neufsSprinter | B8: Véhicules neufs | C8: Sprinter | D8: 0 | E8: 0 | F8: 0 | G8: 0 | H8: 0 | I8: 0 | J8: 0 | K8: 0 | L8: 0 | M8: 0 | N8: 0 | O8: 0 | P8: 0 | Q8: 0 | R8: 0 | S8: 0 | W8: 1
A9: Véhicules neufsMoto détail | B9: Véhicules neufs | C9: Moto détail | D9: 0 | E9: 0 | F9: 0 | G9: 0 | H9: 0 | I9: 0 | J9: 0 | K9: 0 | L9: 0 | M9: 0 | N9: 0 | O9: 0 | P9: 0 | Q9: 0 | R9: 0 | S9: 0
A10: Véhicules neufs[...] | B10: Véhicules neufs | C10: [...] | D10: 0 | E10: 0 | F10: 0 | G10: 0 | H10: 0 | I10: 0 | J10: 0 | K10: 0 | L10: 0 | M10: 0 | N10: 0 | O10: 0 | P10: 0 | Q10: 0 | R10: 0 | S10: 0
A11: Véhicules neufs[...] | B11: Véhicules neufs | C11: [...] | D11: 0 | E11: 0 | F11: 0 | G11: 0 | H11: 0 | I11: 0 | J11: 0 | K11: 0 | L11: 0 | M11: 0 | N11: 0 | O11: 0 | P11: 0 | Q11: 0 | R11: 0 | S11: 0
A12: Véhicules neufs[...] | B12: Véhicules neufs | C12: [...] | D12: 0 | E12: 0 | F12: 0 | G12: 0 | H12: 0 | I12: 0 | J12: 0 | K12: 0 | L12: 0 | M12: 0 | N12: 0 | O12: 0 | P12: 0 | Q12: 0 | R12: 0 | S12: 0
A13: Véhicules neufsTotal Neufs | B13: Véhicules neufs | C13: Total Neufs | D13: 86.515663 | E13: 1940.0612 | F13: 167845.68 | G13: 86.515663 | H13: 1940.0612 | I13: 167845.68 | J13: 43 | K13: 3688.0637 | L13: 158586.74 | M13: -43.515663 | N13: -9258.9429 | O13: 83 | P13: 1793.4583 | Q13: 148857.04 | R13: -40 | S13: 9729.7
A14: Véhicules neufs | B14: Véhicules neufs | R14: -0.48192771 | S14: 0.065362713
A15: Véhicules neufsEx-Démos et courtoisies | B15: Véhicules neufs | C15: Ex-Démos et courtoisies | D15: 8.0963855 | E15: 1386.1016 | F15: 11222.413 | G15: 8.0963855 | H15: 1386.1016 | I15: 11222.413 | J15: 3 | K15: 5865.1167 | L15: 17595.35 | M15: -5.0963855 | N15: 6372.9369 | O15: 4 | P15: 2427.275 | Q15: 9709.1 | R15: -1 | S15: 7886.25
A16: Véhicules neufs | B16: Véhicules neufs
A17: Véhicules neufsFlottes | B17: Véhicules neufs | C17: Flottes | D17: 1.4563843 | E17: 1938.8732 | F17: 2823.7445 | G17: 1.4563843 | H17: 1938.8732 | I17: 2823.7445 | J17: 0 | K17: 0 | L17: 0 | M17: -1.4563843 | N17: -2823.7445 | O17: 4 | P17: 2789.6125 | Q17: 11158.45 | R17: -4 | S17: -11158.45
A18: Véhicules neufs | B18: Véhicules neufs
A19: Véhicules neufsRachat bail | B19: Véhicules neufs | C19: Rachat bail | D19: 0 | E19: 0 | F19: 8416.039 | G19: 0 | H19: 0 | I19: 8416.039 | L19: 10153.06 | N19: 1737.021 | Q19: 6141.99 | R19: 0 | S19: 4011.07
A20: Véhicules neufs | B20: Véhicules neufs
A21: Véhicules neufsRev. Finances | B21: Véhicules neufs | C21: Rev. Finances | D21: 0 | E21: 0 | F21: 2831.1485 | G21: 0 | H21: 0 | I21: 2831.1485 | K21: 235.93391 | L21: 10852.96 | N21: 8021.8115 | P21: 0 | Q21: 0 | R21: -235.93391 | S21: 10852.96
A22: Véhicules neufsRev. Protections | B22: Véhicules neufs | C22: Rev. Protections | D22: 0 | E22: 0 | F22: 75715.126 | G22: 0 | H22: 0 | I22: 75715.126 | K22: 1009.41 | L22: 46432.86 | N22: -29282.266 | P22: 765.23471 | Q22: 66575.42 | R22: -1009.41 | S22: -20142.56
A23: Véhicules neufsRev. Autres | B23: Véhicules neufs | C23: Rev. Autres | D23: 0 | E23: 0 | F23: 1873.9666 | G23: 0 | H23: 0 | I23: 1873.9666 | K23: 6.1243478 | L23: 281.72 | N23: -1592.2466 | P23: 18.082414 | Q23: 1573.17 | R23: -6.1243478 | S23: -1291.45
A24: Véhicules neufsTotal F&I | B24: Véhicules neufs | C24: Total F&I | D24: 94.612048 | E24: 850 | F24: 80420.241 | G24: 94.612048 | H24: 850 | I24: 80420.241 | J24: 46 | K24: 1251.4683 | L24: 57567.54 | M24: -48.612048 | N24: -22852.701 | O24: 87 | P24: 783.31713 | Q24: 68148.59 | S24: -10581.05
A25: Véhicules neufs | B25: Véhicules neufs | N25: -0.28416603 | S25: -0.1552644
A26: Véhicules neufs | B26: Véhicules neufs
A27: Véhicules neufsTotal Dépt. Neufs | B27: Véhicules neufs | C27: Total Dépt. Neufs | D27: 96.068433 | E27: 2818.0758 | F27: 270728.12 | G27: 96.068433 | H27: 2818.0758 | I27: 270728.12 | J27: 46 | K27: 5302.2324 | L27: 243902.69 | M27: -50.068433 | N27: -26825.43 | O27: 91 | P27: 2681.4854 | Q27: 244015.17 | R27: -45 | S27: -112.48
A28: Véhicules neufs | B28: Véhicules neufs | M28: -0.52117466 | N28: -0.099086236 | R28: -0.49450549 | S28: -0.00046095495
A29: Véhicules neufs | B29: Véhicules neufs
A30: Véhicules neufsDEPENSES | B30: Véhicules neufs | C30: DEPENSES
A31: Véhicules neufsComm. vendeurs | B31: Véhicules neufs | C31: Comm. vendeurs | D31: 0.31286677 | E31: 592.14929 | F31: 56024.457 | G31: 0.31286677 | H31: 592.14929 | I31: 56024.457 | J31: 0.28520487 | K31: 1092.3476 | L31: 50247.99 | N31: -5776.4671 | P31: 611.33368 | Q31: 53186.03 | S31: -2938.04
A32: Véhicules neufsComm. F&I | B32: Véhicules neufs | C32: Comm. F&I | D32: 0.3 | E32: 255 | F32: 24126.072 | G32: 0.3 | H32: 255 | I32: 24126.072 | J32: 0.36279907 | K32: 454.03152 | L32: 20885.45 | N32: -3240.6223 | P32: 240.78989 | Q32: 20948.72 | S32: -63.27 | U32: 0.29703872 | V32: <<- F&A total Neuf Usagé Rachat
A33: Véhicules neufsFrais de livraison | B33: Véhicules neufs | C33: Frais de livraison | E33: 167.8493 | F33: 15880.566 | H33: 167.8493 | I33: 15880.566 | K33: 104.73239 | L33: 4817.69 | N33: -11062.876 | P33: 74.75069 | Q33: 6503.31 | S33: -1685.62
A34: Véhicules neufsService gratuit 1 | B34: Véhicules neufs | C34: Service gratuit 1 | E34: 7.3548076 | F34: 695.85341 | H34: 7.3548076 | I34: 695.85341 | K34: 0 | L34: 0 | N34: -695.85341 | P34: 6.8565517 | Q34: 596.52 | S34: -596.52
A35: Véhicules neufsEntretien stock | B35: Véhicules neufs | C35: Entretien stock | E35: 17.733118 | F35: 1677.7666 | H35: 17.733118 | I35: 1677.7666 | K35: 100.76913 | L35: 4635.38 | N35: 2957.6134 | P35: 13.448276 | Q35: 1170 | S35: 3465.38
A36: Véhicules neufsPublicité 1 | B36: Véhicules neufs | C36: Publicité 1 | E36: 195.93765 | F36: 18538.063 | H36: 195.93765 | I36: 18538.063 | K36: 382.71152 | L36: 17604.73 | N36: -933.33265 | P36: 119.94092 | Q36: 10434.86 | S36: 7169.87
A37: Véhicules neufsIntérêt de gros | B37: Véhicules neufs | C37: Intérêt de gros | E37: 83.856314 | F37: 7933.8176 | H37: 83.856314 | I37: 7933.8176 | K37: 5.9121739 | L37: 271.96 | N37: -7661.8576 | P37: 161.06483 | Q37: 14012.64 | S37: -13740.68
A38: Véhicules neufs[...] | B38: Véhicules neufs | C38: [...] | E38: 0 | F38: 0 | H38: 0 | I38: 0 | K38: 0 | L38: 0 | N38: 0 | P38: 0 | Q38: 0 | S38: 0
A39: Véhicules neufs[...] | B39: Véhicules neufs | C39: [...] | E39: 0 | F39: 0 | H39: 0 | I39: 0 | K39: 0 | L39: 0 | N39: 0 | P39: 0 | Q39: 0 | S39: 0
A40: Véhicules neufs[...] | B40: Véhicules neufs | C40: [...] | E40: 0 | F40: 0 | H40: 0 | I40: 0 | K40: 0 | L40: 0 | N40: 0 | P40: 0 | Q40: 0 | S40: 0
A41: Véhicules neufsTOTAL VARIABLES | B41: Véhicules neufs | C41: TOTAL VARIABLES | D41: % brut | E41: 0.46126201 | F41: 124876.6 | G41: % brut | H41: 0.46126201 | I41: 124876.6 | J41: % brut | K41: 0.4036987 | L41: 98463.2 | N41: -26413.396 | O41: % brut | P41: 0.43789114 | Q41: 106852.08 | S41: -8388.88
A42: Véhicules neufsSalaires cadres | B42: Véhicules neufs | C42: Salaires cadres | F42: 15886.261 | I42: 15886.261 | L42: 14110.59 | N42: -1775.6709 | Q42: 21334.91 | S42: -7224.32
A43: Véhicules neufsSalaires commis | B43: Véhicules neufs | C43: Salaires commis | F43: 9822.0278 | I43: 9822.0278 | L43: 7742.61 | N43: -2079.4178 | Q43: 9816.59 | S43: -2073.98
A44: Véhicules neufsSalaires autres | B44: Véhicules neufs | C44: Salaires autres | F44: 8921.4022 | I44: 8921.4022 | L44: 4148.58 | N44: -4772.8222 | Q44: 8653.41 | S44: -4504.83
A45: Véhicules neufsSalaires spécialistes | B45: Véhicules neufs | C45: Salaires spécialistes | F45: 0 | I45: 0 | L45: 0 | N45: 0 | Q45: 0 | S45: 0
A46: Véhicules neufs[...] | B46: Véhicules neufs | C46: [...] | F46: 0 | I46: 0 | L46: 0 | N46: 0 | Q46: 0 | S46: 0
A47: Véhicules neufs[...] | B47: Véhicules neufs | C47: [...] | F47: 0 | I47: 0 | L47: 0 | N47: 0 | Q47: 0 | S47: 0
A48: Véhicules neufs[...] | B48: Véhicules neufs | C48: [...] | F48: 0 | I48: 0 | L48: 0 | N48: 0 | Q48: 0 | S48: 0
A49: Véhicules neufsSalaires en absences | B49: Véhicules neufs | C49: Salaires en absences | F49: 13866.553 | I49: 13866.553 | L49: 16348.41 | N49: 2481.8567 | Q49: 15115.93 | S49: 1232.48
A50: Véhicules neufsDéduction à la source | B50: Véhicules neufs | C50: Déduction à la source | F50: 12418.92 | I50: 12418.92 | L50: 18335.87 | N50: 5916.9501 | Q50: 12289.25 | S50: 6046.62
A51: Véhicules neufsBénéfices marginaux | B51: Véhicules neufs | C51: Bénéfices marginaux | F51: 9862.0834 | I51: 9862.0834 | L51: 6650.68 | N51: -3211.4034 | Q51: 8807.29 | S51: -2156.61
A52: Véhicules neufsCsst | B52: Véhicules neufs | C52: Csst | F52: 4017.8858 | I52: 4017.8858 | L52: 2116.52 | N52: -1901.3658 | Q52: 2048.21 | S52: 68.31
A53: Véhicules neufs[...] | B53: Véhicules neufs | C53: [...] | F53: 0 | I53: 0 | L53: 0 | N53: 0 | Q53: 0 | S53: 0
A54: Véhicules neufsTOTAL PERSONNEL | B54: Véhicules neufs | C54: TOTAL PERSONNEL | D54: % brut | E54: 0.27627397 | F54: 74795.133 | G54: % brut | H54: 0.27627397 | I54: 74795.133 | J54: % brut | K54: 0.28475807 | L54: 69453.26 | N54: -5341.8734 | O54: % brut | P54: 0.31992105 | Q54: 78065.59 | S54: -8612.33
A55: Véhicules neufsPublicité 2 | B55: Véhicules neufs | C55: Publicité 2 | F55: 0 | I55: 0 | L55: 0 | N55: 0 | Q55: 0 | S55: 0
A56: Véhicules neufsService gratuit 2 | B56: Véhicules neufs | C56: Service gratuit 2 | F56: 0 | I56: 0 | L56: 0 | N56: 0 | Q56: 0 | S56: 0
A57: Véhicules neufsFrais véhicules de cie | B57: Véhicules neufs | C57: Frais véhicules de cie | F57: 7322.94 | I57: 7322.94 | L57: 7787.55 | N57: 464.61 | Q57: 6376 | S57: 1411.55
A58: Véhicules neufsInformatique | B58: Véhicules neufs | C58: Informatique | F58: 6834.1988 | I58: 6834.1988 | L58: 7155.57 | N58: 321.37116 | Q58: 6391.27 | S58: 764.3
A59: Véhicules neufsFrais de déplacement | B59: Véhicules neufs | C59: Frais de déplacement | F59: 792.1418 | I59: 792.1418 | L59: 1547.89 | N59: 755.7482 | Q59: 612.46 | S59: 935.43
A60: Véhicules neufsServices extérieurs | B60: Véhicules neufs | C60: Services extérieurs | F60: 6518.7074 | I60: 6518.7074 | L60: 5848.73 | N60: -669.97738 | Q60: 7206.23 | S60: -1357.5
A61: Véhicules neufsFournitures autres | B61: Véhicules neufs | C61: Fournitures autres | F61: 107.68716 | I61: 107.68716 | L61: 15.24 | N61: -92.44716 | Q61: 74.93 | S61: -59.69
A62: Véhicules neufsUniformes | B62: Véhicules neufs | C62: Uniformes | F62: 57.222126 | I62: 57.222126 | L62: 0 | N62: -57.222126 | Q62: 0 | S62: 0
A63: Véhicules neufsPapeterie | B63: Véhicules neufs | C63: Papeterie | F63: 652.86432 | I63: 652.86432 | L63: 677.38 | N63: 24.51568 | Q63: 755.68 | S63: -78.3
A64: Véhicules neufsTéléphone | B64: Véhicules neufs | C64: Téléphone | F64: 301.46453 | I64: 301.46453 | L64: 298.9 | N64: -2.5645267 | Q64: 257.26 | S64: 41.64
A65: Véhicules neufsFrais postaux | B65: Véhicules neufs | C65: Frais postaux | F65: 160.91707 | I65: 160.91707 | L65: 101.47 | N65: -59.447073 | Q65: 162.85 | S65: -61.38
A66: Véhicules neufsDivers | B66: Véhicules neufs | C66: Divers | F66: 776.23359 | I66: 776.23359 | L66: 267.61 | N66: -508.62359 | Q66: 1198.42 | S66: -930.81
... A68: Véhicules neufsFrais bancaires | B68: Véhicules neufs | C68: Frais bancaires | F68: 3066.8322 | I68: 3066.8322 | L68: 4255.965 | N68: 1189.1328 | Q68: 3102.8445 | S68: 1153.1205
A69: Véhicules neufs[...] | B69: Véhicules neufs | C69: [...] | F69: 0 | I69: 0 | N69: 0 | Q69: 0 | S69: 0
A70: Véhicules neufs[...] | B70: Véhicules neufs | C70: [...] | F70: 0 | I70: 0 | L70: 0 | N70: 0 | Q70: 0 | S70: 0
A71: Véhicules neufs[...] | B71: Véhicules neufs | C71: [...] | F71: 0 | I71: 0 | L71: 0 | N71: 0 | Q71: 0 | S71: 0
A72: Véhicules neufsTOTAL SEMI-FIXES | B72: Véhicules neufs | C72: TOTAL SEMI-FIXES | D72: % brut | E72: 0.10248091 | F72: 27744.465 | G72: % brut | H72: 0.10248091 | I72: 27744.465 | J72: % brut | K72: 0.11844644 | L72: 28889.405 | N72: 1144.9398 | O72: % brut | P72: 0.11057212 | Q72: 26981.274 | S72: 1908.1305
A73: Véhicules neufs | B73: Véhicules neufs
A74: Véhicules neufsTOTAL DES DÉPENSES | B74: Véhicules neufs | C74: TOTAL DES DÉPENSES | D74: % brut | E74: 0.84001689 | F74: 227416.19 | G74: % brut | H74: 0.84001689 | I74: 227416.19 | J74: % brut | K74: 0.80690322 | L74: 196805.87 | N74: -30610.33 | O74: % brut | P74: 0.86838431 | Q74: 211898.94 | S74: -15093.079
A75: Véhicules neufsProgramme neuf 1 | B75: Véhicules neufs | C75: Programme neuf 1 | F75: 0 | I75: 0 | L75: 0 | N75: 0 | Q75: 0
A76: Véhicules neufsProgramme neuf 2 | B76: Véhicules neufs | C76: Programme neuf 2 | F76: 0 | I76: 0 | L76: 0 | N76: 0 | Q76: 0 | S76: 0
A77: Véhicules neufsProgramme neuf 3 | B77: Véhicules neufs | C77: Programme neuf 3 | F77: 0 | I77: 0 | L77: 0 | N77: 0 | Q77: 0 | S77: 0
A78: Véhicules neufsHoldbacks | B78: Véhicules neufs | C78: Holdbacks | F78: 100420.53 | I78: 100420.53 | L78: 53351 | N78: -47069.529 | Q78: 102678 | S78: -49327
A79: Véhicules neufs[...] | B79: Véhicules neufs | C79: [...] | F79: 0 | I79: 0 | L79: 0 | N79: 0 | Q79: 0 | S79: 0
A80: Véhicules neufs[...] | B80: Véhicules neufs | C80: [...] | F80: 0 | I80: 0 | L80: 0 | N80: 0 | Q80: 0 | S80: 0
A81: Véhicules neufs[...] | B81: Véhicules neufs | C81: [...] | F81: 0 | I81: 0 | L81: 0 | N81: 0 | Q81: 0 | S81: 0
A82: Véhicules neufsFrais administration | B82: Véhicules neufs | C82: Frais administration | F82: 34498.174 | I82: 34498.174 | J82: 43.483709 | K82: 0.94529803 | L82: 17350 | N82: -17148.174 | Q82: 25377 | S82: -8027
A83: Véhicules neufsAUTRES REVENUS | B83: Véhicules neufs | C83: AUTRES REVENUS | F83: 134918.7 | I83: 134918.7 | L83: 70701 | N83: -64217.703 | Q83: 128055 | S83: -57354
A84: Véhicules neufs | B84: Véhicules neufs
A85: Véhicules neufsPROFIT DÉPARTEMENTAL | B85: Véhicules neufs | C85: PROFIT DÉPARTEMENTAL | F85: 178230.63 | I85: 178230.63 | L85: 117797.82 | N85: -60432.804 | Q85: 160171.23 | S85: -42373.401
C89: Volks | K89: Véhicules usagés | S89: Réalisé, Mai 2022
D91: BUDGET ORIGINAL | G91: BUDGET RÉVISÉ | J91: RÉALISATION | M91: ÉCART réel / révisé | O91: ANNÉE PRÉCÉDENTE | R91: ÉCART réel / original
D92: UNITE | E92: $P/UNITÉ | F92: $PROFITS | G92: UNITE | H92: $P/UNITÉ | I92: $PROFITS | J92: UNITE | K92: $P/UNITE | L92: $PROFITS | M92: UNITÉ | N92: $PROFITS | O92: UNITE | P92: $P/UNITE | Q92: $PROFITS | R92: UNITE | S92: $PROFITS
A93: Véhicules usagésVentes nettes | B93: Véhicules usagés | C93: Ventes nettes | F93: 1415444 | I93: 1415444 | L93: 1527135.3 | Q93: 1425396.5
A94: Véhicules usagésCertifié | B94: Véhicules usagés | C94: Certifié | D94: 43.203883 | E94: 1300 | F94: 56165.049 | G94: 43.203883 | H94: 1300 | I94: 56165.049 | J94: 30 | K94: 2126.6313 | L94: 63798.94 | M94: -13.203883 | N94: 7633.8915 | O94: 38 | P94: 1319.41 | Q94: 50137.58 | R94: -8 | S94: 13661.36
A95: Véhicules usagésNon Certifié | B95: Véhicules usagés | C95: Non Certifié | D95: 2.4271845 | E95: 900 | F95: 2184.466 | G95: 2.4271845 | H95: 900 | I95: 2184.466 | J95: 2 | K95: 959.56 | L95: 1919.12 | M95: -0.42718447 | N95: -265.34602 | O95: 1 | P95: -527.8 | Q95: -527.8 | R95: 1 | S95: 2446.92
A96: Véhicules usagésTotal Usagés | B96: Véhicules usagés | C96: Total Usagés | D96: 45.631068 | E96: 1278.7234 | F96: 58349.515 | G96: 45.631068 | H96: 1278.7234 | I96: 58349.515 | J96: 32 | K96: 2053.6894 | L96: 65718.06 | M96: -13.631068 | N96: 7368.5454 | O96: 39 | P96: 1272.0456 | Q96: 49609.78 | R96: -7 | S96: 16108.28
A97: Véhicules usagés | B97: Véhicules usagés | E97: 0 | H97: 0 | M97: -0.2987234 | N97: 0.12628289 | R97: -0.17948718 | S97: 0.32469969
A98: Véhicules usagésUS | B98: Véhicules usagés | C98: US
A99: Véhicules usagésVentes au Gros | B99: Véhicules usagés | C99: Ventes au Gros | D99: 39.707832 | E99: 212 | F99: 8418.0604 | G99: 39.707832 | H99: 212 | I99: 8418.0604 | J99: 23 | K99: 369.51087 | L99: 8498.75 | M99: -16.707832 | N99: 80.689607 | O99: 41 | P99: 611.62902 | Q99: 25076.79 | R99: -18 | S99: -16578.04 | U99: Incluant Utilisation de 6k$ de Réserve Usagés (2022-05)
A100: Véhicules usagés | B100: Véhicules usagés
A101: Véhicules usagésRev. Finances | B101: Véhicules usagés | C101: Rev. Finances | D101: 0 | E101: 0 | F101: 30069.09 | G101: 0 | H101: 0 | I101: 30069.09 | K101: 1377.9081 | L101: 44093.06 | N101: 14023.97 | P101: 799.67385 | Q101: 31187.28 | R101: -1377.9081 | S101: 12905.78
A102: Véhicules usagésRev. Protections | B102: Véhicules usagés | C102: Rev. Protections | D102: 0 | E102: 0 | F102: 53016.214 | G102: 0 | H102: 0 | I102: 53016.214 | K102: 1512.9972 | L102: 48415.91 | N102: -4600.3036 | P102: 1285.4226 | Q102: 50131.48 | R102: -1512.9972 | S102: -1715.57
A103: Véhicules usagésRev. Autres | B103: Véhicules usagés | C103: Rev. Autres | D103: 0 | E103: 0 | F103: 1503.6901 | G103: 0 | H103: 0 | I103: 1503.6901 | K103: 109.46 | L103: 3502.72 | N103: 1999.0299 | P103: 41.958462 | Q103: 1636.38 | R103: -109.46 | S103: 1866.34
A104: Véhicules usagésTotal F&I | B104: Véhicules usagés | C104: Total F&I | D104: 45.631068 | E104: 1853.7588 | F104: 84588.994 | G104: 45.631068 | H104: 1853.7588 | I104: 84588.994 | J104: 32 | K104: 3000.3653 | L104: 96011.69 | M104: -13.631068 | N104: 11422.696 | O104: 39 | P104: 2127.0549 | Q104: 82955.14 | S104: 13056.55
A105: Véhicules usagés | B105: Véhicules usagés | N105: 0.13503762 | S105: 0.1573929
...

Sheet VW 2022-06
C1: Volks | K1: Véhicules neufs | S1: Réalisé, Juin 2022
D2: X | E2: O | F2: U | G2: X | H2: O | I2: U | J2: NB | L2: $ | O2: NB | Q2: $ | V2: *** *** NE PAS EFFACER *** ***
D3: BUDGET ORIGINAL | G3: BUDGET REVISE | J3: RÉALISATION | M3: ÉCART réel / révisé | O3: ANNÉE PRÉCÉDENTE | R3: ÉCART réel / original | V3: NEUF | W3: 0.45
D4: UNITE | E4: $P/UNITÉ | F4: $PROFITS | G4: UNITE | H4: $P/UNITÉ | I4: $PROFITS | J4: UNITE | K4: $P/UNITE | L4: $PROFITS | M4: UNITÉ | N4: $PROFITS | O4: UNITE | P4: $P/UNITE | Q4: $PROFITS | R4: UNITE | S4: $PROFITS | V4: USAGE | W4: 0.1
A5: Véhicules neufsVentes nettes | B5: Véhicules neufs | C5: Ventes nettes | F5: 2936799 | I5: 2936799 | L5: 2836768.3 | Q5: 3829078.6 | V5: SERVICE | W5: 0.225
A6: Véhicules neufsAutos détail | B6: Véhicules neufs | C6: Autos détail | D6: 14.978313 | E6: 1450.6298 | F6: 21727.987 | G6: 14.978313 | H6: 1450.6298 | I6: 21727.987 | J6: 9 | K6: 2603.6256 | L6: 23432.63 | M6: -5.9783133 | N6: 1704.643 | O6: 25 | P6: 1020.836 | Q6: 25520.9 | R6: -16 | S6: -2088.27 | V6: CARROSSERIE | W6: 0.025
A7: Véhicules neufsCamions détail | B7: Véhicules neufs | C7: Camions détail | D7: 51.710843 | E7: 2081.8276 | F7: 107653.06 | G7: 51.710843 | H7: 2081.8276 | I7: 107653.06 | J7: 43 | K7: 3826.4693 | L7: 164538.18 | M7: -8.7108434 | N7: 56885.12 | O7: 58 | P7: 2126.4852 | Q7: 123336.14 | R7: -15 | S7: 41202.04 | V7: PIECES | W7: 0.2
A8: Véhicules neufsSprinter | B8: Véhicules neufs | C8: Sprinter | D8: 0 | E8: 0 | F8: 0 | G8: 0 | H8: 0 | I8: 0 | J8: 0 | K8: 0 | L8: 0 | M8: 0 | N8: 0 | O8: 0 | P8: 0 | Q8: 0 | R8: 0 | S8: 0 | W8: 1
A9: Véhicules neufsMoto détail | B9: Véhicules neufs | C9: Moto détail | D9: 0 | E9: 0 | F9: 0 | G9: 0 | H9: 0 | I9: 0 | J9: 0 | K9: 0 | L9: 0 | M9: 0 | N9: 0 | O9: 0 | P9: 0 | Q9: 0 | R9: 0 | S9: 0
A10: Véhicules neufs[...] | B10: Véhicules neufs | C10: [...] | D10: 0 | E10: 0 | F10: 0 | G10: 0 | H10: 0 | I10: 0 | J10: 0 | K10: 0 | L10: 0 | M10: 0 | N10: 0 | O10: 0 | P10: 0 | Q10: 0 | R10: 0 | S10: 0
A11: Véhicules neufs[...] | B11: Véhicules neufs | C11: [...] | D11: 0 | E11: 0 | F11: 0 | G11: 0 | H11: 0 | I11: 0 | J11: 0 | K11: 0 | L11: 0 | M11: 0 | N11: 0 | O11: 0 | P11: 0 | Q11: 0 | R11: 0 | S11: 0
A12: Véhicules neufs[...] | B12: Véhicules neufs | C12: [...] | D12: 0 | E12: 0 | F12: 0 | G12: 0 | H12: 0 | I12: 0 | J12: 0 | K12: 0 | L12: 0 | M12: 0 | N12: 0 | O12: 0 | P12: 0 | Q12: 0 | R12: 0 | S12: 0
A13: Véhicules neufsTotal Neufs | B13: Véhicules neufs | C13: Total Neufs | D13: 66.689157 | E13: 1940.0612 | F13: 129381.05 | G13: 66.689157 | H13: 1940.0612 | I13: 129381.05 | J13: 52 | K13: 3614.8233 | L13: 187970.81 | M13: -14.689157 | N13: 58589.763 | O13: 83 | P13: 1793.4583 | Q13: 148857.04 | R13: -31 | S13: 39113.77
A14: Véhicules neufs | B14: Véhicules neufs | R14: -0.37349398 | S14: 0.26276063
A15: Véhicules neufsEx-Démos et courtoisies | B15: Véhicules neufs | C15: Ex-Démos et courtoisies | D15: 6.2409639 | E15: 1386.1016 | F15: 8650.6101 | G15: 6.2409639 | H15: 1386.1016 | I15: 8650.6101 | J15: 4 | K15: 2132.36 | L15: 8529.44 | M15: -2.2409639 | N15: -121.1701 | O15: 4 | P15: 2427.275 | Q15: 9709.1 | R15: 0 | S15: -1179.66
A16: Véhicules neufs | B16: Véhicules neufs
A17: Véhicules neufsFlottes | B17: Véhicules neufs | C17: Flottes | D17: 1.1226296 | E17: 1938.8732 | F17: 2176.6364 | G17: 1.1226296 | H17: 1938.8732 | I17: 2176.6364 | J17: 0 | K17: 0 | L17: 0 | M17: -1.1226296 | N17: -2176.6364 | O17: 4 | P17: 2789.6125 | Q17: 11158.45 | R17: -4 | S17: -11158.45
A18: Véhicules neufs | B18: Véhicules neufs
A19: Véhicules neufsRachat bail | B19: Véhicules neufs | C19: Rachat bail | D19: 0 | E19: 0 | F19: 8416.039 | G19: 0 | H19: 0 | I19: 8416.039 | L19: 13151.1 | N19: 4735.061 | Q19: 6141.99 | R19: 0 | S19: 7009.11
A20: Véhicules neufs | B20: Véhicules neufs
A21: Véhicules neufsRev. Finances | B21: Véhicules neufs | C21: Rev. Finances | D21: 0 | E21: 0 | F21: 2182.3436 | G21: 0 | H21: 0 | I21: 2182.3436 | K21: 228.50482 | L21: 12796.27 | N21: 10613.926 | P21: 0 | Q21: 0 | R21: -228.50482 | S21: 12796.27
A22: Véhicules neufsRev. Protections | B22: Véhicules neufs | C22: Rev. Protections | D22: 0 | E22: 0 | F22: 58363.743 | G22: 0 | H22: 0 | I22: 58363.743 | K22: 947.25268 | L22: 53046.15 | N22: -5317.5929 | P22: 765.23471 | Q22: 66575.42 | R22: -947.25268 | S22: -13529.27
A23: Véhicules neufsRev. Autres | B23: Véhicules neufs | C23: Rev. Autres | D23: 0 | E23: 0 | F23: 1444.5159 | G23: 0 | H23: 0 | I23: 1444.5159 | K23: 13.778571 | L23: 771.6 | N23: -672.9159 | P23: 18.082414 | Q23: 1573.17 | R23: -13.778571 | S23: -801.57
A24: Véhicules neufsTotal F&I | B24: Véhicules neufs | C24: Total F&I | D24: 72.93012 | E24: 850 | F24: 61990.602 | G24: 72.93012 | H24: 850 | I24: 61990.602 | J24: 56 | K24: 1189.5361 | L24: 66614.02 | M24: -16.93012 | N24: 4623.4176 | O24: 87 | P24: 783.31713 | Q24: 68148.59 | S24: -1534.57
A25: Véhicules neufs | B25: Véhicules neufs | N25: 0.074582556 | S25: -0.022518001
A26: Véhicules neufs | B26: Véhicules neufs
A27: Véhicules neufsTotal Dépt. Neufs | B27: Véhicules neufs | C27: Total Dépt. Neufs | D27: 74.05275 | E27: 2844.1204 | F27: 210614.94 | G27: 74.05275 | H27: 2844.1204 | I27: 210614.94 | J27: 56 | K27: 4933.3102 | L27: 276265.37 | M27: -18.05275 | N27: 65650.435 | O27: 91 | P27: 2681.4854 | Q27: 244015.17 | R27: -35 | S27: 32250.2
A28: Véhicules neufs | B28: Véhicules neufs | M28: -0.2437823 | N28: 0.31170835 | R28: -0.38461538 | S28: 0.13216473
A29: Véhicules neufs | B29: Véhicules neufs
A30: Véhicules neufsDEPENSES | B30: Véhicules neufs | C30: DEPENSES
A31: Véhicules neufsComm. vendeurs | B31: Véhicules neufs | C31: Comm. vendeurs | D31: 0.32744374 | E31: 619.73848 | F31: 45197.602 | G31: 0.32744374 | H31: 619.73848 | I31: 45197.602 | J31: 0.27269477 | K31: 956.86768 | L31: 53584.59 | N31: 8386.9877 | P31: 611.33368 | Q31: 53186.03 | S31: 398.56
A32: Véhicules neufsComm. F&I | B32: Véhicules neufs | C32: Comm. F&I | D32: 0.3 | E32: 255 | F32: 18597.181 | G32: 0.3 | H32: 255 | I32: 18597.181 | J32: 0.33398225 | K32: 397.28393 | L32: 22247.9 | N32: 3650.7193 | P32: 240.78989 | Q32: 20948.72 | S32: 1299.18 | U32: 0.291325 | V32: <<- F&A total Neuf Usagé Rachat
A33: Véhicules neufsFrais de livraison | B33: Véhicules neufs | C33: Frais de livraison | E33: 167.8493 | F33: 12241.27 | H33: 167.8493 | I33: 12241.27 | K33: 83.595179 | L33: 4681.33 | N33: -7559.9398 | P33: 74.75069 | Q33: 6503.31 | S33: -1821.98
A34: Véhicules neufsService gratuit 1 | B34: Véhicules neufs | C34: Service gratuit 1 | E34: 7.3548076 | F34: 536.38701 | H34: 7.3548076 | I34: 536.38701 | K34: 10.361964 | L34: 580.27 | N34: 43.882994 | P34: 6.8565517 | Q34: 596.52 | S34: -16.25
A35: Véhicules neufsEntretien stock | B35: Véhicules neufs | C35: Entretien stock | E35: 17.733118 | F35: 1293.2784 | H35: 17.733118 | I35: 1293.2784 | K35: 66.075179 | L35: 3700.21 | N35: 2406.9316 | P35: 13.448276 | Q35: 1170 | S35: 2530.21
A36: Véhicules neufsPublicité 1 | B36: Véhicules neufs | C36: Publicité 1 | E36: 195.93765 | F36: 14289.757 | H36: 195.93765 | I36: 14289.757 | K36: 151.55625 | L36: 8487.15 | N36: -5802.6066 | P36: 119.94092 | Q36: 10434.86 | S36: -1947.71
A37: Véhicules neufsIntérêt de gros | B37: Véhicules neufs | C37: Intérêt de gros | E37: 95.743292 | F37: 6982.5698 | H37: 95.743292 | I37: 6982.5698 | K37: 4.1001786 | L37: 229.61 | N37: -6752.9598 | P37: 161.06483 | Q37: 14012.64 | S37: -13783.03
A38: Véhicules neufs[...] | B38: Véhicules neufs | C38: [...] | E38: 0 | F38: 0 | H38: 0 | I38: 0 | K38: 0 | L38: 0 | N38: 0 | P38: 0 | Q38: 0 | S38: 0
A39: Véhicules neufs[...] | B39: Véhicules neufs | C39: [...] | E39: 0 | F39: 0 | H39: 0 | I39: 0 | K39: 0 | L39: 0 | N39: 0 | P39: 0 | Q39: 0 | S39: 0
A40: Véhicules neufs[...] | B40: Véhicules neufs | C40: [...] | E40: 0 | F40: 0 | H40: 0 | I40: 0 | K40: 0 | L40: 0 | N40: 0 | P40: 0 | Q40: 0 | S40: 0
A41: Véhicules neufsTOTAL VARIABLES | B41: Véhicules neufs | C41: TOTAL VARIABLES | D41: % brut | E41: 0.47070757 | F41: 99138.045 | G41: % brut | H41: 0.47070757 | I41: 99138.045 | J41: % brut | K41: 0.33848274 | L41: 93511.06 | N41: -5626.9848 | O41: % brut | P41: 0.43789114 | Q41: 106852.08 | S41: -13341.02
A42: Véhicules neufsSalaires cadres | B42: Véhicules neufs | C42: Salaires cadres | F42: 15886.261 | I42: 15886.261 | L42: 17258.29 | N42: 1372.0291 | Q42: 21334.91 | S42: -4076.62
A43: Véhicules neufsSalaires commis | B43: Véhicules neufs | C43: Salaires commis | F43: 9822.0278 | I43: 9822.0278 | L43: 7489.24 | N43: -2332.7878 | Q43: 9816.59 | S43: -2327.35
A44: Véhicules neufsSalaires autres | B44: Véhicules neufs | C44: Salaires autres | F44: 8921.4022 | I44: 8921.4022 | L44: 3923.31 | N44: -4998.0922 | Q44: 8653.41 | S44: -4730.1
A45: Véhicules neufsSalaires spécialistes | B45: Véhicules neufs | C45: Salaires spécialistes | F45: 0 | I45: 0 | L45: 0 | N45: 0 | Q45: 0 | S45: 0
A46: Véhicules neufs[...] | B46: Véhicules neufs | C46: [...] | F46: 0 | I46: 0 | L46: 0 | N46: 0 | Q46: 0 | S46: 0
A47: Véhicules neufs[...] | B47: Véhicules neufs | C47: [...] | F47: 0 | I47: 0 | L47: 0 | N47: 0 | Q47: 0 | S47: 0
A48: Véhicules neufs[...] | B48: Véhicules neufs | C48: [...] | F48: 0 | I48: 0 | L48: 0 | N48: 0 | Q48: 0 | S48: 0
A49: Véhicules neufsSalaires en absences | B49: Véhicules neufs | C49: Salaires en absences | F49: 12003.8 | I49: 12003.8 | L49: 17407.08 | N49: 5403.2795 | Q49: 15115.93 | S49: 2291.15
A50: Véhicules neufsDéduction à la source | B50: Véhicules neufs | C50: Déduction à la source | F50: 10750.634 | I50: 10750.634 | L50: 20529.61 | N50: 9778.9762 | Q50: 12289.25 | S50: 8240.36
A51: Véhicules neufsBénéfices marginaux | B51: Véhicules neufs | C51: Bénéfices marginaux | F51: 8537.268 | I51: 8537.268 | L51: 8891.51 | N51: 354.242 | Q51: 8807.29 | S51: 84.22
A52: Véhicules neufsCsst | B52: Véhicules neufs | C52: Csst | F52: 3478.1462 | I52: 3478.1462 | L52: 6026.16 | N52: 2548.0138 | Q52: 2048.21 | S52: 3977.95
A53: Véhicules neufs[...] | B53: Véhicules neufs | C53: [...] | F53: 0 | I53: 0 | L53: 0 | N53: 0 | Q53: 0 | S53: 0
A54: Véhicules neufsTOTAL PERSONNEL | B54: Véhicules neufs | C54: TOTAL PERSONNEL | D54: % brut | E54: 0.32950911 | F54: 69399.539 | G54: % brut | H54: 0.32950911 | I54: 69399.539 | J54: % brut | K54: 0.29509743 | L54: 81525.2 | N54: 12125.661 | O54: % brut | P54: 0.31992105 | Q54: 78065.59 | S54: 3459.61
A55: Véhicules neufsPublicité 2 | B55: Véhicules neufs | C55: Publicité 2 | F55: 0 | I55: 0 | L55: 0 | N55: 0 | Q55: 0 | S55: 0
A56: Véhicules neufsService gratuit 2 | B56: Véhicules neufs | C56: Service gratuit 2 | F56: 0 | I56: 0 | L56: 0 | N56: 0 | Q56: 0 | S56: 0
A57: Véhicules neufsFrais véhicules de cie | B57: Véhicules neufs | C57: Frais véhicules de cie | F57: 7322.94 | I57: 7322.94 | L57: 8324.85 | N57: 1001.91 | Q57: 6376 | S57: 1948.85
A58: Véhicules neufsInformatique | B58: Véhicules neufs | C58: Informatique | F58: 6834.1988 | I58: 6834.1988 | L58: 7033.71 | N58: 199.51116 | Q58: 6391.27 | S58: 642.44
A59: Véhicules neufsFrais de déplacement | B59: Véhicules neufs | C59: Frais de déplacement | F59: 792.1418 | I59: 792.1418 | L59: 2502.76 | N59: 1710.6182 | Q59: 612.46 | S59: 1890.3
A60: Véhicules neufsServices extérieurs | B60: Véhicules neufs | C60: Services extérieurs | F60: 6830.797 | I60: 6830.797 | L60: 7293.4 | N60: 462.60302 | Q60: 7206.23 | S60: 87.17
A61: Véhicules neufsFournitures autres | B61: Véhicules neufs | C61: Fournitures autres | F61: 92.790378 | I61: 92.790378 | L61: 0 | N61: -92.790378 | Q61: 74.93 | S61: -74.93
A62: Véhicules neufsUniformes | B62: Véhicules neufs | C62: Uniformes | F62: 49.306367 | I62: 49.306367 | L62: 0 | N62: -49.306367 | Q62: 0 | S62: 0
A63: Véhicules neufsPapeterie | B63: Véhicules neufs | C63: Papeterie | F63: 652.86432 | I63: 652.86432 | L63: 472.5 | N63: -180.36432 | Q63: 755.68 | S63: -283.18
A64: Véhicules neufsTéléphone | B64: Véhicules neufs | C64: Téléphone | F64: 301.46453 | I64: 301.46453 | L64: 394.79 | N64: 93.325473 | Q64: 257.26 | S64: 137.53
A65: Véhicules neufsFrais postaux | B65: Véhicules neufs | C65: Frais postaux | F65: 160.91707 | I65: 160.91707 | L65: 112.03 | N65: -48.887073 | Q65: 162.85 | S65: -50.82
A66: Véhicules neufsDivers | B66: Véhicules neufs | C66: Divers | F66: 776.23359 | I66: 776.23359 | L66: 238.3 | N66: -537.93359 | Q66: 1198.42 | S66: -960.12
... A68: Véhicules neufsFrais bancaires | B68: Véhicules neufs | C68: Frais bancaires | F68: 1979.113 | I68: 1979.113 | L68: 3064.9995 | N68: 1085.8865 | Q68: 3102.8445 | S68: -37.845
A69: Véhicules neufs[...] | B69: Véhicules neufs | C69: [...] | F69: 0 | I69: 0 | N69: 0 | Q69: 0 | S69: 0
A70: Véhicules neufs[...] | B70: Véhicules neufs | C70: [...] | F70: 0 | I70: 0 | L70: 0 | N70: 0 | Q70: 0 | S70: 0
A71: Véhicules neufs[...] | B71: Véhicules neufs | C71: [...] | F71: 0 | I71: 0 | L71: 0 | N71: 0 | Q71: 0 | S71: 0
A72: Véhicules neufsTOTAL SEMI-FIXES | B72: Véhicules neufs | C72: TOTAL SEMI-FIXES | D72: % brut | E72: 0.12793975 | F72: 26946.023 | G72: % brut | H72: 0.12793975 | I72: 26946.023 | J72: % brut | K72: 0.11178415 | L72: 30882.09 | N72: 3936.0664 | O72: % brut | P72: 0.11057212 | Q72: 26981.274 | S72: 3900.815
A73: Véhicules neufs | B73: Véhicules neufs
A74: Véhicules neufsTOTAL DES DÉPENSES | B74: Véhicules neufs | C74: TOTAL DES DÉPENSES | D74: % brut | E74: 0.92815643 | F74: 195483.61 | G74: % brut | H74: 0.92815643 | I74: 195483.61 | J74: % brut | K74: 0.74536432 | L74: 205918.35 | N74: 10434.742 | O74: % brut | P74: 0.86838431 | Q74: 211898.94 | S74: -5980.595
A75: Véhicules neufsProgramme neuf 1 | B75: Véhicules neufs | C75: Programme neuf 1 | F75: 20185.2 | I75: 20185.2 | L75: 22000 | N75: 1814.8 | Q75: 0
A76: Véhicules neufsProgramme neuf 2 | B76: Véhicules neufs | C76: Programme neuf 2 | F76: 0 | I76: 0 | L76: 0 | N76: 0 | Q76: 0 | S76: 0
A77: Véhicules neufsProgramme neuf 3 | B77: Véhicules neufs | C77: Programme neuf 3 | F77: 0 | I77: 0 | L77: 0 | N77: 0 | Q77: 0 | S77: 0
A78: Véhicules neufsHoldbacks | B78: Véhicules neufs | C78: Holdbacks | F78: 77407.491 | I78: 77407.491 | L78: 66097 | N78: -11310.491 | Q78: 102678 | S78: -36581
A79: Véhicules neufs[...] | B79: Véhicules neufs | C79: [...] | F79: 0 | I79: 0 | L79: 0 | N79: 0 | Q79: 0 | S79: 0
A80: Véhicules neufs[...] | B80: Véhicules neufs | C80: [...] | F80: 0 | I80: 0 | L80: 0 | N80: 0 | Q80: 0 | S80: 0
A81: Véhicules neufs[...] | B81: Véhicules neufs | C81: [...] | F81: 0 | I81: 0 | L81: 0 | N81: 0 | Q81: 0 | S81: 0
A82: Véhicules neufsFrais administration | B82: Véhicules neufs | C82: Frais administration | F82: 26592.343 | I82: 26592.343 | J82: 56 | K82: -516.41071 | L82: -28919 | N82: -55511.343 | Q82: 25377 | S82: -54296
A83: Véhicules neufsAUTRES REVENUS | B83: Véhicules neufs | C83: AUTRES REVENUS | F83: 124185.03 | I83: 124185.03 | L83: 59178 | N83: -65007.033 | Q83: 128055 | S83: -90877
A84: Véhicules neufs | B84: Véhicules neufs
A85: Véhicules neufsPROFIT DÉPARTEMENTAL | B85: Véhicules neufs | C85: PROFIT DÉPARTEMENTAL | F85: 139316.36 | I85: 139316.36 | L85: 129525.02 | N85: -9791.3408 | Q85: 160171.23 | S85: -52646.205
C89: Volks | K89: Véhicules usagés | S89: Réalisé, Juin 2022
D91: BUDGET ORIGINAL | G91: BUDGET RÉVISÉ | J91: RÉALISATION | M91: ÉCART réel / révisé | O91: ANNÉE PRÉCÉDENTE | R91: ÉCART réel / original
D92: UNITE | E92: $P/UNITÉ | F92: $PROFITS | G92: UNITE | H92: $P/UNITÉ | I92: $PROFITS | J92: UNITE | K92: $P/UNITE | L92: $PROFITS | M92: UNITÉ | N92: $PROFITS | O92: UNITE | P92: $P/UNITE | Q92: $PROFITS | R92: UNITE | S92: $PROFITS
A93: Véhicules usagésVentes nettes | B93: Véhicules usagés | C93: Ventes nettes | F93: 1486216.2 | I93: 1486216.2 | L93: 1873950.2 | Q93: 1425396.5
A94: Véhicules usagésCertifié | B94: Véhicules usagés | C94: Certifié | D94: 45.364078 | E94: 1300 | F94: 58973.301 | G94: 45.364078 | H94: 1300 | I94: 58973.301 | J94: 34 | K94: 2572.5085 | L94: 87465.29 | M94: -11.364078 | N94: 28491.989 | O94: 38 | P94: 1319.41 | Q94: 50137.58 | R94: -4 | S94: 37327.71
A95: Véhicules usagésNon Certifié | B95: Véhicules usagés | C95: Non Certifié | D95: 2.5485437 | E95: 900 | F95: 2293.6893 | G95: 2.5485437 | H95: 900 | I95: 2293.6893 | J95: 2 | K95: 1700.39 | L95: 3400.78 | M95: -0.54854369 | N95: 1107.0907 | O95: 1 | P95: -527.8 | Q95: -527.8 | R95: 1 | S95: 3928.58
A96: Véhicules usagésTotal Usagés | B96: Véhicules usagés | C96: Total Usagés | D96: 47.912621 | E96: 1278.7234 | F96: 61266.99 | G96: 47.912621 | H96: 1278.7234 | I96: 61266.99 | J96: 36 | K96: 2524.0575 | L96: 90866.07 | M96: -11.912621 | N96: 29599.08 | O96: 39 | P96: 1272.0456 | Q96: 49609.78 | R96: -3 | S96: 41256.29
A97: Véhicules usagés | B97: Véhicules usagés | E97: 0 | H97: 0 | M97: -0.24863222 | N97: 0.48311627 | R97: -0.076923077 | S97: 0.83161606
A98: Véhicules usagésUS | B98: Véhicules usagés | C98: US
A99: Véhicules usagésVentes au Gros | B99: Véhicules usagés | C99: Ventes au Gros | D99: 41.693224 | E99: 212 | F99: 8838.9634 | G99: 41.693224 | H99: 212 | I99: 8838.9634 | J99: 34 | K99: -56.072059 | L99: -1906.45 | M99: -7.6932236 | N99: -10745.413 | O99: 41 | P99: 611.62902 | Q99: 25076.79 | R99: -7 | S99: -26983.24 | V99: -54 | W99: 0
A100: Véhicules usagés | B100: Véhicules usagés | V100: 200 | W100: 0
A101: Véhicules usagésRev. Finances | B101: Véhicules usagés | C101: Rev. Finances | D101: 0 | E101: 0 | F101: 31572.545 | G101: 0 | H101: 0 | I101: 31572.545 | K101: 1201.3561 | L101: 43248.82 | N101: 11676.275 | P101: 799.67385 | Q101: 31187.28 | R101: -1201.3561 | S101: 12061.54 | W101: 0
A102: Véhicules usagésRev. Protections | B102: Véhicules usagés | C102: Rev. Protections | D102: 0 | E102: 0 | F102: 55667.024 | G102: 0 | H102: 0 | I102: 55667.024 | K102: 1261.9403 | L102: 45429.85 | N102: -10237.174 | P102: 1285.4226 | Q102: 50131.48 | R102: -1261.9403 | S102: -4701.63
A103: Véhicules usagésRev. Autres | B103: Véhicules usagés | C103: Rev. Autres | D103: 0 | E103: 0 | F103: 1578.8746 | G103: 0 | H103: 0 | I103: 1578.8746 | K103: 41.279167 | L103: 1486.05 | N103: -92.824556 | P103: 41.958462 | Q103: 1636.38 | R103: -41.279167 | S103: -150.33
A104: Véhicules usagésTotal F&I | B104: Véhicules usagés | C104: Total F&I | D104: 47.912621 | E104: 1853.7588 | F104: 88818.443 | G104: 47.912621 | H104: 1853.7588 | I104: 88818.443 | J104: 36 | K104: 2504.5756 | L104: 90164.72 | M104: -11.912621 | N104: 1346.2765 | O104: 39 | P104: 2127.0549 | Q104: 82955.14 | S104: 7209.58
A105: Véhicules usagés | B105: Véhicules usagés | N105: 0.015157624 | S105: 0.086909383
...

Sheet END
