Workbook
Name _Dates_Conc: [1]Dealers!$BF$37:$KA$63
Name _scen: '[1]Scen & Sens'!$E$26
Name _scen1: '[1]Scen & Sens'!$E$27
Name _scen2: '[1]Scen & Sens'!$E$28
Name _SCenarios: '[1]Scen & Sens'!$J$26:$O$26
Name _Sens1: '[1]Scen & Sens'!$F$9
Name _Sens2: '[1]Scen & Sens'!$F$10
Name _sensRes1: '[1]Scen & Sens'!$E$15
Name _sensRes2: '[1]Scen & Sens'!$E$16
Name _sensRes3: '[1]Scen & Sens'!$E$17
Name _sensRes4: '[1]Scen & Sens'!$E$18
Name _sensRes5: '[1]Scen & Sens'!$E$19
Name _sensRes6: '[1]Scen & Sens'!$E$20
Name _sensRes7: '[1]Scen & Sens'!$E$21
Name DateRange: [1]Volkswagen!$BF$6:$DY$6
Name Monetary_Unit: [1]Parameters!$B$15
Name Months: [1]Parameters!$E$9:$E$20
Name Rng_Dealers_Names: [1]!Tbl_Dealers[Dealer Name]
Name Rng_Dlr_Dates: [1]!Tbl_V_Dlr_Dates[Date]
Name Ticker: #REF!
Name Ticker: #REF!
Name Titre: [1]Front!$A$9

Sheet Paramètre
B3: VOLKS QUARTER | C3: Volks Juin / Juillet 2023
B6: BUDGET | F6: BUDGET RÉVISÉ | J6: ACTUAL | N6: LAST YEAR
B7: Ventes | C7: Profits bruts | D7: BAIIA | E7: EBIT | F7: Ventes | G7: Profits bruts | H7: BAIIA | I7: EBIT | J7: Ventes | K7: Profits bruts | L7: BAIIA | M7: EBIT | N7: Ventes | O7: Profits bruts | P7: BAIIA | Q7: EBIT
A8: CTRL | B8: =+B9-B10 -> #REF! | C8: =+C9-C10 -> #REF! | D8: =+D9-D10 -> #REF! | E8: =+E9-E10 -> #REF! | F8: =+F9-F10 -> #REF! | G8: =+G9-G10 -> #REF! | H8: =+H9-H10 -> #REF! | I8: =+I9-I10 -> #REF! | ... Q8: =+Q9-Q10 -> #REF!
A9: CONSO | B9: =+Conso!$Z$405 -> 9346028.8 | C9: =+Conso!$Z$406 -> 1339678.4 | D9: =+Conso!$Z$482 -> 359006.39 | E9: =+Conso!$Z$497 -> 348823.91 | F9: =+Conso!$AC$405 -> 0 | G9: =+Conso!$AC$406 -> 0 | H9: =+Conso!$AC$482 -> 0 | I9: =+Conso!$AC$497 -> 0 | J9: =+Conso!$AF$405 -> 10172890 | K9: =+Conso!$AF$406 -> 1288302.5 | L9: =+Conso!$AF$482 -> 361518.19 | M9: =+Conso!$AF$497 -> 352889.19 | N9: =+Conso!$AL$405 -> 10597373 | O9: =+Conso!$AL$406 -> 1497150.1 | P9: =+Conso!$AL$482 -> 519977.36 | Q9: =+Conso!$AL$497 -> 510494.78
A10: TOTAL | B10: =+SUM(B11:B13) -> #REF! | C10: =+SUM(C11:C13) -> #REF! | D10: =+SUM(D11:D13) -> #REF! | E10: =+SUM(E11:E13) -> #REF! | F10: =+SUM(F11:F13) -> #REF! | G10: =+SUM(G11:G13) -> #REF! | H10: =+SUM(H11:H13) -> #REF! | I10: =+SUM(I11:I13) -> #REF! | ... Q10: =+SUM(Q11:Q13) -> #REF!
A11: AUDI 1 | B11: =+#REF! -> #REF! | C11: =+#REF! -> #REF! | D11: =+#REF! -> #REF! | E11: =+#REF! -> #REF! | F11: =+#REF! -> #REF! | G11: =+#REF! -> #REF! | H11: =+#REF! -> #REF! | I11: =+#REF! -> #REF! | ... Q11: =+#REF! -> #REF!
A12: AUDI 2 | B12: =+#REF! -> #REF! | C12: =+#REF! -> #REF! | D12: =+#REF! -> #REF! | E12: =+#REF! -> #REF! | F12: =+#REF! -> #REF! | G12: =+#REF! -> #REF! | H12: =+#REF! -> #REF! | I12: =+#REF! -> #REF! | ... Q12: =+#REF! -> #REF!
A13: AUDI 3 | B13: =+#REF! -> #REF! | C13: =+#REF! -> #REF! | D13: =+#REF! -> #REF! | E13: =+#REF! -> #REF! | F13: =+#REF! -> #REF! | G13: =+#REF! -> #REF! | H13: =+#REF! -> #REF! | I13: =+#REF! -> #REF! | ... Q13: =+#REF! -> #REF!

Sheet Conso
C1: Conso | K1: Véhicules neufs | S1: =CONCATENATE(Paramètre!$C$2," ",Paramètre!$C$3) -> Volks Juin / Juillet 2023
D2: X | E2: O | F2: U | G2: X | H2: O | I2: U
D3: BUDGET ORIGINAL | G3: BUDGET REVISE | J3: RÉALISATION | M3: ÉCART réel / Budget | O3: ANNÉE PRÉCÉDENTE | R3: ECART (réel/ Ann.Préc.)
D4: UNITE | E4: $P/UNITÉ | F4: $PROFITS | G4: UNITE | H4: $P/UNITÉ | I4: $PROFITS | J4: UNITE | K4: $P/UNITE | L4: $PROFITS | M4: UNITÉS | N4: $PROFITS | O4: UNITE | P4: $P/UNITE | Q4: $PROFITS | R4: UNITÉS | S4: $PROFITS
A5: =+B5&C5 -> Véhicules neufsVentes nettes | B5: =+$K$1 -> Véhicules neufs | C5: Ventes nettes | F5: =+SUM(START:END!F5) -> 4632530.7 | I5: =+SUM(START:END!I5) -> 0 | L5: =+SUM(START:END!L5) -> 4973516.2 | Q5: =+SUM(START:END!Q5) -> 5493835.3
A6: =+B6&C6 -> Véhicules neufsAutos détail | B6: =+$K$1 -> Véhicules neufs | C6: Autos détail | D6: =+SUM(START:END!D6) -> 19.737143 | E6: =IF(D6=0,0,F6/D6) -> 1988.434 | F6: =+SUM(START:END!F6) -> 39246.006 | G6: =+SUM(START:END!G6) -> 0 | H6: =IF(G6=0,0,I6/G6) -> 0 | I6: =+SUM(START:END!I6) -> 0 | J6: =+SUM(START:END!J6) -> 28 | K6: =IF(J6=0,0,L6/J6) -> 2008.6254 | L6: =+SUM(START:END!L6) -> 56241.51 | M6: =J6-D6 -> 8.2628571 | N6: =L6-F6 -> 16995.504 | O6: =+SUM(START:END!O6) -> 22 | P6: =IF(O6=0,0,Q6/O6) -> 2731.0177 | Q6: =+SUM(START:END!Q6) -> 60082.39 | R6: =J6-O6 -> 6 | S6: =L6-Q6 -> -3840.88
A7: =+B7&C7 -> Véhicules neufsCamions détail | B7: =+$K$1 -> Véhicules neufs | C7: Camions détail | D7: =+SUM(START:END!D7) -> 78.940677 | E7: =IF(D7=0,0,F7/D7) -> 2556.3336 | F7: =+SUM(START:END!F7) -> 201798.71 | G7: =+SUM(START:END!G7) -> 0 | H7: =IF(G7=0,0,I7/G7) -> 0 | I7: =+SUM(START:END!I7) -> 0 | J7: =+SUM(START:END!J7) -> 63 | K7: =IF(J7=0,0,L7/J7) -> 2495.4514 | L7: =+SUM(START:END!L7) -> 157213.44 | M7: =J7-D7 -> -15.940677 | N7: =L7-F7 -> -44585.267 | O7: =+SUM(START:END!O7) -> 80 | P7: =IF(O7=0,0,Q7/O7) -> 3573.0596 | Q7: =+SUM(START:END!Q7) -> 285844.77 | R7: =J7-O7 -> -17 | S7: =L7-Q7 -> -128631.33
A8: =+B8&C8 -> Véhicules neufsSprinter | B8: =+$K$1 -> Véhicules neufs | C8: Sprinter | D8: =+SUM(START:END!D8) -> 0 | E8: =IF(D8=0,0,F8/D8) -> 0 | F8: =+SUM(START:END!F8) -> 0 | G8: =+SUM(START:END!G8) -> 0 | H8: =IF(G8=0,0,I8/G8) -> 0 | I8: =+SUM(START:END!I8) -> 0 | J8: =+SUM(START:END!J8) -> 0 | K8: =IF(J8=0,0,L8/J8) -> 0 | L8: =+SUM(START:END!L8) -> 0 | M8: =J8-D8 -> 0 | N8: =L8-F8 -> 0 | O8: =+SUM(START:END!O8) -> 0 | P8: =IF(O8=0,0,Q8/O8) -> 0 | Q8: =+SUM(START:END!Q8) -> 0 | R8: =J8-O8 -> 0 | S8: =L8-Q8 -> 0
A9: =+B9&C9 -> Véhicules neufsMoto détail | B9: =+$K$1 -> Véhicules neufs | C9: Moto détail | D9: =+SUM(START:END!D9) -> 0 | E9: =IF(D9=0,0,F9/D9) -> 0 | F9: =+SUM(START:END!F9) -> 0 | G9: =+SUM(START:END!G9) -> 0 | H9: =IF(G9=0,0,I9/G9) -> 0 | I9: =+SUM(START:END!I9) -> 0 | J9: =+SUM(START:END!J9) -> 0 | K9: =IF(J9=0,0,L9/J9) -> 0 | L9: =+SUM(START:END!L9) -> 0 | M9: =J9-D9 -> 0 | N9: =L9-F9 -> 0 | O9: =+SUM(START:END!O9) -> 0 | P9: =IF(O9=0,0,Q9/O9) -> 0 | Q9: =+SUM(START:END!Q9) -> 0 | R9: =J9-O9 -> 0 | S9: =L9-Q9 -> 0
A10: =+B10&C10 -> Véhicules neufs[...] | B10: =+$K$1 -> Véhicules neufs | C10: [...] | D10: =+SUM(START:END!D10) -> 0 | E10: =IF(D10=0,0,F10/D10) -> 0 | F10: =+SUM(START:END!F10) -> 0 | G10: =+SUM(START:END!G10) -> 0 | H10: =IF(G10=0,0,I10/G10) -> 0 | I10: =+SUM(START:END!I10) -> 0 | J10: =+SUM(START:END!J10) -> 0 | K10: =IF(J10=0,0,L10/J10) -> 0 | L10: =+SUM(START:END!L10) -> 0 | M10: =J10-D10 -> 0 | N10: =L10-F10 -> 0 | O10: =+SUM(START:END!O10) -> 0 | P10: =IF(O10=0,0,Q10/O10) -> 0 | Q10: =+SUM(START:END!Q10) -> 0 | R10: =J10-O10 -> 0 | S10: =L10-Q10 -> 0
A11: =+B11&C11 -> Véhicules neufs[...] | B11: =+$K$1 -> Véhicules neufs | C11: [...] | D11: =+SUM(START:END!D11) -> 0 | E11: =IF(D11=0,0,F11/D11) -> 0 | F11: =+SUM(START:END!F11) -> 0 | G11: =+SUM(START:END!G11) -> 0 | H11: =IF(G11=0,0,I11/G11) -> 0 | I11: =+SUM(START:END!I11) -> 0 | J11: =+SUM(START:END!J11) -> 0 | K11: =IF(J11=0,0,L11/J11) -> 0 | L11: =+SUM(START:END!L11) -> 0 | M11: =J11-D11 -> 0 | N11: =L11-F11 -> 0 | O11: =+SUM(START:END!O11) -> 0 | P11: =IF(O11=0,0,Q11/O11) -> 0 | Q11: =+SUM(START:END!Q11) -> 0 | R11: =J11-O11 -> 0 | S11: =L11-Q11 -> 0
A12: =+B12&C12 -> Véhicules neufs[...] | B12: =+$K$1 -> Véhicules neufs | C12: [...] | D12: =+SUM(START:END!D12) -> 0 | E12: =IF(D12=0,0,F12/D12) -> 0 | F12: =+SUM(START:END!F12) -> 0 | G12: =+SUM(START:END!G12) -> 0 | H12: =IF(G12=0,0,I12/G12) -> 0 | I12: =+SUM(START:END!I12) -> 0 | J12: =+SUM(START:END!J12) -> 0 | K12: =IF(J12=0,0,L12/J12) -> 0 | L12: =+SUM(START:END!L12) -> 0 | M12: =J12-D12 -> 0 | N12: =L12-F12 -> 0 | O12: =+SUM(START:END!O12) -> 0 | P12: =IF(O12=0,0,Q12/O12) -> 0 | Q12: =+SUM(START:END!Q12) -> 0 | R12: =J12-O12 -> 0 | S12: =L12-Q12 -> 0
A13: =+B13&C13 -> Véhicules neufsTotal Neufs | B13: =+$K$1 -> Véhicules neufs | C13: Total Neufs | D13: =+SUM(D6:D12) -> 98.677819 | E13: =IF(D13<=0,0,F13/D13) -> 2442.7446 | F13: =+SUM(F6:F12) -> 241044.71 | G13: =+SUM(G6:G12) -> 0 | H13: =IF(G13<=0,0,I13/G13) -> 0 | I13: =+SUM(I6:I12) -> 0 | J13: =+SUM(J6:J12) -> 91 | K13: =IF(J13<=0,0,L13/J13) -> 2345.6588 | L13: =+SUM(L6:L12) -> 213454.95 | M13: =+SUM(M6:M12) -> -7.6778194 | N13: =+SUM(N6:N12) -> -27589.762 | O13: =+SUM(O6:O12) -> 102 | P13: =IF(O13<=0,0,Q13/O13) -> 3391.4427 | Q13: =+SUM(Q6:Q12) -> 345927.16 | R13: =+SUM(R6:R12) -> -11 | S13: =+SUM(S6:S12) -> -132472.21
A14: =+B14&C14 -> Véhicules neufs | B14: =+$K$1 -> Véhicules neufs | M14: =IF(D13=0,0,M13/D13) -> -0.077806943 | N14: =IF(F13=0,0,N13/F13) -> -0.11445911 | R14: =R13/O13 -> -0.10784314 | S14: =IF(Q13=0,0,(S13/Q13)) -> -0.38294828
A15: =+B15&C15 -> Véhicules neufsEx-Démos et courtoisies | B15: =+$K$1 -> Véhicules neufs | C15: Ex-Démos et courtoisies | D15: =+SUM(START:END!D15) -> 4.7142857 | E15: =IF(D15=0,0,F15/D15) -> 2442.5492 | F15: =+SUM(START:END!F15) -> 11514.875 | G15: =+SUM(START:END!G15) -> 0 | H15: =IF(G15=0,0,I15/G15) -> 0 | I15: =+SUM(START:END!I15) -> 0 | J15: =+SUM(START:END!J15) -> 5 | K15: =IF(J15=0,0,L15/J15) -> 1105.4 | L15: =+SUM(START:END!L15) -> 5527 | M15: =J15-D15 -> 0.28571429 | N15: =L15-F15 -> -5987.8748 | O15: =+SUM(START:END!O15) -> 7 | P15: =IF(O15=0,0,Q15/O15) -> 2501.0343 | Q15: =+SUM(START:END!Q15) -> 17507.24 | R15: =J15-O15 -> -2 | S15: =L15-Q15 -> -11980.24
A16: =+B16&C16 -> Véhicules neufs | B16: =+$K$1 -> Véhicules neufs
A17: =+B17&C17 -> Véhicules neufsFlottes | B17: =+$K$1 -> Véhicules neufs | C17: Flottes | D17: =+SUM(START:END!D17) -> 3.7714286 | E17: =IF(D17=0,0,F17/D17) -> 2442.5492 | F17: =+SUM(START:END!F17) -> 9211.8998 | G17: =+SUM(START:END!G17) -> 0 | H17: =IF(G17=0,0,I17/G17) -> 0 | I17: =+SUM(START:END!I17) -> 0 | J17: =+SUM(START:END!J17) -> 3 | K17: =IF(J17=0,0,L17/J17) -> 3401.6467 | L17: =+SUM(START:END!L17) -> 10204.94 | M17: =J17-D17 -> -0.77142857 | N17: =L17-F17 -> 993.04016 | O17: =+SUM(START:END!O17) -> 2 | P17: =IF(O17=0,0,Q17/O17) -> 4190.8 | Q17: =+SUM(START:END!Q17) -> 8381.6 | R17: =J17-O17 -> 1 | S17: =L17-Q17 -> 1823.34
A18: =+B18&C18 -> Véhicules neufs | B18: =+$K$1 -> Véhicules neufs
A19: =+B19&C19 -> Véhicules neufsRachat bail | B19: =+$K$1 -> Véhicules neufs | C19: Rachat bail | F19: =+SUM(START:END!F19) -> 21120 | I19: =+SUM(START:END!I19) -> 0 | L19: =+SUM(START:END!L19) -> 22871.75 | N19: =L19-F19 -> 1751.75 | Q19: =+SUM(START:END!Q19) -> 27119.43 | R19: =O19-K19 -> 0 | S19: =L19-Q19 -> -4247.68
A20: =+B20&C20 -> Véhicules neufs | B20: =+$K$1 -> Véhicules neufs
A21: =+B21&C21 -> Véhicules neufsRev. Finances | B21: =+$K$1 -> Véhicules neufs | C21: Rev. Finances | D21: 0 | E21: =IF(D21=0,0,F21/D21) -> 0 | F21: =+SUM(START:END!F21) -> 17783.442 | G21: 0 | H21: =IF(G21=0,0,I21/G21) -> 0 | I21: =+SUM(START:END!I21) -> 0 | K21: =IF(J13=0,0,L21/(J13+J15)) -> 153.78583 | L21: =+SUM(START:END!L21) -> 14763.44 | N21: =L21-F21 -> -3020.0021 | P21: =IF(O13=0,0,Q21/(O13+O15)) -> 218.88321 | Q21: =+SUM(START:END!Q21) -> 23858.27 | R21: =O21-K21 -> -153.78583 | S21: =L21-Q21 -> -9094.83
A22: =+B22&C22 -> Véhicules neufsRev. Protections | B22: =+$K$1 -> Véhicules neufs | C22: Rev. Protections | D22: 0 | E22: =IF(D22=0,0,F22/D22) -> 0 | F22: =+SUM(START:END!F22) -> 97808.931 | G22: 0 | H22: =IF(G22=0,0,I22/G22) -> 0 | I22: =+SUM(START:END!I22) -> 0 | K22: =IF(J13=0,0,L22/(J13+J15)) -> 966.72667 | L22: =+SUM(START:END!L22) -> 92805.76 | N22: =L22-F22 -> -5003.1715 | P22: =IF(O13=0,0,Q22/(O13+O15)) -> 994.12339 | Q22: =+SUM(START:END!Q22) -> 108359.45 | R22: =O22-K22 -> -966.72667 | S22: =L22-Q22 -> -15553.69
A23: =+B23&C23 -> Véhicules neufsRev. Autres | B23: =+$K$1 -> Véhicules neufs | C23: Rev. Autres | D23: 0 | E23: =IF(D23=0,0,F23/D23) -> 0 | F23: =+SUM(START:END!F23) -> 2998.371 | G23: 0 | H23: =IF(G23=0,0,I23/G23) -> 0 | I23: =+SUM(START:END!I23) -> 0 | K23: =IF(J13=0,0,L23/(J13+J15)) -> 0 | L23: =+SUM(START:END!L23) -> 0 | N23: =L23-F23 -> -2998.371 | P23: =IF(O13=0,0,Q23/(O13+O15)) -> 20.206789 | Q23: =+SUM(START:END!Q23) -> 2202.54 | R23: =O23-K23 -> 0 | S23: =L23-Q23 -> -2202.54
A24: =+B24&C24 -> Véhicules neufsTotal F&I | B24: =+$K$1 -> Véhicules neufs | C24: Total F&I | D24: =+D15+D13 -> 103.39211 | E24: =IF(D24<=0,0,F24/D24) -> 1147 | F24: =F21+F22+F23 -> 118590.74 | G24: =+G15+G13 -> 0 | H24: =IF(G24<=0,0,I24/G24) -> 0 | I24: =I21+I22+I23 -> 0 | J24: =+J15+J13 -> 96 | K24: =IF(J24<=0,0,L24/J24) -> 1120.5125 | L24: =L21+L22+L23 -> 107569.2 | M24: =J24-D24 -> -7.3921051 | N24: =L24-F24 -> -11021.545 | O24: =+O15+O13 -> 109 | P24: =IF(O24<=0,0,Q24/O24) -> 1233.2134 | Q24: =Q21+Q22+Q23 -> 134420.26 | S24: =L24-Q24 -> -26851.06
A25: =+B25&C25 -> Véhicules neufs | B25: =+$K$1 -> Véhicules neufs | N25: =IF(N24=0,0,N24/F24) -> -0.092937646 | S25: =IF(Q24=0,0,(S24/Q24)) -> -0.19975456
A26: =+B26&C26 -> Véhicules neufs | B26: =+$K$1 -> Véhicules neufs
A27: =+B27&C27 -> Véhicules neufsTotal Dépt. Neufs | B27: =+$K$1 -> Véhicules neufs | C27: Total Dépt. Neufs | D27: =+D13+D15+D17 -> 107.16353 | E27: =IF(D27<=0,0,F27/D27) -> 3746.4445 | F27: =F13+F17+F24+F19+F15 -> 401482.23 | G27: =+G13+G15+G17 -> 0 | H27: =IF(G27<=0,0,I27/G27) -> 0 | I27: =I13+I17+I24+I19+I15 -> 0 | J27: =+J13+J15+J17 -> 99 | K27: =IF(J27<=0,0,L27/J27) -> 3632.6044 | L27: =L13+L17+L24+L19+L15 -> 359627.84 | M27: =J27-D27 -> -8.1635337 | N27: =L27-F27 -> -41854.392 | O27: =+O13+O15+O17 -> 111 | P27: =IF(O27<=0,0,Q27/O27) -> 4805.0062 | Q27: =Q13+Q17+Q24+Q19+Q15 -> 533355.69 | R27: =J27-O27 -> -12 | S27: =L27-Q27 -> -173727.85
A28: =+B28&C28 -> Véhicules neufs | B28: =+$K$1 -> Véhicules neufs | M28: =M27/D27 -> -0.07617828 | N28: =N27/F27 -> -0.10424967 | R28: =R27/O27 -> -0.10810811 | S28: =IF(Q27=0,0,S27/Q27) -> -0.32572606
A29: =+B29&C29 -> Véhicules neufs | B29: =+$K$1 -> Véhicules neufs
A30: =+B30&C30 -> Véhicules neufsDEPENSES | B30: =+$K$1 -> Véhicules neufs | C30: DEPENSES
A31: =+B31&C31 -> Véhicules neufsComm. vendeurs | B31: =+$K$1 -> Véhicules neufs | C31: Comm. vendeurs | E31: =F31/D$24 -> 776.22221 | F31: =+SUM(START:END!F31) -> 80255.248 | H31: =I31/G$24 -> #DIV/0! | I31: =+SUM(START:END!I31) -> 0 | J31: =L31/L13 -> 0.35962595 | K31: =IF(L31=0,0,L31/J$24) -> 799.62437 | L31: =+SUM(START:END!L31) -> 76763.94 | N31: =L31-F31 -> -3491.308 | P31: =IF(Q31=0,0,Q31/O$24) -> 1010.7386 | Q31: =+SUM(START:END!Q31) -> 110170.51 | S31: =L31-Q31 -> -33406.57
A32: =+B32&C32 -> Véhicules neufsComm. F&I | B32: =+$K$1 -> Véhicules neufs | C32: Comm. F&I | E32: =F32/D$24 -> 344.1 | F32: =+SUM(START:END!F32) -> 35577.223 | H32: =I32/G$24 -> #DIV/0! | I32: =+SUM(START:END!I32) -> 0 | J32: =L32/L24 -> 0.3004188 | K32: =IF(L32=0,0,L32/J$24) -> 336.62302 | L32: =+SUM(START:END!L32) -> 32315.81 | N32: =L32-F32 -> -3261.4134 | P32: =IF(Q32=0,0,Q32/O$24) -> 410.26229 | Q32: =+SUM(START:END!Q32) -> 44718.59 | S32: =L32-Q32 -> -12402.78
A33: =+B33&C33 -> Véhicules neufsFrais de livraison | B33: =+$K$1 -> Véhicules neufs | C33: Frais de livraison | E33: =F33/D$24 -> 113.25898 | F33: =+SUM(START:END!F33) -> 11710.084 | H33: =I33/G$24 -> #DIV/0! | I33: =+SUM(START:END!I33) -> 0 | K33: =IF(L33=0,0,L33/J$24) -> 126.76219 | L33: =+SUM(START:END!L33) -> 12169.17 | N33: =L33-F33 -> 459.08598 | P33: =IF(Q33=0,0,Q33/O$24) -> 113.8745 | Q33: =+SUM(START:END!Q33) -> 12412.32 | S33: =L33-Q33 -> -243.15
A34: =+B34&C34 -> Véhicules neufsService gratuit 1 | B34: =+$K$1 -> Véhicules neufs | C34: Service gratuit 1 | E34: =F34/D$24 -> 5.1177856 | F34: =+SUM(START:END!F34) -> 529.13863 | H34: =I34/G$24 -> #DIV/0! | I34: =+SUM(START:END!I34) -> 0 | K34: =IF(L34=0,0,L34/J$24) -> 0.41666667 | L34: =+SUM(START:END!L34) -> 40 | N34: =L34-F34 -> -489.13863 | P34: =IF(Q34=0,0,Q34/O$24) -> 7.0702752 | Q34: =+SUM(START:END!Q34) -> 770.66 | S34: =L34-Q34 -> -730.66
A35: =+B35&C35 -> Véhicules neufsEntretien stock | B35: =+$K$1 -> Véhicules neufs | C35: Entretien stock | E35: =F35/D$24 -> 105.01044 | F35: =+SUM(START:END!F35) -> 10857.251 | H35: =I35/G$24 -> #DIV/0! | I35: =+SUM(START:END!I35) -> 0 | K35: =IF(L35=0,0,L35/J$24) -> 89.656562 | L35: =+SUM(START:END!L35) -> 8607.03 | N35: =L35-F35 -> -2250.2208 | P35: =IF(Q35=0,0,Q35/O$24) -> 119.64138 | Q35: =+SUM(START:END!Q35) -> 13040.91 | S35: =L35-Q35 -> -4433.88
A36: =+B36&C36 -> Véhicules neufsPublicité 1 | B36: =+$K$1 -> Véhicules neufs | C36: Publicité 1 | E36: =F36/D$24 -> 300.75552 | F36: =+SUM(START:END!F36) -> 31095.747 | H36: =I36/G$24 -> #DIV/0! | I36: =+SUM(START:END!I36) -> 0 | K36: =IF(L36=0,0,L36/J$24) -> 135.52729 | L36: =+SUM(START:END!L36) -> 13010.62 | N36: =L36-F36 -> -18085.127 | P36: =IF(Q36=0,0,Q36/O$24) -> 168.27872 | Q36: =+SUM(START:END!Q36) -> 18342.38 | S36: =L36-Q36 -> -5331.76
A37: =+B37&C37 -> Véhicules neufsIntérêt de gros | B37: =+$K$1 -> Véhicules neufs | C37: Intérêt de gros | E37: =F37/D$24 -> 48.257416 | F37: =+SUM(START:END!F37) -> 4989.4358 | H37: =I37/G$24 -> #DIV/0! | I37: =+SUM(START:END!I37) -> 0 | K37: =IF(L37=0,0,L37/J$24) -> 86.082917 | L37: =+SUM(START:END!L37) -> 8263.96 | N37: =L37-F37 -> 3274.5242 | P37: =IF(Q37=0,0,Q37/O$24) -> 12.485413 | Q37: =+SUM(START:END!Q37) -> 1360.91 | S37: =L37-Q37 -> 6903.05
A38: =+B38&C38 -> Véhicules neufs[...] | B38: =+$K$1 -> Véhicules neufs | C38: [...] | E38: =F38/D$24 -> 0 | F38: =+SUM(START:END!F38) -> 0 | H38: =I38/G$24 -> #DIV/0! | I38: =+SUM(START:END!I38) -> 0 | K38: =IF(L38=0,0,L38/J$24) -> 0 | L38: =+SUM(START:END!L38) -> 0 | N38: =L38-F38 -> 0 | P38: =IF(Q38=0,0,Q38/O$24) -> 0 | Q38: =+SUM(START:END!Q38) -> 0 | S38: =L38-Q38 -> 0
A39: =+B39&C39 -> Véhicules neufs[...] | B39: =+$K$1 -> Véhicules neufs | C39: [...] | E39: =F39/D$24 -> 0 | F39: =+SUM(START:END!F39) -> 0 | H39: =I39/G$24 -> #DIV/0! | I39: =+SUM(START:END!I39) -> 0 | K39: =IF(L39=0,0,L39/J$24) -> 0 | L39: =+SUM(START:END!L39) -> 0 | N39: =L39-F39 -> 0 | P39: =IF(Q39=0,0,Q39/O$24) -> 0 | Q39: =+SUM(START:END!Q39) -> 0 | S39: =L39-Q39 -> 0
A40: =+B40&C40 -> Véhicules neufs[...] | B40: =+$K$1 -> Véhicules neufs | C40: [...] | E40: =F40/D$24 -> 0 | F40: =+SUM(START:END!F40) -> 0 | H40: =I40/G$24 -> #DIV/0! | I40: =+SUM(START:END!I40) -> 0 | K40: =IF(L40=0,0,L40/J$24) -> 0 | L40: =+SUM(START:END!L40) -> 0 | N40: =L40-F40 -> 0 | P40: =IF(Q40=0,0,Q40/O$24) -> 0 | Q40: =+SUM(START:END!Q40) -> 0 | S40: =L40-Q40 -> 0
A41: =+B41&C41 -> Véhicules neufsTOTAL VARIABLES | B41: =+$K$1 -> Véhicules neufs | C41: TOTAL VARIABLES | D41: % brut | E41: =F41/F$27 -> 0.43591998 | F41: =SUM(F31:F40) -> 175014.13 | G41: % brut | H41: =I41/I$27 -> #DIV/0! | I41: =SUM(I31:I40) -> 0 | J41: % brut | K41: =L41/L$27 -> 0.42035269 | L41: =SUM(L31:L40) -> 151170.53 | N41: =L41-F41 -> -23843.597 | O41: % brut | P41: =Q41/Q$27 -> 0.37651474 | Q41: =SUM(Q31:Q40) -> 200816.28 | S41: =L41-Q41 -> -49645.75
A42: =+B42&C42 -> Véhicules neufsSalaires cadres | B42: =+$K$1 -> Véhicules neufs | C42: Salaires cadres | F42: =+SUM(START:END!F42) -> 34584.993 | G42: =I41/(I27+I83) -> #DIV/0! | I42: =+SUM(START:END!I42) -> 0 | L42: =+SUM(START:END!L42) -> 31618.43 | N42: =L42-F42 -> -2966.5631 | Q42: =+SUM(START:END!Q42) -> 33156.32 | S42: =L42-Q42 -> -1537.89
A43: =+B43&C43 -> Véhicules neufsSalaires commis | B43: =+$K$1 -> Véhicules neufs | C43: Salaires commis | F43: =+SUM(START:END!F43) -> 20449.274 | I43: =+SUM(START:END!I43) -> 0 | L43: =+SUM(START:END!L43) -> 24152.64 | N43: =L43-F43 -> 3703.3655 | Q43: =+SUM(START:END!Q43) -> 14621.97 | S43: =L43-Q43 -> 9530.67
A44: =+B44&C44 -> Véhicules neufsSalaires autres | B44: =+$K$1 -> Véhicules neufs | C44: Salaires autres | F44: =+SUM(START:END!F44) -> 16417.968 | I44: =+SUM(START:END!I44) -> 0 | L44: =+SUM(START:END!L44) -> 25730.89 | N44: =L44-F44 -> 9312.9222 | Q44: =+SUM(START:END!Q44) -> 7432.32 | S44: =L44-Q44 -> 18298.57
A45: =+B45&C45 -> Véhicules neufsSalaires spécialistes | B45: =+$K$1 -> Véhicules neufs | C45: Salaires spécialistes | F45: =+SUM(START:END!F45) -> 0 | I45: =+SUM(START:END!I45) -> 0 | L45: =+SUM(START:END!L45) -> 0 | N45: =L45-F45 -> 0 | Q45: =+SUM(START:END!Q45) -> 0 | S45: =L45-Q45 -> 0
A46: =+B46&C46 -> Véhicules neufs[...] | B46: =+$K$1 -> Véhicules neufs | C46: [...] | F46: =+SUM(START:END!F46) -> 0 | I46: =+SUM(START:END!I46) -> 0 | L46: =+SUM(START:END!L46) -> 0 | N46: =L46-F46 -> 0 | Q46: =+SUM(START:END!Q46) -> 0 | S46: =L46-Q46 -> 0
A47: =+B47&C47 -> Véhicules neufs[...] | B47: =+$K$1 -> Véhicules neufs | C47: [...] | F47: =+SUM(START:END!F47) -> 0 | I47: =+SUM(START:END!I47) -> 0 | L47: =+SUM(START:END!L47) -> 0 | N47: =L47-F47 -> 0 | Q47: =+SUM(START:END!Q47) -> 0 | S47: =L47-Q47 -> 0
A48: =+B48&C48 -> Véhicules neufs[...] | B48: =+$K$1 -> Véhicules neufs | C48: [...] | F48: =+SUM(START:END!F48) -> 0 | I48: =+SUM(START:END!I48) -> 0 | L48: =+SUM(START:END!L48) -> 0 | N48: =L48-F48 -> 0 | Q48: =+SUM(START:END!Q48) -> 0 | S48: =L48-Q48 -> 0
A49: =+B49&C49 -> Véhicules neufsSalaires en absences | B49: =+$K$1 -> Véhicules neufs | C49: Salaires en absences | F49: =+SUM(START:END!F49) -> 22733.852 | I49: =+SUM(START:END!I49) -> 0 | L49: =+SUM(START:END!L49) -> 23068.35 | N49: =L49-F49 -> 334.49819 | Q49: =+SUM(START:END!Q49) -> 37950.6 | S49: =L49-Q49 -> -14882.25
A50: =+B50&C50 -> Véhicules neufsDéduction à la source | B50: =+$K$1 -> Véhicules neufs | C50: Déduction à la source | F50: =+SUM(START:END!F50) -> 22599.687 | I50: =+SUM(START:END!I50) -> 0 | L50: =+SUM(START:END!L50) -> 26783.49 | N50: =L50-F50 -> 4183.803 | Q50: =+SUM(START:END!Q50) -> 38466.55 | S50: =L50-Q50 -> -11683.06
A51: =+B51&C51 -> Véhicules neufsBénéfices marginaux | B51: =+$K$1 -> Véhicules neufs | C51: Bénéfices marginaux | F51: =+SUM(START:END!F51) -> 15825.612 | I51: =+SUM(START:END!I51) -> 0 | L51: =+SUM(START:END!L51) -> 12680.36 | N51: =L51-F51 -> -3145.2524 | Q51: =+SUM(START:END!Q51) -> 16237.25 | S51: =L51-Q51 -> -3556.89
A52: =+B52&C52 -> Véhicules neufsCsst | B52: =+$K$1 -> Véhicules neufs | C52: Csst | F52: =+SUM(START:END!F52) -> 7560.3512 | I52: =+SUM(START:END!I52) -> 0 | L52: =+SUM(START:END!L52) -> 5585.06 | N52: =L52-F52 -> -1975.2912 | Q52: =+SUM(START:END!Q52) -> 11123.54 | S52: =L52-Q52 -> -5538.48
A53: =+B53&C53 -> Véhicules neufs[...] | B53: =+$K$1 -> Véhicules neufs | C53: [...] | F53: =+SUM(START:END!F53) -> 0 | I53: =+SUM(START:END!I53) -> 0 | L53: =+SUM(START:END!L53) -> 0 | N53: =L53-F53 -> 0 | Q53: =+SUM(START:END!Q53) -> 0 | S53: =L53-Q53 -> 0
A54: =+B54&C54 -> Véhicules neufsTOTAL PERSONNEL | B54: =+$K$1 -> Véhicules neufs | C54: TOTAL PERSONNEL | D54: % brut | E54: =F54/F$27 -> 0.34913559 | F54: =+SUM(F42:F53) -> 140171.74 | G54: % brut | H54: =I54/I$27 -> #DIV/0! | I54: =+SUM(I42:I53) -> 0 | J54: % brut | K54: =L54/L$27 -> 0.41603904 | L54: =+SUM(L42:L53) -> 149619.22 | N54: =+SUM(N42:N53) -> 9447.4822 | O54: % brut | P54: =Q54/Q$27 -> 0.29809104 | Q54: =+SUM(Q42:Q53) -> 158988.55 | S54: =+SUM(S42:S53) -> -9369.33
A55: =+B55&C55 -> Véhicules neufsPublicité 2 | B55: =+$K$1 -> Véhicules neufs | C55: Publicité 2 | F55: =+SUM(START:END!F55) -> 0 | G55: =I54/(I27+I83) -> #DIV/0! | I55: =+SUM(START:END!I55) -> 0 | L55: =+SUM(START:END!L55) -> 0 | N55: =L55-F55 -> 0 | Q55: =+SUM(START:END!Q55) -> 0 | S55: =L55-Q55 -> 0
A56: =+B56&C56 -> Véhicules neufsService gratuit 2 | B56: =+$K$1 -> Véhicules neufs | C56: Service gratuit 2 | F56: =+SUM(START:END!F56) -> 0 | I56: =+SUM(START:END!I56) -> 0 | L56: =+SUM(START:END!L56) -> 0 | N56: =L56-F56 -> 0 | Q56: =+SUM(START:END!Q56) -> 0 | S56: =L56-Q56 -> 0
A57: =+B57&C57 -> Véhicules neufsFrais véhicules de cie | B57: =+$K$1 -> Véhicules neufs | C57: Frais véhicules de cie | F57: =+SUM(START:END!F57) -> 15891.667 | I57: =+SUM(START:END!I57) -> 0 | L57: =+SUM(START:END!L57) -> 13196.07 | N57: =L57-F57 -> -2695.5967 | Q57: =+SUM(START:END!Q57) -> 14678.9 | S57: =L57-Q57 -> -1482.83
A58: =+B58&C58 -> Véhicules neufsInformatique | B58: =+$K$1 -> Véhicules neufs | C58: Informatique | F58: =+SUM(START:END!F58) -> 12521.733 | I58: =+SUM(START:END!I58) -> 0 | L58: =+SUM(START:END!L58) -> 14216.67 | N58: =L58-F58 -> 1694.9372 | Q58: =+SUM(START:END!Q58) -> 14323.07 | S58: =L58-Q58 -> -106.4
A59: =+B59&C59 -> Véhicules neufsFrais de déplacement | B59: =+$K$1 -> Véhicules neufs | C59: Frais de déplacement | F59: =+SUM(START:END!F59) -> 2000.1761 | I59: =+SUM(START:END!I59) -> 0 | L59: =+SUM(START:END!L59) -> 1322.18 | N59: =L59-F59 -> -677.99609 | Q59: =+SUM(START:END!Q59) -> 3469.62 | S59: =L59-Q59 -> -2147.44
A60: =+B60&C60 -> Véhicules neufsServices extérieurs | B60: =+$K$1 -> Véhicules neufs | C60: Services extérieurs | F60: =+SUM(START:END!F60) -> 13698.009 | I60: =+SUM(START:END!I60) -> 0 | L60: =+SUM(START:END!L60) -> 12143.32 | N60: =L60-F60 -> -1554.6891 | Q60: =+SUM(START:END!Q60) -> 13806.45 | S60: =L60-Q60 -> -1663.13
A61: =+B61&C61 -> Véhicules neufsFournitures autres | B61: =+$K$1 -> Véhicules neufs | C61: Fournitures autres | F61: =+SUM(START:END!F61) -> 236.92668 | I61: =+SUM(START:END!I61) -> 0 | L61: =+SUM(START:END!L61) -> 0 | N61: =L61-F61 -> -236.92668 | Q61: =+SUM(START:END!Q61) -> 0 | S61: =L61-Q61 -> 0
A62: =+B62&C62 -> Véhicules neufsUniformes | B62: =+$K$1 -> Véhicules neufs | C62: Uniformes | F62: =+SUM(START:END!F62) -> 122.34623 | I62: =+SUM(START:END!I62) -> 0 | L62: =+SUM(START:END!L62) -> 0 | N62: =L62-F62 -> -122.34623 | Q62: =+SUM(START:END!Q62) -> 0 | S62: =L62-Q62 -> 0
A63: =+B63&C63 -> Véhicules neufsPapeterie | B63: =+$K$1 -> Véhicules neufs | C63: Papeterie | F63: =+SUM(START:END!F63) -> 1526.9021 | I63: =+SUM(START:END!I63) -> 0 | L63: =+SUM(START:END!L63) -> 1085.64 | N63: =L63-F63 -> -441.26207 | Q63: =+SUM(START:END!Q63) -> 1456.96 | S63: =L63-Q63 -> -371.32
A64: =+B64&C64 -> Véhicules neufsTéléphone | B64: =+$K$1 -> Véhicules neufs | C64: Téléphone | F64: =+SUM(START:END!F64) -> 517.4405 | I64: =+SUM(START:END!I64) -> 0 | L64: =+SUM(START:END!L64) -> 466.8 | N64: =L64-F64 -> -50.6405 | Q64: =+SUM(START:END!Q64) -> 655.91 | S64: =L64-Q64 -> -189.11
A65: =+B65&C65 -> Véhicules neufsFrais postaux | B65: =+$K$1 -> Véhicules neufs | C65: Frais postaux | F65: =+SUM(START:END!F65) -> 247.48859 | I65: =+SUM(START:END!I65) -> 0 | L65: =+SUM(START:END!L65) -> 211.96 | N65: =L65-F65 -> -35.528588 | Q65: =+SUM(START:END!Q65) -> 313.02 | S65: =L65-Q65 -> -101.06
A66: =+B66&C66 -> Véhicules neufsDivers | B66: =+$K$1 -> Véhicules neufs | C66: Divers | F66: =+SUM(START:END!F66) -> 940.36473 | I66: =+SUM(START:END!I66) -> 0 | L66: =+SUM(START:END!L66) -> 217.55 | N66: =L66-F66 -> -722.81473 | Q66: =+SUM(START:END!Q66) -> 378.51 | S66: =L66-Q66 -> -160.96
A67: =+B67&C67 -> Véhicules neufsFormation | B67: =+$K$1 -> Véhicules neufs | C67: Formation | F67: =+SUM(START:END!F67) -> 1225.4806 | I67: =+SUM(START:END!I67) -> 0 | L67: =+SUM(START:END!L67) -> 665.01 | N67: =L67-F67 -> -560.4706 | Q67: =+SUM(START:END!Q67) -> 2833.09 | S67: =L67-Q67 -> -2168.08
... A71: =+B71&C71 -> Véhicules neufs[...] | B71: =+$K$1 -> Véhicules neufs | C71: [...] | F71: =+SUM(START:END!F71) -> 0 | I71: =+SUM(START:END!I71) -> 0 | L71: =+SUM(START:END!L71) -> 0 | N71: =L71-F71 -> 0 | Q71: =+SUM(START:END!Q71) -> 0 | S71: =L71-Q71 -> 0
A72: =+B72&C72 -> Véhicules neufsTOTAL SEMI-FIXES | B72: =+$K$1 -> Véhicules neufs | C72: TOTAL SEMI-FIXES | D72: % brut | E72: =F72/F$27 -> 0.12768796 | F72: =+SUM(F55:F71) -> 51264.448 | G72: % brut | H72: =I72/I$27 -> #DIV/0! | I72: =+SUM(I55:I71) -> 0 | J72: % brut | K72: =L72/L$27 -> 0.14033613 | L72: =+SUM(L55:L71) -> 50468.78 | N72: =+SUM(N55:N71) -> -795.66819 | O72: % brut | P72: =Q72/Q$27 -> 0.11009861 | Q72: =+SUM(Q55:Q71) -> 58721.721 | S72: =+SUM(S55:S71) -> -8252.9415
A73: =+B73&C73 -> Véhicules neufs | B73: =+$K$1 -> Véhicules neufs
A74: =+B74&C74 -> Véhicules neufsTOTAL DES DÉPENSES | B74: =+$K$1 -> Véhicules neufs | C74: TOTAL DES DÉPENSES | D74: % brut | E74: =F74/F$27 -> 0.91274354 | F74: =F41+F54+F72 -> 366450.31 | G74: % brut | H74: =I74/I$27 -> #DIV/0! | I74: =I41+I54+I72 -> 0 | J74: % brut | K74: =L74/L$27 -> 0.97672786 | L74: =L41+L54+L72 -> 351258.53 | N74: =L74-F74 -> -15191.783 | O74: % brut | P74: =Q74/Q$27 -> 0.78470439 | Q74: =Q41+Q54+Q72 -> 418526.55 | S74: =L74-Q74 -> -67268.021
A75: =+B75&C75 -> Véhicules neufsProgramme neuf 1 | B75: =+$K$1 -> Véhicules neufs | C75: Programme neuf 1 | F75: =+SUM(START:END!F75) -> 16584.69 | I75: =+SUM(START:END!I75) -> 0 | L75: =+SUM(START:END!L75) -> 0 | N75: =L75-F75 -> -16584.69 | Q75: =+SUM(START:END!Q75) -> 22000
A76: =+B76&C76 -> Véhicules neufsProgramme neuf 2 | B76: =+$K$1 -> Véhicules neufs | C76: Programme neuf 2 | F76: =+SUM(START:END!F76) -> 0 | I76: =+SUM(START:END!I76) -> 0 | L76: =+SUM(START:END!L76) -> 0 | N76: =L76-F76 -> 0 | Q76: =+SUM(START:END!Q76) -> 0 | S76: =L76-Q76 -> 0
A77: =+B77&C77 -> Véhicules neufsProgramme neuf 3 | B77: =+$K$1 -> Véhicules neufs | C77: Programme neuf 3 | F77: =+SUM(START:END!F77) -> 0 | I77: =+SUM(START:END!I77) -> 0 | L77: =+SUM(START:END!L77) -> 0 | N77: =L77-F77 -> 0 | Q77: =+SUM(START:END!Q77) -> 0 | S77: =L77-Q77 -> 0
A78: =+B78&C78 -> Véhicules neufsHoldbacks | B78: =+$K$1 -> Véhicules neufs | C78: Holdbacks | F78: =+SUM(START:END!F78) -> 122141.41 | I78: =+SUM(START:END!I78) -> 0 | L78: =+SUM(START:END!L78) -> 106168.1 | N78: =L78-F78 -> -15973.307 | Q78: =+SUM(START:END!Q78) -> 135227 | S78: =L78-Q78 -> -29058.9
A79: =+B79&C79 -> Véhicules neufs[...] | B79: =+$K$1 -> Véhicules neufs | C79: [...] | F79: =+SUM(START:END!F79) -> 0 | I79: =+SUM(START:END!I79) -> 0 | L79: =+SUM(START:END!L79) -> 0 | N79: =L79-F79 -> 0 | Q79: =+SUM(START:END!Q79) -> 0 | S79: =L79-Q79 -> 0
A80: =+B80&C80 -> Véhicules neufs[...] | B80: =+$K$1 -> Véhicules neufs | C80: [...] | F80: =+SUM(START:END!F80) -> 0 | I80: =+SUM(START:END!I80) -> 0 | L80: =+SUM(START:END!L80) -> 0 | N80: =L80-F80 -> 0 | Q80: =+SUM(START:END!Q80) -> 0 | S80: =L80-Q80 -> 0
A81: =+B81&C81 -> Véhicules neufs[...] | B81: =+$K$1 -> Véhicules neufs | C81: [...] | F81: =+SUM(START:END!F81) -> 0 | I81: =+SUM(START:END!I81) -> 0 | L81: =+SUM(START:END!L81) -> 0 | N81: =L81-F81 -> 0 | Q81: =+SUM(START:END!Q81) -> 0 | S81: =L81-Q81 -> 0
A82: =+B82&C82 -> Véhicules neufsFrais administration | B82: =+$K$1 -> Véhicules neufs | C82: Frais administration | F82: =+SUM(START:END!F82) -> 38482.425 | I82: =+SUM(START:END!I82) -> 0 | L82: =+SUM(START:END!L82) -> 45832 | N82: =L82-F82 -> 7349.575 | Q82: =+SUM(START:END!Q82) -> -8537 | S82: =L82-Q82 -> 54369
A83: =+B83&C83 -> Véhicules neufsAUTRES REVENUS | B83: =+$K$1 -> Véhicules neufs | C83: AUTRES REVENUS | F83: =+SUM(F75:F82) -> 177208.52 | I83: =+SUM(I75:I82) -> 0 | L83: =+SUM(L75:L82) -> 152000.1 | N83: =+SUM(N75:N82) -> -25208.421 | Q83: =+SUM(Q75:Q82) -> 148690 | S83: =+SUM(S75:S82) -> 25310.1
A84: =+B84&C84 -> Véhicules neufs | B84: =+$K$1 -> Véhicules neufs
A85: =+B85&C85 -> Véhicules neufsPROFIT DÉPARTEMENTAL | B85: =+$K$1 -> Véhicules neufs | C85: PROFIT DÉPARTEMENTAL | F85: =F27-F74+F83 -> 212240.44 | I85: =I27-I74+I83 -> 0 | L85: =L27-L74+L83 -> 160369.41 | N85: =N27-N41-N54-N72+N83 -> -51871.03 | Q85: =Q27-Q74+Q83 -> 263519.14 | S85: =S27-S41-S54-S72+S83 -> -81149.728
C89: =C1 -> Conso | K89: Véhicules usagés | S89: =$S$1 -> Volks Juin / Juillet 2023
D91: BUDGET ORIGINAL | G91: BUDGET RÉVISÉ | J91: RÉALISATION | M91: ÉCART réel / Budget | O91: ANNÉE PRÉCÉDENTE | R91: ECART (réel/ Ann.Préc.)
D92: UNITE | E92: $P/UNITÉ | F92: $PROFITS | G92: UNITE | H92: $P/UNITÉ | I92: $PROFITS | J92: UNITE | K92: $P/UNITE | L92: $PROFITS | M92: UNITÉS | N92: $PROFITS | O92: UNITE | P92: $P/UNITE | Q92: $PROFITS | R92: UNITÉS | S92: $PROFITS
A93: =+B93&C93 -> Véhicules usagésVentes nettes | B93: Véhicules usagés | C93: Ventes nettes | F93: =+SUM(START:END!F93) -> 3175585.4 | I93: =+SUM(START:END!I93) -> 0 | L93: =+SUM(START:END!L93) -> 3705452.9 | Q93: =+SUM(START:END!Q93) -> 3596877.2
A94: =+B94&C94 -> Véhicules usagésCertifié | B94: Véhicules usagés | C94: Certifié | D94: =+SUM(START:END!D94) -> 76 | E94: =IF(D94=0,0,F94/D94) -> 1858 | F94: =+SUM(START:END!F94) -> 141208 | G94: =+SUM(START:END!G94) -> 0 | H94: =IF(G94=0,0,I94/G94) -> 0 | I94: =+SUM(START:END!I94) -> 0 | J94: =+SUM(START:END!J94) -> 50 | K94: =IF(J94=0,0,L94/J94) -> 2031.7368 | L94: =+SUM(START:END!L94) -> 101586.84 | M94: =J94-D94 -> -26 | N94: =L94-F94 -> -39621.16 | O94: =+SUM(START:END!O94) -> 73 | P94: =IF(O94=0,0,Q94/O94) -> 2195.1263 | Q94: =+SUM(START:END!Q94) -> 160244.22 | R94: =J94-O94 -> -23 | S94: =L94-Q94 -> -58657.38
A95: =+B95&C95 -> Véhicules usagésNon Certifié | B95: Véhicules usagés | C95: Non Certifié | D95: =+SUM(START:END!D95) -> 0 | E95: =IF(D95=0,0,F95/D95) -> 0 | F95: =+SUM(START:END!F95) -> 0 | G95: =+SUM(START:END!G95) -> 0 | H95: =IF(G95=0,0,I95/G95) -> 0 | I95: =+SUM(START:END!I95) -> 0 | J95: =+SUM(START:END!J95) -> 11 | K95: =IF(J95=0,0,L95/J95) -> 1788.9127 | L95: =+SUM(START:END!L95) -> 19678.04 | M95: =J95-D95 -> 11 | N95: =L95-F95 -> 19678.04 | O95: =+SUM(START:END!O95) -> 2 | P95: =IF(O95=0,0,Q95/O95) -> 1700.39 | Q95: =+SUM(START:END!Q95) -> 3400.78 | R95: =J95-O95 -> 9 | S95: =L95-Q95 -> 16277.26
A96: =+B96&C96 -> Véhicules usagésTotal Usagés | B96: Véhicules usagés | C96: Total Usagés | D96: =+D95+D94 -> 76 | E96: =IF(D96=0,0,F96/D96) -> 1858 | F96: =+F94+F95 -> 141208 | G96: =+G95+G94 -> 0 | H96: =IF(G96=0,0,I96/G96) -> 0 | I96: =+I94+I95 -> 0 | J96: =+J94+J95 -> 61 | K96: =IF(J96<=0,0,L96/J96) -> 1987.9489 | L96: =+L94+L95 -> 121264.88 | M96: =J96-D96 -> -15 | N96: =L96-F96 -> -19943.12 | O96: =+O94+O95 -> 75 | P96: =IF(O96<=0,0,Q96/O96) -> 2181.9333 | Q96: =+Q94+Q95 -> 163645 | R96: =R94+R95 -> -14 | S96: =S94+S95 -> -42380.12
A97: =+B97&C97 -> Véhicules usagés | B97: Véhicules usagés | E97: =IF(D97=0,0,F97/D97) -> 0 | H97: =IF(G97=0,0,I97/G97) -> 0 | M97: =M96/D96 -> -0.19736842 | N97: =N96/F96 -> -0.14123222 | R97: =R96/O96 -> -0.18666667 | S97: =IF(Q96=0,0,(S96/Q96)) -> -0.25897595
A98: =+B98&C98 -> Véhicules usagésUS | B98: Véhicules usagés | C98: US | D98: =+SUM(START:END!D98) -> 0 | E98: =IF(D98=0,0,F98/D98) -> 0 | F98: =+SUM(START:END!F98) -> 0 | G98: =+SUM(START:END!G98) -> 0 | H98: =IF(G98=0,0,I98/G98) -> 0 | I98: =+SUM(START:END!I98) -> 0 | J98: =+SUM(START:END!J98) -> 0 | K98: =IF(J98=0,0,L98/J98) -> 0 | L98: =+SUM(START:END!L98) -> 0 | O98: =+SUM(START:END!O98) -> 0 | P98: =IF(O98=0,0,Q98/O98) -> 0 | Q98: =+SUM(START:END!Q98) -> 0
A99: =+B99&C99 -> Véhicules usagésVentes au Gros | B99: Véhicules usagés | C99: Ventes au Gros | D99: =+SUM(START:END!D99) -> 64.307692 | E99: =IF(D99=0,0,F99/D99) -> 399 | F99: =+SUM(START:END!F99) -> 25658.769 | G99: =+SUM(START:END!G99) -> 0 | H99: =IF(G99=0,0,I99/G99) -> 0 | I99: =+SUM(START:END!I99) -> 0 | J99: =+SUM(START:END!J99) -> 85 | K99: =IF(J99=0,0,L99/J99) -> 584.44541 | L99: =+SUM(START:END!L99) -> 49677.86 | M99: =J99-D99 -> 20.692308 | N99: =L99-F99 -> 24019.091 | O99: =+SUM(START:END!O99) -> 73 | P99: =IF(O99=0,0,Q99/O99) -> 196.76247 | Q99: =+SUM(START:END!Q99) -> 14363.66 | R99: =J99-O99 -> 12 | S99: =L99-Q99 -> 35314.2
A100: =+B100&C100 -> Véhicules usagés | B100: Véhicules usagés
A101: =+B101&C101 -> Véhicules usagésRev. Finances | B101: Véhicules usagés | C101: Rev. Finances | D101: 0 | E101: =IF(D101=0,0,F101/D101) -> 0 | F101: =+SUM(START:END!F101) -> 38000 | G101: 0 | H101: =IF(G101=0,0,I101/G101) -> 0 | I101: =+SUM(START:END!I101) -> 0 | K101: =IF(J96=0,0,L101/J96) -> 606.56262 | L101: =+SUM(START:END!L101) -> 37000.32 | N101: =L101-F101 -> -999.68 | P101: =IF(O96=0,0,Q101/O96) -> 871.5552 | Q101: =+SUM(START:END!Q101) -> 65366.64 | R101: =O101-K101 -> -606.56262 | S101: =L101-Q101 -> -28366.32
A102: =+B102&C102 -> Véhicules usagésRev. Protections | B102: Véhicules usagés | C102: Rev. Protections | D102: 0 | E102: =IF(D102=0,0,F102/D102) -> 0 | F102: =+SUM(START:END!F102) -> 95000 | G102: 0 | H102: =IF(G102=0,0,I102/G102) -> 0 | I102: =+SUM(START:END!I102) -> 0 | K102: =IF(J96=0,0,L102/J96) -> 1307.5759 | L102: =+SUM(START:END!L102) -> 79762.13 | N102: =L102-F102 -> -15237.87 | P102: =IF(O96=0,0,Q102/O96) -> 1153.4447 | Q102: =+SUM(START:END!Q102) -> 86508.35 | R102: =O102-K102 -> -1307.5759 | S102: =L102-Q102 -> -6746.22
A103: =+B103&C103 -> Véhicules usagésRev. Autres | B103: Véhicules usagés | C103: Rev. Autres | D103: 0 | E103: =IF(D103=0,0,F103/D103) -> 0 | F103: =+SUM(START:END!F103) -> 26600 | G103: 0 | H103: =IF(G103=0,0,I103/G103) -> 0 | I103: =+SUM(START:END!I103) -> 0 | K103: =IF(J96=0,0,L103/J96) -> 39.466393 | L103: =+SUM(START:END!L103) -> 2407.45 | N103: =L103-F103 -> -24192.55 | P103: =IF(O96=0,0,Q103/O96) -> 41.582 | Q103: =+SUM(START:END!Q103) -> 3118.65 | R103: =O103-K103 -> -39.466393 | S103: =L103-Q103 -> -711.2
A104: =+B104&C104 -> Véhicules usagésTotal F&I | B104: Véhicules usagés | C104: Total F&I | D104: =D96 -> 76 | E104: =IF(D104=0,0,F104/D104) -> 2100 | F104: =F101+F102+F103 -> 159600 | G104: =G96 -> 0 | H104: =IF(G104=0,0,I104/G104) -> 0 | I104: =I101+I102+I103 -> 0 | J104: =J96 -> 61 | K104: =IF(J104<=0,0,L104/J104) -> 1953.6049 | L104: =L101+L102+L103 -> 119169.9 | M104: =J104-D104 -> -15 | N104: =L104-F104 -> -40430.1 | O104: =O96 -> 75 | P104: =IF(O104<=0,0,Q104/O104) -> 2066.5819 | Q104: =Q101+Q102+Q103 -> 154993.64 | S104: =L104-Q104 -> -35823.74
A105: =+B105&C105 -> Véhicules usagés | B105: Véhicules usagés | N105: =N104/F104 -> -0.25332143 | S105: =IF(Q104=0,0,(S104/Q104)) -> -0.23113039
A106: =+B106&C106 -> Véhicules usagés | B106: Véhicules usagés
A107: =+B107&C107 -> Véhicules usagésTotal Dépt. Usagés | B107: Véhicules usagés | C107: Total Dépt. Usagés | D107: =D96+D99 -> 140.30769 | E107: =IF(D107<=0,0,F107/D107) -> 2326.7917 | F107: =F96+F104+F99 -> 326466.77 | G107: =G96+G99 -> 0 | H107: =IF(G107<=0,0,I107/G107) -> 0 | I107: =I96+I104+I99 -> 0 | J107: =J96+J99+J98 -> 146 | K107: =IF(J107<=0,0,L107/J107) -> 1987.0729 | L107: =L96+L104+L99+L98 -> 290112.64 | M107: =J107-D107 -> 5.6923077 | N107: =L107-F107 -> -36354.129 | O107: =O96+O99+O98 -> 148 | P107: =IF(O107<=0,0,Q107/O107) -> 2250.0155 | Q107: =Q96+Q104+Q99+Q98 -> 333002.3 | R107: =J107-O107 -> -2 | S107: =L107-Q107 -> -42889.66
...

Sheet START

Sheet Juillet 2023
C1: =[5]Parametres!B1 -> Volks | K1: Véhicules neufs | S1: =CONCATENATE("Réalisé,"," ",[5]Parametres!B3," ",[5]Parametres!B4) -> Réalisé, Juillet 2023
D2: X | E2: O | F2: U | J2: NB | L2: $ | O2: NB | Q2: $ | V2: *** NE PAS EFFACER / Pour An Précédente ***
D3: BUDGET ORIGINAL | J3: RÉALISATION | M3: ÉCART réel / Budget | O3: ANNÉE PRÉCÉDENTE | R3: ECART (réel/ Ann.Préc.) | V3: NEUF | W3: 0.45
D4: UNITÉS | E4: $P/UNITÉ | F4: $PROFITS | J4: UNITÉS | K4: $P/UNITE | L4: $PROFITS | M4: UNITÉS | N4: $PROFITS | O4: UNITÉS | P4: $P/UNITE | Q4: $PROFITS | R4: UNITÉS | S4: $PROFITS | V4: USAGE | W4: 0.1
A5: Véhicules neufsVentes nettes | B5: Véhicules neufs | C5: Ventes nettes | F5: {=+INDEX('[5]Budget original'!$A$2:$AO$500,MATCH($A5,'[5]Budget original'!$A$2:$A$500,0),MATCH(F$2,'[5]Budget original'!$A$2:$AO$2,0))} -> 2357227.3 | L5: =-SUMIFS([5]BV_Data_An_Cour!$O:$O,[5]BV_Data_An_Cour!$X:$X,"Oui",[5]BV_Data_An_Cour!$U:$U,$B5) -> 2122186.9 | Q5: =-SUMIFS([5]BV_Data_An_Prec!$O:$O,[5]BV_Data_An_Prec!$X:$X,"Oui",[5]BV_Data_An_Prec!$U:$U,$B5) -> 2657067 | V5: SERVICE | W5: 0.225
A6: Véhicules neufsAutos détail | B6: Véhicules neufs | C6: Autos détail | D6: {=+INDEX('[5]Budget original'!$A$2:$AO$500,MATCH($A6,'[5]Budget original'!$A$2:$A$500,0),MATCH(D$2,'[5]Budget original'!$A$2:$AO$2,0))} -> 10.048 | E6: =IF(D6=0,0,F6/D6) -> 1988.434 | F6: {=+INDEX('[5]Budget original'!$A$2:$AO$500,MATCH($A6,'[5]Budget original'!$A$2:$A$500,0),MATCH(F$2,'[5]Budget original'!$A$2:$AO$2,0))} -> 19979.785 | J6: =-SUMIFS([5]BV_Data_An_Cour!$O:$O,[5]BV_Data_An_Cour!$U:$U,$B6,[5]BV_Data_An_Cour!$V:$V,$C6,[5]BV_Data_An_Cour!$W:$W,J$2) -> 12 | K6: =IF(J6=0,0,L6/J6) -> 1882.1942 | L6: =-SUMIFS([5]BV_Data_An_Cour!$O:$O,[5]BV_Data_An_Cour!$U:$U,$B6,[5]BV_Data_An_Cour!$V:$V,$C6,[5]BV_Data_An_Cour!$W:$W,L$2) -> 22586.33 | M6: =J6-D6 -> 1.952 | N6: =L6-F6 -> 2606.5452 | O6: =-SUMIFS([5]BV_Data_An_Prec!$O:$O,[5]BV_Data_An_Prec!$U:$U,$B6,[5]BV_Data_An_Prec!$V:$V,$C6,[5]BV_Data_An_Prec!$W:$W,O$2) -> 13 | P6: =IF(O6=0,0,Q6/O6) -> 2819.2123 | Q6: =-SUMIFS([5]BV_Data_An_Prec!$O:$O,[5]BV_Data_An_Prec!$U:$U,$B6,[5]BV_Data_An_Prec!$V:$V,$C6,[5]BV_Data_An_Prec!$W:$W,Q$2) -> 36649.76 | R6: =J6-O6 -> -1 | S6: =L6-Q6 -> -14063.43 | V6: CARROSSERIE | W6: 0.025
A7: Véhicules neufsCamions détail | B7: Véhicules neufs | C7: Camions détail | D7: {=+INDEX('[5]Budget original'!$A$2:$AO$500,MATCH($A7,'[5]Budget original'!$A$2:$A$500,0),MATCH(D$2,'[5]Budget original'!$A$2:$AO$2,0))} -> 40.187981 | E7: =IF(D7=0,0,F7/D7) -> 2556.3336 | F7: {=+INDEX('[5]Budget original'!$A$2:$AO$500,MATCH($A7,'[5]Budget original'!$A$2:$A$500,0),MATCH(F$2,'[5]Budget original'!$A$2:$AO$2,0))} -> 102733.89 | J7: =-SUMIFS([5]BV_Data_An_Cour!$O:$O,[5]BV_Data_An_Cour!$U:$U,$B7,[5]BV_Data_An_Cour!$V:$V,$C7,[5]BV_Data_An_Cour!$W:$W,J$2) -> 24 | K7: =IF(J7=0,0,L7/J7) -> 2577.0196 | L7: =-SUMIFS([5]BV_Data_An_Cour!$O:$O,[5]BV_Data_An_Cour!$U:$U,$B7,[5]BV_Data_An_Cour!$V:$V,$C7,[5]BV_Data_An_Cour!$W:$W,L$2) -> 61848.47 | M7: =J7-D7 -> -16.187981 | N7: =L7-F7 -> -40885.417 | O7: =-SUMIFS([5]BV_Data_An_Prec!$O:$O,[5]BV_Data_An_Prec!$U:$U,$B7,[5]BV_Data_An_Prec!$V:$V,$C7,[5]BV_Data_An_Prec!$W:$W,O$2) -> 37 | P7: =IF(O7=0,0,Q7/O7) -> 3278.5565 | Q7: =-SUMIFS([5]BV_Data_An_Prec!$O:$O,[5]BV_Data_An_Prec!$U:$U,$B7,[5]BV_Data_An_Prec!$V:$V,$C7,[5]BV_Data_An_Prec!$W:$W,Q$2) -> 121306.59 | R7: =J7-O7 -> -13 | S7: =L7-Q7 -> -59458.12 | V7: PIECES | W7: 0.2
A8: Véhicules neufsSprinter | B8: Véhicules neufs | C8: Sprinter | D8: {=+INDEX('[5]Budget original'!$A$2:$AO$500,MATCH($A8,'[5]Budget original'!$A$2:$A$500,0),MATCH(D$2,'[5]Budget original'!$A$2:$AO$2,0))} -> 0 | E8: =IF(D8=0,0,F8/D8) -> 0 | F8: {=+INDEX('[5]Budget original'!$A$2:$AO$500,MATCH($A8,'[5]Budget original'!$A$2:$A$500,0),MATCH(F$2,'[5]Budget original'!$A$2:$AO$2,0))} -> 0 | J8: =-SUMIFS([5]BV_Data_An_Cour!$O:$O,[5]BV_Data_An_Cour!$U:$U,$B8,[5]BV_Data_An_Cour!$V:$V,$C8,[5]BV_Data_An_Cour!$W:$W,J$2) -> 0 | K8: =IF(J8=0,0,L8/J8) -> 0 | L8: =-SUMIFS([5]BV_Data_An_Cour!$O:$O,[5]BV_Data_An_Cour!$U:$U,$B8,[5]BV_Data_An_Cour!$V:$V,$C8,[5]BV_Data_An_Cour!$W:$W,L$2) -> 0 | M8: =J8-D8 -> 0 | N8: =L8-F8 -> 0 | O8: =-SUMIFS([5]BV_Data_An_Prec!$O:$O,[5]BV_Data_An_Prec!$U:$U,$B8,[5]BV_Data_An_Prec!$V:$V,$C8,[5]BV_Data_An_Prec!$W:$W,O$2) -> 0 | P8: =IF(O8=0,0,Q8/O8) -> 0 | Q8: =-SUMIFS([5]BV_Data_An_Prec!$O:$O,[5]BV_Data_An_Prec!$U:$U,$B8,[5]BV_Data_An_Prec!$V:$V,$C8,[5]BV_Data_An_Prec!$W:$W,Q$2) -> 0 | R8: =J8-O8 -> 0 | S8: =L8-Q8 -> 0 | W8: =SUM(W3:W7) -> 1
A9: Véhicules neufsMoto détail | B9: Véhicules neufs | C9: Moto détail | D9: {=+INDEX('[5]Budget original'!$A$2:$AO$500,MATCH($A9,'[5]Budget original'!$A$2:$A$500,0),MATCH(D$2,'[5]Budget original'!$A$2:$AO$2,0))} -> 0 | E9: =IF(D9=0,0,F9/D9) -> 0 | F9: {=+INDEX('[5]Budget original'!$A$2:$AO$500,MATCH($A9,'[5]Budget original'!$A$2:$A$500,0),MATCH(F$2,'[5]Budget original'!$A$2:$AO$2,0))} -> 0 | J9: =-SUMIFS([5]BV_Data_An_Cour!$O:$O,[5]BV_Data_An_Cour!$U:$U,$B9,[5]BV_Data_An_Cour!$V:$V,$C9,[5]BV_Data_An_Cour!$W:$W,J$2) -> 0 | K9: =IF(J9=0,0,L9/J9) -> 0 | L9: =-SUMIFS([5]BV_Data_An_Cour!$O:$O,[5]BV_Data_An_Cour!$U:$U,$B9,[5]BV_Data_An_Cour!$V:$V,$C9,[5]BV_Data_An_Cour!$W:$W,L$2) -> 0 | M9: =J9-D9 -> 0 | N9: =L9-F9 -> 0 | O9: =-SUMIFS([5]BV_Data_An_Prec!$O:$O,[5]BV_Data_An_Prec!$U:$U,$B9,[5]BV_Data_An_Prec!$V:$V,$C9,[5]BV_Data_An_Prec!$W:$W,O$2) -> 0 | P9: =IF(O9=0,0,Q9/O9) -> 0 | Q9: =-SUMIFS([5]BV_Data_An_Prec!$O:$O,[5]BV_Data_An_Prec!$U:$U,$B9,[5]BV_Data_An_Prec!$V:$V,$C9,[5]BV_Data_An_Prec!$W:$W,Q$2) -> 0 | R9: =J9-O9 -> 0 | S9: =L9-Q9 -> 0
A10: Véhicules neufs[...] | B10: Véhicules neufs | C10: [...] | D10: 0 | E10: =IF(D10=0,0,F10/D10) -> 0 | F10: {=+INDEX('[5]Budget original'!$A$2:$AO$500,MATCH($A10,'[5]Budget original'!$A$2:$A$500,0),MATCH(F$2,'[5]Budget original'!$A$2:$AO$2,0))} -> 0 | J10: =-SUMIFS([5]BV_Data_An_Cour!$O:$O,[5]BV_Data_An_Cour!$U:$U,$B10,[5]BV_Data_An_Cour!$V:$V,$C10,[5]BV_Data_An_Cour!$W:$W,J$2) -> 0 | K10: =IF(J10=0,0,L10/J10) -> 0 | L10: =-SUMIFS([5]BV_Data_An_Cour!$O:$O,[5]BV_Data_An_Cour!$U:$U,$B10,[5]BV_Data_An_Cour!$V:$V,$C10,[5]BV_Data_An_Cour!$W:$W,L$2) -> 0 | M10: =J10-D10 -> 0 | N10: =L10-F10 -> 0 | O10: =-SUMIFS([5]BV_Data_An_Prec!$O:$O,[5]BV_Data_An_Prec!$U:$U,$B10,[5]BV_Data_An_Prec!$V:$V,$C10,[5]BV_Data_An_Prec!$W:$W,O$2) -> 0 | P10: =IF(O10=0,0,Q10/O10) -> 0 | Q10: =-SUMIFS([5]BV_Data_An_Prec!$O:$O,[5]BV_Data_An_Prec!$U:$U,$B10,[5]BV_Data_An_Prec!$V:$V,$C10,[5]BV_Data_An_Prec!$W:$W,Q$2) -> 0 | R10: =J10-O10 -> 0 | S10: =L10-Q10 -> 0
A11: Véhicules neufs[...] | B11: Véhicules neufs | C11: [...] | D11: 0 | E11: =IF(D11=0,0,F11/D11) -> 0 | F11: {=+INDEX('[5]Budget original'!$A$2:$AO$500,MATCH($A11,'[5]Budget original'!$A$2:$A$500,0),MATCH(F$2,'[5]Budget original'!$A$2:$AO$2,0))} -> 0 | J11: =-SUMIFS([5]BV_Data_An_Cour!$O:$O,[5]BV_Data_An_Cour!$U:$U,$B11,[5]BV_Data_An_Cour!$V:$V,$C11,[5]BV_Data_An_Cour!$W:$W,J$2) -> 0 | K11: =IF(J11=0,0,L11/J11) -> 0 | L11: =-SUMIFS([5]BV_Data_An_Cour!$O:$O,[5]BV_Data_An_Cour!$U:$U,$B11,[5]BV_Data_An_Cour!$V:$V,$C11,[5]BV_Data_An_Cour!$W:$W,L$2) -> 0 | M11: =J11-D11 -> 0 | N11: =L11-F11 -> 0 | O11: =-SUMIFS([5]BV_Data_An_Prec!$O:$O,[5]BV_Data_An_Prec!$U:$U,$B11,[5]BV_Data_An_Prec!$V:$V,$C11,[5]BV_Data_An_Prec!$W:$W,O$2) -> 0 | P11: =IF(O11=0,0,Q11/O11) -> 0 | Q11: =-SUMIFS([5]BV_Data_An_Prec!$O:$O,[5]BV_Data_An_Prec!$U:$U,$B11,[5]BV_Data_An_Prec!$V:$V,$C11,[5]BV_Data_An_Prec!$W:$W,Q$2) -> 0 | R11: =J11-O11 -> 0 | S11: =L11-Q11 -> 0
A12: Véhicules neufs[...] | B12: Véhicules neufs | C12: [...] | D12: 0 | E12: =IF(D12=0,0,F12/D12) -> 0 | F12: {=+INDEX('[5]Budget original'!$A$2:$AO$500,MATCH($A12,'[5]Budget original'!$A$2:$A$500,0),MATCH(F$2,'[5]Budget original'!$A$2:$AO$2,0))} -> 0 | J12: =-SUMIFS([5]BV_Data_An_Cour!$O:$O,[5]BV_Data_An_Cour!$U:$U,$B12,[5]BV_Data_An_Cour!$V:$V,$C12,[5]BV_Data_An_Cour!$W:$W,J$2) -> 0 | K12: =IF(J12=0,0,L12/J12) -> 0 | L12: =-SUMIFS([5]BV_Data_An_Cour!$O:$O,[5]BV_Data_An_Cour!$U:$U,$B12,[5]BV_Data_An_Cour!$V:$V,$C12,[5]BV_Data_An_Cour!$W:$W,L$2) -> 0 | M12: =J12-D12 -> 0 | N12: =L12-F12 -> 0 | O12: =-SUMIFS([5]BV_Data_An_Prec!$O:$O,[5]BV_Data_An_Prec!$U:$U,$B12,[5]BV_Data_An_Prec!$V:$V,$C12,[5]BV_Data_An_Prec!$W:$W,O$2) -> 0 | P12: =IF(O12=0,0,Q12/O12) -> 0 | Q12: =-SUMIFS([5]BV_Data_An_Prec!$O:$O,[5]BV_Data_An_Prec!$U:$U,$B12,[5]BV_Data_An_Prec!$V:$V,$C12,[5]BV_Data_An_Prec!$W:$W,Q$2) -> 0 | R12: =J12-O12 -> 0 | S12: =L12-Q12 -> 0
A13: Véhicules neufsTotal Neufs | B13: Véhicules neufs | C13: Total Neufs | D13: =+SUM(D6:D12) -> 50.235981 | E13: =IF(D13<=0,0,F13/D13) -> 2442.7446 | F13: =+SUM(F6:F12) -> 122713.67 | J13: =+SUM(J6:J12) -> 36 | K13: =IF(J13<=0,0,L13/J13) -> 2345.4111 | L13: =+SUM(L6:L12) -> 84434.8 | M13: =+SUM(M6:M12) -> -14.235981 | N13: =+SUM(N6:N12) -> -38278.872 | O13: =+SUM(O6:O12) -> 50 | P13: =IF(O13<=0,0,Q13/O13) -> 3159.127 | Q13: =+SUM(Q6:Q12) -> 157956.35 | R13: =+SUM(R6:R12) -> -14 | S13: =+SUM(S6:S12) -> -73521.55
A14: Véhicules neufs | B14: Véhicules neufs | M14: =IF(D13=0,0,M13/D13) -> -0.28338216 | N14: =IF(F13=0,0,N13/F13) -> -0.31193649 | R14: =R13/O13 -> -0.28 | S14: =IF(Q13=0,0,(S13/Q13)) -> -0.46545486 | AD14: 20 | AE14: 1000 | AF14: =AD14*AE14 -> 20000
A15: Véhicules neufsEx-Démos et courtoisies | B15: Véhicules neufs | C15: Ex-Démos et courtoisies | D15: {=+INDEX('[5]Budget original'!$A$2:$AO$500,MATCH($A15,'[5]Budget original'!$A$2:$A$500,0),MATCH(D$2,'[5]Budget original'!$A$2:$AO$2,0))} -> 2.4 | E15: =IF(D15=0,0,F15/D15) -> 2442.5492 | F15: {=+INDEX('[5]Budget original'!$A$2:$AO$500,MATCH($A15,'[5]Budget original'!$A$2:$A$500,0),MATCH(F$2,'[5]Budget original'!$A$2:$AO$2,0))} -> 5862.1181 | J15: =-SUMIFS([5]BV_Data_An_Cour!$O:$O,[5]BV_Data_An_Cour!$U:$U,$B15,[5]BV_Data_An_Cour!$V:$V,$C15,[5]BV_Data_An_Cour!$W:$W,J$2) -> 3 | K15: =IF(J15=0,0,L15/J15) -> 851.18 | L15: =-SUMIFS([5]BV_Data_An_Cour!$O:$O,[5]BV_Data_An_Cour!$U:$U,$B15,[5]BV_Data_An_Cour!$V:$V,$C15,[5]BV_Data_An_Cour!$W:$W,L$2) -> 2553.54 | M15: =J15-D15 -> 0.6 | N15: =L15-F15 -> -3308.5781 | O15: =-SUMIFS([5]BV_Data_An_Prec!$O:$O,[5]BV_Data_An_Prec!$U:$U,$B15,[5]BV_Data_An_Prec!$V:$V,$C15,[5]BV_Data_An_Prec!$W:$W,O$2) -> 3 | P15: =IF(O15=0,0,Q15/O15) -> 2992.6 | Q15: =-SUMIFS([5]BV_Data_An_Prec!$O:$O,[5]BV_Data_An_Prec!$U:$U,$B15,[5]BV_Data_An_Prec!$V:$V,$C15,[5]BV_Data_An_Prec!$W:$W,Q$2) -> 8977.8 | R15: =J15-O15 -> 0 | S15: =L15-Q15 -> -6424.26 | AD15: 25 | AE15: =AF15/AD15 -> 800 | AF15: =AF14 -> 20000
A16: Véhicules neufs | B16: Véhicules neufs
A17: Véhicules neufsFlottes | B17: Véhicules neufs | C17: Flottes | D17: {=+INDEX('[5]Budget original'!$A$2:$AO$500,MATCH($A17,'[5]Budget original'!$A$2:$A$500,0),MATCH(D$2,'[5]Budget original'!$A$2:$AO$2,0))} -> 1.92 | E17: =IF(D17=0,0,F17/D17) -> 2442.5492 | F17: {=+INDEX('[5]Budget original'!$A$2:$AO$500,MATCH($A17,'[5]Budget original'!$A$2:$A$500,0),MATCH(F$2,'[5]Budget original'!$A$2:$AO$2,0))} -> 4689.6945 | J17: =-SUMIFS([5]BV_Data_An_Cour!$O:$O,[5]BV_Data_An_Cour!$U:$U,$B17,[5]BV_Data_An_Cour!$V:$V,$C17,[5]BV_Data_An_Cour!$W:$W,J$2) -> 1 | K17: =IF(J17=0,0,L17/J17) -> 4279.05 | L17: =-SUMIFS([5]BV_Data_An_Cour!$O:$O,[5]BV_Data_An_Cour!$U:$U,$B17,[5]BV_Data_An_Cour!$V:$V,$C17,[5]BV_Data_An_Cour!$W:$W,L$2) -> 4279.05 | M17: =J17-D17 -> -0.92 | N17: =L17-F17 -> -410.64446 | O17: =-SUMIFS([5]BV_Data_An_Prec!$O:$O,[5]BV_Data_An_Prec!$U:$U,$B17,[5]BV_Data_An_Prec!$V:$V,$C17,[5]BV_Data_An_Prec!$W:$W,O$2) -> 2 | P17: =IF(O17=0,0,Q17/O17) -> 4190.8 | Q17: =-SUMIFS([5]BV_Data_An_Prec!$O:$O,[5]BV_Data_An_Prec!$U:$U,$B17,[5]BV_Data_An_Prec!$V:$V,$C17,[5]BV_Data_An_Prec!$W:$W,Q$2) -> 8381.6 | R17: =J17-O17 -> -1 | S17: =L17-Q17 -> -4102.55 | V17: =+L13+L15+L17-4000 -> 87267.39
A18: Véhicules neufs | B18: Véhicules neufs | V18: =+L31/V17 -> 0.37581129
A19: Véhicules neufsRachat bail | B19: Véhicules neufs | C19: Rachat bail | D19: {=+INDEX('[5]Budget original'!$A$2:$AO$500,MATCH($A19,'[5]Budget original'!$A$2:$A$500,0),MATCH(D$2,'[5]Budget original'!$A$2:$AO$2,0))} -> 0 | E19: =IF(D19=0,0,F19/D19) -> 0 | F19: {=+INDEX('[5]Budget original'!$A$2:$AO$500,MATCH($A19,'[5]Budget original'!$A$2:$A$500,0),MATCH(F$2,'[5]Budget original'!$A$2:$AO$2,0))} -> 9600 | L19: =-SUMIFS([5]BV_Data_An_Cour!$O:$O,[5]BV_Data_An_Cour!$U:$U,$B19,[5]BV_Data_An_Cour!$V:$V,$C19,[5]BV_Data_An_Cour!$W:$W,L$2) -> 9971 | N19: =L19-F19 -> 371 | Q19: =-SUMIFS([5]BV_Data_An_Prec!$O:$O,[5]BV_Data_An_Prec!$U:$U,$B19,[5]BV_Data_An_Prec!$V:$V,$C19,[5]BV_Data_An_Prec!$W:$W,Q$2) -> 13968.33 | R19: =O19-K19 -> 0 | S19: =L19-Q19 -> -3997.33
A20: Véhicules neufs | B20: Véhicules neufs
A21: Véhicules neufsRev. Finances | B21: Véhicules neufs | C21: Rev. Finances | D21: {=+INDEX('[5]Budget original'!$A$2:$AO$500,MATCH($A21,'[5]Budget original'!$A$2:$A$500,0),MATCH(D$2,'[5]Budget original'!$A$2:$AO$2,0))} -> 0 | E21: =IF(D21=0,0,F21/D21) -> 0 | F21: {=+INDEX('[5]Budget original'!$A$2:$AO$500,MATCH($A21,'[5]Budget original'!$A$2:$A$500,0),MATCH(F$2,'[5]Budget original'!$A$2:$AO$2,0))} -> 9053.3887 | K21: =IF(J13=0,0,L21/(J13+J15)) -> 247.8859 | L21: =-SUMIFS([5]BV_Data_An_Cour!$O:$O,[5]BV_Data_An_Cour!$U:$U,$B21,[5]BV_Data_An_Cour!$V:$V,$C21,[5]BV_Data_An_Cour!$W:$W,L$2) -> 9667.55 | N21: =L21-F21 -> 614.1613 | P21: =IF(O13=0,0,Q21/(O13+O15)) -> 208.71698 | Q21: =-SUMIFS([5]BV_Data_An_Prec!$O:$O,[5]BV_Data_An_Prec!$U:$U,$B21,[5]BV_Data_An_Prec!$V:$V,$C21,[5]BV_Data_An_Prec!$W:$W,Q$2) -> 11062 | R21: =O21-K21 -> -247.8859 | S21: =L21-Q21 -> -1394.45
A22: Véhicules neufsRev. Protections | B22: Véhicules neufs | C22: Rev. Protections | D22: {=+INDEX('[5]Budget original'!$A$2:$AO$500,MATCH($A22,'[5]Budget original'!$A$2:$A$500,0),MATCH(D$2,'[5]Budget original'!$A$2:$AO$2,0))} -> 0 | E22: =IF(D22=0,0,F22/D22) -> 0 | F22: {=+INDEX('[5]Budget original'!$A$2:$AO$500,MATCH($A22,'[5]Budget original'!$A$2:$A$500,0),MATCH(F$2,'[5]Budget original'!$A$2:$AO$2,0))} -> 49793.638 | K22: =IF(J13=0,0,L22/(J13+J15)) -> 1110.4236 | L22: =-SUMIFS([5]BV_Data_An_Cour!$O:$O,[5]BV_Data_An_Cour!$U:$U,$B22,[5]BV_Data_An_Cour!$V:$V,$C22,[5]BV_Data_An_Cour!$W:$W,L$2) -> 43306.52 | N22: =L22-F22 -> -6487.1178 | P22: =IF(O13=0,0,Q22/(O13+O15)) -> 1043.6472 | Q22: =-SUMIFS([5]BV_Data_An_Prec!$O:$O,[5]BV_Data_An_Prec!$U:$U,$B22,[5]BV_Data_An_Prec!$V:$V,$C22,[5]BV_Data_An_Prec!$W:$W,Q$2) -> 55313.3 | R22: =O22-K22 -> -1110.4236 | S22: =L22-Q22 -> -12006.78
A23: Véhicules neufsRev. Autres | B23: Véhicules neufs | C23: Rev. Autres | D23: {=+INDEX('[5]Budget original'!$A$2:$AO$500,MATCH($A23,'[5]Budget original'!$A$2:$A$500,0),MATCH(D$2,'[5]Budget original'!$A$2:$AO$2,0))} -> 0 | E23: =IF(D23=0,0,F23/D23) -> 0 | F23: {=+INDEX('[5]Budget original'!$A$2:$AO$500,MATCH($A23,'[5]Budget original'!$A$2:$A$500,0),MATCH(F$2,'[5]Budget original'!$A$2:$AO$2,0))} -> 1526.4434 | K23: =IF(J13=0,0,L23/(J13+J15)) -> 0 | L23: =-SUMIFS([5]BV_Data_An_Cour!$O:$O,[5]BV_Data_An_Cour!$U:$U,$B23,[5]BV_Data_An_Cour!$V:$V,$C23,[5]BV_Data_An_Cour!$W:$W,L$2) -> 0 | N23: =L23-F23 -> -1526.4434 | P23: =IF(O13=0,0,Q23/(O13+O15)) -> 26.998868 | Q23: =-SUMIFS([5]BV_Data_An_Prec!$O:$O,[5]BV_Data_An_Prec!$U:$U,$B23,[5]BV_Data_An_Prec!$V:$V,$C23,[5]BV_Data_An_Prec!$W:$W,Q$2) -> 1430.94 | R23: =O23-K23 -> 0 | S23: =L23-Q23 -> -1430.94
A24: Véhicules neufsTotal F&I | B24: Véhicules neufs | C24: Total F&I | D24: =+D15+D13 -> 52.635981 | E24: =IF(D24<=0,0,F24/D24) -> 1147 | F24: =F21+F22+F23 -> 60373.47 | J24: =+J15+J13 -> 39 | K24: =IF(J24<=0,0,L24/J24) -> 1358.3095 | L24: =L21+L22+L23 -> 52974.07 | M24: =J24-D24 -> -13.635981 | N24: =L24-F24 -> -7399.4 | O24: =+O15+O13 -> 53 | P24: =IF(O24<=0,0,Q24/O24) -> 1279.363 | Q24: =Q21+Q22+Q23 -> 67806.24 | S24: =L24-Q24 -> -14832.17
A25: Véhicules neufs | B25: Véhicules neufs | N25: =IF(N24=0,0,N24/F24) -> -0.12256046 | S25: =IF(Q24=0,0,(S24/Q24)) -> -0.21874344
A26: Véhicules neufs | B26: Véhicules neufs
A27: Véhicules neufsTotal Dépt. Neufs | B27: Véhicules neufs | C27: Total Dépt. Neufs | D27: =+D13+D15+D17 -> 54.555981 | E27: =IF(D27<=0,0,F27/D27) -> 3725.3286 | F27: =F13+F17+F24+F19+F15 -> 203238.95 | J27: =+J13+J15+J17 -> 40 | K27: =IF(J27<=0,0,L27/J27) -> 3855.3115 | L27: =L13+L17+L24+L19+L15 -> 154212.46 | M27: =J27-D27 -> -14.555981 | N27: =L27-F27 -> -49026.494 | O27: =+O13+O15+O17 -> 55 | P27: =IF(O27<=0,0,Q27/O27) -> 4674.3695 | Q27: =Q13+Q17+Q24+Q19+Q15 -> 257090.32 | R27: =J27-O27 -> -15 | S27: =L27-Q27 -> -102877.86
A28: Véhicules neufs | B28: Véhicules neufs | L28: =L27/F27 -> 0.75877413 | M28: =M27/D27 -> -0.26680816 | N28: =N27/F27 -> -0.24122587 | R28: =R27/O27 -> -0.27272727 | S28: =IF(Q27=0,0,S27/Q27) -> -0.40016232
A29: Véhicules neufs | B29: Véhicules neufs
A30: Véhicules neufsDEPENSES | B30: Véhicules neufs | C30: DEPENSES
A31: Véhicules neufsComm. vendeurs | B31: Véhicules neufs | C31: Comm. vendeurs | D31: =F31/(F15+F13+F17) -> 0.30450317 | E31: =F31/D$24 -> 770.95101 | F31: {=+INDEX('[5]Budget original'!$A$2:$AO$500,MATCH($A31,'[5]Budget original'!$A$2:$A$500,0),MATCH(F$2,'[5]Budget original'!$A$2:$AO$2,0))} -> 40579.763 | J31: =L31/(L15+L13+L17) -> 0.3593405 | K31: =IF(L31=0,0,L31/J$24) -> 840.92487 | L31: =SUMIFS([5]BV_Data_An_Cour!$O:$O,[5]BV_Data_An_Cour!$U:$U,$B31,[5]BV_Data_An_Cour!$V:$V,$C31,[5]BV_Data_An_Cour!$W:$W,L$2) -> 32796.07 | N31: =L31-F31 -> -7783.6926 | P31: =IF(Q31=0,0,Q31/O$24) -> 1067.6589 | Q31: =SUMIFS([5]BV_Data_An_Prec!$O:$O,[5]BV_Data_An_Prec!$U:$U,$B31,[5]BV_Data_An_Prec!$V:$V,$C31,[5]BV_Data_An_Prec!$W:$W,Q$2) -> 56585.92 | S31: =L31-Q31 -> -23789.85
A32: Véhicules neufsComm. F&I | B32: Véhicules neufs | C32: Comm. F&I | D32: =F32/F24 -> 0.3 | E32: =F32/D$24 -> 344.1 | F32: {=+INDEX('[5]Budget original'!$A$2:$AO$500,MATCH($A32,'[5]Budget original'!$A$2:$A$500,0),MATCH(F$2,'[5]Budget original'!$A$2:$AO$2,0))} -> 18112.041 | J32: =L32/L24 -> 0.30073846 | K32: =IF(L32=0,0,L32/J$24) -> 408.4959 | L32: =SUMIFS([5]BV_Data_An_Cour!$O:$O,[5]BV_Data_An_Cour!$U:$U,$B32,[5]BV_Data_An_Cour!$V:$V,$C32,[5]BV_Data_An_Cour!$W:$W,L$2) -> 15931.34 | N32: =L32-F32 -> -2180.701 | P32: =IF(Q32=0,0,Q32/O$24) -> 423.97528 | Q32: =SUMIFS([5]BV_Data_An_Prec!$O:$O,[5]BV_Data_An_Prec!$U:$U,$B32,[5]BV_Data_An_Prec!$V:$V,$C32,[5]BV_Data_An_Prec!$W:$W,Q$2) -> 22470.69 | S32: =L32-Q32 -> -6539.35 | U32: =(L32+L112)/(L104+L24+L19) -> 0.26707524 | V32: <<- F&A total Neuf Usagé Rachat | X32: =L24*U32 -> 14148.063 | Y32: =+L32-X32 -> 1783.2773
A33: Véhicules neufsFrais de livraison | B33: Véhicules neufs | C33: Frais de livraison | E33: =F33/D$24 -> 113.25898 | F33: {=+INDEX('[5]Budget original'!$A$2:$AO$500,MATCH($A33,'[5]Budget original'!$A$2:$A$500,0),MATCH(F$2,'[5]Budget original'!$A$2:$AO$2,0))} -> 5961.4973 | K33: =IF(L33=0,0,L33/J$24) -> 168.41974 | L33: =SUMIFS([5]BV_Data_An_Cour!$O:$O,[5]BV_Data_An_Cour!$U:$U,$B33,[5]BV_Data_An_Cour!$V:$V,$C33,[5]BV_Data_An_Cour!$W:$W,L$2) -> 6568.37 | N33: =L33-F33 -> 606.87268 | P33: =IF(Q33=0,0,Q33/O$24) -> 145.86774 | Q33: =SUMIFS([5]BV_Data_An_Prec!$O:$O,[5]BV_Data_An_Prec!$U:$U,$B33,[5]BV_Data_An_Prec!$V:$V,$C33,[5]BV_Data_An_Prec!$W:$W,Q$2) -> 7730.99 | S33: =L33-Q33 -> -1162.62
A34: Véhicules neufsService gratuit 1 | B34: Véhicules neufs | C34: Service gratuit 1 | E34: =F34/D$24 -> 5.1177856 | F34: {=+INDEX('[5]Budget original'!$A$2:$AO$500,MATCH($A34,'[5]Budget original'!$A$2:$A$500,0),MATCH(F$2,'[5]Budget original'!$A$2:$AO$2,0))} -> 269.37967 | K34: =IF(L34=0,0,L34/J$24) -> 1.025641 | L34: =SUMIFS([5]BV_Data_An_Cour!$O:$O,[5]BV_Data_An_Cour!$U:$U,$B34,[5]BV_Data_An_Cour!$V:$V,$C34,[5]BV_Data_An_Cour!$W:$W,L$2) -> 40 | N34: =L34-F34 -> -229.37967 | P34: =IF(Q34=0,0,Q34/O$24) -> 3.5922642 | Q34: =SUMIFS([5]BV_Data_An_Prec!$O:$O,[5]BV_Data_An_Prec!$U:$U,$B34,[5]BV_Data_An_Prec!$V:$V,$C34,[5]BV_Data_An_Prec!$W:$W,Q$2) -> 190.39 | S34: =L34-Q34 -> -150.39
A35: Véhicules neufsEntretien stock | B35: Véhicules neufs | C35: Entretien stock | E35: =F35/D$24 -> 105.01044 | F35: {=+INDEX('[5]Budget original'!$A$2:$AO$500,MATCH($A35,'[5]Budget original'!$A$2:$A$500,0),MATCH(F$2,'[5]Budget original'!$A$2:$AO$2,0))} -> 5527.3277 | K35: =IF(L35=0,0,L35/J$24) -> 118.07769 | L35: =SUMIFS([5]BV_Data_An_Cour!$O:$O,[5]BV_Data_An_Cour!$U:$U,$B35,[5]BV_Data_An_Cour!$V:$V,$C35,[5]BV_Data_An_Cour!$W:$W,L$2) -> 4605.03 | N35: =L35-F35 -> -922.29768 | P35: =IF(Q35=0,0,Q35/O$24) -> 176.23962 | Q35: =SUMIFS([5]BV_Data_An_Prec!$O:$O,[5]BV_Data_An_Prec!$U:$U,$B35,[5]BV_Data_An_Prec!$V:$V,$C35,[5]BV_Data_An_Prec!$W:$W,Q$2) -> 9340.7 | S35: =L35-Q35 -> -4735.67
A36: Véhicules neufsPublicité 1 | B36: Véhicules neufs | C36: Publicité 1 | E36: =F36/D$24 -> 300.75552 | F36: {=+INDEX('[5]Budget original'!$A$2:$AO$500,MATCH($A36,'[5]Budget original'!$A$2:$A$500,0),MATCH(F$2,'[5]Budget original'!$A$2:$AO$2,0))} -> 15830.562 | K36: =IF(L36=0,0,L36/J$24) -> 154.58692 | L36: =SUMIFS([5]BV_Data_An_Cour!$O:$O,[5]BV_Data_An_Cour!$U:$U,$B36,[5]BV_Data_An_Cour!$V:$V,$C36,[5]BV_Data_An_Cour!$W:$W,L$2) -> 6028.89 | N36: =L36-F36 -> -9801.6719 | P36: =IF(Q36=0,0,Q36/O$24) -> 185.94774 | Q36: =SUMIFS([5]BV_Data_An_Prec!$O:$O,[5]BV_Data_An_Prec!$U:$U,$B36,[5]BV_Data_An_Prec!$V:$V,$C36,[5]BV_Data_An_Prec!$W:$W,Q$2) -> 9855.23 | S36: =L36-Q36 -> -3826.34
A37: Véhicules neufsIntérêt de gros | B37: Véhicules neufs | C37: Intérêt de gros | E37: =F37/D$24 -> 50.687592 | F37: {=+INDEX('[5]Budget original'!$A$2:$AO$500,MATCH($A37,'[5]Budget original'!$A$2:$A$500,0),MATCH(F$2,'[5]Budget original'!$A$2:$AO$2,0))} -> 2667.9911 | K37: =IF(L37=0,0,L37/J$24) -> 90.482564 | L37: =SUMIFS([5]BV_Data_An_Cour!$O:$O,[5]BV_Data_An_Cour!$U:$U,$B37,[5]BV_Data_An_Cour!$V:$V,$C37,[5]BV_Data_An_Cour!$W:$W,L$2) -> 3528.82 | N37: =L37-F37 -> 860.82887 | P37: =IF(Q37=0,0,Q37/O$24) -> 21.345283 | Q37: =SUMIFS([5]BV_Data_An_Prec!$O:$O,[5]BV_Data_An_Prec!$U:$U,$B37,[5]BV_Data_An_Prec!$V:$V,$C37,[5]BV_Data_An_Prec!$W:$W,Q$2) -> 1131.3 | S37: =L37-Q37 -> 2397.52
A38: Véhicules neufs[...] | B38: Véhicules neufs | C38: [...] | E38: =F38/D$24 -> 0 | F38: {=+INDEX('[5]Budget original'!$A$2:$AO$500,MATCH($A38,'[5]Budget original'!$A$2:$A$500,0),MATCH(F$2,'[5]Budget original'!$A$2:$AO$2,0))} -> 0 | K38: =IF(L38=0,0,L38/J$24) -> 0 | L38: =SUMIFS([5]BV_Data_An_Cour!$O:$O,[5]BV_Data_An_Cour!$U:$U,$B38,[5]BV_Data_An_Cour!$V:$V,$C38,[5]BV_Data_An_Cour!$W:$W,L$2) -> 0 | N38: =L38-F38 -> 0 | P38: =IF(Q38=0,0,Q38/O$24) -> 0 | Q38: =SUMIFS([5]BV_Data_An_Prec!$O:$O,[5]BV_Data_An_Prec!$U:$U,$B38,[5]BV_Data_An_Prec!$V:$V,$C38,[5]BV_Data_An_Prec!$W:$W,Q$2) -> 0 | S38: =L38-Q38 -> 0
A39: Véhicules neufs[...] | B39: Véhicules neufs | C39: [...] | E39: =F39/D$24 -> 0 | F39: {=+INDEX('[5]Budget original'!$A$2:$AO$500,MATCH($A39,'[5]Budget original'!$A$2:$A$500,0),MATCH(F$2,'[5]Budget original'!$A$2:$AO$2,0))} -> 0 | K39: =IF(L39=0,0,L39/J$24) -> 0 | L39: =SUMIFS([5]BV_Data_An_Cour!$O:$O,[5]BV_Data_An_Cour!$U:$U,$B39,[5]BV_Data_An_Cour!$V:$V,$C39,[5]BV_Data_An_Cour!$W:$W,L$2) -> 0 | N39: =L39-F39 -> 0 | P39: =IF(Q39=0,0,Q39/O$24) -> 0 | Q39: =SUMIFS([5]BV_Data_An_Prec!$O:$O,[5]BV_Data_An_Prec!$U:$U,$B39,[5]BV_Data_An_Prec!$V:$V,$C39,[5]BV_Data_An_Prec!$W:$W,Q$2) -> 0 | S39: =L39-Q39 -> 0
A40: Véhicules neufs[...] | B40: Véhicules neufs | C40: [...] | E40: =F40/D$24 -> 0 | F40: {=+INDEX('[5]Budget original'!$A$2:$AO$500,MATCH($A40,'[5]Budget original'!$A$2:$A$500,0),MATCH(F$2,'[5]Budget original'!$A$2:$AO$2,0))} -> 0 | K40: =IF(L40=0,0,L40/J$24) -> 0 | L40: =SUMIFS([5]BV_Data_An_Cour!$O:$O,[5]BV_Data_An_Cour!$U:$U,$B40,[5]BV_Data_An_Cour!$V:$V,$C40,[5]BV_Data_An_Cour!$W:$W,L$2) -> 0 | N40: =L40-F40 -> 0 | P40: =IF(Q40=0,0,Q40/O$24) -> 0 | Q40: =SUMIFS([5]BV_Data_An_Prec!$O:$O,[5]BV_Data_An_Prec!$U:$U,$B40,[5]BV_Data_An_Prec!$V:$V,$C40,[5]BV_Data_An_Prec!$W:$W,Q$2) -> 0 | S40: =L40-Q40 -> 0
A41: Véhicules neufsTOTAL VARIABLES | B41: Véhicules neufs | C41: TOTAL VARIABLES | D41: % brut | E41: =F41/F$27 -> 0.43765508 | F41: =SUM(F31:F40) -> 88948.561 | J41: % brut | K41: =L41/L$27 -> 0.45066735 | L41: =SUM(L31:L40) -> 69498.52 | N41: =L41-F41 -> -19450.041 | O41: % brut | P41: =Q41/Q$27 -> 0.41738335 | Q41: =SUM(Q31:Q40) -> 107305.22 | S41: =L41-Q41 -> -37806.7
A42: Véhicules neufsSalaires cadres | B42: Véhicules neufs | C42: Salaires cadres | F42: {=+INDEX('[5]Budget original'!$A$2:$AO$500,MATCH($A42,'[5]Budget original'!$A$2:$A$500,0),MATCH(F$2,'[5]Budget original'!$A$2:$AO$2,0))} -> 17292.497 | L42: =SUMIFS([5]BV_Data_An_Cour!$O:$O,[5]BV_Data_An_Cour!$U:$U,$B42,[5]BV_Data_An_Cour!$V:$V,$C42,[5]BV_Data_An_Cour!$W:$W,L$2) -> 17842.1 | N42: =L42-F42 -> 549.60345 | Q42: =SUMIFS([5]BV_Data_An_Prec!$O:$O,[5]BV_Data_An_Prec!$U:$U,$B42,[5]BV_Data_An_Prec!$V:$V,$C42,[5]BV_Data_An_Prec!$W:$W,Q$2) -> 15898.03 | S42: =L42-Q42 -> 1944.07
A43: Véhicules neufsSalaires commis | B43: Véhicules neufs | C43: Salaires commis | F43: {=+INDEX('[5]Budget original'!$A$2:$AO$500,MATCH($A43,'[5]Budget original'!$A$2:$A$500,0),MATCH(F$2,'[5]Budget original'!$A$2:$AO$2,0))} -> 10224.637 | L43: =SUMIFS([5]BV_Data_An_Cour!$O:$O,[5]BV_Data_An_Cour!$U:$U,$B43,[5]BV_Data_An_Cour!$V:$V,$C43,[5]BV_Data_An_Cour!$W:$W,L$2) -> 9643.58 | N43: =L43-F43 -> -581.05724 | Q43: =SUMIFS([5]BV_Data_An_Prec!$O:$O,[5]BV_Data_An_Prec!$U:$U,$B43,[5]BV_Data_An_Prec!$V:$V,$C43,[5]BV_Data_An_Prec!$W:$W,Q$2) -> 7132.73 | S43: =L43-Q43 -> 2510.85
A44: Véhicules neufsSalaires autres | B44: Véhicules neufs | C44: Salaires autres | F44: {=+INDEX('[5]Budget original'!$A$2:$AO$500,MATCH($A44,'[5]Budget original'!$A$2:$A$500,0),MATCH(F$2,'[5]Budget original'!$A$2:$AO$2,0))} -> 8208.9839 | L44: =SUMIFS([5]BV_Data_An_Cour!$O:$O,[5]BV_Data_An_Cour!$U:$U,$B44,[5]BV_Data_An_Cour!$V:$V,$C44,[5]BV_Data_An_Cour!$W:$W,L$2) -> 12343.13 | N44: =L44-F44 -> 4134.1461 | Q44: =SUMIFS([5]BV_Data_An_Prec!$O:$O,[5]BV_Data_An_Prec!$U:$U,$B44,[5]BV_Data_An_Prec!$V:$V,$C44,[5]BV_Data_An_Prec!$W:$W,Q$2) -> 3509.01 | S44: =L44-Q44 -> 8834.12
A45: Véhicules neufsSalaires spécialistes | B45: Véhicules neufs | C45: Salaires spécialistes | F45: {=+INDEX('[5]Budget original'!$A$2:$AO$500,MATCH($A45,'[5]Budget original'!$A$2:$A$500,0),MATCH(F$2,'[5]Budget original'!$A$2:$AO$2,0))} -> 0 | L45: =SUMIFS([5]BV_Data_An_Cour!$O:$O,[5]BV_Data_An_Cour!$U:$U,$B45,[5]BV_Data_An_Cour!$V:$V,$C45,[5]BV_Data_An_Cour!$W:$W,L$2) -> 0 | N45: =L45-F45 -> 0 | Q45: =SUMIFS([5]BV_Data_An_Prec!$O:$O,[5]BV_Data_An_Prec!$U:$U,$B45,[5]BV_Data_An_Prec!$V:$V,$C45,[5]BV_Data_An_Prec!$W:$W,Q$2) -> 0 | S45: =L45-Q45 -> 0
A46: Véhicules neufs[...] | B46: Véhicules neufs | C46: [...] | F46: {=+INDEX('[5]Budget original'!$A$2:$AO$500,MATCH($A46,'[5]Budget original'!$A$2:$A$500,0),MATCH(F$2,'[5]Budget original'!$A$2:$AO$2,0))} -> 0 | L46: =SUMIFS([5]BV_Data_An_Cour!$O:$O,[5]BV_Data_An_Cour!$U:$U,$B46,[5]BV_Data_An_Cour!$V:$V,$C46,[5]BV_Data_An_Cour!$W:$W,L$2) -> 0 | N46: =L46-F46 -> 0 | Q46: =SUMIFS([5]BV_Data_An_Prec!$O:$O,[5]BV_Data_An_Prec!$U:$U,$B46,[5]BV_Data_An_Prec!$V:$V,$C46,[5]BV_Data_An_Prec!$W:$W,Q$2) -> 0 | S46: =L46-Q46 -> 0
A47: Véhicules neufs[...] | B47: Véhicules neufs | C47: [...] | F47: {=+INDEX('[5]Budget original'!$A$2:$AO$500,MATCH($A47,'[5]Budget original'!$A$2:$A$500,0),MATCH(F$2,'[5]Budget original'!$A$2:$AO$2,0))} -> 0 | L47: =SUMIFS([5]BV_Data_An_Cour!$O:$O,[5]BV_Data_An_Cour!$U:$U,$B47,[5]BV_Data_An_Cour!$V:$V,$C47,[5]BV_Data_An_Cour!$W:$W,L$2) -> 0 | N47: =L47-F47 -> 0 | Q47: =SUMIFS([5]BV_Data_An_Prec!$O:$O,[5]BV_Data_An_Prec!$U:$U,$B47,[5]BV_Data_An_Prec!$V:$V,$C47,[5]BV_Data_An_Prec!$W:$W,Q$2) -> 0 | S47: =L47-Q47 -> 0
A48: Véhicules neufs[...] | B48: Véhicules neufs | C48: [...] | F48: {=+INDEX('[5]Budget original'!$A$2:$AO$500,MATCH($A48,'[5]Budget original'!$A$2:$A$500,0),MATCH(F$2,'[5]Budget original'!$A$2:$AO$2,0))} -> 0 | L48: =SUMIFS([5]BV_Data_An_Cour!$O:$O,[5]BV_Data_An_Cour!$U:$U,$B48,[5]BV_Data_An_Cour!$V:$V,$C48,[5]BV_Data_An_Cour!$W:$W,L$2) -> 0 | N48: =L48-F48 -> 0 | Q48: =SUMIFS([5]BV_Data_An_Prec!$O:$O,[5]BV_Data_An_Prec!$U:$U,$B48,[5]BV_Data_An_Prec!$V:$V,$C48,[5]BV_Data_An_Prec!$W:$W,Q$2) -> 0 | S48: =L48-Q48 -> 0
A49: Véhicules neufsSalaires en absences | B49: Véhicules neufs | C49: Salaires en absences | F49: {=+INDEX('[5]Budget original'!$A$2:$AO$500,MATCH($A49,'[5]Budget original'!$A$2:$A$500,0),MATCH(F$2,'[5]Budget original'!$A$2:$AO$2,0))} -> 11454.455 | L49: =SUMIFS([5]BV_Data_An_Cour!$O:$O,[5]BV_Data_An_Cour!$U:$U,$B49,[5]BV_Data_An_Cour!$V:$V,$C49,[5]BV_Data_An_Cour!$W:$W,L$2) -> 10139.23 | N49: =L49-F49 -> -1315.2249 | Q49: =SUMIFS([5]BV_Data_An_Prec!$O:$O,[5]BV_Data_An_Prec!$U:$U,$B49,[5]BV_Data_An_Prec!$V:$V,$C49,[5]BV_Data_An_Prec!$W:$W,Q$2) -> 20543.52 | S49: =L49-Q49 -> -10404.29
A50: Véhicules neufsDéduction à la source | B50: Véhicules neufs | C50: Déduction à la source | F50: {=+INDEX('[5]Budget original'!$A$2:$AO$500,MATCH($A50,'[5]Budget original'!$A$2:$A$500,0),MATCH(F$2,'[5]Budget original'!$A$2:$AO$2,0))} -> 11386.856 | L50: =SUMIFS([5]BV_Data_An_Cour!$O:$O,[5]BV_Data_An_Cour!$U:$U,$B50,[5]BV_Data_An_Cour!$V:$V,$C50,[5]BV_Data_An_Cour!$W:$W,L$2) -> 14378.55 | N50: =L50-F50 -> 2991.6941 | Q50: =SUMIFS([5]BV_Data_An_Prec!$O:$O,[5]BV_Data_An_Prec!$U:$U,$B50,[5]BV_Data_An_Prec!$V:$V,$C50,[5]BV_Data_An_Prec!$W:$W,Q$2) -> 17936.94 | S50: =L50-Q50 -> -3558.39
A51: Véhicules neufsBénéfices marginaux | B51: Véhicules neufs | C51: Bénéfices marginaux | F51: {=+INDEX('[5]Budget original'!$A$2:$AO$500,MATCH($A51,'[5]Budget original'!$A$2:$A$500,0),MATCH(F$2,'[5]Budget original'!$A$2:$AO$2,0))} -> 7973.7373 | L51: =SUMIFS([5]BV_Data_An_Cour!$O:$O,[5]BV_Data_An_Cour!$U:$U,$B51,[5]BV_Data_An_Cour!$V:$V,$C51,[5]BV_Data_An_Cour!$W:$W,L$2) -> 7088.75 | N51: =L51-F51 -> -884.98733 | Q51: =SUMIFS([5]BV_Data_An_Prec!$O:$O,[5]BV_Data_An_Prec!$U:$U,$B51,[5]BV_Data_An_Prec!$V:$V,$C51,[5]BV_Data_An_Prec!$W:$W,Q$2) -> 7345.74 | S51: =L51-Q51 -> -256.99
A52: Véhicules neufsCsst | B52: Véhicules neufs | C52: Csst | F52: {=+INDEX('[5]Budget original'!$A$2:$AO$500,MATCH($A52,'[5]Budget original'!$A$2:$A$500,0),MATCH(F$2,'[5]Budget original'!$A$2:$AO$2,0))} -> 3809.2842 | L52: =SUMIFS([5]BV_Data_An_Cour!$O:$O,[5]BV_Data_An_Cour!$U:$U,$B52,[5]BV_Data_An_Cour!$V:$V,$C52,[5]BV_Data_An_Cour!$W:$W,L$2) -> 2311.3 | N52: =L52-F52 -> -1497.9842 | Q52: =SUMIFS([5]BV_Data_An_Prec!$O:$O,[5]BV_Data_An_Prec!$U:$U,$B52,[5]BV_Data_An_Prec!$V:$V,$C52,[5]BV_Data_An_Prec!$W:$W,Q$2) -> 5097.38 | S52: =L52-Q52 -> -2786.08
A53: Véhicules neufs[...] | B53: Véhicules neufs | C53: [...] | F53: {=+INDEX('[5]Budget original'!$A$2:$AO$500,MATCH($A53,'[5]Budget original'!$A$2:$A$500,0),MATCH(F$2,'[5]Budget original'!$A$2:$AO$2,0))} -> 0 | L53: =SUMIFS([5]BV_Data_An_Cour!$O:$O,[5]BV_Data_An_Cour!$U:$U,$B53,[5]BV_Data_An_Cour!$V:$V,$C53,[5]BV_Data_An_Cour!$W:$W,L$2) -> 0 | N53: =L53-F53 -> 0 | Q53: =SUMIFS([5]BV_Data_An_Prec!$O:$O,[5]BV_Data_An_Prec!$U:$U,$B53,[5]BV_Data_An_Prec!$V:$V,$C53,[5]BV_Data_An_Prec!$W:$W,Q$2) -> 0 | S53: =L53-Q53 -> 0
A54: Véhicules neufsTOTAL PERSONNEL | B54: Véhicules neufs | C54: TOTAL PERSONNEL | D54: % brut | E54: =F54/F$27 -> 0.34614649 | F54: =+SUM(F42:F53) -> 70350.45 | J54: % brut | K54: =L54/L$27 -> 0.47821454 | L54: =+SUM(L42:L53) -> 73746.64 | N54: =+SUM(N42:N53) -> 3396.1901 | O54: % brut | P54: =Q54/Q$27 -> 0.30130792 | Q54: =+SUM(Q42:Q53) -> 77463.35 | S54: =+SUM(S42:S53) -> -3716.71
A55: Véhicules neufsPublicité 2 | B55: Véhicules neufs | C55: Publicité 2 | F55: {=+INDEX('[5]Budget original'!$A$2:$AO$500,MATCH($A55,'[5]Budget original'!$A$2:$A$500,0),MATCH(F$2,'[5]Budget original'!$A$2:$AO$2,0))} -> 0 | L55: =SUMIFS([5]BV_Data_An_Cour!$O:$O,[5]BV_Data_An_Cour!$U:$U,$B55,[5]BV_Data_An_Cour!$V:$V,$C55,[5]BV_Data_An_Cour!$W:$W,L$2) -> 0 | N55: =L55-F55 -> 0 | Q55: =SUMIFS([5]BV_Data_An_Prec!$O:$O,[5]BV_Data_An_Prec!$U:$U,$B55,[5]BV_Data_An_Prec!$V:$V,$C55,[5]BV_Data_An_Prec!$W:$W,Q$2) -> 0 | S55: =L55-Q55 -> 0
A56: Véhicules neufsService gratuit 2 | B56: Véhicules neufs | C56: Service gratuit 2 | F56: {=+INDEX('[5]Budget original'!$A$2:$AO$500,MATCH($A56,'[5]Budget original'!$A$2:$A$500,0),MATCH(F$2,'[5]Budget original'!$A$2:$AO$2,0))} -> 0 | L56: =SUMIFS([5]BV_Data_An_Cour!$O:$O,[5]BV_Data_An_Cour!$U:$U,$B56,[5]BV_Data_An_Cour!$V:$V,$C56,[5]BV_Data_An_Cour!$W:$W,L$2) -> 0 | N56: =L56-F56 -> 0 | Q56: =SUMIFS([5]BV_Data_An_Prec!$O:$O,[5]BV_Data_An_Prec!$U:$U,$B56,[5]BV_Data_An_Prec!$V:$V,$C56,[5]BV_Data_An_Prec!$W:$W,Q$2) -> 0 | S56: =L56-Q56 -> 0
A57: Véhicules neufsFrais véhicules de cie | B57: Véhicules neufs | C57: Frais véhicules de cie | F57: {=+INDEX('[5]Budget original'!$A$2:$AO$500,MATCH($A57,'[5]Budget original'!$A$2:$A$500,0),MATCH(F$2,'[5]Budget original'!$A$2:$AO$2,0))} -> 7945.8333 | L57: =SUMIFS([5]BV_Data_An_Cour!$O:$O,[5]BV_Data_An_Cour!$U:$U,$B57,[5]BV_Data_An_Cour!$V:$V,$C57,[5]BV_Data_An_Cour!$W:$W,L$2) -> 7279.84 | N57: =L57-F57 -> -665.99333 | Q57: =SUMIFS([5]BV_Data_An_Prec!$O:$O,[5]BV_Data_An_Prec!$U:$U,$B57,[5]BV_Data_An_Prec!$V:$V,$C57,[5]BV_Data_An_Prec!$W:$W,Q$2) -> 6354.05 | S57: =L57-Q57 -> 925.79
A58: Véhicules neufsInformatique | B58: Véhicules neufs | C58: Informatique | F58: {=+INDEX('[5]Budget original'!$A$2:$AO$500,MATCH($A58,'[5]Budget original'!$A$2:$A$500,0),MATCH(F$2,'[5]Budget original'!$A$2:$AO$2,0))} -> 6260.8664 | L58: =SUMIFS([5]BV_Data_An_Cour!$O:$O,[5]BV_Data_An_Cour!$U:$U,$B58,[5]BV_Data_An_Cour!$V:$V,$C58,[5]BV_Data_An_Cour!$W:$W,L$2) -> 7196.92 | N58: =L58-F58 -> 936.0536 | Q58: =SUMIFS([5]BV_Data_An_Prec!$O:$O,[5]BV_Data_An_Prec!$U:$U,$B58,[5]BV_Data_An_Prec!$V:$V,$C58,[5]BV_Data_An_Prec!$W:$W,Q$2) -> 7289.36 | S58: =L58-Q58 -> -92.44
A59: Véhicules neufsFrais de déplacement | B59: Véhicules neufs | C59: Frais de déplacement | F59: {=+INDEX('[5]Budget original'!$A$2:$AO$500,MATCH($A59,'[5]Budget original'!$A$2:$A$500,0),MATCH(F$2,'[5]Budget original'!$A$2:$AO$2,0))} -> 1000.088 | L59: =SUMIFS([5]BV_Data_An_Cour!$O:$O,[5]BV_Data_An_Cour!$U:$U,$B59,[5]BV_Data_An_Cour!$V:$V,$C59,[5]BV_Data_An_Cour!$W:$W,L$2) -> 818.1 | N59: =L59-F59 -> -181.98804 | Q59: =SUMIFS([5]BV_Data_An_Prec!$O:$O,[5]BV_Data_An_Prec!$U:$U,$B59,[5]BV_Data_An_Prec!$V:$V,$C59,[5]BV_Data_An_Prec!$W:$W,Q$2) -> 966.86 | S59: =L59-Q59 -> -148.76
A60: Véhicules neufsServices extérieurs | B60: Véhicules neufs | C60: Services extérieurs | F60: {=+INDEX('[5]Budget original'!$A$2:$AO$500,MATCH($A60,'[5]Budget original'!$A$2:$A$500,0),MATCH(F$2,'[5]Budget original'!$A$2:$AO$2,0))} -> 6796.8453 | L60: =SUMIFS([5]BV_Data_An_Cour!$O:$O,[5]BV_Data_An_Cour!$U:$U,$B60,[5]BV_Data_An_Cour!$V:$V,$C60,[5]BV_Data_An_Cour!$W:$W,L$2) -> 5967.65 | N60: =L60-F60 -> -829.19533 | Q60: =SUMIFS([5]BV_Data_An_Prec!$O:$O,[5]BV_Data_An_Prec!$U:$U,$B60,[5]BV_Data_An_Prec!$V:$V,$C60,[5]BV_Data_An_Prec!$W:$W,Q$2) -> 6513.05 | S60: =L60-Q60 -> -545.4
A61: Véhicules neufsFournitures autres | B61: Véhicules neufs | C61: Fournitures autres | F61: {=+INDEX('[5]Budget original'!$A$2:$AO$500,MATCH($A61,'[5]Budget original'!$A$2:$A$500,0),MATCH(F$2,'[5]Budget original'!$A$2:$AO$2,0))} -> 117.13646 | L61: =SUMIFS([5]BV_Data_An_Cour!$O:$O,[5]BV_Data_An_Cour!$U:$U,$B61,[5]BV_Data_An_Cour!$V:$V,$C61,[5]BV_Data_An_Cour!$W:$W,L$2) -> 0 | N61: =L61-F61 -> -117.13646 | Q61: =SUMIFS([5]BV_Data_An_Prec!$O:$O,[5]BV_Data_An_Prec!$U:$U,$B61,[5]BV_Data_An_Prec!$V:$V,$C61,[5]BV_Data_An_Prec!$W:$W,Q$2) -> 0 | S61: =L61-Q61 -> 0
A62: Véhicules neufsUniformes | B62: Véhicules neufs | C62: Uniformes | F62: {=+INDEX('[5]Budget original'!$A$2:$AO$500,MATCH($A62,'[5]Budget original'!$A$2:$A$500,0),MATCH(F$2,'[5]Budget original'!$A$2:$AO$2,0))} -> 60.487931 | L62: =SUMIFS([5]BV_Data_An_Cour!$O:$O,[5]BV_Data_An_Cour!$U:$U,$B62,[5]BV_Data_An_Cour!$V:$V,$C62,[5]BV_Data_An_Cour!$W:$W,L$2) -> 0 | N62: =L62-F62 -> -60.487931 | Q62: =SUMIFS([5]BV_Data_An_Prec!$O:$O,[5]BV_Data_An_Prec!$U:$U,$B62,[5]BV_Data_An_Prec!$V:$V,$C62,[5]BV_Data_An_Prec!$W:$W,Q$2) -> 0 | S62: =L62-Q62 -> 0
A63: Véhicules neufsPapeterie | B63: Véhicules neufs | C63: Papeterie | F63: {=+INDEX('[5]Budget original'!$A$2:$AO$500,MATCH($A63,'[5]Budget original'!$A$2:$A$500,0),MATCH(F$2,'[5]Budget original'!$A$2:$AO$2,0))} -> 763.45104 | L63: =SUMIFS([5]BV_Data_An_Cour!$O:$O,[5]BV_Data_An_Cour!$U:$U,$B63,[5]BV_Data_An_Cour!$V:$V,$C63,[5]BV_Data_An_Cour!$W:$W,L$2) -> 479.83 | N63: =L63-F63 -> -283.62104 | Q63: =SUMIFS([5]BV_Data_An_Prec!$O:$O,[5]BV_Data_An_Prec!$U:$U,$B63,[5]BV_Data_An_Prec!$V:$V,$C63,[5]BV_Data_An_Prec!$W:$W,Q$2) -> 984.46 | S63: =L63-Q63 -> -504.63
A64: Véhicules neufsTéléphone | B64: Véhicules neufs | C64: Téléphone | F64: {=+INDEX('[5]Budget original'!$A$2:$AO$500,MATCH($A64,'[5]Budget original'!$A$2:$A$500,0),MATCH(F$2,'[5]Budget original'!$A$2:$AO$2,0))} -> 258.72025 | L64: =SUMIFS([5]BV_Data_An_Cour!$O:$O,[5]BV_Data_An_Cour!$U:$U,$B64,[5]BV_Data_An_Cour!$V:$V,$C64,[5]BV_Data_An_Cour!$W:$W,L$2) -> 233.9 | N64: =L64-F64 -> -24.82025 | Q64: =SUMIFS([5]BV_Data_An_Prec!$O:$O,[5]BV_Data_An_Prec!$U:$U,$B64,[5]BV_Data_An_Prec!$V:$V,$C64,[5]BV_Data_An_Prec!$W:$W,Q$2) -> 261.12 | S64: =L64-Q64 -> -27.22
A65: Véhicules neufsFrais postaux | B65: Véhicules neufs | C65: Frais postaux | F65: {=+INDEX('[5]Budget original'!$A$2:$AO$500,MATCH($A65,'[5]Budget original'!$A$2:$A$500,0),MATCH(F$2,'[5]Budget original'!$A$2:$AO$2,0))} -> 123.74429 | L65: =SUMIFS([5]BV_Data_An_Cour!$O:$O,[5]BV_Data_An_Cour!$U:$U,$B65,[5]BV_Data_An_Cour!$V:$V,$C65,[5]BV_Data_An_Cour!$W:$W,L$2) -> 130.12 | N65: =L65-F65 -> 6.3757062 | Q65: =SUMIFS([5]BV_Data_An_Prec!$O:$O,[5]BV_Data_An_Prec!$U:$U,$B65,[5]BV_Data_An_Prec!$V:$V,$C65,[5]BV_Data_An_Prec!$W:$W,Q$2) -> 200.99 | S65: =L65-Q65 -> -70.87
A66: Véhicules neufsDivers | B66: Véhicules neufs | C66: Divers | F66: {=+INDEX('[5]Budget original'!$A$2:$AO$500,MATCH($A66,'[5]Budget original'!$A$2:$A$500,0),MATCH(F$2,'[5]Budget original'!$A$2:$AO$2,0))} -> 470.18236 | L66: =SUMIFS([5]BV_Data_An_Cour!$O:$O,[5]BV_Data_An_Cour!$U:$U,$B66,[5]BV_Data_An_Cour!$V:$V,$C66,[5]BV_Data_An_Cour!$W:$W,L$2) -> 106.21 | N66: =L66-F66 -> -363.97236 | Q66: =SUMIFS([5]BV_Data_An_Prec!$O:$O,[5]BV_Data_An_Prec!$U:$U,$B66,[5]BV_Data_An_Prec!$V:$V,$C66,[5]BV_Data_An_Prec!$W:$W,Q$2) -> 140.21 | S66: =L66-Q66 -> -34
A67: Véhicules neufsFormation | B67: Véhicules neufs | C67: Formation | F67: {=+INDEX('[5]Budget original'!$A$2:$AO$500,MATCH($A67,'[5]Budget original'!$A$2:$A$500,0),MATCH(F$2,'[5]Budget original'!$A$2:$AO$2,0))} -> 612.7403 | L67: =SUMIFS([5]BV_Data_An_Cour!$O:$O,[5]BV_Data_An_Cour!$U:$U,$B67,[5]BV_Data_An_Cour!$V:$V,$C67,[5]BV_Data_An_Cour!$W:$W,L$2) -> 177.08 | N67: =L67-F67 -> -435.6603 | Q67: =SUMIFS([5]BV_Data_An_Prec!$O:$O,[5]BV_Data_An_Prec!$U:$U,$B67,[5]BV_Data_An_Prec!$V:$V,$C67,[5]BV_Data_An_Prec!$W:$W,Q$2) -> 1388.34 | S67: =L67-Q67 -> -1211.26
A68: Véhicules neufsFrais bancaires | B68: Véhicules neufs | C68: Frais bancaires | F68: {=+INDEX('[5]Budget original'!$A$2:$AO$500,MATCH($A68,'[5]Budget original'!$A$2:$A$500,0),MATCH(F$2,'[5]Budget original'!$A$2:$AO$2,0))} -> 1131.0254 | L68: =SUMIFS([5]BV_Data_An_Cour!$O:$O,[5]BV_Data_An_Cour!$U:$U,$B68,[5]BV_Data_An_Cour!$V:$V,$C68,[5]BV_Data_An_Cour!$W:$W,L$2) -> 3406.43 | N68: =L68-F68 -> 2275.4046 | Q68: =AL447*W3 -> 3741.192 | S68: =L68-Q68 -> -334.762
A69: Véhicules neufs[...] | B69: Véhicules neufs | C69: [...] | F69: {=+INDEX('[5]Budget original'!$A$2:$AO$500,MATCH($A69,'[5]Budget original'!$A$2:$A$500,0),MATCH(F$2,'[5]Budget original'!$A$2:$AO$2,0))} -> 0 | N69: =L69-F69 -> 0 | Q69: =SUMIFS([5]BV_Data_An_Prec!$O:$O,[5]BV_Data_An_Prec!$U:$U,$B69,[5]BV_Data_An_Prec!$V:$V,$C69,[5]BV_Data_An_Prec!$W:$W,Q$2) -> 0 | S69: =L69-Q69 -> 0
A70: Véhicules neufs[...] | B70: Véhicules neufs | C70: [...] | F70: {=+INDEX('[5]Budget original'!$A$2:$AO$500,MATCH($A70,'[5]Budget original'!$A$2:$A$500,0),MATCH(F$2,'[5]Budget original'!$A$2:$AO$2,0))} -> 0 | L70: =SUMIFS([5]BV_Data_An_Cour!$O:$O,[5]BV_Data_An_Cour!$U:$U,$B70,[5]BV_Data_An_Cour!$V:$V,$C70,[5]BV_Data_An_Cour!$W:$W,L$2) -> 0 | N70: =L70-F70 -> 0 | Q70: =SUMIFS([5]BV_Data_An_Prec!$O:$O,[5]BV_Data_An_Prec!$U:$U,$B70,[5]BV_Data_An_Prec!$V:$V,$C70,[5]BV_Data_An_Prec!$W:$W,Q$2) -> 0 | S70: =L70-Q70 -> 0
A71: Véhicules neufs[...] | B71: Véhicules neufs | C71: [...] | F71: {=+INDEX('[5]Budget original'!$A$2:$AO$500,MATCH($A71,'[5]Budget original'!$A$2:$A$500,0),MATCH(F$2,'[5]Budget original'!$A$2:$AO$2,0))} -> 0 | L71: =SUMIFS([5]BV_Data_An_Cour!$O:$O,[5]BV_Data_An_Cour!$U:$U,$B71,[5]BV_Data_An_Cour!$V:$V,$C71,[5]BV_Data_An_Cour!$W:$W,L$2)*0.32 -> 0 | N71: =L71-F71 -> 0 | Q71: =SUMIFS([5]BV_Data_An_Prec!$O:$O,[5]BV_Data_An_Prec!$U:$U,$B71,[5]BV_Data_An_Prec!$V:$V,$C71,[5]BV_Data_An_Prec!$W:$W,Q$2)*0.32 -> 0 | S71: =L71-Q71 -> 0
A72: Véhicules neufsTOTAL SEMI-FIXES | B72: Véhicules neufs | C72: TOTAL SEMI-FIXES | D72: % brut | E72: =F72/F$27 -> 0.1256704 | F72: =+SUM(F55:F71) -> 25541.121 | J72: % brut | K72: =L72/L$27 -> 0.16727624 | L72: =+SUM(L55:L71) -> 25796.08 | N72: =+SUM(N55:N71) -> 254.9589 | O72: % brut | P72: =Q72/Q$27 -> 0.10828736 | Q72: =+SUM(Q55:Q71) -> 27839.632 | S72: =+SUM(S55:S71) -> -2043.552
A73: Véhicules neufs | B73: Véhicules neufs
A74: Véhicules neufsTOTAL DES DÉPENSES | B74: Véhicules neufs | C74: TOTAL DES DÉPENSES | D74: % brut | E74: =F74/F$27 -> 0.90947197 | F74: =F41+F54+F72 -> 184840.13 | J74: % brut | K74: =L74/L$27 -> 1.0961581 | L74: =L41+L54+L72 -> 169041.24 | N74: =L74-F74 -> -15798.892 | O74: % brut | P74: =Q74/Q$27 -> 0.82697864 | Q74: =Q41+Q54+Q72 -> 212608.2 | S74: =L74-Q74 -> -43566.962
A75: Véhicules neufsProgramme neuf 1 | B75: Véhicules neufs | C75: Programme neuf 1 | F75: {=+INDEX('[5]Budget original'!$A$2:$AO$500,MATCH($A75,'[5]Budget original'!$A$2:$A$500,0),MATCH(F$2,'[5]Budget original'!$A$2:$AO$2,0))} -> 0 | L75: =-SUMIFS([5]BV_Data_An_Cour!$O:$O,[5]BV_Data_An_Cour!$U:$U,$B75,[5]BV_Data_An_Cour!$V:$V,$C75,[5]BV_Data_An_Cour!$W:$W,L$2)-L155 -> 0 | N75: =L75-F75 -> 0 | Q75: =-SUMIFS([5]BV_Data_An_Prec!$O:$O,[5]BV_Data_An_Prec!$U:$U,$B75,[5]BV_Data_An_Prec!$V:$V,$C75,[5]BV_Data_An_Prec!$W:$W,Q$2) -> 0
A76: Véhicules neufsProgramme neuf 2 | B76: Véhicules neufs | C76: Programme neuf 2 | F76: {=+INDEX('[5]Budget original'!$A$2:$AO$500,MATCH($A76,'[5]Budget original'!$A$2:$A$500,0),MATCH(F$2,'[5]Budget original'!$A$2:$AO$2,0))} -> 0 | L76: =-SUMIFS([5]BV_Data_An_Cour!$O:$O,[5]BV_Data_An_Cour!$U:$U,$B76,[5]BV_Data_An_Cour!$V:$V,$C76,[5]BV_Data_An_Cour!$W:$W,L$2) -> 0 | N76: =L76-F76 -> 0 | Q76: =-SUMIFS([5]BV_Data_An_Prec!$O:$O,[5]BV_Data_An_Prec!$U:$U,$B76,[5]BV_Data_An_Prec!$V:$V,$C76,[5]BV_Data_An_Prec!$W:$W,Q$2) -> 0 | S76: =L76-Q76 -> 0
A77: Véhicules neufsProgramme neuf 3 | B77: Véhicules neufs | C77: Programme neuf 3 | F77: {=+INDEX('[5]Budget original'!$A$2:$AO$500,MATCH($A77,'[5]Budget original'!$A$2:$A$500,0),MATCH(F$2,'[5]Budget original'!$A$2:$AO$2,0))} -> 0 | L77: =-SUMIFS([5]BV_Data_An_Cour!$O:$O,[5]BV_Data_An_Cour!$U:$U,$B77,[5]BV_Data_An_Cour!$V:$V,$C77,[5]BV_Data_An_Cour!$W:$W,L$2) -> 0 | N77: =L77-F77 -> 0 | Q77: =-SUMIFS([5]BV_Data_An_Prec!$O:$O,[5]BV_Data_An_Prec!$U:$U,$B77,[5]BV_Data_An_Prec!$V:$V,$C77,[5]BV_Data_An_Prec!$W:$W,Q$2) -> 0 | S77: =L77-Q77 -> 0
A78: Véhicules neufsHoldbacks | B78: Véhicules neufs | C78: Holdbacks | E78: =+F78/D24 -> 1181.3417 | F78: {=+INDEX('[5]Budget original'!$A$2:$AO$500,MATCH($A78,'[5]Budget original'!$A$2:$A$500,0),MATCH(F$2,'[5]Budget original'!$A$2:$AO$2,0))} -> 62181.08 | K78: =+L78/J24 -> 1094.8346 | L78: =-SUMIFS([5]BV_Data_An_Cour!$O:$O,[5]BV_Data_An_Cour!$U:$U,$B78,[5]BV_Data_An_Cour!$V:$V,$C78,[5]BV_Data_An_Cour!$W:$W,L$2) -> 42698.55 | N78: =L78-F78 -> -19482.53 | Q78: =-SUMIFS([5]BV_Data_An_Prec!$O:$O,[5]BV_Data_An_Prec!$U:$U,$B78,[5]BV_Data_An_Prec!$V:$V,$C78,[5]BV_Data_An_Prec!$W:$W,Q$2) -> 69130 | S78: =L78-Q78 -> -26431.45
A79: Véhicules neufs[...] | B79: Véhicules neufs | C79: [...] | F79: {=+INDEX('[5]Budget original'!$A$2:$AO$500,MATCH($A79,'[5]Budget original'!$A$2:$A$500,0),MATCH(F$2,'[5]Budget original'!$A$2:$AO$2,0))} -> 0 | L79: =-SUMIFS([5]BV_Data_An_Cour!$O:$O,[5]BV_Data_An_Cour!$U:$U,$B79,[5]BV_Data_An_Cour!$V:$V,$C79,[5]BV_Data_An_Cour!$W:$W,L$2) -> 0 | N79: =L79-F79 -> 0 | Q79: =-SUMIFS([5]BV_Data_An_Prec!$O:$O,[5]BV_Data_An_Prec!$U:$U,$B79,[5]BV_Data_An_Prec!$V:$V,$C79,[5]BV_Data_An_Prec!$W:$W,Q$2) -> 0 | S79: =L79-Q79 -> 0
A80: Véhicules neufs[...] | B80: Véhicules neufs | C80: [...] | F80: {=+INDEX('[5]Budget original'!$A$2:$AO$500,MATCH($A80,'[5]Budget original'!$A$2:$A$500,0),MATCH(F$2,'[5]Budget original'!$A$2:$AO$2,0))} -> 0 | L80: =-SUMIFS([5]BV_Data_An_Cour!$O:$O,[5]BV_Data_An_Cour!$U:$U,$B80,[5]BV_Data_An_Cour!$V:$V,$C80,[5]BV_Data_An_Cour!$W:$W,L$2) -> 0 | N80: =L80-F80 -> 0 | Q80: =-SUMIFS([5]BV_Data_An_Prec!$O:$O,[5]BV_Data_An_Prec!$U:$U,$B80,[5]BV_Data_An_Prec!$V:$V,$C80,[5]BV_Data_An_Prec!$W:$W,Q$2) -> 0 | S80: =L80-Q80 -> 0
A81: Véhicules neufs[...] | B81: Véhicules neufs | C81: [...] | F81: {=+INDEX('[5]Budget original'!$A$2:$AO$500,MATCH($A81,'[5]Budget original'!$A$2:$A$500,0),MATCH(F$2,'[5]Budget original'!$A$2:$AO$2,0))} -> 0 | L81: =-SUMIFS([5]BV_Data_An_Cour!$O:$O,[5]BV_Data_An_Cour!$U:$U,$B81,[5]BV_Data_An_Cour!$V:$V,$C81,[5]BV_Data_An_Cour!$W:$W,L$2) -> 0 | N81: =L81-F81 -> 0 | Q81: =-SUMIFS([5]BV_Data_An_Prec!$O:$O,[5]BV_Data_An_Prec!$U:$U,$B81,[5]BV_Data_An_Prec!$V:$V,$C81,[5]BV_Data_An_Prec!$W:$W,Q$2) -> 0 | S81: =L81-Q81 -> 0
A82: Véhicules neufsFrais administration | B82: Véhicules neufs | C82: Frais administration | F82: {=+INDEX('[5]Budget original'!$A$2:$AO$500,MATCH($A82,'[5]Budget original'!$A$2:$A$500,0),MATCH(F$2,'[5]Budget original'!$A$2:$AO$2,0))} -> 19591.053 | J82: =+L82/K82 -> 40 | K82: =+L82/J27 -> 486.15 | L82: =-SUMIFS([5]BV_Data_An_Cour!$O:$O,[5]BV_Data_An_Cour!$U:$U,$B82,[5]BV_Data_An_Cour!$V:$V,$C82,[5]BV_Data_An_Cour!$W:$W,L$2) -> 19446 | N82: =L82-F82 -> -145.05271 | Q82: =-SUMIFS([5]BV_Data_An_Prec!$O:$O,[5]BV_Data_An_Prec!$U:$U,$B82,[5]BV_Data_An_Prec!$V:$V,$C82,[5]BV_Data_An_Prec!$W:$W,Q$2) -> 20382 | S82: =L82-Q82 -> -936
A83: Véhicules neufsAUTRES REVENUS | B83: Véhicules neufs | C83: AUTRES REVENUS | F83: =+SUM(F75:F82) -> 81772.133 | L83: =+SUM(L75:L82) -> 62144.55 | N83: =+SUM(N75:N82) -> -19627.583 | Q83: =+SUM(Q75:Q82) -> 89512 | S83: =+SUM(S75:S82) -> -27367.45
A84: Véhicules neufs | B84: Véhicules neufs
A85: Véhicules neufsPROFIT DÉPARTEMENTAL | B85: Véhicules neufs | C85: PROFIT DÉPARTEMENTAL | F85: =F27-F74+F83 -> 100170.95 | L85: =L27-L74+L83 -> 47315.77 | N85: =N27-N41-N54-N72+N83 -> -52855.185 | Q85: =Q27-Q74+Q83 -> 133994.12 | S85: =S27-S41-S54-S72+S83 -> -86678.348
C89: =C1 -> Volks | K89: Véhicules usagés | S89: =$S$1 -> Réalisé, Juillet 2023
D91: BUDGET ORIGINAL | J91: RÉALISATION | M91: ÉCART réel / Budget | O91: ANNÉE PRÉCÉDENTE | R91: ECART (réel/ Ann.Préc.)
D92: UNITÉS | E92: $P/UNITÉ | F92: $PROFITS | J92: UNITÉS | K92: $P/UNITE | L92: $PROFITS | M92: UNITÉS | N92: $PROFITS | O92: UNITÉS | P92: $P/UNITE | Q92: $PROFITS | R92: UNITÉS | S92: $PROFITS
A93: Véhicules usagésVentes nettes | B93: Véhicules usagés | C93: Ventes nettes | F93: {=+INDEX('[5]Budget original'!$A$2:$AO$500,MATCH($A93,'[5]Budget original'!$A$2:$A$500,0),MATCH(F$2,'[5]Budget original'!$A$2:$AO$2,0))} -> 1504224.7 | L93: =-SUMIFS([5]BV_Data_An_Cour!$O:$O,[5]BV_Data_An_Cour!$X:$X,"Oui",[5]BV_Data_An_Cour!$U:$U,$B93) -> 1727866.7 | Q93: =-SUMIFS([5]BV_Data_An_Prec!$O:$O,[5]BV_Data_An_Prec!$X:$X,"Oui",[5]BV_Data_An_Prec!$U:$U,$B93) -> 1722927
A94: Véhicules usagésCertifié | B94: Véhicules usagés | C94: Certifié | D94: {=+INDEX('[5]Budget original'!$A$2:$AO$500,MATCH($A94,'[5]Budget original'!$A$2:$A$500,0),MATCH(D$2,'[5]Budget original'!$A$2:$AO$2,0))} -> 36 | E94: =IF(D94=0,0,F94/D94) -> 1858 | F94: {=+INDEX('[5]Budget original'!$A$2:$AO$500,MATCH($A94,'[5]Budget original'!$A$2:$A$500,0),MATCH(F$2,'[5]Budget original'!$A$2:$AO$2,0))} -> 66888 | J94: =-SUMIFS([5]BV_Data_An_Cour!$O:$O,[5]BV_Data_An_Cour!$U:$U,$B94,[5]BV_Data_An_Cour!$V:$V,$C94,[5]BV_Data_An_Cour!$W:$W,J$2) -> 32 | K94: =IF(J94=0,0,L94/J94) -> 1803.6106 | L94: =-SUMIFS([5]BV_Data_An_Cour!$O:$O,[5]BV_Data_An_Cour!$U:$U,$B94,[5]BV_Data_An_Cour!$V:$V,$C94,[5]BV_Data_An_Cour!$W:$W,$L2) -> 57715.54 | M94: =J94-D94 -> -4 | N94: =L94-F94 -> -9172.46 | O94: =-SUMIFS([5]BV_Data_An_Prec!$O:$O,[5]BV_Data_An_Prec!$U:$U,$B94,[5]BV_Data_An_Prec!$V:$V,$C94,[5]BV_Data_An_Prec!$W:$W,O$2) -> 39 | P94: =IF(O94=0,0,Q94/O94) -> 1866.1264 | Q94: =-SUMIFS([5]BV_Data_An_Prec!$O:$O,[5]BV_Data_An_Prec!$U:$U,$B94,[5]BV_Data_An_Prec!$V:$V,$C94,[5]BV_Data_An_Prec!$W:$W,$L2) -> 72778.93 | R94: =J94-O94 -> -7 | S94: =L94-Q94 -> -15063.39
A95: Véhicules usagésNon Certifié | B95: Véhicules usagés | C95: Non Certifié | D95: {=+INDEX('[5]Budget original'!$A$2:$AO$500,MATCH($A95,'[5]Budget original'!$A$2:$A$500,0),MATCH(D$2,'[5]Budget original'!$A$2:$AO$2,0))} -> 0 | E95: =IF(D95=0,0,F95/D95) -> 0 | F95: {=+INDEX('[5]Budget original'!$A$2:$AO$500,MATCH($A95,'[5]Budget original'!$A$2:$A$500,0),MATCH(F$2,'[5]Budget original'!$A$2:$AO$2,0))} -> 0 | J95: =-SUMIFS([5]BV_Data_An_Cour!$O:$O,[5]BV_Data_An_Cour!$U:$U,$B95,[5]BV_Data_An_Cour!$V:$V,$C95,[5]BV_Data_An_Cour!$W:$W,J$2) -> 4 | K95: =IF(J95=0,0,L95/J95) -> 1549.3475 | L95: =-SUMIFS([5]BV_Data_An_Cour!$O:$O,[5]BV_Data_An_Cour!$U:$U,$B95,[5]BV_Data_An_Cour!$V:$V,$C95,[5]BV_Data_An_Cour!$W:$W,$L2) -> 6197.39 | M95: =J95-D95 -> 4 | N95: =L95-F95 -> 6197.39 | O95: =-SUMIFS([5]BV_Data_An_Prec!$O:$O,[5]BV_Data_An_Prec!$U:$U,$B95,[5]BV_Data_An_Prec!$V:$V,$C95,[5]BV_Data_An_Prec!$W:$W,O$2) -> 0 | P95: =IF(O95=0,0,Q95/O95) -> 0 | Q95: =-SUMIFS([5]BV_Data_An_Prec!$O:$O,[5]BV_Data_An_Prec!$U:$U,$B95,[5]BV_Data_An_Prec!$V:$V,$C95,[5]BV_Data_An_Prec!$W:$W,$L2) -> 0 | R95: =J95-O95 -> 4 | S95: =L95-Q95 -> 6197.39
A96: Véhicules usagésTotal Usagés | B96: Véhicules usagés | C96: Total Usagés | D96: =+D95+D94 -> 36 | E96: =IF(D96=0,0,F96/D96) -> 1858 | F96: =+F94+F95 -> 66888 | J96: =+J94+J95 -> 36 | K96: =IF(J96<=0,0,L96/J96) -> 1775.3592 | L96: =+L94+L95 -> 63912.93 | M96: =J96-D96 -> 0 | N96: =L96-F96 -> -2975.07 | O96: =+O94+O95 -> 39 | P96: =IF(O96<=0,0,Q96/O96) -> 1866.1264 | Q96: =+Q94+Q95 -> 72778.93 | R96: =R94+R95 -> -3 | S96: =S94+S95 -> -8866
A97: Véhicules usagés | B97: Véhicules usagés | E97: =IF(D97=0,0,F97/D97) -> 0 | M97: =M96/D96 -> 0 | N97: =N96/F96 -> -0.044478382 | R97: =R96/O96 -> -0.076923077 | S97: =IF(Q96=0,0,(S96/Q96)) -> -0.12182097
A98: Véhicules usagésUS | B98: Véhicules usagés | C98: US
A99: Véhicules usagésVentes au Gros | B99: Véhicules usagés | C99: Ventes au Gros | D99: {=+INDEX('[5]Budget original'!$A$2:$AO$500,MATCH($A99,'[5]Budget original'!$A$2:$A$500,0),MATCH(D$2,'[5]Budget original'!$A$2:$AO$2,0))} -> 30.461538 | E99: =IF(D99=0,0,F99/D99) -> 399 | F99: {=+INDEX('[5]Budget original'!$A$2:$AO$500,MATCH($A99,'[5]Budget original'!$A$2:$A$500,0),MATCH(F$2,'[5]Budget original'!$A$2:$AO$2,0))} -> 12154.154 | J99: =-SUMIFS([5]BV_Data_An_Cour!$O:$O,[5]BV_Data_An_Cour!$U:$U,$B99,[5]BV_Data_An_Cour!$V:$V,$C99,[5]BV_Data_An_Cour!$W:$W,J$2) -> 28 | K99: =IF(J99=0,0,L99/J99) -> 616.26179 | L99: =-SUMIFS([5]BV_Data_An_Cour!$O:$O,[5]BV_Data_An_Cour!$U:$U,$B99,[5]BV_Data_An_Cour!$V:$V,$C99,[5]BV_Data_An_Cour!$W:$W,L$2) -> 17255.33 | M99: =J99-D99 -> -2.4615385 | N99: =L99-F99 -> 5101.1762 | O99: =-SUMIFS([5]BV_Data_An_Prec!$O:$O,[5]BV_Data_An_Prec!$U:$U,$B99,[5]BV_Data_An_Prec!$V:$V,$C99,[5]BV_Data_An_Prec!$W:$W,O$2) -> 39 | P99: =IF(O99=0,0,Q99/O99) -> 417.18231 | Q99: =-SUMIFS([5]BV_Data_An_Prec!$O:$O,[5]BV_Data_An_Prec!$U:$U,$B99,[5]BV_Data_An_Prec!$V:$V,$C99,[5]BV_Data_An_Prec!$W:$W,Q$2) -> 16270.11 | R99: =J99-O99 -> -11 | S99: =L99-Q99 -> 985.22
A100: Véhicules usagés | B100: Véhicules usagés
A101: Véhicules usagésRev. Finances | B101: Véhicules usagés | C101: Rev. Finances | D101: {=+INDEX('[5]Budget original'!$A$2:$AO$500,MATCH($A101,'[5]Budget original'!$A$2:$A$500,0),MATCH(D$2,'[5]Budget original'!$A$2:$AO$2,0))} -> 0 | E101: =IF(D101=0,0,F101/D101) -> 0 | F101: {=+INDEX('[5]Budget original'!$A$2:$AO$500,MATCH($A101,'[5]Budget original'!$A$2:$A$500,0),MATCH(F$2,'[5]Budget original'!$A$2:$AO$2,0))} -> 18000 | K101: =IF(J96=0,0,L101/J96) -> 517.39306 | L101: =-SUMIFS([5]BV_Data_An_Cour!$O:$O,[5]BV_Data_An_Cour!$U:$U,$B101,[5]BV_Data_An_Cour!$V:$V,$C101,[5]BV_Data_An_Cour!$W:$W,$L2) -> 18626.15 | N101: =L101-F101 -> 626.15 | P101: =IF(O96=0,0,Q101/O96) -> 567.12359 | Q101: =-SUMIFS([5]BV_Data_An_Prec!$O:$O,[5]BV_Data_An_Prec!$U:$U,$B101,[5]BV_Data_An_Prec!$V:$V,$C101,[5]BV_Data_An_Prec!$W:$W,$L2) -> 22117.82 | R101: =O101-K101 -> -517.39306 | S101: =L101-Q101 -> -3491.67
A102: Véhicules usagésRev. Protections | B102: Véhicules usagés | C102: Rev. Protections | D102: {=+INDEX('[5]Budget original'!$A$2:$AO$500,MATCH($A102,'[5]Budget original'!$A$2:$A$500,0),MATCH(D$2,'[5]Budget original'!$A$2:$AO$2,0))} -> 0 | E102: =IF(D102=0,0,F102/D102) -> 0 | F102: {=+INDEX('[5]Budget original'!$A$2:$AO$500,MATCH($A102,'[5]Budget original'!$A$2:$A$500,0),MATCH(F$2,'[5]Budget original'!$A$2:$AO$2,0))} -> 45000 | K102: =IF(J96=0,0,L102/J96) -> 997.11056 | L102: =-SUMIFS([5]BV_Data_An_Cour!$O:$O,[5]BV_Data_An_Cour!$U:$U,$B102,[5]BV_Data_An_Cour!$V:$V,$C102,[5]BV_Data_An_Cour!$W:$W,$L2) -> 35895.98 | N102: =L102-F102 -> -9104.02 | P102: =IF(O96=0,0,Q102/O96) -> 1053.2949 | Q102: =-SUMIFS([5]BV_Data_An_Prec!$O:$O,[5]BV_Data_An_Prec!$U:$U,$B102,[5]BV_Data_An_Prec!$V:$V,$C102,[5]BV_Data_An_Prec!$W:$W,$L2) -> 41078.5 | R102: =O102-K102 -> -997.11056 | S102: =L102-Q102 -> -5182.52
A103: Véhicules usagésRev. Autres | B103: Véhicules usagés | C103: Rev. Autres | D103: {=+INDEX('[5]Budget original'!$A$2:$AO$500,MATCH($A103,'[5]Budget original'!$A$2:$A$500,0),MATCH(D$2,'[5]Budget original'!$A$2:$AO$2,0))} -> 0 | E103: =IF(D103=0,0,F103/D103) -> 0 | F103: {=+INDEX('[5]Budget original'!$A$2:$AO$500,MATCH($A103,'[5]Budget original'!$A$2:$A$500,0),MATCH(F$2,'[5]Budget original'!$A$2:$AO$2,0))} -> 12600 | K103: =IF(J96=0,0,L103/J96) -> 25.253889 | L103: =-SUMIFS([5]BV_Data_An_Cour!$O:$O,[5]BV_Data_An_Cour!$U:$U,$B103,[5]BV_Data_An_Cour!$V:$V,$C103,[5]BV_Data_An_Cour!$W:$W,$L$2) -> 909.14 | N103: =L103-F103 -> -11690.86 | P103: =IF(O96=0,0,Q103/O96) -> 41.861538 | Q103: =-SUMIFS([5]BV_Data_An_Prec!$O:$O,[5]BV_Data_An_Prec!$U:$U,$B103,[5]BV_Data_An_Prec!$V:$V,$C103,[5]BV_Data_An_Prec!$W:$W,$L$2) -> 1632.6 | R103: =O103-K103 -> -25.253889 | S103: =L103-Q103 -> -723.46
A104: Véhicules usagésTotal F&I | B104: Véhicules usagés | C104: Total F&I | D104: =D96 -> 36 | E104: =IF(D104=0,0,F104/D104) -> 2100 | F104: =F101+F102+F103 -> 75600 | J104: =J96 -> 36 | K104: =IF(J104<=0,0,L104/J104) -> 1539.7575 | L104: =L101+L102+L103 -> 55431.27 | M104: =J104-D104 -> 0 | N104: =L104-F104 -> -20168.73 | O104: =O96 -> 39 | P104: =IF(O104<=0,0,Q104/O104) -> 1662.28 | Q104: =Q101+Q102+Q103 -> 64828.92 | S104: =L104-Q104 -> -9397.65
...

Sheet Juin 2023
C1: =[6]Parametres!B1 -> Volks | K1: Véhicules neufs | S1: =CONCATENATE("Réalisé,"," ",[6]Parametres!B3," ",[6]Parametres!B4) -> Réalisé, Juin 2023
D2: X | E2: O | F2: U | J2: NB | L2: $ | O2: NB | Q2: $ | V2: *** NE PAS EFFACER / Pour An Précédente ***
D3: BUDGET ORIGINAL | J3: RÉALISATION | M3: ÉCART réel / Budget | O3: ANNÉE PRÉCÉDENTE | R3: ECART (réel/ Ann.Préc.) | V3: NEUF | W3: 0.45
D4: UNITÉS | E4: $P/UNITÉ | F4: $PROFITS | J4: UNITÉS | K4: $P/UNITE | L4: $PROFITS | M4: UNITÉS | N4: $PROFITS | O4: UNITÉS | P4: $P/UNITE | Q4: $PROFITS | R4: UNITÉS | S4: $PROFITS | V4: USAGE | W4: 0.1
A5: Véhicules neufsVentes nettes | B5: Véhicules neufs | C5: Ventes nettes | F5: {=+INDEX('[6]Budget original'!$A$2:$AO$500,MATCH($A5,'[6]Budget original'!$A$2:$A$500,0),MATCH(F$2,'[6]Budget original'!$A$2:$AO$2,0))} -> 2275303.5 | L5: =-SUMIFS([6]BV_Data_An_Cour!$O:$O,[6]BV_Data_An_Cour!$X:$X,"Oui",[6]BV_Data_An_Cour!$U:$U,$B5) -> 2851329.3 | Q5: =-SUMIFS([6]BV_Data_An_Prec!$O:$O,[6]BV_Data_An_Prec!$X:$X,"Oui",[6]BV_Data_An_Prec!$U:$U,$B5) -> 2836768.3 | V5: SERVICE | W5: 0.225
A6: Véhicules neufsAutos détail | B6: Véhicules neufs | C6: Autos détail | D6: {=+INDEX('[6]Budget original'!$A$2:$AO$500,MATCH($A6,'[6]Budget original'!$A$2:$A$500,0),MATCH(D$2,'[6]Budget original'!$A$2:$AO$2,0))} -> 9.6891429 | E6: =IF(D6=0,0,F6/D6) -> 1988.434 | F6: {=+INDEX('[6]Budget original'!$A$2:$AO$500,MATCH($A6,'[6]Budget original'!$A$2:$A$500,0),MATCH(F$2,'[6]Budget original'!$A$2:$AO$2,0))} -> 19266.221 | J6: =-SUMIFS([6]BV_Data_An_Cour!$O:$O,[6]BV_Data_An_Cour!$U:$U,$B6,[6]BV_Data_An_Cour!$V:$V,$C6,[6]BV_Data_An_Cour!$W:$W,J$2) -> 16 | K6: =IF(J6=0,0,L6/J6) -> 2103.4488 | L6: =-SUMIFS([6]BV_Data_An_Cour!$O:$O,[6]BV_Data_An_Cour!$U:$U,$B6,[6]BV_Data_An_Cour!$V:$V,$C6,[6]BV_Data_An_Cour!$W:$W,L$2) -> 33655.18 | M6: =J6-D6 -> 6.3108571 | N6: =L6-F6 -> 14388.959 | O6: =-SUMIFS([6]BV_Data_An_Prec!$O:$O,[6]BV_Data_An_Prec!$U:$U,$B6,[6]BV_Data_An_Prec!$V:$V,$C6,[6]BV_Data_An_Prec!$W:$W,O$2) -> 9 | P6: =IF(O6=0,0,Q6/O6) -> 2603.6256 | Q6: =-SUMIFS([6]BV_Data_An_Prec!$O:$O,[6]BV_Data_An_Prec!$U:$U,$B6,[6]BV_Data_An_Prec!$V:$V,$C6,[6]BV_Data_An_Prec!$W:$W,Q$2) -> 23432.63 | R6: =J6-O6 -> 7 | S6: =L6-Q6 -> 10222.55 | V6: CARROSSERIE | W6: 0.025
A7: Véhicules neufsCamions détail | B7: Véhicules neufs | C7: Camions détail | D7: {=+INDEX('[6]Budget original'!$A$2:$AO$500,MATCH($A7,'[6]Budget original'!$A$2:$A$500,0),MATCH(D$2,'[6]Budget original'!$A$2:$AO$2,0))} -> 38.752696 | E7: =IF(D7=0,0,F7/D7) -> 2556.3336 | F7: {=+INDEX('[6]Budget original'!$A$2:$AO$500,MATCH($A7,'[6]Budget original'!$A$2:$A$500,0),MATCH(F$2,'[6]Budget original'!$A$2:$AO$2,0))} -> 99064.82 | J7: =-SUMIFS([6]BV_Data_An_Cour!$O:$O,[6]BV_Data_An_Cour!$U:$U,$B7,[6]BV_Data_An_Cour!$V:$V,$C7,[6]BV_Data_An_Cour!$W:$W,J$2) -> 39 | K7: =IF(J7=0,0,L7/J7) -> 2445.2556 | L7: =-SUMIFS([6]BV_Data_An_Cour!$O:$O,[6]BV_Data_An_Cour!$U:$U,$B7,[6]BV_Data_An_Cour!$V:$V,$C7,[6]BV_Data_An_Cour!$W:$W,L$2) -> 95364.97 | M7: =J7-D7 -> 0.24730423 | N7: =L7-F7 -> -3699.8496 | O7: =-SUMIFS([6]BV_Data_An_Prec!$O:$O,[6]BV_Data_An_Prec!$U:$U,$B7,[6]BV_Data_An_Prec!$V:$V,$C7,[6]BV_Data_An_Prec!$W:$W,O$2) -> 43 | P7: =IF(O7=0,0,Q7/O7) -> 3826.4693 | Q7: =-SUMIFS([6]BV_Data_An_Prec!$O:$O,[6]BV_Data_An_Prec!$U:$U,$B7,[6]BV_Data_An_Prec!$V:$V,$C7,[6]BV_Data_An_Prec!$W:$W,Q$2) -> 164538.18 | R7: =J7-O7 -> -4 | S7: =L7-Q7 -> -69173.21 | V7: PIECES | W7: 0.2
A8: Véhicules neufsSprinter | B8: Véhicules neufs | C8: Sprinter | D8: {=+INDEX('[6]Budget original'!$A$2:$AO$500,MATCH($A8,'[6]Budget original'!$A$2:$A$500,0),MATCH(D$2,'[6]Budget original'!$A$2:$AO$2,0))} -> 0 | E8: =IF(D8=0,0,F8/D8) -> 0 | F8: {=+INDEX('[6]Budget original'!$A$2:$AO$500,MATCH($A8,'[6]Budget original'!$A$2:$A$500,0),MATCH(F$2,'[6]Budget original'!$A$2:$AO$2,0))} -> 0 | J8: =-SUMIFS([6]BV_Data_An_Cour!$O:$O,[6]BV_Data_An_Cour!$U:$U,$B8,[6]BV_Data_An_Cour!$V:$V,$C8,[6]BV_Data_An_Cour!$W:$W,J$2) -> 0 | K8: =IF(J8=0,0,L8/J8) -> 0 | L8: =-SUMIFS([6]BV_Data_An_Cour!$O:$O,[6]BV_Data_An_Cour!$U:$U,$B8,[6]BV_Data_An_Cour!$V:$V,$C8,[6]BV_Data_An_Cour!$W:$W,L$2) -> 0 | M8: =J8-D8 -> 0 | N8: =L8-F8 -> 0 | O8: =-SUMIFS([6]BV_Data_An_Prec!$O:$O,[6]BV_Data_An_Prec!$U:$U,$B8,[6]BV_Data_An_Prec!$V:$V,$C8,[6]BV_Data_An_Prec!$W:$W,O$2) -> 0 | P8: =IF(O8=0,0,Q8/O8) -> 0 | Q8: =-SUMIFS([6]BV_Data_An_Prec!$O:$O,[6]BV_Data_An_Prec!$U:$U,$B8,[6]BV_Data_An_Prec!$V:$V,$C8,[6]BV_Data_An_Prec!$W:$W,Q$2) -> 0 | R8: =J8-O8 -> 0 | S8: =L8-Q8 -> 0 | W8: =SUM(W3:W7) -> 1
A9: Véhicules neufsMoto détail | B9: Véhicules neufs | C9: Moto détail | D9: {=+INDEX('[6]Budget original'!$A$2:$AO$500,MATCH($A9,'[6]Budget original'!$A$2:$A$500,0),MATCH(D$2,'[6]Budget original'!$A$2:$AO$2,0))} -> 0 | E9: =IF(D9=0,0,F9/D9) -> 0 | F9: {=+INDEX('[6]Budget original'!$A$2:$AO$500,MATCH($A9,'[6]Budget original'!$A$2:$A$500,0),MATCH(F$2,'[6]Budget original'!$A$2:$AO$2,0))} -> 0 | J9: =-SUMIFS([6]BV_Data_An_Cour!$O:$O,[6]BV_Data_An_Cour!$U:$U,$B9,[6]BV_Data_An_Cour!$V:$V,$C9,[6]BV_Data_An_Cour!$W:$W,J$2) -> 0 | K9: =IF(J9=0,0,L9/J9) -> 0 | L9: =-SUMIFS([6]BV_Data_An_Cour!$O:$O,[6]BV_Data_An_Cour!$U:$U,$B9,[6]BV_Data_An_Cour!$V:$V,$C9,[6]BV_Data_An_Cour!$W:$W,L$2) -> 0 | M9: =J9-D9 -> 0 | N9: =L9-F9 -> 0 | O9: =-SUMIFS([6]BV_Data_An_Prec!$O:$O,[6]BV_Data_An_Prec!$U:$U,$B9,[6]BV_Data_An_Prec!$V:$V,$C9,[6]BV_Data_An_Prec!$W:$W,O$2) -> 0 | P9: =IF(O9=0,0,Q9/O9) -> 0 | Q9: =-SUMIFS([6]BV_Data_An_Prec!$O:$O,[6]BV_Data_An_Prec!$U:$U,$B9,[6]BV_Data_An_Prec!$V:$V,$C9,[6]BV_Data_An_Prec!$W:$W,Q$2) -> 0 | R9: =J9-O9 -> 0 | S9: =L9-Q9 -> 0
A10: Véhicules neufs[...] | B10: Véhicules neufs | C10: [...] | D10: 0 | E10: =IF(D10=0,0,F10/D10) -> 0 | F10: {=+INDEX('[6]Budget original'!$A$2:$AO$500,MATCH($A10,'[6]Budget original'!$A$2:$A$500,0),MATCH(F$2,'[6]Budget original'!$A$2:$AO$2,0))} -> 0 | J10: =-SUMIFS([6]BV_Data_An_Cour!$O:$O,[6]BV_Data_An_Cour!$U:$U,$B10,[6]BV_Data_An_Cour!$V:$V,$C10,[6]BV_Data_An_Cour!$W:$W,J$2) -> 0 | K10: =IF(J10=0,0,L10/J10) -> 0 | L10: =-SUMIFS([6]BV_Data_An_Cour!$O:$O,[6]BV_Data_An_Cour!$U:$U,$B10,[6]BV_Data_An_Cour!$V:$V,$C10,[6]BV_Data_An_Cour!$W:$W,L$2) -> 0 | M10: =J10-D10 -> 0 | N10: =L10-F10 -> 0 | O10: =-SUMIFS([6]BV_Data_An_Prec!$O:$O,[6]BV_Data_An_Prec!$U:$U,$B10,[6]BV_Data_An_Prec!$V:$V,$C10,[6]BV_Data_An_Prec!$W:$W,O$2) -> 0 | P10: =IF(O10=0,0,Q10/O10) -> 0 | Q10: =-SUMIFS([6]BV_Data_An_Prec!$O:$O,[6]BV_Data_An_Prec!$U:$U,$B10,[6]BV_Data_An_Prec!$V:$V,$C10,[6]BV_Data_An_Prec!$W:$W,Q$2) -> 0 | R10: =J10-O10 -> 0 | S10: =L10-Q10 -> 0
A11: Véhicules neufs[...] | B11: Véhicules neufs | C11: [...] | D11: 0 | E11: =IF(D11=0,0,F11/D11) -> 0 | F11: {=+INDEX('[6]Budget original'!$A$2:$AO$500,MATCH($A11,'[6]Budget original'!$A$2:$A$500,0),MATCH(F$2,'[6]Budget original'!$A$2:$AO$2,0))} -> 0 | J11: =-SUMIFS([6]BV_Data_An_Cour!$O:$O,[6]BV_Data_An_Cour!$U:$U,$B11,[6]BV_Data_An_Cour!$V:$V,$C11,[6]BV_Data_An_Cour!$W:$W,J$2) -> 0 | K11: =IF(J11=0,0,L11/J11) -> 0 | L11: =-SUMIFS([6]BV_Data_An_Cour!$O:$O,[6]BV_Data_An_Cour!$U:$U,$B11,[6]BV_Data_An_Cour!$V:$V,$C11,[6]BV_Data_An_Cour!$W:$W,L$2) -> 0 | M11: =J11-D11 -> 0 | N11: =L11-F11 -> 0 | O11: =-SUMIFS([6]BV_Data_An_Prec!$O:$O,[6]BV_Data_An_Prec!$U:$U,$B11,[6]BV_Data_An_Prec!$V:$V,$C11,[6]BV_Data_An_Prec!$W:$W,O$2) -> 0 | P11: =IF(O11=0,0,Q11/O11) -> 0 | Q11: =-SUMIFS([6]BV_Data_An_Prec!$O:$O,[6]BV_Data_An_Prec!$U:$U,$B11,[6]BV_Data_An_Prec!$V:$V,$C11,[6]BV_Data_An_Prec!$W:$W,Q$2) -> 0 | R11: =J11-O11 -> 0 | S11: =L11-Q11 -> 0
A12: Véhicules neufs[...] | B12: Véhicules neufs | C12: [...] | D12: 0 | E12: =IF(D12=0,0,F12/D12) -> 0 | F12: {=+INDEX('[6]Budget original'!$A$2:$AO$500,MATCH($A12,'[6]Budget original'!$A$2:$A$500,0),MATCH(F$2,'[6]Budget original'!$A$2:$AO$2,0))} -> 0 | J12: =-SUMIFS([6]BV_Data_An_Cour!$O:$O,[6]BV_Data_An_Cour!$U:$U,$B12,[6]BV_Data_An_Cour!$V:$V,$C12,[6]BV_Data_An_Cour!$W:$W,J$2) -> 0 | K12: =IF(J12=0,0,L12/J12) -> 0 | L12: =-SUMIFS([6]BV_Data_An_Cour!$O:$O,[6]BV_Data_An_Cour!$U:$U,$B12,[6]BV_Data_An_Cour!$V:$V,$C12,[6]BV_Data_An_Cour!$W:$W,L$2) -> 0 | M12: =J12-D12 -> 0 | N12: =L12-F12 -> 0 | O12: =-SUMIFS([6]BV_Data_An_Prec!$O:$O,[6]BV_Data_An_Prec!$U:$U,$B12,[6]BV_Data_An_Prec!$V:$V,$C12,[6]BV_Data_An_Prec!$W:$W,O$2) -> 0 | P12: =IF(O12=0,0,Q12/O12) -> 0 | Q12: =-SUMIFS([6]BV_Data_An_Prec!$O:$O,[6]BV_Data_An_Prec!$U:$U,$B12,[6]BV_Data_An_Prec!$V:$V,$C12,[6]BV_Data_An_Prec!$W:$W,Q$2) -> 0 | R12: =J12-O12 -> 0 | S12: =L12-Q12 -> 0
A13: Véhicules neufsTotal Neufs | B13: Véhicules neufs | C13: Total Neufs | D13: =+SUM(D6:D12) -> 48.441839 | E13: =IF(D13<=0,0,F13/D13) -> 2442.7446 | F13: =+SUM(F6:F12) -> 118331.04 | J13: =+SUM(J6:J12) -> 55 | K13: =IF(J13<=0,0,L13/J13) -> 2345.8209 | L13: =+SUM(L6:L12) -> 129020.15 | M13: =+SUM(M6:M12) -> 6.5581614 | N13: =+SUM(N6:N12) -> 10689.109 | O13: =+SUM(O6:O12) -> 52 | P13: =IF(O13<=0,0,Q13/O13) -> 3614.8233 | Q13: =+SUM(Q6:Q12) -> 187970.81 | R13: =+SUM(R6:R12) -> 3 | S13: =+SUM(S6:S12) -> -58950.66
A14: Véhicules neufs | B14: Véhicules neufs | M14: =IF(D13=0,0,M13/D13) -> 0.13538217 | N14: =IF(F13=0,0,N13/F13) -> 0.090332252 | R14: =R13/O13 -> 0.057692308 | S14: =IF(Q13=0,0,(S13/Q13)) -> -0.31361603 | AD14: 20 | AE14: 1000 | AF14: =AD14*AE14 -> 20000
A15: Véhicules neufsEx-Démos et courtoisies | B15: Véhicules neufs | C15: Ex-Démos et courtoisies | D15: {=+INDEX('[6]Budget original'!$A$2:$AO$500,MATCH($A15,'[6]Budget original'!$A$2:$A$500,0),MATCH(D$2,'[6]Budget original'!$A$2:$AO$2,0))} -> 2.3142857 | E15: =IF(D15=0,0,F15/D15) -> 2442.5492 | F15: {=+INDEX('[6]Budget original'!$A$2:$AO$500,MATCH($A15,'[6]Budget original'!$A$2:$A$500,0),MATCH(F$2,'[6]Budget original'!$A$2:$AO$2,0))} -> 5652.7567 | J15: =-SUMIFS([6]BV_Data_An_Cour!$O:$O,[6]BV_Data_An_Cour!$U:$U,$B15,[6]BV_Data_An_Cour!$V:$V,$C15,[6]BV_Data_An_Cour!$W:$W,J$2) -> 2 | K15: =IF(J15=0,0,L15/J15) -> 1486.73 | L15: =-SUMIFS([6]BV_Data_An_Cour!$O:$O,[6]BV_Data_An_Cour!$U:$U,$B15,[6]BV_Data_An_Cour!$V:$V,$C15,[6]BV_Data_An_Cour!$W:$W,L$2) -> 2973.46 | M15: =J15-D15 -> -0.31428571 | N15: =L15-F15 -> -2679.2967 | O15: =-SUMIFS([6]BV_Data_An_Prec!$O:$O,[6]BV_Data_An_Prec!$U:$U,$B15,[6]BV_Data_An_Prec!$V:$V,$C15,[6]BV_Data_An_Prec!$W:$W,O$2) -> 4 | P15: =IF(O15=0,0,Q15/O15) -> 2132.36 | Q15: =-SUMIFS([6]BV_Data_An_Prec!$O:$O,[6]BV_Data_An_Prec!$U:$U,$B15,[6]BV_Data_An_Prec!$V:$V,$C15,[6]BV_Data_An_Prec!$W:$W,Q$2) -> 8529.44 | R15: =J15-O15 -> -2 | S15: =L15-Q15 -> -5555.98 | AD15: 25 | AE15: =AF15/AD15 -> 800 | AF15: =AF14 -> 20000
A16: Véhicules neufs | B16: Véhicules neufs
A17: Véhicules neufsFlottes | B17: Véhicules neufs | C17: Flottes | D17: {=+INDEX('[6]Budget original'!$A$2:$AO$500,MATCH($A17,'[6]Budget original'!$A$2:$A$500,0),MATCH(D$2,'[6]Budget original'!$A$2:$AO$2,0))} -> 1.8514286 | E17: =IF(D17=0,0,F17/D17) -> 2442.5492 | F17: {=+INDEX('[6]Budget original'!$A$2:$AO$500,MATCH($A17,'[6]Budget original'!$A$2:$A$500,0),MATCH(F$2,'[6]Budget original'!$A$2:$AO$2,0))} -> 4522.2054 | J17: =-SUMIFS([6]BV_Data_An_Cour!$O:$O,[6]BV_Data_An_Cour!$U:$U,$B17,[6]BV_Data_An_Cour!$V:$V,$C17,[6]BV_Data_An_Cour!$W:$W,J$2) -> 2 | K17: =IF(J17=0,0,L17/J17) -> 2962.945 | L17: =-SUMIFS([6]BV_Data_An_Cour!$O:$O,[6]BV_Data_An_Cour!$U:$U,$B17,[6]BV_Data_An_Cour!$V:$V,$C17,[6]BV_Data_An_Cour!$W:$W,L$2) -> 5925.89 | M17: =J17-D17 -> 0.14857143 | N17: =L17-F17 -> 1403.6846 | O17: =-SUMIFS([6]BV_Data_An_Prec!$O:$O,[6]BV_Data_An_Prec!$U:$U,$B17,[6]BV_Data_An_Prec!$V:$V,$C17,[6]BV_Data_An_Prec!$W:$W,O$2) -> 0 | P17: =IF(O17=0,0,Q17/O17) -> 0 | Q17: =-SUMIFS([6]BV_Data_An_Prec!$O:$O,[6]BV_Data_An_Prec!$U:$U,$B17,[6]BV_Data_An_Prec!$V:$V,$C17,[6]BV_Data_An_Prec!$W:$W,Q$2) -> 0 | R17: =J17-O17 -> 2 | S17: =L17-Q17 -> 5925.89 | V17: =+L13+L15+L17-4000 -> 133919.5
A18: Véhicules neufs | B18: Véhicules neufs | V18: =+L31/V17 -> 0.32831567
A19: Véhicules neufsRachat bail | B19: Véhicules neufs | C19: Rachat bail | D19: {=+INDEX('[6]Budget original'!$A$2:$AO$500,MATCH($A19,'[6]Budget original'!$A$2:$A$500,0),MATCH(D$2,'[6]Budget original'!$A$2:$AO$2,0))} -> 0 | E19: =IF(D19=0,0,F19/D19) -> 0 | F19: {=+INDEX('[6]Budget original'!$A$2:$AO$500,MATCH($A19,'[6]Budget original'!$A$2:$A$500,0),MATCH(F$2,'[6]Budget original'!$A$2:$AO$2,0))} -> 11520 | L19: =-SUMIFS([6]BV_Data_An_Cour!$O:$O,[6]BV_Data_An_Cour!$U:$U,$B19,[6]BV_Data_An_Cour!$V:$V,$C19,[6]BV_Data_An_Cour!$W:$W,L$2) -> 12900.75 | N19: =L19-F19 -> 1380.75 | Q19: =-SUMIFS([6]BV_Data_An_Prec!$O:$O,[6]BV_Data_An_Prec!$U:$U,$B19,[6]BV_Data_An_Prec!$V:$V,$C19,[6]BV_Data_An_Prec!$W:$W,Q$2) -> 13151.1 | R19: =O19-K19 -> 0 | S19: =L19-Q19 -> -250.35
A20: Véhicules neufs | B20: Véhicules neufs
A21: Véhicules neufsRev. Finances | B21: Véhicules neufs | C21: Rev. Finances | D21: {=+INDEX('[6]Budget original'!$A$2:$AO$500,MATCH($A21,'[6]Budget original'!$A$2:$A$500,0),MATCH(D$2,'[6]Budget original'!$A$2:$AO$2,0))} -> 0 | E21: =IF(D21=0,0,F21/D21) -> 0 | F21: {=+INDEX('[6]Budget original'!$A$2:$AO$500,MATCH($A21,'[6]Budget original'!$A$2:$A$500,0),MATCH(F$2,'[6]Budget original'!$A$2:$AO$2,0))} -> 8730.0534 | K21: =IF(J13=0,0,L21/(J13+J15)) -> 89.401579 | L21: =-SUMIFS([6]BV_Data_An_Cour!$O:$O,[6]BV_Data_An_Cour!$U:$U,$B21,[6]BV_Data_An_Cour!$V:$V,$C21,[6]BV_Data_An_Cour!$W:$W,L$2) -> 5095.89 | N21: =L21-F21 -> -3634.1634 | P21: =IF(O13=0,0,Q21/(O13+O15)) -> 228.50482 | Q21: =-SUMIFS([6]BV_Data_An_Prec!$O:$O,[6]BV_Data_An_Prec!$U:$U,$B21,[6]BV_Data_An_Prec!$V:$V,$C21,[6]BV_Data_An_Prec!$W:$W,Q$2) -> 12796.27 | R21: =O21-K21 -> -89.401579 | S21: =L21-Q21 -> -7700.38
A22: Véhicules neufsRev. Protections | B22: Véhicules neufs | C22: Rev. Protections | D22: {=+INDEX('[6]Budget original'!$A$2:$AO$500,MATCH($A22,'[6]Budget original'!$A$2:$A$500,0),MATCH(D$2,'[6]Budget original'!$A$2:$AO$2,0))} -> 0 | E22: =IF(D22=0,0,F22/D22) -> 0 | F22: {=+INDEX('[6]Budget original'!$A$2:$AO$500,MATCH($A22,'[6]Budget original'!$A$2:$A$500,0),MATCH(F$2,'[6]Budget original'!$A$2:$AO$2,0))} -> 48015.294 | K22: =IF(J13=0,0,L22/(J13+J15)) -> 868.40772 | L22: =-SUMIFS([6]BV_Data_An_Cour!$O:$O,[6]BV_Data_An_Cour!$U:$U,$B22,[6]BV_Data_An_Cour!$V:$V,$C22,[6]BV_Data_An_Cour!$W:$W,L$2) -> 49499.24 | N22: =L22-F22 -> 1483.9464 | P22: =IF(O13=0,0,Q22/(O13+O15)) -> 947.25268 | Q22: =-SUMIFS([6]BV_Data_An_Prec!$O:$O,[6]BV_Data_An_Prec!$U:$U,$B22,[6]BV_Data_An_Prec!$V:$V,$C22,[6]BV_Data_An_Prec!$W:$W,Q$2) -> 53046.15 | R22: =O22-K22 -> -868.40772 | S22: =L22-Q22 -> -3546.91
A23: Véhicules neufsRev. Autres | B23: Véhicules neufs | C23: Rev. Autres | D23: {=+INDEX('[6]Budget original'!$A$2:$AO$500,MATCH($A23,'[6]Budget original'!$A$2:$A$500,0),MATCH(D$2,'[6]Budget original'!$A$2:$AO$2,0))} -> 0 | E23: =IF(D23=0,0,F23/D23) -> 0 | F23: {=+INDEX('[6]Budget original'!$A$2:$AO$500,MATCH($A23,'[6]Budget original'!$A$2:$A$500,0),MATCH(F$2,'[6]Budget original'!$A$2:$AO$2,0))} -> 1471.9276 | K23: =IF(J13=0,0,L23/(J13+J15)) -> 0 | L23: =-SUMIFS([6]BV_Data_An_Cour!$O:$O,[6]BV_Data_An_Cour!$U:$U,$B23,[6]BV_Data_An_Cour!$V:$V,$C23,[6]BV_Data_An_Cour!$W:$W,L$2) -> 0 | N23: =L23-F23 -> -1471.9276 | P23: =IF(O13=0,0,Q23/(O13+O15)) -> 13.778571 | Q23: =-SUMIFS([6]BV_Data_An_Prec!$O:$O,[6]BV_Data_An_Prec!$U:$U,$B23,[6]BV_Data_An_Prec!$V:$V,$C23,[6]BV_Data_An_Prec!$W:$W,Q$2) -> 771.6 | R23: =O23-K23 -> 0 | S23: =L23-Q23 -> -771.6
A24: Véhicules neufsTotal F&I | B24: Véhicules neufs | C24: Total F&I | D24: =+D15+D13 -> 50.756124 | E24: =IF(D24<=0,0,F24/D24) -> 1147 | F24: =F21+F22+F23 -> 58217.275 | J24: =+J15+J13 -> 57 | K24: =IF(J24<=0,0,L24/J24) -> 957.8093 | L24: =L21+L22+L23 -> 54595.13 | M24: =J24-D24 -> 6.2438757 | N24: =L24-F24 -> -3622.1446 | O24: =+O15+O13 -> 56 | P24: =IF(O24<=0,0,Q24/O24) -> 1189.5361 | Q24: =Q21+Q22+Q23 -> 66614.02 | S24: =L24-Q24 -> -12018.89
A25: Véhicules neufs | B25: Véhicules neufs | N25: =IF(N24=0,0,N24/F24) -> -0.062217695 | S25: =IF(Q24=0,0,(S24/Q24)) -> -0.18042583
A26: Véhicules neufs | B26: Véhicules neufs
A27: Véhicules neufsTotal Dépt. Neufs | B27: Véhicules neufs | C27: Total Dépt. Neufs | D27: =+D13+D15+D17 -> 52.607553 | E27: =IF(D27<=0,0,F27/D27) -> 3768.3425 | F27: =F13+F17+F24+F19+F15 -> 198243.28 | J27: =+J13+J15+J17 -> 59 | K27: =IF(J27<=0,0,L27/J27) -> 3481.6166 | L27: =L13+L17+L24+L19+L15 -> 205415.38 | M27: =J27-D27 -> 6.3924471 | N27: =L27-F27 -> 7172.1026 | O27: =+O13+O15+O17 -> 56 | P27: =IF(O27<=0,0,Q27/O27) -> 4933.3102 | Q27: =Q13+Q17+Q24+Q19+Q15 -> 276265.37 | R27: =J27-O27 -> 3 | S27: =L27-Q27 -> -70849.99
A28: Véhicules neufs | B28: Véhicules neufs | L28: =L27/F27 -> 1.0361783 | M28: =M27/D27 -> 0.12151196 | N28: =N27/F27 -> 0.036178289 | R28: =R27/O27 -> 0.053571429 | S28: =IF(Q27=0,0,S27/Q27) -> -0.25645628
A29: Véhicules neufs | B29: Véhicules neufs
A30: Véhicules neufsDEPENSES | B30: Véhicules neufs | C30: DEPENSES
A31: Véhicules neufsComm. vendeurs | B31: Véhicules neufs | C31: Comm. vendeurs | D31: =F31/(F15+F13+F17) -> 0.30874422 | E31: =F31/D$24 -> 781.68863 | F31: {=+INDEX('[6]Budget original'!$A$2:$AO$500,MATCH($A31,'[6]Budget original'!$A$2:$A$500,0),MATCH(F$2,'[6]Budget original'!$A$2:$AO$2,0))} -> 39675.485 | J31: =L31/(L15+L13+L17) -> 0.31879372 | K31: =IF(L31=0,0,L31/J$24) -> 771.36614 | L31: =SUMIFS([6]BV_Data_An_Cour!$O:$O,[6]BV_Data_An_Cour!$U:$U,$B31,[6]BV_Data_An_Cour!$V:$V,$C31,[6]BV_Data_An_Cour!$W:$W,L$2) -> 43967.87 | N31: =L31-F31 -> 4292.3846 | P31: =IF(Q31=0,0,Q31/O$24) -> 956.86768 | Q31: =SUMIFS([6]BV_Data_An_Prec!$O:$O,[6]BV_Data_An_Prec!$U:$U,$B31,[6]BV_Data_An_Prec!$V:$V,$C31,[6]BV_Data_An_Prec!$W:$W,Q$2) -> 53584.59 | S31: =L31-Q31 -> -9616.72
A32: Véhicules neufsComm. F&I | B32: Véhicules neufs | C32: Comm. F&I | D32: =F32/F24 -> 0.3 | E32: =F32/D$24 -> 344.1 | F32: {=+INDEX('[6]Budget original'!$A$2:$AO$500,MATCH($A32,'[6]Budget original'!$A$2:$A$500,0),MATCH(F$2,'[6]Budget original'!$A$2:$AO$2,0))} -> 17465.182 | J32: =L32/L24 -> 0.30010864 | K32: =IF(L32=0,0,L32/J$24) -> 287.44684 | L32: =SUMIFS([6]BV_Data_An_Cour!$O:$O,[6]BV_Data_An_Cour!$U:$U,$B32,[6]BV_Data_An_Cour!$V:$V,$C32,[6]BV_Data_An_Cour!$W:$W,L$2) -> 16384.47 | N32: =L32-F32 -> -1080.7124 | P32: =IF(Q32=0,0,Q32/O$24) -> 397.28393 | Q32: =SUMIFS([6]BV_Data_An_Prec!$O:$O,[6]BV_Data_An_Prec!$U:$U,$B32,[6]BV_Data_An_Prec!$V:$V,$C32,[6]BV_Data_An_Prec!$W:$W,Q$2) -> 22247.9 | S32: =L32-Q32 -> -5863.43 | U32: =(L32+L112)/(L104+L24+L19) -> 0.27062904 | V32: <<- F&A total Neuf Usagé Rachat | X32: =L24*U32 -> 14775.028 | Y32: =+L32-X32 -> 1609.4422
A33: Véhicules neufsFrais de livraison | B33: Véhicules neufs | C33: Frais de livraison | E33: =F33/D$24 -> 113.25898 | F33: {=+INDEX('[6]Budget original'!$A$2:$AO$500,MATCH($A33,'[6]Budget original'!$A$2:$A$500,0),MATCH(F$2,'[6]Budget original'!$A$2:$AO$2,0))} -> 5748.5867 | K33: =IF(L33=0,0,L33/J$24) -> 98.259649 | L33: =SUMIFS([6]BV_Data_An_Cour!$O:$O,[6]BV_Data_An_Cour!$U:$U,$B33,[6]BV_Data_An_Cour!$V:$V,$C33,[6]BV_Data_An_Cour!$W:$W,L$2) -> 5600.8 | N33: =L33-F33 -> -147.7867 | P33: =IF(Q33=0,0,Q33/O$24) -> 83.595179 | Q33: =SUMIFS([6]BV_Data_An_Prec!$O:$O,[6]BV_Data_An_Prec!$U:$U,$B33,[6]BV_Data_An_Prec!$V:$V,$C33,[6]BV_Data_An_Prec!$W:$W,Q$2) -> 4681.33 | S33: =L33-Q33 -> 919.47
A34: Véhicules neufsService gratuit 1 | B34: Véhicules neufs | C34: Service gratuit 1 | E34: =F34/D$24 -> 5.1177856 | F34: {=+INDEX('[6]Budget original'!$A$2:$AO$500,MATCH($A34,'[6]Budget original'!$A$2:$A$500,0),MATCH(F$2,'[6]Budget original'!$A$2:$AO$2,0))} -> 259.75896 | K34: =IF(L34=0,0,L34/J$24) -> 0 | L34: =SUMIFS([6]BV_Data_An_Cour!$O:$O,[6]BV_Data_An_Cour!$U:$U,$B34,[6]BV_Data_An_Cour!$V:$V,$C34,[6]BV_Data_An_Cour!$W:$W,L$2) -> 0 | N34: =L34-F34 -> -259.75896 | P34: =IF(Q34=0,0,Q34/O$24) -> 10.361964 | Q34: =SUMIFS([6]BV_Data_An_Prec!$O:$O,[6]BV_Data_An_Prec!$U:$U,$B34,[6]BV_Data_An_Prec!$V:$V,$C34,[6]BV_Data_An_Prec!$W:$W,Q$2) -> 580.27 | S34: =L34-Q34 -> -580.27
A35: Véhicules neufsEntretien stock | B35: Véhicules neufs | C35: Entretien stock | E35: =F35/D$24 -> 105.01044 | F35: {=+INDEX('[6]Budget original'!$A$2:$AO$500,MATCH($A35,'[6]Budget original'!$A$2:$A$500,0),MATCH(F$2,'[6]Budget original'!$A$2:$AO$2,0))} -> 5329.9231 | K35: =IF(L35=0,0,L35/J$24) -> 70.210526 | L35: =SUMIFS([6]BV_Data_An_Cour!$O:$O,[6]BV_Data_An_Cour!$U:$U,$B35,[6]BV_Data_An_Cour!$V:$V,$C35,[6]BV_Data_An_Cour!$W:$W,L$2) -> 4002 | N35: =L35-F35 -> -1327.9231 | P35: =IF(Q35=0,0,Q35/O$24) -> 66.075179 | Q35: =SUMIFS([6]BV_Data_An_Prec!$O:$O,[6]BV_Data_An_Prec!$U:$U,$B35,[6]BV_Data_An_Prec!$V:$V,$C35,[6]BV_Data_An_Prec!$W:$W,Q$2) -> 3700.21 | S35: =L35-Q35 -> 301.79
A36: Véhicules neufsPublicité 1 | B36: Véhicules neufs | C36: Publicité 1 | E36: =F36/D$24 -> 300.75552 | F36: {=+INDEX('[6]Budget original'!$A$2:$AO$500,MATCH($A36,'[6]Budget original'!$A$2:$A$500,0),MATCH(F$2,'[6]Budget original'!$A$2:$AO$2,0))} -> 15265.185 | K36: =IF(L36=0,0,L36/J$24) -> 122.48649 | L36: =SUMIFS([6]BV_Data_An_Cour!$O:$O,[6]BV_Data_An_Cour!$U:$U,$B36,[6]BV_Data_An_Cour!$V:$V,$C36,[6]BV_Data_An_Cour!$W:$W,L$2) -> 6981.73 | N36: =L36-F36 -> -8283.4547 | P36: =IF(Q36=0,0,Q36/O$24) -> 151.55625 | Q36: =SUMIFS([6]BV_Data_An_Prec!$O:$O,[6]BV_Data_An_Prec!$U:$U,$B36,[6]BV_Data_An_Prec!$V:$V,$C36,[6]BV_Data_An_Prec!$W:$W,Q$2) -> 8487.15 | S36: =L36-Q36 -> -1505.42
A37: Véhicules neufsIntérêt de gros | B37: Véhicules neufs | C37: Intérêt de gros | E37: =F37/D$24 -> 45.737234 | F37: {=+INDEX('[6]Budget original'!$A$2:$AO$500,MATCH($A37,'[6]Budget original'!$A$2:$A$500,0),MATCH(F$2,'[6]Budget original'!$A$2:$AO$2,0))} -> 2321.4447 | K37: =IF(L37=0,0,L37/J$24) -> 83.072632 | L37: =SUMIFS([6]BV_Data_An_Cour!$O:$O,[6]BV_Data_An_Cour!$U:$U,$B37,[6]BV_Data_An_Cour!$V:$V,$C37,[6]BV_Data_An_Cour!$W:$W,L$2) -> 4735.14 | N37: =L37-F37 -> 2413.6953 | P37: =IF(Q37=0,0,Q37/O$24) -> 4.1001786 | Q37: =SUMIFS([6]BV_Data_An_Prec!$O:$O,[6]BV_Data_An_Prec!$U:$U,$B37,[6]BV_Data_An_Prec!$V:$V,$C37,[6]BV_Data_An_Prec!$W:$W,Q$2) -> 229.61 | S37: =L37-Q37 -> 4505.53
A38: Véhicules neufs[...] | B38: Véhicules neufs | C38: [...] | E38: =F38/D$24 -> 0 | F38: {=+INDEX('[6]Budget original'!$A$2:$AO$500,MATCH($A38,'[6]Budget original'!$A$2:$A$500,0),MATCH(F$2,'[6]Budget original'!$A$2:$AO$2,0))} -> 0 | K38: =IF(L38=0,0,L38/J$24) -> 0 | L38: =SUMIFS([6]BV_Data_An_Cour!$O:$O,[6]BV_Data_An_Cour!$U:$U,$B38,[6]BV_Data_An_Cour!$V:$V,$C38,[6]BV_Data_An_Cour!$W:$W,L$2) -> 0 | N38: =L38-F38 -> 0 | P38: =IF(Q38=0,0,Q38/O$24) -> 0 | Q38: =SUMIFS([6]BV_Data_An_Prec!$O:$O,[6]BV_Data_An_Prec!$U:$U,$B38,[6]BV_Data_An_Prec!$V:$V,$C38,[6]BV_Data_An_Prec!$W:$W,Q$2) -> 0 | S38: =L38-Q38 -> 0
A39: Véhicules neufs[...] | B39: Véhicules neufs | C39: [...] | E39: =F39/D$24 -> 0 | F39: {=+INDEX('[6]Budget original'!$A$2:$AO$500,MATCH($A39,'[6]Budget original'!$A$2:$A$500,0),MATCH(F$2,'[6]Budget original'!$A$2:$AO$2,0))} -> 0 | K39: =IF(L39=0,0,L39/J$24) -> 0 | L39: =SUMIFS([6]BV_Data_An_Cour!$O:$O,[6]BV_Data_An_Cour!$U:$U,$B39,[6]BV_Data_An_Cour!$V:$V,$C39,[6]BV_Data_An_Cour!$W:$W,L$2) -> 0 | N39: =L39-F39 -> 0 | P39: =IF(Q39=0,0,Q39/O$24) -> 0 | Q39: =SUMIFS([6]BV_Data_An_Prec!$O:$O,[6]BV_Data_An_Prec!$U:$U,$B39,[6]BV_Data_An_Prec!$V:$V,$C39,[6]BV_Data_An_Prec!$W:$W,Q$2) -> 0 | S39: =L39-Q39 -> 0
A40: Véhicules neufs[...] | B40: Véhicules neufs | C40: [...] | E40: =F40/D$24 -> 0 | F40: {=+INDEX('[6]Budget original'!$A$2:$AO$500,MATCH($A40,'[6]Budget original'!$A$2:$A$500,0),MATCH(F$2,'[6]Budget original'!$A$2:$AO$2,0))} -> 0 | K40: =IF(L40=0,0,L40/J$24) -> 0 | L40: =SUMIFS([6]BV_Data_An_Cour!$O:$O,[6]BV_Data_An_Cour!$U:$U,$B40,[6]BV_Data_An_Cour!$V:$V,$C40,[6]BV_Data_An_Cour!$W:$W,L$2) -> 0 | N40: =L40-F40 -> 0 | P40: =IF(Q40=0,0,Q40/O$24) -> 0 | Q40: =SUMIFS([6]BV_Data_An_Prec!$O:$O,[6]BV_Data_An_Prec!$U:$U,$B40,[6]BV_Data_An_Prec!$V:$V,$C40,[6]BV_Data_An_Prec!$W:$W,Q$2) -> 0 | S40: =L40-Q40 -> 0
A41: Véhicules neufsTOTAL VARIABLES | B41: Véhicules neufs | C41: TOTAL VARIABLES | D41: % brut | E41: =F41/F$27 -> 0.43414116 | F41: =SUM(F31:F40) -> 86065.566 | J41: % brut | K41: =L41/L$27 -> 0.39759443 | L41: =SUM(L31:L40) -> 81672.01 | N41: =L41-F41 -> -4393.556 | O41: % brut | P41: =Q41/Q$27 -> 0.33848274 | Q41: =SUM(Q31:Q40) -> 93511.06 | S41: =L41-Q41 -> -11839.05
A42: Véhicules neufsSalaires cadres | B42: Véhicules neufs | C42: Salaires cadres | F42: {=+INDEX('[6]Budget original'!$A$2:$AO$500,MATCH($A42,'[6]Budget original'!$A$2:$A$500,0),MATCH(F$2,'[6]Budget original'!$A$2:$AO$2,0))} -> 17292.497 | L42: =SUMIFS([6]BV_Data_An_Cour!$O:$O,[6]BV_Data_An_Cour!$U:$U,$B42,[6]BV_Data_An_Cour!$V:$V,$C42,[6]BV_Data_An_Cour!$W:$W,L$2) -> 13776.33 | N42: =L42-F42 -> -3516.1666 | Q42: =SUMIFS([6]BV_Data_An_Prec!$O:$O,[6]BV_Data_An_Prec!$U:$U,$B42,[6]BV_Data_An_Prec!$V:$V,$C42,[6]BV_Data_An_Prec!$W:$W,Q$2) -> 17258.29 | S42: =L42-Q42 -> -3481.96
A43: Véhicules neufsSalaires commis | B43: Véhicules neufs | C43: Salaires commis | F43: {=+INDEX('[6]Budget original'!$A$2:$AO$500,MATCH($A43,'[6]Budget original'!$A$2:$A$500,0),MATCH(F$2,'[6]Budget original'!$A$2:$AO$2,0))} -> 10224.637 | L43: =SUMIFS([6]BV_Data_An_Cour!$O:$O,[6]BV_Data_An_Cour!$U:$U,$B43,[6]BV_Data_An_Cour!$V:$V,$C43,[6]BV_Data_An_Cour!$W:$W,L$2) -> 14509.06 | N43: =L43-F43 -> 4284.4228 | Q43: =SUMIFS([6]BV_Data_An_Prec!$O:$O,[6]BV_Data_An_Prec!$U:$U,$B43,[6]BV_Data_An_Prec!$V:$V,$C43,[6]BV_Data_An_Prec!$W:$W,Q$2) -> 7489.24 | S43: =L43-Q43 -> 7019.82
A44: Véhicules neufsSalaires autres | B44: Véhicules neufs | C44: Salaires autres | F44: {=+INDEX('[6]Budget original'!$A$2:$AO$500,MATCH($A44,'[6]Budget original'!$A$2:$A$500,0),MATCH(F$2,'[6]Budget original'!$A$2:$AO$2,0))} -> 8208.9839 | L44: =SUMIFS([6]BV_Data_An_Cour!$O:$O,[6]BV_Data_An_Cour!$U:$U,$B44,[6]BV_Data_An_Cour!$V:$V,$C44,[6]BV_Data_An_Cour!$W:$W,L$2) -> 13387.76 | N44: =L44-F44 -> 5178.7761 | Q44: =SUMIFS([6]BV_Data_An_Prec!$O:$O,[6]BV_Data_An_Prec!$U:$U,$B44,[6]BV_Data_An_Prec!$V:$V,$C44,[6]BV_Data_An_Prec!$W:$W,Q$2) -> 3923.31 | S44: =L44-Q44 -> 9464.45
A45: Véhicules neufsSalaires spécialistes | B45: Véhicules neufs | C45: Salaires spécialistes | F45: {=+INDEX('[6]Budget original'!$A$2:$AO$500,MATCH($A45,'[6]Budget original'!$A$2:$A$500,0),MATCH(F$2,'[6]Budget original'!$A$2:$AO$2,0))} -> 0 | L45: =SUMIFS([6]BV_Data_An_Cour!$O:$O,[6]BV_Data_An_Cour!$U:$U,$B45,[6]BV_Data_An_Cour!$V:$V,$C45,[6]BV_Data_An_Cour!$W:$W,L$2) -> 0 | N45: =L45-F45 -> 0 | Q45: =SUMIFS([6]BV_Data_An_Prec!$O:$O,[6]BV_Data_An_Prec!$U:$U,$B45,[6]BV_Data_An_Prec!$V:$V,$C45,[6]BV_Data_An_Prec!$W:$W,Q$2) -> 0 | S45: =L45-Q45 -> 0
A46: Véhicules neufs[...] | B46: Véhicules neufs | C46: [...] | F46: {=+INDEX('[6]Budget original'!$A$2:$AO$500,MATCH($A46,'[6]Budget original'!$A$2:$A$500,0),MATCH(F$2,'[6]Budget original'!$A$2:$AO$2,0))} -> 0 | L46: =SUMIFS([6]BV_Data_An_Cour!$O:$O,[6]BV_Data_An_Cour!$U:$U,$B46,[6]BV_Data_An_Cour!$V:$V,$C46,[6]BV_Data_An_Cour!$W:$W,L$2) -> 0 | N46: =L46-F46 -> 0 | Q46: =SUMIFS([6]BV_Data_An_Prec!$O:$O,[6]BV_Data_An_Prec!$U:$U,$B46,[6]BV_Data_An_Prec!$V:$V,$C46,[6]BV_Data_An_Prec!$W:$W,Q$2) -> 0 | S46: =L46-Q46 -> 0
A47: Véhicules neufs[...] | B47: Véhicules neufs | C47: [...] | F47: {=+INDEX('[6]Budget original'!$A$2:$AO$500,MATCH($A47,'[6]Budget original'!$A$2:$A$500,0),MATCH(F$2,'[6]Budget original'!$A$2:$AO$2,0))} -> 0 | L47: =SUMIFS([6]BV_Data_An_Cour!$O:$O,[6]BV_Data_An_Cour!$U:$U,$B47,[6]BV_Data_An_Cour!$V:$V,$C47,[6]BV_Data_An_Cour!$W:$W,L$2) -> 0 | N47: =L47-F47 -> 0 | Q47: =SUMIFS([6]BV_Data_An_Prec!$O:$O,[6]BV_Data_An_Prec!$U:$U,$B47,[6]BV_Data_An_Prec!$V:$V,$C47,[6]BV_Data_An_Prec!$W:$W,Q$2) -> 0 | S47: =L47-Q47 -> 0
A48: Véhicules neufs[...] | B48: Véhicules neufs | C48: [...] | F48: {=+INDEX('[6]Budget original'!$A$2:$AO$500,MATCH($A48,'[6]Budget original'!$A$2:$A$500,0),MATCH(F$2,'[6]Budget original'!$A$2:$AO$2,0))} -> 0 | L48: =SUMIFS([6]BV_Data_An_Cour!$O:$O,[6]BV_Data_An_Cour!$U:$U,$B48,[6]BV_Data_An_Cour!$V:$V,$C48,[6]BV_Data_An_Cour!$W:$W,L$2) -> 0 | N48: =L48-F48 -> 0 | Q48: =SUMIFS([6]BV_Data_An_Prec!$O:$O,[6]BV_Data_An_Prec!$U:$U,$B48,[6]BV_Data_An_Prec!$V:$V,$C48,[6]BV_Data_An_Prec!$W:$W,Q$2) -> 0 | S48: =L48-Q48 -> 0
A49: Véhicules neufsSalaires en absences | B49: Véhicules neufs | C49: Salaires en absences | F49: {=+INDEX('[6]Budget original'!$A$2:$AO$500,MATCH($A49,'[6]Budget original'!$A$2:$A$500,0),MATCH(F$2,'[6]Budget original'!$A$2:$AO$2,0))} -> 11279.397 | L49: =SUMIFS([6]BV_Data_An_Cour!$O:$O,[6]BV_Data_An_Cour!$U:$U,$B49,[6]BV_Data_An_Cour!$V:$V,$C49,[6]BV_Data_An_Cour!$W:$W,L$2) -> 12929.12 | N49: =L49-F49 -> 1649.7231 | Q49: =SUMIFS([6]BV_Data_An_Prec!$O:$O,[6]BV_Data_An_Prec!$U:$U,$B49,[6]BV_Data_An_Prec!$V:$V,$C49,[6]BV_Data_An_Prec!$W:$W,Q$2) -> 17407.08 | S49: =L49-Q49 -> -4477.96
A50: Véhicules neufsDéduction à la source | B50: Véhicules neufs | C50: Déduction à la source | F50: {=+INDEX('[6]Budget original'!$A$2:$AO$500,MATCH($A50,'[6]Budget original'!$A$2:$A$500,0),MATCH(F$2,'[6]Budget original'!$A$2:$AO$2,0))} -> 11212.831 | L50: =SUMIFS([6]BV_Data_An_Cour!$O:$O,[6]BV_Data_An_Cour!$U:$U,$B50,[6]BV_Data_An_Cour!$V:$V,$C50,[6]BV_Data_An_Cour!$W:$W,L$2) -> 12404.94 | N50: =L50-F50 -> 1192.1089 | Q50: =SUMIFS([6]BV_Data_An_Prec!$O:$O,[6]BV_Data_An_Prec!$U:$U,$B50,[6]BV_Data_An_Prec!$V:$V,$C50,[6]BV_Data_An_Prec!$W:$W,Q$2) -> 20529.61 | S50: =L50-Q50 -> -8124.67
A51: Véhicules neufsBénéfices marginaux | B51: Véhicules neufs | C51: Bénéfices marginaux | F51: {=+INDEX('[6]Budget original'!$A$2:$AO$500,MATCH($A51,'[6]Budget original'!$A$2:$A$500,0),MATCH(F$2,'[6]Budget original'!$A$2:$AO$2,0))} -> 7851.8751 | L51: =SUMIFS([6]BV_Data_An_Cour!$O:$O,[6]BV_Data_An_Cour!$U:$U,$B51,[6]BV_Data_An_Cour!$V:$V,$C51,[6]BV_Data_An_Cour!$W:$W,L$2) -> 5591.61 | N51: =L51-F51 -> -2260.2651 | Q51: =SUMIFS([6]BV_Data_An_Prec!$O:$O,[6]BV_Data_An_Prec!$U:$U,$B51,[6]BV_Data_An_Prec!$V:$V,$C51,[6]BV_Data_An_Prec!$W:$W,Q$2) -> 8891.51 | S51: =L51-Q51 -> -3299.9
A52: Véhicules neufsCsst | B52: Véhicules neufs | C52: Csst | F52: {=+INDEX('[6]Budget original'!$A$2:$AO$500,MATCH($A52,'[6]Budget original'!$A$2:$A$500,0),MATCH(F$2,'[6]Budget original'!$A$2:$AO$2,0))} -> 3751.067 | L52: =SUMIFS([6]BV_Data_An_Cour!$O:$O,[6]BV_Data_An_Cour!$U:$U,$B52,[6]BV_Data_An_Cour!$V:$V,$C52,[6]BV_Data_An_Cour!$W:$W,L$2) -> 3273.76 | N52: =L52-F52 -> -477.30704 | Q52: =SUMIFS([6]BV_Data_An_Prec!$O:$O,[6]BV_Data_An_Prec!$U:$U,$B52,[6]BV_Data_An_Prec!$V:$V,$C52,[6]BV_Data_An_Prec!$W:$W,Q$2) -> 6026.16 | S52: =L52-Q52 -> -2752.4
A53: Véhicules neufs[...] | B53: Véhicules neufs | C53: [...] | F53: {=+INDEX('[6]Budget original'!$A$2:$AO$500,MATCH($A53,'[6]Budget original'!$A$2:$A$500,0),MATCH(F$2,'[6]Budget original'!$A$2:$AO$2,0))} -> 0 | L53: =SUMIFS([6]BV_Data_An_Cour!$O:$O,[6]BV_Data_An_Cour!$U:$U,$B53,[6]BV_Data_An_Cour!$V:$V,$C53,[6]BV_Data_An_Cour!$W:$W,L$2) -> 0 | N53: =L53-F53 -> 0 | Q53: =SUMIFS([6]BV_Data_An_Prec!$O:$O,[6]BV_Data_An_Prec!$U:$U,$B53,[6]BV_Data_An_Prec!$V:$V,$C53,[6]BV_Data_An_Prec!$W:$W,Q$2) -> 0 | S53: =L53-Q53 -> 0
A54: Véhicules neufsTOTAL PERSONNEL | B54: Véhicules neufs | C54: TOTAL PERSONNEL | D54: % brut | E54: =F54/F$27 -> 0.35220003 | F54: =+SUM(F42:F53) -> 69821.288 | J54: % brut | K54: =L54/L$27 -> 0.36936173 | L54: =+SUM(L42:L53) -> 75872.58 | N54: =+SUM(N42:N53) -> 6051.2921 | O54: % brut | P54: =Q54/Q$27 -> 0.29509743 | Q54: =+SUM(Q42:Q53) -> 81525.2 | S54: =+SUM(S42:S53) -> -5652.62
A55: Véhicules neufsPublicité 2 | B55: Véhicules neufs | C55: Publicité 2 | F55: {=+INDEX('[6]Budget original'!$A$2:$AO$500,MATCH($A55,'[6]Budget original'!$A$2:$A$500,0),MATCH(F$2,'[6]Budget original'!$A$2:$AO$2,0))} -> 0 | L55: =SUMIFS([6]BV_Data_An_Cour!$O:$O,[6]BV_Data_An_Cour!$U:$U,$B55,[6]BV_Data_An_Cour!$V:$V,$C55,[6]BV_Data_An_Cour!$W:$W,L$2) -> 0 | N55: =L55-F55 -> 0 | Q55: =SUMIFS([6]BV_Data_An_Prec!$O:$O,[6]BV_Data_An_Prec!$U:$U,$B55,[6]BV_Data_An_Prec!$V:$V,$C55,[6]BV_Data_An_Prec!$W:$W,Q$2) -> 0 | S55: =L55-Q55 -> 0
A56: Véhicules neufsService gratuit 2 | B56: Véhicules neufs | C56: Service gratuit 2 | F56: {=+INDEX('[6]Budget original'!$A$2:$AO$500,MATCH($A56,'[6]Budget original'!$A$2:$A$500,0),MATCH(F$2,'[6]Budget original'!$A$2:$AO$2,0))} -> 0 | L56: =SUMIFS([6]BV_Data_An_Cour!$O:$O,[6]BV_Data_An_Cour!$U:$U,$B56,[6]BV_Data_An_Cour!$V:$V,$C56,[6]BV_Data_An_Cour!$W:$W,L$2) -> 0 | N56: =L56-F56 -> 0 | Q56: =SUMIFS([6]BV_Data_An_Prec!$O:$O,[6]BV_Data_An_Prec!$U:$U,$B56,[6]BV_Data_An_Prec!$V:$V,$C56,[6]BV_Data_An_Prec!$W:$W,Q$2) -> 0 | S56: =L56-Q56 -> 0
A57: Véhicules neufsFrais véhicules de cie | B57: Véhicules neufs | C57: Frais véhicules de cie | F57: {=+INDEX('[6]Budget original'!$A$2:$AO$500,MATCH($A57,'[6]Budget original'!$A$2:$A$500,0),MATCH(F$2,'[6]Budget original'!$A$2:$AO$2,0))} -> 7945.8333 | L57: =SUMIFS([6]BV_Data_An_Cour!$O:$O,[6]BV_Data_An_Cour!$U:$U,$B57,[6]BV_Data_An_Cour!$V:$V,$C57,[6]BV_Data_An_Cour!$W:$W,L$2) -> 5916.23 | N57: =L57-F57 -> -2029.6033 | Q57: =SUMIFS([6]BV_Data_An_Prec!$O:$O,[6]BV_Data_An_Prec!$U:$U,$B57,[6]BV_Data_An_Prec!$V:$V,$C57,[6]BV_Data_An_Prec!$W:$W,Q$2) -> 8324.85 | S57: =L57-Q57 -> -2408.62
A58: Véhicules neufsInformatique | B58: Véhicules neufs | C58: Informatique | F58: {=+INDEX('[6]Budget original'!$A$2:$AO$500,MATCH($A58,'[6]Budget original'!$A$2:$A$500,0),MATCH(F$2,'[6]Budget original'!$A$2:$AO$2,0))} -> 6260.8664 | L58: =SUMIFS([6]BV_Data_An_Cour!$O:$O,[6]BV_Data_An_Cour!$U:$U,$B58,[6]BV_Data_An_Cour!$V:$V,$C58,[6]BV_Data_An_Cour!$W:$W,L$2) -> 7019.75 | N58: =L58-F58 -> 758.8836 | Q58: =SUMIFS([6]BV_Data_An_Prec!$O:$O,[6]BV_Data_An_Prec!$U:$U,$B58,[6]BV_Data_An_Prec!$V:$V,$C58,[6]BV_Data_An_Prec!$W:$W,Q$2) -> 7033.71 | S58: =L58-Q58 -> -13.96
A59: Véhicules neufsFrais de déplacement | B59: Véhicules neufs | C59: Frais de déplacement | F59: {=+INDEX('[6]Budget original'!$A$2:$AO$500,MATCH($A59,'[6]Budget original'!$A$2:$A$500,0),MATCH(F$2,'[6]Budget original'!$A$2:$AO$2,0))} -> 1000.088 | L59: =SUMIFS([6]BV_Data_An_Cour!$O:$O,[6]BV_Data_An_Cour!$U:$U,$B59,[6]BV_Data_An_Cour!$V:$V,$C59,[6]BV_Data_An_Cour!$W:$W,L$2) -> 504.08 | N59: =L59-F59 -> -496.00804 | Q59: =SUMIFS([6]BV_Data_An_Prec!$O:$O,[6]BV_Data_An_Prec!$U:$U,$B59,[6]BV_Data_An_Prec!$V:$V,$C59,[6]BV_Data_An_Prec!$W:$W,Q$2) -> 2502.76 | S59: =L59-Q59 -> -1998.68
A60: Véhicules neufsServices extérieurs | B60: Véhicules neufs | C60: Services extérieurs | F60: {=+INDEX('[6]Budget original'!$A$2:$AO$500,MATCH($A60,'[6]Budget original'!$A$2:$A$500,0),MATCH(F$2,'[6]Budget original'!$A$2:$AO$2,0))} -> 6901.1637 | L60: =SUMIFS([6]BV_Data_An_Cour!$O:$O,[6]BV_Data_An_Cour!$U:$U,$B60,[6]BV_Data_An_Cour!$V:$V,$C60,[6]BV_Data_An_Cour!$W:$W,L$2) -> 6175.67 | N60: =L60-F60 -> -725.49373 | Q60: =SUMIFS([6]BV_Data_An_Prec!$O:$O,[6]BV_Data_An_Prec!$U:$U,$B60,[6]BV_Data_An_Prec!$V:$V,$C60,[6]BV_Data_An_Prec!$W:$W,Q$2) -> 7293.4 | S60: =L60-Q60 -> -1117.73
A61: Véhicules neufsFournitures autres | B61: Véhicules neufs | C61: Fournitures autres | F61: {=+INDEX('[6]Budget original'!$A$2:$AO$500,MATCH($A61,'[6]Budget original'!$A$2:$A$500,0),MATCH(F$2,'[6]Budget original'!$A$2:$AO$2,0))} -> 119.79022 | L61: =SUMIFS([6]BV_Data_An_Cour!$O:$O,[6]BV_Data_An_Cour!$U:$U,$B61,[6]BV_Data_An_Cour!$V:$V,$C61,[6]BV_Data_An_Cour!$W:$W,L$2) -> 0 | N61: =L61-F61 -> -119.79022 | Q61: =SUMIFS([6]BV_Data_An_Prec!$O:$O,[6]BV_Data_An_Prec!$U:$U,$B61,[6]BV_Data_An_Prec!$V:$V,$C61,[6]BV_Data_An_Prec!$W:$W,Q$2) -> 0 | S61: =L61-Q61 -> 0
A62: Véhicules neufsUniformes | B62: Véhicules neufs | C62: Uniformes | F62: {=+INDEX('[6]Budget original'!$A$2:$AO$500,MATCH($A62,'[6]Budget original'!$A$2:$A$500,0),MATCH(F$2,'[6]Budget original'!$A$2:$AO$2,0))} -> 61.858303 | L62: =SUMIFS([6]BV_Data_An_Cour!$O:$O,[6]BV_Data_An_Cour!$U:$U,$B62,[6]BV_Data_An_Cour!$V:$V,$C62,[6]BV_Data_An_Cour!$W:$W,L$2) -> 0 | N62: =L62-F62 -> -61.858303 | Q62: =SUMIFS([6]BV_Data_An_Prec!$O:$O,[6]BV_Data_An_Prec!$U:$U,$B62,[6]BV_Data_An_Prec!$V:$V,$C62,[6]BV_Data_An_Prec!$W:$W,Q$2) -> 0 | S62: =L62-Q62 -> 0
A63: Véhicules neufsPapeterie | B63: Véhicules neufs | C63: Papeterie | F63: {=+INDEX('[6]Budget original'!$A$2:$AO$500,MATCH($A63,'[6]Budget original'!$A$2:$A$500,0),MATCH(F$2,'[6]Budget original'!$A$2:$AO$2,0))} -> 763.45104 | L63: =SUMIFS([6]BV_Data_An_Cour!$O:$O,[6]BV_Data_An_Cour!$U:$U,$B63,[6]BV_Data_An_Cour!$V:$V,$C63,[6]BV_Data_An_Cour!$W:$W,L$2) -> 605.81 | N63: =L63-F63 -> -157.64104 | Q63: =SUMIFS([6]BV_Data_An_Prec!$O:$O,[6]BV_Data_An_Prec!$U:$U,$B63,[6]BV_Data_An_Prec!$V:$V,$C63,[6]BV_Data_An_Prec!$W:$W,Q$2) -> 472.5 | S63: =L63-Q63 -> 133.31
A64: Véhicules neufsTéléphone | B64: Véhicules neufs | C64: Téléphone | F64: {=+INDEX('[6]Budget original'!$A$2:$AO$500,MATCH($A64,'[6]Budget original'!$A$2:$A$500,0),MATCH(F$2,'[6]Budget original'!$A$2:$AO$2,0))} -> 258.72025 | L64: =SUMIFS([6]BV_Data_An_Cour!$O:$O,[6]BV_Data_An_Cour!$U:$U,$B64,[6]BV_Data_An_Cour!$V:$V,$C64,[6]BV_Data_An_Cour!$W:$W,L$2) -> 232.9 | N64: =L64-F64 -> -25.82025 | Q64: =SUMIFS([6]BV_Data_An_Prec!$O:$O,[6]BV_Data_An_Prec!$U:$U,$B64,[6]BV_Data_An_Prec!$V:$V,$C64,[6]BV_Data_An_Prec!$W:$W,Q$2) -> 394.79 | S64: =L64-Q64 -> -161.89
A65: Véhicules neufsFrais postaux | B65: Véhicules neufs | C65: Frais postaux | F65: {=+INDEX('[6]Budget original'!$A$2:$AO$500,MATCH($A65,'[6]Budget original'!$A$2:$A$500,0),MATCH(F$2,'[6]Budget original'!$A$2:$AO$2,0))} -> 123.74429 | L65: =SUMIFS([6]BV_Data_An_Cour!$O:$O,[6]BV_Data_An_Cour!$U:$U,$B65,[6]BV_Data_An_Cour!$V:$V,$C65,[6]BV_Data_An_Cour!$W:$W,L$2) -> 81.84 | N65: =L65-F65 -> -41.904294 | Q65: =SUMIFS([6]BV_Data_An_Prec!$O:$O,[6]BV_Data_An_Prec!$U:$U,$B65,[6]BV_Data_An_Prec!$V:$V,$C65,[6]BV_Data_An_Prec!$W:$W,Q$2) -> 112.03 | S65: =L65-Q65 -> -30.19
A66: Véhicules neufsDivers | B66: Véhicules neufs | C66: Divers | F66: {=+INDEX('[6]Budget original'!$A$2:$AO$500,MATCH($A66,'[6]Budget original'!$A$2:$A$500,0),MATCH(F$2,'[6]Budget original'!$A$2:$AO$2,0))} -> 470.18236 | L66: =SUMIFS([6]BV_Data_An_Cour!$O:$O,[6]BV_Data_An_Cour!$U:$U,$B66,[6]BV_Data_An_Cour!$V:$V,$C66,[6]BV_Data_An_Cour!$W:$W,L$2) -> 111.34 | N66: =L66-F66 -> -358.84236 | Q66: =SUMIFS([6]BV_Data_An_Prec!$O:$O,[6]BV_Data_An_Prec!$U:$U,$B66,[6]BV_Data_An_Prec!$V:$V,$C66,[6]BV_Data_An_Prec!$W:$W,Q$2) -> 238.3 | S66: =L66-Q66 -> -126.96
A67: Véhicules neufsFormation | B67: Véhicules neufs | C67: Formation | F67: {=+INDEX('[6]Budget original'!$A$2:$AO$500,MATCH($A67,'[6]Budget original'!$A$2:$A$500,0),MATCH(F$2,'[6]Budget original'!$A$2:$AO$2,0))} -> 612.7403 | L67: =SUMIFS([6]BV_Data_An_Cour!$O:$O,[6]BV_Data_An_Cour!$U:$U,$B67,[6]BV_Data_An_Cour!$V:$V,$C67,[6]BV_Data_An_Cour!$W:$W,L$2) -> 487.93 | N67: =L67-F67 -> -124.8103 | Q67: =SUMIFS([6]BV_Data_An_Prec!$O:$O,[6]BV_Data_An_Prec!$U:$U,$B67,[6]BV_Data_An_Prec!$V:$V,$C67,[6]BV_Data_An_Prec!$W:$W,Q$2) -> 1444.75 | S67: =L67-Q67 -> -956.82
A68: Véhicules neufsFrais bancaires | B68: Véhicules neufs | C68: Frais bancaires | F68: {=+INDEX('[6]Budget original'!$A$2:$AO$500,MATCH($A68,'[6]Budget original'!$A$2:$A$500,0),MATCH(F$2,'[6]Budget original'!$A$2:$AO$2,0))} -> 1204.8888 | L68: =SUMIFS([6]BV_Data_An_Cour!$O:$O,[6]BV_Data_An_Cour!$U:$U,$B68,[6]BV_Data_An_Cour!$V:$V,$C68,[6]BV_Data_An_Cour!$W:$W,L$2) -> 3537.15 | N68: =L68-F68 -> 2332.2612 | Q68: =AL447*W3 -> 3064.9995 | S68: =L68-Q68 -> 472.1505
A69: Véhicules neufs[...] | B69: Véhicules neufs | C69: [...] | F69: {=+INDEX('[6]Budget original'!$A$2:$AO$500,MATCH($A69,'[6]Budget original'!$A$2:$A$500,0),MATCH(F$2,'[6]Budget original'!$A$2:$AO$2,0))} -> 0 | N69: =L69-F69 -> 0 | Q69: =SUMIFS([6]BV_Data_An_Prec!$O:$O,[6]BV_Data_An_Prec!$U:$U,$B69,[6]BV_Data_An_Prec!$V:$V,$C69,[6]BV_Data_An_Prec!$W:$W,Q$2) -> 0 | S69: =L69-Q69 -> 0
A70: Véhicules neufs[...] | B70: Véhicules neufs | C70: [...] | F70: {=+INDEX('[6]Budget original'!$A$2:$AO$500,MATCH($A70,'[6]Budget original'!$A$2:$A$500,0),MATCH(F$2,'[6]Budget original'!$A$2:$AO$2,0))} -> 0 | L70: =SUMIFS([6]BV_Data_An_Cour!$O:$O,[6]BV_Data_An_Cour!$U:$U,$B70,[6]BV_Data_An_Cour!$V:$V,$C70,[6]BV_Data_An_Cour!$W:$W,L$2) -> 0 | N70: =L70-F70 -> 0 | Q70: =SUMIFS([6]BV_Data_An_Prec!$O:$O,[6]BV_Data_An_Prec!$U:$U,$B70,[6]BV_Data_An_Prec!$V:$V,$C70,[6]BV_Data_An_Prec!$W:$W,Q$2) -> 0 | S70: =L70-Q70 -> 0
A71: Véhicules neufs[...] | B71: Véhicules neufs | C71: [...] | F71: {=+INDEX('[6]Budget original'!$A$2:$AO$500,MATCH($A71,'[6]Budget original'!$A$2:$A$500,0),MATCH(F$2,'[6]Budget original'!$A$2:$AO$2,0))} -> 0 | L71: =SUMIFS([6]BV_Data_An_Cour!$O:$O,[6]BV_Data_An_Cour!$U:$U,$B71,[6]BV_Data_An_Cour!$V:$V,$C71,[6]BV_Data_An_Cour!$W:$W,L$2)*0.32 -> 0 | N71: =L71-F71 -> 0 | Q71: =SUMIFS([6]BV_Data_An_Prec!$O:$O,[6]BV_Data_An_Prec!$U:$U,$B71,[6]BV_Data_An_Prec!$V:$V,$C71,[6]BV_Data_An_Prec!$W:$W,Q$2)*0.32 -> 0 | S71: =L71-Q71 -> 0
A72: Véhicules neufsTOTAL SEMI-FIXES | B72: Véhicules neufs | C72: TOTAL SEMI-FIXES | D72: % brut | E72: =F72/F$27 -> 0.12975637 | F72: =+SUM(F55:F71) -> 25723.327 | J72: % brut | K72: =L72/L$27 -> 0.12011126 | L72: =+SUM(L55:L71) -> 24672.7 | N72: =+SUM(N55:N71) -> -1050.6271 | O72: % brut | P72: =Q72/Q$27 -> 0.11178415 | Q72: =+SUM(Q55:Q71) -> 30882.09 | S72: =+SUM(S55:S71) -> -6209.3895
A73: Véhicules neufs | B73: Véhicules neufs
A74: Véhicules neufsTOTAL DES DÉPENSES | B74: Véhicules neufs | C74: TOTAL DES DÉPENSES | D74: % brut | E74: =F74/F$27 -> 0.91609755 | F74: =F41+F54+F72 -> 181610.18 | J74: % brut | K74: =L74/L$27 -> 0.88706741 | L74: =L41+L54+L72 -> 182217.29 | N74: =L74-F74 -> 607.10906 | O74: % brut | P74: =Q74/Q$27 -> 0.74536432 | Q74: =Q41+Q54+Q72 -> 205918.35 | S74: =L74-Q74 -> -23701.06
A75: Véhicules neufsProgramme neuf 1 | B75: Véhicules neufs | C75: Programme neuf 1 | F75: {=+INDEX('[6]Budget original'!$A$2:$AO$500,MATCH($A75,'[6]Budget original'!$A$2:$A$500,0),MATCH(F$2,'[6]Budget original'!$A$2:$AO$2,0))} -> 16584.69 | L75: =-SUMIFS([6]BV_Data_An_Cour!$O:$O,[6]BV_Data_An_Cour!$U:$U,$B75,[6]BV_Data_An_Cour!$V:$V,$C75,[6]BV_Data_An_Cour!$W:$W,L$2)-L155 -> 0 | N75: =L75-F75 -> -16584.69 | Q75: =-SUMIFS([6]BV_Data_An_Prec!$O:$O,[6]BV_Data_An_Prec!$U:$U,$B75,[6]BV_Data_An_Prec!$V:$V,$C75,[6]BV_Data_An_Prec!$W:$W,Q$2) -> 22000
A76: Véhicules neufsProgramme neuf 2 | B76: Véhicules neufs | C76: Programme neuf 2 | F76: {=+INDEX('[6]Budget original'!$A$2:$AO$500,MATCH($A76,'[6]Budget original'!$A$2:$A$500,0),MATCH(F$2,'[6]Budget original'!$A$2:$AO$2,0))} -> 0 | L76: =-SUMIFS([6]BV_Data_An_Cour!$O:$O,[6]BV_Data_An_Cour!$U:$U,$B76,[6]BV_Data_An_Cour!$V:$V,$C76,[6]BV_Data_An_Cour!$W:$W,L$2) -> 0 | N76: =L76-F76 -> 0 | Q76: =-SUMIFS([6]BV_Data_An_Prec!$O:$O,[6]BV_Data_An_Prec!$U:$U,$B76,[6]BV_Data_An_Prec!$V:$V,$C76,[6]BV_Data_An_Prec!$W:$W,Q$2) -> 0 | S76: =L76-Q76 -> 0
A77: Véhicules neufsProgramme neuf 3 | B77: Véhicules neufs | C77: Programme neuf 3 | F77: {=+INDEX('[6]Budget original'!$A$2:$AO$500,MATCH($A77,'[6]Budget original'!$A$2:$A$500,0),MATCH(F$2,'[6]Budget original'!$A$2:$AO$2,0))} -> 0 | L77: =-SUMIFS([6]BV_Data_An_Cour!$O:$O,[6]BV_Data_An_Cour!$U:$U,$B77,[6]BV_Data_An_Cour!$V:$V,$C77,[6]BV_Data_An_Cour!$W:$W,L$2) -> 0 | N77: =L77-F77 -> 0 | Q77: =-SUMIFS([6]BV_Data_An_Prec!$O:$O,[6]BV_Data_An_Prec!$U:$U,$B77,[6]BV_Data_An_Prec!$V:$V,$C77,[6]BV_Data_An_Prec!$W:$W,Q$2) -> 0 | S77: =L77-Q77 -> 0
A78: Véhicules neufsHoldbacks | B78: Véhicules neufs | C78: Holdbacks | E78: =+F78/D24 -> 1181.3417 | F78: {=+INDEX('[6]Budget original'!$A$2:$AO$500,MATCH($A78,'[6]Budget original'!$A$2:$A$500,0),MATCH(F$2,'[6]Budget original'!$A$2:$AO$2,0))} -> 59960.327 | K78: =+L78/J24 -> 1113.5009 | L78: =-SUMIFS([6]BV_Data_An_Cour!$O:$O,[6]BV_Data_An_Cour!$U:$U,$B78,[6]BV_Data_An_Cour!$V:$V,$C78,[6]BV_Data_An_Cour!$W:$W,L$2) -> 63469.55 | N78: =L78-F78 -> 3509.2229 | Q78: =-SUMIFS([6]BV_Data_An_Prec!$O:$O,[6]BV_Data_An_Prec!$U:$U,$B78,[6]BV_Data_An_Prec!$V:$V,$C78,[6]BV_Data_An_Prec!$W:$W,Q$2) -> 66097 | S78: =L78-Q78 -> -2627.45
A79: Véhicules neufs[...] | B79: Véhicules neufs | C79: [...] | F79: {=+INDEX('[6]Budget original'!$A$2:$AO$500,MATCH($A79,'[6]Budget original'!$A$2:$A$500,0),MATCH(F$2,'[6]Budget original'!$A$2:$AO$2,0))} -> 0 | L79: =-SUMIFS([6]BV_Data_An_Cour!$O:$O,[6]BV_Data_An_Cour!$U:$U,$B79,[6]BV_Data_An_Cour!$V:$V,$C79,[6]BV_Data_An_Cour!$W:$W,L$2) -> 0 | N79: =L79-F79 -> 0 | Q79: =-SUMIFS([6]BV_Data_An_Prec!$O:$O,[6]BV_Data_An_Prec!$U:$U,$B79,[6]BV_Data_An_Prec!$V:$V,$C79,[6]BV_Data_An_Prec!$W:$W,Q$2) -> 0 | S79: =L79-Q79 -> 0
A80: Véhicules neufs[...] | B80: Véhicules neufs | C80: [...] | F80: {=+INDEX('[6]Budget original'!$A$2:$AO$500,MATCH($A80,'[6]Budget original'!$A$2:$A$500,0),MATCH(F$2,'[6]Budget original'!$A$2:$AO$2,0))} -> 0 | L80: =-SUMIFS([6]BV_Data_An_Cour!$O:$O,[6]BV_Data_An_Cour!$U:$U,$B80,[6]BV_Data_An_Cour!$V:$V,$C80,[6]BV_Data_An_Cour!$W:$W,L$2) -> 0 | N80: =L80-F80 -> 0 | Q80: =-SUMIFS([6]BV_Data_An_Prec!$O:$O,[6]BV_Data_An_Prec!$U:$U,$B80,[6]BV_Data_An_Prec!$V:$V,$C80,[6]BV_Data_An_Prec!$W:$W,Q$2) -> 0 | S80: =L80-Q80 -> 0
A81: Véhicules neufs[...] | B81: Véhicules neufs | C81: [...] | F81: {=+INDEX('[6]Budget original'!$A$2:$AO$500,MATCH($A81,'[6]Budget original'!$A$2:$A$500,0),MATCH(F$2,'[6]Budget original'!$A$2:$AO$2,0))} -> 0 | L81: =-SUMIFS([6]BV_Data_An_Cour!$O:$O,[6]BV_Data_An_Cour!$U:$U,$B81,[6]BV_Data_An_Cour!$V:$V,$C81,[6]BV_Data_An_Cour!$W:$W,L$2) -> 0 | N81: =L81-F81 -> 0 | Q81: =-SUMIFS([6]BV_Data_An_Prec!$O:$O,[6]BV_Data_An_Prec!$U:$U,$B81,[6]BV_Data_An_Prec!$V:$V,$C81,[6]BV_Data_An_Prec!$W:$W,Q$2) -> 0 | S81: =L81-Q81 -> 0
A82: Véhicules neufsFrais administration | B82: Véhicules neufs | C82: Frais administration | F82: {=+INDEX('[6]Budget original'!$A$2:$AO$500,MATCH($A82,'[6]Budget original'!$A$2:$A$500,0),MATCH(F$2,'[6]Budget original'!$A$2:$AO$2,0))} -> 18891.372 | J82: =+L82/K82 -> 59 | K82: =+L82/J27 -> 447.22034 | L82: =-SUMIFS([6]BV_Data_An_Cour!$O:$O,[6]BV_Data_An_Cour!$U:$U,$B82,[6]BV_Data_An_Cour!$V:$V,$C82,[6]BV_Data_An_Cour!$W:$W,L$2) -> 26386 | N82: =L82-F82 -> 7494.6277 | Q82: =-SUMIFS([6]BV_Data_An_Prec!$O:$O,[6]BV_Data_An_Prec!$U:$U,$B82,[6]BV_Data_An_Prec!$V:$V,$C82,[6]BV_Data_An_Prec!$W:$W,Q$2) -> -28919 | S82: =L82-Q82 -> 55305
A83: Véhicules neufsAUTRES REVENUS | B83: Véhicules neufs | C83: AUTRES REVENUS | F83: =+SUM(F75:F82) -> 95436.389 | L83: =+SUM(L75:L82) -> 89855.55 | N83: =+SUM(N75:N82) -> -5580.8388 | Q83: =+SUM(Q75:Q82) -> 59178 | S83: =+SUM(S75:S82) -> 52677.55
A84: Véhicules neufs | B84: Véhicules neufs
A85: Véhicules neufsPROFIT DÉPARTEMENTAL | B85: Véhicules neufs | C85: PROFIT DÉPARTEMENTAL | F85: =F27-F74+F83 -> 112069.49 | L85: =L27-L74+L83 -> 113053.64 | N85: =N27-N41-N54-N72+N83 -> 984.15471 | Q85: =Q27-Q74+Q83 -> 129525.02 | S85: =S27-S41-S54-S72+S83 -> 5528.6195
C89: =C1 -> Volks | K89: Véhicules usagés | S89: =$S$1 -> Réalisé, Juin 2023
D91: BUDGET ORIGINAL | J91: RÉALISATION | M91: ÉCART réel / Budget | O91: ANNÉE PRÉCÉDENTE | R91: ECART (réel/ Ann.Préc.)
D92: UNITÉS | E92: $P/UNITÉ | F92: $PROFITS | J92: UNITÉS | K92: $P/UNITE | L92: $PROFITS | M92: UNITÉS | N92: $PROFITS | O92: UNITÉS | P92: $P/UNITE | Q92: $PROFITS | R92: UNITÉS | S92: $PROFITS
A93: Véhicules usagésVentes nettes | B93: Véhicules usagés | C93: Ventes nettes | F93: {=+INDEX('[6]Budget original'!$A$2:$AO$500,MATCH($A93,'[6]Budget original'!$A$2:$A$500,0),MATCH(F$2,'[6]Budget original'!$A$2:$AO$2,0))} -> 1671360.8 | L93: =-SUMIFS([6]BV_Data_An_Cour!$O:$O,[6]BV_Data_An_Cour!$X:$X,"Oui",[6]BV_Data_An_Cour!$U:$U,$B93) -> 1977586.1 | Q93: =-SUMIFS([6]BV_Data_An_Prec!$O:$O,[6]BV_Data_An_Prec!$X:$X,"Oui",[6]BV_Data_An_Prec!$U:$U,$B93) -> 1873950.2
A94: Véhicules usagésCertifié | B94: Véhicules usagés | C94: Certifié | D94: {=+INDEX('[6]Budget original'!$A$2:$AO$500,MATCH($A94,'[6]Budget original'!$A$2:$A$500,0),MATCH(D$2,'[6]Budget original'!$A$2:$AO$2,0))} -> 40 | E94: =IF(D94=0,0,F94/D94) -> 1858 | F94: {=+INDEX('[6]Budget original'!$A$2:$AO$500,MATCH($A94,'[6]Budget original'!$A$2:$A$500,0),MATCH(F$2,'[6]Budget original'!$A$2:$AO$2,0))} -> 74320 | J94: =-SUMIFS([6]BV_Data_An_Cour!$O:$O,[6]BV_Data_An_Cour!$U:$U,$B94,[6]BV_Data_An_Cour!$V:$V,$C94,[6]BV_Data_An_Cour!$W:$W,J$2) -> 18 | K94: =IF(J94=0,0,L94/J94) -> 2437.2944 | L94: =-SUMIFS([6]BV_Data_An_Cour!$O:$O,[6]BV_Data_An_Cour!$U:$U,$B94,[6]BV_Data_An_Cour!$V:$V,$C94,[6]BV_Data_An_Cour!$W:$W,$L2) -> 43871.3 | M94: =J94-D94 -> -22 | N94: =L94-F94 -> -30448.7 | O94: =-SUMIFS([6]BV_Data_An_Prec!$O:$O,[6]BV_Data_An_Prec!$U:$U,$B94,[6]BV_Data_An_Prec!$V:$V,$C94,[6]BV_Data_An_Prec!$W:$W,O$2) -> 34 | P94: =IF(O94=0,0,Q94/O94) -> 2572.5085 | Q94: =-SUMIFS([6]BV_Data_An_Prec!$O:$O,[6]BV_Data_An_Prec!$U:$U,$B94,[6]BV_Data_An_Prec!$V:$V,$C94,[6]BV_Data_An_Prec!$W:$W,$L2) -> 87465.29 | R94: =J94-O94 -> -16 | S94: =L94-Q94 -> -43593.99
A95: Véhicules usagésNon Certifié | B95: Véhicules usagés | C95: Non Certifié | D95: {=+INDEX('[6]Budget original'!$A$2:$AO$500,MATCH($A95,'[6]Budget original'!$A$2:$A$500,0),MATCH(D$2,'[6]Budget original'!$A$2:$AO$2,0))} -> 0 | E95: =IF(D95=0,0,F95/D95) -> 0 | F95: {=+INDEX('[6]Budget original'!$A$2:$AO$500,MATCH($A95,'[6]Budget original'!$A$2:$A$500,0),MATCH(F$2,'[6]Budget original'!$A$2:$AO$2,0))} -> 0 | J95: =-SUMIFS([6]BV_Data_An_Cour!$O:$O,[6]BV_Data_An_Cour!$U:$U,$B95,[6]BV_Data_An_Cour!$V:$V,$C95,[6]BV_Data_An_Cour!$W:$W,J$2) -> 7 | K95: =IF(J95=0,0,L95/J95) -> 1925.8071 | L95: =-SUMIFS([6]BV_Data_An_Cour!$O:$O,[6]BV_Data_An_Cour!$U:$U,$B95,[6]BV_Data_An_Cour!$V:$V,$C95,[6]BV_Data_An_Cour!$W:$W,$L2) -> 13480.65 | M95: =J95-D95 -> 7 | N95: =L95-F95 -> 13480.65 | O95: =-SUMIFS([6]BV_Data_An_Prec!$O:$O,[6]BV_Data_An_Prec!$U:$U,$B95,[6]BV_Data_An_Prec!$V:$V,$C95,[6]BV_Data_An_Prec!$W:$W,O$2) -> 2 | P95: =IF(O95=0,0,Q95/O95) -> 1700.39 | Q95: =-SUMIFS([6]BV_Data_An_Prec!$O:$O,[6]BV_Data_An_Prec!$U:$U,$B95,[6]BV_Data_An_Prec!$V:$V,$C95,[6]BV_Data_An_Prec!$W:$W,$L2) -> 3400.78 | R95: =J95-O95 -> 5 | S95: =L95-Q95 -> 10079.87
A96: Véhicules usagésTotal Usagés | B96: Véhicules usagés | C96: Total Usagés | D96: =+D95+D94 -> 40 | E96: =IF(D96=0,0,F96/D96) -> 1858 | F96: =+F94+F95 -> 74320 | J96: =+J94+J95 -> 25 | K96: =IF(J96<=0,0,L96/J96) -> 2294.078 | L96: =+L94+L95 -> 57351.95 | M96: =J96-D96 -> -15 | N96: =L96-F96 -> -16968.05 | O96: =+O94+O95 -> 36 | P96: =IF(O96<=0,0,Q96/O96) -> 2524.0575 | Q96: =+Q94+Q95 -> 90866.07 | R96: =R94+R95 -> -11 | S96: =S94+S95 -> -33514.12
A97: Véhicules usagés | B97: Véhicules usagés | E97: =IF(D97=0,0,F97/D97) -> 0 | M97: =M96/D96 -> -0.375 | N97: =N96/F96 -> -0.22831068 | R97: =R96/O96 -> -0.30555556 | S97: =IF(Q96=0,0,(S96/Q96)) -> -0.36882986
A98: Véhicules usagésUS | B98: Véhicules usagés | C98: US
A99: Véhicules usagésVentes au Gros | B99: Véhicules usagés | C99: Ventes au Gros | D99: {=+INDEX('[6]Budget original'!$A$2:$AO$500,MATCH($A99,'[6]Budget original'!$A$2:$A$500,0),MATCH(D$2,'[6]Budget original'!$A$2:$AO$2,0))} -> 33.846154 | E99: =IF(D99=0,0,F99/D99) -> 399 | F99: {=+INDEX('[6]Budget original'!$A$2:$AO$500,MATCH($A99,'[6]Budget original'!$A$2:$A$500,0),MATCH(F$2,'[6]Budget original'!$A$2:$AO$2,0))} -> 13504.615 | J99: =-SUMIFS([6]BV_Data_An_Cour!$O:$O,[6]BV_Data_An_Cour!$U:$U,$B99,[6]BV_Data_An_Cour!$V:$V,$C99,[6]BV_Data_An_Cour!$W:$W,J$2) -> 57 | K99: =IF(J99=0,0,L99/J99) -> 568.81632 | L99: =-SUMIFS([6]BV_Data_An_Cour!$O:$O,[6]BV_Data_An_Cour!$U:$U,$B99,[6]BV_Data_An_Cour!$V:$V,$C99,[6]BV_Data_An_Cour!$W:$W,L$2) -> 32422.53 | M99: =J99-D99 -> 23.153846 | N99: =L99-F99 -> 18917.915 | O99: =-SUMIFS([6]BV_Data_An_Prec!$O:$O,[6]BV_Data_An_Prec!$U:$U,$B99,[6]BV_Data_An_Prec!$V:$V,$C99,[6]BV_Data_An_Prec!$W:$W,O$2) -> 34 | P99: =IF(O99=0,0,Q99/O99) -> -56.072059 | Q99: =-SUMIFS([6]BV_Data_An_Prec!$O:$O,[6]BV_Data_An_Prec!$U:$U,$B99,[6]BV_Data_An_Prec!$V:$V,$C99,[6]BV_Data_An_Prec!$W:$W,Q$2) -> -1906.45 | R99: =J99-O99 -> 23 | S99: =L99-Q99 -> 34328.98
A100: Véhicules usagés | B100: Véhicules usagés
A101: Véhicules usagésRev. Finances | B101: Véhicules usagés | C101: Rev. Finances | D101: {=+INDEX('[6]Budget original'!$A$2:$AO$500,MATCH($A101,'[6]Budget original'!$A$2:$A$500,0),MATCH(D$2,'[6]Budget original'!$A$2:$AO$2,0))} -> 0 | E101: =IF(D101=0,0,F101/D101) -> 0 | F101: {=+INDEX('[6]Budget original'!$A$2:$AO$500,MATCH($A101,'[6]Budget original'!$A$2:$A$500,0),MATCH(F$2,'[6]Budget original'!$A$2:$AO$2,0))} -> 20000 | K101: =IF(J96=0,0,L101/J96) -> 734.9668 | L101: =-SUMIFS([6]BV_Data_An_Cour!$O:$O,[6]BV_Data_An_Cour!$U:$U,$B101,[6]BV_Data_An_Cour!$V:$V,$C101,[6]BV_Data_An_Cour!$W:$W,$L2) -> 18374.17 | N101: =L101-F101 -> -1625.83 | P101: =IF(O96=0,0,Q101/O96) -> 1201.3561 | Q101: =-SUMIFS([6]BV_Data_An_Prec!$O:$O,[6]BV_Data_An_Prec!$U:$U,$B101,[6]BV_Data_An_Prec!$V:$V,$C101,[6]BV_Data_An_Prec!$W:$W,$L2) -> 43248.82 | R101: =O101-K101 -> -734.9668 | S101: =L101-Q101 -> -24874.65
A102: Véhicules usagésRev. Protections | B102: Véhicules usagés | C102: Rev. Protections | D102: {=+INDEX('[6]Budget original'!$A$2:$AO$500,MATCH($A102,'[6]Budget original'!$A$2:$A$500,0),MATCH(D$2,'[6]Budget original'!$A$2:$AO$2,0))} -> 0 | E102: =IF(D102=0,0,F102/D102) -> 0 | F102: {=+INDEX('[6]Budget original'!$A$2:$AO$500,MATCH($A102,'[6]Budget original'!$A$2:$A$500,0),MATCH(F$2,'[6]Budget original'!$A$2:$AO$2,0))} -> 50000 | K102: =IF(J96=0,0,L102/J96) -> 1754.646 | L102: =-SUMIFS([6]BV_Data_An_Cour!$O:$O,[6]BV_Data_An_Cour!$U:$U,$B102,[6]BV_Data_An_Cour!$V:$V,$C102,[6]BV_Data_An_Cour!$W:$W,$L2) -> 43866.15 | N102: =L102-F102 -> -6133.85 | P102: =IF(O96=0,0,Q102/O96) -> 1261.9403 | Q102: =-SUMIFS([6]BV_Data_An_Prec!$O:$O,[6]BV_Data_An_Prec!$U:$U,$B102,[6]BV_Data_An_Prec!$V:$V,$C102,[6]BV_Data_An_Prec!$W:$W,$L2) -> 45429.85 | R102: =O102-K102 -> -1754.646 | S102: =L102-Q102 -> -1563.7
A103: Véhicules usagésRev. Autres | B103: Véhicules usagés | C103: Rev. Autres | D103: {=+INDEX('[6]Budget original'!$A$2:$AO$500,MATCH($A103,'[6]Budget original'!$A$2:$A$500,0),MATCH(D$2,'[6]Budget original'!$A$2:$AO$2,0))} -> 0 | E103: =IF(D103=0,0,F103/D103) -> 0 | F103: {=+INDEX('[6]Budget original'!$A$2:$AO$500,MATCH($A103,'[6]Budget original'!$A$2:$A$500,0),MATCH(F$2,'[6]Budget original'!$A$2:$AO$2,0))} -> 14000 | K103: =IF(J96=0,0,L103/J96) -> 59.9324 | L103: =-SUMIFS([6]BV_Data_An_Cour!$O:$O,[6]BV_Data_An_Cour!$U:$U,$B103,[6]BV_Data_An_Cour!$V:$V,$C103,[6]BV_Data_An_Cour!$W:$W,$L$2) -> 1498.31 | N103: =L103-F103 -> -12501.69 | P103: =IF(O96=0,0,Q103/O96) -> 41.279167 | Q103: =-SUMIFS([6]BV_Data_An_Prec!$O:$O,[6]BV_Data_An_Prec!$U:$U,$B103,[6]BV_Data_An_Prec!$V:$V,$C103,[6]BV_Data_An_Prec!$W:$W,$L$2) -> 1486.05 | R103: =O103-K103 -> -59.9324 | S103: =L103-Q103 -> 12.26
A104: Véhicules usagésTotal F&I | B104: Véhicules usagés | C104: Total F&I | D104: =D96 -> 40 | E104: =IF(D104=0,0,F104/D104) -> 2100 | F104: =F101+F102+F103 -> 84000 | J104: =J96 -> 25 | K104: =IF(J104<=0,0,L104/J104) -> 2549.5452 | L104: =L101+L102+L103 -> 63738.63 | M104: =J104-D104 -> -15 | N104: =L104-F104 -> -20261.37 | O104: =O96 -> 36 | P104: =IF(O104<=0,0,Q104/O104) -> 2504.5756 | Q104: =Q101+Q102+Q103 -> 90164.72 | S104: =L104-Q104 -> -26426.09
...

Sheet END
